{
  "type": "Feature",
  "properties": {
    "gn:admin1_code":"13",
    "gn:admin2_code":"62",
    "gn:admin3_code":"166816000.0",
    "gn:asciiname":"Umalag",
    "gn:country_code":"PH",
    "gn:dem":38,
    "gn:feature_class":"P",
    "gn:feature_code":"PPL",
    "gn:name":"Umalag",
    "gn:population":0,
    "gn:timezone":"Asia/Manila",
    "iso:country":"PH",
    "name:fil_x_preferred":[
        "Umalag"
    ],
    "wof:name":"Umalag",
    "wof:placetype":"locality"
},
  "geometry": {"coordinates":[125.94,9.0086],"type":"Point"}
}