{
  "type": "Feature",
  "properties": {
    "gn:admin1_code":"07",
    "gn:admin2_code":"21",
    "gn:admin3_code":"72210000.0",
    "gn:asciiname":"Azucena",
    "gn:country_code":"PH",
    "gn:dem":74,
    "gn:feature_class":"P",
    "gn:feature_code":"PPL",
    "gn:name":"Azucena",
    "gn:population":0,
    "gn:timezone":"Asia/Manila",
    "iso:country":"PH",
    "name:arg_x_preferred":[
        "Azuzena"
    ],
    "name:ceb_x_preferred":[
        "A\u00e7ucena"
    ],
    "name:fil_x_preferred":[
        "Azucena"
    ],
    "name:por_x_preferred":[
        "A\u00e7ucena"
    ],
    "name:spa_x_preferred":[
        "Azucena"
    ],
    "name:swe_x_preferred":[
        "A\u00e7ucena"
    ],
    "wof:name":"Azucena",
    "wof:placetype":"locality"
},
  "geometry": {"coordinates":[123.51479999999999,10.1236],"type":"Point"}
}