{
  "type": "Feature",
  "properties": {
    "gn:admin1_code":"41",
    "gn:admin2_code":"49",
    "gn:admin3_code":"175320000.0",
    "gn:asciiname":"Bambanan",
    "gn:country_code":"PH",
    "gn:dem":6,
    "gn:feature_class":"P",
    "gn:feature_code":"PPL",
    "gn:name":"Bambanan",
    "gn:population":0,
    "gn:timezone":"Asia/Manila",
    "iso:country":"PH",
    "name:fil_x_preferred":[
        "Bambanan"
    ],
    "wof:name":"Bambanan",
    "wof:placetype":"locality"
},
  "geometry": {"coordinates":[119.35444,10.79583],"type":"Point"}
}