{
  "type": "Feature",
  "properties": {
    "gn:admin1_code":"40",
    "gn:admin2_code":"09",
    "gn:admin3_code":"41003000.0",
    "gn:asciiname":"Calzada",
    "gn:country_code":"PH",
    "gn:dem":17,
    "gn:feature_class":"P",
    "gn:feature_code":"PPL",
    "gn:name":"Calzada",
    "gn:population":0,
    "gn:timezone":"Asia/Manila",
    "iso:country":"PH",
    "name:fil_x_preferred":[
        "Calzada"
    ],
    "name:fra_x_preferred":[
        "Calzada"
    ],
    "name:por_x_preferred":[
        "Calzada"
    ],
    "name:rus_x_preferred":[
        "\u041a\u0430\u043b\u044c\u0441\u0430\u0434\u0430"
    ],
    "name:sco_x_preferred":[
        "Calzada"
    ],
    "name:spa_x_preferred":[
        "Calzada"
    ],
    "wof:name":"Calzada",
    "wof:placetype":"locality"
},
  "geometry": {"coordinates":[120.72902000000001,13.94383],"type":"Point"}
}