{
  "type": "Feature",
  "properties": {
    "gn:admin1_code":"03",
    "gn:admin2_code":"63",
    "gn:asciiname":"Buingan",
    "gn:country_code":"PH",
    "gn:dem":30,
    "gn:feature_class":"P",
    "gn:feature_code":"PPL",
    "gn:name":"Buingan",
    "gn:population":0,
    "gn:timezone":"Asia/Manila",
    "iso:country":"PH",
    "name:fil_x_preferred":[
        "Buingan"
    ],
    "name:und_x_variant":[
        "Buggin",
        "Buingan"
    ],
    "wof:name":"Buingan",
    "wof:placetype":"locality"
},
  "geometry": {"coordinates":[120.44937,15.74638],"type":"Point"}
}