{
  "type": "Feature",
  "properties": {
    "gn:admin1_code":"06",
    "gn:admin2_code":"30",
    "gn:admin3_code":"63002000.0",
    "gn:asciiname":"Agsing",
    "gn:country_code":"PH",
    "gn:dem":113,
    "gn:feature_class":"P",
    "gn:feature_code":"PPL",
    "gn:name":"Agsing",
    "gn:population":0,
    "gn:timezone":"Asia/Manila",
    "iso:country":"PH",
    "name:fil_x_preferred":[
        "Agsing"
    ],
    "wof:name":"Agsing",
    "wof:placetype":"locality"
},
  "geometry": {"coordinates":[122.3922,10.8349],"type":"Point"}
}