{
  "type": "Feature",
  "properties": {
    "gn:country":"PH",
    "gn:fcode":"PPL",
    "gn:population":3439,
    "iso:country":"PH",
    "name:deu_x_preferred":[
        "Lan Na"
    ],
    "name:eng_x_preferred":[
        "Lanna"
    ],
    "name:fil_x_preferred":[
        "Lanna"
    ],
    "name:fin_x_preferred":[
        "Lanna"
    ],
    "name:fra_x_preferred":[
        "Lanna"
    ],
    "name:hun_x_preferred":[
        "Lannathai kir\u00e1lys\u00e1g"
    ],
    "name:ind_x_preferred":[
        "Lanna"
    ],
    "name:ita_x_preferred":[
        "Lanna"
    ],
    "name:jpn_x_preferred":[
        "\u30e9\u30fc\u30f3\u30ca\u30fc"
    ],
    "name:kor_x_preferred":[
        "\ub780\ub098"
    ],
    "name:lao_x_preferred":[
        "\u0ead\u0eb2\u0e99\u0eb2\u0e88\u0eb1\u0e81\u0ea5\u0ec9\u0eb2\u0e99\u0e99\u0eb2"
    ],
    "name:msa_x_preferred":[
        "Lanna"
    ],
    "name:nan_x_preferred":[
        "Lan Na"
    ],
    "name:nld_x_preferred":[
        "Koninkrijk Lanna"
    ],
    "name:oci_x_preferred":[
        "Lanna"
    ],
    "name:pol_x_preferred":[
        "Lanna"
    ],
    "name:por_x_preferred":[
        "Lanna"
    ],
    "name:rus_x_preferred":[
        "\u041b\u0430\u043d\u043d\u0430\u0442\u0430\u0439"
    ],
    "name:spa_x_preferred":[
        "Lanna"
    ],
    "name:tel_x_preferred":[
        "\u0c32\u0c28\u0c4d\u0c28\u0c3e"
    ],
    "name:tha_x_preferred":[
        "\u0e2d\u0e32\u0e13\u0e32\u0e08\u0e31\u0e01\u0e23\u0e25\u0e49\u0e32\u0e19\u0e19\u0e32"
    ],
    "name:ukr_x_preferred":[
        "\u041b\u0430\u043d\u043d\u0430"
    ],
    "name:uzb_x_preferred":[
        "Chiangmay"
    ],
    "name:vie_x_preferred":[
        "Lan Na"
    ],
    "name:zho_x_preferred":[
        "\u862d\u7d0d"
    ],
    "qs:name":"Lanna",
    "qs:photos_9r":0,
    "qs:photos_sr":0,
    "qs:pop_sr":"4",
    "wd:wordcount":2498,
    "wof:name":"Lanna",
    "wof:placetype":"locality",
    "wof:population":3439
},
  "geometry": {"coordinates":[121.70059999999999,17.694],"type":"Point"}
}