{
  "type": "Feature",
  "properties": {
    "gn:admin1_code":"02",
    "gn:admin2_code":"48",
    "gn:admin3_code":"25009000.0",
    "gn:asciiname":"Dilaping",
    "gn:country_code":"PH",
    "gn:dem":723,
    "gn:feature_class":"P",
    "gn:feature_code":"PPL",
    "gn:name":"Dilaping",
    "gn:population":0,
    "gn:timezone":"Asia/Manila",
    "iso:country":"PH",
    "name:fil_x_preferred":[
        "Dilaping"
    ],
    "wof:name":"Dilaping",
    "wof:placetype":"locality"
},
  "geometry": {"coordinates":[121.2967,16.324],"type":"Point"}
}