{
  "type": "Feature",
  "properties": {
    "gn:admin1_code":"07",
    "gn:admin2_code":"21",
    "gn:admin3_code":"72218000.0",
    "gn:asciiname":"Tag-ube",
    "gn:country_code":"PH",
    "gn:dem":266,
    "gn:feature_class":"P",
    "gn:feature_code":"PPL",
    "gn:name":"Tag-ube",
    "gn:population":0,
    "gn:timezone":"Asia/Manila",
    "iso:country":"PH",
    "name:fil_x_preferred":[
        "Tag-ubi"
    ],
    "wof:name":"Tag-ube",
    "wof:placetype":"locality"
},
  "geometry": {"coordinates":[123.9157,10.49103],"type":"Point"}
}