{
  "type": "Feature",
  "properties": {
    "gn:admin1_code":"03",
    "gn:admin2_code":"47",
    "gn:admin3_code":"34926000.0",
    "gn:asciiname":"Tulay",
    "gn:country_code":"PH",
    "gn:dem":102,
    "gn:feature_class":"P",
    "gn:feature_code":"PPL",
    "gn:name":"Tulay",
    "gn:population":0,
    "gn:timezone":"Asia/Manila",
    "iso:country":"PH",
    "name:ceb_x_preferred":[
        "Tulay"
    ],
    "name:fil_x_preferred":[
        "Tulay"
    ],
    "wof:name":"Tulay",
    "wof:placetype":"locality"
},
  "geometry": {"coordinates":[121.01909999999999,15.7553],"type":"Point"}
}