{
  "type": "Feature",
  "properties": {
    "gn:admin1_code":"03",
    "gn:admin2_code":"13",
    "gn:asciiname":"Simarran",
    "gn:country_code":"PH",
    "gn:dem":12,
    "gn:feature_class":"P",
    "gn:feature_code":"PPL",
    "gn:name":"Simarran",
    "gn:population":0,
    "gn:timezone":"Asia/Manila",
    "iso:country":"PH",
    "name:fil_x_preferred":[
        "Simarran"
    ],
    "name:und_x_variant":[
        "Simarron"
    ],
    "wof:name":"Simarran",
    "wof:placetype":"locality"
},
  "geometry": {"coordinates":[121.1636,13.3414],"type":"Point"}
}