{
  "type": "Feature",
  "properties": {
    "gn:admin1_code":"41",
    "gn:admin2_code":"49",
    "gn:admin3_code":"175303000.0",
    "gn:asciiname":"Tinintinan",
    "gn:country_code":"PH",
    "gn:dem":8,
    "gn:feature_class":"P",
    "gn:feature_code":"PPL",
    "gn:name":"Tinintinan",
    "gn:population":0,
    "gn:timezone":"Asia/Manila",
    "iso:country":"PH",
    "name:eng_x_preferred":[
        "Tinintinan"
    ],
    "wof:name":"Tinintinan",
    "wof:placetype":"locality"
},
  "geometry": {"coordinates":[119.9915,10.5723],"type":"Point"}
}