{
  "type": "Feature",
  "properties": {
    "gn:admin1_code":"41",
    "gn:admin2_code":"41",
    "gn:asciiname":"Agsalin",
    "gn:country_code":"PH",
    "gn:dem":4,
    "gn:feature_class":"P",
    "gn:feature_code":"PPL",
    "gn:name":"Agsalin",
    "gn:population":0,
    "gn:timezone":"Asia/Manila",
    "iso:country":"PH",
    "name:fil_x_preferred":[
        "Agsalin"
    ],
    "wof:name":"Agsalin",
    "wof:placetype":"locality"
},
  "geometry": {"coordinates":[121.48492,12.87931],"type":"Point"}
}