{
  "type": "Feature",
  "properties": {
    "gn:admin1_code":"01",
    "gn:admin2_code":"51",
    "gn:admin3_code":"15535000.0",
    "gn:asciiname":"Guiset West",
    "gn:country_code":"PH",
    "gn:dem":70,
    "gn:feature_class":"P",
    "gn:feature_code":"PPL",
    "gn:name":"Guiset West",
    "gn:population":0,
    "gn:timezone":"Asia/Manila",
    "iso:country":"PH",
    "name:fil_x_preferred":[
        "Guiset West"
    ],
    "wof:name":"Guiset West",
    "wof:placetype":"locality"
},
  "geometry": {"coordinates":[120.65000000000001,16.06667],"type":"Point"}
}