{
  "type": "Feature",
  "properties": {
    "gn:admin1_code":"07",
    "gn:admin2_code":"11",
    "gn:asciiname":"Hingotanen Island",
    "gn:country_code":"PH",
    "gn:dem":-9999,
    "gn:feature_class":"P",
    "gn:feature_code":"PPL",
    "gn:name":"Hingotanen Island",
    "gn:population":0,
    "gn:timezone":"Asia/Manila",
    "iso:country":"PH",
    "name:fil_x_preferred":[
        "Hingotanen Island"
    ],
    "wof:name":"Hingotanen Island",
    "wof:placetype":"locality"
},
  "geometry": {"coordinates":[124.48333,10.23333],"type":"Point"}
}