{
  "type": "Feature",
  "properties": {
    "gn:admin1_code":"01",
    "gn:admin2_code":"28",
    "gn:admin3_code":"12820000.0",
    "gn:asciiname":"San Guillermo",
    "gn:country_code":"PH",
    "gn:dem":18,
    "gn:feature_class":"P",
    "gn:feature_code":"PPL",
    "gn:name":"San Guillermo",
    "gn:population":0,
    "gn:timezone":"Asia/Manila",
    "iso:country":"PH",
    "name:fil_x_preferred":[
        "San Guillermo"
    ],
    "wof:name":"San Guillermo",
    "wof:placetype":"locality"
},
  "geometry": {"coordinates":[120.59699999999999,18.1533],"type":"Point"}
}