{
  "type": "Feature",
  "properties": {
    "gn:admin1_code":"40",
    "gn:admin2_code":"09",
    "gn:admin3_code":"41032000.0",
    "gn:asciiname":"Mataasnalupa",
    "gn:country_code":"PH",
    "gn:dem":151,
    "gn:feature_class":"P",
    "gn:feature_code":"PPL",
    "gn:name":"Mataasnalupa",
    "gn:population":0,
    "gn:timezone":"Asia/Manila",
    "iso:country":"PH",
    "name:eng_x_preferred":[
        "Mataasnalupa"
    ],
    "wof:name":"Mataasnalupa",
    "wof:placetype":"locality"
},
  "geometry": {"coordinates":[121.2012,13.7746],"type":"Point"}
}