{
  "type": "Feature",
  "properties": {
    "gn:admin1_code":"07",
    "gn:admin2_code":"11",
    "gn:admin3_code":"71201000.0",
    "gn:asciiname":"Dangay",
    "gn:country_code":"PH",
    "gn:dem":103,
    "gn:feature_class":"P",
    "gn:feature_code":"PPL",
    "gn:name":"Dangay",
    "gn:population":0,
    "gn:timezone":"Asia/Manila",
    "iso:country":"PH",
    "name:fil_x_preferred":[
        "Dangay"
    ],
    "wof:name":"Dangay",
    "wof:placetype":"locality"
},
  "geometry": {"coordinates":[123.9676,9.6688],"type":"Point"}
}