{
  "type": "Feature",
  "properties": {
    "gn:admin1_code":"07",
    "gn:admin2_code":"11",
    "gn:admin3_code":"71209000.0",
    "gn:asciiname":"Hobangan",
    "gn:country_code":"PH",
    "gn:dem":191,
    "gn:feature_class":"P",
    "gn:feature_code":"PPL",
    "gn:name":"Hobangan",
    "gn:population":0,
    "gn:timezone":"Asia/Manila",
    "iso:country":"PH",
    "name:fil_x_preferred":[
        "Hobangan"
    ],
    "wof:name":"Hobangan",
    "wof:placetype":"locality"
},
  "geometry": {"coordinates":[124.18333,10.06667],"type":"Point"}
}