{
  "type": "Feature",
  "properties": {
    "gn:admin1_code":"15",
    "gn:admin2_code":"27",
    "gn:admin3_code":"142702000.0",
    "gn:asciiname":"Gumhang",
    "gn:country_code":"PH",
    "gn:dem":949,
    "gn:feature_class":"P",
    "gn:feature_code":"PPL",
    "gn:name":"Gumhang",
    "gn:population":0,
    "gn:timezone":"Asia/Manila",
    "iso:country":"PH",
    "name:fil_x_preferred":[
        "Gumhang"
    ],
    "wof:name":"Gumhang",
    "wof:placetype":"locality"
},
  "geometry": {"coordinates":[121.04134000000001,16.80386],"type":"Point"}
}