{
  "type": "Feature",
  "properties": {
    "gn:admin1_code":"03",
    "gn:admin2_code":"47",
    "gn:admin3_code":"34930000.0",
    "gn:asciiname":"Bugtong na Buli",
    "gn:country_code":"PH",
    "gn:dem":49,
    "gn:feature_class":"P",
    "gn:feature_code":"PPL",
    "gn:name":"Bugtong na Buli",
    "gn:population":0,
    "gn:timezone":"Asia/Manila",
    "iso:country":"PH",
    "name:fil_x_preferred":[
        "Bugton Nabuli"
    ],
    "name:fil_x_variant":[
        "Bugtung-Buli",
        "Bugtong na Buli"
    ],
    "name:und_x_variant":[
        "Bugtung-Buli",
        "Bugtong na Buli"
    ],
    "wof:name":"Bugtong na Buli",
    "wof:placetype":"locality"
},
  "geometry": {"coordinates":[120.94216000000002,15.60721],"type":"Point"}
}