{
  "type": "Feature",
  "properties": {
    "gn:admin1_code":"15",
    "gn:admin2_code":"27",
    "gn:admin3_code":"142708000.0",
    "gn:asciiname":"Damag",
    "gn:country_code":"PH",
    "gn:dem":866,
    "gn:feature_class":"P",
    "gn:feature_code":"PPL",
    "gn:name":"Damag",
    "gn:population":0,
    "gn:timezone":"Asia/Manila",
    "iso:country":"PH",
    "name:fil_x_preferred":[
        "Damag"
    ],
    "wof:name":"Damag",
    "wof:placetype":"locality"
},
  "geometry": {"coordinates":[121.31404000000001,17.00725],"type":"Point"}
}