{
  "type": "Feature",
  "properties": {
    "gn:admin1_code":"03",
    "gn:admin2_code":"47",
    "gn:admin3_code":"34903000.0",
    "gn:asciiname":"Calawagan",
    "gn:country_code":"PH",
    "gn:dem":45,
    "gn:feature_class":"P",
    "gn:feature_code":"PPL",
    "gn:name":"Calawagan",
    "gn:population":0,
    "gn:timezone":"Asia/Manila",
    "iso:country":"PH",
    "name:fil_x_preferred":[
        "Kalawayan"
    ],
    "name:und_x_variant":[
        "Kalawagan"
    ],
    "wof:name":"Calawagan",
    "wof:placetype":"locality"
},
  "geometry": {"coordinates":[121.04501999999999,15.52978],"type":"Point"}
}