{
  "type": "Feature",
  "properties": {
    "gn:admin1_code":"07",
    "gn:admin2_code":"11",
    "gn:admin3_code":"71240000.0",
    "gn:asciiname":"Candagas",
    "gn:country_code":"PH",
    "gn:dem":191,
    "gn:feature_class":"P",
    "gn:feature_code":"PPL",
    "gn:name":"Candagas",
    "gn:population":0,
    "gn:timezone":"Asia/Manila",
    "iso:country":"PH",
    "name:fil_x_preferred":[
        "Candagas"
    ],
    "wof:name":"Candagas",
    "wof:placetype":"locality"
},
  "geometry": {"coordinates":[124.27583,9.79944],"type":"Point"}
}