{
  "type": "Feature",
  "properties": {
    "gn:admin1_code":"15",
    "gn:admin2_code":"27",
    "gn:admin3_code":"142701000.0",
    "gn:asciiname":"Bockiaman",
    "gn:country_code":"PH",
    "gn:dem":1166,
    "gn:feature_class":"P",
    "gn:feature_code":"PPL",
    "gn:name":"Bockiaman",
    "gn:population":0,
    "gn:timezone":"Asia/Manila",
    "iso:country":"PH",
    "name:fil_x_preferred":[
        "Bockiaman"
    ],
    "wof:name":"Bockiaman",
    "wof:placetype":"locality"
},
  "geometry": {"coordinates":[121.06667,16.91667],"type":"Point"}
}