{
  "type": "Feature",
  "properties": {
    "gn:admin1_code":"40",
    "gn:admin2_code":"H2",
    "gn:admin3_code":"45602000.0",
    "gn:asciiname":"Villajesus",
    "gn:country_code":"PH",
    "gn:dem":19,
    "gn:feature_class":"P",
    "gn:feature_code":"PPL",
    "gn:name":"Villajesus",
    "gn:population":0,
    "gn:timezone":"Asia/Manila",
    "iso:country":"PH",
    "name:fil_x_preferred":[
        "Villajesus"
    ],
    "wof:name":"Villajesus",
    "wof:placetype":"locality"
},
  "geometry": {"coordinates":[122.0365,14.0948],"type":"Point"}
}