{
  "type": "Feature",
  "properties": {
    "gn:admin1_code":"10",
    "gn:admin2_code":"34",
    "gn:asciiname":"Liangan",
    "gn:country_code":"PH",
    "gn:dem":9,
    "gn:feature_class":"P",
    "gn:feature_code":"PPL",
    "gn:name":"Liangan",
    "gn:population":0,
    "gn:timezone":"Asia/Manila",
    "iso:country":"PH",
    "name:eng_x_preferred":[
        "Liangan"
    ],
    "name:und_x_variant":[
        "Langan"
    ],
    "wof:name":"Liangan",
    "wof:placetype":"locality"
},
  "geometry": {"coordinates":[123.9875,8.1781],"type":"Point"}
}