{
  "type": "Feature",
  "properties": {
    "gn:admin1_code":"05",
    "gn:admin2_code":"05",
    "gn:admin3_code":"50515000.0",
    "gn:asciiname":"Linao",
    "gn:country_code":"PH",
    "gn:dem":9,
    "gn:feature_class":"P",
    "gn:feature_code":"PPL",
    "gn:name":"Linao",
    "gn:population":0,
    "gn:timezone":"Asia/Manila",
    "iso:country":"PH",
    "name:fil_x_preferred":[
        "Linao"
    ],
    "wof:name":"Linao",
    "wof:placetype":"locality"
},
  "geometry": {"coordinates":[124.2122,13.2004],"type":"Point"}
}