{
  "type": "Feature",
  "properties": {
    "gn:admin1_code":"40",
    "gn:admin2_code":"H2",
    "gn:admin3_code":"45607000.0",
    "gn:asciiname":"Salvacion",
    "gn:country_code":"PH",
    "gn:dem":200,
    "gn:feature_class":"P",
    "gn:feature_code":"PPL",
    "gn:name":"Salvacion",
    "gn:population":0,
    "gn:timezone":"Asia/Manila",
    "iso:country":"PH",
    "name:fil_x_preferred":[
        "Salvacion"
    ],
    "wof:name":"Salvacion",
    "wof:placetype":"locality"
},
  "geometry": {"coordinates":[122.38420000000001,13.9215],"type":"Point"}
}