{
  "type": "Feature",
  "properties": {
    "gn:country":"PH",
    "gn:fcode":"ADM3",
    "gn:population":12320,
    "iso:country":"PH",
    "name:bcl_x_preferred":[
        "Belison"
    ],
    "name:ceb_x_preferred":[
        "Belison"
    ],
    "name:deu_x_preferred":[
        "Belison"
    ],
    "name:fil_x_preferred":[
        "Belison"
    ],
    "name:fra_x_preferred":[
        "Belison"
    ],
    "name:ilo_x_preferred":[
        "Belison"
    ],
    "name:ind_x_preferred":[
        "Belison"
    ],
    "name:ita_x_preferred":[
        "Belison"
    ],
    "name:msa_x_preferred":[
        "Belison"
    ],
    "name:nld_x_preferred":[
        "Belison"
    ],
    "name:pag_x_preferred":[
        "Belison"
    ],
    "name:pam_x_preferred":[
        "Belison"
    ],
    "name:swe_x_preferred":[
        "Belison"
    ],
    "name:tgl_x_preferred":[
        "Belison"
    ],
    "name:urd_x_preferred":[
        "\u0628\u06cc\u0644\u06cc\u0633\u0648\u0646"
    ],
    "name:vec_x_preferred":[
        "Belison"
    ],
    "name:vie_x_preferred":[
        "Belison"
    ],
    "name:war_x_preferred":[
        "Belison"
    ],
    "qs:name":"Belison",
    "qs:photos_9r":0,
    "qs:photos_sr":0,
    "qs:pop_sr":"6",
    "wof:name":"Belison",
    "wof:placetype":"localadmin",
    "wof:population":12320
},
  "geometry": {"coordinates":[121.98333,10.85],"type":"Point"}
}