{
  "type": "Feature",
  "properties": {
    "gn:country":"PH",
    "gn:fcode":"ADM3",
    "gn:pop":12320,
    "iso:country":"PH",
    "name:fil_x_preferred":[
        "Belison"
    ],
    "qs:name":"Belison",
    "qs:photos_9r":0,
    "qs:photos_sr":0,
    "qs:pop_sr":"6",
    "wof:name":"Belison",
    "wof:placetype":"localadmin",
    "wof:population":12320
},
  "geometry": {"coordinates":[121.98333,10.85],"type":"Point"}
}