{
  "type": "Feature",
  "properties": {
    "gn:admin1_code":"05",
    "gn:admin2_code":"16",
    "gn:admin3_code":"51737000.0",
    "gn:asciiname":"Carinogan",
    "gn:country_code":"PH",
    "gn:dem":69,
    "gn:feature_class":"P",
    "gn:feature_code":"PPL",
    "gn:name":"Carinogan",
    "gn:population":0,
    "gn:timezone":"Asia/Manila",
    "iso:country":"PH",
    "name:fil_x_preferred":[
        "Carinogan"
    ],
    "wof:name":"Carinogan",
    "wof:placetype":"locality"
},
  "geometry": {"coordinates":[123.3047,13.9361],"type":"Point"}
}