{
  "type": "Feature",
  "properties": {
    "gn:country":"PH",
    "gn:fcode":"PPL",
    "gn:pop":3462,
    "iso:country":"PH",
    "qs:name":"Brgy. Bulwang, Numancia",
    "qs:photos_9r":0,
    "qs:photos_sr":0,
    "qs:pop_sr":"4",
    "wof:name":"Brgy. Bulwang, Numancia",
    "wof:placetype":"locality",
    "wof:population":3462
},
  "geometry": {"coordinates":[122.36111,11.72194],"type":"Point"}
}