{
  "type": "Feature",
  "properties": {
    "gn:admin1_code":"09",
    "gn:admin2_code":"ZSI",
    "gn:admin3_code":"98301000.0",
    "gn:asciiname":"Gulayan",
    "gn:country_code":"PH",
    "gn:dem":29,
    "gn:feature_class":"P",
    "gn:feature_code":"PPL",
    "gn:name":"Gulayan",
    "gn:population":0,
    "gn:timezone":"Asia/Manila",
    "iso:country":"PH",
    "name:fil_x_preferred":[
        "Gulayan"
    ],
    "wof:name":"Gulayan",
    "wof:placetype":"locality"
},
  "geometry": {"coordinates":[122.88500000000001,7.52917],"type":"Point"}
}