{
  "type": "Feature",
  "properties": {
    "gn:admin1_code":"03",
    "gn:admin2_code":"13",
    "gn:asciiname":"Biga",
    "gn:country_code":"PH",
    "gn:dem":17,
    "gn:feature_class":"P",
    "gn:feature_code":"PPL",
    "gn:name":"Biga",
    "gn:population":2365,
    "gn:timezone":"Asia/Manila",
    "iso:country":"PH",
    "name:fil_x_preferred":[
        "Biga"
    ],
    "wof:name":"Biga",
    "wof:placetype":"locality",
    "wof:population":2365
},
  "geometry": {"coordinates":[121.161,13.3106],"type":"Point"}
}