{
  "type": "Feature",
  "properties": {
    "gn:admin1_code":"03",
    "gn:admin2_code":"13",
    "gn:asciiname":"Biga",
    "gn:country_code":"PH",
    "gn:dem":17,
    "gn:feature_class":"P",
    "gn:feature_code":"PPL",
    "gn:name":"Biga",
    "gn:population":2365,
    "gn:timezone":"Asia/Manila",
    "iso:country":"PH",
    "name:cat_x_preferred":[
        "Biga"
    ],
    "name:ceb_x_preferred":[
        "Biga"
    ],
    "name:deu_x_preferred":[
        "Biga"
    ],
    "name:fil_x_preferred":[
        "Biga"
    ],
    "name:fra_x_preferred":[
        "Biga"
    ],
    "name:ind_x_preferred":[
        "Biga"
    ],
    "name:ita_x_preferred":[
        "Biga"
    ],
    "name:min_x_preferred":[
        "Biga"
    ],
    "name:nld_x_preferred":[
        "Biga"
    ],
    "name:pol_x_preferred":[
        "Biga"
    ],
    "name:rus_x_preferred":[
        "\u0411\u0438\u0433\u0430"
    ],
    "name:ukr_x_preferred":[
        "\u0411\u0456\u0433\u0430"
    ],
    "wof:name":"Biga",
    "wof:placetype":"locality",
    "wof:population":2365
},
  "geometry": {"coordinates":[121.161,13.3106],"type":"Point"}
}