{
  "type": "Feature",
  "properties": {
    "gn:admin1_code":"01",
    "gn:admin2_code":"51",
    "gn:admin3_code":"15532000.0",
    "gn:asciiname":"Nilentap",
    "gn:country_code":"PH",
    "gn:dem":15,
    "gn:feature_class":"P",
    "gn:feature_code":"PPL",
    "gn:name":"Nilentap",
    "gn:population":0,
    "gn:timezone":"Asia/Manila",
    "iso:country":"PH",
    "name:fil_x_preferred":[
        "Nilentap"
    ],
    "wof:name":"Nilentap",
    "wof:placetype":"locality"
},
  "geometry": {"coordinates":[120.36409999999999,15.95342],"type":"Point"}
}