{
  "type": "Feature",
  "properties": {
    "gn:admin1_code":"01",
    "gn:admin2_code":"51",
    "gn:admin3_code":"15514000.0",
    "gn:asciiname":"Tupo",
    "gn:country_code":"PH",
    "gn:dem":90,
    "gn:feature_class":"P",
    "gn:feature_code":"PPL",
    "gn:name":"Tupo",
    "gn:population":0,
    "gn:timezone":"Asia/Manila",
    "iso:country":"PH",
    "name:fil_x_preferred":[
        "Tupo"
    ],
    "name:und_x_variant":[
        "Tupa"
    ],
    "wof:name":"Tupo",
    "wof:placetype":"locality"
},
  "geometry": {"coordinates":[119.8597,16.3287],"type":"Point"}
}