{
  "type": "Feature",
  "properties": {
    "gn:admin1_code":"08",
    "gn:admin2_code":"55",
    "gn:admin3_code":"86020000.0",
    "gn:asciiname":"Majacob",
    "gn:country_code":"PH",
    "gn:dem":8,
    "gn:feature_class":"P",
    "gn:feature_code":"PPL",
    "gn:name":"Majacob",
    "gn:population":0,
    "gn:timezone":"Asia/Manila",
    "iso:country":"PH",
    "name:und_x_variant":[
        "Mahaca",
        "Majacob"
    ],
    "wof:name":"Majacob",
    "wof:placetype":"locality"
},
  "geometry": {"coordinates":[124.80043999999999,11.85589],"type":"Point"}
}