{
  "type": "Feature",
  "properties": {
    "gn:admin1_code":"14",
    "gn:admin2_code":"56",
    "gn:admin3_code":"153809000.0",
    "gn:asciiname":"Aras",
    "gn:country_code":"PH",
    "gn:dem":137,
    "gn:feature_class":"P",
    "gn:feature_code":"PPL",
    "gn:name":"Aras",
    "gn:population":0,
    "gn:timezone":"Asia/Manila",
    "iso:country":"PH",
    "name:arg_x_preferred":[
        "Aras"
    ],
    "name:aze_x_preferred":[
        "Araz"
    ],
    "name:ceb_x_preferred":[
        "Aras"
    ],
    "name:deu_x_preferred":[
        "Aras"
    ],
    "name:fil_x_preferred":[
        "Aras"
    ],
    "name:fra_x_preferred":[
        "Aras"
    ],
    "name:ita_x_preferred":[
        "Aras"
    ],
    "name:lit_x_preferred":[
        "Aras"
    ],
    "name:nld_x_preferred":[
        "Aras"
    ],
    "name:por_x_preferred":[
        "Aras"
    ],
    "name:ron_x_preferred":[
        "Aras"
    ],
    "name:sco_x_preferred":[
        "Aras"
    ],
    "name:swe_x_preferred":[
        "Aras"
    ],
    "name:tur_x_preferred":[
        "Aras"
    ],
    "name:ukr_x_preferred":[
        "\u0410\u0440\u0430\u0441"
    ],
    "wof:name":"Aras",
    "wof:placetype":"locality"
},
  "geometry": {"coordinates":[124.21666999999999,7.43333],"type":"Point"}
}