{
  "type": "Feature",
  "properties": {
    "gn:admin1_code":"01",
    "gn:admin2_code":"51",
    "gn:admin3_code":"15514000.0",
    "gn:asciiname":"Liwa Liwa",
    "gn:country_code":"PH",
    "gn:dem":42,
    "gn:feature_class":"P",
    "gn:feature_code":"PPL",
    "gn:name":"Liwa Liwa",
    "gn:population":0,
    "gn:timezone":"Asia/Manila",
    "iso:country":"PH",
    "name:fil_x_preferred":[
        "Liwa Liwa"
    ],
    "wof:name":"Liwa Liwa",
    "wof:placetype":"locality"
},
  "geometry": {"coordinates":[119.8939,16.3773],"type":"Point"}
}