{
  "type": "Feature",
  "properties": {
    "gn:admin1_code":"09",
    "gn:admin2_code":"66",
    "gn:admin3_code":"97322000.0",
    "gn:asciiname":"Bogo",
    "gn:country_code":"PH",
    "gn:dem":381,
    "gn:feature_class":"P",
    "gn:feature_code":"PPL",
    "gn:name":"Bogo",
    "gn:population":0,
    "gn:timezone":"Asia/Manila",
    "iso:country":"PH",
    "name:ceb_x_preferred":[
        "Bogo"
    ],
    "name:dan_x_preferred":[
        "Bog\u00f8"
    ],
    "name:deu_x_preferred":[
        "Bogo"
    ],
    "name:fra_x_preferred":[
        "Bogo"
    ],
    "name:ind_x_preferred":[
        "Bogo"
    ],
    "name:nld_x_preferred":[
        "Bogo"
    ],
    "name:pol_x_preferred":[
        "Bogo"
    ],
    "name:swe_x_preferred":[
        "Bogo"
    ],
    "wof:name":"Bogo",
    "wof:placetype":"locality"
},
  "geometry": {"coordinates":[123.4079,7.8663],"type":"Point"}
}