{
  "type": "Feature",
  "properties": {
    "gn:admin1_code":"01",
    "gn:admin2_code":"36",
    "gn:admin3_code":"13307000.0",
    "gn:asciiname":"Narra Este",
    "gn:country_code":"PH",
    "gn:dem":190,
    "gn:feature_class":"P",
    "gn:feature_code":"PPL",
    "gn:name":"Narra Este",
    "gn:population":0,
    "gn:timezone":"Asia/Manila",
    "iso:country":"PH",
    "name:fil_x_preferred":[
        "Narra Este"
    ],
    "wof:name":"Narra Este",
    "wof:placetype":"locality"
},
  "geometry": {"coordinates":[120.34999999999999,16.56667],"type":"Point"}
}