{
  "type": "Feature",
  "properties": {
    "gn:admin1_code":"08",
    "gn:admin2_code":"23",
    "gn:asciiname":"Catadungan",
    "gn:country_code":"PH",
    "gn:dem":-9999,
    "gn:feature_class":"P",
    "gn:feature_code":"PPL",
    "gn:name":"Catadungan",
    "gn:population":0,
    "gn:timezone":"Asia/Manila",
    "iso:country":"PH",
    "name:fil_x_preferred":[
        "Catadungan"
    ],
    "wof:name":"Catadungan",
    "wof:placetype":"locality"
},
  "geometry": {"coordinates":[125.48333,11.66667],"type":"Point"}
}