{
  "type": "Feature",
  "properties": {
    "gn:admin1_code":"01",
    "gn:admin2_code":"51",
    "gn:admin3_code":"15523000.0",
    "gn:asciiname":"De Guzman",
    "gn:country_code":"PH",
    "gn:dem":39,
    "gn:feature_class":"P",
    "gn:feature_code":"PPL",
    "gn:name":"De Guzman",
    "gn:population":0,
    "gn:timezone":"Asia/Manila",
    "iso:country":"PH",
    "name:fil_x_preferred":[
        "De Guzman"
    ],
    "wof:name":"De Guzman",
    "wof:placetype":"locality"
},
  "geometry": {"coordinates":[119.9502,16.0479],"type":"Point"}
}