{
  "type": "Feature",
  "properties": {
    "gn:admin1_code":"11",
    "gn:admin2_code":"P3",
    "gn:admin3_code":"118602000.0",
    "gn:asciiname":"Kipagah",
    "gn:country_code":"PH",
    "gn:dem":51,
    "gn:feature_class":"P",
    "gn:feature_code":"PPL",
    "gn:name":"Kipagah",
    "gn:population":0,
    "gn:timezone":"Asia/Manila",
    "iso:country":"PH",
    "name:fil_x_preferred":[
        "Kipagah"
    ],
    "wof:name":"Kipagah",
    "wof:placetype":"locality"
},
  "geometry": {"coordinates":[125.41472,5.64444],"type":"Point"}
}