{
  "type": "Feature",
  "properties": {
    "gn:admin1_code":"08",
    "gn:admin2_code":"37",
    "gn:admin3_code":"83740000.0",
    "gn:asciiname":"Plaridel",
    "gn:country_code":"PH",
    "gn:dem":3,
    "gn:feature_class":"P",
    "gn:feature_code":"PPL",
    "gn:name":"Plaridel",
    "gn:population":0,
    "gn:timezone":"Asia/Manila",
    "iso:country":"PH",
    "name:ceb_x_preferred":[
        "Plaridel"
    ],
    "name:deu_x_preferred":[
        "Plaridel"
    ],
    "name:fil_x_preferred":[
        "Plaridel"
    ],
    "name:fra_x_preferred":[
        "Plaridel"
    ],
    "name:ita_x_preferred":[
        "Plaridel"
    ],
    "name:nld_x_preferred":[
        "Plaridel"
    ],
    "name:war_x_preferred":[
        "Plaridel"
    ],
    "wof:name":"Plaridel",
    "wof:placetype":"locality"
},
  "geometry": {"coordinates":[124.38333,11.06667],"type":"Point"}
}