{
  "type": "Feature",
  "properties": {
    "gn:admin1_code":"06",
    "gn:admin2_code":"H3",
    "gn:admin3_code":"64508000.0",
    "gn:asciiname":"Hacienda Cadangdang Two",
    "gn:country_code":"PH",
    "gn:dem":15,
    "gn:feature_class":"P",
    "gn:feature_code":"PPL",
    "gn:name":"Hacienda Cadangdang Two",
    "gn:population":0,
    "gn:timezone":"Asia/Manila",
    "iso:country":"PH",
    "name:fil_x_preferred":[
        "Hacienda Cadangdang Two"
    ],
    "wof:name":"Hacienda Cadangdang Two",
    "wof:placetype":"locality"
},
  "geometry": {"coordinates":[123.0241,10.86874],"type":"Point"}
}