{
  "type": "Feature",
  "properties": {
    "gn:admin1_code":"15",
    "gn:admin2_code":"10",
    "gn:admin3_code":"141109000.0",
    "gn:asciiname":"Amsuling",
    "gn:country_code":"PH",
    "gn:dem":1455,
    "gn:feature_class":"P",
    "gn:feature_code":"PPL",
    "gn:name":"Amsuling",
    "gn:population":0,
    "gn:timezone":"Asia/Manila",
    "iso:country":"PH",
    "name:fil_x_preferred":[
        "Amsuling"
    ],
    "wof:name":"Amsuling",
    "wof:placetype":"locality"
},
  "geometry": {"coordinates":[120.66667,16.66667],"type":"Point"}
}