{
  "type": "Feature",
  "properties": {
    "gn:admin1_code":"08",
    "gn:admin2_code":"55",
    "gn:admin3_code":"86003000.0",
    "gn:asciiname":"Pilar",
    "gn:country_code":"PH",
    "gn:dem":22,
    "gn:feature_class":"P",
    "gn:feature_code":"PPL",
    "gn:name":"Pilar",
    "gn:population":0,
    "gn:timezone":"Asia/Manila",
    "iso:country":"PH",
    "name:bre_x_preferred":[
        "Pilar"
    ],
    "name:cat_x_preferred":[
        "Pilar"
    ],
    "name:ceb_x_preferred":[
        "Pilar"
    ],
    "name:deu_x_preferred":[
        "Pilar"
    ],
    "name:fil_x_preferred":[
        "Pilar"
    ],
    "name:fra_x_preferred":[
        "Pilar"
    ],
    "name:ilo_x_preferred":[
        "Pilar"
    ],
    "name:ind_x_preferred":[
        "Pilar"
    ],
    "name:ita_x_preferred":[
        "Pilar"
    ],
    "name:jpn_x_preferred":[
        "\u30d4\u30e9\u30fc\u30eb"
    ],
    "name:lit_x_preferred":[
        "Pilaras"
    ],
    "name:nld_x_preferred":[
        "Pilar"
    ],
    "name:nor_x_preferred":[
        "Pilar"
    ],
    "name:por_x_preferred":[
        "Pilar"
    ],
    "name:sco_x_preferred":[
        "Pilar"
    ],
    "name:slv_x_preferred":[
        "Pilar"
    ],
    "name:spa_x_preferred":[
        "Pilar"
    ],
    "name:swe_x_preferred":[
        "Pilar"
    ],
    "name:vie_x_preferred":[
        "Pilar"
    ],
    "name:vol_x_preferred":[
        "Pilar"
    ],
    "name:war_x_preferred":[
        "Pilar"
    ],
    "name:zho_x_preferred":[
        "\u76ae\u62c9\u723e"
    ],
    "wof:name":"Pilar",
    "wof:placetype":"locality"
},
  "geometry": {"coordinates":[124.48688,12.25482],"type":"Point"}
}