{
  "type": "Feature",
  "properties": {
    "gn:country":"PH",
    "gn:fcode":"PPL",
    "gn:population":2758,
    "iso:country":"PH",
    "name:und_x_variant":[
        "Miteb"
    ],
    "qs:name":"Mileb",
    "qs:photos_9r":0,
    "qs:photos_sr":0,
    "qs:pop_sr":"4",
    "wof:name":"Mileb",
    "wof:placetype":"locality",
    "wof:population":2758
},
  "geometry": {"coordinates":[124.58389,6.89861],"type":"Point"}
}