{
  "type": "Feature",
  "properties": {
    "gn:admin1_code":"01",
    "gn:admin2_code":"29",
    "gn:admin3_code":"12914000.0",
    "gn:asciiname":"Sarmingan",
    "gn:country_code":"PH",
    "gn:dem":31,
    "gn:feature_class":"P",
    "gn:feature_code":"PPL",
    "gn:name":"Sarmingan",
    "gn:population":0,
    "gn:timezone":"Asia/Manila",
    "iso:country":"PH",
    "name:fil_x_preferred":[
        "Sarmingan"
    ],
    "wof:name":"Sarmingan",
    "wof:placetype":"locality"
},
  "geometry": {"coordinates":[120.5326,17.4589],"type":"Point"}
}