{
  "type": "Feature",
  "properties": {
    "gn:country":"PH",
    "gn:fcode":"PPL",
    "gn:pop":2700,
    "iso:country":"PH",
    "name:unk_x_variant":[
        "Alubihid"
    ],
    "qs:name":"Alubijid",
    "qs:photos_9r":0,
    "qs:photos_sr":0,
    "qs:pop_sr":"4",
    "wof:name":"Alubijid",
    "wof:placetype":"locality",
    "wof:population":2700
},
  "geometry": {"coordinates":[125.42583,8.96278],"type":"Point"}
}