{
  "type": "Feature",
  "properties": {
    "gn:country":"PH",
    "gn:fcode":"PPL",
    "gn:pop":2700,
    "iso:country":"PH",
    "name:bcl_x_preferred":[
        "Alubijid"
    ],
    "name:ceb_x_preferred":[
        "Alubijid"
    ],
    "name:deu_x_preferred":[
        "Alubijid"
    ],
    "name:fas_x_preferred":[
        "\u0627\u0644\u0648\u0628\u06cc\u062c\u06cc\u062f"
    ],
    "name:fra_x_preferred":[
        "Alubijid"
    ],
    "name:ilo_x_preferred":[
        "Alubijid"
    ],
    "name:ind_x_preferred":[
        "Alubijid"
    ],
    "name:ita_x_preferred":[
        "Alubijid"
    ],
    "name:nld_x_preferred":[
        "Alubijid"
    ],
    "name:pag_x_preferred":[
        "Alubijid"
    ],
    "name:pam_x_preferred":[
        "Alubijid"
    ],
    "name:spa_x_preferred":[
        "Alubijid"
    ],
    "name:swe_x_preferred":[
        "Alubijid"
    ],
    "name:tgl_x_preferred":[
        "Alubijid"
    ],
    "name:unk_x_variant":[
        "Alubihid"
    ],
    "name:vie_x_preferred":[
        "Alubijid"
    ],
    "name:war_x_preferred":[
        "Alubijid"
    ],
    "qs:name":"Alubijid",
    "qs:photos_9r":0,
    "qs:photos_sr":0,
    "qs:pop_sr":"4",
    "wof:name":"Alubijid",
    "wof:placetype":"locality",
    "wof:population":2700
},
  "geometry": {"coordinates":[125.42583,8.96278],"type":"Point"}
}