{
  "type": "Feature",
  "properties": {
    "gn:admin1_code":"08",
    "gn:admin2_code":"37",
    "gn:admin3_code":"83739000.0",
    "gn:asciiname":"Luntad",
    "gn:country_code":"PH",
    "gn:dem":12,
    "gn:feature_class":"P",
    "gn:feature_code":"PPL",
    "gn:name":"Luntad",
    "gn:population":0,
    "gn:timezone":"Asia/Manila",
    "iso:country":"PH",
    "name:fil_x_preferred":[
        "Luntad"
    ],
    "wof:name":"Luntad",
    "wof:placetype":"locality"
},
  "geometry": {"coordinates":[125.0025,11.16278],"type":"Point"}
}