{
  "type": "Feature",
  "properties": {
    "gn:admin1_code":"01",
    "gn:admin2_code":"29",
    "gn:admin3_code":"12917000.0",
    "gn:asciiname":"Masiosioay",
    "gn:country_code":"PH",
    "gn:dem":422,
    "gn:feature_class":"P",
    "gn:feature_code":"PPL",
    "gn:name":"Masiosioay",
    "gn:population":0,
    "gn:timezone":"Asia/Manila",
    "iso:country":"PH",
    "name:fil_x_preferred":[
        "Masiosioay"
    ],
    "wof:name":"Masiosioay",
    "wof:placetype":"locality"
},
  "geometry": {"coordinates":[120.63333,17.25],"type":"Point"}
}