{
  "type": "Feature",
  "properties": {
    "gn:admin1_code":"07",
    "gn:admin2_code":"11",
    "gn:admin3_code":"71242000.0",
    "gn:asciiname":"Cabawan",
    "gn:country_code":"PH",
    "gn:dem":50,
    "gn:feature_class":"P",
    "gn:feature_code":"PPL",
    "gn:name":"Cabawan",
    "gn:population":0,
    "gn:timezone":"Asia/Manila",
    "iso:country":"PH",
    "name:fil_x_preferred":[
        "Cabawan"
    ],
    "wof:name":"Cabawan",
    "wof:placetype":"locality"
},
  "geometry": {"coordinates":[123.88476,9.68472],"type":"Point"}
}