{
  "type": "Feature",
  "properties": {
    "gn:admin1_code":"07",
    "gn:admin2_code":"21",
    "gn:admin3_code":"72210000.0",
    "gn:asciiname":"Luvo",
    "gn:country_code":"PH",
    "gn:dem":148,
    "gn:feature_class":"P",
    "gn:feature_code":"PPL",
    "gn:name":"Luvo",
    "gn:population":0,
    "gn:timezone":"Asia/Manila",
    "iso:country":"PH",
    "name:fil_x_preferred":[
        "Luvo"
    ],
    "wof:name":"Luvo",
    "wof:placetype":"locality"
},
  "geometry": {"coordinates":[123.5052,10.0867],"type":"Point"}
}