{
  "type": "Feature",
  "properties": {
    "gn:admin1_code":"01",
    "gn:admin2_code":"51",
    "gn:admin3_code":"15511000.0",
    "gn:asciiname":"Pugo",
    "gn:country_code":"PH",
    "gn:dem":24,
    "gn:feature_class":"P",
    "gn:feature_code":"PPL",
    "gn:name":"Pugo",
    "gn:population":0,
    "gn:timezone":"Asia/Manila",
    "iso:country":"PH",
    "name:ceb_x_preferred":[
        "Pugo"
    ],
    "name:deu_x_preferred":[
        "Pugo"
    ],
    "name:tgl_x_preferred":[
        "Pugo"
    ],
    "wof:name":"Pugo",
    "wof:placetype":"locality"
},
  "geometry": {"coordinates":[120.45402,15.76264],"type":"Point"}
}