{
  "type": "Feature",
  "properties": {
    "gn:admin1_code":"07",
    "gn:admin2_code":"46",
    "gn:admin3_code":"74611000.0",
    "gn:asciiname":"Guinayunan",
    "gn:country_code":"PH",
    "gn:dem":271,
    "gn:feature_class":"P",
    "gn:feature_code":"PPL",
    "gn:name":"Guinayunan",
    "gn:population":0,
    "gn:timezone":"Asia/Manila",
    "iso:country":"PH",
    "name:fil_x_preferred":[
        "Guinayunan"
    ],
    "wof:name":"Guinayunan",
    "wof:placetype":"locality"
},
  "geometry": {"coordinates":[123.2244,10.1167],"type":"Point"}
}