{
  "type": "Feature",
  "properties": {
    "gn:admin1_code":"01",
    "gn:admin2_code":"29",
    "gn:admin3_code":"12904000.0",
    "gn:asciiname":"Lesseb",
    "gn:country_code":"PH",
    "gn:dem":18,
    "gn:feature_class":"P",
    "gn:feature_code":"PPL",
    "gn:name":"Lesseb",
    "gn:population":0,
    "gn:timezone":"Asia/Manila",
    "iso:country":"PH",
    "name:fil_x_preferred":[
        "Lesseb"
    ],
    "wof:name":"Lesseb",
    "wof:placetype":"locality"
},
  "geometry": {"coordinates":[120.50539999999999,17.3448],"type":"Point"}
}