{
  "type": "Feature",
  "properties": {
    "gn:admin1_code":"02",
    "gn:admin2_code":"68",
    "gn:admin3_code":"25706000.0",
    "gn:asciiname":"Dilavuan",
    "gn:country_code":"PH",
    "gn:dem":195,
    "gn:feature_class":"P",
    "gn:feature_code":"PPL",
    "gn:name":"Dilavuan",
    "gn:population":0,
    "gn:timezone":"Asia/Manila",
    "iso:country":"PH",
    "name:fil_x_preferred":[
        "Dilavuan"
    ],
    "wof:name":"Dilavuan",
    "wof:placetype":"locality"
},
  "geometry": {"coordinates":[121.66667,16.26667],"type":"Point"}
}