{
  "type": "Feature",
  "properties": {
    "gn:admin1_code":"08",
    "gn:admin2_code":"67",
    "gn:admin3_code":"84803000.0",
    "gn:asciiname":"Buyo",
    "gn:country_code":"PH",
    "gn:dem":6,
    "gn:feature_class":"P",
    "gn:feature_code":"PPL",
    "gn:name":"Buyo",
    "gn:population":0,
    "gn:timezone":"Asia/Manila",
    "iso:country":"PH",
    "name:fil_x_preferred":[
        "Buyo"
    ],
    "wof:name":"Buyo",
    "wof:placetype":"locality"
},
  "geometry": {"coordinates":[124.55759999999999,12.5073],"type":"Point"}
}