{
  "type": "Feature",
  "properties": {
    "gn:admin1_code":"01",
    "gn:admin2_code":"51",
    "gn:admin3_code":"15513000.0",
    "gn:asciiname":"Balagan",
    "gn:country_code":"PH",
    "gn:dem":4,
    "gn:feature_class":"P",
    "gn:feature_code":"PPL",
    "gn:name":"Balagan",
    "gn:population":0,
    "gn:timezone":"Asia/Manila",
    "iso:country":"PH",
    "name:fil_x_preferred":[
        "Balagan"
    ],
    "wof:name":"Balagan",
    "wof:placetype":"locality"
},
  "geometry": {"coordinates":[120.29783999999999,15.97866],"type":"Point"}
}