{
  "type": "Feature",
  "properties": {
    "gn:admin1_code":"01",
    "gn:admin2_code":"29",
    "gn:admin3_code":"12915000.0",
    "gn:asciiname":"Quirino",
    "gn:cc2":"PH",
    "gn:country_code":"PH",
    "gn:dem":317,
    "gn:feature_class":"P",
    "gn:feature_code":"PPLA3",
    "gn:name":"Quirino",
    "gn:population":0,
    "gn:timezone":"Asia/Manila",
    "iso:country":"PH",
    "name:bcl_x_preferred":[
        "Quirino"
    ],
    "name:ceb_x_preferred":[
        "Quirino"
    ],
    "name:deu_x_preferred":[
        "Quirino"
    ],
    "name:fra_x_preferred":[
        "Quirino"
    ],
    "name:heb_x_preferred":[
        "\u05e7\u05d5\u05d5\u05d9\u05e8\u05d9\u05e0\u05d5"
    ],
    "name:hun_x_preferred":[
        "Quirino"
    ],
    "name:ilo_x_preferred":[
        "Quirino"
    ],
    "name:ind_x_preferred":[
        "Quirino"
    ],
    "name:ita_x_preferred":[
        "Quirino"
    ],
    "name:nld_x_preferred":[
        "Quirino"
    ],
    "name:pag_x_preferred":[
        "Quirino"
    ],
    "name:pam_x_preferred":[
        "Quirino"
    ],
    "name:spa_x_preferred":[
        "Quirino"
    ],
    "name:swe_x_preferred":[
        "Quirino"
    ],
    "name:tgl_x_preferred":[
        "Quirino"
    ],
    "name:und_x_variant":[
        "Angaki"
    ],
    "name:vie_x_preferred":[
        "Quirino"
    ],
    "name:war_x_preferred":[
        "Quirino"
    ],
    "wof:name":"Quirino",
    "wof:placetype":"locality"
},
  "geometry": {"coordinates":[120.67,17.15556],"type":"Point"}
}