{
  "type": "Feature",
  "properties": {
    "gn:country":"PH",
    "gn:fcode":"PPL",
    "gn:pop":3731,
    "iso:country":"PH",
    "name:fil_x_preferred":[
        "Prinza"
    ],
    "name:fil_x_variant":[
        "Prenza"
    ],
    "qs:name":"Prinza",
    "qs:photos_9r":0,
    "qs:photos_sr":0,
    "qs:pop_sr":"4",
    "wof:name":"Prinza",
    "wof:placetype":"locality",
    "wof:population":3731
},
  "geometry": {"coordinates":[120.65409,13.99679],"type":"Point"}
}