{
  "type": "Feature",
  "properties": {
    "gn:admin1_code":"03",
    "gn:admin2_code":"47",
    "gn:admin3_code":"34919000.0",
    "gn:asciiname":"Imelda Valley",
    "gn:country_code":"PH",
    "gn:dem":90,
    "gn:feature_class":"P",
    "gn:feature_code":"PPL",
    "gn:name":"Imelda Valley",
    "gn:population":0,
    "gn:timezone":"Asia/Manila",
    "iso:country":"PH",
    "name:fil_x_preferred":[
        "Imelda Valley"
    ],
    "wof:name":"Imelda Valley",
    "wof:placetype":"locality"
},
  "geometry": {"coordinates":[121.12220000000001,15.5764],"type":"Point"}
}