{
  "type": "Feature",
  "properties": {
    "gn:admin1_code":"15",
    "gn:admin2_code":"10",
    "gn:admin3_code":"141104000.0",
    "gn:asciiname":"Chanom",
    "gn:country_code":"PH",
    "gn:dem":1133,
    "gn:feature_class":"P",
    "gn:feature_code":"PPL",
    "gn:name":"Chanom",
    "gn:population":0,
    "gn:timezone":"Asia/Manila",
    "iso:country":"PH",
    "name:fil_x_preferred":[
        "Chanom"
    ],
    "wof:name":"Chanom",
    "wof:placetype":"locality"
},
  "geometry": {"coordinates":[120.84999999999999,16.51667],"type":"Point"}
}