{
  "type": "Feature",
  "properties": {
    "gn:admin1_code":"06",
    "gn:admin2_code":"30",
    "gn:admin3_code":"63037000.0",
    "gn:asciiname":"San Julian",
    "gn:country_code":"PH",
    "gn:dem":48,
    "gn:feature_class":"P",
    "gn:feature_code":"PPL",
    "gn:name":"San Julian",
    "gn:population":0,
    "gn:timezone":"Asia/Manila",
    "iso:country":"PH",
    "name:fil_x_preferred":[
        "San Julian"
    ],
    "wof:name":"San Julian",
    "wof:placetype":"locality"
},
  "geometry": {"coordinates":[122.583,10.9765],"type":"Point"}
}