{
  "type": "Feature",
  "properties": {
    "gn:admin1_code":"09",
    "gn:admin2_code":"65",
    "gn:admin3_code":"97221000.0",
    "gn:asciiname":"Tamilisan",
    "gn:country_code":"PH",
    "gn:dem":199,
    "gn:feature_class":"P",
    "gn:feature_code":"PPL",
    "gn:name":"Tamilisan",
    "gn:population":0,
    "gn:timezone":"Asia/Manila",
    "iso:country":"PH",
    "name:fil_x_preferred":[
        "Tamilisan"
    ],
    "name:und_x_variant":[
        "Tampilisan"
    ],
    "wof:name":"Tamilisan",
    "wof:placetype":"locality"
},
  "geometry": {"coordinates":[122.7054,7.9835],"type":"Point"}
}