{
  "type": "Feature",
  "properties": {
    "gn:admin1_code":"05",
    "gn:admin2_code":"58",
    "gn:admin3_code":"56203000.0",
    "gn:asciiname":"Biton",
    "gn:country_code":"PH",
    "gn:dem":12,
    "gn:feature_class":"P",
    "gn:feature_code":"PPL",
    "gn:name":"Biton",
    "gn:population":0,
    "gn:timezone":"Asia/Manila",
    "iso:country":"PH",
    "name:fil_x_preferred":[
        "Biton"
    ],
    "wof:name":"Biton",
    "wof:placetype":"locality"
},
  "geometry": {"coordinates":[123.9409,12.6111],"type":"Point"}
}