{
  "type": "Feature",
  "properties": {
    "gn:country":"PH",
    "gn:fcode":"PPL",
    "gn:pop":2638,
    "iso:country":"PH",
    "name:fil_x_preferred":[
        "Longos"
    ],
    "qs:name":"Longos",
    "qs:photos_9r":0,
    "qs:photos_sr":0,
    "qs:pop_sr":"4",
    "wd:wordcount":93,
    "wof:name":"Longos",
    "wof:placetype":"locality",
    "wof:population":2638
},
  "geometry": {"coordinates":[120.39658,16.10734],"type":"Point"}
}