{
  "type": "Feature",
  "properties": {
    "gn:admin1_code":"01",
    "gn:admin2_code":"51",
    "gn:admin3_code":"15533000.0",
    "gn:asciiname":"Longos",
    "gn:country":"PH",
    "gn:country_code":"PH",
    "gn:dem":7,
    "gn:fcode":"PPL",
    "gn:feature_class":"P",
    "gn:feature_code":"PPL",
    "gn:name":"Longos",
    "gn:population":2638,
    "gn:timezone":"Asia/Manila",
    "iso:country":"PH",
    "name:ceb_x_preferred":[
        "Longos"
    ],
    "name:fil_x_preferred":[
        "Longos"
    ],
    "name:glg_x_preferred":[
        "Longos"
    ],
    "name:ind_x_preferred":[
        "Longos"
    ],
    "name:swe_x_preferred":[
        "Longos"
    ],
    "qs:name":"Longos",
    "qs:photos_9r":0,
    "qs:photos_sr":0,
    "qs:pop_sr":"4",
    "wd:wordcount":93,
    "wof:name":"Longos",
    "wof:placetype":"locality",
    "wof:population":2638
},
  "geometry": {"coordinates":[120.39658,16.10734],"type":"Point"}
}