{
  "type": "Feature",
  "properties": {
    "gn:admin1_code":"15",
    "gn:admin2_code":"01",
    "gn:admin3_code":"140112000.0",
    "gn:asciiname":"Dalayop",
    "gn:country_code":"PH",
    "gn:dem":41,
    "gn:feature_class":"P",
    "gn:feature_code":"PPL",
    "gn:name":"Dalayop",
    "gn:population":0,
    "gn:timezone":"Asia/Manila",
    "iso:country":"PH",
    "name:fil_x_preferred":[
        "Dalayap"
    ],
    "name:fil_x_variant":[
        "Dalayop"
    ],
    "wof:name":"Dalayop",
    "wof:placetype":"locality"
},
  "geometry": {"coordinates":[120.5609,17.5748],"type":"Point"}
}