{
  "type": "Feature",
  "properties": {
    "gn:admin1_code":"14",
    "gn:admin2_code":"35",
    "gn:admin3_code":"153633000.0",
    "gn:asciiname":"Gata",
    "gn:country_code":"PH",
    "gn:dem":708,
    "gn:feature_class":"P",
    "gn:feature_code":"PPL",
    "gn:name":"Gata",
    "gn:population":0,
    "gn:timezone":"Asia/Manila",
    "iso:country":"PH",
    "name:fil_x_preferred":[
        "Gata"
    ],
    "wof:name":"Gata",
    "wof:placetype":"locality"
},
  "geometry": {"coordinates":[124.38806,7.96111],"type":"Point"}
}