{
  "type": "Feature",
  "properties": {
    "gn:admin1_code":"05",
    "gn:admin2_code":"16",
    "gn:admin3_code":"51716000.0",
    "gn:asciiname":"San Nicolas",
    "gn:cc2":"PH",
    "gn:country_code":"PH",
    "gn:dem":49,
    "gn:feature_class":"P",
    "gn:feature_code":"PPL",
    "gn:name":"San Nicolas",
    "gn:population":0,
    "gn:timezone":"Asia/Manila",
    "iso:country":"PH",
    "name:und_x_variant":[
        "Santa Nicolas",
        "San Nicolas"
    ],
    "wof:name":"San Nicolas",
    "wof:placetype":"locality"
},
  "geometry": {"coordinates":[123.41472,13.43972],"type":"Point"}
}