{
  "type": "Feature",
  "properties": {
    "gn:admin1_code":"01",
    "gn:admin2_code":"51",
    "gn:admin3_code":"15527000.0",
    "gn:asciiname":"Parian",
    "gn:country_code":"PH",
    "gn:dem":28,
    "gn:feature_class":"P",
    "gn:feature_code":"PPL",
    "gn:name":"Parian",
    "gn:population":0,
    "gn:timezone":"Asia/Manila",
    "iso:country":"PH",
    "name:ceb_x_preferred":[
        "Parian"
    ],
    "name:fil_x_preferred":[
        "Parian"
    ],
    "name:swe_x_preferred":[
        "Parian"
    ],
    "wof:name":"Parian",
    "wof:placetype":"locality"
},
  "geometry": {"coordinates":[120.27249999999999,15.78445],"type":"Point"}
}