{
  "type": "Feature",
  "properties": {
    "gn:admin1_code":"14",
    "gn:admin2_code":"56",
    "gn:admin3_code":"153828000.0",
    "gn:asciiname":"Kamasi",
    "gn:country_code":"PH",
    "gn:dem":39,
    "gn:feature_class":"P",
    "gn:feature_code":"PPL",
    "gn:name":"Kamasi",
    "gn:population":0,
    "gn:timezone":"Asia/Manila",
    "iso:country":"PH",
    "name:fil_x_preferred":[
        "Kamasi"
    ],
    "wof:name":"Kamasi",
    "wof:placetype":"locality"
},
  "geometry": {"coordinates":[124.49008000000001,6.75056],"type":"Point"}
}