{
  "type": "Feature",
  "properties": {
    "gn:admin1_code":"15",
    "gn:admin2_code":"10",
    "gn:admin3_code":"141111000.0",
    "gn:asciiname":"Payed",
    "gn:country_code":"PH",
    "gn:dem":964,
    "gn:feature_class":"P",
    "gn:feature_code":"PPL",
    "gn:name":"Payed",
    "gn:population":0,
    "gn:timezone":"Asia/Manila",
    "iso:country":"PH",
    "name:fil_x_preferred":[
        "Payed"
    ],
    "wof:name":"Payed",
    "wof:placetype":"locality"
},
  "geometry": {"coordinates":[120.8008,16.8737],"type":"Point"}
}