{
  "type": "Feature",
  "properties": {
    "gn:admin1_code":"14",
    "gn:admin2_code":"72",
    "gn:asciiname":"Sibukllon",
    "gn:country_code":"PH",
    "gn:dem":-9999,
    "gn:feature_class":"P",
    "gn:feature_code":"PPL",
    "gn:name":"Sibukllon",
    "gn:population":0,
    "gn:timezone":"Asia/Manila",
    "iso:country":"PH",
    "name:eng_x_preferred":[
        "Sibukllon"
    ],
    "wof:name":"Sibukllon",
    "wof:placetype":"locality"
},
  "geometry": {"coordinates":[120.3306,5.1586],"type":"Point"}
}