{
  "type": "Feature",
  "properties": {
    "gn:admin1_code":"08",
    "gn:admin2_code":"37",
    "gn:admin3_code":"83701000.0",
    "gn:asciiname":"San Roque",
    "gn:country_code":"PH",
    "gn:dem":6,
    "gn:feature_class":"P",
    "gn:feature_code":"PPL",
    "gn:name":"San Roque",
    "gn:population":0,
    "gn:timezone":"Asia/Manila",
    "iso:country":"PH",
    "name:fil_x_preferred":[
        "San Roque"
    ],
    "wof:name":"San Roque",
    "wof:placetype":"locality"
},
  "geometry": {"coordinates":[125.1293,10.647],"type":"Point"}
}