{
  "type": "Feature",
  "properties": {
    "gn:admin1_code":"01",
    "gn:admin2_code":"51",
    "gn:admin3_code":"15536000.0",
    "gn:asciiname":"Caarosipan",
    "gn:country_code":"PH",
    "gn:dem":99,
    "gn:feature_class":"P",
    "gn:feature_code":"PPL",
    "gn:name":"Caarosipan",
    "gn:population":0,
    "gn:timezone":"Asia/Manila",
    "iso:country":"PH",
    "name:fil_x_preferred":[
        "Caarosipan"
    ],
    "wof:name":"Caarosipan",
    "wof:placetype":"locality"
},
  "geometry": {"coordinates":[120.71666999999999,16.11667000000001],"type":"Point"}
}