{
  "type": "Feature",
  "properties": {
    "gn:admin1_code":"08",
    "gn:admin2_code":"37",
    "gn:admin3_code":"83739000.0",
    "gn:asciiname":"Lanawan",
    "gn:country_code":"PH",
    "gn:dem":19,
    "gn:feature_class":"P",
    "gn:feature_code":"PPL",
    "gn:name":"Lanawan",
    "gn:population":0,
    "gn:timezone":"Asia/Manila",
    "iso:country":"PH",
    "name:fil_x_preferred":[
        "Lanawan"
    ],
    "wof:name":"Lanawan",
    "wof:placetype":"locality"
},
  "geometry": {"coordinates":[124.93333,11.13333],"type":"Point"}
}