{
  "type": "Feature",
  "properties": {
    "gn:admin1_code":"40",
    "gn:admin2_code":"20",
    "gn:admin3_code":"42118000.0",
    "gn:asciiname":"Biluso",
    "gn:country_code":"PH",
    "gn:dem":279,
    "gn:feature_class":"P",
    "gn:feature_code":"PPL",
    "gn:name":"Biluso",
    "gn:population":0,
    "gn:timezone":"Asia/Manila",
    "iso:country":"PH",
    "name:fil_x_preferred":[
        "Biluso"
    ],
    "wof:name":"Biluso",
    "wof:placetype":"locality"
},
  "geometry": {"coordinates":[120.95631000000002,14.24291],"type":"Point"}
}