{
  "type": "Feature",
  "properties": {
    "gn:admin1_code":"01",
    "gn:admin2_code":"29",
    "gn:asciiname":"Guimud Norte",
    "gn:cc2":"PH",
    "gn:country_code":"PH",
    "gn:dem":-9999,
    "gn:feature_class":"P",
    "gn:feature_code":"PPL",
    "gn:name":"Guimud Norte",
    "gn:population":0,
    "gn:timezone":"Asia/Manila",
    "iso:country":"PH",
    "name:und_x_variant":[
        "Guimod Norte",
        "Guimud Norte"
    ],
    "wof:name":"Guimud Norte",
    "wof:placetype":"locality"
},
  "geometry": {"coordinates":[120.43333,17.73333],"type":"Point"}
}