{
  "type": "Feature",
  "properties": {
    "gn:country":"PH",
    "gn:fcode":"PPLA3",
    "gn:population":2133,
    "iso:country":"PH",
    "name:bcl_x_preferred":[
        "Pamplona"
    ],
    "name:ben_x_preferred":[
        "\u09aa\u09be\u09ae\u09aa\u09cd\u09b2\u09cb\u09a8\u09be"
    ],
    "name:cat_x_preferred":[
        "Pamplona"
    ],
    "name:ceb_x_preferred":[
        "Pamplona"
    ],
    "name:deu_x_preferred":[
        "Pamplona"
    ],
    "name:ell_x_preferred":[
        "\u03a0\u03b1\u03bc\u03c0\u03bb\u03cc\u03bd\u03b1"
    ],
    "name:eng_x_preferred":[
        "Pamplona"
    ],
    "name:fas_x_preferred":[
        "\u067e\u0627\u0645\u067e\u0644\u0648\u0646\u0627\u060c \u06a9\u0627\u06af\u0627\u06cc\u0627\u0646"
    ],
    "name:fas_x_variant":[
        "\u067e\u0627\u0645\u067e\u0644\u0648\u0646\u0627"
    ],
    "name:fra_x_preferred":[
        "Pamplona"
    ],
    "name:heb_x_preferred":[
        "\u05e4\u05de\u05e4\u05dc\u05d5\u05e0\u05d4"
    ],
    "name:hin_x_preferred":[
        "\u092a\u093e\u0902\u092a\u0932\u094b\u0928\u093e"
    ],
    "name:hun_x_preferred":[
        "Pamplona"
    ],
    "name:ilo_x_preferred":[
        "Pamplona"
    ],
    "name:ind_x_preferred":[
        "Pamplona"
    ],
    "name:ita_x_preferred":[
        "Pamplona"
    ],
    "name:jpn_x_preferred":[
        "\u30d1\u30f3\u30d7\u30ed\u30fc\u30ca"
    ],
    "name:kor_x_preferred":[
        "\ud31c\ud50c\ub85c\ub098"
    ],
    "name:nld_x_preferred":[
        "Pamplona"
    ],
    "name:oci_x_preferred":[
        "Pamplona"
    ],
    "name:pag_x_preferred":[
        "Pamplona"
    ],
    "name:pam_x_preferred":[
        "Pamplona"
    ],
    "name:spa_x_preferred":[
        "Pamplona de Cagay\u00e1n"
    ],
    "name:swe_x_preferred":[
        "Pamplona"
    ],
    "name:tgl_x_preferred":[
        "Pamplona"
    ],
    "name:tur_x_preferred":[
        "Pamplona"
    ],
    "name:und_x_variant":[
        "Bidduang"
    ],
    "name:urd_x_preferred":[
        "\u067e\u06cc\u0645\u067e\u0644\u0648\u0646\u0627"
    ],
    "name:vie_x_preferred":[
        "Pamplona"
    ],
    "name:war_x_preferred":[
        "Pamplona"
    ],
    "qs:name":"Pamplona",
    "qs:photos_9r":0,
    "qs:photos_sr":0,
    "qs:pop_sr":"4",
    "wof:name":"Pamplona",
    "wof:placetype":"locality",
    "wof:population":2133
},
  "geometry": {"coordinates":[121.34111,18.46639],"type":"Point"}
}