{
  "type": "Feature",
  "properties": {
    "gn:admin1_code":"12",
    "gn:admin2_code":"M9",
    "gn:admin3_code":"128001000.0",
    "gn:asciiname":"Bitu",
    "gn:country_code":"PH",
    "gn:dem":46,
    "gn:feature_class":"P",
    "gn:feature_code":"PPL",
    "gn:name":"Bitu",
    "gn:population":0,
    "gn:timezone":"Asia/Manila",
    "iso:country":"PH",
    "name:fil_x_preferred":[
        "Bitu"
    ],
    "wof:name":"Bitu",
    "wof:placetype":"locality"
},
  "geometry": {"coordinates":[125.29806000000001,6.10361],"type":"Point"}
}