{
  "type": "Feature",
  "properties": {
    "gn:admin1_code":"02",
    "gn:admin2_code":"48",
    "gn:admin3_code":"25004000.0",
    "gn:asciiname":"Camp Rosario",
    "gn:country_code":"PH",
    "gn:dem":331,
    "gn:feature_class":"P",
    "gn:feature_code":"PPL",
    "gn:name":"Camp Rosario",
    "gn:population":0,
    "gn:timezone":"Asia/Manila",
    "iso:country":"PH",
    "name:fil_x_preferred":[
        "Camp Rosario"
    ],
    "wof:name":"Camp Rosario",
    "wof:placetype":"locality"
},
  "geometry": {"coordinates":[121.15000000000001,16.38332999999999],"type":"Point"}
}