{
  "type": "Feature",
  "properties": {
    "gn:admin1_code":"05",
    "gn:admin2_code":"16",
    "gn:admin3_code":"51718000.0",
    "gn:asciiname":"Tamban",
    "gn:country_code":"PH",
    "gn:dem":98,
    "gn:feature_class":"P",
    "gn:feature_code":"PPL",
    "gn:name":"Tamban",
    "gn:population":0,
    "gn:timezone":"Asia/Manila",
    "iso:country":"PH",
    "name:fil_x_preferred":[
        "Tamban"
    ],
    "wof:name":"Tamban",
    "wof:placetype":"locality"
},
  "geometry": {"coordinates":[122.911,13.6753],"type":"Point"}
}