{
  "type": "Feature",
  "properties": {
    "gn:admin1_code":"15",
    "gn:admin2_code":"01",
    "gn:admin3_code":"140127000.0",
    "gn:asciiname":"Mabilong",
    "gn:country_code":"PH",
    "gn:dem":144,
    "gn:feature_class":"P",
    "gn:feature_code":"PPL",
    "gn:name":"Mabilong",
    "gn:population":0,
    "gn:timezone":"Asia/Manila",
    "iso:country":"PH",
    "name:fil_x_preferred":[
        "Mabilong"
    ],
    "wof:name":"Mabilong",
    "wof:placetype":"locality"
},
  "geometry": {"coordinates":[120.61920000000001,17.4611],"type":"Point"}
}