{
  "type": "Feature",
  "properties": {
    "gn:admin1_code":"07",
    "gn:admin2_code":"69",
    "gn:admin3_code":"76105000.0",
    "gn:asciiname":"Napo",
    "gn:country_code":"PH",
    "gn:dem":190,
    "gn:feature_class":"P",
    "gn:feature_code":"PPL",
    "gn:name":"Napo",
    "gn:population":0,
    "gn:timezone":"Asia/Manila",
    "iso:country":"PH",
    "name:ceb_x_preferred":[
        "Napo"
    ],
    "name:deu_x_preferred":[
        "Napo"
    ],
    "name:fil_x_preferred":[
        "Napo"
    ],
    "name:fra_x_preferred":[
        "Napo"
    ],
    "name:ita_x_preferred":[
        "Napo"
    ],
    "name:nld_x_preferred":[
        "Napo"
    ],
    "name:nor_x_preferred":[
        "Napo"
    ],
    "name:por_x_preferred":[
        "Napo"
    ],
    "name:que_x_preferred":[
        "Napu"
    ],
    "name:ron_x_preferred":[
        "Napo"
    ],
    "name:spa_x_preferred":[
        "Napo"
    ],
    "name:swe_x_preferred":[
        "Napo"
    ],
    "wof:name":"Napo",
    "wof:placetype":"locality"
},
  "geometry": {"coordinates":[123.5393,9.1518],"type":"Point"}
}