{
  "type": "Feature",
  "properties": {
    "gn:admin1_code":"07",
    "gn:admin2_code":"21",
    "gn:admin3_code":"72204000.0",
    "gn:asciiname":"Angilan",
    "gn:country_code":"PH",
    "gn:dem":24,
    "gn:feature_class":"P",
    "gn:feature_code":"PPL",
    "gn:name":"Angilan",
    "gn:population":0,
    "gn:timezone":"Asia/Manila",
    "iso:country":"PH",
    "name:fil_x_preferred":[
        "Angilan"
    ],
    "wof:name":"Angilan",
    "wof:placetype":"locality"
},
  "geometry": {"coordinates":[123.5718,10.219],"type":"Point"}
}