{
  "type": "Feature",
  "properties": {
    "gn:admin1_code":"06",
    "gn:admin2_code":"30",
    "gn:admin3_code":"63021000.0",
    "gn:asciiname":"Labon",
    "gn:country_code":"PH",
    "gn:dem":90,
    "gn:feature_class":"P",
    "gn:feature_code":"PPL",
    "gn:name":"Labon",
    "gn:population":0,
    "gn:timezone":"Asia/Manila",
    "iso:country":"PH",
    "name:fas_x_preferred":[
        "\u0644\u0627\u0628\u0646"
    ],
    "name:fil_x_preferred":[
        "Labon"
    ],
    "name:msa_x_preferred":[
        "Labon"
    ],
    "name:ukr_x_preferred":[
        "\u041b\u0430\u0431\u043e\u043d"
    ],
    "name:und_x_variant":[
        "Lob-on"
    ],
    "name:urd_x_preferred":[
        "\u0644\u0627\u0628\u0648\u0646"
    ],
    "wof:name":"Labon",
    "wof:placetype":"locality"
},
  "geometry": {"coordinates":[122.2332,10.74945],"type":"Point"}
}