{
  "type": "Feature",
  "properties": {
    "gn:admin1_code":"41",
    "gn:admin2_code":"49",
    "gn:admin3_code":"175312000.0",
    "gn:asciiname":"Manlag",
    "gn:country_code":"PH",
    "gn:dem":10,
    "gn:feature_class":"P",
    "gn:feature_code":"PPL",
    "gn:name":"Manlag",
    "gn:population":0,
    "gn:timezone":"Asia/Manila",
    "iso:country":"PH",
    "name:fil_x_preferred":[
        "Manlag"
    ],
    "wof:name":"Manlag",
    "wof:placetype":"locality"
},
  "geometry": {"coordinates":[119.42574999999999,11.11342],"type":"Point"}
}