{
  "type": "Feature",
  "properties": {
    "gn:admin1_code":"02",
    "gn:admin2_code":"14",
    "gn:admin3_code":"21503000.0",
    "gn:asciiname":"Capagaran",
    "gn:country_code":"PH",
    "gn:dem":37,
    "gn:feature_class":"P",
    "gn:feature_code":"PPL",
    "gn:name":"Capagaran",
    "gn:population":0,
    "gn:timezone":"Asia/Manila",
    "iso:country":"PH",
    "name:fil_x_preferred":[
        "Kapagaran"
    ],
    "name:und_x_variant":[
        "Brigida"
    ],
    "wof:name":"Capagaran",
    "wof:placetype":"locality"
},
  "geometry": {"coordinates":[121.53444,18.17389],"type":"Point"}
}