{
  "type": "Feature",
  "properties": {
    "gn:admin1_code":"01",
    "gn:admin2_code":"29",
    "gn:admin3_code":"12928000.0",
    "gn:asciiname":"Arnap",
    "gn:country_code":"PH",
    "gn:dem":39,
    "gn:feature_class":"P",
    "gn:feature_code":"PPL",
    "gn:name":"Arnap",
    "gn:population":0,
    "gn:timezone":"Asia/Manila",
    "iso:country":"PH",
    "name:fil_x_preferred":[
        "Arnap"
    ],
    "wof:name":"Arnap",
    "wof:placetype":"locality"
},
  "geometry": {"coordinates":[120.45,17.61667000000001],"type":"Point"}
}