{
  "type": "Feature",
  "properties": {
    "gn:admin1_code":"14",
    "gn:admin2_code":"56",
    "gn:admin3_code":"153815000.0",
    "gn:asciiname":"Burungutan",
    "gn:country_code":"PH",
    "gn:dem":538,
    "gn:feature_class":"P",
    "gn:feature_code":"PPL",
    "gn:name":"Buru\u00f1gutan",
    "gn:population":0,
    "gn:timezone":"Asia/Manila",
    "iso:country":"PH",
    "name:fil_x_preferred":[
        "Buru\u00f1gutan"
    ],
    "wof:name":"Burungutan",
    "wof:placetype":"locality"
},
  "geometry": {"coordinates":[124.11667,6.88333],"type":"Point"}
}