{
  "type": "Feature",
  "properties": {
    "gn:admin1_code":"08",
    "gn:admin2_code":"67",
    "gn:admin3_code":"84805000.0",
    "gn:asciiname":"Rizal",
    "gn:cc2":"PH",
    "gn:country_code":"PH",
    "gn:dem":42,
    "gn:feature_class":"P",
    "gn:feature_code":"PPL",
    "gn:name":"Rizal",
    "gn:population":0,
    "gn:timezone":"Asia/Manila",
    "iso:country":"PH",
    "name:und_x_variant":[
        "New Rizal",
        "Rizal"
    ],
    "wof:name":"Rizal",
    "wof:placetype":"locality"
},
  "geometry": {"coordinates":[124.58167,12.43722],"type":"Point"}
}