{
  "type": "Feature",
  "properties": {
    "gn:admin1_code":"10",
    "gn:admin2_code":"43",
    "gn:admin3_code":"104308000.0",
    "gn:asciiname":"Kaligiran",
    "gn:country_code":"PH",
    "gn:dem":476,
    "gn:feature_class":"P",
    "gn:feature_code":"PPL",
    "gn:name":"Kaligiran",
    "gn:population":0,
    "gn:timezone":"Asia/Manila",
    "iso:country":"PH",
    "name:fil_x_preferred":[
        "Kaligiran"
    ],
    "wof:name":"Kaligiran",
    "wof:placetype":"locality"
},
  "geometry": {"coordinates":[125.05528,8.79861],"type":"Point"}
}