{
  "type": "Feature",
  "properties": {
    "gn:admin1_code":"40",
    "gn:admin2_code":"H2",
    "gn:admin3_code":"45649000.0",
    "gn:asciiname":"Poctol",
    "gn:country_code":"PH",
    "gn:dem":24,
    "gn:feature_class":"P",
    "gn:feature_code":"PPL",
    "gn:name":"Poctol",
    "gn:population":0,
    "gn:timezone":"Asia/Manila",
    "iso:country":"PH",
    "name:fil_x_preferred":[
        "Poctol"
    ],
    "wof:name":"Poctol",
    "wof:placetype":"locality"
},
  "geometry": {"coordinates":[122.0047,13.8794],"type":"Point"}
}