{
  "type": "Feature",
  "properties": {
    "gn:admin1_code":"02",
    "gn:admin2_code":"14",
    "gn:admin3_code":"21522000.0",
    "gn:asciiname":"Dagsan",
    "gn:country_code":"PH",
    "gn:dem":22,
    "gn:feature_class":"P",
    "gn:feature_code":"PPL",
    "gn:name":"Dagsan",
    "gn:population":0,
    "gn:timezone":"Asia/Manila",
    "iso:country":"PH",
    "name:fil_x_preferred":[
        "Dagsan"
    ],
    "wof:name":"Dagsan",
    "wof:placetype":"locality"
},
  "geometry": {"coordinates":[121.18755,18.55592],"type":"Point"}
}