{
  "type": "Feature",
  "properties": {
    "gn:admin1_code":"14",
    "gn:admin2_code":"56",
    "gn:admin3_code":"153817000.0",
    "gn:asciiname":"Luoy",
    "gn:country_code":"PH",
    "gn:dem":716,
    "gn:feature_class":"P",
    "gn:feature_code":"PPL",
    "gn:name":"Luoy",
    "gn:population":0,
    "gn:timezone":"Asia/Manila",
    "iso:country":"PH",
    "name:fil_x_preferred":[
        "Luoy"
    ],
    "wof:name":"Luoy",
    "wof:placetype":"locality"
},
  "geometry": {"coordinates":[124.15889,6.92889],"type":"Point"}
}