{
  "type": "Feature",
  "properties": {
    "gn:admin1_code":"07",
    "gn:admin2_code":"69",
    "gn:admin3_code":"76102000.0",
    "gn:asciiname":"Candigum",
    "gn:country_code":"PH",
    "gn:dem":190,
    "gn:feature_class":"P",
    "gn:feature_code":"PPL",
    "gn:name":"Candigum",
    "gn:population":0,
    "gn:timezone":"Asia/Manila",
    "iso:country":"PH",
    "name:fil_x_preferred":[
        "Candigum"
    ],
    "name:und_x_variant":[
        "Kandigon"
    ],
    "wof:name":"Candigum",
    "wof:placetype":"locality"
},
  "geometry": {"coordinates":[123.59795,9.20798],"type":"Point"}
}