{
  "type": "Feature",
  "properties": {
    "gn:admin1_code":"08",
    "gn:admin2_code":"59",
    "gn:asciiname":"Hinabuyan",
    "gn:country_code":"PH",
    "gn:dem":1,
    "gn:feature_class":"P",
    "gn:feature_code":"PPL",
    "gn:name":"Hinabuyan",
    "gn:population":0,
    "gn:timezone":"Asia/Manila",
    "iso:country":"PH",
    "name:fil_x_preferred":[
        "Hinabuyan"
    ],
    "wof:name":"Hinabuyan",
    "wof:placetype":"locality"
},
  "geometry": {"coordinates":[125.01278000000001,10.10889],"type":"Point"}
}