{
  "type": "Feature",
  "properties": {
    "gn:admin1_code":"08",
    "gn:admin2_code":"67",
    "gn:admin3_code":"84806000.0",
    "gn:asciiname":"Opang",
    "gn:country_code":"PH",
    "gn:dem":4,
    "gn:feature_class":"P",
    "gn:feature_code":"PPL",
    "gn:name":"Opang",
    "gn:population":0,
    "gn:timezone":"Asia/Manila",
    "iso:country":"PH",
    "name:fil_x_preferred":[
        "Opang"
    ],
    "name:und_x_variant":[
        "Opano"
    ],
    "wof:name":"Opang",
    "wof:placetype":"locality"
},
  "geometry": {"coordinates":[125.04819999999999,12.4273],"type":"Point"}
}