{
  "type": "Feature",
  "properties": {
    "gn:admin1_code":"07",
    "gn:admin2_code":"11",
    "gn:admin3_code":"71212000.0",
    "gn:asciiname":"Nueva Vida Norte",
    "gn:country_code":"PH",
    "gn:dem":359,
    "gn:feature_class":"P",
    "gn:feature_code":"PPL",
    "gn:name":"Nueva Vida Norte",
    "gn:population":0,
    "gn:timezone":"Asia/Manila",
    "iso:country":"PH",
    "name:fil_x_preferred":[
        "Nueva Vida Norte"
    ],
    "wof:name":"Nueva Vida Norte",
    "wof:placetype":"locality"
},
  "geometry": {"coordinates":[124.1913,9.7898],"type":"Point"}
}