{
  "type": "Feature",
  "properties": {
    "gn:admin1_code":"07",
    "gn:admin2_code":"11",
    "gn:admin3_code":"71243000.0",
    "gn:asciiname":"Lipoton",
    "gn:country_code":"PH",
    "gn:dem":69,
    "gn:feature_class":"P",
    "gn:feature_code":"PPL",
    "gn:name":"Lipoton",
    "gn:population":0,
    "gn:timezone":"Asia/Manila",
    "iso:country":"PH",
    "name:fil_x_preferred":[
        "Lipoton"
    ],
    "wof:name":"Lipoton",
    "wof:placetype":"locality"
},
  "geometry": {"coordinates":[124.28333000000001,10.06667],"type":"Point"}
}