{
  "type": "Feature",
  "properties": {
    "gn:country":"PH",
    "gn:fcode":"PPL",
    "gn:pop":11000,
    "iso:country":"PH",
    "name:fil_x_preferred":[
        "Damilag"
    ],
    "name:unk_x_variant":[
        "Damilog"
    ],
    "qs:name":"Damilag",
    "qs:photos_9r":0,
    "qs:photos_sr":0,
    "qs:pop_sr":"6",
    "wof:name":"Damilag",
    "wof:placetype":"locality",
    "wof:population":11000
},
  "geometry": {"coordinates":[124.81222,8.35472],"type":"Point"}
}