{
  "type": "Feature",
  "properties": {
    "gn:admin1_code":"13",
    "gn:admin2_code":"03",
    "gn:admin3_code":"160311000.0",
    "gn:asciiname":"Buena Gracia",
    "gn:cc2":"PH",
    "gn:country_code":"PH",
    "gn:dem":19,
    "gn:feature_class":"P",
    "gn:feature_code":"PPL",
    "gn:name":"Buena Gracia",
    "gn:population":0,
    "gn:timezone":"Asia/Manila",
    "iso:country":"PH",
    "name:und_x_variant":[
        "Buena Garcia",
        "Buena Gracia"
    ],
    "wof:name":"Buena Gracia",
    "wof:placetype":"locality"
},
  "geometry": {"coordinates":[125.81167000000001,8.42278],"type":"Point"}
}