{
  "type": "Feature",
  "properties": {
    "gn:admin1_code":"15",
    "gn:admin2_code":"01",
    "gn:admin3_code":"140104000.0",
    "gn:asciiname":"Labaan",
    "gn:country_code":"PH",
    "gn:dem":295,
    "gn:feature_class":"P",
    "gn:feature_code":"PPL",
    "gn:name":"Labaan",
    "gn:population":0,
    "gn:timezone":"Asia/Manila",
    "iso:country":"PH",
    "name:fil_x_preferred":[
        "Labaan"
    ],
    "wof:name":"Labaan",
    "wof:placetype":"locality"
},
  "geometry": {"coordinates":[120.82585,17.44373],"type":"Point"}
}