{
  "type": "Feature",
  "properties": {
    "gn:admin1_code":"06",
    "gn:admin2_code":"H3",
    "gn:admin3_code":"64502000.0",
    "gn:asciiname":"Laura",
    "gn:country_code":"PH",
    "gn:dem":11,
    "gn:feature_class":"P",
    "gn:feature_code":"PPL",
    "gn:name":"Laura",
    "gn:population":0,
    "gn:timezone":"Asia/Manila",
    "iso:country":"PH",
    "name:fil_x_preferred":[
        "Laura"
    ],
    "wof:name":"Laura",
    "wof:placetype":"locality"
},
  "geometry": {"coordinates":[122.85639999999999,10.5065],"type":"Point"}
}