{
  "type": "Feature",
  "properties": {
    "gn:admin1_code":"01",
    "gn:admin2_code":"29",
    "gn:admin3_code":"12919000.0",
    "gn:asciiname":"Bungro",
    "gn:country_code":"PH",
    "gn:dem":24,
    "gn:feature_class":"P",
    "gn:feature_code":"PPL",
    "gn:name":"Bungro",
    "gn:population":0,
    "gn:timezone":"Asia/Manila",
    "iso:country":"PH",
    "name:und_x_variant":[
        "Bongro",
        "Bungro"
    ],
    "wof:name":"Bungro",
    "wof:placetype":"locality"
},
  "geometry": {"coordinates":[120.43226,17.62175],"type":"Point"}
}