{
  "type": "Feature",
  "properties": {
    "gn:admin1_code":"02",
    "gn:admin2_code":"31",
    "gn:admin3_code":"23125000.0",
    "gn:asciiname":"Santor",
    "gn:country_code":"PH",
    "gn:dem":58,
    "gn:feature_class":"P",
    "gn:feature_code":"PPL",
    "gn:name":"Santor",
    "gn:population":0,
    "gn:timezone":"Asia/Manila",
    "iso:country":"PH",
    "name:fil_x_preferred":[
        "Santor"
    ],
    "wof:name":"Santor",
    "wof:placetype":"locality"
},
  "geometry": {"coordinates":[121.74124,16.99205],"type":"Point"}
}