{
  "type": "Feature",
  "properties": {
    "gn:gn_country":"PH",
    "gn:gn_fcode":"PPL",
    "gn:gn_pop":2829,
    "gn:population":2829,
    "iso:country":"PH",
    "qs_pg:aaroncc":"PH",
    "qs_pg:gn_country":"PH",
    "qs_pg:gn_fcode":"PPL",
    "qs_pg:gn_pop":2829,
    "qs_pg:name":"Cabulay",
    "qs_pg:photos_9r":0,
    "qs_pg:photos_sr":0,
    "qs_pg:pop_sr":4,
    "qs_pg:qs_pg_placetype":"locality",
    "wof:name":"Cabulay",
    "wof:placetype":"locality",
    "wof:population":2829
},
  "geometry": {"coordinates":[121.4975,16.74556],"type":"Point"}
}