{
  "type": "Feature",
  "properties": {
    "gn:admin1_code":"02",
    "gn:admin2_code":"31",
    "gn:admin3_code":"23133000.0",
    "gn:asciiname":"Centro",
    "gn:country_code":"PH",
    "gn:dem":34,
    "gn:feature_class":"P",
    "gn:feature_code":"PPL",
    "gn:name":"Centro",
    "gn:population":0,
    "gn:timezone":"Asia/Manila",
    "iso:country":"PH",
    "wof:name":"Centro",
    "wof:placetype":"locality"
},
  "geometry": {"coordinates":[121.79425999999999,17.44959],"type":"Point"}
}