{
  "type": "Feature",
  "properties": {
    "gn:admin1_code":"40",
    "gn:admin2_code":"20",
    "gn:admin3_code":"42106000.0",
    "gn:asciiname":"San Manuel Primero",
    "gn:country_code":"PH",
    "gn:dem":85,
    "gn:feature_class":"P",
    "gn:feature_code":"PPL",
    "gn:name":"San Manuel Primero",
    "gn:population":0,
    "gn:timezone":"Asia/Manila",
    "iso:country":"PH",
    "wof:name":"San Manuel Primero",
    "wof:placetype":"locality"
},
  "geometry": {"coordinates":[120.95061,14.33707],"type":"Point"}
}