{
  "type": "Feature",
  "properties": {
    "gn:admin1_code":"41",
    "gn:admin2_code":"54",
    "gn:admin3_code":"175910000.0",
    "gn:asciiname":"Guinpingan",
    "gn:country_code":"PH",
    "gn:dem":201,
    "gn:feature_class":"P",
    "gn:feature_code":"PPL",
    "gn:name":"Guinpingan",
    "gn:population":0,
    "gn:timezone":"Asia/Manila",
    "iso:country":"PH",
    "name:eng_x_preferred":[
        "Guinpingan"
    ],
    "name:und_x_variant":[
        "Guimpingan"
    ],
    "wof:name":"Guinpingan",
    "wof:placetype":"locality"
},
  "geometry": {"coordinates":[122.28831,12.61522],"type":"Point"}
}