{
  "type": "Feature",
  "properties": {
    "gn:admin1_code":"15",
    "gn:admin2_code":"10",
    "gn:admin3_code":"141112000.0",
    "gn:asciiname":"Basca",
    "gn:country_code":"PH",
    "gn:dem":465,
    "gn:feature_class":"P",
    "gn:feature_code":"PPL",
    "gn:name":"Basca",
    "gn:population":0,
    "gn:timezone":"Asia/Manila",
    "iso:country":"PH",
    "name:fil_x_preferred":[
        "Basca"
    ],
    "wof:name":"Basca",
    "wof:placetype":"locality"
},
  "geometry": {"coordinates":[120.48333,16.46667],"type":"Point"}
}