{
  "type": "Feature",
  "properties": {
    "gn:admin1_code":"08",
    "gn:admin2_code":"37",
    "gn:admin3_code":"83705000.0",
    "gn:asciiname":"Dalakit",
    "gn:country_code":"PH",
    "gn:dem":7,
    "gn:feature_class":"P",
    "gn:feature_code":"PPL",
    "gn:name":"Dalakit",
    "gn:population":0,
    "gn:timezone":"Asia/Manila",
    "iso:country":"PH",
    "name:fil_x_preferred":[
        "Dalakit"
    ],
    "name:und_x_variant":[
        "Dalakito"
    ],
    "wof:name":"Dalakit",
    "wof:placetype":"locality"
},
  "geometry": {"coordinates":[124.857,11.4271],"type":"Point"}
}