{
  "type": "Feature",
  "properties": {
    "gn:admin1_code":"01",
    "gn:admin2_code":"51",
    "gn:admin3_code":"15511000.0",
    "gn:asciiname":"Ataynan",
    "gn:country_code":"PH",
    "gn:dem":26,
    "gn:feature_class":"P",
    "gn:feature_code":"PPL",
    "gn:name":"Ataynan",
    "gn:population":0,
    "gn:timezone":"Asia/Manila",
    "iso:country":"PH",
    "name:fil_x_preferred":[
        "Ataynar"
    ],
    "name:und_x_variant":[
        "Atainan",
        "Ataynan"
    ],
    "wof:name":"Ataynan",
    "wof:placetype":"locality"
},
  "geometry": {"coordinates":[120.46962000000001,15.83128],"type":"Point"}
}