{
  "type": "Feature",
  "properties": {
    "gn:admin1_code":"14",
    "gn:admin2_code":"60",
    "gn:asciiname":"Tulin Can",
    "gn:country_code":"PH",
    "gn:dem":9,
    "gn:feature_class":"P",
    "gn:feature_code":"PPL",
    "gn:name":"Tulin Can",
    "gn:population":0,
    "gn:timezone":"Asia/Manila",
    "iso:country":"PH",
    "name:eng_x_preferred":[
        "Tulin Can"
    ],
    "name:und_x_variant":[
        "Tulakan"
    ],
    "wof:name":"Tulin Can",
    "wof:placetype":"locality"
},
  "geometry": {"coordinates":[120.88379999999999,5.7187],"type":"Point"}
}