{
  "type": "Feature",
  "properties": {
    "gn:country":"PH",
    "gn:fcode":"PPLA3",
    "gn:population":9043,
    "iso:country":"PH",
    "name:bcl_x_preferred":[
        "Lagonglong"
    ],
    "name:ceb_x_preferred":[
        "Lagonglong"
    ],
    "name:deu_x_preferred":[
        "Lagonglong"
    ],
    "name:eng_x_preferred":[
        "Lagonglong"
    ],
    "name:fra_x_preferred":[
        "Lagonglong"
    ],
    "name:ilo_x_preferred":[
        "Lagonglong"
    ],
    "name:ind_x_preferred":[
        "Lagonglong"
    ],
    "name:ita_x_preferred":[
        "Lagonglong"
    ],
    "name:nld_x_preferred":[
        "Lagonglong"
    ],
    "name:nob_x_preferred":[
        "Lagonglong"
    ],
    "name:pag_x_preferred":[
        "Lagonglong"
    ],
    "name:pam_x_preferred":[
        "Lagonglong"
    ],
    "name:spa_x_preferred":[
        "Lagonlong"
    ],
    "name:swe_x_preferred":[
        "Lagonglong"
    ],
    "name:tgl_x_preferred":[
        "Lagonglong"
    ],
    "name:vie_x_preferred":[
        "Lagonglong"
    ],
    "name:war_x_preferred":[
        "Lagonglong"
    ],
    "qs:name":"Lagonglong",
    "qs:photos_9r":0,
    "qs:photos_sr":0,
    "qs:pop_sr":"5",
    "wof:name":"Lagonglong",
    "wof:placetype":"locality",
    "wof:population":9043
},
  "geometry": {"coordinates":[124.79028,8.80722],"type":"Point"}
}