{
  "type": "Feature",
  "properties": {
    "gn:country":"PH",
    "gn:fcode":"PPL",
    "gn:population":2866,
    "iso:country":"PH",
    "name:fil_x_preferred":[
        "Tamisan"
    ],
    "qs:name":"Tamisan",
    "qs:photos_9r":0,
    "qs:photos_sr":0,
    "qs:pop_sr":"4",
    "wof:name":"Tamisan",
    "wof:placetype":"locality",
    "wof:population":2866
},
  "geometry": {"coordinates":[126.29837999999999,6.84372],"type":"Point"}
}