{
  "type": "Feature",
  "properties": {
    "gn:admin1_code":"08",
    "gn:admin2_code":"23",
    "gn:admin3_code":"82609000.0",
    "gn:asciiname":"Manban",
    "gn:country_code":"PH",
    "gn:dem":10,
    "gn:feature_class":"P",
    "gn:feature_code":"PPL",
    "gn:name":"Manban",
    "gn:population":0,
    "gn:timezone":"Asia/Manila",
    "iso:country":"PH",
    "name:fil_x_preferred":[
        "Manban"
    ],
    "wof:name":"Manban",
    "wof:placetype":"locality"
},
  "geometry": {"coordinates":[125.6537,10.9904],"type":"Point"}
}