{
  "type": "Feature",
  "properties": {
    "gn:admin1_code":"07",
    "gn:admin2_code":"69",
    "gn:admin3_code":"76101000.0",
    "gn:asciiname":"Camugao",
    "gn:cc2":"PH",
    "gn:country_code":"PH",
    "gn:dem":5,
    "gn:feature_class":"P",
    "gn:feature_code":"PPL",
    "gn:name":"Camugao",
    "gn:population":0,
    "gn:timezone":"Asia/Manila",
    "iso:country":"PH",
    "name:und_x_variant":[
        "Kamugao",
        "Camugao"
    ],
    "wof:name":"Camugao",
    "wof:placetype":"locality"
},
  "geometry": {"coordinates":[123.65000000000001,9.26667],"type":"Point"}
}