{
  "type": "Feature",
  "properties": {
    "gn:admin1_code":"08",
    "gn:admin2_code":"23",
    "gn:admin3_code":"82615000.0",
    "gn:asciiname":"Linalan",
    "gn:cc2":"PH",
    "gn:country_code":"PH",
    "gn:dem":24,
    "gn:feature_class":"P",
    "gn:feature_code":"PPL",
    "gn:name":"Linalan",
    "gn:population":0,
    "gn:timezone":"Asia/Manila",
    "iso:country":"PH",
    "name:und_x_variant":[
        "Linaton",
        "Linalan"
    ],
    "wof:name":"Linalan",
    "wof:placetype":"locality"
},
  "geometry": {"coordinates":[125.40000000000001,11.43639],"type":"Point"}
}