{
  "type": "Feature",
  "properties": {
    "gn:admin1_code":"03",
    "gn:admin2_code":"50",
    "gn:admin3_code":"35410000.0",
    "gn:asciiname":"Cotod",
    "gn:country_code":"PH",
    "gn:dem":3,
    "gn:feature_class":"P",
    "gn:feature_code":"PPL",
    "gn:name":"Cotod",
    "gn:population":0,
    "gn:timezone":"Asia/Manila",
    "iso:country":"PH",
    "name:fil_x_preferred":[
        "Cotod"
    ],
    "wof:name":"Cotod",
    "wof:placetype":"locality"
},
  "geometry": {"coordinates":[120.6422,14.9252],"type":"Point"}
}