{
  "type": "Feature",
  "properties": {
    "gn:admin1_code":"14",
    "gn:admin2_code":"35",
    "gn:admin3_code":"153619000.0",
    "gn:asciiname":"Dilabayan",
    "gn:country_code":"PH",
    "gn:dem":707,
    "gn:feature_class":"P",
    "gn:feature_code":"PPL",
    "gn:name":"Dilabayan",
    "gn:population":0,
    "gn:timezone":"Asia/Manila",
    "iso:country":"PH",
    "name:fil_x_preferred":[
        "Dilabayan"
    ],
    "wof:name":"Dilabayan",
    "wof:placetype":"locality"
},
  "geometry": {"coordinates":[124.35138999999999,7.91722],"type":"Point"}
}