{
  "type": "Feature",
  "properties": {
    "gn:admin1_code":"09",
    "gn:admin2_code":"ZSI",
    "gn:admin3_code":"98302000.0",
    "gn:asciiname":"Compostela",
    "gn:country_code":"PH",
    "gn:dem":124,
    "gn:feature_class":"P",
    "gn:feature_code":"PPL",
    "gn:name":"Compostela",
    "gn:population":0,
    "gn:timezone":"Asia/Manila",
    "iso:country":"PH",
    "name:ceb_x_preferred":[
        "Compostela"
    ],
    "name:deu_x_preferred":[
        "Compostela"
    ],
    "name:fas_x_preferred":[
        "\u06a9\u0648\u0645\u067e\u0633\u062a\u0644\u0627"
    ],
    "name:fas_x_variant":[
        "\u06a9\u0627\u0645\u067e\u0648\u0633\u062a\u0644\u0627"
    ],
    "name:fil_x_preferred":[
        "Compostela"
    ],
    "name:fra_x_preferred":[
        "Compostela"
    ],
    "name:glg_x_preferred":[
        "Compostela"
    ],
    "name:heb_x_preferred":[
        "\u05e7\u05d5\u05de\u05e4\u05d5\u05e1\u05d8\u05dc\u05d4"
    ],
    "name:hin_x_preferred":[
        "\u0915\u0902\u092a\u094b\u0938\u094d\u091f\u0947\u0932\u093e"
    ],
    "name:hun_x_preferred":[
        "Compostela"
    ],
    "name:ind_x_preferred":[
        "Compostela"
    ],
    "name:ita_x_preferred":[
        "Compostela"
    ],
    "name:kor_x_preferred":[
        "\ucf64\ud3ec\uc2a4\ud154\ub77c"
    ],
    "name:nld_x_preferred":[
        "Compostela"
    ],
    "name:pol_x_preferred":[
        "Compostela"
    ],
    "name:por_x_preferred":[
        "Compostela"
    ],
    "name:rus_x_preferred":[
        "\u041a\u043e\u043c\u043f\u043e\u0441\u0442\u0435\u043b\u0430"
    ],
    "name:sco_x_preferred":[
        "Compostela"
    ],
    "name:spa_x_preferred":[
        "Compostela"
    ],
    "name:srp_x_preferred":[
        "\u041a\u043e\u043c\u043f\u043e\u0441\u0442\u0435\u043b\u0430"
    ],
    "name:swe_x_preferred":[
        "Compostela"
    ],
    "name:tur_x_preferred":[
        "Compostela"
    ],
    "name:ukr_x_preferred":[
        "\u041a\u043e\u043c\u043f\u043e\u0441\u0442\u0435\u043b\u0430"
    ],
    "name:urd_x_preferred":[
        "\u06a9\u067e\u0645\u0648\u0633\u062a\u06cc\u0644\u0627"
    ],
    "name:vie_x_preferred":[
        "Compostela"
    ],
    "name:war_x_preferred":[
        "Compostela"
    ],
    "name:zho_cn_x_preferred":[
        "\u5b54\u6ce2\u65af\u7279\u62c9"
    ],
    "name:zho_tw_x_preferred":[
        "\u5b54\u6ce2\u65af\u7279\u62c9"
    ],
    "wof:name":"Compostela",
    "wof:placetype":"locality"
},
  "geometry": {"coordinates":[123.05194,7.70167],"type":"Point"}
}