{
  "type": "Feature",
  "properties": {
    "gn:admin1_code":"02",
    "gn:admin2_code":"48",
    "gn:admin3_code":"25007000.0",
    "gn:asciiname":"Pinogilit",
    "gn:country_code":"PH",
    "gn:dem":394,
    "gn:feature_class":"P",
    "gn:feature_code":"PPL",
    "gn:name":"Pinogilit",
    "gn:population":0,
    "gn:timezone":"Asia/Manila",
    "iso:country":"PH",
    "name:fil_x_preferred":[
        "Pinogilit"
    ],
    "wof:name":"Pinogilit",
    "wof:placetype":"locality"
},
  "geometry": {"coordinates":[121.18380000000001,16.2825],"type":"Point"}
}