{
  "type": "Feature",
  "properties": {
    "gn:admin1_code":"14",
    "gn:admin2_code":"56",
    "gn:admin3_code":"153832000.0",
    "gn:asciiname":"Tukanabago",
    "gn:country_code":"PH",
    "gn:dem":14,
    "gn:feature_class":"P",
    "gn:feature_code":"PPL",
    "gn:name":"Tukanabago",
    "gn:population":0,
    "gn:timezone":"Asia/Manila",
    "iso:country":"PH",
    "name:fil_x_preferred":[
        "Tukanabago"
    ],
    "wof:name":"Tukanabago",
    "wof:placetype":"locality"
},
  "geometry": {"coordinates":[124.83750000000001,6.70361],"type":"Point"}
}