{
  "type": "Feature",
  "properties": {
    "gn:admin1_code":"02",
    "gn:admin2_code":"31",
    "gn:admin3_code":"23120000.0",
    "gn:asciiname":"Punit",
    "gn:country_code":"PH",
    "gn:dem":86,
    "gn:feature_class":"P",
    "gn:feature_code":"PPL",
    "gn:name":"Punit",
    "gn:population":0,
    "gn:timezone":"Asia/Manila",
    "iso:country":"PH",
    "name:fil_x_preferred":[
        "Punit"
    ],
    "wof:name":"Punit",
    "wof:placetype":"locality"
},
  "geometry": {"coordinates":[121.92180999999999,17.00446],"type":"Point"}
}