{
  "type": "Feature",
  "properties": {
    "gn:admin1_code":"03",
    "gn:admin2_code":"50",
    "gn:admin3_code":"35410000.0",
    "gn:asciiname":"Pulo",
    "gn:country_code":"PH",
    "gn:dem":10,
    "gn:feature_class":"P",
    "gn:feature_code":"PPL",
    "gn:name":"Pulo",
    "gn:population":0,
    "gn:timezone":"Asia/Manila",
    "iso:country":"PH",
    "name:ceb_x_preferred":[
        "Pulo"
    ],
    "name:fil_x_preferred":[
        "Pulo"
    ],
    "name:ind_x_preferred":[
        "Pulo"
    ],
    "name:ita_x_preferred":[
        "Pulo"
    ],
    "name:nld_x_preferred":[
        "Pulo"
    ],
    "name:swe_x_preferred":[
        "Pulo"
    ],
    "wof:name":"Pulo",
    "wof:placetype":"locality"
},
  "geometry": {"coordinates":[120.7162,14.8837],"type":"Point"}
}