{
  "type": "Feature",
  "properties": {
    "gn:admin1_code":"40",
    "gn:admin2_code":"H2",
    "gn:admin3_code":"45606000.0",
    "gn:asciiname":"Angib",
    "gn:country_code":"PH",
    "gn:dem":8,
    "gn:feature_class":"P",
    "gn:feature_code":"PPL",
    "gn:name":"Angib",
    "gn:population":0,
    "gn:timezone":"Asia/Manila",
    "iso:country":"PH",
    "name:fil_x_preferred":[
        "Angib"
    ],
    "name:und_x_variant":[
        "Angeb"
    ],
    "wof:name":"Angib",
    "wof:placetype":"locality"
},
  "geometry": {"coordinates":[121.96856,14.86267],"type":"Point"}
}