{
  "type": "Feature",
  "properties": {
    "gn:admin1_code":"12",
    "gn:admin2_code":"M9",
    "gn:admin3_code":"128005000.0",
    "gn:asciiname":"Luan",
    "gn:country_code":"PH",
    "gn:dem":7,
    "gn:feature_class":"P",
    "gn:feature_code":"PPL",
    "gn:name":"Luan",
    "gn:population":0,
    "gn:timezone":"Asia/Manila",
    "iso:country":"PH",
    "name:ara_x_preferred":[
        "\u0644\u0648\u0627\u0646"
    ],
    "name:ben_x_preferred":[
        "\u09b2\u09c1\u09df\u09be\u09a8"
    ],
    "name:deu_x_preferred":[
        "Luan"
    ],
    "name:ell_x_preferred":[
        "\u039b\u03bf\u03c5\u03ac\u03bd"
    ],
    "name:fas_x_preferred":[
        "\u0644\u0648\u0627\u0646"
    ],
    "name:fil_x_preferred":[
        "Luan"
    ],
    "name:fra_x_preferred":[
        "Luan"
    ],
    "name:heb_x_preferred":[
        "\u05dc\u05d5\u05d0\u05e0\u05d3\u05d4"
    ],
    "name:hin_x_preferred":[
        "\u0932\u0941\u0906\u0928"
    ],
    "name:hun_x_preferred":[
        "Luan"
    ],
    "name:ind_x_preferred":[
        "Luan"
    ],
    "name:ita_x_preferred":[
        "Luan"
    ],
    "name:nor_x_preferred":[
        "Luan"
    ],
    "name:por_x_preferred":[
        "Lu'an"
    ],
    "name:por_x_variant":[
        "Luan"
    ],
    "name:spa_x_preferred":[
        "Luan"
    ],
    "name:swe_x_preferred":[
        "Luan"
    ],
    "name:tur_x_preferred":[
        "Luan"
    ],
    "name:ukr_x_preferred":[
        "\u041b\u0443\u0430\u043d"
    ],
    "name:urd_x_preferred":[
        "\u0644\u0648\u0627\u0646"
    ],
    "wof:name":"Luan",
    "wof:placetype":"locality"
},
  "geometry": {"coordinates":[124.41611,6.09167],"type":"Point"}
}