{
  "type": "Feature",
  "properties": {
    "gn:admin1_code":"12",
    "gn:admin2_code":"M9",
    "gn:admin3_code":"128005000.0",
    "gn:asciiname":"Luan",
    "gn:country_code":"PH",
    "gn:dem":7,
    "gn:feature_class":"P",
    "gn:feature_code":"PPL",
    "gn:name":"Luan",
    "gn:population":0,
    "gn:timezone":"Asia/Manila",
    "iso:country":"PH",
    "name:deu_x_preferred":[
        "Luan"
    ],
    "name:fil_x_preferred":[
        "Luan"
    ],
    "name:fra_x_preferred":[
        "Luan"
    ],
    "name:ita_x_preferred":[
        "Luan"
    ],
    "name:nor_x_preferred":[
        "Luan"
    ],
    "name:por_x_preferred":[
        "Luan"
    ],
    "name:swe_x_preferred":[
        "Luan"
    ],
    "wof:name":"Luan",
    "wof:placetype":"locality"
},
  "geometry": {"coordinates":[124.41611,6.09167],"type":"Point"}
}