{
  "type": "Feature",
  "properties": {
    "gn:admin1_code":"03",
    "gn:admin2_code":"47",
    "gn:admin3_code":"34909000.0",
    "gn:asciiname":"Panaksak",
    "gn:country_code":"PH",
    "gn:dem":55,
    "gn:feature_class":"P",
    "gn:feature_code":"PPL",
    "gn:name":"Panaksak",
    "gn:population":0,
    "gn:timezone":"Asia/Manila",
    "iso:country":"PH",
    "wof:name":"Panaksak",
    "wof:placetype":"locality"
},
  "geometry": {"coordinates":[121.09999999999999,15.58333],"type":"Point"}
}