{
  "type": "Feature",
  "properties": {
    "gn:country":"PH",
    "gn:fcode":"PPL",
    "gn:pop":4614,
    "iso:country":"PH",
    "name:fil_x_preferred":[
        "Makiwalo"
    ],
    "name:unk_x_variant":[
        "Maquinalo"
    ],
    "qs:name":"Makiwalo",
    "qs:photos_9r":0,
    "qs:photos_sr":0,
    "qs:pop_sr":"4",
    "wof:name":"Makiwalo",
    "wof:placetype":"locality",
    "wof:population":4614
},
  "geometry": {"coordinates":[124.706,12.5101],"type":"Point"}
}