{
  "type": "Feature",
  "properties": {
    "gn:admin1_code":"15",
    "gn:admin2_code":"44",
    "gn:admin3_code":"144403000.0",
    "gn:asciiname":"Banguita",
    "gn:country_code":"PH",
    "gn:dem":1393,
    "gn:feature_class":"P",
    "gn:feature_code":"PPL",
    "gn:name":"Banguita",
    "gn:population":0,
    "gn:timezone":"Asia/Manila",
    "iso:country":"PH",
    "name:fil_x_preferred":[
        "Banguita"
    ],
    "name:und_x_variant":[
        "Bangitan"
    ],
    "wof:name":"Banguita",
    "wof:placetype":"locality"
},
  "geometry": {"coordinates":[120.85590000000001,17.0762],"type":"Point"}
}