{
  "type": "Feature",
  "properties": {
    "gn:admin1_code":"11",
    "gn:admin2_code":"P3",
    "gn:admin3_code":"118602000.0",
    "gn:asciiname":"Luwang",
    "gn:country_code":"PH",
    "gn:dem":58,
    "gn:feature_class":"P",
    "gn:feature_code":"PPL",
    "gn:name":"Luwang",
    "gn:population":0,
    "gn:timezone":"Asia/Manila",
    "iso:country":"PH",
    "name:fil_x_preferred":[
        "Luwang"
    ],
    "wof:name":"Luwang",
    "wof:placetype":"locality"
},
  "geometry": {"coordinates":[125.68083,5.97194],"type":"Point"}
}