{
  "type": "Feature",
  "properties": {
    "gn:admin1_code":"41",
    "gn:admin2_code":"41",
    "gn:admin3_code":"175206000.0",
    "gn:asciiname":"Pabandugin",
    "gn:country_code":"PH",
    "gn:dem":33,
    "gn:feature_class":"P",
    "gn:feature_code":"PPL",
    "gn:name":"Pabandugin",
    "gn:population":0,
    "gn:timezone":"Asia/Manila",
    "iso:country":"PH",
    "name:eng_x_preferred":[
        "Pabandugin"
    ],
    "wof:name":"Pabandugin",
    "wof:placetype":"locality"
},
  "geometry": {"coordinates":[121.42471999999999,12.94581],"type":"Point"}
}