{
  "type": "Feature",
  "properties": {
    "gn:admin1_code":"06",
    "gn:admin2_code":"18",
    "gn:admin3_code":"61917000.0",
    "gn:asciiname":"Da-an Norte",
    "gn:country_code":"PH",
    "gn:dem":235,
    "gn:feature_class":"P",
    "gn:feature_code":"PPL",
    "gn:name":"Da-an Norte",
    "gn:population":0,
    "gn:timezone":"Asia/Manila",
    "iso:country":"PH",
    "name:fil_x_preferred":[
        "Da-an Norte"
    ],
    "wof:name":"Da-an Norte",
    "wof:placetype":"locality"
},
  "geometry": {"coordinates":[122.4263,11.2911],"type":"Point"}
}