{
  "type": "Feature",
  "properties": {
    "gn:admin1_code":"40",
    "gn:admin2_code":"H2",
    "gn:admin3_code":"45647000.0",
    "gn:asciiname":"Mainit, Tayabas City",
    "gn:country_code":"PH",
    "gn:dem":194,
    "gn:feature_class":"P",
    "gn:feature_code":"PPL",
    "gn:name":"Mainit, Tayabas City",
    "gn:population":0,
    "gn:timezone":"Asia/Manila",
    "iso:country":"PH",
    "wof:name":"Mainit, Tayabas City",
    "wof:placetype":"locality"
},
  "geometry": {"coordinates":[121.63299000000001,14.06378],"type":"Point"}
}