{
  "type": "Feature",
  "properties": {
    "gn:country":"PH",
    "gn:fcode":"PPL",
    "gn:population":7403,
    "iso:country":"PH",
    "name:fil_x_preferred":[
        "Dulao"
    ],
    "qs_pg:aaroncc":"PH",
    "qs_pg:gn_country":"PH",
    "qs_pg:gn_fcode":"PPL",
    "qs_pg:gn_pop":7403,
    "qs_pg:name":"Dulao",
    "qs_pg:photos_9r":0,
    "qs_pg:photos_sr":0,
    "qs_pg:pop_sr":5,
    "qs_pg:qs_pg_placetype":"locality",
    "wof:name":"Dulao",
    "wof:placetype":"locality",
    "wof:population":7403
},
  "geometry": {"coordinates":[122.9383,10.54176],"type":"Point"}
}