{
  "type": "Feature",
  "properties": {
    "gn:admin1_code":"07",
    "gn:admin2_code":"11",
    "gn:admin3_code":"71225000.0",
    "gn:asciiname":"Can-upao",
    "gn:country_code":"PH",
    "gn:dem":9,
    "gn:feature_class":"P",
    "gn:feature_code":"PPL",
    "gn:name":"Can-upao",
    "gn:population":0,
    "gn:timezone":"Asia/Manila",
    "iso:country":"PH",
    "name:fil_x_preferred":[
        "Can-upao"
    ],
    "name:und_x_variant":[
        "Kanopao",
        "Canuba"
    ],
    "wof:name":"Can-upao",
    "wof:placetype":"locality"
},
  "geometry": {"coordinates":[124.3588,9.6418],"type":"Point"}
}