{
  "type": "Feature",
  "properties": {
    "gn:admin1_code":"01",
    "gn:admin2_code":"28",
    "gn:admin3_code":"12819000.0",
    "gn:asciiname":"Baybayaoas",
    "gn:country_code":"PH",
    "gn:dem":54,
    "gn:feature_class":"P",
    "gn:feature_code":"PPL",
    "gn:name":"Baybayaoas",
    "gn:population":0,
    "gn:timezone":"Asia/Manila",
    "iso:country":"PH",
    "name:fil_x_preferred":[
        "Baybayaoas"
    ],
    "wof:name":"Baybayaoas",
    "wof:placetype":"locality"
},
  "geometry": {"coordinates":[120.5137,17.9424],"type":"Point"}
}