{
  "type": "Feature",
  "properties": {
    "gn:country":"PH",
    "gn:fcode":"PPL",
    "gn:population":2213,
    "iso:country":"PH",
    "name:ceb_x_preferred":[
        "Del Monte"
    ],
    "name:fil_x_preferred":[
        "Del Monte"
    ],
    "name:ita_x_preferred":[
        "Del Monte"
    ],
    "name:jpn_x_preferred":[
        "\u30c7\u30eb\u30e2\u30f3\u30c6"
    ],
    "name:nld_x_preferred":[
        "Del Monte"
    ],
    "qs:name":"Del Monte",
    "qs:photos_9r":0,
    "qs:photos_sr":0,
    "qs:pop_sr":"4",
    "wd:wordcount":105,
    "wof:name":"Del Monte",
    "wof:placetype":"locality",
    "wof:population":2213
},
  "geometry": {"coordinates":[123.00806,7.72583],"type":"Point"}
}