{
  "type": "Feature",
  "properties": {
    "gn:country":"PH",
    "gn:fcode":"PPLA3",
    "gn:pop":27247,
    "iso:country":"PH",
    "name:bcl_x_preferred":[
        "Lupon"
    ],
    "name:ceb_x_preferred":[
        "Lupon"
    ],
    "name:deu_x_preferred":[
        "Lupon"
    ],
    "name:dty_x_preferred":[
        "\u0932\u0941\u092a\u094b\u0928"
    ],
    "name:eng_x_preferred":[
        "Lupon"
    ],
    "name:fra_x_preferred":[
        "Lupon"
    ],
    "name:hin_x_preferred":[
        "\u0932\u0941\u092a\u094b\u0928"
    ],
    "name:ilo_x_preferred":[
        "Lupon"
    ],
    "name:ind_x_preferred":[
        "Lupon"
    ],
    "name:ita_x_preferred":[
        "Lupon"
    ],
    "name:nep_x_preferred":[
        "\u0932\u0941\u092a\u094b\u0928"
    ],
    "name:nld_x_preferred":[
        "Lupon"
    ],
    "name:nob_x_preferred":[
        "Lupon"
    ],
    "name:pag_x_preferred":[
        "Lupon"
    ],
    "name:pam_x_preferred":[
        "Lupon"
    ],
    "name:spa_x_preferred":[
        "Lup\u00f3n"
    ],
    "name:swe_x_preferred":[
        "Lupon"
    ],
    "name:tgl_x_preferred":[
        "Lupon"
    ],
    "name:unk_x_variant":[
        "Sumlog"
    ],
    "name:vie_x_preferred":[
        "Lupon"
    ],
    "name:war_x_preferred":[
        "Lupon"
    ],
    "qs:name":"Lupon",
    "qs:photos_9r":0,
    "qs:photos_sr":0,
    "qs:pop_sr":"7",
    "wof:name":"Lupon",
    "wof:placetype":"locality",
    "wof:population":27247
},
  "geometry": {"coordinates":[126.00961,6.89814],"type":"Point"}
}