{
  "type": "Feature",
  "properties": {
    "gn:admin1_code":"06",
    "gn:admin2_code":"30",
    "gn:admin3_code":"63013000.0",
    "gn:asciiname":"Banban Pequeno",
    "gn:country_code":"PH",
    "gn:dem":92,
    "gn:feature_class":"P",
    "gn:feature_code":"PPL",
    "gn:name":"Banban Peque\u00f1o",
    "gn:population":0,
    "gn:timezone":"Asia/Manila",
    "iso:country":"PH",
    "name:fil_x_preferred":[
        "Banban Peque\u00f1o"
    ],
    "wof:name":"Banban Pequeno",
    "wof:placetype":"locality"
},
  "geometry": {"coordinates":[122.51667,11.15],"type":"Point"}
}