{
  "type": "Feature",
  "properties": {
    "gn:admin1_code":"06",
    "gn:admin2_code":"30",
    "gn:admin3_code":"63003000.0",
    "gn:asciiname":"Manganese",
    "gn:country_code":"PH",
    "gn:dem":125,
    "gn:feature_class":"P",
    "gn:feature_code":"PPL",
    "gn:name":"Manganese",
    "gn:population":0,
    "gn:timezone":"Asia/Manila",
    "iso:country":"PH",
    "name:fil_x_preferred":[
        "Manganese"
    ],
    "wof:name":"Manganese",
    "wof:placetype":"locality"
},
  "geometry": {"coordinates":[122.73333,10.98333],"type":"Point"}
}