{
  "type": "Feature",
  "properties": {
    "gn:admin1_code":"40",
    "gn:admin2_code":"33",
    "gn:admin3_code":"43417000.0",
    "gn:asciiname":"Lawaguin",
    "gn:cc2":"PH",
    "gn:country_code":"PH",
    "gn:dem":184,
    "gn:feature_class":"P",
    "gn:feature_code":"PPL",
    "gn:name":"Lawaguin",
    "gn:population":0,
    "gn:timezone":"Asia/Manila",
    "iso:country":"PH",
    "name:und_x_variant":[
        "Lawagin"
    ],
    "wof:name":"Lawaguin",
    "wof:placetype":"locality"
},
  "geometry": {"coordinates":[121.38333,14.15],"type":"Point"}
}