{
  "type": "Feature",
  "properties": {
    "gn:admin1_code":"15",
    "gn:admin2_code":"10",
    "gn:admin3_code":"141111000.0",
    "gn:asciiname":"Pongo",
    "gn:country_code":"PH",
    "gn:dem":1277,
    "gn:feature_class":"P",
    "gn:feature_code":"PPL",
    "gn:name":"Pongo",
    "gn:population":0,
    "gn:timezone":"Asia/Manila",
    "iso:country":"PH",
    "name:ceb_x_preferred":[
        "Pongo"
    ],
    "name:deu_x_preferred":[
        "Pongo"
    ],
    "name:fil_x_preferred":[
        "Pongo"
    ],
    "name:fra_x_preferred":[
        "Pongo"
    ],
    "name:ita_x_preferred":[
        "Pongo"
    ],
    "name:swe_x_preferred":[
        "Pongo"
    ],
    "wof:name":"Pongo",
    "wof:placetype":"locality"
},
  "geometry": {"coordinates":[120.7741,16.7936],"type":"Point"}
}