{
  "type": "Feature",
  "properties": {
    "gn:gn_country":"PH",
    "gn:gn_fcode":"ADM3",
    "gn:gn_pop":17864,
    "gn:population":17864,
    "iso:country":"PH",
    "name:bcl_x_preferred":[
        "Bobon"
    ],
    "name:ceb_x_preferred":[
        "Bobon"
    ],
    "name:deu_x_preferred":[
        "Bobon"
    ],
    "name:fil_x_preferred":[
        "Bobon"
    ],
    "name:fra_x_preferred":[
        "Bobon"
    ],
    "name:ilo_x_preferred":[
        "Bobon"
    ],
    "name:ind_x_preferred":[
        "Bobon"
    ],
    "name:ita_x_preferred":[
        "Bobon"
    ],
    "name:nld_x_preferred":[
        "Bobon"
    ],
    "name:pag_x_preferred":[
        "Bobon"
    ],
    "name:pam_x_preferred":[
        "Bobon"
    ],
    "name:swe_x_preferred":[
        "Bobon"
    ],
    "name:tgl_x_preferred":[
        "Bobon"
    ],
    "name:vie_x_preferred":[
        "Bobon"
    ],
    "name:war_x_preferred":[
        "Bobon"
    ],
    "qs_pg:aaroncc":"PH",
    "qs_pg:gn_country":"PH",
    "qs_pg:gn_fcode":"ADM3",
    "qs_pg:gn_pop":17864,
    "qs_pg:name":"Bobon",
    "qs_pg:photos_9r":0,
    "qs_pg:photos_sr":0,
    "qs_pg:pop_sr":6,
    "qs_pg:qs_pg_placetype":"localadmin",
    "wof:name":"Bobon",
    "wof:placetype":"localadmin",
    "wof:population":17864
},
  "geometry": {"coordinates":[124.53333000000001,12.45],"type":"Point"}
}