{
  "type": "Feature",
  "properties": {
    "gn:admin1_code":"01",
    "gn:admin2_code":"51",
    "gn:admin3_code":"15548000.0",
    "gn:asciiname":"Caaringayan",
    "gn:country_code":"PH",
    "gn:dem":31,
    "gn:feature_class":"P",
    "gn:feature_code":"PPL",
    "gn:name":"Caaringayan",
    "gn:population":0,
    "gn:timezone":"Asia/Manila",
    "iso:country":"PH",
    "name:fil_x_preferred":[
        "Carringayan"
    ],
    "name:fil_x_variant":[
        "Caaringayan"
    ],
    "wof:name":"Caaringayan",
    "wof:placetype":"locality"
},
  "geometry": {"coordinates":[120.56116000000002,16.03862],"type":"Point"}
}