{
  "type": "Feature",
  "properties": {
    "gn:admin1_code":"05",
    "gn:admin2_code":"19",
    "gn:admin3_code":"52008000.0",
    "gn:asciiname":"Jose Rizal",
    "gn:country_code":"PH",
    "gn:dem":56,
    "gn:feature_class":"P",
    "gn:feature_code":"PPL",
    "gn:name":"Jose Rizal",
    "gn:population":0,
    "gn:timezone":"Asia/Manila",
    "iso:country":"PH",
    "name:fil_x_preferred":[
        "Jose Rizal"
    ],
    "wof:name":"Jose Rizal",
    "wof:placetype":"locality"
},
  "geometry": {"coordinates":[124.1489,13.6017],"type":"Point"}
}