{
  "type": "Feature",
  "properties": {
    "gn:admin1_code":"03",
    "gn:admin2_code":"13",
    "gn:admin3_code":"31404000.0",
    "gn:asciiname":"Kaingin",
    "gn:country_code":"PH",
    "gn:dem":7,
    "gn:feature_class":"P",
    "gn:feature_code":"PPL",
    "gn:name":"Kaingin",
    "gn:population":0,
    "gn:timezone":"Asia/Manila",
    "iso:country":"PH",
    "name:fil_x_preferred":[
        "Caingin"
    ],
    "wof:name":"Kaingin",
    "wof:placetype":"locality"
},
  "geometry": {"coordinates":[120.91853999999999,14.80655],"type":"Point"}
}