{
  "type": "Feature",
  "properties": {
    "gn:admin1_code":"07",
    "gn:admin2_code":"11",
    "gn:admin3_code":"71211000.0",
    "gn:asciiname":"Aliguay",
    "gn:country_code":"PH",
    "gn:dem":186,
    "gn:feature_class":"P",
    "gn:feature_code":"PPL",
    "gn:name":"Aliguay",
    "gn:population":0,
    "gn:timezone":"Asia/Manila",
    "iso:country":"PH",
    "name:fil_x_preferred":[
        "Aliguay"
    ],
    "name:und_x_variant":[
        "Aligway"
    ],
    "wof:name":"Aliguay",
    "wof:placetype":"locality"
},
  "geometry": {"coordinates":[124.4423,9.8276],"type":"Point"}
}