{
  "type": "Feature",
  "properties": {
    "gn:admin1_code":"13",
    "gn:admin2_code":"61",
    "gn:admin3_code":"166724000.0",
    "gn:asciiname":"Sani-Sani",
    "gn:country_code":"PH",
    "gn:dem":40,
    "gn:feature_class":"P",
    "gn:feature_code":"PPL",
    "gn:name":"Sani-Sani",
    "gn:population":0,
    "gn:timezone":"Asia/Manila",
    "iso:country":"PH",
    "name:fil_x_preferred":[
        "Sani-Sani"
    ],
    "wof:name":"Sani-Sani",
    "wof:placetype":"locality"
},
  "geometry": {"coordinates":[125.44280000000001,9.8237],"type":"Point"}
}