{
  "type": "Feature",
  "properties": {
    "gn:country":"PH",
    "gn:fcode":"PPL",
    "gn:pop":2394,
    "iso:country":"PH",
    "name:fil_x_preferred":[
        "Mamali"
    ],
    "qs:name":"Mamali",
    "qs:photos_9r":0,
    "qs:photos_sr":0,
    "qs:pop_sr":"4",
    "wof:name":"Mamali",
    "wof:placetype":"locality",
    "wof:population":2394
},
  "geometry": {"coordinates":[124.645,6.77667],"type":"Point"}
}