{
  "type": "Feature",
  "properties": {
    "gn:admin1_code":"02",
    "gn:admin2_code":"31",
    "gn:admin3_code":"23111000.0",
    "gn:asciiname":"Dicatian",
    "gn:country_code":"PH",
    "gn:dem":6,
    "gn:feature_class":"P",
    "gn:feature_code":"PPL",
    "gn:name":"Dicatian",
    "gn:population":0,
    "gn:timezone":"Asia/Manila",
    "iso:country":"PH",
    "name:fil_x_preferred":[
        "Dicatian"
    ],
    "wof:name":"Dicatian",
    "wof:placetype":"locality"
},
  "geometry": {"coordinates":[122.26045000000001,17.35472],"type":"Point"}
}