{
  "type": "Feature",
  "properties": {
    "gn:admin1_code":"03",
    "gn:admin2_code":"63",
    "gn:admin3_code":"36906000.0",
    "gn:asciiname":"New Salem",
    "gn:country_code":"PH",
    "gn:dem":41,
    "gn:feature_class":"P",
    "gn:feature_code":"PPL",
    "gn:name":"New Salem",
    "gn:population":0,
    "gn:timezone":"Asia/Manila",
    "iso:country":"PH",
    "name:cat_x_preferred":[
        "New Salem"
    ],
    "name:ceb_x_preferred":[
        "New Salem"
    ],
    "name:deu_x_preferred":[
        "New Salem"
    ],
    "name:eng_x_preferred":[
        "New Salem"
    ],
    "name:ita_x_preferred":[
        "New Salem"
    ],
    "name:nld_x_preferred":[
        "New Salem"
    ],
    "name:pol_x_preferred":[
        "New Salem"
    ],
    "name:srp_x_preferred":[
        "\u040a\u0443 \u0421\u0435\u0458\u043b\u0435\u043c"
    ],
    "name:swe_x_preferred":[
        "New Salem"
    ],
    "name:vol_x_preferred":[
        "New Salem"
    ],
    "wof:name":"New Salem",
    "wof:placetype":"locality"
},
  "geometry": {"coordinates":[120.51324,15.60337],"type":"Point"}
}