{
  "type": "Feature",
  "properties": {
    "gn:admin1_code":"08",
    "gn:admin2_code":"37",
    "gn:admin3_code":"83738000.0",
    "gn:asciiname":"Cabulihan",
    "gn:cc2":"PH",
    "gn:country_code":"PH",
    "gn:dem":65,
    "gn:feature_class":"P",
    "gn:feature_code":"PPL",
    "gn:name":"Cabulihan",
    "gn:population":0,
    "gn:timezone":"Asia/Manila",
    "iso:country":"PH",
    "name:und_x_variant":[
        "Kabulihan"
    ],
    "wof:name":"Cabulihan",
    "wof:placetype":"locality"
},
  "geometry": {"coordinates":[124.58778,11.09139],"type":"Point"}
}