{
  "type": "Feature",
  "properties": {
    "gn:admin1_code":"02",
    "gn:admin2_code":"31",
    "gn:admin3_code":"23137000.0",
    "gn:asciiname":"Pilitan",
    "gn:country_code":"PH",
    "gn:dem":37,
    "gn:feature_class":"P",
    "gn:feature_code":"PPL",
    "gn:name":"Pilitan",
    "gn:population":0,
    "gn:timezone":"Asia/Manila",
    "iso:country":"PH",
    "name:fil_x_preferred":[
        "Pilitan"
    ],
    "wof:name":"Pilitan",
    "wof:placetype":"locality"
},
  "geometry": {"coordinates":[121.82708999999998,17.24446],"type":"Point"}
}