{
  "type": "Feature",
  "properties": {
    "gn:admin1_code":"12",
    "gn:admin2_code":"B8",
    "gn:asciiname":"Guson",
    "gn:country_code":"PH",
    "gn:dem":7,
    "gn:feature_class":"P",
    "gn:feature_code":"PPL",
    "gn:name":"Guson",
    "gn:population":0,
    "gn:timezone":"Asia/Manila",
    "iso:country":"PH",
    "wof:name":"Guson",
    "wof:placetype":"locality"
},
  "geometry": {"coordinates":[124.27694,7.17028],"type":"Point"}
}