{
  "type": "Feature",
  "properties": {
    "gn:admin1_code":"05",
    "gn:admin2_code":"05",
    "gn:admin3_code":"50501000.0",
    "gn:asciiname":"Picadero",
    "gn:country_code":"PH",
    "gn:dem":45,
    "gn:feature_class":"P",
    "gn:feature_code":"PPL",
    "gn:name":"Picadero",
    "gn:population":0,
    "gn:timezone":"Asia/Manila",
    "iso:country":"PH",
    "name:fil_x_preferred":[
        "Picadero"
    ],
    "wof:name":"Picadero",
    "wof:placetype":"locality"
},
  "geometry": {"coordinates":[123.86360000000001,13.2383],"type":"Point"}
}