{
  "type": "Feature",
  "properties": {
    "gn:admin1_code":"05",
    "gn:admin2_code":"05",
    "gn:admin3_code":"50502000.0",
    "gn:asciiname":"Bariw",
    "gn:country_code":"PH",
    "gn:dem":110,
    "gn:feature_class":"P",
    "gn:feature_code":"PPL",
    "gn:name":"Bariw",
    "gn:population":0,
    "gn:timezone":"Asia/Manila",
    "iso:country":"PH",
    "name:fil_x_preferred":[
        "Bariw"
    ],
    "name:und_x_variant":[
        "Barliw"
    ],
    "wof:name":"Bariw",
    "wof:placetype":"locality"
},
  "geometry": {"coordinates":[123.62730000000001,13.1665],"type":"Point"}
}