{
  "type": "Feature",
  "properties": {
    "gn:admin1_code":"15",
    "gn:admin2_code":"01",
    "gn:admin3_code":"140126000.0",
    "gn:asciiname":"Tubo",
    "gn:country_code":"PH",
    "gn:dem":333,
    "gn:feature_class":"P",
    "gn:feature_code":"PPLA3",
    "gn:name":"Tubo",
    "gn:population":0,
    "gn:timezone":"Asia/Manila",
    "iso:country":"PH",
    "name:ceb_x_preferred":[
        "Tubo"
    ],
    "name:fil_x_preferred":[
        "Tubo"
    ],
    "name:glg_x_preferred":[
        "Tubo"
    ],
    "name:ita_x_preferred":[
        "Tubo"
    ],
    "name:nld_x_preferred":[
        "Tubo"
    ],
    "name:spa_x_preferred":[
        "Tubo"
    ],
    "name:swe_x_preferred":[
        "Tubo"
    ],
    "name:tgl_x_preferred":[
        "Tubo"
    ],
    "name:war_x_preferred":[
        "Tubo"
    ],
    "wof:name":"Tubo",
    "wof:placetype":"locality"
},
  "geometry": {"coordinates":[120.7355,17.2667],"type":"Point"}
}