{
  "type": "Feature",
  "properties": {
    "gn:country":"PH",
    "gn:fcode":"ADM3",
    "gn:pop":45332,
    "iso:country":"PH",
    "name:fil_x_preferred":[
        "Ayungon"
    ],
    "qs:name":"Ayungon",
    "qs:photos_9r":0,
    "qs:photos_sr":0,
    "qs:pop_sr":"7",
    "wd:wordcount":337,
    "wof:name":"Ayungon",
    "wof:placetype":"localadmin",
    "wof:population":45332
},
  "geometry": {"coordinates":[123.06667,9.86667],"type":"Point"}
}