{
  "type": "Feature",
  "properties": {
    "gn:admin1_code":"05",
    "gn:admin2_code":"58",
    "gn:admin3_code":"56216000.0",
    "gn:asciiname":"Himaog",
    "gn:country_code":"PH",
    "gn:dem":85,
    "gn:feature_class":"P",
    "gn:feature_code":"PPL",
    "gn:name":"Himaog",
    "gn:population":0,
    "gn:timezone":"Asia/Manila",
    "iso:country":"PH",
    "name:fil_x_preferred":[
        "Himaog"
    ],
    "wof:name":"Himaog",
    "wof:placetype":"locality"
},
  "geometry": {"coordinates":[124.01667,13.05],"type":"Point"}
}