{
  "type": "Feature",
  "properties": {
    "gn:admin1_code":"40",
    "gn:admin2_code":"33",
    "gn:admin3_code":"43425000.0",
    "gn:asciiname":"Santo Nino",
    "gn:country_code":"PH",
    "gn:dem":10,
    "gn:feature_class":"P",
    "gn:feature_code":"PPL",
    "gn:name":"Santo Ni\u00f1o",
    "gn:population":0,
    "gn:timezone":"Asia/Manila",
    "iso:country":"PH",
    "name:fil_x_preferred":[
        "Santo Ni\u00f1o"
    ],
    "wof:name":"Santo Nino",
    "wof:placetype":"locality"
},
  "geometry": {"coordinates":[121.05951,14.36775],"type":"Point"}
}