{
  "type": "Feature",
  "properties": {
    "gn:admin1_code":"08",
    "gn:admin2_code":"37",
    "gn:admin3_code":"83715000.0",
    "gn:asciiname":"Sadyapun",
    "gn:country_code":"PH",
    "gn:dem":108,
    "gn:feature_class":"P",
    "gn:feature_code":"PPL",
    "gn:name":"Sadyapun",
    "gn:population":0,
    "gn:timezone":"Asia/Manila",
    "iso:country":"PH",
    "name:fil_x_preferred":[
        "Sadyapun"
    ],
    "wof:name":"Sadyapun",
    "wof:placetype":"locality"
},
  "geometry": {"coordinates":[124.73333,11.23333],"type":"Point"}
}