{
  "type": "Feature",
  "properties": {
    "gn:admin1_code":"05",
    "gn:admin2_code":"15",
    "gn:admin3_code":"51603000.0",
    "gn:asciiname":"Malape",
    "gn:country_code":"PH",
    "gn:dem":3,
    "gn:feature_class":"P",
    "gn:feature_code":"PPL",
    "gn:name":"Malape",
    "gn:population":0,
    "gn:timezone":"Asia/Manila",
    "iso:country":"PH",
    "name:fil_x_preferred":[
        "Malape"
    ],
    "name:und_x_variant":[
        "Malope"
    ],
    "wof:name":"Malape",
    "wof:placetype":"locality"
},
  "geometry": {"coordinates":[122.9658,14.1447],"type":"Point"}
}