{
  "type": "Feature",
  "properties": {
    "gn:admin1_code":"10",
    "gn:admin2_code":"42",
    "gn:admin3_code":"104215000.0",
    "gn:asciiname":"Bintana",
    "gn:country_code":"PH",
    "gn:dem":195,
    "gn:feature_class":"P",
    "gn:feature_code":"PPL",
    "gn:name":"Bintana",
    "gn:population":0,
    "gn:timezone":"Asia/Manila",
    "iso:country":"PH",
    "name:fil_x_preferred":[
        "Bintana"
    ],
    "wof:name":"Bintana",
    "wof:placetype":"locality"
},
  "geometry": {"coordinates":[123.68600000000001,8.0797],"type":"Point"}
}