{
  "type": "Feature",
  "properties": {
    "gn:admin1_code":"08",
    "gn:admin2_code":"55",
    "gn:admin3_code":"86013000.0",
    "gn:asciiname":"Lale",
    "gn:cc2":"PH",
    "gn:country_code":"PH",
    "gn:dem":84,
    "gn:feature_class":"P",
    "gn:feature_code":"PPL",
    "gn:name":"Lale",
    "gn:population":0,
    "gn:timezone":"Asia/Manila",
    "iso:country":"PH",
    "name:ceb_x_preferred":[
        "Lale"
    ],
    "name:deu_x_preferred":[
        "Lale"
    ],
    "name:fra_x_preferred":[
        "Lale"
    ],
    "name:glg_x_preferred":[
        "Lale"
    ],
    "name:swe_x_preferred":[
        "Lale"
    ],
    "name:tur_x_preferred":[
        "Lale"
    ],
    "name:und_x_variant":[
        "Lalo"
    ],
    "wof:name":"Lale",
    "wof:placetype":"locality"
},
  "geometry": {"coordinates":[125.05,11.53333],"type":"Point"}
}