{
  "type": "Feature",
  "properties": {
    "gn:admin1_code":"03",
    "gn:admin2_code":"47",
    "gn:admin3_code":"34919000.0",
    "gn:asciiname":"Maligaya",
    "gn:country_code":"PH",
    "gn:dem":122,
    "gn:feature_class":"P",
    "gn:feature_code":"PPL",
    "gn:name":"Maligaya",
    "gn:population":0,
    "gn:timezone":"Asia/Manila",
    "iso:country":"PH",
    "name:fil_x_preferred":[
        "Maligaya"
    ],
    "wof:name":"Maligaya",
    "wof:placetype":"locality"
},
  "geometry": {"coordinates":[121.1186,15.46182],"type":"Point"}
}