{
  "type": "Feature",
  "properties": {
    "gn:admin1_code":"03",
    "gn:admin2_code":"50",
    "gn:admin3_code":"35401000.0",
    "gn:asciiname":"Pulungcacutud",
    "gn:country_code":"PH",
    "gn:dem":74,
    "gn:feature_class":"P",
    "gn:feature_code":"PPL",
    "gn:name":"Pulungcacutud",
    "gn:population":0,
    "gn:timezone":"Asia/Manila",
    "iso:country":"PH",
    "name:fil_x_preferred":[
        "Pulungcacutud"
    ],
    "name:fil_x_variant":[
        "Pulong Cacutud"
    ],
    "name:und_x_variant":[
        "Pulong Cacutud"
    ],
    "wof:name":"Pulungcacutud",
    "wof:placetype":"locality"
},
  "geometry": {"coordinates":[120.6262,15.1756],"type":"Point"}
}