{
  "type": "Feature",
  "properties": {
    "gn:admin1_code":"15",
    "gn:admin2_code":"32",
    "gn:admin3_code":"143201000.0",
    "gn:asciiname":"Balantoy",
    "gn:country_code":"PH",
    "gn:dem":832,
    "gn:feature_class":"P",
    "gn:feature_code":"PPL",
    "gn:name":"Balantoy",
    "gn:population":0,
    "gn:timezone":"Asia/Manila",
    "iso:country":"PH",
    "name:fil_x_preferred":[
        "Balantoy"
    ],
    "wof:name":"Balantoy",
    "wof:placetype":"locality"
},
  "geometry": {"coordinates":[121.22410000000001,17.4803],"type":"Point"}
}