{
  "type": "Feature",
  "properties": {
    "gn:country":"PH",
    "gn:fcode":"PPL",
    "gn:population":3610,
    "iso:country":"PH",
    "name:und_x_variant":[
        "Bactad West"
    ],
    "qs:name":"Bactad Proper",
    "qs:photos_9r":0,
    "qs:photos_sr":0,
    "qs:pop_sr":"4",
    "wof:name":"Bactad Proper",
    "wof:placetype":"locality",
    "wof:population":3610
},
  "geometry": {"coordinates":[120.61026,15.97842],"type":"Point"}
}