{
  "type": "Feature",
  "properties": {
    "gn:admin1_code":"40",
    "gn:admin2_code":"09",
    "gn:admin3_code":"41024000.0",
    "gn:asciiname":"Bagong Tubig",
    "gn:country_code":"PH",
    "gn:dem":7,
    "gn:feature_class":"P",
    "gn:feature_code":"PPL",
    "gn:name":"Bagong Tubig",
    "gn:population":0,
    "gn:timezone":"Asia/Manila",
    "iso:country":"PH",
    "name:und_x_variant":[
        "Baguntubig",
        "Bagong Tubig"
    ],
    "wof:name":"Bagong Tubig",
    "wof:placetype":"locality"
},
  "geometry": {"coordinates":[120.91764000000001,13.84358],"type":"Point"}
}