{
  "type": "Feature",
  "properties": {
    "gn:country":"PH",
    "gn:fcode":"PPL",
    "gn:population":2173,
    "iso:country":"PH",
    "name:fil_x_preferred":[
        "Banquero"
    ],
    "name:fil_x_variant":[
        "Banguero"
    ],
    "qs:name":"Banguero",
    "qs:photos_9r":0,
    "qs:photos_sr":0,
    "qs:pop_sr":"4",
    "wof:name":"Banguero",
    "wof:placetype":"locality",
    "wof:population":2173
},
  "geometry": {"coordinates":[121.77834,17.02305],"type":"Point"}
}