{
  "type": "Feature",
  "properties": {
    "gn:admin1_code":"41",
    "gn:admin2_code":"54",
    "gn:admin3_code":"175910000.0",
    "gn:asciiname":"Capaclan",
    "gn:country_code":"PH",
    "gn:dem":19,
    "gn:feature_class":"P",
    "gn:feature_code":"PPL",
    "gn:name":"Capaclan",
    "gn:population":0,
    "gn:timezone":"Asia/Manila",
    "iso:country":"PH",
    "name:fil_x_preferred":[
        "Capaclan"
    ],
    "wof:name":"Capaclan",
    "wof:placetype":"locality"
},
  "geometry": {"coordinates":[122.27481,12.58953],"type":"Point"}
}