{
  "type": "Feature",
  "properties": {
    "iso:country":"PH",
    "name:bcl_x_preferred":[
        "Medina"
    ],
    "name:cbk_zam_x_preferred":[
        "Medina"
    ],
    "name:ceb_x_preferred":[
        "Medina"
    ],
    "name:deu_x_preferred":[
        "Medina"
    ],
    "name:eng_x_preferred":[
        "Medina"
    ],
    "name:fra_x_preferred":[
        "Medina"
    ],
    "name:ilo_x_preferred":[
        "Medina"
    ],
    "name:ind_x_preferred":[
        "Medina"
    ],
    "name:ita_x_preferred":[
        "Medina"
    ],
    "name:nld_x_preferred":[
        "Medina"
    ],
    "name:pag_x_preferred":[
        "Medina"
    ],
    "name:pam_x_preferred":[
        "Medina"
    ],
    "name:spa_x_preferred":[
        "Medina de Gi\u00f1goog"
    ],
    "name:swe_x_preferred":[
        "Medina"
    ],
    "name:tgl_x_preferred":[
        "Medina"
    ],
    "name:urd_x_preferred":[
        "\u0645\u062f\u06cc\u0646\u06c1\u060c \u0645\u06cc\u0633\u0627\u0645\u0633 \u0634\u0631\u0642\u06cc"
    ],
    "name:urd_x_variant":[
        "\u0645\u062f\u06cc\u0646\u06c1"
    ],
    "name:vie_x_preferred":[
        "Medina"
    ],
    "name:war_x_preferred":[
        "Medina"
    ],
    "qs:gn_country":"PH",
    "qs:gn_fcode":"PPLA3",
    "qs:gn_pop":9201,
    "qs:name":"Medina",
    "qs:name_adm0":"Philippines",
    "qs:name_adm1":"Northern Mindanao",
    "qs:photos":130,
    "qs:photos_1k":26,
    "qs:photos_9k":1,
    "qs:photos_9r":3,
    "qs:photos_all":130,
    "qs:photos_sr":3,
    "qs:placetype":"Town",
    "qs:pop_sr":"5",
    "qs:woe_adm0":23424934,
    "wd:wordcount":172,
    "wof:name":"Medina",
    "wof:placetype":"locality",
    "wof:population":9201
},
  "geometry": {"coordinates":[125.02444,8.91222],"type":"Point"}
}