{
  "type": "Feature",
  "properties": {
    "gn:admin1_code":"41",
    "gn:admin2_code":"49",
    "gn:admin3_code":"175305000.0",
    "gn:asciiname":"Kamaga",
    "gn:country_code":"PH",
    "gn:dem":7,
    "gn:feature_class":"P",
    "gn:feature_code":"PPL",
    "gn:name":"Kamaga",
    "gn:population":0,
    "gn:timezone":"Asia/Manila",
    "iso:country":"PH",
    "name:eng_x_preferred":[
        "Kamaga"
    ],
    "wof:name":"Kamaga",
    "wof:placetype":"locality"
},
  "geometry": {"coordinates":[117.17859,8.36004],"type":"Point"}
}