{
  "type": "Feature",
  "properties": {
    "gn:admin1_code":"11",
    "gn:admin2_code":"26",
    "gn:admin3_code":"112504000.0",
    "gn:asciiname":"Carmelo",
    "gn:country_code":"PH",
    "gn:dem":1210,
    "gn:feature_class":"P",
    "gn:feature_code":"PPL",
    "gn:name":"Carmelo",
    "gn:population":0,
    "gn:timezone":"Asia/Manila",
    "iso:country":"PH",
    "name:bre_x_preferred":[
        "Carmelo"
    ],
    "name:deu_x_preferred":[
        "Carmelo"
    ],
    "name:fil_x_preferred":[
        "Carmelo"
    ],
    "name:hun_x_preferred":[
        "Carmelo"
    ],
    "name:ita_x_preferred":[
        "Carmelo"
    ],
    "name:lat_x_preferred":[
        "Carmelo"
    ],
    "name:nor_x_preferred":[
        "Carmelo"
    ],
    "name:spa_x_preferred":[
        "Carmelo"
    ],
    "wof:name":"Carmelo",
    "wof:placetype":"locality"
},
  "geometry": {"coordinates":[126.40000000000001,7.35],"type":"Point"}
}