{
  "type": "Feature",
  "properties": {
    "gn:country":"PH",
    "gn:fcode":"ADM3",
    "gn:population":68846,
    "iso:country":"PH",
    "name:bul_x_preferred":[
        "\u041b\u0438\u0431\u043e\u043d"
    ],
    "name:ceb_x_preferred":[
        "Libon"
    ],
    "name:deu_x_preferred":[
        "Libon"
    ],
    "name:fil_x_preferred":[
        "Libon"
    ],
    "name:fra_x_preferred":[
        "Libon"
    ],
    "name:rus_x_preferred":[
        "\u041b\u0438\u0431\u043e\u043d"
    ],
    "name:swe_x_preferred":[
        "Libon"
    ],
    "qs:name":"Libon",
    "qs:photos_9r":0,
    "qs:photos_sr":0,
    "qs:pop_sr":"8",
    "wd:wordcount":38,
    "wof:name":"Libon",
    "wof:placetype":"localadmin",
    "wof:population":68846
},
  "geometry": {"coordinates":[123.38333,13.26667],"type":"Point"}
}