{
  "type": "Feature",
  "properties": {
    "gn:admin1_code":"12",
    "gn:admin2_code":"71",
    "gn:admin3_code":"126501000.0",
    "gn:asciiname":"New Pangasinan",
    "gn:country_code":"PH",
    "gn:dem":77,
    "gn:feature_class":"P",
    "gn:feature_code":"PPL",
    "gn:name":"New Pangasinan",
    "gn:population":0,
    "gn:timezone":"Asia/Manila",
    "iso:country":"PH",
    "name:fil_x_preferred":[
        "New Pangasinan"
    ],
    "wof:name":"New Pangasinan",
    "wof:placetype":"locality"
},
  "geometry": {"coordinates":[124.56134,6.62404],"type":"Point"}
}