{
  "type": "Feature",
  "properties": {
    "gn:gn_country":"PH",
    "gn:gn_fcode":"PPL",
    "gn:gn_pop":3715,
    "gn:population":3715,
    "iso:country":"PH",
    "name:fil_x_preferred":[
        "Ayusan"
    ],
    "name:fil_x_variant":[
        "Ayusan I"
    ],
    "qs_pg:aaroncc":"PH",
    "qs_pg:gn_country":"PH",
    "qs_pg:gn_fcode":"PPL",
    "qs_pg:gn_pop":3715,
    "qs_pg:name":"Ayusan Uno",
    "qs_pg:photos_9r":0,
    "qs_pg:photos_sr":0,
    "qs_pg:pop_sr":4,
    "qs_pg:qs_pg_placetype":"locality",
    "wof:name":"Ayusan Uno",
    "wof:placetype":"locality",
    "wof:population":3715
},
  "geometry": {"coordinates":[121.30765,13.95609],"type":"Point"}
}