{
  "type": "Feature",
  "properties": {
    "gn:admin1_code":"08",
    "gn:admin2_code":"55",
    "gn:admin3_code":"86019000.0",
    "gn:asciiname":"Corregidor",
    "gn:country_code":"PH",
    "gn:dem":11,
    "gn:feature_class":"P",
    "gn:feature_code":"PPL",
    "gn:name":"Corregidor",
    "gn:population":0,
    "gn:timezone":"Asia/Manila",
    "iso:country":"PH",
    "name:ceb_x_preferred":[
        "Corregidor"
    ],
    "name:ces_x_preferred":[
        "Corregidor"
    ],
    "name:dan_x_preferred":[
        "Corregidor"
    ],
    "name:deu_x_preferred":[
        "Corregidor"
    ],
    "name:epo_x_preferred":[
        "Corregidor"
    ],
    "name:fil_x_preferred":[
        "Corregidor"
    ],
    "name:fra_x_preferred":[
        "Corregidor"
    ],
    "name:ilo_x_preferred":[
        "Corregidor"
    ],
    "name:ind_x_preferred":[
        "Corregidor"
    ],
    "name:ita_x_preferred":[
        "Corregidor"
    ],
    "name:jpn_x_preferred":[
        "\u30b3\u30ec\u30d2\u30c9\u30fc\u30eb\u5cf6"
    ],
    "name:kor_x_preferred":[
        "\ucf54\ub808\ud788\ub3c4\ub974\uc12c"
    ],
    "name:lit_x_preferred":[
        "Koregidoras"
    ],
    "name:msa_x_preferred":[
        "Corregidor"
    ],
    "name:nld_x_preferred":[
        "Corregidor"
    ],
    "name:nor_x_preferred":[
        "Corregidor"
    ],
    "name:pag_x_preferred":[
        "Corregidor"
    ],
    "name:pol_x_preferred":[
        "Corregidor"
    ],
    "name:por_x_preferred":[
        "Corregidor"
    ],
    "name:spa_x_preferred":[
        "Corregidor"
    ],
    "name:swe_x_preferred":[
        "Corregidor"
    ],
    "name:tgl_x_preferred":[
        "Corregidor"
    ],
    "name:tha_x_preferred":[
        "\u0e40\u0e01\u0e32\u0e30\u0e01\u0e2d\u0e23\u0e4c\u0e40\u0e23\u0e2e\u0e35\u0e14\u0e2d\u0e23\u0e4c"
    ],
    "name:ukr_x_preferred":[
        "\u041a\u043e\u0440\u0440\u0435\u0445\u0456\u0434\u043e\u0440"
    ],
    "name:zho_x_preferred":[
        "\u79d1\u96f7\u5e0c\u591a\u5c9b"
    ],
    "wof:name":"Corregidor",
    "wof:placetype":"locality"
},
  "geometry": {"coordinates":[124.83620000000001,11.4766],"type":"Point"}
}