{
  "type": "Feature",
  "properties": {
    "gn:admin1_code":"06",
    "gn:admin2_code":"H3",
    "gn:admin3_code":"64524000.0",
    "gn:asciiname":"Fortuna",
    "gn:country_code":"PH",
    "gn:dem":6,
    "gn:feature_class":"P",
    "gn:feature_code":"PPL",
    "gn:name":"Fortuna",
    "gn:population":0,
    "gn:timezone":"Asia/Manila",
    "iso:country":"PH",
    "name:fil_x_preferred":[
        "La Fortuna"
    ],
    "name:und_x_variant":[
        "Portuna",
        "Fortuna"
    ],
    "wof:name":"Fortuna",
    "wof:placetype":"locality"
},
  "geometry": {"coordinates":[123.352,10.41267],"type":"Point"}
}