{
  "type": "Feature",
  "properties": {
    "gn:admin1_code":"02",
    "gn:admin2_code":"48",
    "gn:admin3_code":"25004000.0",
    "gn:asciiname":"Ducait",
    "gn:country_code":"PH",
    "gn:dem":338,
    "gn:feature_class":"P",
    "gn:feature_code":"PPL",
    "gn:name":"Ducait",
    "gn:population":0,
    "gn:timezone":"Asia/Manila",
    "iso:country":"PH",
    "name:fil_x_preferred":[
        "Ducait"
    ],
    "wof:name":"Ducait",
    "wof:placetype":"locality"
},
  "geometry": {"coordinates":[121.08333,16.36667000000001],"type":"Point"}
}