{
  "type": "Feature",
  "properties": {
    "gn:country":"PH",
    "gn:fcode":"PPL",
    "gn:pop":4644,
    "iso:country":"PH",
    "name:fil_x_preferred":[
        "San Carlos"
    ],
    "qs:name":"San Carlos",
    "qs:photos_9r":0,
    "qs:photos_sr":0,
    "qs:pop_sr":"4",
    "wd:wordcount":508,
    "wof:name":"San Carlos",
    "wof:placetype":"locality",
    "wof:population":4644
},
  "geometry": {"coordinates":[121.24160000000001,13.8422],"type":"Point"}
}