{
  "type": "Feature",
  "properties": {
    "gn:admin1_code":"15",
    "gn:admin2_code":"27",
    "gn:admin3_code":"142702000.0",
    "gn:asciiname":"Awa",
    "gn:country_code":"PH",
    "gn:dem":940,
    "gn:feature_class":"P",
    "gn:feature_code":"PPL",
    "gn:name":"Awa",
    "gn:population":0,
    "gn:timezone":"Asia/Manila",
    "iso:country":"PH",
    "name:fil_x_preferred":[
        "Awa"
    ],
    "wof:name":"Awa",
    "wof:placetype":"locality"
},
  "geometry": {"coordinates":[120.9948,16.8063],"type":"Point"}
}