{
  "type": "Feature",
  "properties": {
    "gn:country":"PH",
    "gn:fcode":"PPL",
    "gn:pop":2587,
    "iso:country":"PH",
    "name:unk_x_variant":[
        "Calapi"
    ],
    "qs:name":"Calape",
    "qs:photos_9r":0,
    "qs:photos_sr":0,
    "qs:pop_sr":"4",
    "wof:name":"Calape",
    "wof:placetype":"locality",
    "wof:population":2587
},
  "geometry": {"coordinates":[125.02139,11.9425],"type":"Point"}
}