{
  "type": "Feature",
  "properties": {
    "gn:admin1_code":"14",
    "gn:admin2_code":"35",
    "gn:admin3_code":"153632000.0",
    "gn:asciiname":"Tatarikan",
    "gn:country_code":"PH",
    "gn:dem":697,
    "gn:feature_class":"P",
    "gn:feature_code":"PPL",
    "gn:name":"Tatarikan",
    "gn:population":0,
    "gn:timezone":"Asia/Manila",
    "iso:country":"PH",
    "name:fil_x_preferred":[
        "Tatarikan"
    ],
    "wof:name":"Tatarikan",
    "wof:placetype":"locality"
},
  "geometry": {"coordinates":[124.07861,7.73833],"type":"Point"}
}