{
  "type": "Feature",
  "properties": {
    "gn:admin1_code":"41",
    "gn:admin2_code":"54",
    "gn:admin3_code":"175909000.0",
    "gn:asciiname":"Amatong",
    "gn:country_code":"PH",
    "gn:dem":294,
    "gn:feature_class":"P",
    "gn:feature_code":"PPL",
    "gn:name":"Amatong",
    "gn:population":0,
    "gn:timezone":"Asia/Manila",
    "iso:country":"PH",
    "name:fil_x_preferred":[
        "Amatong"
    ],
    "wof:name":"Amatong",
    "wof:placetype":"locality"
},
  "geometry": {"coordinates":[122.04671,12.36129],"type":"Point"}
}