{
  "type": "Feature",
  "properties": {
    "gn:admin1_code":"01",
    "gn:admin2_code":"51",
    "gn:admin3_code":"15535000.0",
    "gn:asciiname":"Cabaritan",
    "gn:country_code":"PH",
    "gn:dem":55,
    "gn:feature_class":"P",
    "gn:feature_code":"PPL",
    "gn:name":"Cabaritan",
    "gn:population":0,
    "gn:timezone":"Asia/Manila",
    "iso:country":"PH",
    "name:fil_x_preferred":[
        "Cabaritan"
    ],
    "wof:name":"Cabaritan",
    "wof:placetype":"locality"
},
  "geometry": {"coordinates":[120.65219,16.04807000000001],"type":"Point"}
}