{
  "type": "Feature",
  "properties": {
    "gn:admin1_code":"05",
    "gn:admin2_code":"39",
    "gn:admin3_code":"54110000.0",
    "gn:asciiname":"Looc",
    "gn:country_code":"PH",
    "gn:dem":10,
    "gn:feature_class":"P",
    "gn:feature_code":"PPL",
    "gn:name":"Looc",
    "gn:population":0,
    "gn:timezone":"Asia/Manila",
    "iso:country":"PH",
    "name:ceb_x_preferred":[
        "Looc"
    ],
    "name:deu_x_preferred":[
        "Looc"
    ],
    "name:fil_x_preferred":[
        "Looc"
    ],
    "name:ita_x_preferred":[
        "Looc"
    ],
    "name:nld_x_preferred":[
        "Looc"
    ],
    "name:war_x_preferred":[
        "Looc"
    ],
    "wof:name":"Looc",
    "wof:placetype":"locality"
},
  "geometry": {"coordinates":[123.25411,12.11575],"type":"Point"}
}