{
  "type": "Feature",
  "properties": {
    "gn:country":"PH",
    "gn:fcode":"PPL",
    "gn:pop":5418,
    "iso:country":"PH",
    "name:fil_x_preferred":[
        "Soyung"
    ],
    "name:fil_x_variant":[
        "Soyon"
    ],
    "name:unk_x_variant":[
        "Soyon"
    ],
    "qs:name":"Soyung",
    "qs:photos_9r":0,
    "qs:photos_sr":0,
    "qs:pop_sr":"5",
    "wof:name":"Soyung",
    "wof:placetype":"locality",
    "wof:population":5418
},
  "geometry": {"coordinates":[121.66549999999999,16.7001],"type":"Point"}
}