{
  "type": "Feature",
  "properties": {
    "gn:admin1_code":"07",
    "gn:admin2_code":"21",
    "gn:admin3_code":"72213000.0",
    "gn:asciiname":"Bongoyan",
    "gn:cc2":"PH",
    "gn:country_code":"PH",
    "gn:dem":129,
    "gn:feature_class":"P",
    "gn:feature_code":"PPL",
    "gn:name":"Bongoyan",
    "gn:population":0,
    "gn:timezone":"Asia/Manila",
    "iso:country":"PH",
    "name:und_x_variant":[
        "Bongayan",
        "Bongoyan"
    ],
    "wof:name":"Bongoyan",
    "wof:placetype":"locality"
},
  "geometry": {"coordinates":[124.00388999999998,10.85778],"type":"Point"}
}