{
  "type": "Feature",
  "properties": {
    "gn:country":"PH",
    "gn:fcode":"PPLA3",
    "gn:pop":6345,
    "iso:country":"PH",
    "name:bcl_x_preferred":[
        "San Fernando"
    ],
    "name:ceb_x_preferred":[
        "San Fernando"
    ],
    "name:deu_x_preferred":[
        "San Fernando"
    ],
    "name:eng_x_preferred":[
        "San Fernando"
    ],
    "name:fil_x_preferred":[
        "San Fernando"
    ],
    "name:fra_x_preferred":[
        "San Fernando"
    ],
    "name:gor_x_preferred":[
        "San Fernando"
    ],
    "name:ilo_x_preferred":[
        "San Fernando"
    ],
    "name:ind_x_preferred":[
        "San Fernando"
    ],
    "name:ita_x_preferred":[
        "San Fernando"
    ],
    "name:nld_x_preferred":[
        "San Fernando"
    ],
    "name:pag_x_preferred":[
        "San Fernando"
    ],
    "name:pam_x_preferred":[
        "San Fernando"
    ],
    "name:rus_x_preferred":[
        "\u0421\u0430\u043d - \u0424\u0435\u0440\u043d\u0430\u043d\u0434\u043e"
    ],
    "name:swe_x_preferred":[
        "San Fernando"
    ],
    "name:tgl_x_preferred":[
        "San Fernando"
    ],
    "name:war_x_preferred":[
        "San Fernando"
    ],
    "qs:name":"San Fernando",
    "qs:photos_9r":0,
    "qs:photos_sr":0,
    "qs:pop_sr":"5",
    "wd:wordcount":216,
    "wof:name":"San Fernando",
    "wof:placetype":"locality",
    "wof:population":6345
},
  "geometry": {"coordinates":[123.14530000000001,13.5656],"type":"Point"}
}