{
  "type": "Feature",
  "properties": {
    "gn:country":"PH",
    "gn:fcode":"PPL",
    "gn:pop":2262,
    "iso:country":"PH",
    "name:fil_x_preferred":[
        "Upig"
    ],
    "name:fil_x_variant":[
        "Upeg"
    ],
    "name:unk_x_variant":[
        "Upeg"
    ],
    "qs:name":"Upig",
    "qs:photos_9r":0,
    "qs:photos_sr":0,
    "qs:pop_sr":"4",
    "wof:name":"Upig",
    "wof:placetype":"locality",
    "wof:population":2262
},
  "geometry": {"coordinates":[120.99193,15.02551],"type":"Point"}
}