{
  "type": "Feature",
  "properties": {
    "gn:country":"PH",
    "gn:fcode":"PPLA3",
    "gn:population":4276,
    "iso:country":"PH",
    "name:bcl_x_preferred":[
        "Del Carmen"
    ],
    "name:cat_x_preferred":[
        "Del Carmen"
    ],
    "name:ceb_x_preferred":[
        "Del Carmen"
    ],
    "name:deu_x_preferred":[
        "Del Carmen"
    ],
    "name:eng_x_preferred":[
        "Del Carmen, Surigao del Norte"
    ],
    "name:eng_x_variant":[
        "Del Carmen"
    ],
    "name:fra_x_preferred":[
        "Del Carmen"
    ],
    "name:ilo_x_preferred":[
        "Del Carmen"
    ],
    "name:ind_x_preferred":[
        "Del Carmen"
    ],
    "name:ita_x_preferred":[
        "Del Carmen"
    ],
    "name:jpn_x_preferred":[
        "\u30c7\u30eb\u30ab\u30eb\u30e1\u30f3"
    ],
    "name:nld_x_preferred":[
        "Del Carmen"
    ],
    "name:nob_x_preferred":[
        "Del Carmen"
    ],
    "name:oci_x_preferred":[
        "Del Carmen"
    ],
    "name:pag_x_preferred":[
        "Del Carmen"
    ],
    "name:pam_x_preferred":[
        "Del Carmen"
    ],
    "name:spa_x_preferred":[
        "Del Carmen"
    ],
    "name:swe_x_preferred":[
        "Del Carmen"
    ],
    "name:tgl_x_preferred":[
        "Del Carmen"
    ],
    "name:und_x_variant":[
        "Nomantag"
    ],
    "name:vie_x_preferred":[
        "Del Carmen"
    ],
    "name:war_x_preferred":[
        "Del Carmen"
    ],
    "qs:name":"Del Carmen",
    "qs:photos_9r":0,
    "qs:photos_sr":0,
    "qs:pop_sr":"4",
    "wof:name":"Del Carmen",
    "wof:placetype":"locality",
    "wof:population":4276
},
  "geometry": {"coordinates":[125.96972,9.86944],"type":"Point"}
}