{
  "type": "Feature",
  "properties": {
    "gn:admin1_code":"14",
    "gn:admin2_code":"60",
    "gn:admin3_code":"156616000.0",
    "gn:asciiname":"Tiptipon",
    "gn:country_code":"PH",
    "gn:dem":104,
    "gn:feature_class":"P",
    "gn:feature_code":"PPL",
    "gn:name":"Tiptipon",
    "gn:population":0,
    "gn:timezone":"Asia/Manila",
    "iso:country":"PH",
    "name:fil_x_preferred":[
        "Tiptipon"
    ],
    "wof:name":"Tiptipon",
    "wof:placetype":"locality"
},
  "geometry": {"coordinates":[121.16639000000001,5.99694],"type":"Point"}
}