{
  "type": "Feature",
  "properties": {
    "gn:admin1_code":"06",
    "gn:admin2_code":"30",
    "gn:admin3_code":"63030000.0",
    "gn:asciiname":"Quirayan",
    "gn:country_code":"PH",
    "gn:dem":16,
    "gn:feature_class":"P",
    "gn:feature_code":"PPL",
    "gn:name":"Quirayan",
    "gn:population":0,
    "gn:timezone":"Asia/Manila",
    "iso:country":"PH",
    "name:fil_x_preferred":[
        "Quirayan"
    ],
    "name:und_x_variant":[
        "Kirayan",
        "Quirayan Tacas"
    ],
    "wof:name":"Quirayan",
    "wof:placetype":"locality"
},
  "geometry": {"coordinates":[122.25109999999999,10.6455],"type":"Point"}
}