{
  "type": "Feature",
  "properties": {
    "gn:admin1_code":"40",
    "gn:admin2_code":"09",
    "gn:admin3_code":"41031000.0",
    "gn:asciiname":"Pantay na Bata",
    "gn:country_code":"PH",
    "gn:dem":142,
    "gn:feature_class":"P",
    "gn:feature_code":"PPL",
    "gn:name":"Pantay na Bata",
    "gn:population":0,
    "gn:timezone":"Asia/Manila",
    "iso:country":"PH",
    "name:fil_x_preferred":[
        "Pantay na Bata"
    ],
    "wof:name":"Pantay na Bata",
    "wof:placetype":"locality"
},
  "geometry": {"coordinates":[121.11739,14.12776],"type":"Point"}
}