{
  "type": "Feature",
  "properties": {
    "gn:gn_country":"PH",
    "gn:gn_fcode":"PPL",
    "gn:gn_pop":7298,
    "gn:population":7298,
    "iso:country":"PH",
    "name:unk_x_variant":[
        "Baracaton"
    ],
    "qs_pg:aaroncc":"PH",
    "qs_pg:gn_country":"PH",
    "qs_pg:gn_fcode":"PPL",
    "qs_pg:gn_pop":7298,
    "qs_pg:name":"Baracatan",
    "qs_pg:photos_9r":0,
    "qs_pg:photos_sr":0,
    "qs_pg:pop_sr":5,
    "qs_pg:qs_pg_placetype":"locality",
    "wof:name":"Baracatan",
    "wof:placetype":"locality",
    "wof:population":7298
},
  "geometry": {"coordinates":[125.41583,6.9675],"type":"Point"}
}