{
  "type": "Feature",
  "properties": {
    "gn:admin1_code":"07",
    "gn:admin2_code":"21",
    "gn:admin3_code":"72248000.0",
    "gn:asciiname":"Lib-og",
    "gn:country_code":"PH",
    "gn:dem":22,
    "gn:feature_class":"P",
    "gn:feature_code":"PPL",
    "gn:name":"Lib-og",
    "gn:population":0,
    "gn:timezone":"Asia/Manila",
    "iso:country":"PH",
    "name:fil_x_preferred":[
        "Lib-og"
    ],
    "wof:name":"Lib-og",
    "wof:placetype":"locality"
},
  "geometry": {"coordinates":[124.0415,10.9815],"type":"Point"}
}