{
  "type": "Feature",
  "properties": {
    "gn:admin1_code":"01",
    "gn:admin2_code":"28",
    "gn:admin3_code":"12819000.0",
    "gn:asciiname":"Nagnoidan",
    "gn:country_code":"PH",
    "gn:dem":82,
    "gn:feature_class":"P",
    "gn:feature_code":"PPL",
    "gn:name":"Nagnoidan",
    "gn:population":0,
    "gn:timezone":"Asia/Manila",
    "iso:country":"PH",
    "name:fil_x_preferred":[
        "Nagnoidan"
    ],
    "name:und_x_variant":[
        "Natrigoan"
    ],
    "wof:name":"Nagnoidan",
    "wof:placetype":"locality"
},
  "geometry": {"coordinates":[120.5513,17.9717],"type":"Point"}
}