{
  "type": "Feature",
  "properties": {
    "gn:admin1_code":"05",
    "gn:admin2_code":"39",
    "gn:admin3_code":"54112000.0",
    "gn:asciiname":"Nabalasan",
    "gn:country_code":"PH",
    "gn:dem":9,
    "gn:feature_class":"P",
    "gn:feature_code":"PPL",
    "gn:name":"Nabalasan",
    "gn:population":0,
    "gn:timezone":"Asia/Manila",
    "iso:country":"PH",
    "name:fil_x_preferred":[
        "Nabalasan"
    ],
    "wof:name":"Nabalasan",
    "wof:placetype":"locality"
},
  "geometry": {"coordinates":[123.5949,12.1379],"type":"Point"}
}