{
  "type": "Feature",
  "properties": {
    "gn:admin1_code":"06",
    "gn:admin2_code":"04",
    "gn:asciiname":"Aslum",
    "gn:cc2":"PH",
    "gn:country_code":"PH",
    "gn:dem":-9999,
    "gn:feature_class":"P",
    "gn:feature_code":"PPL",
    "gn:name":"Aslum",
    "gn:population":0,
    "gn:timezone":"Asia/Manila",
    "iso:country":"PH",
    "name:und_x_variant":[
        "Aslom",
        "Aslum"
    ],
    "wof:name":"Aslum",
    "wof:placetype":"locality"
},
  "geometry": {"coordinates":[122.48333,11.81667],"type":"Point"}
}