{
  "type": "Feature",
  "properties": {
    "gn:admin1_code":"02",
    "gn:admin2_code":"48",
    "gn:admin3_code":"25002000.0",
    "gn:asciiname":"Tolitul",
    "gn:country_code":"PH",
    "gn:dem":623,
    "gn:feature_class":"P",
    "gn:feature_code":"PPL",
    "gn:name":"Tolitul",
    "gn:population":0,
    "gn:timezone":"Asia/Manila",
    "iso:country":"PH",
    "name:fil_x_preferred":[
        "Tolitul"
    ],
    "wof:name":"Tolitul",
    "wof:placetype":"locality"
},
  "geometry": {"coordinates":[120.95,16.28333],"type":"Point"}
}