{
  "type": "Feature",
  "properties": {
    "gn:admin1_code":"06",
    "gn:admin2_code":"06",
    "gn:admin3_code":"60614000.0",
    "gn:asciiname":"Danao Igas",
    "gn:country_code":"PH",
    "gn:dem":64,
    "gn:feature_class":"P",
    "gn:feature_code":"PPL",
    "gn:name":"Danao Igas",
    "gn:population":0,
    "gn:timezone":"Asia/Manila",
    "iso:country":"PH",
    "name:fil_x_preferred":[
        "Danao Igas"
    ],
    "wof:name":"Danao Igas",
    "wof:placetype":"locality"
},
  "geometry": {"coordinates":[122.09350000000001,10.8569],"type":"Point"}
}