{
  "type": "Feature",
  "properties": {
    "gn:country":"PH",
    "gn:fcode":"ADM3",
    "gn:population":57782,
    "iso:country":"PH",
    "name:fil_x_preferred":[
        "Bansalan"
    ],
    "qs_pg:aaroncc":"PH",
    "qs_pg:gn_country":"PH",
    "qs_pg:gn_fcode":"ADM3",
    "qs_pg:gn_pop":57782,
    "qs_pg:name":"Bansalan",
    "qs_pg:photos_9r":0,
    "qs_pg:photos_sr":0,
    "qs_pg:pop_sr":8,
    "qs_pg:qs_pg_placetype":"localadmin",
    "wof:name":"Bansalan",
    "wof:placetype":"localadmin",
    "wof:population":57782
},
  "geometry": {"coordinates":[125.21666999999999,6.81667],"type":"Point"}
}