{
  "type": "Feature",
  "properties": {
    "gn:admin1_code":"07",
    "gn:admin2_code":"46",
    "gn:admin3_code":"74607000.0",
    "gn:asciiname":"Tamlang",
    "gn:country_code":"PH",
    "gn:dem":267,
    "gn:feature_class":"P",
    "gn:feature_code":"PPL",
    "gn:name":"Tamlang",
    "gn:population":0,
    "gn:timezone":"Asia/Manila",
    "iso:country":"PH",
    "name:fil_x_preferred":[
        "Tamlang"
    ],
    "wof:name":"Tamlang",
    "wof:placetype":"locality"
},
  "geometry": {"coordinates":[123.1086,9.7673],"type":"Point"}
}