{
  "type": "Feature",
  "properties": {
    "gn:admin1_code":"14",
    "gn:admin2_code":"22",
    "gn:admin3_code":"150711000.0",
    "gn:asciiname":"Amaloy",
    "gn:country_code":"PH",
    "gn:dem":19,
    "gn:feature_class":"P",
    "gn:feature_code":"PPL",
    "gn:name":"Amaloy",
    "gn:population":0,
    "gn:timezone":"Asia/Manila",
    "iso:country":"PH",
    "name:und_x_variant":[
        "Amoyloi",
        "Amaloy"
    ],
    "wof:name":"Amaloy",
    "wof:placetype":"locality"
},
  "geometry": {"coordinates":[122.12333,6.44139],"type":"Point"}
}