{
  "type": "Feature",
  "properties": {
    "gn:admin1_code":"06",
    "gn:admin2_code":"18",
    "gn:admin3_code":"61902000.0",
    "gn:asciiname":"Cabugcabug",
    "gn:country_code":"PH",
    "gn:dem":17,
    "gn:feature_class":"P",
    "gn:feature_code":"PPL",
    "gn:name":"Cabugcabug",
    "gn:population":0,
    "gn:timezone":"Asia/Manila",
    "iso:country":"PH",
    "name:fil_x_preferred":[
        "Cabugcabug"
    ],
    "name:und_x_variant":[
        "Cabuq cabug"
    ],
    "wof:name":"Cabugcabug",
    "wof:placetype":"locality"
},
  "geometry": {"coordinates":[122.7531,11.3477],"type":"Point"}
}