{
  "type": "Feature",
  "properties": {
    "gn:admin1_code":"05",
    "gn:admin2_code":"16",
    "gn:admin3_code":"51711000.0",
    "gn:asciiname":"Haponan",
    "gn:country_code":"PH",
    "gn:dem":2,
    "gn:feature_class":"P",
    "gn:feature_code":"PPL",
    "gn:name":"Haponan",
    "gn:population":0,
    "gn:timezone":"Asia/Manila",
    "iso:country":"PH",
    "name:fil_x_preferred":[
        "Haponan"
    ],
    "wof:name":"Haponan",
    "wof:placetype":"locality"
},
  "geometry": {"coordinates":[123.8476,13.8382],"type":"Point"}
}