{
  "type": "Feature",
  "properties": {
    "gn:admin1_code":"08",
    "gn:admin2_code":"H9",
    "gn:admin3_code":"87805000.0",
    "gn:asciiname":"Bohol",
    "gn:cc2":"PH",
    "gn:country_code":"PH",
    "gn:dem":6,
    "gn:feature_class":"P",
    "gn:feature_code":"PPL",
    "gn:name":"Bohol",
    "gn:population":0,
    "gn:timezone":"Asia/Manila",
    "iso:country":"PH",
    "name:ace_x_preferred":[
        "Propinsi Bohol"
    ],
    "name:ara_x_preferred":[
        "\u0628\u0648\u0647\u0648\u0644"
    ],
    "name:azb_x_preferred":[
        "\u0628\u0647\u0644"
    ],
    "name:aze_x_preferred":[
        "Bohol"
    ],
    "name:bcl_x_preferred":[
        "Bohol"
    ],
    "name:cat_x_preferred":[
        "Bohol"
    ],
    "name:ceb_x_preferred":[
        "Bohol"
    ],
    "name:dan_x_preferred":[
        "Bohol"
    ],
    "name:deu_x_preferred":[
        "Bohol"
    ],
    "name:epo_x_preferred":[
        "Boholo"
    ],
    "name:est_x_preferred":[
        "Bohol"
    ],
    "name:eus_x_preferred":[
        "Bohol"
    ],
    "name:fas_x_preferred":[
        "\u0628\u0647\u0644"
    ],
    "name:fin_x_preferred":[
        "Bohol"
    ],
    "name:fra_x_preferred":[
        "Bohol"
    ],
    "name:glg_x_preferred":[
        "Bohol"
    ],
    "name:hin_x_preferred":[
        "\u092c\u094b\u0939\u094b\u0932"
    ],
    "name:hun_x_preferred":[
        "Bohol"
    ],
    "name:ilo_x_preferred":[
        "Bohol"
    ],
    "name:ind_x_preferred":[
        "Bohol"
    ],
    "name:jav_x_preferred":[
        "Bohol"
    ],
    "name:jpn_x_preferred":[
        "\u30dc\u30db\u30fc\u30eb\u5dde"
    ],
    "name:kor_x_preferred":[
        "\ubcf4\ud640\uc8fc"
    ],
    "name:lat_x_preferred":[
        "Bohol"
    ],
    "name:lit_x_preferred":[
        "Boholis"
    ],
    "name:mal_x_preferred":[
        "\u0d2c\u0d4a\u0d39\u0d4b\u0d7e"
    ],
    "name:mkd_x_preferred":[
        "\u0411\u043e\u0445\u043e\u043b"
    ],
    "name:mrj_x_preferred":[
        "\u0411\u043e\u0445\u043e\u043b\u044c"
    ],
    "name:nld_x_preferred":[
        "Bohol"
    ],
    "name:nor_x_preferred":[
        "Bohol"
    ],
    "name:pag_x_preferred":[
        "Bohol"
    ],
    "name:pam_x_preferred":[
        "Bohol"
    ],
    "name:pol_x_preferred":[
        "Bohol"
    ],
    "name:por_x_preferred":[
        "Bohol"
    ],
    "name:rus_x_preferred":[
        "\u0411\u043e\u0445\u043e\u043b\u044c"
    ],
    "name:sco_x_preferred":[
        "Bohol"
    ],
    "name:spa_x_preferred":[
        "Bohol"
    ],
    "name:srp_x_preferred":[
        "\u0411\u043e\u0445\u043e\u043b"
    ],
    "name:swe_x_preferred":[
        "Bohol"
    ],
    "name:tam_x_preferred":[
        "\u0baa\u0bcb\u0b95\u0bca\u0bb2\u0bcd"
    ],
    "name:tgl_x_preferred":[
        "Bohol"
    ],
    "name:tha_x_preferred":[
        "\u0e08\u0e31\u0e07\u0e2b\u0e27\u0e31\u0e14\u0e42\u0e1a\u0e42\u0e2e\u0e25"
    ],
    "name:tur_x_preferred":[
        "Bohol"
    ],
    "name:ukr_x_preferred":[
        "\u0411\u043e\u0445\u043e\u043b\u044c"
    ],
    "name:und_x_variant":[
        "Bool",
        "Bohol"
    ],
    "name:urd_x_preferred":[
        "\u0628\u0648\u06c1\u0648\u0644"
    ],
    "name:vie_x_preferred":[
        "Bohol"
    ],
    "name:war_x_preferred":[
        "Bohol"
    ],
    "name:zho_x_preferred":[
        "\u4fdd\u548c\u7701"
    ],
    "wof:name":"Bohol",
    "wof:placetype":"locality"
},
  "geometry": {"coordinates":[124.51667,11.68028],"type":"Point"}
}