{
  "type": "Feature",
  "properties": {
    "gn:admin1_code":"08",
    "gn:admin2_code":"H9",
    "gn:admin3_code":"87805000.0",
    "gn:asciiname":"Bohol",
    "gn:cc2":"PH",
    "gn:country_code":"PH",
    "gn:dem":6,
    "gn:feature_class":"P",
    "gn:feature_code":"PPL",
    "gn:name":"Bohol",
    "gn:population":0,
    "gn:timezone":"Asia/Manila",
    "iso:country":"PH",
    "name:rus_x_preferred":[
        "\u0411\u043e\u0445\u043e\u043b\u044c"
    ],
    "name:und_x_variant":[
        "Bool",
        "Bohol"
    ],
    "wof:name":"Bohol",
    "wof:placetype":"locality"
},
  "geometry": {"coordinates":[124.51667,11.68028],"type":"Point"}
}