{
  "type": "Feature",
  "properties": {
    "gn:admin1_code":"12",
    "gn:admin2_code":"57",
    "gn:admin3_code":"124705000.0",
    "gn:asciiname":"Muntay",
    "gn:country_code":"PH",
    "gn:dem":38,
    "gn:feature_class":"P",
    "gn:feature_code":"PPL",
    "gn:name":"Muntay",
    "gn:population":0,
    "gn:timezone":"Asia/Manila",
    "iso:country":"PH",
    "name:fil_x_preferred":[
        "Muntay"
    ],
    "wof:name":"Muntay",
    "wof:placetype":"locality"
},
  "geometry": {"coordinates":[124.55138999999998,7.26278],"type":"Point"}
}