{
  "type": "Feature",
  "properties": {
    "gn:admin1_code":"07",
    "gn:admin2_code":"11",
    "gn:admin3_code":"71224000.0",
    "gn:asciiname":"Cambohat",
    "gn:country_code":"PH",
    "gn:dem":6,
    "gn:feature_class":"P",
    "gn:feature_code":"PPL",
    "gn:name":"Cambohat",
    "gn:population":0,
    "gn:timezone":"Asia/Manila",
    "iso:country":"PH",
    "name:fil_x_preferred":[
        "Cambohat"
    ],
    "name:und_x_variant":[
        "Cambuhat"
    ],
    "wof:name":"Cambohat",
    "wof:placetype":"locality"
},
  "geometry": {"coordinates":[124.0723,10.0513],"type":"Point"}
}