{
  "type": "Feature",
  "properties": {
    "gn:admin1_code":"11",
    "gn:admin2_code":"I7",
    "gn:admin3_code":"112317000.0",
    "gn:asciiname":"Santo Nino",
    "gn:country_code":"PH",
    "gn:dem":94,
    "gn:feature_class":"P",
    "gn:feature_code":"PPL",
    "gn:name":"Santo Nino",
    "gn:population":0,
    "gn:timezone":"Asia/Manila",
    "iso:country":"PH",
    "name:fil_x_preferred":[
        "Santo Nino"
    ],
    "wof:name":"Santo Nino",
    "wof:placetype":"locality"
},
  "geometry": {"coordinates":[125.77630000000001,6.9278],"type":"Point"}
}