{
  "type": "Feature",
  "properties": {
    "gn:admin1_code":"02",
    "gn:admin2_code":"14",
    "gn:admin3_code":"21505000.0",
    "gn:asciiname":"Yrao",
    "gn:country_code":"PH",
    "gn:dem":3,
    "gn:feature_class":"P",
    "gn:feature_code":"PPL",
    "gn:name":"Yrao",
    "gn:population":0,
    "gn:timezone":"Asia/Manila",
    "iso:country":"PH",
    "name:fil_x_preferred":[
        "Yrao"
    ],
    "wof:name":"Yrao",
    "wof:placetype":"locality"
},
  "geometry": {"coordinates":[121.6067,18.359],"type":"Point"}
}