{
  "type": "Feature",
  "properties": {
    "gn:admin1_code":"15",
    "gn:admin2_code":"44",
    "gn:admin3_code":"144403000.0",
    "gn:asciiname":"Tamboan",
    "gn:country_code":"PH",
    "gn:dem":861,
    "gn:feature_class":"P",
    "gn:feature_code":"PPL",
    "gn:name":"Tamboan",
    "gn:population":0,
    "gn:timezone":"Asia/Manila",
    "iso:country":"PH",
    "name:fil_x_preferred":[
        "Tamboan"
    ],
    "wof:name":"Tamboan",
    "wof:placetype":"locality"
},
  "geometry": {"coordinates":[120.8036,17.1103],"type":"Point"}
}