{
  "type": "Feature",
  "properties": {
    "gn:admin1_code":"40",
    "gn:admin2_code":"H2",
    "gn:admin3_code":"45634000.0",
    "gn:asciiname":"Quezon",
    "gn:country_code":"PH",
    "gn:dem":16,
    "gn:feature_class":"P",
    "gn:feature_code":"PPL",
    "gn:name":"Quezon",
    "gn:population":0,
    "gn:timezone":"Asia/Manila",
    "iso:country":"PH",
    "name:fil_x_preferred":[
        "Quezon"
    ],
    "wof:name":"Quezon",
    "wof:placetype":"locality"
},
  "geometry": {"coordinates":[122.08110000000001,13.8409],"type":"Point"}
}