{
  "type": "Feature",
  "properties": {
    "gn:admin1_code":"01",
    "gn:admin2_code":"28",
    "gn:admin3_code":"12806000.0",
    "gn:asciiname":"Sukit",
    "gn:country_code":"PH",
    "gn:dem":413,
    "gn:feature_class":"P",
    "gn:feature_code":"PPL",
    "gn:name":"Sukit",
    "gn:population":0,
    "gn:timezone":"Asia/Manila",
    "iso:country":"PH",
    "name:fil_x_preferred":[
        "Sukit"
    ],
    "wof:name":"Sukit",
    "wof:placetype":"locality"
},
  "geometry": {"coordinates":[120.6615,18.4244],"type":"Point"}
}