{
  "type": "Feature",
  "properties": {
    "gn:admin1_code":"40",
    "gn:admin2_code":"09",
    "gn:admin3_code":"41026000.0",
    "gn:asciiname":"San Mariano",
    "gn:country_code":"PH",
    "gn:dem":193,
    "gn:feature_class":"P",
    "gn:feature_code":"PPL",
    "gn:name":"San Mariano",
    "gn:population":0,
    "gn:timezone":"Asia/Manila",
    "iso:country":"PH",
    "name:fil_x_preferred":[
        "San Mariano"
    ],
    "wof:name":"San Mariano",
    "wof:placetype":"locality"
},
  "geometry": {"coordinates":[121.0474,13.8482],"type":"Point"}
}