{
  "type": "Feature",
  "properties": {
    "gn:admin1_code":"02",
    "gn:admin2_code":"31",
    "gn:admin3_code":"23112000.0",
    "gn:asciiname":"Castillo",
    "gn:country_code":"PH",
    "gn:dem":70,
    "gn:feature_class":"P",
    "gn:feature_code":"PPL",
    "gn:name":"Castillo",
    "gn:population":0,
    "gn:timezone":"Asia/Manila",
    "iso:country":"PH",
    "wof:name":"Castillo",
    "wof:placetype":"locality"
},
  "geometry": {"coordinates":[121.69347,16.7396],"type":"Point"}
}