{
  "type": "Feature",
  "properties": {
    "gn:admin1_code":"02",
    "gn:admin2_code":"31",
    "gn:admin3_code":"23112000.0",
    "gn:asciiname":"Castillo",
    "gn:country_code":"PH",
    "gn:dem":70,
    "gn:feature_class":"P",
    "gn:feature_code":"PPL",
    "gn:name":"Castillo",
    "gn:population":0,
    "gn:timezone":"Asia/Manila",
    "iso:country":"PH",
    "name:ast_x_preferred":[
        "Castiellu"
    ],
    "name:cat_x_preferred":[
        "Castillo"
    ],
    "name:ceb_x_preferred":[
        "Castillo"
    ],
    "name:ces_x_preferred":[
        "Castillo"
    ],
    "name:deu_x_preferred":[
        "Castillo"
    ],
    "name:fin_x_preferred":[
        "Castillo"
    ],
    "name:fra_x_preferred":[
        "Castillo"
    ],
    "name:glg_x_preferred":[
        "Castillo"
    ],
    "name:ita_x_preferred":[
        "Castillo"
    ],
    "name:jpn_x_preferred":[
        "\u30ab\u30b9\u30c6\u30a3\u30ea\u30e7"
    ],
    "name:nld_x_preferred":[
        "Castillo"
    ],
    "name:rus_x_preferred":[
        "\u041a\u0430\u0441\u0442\u0438\u043b\u044c\u043e"
    ],
    "name:sco_x_preferred":[
        "Castillo"
    ],
    "name:spa_x_preferred":[
        "Castillo"
    ],
    "name:swe_x_preferred":[
        "Castillo"
    ],
    "name:ukr_x_preferred":[
        "\u041a\u0430\u0441\u0442\u0456\u043b\u044c\u0439\u043e"
    ],
    "name:zho_x_preferred":[
        "\u5361\u65af\u8482\u7565"
    ],
    "wof:name":"Castillo",
    "wof:placetype":"locality"
},
  "geometry": {"coordinates":[121.69347,16.7396],"type":"Point"}
}