{
  "type": "Feature",
  "properties": {
    "gn:admin1_code":"02",
    "gn:admin2_code":"08",
    "gn:admin3_code":"20903000.0",
    "gn:asciiname":"Panatayan",
    "gn:country_code":"PH",
    "gn:dem":127,
    "gn:feature_class":"P",
    "gn:feature_code":"PPL",
    "gn:name":"Panatayan",
    "gn:population":0,
    "gn:timezone":"Asia/Manila",
    "iso:country":"PH",
    "name:fil_x_preferred":[
        "Panatayan"
    ],
    "wof:name":"Panatayan",
    "wof:placetype":"locality"
},
  "geometry": {"coordinates":[121.93597,20.40625],"type":"Point"}
}