{
  "type": "Feature",
  "properties": {
    "gn:admin1_code":"06",
    "gn:admin2_code":"30",
    "gn:admin3_code":"63040000.0",
    "gn:asciiname":"Talos",
    "gn:country_code":"PH",
    "gn:dem":31,
    "gn:feature_class":"P",
    "gn:feature_code":"PPL",
    "gn:name":"Talos",
    "gn:population":0,
    "gn:timezone":"Asia/Manila",
    "iso:country":"PH",
    "name:als_x_preferred":[
        "Talos"
    ],
    "name:ara_x_preferred":[
        "\u062a\u0627\u0644\u0648\u0633"
    ],
    "name:bul_x_preferred":[
        "\u0422\u0430\u043b\u043e\u0441"
    ],
    "name:cat_x_preferred":[
        "Talos"
    ],
    "name:deu_x_preferred":[
        "Talos"
    ],
    "name:ell_x_preferred":[
        "\u03a4\u03ac\u03bb\u03c9\u03c2"
    ],
    "name:est_x_preferred":[
        "Talos"
    ],
    "name:fil_x_preferred":[
        "Talos"
    ],
    "name:fin_x_preferred":[
        "Talos"
    ],
    "name:fra_x_preferred":[
        "Talos"
    ],
    "name:hrv_x_preferred":[
        "Tal"
    ],
    "name:ind_x_preferred":[
        "Talos"
    ],
    "name:ita_x_preferred":[
        "Talo"
    ],
    "name:jpn_x_preferred":[
        "\u30bf\u30ed\u30fc\u30b9"
    ],
    "name:lit_x_preferred":[
        "Talas"
    ],
    "name:nld_x_preferred":[
        "Talos"
    ],
    "name:nor_x_preferred":[
        "Talos"
    ],
    "name:pol_x_preferred":[
        "Talos"
    ],
    "name:por_x_preferred":[
        "Talos"
    ],
    "name:rus_x_preferred":[
        "\u0422\u0430\u043b\u043e\u0441"
    ],
    "name:slk_x_preferred":[
        "Tal\u00f3s"
    ],
    "name:spa_x_preferred":[
        "Talos"
    ],
    "name:srp_x_preferred":[
        "\u0422\u0430\u043b"
    ],
    "name:swe_x_preferred":[
        "Talos"
    ],
    "name:tha_x_preferred":[
        "\u0e17\u0e32\u0e25\u0e2d\u0e2a"
    ],
    "name:tur_x_preferred":[
        "Talos"
    ],
    "name:ukr_x_preferred":[
        "\u0422\u0430\u043b"
    ],
    "name:zho_x_preferred":[
        "\u5854\u7f57\u65af"
    ],
    "wof:name":"Talos",
    "wof:placetype":"locality"
},
  "geometry": {"coordinates":[122.0467,10.4883],"type":"Point"}
}