{
  "type": "Feature",
  "properties": {
    "gn:admin1_code":"06",
    "gn:admin2_code":"30",
    "gn:admin3_code":"63040000.0",
    "gn:asciiname":"Talos",
    "gn:country_code":"PH",
    "gn:dem":31,
    "gn:feature_class":"P",
    "gn:feature_code":"PPL",
    "gn:name":"Talos",
    "gn:population":0,
    "gn:timezone":"Asia/Manila",
    "iso:country":"PH",
    "name:fil_x_preferred":[
        "Talos"
    ],
    "wof:name":"Talos",
    "wof:placetype":"locality"
},
  "geometry": {"coordinates":[122.0467,10.4883],"type":"Point"}
}