{
  "type": "Feature",
  "properties": {
    "gn:admin1_code":"12",
    "gn:admin2_code":"71",
    "gn:admin3_code":"126508000.0",
    "gn:asciiname":"Tomiao",
    "gn:country_code":"PH",
    "gn:dem":31,
    "gn:feature_class":"P",
    "gn:feature_code":"PPLL",
    "gn:name":"Tomiao",
    "gn:population":0,
    "gn:timezone":"Asia/Manila",
    "iso:country":"PH",
    "name:fil_x_preferred":[
        "Tomiao"
    ],
    "wof:name":"Tomiao",
    "wof:placetype":"locality"
},
  "geometry": {"coordinates":[124.67139,6.75751],"type":"Point"}
}