{
  "type": "Feature",
  "properties": {
    "gn:country":"PH",
    "gn:fcode":"PPL",
    "gn:pop":3866,
    "iso:country":"PH",
    "name:fil_x_preferred":[
        "Tubigagmanoc"
    ],
    "name:unk_x_variant":[
        "Tibugagmanok"
    ],
    "qs:name":"Tubigagmanoc",
    "qs:photos_9r":0,
    "qs:photos_sr":0,
    "qs:pop_sr":"4",
    "wof:name":"Tubigagmanoc",
    "wof:placetype":"locality",
    "wof:population":3866
},
  "geometry": {"coordinates":[123.74890000000001,10.6282],"type":"Point"}
}