{
  "type": "Feature",
  "properties": {
    "gn:country":"PH",
    "gn:fcode":"PPL",
    "gn:pop":3481,
    "iso:country":"PH",
    "name:fil_x_preferred":[
        "Aurora"
    ],
    "qs:name":"Aurora",
    "qs:photos_9r":0,
    "qs:photos_sr":0,
    "qs:pop_sr":"4",
    "wd:wordcount":8987,
    "wof:name":"Aurora",
    "wof:placetype":"locality",
    "wof:population":3481
},
  "geometry": {"coordinates":[121.1203,13.2322],"type":"Point"}
}