{
  "type": "Feature",
  "properties": {
    "gn:admin1_code":"06",
    "gn:admin2_code":"30",
    "gn:admin3_code":"63021000.0",
    "gn:asciiname":"Bontoc",
    "gn:country_code":"PH",
    "gn:dem":83,
    "gn:feature_class":"P",
    "gn:feature_code":"PPL",
    "gn:name":"Bontoc",
    "gn:population":0,
    "gn:timezone":"Asia/Manila",
    "iso:country":"PH",
    "name:fil_x_preferred":[
        "Bontoc"
    ],
    "name:und_x_variant":[
        "Bondoc"
    ],
    "wof:name":"Bontoc",
    "wof:placetype":"locality"
},
  "geometry": {"coordinates":[122.2787,10.72175],"type":"Point"}
}