{
  "type": "Feature",
  "properties": {
    "gn:admin1_code":"06",
    "gn:admin2_code":"30",
    "gn:admin3_code":"63007000.0",
    "gn:asciiname":"Cruz",
    "gn:country_code":"PH",
    "gn:dem":13,
    "gn:feature_class":"P",
    "gn:feature_code":"PPL",
    "gn:name":"Cruz",
    "gn:population":0,
    "gn:timezone":"Asia/Manila",
    "iso:country":"PH",
    "name:ces_x_preferred":[
        "Cruz"
    ],
    "name:deu_x_preferred":[
        "Cruz"
    ],
    "name:fil_x_preferred":[
        "Cruz"
    ],
    "wof:name":"Cruz",
    "wof:placetype":"locality"
},
  "geometry": {"coordinates":[122.70471999999999,10.88],"type":"Point"}
}