{
  "type": "Feature",
  "properties": {
    "gn:admin1_code":"12",
    "gn:admin2_code":"57",
    "gn:admin3_code":"124712000.0",
    "gn:asciiname":"Tambal",
    "gn:country_code":"PH",
    "gn:dem":8,
    "gn:feature_class":"P",
    "gn:feature_code":"PPL",
    "gn:name":"Tambal",
    "gn:population":0,
    "gn:timezone":"Asia/Manila",
    "iso:country":"PH",
    "name:fil_x_preferred":[
        "Tambal"
    ],
    "wof:name":"Tambal",
    "wof:placetype":"locality"
},
  "geometry": {"coordinates":[124.58194,7.02861],"type":"Point"}
}