{
  "type": "Feature",
  "properties": {
    "gn:admin1_code":"02",
    "gn:admin2_code":"48",
    "gn:admin3_code":"25004000.0",
    "gn:asciiname":"Mauan",
    "gn:country_code":"PH",
    "gn:dem":381,
    "gn:feature_class":"P",
    "gn:feature_code":"PPL",
    "gn:name":"Mauan",
    "gn:population":0,
    "gn:timezone":"Asia/Manila",
    "iso:country":"PH",
    "name:fil_x_preferred":[
        "Mauan"
    ],
    "wof:name":"Mauan",
    "wof:placetype":"locality"
},
  "geometry": {"coordinates":[121.0547,16.3556],"type":"Point"}
}