{
  "type": "Feature",
  "properties": {
    "gn:admin1_code":"06",
    "gn:admin2_code":"30",
    "gn:admin3_code":"63017000.0",
    "gn:asciiname":"Madaron",
    "gn:country_code":"PH",
    "gn:dem":89,
    "gn:feature_class":"P",
    "gn:feature_code":"PPL",
    "gn:name":"Madaron",
    "gn:population":0,
    "gn:timezone":"Asia/Manila",
    "iso:country":"PH",
    "name:fil_x_preferred":[
        "Madaron"
    ],
    "wof:name":"Madaron",
    "wof:placetype":"locality"
},
  "geometry": {"coordinates":[122.56471999999999,11.05583],"type":"Point"}
}