{
  "type": "Feature",
  "properties": {
    "gn:admin1_code":"07",
    "gn:admin2_code":"11",
    "gn:admin3_code":"71224000.0",
    "gn:asciiname":"Santo Nino",
    "gn:country_code":"PH",
    "gn:dem":2,
    "gn:feature_class":"P",
    "gn:feature_code":"PPL",
    "gn:name":"Santo Ni\u00f1o",
    "gn:population":0,
    "gn:timezone":"Asia/Manila",
    "iso:country":"PH",
    "name:fil_x_preferred":[
        "Santo Ni\u00f1o"
    ],
    "wof:name":"Santo Nino",
    "wof:placetype":"locality"
},
  "geometry": {"coordinates":[124.06896999999999,10.06867],"type":"Point"}
}