{
  "type": "Feature",
  "properties": {
    "gn:admin1_code":"03",
    "gn:admin2_code":"47",
    "gn:admin3_code":"34918000.0",
    "gn:asciiname":"Maeling",
    "gn:country_code":"PH",
    "gn:dem":25,
    "gn:feature_class":"P",
    "gn:feature_code":"PPL",
    "gn:name":"Maeling",
    "gn:population":0,
    "gn:timezone":"Asia/Manila",
    "iso:country":"PH",
    "name:fil_x_preferred":[
        "Maeling"
    ],
    "wof:name":"Maeling",
    "wof:placetype":"locality"
},
  "geometry": {"coordinates":[120.6567,15.6869],"type":"Point"}
}