{
  "type": "Feature",
  "properties": {
    "gn:admin1_code":"40",
    "gn:admin2_code":"53",
    "gn:admin3_code":"45809000.0",
    "gn:asciiname":"Maybancal",
    "gn:country_code":"PH",
    "gn:dem":33,
    "gn:feature_class":"P",
    "gn:feature_code":"PPL",
    "gn:name":"Maybancal",
    "gn:population":0,
    "gn:timezone":"Asia/Manila",
    "iso:country":"PH",
    "name:fil_x_preferred":[
        "Maybangcal"
    ],
    "name:fil_x_variant":[
        "Maybancal",
        "Maybangkal"
    ],
    "name:und_x_variant":[
        "Maybangkal"
    ],
    "wof:name":"Maybancal",
    "wof:placetype":"locality"
},
  "geometry": {"coordinates":[121.2299,14.5249],"type":"Point"}
}