{
  "type": "Feature",
  "properties": {
    "gn:admin1_code":"06",
    "gn:admin2_code":"30",
    "gn:admin3_code":"63025000.0",
    "gn:asciiname":"Bayaco",
    "gn:country_code":"PH",
    "gn:dem":124,
    "gn:feature_class":"P",
    "gn:feature_code":"PPL",
    "gn:name":"Bayaco",
    "gn:population":0,
    "gn:timezone":"Asia/Manila",
    "iso:country":"PH",
    "name:fil_x_preferred":[
        "Bayaco"
    ],
    "name:und_x_variant":[
        "Bayuco",
        "Bayoco"
    ],
    "wof:name":"Bayaco",
    "wof:placetype":"locality"
},
  "geometry": {"coordinates":[122.45699999999999,11.08633],"type":"Point"}
}