{
  "type": "Feature",
  "properties": {
    "gn:admin1_code":"14",
    "gn:admin2_code":"60",
    "gn:admin3_code":"156610000.0",
    "gn:asciiname":"Tambulian",
    "gn:country_code":"PH",
    "gn:dem":0,
    "gn:feature_class":"P",
    "gn:feature_code":"PPL",
    "gn:name":"Tambulian",
    "gn:population":0,
    "gn:timezone":"Asia/Manila",
    "iso:country":"PH",
    "name:eng_x_preferred":[
        "Tambulian"
    ],
    "wof:name":"Tambulian",
    "wof:placetype":"locality"
},
  "geometry": {"coordinates":[121.21299999999999,5.8711],"type":"Point"}
}