{
  "type": "Feature",
  "properties": {
    "gn:admin1_code":"15",
    "gn:admin2_code":"44",
    "gn:admin3_code":"144402000.0",
    "gn:asciiname":"Balintaugan",
    "gn:country_code":"PH",
    "gn:dem":1251,
    "gn:feature_class":"P",
    "gn:feature_code":"PPL",
    "gn:name":"Balintaugan",
    "gn:population":0,
    "gn:timezone":"Asia/Manila",
    "iso:country":"PH",
    "name:fil_x_preferred":[
        "Balintaugan"
    ],
    "wof:name":"Balintaugan",
    "wof:placetype":"locality"
},
  "geometry": {"coordinates":[120.86669999999999,16.9833],"type":"Point"}
}