{
  "type": "Feature",
  "properties": {
    "gn:admin1_code":"05",
    "gn:admin2_code":"39",
    "gn:admin3_code":"54107000.0",
    "gn:asciiname":"Enermetahan",
    "gn:country_code":"PH",
    "gn:dem":57,
    "gn:feature_class":"P",
    "gn:feature_code":"PPL",
    "gn:name":"Enermetahan",
    "gn:population":0,
    "gn:timezone":"Asia/Manila",
    "iso:country":"PH",
    "name:fil_x_preferred":[
        "Enermetahan"
    ],
    "name:und_x_variant":[
        "Ermitahan"
    ],
    "wof:name":"Enermetahan",
    "wof:placetype":"locality"
},
  "geometry": {"coordinates":[123.29640000000001,12.8015],"type":"Point"}
}