{
  "type": "Feature",
  "properties": {
    "gn:admin1_code":"NCR",
    "gn:admin2_code":"137500000",
    "gn:admin3_code":"137502000.0",
    "gn:asciiname":"Bayanbayanan",
    "gn:country_code":"PH",
    "gn:dem":5,
    "gn:feature_class":"P",
    "gn:feature_code":"PPL",
    "gn:name":"Bayanbayanan",
    "gn:population":0,
    "gn:timezone":"Asia/Manila",
    "iso:country":"PH",
    "wof:name":"Bayanbayanan",
    "wof:placetype":"locality"
},
  "geometry": {"coordinates":[120.9425,14.67861],"type":"Point"}
}