{
  "type": "Feature",
  "properties": {
    "gn:country":"PH",
    "gn:fcode":"PPL",
    "gn:population":2139,
    "iso:country":"PH",
    "name:fil_x_preferred":[
        "Abaca"
    ],
    "qs_pg:aaroncc":"PH",
    "qs_pg:gn_country":"PH",
    "qs_pg:gn_fcode":"PPL",
    "qs_pg:gn_pop":2139,
    "qs_pg:name":"Abaca",
    "qs_pg:photos_9r":0,
    "qs_pg:photos_sr":0,
    "qs_pg:pop_sr":4,
    "qs_pg:qs_pg_placetype":"locality",
    "wof:name":"Abaca",
    "wof:placetype":"locality",
    "wof:population":2139
},
  "geometry": {"coordinates":[122.71559999999999,11.1342],"type":"Point"}
}