{
  "type": "Feature",
  "properties": {
    "gn:country":"PH",
    "gn:fcode":"PPL",
    "gn:pop":2814,
    "iso:country":"PH",
    "name:fil_x_preferred":[
        "Matiao"
    ],
    "qs:name":"Matiao",
    "qs:photos_9r":0,
    "qs:photos_sr":0,
    "qs:pop_sr":"4",
    "wof:name":"Matiao",
    "wof:placetype":"locality",
    "wof:population":2814
},
  "geometry": {"coordinates":[125.9362,7.0828],"type":"Point"}
}