{
  "type": "Feature",
  "properties": {
    "gn:admin1_code":"01",
    "gn:admin2_code":"36",
    "gn:admin3_code":"13302000.0",
    "gn:asciiname":"Pangaoaoangan East",
    "gn:country_code":"PH",
    "gn:dem":38,
    "gn:feature_class":"P",
    "gn:feature_code":"PPL",
    "gn:name":"Pangaoaoangan East",
    "gn:population":0,
    "gn:timezone":"Asia/Manila",
    "iso:country":"PH",
    "name:eng_x_preferred":[
        "Pangaoaoangan East"
    ],
    "wof:name":"Pangaoaoangan East",
    "wof:placetype":"locality"
},
  "geometry": {"coordinates":[120.3899,16.3701],"type":"Point"}
}