{
  "type": "Feature",
  "properties": {
    "gn:admin1_code":"15",
    "gn:admin2_code":"27",
    "gn:admin3_code":"142703000.0",
    "gn:asciiname":"Pakawol",
    "gn:country_code":"PH",
    "gn:dem":1014,
    "gn:feature_class":"P",
    "gn:feature_code":"PPL",
    "gn:name":"Pakawol",
    "gn:population":0,
    "gn:timezone":"Asia/Manila",
    "iso:country":"PH",
    "name:fil_x_preferred":[
        "Pakawol"
    ],
    "name:fil_x_variant":[
        "Pacawol",
        "Pacawal"
    ],
    "name:und_x_variant":[
        "Pacawal"
    ],
    "wof:name":"Pakawol",
    "wof:placetype":"locality"
},
  "geometry": {"coordinates":[121.03754000000001,16.78557],"type":"Point"}
}