{
  "type": "Feature",
  "properties": {
    "gn:admin1_code":"01",
    "gn:admin2_code":"28",
    "gn:admin3_code":"12804000.0",
    "gn:asciiname":"Manayan",
    "gn:country_code":"PH",
    "gn:dem":13,
    "gn:feature_class":"P",
    "gn:feature_code":"PPL",
    "gn:name":"Manayan",
    "gn:population":0,
    "gn:timezone":"Asia/Manila",
    "iso:country":"PH",
    "name:fil_x_preferred":[
        "Manayan"
    ],
    "wof:name":"Manayan",
    "wof:placetype":"locality"
},
  "geometry": {"coordinates":[120.7445,18.5234],"type":"Point"}
}