{
  "type": "Feature",
  "properties": {
    "gn:gn_country":"PH",
    "gn:gn_fcode":"PPL",
    "gn:gn_pop":2223,
    "gn:population":2223,
    "iso:country":"PH",
    "name:fil_x_preferred":[
        "Angad"
    ],
    "qs_pg:aaroncc":"PH",
    "qs_pg:gn_country":"PH",
    "qs_pg:gn_fcode":"PPL",
    "qs_pg:gn_pop":2223,
    "qs_pg:name":"Angad",
    "qs_pg:photos_9r":0,
    "qs_pg:photos_sr":0,
    "qs_pg:pop_sr":4,
    "qs_pg:qs_pg_placetype":"locality",
    "wof:name":"Angad",
    "wof:placetype":"locality",
    "wof:population":2223
},
  "geometry": {"coordinates":[120.62569999999999,17.5849],"type":"Point"}
}