{
  "type": "Feature",
  "properties": {
    "gn:admin1_code":"11",
    "gn:admin2_code":"I6",
    "gn:admin3_code":"118208000.0",
    "gn:asciiname":"Inugtan",
    "gn:country_code":"PH",
    "gn:dem":203,
    "gn:feature_class":"P",
    "gn:feature_code":"PPL",
    "gn:name":"Inugtan",
    "gn:population":0,
    "gn:timezone":"Asia/Manila",
    "iso:country":"PH",
    "name:fil_x_preferred":[
        "Inugtan"
    ],
    "wof:name":"Inugtan",
    "wof:placetype":"locality"
},
  "geometry": {"coordinates":[125.96666999999999,7.76667],"type":"Point"}
}