{
  "type": "Feature",
  "properties": {
    "iso:country":"PH",
    "name:bcl_x_preferred":[
        "Plaridel"
    ],
    "name:cat_x_preferred":[
        "Plaridel"
    ],
    "name:cbk_zam_x_preferred":[
        "Plaridel"
    ],
    "name:ceb_x_preferred":[
        "Plaridel"
    ],
    "name:ces_x_preferred":[
        "Plaridel"
    ],
    "name:deu_x_preferred":[
        "Plaridel"
    ],
    "name:eng_x_preferred":[
        "Plaridel"
    ],
    "name:fra_x_preferred":[
        "Plaridel"
    ],
    "name:ilo_x_preferred":[
        "Plaridel"
    ],
    "name:ind_x_preferred":[
        "Plaridel"
    ],
    "name:ita_x_preferred":[
        "Plaridel"
    ],
    "name:jpn_x_preferred":[
        "\u30d7\u30e9\u30ea\u30c7\u30eb"
    ],
    "name:nld_x_preferred":[
        "Plaridel"
    ],
    "name:nob_x_preferred":[
        "Plaridel"
    ],
    "name:oci_x_preferred":[
        "Plaridel"
    ],
    "name:pag_x_preferred":[
        "Plaridel"
    ],
    "name:pam_x_preferred":[
        "Plaridel"
    ],
    "name:pol_x_preferred":[
        "Plaridel"
    ],
    "name:spa_x_preferred":[
        "Plaridel"
    ],
    "name:swe_x_preferred":[
        "Plaridel"
    ],
    "name:tgl_x_preferred":[
        "Plaridel"
    ],
    "name:unk_x_variant":[
        "Quingua"
    ],
    "name:urd_x_preferred":[
        "\u067e\u0644\u0627\u0631\u06cc\u062f\u06cc\u0644"
    ],
    "name:vie_x_preferred":[
        "Pandi"
    ],
    "name:war_x_preferred":[
        "Plaridel"
    ],
    "name:zho_x_preferred":[
        "\u666e\u62c9\u5229\u5fb7\u5c14"
    ],
    "qs:gn_country":"PH",
    "qs:gn_fcode":"PPLA3",
    "qs:gn_pop":70781,
    "qs:name":"Plaridel",
    "qs:name_adm0":"Philippines",
    "qs:name_adm1":"Central Luzon",
    "qs:photos":101,
    "qs:photos_1k":20,
    "qs:photos_9k":1,
    "qs:photos_9r":3,
    "qs:photos_all":101,
    "qs:photos_sr":3,
    "qs:placetype":"Town",
    "qs:pop_sr":"8",
    "qs:woe_adm0":23424934,
    "wd:wordcount":1233,
    "wof:name":"Plaridel",
    "wof:placetype":"locality",
    "wof:population":70781
},
  "geometry": {"coordinates":[120.85722,14.88722],"type":"Point"}
}