{
  "type": "Feature",
  "properties": {
    "gn:admin1_code":"05",
    "gn:admin2_code":"05",
    "gn:admin3_code":"50517000.0",
    "gn:asciiname":"Tagas",
    "gn:country_code":"PH",
    "gn:dem":16,
    "gn:feature_class":"P",
    "gn:feature_code":"PPL",
    "gn:name":"Tagas",
    "gn:population":0,
    "gn:timezone":"Asia/Manila",
    "iso:country":"PH",
    "name:fil_x_preferred":[
        "Tagas"
    ],
    "name:und_x_variant":[
        "Tagas Grande"
    ],
    "wof:name":"Tagas",
    "wof:placetype":"locality"
},
  "geometry": {"coordinates":[123.729,13.3488],"type":"Point"}
}