{
  "type": "Feature",
  "properties": {
    "gn:admin1_code":"03",
    "gn:admin2_code":"63",
    "gn:admin3_code":"36916000.0",
    "gn:asciiname":"Libertad",
    "gn:country_code":"PH",
    "gn:dem":39,
    "gn:feature_class":"P",
    "gn:feature_code":"PPL",
    "gn:name":"Libertad",
    "gn:population":0,
    "gn:timezone":"Asia/Manila",
    "iso:country":"PH",
    "name:fil_x_preferred":[
        "Libertad"
    ],
    "wof:name":"Libertad",
    "wof:placetype":"locality"
},
  "geometry": {"coordinates":[120.5823,15.5452],"type":"Point"}
}