{
  "type": "Feature",
  "properties": {
    "gn:country":"PH",
    "gn:fcode":"PPLA3",
    "gn:population":0,
    "iso:country":"PH",
    "name:bcl_x_preferred":[
        "Burgos"
    ],
    "name:cat_x_preferred":[
        "Burgos"
    ],
    "name:ceb_x_preferred":[
        "Burgos"
    ],
    "name:ces_x_preferred":[
        "Burgos"
    ],
    "name:deu_x_preferred":[
        "Burgos"
    ],
    "name:eng_x_preferred":[
        "Burgos"
    ],
    "name:fas_x_preferred":[
        "\u0628\u0648\u0631\u06af\u0648\u0633\u060c \u0627\u06cc\u0644\u0648\u06a9\u0648\u0633 \u0634\u0645\u0627\u0644\u06cc"
    ],
    "name:fas_x_variant":[
        "\u0628\u0648\u0631\u06af\u0648\u0633"
    ],
    "name:fil_x_preferred":[
        "Burgos"
    ],
    "name:fra_x_preferred":[
        "Burgos"
    ],
    "name:glg_x_preferred":[
        "Burgos"
    ],
    "name:ilo_x_preferred":[
        "Burgos"
    ],
    "name:ind_x_preferred":[
        "Burgos"
    ],
    "name:ita_x_preferred":[
        "Burgos"
    ],
    "name:nld_x_preferred":[
        "Burgos"
    ],
    "name:oci_x_preferred":[
        "Burgos"
    ],
    "name:pag_x_preferred":[
        "Burgos"
    ],
    "name:pam_x_preferred":[
        "Burgos"
    ],
    "name:spa_x_preferred":[
        "Burgos"
    ],
    "name:swe_x_preferred":[
        "Burgos"
    ],
    "name:tgl_x_preferred":[
        "Burgos"
    ],
    "name:vie_x_preferred":[
        "Burgos"
    ],
    "name:war_x_preferred":[
        "Burgos"
    ],
    "qs:gn_pop":0,
    "qs:name":"Burgos",
    "qs:name_adm0":"Philippines",
    "qs:name_adm1":"Ilocos Region",
    "qs:photos":204,
    "qs:photos_1k":41,
    "qs:photos_9k":1,
    "qs:photos_9r":4,
    "qs:photos_all":204,
    "qs:photos_sr":4,
    "qs:placetype":"Town",
    "qs:pop_sr":"0",
    "qs:woe_adm0":23424934,
    "wof:name":"Burgos",
    "wof:placetype":"locality",
    "wof:population":0
},
  "geometry": {"coordinates":[120.63330000000001,18.5167],"type":"Point"}
}