{
  "type": "Feature",
  "properties": {
    "gn:admin1_code":"01",
    "gn:admin2_code":"36",
    "gn:admin3_code":"13313000.0",
    "gn:asciiname":"Cataguintingan Norte",
    "gn:country_code":"PH",
    "gn:dem":109,
    "gn:feature_class":"P",
    "gn:feature_code":"PPL",
    "gn:name":"Cataguintingan Norte",
    "gn:population":0,
    "gn:timezone":"Asia/Manila",
    "iso:country":"PH",
    "name:fil_x_preferred":[
        "Cataguintingan Norte"
    ],
    "wof:name":"Cataguintingan Norte",
    "wof:placetype":"locality"
},
  "geometry": {"coordinates":[120.45966,16.22566],"type":"Point"}
}