{
  "type": "Feature",
  "properties": {
    "gn:admin1_code":"07",
    "gn:admin2_code":"11",
    "gn:admin3_code":"71229000.0",
    "gn:asciiname":"Owac",
    "gn:country_code":"PH",
    "gn:dem":393,
    "gn:feature_class":"P",
    "gn:feature_code":"PPL",
    "gn:name":"Owac",
    "gn:population":0,
    "gn:timezone":"Asia/Manila",
    "iso:country":"PH",
    "name:fil_x_preferred":[
        "Owac"
    ],
    "wof:name":"Owac",
    "wof:placetype":"locality"
},
  "geometry": {"coordinates":[124.06667,9.63333],"type":"Point"}
}