{
  "type": "Feature",
  "properties": {
    "gn:admin1_code":"14",
    "gn:admin2_code":"22",
    "gn:admin3_code":"150702000.0",
    "gn:asciiname":"Parangbasak",
    "gn:country_code":"PH",
    "gn:dem":240,
    "gn:feature_class":"P",
    "gn:feature_code":"PPL",
    "gn:name":"Parangbasak",
    "gn:population":0,
    "gn:timezone":"Asia/Manila",
    "iso:country":"PH",
    "name:und_x_variant":[
        "Paranbasac",
        "Parangbasak"
    ],
    "wof:name":"Parangbasak",
    "wof:placetype":"locality"
},
  "geometry": {"coordinates":[122.17389,6.56528],"type":"Point"}
}