{
  "type": "Feature",
  "properties": {
    "gn:admin1_code":"14",
    "gn:admin2_code":"35",
    "gn:admin3_code":"153628000.0",
    "gn:asciiname":"Pango-ay",
    "gn:country_code":"PH",
    "gn:dem":764,
    "gn:feature_class":"P",
    "gn:feature_code":"PPL",
    "gn:name":"Pango-ay",
    "gn:population":0,
    "gn:timezone":"Asia/Manila",
    "iso:country":"PH",
    "name:fil_x_preferred":[
        "Pango-ay"
    ],
    "wof:name":"Pango-ay",
    "wof:placetype":"locality"
},
  "geometry": {"coordinates":[124.18333,7.73333],"type":"Point"}
}