{
  "type": "Feature",
  "properties": {
    "gn:admin1_code":"01",
    "gn:admin2_code":"36",
    "gn:admin3_code":"13305000.0",
    "gn:asciiname":"Nalasin",
    "gn:country_code":"PH",
    "gn:dem":18,
    "gn:feature_class":"P",
    "gn:feature_code":"PPL",
    "gn:name":"Nalasin",
    "gn:population":0,
    "gn:timezone":"Asia/Manila",
    "iso:country":"PH",
    "name:fil_x_preferred":[
        "Nalasin"
    ],
    "wof:name":"Nalasin",
    "wof:placetype":"locality"
},
  "geometry": {"coordinates":[120.40560000000001,16.8126],"type":"Point"}
}