{
  "type": "Feature",
  "properties": {
    "gn:admin1_code":"06",
    "gn:admin2_code":"06",
    "gn:admin3_code":"60616000.0",
    "gn:asciiname":"Mojon",
    "gn:country_code":"PH",
    "gn:dem":12,
    "gn:feature_class":"P",
    "gn:feature_code":"PPL",
    "gn:name":"Mojon",
    "gn:population":0,
    "gn:timezone":"Asia/Manila",
    "iso:country":"PH",
    "name:fil_x_preferred":[
        "Mojon"
    ],
    "wof:name":"Mojon",
    "wof:placetype":"locality"
},
  "geometry": {"coordinates":[121.98333,10.81667],"type":"Point"}
}