{
  "type": "Feature",
  "properties": {
    "gn:admin1_code":"08",
    "gn:admin2_code":"59",
    "gn:admin3_code":"86403000.0",
    "gn:asciiname":"Catublian",
    "gn:country_code":"PH",
    "gn:dem":10,
    "gn:feature_class":"P",
    "gn:feature_code":"PPL",
    "gn:name":"Catublian",
    "gn:population":0,
    "gn:timezone":"Asia/Manila",
    "iso:country":"PH",
    "name:fil_x_preferred":[
        "Catublian"
    ],
    "name:und_x_variant":[
        "Catublian A"
    ],
    "wof:name":"Catublian",
    "wof:placetype":"locality"
},
  "geometry": {"coordinates":[125.1812,10.3835],"type":"Point"}
}