{
  "type": "Feature",
  "properties": {
    "gn:admin1_code":"05",
    "gn:admin2_code":"05",
    "gn:admin3_code":"50502000.0",
    "gn:asciiname":"Palanog",
    "gn:country_code":"PH",
    "gn:dem":148,
    "gn:feature_class":"P",
    "gn:feature_code":"PPL",
    "gn:name":"Palanog",
    "gn:population":0,
    "gn:timezone":"Asia/Manila",
    "iso:country":"PH",
    "name:fil_x_preferred":[
        "Palanog"
    ],
    "wof:name":"Palanog",
    "wof:placetype":"locality"
},
  "geometry": {"coordinates":[123.6153,13.146],"type":"Point"}
}