{
  "type": "Feature",
  "properties": {
    "gn:admin1_code":"12",
    "gn:admin2_code":"57",
    "gn:admin3_code":"124716000.0",
    "gn:asciiname":"Panapilan",
    "gn:country_code":"PH",
    "gn:dem":668,
    "gn:feature_class":"P",
    "gn:feature_code":"PPL",
    "gn:name":"Panapilan",
    "gn:population":0,
    "gn:timezone":"Asia/Manila",
    "iso:country":"PH",
    "name:fil_x_preferred":[
        "Panapilan"
    ],
    "wof:name":"Panapilan",
    "wof:placetype":"locality"
},
  "geometry": {"coordinates":[124.71939999999999,7.58128],"type":"Point"}
}