{
  "type": "Feature",
  "properties": {
    "gn:admin1_code":"05",
    "gn:admin2_code":"58",
    "gn:admin3_code":"56216000.0",
    "gn:asciiname":"Bonga",
    "gn:country_code":"PH",
    "gn:dem":6,
    "gn:feature_class":"P",
    "gn:feature_code":"PPL",
    "gn:name":"Bo\u00f1ga",
    "gn:population":0,
    "gn:timezone":"Asia/Manila",
    "iso:country":"PH",
    "name:amh_x_preferred":[
        "\u1266\u1295\u130b"
    ],
    "name:deu_x_preferred":[
        "Bonga"
    ],
    "name:fil_x_preferred":[
        "Bo\u00f1ga"
    ],
    "name:fra_x_preferred":[
        "Bonga"
    ],
    "name:ita_x_preferred":[
        "Bonga"
    ],
    "name:pol_x_preferred":[
        "Bonga"
    ],
    "name:ron_x_preferred":[
        "Bonga"
    ],
    "name:rus_x_preferred":[
        "\u0411\u043e\u043d\u0433\u0430"
    ],
    "wof:name":"Bonga",
    "wof:placetype":"locality"
},
  "geometry": {"coordinates":[124.06471999999999,13.02889],"type":"Point"}
}