{
  "type": "Feature",
  "properties": {
    "gn:admin1_code":"15",
    "gn:admin2_code":"32",
    "gn:admin3_code":"143214000.0",
    "gn:asciiname":"Bonat",
    "gn:country_code":"PH",
    "gn:dem":277,
    "gn:feature_class":"P",
    "gn:feature_code":"PPL",
    "gn:name":"Bonat",
    "gn:population":0,
    "gn:timezone":"Asia/Manila",
    "iso:country":"PH",
    "name:fil_x_preferred":[
        "Bonat"
    ],
    "wof:name":"Bonat",
    "wof:placetype":"locality"
},
  "geometry": {"coordinates":[121.354,17.2744],"type":"Point"}
}