{
  "type": "Feature",
  "properties": {
    "gn:admin1_code":"02",
    "gn:admin2_code":"14",
    "gn:admin3_code":"21504000.0",
    "gn:asciiname":"Nangalisan",
    "gn:country_code":"PH",
    "gn:dem":20,
    "gn:feature_class":"P",
    "gn:feature_code":"PPL",
    "gn:name":"Nangalisan",
    "gn:population":0,
    "gn:timezone":"Asia/Manila",
    "iso:country":"PH",
    "name:fil_x_preferred":[
        "Nangalasuan"
    ],
    "name:fil_x_variant":[
        "Nangalasaoan",
        "Nangalasauan"
    ],
    "name:und_x_variant":[
        "Nangalasauan",
        "Nangalisan",
        "Nangalagaoan"
    ],
    "wof:name":"Nangalisan",
    "wof:placetype":"locality"
},
  "geometry": {"coordinates":[121.65713,17.75765],"type":"Point"}
}