{
  "type": "Feature",
  "properties": {
    "gn:admin1_code":"15",
    "gn:admin2_code":"27",
    "gn:asciiname":"Taotao",
    "gn:country_code":"PH",
    "gn:dem":82,
    "gn:feature_class":"P",
    "gn:feature_code":"PPL",
    "gn:name":"Taotao",
    "gn:population":0,
    "gn:timezone":"Asia/Manila",
    "iso:country":"PH",
    "name:fil_x_preferred":[
        "Taotao"
    ],
    "wof:name":"Taotao",
    "wof:placetype":"locality"
},
  "geometry": {"coordinates":[121.56883999999999,16.91795],"type":"Point"}
}