{
  "type": "Feature",
  "properties": {
    "gn:admin1_code":"09",
    "gn:admin2_code":"ZSI",
    "gn:admin3_code":"98302000.0",
    "gn:asciiname":"Bauang",
    "gn:country_code":"PH",
    "gn:dem":42,
    "gn:feature_class":"P",
    "gn:feature_code":"PPL",
    "gn:name":"Bauang",
    "gn:population":0,
    "gn:timezone":"Asia/Manila",
    "iso:country":"PH",
    "name:eng_x_preferred":[
        "Bauang"
    ],
    "name:und_x_variant":[
        "Bawang"
    ],
    "wof:name":"Bauang",
    "wof:placetype":"locality"
},
  "geometry": {"coordinates":[123.06910000000001,7.6858],"type":"Point"}
}