{
  "type": "Feature",
  "properties": {
    "gn:admin1_code":"03",
    "gn:admin2_code":"47",
    "gn:admin3_code":"34916000.0",
    "gn:asciiname":"Agupalo Oeste",
    "gn:country_code":"PH",
    "gn:dem":96,
    "gn:feature_class":"P",
    "gn:feature_code":"PPL",
    "gn:name":"Agupalo Oeste",
    "gn:population":0,
    "gn:timezone":"Asia/Manila",
    "iso:country":"PH",
    "name:eng_x_preferred":[
        "Agupalo West"
    ],
    "name:fil_x_preferred":[
        "Agupalo Oeste"
    ],
    "name:und_x_variant":[
        "Agupalo West",
        "Agupalo Oeste"
    ],
    "wof:name":"Agupalo Oeste",
    "wof:placetype":"locality"
},
  "geometry": {"coordinates":[120.8845,15.8395],"type":"Point"}
}