{
  "type": "Feature",
  "properties": {
    "gn:admin1_code":"03",
    "gn:admin2_code":"47",
    "gn:admin3_code":"34930000.0",
    "gn:asciiname":"Dimasalang Norte",
    "gn:country_code":"PH",
    "gn:dem":53,
    "gn:feature_class":"P",
    "gn:feature_code":"PPL",
    "gn:name":"Dimasalang Norte",
    "gn:population":0,
    "gn:timezone":"Asia/Manila",
    "iso:country":"PH",
    "name:fil_x_preferred":[
        "Dimasalang Norte"
    ],
    "wof:name":"Dimasalang Norte",
    "wof:placetype":"locality"
},
  "geometry": {"coordinates":[120.96769999999999,15.6103],"type":"Point"}
}