{
  "type": "Feature",
  "properties": {
    "gn:admin1_code":"41",
    "gn:admin2_code":"40",
    "gn:admin3_code":"175111000.0",
    "gn:asciiname":"Payompon",
    "gn:country_code":"PH",
    "gn:dem":7,
    "gn:feature_class":"P",
    "gn:feature_code":"PPL",
    "gn:name":"Payompon",
    "gn:population":0,
    "gn:timezone":"Asia/Manila",
    "iso:country":"PH",
    "name:fil_x_preferred":[
        "Payompon"
    ],
    "wof:name":"Payompon",
    "wof:placetype":"locality"
},
  "geometry": {"coordinates":[120.70399999999999,13.1119],"type":"Point"}
}