{
  "type": "Feature",
  "properties": {
    "gn:admin1_code":"02",
    "gn:admin2_code":"14",
    "gn:admin3_code":"21522000.0",
    "gn:asciiname":"Basay",
    "gn:country_code":"PH",
    "gn:dem":16,
    "gn:feature_class":"P",
    "gn:feature_code":"PPL",
    "gn:name":"Basay",
    "gn:population":0,
    "gn:timezone":"Asia/Manila",
    "iso:country":"PH",
    "name:ceb_x_preferred":[
        "Basay"
    ],
    "name:deu_x_preferred":[
        "Basay"
    ],
    "name:fra_x_preferred":[
        "Basay"
    ],
    "name:ita_x_preferred":[
        "Basay"
    ],
    "name:nld_x_preferred":[
        "Basay"
    ],
    "name:und_x_variant":[
        "Bacsay"
    ],
    "wof:name":"Basay",
    "wof:placetype":"locality"
},
  "geometry": {"coordinates":[121.22772000000001,18.52405],"type":"Point"}
}