{
  "type": "Feature",
  "properties": {
    "gn:admin1_code":"03",
    "gn:admin2_code":"50",
    "gn:admin3_code":"35415000.0",
    "gn:asciiname":"Mancatian",
    "gn:country_code":"PH",
    "gn:dem":105,
    "gn:feature_class":"P",
    "gn:feature_code":"PPL",
    "gn:name":"Mancatian",
    "gn:population":0,
    "gn:timezone":"Asia/Manila",
    "iso:country":"PH",
    "name:fil_x_preferred":[
        "Mancatian"
    ],
    "wof:name":"Mancatian",
    "wof:placetype":"locality"
},
  "geometry": {"coordinates":[120.55104,15.08472],"type":"Point"}
}