{
  "type": "Feature",
  "properties": {
    "gn:admin1_code":"12",
    "gn:admin2_code":"71",
    "gn:asciiname":"Dilag",
    "gn:cc2":"PH",
    "gn:country_code":"PH",
    "gn:dem":14,
    "gn:feature_class":"P",
    "gn:feature_code":"PPL",
    "gn:name":"Dilag",
    "gn:population":0,
    "gn:timezone":"Asia/Manila",
    "iso:country":"PH",
    "name:und_x_variant":[
        "Dalag",
        "Dilag Upper",
        "Dilag"
    ],
    "wof:name":"Dilag",
    "wof:placetype":"locality"
},
  "geometry": {"coordinates":[124.78778,6.74028],"type":"Point"}
}