{
  "type": "Feature",
  "properties": {
    "gn:country":"PH",
    "gn:fcode":"PPL",
    "gn:population":2504,
    "iso:country":"PH",
    "name:fil_x_preferred":[
        "Platagata"
    ],
    "name:und_x_variant":[
        "Taloto-an"
    ],
    "qs:name":"Platagata",
    "qs:photos_9r":0,
    "qs:photos_sr":0,
    "qs:pop_sr":"4",
    "wof:name":"Platagata",
    "wof:placetype":"locality",
    "wof:population":2504
},
  "geometry": {"coordinates":[123.1567,11.303],"type":"Point"}
}