{
  "type": "Feature",
  "properties": {
    "gn:admin1_code":"14",
    "gn:admin2_code":"35",
    "gn:admin3_code":"153636000.0",
    "gn:asciiname":"Diromoyod",
    "gn:country_code":"PH",
    "gn:dem":735,
    "gn:feature_class":"P",
    "gn:feature_code":"PPL",
    "gn:name":"Diromoyod",
    "gn:population":0,
    "gn:timezone":"Asia/Manila",
    "iso:country":"PH",
    "name:fil_x_preferred":[
        "Diromoyod"
    ],
    "wof:name":"Diromoyod",
    "wof:placetype":"locality"
},
  "geometry": {"coordinates":[124.28333000000001,7.78861],"type":"Point"}
}