{
  "type": "Feature",
  "properties": {
    "gn:admin1_code":"05",
    "gn:admin2_code":"15",
    "gn:admin3_code":"51602000.0",
    "gn:asciiname":"Mataque",
    "gn:country_code":"PH",
    "gn:dem":4,
    "gn:feature_class":"P",
    "gn:feature_code":"PPL",
    "gn:name":"Mataque",
    "gn:population":0,
    "gn:timezone":"Asia/Manila",
    "iso:country":"PH",
    "name:fil_x_preferred":[
        "Mataque"
    ],
    "name:und_x_variant":[
        "Mataqui"
    ],
    "wof:name":"Mataque",
    "wof:placetype":"locality"
},
  "geometry": {"coordinates":[122.5175,14.3019],"type":"Point"}
}