{
  "type": "Feature",
  "properties": {
    "gn:admin1_code":"40",
    "gn:admin2_code":"20",
    "gn:admin3_code":"42119000.0",
    "gn:asciiname":"Iruhin",
    "gn:country_code":"PH",
    "gn:dem":546,
    "gn:feature_class":"P",
    "gn:feature_code":"PPL",
    "gn:name":"Iruhin",
    "gn:population":0,
    "gn:timezone":"Asia/Manila",
    "iso:country":"PH",
    "name:fil_x_preferred":[
        "Iruhin"
    ],
    "wof:name":"Iruhin",
    "wof:placetype":"locality"
},
  "geometry": {"coordinates":[121.00556,14.13111],"type":"Point"}
}