{
  "type": "Feature",
  "properties": {
    "gn:admin1_code":"01",
    "gn:admin2_code":"51",
    "gn:admin3_code":"15511000.0",
    "gn:asciiname":"Beleng",
    "gn:country_code":"PH",
    "gn:dem":16,
    "gn:feature_class":"P",
    "gn:feature_code":"PPL",
    "gn:name":"Beleng",
    "gn:population":0,
    "gn:timezone":"Asia/Manila",
    "iso:country":"PH",
    "name:fil_x_preferred":[
        "Beleng"
    ],
    "name:und_x_variant":[
        "Bulung"
    ],
    "wof:name":"Beleng",
    "wof:placetype":"locality"
},
  "geometry": {"coordinates":[120.38839,15.82879],"type":"Point"}
}