{
  "type": "Feature",
  "properties": {
    "gn:admin1_code":"06",
    "gn:admin2_code":"30",
    "gn:admin3_code":"63008000.0",
    "gn:asciiname":"General Luna",
    "gn:country_code":"PH",
    "gn:dem":8,
    "gn:feature_class":"P",
    "gn:feature_code":"PPL",
    "gn:name":"General Luna",
    "gn:population":0,
    "gn:timezone":"Asia/Manila",
    "iso:country":"PH",
    "name:ceb_x_preferred":[
        "General Luna"
    ],
    "name:deu_x_preferred":[
        "General Luna"
    ],
    "name:fil_x_preferred":[
        "General Luna"
    ],
    "name:ita_x_preferred":[
        "General Luna"
    ],
    "name:nld_x_preferred":[
        "General Luna"
    ],
    "name:spa_x_preferred":[
        "General Luna"
    ],
    "name:war_x_preferred":[
        "General Luna"
    ],
    "wof:name":"General Luna",
    "wof:placetype":"locality"
},
  "geometry": {"coordinates":[122.84999999999999,11.05],"type":"Point"}
}