{
  "type": "Feature",
  "properties": {
    "gn:admin1_code":"02",
    "gn:admin2_code":"31",
    "gn:admin3_code":"23114000.0",
    "gn:asciiname":"Malasin",
    "gn:country_code":"PH",
    "gn:dem":41,
    "gn:feature_class":"P",
    "gn:feature_code":"PPL",
    "gn:name":"Malasin",
    "gn:population":0,
    "gn:timezone":"Asia/Manila",
    "iso:country":"PH",
    "name:und_x_variant":[
        "Angeles"
    ],
    "wof:name":"Malasin",
    "wof:placetype":"locality"
},
  "geometry": {"coordinates":[121.84918,17.16128],"type":"Point"}
}