{
  "type": "Feature",
  "properties": {
    "gn:country":"PH",
    "gn:fcode":"ADM3",
    "gn:pop":23085,
    "iso:country":"PH",
    "name:cat_x_preferred":[
        "Solsona"
    ],
    "name:ceb_x_preferred":[
        "Solsona"
    ],
    "name:deu_x_preferred":[
        "Solsona"
    ],
    "name:fil_x_preferred":[
        "Bayan ng Solsona"
    ],
    "name:fil_x_variant":[
        "Solsona"
    ],
    "name:fra_x_preferred":[
        "Solsona"
    ],
    "name:ita_x_preferred":[
        "Solsona"
    ],
    "name:nld_x_preferred":[
        "Solsona"
    ],
    "name:sco_x_preferred":[
        "Solsona"
    ],
    "name:swe_x_preferred":[
        "Solsona"
    ],
    "name:vie_x_preferred":[
        "Solsona"
    ],
    "name:war_x_preferred":[
        "Solsona"
    ],
    "qs:name":"Solsona",
    "qs:photos_9r":0,
    "qs:photos_sr":0,
    "qs:pop_sr":"7",
    "wd:wordcount":23,
    "wof:name":"Solsona",
    "wof:placetype":"localadmin",
    "wof:population":23085
},
  "geometry": {"coordinates":[120.82217,18.11615],"type":"Point"}
}