{
  "type": "Feature",
  "properties": {
    "gn:admin1_code":"08",
    "gn:admin2_code":"37",
    "gn:admin3_code":"83708000.0",
    "gn:asciiname":"Mapgap",
    "gn:country_code":"PH",
    "gn:dem":107,
    "gn:feature_class":"P",
    "gn:feature_code":"PPL",
    "gn:name":"Mapgap",
    "gn:population":0,
    "gn:timezone":"Asia/Manila",
    "iso:country":"PH",
    "name:fil_x_preferred":[
        "Mapgap"
    ],
    "wof:name":"Mapgap",
    "wof:placetype":"locality"
},
  "geometry": {"coordinates":[124.8616,10.6104],"type":"Point"}
}