{
  "type": "Feature",
  "properties": {
    "gn:admin1_code":"07",
    "gn:admin2_code":"21",
    "gn:admin3_code":"72203000.0",
    "gn:asciiname":"Alangasil",
    "gn:country_code":"PH",
    "gn:dem":36,
    "gn:feature_class":"P",
    "gn:feature_code":"PPL",
    "gn:name":"Alangasil",
    "gn:population":0,
    "gn:timezone":"Asia/Manila",
    "iso:country":"PH",
    "name:fil_x_preferred":[
        "Alangasil"
    ],
    "name:und_x_variant":[
        "Alangasel"
    ],
    "wof:name":"Alangasil",
    "wof:placetype":"locality"
},
  "geometry": {"coordinates":[123.3464,9.7656],"type":"Point"}
}