{
  "type": "Feature",
  "properties": {
    "gn:admin1_code":"03",
    "gn:admin2_code":"47",
    "gn:admin3_code":"34910000.0",
    "gn:asciiname":"Capotatan",
    "gn:country_code":"PH",
    "gn:dem":73,
    "gn:feature_class":"P",
    "gn:feature_code":"PPL",
    "gn:name":"Capotatan",
    "gn:population":0,
    "gn:timezone":"Asia/Manila",
    "iso:country":"PH",
    "name:fil_x_preferred":[
        "Capotatan"
    ],
    "name:fil_x_variant":[
        "Sapang Caputatan",
        "Caputatan"
    ],
    "wof:name":"Capotatan",
    "wof:placetype":"locality"
},
  "geometry": {"coordinates":[121.11293999999999,15.31501],"type":"Point"}
}