{
  "type": "Feature",
  "properties": {
    "gn:country":"PH",
    "gn:fcode":"ADM3",
    "gn:pop":16685,
    "iso:country":"PH",
    "name:fil_x_preferred":[
        "Baclayon"
    ],
    "qs:name":"Baclayon",
    "qs:photos_9r":0,
    "qs:photos_sr":0,
    "qs:pop_sr":"6",
    "wof:name":"Baclayon",
    "wof:placetype":"localadmin",
    "wof:population":16685
},
  "geometry": {"coordinates":[123.91328,9.64496],"type":"Point"}
}