{
  "type": "Feature",
  "properties": {
    "gn:country":"PH",
    "gn:fcode":"ADM3",
    "gn:pop":16685,
    "iso:country":"PH",
    "name:bcl_x_preferred":[
        "Baclayon"
    ],
    "name:ceb_x_preferred":[
        "Baclayon"
    ],
    "name:deu_x_preferred":[
        "Baclayon"
    ],
    "name:fil_x_preferred":[
        "Baclayon"
    ],
    "name:fra_x_preferred":[
        "Baclayon"
    ],
    "name:ilo_x_preferred":[
        "Baclayon"
    ],
    "name:ind_x_preferred":[
        "Baclayon"
    ],
    "name:ita_x_preferred":[
        "Baclayon"
    ],
    "name:nld_x_preferred":[
        "Baclayon"
    ],
    "name:nor_x_preferred":[
        "Baclayon"
    ],
    "name:pag_x_preferred":[
        "Baclayon"
    ],
    "name:pam_x_preferred":[
        "Baclayon"
    ],
    "name:swe_x_preferred":[
        "Baclayon"
    ],
    "name:tgl_x_preferred":[
        "Baclayon"
    ],
    "name:urd_x_preferred":[
        "\u0628\u0627\u06a9\u0644\u0627\u06cc\u0648\u0646"
    ],
    "name:vie_x_preferred":[
        "Baclayon"
    ],
    "name:war_x_preferred":[
        "Baclayon"
    ],
    "qs:name":"Baclayon",
    "qs:photos_9r":0,
    "qs:photos_sr":0,
    "qs:pop_sr":"6",
    "wof:name":"Baclayon",
    "wof:placetype":"localadmin",
    "wof:population":16685
},
  "geometry": {"coordinates":[123.91328,9.64496],"type":"Point"}
}