{
  "type": "Feature",
  "properties": {
    "gn:admin1_code":"09",
    "gn:admin2_code":"65",
    "gn:admin3_code":"97206000.0",
    "gn:asciiname":"Salucap",
    "gn:cc2":"PH",
    "gn:country_code":"PH",
    "gn:dem":84,
    "gn:feature_class":"P",
    "gn:feature_code":"PPL",
    "gn:name":"Salucap",
    "gn:population":0,
    "gn:timezone":"Asia/Manila",
    "iso:country":"PH",
    "name:und_x_variant":[
        "Silucap",
        "Salucap"
    ],
    "wof:name":"Salucap",
    "wof:placetype":"locality"
},
  "geometry": {"coordinates":[122.66694,8.0625],"type":"Point"}
}