{
  "type": "Feature",
  "properties": {
    "gn:admin1_code":"06",
    "gn:admin2_code":"06",
    "gn:asciiname":"Dauis",
    "gn:country_code":"PH",
    "gn:dem":-9999,
    "gn:feature_class":"P",
    "gn:feature_code":"PPL",
    "gn:name":"Dauis",
    "gn:population":0,
    "gn:timezone":"Asia/Manila",
    "iso:country":"PH",
    "name:fil_x_preferred":[
        "Dauis"
    ],
    "name:und_x_variant":[
        "Dawis"
    ],
    "wof:name":"Dauis",
    "wof:placetype":"locality"
},
  "geometry": {"coordinates":[121.5697,11.8922],"type":"Point"}
}