{
  "type": "Feature",
  "properties": {
    "gn:admin1_code":"14",
    "gn:admin2_code":"56",
    "gn:admin3_code":"153803000.0",
    "gn:asciiname":"Masilang",
    "gn:country_code":"PH",
    "gn:dem":11,
    "gn:feature_class":"P",
    "gn:feature_code":"PPL",
    "gn:name":"Masilang",
    "gn:population":0,
    "gn:timezone":"Asia/Manila",
    "iso:country":"PH",
    "name:fil_x_preferred":[
        "Masilang"
    ],
    "wof:name":"Masilang",
    "wof:placetype":"locality"
},
  "geometry": {"coordinates":[124.81139,6.67167],"type":"Point"}
}