{
  "type": "Feature",
  "properties": {
    "gn:admin1_code":"08",
    "gn:admin2_code":"55",
    "gn:admin3_code":"86025000.0",
    "gn:asciiname":"Malapgap",
    "gn:country_code":"PH",
    "gn:dem":202,
    "gn:feature_class":"P",
    "gn:feature_code":"PPL",
    "gn:name":"Malapgap",
    "gn:population":0,
    "gn:timezone":"Asia/Manila",
    "iso:country":"PH",
    "name:fil_x_preferred":[
        "Malapgap"
    ],
    "wof:name":"Malapgap",
    "wof:placetype":"locality"
},
  "geometry": {"coordinates":[124.9015,11.9999],"type":"Point"}
}