{
  "type": "Feature",
  "properties": {
    "gn:admin1_code":"09",
    "gn:admin2_code":"66",
    "gn:admin3_code":"97306000.0",
    "gn:asciiname":"Lucoban",
    "gn:cc2":"PH",
    "gn:country_code":"PH",
    "gn:dem":78,
    "gn:feature_class":"P",
    "gn:feature_code":"PPL",
    "gn:name":"Lucoban",
    "gn:population":0,
    "gn:timezone":"Asia/Manila",
    "iso:country":"PH",
    "name:und_x_variant":[
        "Lukuban",
        "Lucoban"
    ],
    "wof:name":"Lucoban",
    "wof:placetype":"locality"
},
  "geometry": {"coordinates":[123.32832999999999,7.56583],"type":"Point"}
}