{
  "type": "Feature",
  "properties": {
    "gn:admin1_code":"03",
    "gn:admin2_code":"63",
    "gn:admin3_code":"36910000.0",
    "gn:asciiname":"Carapdapan",
    "gn:country_code":"PH",
    "gn:dem":21,
    "gn:feature_class":"P",
    "gn:feature_code":"PPL",
    "gn:name":"Carapdapan",
    "gn:population":0,
    "gn:timezone":"Asia/Manila",
    "iso:country":"PH",
    "name:fil_x_preferred":[
        "Carapdapan"
    ],
    "wof:name":"Carapdapan",
    "wof:placetype":"locality"
},
  "geometry": {"coordinates":[120.56667,15.68333],"type":"Point"}
}