{
  "type": "Feature",
  "properties": {
    "gn:admin1_code":"40",
    "gn:admin2_code":"H2",
    "gn:asciiname":"Guinaygayan",
    "gn:country_code":"PH",
    "gn:dem":7,
    "gn:feature_class":"P",
    "gn:feature_code":"PPL",
    "gn:name":"Guinaygayan",
    "gn:population":0,
    "gn:timezone":"Asia/Manila",
    "iso:country":"PH",
    "name:fil_x_preferred":[
        "Guinaygayan"
    ],
    "wof:name":"Guinaygayan",
    "wof:placetype":"locality"
},
  "geometry": {"coordinates":[122.25790000000001,14.7902],"type":"Point"}
}