{
  "type": "Feature",
  "properties": {
    "gn:admin1_code":"11",
    "gn:admin2_code":"I6",
    "gn:admin3_code":"118203000.0",
    "gn:asciiname":"Maubog",
    "gn:country_code":"PH",
    "gn:dem":58,
    "gn:feature_class":"P",
    "gn:feature_code":"PPL",
    "gn:name":"Maubog",
    "gn:population":0,
    "gn:timezone":"Asia/Manila",
    "iso:country":"PH",
    "name:fil_x_preferred":[
        "Maubog"
    ],
    "wof:name":"Maubog",
    "wof:placetype":"locality"
},
  "geometry": {"coordinates":[125.8805,7.2482],"type":"Point"}
}