{
  "type": "Feature",
  "properties": {
    "gn:admin1_code":"06",
    "gn:admin2_code":"04",
    "gn:admin3_code":"60406000.0",
    "gn:asciiname":"Batong Bato",
    "gn:country_code":"PH",
    "gn:dem":12,
    "gn:feature_class":"P",
    "gn:feature_code":"PPL",
    "gn:name":"Batong Bato",
    "gn:population":0,
    "gn:timezone":"Asia/Manila",
    "iso:country":"PH",
    "name:fil_x_preferred":[
        "Batong Bato"
    ],
    "name:und_x_variant":[
        "Bugtong Bato"
    ],
    "wof:name":"Batong Bato",
    "wof:placetype":"locality"
},
  "geometry": {"coordinates":[122.2127,11.8072],"type":"Point"}
}