{
  "type": "Feature",
  "properties": {
    "gn:admin1_code":"05",
    "gn:admin2_code":"58",
    "gn:admin3_code":"56206000.0",
    "gn:asciiname":"Corocauayan",
    "gn:country_code":"PH",
    "gn:dem":46,
    "gn:feature_class":"P",
    "gn:feature_code":"PPL",
    "gn:name":"Corocauayan",
    "gn:population":0,
    "gn:timezone":"Asia/Manila",
    "iso:country":"PH",
    "name:fil_x_preferred":[
        "Corocauayan"
    ],
    "wof:name":"Corocauayan",
    "wof:placetype":"locality"
},
  "geometry": {"coordinates":[123.86667,12.93333],"type":"Point"}
}