{
  "type": "Feature",
  "properties": {
    "gn:admin1_code":"06",
    "gn:admin2_code":"06",
    "gn:admin3_code":"60608000.0",
    "gn:asciiname":"Jungao",
    "gn:country_code":"PH",
    "gn:dem":317,
    "gn:feature_class":"P",
    "gn:feature_code":"PPL",
    "gn:name":"Jungao",
    "gn:population":0,
    "gn:timezone":"Asia/Manila",
    "iso:country":"PH",
    "name:fil_x_preferred":[
        "Jungao"
    ],
    "wof:name":"Jungao",
    "wof:placetype":"locality"
},
  "geometry": {"coordinates":[122.03333000000001,10.66667],"type":"Point"}
}