{
  "type": "Feature",
  "properties": {
    "gn:admin1_code":"13",
    "gn:admin2_code":"03",
    "gn:admin3_code":"160303000.0",
    "gn:asciiname":"Milagros",
    "gn:country_code":"PH",
    "gn:dem":23,
    "gn:feature_class":"P",
    "gn:feature_code":"PPL",
    "gn:name":"Milagros",
    "gn:population":0,
    "gn:timezone":"Asia/Manila",
    "iso:country":"PH",
    "name:ceb_x_preferred":[
        "Milagros"
    ],
    "name:deu_x_preferred":[
        "Milagros"
    ],
    "name:fil_x_preferred":[
        "Milagros"
    ],
    "name:fra_x_preferred":[
        "Milagros"
    ],
    "name:ita_x_preferred":[
        "Milagros"
    ],
    "name:nld_x_preferred":[
        "Milagros"
    ],
    "name:swe_x_preferred":[
        "Milagros"
    ],
    "name:vie_x_preferred":[
        "Milagros"
    ],
    "name:war_x_preferred":[
        "Milagros"
    ],
    "wof:name":"Milagros",
    "wof:placetype":"locality"
},
  "geometry": {"coordinates":[125.58083000000001,8.64556],"type":"Point"}
}