{
  "type": "Feature",
  "properties": {
    "gn:admin1_code":"02",
    "gn:admin2_code":"48",
    "gn:admin3_code":"25003000.0",
    "gn:asciiname":"Baretbet",
    "gn:country_code":"PH",
    "gn:dem":225,
    "gn:feature_class":"P",
    "gn:feature_code":"PPL",
    "gn:name":"Baretbet",
    "gn:population":0,
    "gn:timezone":"Asia/Manila",
    "iso:country":"PH",
    "name:fil_x_preferred":[
        "Baretbet"
    ],
    "wof:name":"Baretbet",
    "wof:placetype":"locality"
},
  "geometry": {"coordinates":[121.25239999999999,16.5772],"type":"Point"}
}