{
  "type": "Feature",
  "properties": {
    "gn:admin1_code":"01",
    "gn:admin2_code":"51",
    "gn:admin3_code":"15526000.0",
    "gn:asciiname":"Guesang",
    "gn:country_code":"PH",
    "gn:dem":13,
    "gn:feature_class":"P",
    "gn:feature_code":"PPL",
    "gn:name":"Guesang",
    "gn:population":0,
    "gn:timezone":"Asia/Manila",
    "iso:country":"PH",
    "name:fil_x_preferred":[
        "Guesang"
    ],
    "wof:name":"Guesang",
    "wof:placetype":"locality"
},
  "geometry": {"coordinates":[120.43179000000001,16.0472],"type":"Point"}
}