{
  "type": "Feature",
  "properties": {
    "gn:admin1_code":"10",
    "gn:admin2_code":"42",
    "gn:admin3_code":"104215000.0",
    "gn:asciiname":"Manga",
    "gn:country_code":"PH",
    "gn:dem":73,
    "gn:feature_class":"P",
    "gn:feature_code":"PPL",
    "gn:name":"Manga",
    "gn:population":0,
    "gn:timezone":"Asia/Manila",
    "iso:country":"PH",
    "name:fil_x_preferred":[
        "Manga"
    ],
    "wof:name":"Manga",
    "wof:placetype":"locality"
},
  "geometry": {"coordinates":[123.74379999999999,8.0917],"type":"Point"}
}