{
  "type": "Feature",
  "properties": {
    "gn:admin1_code":"15",
    "gn:admin2_code":"H6",
    "gn:admin3_code":"148103000.0",
    "gn:asciiname":"Malabibit",
    "gn:country_code":"PH",
    "gn:dem":27,
    "gn:feature_class":"P",
    "gn:feature_code":"PPL",
    "gn:name":"Malabibit",
    "gn:population":0,
    "gn:timezone":"Asia/Manila",
    "iso:country":"PH",
    "name:fil_x_preferred":[
        "Malabibit"
    ],
    "wof:name":"Malabibit",
    "wof:placetype":"locality"
},
  "geometry": {"coordinates":[121.4496,18.2349],"type":"Point"}
}