{
  "type": "Feature",
  "properties": {
    "gn:admin1_code":"06",
    "gn:admin2_code":"30",
    "gn:admin3_code":"63017000.0",
    "gn:asciiname":"Sawe",
    "gn:country_code":"PH",
    "gn:dem":83,
    "gn:feature_class":"P",
    "gn:feature_code":"PPL",
    "gn:name":"Sawe",
    "gn:population":0,
    "gn:timezone":"Asia/Manila",
    "iso:country":"PH",
    "name:fil_x_preferred":[
        "Sawe"
    ],
    "wof:name":"Sawe",
    "wof:placetype":"locality"
},
  "geometry": {"coordinates":[122.5822,11.0885],"type":"Point"}
}