{
  "type": "Feature",
  "properties": {
    "gn:admin1_code":"02",
    "gn:admin2_code":"31",
    "gn:admin3_code":"23122000.0",
    "gn:asciiname":"Talaca",
    "gn:country_code":"PH",
    "gn:dem":110,
    "gn:feature_class":"P",
    "gn:feature_code":"PPL",
    "gn:name":"Talaca",
    "gn:population":0,
    "gn:timezone":"Asia/Manila",
    "iso:country":"PH",
    "name:fil_x_preferred":[
        "Talaca"
    ],
    "wof:name":"Talaca",
    "wof:placetype":"locality"
},
  "geometry": {"coordinates":[121.60274,17.31172999999999],"type":"Point"}
}