{
  "type": "Feature",
  "properties": {
    "gn:admin1_code":"03",
    "gn:admin2_code":"47",
    "gn:admin3_code":"34930000.0",
    "gn:asciiname":"Valle",
    "gn:country_code":"PH",
    "gn:dem":56,
    "gn:feature_class":"P",
    "gn:feature_code":"PPL",
    "gn:name":"Valle",
    "gn:population":0,
    "gn:timezone":"Asia/Manila",
    "iso:country":"PH",
    "name:ast_x_preferred":[
        "Valle"
    ],
    "name:cat_x_preferred":[
        "Valle"
    ],
    "name:ceb_x_preferred":[
        "Valle"
    ],
    "name:dan_x_preferred":[
        "Valle"
    ],
    "name:deu_x_preferred":[
        "Valle"
    ],
    "name:epo_x_preferred":[
        "Valle"
    ],
    "name:est_x_preferred":[
        "Valle"
    ],
    "name:eus_x_preferred":[
        "Valle"
    ],
    "name:fil_x_preferred":[
        "Valle"
    ],
    "name:fin_x_preferred":[
        "Valle"
    ],
    "name:fra_x_preferred":[
        "Valle"
    ],
    "name:hrv_x_preferred":[
        "Valle"
    ],
    "name:ita_x_preferred":[
        "Valle"
    ],
    "name:nld_x_preferred":[
        "Valle"
    ],
    "name:nor_x_preferred":[
        "Valle"
    ],
    "name:pol_x_preferred":[
        "Valle"
    ],
    "name:ron_x_preferred":[
        "Valle"
    ],
    "name:rus_x_preferred":[
        "\u0412\u0430\u043b\u044c\u0435"
    ],
    "name:spa_x_preferred":[
        "Valle"
    ],
    "name:srp_x_preferred":[
        "\u0412\u0430\u043b\u0435"
    ],
    "name:swe_x_preferred":[
        "Valle"
    ],
    "wof:name":"Valle",
    "wof:placetype":"locality"
},
  "geometry": {"coordinates":[120.93935999999999,15.63819],"type":"Point"}
}