{
  "type": "Feature",
  "properties": {
    "gn:admin1_code":"03",
    "gn:admin2_code":"47",
    "gn:admin3_code":"34930000.0",
    "gn:asciiname":"Valle",
    "gn:country_code":"PH",
    "gn:dem":56,
    "gn:feature_class":"P",
    "gn:feature_code":"PPL",
    "gn:name":"Valle",
    "gn:population":0,
    "gn:timezone":"Asia/Manila",
    "iso:country":"PH",
    "name:fil_x_preferred":[
        "Valle"
    ],
    "wof:name":"Valle",
    "wof:placetype":"locality"
},
  "geometry": {"coordinates":[120.93935999999999,15.63819],"type":"Point"}
}