{
  "type": "Feature",
  "properties": {
    "gn:country":"PH",
    "gn:fcode":"PPL",
    "gn:population":4297,
    "iso:country":"PH",
    "name:bel_x_preferred":[
        "\u0421\u0430\u043d-\u0412\u0456\u0441\u0435\u043d\u0442\u044d"
    ],
    "name:bre_x_preferred":[
        "San Vicente"
    ],
    "name:cat_x_preferred":[
        "San Vicente"
    ],
    "name:ceb_x_preferred":[
        "San Vicente"
    ],
    "name:deu_x_preferred":[
        "San Vicente"
    ],
    "name:eus_x_preferred":[
        "San Vicente"
    ],
    "name:fil_x_preferred":[
        "San Vicente"
    ],
    "name:fra_x_preferred":[
        "San Vicente"
    ],
    "name:glg_x_preferred":[
        "San Vicente"
    ],
    "name:ilo_x_preferred":[
        "San Vicente"
    ],
    "name:ita_x_preferred":[
        "San Vicente"
    ],
    "name:kor_x_preferred":[
        "\uc0b0\ube44\uc13c\ud14c"
    ],
    "name:lit_x_preferred":[
        "San Visent\u0117"
    ],
    "name:nah_x_preferred":[
        "San Vicente"
    ],
    "name:nds_x_preferred":[
        "San Vicente"
    ],
    "name:nld_x_preferred":[
        "San Vicente"
    ],
    "name:pol_x_preferred":[
        "San Vicente"
    ],
    "name:por_x_preferred":[
        "San Vicente"
    ],
    "name:ron_x_preferred":[
        "San Vicente"
    ],
    "name:rus_x_preferred":[
        "\u0421\u0430\u043d-\u0412\u0438\u0441\u0435\u043d\u0442\u0435"
    ],
    "name:sco_x_preferred":[
        "San Vicente"
    ],
    "name:slk_x_preferred":[
        "San Vicente"
    ],
    "name:spa_x_preferred":[
        "San Vicente"
    ],
    "name:swe_x_preferred":[
        "San Vicente"
    ],
    "name:ukr_x_preferred":[
        "\u0421\u0430\u043d-\u0412\u0456\u0441\u0435\u043d\u0442\u0435"
    ],
    "name:war_x_preferred":[
        "San Vicente"
    ],
    "qs:name":"San Vicente",
    "qs:photos_9r":0,
    "qs:photos_sr":0,
    "qs:pop_sr":"4",
    "wd:wordcount":196,
    "wof:name":"San Vicente",
    "wof:placetype":"locality",
    "wof:population":4297
},
  "geometry": {"coordinates":[123.4188,13.4081],"type":"Point"}
}