{
  "type": "Feature",
  "properties": {
    "gn:country":"PH",
    "gn:fcode":"PPL",
    "gn:pop":4297,
    "iso:country":"PH",
    "name:fil_x_preferred":[
        "San Vicente"
    ],
    "qs:name":"San Vicente",
    "qs:photos_9r":0,
    "qs:photos_sr":0,
    "qs:pop_sr":"4",
    "wd:wordcount":196,
    "wof:name":"San Vicente",
    "wof:placetype":"locality",
    "wof:population":4297
},
  "geometry": {"coordinates":[123.4188,13.4081],"type":"Point"}
}