{
  "type": "Feature",
  "properties": {
    "gn:admin1_code":"06",
    "gn:admin2_code":"H3",
    "gn:admin3_code":"64504000.0",
    "gn:asciiname":"Canibungan",
    "gn:country_code":"PH",
    "gn:dem":23,
    "gn:feature_class":"P",
    "gn:feature_code":"PPL",
    "gn:name":"Canibungan",
    "gn:population":0,
    "gn:timezone":"Asia/Manila",
    "iso:country":"PH",
    "name:fil_x_preferred":[
        "Canibungan"
    ],
    "wof:name":"Canibungan",
    "wof:placetype":"locality"
},
  "geometry": {"coordinates":[123.2478,10.9457],"type":"Point"}
}