{
  "type": "Feature",
  "properties": {
    "iso:country":"PH",
    "name:fil_x_preferred":[
        "Salvacion"
    ],
    "qs:gn_country":"PH",
    "qs:gn_fcode":"PPL",
    "qs:gn_pop":2088,
    "qs:name":"Salvacion",
    "qs:name_adm0":"Philippines",
    "qs:name_adm1":"Caraga",
    "qs:photos":0,
    "qs:photos_1k":0,
    "qs:photos_9k":1,
    "qs:photos_9r":1,
    "qs:photos_all":12,
    "qs:photos_sr":0,
    "qs:placetype":"Town",
    "qs:pop_sr":"4",
    "qs:woe_adm0":23424934,
    "wd:elevation":550.0,
    "wd:wordcount":37,
    "wof:name":"Salvacion",
    "wof:placetype":"locality",
    "wof:population":2088
},
  "geometry": {"coordinates":[126.20806,8.71278],"type":"Point"}
}