{
  "type": "Feature",
  "properties": {
    "gn:admin1_code":"09",
    "gn:admin2_code":"ZSI",
    "gn:admin3_code":"98308000.0",
    "gn:asciiname":"Kigay",
    "gn:country_code":"PH",
    "gn:dem":37,
    "gn:feature_class":"P",
    "gn:feature_code":"PPL",
    "gn:name":"Kigay",
    "gn:population":0,
    "gn:timezone":"Asia/Manila",
    "iso:country":"PH",
    "name:eng_x_preferred":[
        "Kigay"
    ],
    "wof:name":"Kigay",
    "wof:placetype":"locality"
},
  "geometry": {"coordinates":[123.04600000000001,7.6276],"type":"Point"}
}