{
  "type": "Feature",
  "properties": {
    "gn:admin1_code":"07",
    "gn:admin2_code":"11",
    "gn:admin3_code":"71206000.0",
    "gn:asciiname":"Hanopol",
    "gn:country_code":"PH",
    "gn:dem":117,
    "gn:feature_class":"P",
    "gn:feature_code":"PPL",
    "gn:name":"Hanopol",
    "gn:population":0,
    "gn:timezone":"Asia/Manila",
    "iso:country":"PH",
    "name:fil_x_preferred":[
        "Hanopol"
    ],
    "wof:name":"Hanopol",
    "wof:placetype":"locality"
},
  "geometry": {"coordinates":[124.0108,9.7448],"type":"Point"}
}