{
  "type": "Feature",
  "properties": {
    "gn:admin1_code":"09",
    "gn:admin2_code":"ZSI",
    "gn:admin3_code":"98311000.0",
    "gn:asciiname":"Taguisian",
    "gn:country_code":"PH",
    "gn:dem":121,
    "gn:feature_class":"P",
    "gn:feature_code":"PPL",
    "gn:name":"Taguisian",
    "gn:population":0,
    "gn:timezone":"Asia/Manila",
    "iso:country":"PH",
    "name:fil_x_preferred":[
        "Taguisian"
    ],
    "wof:name":"Taguisian",
    "wof:placetype":"locality"
},
  "geometry": {"coordinates":[122.88333,7.56667],"type":"Point"}
}