{
  "type": "Feature",
  "properties": {
    "gn:admin1_code":"14",
    "gn:admin2_code":"56",
    "gn:admin3_code":"153805000.0",
    "gn:asciiname":"Bialong",
    "gn:country_code":"PH",
    "gn:dem":41,
    "gn:feature_class":"P",
    "gn:feature_code":"PPL",
    "gn:name":"Bialong",
    "gn:population":0,
    "gn:timezone":"Asia/Manila",
    "iso:country":"PH",
    "name:fil_x_preferred":[
        "Bialong"
    ],
    "wof:name":"Bialong",
    "wof:placetype":"locality"
},
  "geometry": {"coordinates":[124.91667,6.73333],"type":"Point"}
}