{
  "type": "Feature",
  "properties": {
    "gn:admin1_code":"01",
    "gn:admin2_code":"51",
    "gn:admin3_code":"15514000.0",
    "gn:asciiname":"Catubig",
    "gn:country_code":"PH",
    "gn:dem":17,
    "gn:feature_class":"P",
    "gn:feature_code":"PPL",
    "gn:name":"Catubig",
    "gn:population":0,
    "gn:timezone":"Asia/Manila",
    "iso:country":"PH",
    "name:fil_x_preferred":[
        "Catubig"
    ],
    "wof:name":"Catubig",
    "wof:placetype":"locality"
},
  "geometry": {"coordinates":[119.9132,16.2924],"type":"Point"}
}