{
  "type": "Feature",
  "properties": {
    "gn:admin1_code":"02",
    "gn:admin2_code":"68",
    "gn:admin3_code":"25705000.0",
    "gn:asciiname":"Salvacion",
    "gn:country_code":"PH",
    "gn:dem":102,
    "gn:feature_class":"P",
    "gn:feature_code":"PPL",
    "gn:name":"Salvacion",
    "gn:population":0,
    "gn:timezone":"Asia/Manila",
    "iso:country":"PH",
    "wof:name":"Salvacion",
    "wof:placetype":"locality"
},
  "geometry": {"coordinates":[121.59025,16.56857999999999],"type":"Point"}
}