{
  "type": "Feature",
  "properties": {
    "gn:admin1_code":"07",
    "gn:admin2_code":"11",
    "gn:admin3_code":"71209000.0",
    "gn:asciiname":"Lubang",
    "gn:country_code":"PH",
    "gn:dem":182,
    "gn:feature_class":"P",
    "gn:feature_code":"PPL",
    "gn:name":"Lubang",
    "gn:population":0,
    "gn:timezone":"Asia/Manila",
    "iso:country":"PH",
    "name:fil_x_preferred":[
        "Lubang"
    ],
    "wof:name":"Lubang",
    "wof:placetype":"locality"
},
  "geometry": {"coordinates":[124.19336,10.0482],"type":"Point"}
}