{
  "type": "Feature",
  "properties": {
    "gn:admin1_code":"05",
    "gn:admin2_code":"39",
    "gn:admin3_code":"54111000.0",
    "gn:asciiname":"Sinalongan",
    "gn:country_code":"PH",
    "gn:dem":56,
    "gn:feature_class":"P",
    "gn:feature_code":"PPL",
    "gn:name":"Sinalongan",
    "gn:population":0,
    "gn:timezone":"Asia/Manila",
    "iso:country":"PH",
    "name:fil_x_preferred":[
        "Sinalongan"
    ],
    "wof:name":"Sinalongan",
    "wof:placetype":"locality"
},
  "geometry": {"coordinates":[123.58841,12.27004],"type":"Point"}
}