{
  "type": "Feature",
  "properties": {
    "gn:admin1_code":"41",
    "gn:admin2_code":"49",
    "gn:admin3_code":"175305000.0",
    "gn:asciiname":"Iwahig",
    "gn:country_code":"PH",
    "gn:dem":19,
    "gn:feature_class":"P",
    "gn:feature_code":"PPL",
    "gn:name":"Iwahig",
    "gn:population":0,
    "gn:timezone":"Asia/Manila",
    "iso:country":"PH",
    "name:fil_x_preferred":[
        "Iwahig"
    ],
    "wof:name":"Iwahig",
    "wof:placetype":"locality"
},
  "geometry": {"coordinates":[117.51667,8.59917],"type":"Point"}
}