{
  "type": "Feature",
  "properties": {
    "gn:admin1_code":"06",
    "gn:admin2_code":"30",
    "gn:admin3_code":"63008000.0",
    "gn:asciiname":"Puerto Princesa",
    "gn:country_code":"PH",
    "gn:dem":12,
    "gn:feature_class":"P",
    "gn:feature_code":"PPL",
    "gn:name":"Puerto Princesa",
    "gn:population":0,
    "gn:timezone":"Asia/Manila",
    "iso:country":"PH",
    "name:fil_x_preferred":[
        "Puerto Princesa"
    ],
    "wof:name":"Puerto Princesa",
    "wof:placetype":"locality"
},
  "geometry": {"coordinates":[122.8925,11.03361],"type":"Point"}
}