{
  "type": "Feature",
  "properties": {
    "gn:admin1_code":"06",
    "gn:admin2_code":"30",
    "gn:admin3_code":"63008000.0",
    "gn:asciiname":"Puerto Princesa",
    "gn:country_code":"PH",
    "gn:dem":12,
    "gn:feature_class":"P",
    "gn:feature_code":"PPL",
    "gn:name":"Puerto Princesa",
    "gn:population":0,
    "gn:timezone":"Asia/Manila",
    "iso:country":"PH",
    "name:ara_x_preferred":[
        "\u0628\u0648\u0631\u062a\u0648\u0628\u0631\u0646\u0633\u0633"
    ],
    "name:bcl_x_preferred":[
        "Puerto Princesa"
    ],
    "name:bul_x_preferred":[
        "\u041f\u0443\u0435\u0440\u0442\u043e \u041f\u0440\u0438\u043d\u0441\u0435\u0441\u0430"
    ],
    "name:ceb_x_preferred":[
        "Puerto Princesa"
    ],
    "name:dan_x_preferred":[
        "Puerto Princesa City"
    ],
    "name:deu_x_preferred":[
        "Puerto Princesa"
    ],
    "name:fas_x_preferred":[
        "\u067e\u0648\u0631\u062a\u0648\u067e\u0631\u0646\u0633\u0633"
    ],
    "name:fil_x_preferred":[
        "Puerto Princesa"
    ],
    "name:fin_x_preferred":[
        "Puerto Princesa"
    ],
    "name:fra_x_preferred":[
        "Puerto Princesa"
    ],
    "name:ilo_x_preferred":[
        "Puerto Princesa"
    ],
    "name:ind_x_preferred":[
        "Kota Puerto Princesa"
    ],
    "name:ita_x_preferred":[
        "Puerto Princesa"
    ],
    "name:jpn_x_preferred":[
        "\u30d7\u30a8\u30eb\u30c8\u30fb\u30d7\u30ea\u30f3\u30bb\u30b5"
    ],
    "name:kor_x_preferred":[
        "\ud478\uc5d0\ub974\ud1a0\ud504\ub9b0\uc138\uc0ac"
    ],
    "name:nld_x_preferred":[
        "Puerto Princesa"
    ],
    "name:nno_x_preferred":[
        "Puerto Princesa"
    ],
    "name:nor_x_preferred":[
        "Puerto Princesa City"
    ],
    "name:pag_x_preferred":[
        "Puerto Princesa"
    ],
    "name:pam_x_preferred":[
        "Puerto Princesa"
    ],
    "name:pol_x_preferred":[
        "Puerto Princesa"
    ],
    "name:por_x_preferred":[
        "Puerto Princesa"
    ],
    "name:rus_x_preferred":[
        "\u041f\u0443\u044d\u0440\u0442\u043e-\u041f\u0440\u0438\u043d\u0441\u0435\u0441\u0430"
    ],
    "name:spa_x_preferred":[
        "Puerto Princesa"
    ],
    "name:swe_x_preferred":[
        "Puerto Princesa"
    ],
    "name:tgl_x_preferred":[
        "Puerto Princesa"
    ],
    "name:tha_x_preferred":[
        "\u0e1b\u0e39\u0e40\u0e27\u0e23\u0e4c\u0e42\u0e15\u0e1b\u0e23\u0e34\u0e19\u0e40\u0e0b\u0e0b\u0e32"
    ],
    "name:tur_x_preferred":[
        "Puerto Princesa"
    ],
    "name:ukr_x_preferred":[
        "\u041f\u0443\u0435\u0440\u0442\u043e-\u041f\u0440\u0438\u043d\u0441\u0435\u0441\u0430"
    ],
    "name:urd_x_preferred":[
        "\u067e\u0648\u0631\u062a\u0648 \u067e\u0631\u0646\u0633\u06cc\u0633\u0627"
    ],
    "name:urd_x_variant":[
        "\u067e\u0648\u06cc\u0631\u062a\u0648 \u067e\u0631\u0646\u0633\u06cc\u0633\u0627"
    ],
    "name:vie_x_preferred":[
        "Puerto Princesa"
    ],
    "name:war_x_preferred":[
        "Puerto Princesa"
    ],
    "name:zho_cn_x_preferred":[
        "\u666e\u6797\u585e\u8428\u6e2f"
    ],
    "name:zho_tw_x_preferred":[
        "\u516c\u4e3b\u6e2f"
    ],
    "name:zho_x_preferred":[
        "\u666e\u6797\u585e\u85a9\u6e2f"
    ],
    "wof:name":"Puerto Princesa",
    "wof:placetype":"locality"
},
  "geometry": {"coordinates":[122.8925,11.03361],"type":"Point"}
}