{
  "type": "Feature",
  "properties": {
    "gn:admin1_code":"05",
    "gn:admin2_code":"39",
    "gn:admin3_code":"54121000.0",
    "gn:asciiname":"Pulot",
    "gn:country_code":"PH",
    "gn:dem":96,
    "gn:feature_class":"P",
    "gn:feature_code":"PPL",
    "gn:name":"Pulot",
    "gn:population":0,
    "gn:timezone":"Asia/Manila",
    "iso:country":"PH",
    "name:fil_x_preferred":[
        "Pulot"
    ],
    "wof:name":"Pulot",
    "wof:placetype":"locality"
},
  "geometry": {"coordinates":[123.79179999999999,12.1071],"type":"Point"}
}