{
  "type": "Feature",
  "properties": {
    "gn:gn_country":"PH",
    "gn:gn_fcode":"PPL",
    "gn:gn_pop":3461,
    "gn:population":3461,
    "iso:country":"PH",
    "name:eng_x_preferred":[
        "Bawison"
    ],
    "name:unk_x_variant":[
        "Bawisan"
    ],
    "qs_pg:aaroncc":"PH",
    "qs_pg:gn_country":"PH",
    "qs_pg:gn_fcode":"PPL",
    "qs_pg:gn_pop":3461,
    "qs_pg:name":"Bawison",
    "qs_pg:photos_9r":0,
    "qs_pg:photos_sr":0,
    "qs_pg:pop_sr":4,
    "qs_pg:qs_pg_placetype":"locality",
    "wof:name":"Bawison",
    "wof:placetype":"locality",
    "wof:population":3461
},
  "geometry": {"coordinates":[120.8745,5.9375],"type":"Point"}
}