{
  "type": "Feature",
  "properties": {
    "gn:admin1_code":"06",
    "gn:admin2_code":"H3",
    "gn:admin3_code":"64522000.0",
    "gn:asciiname":"Kulo",
    "gn:country_code":"PH",
    "gn:dem":1,
    "gn:feature_class":"P",
    "gn:feature_code":"PPL",
    "gn:name":"Kulo",
    "gn:population":0,
    "gn:timezone":"Asia/Manila",
    "iso:country":"PH",
    "name:fil_x_preferred":[
        "Kulo"
    ],
    "name:und_x_variant":[
        "Culo"
    ],
    "wof:name":"Kulo",
    "wof:placetype":"locality"
},
  "geometry": {"coordinates":[122.82980000000001,10.5283],"type":"Point"}
}