{
  "type": "Feature",
  "properties": {
    "gn:admin1_code":"15",
    "gn:admin2_code":"01",
    "gn:admin3_code":"140115000.0",
    "gn:asciiname":"Manmanoc",
    "gn:country_code":"PH",
    "gn:dem":730,
    "gn:feature_class":"P",
    "gn:feature_code":"PPL",
    "gn:name":"Manmanoc",
    "gn:population":0,
    "gn:timezone":"Asia/Manila",
    "iso:country":"PH",
    "name:fil_x_preferred":[
        "Manmanoc"
    ],
    "wof:name":"Manmanoc",
    "wof:placetype":"locality"
},
  "geometry": {"coordinates":[121.0471,17.629],"type":"Point"}
}