{
  "type": "Feature",
  "properties": {
    "gn:country":"PH",
    "gn:fcode":"PPL",
    "gn:pop":2598,
    "iso:country":"PH",
    "name:fil_x_preferred":[
        "Alacaygan"
    ],
    "qs:name":"Alacaygan",
    "qs:photos_9r":0,
    "qs:photos_sr":0,
    "qs:pop_sr":"4",
    "wof:name":"Alacaygan",
    "wof:placetype":"locality",
    "wof:population":2598
},
  "geometry": {"coordinates":[123.0583,10.84014],"type":"Point"}
}