{
  "type": "Feature",
  "properties": {
    "gn:admin1_code":"40",
    "gn:admin2_code":"09",
    "gn:admin3_code":"41005000.0",
    "gn:asciiname":"Talahib",
    "gn:country_code":"PH",
    "gn:dem":19,
    "gn:feature_class":"P",
    "gn:feature_code":"PPL",
    "gn:name":"Talahib",
    "gn:population":0,
    "gn:timezone":"Asia/Manila",
    "iso:country":"PH",
    "name:eng_x_preferred":[
        "Talahib"
    ],
    "name:und_x_variant":[
        "Talahib Pandayan"
    ],
    "wof:name":"Talahib",
    "wof:placetype":"locality"
},
  "geometry": {"coordinates":[121.14360000000001,13.6396],"type":"Point"}
}