{
  "type": "Feature",
  "properties": {
    "gn:admin1_code":"05",
    "gn:admin2_code":"15",
    "gn:admin3_code":"51607000.0",
    "gn:asciiname":"Lapuguin",
    "gn:country_code":"PH",
    "gn:dem":0,
    "gn:feature_class":"P",
    "gn:feature_code":"PPL",
    "gn:name":"Lapuguin",
    "gn:population":0,
    "gn:timezone":"Asia/Manila",
    "iso:country":"PH",
    "name:fil_x_preferred":[
        "Lapuguin"
    ],
    "wof:name":"Lapuguin",
    "wof:placetype":"locality"
},
  "geometry": {"coordinates":[123.0637,13.9905],"type":"Point"}
}