{
  "type": "Feature",
  "properties": {
    "gn:admin1_code":"11",
    "gn:admin2_code":"25",
    "gn:admin3_code":"112402000.0",
    "gn:asciiname":"Kilate",
    "gn:country_code":"PH",
    "gn:dem":490,
    "gn:feature_class":"P",
    "gn:feature_code":"PPL",
    "gn:name":"Kilate",
    "gn:population":0,
    "gn:timezone":"Asia/Manila",
    "iso:country":"PH",
    "name:fil_x_preferred":[
        "Kilate"
    ],
    "wof:name":"Kilate",
    "wof:placetype":"locality"
},
  "geometry": {"coordinates":[125.42667,7.04694],"type":"Point"}
}