{
  "type": "Feature",
  "properties": {
    "gn:admin1_code":"06",
    "gn:admin2_code":"06",
    "gn:admin3_code":"60609000.0",
    "gn:asciiname":"Mauno",
    "gn:country_code":"PH",
    "gn:dem":14,
    "gn:feature_class":"P",
    "gn:feature_code":"PPL",
    "gn:name":"Mauno",
    "gn:population":0,
    "gn:timezone":"Asia/Manila",
    "iso:country":"PH",
    "name:deu_x_preferred":[
        "Mauno"
    ],
    "name:fil_x_preferred":[
        "Mauno"
    ],
    "name:fin_x_preferred":[
        "Mauno"
    ],
    "wof:name":"Mauno",
    "wof:placetype":"locality"
},
  "geometry": {"coordinates":[122.0389,11.1617],"type":"Point"}
}