{
  "type": "Feature",
  "properties": {
    "gn:admin1_code":"08",
    "gn:admin2_code":"37",
    "gn:admin3_code":"83723000.0",
    "gn:asciiname":"Daro",
    "gn:country_code":"PH",
    "gn:dem":207,
    "gn:feature_class":"P",
    "gn:feature_code":"PPL",
    "gn:name":"Daro",
    "gn:population":0,
    "gn:timezone":"Asia/Manila",
    "iso:country":"PH",
    "name:fil_x_preferred":[
        "Daro"
    ],
    "wof:name":"Daro",
    "wof:placetype":"locality"
},
  "geometry": {"coordinates":[124.74861,11.17944],"type":"Point"}
}