{
  "type": "Feature",
  "properties": {
    "gn:admin1_code":"07",
    "gn:admin2_code":"46",
    "gn:admin3_code":"74612000.0",
    "gn:asciiname":"Bonga",
    "gn:country_code":"PH",
    "gn:dem":45,
    "gn:feature_class":"P",
    "gn:feature_code":"PPL",
    "gn:name":"Bonga",
    "gn:population":0,
    "gn:timezone":"Asia/Manila",
    "iso:country":"PH",
    "name:amh_x_preferred":[
        "\u1266\u1295\u130b"
    ],
    "name:deu_x_preferred":[
        "Bonga"
    ],
    "name:fil_x_preferred":[
        "Bonga"
    ],
    "name:fra_x_preferred":[
        "Bonga"
    ],
    "name:ita_x_preferred":[
        "Bonga"
    ],
    "name:pol_x_preferred":[
        "Bonga"
    ],
    "name:ron_x_preferred":[
        "Bonga"
    ],
    "name:rus_x_preferred":[
        "\u0411\u043e\u043d\u0433\u0430"
    ],
    "wof:name":"Bonga",
    "wof:placetype":"locality"
},
  "geometry": {"coordinates":[123.20569999999999,9.9928],"type":"Point"}
}