{
  "type": "Feature",
  "properties": {
    "gn:admin1_code":"03",
    "gn:admin2_code":"13",
    "gn:admin3_code":"31402000.0",
    "gn:asciiname":"Balagtas Municipal Hall",
    "gn:country_code":"PH",
    "gn:dem":8,
    "gn:feature_class":"P",
    "gn:feature_code":"PPL",
    "gn:name":"Balagtas Municipal Hall",
    "gn:population":0,
    "gn:timezone":"Asia/Manila",
    "iso:country":"PH",
    "wof:name":"Balagtas Municipal Hall",
    "wof:placetype":"locality"
},
  "geometry": {"coordinates":[120.90822,14.81758],"type":"Point"}
}