{
  "type": "Feature",
  "properties": {
    "gn:country":"PH",
    "gn:fcode":"PPL",
    "gn:pop":5321,
    "iso:country":"PH",
    "name:bcl_x_preferred":[
        "Infanta"
    ],
    "name:cat_x_preferred":[
        "Infanta"
    ],
    "name:deu_x_preferred":[
        "Infanta"
    ],
    "name:eng_x_preferred":[
        "Infanta"
    ],
    "name:fil_x_preferred":[
        "Infanta"
    ],
    "name:fra_x_preferred":[
        "Infanta"
    ],
    "name:ilo_x_preferred":[
        "Infanta"
    ],
    "name:ind_x_preferred":[
        "Infanta"
    ],
    "name:ita_x_preferred":[
        "Infanta"
    ],
    "name:nld_x_preferred":[
        "Infanta"
    ],
    "name:oci_x_preferred":[
        "Infanta"
    ],
    "name:pag_x_preferred":[
        "Infanta"
    ],
    "name:pam_x_preferred":[
        "Infanta"
    ],
    "name:swe_x_preferred":[
        "Infanta"
    ],
    "name:tgl_x_preferred":[
        "Infanta"
    ],
    "name:vie_x_preferred":[
        "Infanta"
    ],
    "name:war_x_preferred":[
        "Infanta"
    ],
    "name:zho_x_preferred":[
        "\u56e0\u51e1\u5854"
    ],
    "qs:name":"Infanta",
    "qs:photos_9r":0,
    "qs:photos_sr":0,
    "qs:pop_sr":"5",
    "wd:wordcount":1083,
    "wof:name":"Infanta",
    "wof:placetype":"locality",
    "wof:population":5321
},
  "geometry": {"coordinates":[121.64953,14.74495],"type":"Point"}
}