{
  "type": "Feature",
  "properties": {
    "gn:admin1_code":"41",
    "gn:admin2_code":"49",
    "gn:admin3_code":"175305000.0",
    "gn:asciiname":"Marangus",
    "gn:country_code":"PH",
    "gn:dem":10,
    "gn:feature_class":"P",
    "gn:feature_code":"PPL",
    "gn:name":"Marangus",
    "gn:population":0,
    "gn:timezone":"Asia/Manila",
    "iso:country":"PH",
    "name:und_x_variant":[
        "Marangas"
    ],
    "wof:name":"Marangus",
    "wof:placetype":"locality"
},
  "geometry": {"coordinates":[117.62141,8.65841],"type":"Point"}
}