{
  "type": "Feature",
  "properties": {
    "gn:country":"PH",
    "gn:fcode":"PPL",
    "gn:pop":4079,
    "iso:country":"PH",
    "name:fil_x_preferred":[
        "San Pedro"
    ],
    "qs:name":"San Pedro",
    "qs:photos_9r":0,
    "qs:photos_sr":0,
    "qs:pop_sr":"4",
    "wd:wordcount":654,
    "wof:name":"San Pedro",
    "wof:placetype":"locality",
    "wof:population":4079
},
  "geometry": {"coordinates":[126.5175,7.34194],"type":"Point"}
}