{
  "type": "Feature",
  "properties": {
    "gn:admin1_code":"05",
    "gn:admin2_code":"05",
    "gn:admin3_code":"50514000.0",
    "gn:asciiname":"Basud",
    "gn:country_code":"PH",
    "gn:dem":27,
    "gn:feature_class":"P",
    "gn:feature_code":"PPL",
    "gn:name":"Basud",
    "gn:population":0,
    "gn:timezone":"Asia/Manila",
    "iso:country":"PH",
    "name:bcl_x_preferred":[
        "Basud"
    ],
    "name:ceb_x_preferred":[
        "Basud"
    ],
    "name:deu_x_preferred":[
        "Basud"
    ],
    "name:fil_x_preferred":[
        "Basud"
    ],
    "name:fra_x_preferred":[
        "Basud"
    ],
    "name:gor_x_preferred":[
        "Basud"
    ],
    "name:ilo_x_preferred":[
        "Basud"
    ],
    "name:ind_x_preferred":[
        "Basud"
    ],
    "name:ita_x_preferred":[
        "Basud"
    ],
    "name:nld_x_preferred":[
        "Basud"
    ],
    "name:nor_x_preferred":[
        "Basud"
    ],
    "name:pag_x_preferred":[
        "Basud"
    ],
    "name:pam_x_preferred":[
        "Basud"
    ],
    "name:swe_x_preferred":[
        "Basud"
    ],
    "name:tgl_x_preferred":[
        "Basud"
    ],
    "name:und_x_variant":[
        "Basud-Obaliw"
    ],
    "name:war_x_preferred":[
        "Basud"
    ],
    "wof:name":"Basud",
    "wof:placetype":"locality"
},
  "geometry": {"coordinates":[123.49169999999999,13.2803],"type":"Point"}
}