{
  "type": "Feature",
  "properties": {
    "gn:admin1_code":"05",
    "gn:admin2_code":"05",
    "gn:admin3_code":"50514000.0",
    "gn:asciiname":"Basud",
    "gn:country_code":"PH",
    "gn:dem":27,
    "gn:feature_class":"P",
    "gn:feature_code":"PPL",
    "gn:name":"Basud",
    "gn:population":0,
    "gn:timezone":"Asia/Manila",
    "iso:country":"PH",
    "name:fil_x_preferred":[
        "Basud"
    ],
    "name:und_x_variant":[
        "Basud-Obaliw"
    ],
    "wof:name":"Basud",
    "wof:placetype":"locality"
},
  "geometry": {"coordinates":[123.49169999999999,13.2803],"type":"Point"}
}