{
  "type": "Feature",
  "properties": {
    "gn:admin1_code":"07",
    "gn:admin2_code":"21",
    "gn:admin3_code":"72203000.0",
    "gn:asciiname":"Cambinocot",
    "gn:country_code":"PH",
    "gn:dem":541,
    "gn:feature_class":"P",
    "gn:feature_code":"PPL",
    "gn:name":"Cambinocot",
    "gn:population":0,
    "gn:timezone":"Asia/Manila",
    "iso:country":"PH",
    "name:fil_x_preferred":[
        "Cambinocot"
    ],
    "wof:name":"Cambinocot",
    "wof:placetype":"locality"
},
  "geometry": {"coordinates":[123.38030000000001,9.7393],"type":"Point"}
}