{
  "type": "Feature",
  "properties": {
    "gn:gn_country":"PH",
    "gn:gn_fcode":"PPLA3",
    "gn:gn_pop":12734,
    "gn:population":12734,
    "iso:country":"PH",
    "name:bcl_x_preferred":[
        "Urbiztondo"
    ],
    "name:cat_x_preferred":[
        "Urbiztondo"
    ],
    "name:dut_x_preferred":[
        "Urbiztondo"
    ],
    "name:eng_x_preferred":[
        "Urbiztondo"
    ],
    "name:fil_x_preferred":[
        "Urbiztondo"
    ],
    "name:fre_x_preferred":[
        "Urbiztondo"
    ],
    "name:ger_x_preferred":[
        "Urbiztondo"
    ],
    "name:ilo_x_preferred":[
        "Urbiztondo"
    ],
    "name:ind_x_preferred":[
        "Urbiztondo"
    ],
    "name:ita_x_preferred":[
        "Urbiztondo"
    ],
    "name:jpn_x_preferred":[
        "\u30a6\u30eb\u30d3\u30b9\u30c8\u30f3\u30c9"
    ],
    "name:oci_x_preferred":[
        "Urbiztondo"
    ],
    "name:pag_x_preferred":[
        "Urbiztondo"
    ],
    "name:pam_x_preferred":[
        "Urbiztondo"
    ],
    "name:spa_x_preferred":[
        "Urbiztondo"
    ],
    "name:swe_x_preferred":[
        "Urbiztondo"
    ],
    "name:tgl_x_preferred":[
        "Urbiztondo"
    ],
    "name:unk_x_variant":[
        "Urbistondo"
    ],
    "name:vie_x_preferred":[
        "Urbiztondo"
    ],
    "name:war_x_preferred":[
        "Urbiztondo"
    ],
    "qs_pg:aaroncc":"PH",
    "qs_pg:gn_country":"PH",
    "qs_pg:gn_fcode":"PPLA3",
    "qs_pg:gn_pop":12734,
    "qs_pg:name":"Urbiztondo",
    "qs_pg:photos_9r":0,
    "qs_pg:photos_sr":0,
    "qs_pg:pop_sr":6,
    "qs_pg:qs_pg_placetype":"locality",
    "wof:name":"Urbiztondo",
    "wof:placetype":"locality",
    "wof:population":12734
},
  "geometry": {"coordinates":[120.3295,15.8227],"type":"Point"}
}