{
  "type": "Feature",
  "properties": {
    "gn:admin1_code":"06",
    "gn:admin2_code":"18",
    "gn:admin3_code":"61901000.0",
    "gn:asciiname":"Tinaytayan",
    "gn:country_code":"PH",
    "gn:dem":29,
    "gn:feature_class":"P",
    "gn:feature_code":"PPL",
    "gn:name":"Tinaytayan",
    "gn:population":0,
    "gn:timezone":"Asia/Manila",
    "iso:country":"PH",
    "name:fil_x_preferred":[
        "Tinaytayan"
    ],
    "wof:name":"Tinaytayan",
    "wof:placetype":"locality"
},
  "geometry": {"coordinates":[122.6707,11.3072],"type":"Point"}
}