{
  "type": "Feature",
  "properties": {
    "gn:admin1_code":"41",
    "gn:admin2_code":"54",
    "gn:admin3_code":"175913000.0",
    "gn:asciiname":"Manabo",
    "gn:country_code":"PH",
    "gn:dem":13,
    "gn:feature_class":"P",
    "gn:feature_code":"PPL",
    "gn:name":"Manabo",
    "gn:population":0,
    "gn:timezone":"Asia/Manila",
    "iso:country":"PH",
    "name:bcl_x_preferred":[
        "Manabo"
    ],
    "name:ceb_x_preferred":[
        "Manabo"
    ],
    "name:deu_x_preferred":[
        "Manabo"
    ],
    "name:fil_x_preferred":[
        "Manabo"
    ],
    "name:fra_x_preferred":[
        "Manabo"
    ],
    "name:ilo_x_preferred":[
        "Manabo"
    ],
    "name:ind_x_preferred":[
        "Manabo"
    ],
    "name:ita_x_preferred":[
        "Manabo"
    ],
    "name:msa_x_preferred":[
        "Manabo"
    ],
    "name:nld_x_preferred":[
        "Manabo"
    ],
    "name:pag_x_preferred":[
        "Manabo"
    ],
    "name:pam_x_preferred":[
        "Manabo"
    ],
    "name:spa_x_preferred":[
        "Manabo"
    ],
    "name:swe_x_preferred":[
        "Manabo"
    ],
    "name:tgl_x_preferred":[
        "Manabo"
    ],
    "name:urd_x_preferred":[
        "\u0645\u0627\u0646\u0627\u0628\u0648"
    ],
    "name:vie_x_preferred":[
        "Manabo"
    ],
    "name:war_x_preferred":[
        "Manabo"
    ],
    "wof:name":"Manabo",
    "wof:placetype":"locality"
},
  "geometry": {"coordinates":[122.57771,12.31764],"type":"Point"}
}