{
  "type": "Feature",
  "properties": {
    "gn:admin1_code":"05",
    "gn:admin2_code":"15",
    "gn:admin3_code":"51604000.0",
    "gn:asciiname":"Potot",
    "gn:country_code":"PH",
    "gn:dem":49,
    "gn:feature_class":"P",
    "gn:feature_code":"PPL",
    "gn:name":"Potot",
    "gn:population":0,
    "gn:timezone":"Asia/Manila",
    "iso:country":"PH",
    "name:fil_x_preferred":[
        "Potot"
    ],
    "wof:name":"Potot",
    "wof:placetype":"locality"
},
  "geometry": {"coordinates":[122.91667,14.05],"type":"Point"}
}