{
  "type": "Feature",
  "properties": {
    "gn:admin1_code":"11",
    "gn:admin2_code":"I6",
    "gn:admin3_code":"118209000.0",
    "gn:asciiname":"Mandaya Clearing's",
    "gn:country_code":"PH",
    "gn:dem":80,
    "gn:feature_class":"P",
    "gn:feature_code":"PPL",
    "gn:name":"Mandaya Clearing\u2019s",
    "gn:population":0,
    "gn:timezone":"Asia/Manila",
    "iso:country":"PH",
    "name:eng_x_preferred":[
        "Mandaya Clearing\u2019s"
    ],
    "wof:name":"Mandaya Clearing's",
    "wof:placetype":"locality"
},
  "geometry": {"coordinates":[126.0347,7.6081],"type":"Point"}
}