{
  "type": "Feature",
  "properties": {
    "gn:admin1_code":"05",
    "gn:admin2_code":"16",
    "gn:admin3_code":"51736000.0",
    "gn:asciiname":"Mabalodbalod",
    "gn:country_code":"PH",
    "gn:dem":85,
    "gn:feature_class":"P",
    "gn:feature_code":"PPL",
    "gn:name":"Mabalodbalod",
    "gn:population":0,
    "gn:timezone":"Asia/Manila",
    "iso:country":"PH",
    "name:fil_x_preferred":[
        "Mabalodbalod"
    ],
    "name:und_x_variant":[
        "Malodbalod",
        "Mabaludbalud",
        "Mabalodbalod",
        "Mabaludbalod"
    ],
    "wof:name":"Mabalodbalod",
    "wof:placetype":"locality"
},
  "geometry": {"coordinates":[123.4554,13.5888],"type":"Point"}
}