{
  "type": "Feature",
  "properties": {
    "gn:admin1_code":"11",
    "gn:admin2_code":"I7",
    "gn:admin3_code":"112303000.0",
    "gn:asciiname":"Mabawos",
    "gn:country_code":"PH",
    "gn:dem":5,
    "gn:feature_class":"P",
    "gn:feature_code":"PPL",
    "gn:name":"Mabawos",
    "gn:population":0,
    "gn:timezone":"Asia/Manila",
    "iso:country":"PH",
    "name:fil_x_preferred":[
        "Mabawos"
    ],
    "wof:name":"Mabawos",
    "wof:placetype":"locality"
},
  "geometry": {"coordinates":[125.73917,7.39722],"type":"Point"}
}