{
  "type": "Feature",
  "properties": {
    "gn:country":"PH",
    "gn:fcode":"PPL",
    "gn:pop":7263,
    "iso:country":"PH",
    "name:fil_x_preferred":[
        "Patin-ay"
    ],
    "qs:name":"Patin-ay",
    "qs:photos_9r":0,
    "qs:photos_sr":0,
    "qs:pop_sr":"5",
    "wof:name":"Patin-ay",
    "wof:placetype":"locality",
    "wof:population":7263
},
  "geometry": {"coordinates":[125.93722,8.55056],"type":"Point"}
}