{
  "type": "Feature",
  "properties": {
    "gn:admin1_code":"01",
    "gn:admin2_code":"36",
    "gn:admin3_code":"13320000.0",
    "gn:asciiname":"Ortega",
    "gn:country_code":"PH",
    "gn:dem":43,
    "gn:feature_class":"P",
    "gn:feature_code":"PPL",
    "gn:name":"Ortega",
    "gn:population":0,
    "gn:timezone":"Asia/Manila",
    "iso:country":"PH",
    "name:fil_x_preferred":[
        "Ortega"
    ],
    "wof:name":"Ortega",
    "wof:placetype":"locality"
},
  "geometry": {"coordinates":[120.4376,16.3693],"type":"Point"}
}