{
  "type": "Feature",
  "properties": {
    "gn:admin1_code":"08",
    "gn:admin2_code":"37",
    "gn:admin3_code":"83708000.0",
    "gn:asciiname":"Maslog",
    "gn:country_code":"PH",
    "gn:dem":8,
    "gn:feature_class":"P",
    "gn:feature_code":"PPL",
    "gn:name":"Maslog",
    "gn:population":0,
    "gn:timezone":"Asia/Manila",
    "iso:country":"PH",
    "name:fil_x_preferred":[
        "Maslog"
    ],
    "name:und_x_variant":[
        "Maslug",
        "Maslog"
    ],
    "wof:name":"Maslog",
    "wof:placetype":"locality"
},
  "geometry": {"coordinates":[124.7659,10.5804],"type":"Point"}
}