{
  "type": "Feature",
  "properties": {
    "gn:admin1_code":"03",
    "gn:admin2_code":"13",
    "gn:admin3_code":"31406000.0",
    "gn:asciiname":"Bonga Menor",
    "gn:country_code":"PH",
    "gn:dem":24,
    "gn:feature_class":"P",
    "gn:feature_code":"PPL",
    "gn:name":"Bonga Menor",
    "gn:population":0,
    "gn:timezone":"Asia/Manila",
    "iso:country":"PH",
    "name:und_x_variant":[
        "Bunga Menor",
        "Bonga",
        "Bonga Menor"
    ],
    "wof:name":"Bonga Menor",
    "wof:placetype":"locality"
},
  "geometry": {"coordinates":[120.93062,14.94936],"type":"Point"}
}