{
  "type": "Feature",
  "properties": {
    "gn:admin1_code":"15",
    "gn:admin2_code":"44",
    "gn:admin3_code":"144406000.0",
    "gn:asciiname":"Butigue",
    "gn:country_code":"PH",
    "gn:dem":141,
    "gn:feature_class":"P",
    "gn:feature_code":"PPL",
    "gn:name":"Butigue",
    "gn:population":0,
    "gn:timezone":"Asia/Manila",
    "iso:country":"PH",
    "name:fil_x_preferred":[
        "Butigue"
    ],
    "wof:name":"Butigue",
    "wof:placetype":"locality"
},
  "geometry": {"coordinates":[121.45654,17.10514],"type":"Point"}
}