{
  "type": "Feature",
  "properties": {
    "gn:admin1_code":"41",
    "gn:admin2_code":"40",
    "gn:admin3_code":"175110000.0",
    "gn:asciiname":"Progreso",
    "gn:country_code":"PH",
    "gn:dem":19,
    "gn:feature_class":"P",
    "gn:feature_code":"PPL",
    "gn:name":"Progreso",
    "gn:population":0,
    "gn:timezone":"Asia/Manila",
    "iso:country":"PH",
    "name:cat_x_preferred":[
        "Progreso"
    ],
    "name:ceb_x_preferred":[
        "Progreso"
    ],
    "name:deu_x_preferred":[
        "Progreso"
    ],
    "name:epo_x_preferred":[
        "Progreso"
    ],
    "name:fil_x_preferred":[
        "Progreso"
    ],
    "name:fra_x_preferred":[
        "Progreso"
    ],
    "name:ina_x_preferred":[
        "Progreso"
    ],
    "name:jpn_x_preferred":[
        "\u30d7\u30ed\u30b0\u30ec\u30c3\u30bd"
    ],
    "name:nds_x_preferred":[
        "Progreso"
    ],
    "name:nld_x_preferred":[
        "Progreso"
    ],
    "name:pol_x_preferred":[
        "Progreso"
    ],
    "name:por_x_preferred":[
        "Progreso"
    ],
    "name:rus_x_preferred":[
        "\u041f\u0440\u043e\u0433\u0440\u0435\u0441\u043e"
    ],
    "name:sco_x_preferred":[
        "Progreso"
    ],
    "name:spa_x_preferred":[
        "Progreso"
    ],
    "name:srp_x_preferred":[
        "\u041f\u0440\u043e\u0433\u0440\u0435\u0441\u043e"
    ],
    "name:swe_x_preferred":[
        "Progreso"
    ],
    "wof:name":"Progreso",
    "wof:placetype":"locality"
},
  "geometry": {"coordinates":[121.07531000000002,12.41804],"type":"Point"}
}