{
  "type": "Feature",
  "properties": {
    "gn:admin1_code":"06",
    "gn:admin2_code":"30",
    "gn:admin3_code":"63035000.0",
    "gn:asciiname":"Cabunga",
    "gn:country_code":"PH",
    "gn:dem":72,
    "gn:feature_class":"P",
    "gn:feature_code":"PPL",
    "gn:name":"Cabu\u00f1ga",
    "gn:population":0,
    "gn:timezone":"Asia/Manila",
    "iso:country":"PH",
    "name:fil_x_preferred":[
        "Cabu\u00f1ga"
    ],
    "wof:name":"Cabunga",
    "wof:placetype":"locality"
},
  "geometry": {"coordinates":[122.61667,11.18333],"type":"Point"}
}