{
  "type": "Feature",
  "properties": {
    "gn:admin1_code":"40",
    "gn:admin2_code":"H2",
    "gn:admin3_code":"45649000.0",
    "gn:asciiname":"Kalilayan Ibaba",
    "gn:country_code":"PH",
    "gn:dem":45,
    "gn:feature_class":"P",
    "gn:feature_code":"PPL",
    "gn:name":"Kalilayan Ibaba",
    "gn:population":0,
    "gn:timezone":"Asia/Manila",
    "iso:country":"PH",
    "name:fil_x_preferred":[
        "Kalilayan Ibaba"
    ],
    "name:fil_x_variant":[
        "Ibabang Calilayan"
    ],
    "wof:name":"Kalilayan Ibaba",
    "wof:placetype":"locality"
},
  "geometry": {"coordinates":[121.97110000000001,13.84749],"type":"Point"}
}