{
  "type": "Feature",
  "properties": {
    "gn:country":"PH",
    "gn:fcode":"PPL",
    "gn:pop":3089,
    "iso:country":"PH",
    "name:fil_x_preferred":[
        "Hamoraon"
    ],
    "name:unk_x_variant":[
        "Jamoraon"
    ],
    "qs:name":"Hamoraon",
    "qs:photos_9r":0,
    "qs:photos_sr":0,
    "qs:pop_sr":"4",
    "wof:name":"Hamoraon",
    "wof:placetype":"locality",
    "wof:population":3089
},
  "geometry": {"coordinates":[123.55150999999999,12.22564],"type":"Point"}
}