{
  "type": "Feature",
  "properties": {
    "gn:admin1_code":"41",
    "gn:admin2_code":"41",
    "gn:admin3_code":"175214000.0",
    "gn:asciiname":"Ginhawa",
    "gn:country_code":"PH",
    "gn:dem":39,
    "gn:feature_class":"P",
    "gn:feature_code":"PPL",
    "gn:name":"Ginhawa",
    "gn:population":0,
    "gn:timezone":"Asia/Manila",
    "iso:country":"PH",
    "name:fil_x_preferred":[
        "Ginhawa"
    ],
    "wof:name":"Ginhawa",
    "wof:placetype":"locality"
},
  "geometry": {"coordinates":[121.36232,13.0753],"type":"Point"}
}