{
  "type": "Feature",
  "properties": {
    "gn:admin1_code":"06",
    "gn:admin2_code":"30",
    "gn:admin3_code":"63036000.0",
    "gn:asciiname":"Pandac",
    "gn:cc2":"PH",
    "gn:country_code":"PH",
    "gn:dem":15,
    "gn:feature_class":"P",
    "gn:feature_code":"PPL",
    "gn:name":"Pandac",
    "gn:population":0,
    "gn:timezone":"Asia/Manila",
    "iso:country":"PH",
    "name:und_x_variant":[
        "Panda",
        "Pandac"
    ],
    "wof:name":"Pandac",
    "wof:placetype":"locality"
},
  "geometry": {"coordinates":[122.51667,10.75],"type":"Point"}
}