{
  "type": "Feature",
  "properties": {
    "gn:admin1_code":"06",
    "gn:admin2_code":"06",
    "gn:admin3_code":"60608000.0",
    "gn:asciiname":"Bigaa",
    "gn:country_code":"PH",
    "gn:dem":8,
    "gn:feature_class":"P",
    "gn:feature_code":"PPL",
    "gn:name":"Bigaa",
    "gn:population":0,
    "gn:timezone":"Asia/Manila",
    "iso:country":"PH",
    "name:fil_x_preferred":[
        "Bigaa"
    ],
    "wof:name":"Bigaa",
    "wof:placetype":"locality"
},
  "geometry": {"coordinates":[121.9868,10.725],"type":"Point"}
}