{
  "type": "Feature",
  "properties": {
    "gn:admin1_code":"01",
    "gn:admin2_code":"28",
    "gn:admin3_code":"12816000.0",
    "gn:asciiname":"Cabagoan",
    "gn:country_code":"PH",
    "gn:dem":9,
    "gn:feature_class":"P",
    "gn:feature_code":"PPL",
    "gn:name":"Cabagoan",
    "gn:population":0,
    "gn:timezone":"Asia/Manila",
    "iso:country":"PH",
    "name:fil_x_preferred":[
        "Cabagoan"
    ],
    "wof:name":"Cabagoan",
    "wof:placetype":"locality"
},
  "geometry": {"coordinates":[120.51667,18.06667],"type":"Point"}
}