{
  "type": "Feature",
  "properties": {
    "gn:admin1_code":"01",
    "gn:admin2_code":"28",
    "gn:admin3_code":"12817000.0",
    "gn:asciiname":"Rantay",
    "gn:country_code":"PH",
    "gn:dem":12,
    "gn:feature_class":"P",
    "gn:feature_code":"PPL",
    "gn:name":"Rantay",
    "gn:population":0,
    "gn:timezone":"Asia/Manila",
    "iso:country":"PH",
    "name:fil_x_preferred":[
        "Rantay"
    ],
    "wof:name":"Rantay",
    "wof:placetype":"locality"
},
  "geometry": {"coordinates":[120.6041,18.318],"type":"Point"}
}