{
  "type": "Feature",
  "properties": {
    "gn:admin1_code":"02",
    "gn:admin2_code":"48",
    "gn:admin3_code":"25010000.0",
    "gn:asciiname":"Babadi",
    "gn:country_code":"PH",
    "gn:dem":1123,
    "gn:feature_class":"P",
    "gn:feature_code":"PPL",
    "gn:name":"Babadi",
    "gn:population":0,
    "gn:timezone":"Asia/Manila",
    "iso:country":"PH",
    "name:eng_x_preferred":[
        "Babadi"
    ],
    "name:und_x_variant":[
        "Babaddi"
    ],
    "wof:name":"Babadi",
    "wof:placetype":"locality"
},
  "geometry": {"coordinates":[120.9333,16.3837],"type":"Point"}
}