{
  "type": "Feature",
  "properties": {
    "gn:admin1_code":"05",
    "gn:admin2_code":"05",
    "gn:admin3_code":"50511000.0",
    "gn:asciiname":"Naghaso",
    "gn:country_code":"PH",
    "gn:dem":47,
    "gn:feature_class":"P",
    "gn:feature_code":"PPL",
    "gn:name":"Naghaso",
    "gn:population":0,
    "gn:timezone":"Asia/Manila",
    "iso:country":"PH",
    "name:eng_x_preferred":[
        "Naghaso"
    ],
    "wof:name":"Naghaso",
    "wof:placetype":"locality"
},
  "geometry": {"coordinates":[123.9049,13.1359],"type":"Point"}
}