{
  "type": "Feature",
  "properties": {
    "gn:admin1_code":"06",
    "gn:admin2_code":"30",
    "gn:admin3_code":"63025000.0",
    "gn:asciiname":"Puganan",
    "gn:country_code":"PH",
    "gn:dem":146,
    "gn:feature_class":"P",
    "gn:feature_code":"PPL",
    "gn:name":"Puganan",
    "gn:population":0,
    "gn:timezone":"Asia/Manila",
    "iso:country":"PH",
    "name:fil_x_preferred":[
        "Puganan"
    ],
    "name:und_x_variant":[
        "Pughanan"
    ],
    "wof:name":"Puganan",
    "wof:placetype":"locality"
},
  "geometry": {"coordinates":[122.44750999999999,11.03863],"type":"Point"}
}