{
  "type": "Feature",
  "properties": {
    "gn:admin1_code":"02",
    "gn:admin2_code":"31",
    "gn:admin3_code":"23114000.0",
    "gn:asciiname":"Villa Imelda",
    "gn:country_code":"PH",
    "gn:dem":113,
    "gn:feature_class":"P",
    "gn:feature_code":"PPL",
    "gn:name":"Villa Imelda",
    "gn:population":0,
    "gn:timezone":"Asia/Manila",
    "iso:country":"PH",
    "name:eng_x_preferred":[
        "Villa Imelda"
    ],
    "wof:name":"Villa Imelda",
    "wof:placetype":"locality"
},
  "geometry": {"coordinates":[122.01354000000001,17.10784],"type":"Point"}
}