{
  "type": "Feature",
  "properties": {
    "gn:admin1_code":"06",
    "gn:admin2_code":"30",
    "gn:admin3_code":"63038000.0",
    "gn:asciiname":"Pasi",
    "gn:country_code":"PH",
    "gn:dem":23,
    "gn:feature_class":"P",
    "gn:feature_code":"PPL",
    "gn:name":"Pasi",
    "gn:population":0,
    "gn:timezone":"Asia/Manila",
    "iso:country":"PH",
    "name:ceb_x_preferred":[
        "Pasi"
    ],
    "name:deu_x_preferred":[
        "Pasi"
    ],
    "name:fil_x_preferred":[
        "Pasi"
    ],
    "name:fin_x_preferred":[
        "Pasi"
    ],
    "name:ita_x_preferred":[
        "Pasi"
    ],
    "name:nld_x_preferred":[
        "Pasi"
    ],
    "name:swe_x_preferred":[
        "Pasi"
    ],
    "name:und_x_variant":[
        "Pase"
    ],
    "wof:name":"Pasi",
    "wof:placetype":"locality"
},
  "geometry": {"coordinates":[123.0737,11.295],"type":"Point"}
}