{
  "type": "Feature",
  "properties": {
    "gn:admin1_code":"01",
    "gn:admin2_code":"28",
    "gn:admin3_code":"12822000.0",
    "gn:asciiname":"Memang",
    "gn:country_code":"PH",
    "gn:dem":87,
    "gn:feature_class":"P",
    "gn:feature_code":"PPL",
    "gn:name":"Memang",
    "gn:population":0,
    "gn:timezone":"Asia/Manila",
    "iso:country":"PH",
    "name:fil_x_preferred":[
        "Memang"
    ],
    "wof:name":"Memang",
    "wof:placetype":"locality"
},
  "geometry": {"coordinates":[120.80575,18.10004],"type":"Point"}
}