{
  "type": "Feature",
  "properties": {
    "gn:country":"PH",
    "gn:fcode":"ADM3",
    "gn:pop":18504,
    "iso:country":"PH",
    "name:bcl_x_preferred":[
        "Tongkil"
    ],
    "name:ceb_x_preferred":[
        "Banguingui"
    ],
    "name:deu_x_preferred":[
        "Banguingui"
    ],
    "name:eng_x_preferred":[
        "Municipality of Tongkil"
    ],
    "name:eng_x_variant":[
        "Banguingui"
    ],
    "name:fil_x_preferred":[
        "Municipality Banguingui"
    ],
    "name:fra_x_preferred":[
        "Tongkil"
    ],
    "name:ilo_x_preferred":[
        "Banguingui"
    ],
    "name:ind_x_preferred":[
        "Banguingui"
    ],
    "name:ita_x_preferred":[
        "Tongkil"
    ],
    "name:nld_x_preferred":[
        "Tongkil"
    ],
    "name:pag_x_preferred":[
        "Banguingui"
    ],
    "name:pam_x_preferred":[
        "Tongkil"
    ],
    "name:sco_x_preferred":[
        "Banguingui"
    ],
    "name:swe_x_preferred":[
        "Bangulngi"
    ],
    "name:tgl_x_preferred":[
        "Banguingui"
    ],
    "name:unk_x_variant":[
        "Tongkil"
    ],
    "name:urd_x_preferred":[
        "\u0628\u0627\u0646\u06af\u0648\u06cc\u0646\u06af\u0648\u06cc"
    ],
    "name:vie_x_preferred":[
        "Tongkil"
    ],
    "name:war_x_preferred":[
        "Banguingui"
    ],
    "name:zho_x_preferred":[
        "\u73ed\u5409\u56e0\u5409"
    ],
    "qs:name":"Municipality of Tongkil",
    "qs:photos_9r":0,
    "qs:photos_sr":0,
    "qs:pop_sr":"6",
    "wd:wordcount":238,
    "wof:name":"Municipality of Tongkil",
    "wof:placetype":"localadmin",
    "wof:population":18504
},
  "geometry": {"coordinates":[121.76048,6.04551],"type":"Point"}
}