{
  "type": "Feature",
  "properties": {
    "gn:admin1_code":"07",
    "gn:admin2_code":"11",
    "gn:admin3_code":"71234000.0",
    "gn:asciiname":"Pamacsalan",
    "gn:country_code":"PH",
    "gn:dem":188,
    "gn:feature_class":"P",
    "gn:feature_code":"PPL",
    "gn:name":"Pamacsalan",
    "gn:population":0,
    "gn:timezone":"Asia/Manila",
    "iso:country":"PH",
    "name:fil_x_preferred":[
        "Pamacsalan"
    ],
    "wof:name":"Pamacsalan",
    "wof:placetype":"locality"
},
  "geometry": {"coordinates":[124.35193999999998,9.85861],"type":"Point"}
}