{
  "type": "Feature",
  "properties": {
    "gn:admin1_code":"12",
    "gn:admin2_code":"57",
    "gn:admin3_code":"124709000.0",
    "gn:asciiname":"Kiwanon",
    "gn:country_code":"PH",
    "gn:dem":42,
    "gn:feature_class":"P",
    "gn:feature_code":"PPL",
    "gn:name":"Kiwanon",
    "gn:population":0,
    "gn:timezone":"Asia/Manila",
    "iso:country":"PH",
    "name:fil_x_preferred":[
        "Kiwanon"
    ],
    "wof:name":"Kiwanon",
    "wof:placetype":"locality"
},
  "geometry": {"coordinates":[124.55972,7.20917],"type":"Point"}
}