{
  "type": "Feature",
  "properties": {
    "gn:admin1_code":"41",
    "gn:admin2_code":"49",
    "gn:admin3_code":"175309000.0",
    "gn:asciiname":"Cayancan",
    "gn:country_code":"PH",
    "gn:dem":35,
    "gn:feature_class":"P",
    "gn:feature_code":"PPL",
    "gn:name":"Cayancan",
    "gn:population":0,
    "gn:timezone":"Asia/Manila",
    "iso:country":"PH",
    "name:fil_x_preferred":[
        "Cayancan"
    ],
    "name:und_x_variant":[
        "Cayangcanan"
    ],
    "wof:name":"Cayancan",
    "wof:placetype":"locality"
},
  "geometry": {"coordinates":[120.0414,12.0073],"type":"Point"}
}