{
  "type": "Feature",
  "properties": {
    "gn:admin1_code":"13",
    "gn:admin2_code":"I9",
    "gn:admin3_code":"168505000.0",
    "gn:asciiname":"Buyo",
    "gn:country_code":"PH",
    "gn:dem":31,
    "gn:feature_class":"P",
    "gn:feature_code":"PPL",
    "gn:name":"Buyo",
    "gn:population":0,
    "gn:timezone":"Asia/Manila",
    "iso:country":"PH",
    "name:ceb_x_preferred":[
        "Buyo"
    ],
    "name:deu_x_preferred":[
        "Buyo"
    ],
    "name:fil_x_preferred":[
        "Buyo"
    ],
    "name:fra_x_preferred":[
        "Buyo"
    ],
    "name:rus_x_preferred":[
        "\u0411\u0443\u0439\u043e"
    ],
    "name:tgl_x_preferred":[
        "Buyo"
    ],
    "wof:name":"Buyo",
    "wof:placetype":"locality"
},
  "geometry": {"coordinates":[125.57850000000001,10.3409],"type":"Point"}
}