{
  "type": "Feature",
  "properties": {
    "gn:country":"PH",
    "gn:fcode":"PPL",
    "gn:population":3421,
    "iso:country":"PH",
    "name:und_x_variant":[
        "Jalavera"
    ],
    "qs:name":"Javalera",
    "qs:photos_9r":0,
    "qs:photos_sr":0,
    "qs:pop_sr":"4",
    "wof:name":"Javalera",
    "wof:placetype":"locality",
    "wof:population":3421
},
  "geometry": {"coordinates":[120.91661999999999,14.2549],"type":"Point"}
}