{
  "type": "Feature",
  "properties": {
    "gn:admin1_code":"06",
    "gn:admin2_code":"30",
    "gn:admin3_code":"63003000.0",
    "gn:asciiname":"Lamboy",
    "gn:country_code":"PH",
    "gn:dem":21,
    "gn:feature_class":"P",
    "gn:feature_code":"PPL",
    "gn:name":"Lamboy",
    "gn:population":0,
    "gn:timezone":"Asia/Manila",
    "iso:country":"PH",
    "name:fil_x_preferred":[
        "Lamboy"
    ],
    "wof:name":"Lamboy",
    "wof:placetype":"locality"
},
  "geometry": {"coordinates":[122.74222,10.96833],"type":"Point"}
}