{
  "type": "Feature",
  "properties": {
    "gn:admin1_code":"06",
    "gn:admin2_code":"06",
    "gn:admin3_code":"60609000.0",
    "gn:asciiname":"Virginia",
    "gn:country_code":"PH",
    "gn:dem":319,
    "gn:feature_class":"P",
    "gn:feature_code":"PPL",
    "gn:name":"Virginia",
    "gn:population":0,
    "gn:timezone":"Asia/Manila",
    "iso:country":"PH",
    "name:fil_x_preferred":[
        "Virginia"
    ],
    "wof:name":"Virginia",
    "wof:placetype":"locality"
},
  "geometry": {"coordinates":[122.13030000000001,11.1359],"type":"Point"}
}