{
  "type": "Feature",
  "properties": {
    "gn:country":"PH",
    "gn:fcode":"PPL",
    "gn:pop":2085,
    "iso:country":"PH",
    "name:fil_x_preferred":[
        "Da-an Sur"
    ],
    "name:unk_x_variant":[
        "Da-an"
    ],
    "qs:name":"Da-an Sur",
    "qs:photos_9r":0,
    "qs:photos_sr":0,
    "qs:pop_sr":"4",
    "wof:name":"Da-an Sur",
    "wof:placetype":"locality",
    "wof:population":2085
},
  "geometry": {"coordinates":[122.42019999999999,11.2612],"type":"Point"}
}