{
  "type": "Feature",
  "properties": {
    "gn:admin1_code":"14",
    "gn:admin2_code":"35",
    "gn:admin3_code":"153629000.0",
    "gn:asciiname":"Kayagan",
    "gn:country_code":"PH",
    "gn:dem":740,
    "gn:feature_class":"P",
    "gn:feature_code":"PPL",
    "gn:name":"Kayagan",
    "gn:population":0,
    "gn:timezone":"Asia/Manila",
    "iso:country":"PH",
    "name:fil_x_preferred":[
        "Kayagan"
    ],
    "wof:name":"Kayagan",
    "wof:placetype":"locality"
},
  "geometry": {"coordinates":[124.19101999999999,7.8823],"type":"Point"}
}