{
  "type": "Feature",
  "properties": {
    "gn:admin1_code":"12",
    "gn:admin2_code":"M9",
    "gn:admin3_code":"128004000.0",
    "gn:asciiname":"Bual",
    "gn:country_code":"PH",
    "gn:dem":17,
    "gn:feature_class":"P",
    "gn:feature_code":"PPL",
    "gn:name":"Bual",
    "gn:population":0,
    "gn:timezone":"Asia/Manila",
    "iso:country":"PH",
    "name:fil_x_preferred":[
        "Bual"
    ],
    "wof:name":"Bual",
    "wof:placetype":"locality"
},
  "geometry": {"coordinates":[124.92417,5.86389],"type":"Point"}
}