{
  "type": "Feature",
  "properties": {
    "gn:admin1_code":"NCR",
    "gn:admin2_code":"137600000",
    "gn:admin3_code":"137607000.0",
    "gn:asciiname":"Hagonoy",
    "gn:country_code":"PH",
    "gn:dem":4,
    "gn:feature_class":"P",
    "gn:feature_code":"PPL",
    "gn:name":"Hagonoy",
    "gn:population":0,
    "gn:timezone":"Asia/Manila",
    "iso:country":"PH",
    "name:ceb_x_preferred":[
        "Hagonoy"
    ],
    "name:deu_x_preferred":[
        "Hagonoy"
    ],
    "name:fra_x_preferred":[
        "Hagonoy"
    ],
    "name:ita_x_preferred":[
        "Hagonoy"
    ],
    "name:nld_x_preferred":[
        "Hagonoy"
    ],
    "name:nor_x_preferred":[
        "Hagonoy"
    ],
    "name:war_x_preferred":[
        "Hagonoy"
    ],
    "wof:name":"Hagonoy",
    "wof:placetype":"locality"
},
  "geometry": {"coordinates":[121.0788,14.5122],"type":"Point"}
}