{
  "type": "Feature",
  "properties": {
    "gn:admin1_code":"03",
    "gn:admin2_code":"64",
    "gn:admin3_code":"37112000.0",
    "gn:asciiname":"Namatacan",
    "gn:country_code":"PH",
    "gn:dem":31,
    "gn:feature_class":"P",
    "gn:feature_code":"PPL",
    "gn:name":"Namatacan",
    "gn:population":0,
    "gn:timezone":"Asia/Manila",
    "iso:country":"PH",
    "name:eng_x_preferred":[
        "Namatacan"
    ],
    "wof:name":"Namatacan",
    "wof:placetype":"locality"
},
  "geometry": {"coordinates":[120.13,14.999],"type":"Point"}
}