{
  "type": "Feature",
  "properties": {
    "gn:admin1_code":"02",
    "gn:admin2_code":"31",
    "gn:admin3_code":"23101000.0",
    "gn:asciiname":"Callao",
    "gn:country_code":"PH",
    "gn:dem":78,
    "gn:feature_class":"P",
    "gn:feature_code":"PPL",
    "gn:name":"Callao",
    "gn:population":0,
    "gn:timezone":"Asia/Manila",
    "iso:country":"PH",
    "name:fil_x_preferred":[
        "Callao"
    ],
    "wof:name":"Callao",
    "wof:placetype":"locality"
},
  "geometry": {"coordinates":[121.67513999999998,16.79196],"type":"Point"}
}