{
  "type": "Feature",
  "properties": {
    "gn:admin1_code":"02",
    "gn:admin2_code":"14",
    "gn:admin3_code":"21518000.0",
    "gn:asciiname":"Ziuanan",
    "gn:country_code":"PH",
    "gn:dem":72,
    "gn:feature_class":"P",
    "gn:feature_code":"PPL",
    "gn:name":"Ziuanan",
    "gn:population":0,
    "gn:timezone":"Asia/Manila",
    "iso:country":"PH",
    "name:und_x_variant":[
        "Zimigui-Ziuana",
        "Ziuanan"
    ],
    "wof:name":"Ziuanan",
    "wof:placetype":"locality"
},
  "geometry": {"coordinates":[121.28943999999998,18.43517],"type":"Point"}
}