{
  "type": "Feature",
  "properties": {
    "gn:admin1_code":"12",
    "gn:admin2_code":"57",
    "gn:admin3_code":"124704000.0",
    "gn:asciiname":"Ilian",
    "gn:country_code":"PH",
    "gn:dem":109,
    "gn:feature_class":"P",
    "gn:feature_code":"PPL",
    "gn:name":"Ilian",
    "gn:population":0,
    "gn:timezone":"Asia/Manila",
    "iso:country":"PH",
    "name:fil_x_preferred":[
        "Ilian"
    ],
    "wof:name":"Ilian",
    "wof:placetype":"locality"
},
  "geometry": {"coordinates":[124.995,7.03778],"type":"Point"}
}