{
  "type": "Feature",
  "properties": {
    "gn:admin1_code":"02",
    "gn:admin2_code":"31",
    "gn:admin3_code":"23132000.0",
    "gn:asciiname":"Salinungan East",
    "gn:country_code":"PH",
    "gn:dem":78,
    "gn:feature_class":"P",
    "gn:feature_code":"PPL",
    "gn:name":"Salinungan East",
    "gn:population":0,
    "gn:timezone":"Asia/Manila",
    "iso:country":"PH",
    "name:eng_x_preferred":[
        "Salinungan East"
    ],
    "wof:name":"Salinungan East",
    "wof:placetype":"locality"
},
  "geometry": {"coordinates":[121.62079,16.87381],"type":"Point"}
}