{
  "type": "Feature",
  "properties": {
    "iso:country":"PH",
    "name:bcl_x_preferred":[
        "Garcia Hernandez"
    ],
    "name:cbk_zam_x_preferred":[
        "Garcia Hernandez"
    ],
    "name:ceb_x_preferred":[
        "Garcia Hernandez"
    ],
    "name:deu_x_preferred":[
        "Garcia Hernandez"
    ],
    "name:eng_x_preferred":[
        "Garcia Hernandez"
    ],
    "name:fil_x_preferred":[
        "Garcia Hernandez"
    ],
    "name:fra_x_preferred":[
        "Garcia Hernandez"
    ],
    "name:ilo_x_preferred":[
        "Garcia Hernandez"
    ],
    "name:ind_x_preferred":[
        "Garcia Hernandez"
    ],
    "name:ita_x_preferred":[
        "Garcia Hernandez"
    ],
    "name:nld_x_preferred":[
        "Garcia Hernandez"
    ],
    "name:nob_x_preferred":[
        "Garcia Hernandez"
    ],
    "name:nor_x_preferred":[
        "Garcia Hernandez"
    ],
    "name:pag_x_preferred":[
        "Garcia Hernandez"
    ],
    "name:pam_x_preferred":[
        "Garcia Hernandez"
    ],
    "name:swe_x_preferred":[
        "Garcia Hernandez"
    ],
    "name:tgl_x_preferred":[
        "Garcia Hernandez"
    ],
    "name:unk_x_variant":[
        "Garcia"
    ],
    "name:vie_x_preferred":[
        "Garcia Hernandez"
    ],
    "name:war_x_preferred":[
        "Garcia Hernandez"
    ],
    "qs:gn_country":"PH",
    "qs:gn_fcode":"PPL",
    "qs:gn_pop":2643,
    "qs:name":"Garcia-Hernandez",
    "qs:name_adm0":"Philippines",
    "qs:name_adm1":"Central Visayas",
    "qs:photos":0,
    "qs:photos_1k":0,
    "qs:photos_9k":0,
    "qs:photos_9r":0,
    "qs:photos_all":0,
    "qs:photos_sr":0,
    "qs:placetype":"Town",
    "qs:pop_sr":"4",
    "qs:woe_adm0":23424934,
    "wd:wordcount":156,
    "wof:name":"Garcia-Hernandez",
    "wof:placetype":"locality",
    "wof:population":2643
},
  "geometry": {"coordinates":[124.2946,9.6144],"type":"Point"}
}