{
  "type": "Feature",
  "properties": {
    "gn:admin1_code":"02",
    "gn:admin2_code":"31",
    "gn:admin3_code":"23125000.0",
    "gn:asciiname":"Cutog Pequeno",
    "gn:country_code":"PH",
    "gn:dem":57,
    "gn:feature_class":"P",
    "gn:feature_code":"PPL",
    "gn:name":"Cutog Peque\u00f1o",
    "gn:population":0,
    "gn:timezone":"Asia/Manila",
    "iso:country":"PH",
    "wof:name":"Cutog Pequeno",
    "wof:placetype":"locality"
},
  "geometry": {"coordinates":[121.76309000000001,16.98033],"type":"Point"}
}