{
  "type": "Feature",
  "properties": {
    "gn:admin1_code":"15",
    "gn:admin2_code":"27",
    "gn:admin3_code":"142711000.0",
    "gn:asciiname":"Bayoccan",
    "gn:country_code":"PH",
    "gn:dem":884,
    "gn:feature_class":"P",
    "gn:feature_code":"PPL",
    "gn:name":"Bayoccan",
    "gn:population":0,
    "gn:timezone":"Asia/Manila",
    "iso:country":"PH",
    "name:fil_x_preferred":[
        "Bayoccan"
    ],
    "wof:name":"Bayoccan",
    "wof:placetype":"locality"
},
  "geometry": {"coordinates":[121.07093999999999,16.63238],"type":"Point"}
}