{
  "type": "Feature",
  "properties": {
    "gn:admin1_code":"07",
    "gn:admin2_code":"11",
    "gn:admin3_code":"71239000.0",
    "gn:asciiname":"Magsaysay",
    "gn:country_code":"PH",
    "gn:dem":150,
    "gn:feature_class":"P",
    "gn:feature_code":"PPL",
    "gn:name":"Magsaysay",
    "gn:population":0,
    "gn:timezone":"Asia/Manila",
    "iso:country":"PH",
    "name:fil_x_preferred":[
        "Magsaysay"
    ],
    "wof:name":"Magsaysay",
    "wof:placetype":"locality"
},
  "geometry": {"coordinates":[124.05311,9.74297],"type":"Point"}
}