{
  "type": "Feature",
  "properties": {
    "gn:admin1_code":"41",
    "gn:admin2_code":"41",
    "gn:admin3_code":"175204000.0",
    "gn:asciiname":"Binaliw",
    "gn:country_code":"PH",
    "gn:dem":230,
    "gn:feature_class":"P",
    "gn:feature_code":"PPL",
    "gn:name":"Binaliw",
    "gn:population":0,
    "gn:timezone":"Asia/Manila",
    "iso:country":"PH",
    "name:fil_x_preferred":[
        "Binaliw"
    ],
    "wof:name":"Binaliw",
    "wof:placetype":"locality"
},
  "geometry": {"coordinates":[121.24722,12.27472],"type":"Point"}
}