{
  "type": "Feature",
  "properties": {
    "gn:admin1_code":"40",
    "gn:admin2_code":"33",
    "gn:admin3_code":"43408000.0",
    "gn:asciiname":"Cuevang Bato",
    "gn:country_code":"PH",
    "gn:dem":259,
    "gn:feature_class":"P",
    "gn:feature_code":"PPL",
    "gn:name":"Cuevang Bato",
    "gn:population":0,
    "gn:timezone":"Asia/Manila",
    "iso:country":"PH",
    "name:fil_x_preferred":[
        "Cuevang Bato"
    ],
    "wof:name":"Cuevang Bato",
    "wof:placetype":"locality"
},
  "geometry": {"coordinates":[121.4616,14.4883],"type":"Point"}
}