{
  "type": "Feature",
  "properties": {
    "gn:admin1_code":"10",
    "gn:admin2_code":"12",
    "gn:admin3_code":"101301000.0",
    "gn:asciiname":"Daco",
    "gn:country_code":"PH",
    "gn:dem":391,
    "gn:feature_class":"P",
    "gn:feature_code":"PPL",
    "gn:name":"Daco",
    "gn:population":0,
    "gn:timezone":"Asia/Manila",
    "iso:country":"PH",
    "name:fil_x_preferred":[
        "Daco"
    ],
    "wof:name":"Daco",
    "wof:placetype":"locality"
},
  "geometry": {"coordinates":[124.64361,8.28139],"type":"Point"}
}