{
  "type": "Feature",
  "properties": {
    "gn:admin1_code":"40",
    "gn:admin2_code":"53",
    "gn:admin3_code":"45808000.0",
    "gn:asciiname":"Amityville",
    "gn:country_code":"PH",
    "gn:dem":83,
    "gn:feature_class":"P",
    "gn:feature_code":"PPL",
    "gn:name":"Amityville",
    "gn:population":0,
    "gn:timezone":"Asia/Manila",
    "iso:country":"PH",
    "name:fil_x_preferred":[
        "Amitty Ville"
    ],
    "wof:name":"Amityville",
    "wof:placetype":"locality"
},
  "geometry": {"coordinates":[121.12967,14.75092],"type":"Point"}
}