{
  "type": "Feature",
  "properties": {
    "gn:admin1_code":"09",
    "gn:admin2_code":"66",
    "gn:admin3_code":"97302000.0",
    "gn:asciiname":"Monte Alegre",
    "gn:country_code":"PH",
    "gn:dem":291,
    "gn:feature_class":"P",
    "gn:feature_code":"PPL",
    "gn:name":"Monte Alegre",
    "gn:population":0,
    "gn:timezone":"Asia/Manila",
    "iso:country":"PH",
    "name:eng_x_preferred":[
        "Monte Alegre"
    ],
    "wof:name":"Monte Alegre",
    "wof:placetype":"locality"
},
  "geometry": {"coordinates":[123.53100000000001,7.9612],"type":"Point"}
}