{
  "type": "Feature",
  "properties": {
    "gn:admin1_code":"09",
    "gn:admin2_code":"66",
    "gn:admin3_code":"97302000.0",
    "gn:asciiname":"Monte Alegre",
    "gn:country_code":"PH",
    "gn:dem":291,
    "gn:feature_class":"P",
    "gn:feature_code":"PPL",
    "gn:name":"Monte Alegre",
    "gn:population":0,
    "gn:timezone":"Asia/Manila",
    "iso:country":"PH",
    "name:bpy_x_preferred":[
        "\u09ae\u09cb\u09a8\u09cd\u099f\u09c7 \u0986\u09b2\u09c7\u0997\u09cd\u09b0\u09c7"
    ],
    "name:ceb_x_preferred":[
        "Monte Alegre"
    ],
    "name:deu_x_preferred":[
        "Monte Alegre"
    ],
    "name:eng_x_preferred":[
        "Monte Alegre"
    ],
    "name:fra_x_preferred":[
        "Monte Alegre"
    ],
    "name:ita_x_preferred":[
        "Monte Alegre"
    ],
    "name:nld_x_preferred":[
        "Monte Alegre"
    ],
    "name:nor_x_preferred":[
        "Monte Alegre"
    ],
    "name:por_x_preferred":[
        "Monte Alegre"
    ],
    "name:srp_x_preferred":[
        "\u041c\u043e\u043d\u0442\u0435 \u0410\u043b\u0435\u0433\u0440\u0435"
    ],
    "name:swe_x_preferred":[
        "Monte Alegre"
    ],
    "name:vie_x_preferred":[
        "Monte Alegre"
    ],
    "name:vol_x_preferred":[
        "Monte Alegre"
    ],
    "wof:name":"Monte Alegre",
    "wof:placetype":"locality"
},
  "geometry": {"coordinates":[123.53100000000001,7.9612],"type":"Point"}
}