{
  "type": "Feature",
  "properties": {
    "gn:admin1_code":"08",
    "gn:admin2_code":"59",
    "gn:admin3_code":"86407000.0",
    "gn:asciiname":"Isagani",
    "gn:country_code":"PH",
    "gn:dem":40,
    "gn:feature_class":"P",
    "gn:feature_code":"PPL",
    "gn:name":"Isagani",
    "gn:population":0,
    "gn:timezone":"Asia/Manila",
    "iso:country":"PH",
    "name:fil_x_preferred":[
        "Isagani"
    ],
    "wof:name":"Isagani",
    "wof:placetype":"locality"
},
  "geometry": {"coordinates":[124.86667,10.13333],"type":"Point"}
}