{
  "type": "Feature",
  "properties": {
    "gn:admin1_code":"40",
    "gn:admin2_code":"09",
    "gn:admin3_code":"41003000.0",
    "gn:asciiname":"Tanggoy",
    "gn:country_code":"PH",
    "gn:dem":35,
    "gn:feature_class":"P",
    "gn:feature_code":"PPL",
    "gn:name":"Tanggoy",
    "gn:population":0,
    "gn:timezone":"Asia/Manila",
    "iso:country":"PH",
    "name:fil_x_preferred":[
        "Tanggoy"
    ],
    "wof:name":"Tanggoy",
    "wof:placetype":"locality"
},
  "geometry": {"coordinates":[120.6763,13.9495],"type":"Point"}
}