{
  "type": "Feature",
  "properties": {
    "gn:country":"PH",
    "gn:fcode":"PPL",
    "gn:pop":2927,
    "iso:country":"PH",
    "name:fil_x_preferred":[
        "Pung-Pang"
    ],
    "name:unk_x_variant":[
        "Pongpong"
    ],
    "qs:name":"Pung-Pang",
    "qs:photos_9r":0,
    "qs:photos_sr":0,
    "qs:pop_sr":"4",
    "wof:name":"Pung-Pang",
    "wof:placetype":"locality",
    "wof:population":2927
},
  "geometry": {"coordinates":[125.46333,6.4975],"type":"Point"}
}