{
  "type": "Feature",
  "properties": {
    "gn:admin1_code":"41",
    "gn:admin2_code":"40",
    "gn:admin3_code":"175103000.0",
    "gn:asciiname":"Tolingonan",
    "gn:country_code":"PH",
    "gn:dem":14,
    "gn:feature_class":"P",
    "gn:feature_code":"PPL",
    "gn:name":"Tolingonan",
    "gn:population":0,
    "gn:timezone":"Asia/Manila",
    "iso:country":"PH",
    "name:fil_x_preferred":[
        "Tolingonan"
    ],
    "wof:name":"Tolingonan",
    "wof:placetype":"locality"
},
  "geometry": {"coordinates":[120.4126,13.6497],"type":"Point"}
}