{
  "type": "Feature",
  "properties": {
    "gn:country":"PH",
    "gn:fcode":"PPL",
    "gn:population":2817,
    "iso:country":"PH",
    "name:und_x_variant":[
        "Balutakai"
    ],
    "qs:name":"Balutakay",
    "qs:photos_9r":0,
    "qs:photos_sr":0,
    "qs:pop_sr":"4",
    "wof:name":"Balutakay",
    "wof:placetype":"locality",
    "wof:population":2817
},
  "geometry": {"coordinates":[125.35167,6.72111],"type":"Point"}
}