{
  "type": "Feature",
  "properties": {
    "gn:admin1_code":"01",
    "gn:admin2_code":"51",
    "gn:admin3_code":"15517000.0",
    "gn:asciiname":"Songkoy",
    "gn:country_code":"PH",
    "gn:dem":13,
    "gn:feature_class":"P",
    "gn:feature_code":"PPL",
    "gn:name":"Songkoy",
    "gn:population":0,
    "gn:timezone":"Asia/Manila",
    "iso:country":"PH",
    "name:fil_x_preferred":[
        "Sonkoy"
    ],
    "wof:name":"Songkoy",
    "wof:placetype":"locality"
},
  "geometry": {"coordinates":[120.37824999999999,15.96646],"type":"Point"}
}