{
  "type": "Feature",
  "properties": {
    "gn:admin1_code":"03",
    "gn:admin2_code":"47",
    "gn:admin3_code":"34930000.0",
    "gn:asciiname":"Baluga",
    "gn:country_code":"PH",
    "gn:dem":42,
    "gn:feature_class":"P",
    "gn:feature_code":"PPL",
    "gn:name":"Baluga",
    "gn:population":0,
    "gn:timezone":"Asia/Manila",
    "iso:country":"PH",
    "name:fil_x_preferred":[
        "Baluga"
    ],
    "name:fil_x_variant":[
        "Balula"
    ],
    "name:fra_x_preferred":[
        "Baluga"
    ],
    "name:slv_x_preferred":[
        "Baluga"
    ],
    "wof:name":"Baluga",
    "wof:placetype":"locality"
},
  "geometry": {"coordinates":[120.9478,15.5619],"type":"Point"}
}