{
  "type": "Feature",
  "properties": {
    "gn:admin1_code":"13",
    "gn:admin2_code":"61",
    "gn:admin3_code":"166722000.0",
    "gn:asciiname":"Tagbayani",
    "gn:cc2":"PH",
    "gn:country_code":"PH",
    "gn:dem":96,
    "gn:feature_class":"P",
    "gn:feature_code":"PPL",
    "gn:name":"Tagbayani",
    "gn:population":0,
    "gn:timezone":"Asia/Manila",
    "iso:country":"PH",
    "name:und_x_variant":[
        "Tagbiyani",
        "Tagbayani"
    ],
    "wof:name":"Tagbayani",
    "wof:placetype":"locality"
},
  "geometry": {"coordinates":[125.48278000000001,9.65111],"type":"Point"}
}