{
  "type": "Feature",
  "properties": {
    "gn:admin1_code":"03",
    "gn:admin2_code":"50",
    "gn:admin3_code":"35405000.0",
    "gn:asciiname":"Pescadores",
    "gn:country_code":"PH",
    "gn:dem":13,
    "gn:feature_class":"P",
    "gn:feature_code":"PPL",
    "gn:name":"Pescadores",
    "gn:population":0,
    "gn:timezone":"Asia/Manila",
    "iso:country":"PH",
    "name:fil_x_preferred":[
        "Pescadores"
    ],
    "wof:name":"Pescadores",
    "wof:placetype":"locality"
},
  "geometry": {"coordinates":[120.81938,15.09195],"type":"Point"}
}