{
  "type": "Feature",
  "properties": {
    "gn:admin1_code":"41",
    "gn:admin2_code":"40",
    "gn:admin3_code":"175104000.0",
    "gn:asciiname":"Pampang",
    "gn:country_code":"PH",
    "gn:dem":39,
    "gn:feature_class":"P",
    "gn:feature_code":"PPL",
    "gn:name":"Pampang",
    "gn:population":0,
    "gn:timezone":"Asia/Manila",
    "iso:country":"PH",
    "name:fil_x_preferred":[
        "Pampang"
    ],
    "wof:name":"Pampang",
    "wof:placetype":"locality"
},
  "geometry": {"coordinates":[120.11667,13.81667],"type":"Point"}
}