{
  "type": "Feature",
  "properties": {
    "gn:admin1_code":"01",
    "gn:admin2_code":"51",
    "gn:admin3_code":"15522000.0",
    "gn:asciiname":"Namolan",
    "gn:country_code":"PH",
    "gn:dem":6,
    "gn:feature_class":"P",
    "gn:feature_code":"PPL",
    "gn:name":"Namolan",
    "gn:population":0,
    "gn:timezone":"Asia/Manila",
    "iso:country":"PH",
    "name:fil_x_preferred":[
        "Namolan"
    ],
    "wof:name":"Namolan",
    "wof:placetype":"locality"
},
  "geometry": {"coordinates":[120.24284,16.01672],"type":"Point"}
}