{
  "type": "Feature",
  "properties": {
    "gn:admin1_code":"40",
    "gn:admin2_code":"H2",
    "gn:admin3_code":"45634000.0",
    "gn:asciiname":"Sumag Norte",
    "gn:country_code":"PH",
    "gn:dem":63,
    "gn:feature_class":"P",
    "gn:feature_code":"PPL",
    "gn:name":"Sumag Norte",
    "gn:population":0,
    "gn:timezone":"Asia/Manila",
    "iso:country":"PH",
    "name:fil_x_preferred":[
        "Sumag"
    ],
    "wof:name":"Sumag Norte",
    "wof:placetype":"locality"
},
  "geometry": {"coordinates":[122.05759999999999,13.7933],"type":"Point"}
}