{
  "type": "Feature",
  "properties": {
    "gn:admin1_code":"41",
    "gn:admin2_code":"49",
    "gn:admin3_code":"175322000.0",
    "gn:asciiname":"Balolo",
    "gn:country_code":"PH",
    "gn:dem":11,
    "gn:feature_class":"P",
    "gn:feature_code":"PPL",
    "gn:name":"Balolo",
    "gn:population":0,
    "gn:timezone":"Asia/Manila",
    "iso:country":"PH",
    "name:fil_x_preferred":[
        "Balolo"
    ],
    "name:und_x_variant":[
        "Balola"
    ],
    "wof:name":"Balolo",
    "wof:placetype":"locality"
},
  "geometry": {"coordinates":[119.8498,11.9723],"type":"Point"}
}