{
  "type": "Feature",
  "properties": {
    "gn:admin1_code":"41",
    "gn:admin2_code":"49",
    "gn:admin3_code":"175313000.0",
    "gn:asciiname":"Agutayandilit",
    "gn:country_code":"PH",
    "gn:dem":5,
    "gn:feature_class":"P",
    "gn:feature_code":"PPL",
    "gn:name":"Agutayandilit",
    "gn:population":0,
    "gn:timezone":"Asia/Manila",
    "iso:country":"PH",
    "name:fil_x_preferred":[
        "Agutayandilit"
    ],
    "name:und_x_variant":[
        "Agutayandelic"
    ],
    "wof:name":"Agutayandilit",
    "wof:placetype":"locality"
},
  "geometry": {"coordinates":[119.8631,11.4511],"type":"Point"}
}