{
  "type": "Feature",
  "properties": {
    "gn:admin1_code":"05",
    "gn:admin2_code":"39",
    "gn:admin3_code":"54114000.0",
    "gn:asciiname":"Cabancalan",
    "gn:country_code":"PH",
    "gn:dem":38,
    "gn:feature_class":"P",
    "gn:feature_code":"PPL",
    "gn:name":"Cabancalan",
    "gn:population":0,
    "gn:timezone":"Asia/Manila",
    "iso:country":"PH",
    "name:fil_x_preferred":[
        "Cabancalan"
    ],
    "wof:name":"Cabancalan",
    "wof:placetype":"locality"
},
  "geometry": {"coordinates":[123.5993,12.6156],"type":"Point"}
}