{
  "type": "Feature",
  "properties": {
    "gn:admin1_code":"08",
    "gn:admin2_code":"59",
    "gn:asciiname":"Burak",
    "gn:country_code":"PH",
    "gn:dem":100,
    "gn:feature_class":"P",
    "gn:feature_code":"PPL",
    "gn:name":"Burak",
    "gn:population":0,
    "gn:timezone":"Asia/Manila",
    "iso:country":"PH",
    "name:fas_x_preferred":[
        "\u0628\u0648\u0631\u06a9"
    ],
    "name:fil_x_preferred":[
        "Burac"
    ],
    "name:pol_x_preferred":[
        "Burak"
    ],
    "wof:name":"Burak",
    "wof:placetype":"locality"
},
  "geometry": {"coordinates":[122.46550000000001,10.9379],"type":"Point"}
}