{
  "type": "Feature",
  "properties": {
    "gn:admin1_code":"41",
    "gn:admin2_code":"38",
    "gn:admin3_code":"174003000.0",
    "gn:asciiname":"Tapuyan",
    "gn:country_code":"PH",
    "gn:dem":41,
    "gn:feature_class":"P",
    "gn:feature_code":"PPL",
    "gn:name":"Tapuyan",
    "gn:population":0,
    "gn:timezone":"Asia/Manila",
    "iso:country":"PH",
    "name:fil_x_preferred":[
        "Tapuyan"
    ],
    "wof:name":"Tapuyan",
    "wof:placetype":"locality"
},
  "geometry": {"coordinates":[121.85169999999999,13.3657],"type":"Point"}
}