{
  "type": "Feature",
  "properties": {
    "gn:admin1_code":"02",
    "gn:admin2_code":"31",
    "gn:admin3_code":"23114000.0",
    "gn:asciiname":"Marana II",
    "gn:country_code":"PH",
    "gn:dem":40,
    "gn:feature_class":"P",
    "gn:feature_code":"PPL",
    "gn:name":"Marana II",
    "gn:population":0,
    "gn:timezone":"Asia/Manila",
    "iso:country":"PH",
    "name:fil_x_preferred":[
        "Marana II"
    ],
    "wof:name":"Marana II",
    "wof:placetype":"locality"
},
  "geometry": {"coordinates":[121.91584,17.14204],"type":"Point"}
}