{
  "type": "Feature",
  "properties": {
    "gn:admin1_code":"11",
    "gn:admin2_code":"26",
    "gn:admin3_code":"112509000.0",
    "gn:asciiname":"Panombon",
    "gn:country_code":"PH",
    "gn:dem":16,
    "gn:feature_class":"P",
    "gn:feature_code":"PPL",
    "gn:name":"Panombon",
    "gn:population":0,
    "gn:timezone":"Asia/Manila",
    "iso:country":"PH",
    "name:fil_x_preferred":[
        "Panombon"
    ],
    "wof:name":"Panombon",
    "wof:placetype":"locality"
},
  "geometry": {"coordinates":[126.30817999999999,6.97461],"type":"Point"}
}