{
  "type": "Feature",
  "properties": {
    "gn:admin1_code":"06",
    "gn:admin2_code":"30",
    "gn:admin3_code":"63044000.0",
    "gn:asciiname":"Masonson",
    "gn:country_code":"PH",
    "gn:dem":25,
    "gn:feature_class":"P",
    "gn:feature_code":"PPL",
    "gn:name":"Masonson",
    "gn:population":0,
    "gn:timezone":"Asia/Manila",
    "iso:country":"PH",
    "name:fil_x_preferred":[
        "Masonson"
    ],
    "wof:name":"Masonson",
    "wof:placetype":"locality"
},
  "geometry": {"coordinates":[123.03060000000001,11.2702],"type":"Point"}
}