{
  "type": "Feature",
  "properties": {
    "gn:admin1_code":"11",
    "gn:admin2_code":"I7",
    "gn:admin3_code":"112303000.0",
    "gn:asciiname":"Sibulano",
    "gn:cc2":"PH",
    "gn:country_code":"PH",
    "gn:dem":15,
    "gn:feature_class":"P",
    "gn:feature_code":"PPL",
    "gn:name":"Sibulano",
    "gn:population":0,
    "gn:timezone":"Asia/Manila",
    "iso:country":"PH",
    "name:und_x_variant":[
        "Cebulano",
        "Sibulano"
    ],
    "wof:name":"Sibulano",
    "wof:placetype":"locality"
},
  "geometry": {"coordinates":[125.67167000000001,7.35028],"type":"Point"}
}