{
  "type": "Feature",
  "properties": {
    "gn:admin1_code":"12",
    "gn:admin2_code":"57",
    "gn:admin3_code":"124717000.0",
    "gn:asciiname":"Pakagangan",
    "gn:country_code":"PH",
    "gn:dem":58,
    "gn:feature_class":"P",
    "gn:feature_code":"PPL",
    "gn:name":"Pakagangan",
    "gn:population":0,
    "gn:timezone":"Asia/Manila",
    "iso:country":"PH",
    "name:fil_x_preferred":[
        "Pakagangan"
    ],
    "wof:name":"Pakagangan",
    "wof:placetype":"locality"
},
  "geometry": {"coordinates":[124.59528,7.12111],"type":"Point"}
}