{
  "type": "Feature",
  "properties": {
    "gn:admin1_code":"03",
    "gn:admin2_code":"13",
    "gn:admin3_code":"31419000.0",
    "gn:asciiname":"Pinaod",
    "gn:country_code":"PH",
    "gn:dem":28,
    "gn:feature_class":"P",
    "gn:feature_code":"PPL",
    "gn:name":"Pinaod",
    "gn:population":0,
    "gn:timezone":"Asia/Manila",
    "iso:country":"PH",
    "name:fil_x_preferred":[
        "Pinaod"
    ],
    "wof:name":"Pinaod",
    "wof:placetype":"locality"
},
  "geometry": {"coordinates":[120.96071000000001,15.07341],"type":"Point"}
}