{
  "type": "Feature",
  "properties": {
    "gn:admin1_code":"15",
    "gn:admin2_code":"32",
    "gn:admin3_code":"143209000.0",
    "gn:asciiname":"Asibanglan",
    "gn:country_code":"PH",
    "gn:dem":595,
    "gn:feature_class":"P",
    "gn:feature_code":"PPL",
    "gn:name":"Asibanglan",
    "gn:population":0,
    "gn:timezone":"Asia/Manila",
    "iso:country":"PH",
    "name:fil_x_preferred":[
        "Asibanglan"
    ],
    "wof:name":"Asibanglan",
    "wof:placetype":"locality"
},
  "geometry": {"coordinates":[121.2867,17.4625],"type":"Point"}
}