{
  "type": "Feature",
  "properties": {
    "gn:country":"PH",
    "gn:fcode":"ADM3",
    "gn:pop":52461,
    "iso:country":"PH",
    "name:fil_x_preferred":[
        "Hermosa"
    ],
    "name:unk_x_variant":[
        "Llana Hermosa"
    ],
    "qs:name":"Hermosa",
    "qs:photos_9r":0,
    "qs:photos_sr":0,
    "qs:pop_sr":"8",
    "wd:wordcount":58,
    "wof:name":"Hermosa",
    "wof:placetype":"localadmin",
    "wof:population":52461
},
  "geometry": {"coordinates":[120.45609,14.81694],"type":"Point"}
}