{
  "type": "Feature",
  "properties": {
    "gn:admin1_code":"09",
    "gn:admin2_code":"ZSI",
    "gn:admin3_code":"98301000.0",
    "gn:asciiname":"Tangcong",
    "gn:country_code":"PH",
    "gn:dem":8,
    "gn:feature_class":"P",
    "gn:feature_code":"PPL",
    "gn:name":"Tangcong",
    "gn:population":0,
    "gn:timezone":"Asia/Manila",
    "iso:country":"PH",
    "name:fil_x_preferred":[
        "Tangcong"
    ],
    "wof:name":"Tangcong",
    "wof:placetype":"locality"
},
  "geometry": {"coordinates":[122.92417,7.55667],"type":"Point"}
}