{
  "type": "Feature",
  "properties": {
    "gn:country":"PH",
    "gn:fcode":"PPL",
    "gn:pop":2466,
    "iso:country":"PH",
    "name:fil_x_preferred":[
        "Mangoso"
    ],
    "qs:name":"Mangoso",
    "qs:photos_9r":0,
    "qs:photos_sr":0,
    "qs:pop_sr":"4",
    "wof:name":"Mangoso",
    "wof:placetype":"locality",
    "wof:population":2466
},
  "geometry": {"coordinates":[122.6382,11.4175],"type":"Point"}
}