{
  "type": "Feature",
  "properties": {
    "gn:admin1_code":"02",
    "gn:admin2_code":"48",
    "gn:admin3_code":"25013000.0",
    "gn:asciiname":"Bannawag",
    "gn:country_code":"PH",
    "gn:dem":243,
    "gn:feature_class":"P",
    "gn:feature_code":"PPL",
    "gn:name":"Bannawag",
    "gn:population":0,
    "gn:timezone":"Asia/Manila",
    "iso:country":"PH",
    "name:fil_x_preferred":[
        "Bannawag"
    ],
    "name:ilo_x_preferred":[
        "Bannawag"
    ],
    "name:tgl_x_preferred":[
        "Bannawag"
    ],
    "wof:name":"Bannawag",
    "wof:placetype":"locality"
},
  "geometry": {"coordinates":[121.21263999999999,16.56038],"type":"Point"}
}