{
  "type": "Feature",
  "properties": {
    "gn:admin1_code":"40",
    "gn:admin2_code":"09",
    "gn:admin3_code":"41018000.0",
    "gn:asciiname":"San Sebastian",
    "gn:country_code":"PH",
    "gn:dem":278,
    "gn:feature_class":"P",
    "gn:feature_code":"PPL",
    "gn:name":"San Sebastian",
    "gn:population":0,
    "gn:timezone":"Asia/Manila",
    "iso:country":"PH",
    "name:fil_x_preferred":[
        "San Sebastian"
    ],
    "wof:name":"San Sebastian",
    "wof:placetype":"locality"
},
  "geometry": {"coordinates":[121.1018,13.9816],"type":"Point"}
}