{
  "type": "Feature",
  "properties": {
    "gn:admin1_code":"01",
    "gn:admin2_code":"51",
    "gn:admin3_code":"15517000.0",
    "gn:asciiname":"Banaoang",
    "gn:country_code":"PH",
    "gn:dem":10,
    "gn:feature_class":"P",
    "gn:feature_code":"PPL",
    "gn:name":"Banaoang",
    "gn:population":0,
    "gn:timezone":"Asia/Manila",
    "iso:country":"PH",
    "name:fil_x_preferred":[
        "Banaoang"
    ],
    "wof:name":"Banaoang",
    "wof:placetype":"locality"
},
  "geometry": {"coordinates":[120.33880000000001,16.01148],"type":"Point"}
}