{
  "type": "Feature",
  "properties": {
    "gn:admin1_code":"07",
    "gn:admin2_code":"11",
    "gn:admin3_code":"71247000.0",
    "gn:asciiname":"Lapsaon",
    "gn:country_code":"PH",
    "gn:dem":265,
    "gn:feature_class":"P",
    "gn:feature_code":"PPL",
    "gn:name":"Lapsaon",
    "gn:population":0,
    "gn:timezone":"Asia/Manila",
    "iso:country":"PH",
    "name:fil_x_preferred":[
        "Lapsaon"
    ],
    "wof:name":"Lapsaon",
    "wof:placetype":"locality"
},
  "geometry": {"coordinates":[124.18333,9.66667],"type":"Point"}
}