{
  "type": "Feature",
  "properties": {
    "gn:admin1_code":"06",
    "gn:admin2_code":"30",
    "gn:admin3_code":"63018000.0",
    "gn:asciiname":"Sulangan",
    "gn:country_code":"PH",
    "gn:dem":4,
    "gn:feature_class":"P",
    "gn:feature_code":"PPL",
    "gn:name":"Sulangan",
    "gn:population":0,
    "gn:timezone":"Asia/Manila",
    "iso:country":"PH",
    "name:fil_x_preferred":[
        "Sulangan"
    ],
    "wof:name":"Sulangan",
    "wof:placetype":"locality"
},
  "geometry": {"coordinates":[122.664,10.811],"type":"Point"}
}