{
  "type": "Feature",
  "properties": {
    "gn:admin1_code":"05",
    "gn:admin2_code":"58",
    "gn:admin3_code":"56209000.0",
    "gn:asciiname":"Patag",
    "gn:country_code":"PH",
    "gn:dem":195,
    "gn:feature_class":"P",
    "gn:feature_code":"PPL",
    "gn:name":"Patag",
    "gn:population":0,
    "gn:timezone":"Asia/Manila",
    "iso:country":"PH",
    "name:fil_x_preferred":[
        "Patag"
    ],
    "wof:name":"Patag",
    "wof:placetype":"locality"
},
  "geometry": {"coordinates":[124.06253,12.72572],"type":"Point"}
}