{
  "type": "Feature",
  "properties": {
    "gn:admin1_code":"40",
    "gn:admin2_code":"33",
    "gn:admin3_code":"43426000.0",
    "gn:asciiname":"Callos",
    "gn:country_code":"PH",
    "gn:dem":8,
    "gn:feature_class":"P",
    "gn:feature_code":"PPL",
    "gn:name":"Callos",
    "gn:population":0,
    "gn:timezone":"Asia/Manila",
    "iso:country":"PH",
    "name:fil_x_preferred":[
        "Calios"
    ],
    "name:fil_x_variant":[
        "Callos"
    ],
    "wof:name":"Callos",
    "wof:placetype":"locality"
},
  "geometry": {"coordinates":[121.4045,14.2741],"type":"Point"}
}