{
  "type": "Feature",
  "properties": {
    "gn:admin1_code":"10",
    "gn:admin2_code":"43",
    "gn:admin3_code":"104318000.0",
    "gn:asciiname":"Digkilaan",
    "gn:country_code":"PH",
    "gn:dem":679,
    "gn:feature_class":"P",
    "gn:feature_code":"PPL",
    "gn:name":"Digkilaan",
    "gn:population":0,
    "gn:timezone":"Asia/Manila",
    "iso:country":"PH",
    "name:fil_x_preferred":[
        "Digkilaan"
    ],
    "wof:name":"Digkilaan",
    "wof:placetype":"locality"
},
  "geometry": {"coordinates":[124.38527999999999,8.34694],"type":"Point"}
}