{
  "type": "Feature",
  "properties": {
    "gn:admin1_code":"06",
    "gn:admin2_code":"18",
    "gn:admin3_code":"61910000.0",
    "gn:asciiname":"Tabuk",
    "gn:country_code":"PH",
    "gn:dem":13,
    "gn:feature_class":"P",
    "gn:feature_code":"PPL",
    "gn:name":"Tabuk",
    "gn:population":0,
    "gn:timezone":"Asia/Manila",
    "iso:country":"PH",
    "name:ceb_x_preferred":[
        "Tabuk"
    ],
    "name:deu_x_preferred":[
        "Tabuk"
    ],
    "name:eus_x_preferred":[
        "Tabuk"
    ],
    "name:fas_x_preferred":[
        "\u062a\u0628\u0648\u06a9"
    ],
    "name:fil_x_preferred":[
        "Tabuk"
    ],
    "name:heb_x_preferred":[
        "\u05d8\u05d1\u05d5\u05e7"
    ],
    "name:ilo_x_preferred":[
        "Tabuk"
    ],
    "name:ita_x_preferred":[
        "Tabuk"
    ],
    "name:kor_x_preferred":[
        "\ud0c0\ubd80\ud06c"
    ],
    "name:nld_x_preferred":[
        "Tabuk"
    ],
    "name:nor_x_preferred":[
        "Tabuk"
    ],
    "name:pol_x_preferred":[
        "Tabuk"
    ],
    "name:swe_x_preferred":[
        "Tabuk"
    ],
    "name:und_x_variant":[
        "Tabuc"
    ],
    "name:urd_x_preferred":[
        "\u062a\u0628\u0648\u06a9"
    ],
    "name:war_x_preferred":[
        "Tabuk"
    ],
    "wof:name":"Tabuk",
    "wof:placetype":"locality"
},
  "geometry": {"coordinates":[122.77500000000001,11.4694],"type":"Point"}
}