{
  "type": "Feature",
  "properties": {
    "gn:admin1_code":"06",
    "gn:admin2_code":"18",
    "gn:admin3_code":"61910000.0",
    "gn:asciiname":"Tabuk",
    "gn:country_code":"PH",
    "gn:dem":13,
    "gn:feature_class":"P",
    "gn:feature_code":"PPL",
    "gn:name":"Tabuk",
    "gn:population":0,
    "gn:timezone":"Asia/Manila",
    "iso:country":"PH",
    "name:fil_x_preferred":[
        "Tabuk"
    ],
    "name:und_x_variant":[
        "Tabuc"
    ],
    "wof:name":"Tabuk",
    "wof:placetype":"locality"
},
  "geometry": {"coordinates":[122.77500000000001,11.4694],"type":"Point"}
}