{
  "type": "Feature",
  "properties": {
    "gn:admin1_code":"15",
    "gn:admin2_code":"01",
    "gn:admin3_code":"140106000.0",
    "gn:asciiname":"Abut",
    "gn:country_code":"PH",
    "gn:dem":102,
    "gn:feature_class":"P",
    "gn:feature_code":"PPL",
    "gn:name":"Abut",
    "gn:population":0,
    "gn:timezone":"Asia/Manila",
    "iso:country":"PH",
    "name:fil_x_preferred":[
        "Abut"
    ],
    "name:fil_x_variant":[
        "Abot"
    ],
    "name:und_x_variant":[
        "Abot"
    ],
    "wof:name":"Abut",
    "wof:placetype":"locality"
},
  "geometry": {"coordinates":[120.67610000000001,17.7104],"type":"Point"}
}