{
  "type": "Feature",
  "properties": {
    "gn:admin1_code":"05",
    "gn:admin2_code":"15",
    "gn:admin3_code":"51612000.0",
    "gn:asciiname":"Balogo",
    "gn:country_code":"PH",
    "gn:dem":6,
    "gn:feature_class":"P",
    "gn:feature_code":"PPL",
    "gn:name":"Balogo",
    "gn:population":0,
    "gn:timezone":"Asia/Manila",
    "iso:country":"PH",
    "name:fil_x_preferred":[
        "Balogo"
    ],
    "wof:name":"Balogo",
    "wof:placetype":"locality"
},
  "geometry": {"coordinates":[122.88333,14.18333],"type":"Point"}
}