{
  "type": "Feature",
  "properties": {
    "gn:admin1_code":"06",
    "gn:admin2_code":"30",
    "gn:admin3_code":"63044000.0",
    "gn:asciiname":"Nabitasan",
    "gn:country_code":"PH",
    "gn:dem":24,
    "gn:feature_class":"P",
    "gn:feature_code":"PPL",
    "gn:name":"Nabitasan",
    "gn:population":0,
    "gn:timezone":"Asia/Manila",
    "iso:country":"PH",
    "name:fil_x_preferred":[
        "Nabitasan"
    ],
    "wof:name":"Nabitasan",
    "wof:placetype":"locality"
},
  "geometry": {"coordinates":[123.01990000000001,11.2256],"type":"Point"}
}