{
  "type": "Feature",
  "properties": {
    "gn:admin1_code":"01",
    "gn:admin2_code":"28",
    "gn:admin3_code":"12817000.0",
    "gn:asciiname":"Caruon",
    "gn:country_code":"PH",
    "gn:dem":397,
    "gn:feature_class":"P",
    "gn:feature_code":"PPL",
    "gn:name":"Caruon",
    "gn:population":0,
    "gn:timezone":"Asia/Manila",
    "iso:country":"PH",
    "name:fil_x_preferred":[
        "Caruon"
    ],
    "wof:name":"Caruon",
    "wof:placetype":"locality"
},
  "geometry": {"coordinates":[120.6879,18.4052],"type":"Point"}
}