{
  "type": "Feature",
  "properties": {
    "gn:country":"PH",
    "gn:fcode":"PPL",
    "gn:population":4048,
    "iso:country":"PH",
    "name:aze_x_preferred":[
        "D\u0259van"
    ],
    "name:ceb_x_preferred":[
        "Dav\u0101n"
    ],
    "name:fas_x_preferred":[
        "\u062f\u0648\u0627\u0646"
    ],
    "name:fil_x_preferred":[
        "Davan"
    ],
    "name:msa_x_preferred":[
        "Davan"
    ],
    "name:swe_x_preferred":[
        "Dav\u0101n"
    ],
    "name:und_x_variant":[
        "Cabuaga"
    ],
    "qs_pg:aaroncc":"PH",
    "qs_pg:gn_country":"PH",
    "qs_pg:gn_fcode":"PPL",
    "qs_pg:gn_pop":4048,
    "qs_pg:name":"Davan",
    "qs_pg:photos_9r":0,
    "qs_pg:photos_sr":0,
    "qs_pg:pop_sr":4,
    "qs_pg:qs_pg_placetype":"locality",
    "wof:name":"Davan",
    "wof:placetype":"locality",
    "wof:population":4048
},
  "geometry": {"coordinates":[126.15322999999999,6.91487],"type":"Point"}
}