{
  "type": "Feature",
  "properties": {
    "gn:admin1_code":"06",
    "gn:admin2_code":"J3",
    "gn:admin3_code":"67903000.0",
    "gn:asciiname":"Tando",
    "gn:country_code":"PH",
    "gn:dem":12,
    "gn:feature_class":"P",
    "gn:feature_code":"PPL",
    "gn:name":"Tando",
    "gn:population":0,
    "gn:timezone":"Asia/Manila",
    "iso:country":"PH",
    "name:fil_x_preferred":[
        "Tando"
    ],
    "wof:name":"Tando",
    "wof:placetype":"locality"
},
  "geometry": {"coordinates":[122.4931,10.4732],"type":"Point"}
}