{
  "type": "Feature",
  "properties": {
    "gn:country":"PH",
    "gn:fcode":"ADM3",
    "gn:pop":22230,
    "iso:country":"PH",
    "name:fil_x_preferred":[
        "Banaue"
    ],
    "qs:name":"Banaue",
    "qs:photos_9r":0,
    "qs:photos_sr":0,
    "qs:pop_sr":"7",
    "wd:wordcount":882,
    "wof:name":"Banaue",
    "wof:placetype":"localadmin",
    "wof:population":22230
},
  "geometry": {"coordinates":[121.06667,16.95],"type":"Point"}
}