{
  "type": "Feature",
  "properties": {
    "gn:admin1_code":"01",
    "gn:admin2_code":"29",
    "gn:admin3_code":"12914000.0",
    "gn:asciiname":"Orence",
    "gn:country_code":"PH",
    "gn:dem":13,
    "gn:feature_class":"P",
    "gn:feature_code":"PPL",
    "gn:name":"Orence",
    "gn:population":0,
    "gn:timezone":"Asia/Manila",
    "iso:country":"PH",
    "name:fil_x_preferred":[
        "Orence"
    ],
    "name:fil_x_variant":[
        "Orense"
    ],
    "wof:name":"Orence",
    "wof:placetype":"locality"
},
  "geometry": {"coordinates":[120.4906,17.4221],"type":"Point"}
}