{
  "type": "Feature",
  "properties": {
    "gn:admin1_code":"09",
    "gn:admin2_code":"66",
    "gn:admin3_code":"97332000.0",
    "gn:asciiname":"Lapacan",
    "gn:country_code":"PH",
    "gn:dem":99,
    "gn:feature_class":"P",
    "gn:feature_code":"PPL",
    "gn:name":"Lapacan",
    "gn:population":0,
    "gn:timezone":"Asia/Manila",
    "iso:country":"PH",
    "wof:name":"Lapacan",
    "wof:placetype":"locality"
},
  "geometry": {"coordinates":[122.16583,7.03],"type":"Point"}
}