{
  "type": "Feature",
  "properties": {
    "gn:admin1_code":"06",
    "gn:admin2_code":"30",
    "gn:admin3_code":"63035000.0",
    "gn:asciiname":"Lonoy",
    "gn:country_code":"PH",
    "gn:dem":40,
    "gn:feature_class":"P",
    "gn:feature_code":"PPL",
    "gn:name":"Lonoy",
    "gn:population":0,
    "gn:timezone":"Asia/Manila",
    "iso:country":"PH",
    "name:fil_x_preferred":[
        "Lonoy"
    ],
    "wof:name":"Lonoy",
    "wof:placetype":"locality"
},
  "geometry": {"coordinates":[122.61667,11.11667],"type":"Point"}
}