{
  "type": "Feature",
  "properties": {
    "gn:admin1_code":"03",
    "gn:admin2_code":"13",
    "gn:admin3_code":"31421000.0",
    "gn:asciiname":"Bantog",
    "gn:country_code":"PH",
    "gn:dem":19,
    "gn:feature_class":"P",
    "gn:feature_code":"PPL",
    "gn:name":"Bantog",
    "gn:population":0,
    "gn:timezone":"Asia/Manila",
    "iso:country":"PH",
    "name:fil_x_preferred":[
        "Bantog"
    ],
    "wof:name":"Bantog",
    "wof:placetype":"locality"
},
  "geometry": {"coordinates":[120.95612,15.21094],"type":"Point"}
}