{
  "type": "Feature",
  "properties": {
    "gn:admin1_code":"14",
    "gn:admin2_code":"35",
    "gn:admin3_code":"153618000.0",
    "gn:asciiname":"Malacanan",
    "gn:country_code":"PH",
    "gn:dem":715,
    "gn:feature_class":"P",
    "gn:feature_code":"PPL",
    "gn:name":"Malacanan",
    "gn:population":0,
    "gn:timezone":"Asia/Manila",
    "iso:country":"PH",
    "name:fil_x_preferred":[
        "Malacanan"
    ],
    "wof:name":"Malacanan",
    "wof:placetype":"locality"
},
  "geometry": {"coordinates":[124.32805999999999,7.81639],"type":"Point"}
}