{
  "type": "Feature",
  "properties": {
    "gn:country":"PH",
    "gn:fcode":"PPLA3",
    "gn:pop":3142,
    "iso:country":"PH",
    "name:bcl_x_preferred":[
        "Bacnotan"
    ],
    "name:cat_x_preferred":[
        "Bacnotan"
    ],
    "name:deu_x_preferred":[
        "Bacnotan"
    ],
    "name:eng_x_preferred":[
        "Bacnotan"
    ],
    "name:fra_x_preferred":[
        "Bacnotan"
    ],
    "name:ilo_x_preferred":[
        "Bacnotan"
    ],
    "name:ind_x_preferred":[
        "Bacnotan"
    ],
    "name:ita_x_preferred":[
        "Bacnotan"
    ],
    "name:nld_x_preferred":[
        "Bacnotan"
    ],
    "name:oci_x_preferred":[
        "Bacnotan"
    ],
    "name:pag_x_preferred":[
        "Bacnotan"
    ],
    "name:pam_x_preferred":[
        "Bacnotan"
    ],
    "name:spa_x_preferred":[
        "Bacnotan"
    ],
    "name:swe_x_preferred":[
        "Bacnotan"
    ],
    "name:tgl_x_preferred":[
        "Bacnotan"
    ],
    "name:unk_x_variant":[
        "Bacnaton"
    ],
    "name:vie_x_preferred":[
        "Bacnotan"
    ],
    "name:war_x_preferred":[
        "Bacnotan"
    ],
    "qs:name":"Bacnotan",
    "qs:photos_9r":0,
    "qs:photos_sr":0,
    "qs:pop_sr":"4",
    "wd:wordcount":1204,
    "wof:name":"Bacnotan",
    "wof:placetype":"locality",
    "wof:population":3142
},
  "geometry": {"coordinates":[120.35250000000001,16.72222],"type":"Point"}
}