{
  "type": "Feature",
  "properties": {
    "gn:admin1_code":"01",
    "gn:admin2_code":"36",
    "gn:admin3_code":"13314000.0",
    "gn:asciiname":"Sevilla Centro",
    "gn:cc2":"PH",
    "gn:country_code":"PH",
    "gn:dem":69,
    "gn:feature_class":"P",
    "gn:feature_code":"PPL",
    "gn:name":"Sevilla Centro",
    "gn:population":0,
    "gn:timezone":"Asia/Manila",
    "iso:country":"PH",
    "name:und_x_variant":[
        "Sevilla",
        "Sevilla Centro"
    ],
    "wof:name":"Sevilla Centro",
    "wof:placetype":"locality"
},
  "geometry": {"coordinates":[120.32861,16.58333],"type":"Point"}
}