{
  "type": "Feature",
  "properties": {
    "gn:country":"PH",
    "gn:fcode":"PPL",
    "gn:pop":3938,
    "iso:country":"PH",
    "name:fil_x_preferred":[
        "Calepaan"
    ],
    "qs:name":"Calepaan",
    "qs:photos_9r":0,
    "qs:photos_sr":0,
    "qs:pop_sr":"4",
    "wof:name":"Calepaan",
    "wof:placetype":"locality",
    "wof:population":3938
},
  "geometry": {"coordinates":[120.619,16.0195],"type":"Point"}
}