{
  "type": "Feature",
  "properties": {
    "gn:admin1_code":"08",
    "gn:admin2_code":"37",
    "gn:admin3_code":"83717000.0",
    "gn:asciiname":"Hiabangan",
    "gn:country_code":"PH",
    "gn:dem":29,
    "gn:feature_class":"P",
    "gn:feature_code":"PPL",
    "gn:name":"Hiabangan",
    "gn:population":0,
    "gn:timezone":"Asia/Manila",
    "iso:country":"PH",
    "name:fil_x_preferred":[
        "Hiabangan"
    ],
    "wof:name":"Hiabangan",
    "wof:placetype":"locality"
},
  "geometry": {"coordinates":[124.89278,11.05944],"type":"Point"}
}