{
  "type": "Feature",
  "properties": {
    "gn:admin1_code":"02",
    "gn:admin2_code":"31",
    "gn:admin3_code":"23130000.0",
    "gn:asciiname":"Sandiat East",
    "gn:country_code":"PH",
    "gn:dem":57,
    "gn:feature_class":"P",
    "gn:feature_code":"PPL",
    "gn:name":"Sandiat East",
    "gn:population":0,
    "gn:timezone":"Asia/Manila",
    "iso:country":"PH",
    "wof:name":"Sandiat East",
    "wof:placetype":"locality"
},
  "geometry": {"coordinates":[121.63968,17.07515],"type":"Point"}
}