{
  "type": "Feature",
  "properties": {
    "gn:admin1_code":"08",
    "gn:admin2_code":"55",
    "gn:admin3_code":"86021000.0",
    "gn:asciiname":"Tomabe",
    "gn:country_code":"PH",
    "gn:dem":17,
    "gn:feature_class":"P",
    "gn:feature_code":"PPL",
    "gn:name":"Tomabe",
    "gn:population":0,
    "gn:timezone":"Asia/Manila",
    "iso:country":"PH",
    "name:fil_x_preferred":[
        "Tomabe"
    ],
    "wof:name":"Tomabe",
    "wof:placetype":"locality"
},
  "geometry": {"coordinates":[124.96210000000001,11.5216],"type":"Point"}
}