{
  "type": "Feature",
  "properties": {
    "gn:country":"PH",
    "gn:fcode":"ADM3",
    "gn:pop":10655,
    "iso:country":"PH",
    "name:fil_x_preferred":[
        "Santa Marcela"
    ],
    "name:fil_x_variant":[
        "Bayan ng Santa Marcela"
    ],
    "qs:name":"Santa Marcela",
    "qs:photos_9r":0,
    "qs:photos_sr":0,
    "qs:pop_sr":"6",
    "wd:wordcount":175,
    "wof:name":"Santa Marcela",
    "wof:placetype":"localadmin",
    "wof:population":10655
},
  "geometry": {"coordinates":[121.41667,18.28333],"type":"Point"}
}