{
  "type": "Feature",
  "properties": {
    "gn:country":"PH",
    "gn:fcode":"ADM3",
    "gn:pop":10655,
    "iso:country":"PH",
    "name:bcl_x_preferred":[
        "Santa Marcela"
    ],
    "name:cat_x_preferred":[
        "Santa Marcela"
    ],
    "name:ceb_x_preferred":[
        "Santa Marcela"
    ],
    "name:deu_x_preferred":[
        "Santa Marcela"
    ],
    "name:eng_x_preferred":[
        "Santa Marcela"
    ],
    "name:fil_x_preferred":[
        "Santa Marcela"
    ],
    "name:fil_x_variant":[
        "Bayan ng Santa Marcela"
    ],
    "name:fra_x_preferred":[
        "Santa Marcela"
    ],
    "name:ilo_x_preferred":[
        "Santa Marcela"
    ],
    "name:ind_x_preferred":[
        "Santa Marcela"
    ],
    "name:ita_x_preferred":[
        "Santa Marcela"
    ],
    "name:msa_x_preferred":[
        "Santa Marcela"
    ],
    "name:nld_x_preferred":[
        "Santa Marcela"
    ],
    "name:nob_x_preferred":[
        "Santa Marcela"
    ],
    "name:oci_x_preferred":[
        "Santa Marcela"
    ],
    "name:pag_x_preferred":[
        "Santa Marcela"
    ],
    "name:pam_x_preferred":[
        "Santa Marcela"
    ],
    "name:spa_x_preferred":[
        "Santa Marcela"
    ],
    "name:swe_x_preferred":[
        "Santa Marcela"
    ],
    "name:tgl_x_preferred":[
        "Santa Marcela"
    ],
    "name:urd_x_preferred":[
        "\u0633\u0627\u0646\u062a\u0627 \u0645\u0627\u0631\u0633\u06cc\u0644\u0627"
    ],
    "name:vie_x_preferred":[
        "Santa Marcela"
    ],
    "name:war_x_preferred":[
        "Santa Marcela"
    ],
    "qs:name":"Santa Marcela",
    "qs:photos_9r":0,
    "qs:photos_sr":0,
    "qs:pop_sr":"6",
    "wd:wordcount":175,
    "wof:name":"Santa Marcela",
    "wof:placetype":"localadmin",
    "wof:population":10655
},
  "geometry": {"coordinates":[121.41667,18.28333],"type":"Point"}
}