{
  "type": "Feature",
  "properties": {
    "gn:admin1_code":"07",
    "gn:admin2_code":"11",
    "gn:admin3_code":"71213000.0",
    "gn:asciiname":"Magtica",
    "gn:country_code":"PH",
    "gn:dem":235,
    "gn:feature_class":"P",
    "gn:feature_code":"PPL",
    "gn:name":"Magtica",
    "gn:population":0,
    "gn:timezone":"Asia/Manila",
    "iso:country":"PH",
    "name:fil_x_preferred":[
        "Magtica"
    ],
    "wof:name":"Magtica",
    "wof:placetype":"locality"
},
  "geometry": {"coordinates":[124.05806,9.86528],"type":"Point"}
}