{
  "type": "Feature",
  "properties": {
    "gn:country":"PH",
    "gn:fcode":"ADM3",
    "gn:pop":56348,
    "iso:country":"PH",
    "qs:name":"Rosales",
    "qs:photos_9r":0,
    "qs:photos_sr":0,
    "qs:pop_sr":"8",
    "wd:wordcount":637,
    "wof:name":"Rosales",
    "wof:placetype":"localadmin",
    "wof:population":56348
},
  "geometry": {"coordinates":[120.62335,15.88765],"type":"Point"}
}