{
  "type": "Feature",
  "properties": {
    "gn:admin1_code":"15",
    "gn:admin2_code":"10",
    "gn:admin3_code":"141114000.0",
    "gn:asciiname":"Bunicaucau",
    "gn:country_code":"PH",
    "gn:dem":1039,
    "gn:feature_class":"P",
    "gn:feature_code":"PPL",
    "gn:name":"Bunicaucau",
    "gn:population":0,
    "gn:timezone":"Asia/Manila",
    "iso:country":"PH",
    "name:fil_x_preferred":[
        "Bunicaucau"
    ],
    "wof:name":"Bunicaucau",
    "wof:placetype":"locality"
},
  "geometry": {"coordinates":[120.6297,16.5091],"type":"Point"}
}