{
  "type": "Feature",
  "properties": {
    "gn:admin1_code":"15",
    "gn:admin2_code":"32",
    "gn:admin3_code":"143213000.0",
    "gn:asciiname":"Amalao",
    "gn:country_code":"PH",
    "gn:dem":274,
    "gn:feature_class":"P",
    "gn:feature_code":"PPL",
    "gn:name":"Amalao",
    "gn:population":0,
    "gn:timezone":"Asia/Manila",
    "iso:country":"PH",
    "name:fil_x_preferred":[
        "Amlao"
    ],
    "name:fil_x_variant":[
        "Amalao"
    ],
    "wof:name":"Amalao",
    "wof:placetype":"locality"
},
  "geometry": {"coordinates":[121.3134,17.3993],"type":"Point"}
}