{
  "type": "Feature",
  "properties": {
    "gn:country":"PH",
    "gn:fcode":"PPL",
    "gn:population":2462,
    "iso:country":"PH",
    "name:fil_x_preferred":[
        "Tariric"
    ],
    "qs:name":"Tariric",
    "qs:photos_9r":0,
    "qs:photos_sr":0,
    "qs:pop_sr":"4",
    "wof:name":"Tariric",
    "wof:placetype":"locality",
    "wof:population":2462
},
  "geometry": {"coordinates":[123.2235,13.5723],"type":"Point"}
}