{
  "type": "Feature",
  "properties": {
    "gn:admin1_code":"11",
    "gn:admin2_code":"I7",
    "gn:admin3_code":"112319000.0",
    "gn:asciiname":"Hijo Aploya",
    "gn:country_code":"PH",
    "gn:dem":8,
    "gn:feature_class":"P",
    "gn:feature_code":"PPL",
    "gn:name":"Hijo Aploya",
    "gn:population":0,
    "gn:timezone":"Asia/Manila",
    "iso:country":"PH",
    "name:fil_x_preferred":[
        "Hijo Aploya"
    ],
    "wof:name":"Hijo Aploya",
    "wof:placetype":"locality"
},
  "geometry": {"coordinates":[125.8253,7.3661],"type":"Point"}
}