{
  "type": "Feature",
  "properties": {
    "gn:admin1_code":"40",
    "gn:admin2_code":"H2",
    "gn:admin3_code":"45642000.0",
    "gn:asciiname":"Dinansalaw",
    "gn:country_code":"PH",
    "gn:dem":5,
    "gn:feature_class":"P",
    "gn:feature_code":"PPL",
    "gn:name":"Dinansalaw",
    "gn:population":0,
    "gn:timezone":"Asia/Manila",
    "iso:country":"PH",
    "name:fil_x_preferred":[
        "Dinansalaw"
    ],
    "name:fil_x_variant":[
        "Dinansalau"
    ],
    "wof:name":"Dinansalaw",
    "wof:placetype":"locality"
},
  "geometry": {"coordinates":[122.56985,13.17866],"type":"Point"}
}