{
  "type": "Feature",
  "properties": {
    "gn:admin1_code":"05",
    "gn:admin2_code":"39",
    "gn:admin3_code":"54114000.0",
    "gn:asciiname":"Cantorna",
    "gn:country_code":"PH",
    "gn:dem":94,
    "gn:feature_class":"P",
    "gn:feature_code":"PPL",
    "gn:name":"Cantorna",
    "gn:population":0,
    "gn:timezone":"Asia/Manila",
    "iso:country":"PH",
    "name:fil_x_preferred":[
        "Cantorna"
    ],
    "name:und_x_variant":[
        "Canturna"
    ],
    "wof:name":"Cantorna",
    "wof:placetype":"locality"
},
  "geometry": {"coordinates":[123.6296,12.6149],"type":"Point"}
}