{
  "type": "Feature",
  "properties": {
    "gn:admin1_code":"05",
    "gn:admin2_code":"15",
    "gn:admin3_code":"51603000.0",
    "gn:asciiname":"Bactas",
    "gn:country_code":"PH",
    "gn:dem":3,
    "gn:feature_class":"P",
    "gn:feature_code":"PPL",
    "gn:name":"Bactas",
    "gn:population":0,
    "gn:timezone":"Asia/Manila",
    "iso:country":"PH",
    "name:fil_x_preferred":[
        "Bactas"
    ],
    "name:und_x_variant":[
        "Bactan"
    ],
    "wof:name":"Bactas",
    "wof:placetype":"locality"
},
  "geometry": {"coordinates":[122.9752,14.0926],"type":"Point"}
}