{
  "type": "Feature",
  "properties": {
    "iso:country":"PH",
    "name:bcl_x_preferred":[
        "Palimbang"
    ],
    "name:ceb_x_preferred":[
        "Palimbang"
    ],
    "name:deu_x_preferred":[
        "Palimbang"
    ],
    "name:eng_x_preferred":[
        "Palimbang"
    ],
    "name:fra_x_preferred":[
        "Palimbang"
    ],
    "name:ilo_x_preferred":[
        "Palimbang"
    ],
    "name:ind_x_preferred":[
        "Palimbang"
    ],
    "name:ita_x_preferred":[
        "Palimbang"
    ],
    "name:nld_x_preferred":[
        "Palimbang"
    ],
    "name:pag_x_preferred":[
        "Palimbang"
    ],
    "name:pam_x_preferred":[
        "Palimbang"
    ],
    "name:spa_x_preferred":[
        "Palimbang"
    ],
    "name:swe_x_preferred":[
        "Palimbang"
    ],
    "name:tgl_x_preferred":[
        "Palimbang"
    ],
    "name:und_x_variant":[
        "Palimban"
    ],
    "name:vie_x_preferred":[
        "Palimbang"
    ],
    "name:war_x_preferred":[
        "Palimbang"
    ],
    "qs:gn_country":"PH",
    "qs:gn_fcode":"PPL",
    "qs:gn_pop":4858,
    "qs:name":"Palimbang",
    "qs:name_adm0":"Philippines",
    "qs:name_adm1":"Soccsksargen",
    "qs:photos":0,
    "qs:photos_1k":0,
    "qs:photos_9k":0,
    "qs:photos_9r":0,
    "qs:photos_all":0,
    "qs:photos_sr":0,
    "qs:placetype":"Town",
    "qs:pop_sr":"4",
    "qs:woe_adm0":23424934,
    "wof:name":"Palimbang",
    "wof:placetype":"locality",
    "wof:population":4858
},
  "geometry": {"coordinates":[124.18944,6.21056],"type":"Point"}
}