{
  "type": "Feature",
  "properties": {
    "gn:admin1_code":"05",
    "gn:admin2_code":"16",
    "gn:admin3_code":"51730000.0",
    "gn:asciiname":"Port Junction",
    "gn:country_code":"PH",
    "gn:dem":40,
    "gn:feature_class":"P",
    "gn:feature_code":"PPL",
    "gn:name":"Port Junction",
    "gn:population":0,
    "gn:timezone":"Asia/Manila",
    "iso:country":"PH",
    "name:eng_x_preferred":[
        "Port Junction"
    ],
    "wof:name":"Port Junction",
    "wof:placetype":"locality"
},
  "geometry": {"coordinates":[122.6755,13.8579],"type":"Point"}
}