{
  "type": "Feature",
  "properties": {
    "gn:admin1_code":"08",
    "gn:admin2_code":"37",
    "gn:admin3_code":"83731000.0",
    "gn:asciiname":"Kinauit",
    "gn:country_code":"PH",
    "gn:dem":182,
    "gn:feature_class":"P",
    "gn:feature_code":"PPL",
    "gn:name":"Kinauit",
    "gn:population":0,
    "gn:timezone":"Asia/Manila",
    "iso:country":"PH",
    "name:fil_x_preferred":[
        "Kinauit"
    ],
    "name:und_x_variant":[
        "Kinawit"
    ],
    "wof:name":"Kinauit",
    "wof:placetype":"locality"
},
  "geometry": {"coordinates":[124.9555,10.6611],"type":"Point"}
}