{
  "type": "Feature",
  "properties": {
    "gn:country":"PH",
    "gn:fcode":"PPL",
    "gn:pop":2275,
    "iso:country":"PH",
    "name:fil_x_preferred":[
        "Sadsalan"
    ],
    "qs:name":"Sadsalan",
    "qs:photos_9r":0,
    "qs:photos_sr":0,
    "qs:pop_sr":"4",
    "wof:name":"Sadsalan",
    "wof:placetype":"locality",
    "wof:population":2275
},
  "geometry": {"coordinates":[124.62222,6.82306],"type":"Point"}
}