{
  "type": "Feature",
  "properties": {
    "gn:gn_country":"PH",
    "gn:gn_fcode":"PPL",
    "gn:gn_pop":4884,
    "gn:population":4884,
    "iso:country":"PH",
    "name:fil_x_preferred":[
        "Boot"
    ],
    "qs_pg:aaroncc":"PH",
    "qs_pg:gn_country":"PH",
    "qs_pg:gn_fcode":"PPL",
    "qs_pg:gn_pop":4884,
    "qs_pg:name":"Boot",
    "qs_pg:photos_9r":0,
    "qs_pg:photos_sr":0,
    "qs_pg:pop_sr":4,
    "qs_pg:qs_pg_placetype":"locality",
    "wof:name":"Boot",
    "wof:placetype":"locality",
    "wof:population":4884
},
  "geometry": {"coordinates":[121.07722,14.04556],"type":"Point"}
}