{
  "type": "Feature",
  "properties": {
    "gn:admin1_code":"07",
    "gn:admin2_code":"46",
    "gn:admin3_code":"74611000.0",
    "gn:asciiname":"Tinayunan",
    "gn:country_code":"PH",
    "gn:dem":9,
    "gn:feature_class":"P",
    "gn:feature_code":"PPL",
    "gn:name":"Tinayunan",
    "gn:population":0,
    "gn:timezone":"Asia/Manila",
    "iso:country":"PH",
    "name:fil_x_preferred":[
        "Tinayunan"
    ],
    "name:und_x_variant":[
        "Tinayunan Beach"
    ],
    "wof:name":"Tinayunan",
    "wof:placetype":"locality"
},
  "geometry": {"coordinates":[123.2675,10.1066],"type":"Point"}
}