{
  "type": "Feature",
  "properties": {
    "gn:admin1_code":"12",
    "gn:admin2_code":"70",
    "gn:admin3_code":"126319000.0",
    "gn:asciiname":"Alah",
    "gn:country_code":"PH",
    "gn:dem":544,
    "gn:feature_class":"P",
    "gn:feature_code":"PPL",
    "gn:name":"Alah",
    "gn:population":0,
    "gn:timezone":"Asia/Manila",
    "iso:country":"PH",
    "name:und_x_variant":[
        "Alah Valley",
        "Alah"
    ],
    "wof:name":"Alah",
    "wof:placetype":"locality"
},
  "geometry": {"coordinates":[124.77197,6.1964],"type":"Point"}
}