{
  "type": "Feature",
  "properties": {
    "gn:country":"PH",
    "gn:fcode":"ADM3",
    "gn:pop":16833,
    "iso:country":"PH",
    "qs:name":"Kauswagan",
    "qs:photos_9r":0,
    "qs:photos_sr":0,
    "qs:pop_sr":"6",
    "wof:name":"Kauswagan",
    "wof:placetype":"localadmin",
    "wof:population":16833
},
  "geometry": {"coordinates":[124.08333,8.16667],"type":"Point"}
}