{
  "type": "Feature",
  "properties": {
    "gn:admin1_code":"01",
    "gn:admin2_code":"28",
    "gn:admin3_code":"12816000.0",
    "gn:asciiname":"Cabalingasaan",
    "gn:country_code":"PH",
    "gn:dem":22,
    "gn:feature_class":"P",
    "gn:feature_code":"PPL",
    "gn:name":"Cabalingasaan",
    "gn:population":0,
    "gn:timezone":"Asia/Manila",
    "iso:country":"PH",
    "name:fil_x_preferred":[
        "Cabalingasaan"
    ],
    "wof:name":"Cabalingasaan",
    "wof:placetype":"locality"
},
  "geometry": {"coordinates":[120.5181,18.0351],"type":"Point"}
}