{
  "type": "Feature",
  "properties": {
    "gn:country":"PH",
    "gn:fcode":"ADM3",
    "gn:population":29837,
    "iso:country":"PH",
    "name:bcl_x_preferred":[
        "Aborlan"
    ],
    "name:cat_x_preferred":[
        "Aborlan"
    ],
    "name:ceb_x_preferred":[
        "Aborlan"
    ],
    "name:deu_x_preferred":[
        "Aborlan"
    ],
    "name:eng_x_preferred":[
        "Aborlan"
    ],
    "name:fas_x_preferred":[
        "\u0627\u0628\u0648\u0631\u0644\u0627\u0646"
    ],
    "name:fil_x_preferred":[
        "Aborlan"
    ],
    "name:fra_x_preferred":[
        "Aborlan"
    ],
    "name:ilo_x_preferred":[
        "Aborlan"
    ],
    "name:ind_x_preferred":[
        "Aborlan"
    ],
    "name:ita_x_preferred":[
        "Aborlan"
    ],
    "name:nld_x_preferred":[
        "Aborlan"
    ],
    "name:oci_x_preferred":[
        "Aborlan"
    ],
    "name:pag_x_preferred":[
        "Aborlan"
    ],
    "name:pam_x_preferred":[
        "Aborlan"
    ],
    "name:spa_x_preferred":[
        "Aborl\u00e1n"
    ],
    "name:swe_x_preferred":[
        "Aborlan"
    ],
    "name:tgl_x_preferred":[
        "Aborlan"
    ],
    "name:vie_x_preferred":[
        "Aborlan"
    ],
    "name:war_x_preferred":[
        "Aborlan"
    ],
    "name:zho_x_preferred":[
        "\u963f\u535a\u862d"
    ],
    "qs:name":"Aborlan",
    "qs:photos_9r":0,
    "qs:photos_sr":0,
    "qs:pop_sr":"7",
    "wd:wordcount":260,
    "wof:name":"Aborlan",
    "wof:placetype":"localadmin",
    "wof:population":29837
},
  "geometry": {"coordinates":[118.45,9.51667],"type":"Point"}
}