{
  "type": "Feature",
  "properties": {
    "gn:country":"PH",
    "gn:fcode":"ADM3",
    "gn:pop":29837,
    "iso:country":"PH",
    "name:fil_x_preferred":[
        "Aborlan"
    ],
    "qs:name":"Aborlan",
    "qs:photos_9r":0,
    "qs:photos_sr":0,
    "qs:pop_sr":"7",
    "wd:wordcount":260,
    "wof:name":"Aborlan",
    "wof:placetype":"localadmin",
    "wof:population":29837
},
  "geometry": {"coordinates":[118.45,9.51667],"type":"Point"}
}