{
  "type": "Feature",
  "properties": {
    "gn:admin1_code":"01",
    "gn:admin2_code":"51",
    "gn:admin3_code":"15501000.0",
    "gn:asciiname":"Layog",
    "gn:country_code":"PH",
    "gn:dem":17,
    "gn:feature_class":"P",
    "gn:feature_code":"PPL",
    "gn:name":"Layog",
    "gn:population":0,
    "gn:timezone":"Asia/Manila",
    "iso:country":"PH",
    "name:fil_x_preferred":[
        "Layog"
    ],
    "wof:name":"Layog",
    "wof:placetype":"locality"
},
  "geometry": {"coordinates":[119.78019999999999,16.019],"type":"Point"}
}