{
  "type": "Feature",
  "properties": {
    "gn:admin1_code":"03",
    "gn:admin2_code":"63",
    "gn:admin3_code":"36903000.0",
    "gn:asciiname":"Telbang",
    "gn:country_code":"PH",
    "gn:dem":30,
    "gn:feature_class":"P",
    "gn:feature_code":"PPL",
    "gn:name":"Telbang",
    "gn:population":0,
    "gn:timezone":"Asia/Manila",
    "iso:country":"PH",
    "wof:name":"Telbang",
    "wof:placetype":"locality"
},
  "geometry": {"coordinates":[120.40418,15.64721],"type":"Point"}
}