{
  "type": "Feature",
  "properties": {
    "gn:admin1_code":"01",
    "gn:admin2_code":"36",
    "gn:admin3_code":"13309000.0",
    "gn:asciiname":"Liquicia",
    "gn:country_code":"PH",
    "gn:dem":61,
    "gn:feature_class":"P",
    "gn:feature_code":"PPL",
    "gn:name":"Liquicia",
    "gn:population":0,
    "gn:timezone":"Asia/Manila",
    "iso:country":"PH",
    "name:fil_x_preferred":[
        "Liquicia"
    ],
    "wof:name":"Liquicia",
    "wof:placetype":"locality"
},
  "geometry": {"coordinates":[120.40819999999999,16.4354],"type":"Point"}
}