{
  "type": "Feature",
  "properties": {
    "gn:country":"PH",
    "gn:fcode":"PPLA3",
    "gn:population":44930,
    "iso:country":"PH",
    "name:bcl_x_preferred":[
        "Parang"
    ],
    "name:ceb_x_preferred":[
        "Parang"
    ],
    "name:deu_x_preferred":[
        "Parang"
    ],
    "name:eng_x_preferred":[
        "Parang"
    ],
    "name:fas_x_preferred":[
        "\u067e\u0631\u0646\u06af\u060c \u0645\u0627\u06af\u0648\u0626\u06cc\u0646\u062f\u0627\u0646\u0627\u0626\u0648"
    ],
    "name:fas_x_variant":[
        "\u067e\u0631\u0646\u06af"
    ],
    "name:fra_x_preferred":[
        "Parang"
    ],
    "name:ilo_x_preferred":[
        "Parang"
    ],
    "name:ind_x_preferred":[
        "Parang"
    ],
    "name:ita_x_preferred":[
        "Parang"
    ],
    "name:jpn_x_preferred":[
        "\u30d1\u30e9\u30f3"
    ],
    "name:nld_x_preferred":[
        "Parang"
    ],
    "name:pag_x_preferred":[
        "Parang"
    ],
    "name:pam_x_preferred":[
        "Parang"
    ],
    "name:spa_x_preferred":[
        "Parang"
    ],
    "name:swe_x_preferred":[
        "Parang"
    ],
    "name:tgl_x_preferred":[
        "Parang"
    ],
    "name:urd_x_preferred":[
        "\u067e\u0627\u0631\u0627\u0646\u06af\u060c \u0645\u0627\u06af\u0648\u0626\u0646\u062f\u0627\u0646\u0627\u0624"
    ],
    "name:urd_x_variant":[
        "\u067e\u0627\u0631\u0627\u0646\u06af"
    ],
    "name:vie_x_preferred":[
        "Parang"
    ],
    "name:war_x_preferred":[
        "Parang"
    ],
    "name:zho_x_preferred":[
        "\u5e15\u6717"
    ],
    "qs:name":"Parang",
    "qs:photos_9r":0,
    "qs:photos_sr":0,
    "qs:pop_sr":"7",
    "wd:wordcount":882,
    "wof:name":"Parang",
    "wof:placetype":"locality",
    "wof:population":44930
},
  "geometry": {"coordinates":[124.26973,7.37035],"type":"Point"}
}