{
  "type": "Feature",
  "properties": {
    "gn:admin1_code":"41",
    "gn:admin2_code":"49",
    "gn:admin3_code":"175304000.0",
    "gn:asciiname":"Loudon",
    "gn:country_code":"PH",
    "gn:dem":7,
    "gn:feature_class":"P",
    "gn:feature_code":"PPL",
    "gn:name":"Loudon",
    "gn:population":0,
    "gn:timezone":"Asia/Manila",
    "iso:country":"PH",
    "name:cat_x_preferred":[
        "Loudon"
    ],
    "name:ceb_x_preferred":[
        "Loudon"
    ],
    "name:deu_x_preferred":[
        "Loudon"
    ],
    "name:eng_x_preferred":[
        "Loudon"
    ],
    "name:fra_x_preferred":[
        "Loudon"
    ],
    "name:ita_x_preferred":[
        "Loudon"
    ],
    "name:nld_x_preferred":[
        "Loudon"
    ],
    "name:pol_x_preferred":[
        "Loudon"
    ],
    "name:rus_x_preferred":[
        "\u041b\u0430\u0443\u0434\u043e\u043d"
    ],
    "name:srp_x_preferred":[
        "\u041b\u0430\u0443\u0434\u043e\u043d"
    ],
    "name:ukr_x_preferred":[
        "\u041b\u0430\u0443\u0434\u043e\u043d"
    ],
    "name:und_x_variant":[
        "Loudan"
    ],
    "name:vol_x_preferred":[
        "Loudon"
    ],
    "wof:name":"Loudon",
    "wof:placetype":"locality"
},
  "geometry": {"coordinates":[117.09179,8.21485],"type":"Point"}
}