{
  "type": "Feature",
  "properties": {
    "gn:admin1_code":"06",
    "gn:admin2_code":"H3",
    "gn:admin3_code":"64512000.0",
    "gn:asciiname":"Campomanes",
    "gn:country_code":"PH",
    "gn:dem":13,
    "gn:feature_class":"P",
    "gn:feature_code":"PPL",
    "gn:name":"Campomanes",
    "gn:population":0,
    "gn:timezone":"Asia/Manila",
    "iso:country":"PH",
    "name:deu_x_preferred":[
        "Campomanes"
    ],
    "name:fil_x_preferred":[
        "Campomanes"
    ],
    "name:fra_x_preferred":[
        "Campomanes"
    ],
    "name:rus_x_preferred":[
        "\u041a\u0430\u043c\u043f\u043e\u043c\u0430\u043d\u0435\u0441"
    ],
    "name:spa_x_preferred":[
        "Campomanes"
    ],
    "wof:name":"Campomanes",
    "wof:placetype":"locality"
},
  "geometry": {"coordinates":[122.4671,9.6304],"type":"Point"}
}