{
  "type": "Feature",
  "properties": {
    "gn:admin1_code":"40",
    "gn:admin2_code":"20",
    "gn:admin3_code":"42103000.0",
    "gn:asciiname":"Bamayang",
    "gn:country_code":"PH",
    "gn:dem":36,
    "gn:feature_class":"P",
    "gn:feature_code":"PPL",
    "gn:name":"Bamayang",
    "gn:population":0,
    "gn:timezone":"Asia/Manila",
    "iso:country":"PH",
    "wof:name":"Bamayang",
    "wof:placetype":"locality"
},
  "geometry": {"coordinates":[120.97008999999998,14.3985],"type":"Point"}
}