{
  "type": "Feature",
  "properties": {
    "gn:admin1_code":"41",
    "gn:admin2_code":"41",
    "gn:admin3_code":"175207000.0",
    "gn:asciiname":"Amuguis",
    "gn:country_code":"PH",
    "gn:dem":69,
    "gn:feature_class":"P",
    "gn:feature_code":"PPL",
    "gn:name":"Amuguis",
    "gn:population":0,
    "gn:timezone":"Asia/Manila",
    "iso:country":"PH",
    "name:fil_x_preferred":[
        "Amuguis"
    ],
    "name:und_x_variant":[
        "Amugis"
    ],
    "wof:name":"Amuguis",
    "wof:placetype":"locality"
},
  "geometry": {"coordinates":[121.4053,12.4732],"type":"Point"}
}