{
  "type": "Feature",
  "properties": {
    "gn:admin1_code":"14",
    "gn:admin2_code":"22",
    "gn:admin3_code":"150702000.0",
    "gn:asciiname":"Sugpangan",
    "gn:country_code":"PH",
    "gn:dem":16,
    "gn:feature_class":"P",
    "gn:feature_code":"PPL",
    "gn:name":"Sugpangan",
    "gn:population":0,
    "gn:timezone":"Asia/Manila",
    "iso:country":"PH",
    "name:fil_x_preferred":[
        "Sugpangan"
    ],
    "wof:name":"Sugpangan",
    "wof:placetype":"locality"
},
  "geometry": {"coordinates":[122.12472,6.6275],"type":"Point"}
}