{
  "type": "Feature",
  "properties": {
    "gn:admin1_code":"40",
    "gn:admin2_code":"09",
    "gn:admin3_code":"41031000.0",
    "gn:asciiname":"Banjo West",
    "gn:country_code":"PH",
    "gn:dem":186,
    "gn:feature_class":"P",
    "gn:feature_code":"PPL",
    "gn:name":"Banjo West",
    "gn:population":0,
    "gn:timezone":"Asia/Manila",
    "iso:country":"PH",
    "name:und_x_variant":[
        "Banjo"
    ],
    "wof:name":"Banjo West",
    "wof:placetype":"locality"
},
  "geometry": {"coordinates":[121.13339000000001,14.05399],"type":"Point"}
}