{
  "type": "Feature",
  "properties": {
    "gn:admin1_code":"06",
    "gn:admin2_code":"06",
    "gn:admin3_code":"60617000.0",
    "gn:asciiname":"Cubay",
    "gn:country_code":"PH",
    "gn:dem":8,
    "gn:feature_class":"P",
    "gn:feature_code":"PPL",
    "gn:name":"Cubay",
    "gn:population":0,
    "gn:timezone":"Asia/Manila",
    "iso:country":"PH",
    "name:fil_x_preferred":[
        "Cubay"
    ],
    "wof:name":"Cubay",
    "wof:placetype":"locality"
},
  "geometry": {"coordinates":[122.05801,11.25232],"type":"Point"}
}