{
  "type": "Feature",
  "properties": {
    "gn:admin1_code":"40",
    "gn:admin2_code":"33",
    "gn:admin3_code":"43428000.0",
    "gn:asciiname":"Ganado",
    "gn:country_code":"PH",
    "gn:dem":41,
    "gn:feature_class":"P",
    "gn:feature_code":"PPL",
    "gn:name":"Ganado",
    "gn:population":0,
    "gn:timezone":"Asia/Manila",
    "iso:country":"PH",
    "name:fil_x_preferred":[
        "Ganado"
    ],
    "wof:name":"Ganado",
    "wof:placetype":"locality"
},
  "geometry": {"coordinates":[121.08248,14.27997],"type":"Point"}
}