{
  "type": "Feature",
  "properties": {
    "gn:admin1_code":"01",
    "gn:admin2_code":"51",
    "gn:admin3_code":"15503000.0",
    "gn:asciiname":"Balangobong",
    "gn:country_code":"PH",
    "gn:dem":14,
    "gn:feature_class":"P",
    "gn:feature_code":"PPL",
    "gn:name":"Balangobong",
    "gn:population":0,
    "gn:timezone":"Asia/Manila",
    "iso:country":"PH",
    "name:fil_x_preferred":[
        "Balangobong"
    ],
    "wof:name":"Balangobong",
    "wof:placetype":"locality"
},
  "geometry": {"coordinates":[119.988,16.1208],"type":"Point"}
}