{
  "type": "Feature",
  "properties": {
    "gn:admin1_code":"01",
    "gn:admin2_code":"51",
    "gn:admin3_code":"15529000.0",
    "gn:asciiname":"San Maximo",
    "gn:country_code":"PH",
    "gn:dem":87,
    "gn:feature_class":"P",
    "gn:feature_code":"PPL",
    "gn:name":"San Maximo",
    "gn:population":0,
    "gn:timezone":"Asia/Manila",
    "iso:country":"PH",
    "name:fil_x_preferred":[
        "San Maximo"
    ],
    "wof:name":"San Maximo",
    "wof:placetype":"locality"
},
  "geometry": {"coordinates":[120.7936,16.0344],"type":"Point"}
}