{
  "type": "Feature",
  "properties": {
    "gn:admin1_code":"40",
    "gn:admin2_code":"H2",
    "gn:admin3_code":"45644000.0",
    "gn:asciiname":"Bato",
    "gn:country_code":"PH",
    "gn:dem":144,
    "gn:feature_class":"P",
    "gn:feature_code":"PPL",
    "gn:name":"Bato",
    "gn:population":0,
    "gn:timezone":"Asia/Manila",
    "iso:country":"PH",
    "name:fil_x_preferred":[
        "Bato"
    ],
    "wof:name":"Bato",
    "wof:placetype":"locality"
},
  "geometry": {"coordinates":[122.5303,13.5292],"type":"Point"}
}