{
  "type": "Feature",
  "properties": {
    "gn:admin1_code":"08",
    "gn:admin2_code":"55",
    "gn:admin3_code":"86025000.0",
    "gn:asciiname":"Matalud",
    "gn:country_code":"PH",
    "gn:dem":200,
    "gn:feature_class":"P",
    "gn:feature_code":"PPL",
    "gn:name":"Matalud",
    "gn:population":0,
    "gn:timezone":"Asia/Manila",
    "iso:country":"PH",
    "name:fil_x_preferred":[
        "Matalud"
    ],
    "wof:name":"Matalud",
    "wof:placetype":"locality"
},
  "geometry": {"coordinates":[124.91611,11.99194],"type":"Point"}
}