{
  "type": "Feature",
  "properties": {
    "gn:admin1_code":"15",
    "gn:admin2_code":"27",
    "gn:admin3_code":"142704000.0",
    "gn:asciiname":"Empelet",
    "gn:country_code":"PH",
    "gn:dem":364,
    "gn:feature_class":"P",
    "gn:feature_code":"PPL",
    "gn:name":"Empelet",
    "gn:population":0,
    "gn:timezone":"Asia/Manila",
    "iso:country":"PH",
    "name:fil_x_preferred":[
        "Empelet"
    ],
    "wof:name":"Empelet",
    "wof:placetype":"locality"
},
  "geometry": {"coordinates":[121.25,16.81667],"type":"Point"}
}