{
  "type": "Feature",
  "properties": {
    "gn:admin1_code":"07",
    "gn:admin2_code":"46",
    "gn:admin3_code":"74604000.0",
    "gn:asciiname":"Tamiso Real",
    "gn:country_code":"PH",
    "gn:dem":5,
    "gn:feature_class":"P",
    "gn:feature_code":"PPL",
    "gn:name":"Tamiso Real",
    "gn:population":0,
    "gn:timezone":"Asia/Manila",
    "iso:country":"PH",
    "name:fil_x_preferred":[
        "Tamiso Real"
    ],
    "name:fil_x_variant":[
        "Tamisu Real"
    ],
    "wof:name":"Tamiso Real",
    "wof:placetype":"locality"
},
  "geometry": {"coordinates":[123.0977,9.6245],"type":"Point"}
}