{
  "type": "Feature",
  "properties": {
    "iso:country":"PH",
    "name:deu_x_preferred":[
        "Naguilian"
    ],
    "name:fil_x_preferred":[
        "Naguilayan"
    ],
    "name:fil_x_variant":[
        "Naguilaryan"
    ],
    "name:ita_x_preferred":[
        "Naguilian"
    ],
    "name:nld_x_preferred":[
        "Naguilian"
    ],
    "name:unk_x_variant":[
        "Naguilaryan"
    ],
    "name:war_x_preferred":[
        "Naguilian"
    ],
    "qs:gn_country":"PH",
    "qs:gn_fcode":"PPL",
    "qs:gn_pop":3777,
    "qs:name":"Naguilian",
    "qs:name_adm0":"Philippines",
    "qs:name_adm1":"Ilocos Region",
    "qs:photos":88,
    "qs:photos_1k":18,
    "qs:photos_9k":1,
    "qs:photos_9r":3,
    "qs:photos_all":88,
    "qs:photos_sr":3,
    "qs:placetype":"Town",
    "qs:pop_sr":"4",
    "qs:woe_adm0":23424934,
    "wd:wordcount":15,
    "wof:name":"Naguilian",
    "wof:placetype":"locality",
    "wof:population":3777
},
  "geometry": {"coordinates":[120.29107999999999,16.00304],"type":"Point"}
}