{
  "type": "Feature",
  "properties": {
    "gn:admin1_code":"06",
    "gn:admin2_code":"30",
    "gn:admin3_code":"63014000.0",
    "gn:asciiname":"Binuluangan",
    "gn:country_code":"PH",
    "gn:dem":11,
    "gn:feature_class":"P",
    "gn:feature_code":"PPL",
    "gn:name":"Binuluangan",
    "gn:population":0,
    "gn:timezone":"Asia/Manila",
    "iso:country":"PH",
    "name:fil_x_preferred":[
        "Binuluangan"
    ],
    "wof:name":"Binuluangan",
    "wof:placetype":"locality"
},
  "geometry": {"coordinates":[123.18210000000001,11.5258],"type":"Point"}
}