{
  "type": "Feature",
  "properties": {
    "gn:admin1_code":"14",
    "gn:admin2_code":"56",
    "gn:admin3_code":"153811000.0",
    "gn:asciiname":"Cabuan",
    "gn:country_code":"PH",
    "gn:dem":59,
    "gn:feature_class":"P",
    "gn:feature_code":"PPL",
    "gn:name":"Cabuan",
    "gn:population":0,
    "gn:timezone":"Asia/Manila",
    "iso:country":"PH",
    "name:fil_x_preferred":[
        "Cabuan"
    ],
    "wof:name":"Cabuan",
    "wof:placetype":"locality"
},
  "geometry": {"coordinates":[124.35361,7.35639],"type":"Point"}
}