{
  "type": "Feature",
  "properties": {
    "gn:admin1_code":"15",
    "gn:admin2_code":"10",
    "gn:admin3_code":"141112000.0",
    "gn:asciiname":"Amica",
    "gn:country_code":"PH",
    "gn:dem":418,
    "gn:feature_class":"P",
    "gn:feature_code":"PPL",
    "gn:name":"Amica",
    "gn:population":0,
    "gn:timezone":"Asia/Manila",
    "iso:country":"PH",
    "name:deu_x_preferred":[
        "Amica"
    ],
    "name:fil_x_preferred":[
        "Amica"
    ],
    "name:fin_x_preferred":[
        "Amica"
    ],
    "name:fra_x_preferred":[
        "Amica"
    ],
    "name:ita_x_preferred":[
        "Amica"
    ],
    "wof:name":"Amica",
    "wof:placetype":"locality"
},
  "geometry": {"coordinates":[120.48333,16.48333],"type":"Point"}
}