{
  "type": "Feature",
  "properties": {
    "gn:admin1_code":"06",
    "gn:admin2_code":"06",
    "gn:admin3_code":"60611000.0",
    "gn:asciiname":"Ouiligdon",
    "gn:country_code":"PH",
    "gn:dem":12,
    "gn:feature_class":"P",
    "gn:feature_code":"PPL",
    "gn:name":"Ouiligdon",
    "gn:population":0,
    "gn:timezone":"Asia/Manila",
    "iso:country":"PH",
    "name:fil_x_preferred":[
        "Ouiligdon"
    ],
    "name:und_x_variant":[
        "Quiligdon"
    ],
    "wof:name":"Ouiligdon",
    "wof:placetype":"locality"
},
  "geometry": {"coordinates":[122.0568,11.7407],"type":"Point"}
}