{
  "type": "Feature",
  "properties": {
    "gn:country":"PH",
    "gn:fcode":"PPLA3",
    "gn:population":134327,
    "iso:country":"PH",
    "name:bcl_x_preferred":[
        "San Mateo"
    ],
    "name:cat_x_preferred":[
        "San Mateo"
    ],
    "name:ceb_x_preferred":[
        "San Mateo"
    ],
    "name:deu_x_preferred":[
        "San Mateo"
    ],
    "name:eng_x_preferred":[
        "San Mateo"
    ],
    "name:fil_x_preferred":[
        "San Mateo"
    ],
    "name:fra_x_preferred":[
        "San Mateo"
    ],
    "name:ilo_x_preferred":[
        "San Mateo"
    ],
    "name:ind_x_preferred":[
        "San Mateo"
    ],
    "name:ita_x_preferred":[
        "San Mateo"
    ],
    "name:nld_x_preferred":[
        "San Mateo"
    ],
    "name:oci_x_preferred":[
        "San Mateo"
    ],
    "name:pag_x_preferred":[
        "San Mateo"
    ],
    "name:pam_x_preferred":[
        "San Mateo"
    ],
    "name:pol_x_preferred":[
        "San Mateo"
    ],
    "name:spa_x_preferred":[
        "San Mateo"
    ],
    "name:swe_x_preferred":[
        "San Mateo"
    ],
    "name:tgl_x_preferred":[
        "San Mateo"
    ],
    "name:war_x_preferred":[
        "San Mateo"
    ],
    "name:zho_x_preferred":[
        "\u8056\u99ac\u7279\u5967"
    ],
    "qs:name":"San Mateo",
    "qs:photos_9r":0,
    "qs:photos_sr":0,
    "qs:pop_sr":"9",
    "wd:wordcount":187,
    "wof:name":"San Mateo",
    "wof:placetype":"locality",
    "wof:population":134327
},
  "geometry": {"coordinates":[121.1236,14.6982],"type":"Point"}
}