{
  "type": "Feature",
  "properties": {
    "gn:admin1_code":"07",
    "gn:admin2_code":"11",
    "gn:admin3_code":"71209000.0",
    "gn:asciiname":"Hunan",
    "gn:country_code":"PH",
    "gn:dem":0,
    "gn:feature_class":"P",
    "gn:feature_code":"PPL",
    "gn:name":"Hunan",
    "gn:population":0,
    "gn:timezone":"Asia/Manila",
    "iso:country":"PH",
    "name:fil_x_preferred":[
        "Hunan"
    ],
    "wof:name":"Hunan",
    "wof:placetype":"locality"
},
  "geometry": {"coordinates":[124.12372999999999,10.08323],"type":"Point"}
}