{
  "type": "Feature",
  "properties": {
    "gn:admin1_code":"02",
    "gn:admin2_code":"14",
    "gn:admin3_code":"21510000.0",
    "gn:asciiname":"Dacal-Lafugu",
    "gn:country_code":"PH",
    "gn:dem":6,
    "gn:feature_class":"P",
    "gn:feature_code":"PPL",
    "gn:name":"Dacal-Lafugu",
    "gn:population":0,
    "gn:timezone":"Asia/Manila",
    "iso:country":"PH",
    "name:fil_x_preferred":[
        "Dacal Fugu"
    ],
    "name:fil_x_variant":[
        "Dacal-Lafugu",
        "Dacal-a-fugu"
    ],
    "name:und_x_variant":[
        "Dacal-a-fugu"
    ],
    "wof:name":"Dacal-Lafugu",
    "wof:placetype":"locality"
},
  "geometry": {"coordinates":[121.67829999999999,18.27],"type":"Point"}
}