{
  "type": "Feature",
  "properties": {
    "gn:admin1_code":"08",
    "gn:admin2_code":"55",
    "gn:admin3_code":"86025000.0",
    "gn:asciiname":"Bahay",
    "gn:country_code":"PH",
    "gn:dem":26,
    "gn:feature_class":"P",
    "gn:feature_code":"PPL",
    "gn:name":"Bahay",
    "gn:population":0,
    "gn:timezone":"Asia/Manila",
    "iso:country":"PH",
    "name:fil_x_preferred":[
        "Bahay"
    ],
    "wof:name":"Bahay",
    "wof:placetype":"locality"
},
  "geometry": {"coordinates":[124.83,11.92278],"type":"Point"}
}