{
  "type": "Feature",
  "properties": {
    "gn:admin1_code":"06",
    "gn:admin2_code":"30",
    "gn:admin3_code":"63016000.0",
    "gn:asciiname":"Tabugon",
    "gn:country_code":"PH",
    "gn:dem":59,
    "gn:feature_class":"P",
    "gn:feature_code":"PPL",
    "gn:name":"Tabugon",
    "gn:population":0,
    "gn:timezone":"Asia/Manila",
    "iso:country":"PH",
    "name:fil_x_preferred":[
        "Tabugon"
    ],
    "wof:name":"Tabugon",
    "wof:placetype":"locality"
},
  "geometry": {"coordinates":[122.6172,11.0216],"type":"Point"}
}