{
  "type": "Feature",
  "properties": {
    "gn:admin1_code":"11",
    "gn:admin2_code":"25",
    "gn:admin3_code":"112402000.0",
    "gn:asciiname":"Binugao",
    "gn:cc2":"PH",
    "gn:country_code":"PH",
    "gn:dem":24,
    "gn:feature_class":"P",
    "gn:feature_code":"PPL",
    "gn:name":"Binugao",
    "gn:population":0,
    "gn:timezone":"Asia/Manila",
    "iso:country":"PH",
    "name:und_x_variant":[
        "Binagao"
    ],
    "wof:name":"Binugao",
    "wof:placetype":"locality"
},
  "geometry": {"coordinates":[125.47778,6.97639],"type":"Point"}
}