{
  "type": "Feature",
  "properties": {
    "gn:admin1_code":"06",
    "gn:admin2_code":"H3",
    "gn:admin3_code":"64521000.0",
    "gn:asciiname":"Cambaros Dacu",
    "gn:country_code":"PH",
    "gn:dem":46,
    "gn:feature_class":"P",
    "gn:feature_code":"PPL",
    "gn:name":"Cambaros Dacu",
    "gn:population":0,
    "gn:timezone":"Asia/Manila",
    "iso:country":"PH",
    "name:fil_x_preferred":[
        "Cambaros Dacu"
    ],
    "name:und_x_variant":[
        "Cambaros"
    ],
    "wof:name":"Cambaros Dacu",
    "wof:placetype":"locality"
},
  "geometry": {"coordinates":[122.9391,10.3418],"type":"Point"}
}