{
  "type": "Feature",
  "properties": {
    "gn:admin1_code":"NCR",
    "gn:admin2_code":"137400000",
    "gn:admin3_code":"137402000.0",
    "gn:asciiname":"Concepcion Dos",
    "gn:country_code":"PH",
    "gn:dem":14,
    "gn:feature_class":"P",
    "gn:feature_code":"PPL",
    "gn:name":"Concepcion Dos",
    "gn:population":0,
    "gn:timezone":"Asia/Manila",
    "iso:country":"PH",
    "name:fil_x_preferred":[
        "Concepcion 2"
    ],
    "name:fil_x_variant":[
        "Concepcion II"
    ],
    "wof:name":"Concepcion Dos",
    "wof:placetype":"locality"
},
  "geometry": {"coordinates":[121.111,14.63794],"type":"Point"}
}