{
  "type": "Feature",
  "properties": {
    "gn:admin1_code":"41",
    "gn:admin2_code":"40",
    "gn:admin3_code":"175101000.0",
    "gn:asciiname":"Matabang",
    "gn:country_code":"PH",
    "gn:dem":9,
    "gn:feature_class":"P",
    "gn:feature_code":"PPL",
    "gn:name":"Matabang",
    "gn:population":0,
    "gn:timezone":"Asia/Manila",
    "iso:country":"PH",
    "name:eng_x_preferred":[
        "Matabang"
    ],
    "wof:name":"Matabang",
    "wof:placetype":"locality"
},
  "geometry": {"coordinates":[120.7662,13.4628],"type":"Point"}
}