{
  "type": "Feature",
  "properties": {
    "gn:admin1_code":"00",
    "gn:admin2_code":"A2",
    "gn:asciiname":"Macatul",
    "gn:country_code":"PH",
    "gn:dem":1,
    "gn:feature_class":"P",
    "gn:feature_code":"PPL",
    "gn:name":"Macatul",
    "gn:population":0,
    "gn:timezone":"Asia/Manila",
    "iso:country":"PH",
    "wof:name":"Macatul",
    "wof:placetype":"locality"
},
  "geometry": {"coordinates":[122.91667,10.63333],"type":"Point"}
}