{
  "type": "Feature",
  "properties": {
    "gn:admin1_code":"40",
    "gn:admin2_code":"H2",
    "gn:admin3_code":"45606000.0",
    "gn:asciiname":"Pamagijan",
    "gn:country_code":"PH",
    "gn:dem":50,
    "gn:feature_class":"P",
    "gn:feature_code":"PPL",
    "gn:name":"Pamagijan",
    "gn:population":0,
    "gn:timezone":"Asia/Manila",
    "iso:country":"PH",
    "name:fil_x_preferred":[
        "Pamagijan"
    ],
    "name:fil_x_variant":[
        "Pamogijan"
    ],
    "wof:name":"Pamagijan",
    "wof:placetype":"locality"
},
  "geometry": {"coordinates":[121.98568,14.91358],"type":"Point"}
}