{
  "type": "Feature",
  "properties": {
    "gn:admin1_code":"15",
    "gn:admin2_code":"27",
    "gn:admin3_code":"142710000.0",
    "gn:asciiname":"Lusod",
    "gn:country_code":"PH",
    "gn:dem":1269,
    "gn:feature_class":"P",
    "gn:feature_code":"PPL",
    "gn:name":"Lusod",
    "gn:population":0,
    "gn:timezone":"Asia/Manila",
    "iso:country":"PH",
    "name:fil_x_preferred":[
        "Lusod"
    ],
    "wof:name":"Lusod",
    "wof:placetype":"locality"
},
  "geometry": {"coordinates":[120.95404000000001,16.60318],"type":"Point"}
}