{
  "type": "Feature",
  "properties": {
    "gn:admin1_code":"14",
    "gn:admin2_code":"60",
    "gn:admin3_code":"156619000.0",
    "gn:asciiname":"Taguias",
    "gn:country_code":"PH",
    "gn:dem":57,
    "gn:feature_class":"P",
    "gn:feature_code":"PPL",
    "gn:name":"Taguias",
    "gn:population":0,
    "gn:timezone":"Asia/Manila",
    "iso:country":"PH",
    "name:fil_x_preferred":[
        "Taguias"
    ],
    "wof:name":"Taguias",
    "wof:placetype":"locality"
},
  "geometry": {"coordinates":[121.38556,5.99583],"type":"Point"}
}