{
  "type": "Feature",
  "properties": {
    "gn:admin1_code":"05",
    "gn:admin2_code":"58",
    "gn:admin3_code":"56205000.0",
    "gn:asciiname":"Tiris",
    "gn:country_code":"PH",
    "gn:dem":39,
    "gn:feature_class":"P",
    "gn:feature_code":"PPL",
    "gn:name":"Tiris",
    "gn:population":0,
    "gn:timezone":"Asia/Manila",
    "iso:country":"PH",
    "name:fil_x_preferred":[
        "Tiris"
    ],
    "wof:name":"Tiris",
    "wof:placetype":"locality"
},
  "geometry": {"coordinates":[124.02889999999999,12.869],"type":"Point"}
}