{
  "type": "Feature",
  "properties": {
    "gn:admin1_code":"15",
    "gn:admin2_code":"32",
    "gn:admin3_code":"143209000.0",
    "gn:asciiname":"Baguan",
    "gn:country_code":"PH",
    "gn:dem":628,
    "gn:feature_class":"P",
    "gn:feature_code":"PPL",
    "gn:name":"Baguan",
    "gn:population":0,
    "gn:timezone":"Asia/Manila",
    "iso:country":"PH",
    "name:fil_x_preferred":[
        "Baguan"
    ],
    "wof:name":"Baguan",
    "wof:placetype":"locality"
},
  "geometry": {"coordinates":[121.2945,17.4729],"type":"Point"}
}