{
  "type": "Feature",
  "properties": {
    "gn:admin1_code":"15",
    "gn:admin2_code":"10",
    "gn:admin3_code":"141114000.0",
    "gn:asciiname":"Chicao",
    "gn:country_code":"PH",
    "gn:dem":1118,
    "gn:feature_class":"P",
    "gn:feature_code":"PPL",
    "gn:name":"Chicao",
    "gn:population":0,
    "gn:timezone":"Asia/Manila",
    "iso:country":"PH",
    "name:fil_x_preferred":[
        "Chagao"
    ],
    "name:fil_x_variant":[
        "Chicao"
    ],
    "wof:name":"Chicao",
    "wof:placetype":"locality"
},
  "geometry": {"coordinates":[120.63509999999999,16.5124],"type":"Point"}
}