{
  "type": "Feature",
  "properties": {
    "gn:admin1_code":"07",
    "gn:admin2_code":"69",
    "gn:admin3_code":"76105000.0",
    "gn:asciiname":"Taguibo",
    "gn:country_code":"PH",
    "gn:dem":32,
    "gn:feature_class":"P",
    "gn:feature_code":"PPL",
    "gn:name":"Taguibo",
    "gn:population":0,
    "gn:timezone":"Asia/Manila",
    "iso:country":"PH",
    "name:fil_x_preferred":[
        "Tag-ibo"
    ],
    "wof:name":"Taguibo",
    "wof:placetype":"locality"
},
  "geometry": {"coordinates":[123.5338,9.1315],"type":"Point"}
}