{
  "type": "Feature",
  "properties": {
    "gn:admin1_code":"02",
    "gn:admin2_code":"14",
    "gn:admin3_code":"21504000.0",
    "gn:asciiname":"Agguirit",
    "gn:country_code":"PH",
    "gn:dem":16,
    "gn:feature_class":"P",
    "gn:feature_code":"PPL",
    "gn:name":"Agguirit",
    "gn:population":0,
    "gn:timezone":"Asia/Manila",
    "iso:country":"PH",
    "name:fil_x_preferred":[
        "Agguirit"
    ],
    "wof:name":"Agguirit",
    "wof:placetype":"locality"
},
  "geometry": {"coordinates":[121.68749,17.76202],"type":"Point"}
}