{
  "type": "Feature",
  "properties": {
    "gn:admin1_code":"07",
    "gn:admin2_code":"11",
    "gn:admin3_code":"71244000.0",
    "gn:asciiname":"Guinobatan",
    "gn:country_code":"PH",
    "gn:dem":11,
    "gn:feature_class":"P",
    "gn:feature_code":"PPL",
    "gn:name":"Guinobatan",
    "gn:population":0,
    "gn:timezone":"Asia/Manila",
    "iso:country":"PH",
    "name:fil_x_preferred":[
        "Ginobatan"
    ],
    "name:und_x_variant":[
        "Ginobatan",
        "Guinobatan"
    ],
    "wof:name":"Guinobatan",
    "wof:placetype":"locality"
},
  "geometry": {"coordinates":[124.37774,10.06077],"type":"Point"}
}