{
  "type": "Feature",
  "properties": {
    "gn:admin1_code":"07",
    "gn:admin2_code":"11",
    "gn:admin3_code":"71244000.0",
    "gn:asciiname":"Guinobatan",
    "gn:country_code":"PH",
    "gn:dem":11,
    "gn:feature_class":"P",
    "gn:feature_code":"PPL",
    "gn:name":"Guinobatan",
    "gn:population":0,
    "gn:timezone":"Asia/Manila",
    "iso:country":"PH",
    "name:bcl_x_preferred":[
        "Guinobatan"
    ],
    "name:ceb_x_preferred":[
        "Guinobatan"
    ],
    "name:deu_x_preferred":[
        "Guinobatan"
    ],
    "name:fil_x_preferred":[
        "Ginobatan"
    ],
    "name:fra_x_preferred":[
        "Guinobatan"
    ],
    "name:gor_x_preferred":[
        "Guinobatan"
    ],
    "name:ilo_x_preferred":[
        "Guinobatan"
    ],
    "name:ind_x_preferred":[
        "Guinobatan"
    ],
    "name:ita_x_preferred":[
        "Guinobatan"
    ],
    "name:nld_x_preferred":[
        "Guinobatan"
    ],
    "name:nor_x_preferred":[
        "Guinobatan"
    ],
    "name:pag_x_preferred":[
        "Guinobatan"
    ],
    "name:pam_x_preferred":[
        "Guinobatan"
    ],
    "name:swe_x_preferred":[
        "Guinobatan"
    ],
    "name:tgl_x_preferred":[
        "Guinobatan"
    ],
    "name:und_x_variant":[
        "Ginobatan",
        "Guinobatan"
    ],
    "name:urd_x_preferred":[
        "\u06af\u0648\u06cc\u0646\u0648\u0628\u0627\u062a\u0627\u0646"
    ],
    "name:vie_x_preferred":[
        "Guinobatan"
    ],
    "name:war_x_preferred":[
        "Guinobatan"
    ],
    "wof:name":"Guinobatan",
    "wof:placetype":"locality"
},
  "geometry": {"coordinates":[124.37774,10.06077],"type":"Point"}
}