{
  "type": "Feature",
  "properties": {
    "gn:admin1_code":"03",
    "gn:admin2_code":"63",
    "gn:admin3_code":"36904000.0",
    "gn:asciiname":"Santo Domingo Second",
    "gn:country_code":"PH",
    "gn:dem":54,
    "gn:feature_class":"P",
    "gn:feature_code":"PPL",
    "gn:name":"Santo Domingo Second",
    "gn:population":0,
    "gn:timezone":"Asia/Manila",
    "iso:country":"PH",
    "name:und_x_variant":[
        "Santo Domingo Segundo"
    ],
    "wof:name":"Santo Domingo Second",
    "wof:placetype":"locality"
},
  "geometry": {"coordinates":[120.59129,15.34722],"type":"Point"}
}