{
  "type": "Feature",
  "properties": {
    "gn:admin1_code":"08",
    "gn:admin2_code":"67",
    "gn:admin3_code":"84815000.0",
    "gn:asciiname":"Batu",
    "gn:country_code":"PH",
    "gn:dem":8,
    "gn:feature_class":"P",
    "gn:feature_code":"PPL",
    "gn:name":"Batu",
    "gn:population":0,
    "gn:timezone":"Asia/Manila",
    "iso:country":"PH",
    "name:cat_x_preferred":[
        "Batu"
    ],
    "name:ceb_x_preferred":[
        "Batu"
    ],
    "name:deu_x_preferred":[
        "Batu"
    ],
    "name:fil_x_preferred":[
        "Batu"
    ],
    "name:fin_x_preferred":[
        "Batu"
    ],
    "name:fra_x_preferred":[
        "Batu"
    ],
    "name:hrv_x_preferred":[
        "Batu"
    ],
    "name:ind_x_preferred":[
        "Batu"
    ],
    "name:kor_x_preferred":[
        "\ubc14\ud22c"
    ],
    "name:msa_x_preferred":[
        "Batu"
    ],
    "name:nld_x_preferred":[
        "Batu"
    ],
    "name:pol_x_preferred":[
        "Batu"
    ],
    "name:por_x_preferred":[
        "Batu"
    ],
    "name:spa_x_preferred":[
        "Batu"
    ],
    "name:swe_x_preferred":[
        "Batu"
    ],
    "wof:name":"Batu",
    "wof:placetype":"locality"
},
  "geometry": {"coordinates":[124.9097,12.5429],"type":"Point"}
}