{
  "type": "Feature",
  "properties": {
    "gn:admin1_code":"03",
    "gn:admin2_code":"47",
    "gn:admin3_code":"34922000.0",
    "gn:asciiname":"Santo Rosario",
    "gn:country_code":"PH",
    "gn:dem":35,
    "gn:feature_class":"P",
    "gn:feature_code":"PPL",
    "gn:name":"Santo Rosario",
    "gn:population":0,
    "gn:timezone":"Asia/Manila",
    "iso:country":"PH",
    "name:ceb_x_preferred":[
        "Santo Rosario"
    ],
    "name:fil_x_preferred":[
        "Santo Rosario"
    ],
    "wof:name":"Santo Rosario",
    "wof:placetype":"locality"
},
  "geometry": {"coordinates":[120.8677,15.5623],"type":"Point"}
}