{
  "type": "Feature",
  "properties": {
    "gn:admin1_code":"03",
    "gn:admin2_code":"47",
    "gn:admin3_code":"34930000.0",
    "gn:asciiname":"Caputican",
    "gn:country_code":"PH",
    "gn:dem":65,
    "gn:feature_class":"P",
    "gn:feature_code":"PPL",
    "gn:name":"Caputican",
    "gn:population":0,
    "gn:timezone":"Asia/Manila",
    "iso:country":"PH",
    "name:fil_x_preferred":[
        "Kaputikan"
    ],
    "name:fil_x_variant":[
        "Kaputatan Munti"
    ],
    "name:und_x_variant":[
        "Kaputatan Munti",
        "Kaputikan",
        "Caputican"
    ],
    "wof:name":"Caputican",
    "wof:placetype":"locality"
},
  "geometry": {"coordinates":[120.9795,15.66229],"type":"Point"}
}