{
  "type": "Feature",
  "properties": {
    "gn:admin1_code":"15",
    "gn:admin2_code":"10",
    "gn:admin3_code":"141108000.0",
    "gn:asciiname":"Bileng-Belis",
    "gn:country_code":"PH",
    "gn:dem":1224,
    "gn:feature_class":"P",
    "gn:feature_code":"PPL",
    "gn:name":"Bileng-Belis",
    "gn:population":0,
    "gn:timezone":"Asia/Manila",
    "iso:country":"PH",
    "name:fil_x_preferred":[
        "Bileng-Belis"
    ],
    "wof:name":"Bileng-Belis",
    "wof:placetype":"locality"
},
  "geometry": {"coordinates":[120.6404,16.6507],"type":"Point"}
}