{
  "type": "Feature",
  "properties": {
    "gn:admin1_code":"03",
    "gn:admin2_code":"G8",
    "gn:admin3_code":"37702000.0",
    "gn:asciiname":"Calancuasan",
    "gn:country_code":"PH",
    "gn:dem":9,
    "gn:feature_class":"P",
    "gn:feature_code":"PPL",
    "gn:name":"Calancuasan",
    "gn:population":0,
    "gn:timezone":"Asia/Manila",
    "iso:country":"PH",
    "name:fil_x_preferred":[
        "Calancuasan"
    ],
    "name:und_x_variant":[
        "Calangcuasan"
    ],
    "wof:name":"Calancuasan",
    "wof:placetype":"locality"
},
  "geometry": {"coordinates":[122.1097,16.2699],"type":"Point"}
}