{
  "type": "Feature",
  "properties": {
    "gn:admin1_code":"10",
    "gn:admin2_code":"43",
    "gn:admin3_code":"104308000.0",
    "gn:asciiname":"Pangasihan",
    "gn:cc2":"PH",
    "gn:country_code":"PH",
    "gn:dem":13,
    "gn:feature_class":"P",
    "gn:feature_code":"PPL",
    "gn:name":"Pangasihan",
    "gn:population":0,
    "gn:timezone":"Asia/Manila",
    "iso:country":"PH",
    "name:und_x_variant":[
        "Pangasiban",
        "Pangasihan"
    ],
    "wof:name":"Pangasihan",
    "wof:placetype":"locality"
},
  "geometry": {"coordinates":[125.17028000000001,8.86417],"type":"Point"}
}