{
  "type": "Feature",
  "properties": {
    "gn:admin1_code":"07",
    "gn:admin2_code":"11",
    "gn:admin3_code":"71208000.0",
    "gn:asciiname":"Canmuga",
    "gn:country_code":"PH",
    "gn:dem":363,
    "gn:feature_class":"P",
    "gn:feature_code":"PPL",
    "gn:name":"Canmuga",
    "gn:population":0,
    "gn:timezone":"Asia/Manila",
    "iso:country":"PH",
    "name:fil_x_preferred":[
        "Canmuga"
    ],
    "wof:name":"Canmuga",
    "wof:placetype":"locality"
},
  "geometry": {"coordinates":[124.11667,9.76667],"type":"Point"}
}