{
  "type": "Feature",
  "properties": {
    "gn:admin1_code":"02",
    "gn:admin2_code":"48",
    "gn:asciiname":"Ansipsip",
    "gn:country_code":"PH",
    "gn:dem":1694,
    "gn:feature_class":"P",
    "gn:feature_code":"PPL",
    "gn:name":"Ansipsip",
    "gn:population":0,
    "gn:timezone":"Asia/Manila",
    "iso:country":"PH",
    "name:eng_x_preferred":[
        "Ansipsip"
    ],
    "wof:name":"Ansipsip",
    "wof:placetype":"locality"
},
  "geometry": {"coordinates":[120.81019999999999,16.3062],"type":"Point"}
}