{
  "type": "Feature",
  "properties": {
    "gn:admin1_code":"03",
    "gn:admin2_code":"64",
    "gn:admin3_code":"37113000.0",
    "gn:asciiname":"Tubo-Tubo North",
    "gn:country_code":"PH",
    "gn:dem":6,
    "gn:feature_class":"P",
    "gn:feature_code":"PPL",
    "gn:name":"Tubo-Tubo North",
    "gn:population":0,
    "gn:timezone":"Asia/Manila",
    "iso:country":"PH",
    "name:eng_x_preferred":[
        "Tubo-Tubo North"
    ],
    "name:und_x_variant":[
        "Tubotubo"
    ],
    "wof:name":"Tubo-Tubo North",
    "wof:placetype":"locality"
},
  "geometry": {"coordinates":[119.9205,15.7588],"type":"Point"}
}