{
  "type": "Feature",
  "properties": {
    "gn:country":"PH",
    "gn:fcode":"PPL",
    "gn:population":3064,
    "iso:country":"PH",
    "name:fil_x_preferred":[
        "San Alejandro"
    ],
    "qs:name":"San Alejandro",
    "qs:photos_9r":0,
    "qs:photos_sr":0,
    "qs:pop_sr":"4",
    "wof:name":"San Alejandro",
    "wof:placetype":"locality",
    "wof:population":3064
},
  "geometry": {"coordinates":[120.8601,15.5497],"type":"Point"}
}