{
  "type": "Feature",
  "properties": {
    "gn:admin1_code":"40",
    "gn:admin2_code":"H2",
    "gn:admin3_code":"45617000.0",
    "gn:asciiname":"Idjang",
    "gn:country_code":"PH",
    "gn:dem":18,
    "gn:feature_class":"P",
    "gn:feature_code":"PPL",
    "gn:name":"Idjang",
    "gn:population":0,
    "gn:timezone":"Asia/Manila",
    "iso:country":"PH",
    "name:fil_x_preferred":[
        "Idjang"
    ],
    "wof:name":"Idjang",
    "wof:placetype":"locality"
},
  "geometry": {"coordinates":[121.4212,15.1947],"type":"Point"}
}