{
  "type": "Feature",
  "properties": {
    "gn:country":"PH",
    "gn:fcode":"PPL",
    "gn:pop":2178,
    "iso:country":"PH",
    "name:fil_x_preferred":[
        "Basud"
    ],
    "qs:name":"Basud",
    "qs:photos_9r":0,
    "qs:photos_sr":0,
    "qs:pop_sr":"4",
    "wof:name":"Basud",
    "wof:placetype":"locality",
    "wof:population":2178
},
  "geometry": {"coordinates":[123.95,12.98889],"type":"Point"}
}