{
  "type": "Feature",
  "properties": {
    "gn:country":"PH",
    "gn:fcode":"PPL",
    "gn:pop":2178,
    "iso:country":"PH",
    "name:bcl_x_preferred":[
        "Basud"
    ],
    "name:ceb_x_preferred":[
        "Basud"
    ],
    "name:deu_x_preferred":[
        "Basud"
    ],
    "name:fil_x_preferred":[
        "Basud"
    ],
    "name:fra_x_preferred":[
        "Basud"
    ],
    "name:gor_x_preferred":[
        "Basud"
    ],
    "name:ilo_x_preferred":[
        "Basud"
    ],
    "name:ind_x_preferred":[
        "Basud"
    ],
    "name:ita_x_preferred":[
        "Basud"
    ],
    "name:nld_x_preferred":[
        "Basud"
    ],
    "name:nor_x_preferred":[
        "Basud"
    ],
    "name:pag_x_preferred":[
        "Basud"
    ],
    "name:pam_x_preferred":[
        "Basud"
    ],
    "name:swe_x_preferred":[
        "Basud"
    ],
    "name:tgl_x_preferred":[
        "Basud"
    ],
    "name:war_x_preferred":[
        "Basud"
    ],
    "qs:name":"Basud",
    "qs:photos_9r":0,
    "qs:photos_sr":0,
    "qs:pop_sr":"4",
    "wof:name":"Basud",
    "wof:placetype":"locality",
    "wof:population":2178
},
  "geometry": {"coordinates":[123.95,12.98889],"type":"Point"}
}