{
  "type": "Feature",
  "properties": {
    "gn:admin1_code":"07",
    "gn:admin2_code":"21",
    "gn:admin3_code":"72219000.0",
    "gn:asciiname":"Pitogo",
    "gn:country_code":"PH",
    "gn:dem":3,
    "gn:feature_class":"P",
    "gn:feature_code":"PPL",
    "gn:name":"Pitogo",
    "gn:population":0,
    "gn:timezone":"Asia/Manila",
    "iso:country":"PH",
    "name:ceb_x_preferred":[
        "Pitogo"
    ],
    "name:deu_x_preferred":[
        "Pitogo"
    ],
    "name:fil_x_preferred":[
        "Pitogo"
    ],
    "name:ita_x_preferred":[
        "Pitogo"
    ],
    "name:nld_x_preferred":[
        "Pitogo"
    ],
    "name:war_x_preferred":[
        "Pitogo"
    ],
    "wof:name":"Pitogo",
    "wof:placetype":"locality"
},
  "geometry": {"coordinates":[123.97063,10.38481],"type":"Point"}
}