{
  "type": "Feature",
  "properties": {
    "gn:admin1_code":"08",
    "gn:admin2_code":"59",
    "gn:admin3_code":"86404000.0",
    "gn:asciiname":"Amaga",
    "gn:cc2":"PH",
    "gn:country_code":"PH",
    "gn:dem":205,
    "gn:feature_class":"P",
    "gn:feature_code":"PPL",
    "gn:name":"Amaga",
    "gn:population":0,
    "gn:timezone":"Asia/Manila",
    "iso:country":"PH",
    "name:und_x_variant":[
        "Omaga",
        "Amaga"
    ],
    "wof:name":"Amaga",
    "wof:placetype":"locality"
},
  "geometry": {"coordinates":[125.23333,10.31667],"type":"Point"}
}