{
  "type": "Feature",
  "properties": {
    "gn:admin1_code":"06",
    "gn:admin2_code":"H3",
    "gn:admin3_code":"64528000.0",
    "gn:asciiname":"Hacienda Esmeralda",
    "gn:country_code":"PH",
    "gn:dem":141,
    "gn:feature_class":"P",
    "gn:feature_code":"PPL",
    "gn:name":"Hacienda Esmeralda",
    "gn:population":0,
    "gn:timezone":"Asia/Manila",
    "iso:country":"PH",
    "name:fil_x_preferred":[
        "Hacienda Esmeralda"
    ],
    "name:fil_x_variant":[
        "Esmeralda Hacienda"
    ],
    "wof:name":"Hacienda Esmeralda",
    "wof:placetype":"locality"
},
  "geometry": {"coordinates":[123.0718,10.7184],"type":"Point"}
}