{
  "type": "Feature",
  "properties": {
    "gn:admin1_code":"03",
    "gn:admin2_code":"13",
    "gn:admin3_code":"31409000.0",
    "gn:asciiname":"Tibanguin",
    "gn:country_code":"PH",
    "gn:dem":6,
    "gn:feature_class":"P",
    "gn:feature_code":"PPL",
    "gn:name":"Tibanguin",
    "gn:population":0,
    "gn:timezone":"Asia/Manila",
    "iso:country":"PH",
    "wof:name":"Tibanguin",
    "wof:placetype":"locality"
},
  "geometry": {"coordinates":[120.754,14.77232],"type":"Point"}
}