{
  "type": "Feature",
  "properties": {
    "gn:country":"PH",
    "gn:fcode":"PPL",
    "gn:population":2468,
    "iso:country":"PH",
    "name:und_x_variant":[
        "Punol"
    ],
    "qs:name":"Punolu",
    "qs:photos_9r":0,
    "qs:photos_sr":0,
    "qs:pop_sr":"4",
    "wof:name":"Punolu",
    "wof:placetype":"locality",
    "wof:population":2468
},
  "geometry": {"coordinates":[124.58333,7.05],"type":"Point"}
}