{
  "type": "Feature",
  "properties": {
    "gn:country":"PH",
    "gn:fcode":"PPL",
    "gn:pop":3169,
    "iso:country":"PH",
    "name:fil_x_preferred":[
        "Malaruhatan"
    ],
    "qs:name":"Malaruhatan",
    "qs:photos_9r":0,
    "qs:photos_sr":0,
    "qs:pop_sr":"4",
    "wof:name":"Malaruhatan",
    "wof:placetype":"locality",
    "wof:population":3169
},
  "geometry": {"coordinates":[120.68040000000001,14.0306],"type":"Point"}
}