{
  "type": "Feature",
  "properties": {
    "gn:country":"PH",
    "gn:fcode":"PPL",
    "gn:pop":3663,
    "iso:country":"PH",
    "name:fil_x_preferred":[
        "Malocloc"
    ],
    "qs:name":"Malocloc",
    "qs:photos_9r":0,
    "qs:photos_sr":0,
    "qs:pop_sr":"4",
    "wof:name":"Malocloc",
    "wof:placetype":"locality",
    "wof:population":3663
},
  "geometry": {"coordinates":[122.67833,11.50583],"type":"Point"}
}