{
  "type": "Feature",
  "properties": {
    "gn:admin1_code":"02",
    "gn:admin2_code":"48",
    "gn:admin3_code":"25002000.0",
    "gn:asciiname":"Banila",
    "gn:country_code":"PH",
    "gn:dem":526,
    "gn:feature_class":"P",
    "gn:feature_code":"PPL",
    "gn:name":"Banila",
    "gn:population":0,
    "gn:timezone":"Asia/Manila",
    "iso:country":"PH",
    "name:fil_x_preferred":[
        "Banila"
    ],
    "name:jpn_x_preferred":[
        "\u30d0\u30cb\u30e9"
    ],
    "wof:name":"Banila",
    "wof:placetype":"locality"
},
  "geometry": {"coordinates":[121.06113999999999,16.1935],"type":"Point"}
}