{
  "type": "Feature",
  "properties": {
    "gn:admin1_code":"40",
    "gn:admin2_code":"F2",
    "gn:asciiname":"Marilag",
    "gn:country_code":"PH",
    "gn:dem":53,
    "gn:feature_class":"P",
    "gn:feature_code":"PPL",
    "gn:name":"Marilag",
    "gn:population":0,
    "gn:timezone":"Asia/Manila",
    "iso:country":"PH",
    "name:fil_x_preferred":[
        "Marilag"
    ],
    "wof:name":"Marilag",
    "wof:placetype":"locality"
},
  "geometry": {"coordinates":[121.0703,14.6211],"type":"Point"}
}