{
  "type": "Feature",
  "properties": {
    "gn:admin1_code":"07",
    "gn:admin2_code":"11",
    "gn:admin3_code":"71210000.0",
    "gn:asciiname":"Mandaug",
    "gn:country_code":"PH",
    "gn:dem":15,
    "gn:feature_class":"P",
    "gn:feature_code":"PPL",
    "gn:name":"Mandaug",
    "gn:population":0,
    "gn:timezone":"Asia/Manila",
    "iso:country":"PH",
    "name:fil_x_preferred":[
        "Mandaug"
    ],
    "wof:name":"Mandaug",
    "wof:placetype":"locality"
},
  "geometry": {"coordinates":[123.9114,9.9058],"type":"Point"}
}