{
  "type": "Feature",
  "properties": {
    "gn:admin1_code":"01",
    "gn:admin2_code":"28",
    "gn:admin3_code":"12812000.0",
    "gn:asciiname":"Tangid",
    "gn:country_code":"PH",
    "gn:dem":11,
    "gn:feature_class":"P",
    "gn:feature_code":"PPL",
    "gn:name":"Tangid",
    "gn:population":0,
    "gn:timezone":"Asia/Manila",
    "iso:country":"PH",
    "name:fil_x_preferred":[
        "Tangid"
    ],
    "name:fil_x_variant":[
        "Tangib"
    ],
    "wof:name":"Tangid",
    "wof:placetype":"locality"
},
  "geometry": {"coordinates":[120.5692,18.1949],"type":"Point"}
}