{
  "type": "Feature",
  "properties": {
    "gn:admin1_code":"14",
    "gn:admin2_code":"22",
    "gn:admin3_code":"150702000.0",
    "gn:asciiname":"Yacan",
    "gn:country_code":"PH",
    "gn:dem":228,
    "gn:feature_class":"P",
    "gn:feature_code":"PPL",
    "gn:name":"Yacan",
    "gn:population":0,
    "gn:timezone":"Asia/Manila",
    "iso:country":"PH",
    "name:fil_x_preferred":[
        "Yacan"
    ],
    "wof:name":"Yacan",
    "wof:placetype":"locality"
},
  "geometry": {"coordinates":[122.19110999999999,6.57222],"type":"Point"}
}