{
  "type": "Feature",
  "properties": {
    "gn:country":"PH",
    "gn:fcode":"PPL",
    "gn:pop":3371,
    "iso:country":"PH",
    "name:fil_x_preferred":[
        "Bulihan"
    ],
    "qs:name":"Bulihan",
    "qs:photos_9r":0,
    "qs:photos_sr":0,
    "qs:pop_sr":"4",
    "wof:name":"Bulihan",
    "wof:placetype":"locality",
    "wof:population":3371
},
  "geometry": {"coordinates":[121.24850000000001,13.8091],"type":"Point"}
}