{
  "type": "Feature",
  "properties": {
    "gn:admin1_code":"12",
    "gn:admin2_code":"M9",
    "gn:admin3_code":"128001000.0",
    "gn:asciiname":"Lot",
    "gn:country_code":"PH",
    "gn:dem":13,
    "gn:feature_class":"P",
    "gn:feature_code":"PPL",
    "gn:name":"Lot",
    "gn:population":0,
    "gn:timezone":"Asia/Manila",
    "iso:country":"PH",
    "name:fil_x_preferred":[
        "Lot"
    ],
    "wof:name":"Lot",
    "wof:placetype":"locality"
},
  "geometry": {"coordinates":[125.25,6.11667],"type":"Point"}
}