{
  "type": "Feature",
  "properties": {
    "gn:admin1_code":"12",
    "gn:admin2_code":"M9",
    "gn:admin3_code":"128001000.0",
    "gn:asciiname":"Lot",
    "gn:country_code":"PH",
    "gn:dem":13,
    "gn:feature_class":"P",
    "gn:feature_code":"PPL",
    "gn:name":"Lot",
    "gn:population":0,
    "gn:timezone":"Asia/Manila",
    "iso:country":"PH",
    "name:ara_x_preferred":[
        "\u0644\u0648"
    ],
    "name:bre_x_preferred":[
        "Lot"
    ],
    "name:bul_x_preferred":[
        "\u041b\u043e\u0442"
    ],
    "name:cat_x_preferred":[
        "Lot"
    ],
    "name:ceb_x_preferred":[
        "Lot"
    ],
    "name:ces_x_preferred":[
        "Lot"
    ],
    "name:cym_x_preferred":[
        "Lot"
    ],
    "name:dan_x_preferred":[
        "Lot"
    ],
    "name:deu_x_preferred":[
        "Lot"
    ],
    "name:est_x_preferred":[
        "LOT"
    ],
    "name:eus_x_preferred":[
        "Lot"
    ],
    "name:fas_x_preferred":[
        "\u0644\u0648"
    ],
    "name:fil_x_preferred":[
        "Lot"
    ],
    "name:fin_x_preferred":[
        "Lot"
    ],
    "name:fra_x_preferred":[
        "Lot"
    ],
    "name:frr_x_preferred":[
        "Luad"
    ],
    "name:heb_x_preferred":[
        "\u05dc\u05d5\u05d8"
    ],
    "name:hun_x_preferred":[
        "Lot"
    ],
    "name:ind_x_preferred":[
        "Lot"
    ],
    "name:ita_x_preferred":[
        "LOT"
    ],
    "name:kaz_x_preferred":[
        "\u041b\u043e\u0442"
    ],
    "name:kur_x_preferred":[
        "L\u00fbt"
    ],
    "name:lim_x_preferred":[
        "Lot"
    ],
    "name:nld_x_preferred":[
        "Lot"
    ],
    "name:nno_x_preferred":[
        "Lot"
    ],
    "name:nor_x_preferred":[
        "Lot"
    ],
    "name:pol_x_preferred":[
        "Lot"
    ],
    "name:por_x_preferred":[
        "Lot"
    ],
    "name:rus_x_preferred":[
        "\u041b\u043e\u0442"
    ],
    "name:slk_x_preferred":[
        "Lot"
    ],
    "name:slv_x_preferred":[
        "Lot"
    ],
    "name:spa_x_preferred":[
        "Lot"
    ],
    "name:srp_x_preferred":[
        "\u041b\u043e\u0442"
    ],
    "name:swe_x_preferred":[
        "Lot"
    ],
    "name:tat_x_preferred":[
        "\u041b\u043e\u0442"
    ],
    "name:ukr_x_preferred":[
        "\u041b\u043e\u0442"
    ],
    "wof:name":"Lot",
    "wof:placetype":"locality"
},
  "geometry": {"coordinates":[125.25,6.11667],"type":"Point"}
}