{
  "type": "Feature",
  "properties": {
    "gn:country":"PH",
    "gn:fcode":"PPL",
    "gn:population":4710,
    "iso:country":"PH",
    "name:und_x_variant":[
        "Catidtuan"
    ],
    "qs:name":"Katidtuan",
    "qs:photos_9r":0,
    "qs:photos_sr":0,
    "qs:pop_sr":"4",
    "wof:name":"Katidtuan",
    "wof:placetype":"locality",
    "wof:population":4710
},
  "geometry": {"coordinates":[124.31528,7.18861],"type":"Point"}
}