{
  "type": "Feature",
  "properties": {
    "gn:admin1_code":"05",
    "gn:admin2_code":"16",
    "gn:admin3_code":"51724000.0",
    "gn:asciiname":"Concepcion",
    "gn:cc2":"PH",
    "gn:country_code":"PH",
    "gn:dem":10,
    "gn:feature_class":"P",
    "gn:feature_code":"PPL",
    "gn:name":"Concepcion",
    "gn:population":0,
    "gn:timezone":"Asia/Manila",
    "iso:country":"PH",
    "name:und_x_variant":[
        "Grande",
        "Concepcion VI"
    ],
    "wof:name":"Concepcion",
    "wof:placetype":"locality"
},
  "geometry": {"coordinates":[123.19833,13.62472],"type":"Point"}
}