{
  "type": "Feature",
  "properties": {
    "gn:admin1_code":"40",
    "gn:admin2_code":"33",
    "gn:admin3_code":"43430000.0",
    "gn:asciiname":"San Benito",
    "gn:country_code":"PH",
    "gn:dem":10,
    "gn:feature_class":"P",
    "gn:feature_code":"PPL",
    "gn:name":"San Benito",
    "gn:population":0,
    "gn:timezone":"Asia/Manila",
    "iso:country":"PH",
    "name:bre_x_preferred":[
        "San Benito"
    ],
    "name:cat_x_preferred":[
        "San Benito"
    ],
    "name:ceb_x_preferred":[
        "San Benito"
    ],
    "name:deu_x_preferred":[
        "San Benito"
    ],
    "name:fas_x_preferred":[
        "\u0633\u0646 \u0628\u0646\u06cc\u062a\u0648"
    ],
    "name:fil_x_preferred":[
        "San Benito"
    ],
    "name:fra_x_preferred":[
        "San Benito"
    ],
    "name:ita_x_preferred":[
        "San Benito"
    ],
    "name:lit_x_preferred":[
        "San Benitas"
    ],
    "name:nds_x_preferred":[
        "San Benito"
    ],
    "name:nld_x_preferred":[
        "San Benito"
    ],
    "name:pol_x_preferred":[
        "San Benito"
    ],
    "name:por_x_preferred":[
        "San Benito"
    ],
    "name:spa_x_preferred":[
        "San Benito"
    ],
    "name:srp_x_preferred":[
        "\u0421\u0430\u043d \u0411\u0435\u043d\u0438\u0442\u043e"
    ],
    "name:swe_x_preferred":[
        "San Benito"
    ],
    "name:ukr_x_preferred":[
        "\u0421\u0430\u043d-\u0411\u0435\u043d\u0456\u0442\u043e"
    ],
    "name:war_x_preferred":[
        "San Benito"
    ],
    "wof:name":"San Benito",
    "wof:placetype":"locality"
},
  "geometry": {"coordinates":[121.3233,14.1924],"type":"Point"}
}