{
  "type": "Feature",
  "properties": {
    "gn:admin1_code":"07",
    "gn:admin2_code":"21",
    "gn:admin3_code":"72205000.0",
    "gn:asciiname":"Alambijud",
    "gn:country_code":"PH",
    "gn:dem":423,
    "gn:feature_class":"P",
    "gn:feature_code":"PPL",
    "gn:name":"Alambijud",
    "gn:population":0,
    "gn:timezone":"Asia/Manila",
    "iso:country":"PH",
    "name:und_x_variant":[
        "Alambijod",
        "Alambihud"
    ],
    "wof:name":"Alambijud",
    "wof:placetype":"locality"
},
  "geometry": {"coordinates":[123.52382,9.94855],"type":"Point"}
}