{
  "type": "Feature",
  "properties": {
    "gn:admin1_code":"02",
    "gn:admin2_code":"31",
    "gn:admin3_code":"23125000.0",
    "gn:asciiname":"Labinab Grande",
    "gn:country_code":"PH",
    "gn:dem":55,
    "gn:feature_class":"P",
    "gn:feature_code":"PPL",
    "gn:name":"Labinab Grande",
    "gn:population":0,
    "gn:timezone":"Asia/Manila",
    "iso:country":"PH",
    "name:fil_x_preferred":[
        "Libenab Grande"
    ],
    "name:fil_x_variant":[
        "Labinab Grande"
    ],
    "wof:name":"Labinab Grande",
    "wof:placetype":"locality"
},
  "geometry": {"coordinates":[121.81366,16.98776],"type":"Point"}
}