{
  "type": "Feature",
  "properties": {
    "gn:country":"PH",
    "gn:fcode":"PPL",
    "gn:pop":2978,
    "iso:country":"PH",
    "name:fil_x_preferred":[
        "Malasugui"
    ],
    "name:unk_x_variant":[
        "Malasugui Lica"
    ],
    "qs:name":"Malasugui",
    "qs:photos_9r":0,
    "qs:photos_sr":0,
    "qs:pop_sr":"4",
    "wof:name":"Malasugui",
    "wof:placetype":"locality",
    "wof:population":2978
},
  "geometry": {"coordinates":[122.8471,14.1439],"type":"Point"}
}