{
  "type": "Feature",
  "properties": {
    "gn:country":"PH",
    "gn:fcode":"PPL",
    "gn:population":2219,
    "iso:country":"PH",
    "name:fil_x_preferred":[
        "Butigui"
    ],
    "name:fil_x_variant":[
        "Butiqui"
    ],
    "qs:name":"Butigui",
    "qs:photos_9r":0,
    "qs:photos_sr":0,
    "qs:pop_sr":"4",
    "wof:name":"Butigui",
    "wof:placetype":"locality",
    "wof:population":2219
},
  "geometry": {"coordinates":[121.43304000000001,17.11534],"type":"Point"}
}