{
  "type": "Feature",
  "properties": {
    "gn:admin1_code":"12",
    "gn:admin2_code":"M9",
    "gn:admin3_code":"128002000.0",
    "gn:asciiname":"Dongcaling",
    "gn:country_code":"PH",
    "gn:dem":37,
    "gn:feature_class":"P",
    "gn:feature_code":"PPL",
    "gn:name":"Dongcaling",
    "gn:population":0,
    "gn:timezone":"Asia/Manila",
    "iso:country":"PH",
    "name:fil_x_preferred":[
        "Dongcaling"
    ],
    "wof:name":"Dongcaling",
    "wof:placetype":"locality"
},
  "geometry": {"coordinates":[125.30110999999999,5.58306],"type":"Point"}
}