{
  "type": "Feature",
  "properties": {
    "gn:admin1_code":"14",
    "gn:admin2_code":"22",
    "gn:admin3_code":"150705000.0",
    "gn:asciiname":"Etub-Etub",
    "gn:country_code":"PH",
    "gn:dem":134,
    "gn:feature_class":"P",
    "gn:feature_code":"PPL",
    "gn:name":"Etub-Etub",
    "gn:population":0,
    "gn:timezone":"Asia/Manila",
    "iso:country":"PH",
    "name:fil_x_preferred":[
        "Etub-Etub"
    ],
    "wof:name":"Etub-Etub",
    "wof:placetype":"locality"
},
  "geometry": {"coordinates":[122.06528,6.43278],"type":"Point"}
}