{
  "type": "Feature",
  "properties": {
    "gn:country":"PH",
    "gn:fcode":"PPL",
    "gn:population":4491,
    "iso:country":"PH",
    "name:fil_x_preferred":[
        "Tinago"
    ],
    "qs:name":"Tinago",
    "qs:photos_9r":0,
    "qs:photos_sr":0,
    "qs:pop_sr":"4",
    "wof:name":"Tinago",
    "wof:placetype":"locality",
    "wof:population":4491
},
  "geometry": {"coordinates":[123.65000000000001,13.18333],"type":"Point"}
}