{
  "type": "Feature",
  "properties": {
    "gn:admin1_code":"01",
    "gn:admin2_code":"29",
    "gn:admin3_code":"12915000.0",
    "gn:asciiname":"Dagmam",
    "gn:country_code":"PH",
    "gn:dem":461,
    "gn:feature_class":"P",
    "gn:feature_code":"PPL",
    "gn:name":"Dagmam",
    "gn:population":0,
    "gn:timezone":"Asia/Manila",
    "iso:country":"PH",
    "name:fil_x_preferred":[
        "Dagmam"
    ],
    "wof:name":"Dagmam",
    "wof:placetype":"locality"
},
  "geometry": {"coordinates":[120.66667,17.11667000000001],"type":"Point"}
}