{
  "type": "Feature",
  "properties": {
    "gn:admin1_code":"14",
    "gn:admin2_code":"60",
    "gn:admin3_code":"156609000.0",
    "gn:asciiname":"Lagasan",
    "gn:country_code":"PH",
    "gn:dem":26,
    "gn:feature_class":"P",
    "gn:feature_code":"PPL",
    "gn:name":"Lagasan",
    "gn:population":0,
    "gn:timezone":"Asia/Manila",
    "iso:country":"PH",
    "name:eng_x_preferred":[
        "Lagasan"
    ],
    "name:und_x_variant":[
        "Marasan"
    ],
    "wof:name":"Lagasan",
    "wof:placetype":"locality"
},
  "geometry": {"coordinates":[120.9509,5.9025],"type":"Point"}
}