{
  "type": "Feature",
  "properties": {
    "gn:admin1_code":"07",
    "gn:admin2_code":"46",
    "gn:admin3_code":"74623000.0",
    "gn:asciiname":"Jawa",
    "gn:country_code":"PH",
    "gn:dem":227,
    "gn:feature_class":"P",
    "gn:feature_code":"PPL",
    "gn:name":"Jawa",
    "gn:population":0,
    "gn:timezone":"Asia/Manila",
    "iso:country":"PH",
    "name:ceb_x_preferred":[
        "Jawa"
    ],
    "name:dan_x_preferred":[
        "Jawa"
    ],
    "name:deu_x_preferred":[
        "Jawa"
    ],
    "name:fas_x_preferred":[
        "\u062c\u0627\u0648\u0647"
    ],
    "name:fil_x_preferred":[
        "Jawa"
    ],
    "name:fra_x_preferred":[
        "Jawa"
    ],
    "name:hun_x_preferred":[
        "Jawa"
    ],
    "name:ind_x_preferred":[
        "Jawa"
    ],
    "name:ita_x_preferred":[
        "Jawa"
    ],
    "name:min_x_preferred":[
        "Jawa"
    ],
    "name:nld_x_preferred":[
        "Jawa"
    ],
    "name:pol_x_preferred":[
        "Jawa"
    ],
    "name:sco_x_preferred":[
        "Jawa"
    ],
    "name:slv_x_preferred":[
        "Jawa"
    ],
    "name:spa_x_preferred":[
        "Jawa"
    ],
    "name:sun_x_preferred":[
        "Jawa"
    ],
    "name:swe_x_preferred":[
        "Jawa"
    ],
    "wof:name":"Jawa",
    "wof:placetype":"locality"
},
  "geometry": {"coordinates":[123.2467,9.2696],"type":"Point"}
}