{
  "type": "Feature",
  "properties": {
    "gn:admin1_code":"02",
    "gn:admin2_code":"31",
    "gn:admin3_code":"23137000.0",
    "gn:asciiname":"Sisim Alto",
    "gn:country_code":"PH",
    "gn:dem":44,
    "gn:feature_class":"P",
    "gn:feature_code":"PPL",
    "gn:name":"Sisim Alto",
    "gn:population":0,
    "gn:timezone":"Asia/Manila",
    "iso:country":"PH",
    "name:fil_x_preferred":[
        "Sisim Alto"
    ],
    "name:fil_x_variant":[
        "Sisim"
    ],
    "wof:name":"Sisim Alto",
    "wof:placetype":"locality"
},
  "geometry": {"coordinates":[121.85748999999998,17.27939],"type":"Point"}
}