{
  "type": "Feature",
  "properties": {
    "gn:country":"PH",
    "gn:fcode":"ADM3",
    "gn:pop":118807,
    "iso:country":"PH",
    "name:fil_x_preferred":[
        "San Jose"
    ],
    "name:unk_x_variant":[
        "Mangarin"
    ],
    "qs:name":"San Jose",
    "qs:photos_9r":0,
    "qs:photos_sr":0,
    "qs:pop_sr":"9",
    "wd:wordcount":802,
    "wof:name":"San Jose",
    "wof:placetype":"localadmin",
    "wof:population":118807
},
  "geometry": {"coordinates":[121.11667,12.45],"type":"Point"}
}