{
  "type": "Feature",
  "properties": {
    "gn:admin1_code":"15",
    "gn:admin2_code":"01",
    "gn:admin3_code":"140110000.0",
    "gn:asciiname":"Nagsayangan",
    "gn:country_code":"PH",
    "gn:dem":99,
    "gn:feature_class":"P",
    "gn:feature_code":"PPL",
    "gn:name":"Nagsayangan",
    "gn:population":0,
    "gn:timezone":"Asia/Manila",
    "iso:country":"PH",
    "name:fil_x_preferred":[
        "Nagsayangan"
    ],
    "wof:name":"Nagsayangan",
    "wof:placetype":"locality"
},
  "geometry": {"coordinates":[120.7501,17.6035],"type":"Point"}
}