{
  "type": "Feature",
  "properties": {
    "gn:admin1_code":"07",
    "gn:admin2_code":"21",
    "gn:admin3_code":"72205000.0",
    "gn:asciiname":"Bug-ong",
    "gn:country_code":"PH",
    "gn:dem":389,
    "gn:feature_class":"P",
    "gn:feature_code":"PPL",
    "gn:name":"Bug-ong",
    "gn:population":0,
    "gn:timezone":"Asia/Manila",
    "iso:country":"PH",
    "wof:name":"Bug-ong",
    "wof:placetype":"locality"
},
  "geometry": {"coordinates":[123.53722999999999,9.90149],"type":"Point"}
}