{
  "type": "Feature",
  "properties": {
    "gn:admin1_code":"01",
    "gn:admin2_code":"51",
    "gn:admin3_code":"15526000.0",
    "gn:asciiname":"Osiem",
    "gn:country_code":"PH",
    "gn:dem":14,
    "gn:feature_class":"P",
    "gn:feature_code":"PPL",
    "gn:name":"Osiem",
    "gn:population":0,
    "gn:timezone":"Asia/Manila",
    "iso:country":"PH",
    "name:fil_x_preferred":[
        "Osiem"
    ],
    "wof:name":"Osiem",
    "wof:placetype":"locality"
},
  "geometry": {"coordinates":[120.42314,16.05917],"type":"Point"}
}