{
  "type": "Feature",
  "properties": {
    "gn:country":"PH",
    "gn:fcode":"PPL",
    "gn:pop":2133,
    "iso:country":"PH",
    "name:fil_x_preferred":[
        "Madalag"
    ],
    "name:unk_x_variant":[
        "Madolag"
    ],
    "qs:name":"Madalag",
    "qs:photos_9r":0,
    "qs:photos_sr":0,
    "qs:pop_sr":"4",
    "wof:name":"Madalag",
    "wof:placetype":"locality",
    "wof:population":2133
},
  "geometry": {"coordinates":[122.9828,10.89944],"type":"Point"}
}