{
  "type": "Feature",
  "properties": {
    "gn:country":"PH",
    "gn:fcode":"PPL",
    "gn:population":2133,
    "iso:country":"PH",
    "name:bcl_x_preferred":[
        "Madalag"
    ],
    "name:ceb_x_preferred":[
        "Madalag"
    ],
    "name:deu_x_preferred":[
        "Madalag"
    ],
    "name:fil_x_preferred":[
        "Madalag"
    ],
    "name:fra_x_preferred":[
        "Madalag"
    ],
    "name:ilo_x_preferred":[
        "Madalag"
    ],
    "name:ind_x_preferred":[
        "Madalag"
    ],
    "name:ita_x_preferred":[
        "Madalag"
    ],
    "name:nld_x_preferred":[
        "Madalag"
    ],
    "name:nor_x_preferred":[
        "Madalag"
    ],
    "name:pag_x_preferred":[
        "Madalag"
    ],
    "name:pam_x_preferred":[
        "Madalag"
    ],
    "name:swe_x_preferred":[
        "Madalag"
    ],
    "name:tgl_x_preferred":[
        "Madalag"
    ],
    "name:und_x_variant":[
        "Madolag"
    ],
    "name:urd_x_preferred":[
        "\u0645\u06cc\u062f\u0627\u0644\u0627\u06af"
    ],
    "name:vie_x_preferred":[
        "Madalag"
    ],
    "name:war_x_preferred":[
        "Madalag"
    ],
    "qs:name":"Madalag",
    "qs:photos_9r":0,
    "qs:photos_sr":0,
    "qs:pop_sr":"4",
    "wof:name":"Madalag",
    "wof:placetype":"locality",
    "wof:population":2133
},
  "geometry": {"coordinates":[122.9828,10.89944],"type":"Point"}
}