{
  "type": "Feature",
  "properties": {
    "gn:admin1_code":"13",
    "gn:admin2_code":"03",
    "gn:admin3_code":"160303000.0",
    "gn:asciiname":"Bunaguit",
    "gn:country_code":"PH",
    "gn:dem":56,
    "gn:feature_class":"P",
    "gn:feature_code":"PPL",
    "gn:name":"Bunaguit",
    "gn:population":0,
    "gn:timezone":"Asia/Manila",
    "iso:country":"PH",
    "name:fil_x_preferred":[
        "Bunaguit"
    ],
    "wof:name":"Bunaguit",
    "wof:placetype":"locality"
},
  "geometry": {"coordinates":[125.4875,8.61778],"type":"Point"}
}