{
  "type": "Feature",
  "properties": {
    "gn:admin1_code":"03",
    "gn:admin2_code":"47",
    "gn:admin3_code":"34929000.0",
    "gn:asciiname":"Pudiot",
    "gn:country_code":"PH",
    "gn:dem":58,
    "gn:feature_class":"P",
    "gn:feature_code":"PPL",
    "gn:name":"Pudiot",
    "gn:population":0,
    "gn:timezone":"Asia/Manila",
    "iso:country":"PH",
    "name:fil_x_preferred":[
        "Pudiot"
    ],
    "wof:name":"Pudiot",
    "wof:placetype":"locality"
},
  "geometry": {"coordinates":[120.9247,15.6769],"type":"Point"}
}