{
  "type": "Feature",
  "properties": {
    "gn:country":"PH",
    "gn:fcode":"PPL",
    "gn:population":2397,
    "iso:country":"PH",
    "name:fil_x_preferred":[
        "Kinalaglagan"
    ],
    "name:und_x_variant":[
        "Quinalaglagan"
    ],
    "qs:name":"Kinalaglagan",
    "qs:photos_9r":0,
    "qs:photos_sr":0,
    "qs:pop_sr":"4",
    "wof:name":"Kinalaglagan",
    "wof:placetype":"locality",
    "wof:population":2397
},
  "geometry": {"coordinates":[121.09772,14.00149],"type":"Point"}
}