{
  "type": "Feature",
  "properties": {
    "gn:admin1_code":"08",
    "gn:admin2_code":"37",
    "gn:admin3_code":"83703000.0",
    "gn:asciiname":"Buac",
    "gn:country_code":"PH",
    "gn:dem":50,
    "gn:elevation":"0.0",
    "gn:feature_class":"P",
    "gn:feature_code":"PPL",
    "gn:name":"Buac",
    "gn:population":0,
    "gn:timezone":"Asia/Manila",
    "iso:country":"PH",
    "name:fil_x_preferred":[
        "Buac"
    ],
    "wof:name":"Buac",
    "wof:placetype":"locality"
},
  "geometry": {"coordinates":[124.74760000000001,10.8614],"type":"Point"}
}