{
  "type": "Feature",
  "properties": {
    "gn:country":"PH",
    "gn:fcode":"ADM3",
    "gn:population":30067,
    "iso:country":"PH",
    "name:bcl_x_preferred":[
        "Amadeo"
    ],
    "name:cat_x_preferred":[
        "Amadeo"
    ],
    "name:ceb_x_preferred":[
        "Amadeo"
    ],
    "name:ces_x_preferred":[
        "Amadeo"
    ],
    "name:deu_x_preferred":[
        "Amadeo"
    ],
    "name:eng_x_preferred":[
        "Amadeo"
    ],
    "name:fas_x_preferred":[
        "\u0627\u0645\u0627\u062f\u0626\u0648"
    ],
    "name:fil_x_preferred":[
        "Amadeo"
    ],
    "name:fra_x_preferred":[
        "Amadeo"
    ],
    "name:glg_x_preferred":[
        "Amadeo"
    ],
    "name:ilo_x_preferred":[
        "Amadeo"
    ],
    "name:ind_x_preferred":[
        "Amadeo"
    ],
    "name:ita_x_preferred":[
        "Amadeo"
    ],
    "name:jpn_x_preferred":[
        "\u30a2\u30de\u30c7\u30aa"
    ],
    "name:msa_x_preferred":[
        "Amadeo"
    ],
    "name:nld_x_preferred":[
        "Amadeo"
    ],
    "name:oci_x_preferred":[
        "Amadeo"
    ],
    "name:pag_x_preferred":[
        "Amadeo"
    ],
    "name:pam_x_preferred":[
        "Amadeo"
    ],
    "name:spa_x_preferred":[
        "Amadeo"
    ],
    "name:swe_x_preferred":[
        "Amadeo"
    ],
    "name:tgl_x_preferred":[
        "Amadeo"
    ],
    "name:vie_x_preferred":[
        "Amadeo"
    ],
    "name:war_x_preferred":[
        "Amadeo"
    ],
    "qs:name":"Amadeo",
    "qs:photos_9r":0,
    "qs:photos_sr":0,
    "qs:pop_sr":"7",
    "wd:wordcount":227,
    "wof:name":"Amadeo",
    "wof:placetype":"localadmin",
    "wof:population":30067
},
  "geometry": {"coordinates":[120.92493,14.19131],"type":"Point"}
}