{
  "type": "Feature",
  "properties": {
    "gn:country":"PH",
    "gn:fcode":"ADM3",
    "gn:pop":30067,
    "iso:country":"PH",
    "name:fil_x_preferred":[
        "Amadeo"
    ],
    "qs:name":"Amadeo",
    "qs:photos_9r":0,
    "qs:photos_sr":0,
    "qs:pop_sr":"7",
    "wd:wordcount":227,
    "wof:name":"Amadeo",
    "wof:placetype":"localadmin",
    "wof:population":30067
},
  "geometry": {"coordinates":[120.92493,14.19131],"type":"Point"}
}