{
  "type": "Feature",
  "properties": {
    "gn:country":"PH",
    "gn:fcode":"PPL",
    "gn:population":2209,
    "iso:country":"PH",
    "name:ceb_x_preferred":[
        "Looc"
    ],
    "name:deu_x_preferred":[
        "Looc"
    ],
    "name:eng_x_preferred":[
        "Looc"
    ],
    "name:ita_x_preferred":[
        "Looc"
    ],
    "name:nld_x_preferred":[
        "Looc"
    ],
    "name:und_x_variant":[
        "Lo-ok"
    ],
    "name:war_x_preferred":[
        "Looc"
    ],
    "qs:name":"Looc",
    "qs:photos_9r":0,
    "qs:photos_sr":0,
    "qs:pop_sr":"4",
    "wof:name":"Looc",
    "wof:placetype":"locality",
    "wof:population":2209
},
  "geometry": {"coordinates":[124.55419999999999,11.4788],"type":"Point"}
}