{
  "type": "Feature",
  "properties": {
    "gn:admin1_code":"01",
    "gn:admin2_code":"29",
    "gn:admin3_code":"12927000.0",
    "gn:asciiname":"Danar",
    "gn:country_code":"PH",
    "gn:dem":37,
    "gn:feature_class":"P",
    "gn:feature_code":"PPL",
    "gn:name":"Danar",
    "gn:population":0,
    "gn:timezone":"Asia/Manila",
    "iso:country":"PH",
    "name:fil_x_preferred":[
        "Danar"
    ],
    "wof:name":"Danar",
    "wof:placetype":"locality"
},
  "geometry": {"coordinates":[120.4421,17.2516],"type":"Point"}
}