{
  "type": "Feature",
  "properties": {
    "gn:country":"PH",
    "gn:fcode":"PPL",
    "gn:pop":2132,
    "iso:country":"PH",
    "name:fil_x_preferred":[
        "Alijis"
    ],
    "qs:name":"Alijis",
    "qs:photos_9r":0,
    "qs:photos_sr":0,
    "qs:pop_sr":"4",
    "wof:name":"Alijis",
    "wof:placetype":"locality",
    "wof:population":2132
},
  "geometry": {"coordinates":[122.8348,10.4583],"type":"Point"}
}