{
  "type": "Feature",
  "properties": {
    "gn:admin1_code":"05",
    "gn:admin2_code":"58",
    "gn:admin3_code":"56216000.0",
    "gn:asciiname":"Gatbo",
    "gn:cc2":"PH",
    "gn:country_code":"PH",
    "gn:dem":26,
    "gn:feature_class":"P",
    "gn:feature_code":"PPL",
    "gn:name":"Gatbo",
    "gn:population":0,
    "gn:timezone":"Asia/Manila",
    "iso:country":"PH",
    "name:und_x_variant":[
        "San Antonio",
        "Gatbo"
    ],
    "wof:name":"Gatbo",
    "wof:placetype":"locality"
},
  "geometry": {"coordinates":[124.10250000000001,13.01861],"type":"Point"}
}