{
  "type": "Feature",
  "properties": {
    "gn:country":"PH",
    "gn:fcode":"PPL",
    "gn:population":3212,
    "iso:country":"PH",
    "name:fil_x_preferred":[
        "Mabay"
    ],
    "qs_pg:aaroncc":"PH",
    "qs_pg:gn_country":"PH",
    "qs_pg:gn_fcode":"PPL",
    "qs_pg:gn_pop":3212,
    "qs_pg:name":"Mabay",
    "qs_pg:photos_9r":0,
    "qs_pg:photos_sr":0,
    "qs_pg:pop_sr":4,
    "qs_pg:qs_pg_placetype":"locality",
    "wof:name":"Mabay",
    "wof:placetype":"locality",
    "wof:population":3212
},
  "geometry": {"coordinates":[124.46661,6.05772],"type":"Point"}
}