{
  "type": "Feature",
  "properties": {
    "gn:admin1_code":"14",
    "gn:admin2_code":"56",
    "gn:admin3_code":"153812000.0",
    "gn:asciiname":"Agkalangan",
    "gn:country_code":"PH",
    "gn:dem":33,
    "gn:feature_class":"P",
    "gn:feature_code":"PPL",
    "gn:name":"Agkalangan",
    "gn:population":0,
    "gn:timezone":"Asia/Manila",
    "iso:country":"PH",
    "name:und_x_variant":[
        "Aokalangan"
    ],
    "wof:name":"Agkalangan",
    "wof:placetype":"locality"
},
  "geometry": {"coordinates":[124.35583,7.25889],"type":"Point"}
}