{
  "type": "Feature",
  "properties": {
    "gn:admin1_code":"03",
    "gn:admin2_code":"63",
    "gn:admin3_code":"36906000.0",
    "gn:asciiname":"Oloybuaya",
    "gn:country_code":"PH",
    "gn:dem":23,
    "gn:feature_class":"P",
    "gn:feature_code":"PPL",
    "gn:name":"Oloybuaya",
    "gn:population":0,
    "gn:timezone":"Asia/Manila",
    "iso:country":"PH",
    "name:fil_x_preferred":[
        "Oloybuaya"
    ],
    "wof:name":"Oloybuaya",
    "wof:placetype":"locality"
},
  "geometry": {"coordinates":[120.61673,15.64174],"type":"Point"}
}