{
  "type": "Feature",
  "properties": {
    "gn:admin1_code":"14",
    "gn:admin2_code":"35",
    "gn:admin3_code":"153626000.0",
    "gn:asciiname":"Ingud",
    "gn:country_code":"PH",
    "gn:dem":709,
    "gn:feature_class":"P",
    "gn:feature_code":"PPL",
    "gn:name":"Ingud",
    "gn:population":0,
    "gn:timezone":"Asia/Manila",
    "iso:country":"PH",
    "name:und_x_variant":[
        "Lumbak-a-Ingud"
    ],
    "wof:name":"Ingud",
    "wof:placetype":"locality"
},
  "geometry": {"coordinates":[124.33693999999998,7.86],"type":"Point"}
}