{
  "type": "Feature",
  "properties": {
    "iso:country":"PH",
    "name:bcl_x_preferred":[
        "Pitogo"
    ],
    "name:deu_x_preferred":[
        "Pitogo"
    ],
    "name:eng_x_preferred":[
        "Pitogo"
    ],
    "name:fra_x_preferred":[
        "Pitogo"
    ],
    "name:ilo_x_preferred":[
        "Pitogo"
    ],
    "name:ind_x_preferred":[
        "Pitogo"
    ],
    "name:ita_x_preferred":[
        "Pitogo"
    ],
    "name:nld_x_preferred":[
        "Pitogo"
    ],
    "name:pag_x_preferred":[
        "Pitogo"
    ],
    "name:pam_x_preferred":[
        "Pitogo"
    ],
    "name:swe_x_preferred":[
        "Pitogo"
    ],
    "name:tgl_x_preferred":[
        "Pitogo"
    ],
    "name:vie_x_preferred":[
        "Pitogo"
    ],
    "name:war_x_preferred":[
        "Pitogo"
    ],
    "qs:gn_country":"PH",
    "qs:gn_fcode":"PPL",
    "qs:gn_pop":5972,
    "qs:name":"Pitogo",
    "qs:name_adm0":"Philippines",
    "qs:name_adm1":"Zamboanga Peninsula",
    "qs:photos":0,
    "qs:photos_1k":0,
    "qs:photos_9k":1,
    "qs:photos_9r":3,
    "qs:photos_all":81,
    "qs:photos_sr":0,
    "qs:placetype":"Town",
    "qs:pop_sr":"5",
    "qs:woe_adm0":23424934,
    "wof:name":"Pitogo",
    "wof:placetype":"locality",
    "wof:population":5972
},
  "geometry": {"coordinates":[123.3111,7.4546],"type":"Point"}
}