{
  "type": "Feature",
  "properties": {
    "gn:country":"PH",
    "gn:fcode":"PPLA3",
    "gn:population":3069,
    "iso:country":"PH",
    "name:bcl_x_preferred":[
        "Daram"
    ],
    "name:ceb_x_preferred":[
        "Daram"
    ],
    "name:deu_x_preferred":[
        "Daram"
    ],
    "name:eng_x_preferred":[
        "Daram"
    ],
    "name:fil_x_preferred":[
        "Daram"
    ],
    "name:fra_x_preferred":[
        "Daram"
    ],
    "name:ilo_x_preferred":[
        "Daram"
    ],
    "name:ind_x_preferred":[
        "Daram"
    ],
    "name:ita_x_preferred":[
        "Daram"
    ],
    "name:nld_x_preferred":[
        "Daram"
    ],
    "name:nob_x_preferred":[
        "Daram"
    ],
    "name:pag_x_preferred":[
        "Daram"
    ],
    "name:pam_x_preferred":[
        "Daram"
    ],
    "name:spa_x_preferred":[
        "Daram"
    ],
    "name:swe_x_preferred":[
        "Daram"
    ],
    "name:tgl_x_preferred":[
        "Daram"
    ],
    "name:war_x_preferred":[
        "Daram"
    ],
    "qs_pg:aaroncc":"PH",
    "qs_pg:gn_country":"PH",
    "qs_pg:gn_fcode":"PPLA3",
    "qs_pg:gn_pop":3069,
    "qs_pg:name":"Daram",
    "qs_pg:photos_9r":0,
    "qs_pg:photos_sr":0,
    "qs_pg:pop_sr":4,
    "qs_pg:qs_pg_placetype":"locality",
    "wof:name":"Daram",
    "wof:placetype":"locality",
    "wof:population":3069
},
  "geometry": {"coordinates":[124.79470000000001,11.6341],"type":"Point"}
}