{
  "type": "Feature",
  "properties": {
    "gn:admin1_code":"02",
    "gn:admin2_code":"31",
    "gn:admin3_code":"23130000.0",
    "gn:asciiname":"Sandiat West",
    "gn:country_code":"PH",
    "gn:dem":63,
    "gn:feature_class":"P",
    "gn:feature_code":"PPL",
    "gn:name":"Sandiat West",
    "gn:population":0,
    "gn:timezone":"Asia/Manila",
    "iso:country":"PH",
    "name:fil_x_preferred":[
        "Sandiat Weste"
    ],
    "wof:name":"Sandiat West",
    "wof:placetype":"locality"
},
  "geometry": {"coordinates":[121.63536999999999,17.07102],"type":"Point"}
}