{
  "type": "Feature",
  "properties": {
    "gn:admin1_code":"05",
    "gn:admin2_code":"58",
    "gn:admin3_code":"56212000.0",
    "gn:asciiname":"Bon-ot Daco",
    "gn:country_code":"PH",
    "gn:dem":10,
    "gn:feature_class":"P",
    "gn:feature_code":"PPL",
    "gn:name":"Bon-ot Daco",
    "gn:population":0,
    "gn:timezone":"Asia/Manila",
    "iso:country":"PH",
    "name:fil_x_preferred":[
        "Bon-ot Daco"
    ],
    "wof:name":"Bon-ot Daco",
    "wof:placetype":"locality"
},
  "geometry": {"coordinates":[124.0403,12.5353],"type":"Point"}
}