{
  "type": "Feature",
  "properties": {
    "gn:admin1_code":"01",
    "gn:admin2_code":"51",
    "gn:admin3_code":"15502000.0",
    "gn:asciiname":"Sipitan",
    "gn:country_code":"PH",
    "gn:dem":14,
    "gn:feature_class":"P",
    "gn:feature_code":"PPL",
    "gn:name":"Sipitan",
    "gn:population":0,
    "gn:timezone":"Asia/Manila",
    "iso:country":"PH",
    "name:fil_x_preferred":[
        "Sipitan"
    ],
    "wof:name":"Sipitan",
    "wof:placetype":"locality"
},
  "geometry": {"coordinates":[120.26260000000001,15.903],"type":"Point"}
}