{
  "type": "Feature",
  "properties": {
    "gn:admin1_code":"02",
    "gn:admin2_code":"14",
    "gn:admin3_code":"21521000.0",
    "gn:asciiname":"Balungcanag",
    "gn:country_code":"PH",
    "gn:dem":35,
    "gn:feature_class":"P",
    "gn:feature_code":"PPL",
    "gn:name":"Balungcanag",
    "gn:population":0,
    "gn:timezone":"Asia/Manila",
    "iso:country":"PH",
    "name:fil_x_preferred":[
        "Balungcanag"
    ],
    "name:fil_x_variant":[
        "Baluncanag"
    ],
    "wof:name":"Balungcanag",
    "wof:placetype":"locality"
},
  "geometry": {"coordinates":[121.43376000000001,17.8024],"type":"Point"}
}