{
  "type": "Feature",
  "properties": {
    "gn:admin1_code":"14",
    "gn:admin2_code":"60",
    "gn:admin3_code":"156610000.0",
    "gn:asciiname":"Manaling",
    "gn:country_code":"PH",
    "gn:dem":60,
    "gn:feature_class":"P",
    "gn:feature_code":"PPL",
    "gn:name":"Manaling",
    "gn:population":0,
    "gn:timezone":"Asia/Manila",
    "iso:country":"PH",
    "name:und_x_variant":[
        "Likad",
        "Likod",
        "Likoa",
        "Manaling"
    ],
    "wof:name":"Manaling",
    "wof:placetype":"locality"
},
  "geometry": {"coordinates":[121.19549000000001,5.81011],"type":"Point"}
}