{
  "type": "Feature",
  "properties": {
    "gn:admin1_code":"01",
    "gn:admin2_code":"51",
    "gn:admin3_code":"15544000.0",
    "gn:asciiname":"Pemienta",
    "gn:country_code":"PH",
    "gn:dem":101,
    "gn:feature_class":"P",
    "gn:feature_code":"PPL",
    "gn:name":"Pemienta",
    "gn:population":0,
    "gn:timezone":"Asia/Manila",
    "iso:country":"PH",
    "name:fil_x_preferred":[
        "Pemienta"
    ],
    "name:fil_x_variant":[
        "Pamienta"
    ],
    "wof:name":"Pemienta",
    "wof:placetype":"locality"
},
  "geometry": {"coordinates":[120.8344,15.9266],"type":"Point"}
}