{
  "type": "Feature",
  "properties": {
    "gn:admin1_code":"40",
    "gn:admin2_code":"20",
    "gn:admin3_code":"42106000.0",
    "gn:asciiname":"Pasong Bayog",
    "gn:country_code":"PH",
    "gn:dem":109,
    "gn:feature_class":"P",
    "gn:feature_code":"PPL",
    "gn:name":"Pasong Bayog",
    "gn:population":0,
    "gn:timezone":"Asia/Manila",
    "iso:country":"PH",
    "name:fil_x_preferred":[
        "Pasong Bayog"
    ],
    "wof:name":"Pasong Bayog",
    "wof:placetype":"locality"
},
  "geometry": {"coordinates":[120.95338,14.32289],"type":"Point"}
}