{
  "type": "Feature",
  "properties": {
    "gn:country":"PH",
    "gn:fcode":"ADM3",
    "gn:population":55815,
    "iso:country":"PH",
    "qs:name":"Cawayan",
    "qs:photos_9r":0,
    "qs:photos_sr":0,
    "qs:pop_sr":"8",
    "wof:name":"Cawayan",
    "wof:placetype":"localadmin",
    "wof:population":55815
},
  "geometry": {"coordinates":[123.68333,12.01667],"type":"Point"}
}