{
  "type": "Feature",
  "properties": {
    "gn:admin1_code":"07",
    "gn:admin2_code":"11",
    "gn:admin3_code":"71237000.0",
    "gn:asciiname":"Agbuaya",
    "gn:country_code":"PH",
    "gn:dem":207,
    "gn:feature_class":"P",
    "gn:feature_code":"PPL",
    "gn:name":"Agbuaya",
    "gn:population":0,
    "gn:timezone":"Asia/Manila",
    "iso:country":"PH",
    "name:fil_x_preferred":[
        "Agbuaya"
    ],
    "name:und_x_variant":[
        "Agbuayan"
    ],
    "wof:name":"Agbuaya",
    "wof:placetype":"locality"
},
  "geometry": {"coordinates":[123.9624,9.8328],"type":"Point"}
}