{
  "type": "Feature",
  "properties": {
    "gn:admin1_code":"41",
    "gn:admin2_code":"54",
    "gn:admin3_code":"175907000.0",
    "gn:asciiname":"Lumbia",
    "gn:country_code":"PH",
    "gn:dem":37,
    "gn:feature_class":"P",
    "gn:feature_code":"PPL",
    "gn:name":"Lumbia",
    "gn:population":0,
    "gn:timezone":"Asia/Manila",
    "iso:country":"PH",
    "name:fil_x_preferred":[
        "Lumbia"
    ],
    "wof:name":"Lumbia",
    "wof:placetype":"locality"
},
  "geometry": {"coordinates":[122.01600000000001,12.2943],"type":"Point"}
}