{
  "type": "Feature",
  "properties": {
    "gn:admin1_code":"40",
    "gn:admin2_code":"H2",
    "gn:admin3_code":"45636000.0",
    "gn:asciiname":"Abad",
    "gn:country_code":"PH",
    "gn:dem":19,
    "gn:feature_class":"P",
    "gn:feature_code":"PPL",
    "gn:name":"Abad",
    "gn:population":0,
    "gn:timezone":"Asia/Manila",
    "iso:country":"PH",
    "name:azb_x_preferred":[
        "\u0622\u0628\u0627\u062f"
    ],
    "name:aze_x_preferred":[
        "Abad"
    ],
    "name:cat_x_preferred":[
        "Abad"
    ],
    "name:ces_x_preferred":[
        "Abad"
    ],
    "name:deu_x_preferred":[
        "Abad"
    ],
    "name:fas_x_preferred":[
        "\u0622\u0628\u0627\u062f"
    ],
    "name:fil_x_preferred":[
        "Abad"
    ],
    "name:fra_x_preferred":[
        "Abad"
    ],
    "name:hun_x_preferred":[
        "Ab\u00e1d"
    ],
    "name:ita_x_preferred":[
        "Abad"
    ],
    "name:kat_x_preferred":[
        "\u10d0\u10d1\u10d0\u10d3\u10d8"
    ],
    "name:por_x_preferred":[
        "Abad"
    ],
    "name:rus_x_preferred":[
        "\u0410\u0431\u0430\u0434"
    ],
    "name:slv_x_preferred":[
        "Abad"
    ],
    "name:spa_x_preferred":[
        "Abad"
    ],
    "wof:name":"Abad",
    "wof:placetype":"locality"
},
  "geometry": {"coordinates":[121.93778,14.63],"type":"Point"}
}