{
  "type": "Feature",
  "properties": {
    "gn:admin1_code":"05",
    "gn:admin2_code":"58",
    "gn:admin3_code":"56203000.0",
    "gn:asciiname":"Inalapan",
    "gn:country_code":"PH",
    "gn:dem":4,
    "gn:feature_class":"P",
    "gn:feature_code":"PPL",
    "gn:name":"Inalapan",
    "gn:population":0,
    "gn:timezone":"Asia/Manila",
    "iso:country":"PH",
    "name:fil_x_preferred":[
        "Inalapan"
    ],
    "wof:name":"Inalapan",
    "wof:placetype":"locality"
},
  "geometry": {"coordinates":[123.84860999999999,12.74694],"type":"Point"}
}