{
  "type": "Feature",
  "properties": {
    "gn:admin1_code":"01",
    "gn:admin2_code":"51",
    "gn:admin3_code":"15546000.0",
    "gn:asciiname":"Palina West",
    "gn:country_code":"PH",
    "gn:dem":29,
    "gn:feature_class":"P",
    "gn:feature_code":"PPL",
    "gn:name":"Palina West",
    "gn:population":0,
    "gn:timezone":"Asia/Manila",
    "iso:country":"PH",
    "wof:name":"Palina West",
    "wof:placetype":"locality"
},
  "geometry": {"coordinates":[120.53739,15.95088],"type":"Point"}
}