{
  "type": "Feature",
  "properties": {
    "gn:admin1_code":"03",
    "gn:admin2_code":"64",
    "gn:admin3_code":"37106000.0",
    "gn:asciiname":"Cabangon",
    "gn:country_code":"PH",
    "gn:dem":10,
    "gn:feature_class":"P",
    "gn:feature_code":"PPL",
    "gn:name":"Cabangon",
    "gn:population":0,
    "gn:timezone":"Asia/Manila",
    "iso:country":"PH",
    "name:fil_x_preferred":[
        "Cabangon"
    ],
    "wof:name":"Cabangon",
    "wof:placetype":"locality"
},
  "geometry": {"coordinates":[119.9076,15.5124],"type":"Point"}
}