{
  "type": "Feature",
  "properties": {
    "gn:admin1_code":"06",
    "gn:admin2_code":"30",
    "gn:admin3_code":"63025000.0",
    "gn:asciiname":"Patag",
    "gn:country_code":"PH",
    "gn:dem":81,
    "gn:feature_class":"P",
    "gn:feature_code":"PPL",
    "gn:name":"Patag",
    "gn:population":0,
    "gn:timezone":"Asia/Manila",
    "iso:country":"PH",
    "name:fil_x_preferred":[
        "Patag"
    ],
    "wof:name":"Patag",
    "wof:placetype":"locality"
},
  "geometry": {"coordinates":[122.53333000000001,11.06667],"type":"Point"}
}