{
  "type": "Feature",
  "properties": {
    "iso:country":"PH",
    "name:bcl_x_preferred":[
        "Maribojoc"
    ],
    "name:cbk_zam_x_preferred":[
        "Maribojoc"
    ],
    "name:ceb_x_preferred":[
        "Maribojoc"
    ],
    "name:deu_x_preferred":[
        "Maribojoc"
    ],
    "name:eng_x_preferred":[
        "Maribojoc"
    ],
    "name:fil_x_preferred":[
        "Maribojoc"
    ],
    "name:fra_x_preferred":[
        "Maribojoc"
    ],
    "name:ilo_x_preferred":[
        "Maribojoc"
    ],
    "name:ind_x_preferred":[
        "Maribojoc"
    ],
    "name:ita_x_preferred":[
        "Maribojoc"
    ],
    "name:nld_x_preferred":[
        "Maribojoc"
    ],
    "name:pag_x_preferred":[
        "Maribojoc"
    ],
    "name:pam_x_preferred":[
        "Maribojoc"
    ],
    "name:spa_x_preferred":[
        "Maribojoc"
    ],
    "name:swe_x_preferred":[
        "Maribojoc"
    ],
    "name:tgl_x_preferred":[
        "Maribojoc"
    ],
    "name:vie_x_preferred":[
        "Maribojoc"
    ],
    "name:war_x_preferred":[
        "Maribojoc"
    ],
    "qs:gn_country":"PH",
    "qs:gn_fcode":"PPLA3",
    "qs:gn_pop":2476,
    "qs:name":"Maribojoc",
    "qs:name_adm0":"Philippines",
    "qs:name_adm1":"Central Visayas",
    "qs:photos":81,
    "qs:photos_1k":16,
    "qs:photos_9k":1,
    "qs:photos_9r":3,
    "qs:photos_all":81,
    "qs:photos_sr":3,
    "qs:placetype":"Town",
    "qs:pop_sr":"4",
    "qs:woe_adm0":23424934,
    "wd:wordcount":544,
    "wof:name":"Maribojoc",
    "wof:placetype":"locality",
    "wof:population":2476
},
  "geometry": {"coordinates":[123.8446,9.7417],"type":"Point"}
}