{
  "type": "Feature",
  "properties": {
    "gn:admin1_code":"11",
    "gn:admin2_code":"P3",
    "gn:admin3_code":"118601000.0",
    "gn:asciiname":"Bulata",
    "gn:country_code":"PH",
    "gn:dem":92,
    "gn:feature_class":"P",
    "gn:feature_code":"PPL",
    "gn:name":"Bulata",
    "gn:population":0,
    "gn:timezone":"Asia/Manila",
    "iso:country":"PH",
    "name:fil_x_preferred":[
        "Bulata"
    ],
    "wof:name":"Bulata",
    "wof:placetype":"locality"
},
  "geometry": {"coordinates":[125.69417,6.04694],"type":"Point"}
}