{
  "type": "Feature",
  "properties": {
    "gn:admin1_code":"08",
    "gn:admin2_code":"55",
    "gn:admin3_code":"86007000.0",
    "gn:asciiname":"San Pelagio",
    "gn:country_code":"PH",
    "gn:dem":8,
    "gn:feature_class":"P",
    "gn:feature_code":"PPL",
    "gn:name":"San Pelagio",
    "gn:population":0,
    "gn:timezone":"Asia/Manila",
    "iso:country":"PH",
    "name:und_x_variant":[
        "San Pelayo",
        "San Pelagio"
    ],
    "wof:name":"San Pelagio",
    "wof:placetype":"locality"
},
  "geometry": {"coordinates":[124.78245,11.99162],"type":"Point"}
}