{
  "type": "Feature",
  "properties": {
    "gn:admin1_code":"02",
    "gn:admin2_code":"14",
    "gn:admin3_code":"21527000.0",
    "gn:asciiname":"Masin",
    "gn:country_code":"PH",
    "gn:dem":30,
    "gn:feature_class":"P",
    "gn:feature_code":"PPL",
    "gn:name":"Masin",
    "gn:population":0,
    "gn:timezone":"Asia/Manila",
    "iso:country":"PH",
    "name:ceb_x_preferred":[
        "Masin"
    ],
    "name:deu_x_preferred":[
        "Masin"
    ],
    "name:fil_x_preferred":[
        "Masin"
    ],
    "name:ita_x_preferred":[
        "Masin"
    ],
    "name:swe_x_preferred":[
        "Masin"
    ],
    "wof:name":"Masin",
    "wof:placetype":"locality"
},
  "geometry": {"coordinates":[121.636,17.7054],"type":"Point"}
}