{
  "type": "Feature",
  "properties": {
    "gn:admin1_code":"06",
    "gn:admin2_code":"18",
    "gn:admin3_code":"61906000.0",
    "gn:asciiname":"Caridad",
    "gn:country_code":"PH",
    "gn:dem":29,
    "gn:feature_class":"P",
    "gn:feature_code":"PPL",
    "gn:name":"Caridad",
    "gn:population":0,
    "gn:timezone":"Asia/Manila",
    "iso:country":"PH",
    "name:fil_x_preferred":[
        "Caridad"
    ],
    "name:fra_x_preferred":[
        "Caridad"
    ],
    "name:ita_x_preferred":[
        "Caridad"
    ],
    "name:jpn_x_preferred":[
        "\u30ab\u30ea\u30c0"
    ],
    "name:nld_x_preferred":[
        "Caridad"
    ],
    "name:por_x_preferred":[
        "Caridad"
    ],
    "name:spa_x_preferred":[
        "Caridad"
    ],
    "name:zho_x_preferred":[
        "\u5361\u91cc\u9054"
    ],
    "wof:name":"Caridad",
    "wof:placetype":"locality"
},
  "geometry": {"coordinates":[122.5261,11.3903],"type":"Point"}
}