{
  "type": "Feature",
  "properties": {
    "gn:country":"PH",
    "gn:fcode":"PPL",
    "gn:population":5135,
    "iso:country":"PH",
    "name:fil_x_preferred":[
        "Canturay"
    ],
    "qs:name":"Canturay",
    "qs:photos_9r":0,
    "qs:photos_sr":0,
    "qs:pop_sr":"5",
    "wof:name":"Canturay",
    "wof:placetype":"locality",
    "wof:population":5135
},
  "geometry": {"coordinates":[122.4543,9.7937],"type":"Point"}
}