{
  "type": "Feature",
  "properties": {
    "gn:admin1_code":"08",
    "gn:admin2_code":"37",
    "gn:admin3_code":"83702000.0",
    "gn:asciiname":"Mainit",
    "gn:country_code":"PH",
    "gn:dem":42,
    "gn:feature_class":"P",
    "gn:feature_code":"PPL",
    "gn:name":"Mainit",
    "gn:population":0,
    "gn:timezone":"Asia/Manila",
    "iso:country":"PH",
    "name:fil_x_preferred":[
        "Mainit"
    ],
    "wof:name":"Mainit",
    "wof:placetype":"locality"
},
  "geometry": {"coordinates":[124.83028,11.21444],"type":"Point"}
}