{
  "type": "Feature",
  "properties": {
    "gn:gn_country":"PH",
    "gn:gn_fcode":"PPL",
    "gn:gn_pop":2373,
    "gn:population":2373,
    "iso:country":"PH",
    "name:fil_x_preferred":[
        "Tugdan"
    ],
    "qs_pg:aaroncc":"PH",
    "qs_pg:gn_country":"PH",
    "qs_pg:gn_fcode":"PPL",
    "qs_pg:gn_pop":2373,
    "qs_pg:name":"Tugdan",
    "qs_pg:photos_9r":0,
    "qs_pg:photos_sr":0,
    "qs_pg:pop_sr":4,
    "qs_pg:qs_pg_placetype":"locality",
    "wof:name":"Tugdan",
    "wof:placetype":"locality",
    "wof:population":2373
},
  "geometry": {"coordinates":[122.0853,12.3134],"type":"Point"}
}