{
  "type": "Feature",
  "properties": {
    "gn:admin1_code":"03",
    "gn:admin2_code":"G8",
    "gn:admin3_code":"37706000.0",
    "gn:asciiname":"Buenavista",
    "gn:country_code":"PH",
    "gn:dem":14,
    "gn:feature_class":"P",
    "gn:feature_code":"PPL",
    "gn:name":"Buenavista",
    "gn:population":0,
    "gn:timezone":"Asia/Manila",
    "iso:country":"PH",
    "name:fil_x_preferred":[
        "Buenavista"
    ],
    "wof:name":"Buenavista",
    "wof:placetype":"locality"
},
  "geometry": {"coordinates":[121.51600000000001,15.8484],"type":"Point"}
}