{
  "type": "Feature",
  "properties": {
    "gn:admin1_code":"07",
    "gn:admin2_code":"11",
    "gn:admin3_code":"71202000.0",
    "gn:asciiname":"Bughayan",
    "gn:country_code":"PH",
    "gn:dem":30,
    "gn:feature_class":"P",
    "gn:feature_code":"PPL",
    "gn:name":"Bughayan",
    "gn:population":0,
    "gn:timezone":"Asia/Manila",
    "iso:country":"PH",
    "name:fil_x_preferred":[
        "Bughayan"
    ],
    "wof:name":"Bughayan",
    "wof:placetype":"locality"
},
  "geometry": {"coordinates":[124.4314,9.9025],"type":"Point"}
}