{
  "type": "Feature",
  "properties": {
    "gn:admin1_code":"14",
    "gn:admin2_code":"22",
    "gn:admin3_code":"150713000.0",
    "gn:asciiname":"Somapilong",
    "gn:country_code":"PH",
    "gn:dem":21,
    "gn:feature_class":"P",
    "gn:feature_code":"PPL",
    "gn:name":"Somapilong",
    "gn:population":0,
    "gn:timezone":"Asia/Manila",
    "iso:country":"PH",
    "name:fil_x_preferred":[
        "Somapilong"
    ],
    "wof:name":"Somapilong",
    "wof:placetype":"locality"
},
  "geometry": {"coordinates":[121.95780999999999,6.3021],"type":"Point"}
}