{
  "type": "Feature",
  "properties": {
    "gn:admin1_code":"06",
    "gn:admin2_code":"30",
    "gn:admin3_code":"63035000.0",
    "gn:asciiname":"Gigaciac",
    "gn:country_code":"PH",
    "gn:dem":78,
    "gn:feature_class":"P",
    "gn:feature_code":"PPL",
    "gn:name":"Gigaciac",
    "gn:population":0,
    "gn:timezone":"Asia/Manila",
    "iso:country":"PH",
    "name:fil_x_preferred":[
        "Gigaciac"
    ],
    "name:fil_x_variant":[
        "Gigacogac"
    ],
    "wof:name":"Gigaciac",
    "wof:placetype":"locality"
},
  "geometry": {"coordinates":[122.6048,11.2013],"type":"Point"}
}