{
  "type": "Feature",
  "properties": {
    "gn:admin1_code":"09",
    "gn:admin2_code":"66",
    "gn:admin3_code":"97332000.0",
    "gn:asciiname":"Tigbalabag",
    "gn:cc2":"PH",
    "gn:country_code":"PH",
    "gn:dem":142,
    "gn:feature_class":"P",
    "gn:feature_code":"PPL",
    "gn:name":"Tigbalabag",
    "gn:population":0,
    "gn:timezone":"Asia/Manila",
    "iso:country":"PH",
    "name:und_x_variant":[
        "Tigbalabog",
        "Tigbalabag"
    ],
    "wof:name":"Tigbalabag",
    "wof:placetype":"locality"
},
  "geometry": {"coordinates":[122.26306,7.31889],"type":"Point"}
}