{
  "type": "Feature",
  "properties": {
    "gn:admin1_code":"02",
    "gn:admin2_code":"31",
    "gn:admin3_code":"23103000.0",
    "gn:asciiname":"Ballesteros",
    "gn:country_code":"PH",
    "gn:dem":62,
    "gn:feature_class":"P",
    "gn:feature_code":"PPL",
    "gn:name":"Ballesteros",
    "gn:population":0,
    "gn:timezone":"Asia/Manila",
    "iso:country":"PH",
    "wof:name":"Ballesteros",
    "wof:placetype":"locality"
},
  "geometry": {"coordinates":[121.62478,16.98696],"type":"Point"}
}