{
  "type": "Feature",
  "properties": {
    "gn:admin1_code":"01",
    "gn:admin2_code":"36",
    "gn:admin3_code":"13307000.0",
    "gn:asciiname":"Bueayob",
    "gn:country_code":"PH",
    "gn:dem":20,
    "gn:feature_class":"P",
    "gn:feature_code":"PPL",
    "gn:name":"Bueayob",
    "gn:population":0,
    "gn:timezone":"Asia/Manila",
    "iso:country":"PH",
    "name:fil_x_preferred":[
        "Bueayob"
    ],
    "wof:name":"Bueayob",
    "wof:placetype":"locality"
},
  "geometry": {"coordinates":[120.35612999999999,16.51098],"type":"Point"}
}