{
  "type": "Feature",
  "properties": {
    "gn:admin1_code":"15",
    "gn:admin2_code":"10",
    "gn:admin3_code":"141107000.0",
    "gn:asciiname":"Besang",
    "gn:country_code":"PH",
    "gn:dem":1212,
    "gn:feature_class":"P",
    "gn:feature_code":"PPL",
    "gn:name":"Besang",
    "gn:population":0,
    "gn:timezone":"Asia/Manila",
    "iso:country":"PH",
    "name:fil_x_preferred":[
        "Besang"
    ],
    "wof:name":"Besang",
    "wof:placetype":"locality"
},
  "geometry": {"coordinates":[120.82004000000001,16.65098],"type":"Point"}
}