{
  "type": "Feature",
  "properties": {
    "gn:admin1_code":"01",
    "gn:admin2_code":"51",
    "gn:admin3_code":"15511000.0",
    "gn:asciiname":"Ouou",
    "gn:cc2":"PH",
    "gn:country_code":"PH",
    "gn:dem":21,
    "gn:feature_class":"P",
    "gn:feature_code":"PPL",
    "gn:name":"Ouou",
    "gn:population":0,
    "gn:timezone":"Asia/Manila",
    "iso:country":"PH",
    "name:und_x_variant":[
        "Quou",
        "Ouou"
    ],
    "wof:name":"Ouou",
    "wof:placetype":"locality"
},
  "geometry": {"coordinates":[120.44693999999998,15.75611],"type":"Point"}
}