{
  "type": "Feature",
  "properties": {
    "gn:admin1_code":"03",
    "gn:admin2_code":"47",
    "gn:admin3_code":"34930000.0",
    "gn:asciiname":"Mabuhay",
    "gn:country_code":"PH",
    "gn:dem":61,
    "gn:feature_class":"P",
    "gn:feature_code":"PPL",
    "gn:name":"Mabuhay",
    "gn:population":0,
    "gn:timezone":"Asia/Manila",
    "iso:country":"PH",
    "name:fil_x_preferred":[
        "Mabuhay"
    ],
    "wof:name":"Mabuhay",
    "wof:placetype":"locality"
},
  "geometry": {"coordinates":[120.9615,15.6438],"type":"Point"}
}