{
  "type": "Feature",
  "properties": {
    "gn:admin1_code":"40",
    "gn:admin2_code":"09",
    "gn:admin3_code":"41016000.0",
    "gn:asciiname":"Panay",
    "gn:country_code":"PH",
    "gn:dem":155,
    "gn:feature_class":"P",
    "gn:feature_code":"PPL",
    "gn:name":"Panay",
    "gn:population":0,
    "gn:timezone":"Asia/Manila",
    "iso:country":"PH",
    "name:fil_x_preferred":[
        "Panay"
    ],
    "wof:name":"Panay",
    "wof:placetype":"locality"
},
  "geometry": {"coordinates":[120.88333,13.71667],"type":"Point"}
}