{
  "type": "Feature",
  "properties": {
    "gn:country":"PH",
    "gn:fcode":"ADM3",
    "gn:population":26796,
    "iso:country":"PH",
    "name:fil_x_preferred":[
        "Mendez-Nu\u00f1ez"
    ],
    "qs_pg:aaroncc":"PH",
    "qs_pg:gn_country":"PH",
    "qs_pg:gn_fcode":"ADM3",
    "qs_pg:gn_pop":26796,
    "qs_pg:name":"Mendez-Nu\u00f1ez",
    "qs_pg:photos_9r":0,
    "qs_pg:photos_sr":0,
    "qs_pg:pop_sr":7,
    "qs_pg:qs_pg_placetype":"localadmin",
    "wof:name":"Mendez-Nu\u00f1ez",
    "wof:placetype":"localadmin",
    "wof:population":26796
},
  "geometry": {"coordinates":[120.89836,14.12975],"type":"Point"}
}