{
  "type": "Feature",
  "properties": {
    "gn:admin1_code":"01",
    "gn:admin2_code":"36",
    "gn:admin3_code":"13316000.0",
    "gn:asciiname":"Nadsaag",
    "gn:country_code":"PH",
    "gn:dem":13,
    "gn:feature_class":"P",
    "gn:feature_code":"PPL",
    "gn:name":"Nadsaag",
    "gn:population":0,
    "gn:timezone":"Asia/Manila",
    "iso:country":"PH",
    "name:fil_x_preferred":[
        "Nadsaag"
    ],
    "wof:name":"Nadsaag",
    "wof:placetype":"locality"
},
  "geometry": {"coordinates":[120.38333,16.66667],"type":"Point"}
}