{
  "type": "Feature",
  "properties": {
    "gn:country":"PH",
    "gn:fcode":"PPL",
    "gn:pop":4115,
    "iso:country":"PH",
    "name:eng_x_preferred":[
        "Caruray"
    ],
    "qs:name":"Caruray",
    "qs:photos_9r":0,
    "qs:photos_sr":0,
    "qs:pop_sr":"4",
    "wof:name":"Caruray",
    "wof:placetype":"locality",
    "wof:population":4115
},
  "geometry": {"coordinates":[119.0128,10.3094],"type":"Point"}
}