{
  "type": "Feature",
  "properties": {
    "gn:country":"PH",
    "gn:fcode":"PPLA3",
    "gn:pop":3540,
    "iso:country":"PH",
    "name:bcl_x_preferred":[
        "Mandaon"
    ],
    "name:ceb_x_preferred":[
        "Mandaon"
    ],
    "name:deu_x_preferred":[
        "Mandaon"
    ],
    "name:eng_x_preferred":[
        "Mandaon"
    ],
    "name:fil_x_preferred":[
        "Mandaon"
    ],
    "name:fra_x_preferred":[
        "Mandaon"
    ],
    "name:ilo_x_preferred":[
        "Mandaon"
    ],
    "name:ind_x_preferred":[
        "Mandaon"
    ],
    "name:ita_x_preferred":[
        "Mandaon"
    ],
    "name:nld_x_preferred":[
        "Mandaon"
    ],
    "name:pag_x_preferred":[
        "Mandaon"
    ],
    "name:pam_x_preferred":[
        "Mandaon"
    ],
    "name:swe_x_preferred":[
        "Mandaon"
    ],
    "name:tgl_x_preferred":[
        "Mandaon"
    ],
    "name:vie_x_preferred":[
        "Mandaon"
    ],
    "name:war_x_preferred":[
        "Mandaon"
    ],
    "qs:name":"Mandaon",
    "qs:photos_9r":0,
    "qs:photos_sr":0,
    "qs:pop_sr":"4",
    "wof:name":"Mandaon",
    "wof:placetype":"locality",
    "wof:population":3540
},
  "geometry": {"coordinates":[123.28421,12.22594],"type":"Point"}
}