{
  "type": "Feature",
  "properties": {
    "gn:admin1_code":"08",
    "gn:admin2_code":"37",
    "gn:admin3_code":"83740000.0",
    "gn:asciiname":"Kataguman",
    "gn:country_code":"PH",
    "gn:dem":59,
    "gn:feature_class":"P",
    "gn:feature_code":"PPL",
    "gn:name":"Kataguman",
    "gn:population":0,
    "gn:timezone":"Asia/Manila",
    "iso:country":"PH",
    "name:fil_x_preferred":[
        "Kataguman"
    ],
    "wof:name":"Kataguman",
    "wof:placetype":"locality"
},
  "geometry": {"coordinates":[124.4365,11.0142],"type":"Point"}
}