{
  "type": "Feature",
  "properties": {
    "gn:admin1_code":"01",
    "gn:admin2_code":"28",
    "gn:admin3_code":"12815000.0",
    "gn:asciiname":"Pasaleng",
    "gn:country_code":"PH",
    "gn:dem":21,
    "gn:feature_class":"P",
    "gn:feature_code":"PPL",
    "gn:name":"Pasaleng",
    "gn:population":0,
    "gn:timezone":"Asia/Manila",
    "iso:country":"PH",
    "name:fil_x_preferred":[
        "Pasaleng"
    ],
    "wof:name":"Pasaleng",
    "wof:placetype":"locality"
},
  "geometry": {"coordinates":[120.92766,18.55082],"type":"Point"}
}