{
  "type": "Feature",
  "properties": {
    "gn:country":"PH",
    "gn:fcode":"PPL",
    "gn:pop":4150,
    "iso:country":"PH",
    "name:fil_x_preferred":[
        "Bobon"
    ],
    "name:unk_x_variant":[
        "Bobon"
    ],
    "qs:name":"Bobon Second",
    "qs:photos_9r":0,
    "qs:photos_sr":0,
    "qs:pop_sr":"4",
    "wof:name":"Bobon Second",
    "wof:placetype":"locality",
    "wof:population":4150
},
  "geometry": {"coordinates":[120.38118,15.65653],"type":"Point"}
}