{
  "type": "Feature",
  "properties": {
    "gn:country":"PH",
    "gn:fcode":"PPL",
    "gn:pop":6300,
    "iso:country":"PH",
    "name:fil_x_preferred":[
        "San Ignacio"
    ],
    "qs:name":"San Ignacio",
    "qs:photos_9r":0,
    "qs:photos_sr":0,
    "qs:pop_sr":"5",
    "wd:wordcount":111,
    "wof:name":"San Ignacio",
    "wof:placetype":"locality",
    "wof:population":6300
},
  "geometry": {"coordinates":[126.48838000000001,7.1189],"type":"Point"}
}