{
  "type": "Feature",
  "properties": {
    "gn:admin1_code":"05",
    "gn:admin2_code":"05",
    "gn:admin3_code":"50516000.0",
    "gn:asciiname":"San Andres",
    "gn:country_code":"PH",
    "gn:dem":71,
    "gn:feature_class":"P",
    "gn:feature_code":"PPL",
    "gn:name":"San Andres",
    "gn:population":2250,
    "gn:timezone":"Asia/Manila",
    "iso:country":"PH",
    "name:fil_x_preferred":[
        "San Andres"
    ],
    "wof:name":"San Andres",
    "wof:placetype":"locality",
    "wof:population":2250
},
  "geometry": {"coordinates":[123.7795,13.2614],"type":"Point"}
}