{
  "type": "Feature",
  "properties": {
    "gn:admin1_code":"06",
    "gn:admin2_code":"H3",
    "gn:admin3_code":"64503000.0",
    "gn:asciiname":"Cambalan",
    "gn:country_code":"PH",
    "gn:dem":134,
    "gn:feature_class":"P",
    "gn:feature_code":"PPL",
    "gn:name":"Cambalan",
    "gn:population":0,
    "gn:timezone":"Asia/Manila",
    "iso:country":"PH",
    "name:fil_x_preferred":[
        "Cambalan"
    ],
    "wof:name":"Cambalan",
    "wof:placetype":"locality"
},
  "geometry": {"coordinates":[123.0154,10.1415],"type":"Point"}
}