{
  "type": "Feature",
  "properties": {
    "gn:country":"PH",
    "gn:fcode":"PPL",
    "gn:population":2349,
    "iso:country":"PH",
    "name:bel_x_preferred":[
        "\u0413\u0430\u0440\u044b\u0441\u0430\u043d"
    ],
    "name:cat_x_preferred":[
        "Harrison"
    ],
    "name:ceb_x_preferred":[
        "Harrison"
    ],
    "name:ces_x_preferred":[
        "Harrison"
    ],
    "name:deu_x_preferred":[
        "Harrison"
    ],
    "name:fas_x_preferred":[
        "\u0647\u0631\u06cc\u0633\u0648\u0646"
    ],
    "name:fil_x_preferred":[
        "Harrison"
    ],
    "name:fin_x_preferred":[
        "Harrison"
    ],
    "name:fra_x_preferred":[
        "Harrison"
    ],
    "name:heb_x_preferred":[
        "\u05d4\u05e8\u05d9\u05e1\u05d5\u05df"
    ],
    "name:ita_x_preferred":[
        "Harrison"
    ],
    "name:jpn_x_preferred":[
        "\u30cf\u30ea\u30bd\u30f3"
    ],
    "name:kor_x_preferred":[
        "\ud574\ub9ac\uc2a8"
    ],
    "name:lav_x_preferred":[
        "Herisons"
    ],
    "name:lit_x_preferred":[
        "Harrison"
    ],
    "name:nds_x_preferred":[
        "Harrison"
    ],
    "name:nld_x_preferred":[
        "Harrison"
    ],
    "name:pol_x_preferred":[
        "Harrison"
    ],
    "name:por_x_preferred":[
        "Harrison"
    ],
    "name:ron_x_preferred":[
        "Harrison"
    ],
    "name:rus_x_preferred":[
        "\u0425\u0430\u0440\u0440\u0438\u0441\u043e\u043d"
    ],
    "name:spa_x_preferred":[
        "Harrison"
    ],
    "name:srp_x_preferred":[
        "\u0425\u0430\u0440\u0438\u0441\u043e\u043d"
    ],
    "name:swa_x_preferred":[
        "Harrison"
    ],
    "name:swe_x_preferred":[
        "Harrison"
    ],
    "name:ukr_x_preferred":[
        "\u0413\u0430\u0440\u0440\u0456\u0441\u043e\u043d"
    ],
    "name:vol_x_preferred":[
        "Harrison"
    ],
    "qs:name":"Harrison",
    "qs:photos_9r":0,
    "qs:photos_sr":0,
    "qs:pop_sr":"4",
    "wd:wordcount":287,
    "wof:name":"Harrison",
    "wof:placetype":"locality",
    "wof:population":2349
},
  "geometry": {"coordinates":[120.43333,13.45],"type":"Point"}
}