{
  "type": "Feature",
  "properties": {
    "gn:country":"PH",
    "gn:fcode":"PPL",
    "gn:pop":2349,
    "iso:country":"PH",
    "name:fil_x_preferred":[
        "Harrison"
    ],
    "qs:name":"Harrison",
    "qs:photos_9r":0,
    "qs:photos_sr":0,
    "qs:pop_sr":"4",
    "wd:wordcount":287,
    "wof:name":"Harrison",
    "wof:placetype":"locality",
    "wof:population":2349
},
  "geometry": {"coordinates":[120.43333,13.45],"type":"Point"}
}