{
  "type": "Feature",
  "properties": {
    "gn:country":"PH",
    "gn:fcode":"PPL",
    "gn:pop":12867,
    "iso:country":"PH",
    "name:fil_x_preferred":[
        "Malandag"
    ],
    "qs:name":"Malandag",
    "qs:photos_9r":0,
    "qs:photos_sr":0,
    "qs:pop_sr":"6",
    "wof:name":"Malandag",
    "wof:placetype":"locality",
    "wof:population":12867
},
  "geometry": {"coordinates":[125.24278,6.30944],"type":"Point"}
}