{
  "type": "Feature",
  "properties": {
    "gn:admin1_code":"06",
    "gn:admin2_code":"30",
    "gn:admin3_code":"63002000.0",
    "gn:asciiname":"Malamhay",
    "gn:country_code":"PH",
    "gn:dem":175,
    "gn:feature_class":"P",
    "gn:feature_code":"PPL",
    "gn:name":"Malamhay",
    "gn:population":0,
    "gn:timezone":"Asia/Manila",
    "iso:country":"PH",
    "name:fil_x_preferred":[
        "Malamhay"
    ],
    "wof:name":"Malamhay",
    "wof:placetype":"locality"
},
  "geometry": {"coordinates":[122.41752,10.81564],"type":"Point"}
}