{
  "type": "Feature",
  "properties": {
    "gn:admin1_code":"02",
    "gn:admin2_code":"14",
    "gn:admin3_code":"21527000.0",
    "gn:asciiname":"Iraga",
    "gn:country_code":"PH",
    "gn:dem":20,
    "gn:feature_class":"P",
    "gn:feature_code":"PPL",
    "gn:name":"Iraga",
    "gn:population":0,
    "gn:timezone":"Asia/Manila",
    "iso:country":"PH",
    "name:fil_x_preferred":[
        "Iraga"
    ],
    "wof:name":"Iraga",
    "wof:placetype":"locality"
},
  "geometry": {"coordinates":[121.66631,17.7263],"type":"Point"}
}