{
  "type": "Feature",
  "properties": {
    "gn:admin1_code":"06",
    "gn:admin2_code":"H3",
    "gn:admin3_code":"64502000.0",
    "gn:asciiname":"Hacienda Binobunan",
    "gn:country_code":"PH",
    "gn:dem":101,
    "gn:feature_class":"P",
    "gn:feature_code":"PPL",
    "gn:name":"Hacienda Binobunan",
    "gn:population":0,
    "gn:timezone":"Asia/Manila",
    "iso:country":"PH",
    "name:fil_x_preferred":[
        "Hacienda Binobunan"
    ],
    "name:fil_x_variant":[
        "Binobuhan Hacienda"
    ],
    "wof:name":"Hacienda Binobunan",
    "wof:placetype":"locality"
},
  "geometry": {"coordinates":[123.00060000000001,10.45],"type":"Point"}
}