{
  "type": "Feature",
  "properties": {
    "gn:country":"PH",
    "gn:fcode":"ADM3",
    "gn:population":1379,
    "iso:country":"PH",
    "qs:name":"Uyugan",
    "qs:photos_9r":0,
    "qs:photos_sr":0,
    "qs:pop_sr":"3",
    "wof:name":"Uyugan",
    "wof:placetype":"localadmin",
    "wof:population":1379
},
  "geometry": {"coordinates":[121.95,20.38333],"type":"Point"}
}