{
  "type": "Feature",
  "properties": {
    "gn:admin1_code":"05",
    "gn:admin2_code":"19",
    "gn:admin3_code":"52006000.0",
    "gn:asciiname":"Marambong",
    "gn:country_code":"PH",
    "gn:dem":16,
    "gn:feature_class":"P",
    "gn:feature_code":"PPL",
    "gn:name":"Marambong",
    "gn:population":0,
    "gn:timezone":"Asia/Manila",
    "iso:country":"PH",
    "name:fil_x_preferred":[
        "Marambong"
    ],
    "wof:name":"Marambong",
    "wof:placetype":"locality"
},
  "geometry": {"coordinates":[124.2251,14.0674],"type":"Point"}
}