{
  "type": "Feature",
  "properties": {
    "gn:admin1_code":"41",
    "gn:admin2_code":"41",
    "gn:admin3_code":"175215000.0",
    "gn:asciiname":"Macatoc",
    "gn:country_code":"PH",
    "gn:dem":9,
    "gn:feature_class":"P",
    "gn:feature_code":"PPL",
    "gn:name":"Macatoc",
    "gn:population":0,
    "gn:timezone":"Asia/Manila",
    "iso:country":"PH",
    "name:fil_x_preferred":[
        "Macatoc"
    ],
    "name:und_x_variant":[
        "Macato"
    ],
    "wof:name":"Macatoc",
    "wof:placetype":"locality"
},
  "geometry": {"coordinates":[121.30531999999999,13.19869],"type":"Point"}
}