{
  "type": "Feature",
  "properties": {
    "gn:country":"PH",
    "gn:fcode":"PPL",
    "gn:pop":2318,
    "iso:country":"PH",
    "name:fil_x_preferred":[
        "Rosario"
    ],
    "qs:name":"Rosario",
    "qs:photos_9r":0,
    "qs:photos_sr":0,
    "qs:pop_sr":"4",
    "wof:name":"Rosario",
    "wof:placetype":"locality",
    "wof:population":2318
},
  "geometry": {"coordinates":[122.3019,11.5832],"type":"Point"}
}