{
  "type": "Feature",
  "properties": {
    "gn:country":"PH",
    "gn:fcode":"PPL",
    "gn:population":2318,
    "iso:country":"PH",
    "name:ben_x_preferred":[
        "\u09b0\u09cb\u09b8\u09be\u09b0\u09bf\u0993"
    ],
    "name:ell_x_preferred":[
        "\u03a1\u03bf\u03b6\u03ac\u03c1\u03b9\u03bf"
    ],
    "name:fil_x_preferred":[
        "Rosario"
    ],
    "name:hin_x_preferred":[
        "\u0930\u094b\u091c\u093c\u093e\u0930\u093f\u092f\u094b"
    ],
    "name:kor_x_preferred":[
        "\ub85c\uc0ac\ub9ac\uc624"
    ],
    "name:tur_x_preferred":[
        "Rosario"
    ],
    "name:urd_x_preferred":[
        "\u0631\u0627\u0632\u0627\u0631\u06cc\u0648"
    ],
    "name:vie_x_preferred":[
        "Rosario"
    ],
    "qs:name":"Rosario",
    "qs:photos_9r":0,
    "qs:photos_sr":0,
    "qs:pop_sr":"4",
    "wof:name":"Rosario",
    "wof:placetype":"locality",
    "wof:population":2318
},
  "geometry": {"coordinates":[122.3019,11.5832],"type":"Point"}
}