{
  "type": "Feature",
  "properties": {
    "gn:country":"PH",
    "gn:fcode":"PPL",
    "gn:pop":13026,
    "iso:country":"PH",
    "name:fil_x_preferred":[
        "Codcod"
    ],
    "qs:name":"Codcod",
    "qs:photos_9r":0,
    "qs:photos_sr":0,
    "qs:pop_sr":"6",
    "wd:wordcount":822,
    "wof:name":"Codcod",
    "wof:placetype":"locality",
    "wof:population":13026
},
  "geometry": {"coordinates":[123.2495,10.46337],"type":"Point"}
}