{
  "type": "Feature",
  "properties": {
    "gn:country":"PH",
    "gn:fcode":"PPL",
    "gn:pop":2418,
    "iso:country":"PH",
    "name:eng_x_preferred":[
        "Sindon"
    ],
    "qs:name":"Sindon",
    "qs:photos_9r":0,
    "qs:photos_sr":0,
    "qs:pop_sr":"4",
    "wof:name":"Sindon",
    "wof:placetype":"locality",
    "wof:population":2418
},
  "geometry": {"coordinates":[122.01514,17.06034],"type":"Point"}
}