{
  "type": "Feature",
  "properties": {
    "gn:country":"PH",
    "gn:fcode":"PPL",
    "gn:pop":2211,
    "iso:country":"PH",
    "name:fil_x_preferred":[
        "Siguinon"
    ],
    "name:unk_x_variant":[
        "Seguinon"
    ],
    "qs:name":"Siguinon",
    "qs:photos_9r":0,
    "qs:photos_sr":0,
    "qs:pop_sr":"4",
    "wof:name":"Siguinon",
    "wof:placetype":"locality",
    "wof:population":2211
},
  "geometry": {"coordinates":[124.6806,10.9423],"type":"Point"}
}