{
  "type": "Feature",
  "properties": {
    "gn:admin1_code":"10",
    "gn:admin2_code":"42",
    "gn:admin3_code":"104209000.0",
    "gn:asciiname":"Dolipos",
    "gn:country_code":"PH",
    "gn:dem":117,
    "gn:feature_class":"P",
    "gn:feature_code":"PPL",
    "gn:name":"Dolipos",
    "gn:population":0,
    "gn:timezone":"Asia/Manila",
    "iso:country":"PH",
    "name:fil_x_preferred":[
        "Dolipos"
    ],
    "wof:name":"Dolipos",
    "wof:placetype":"locality"
},
  "geometry": {"coordinates":[123.76130000000001,8.4708],"type":"Point"}
}