{
  "type": "Feature",
  "properties": {
    "gn:admin1_code":"02",
    "gn:admin2_code":"68",
    "gn:admin3_code":"25702000.0",
    "gn:asciiname":"Burgos",
    "gn:country_code":"PH",
    "gn:dem":136,
    "gn:feature_class":"P",
    "gn:feature_code":"PPL",
    "gn:name":"Burgos",
    "gn:population":0,
    "gn:timezone":"Asia/Manila",
    "iso:country":"PH",
    "name:fil_x_preferred":[
        "Burgos"
    ],
    "wof:name":"Burgos",
    "wof:placetype":"locality"
},
  "geometry": {"coordinates":[121.51179999999999,16.4585],"type":"Point"}
}