{
  "type": "Feature",
  "properties": {
    "gn:admin1_code":"01",
    "gn:admin2_code":"29",
    "gn:admin3_code":"12907000.0",
    "gn:asciiname":"Anonang Mayor",
    "gn:country_code":"PH",
    "gn:dem":7,
    "gn:feature_class":"P",
    "gn:feature_code":"PPL",
    "gn:name":"Anonang Mayor",
    "gn:population":0,
    "gn:timezone":"Asia/Manila",
    "iso:country":"PH",
    "name:und_x_variant":[
        "Anomang Mayor"
    ],
    "wof:name":"Anonang Mayor",
    "wof:placetype":"locality"
},
  "geometry": {"coordinates":[120.3904,17.55064],"type":"Point"}
}