{
  "type": "Feature",
  "properties": {
    "iso:country":"PH",
    "name:fil_x_preferred":[
        "Bacong"
    ],
    "qs:gn_country":"PH",
    "qs:gn_fcode":"PPL",
    "qs:gn_pop":0,
    "qs:name":"Bacong",
    "qs:name_adm0":"Philippines",
    "qs:name_adm1":"Central Visayas",
    "qs:photos":282,
    "qs:photos_1k":57,
    "qs:photos_9k":1,
    "qs:photos_9r":4,
    "qs:photos_all":282,
    "qs:photos_sr":5,
    "qs:placetype":"Town",
    "qs:pop_sr":"0",
    "qs:woe_adm0":23424934,
    "wd:wordcount":386,
    "wof:name":"Bacong",
    "wof:placetype":"locality"
},
  "geometry": {"coordinates":[123.1602,9.948],"type":"Point"}
}