{
  "type": "Feature",
  "properties": {
    "iso:country":"PH",
    "name:bcl_x_preferred":[
        "Bacong"
    ],
    "name:cat_x_preferred":[
        "Bacong"
    ],
    "name:ceb_x_preferred":[
        "Bacong"
    ],
    "name:deu_x_preferred":[
        "Bacong"
    ],
    "name:eng_x_preferred":[
        "Bacong"
    ],
    "name:fil_x_preferred":[
        "Bacong"
    ],
    "name:fra_x_preferred":[
        "Bacong"
    ],
    "name:ilo_x_preferred":[
        "Bacong"
    ],
    "name:ind_x_preferred":[
        "Bacong"
    ],
    "name:ita_x_preferred":[
        "Bacong"
    ],
    "name:nld_x_preferred":[
        "Bacong"
    ],
    "name:nob_x_preferred":[
        "Bacong"
    ],
    "name:pag_x_preferred":[
        "Bacong"
    ],
    "name:pam_x_preferred":[
        "Bacong"
    ],
    "name:spa_x_preferred":[
        "Bacong"
    ],
    "name:swe_x_preferred":[
        "Bacong"
    ],
    "name:tgl_x_preferred":[
        "Bacong"
    ],
    "name:vie_x_preferred":[
        "Bacong"
    ],
    "name:war_x_preferred":[
        "Bacong"
    ],
    "name:zho_x_preferred":[
        "\u5df4\u5b54"
    ],
    "qs:gn_country":"PH",
    "qs:gn_fcode":"PPL",
    "qs:gn_pop":0,
    "qs:name":"Bacong",
    "qs:name_adm0":"Philippines",
    "qs:name_adm1":"Central Visayas",
    "qs:photos":282,
    "qs:photos_1k":57,
    "qs:photos_9k":1,
    "qs:photos_9r":4,
    "qs:photos_all":282,
    "qs:photos_sr":5,
    "qs:placetype":"Town",
    "qs:pop_sr":"0",
    "qs:woe_adm0":23424934,
    "wd:wordcount":386,
    "wof:name":"Bacong",
    "wof:placetype":"locality"
},
  "geometry": {"coordinates":[123.1602,9.948],"type":"Point"}
}