{
  "type": "Feature",
  "properties": {
    "gn:admin1_code":"07",
    "gn:admin2_code":"69",
    "gn:admin3_code":"76103000.0",
    "gn:asciiname":"Mausuagon",
    "gn:country_code":"PH",
    "gn:dem":130,
    "gn:feature_class":"P",
    "gn:feature_code":"PPL",
    "gn:name":"Mausuagon",
    "gn:population":0,
    "gn:timezone":"Asia/Manila",
    "iso:country":"PH",
    "name:fil_x_preferred":[
        "Mausuagon"
    ],
    "name:und_x_variant":[
        "Mauswagon"
    ],
    "wof:name":"Mausuagon",
    "wof:placetype":"locality"
},
  "geometry": {"coordinates":[123.6156,9.1568],"type":"Point"}
}