{
  "type": "Feature",
  "properties": {
    "gn:admin1_code":"06",
    "gn:admin2_code":"30",
    "gn:admin3_code":"63014000.0",
    "gn:asciiname":"Alipato",
    "gn:country_code":"PH",
    "gn:dem":77,
    "gn:feature_class":"P",
    "gn:feature_code":"PPL",
    "gn:name":"Alipato",
    "gn:population":0,
    "gn:timezone":"Asia/Manila",
    "iso:country":"PH",
    "name:fil_x_preferred":[
        "Alipato"
    ],
    "wof:name":"Alipato",
    "wof:placetype":"locality"
},
  "geometry": {"coordinates":[123.25472000000001,11.43889],"type":"Point"}
}