{
  "type": "Feature",
  "properties": {
    "gn:admin1_code":"08",
    "gn:admin2_code":"37",
    "gn:admin3_code":"83751000.0",
    "gn:asciiname":"Iligay",
    "gn:country_code":"PH",
    "gn:dem":93,
    "gn:feature_class":"P",
    "gn:feature_code":"PPL",
    "gn:name":"Iligay",
    "gn:population":0,
    "gn:timezone":"Asia/Manila",
    "iso:country":"PH",
    "name:eng_x_preferred":[
        "Iligay"
    ],
    "wof:name":"Iligay",
    "wof:placetype":"locality"
},
  "geometry": {"coordinates":[124.44670000000001,11.2598],"type":"Point"}
}