{
  "type": "Feature",
  "properties": {
    "gn:admin1_code":"41",
    "gn:admin2_code":"54",
    "gn:admin3_code":"175906000.0",
    "gn:asciiname":"Mangansag",
    "gn:country_code":"PH",
    "gn:dem":21,
    "gn:feature_class":"P",
    "gn:feature_code":"PPL",
    "gn:name":"Mangansag",
    "gn:population":0,
    "gn:timezone":"Asia/Manila",
    "iso:country":"PH",
    "name:fil_x_preferred":[
        "Mangansag"
    ],
    "name:und_x_variant":[
        "Mahgansag"
    ],
    "wof:name":"Mangansag",
    "wof:placetype":"locality"
},
  "geometry": {"coordinates":[122.06021,12.81921],"type":"Point"}
}