{
  "type": "Feature",
  "properties": {
    "gn:admin1_code":"12",
    "gn:admin2_code":"57",
    "gn:admin3_code":"124712000.0",
    "gn:asciiname":"Balong",
    "gn:country_code":"PH",
    "gn:dem":16,
    "gn:feature_class":"P",
    "gn:feature_code":"PPL",
    "gn:name":"Balong",
    "gn:population":0,
    "gn:timezone":"Asia/Manila",
    "iso:country":"PH",
    "name:fil_x_preferred":[
        "Balong"
    ],
    "wof:name":"Balong",
    "wof:placetype":"locality"
},
  "geometry": {"coordinates":[124.63,7.03306],"type":"Point"}
}