{
  "type": "Feature",
  "properties": {
    "gn:admin1_code":"09",
    "gn:admin2_code":"66",
    "gn:admin3_code":"97317000.0",
    "gn:asciiname":"Sagwa",
    "gn:country_code":"PH",
    "gn:dem":379,
    "gn:feature_class":"P",
    "gn:feature_code":"PPL",
    "gn:name":"Sagwa",
    "gn:population":0,
    "gn:timezone":"Asia/Manila",
    "iso:country":"PH",
    "name:eng_x_preferred":[
        "Sagwa"
    ],
    "wof:name":"Sagwa",
    "wof:placetype":"locality"
},
  "geometry": {"coordinates":[123.2431,7.5928],"type":"Point"}
}