{
  "type": "Feature",
  "properties": {
    "gn:admin1_code":"13",
    "gn:admin2_code":"02",
    "gn:admin3_code":"160201000.0",
    "gn:asciiname":"Talaganao",
    "gn:country_code":"PH",
    "gn:dem":14,
    "gn:feature_class":"P",
    "gn:feature_code":"PPL",
    "gn:name":"Talaganao",
    "gn:population":0,
    "gn:timezone":"Asia/Manila",
    "iso:country":"PH",
    "name:fil_x_preferred":[
        "Talaganao"
    ],
    "wof:name":"Talaganao",
    "wof:placetype":"locality"
},
  "geometry": {"coordinates":[125.43333,8.95],"type":"Point"}
}