{
  "type": "Feature",
  "properties": {
    "gn:admin1_code":"03",
    "gn:admin2_code":"47",
    "gn:admin3_code":"34918000.0",
    "gn:asciiname":"Monic",
    "gn:country_code":"PH",
    "gn:dem":28,
    "gn:feature_class":"P",
    "gn:feature_code":"PPL",
    "gn:name":"Monic",
    "gn:population":0,
    "gn:timezone":"Asia/Manila",
    "iso:country":"PH",
    "name:fil_x_preferred":[
        "Monic"
    ],
    "wof:name":"Monic",
    "wof:placetype":"locality"
},
  "geometry": {"coordinates":[120.68288,15.6901],"type":"Point"}
}