{
  "type": "Feature",
  "properties": {
    "gn:admin1_code":"07",
    "gn:admin2_code":"46",
    "gn:admin3_code":"74619000.0",
    "gn:asciiname":"Malabohan",
    "gn:country_code":"PH",
    "gn:dem":13,
    "gn:feature_class":"P",
    "gn:feature_code":"PPL",
    "gn:name":"Malabohan",
    "gn:population":0,
    "gn:timezone":"Asia/Manila",
    "iso:country":"PH",
    "name:fil_x_preferred":[
        "Malabohan"
    ],
    "wof:name":"Malabohan",
    "wof:placetype":"locality"
},
  "geometry": {"coordinates":[123.0749,9.0677],"type":"Point"}
}