{
  "type": "Feature",
  "properties": {
    "gn:admin1_code":"06",
    "gn:admin2_code":"30",
    "gn:admin3_code":"63009000.0",
    "gn:asciiname":"Calangag",
    "gn:country_code":"PH",
    "gn:dem":35,
    "gn:feature_class":"P",
    "gn:feature_code":"PPL",
    "gn:name":"Cala\u00f1gag",
    "gn:population":0,
    "gn:timezone":"Asia/Manila",
    "iso:country":"PH",
    "name:fil_x_preferred":[
        "Cala\u00f1gag"
    ],
    "wof:name":"Calangag",
    "wof:placetype":"locality"
},
  "geometry": {"coordinates":[123.08333,11.41667],"type":"Point"}
}