{
  "type": "Feature",
  "properties": {
    "gn:country":"PH",
    "gn:fcode":"PPL",
    "gn:population":2658,
    "iso:country":"PH",
    "name:fil_x_preferred":[
        "Cambanay"
    ],
    "qs:name":"Cambanay",
    "qs:photos_9r":0,
    "qs:photos_sr":0,
    "qs:pop_sr":"4",
    "wof:name":"Cambanay",
    "wof:placetype":"locality",
    "wof:population":2658
},
  "geometry": {"coordinates":[123.98611,10.54361],"type":"Point"}
}