{
  "type": "Feature",
  "properties": {
    "gn:admin1_code":"06",
    "gn:admin2_code":"30",
    "gn:admin3_code":"63027000.0",
    "gn:asciiname":"Taluay",
    "gn:country_code":"PH",
    "gn:dem":100,
    "gn:feature_class":"P",
    "gn:feature_code":"PPL",
    "gn:name":"Taluay",
    "gn:population":0,
    "gn:timezone":"Asia/Manila",
    "iso:country":"PH",
    "name:fil_x_preferred":[
        "Taluay"
    ],
    "wof:name":"Taluay",
    "wof:placetype":"locality"
},
  "geometry": {"coordinates":[122.9597,11.244],"type":"Point"}
}