{
  "type": "Feature",
  "properties": {
    "gn:admin1_code":"02",
    "gn:admin2_code":"31",
    "gn:admin3_code":"23135000.0",
    "gn:asciiname":"Sinappil",
    "gn:cc2":"PH",
    "gn:country_code":"PH",
    "gn:dem":103,
    "gn:elevation":"95.0",
    "gn:feature_class":"P",
    "gn:feature_code":"PPL",
    "gn:name":"Sinappil",
    "gn:population":0,
    "gn:timezone":"Asia/Manila",
    "iso:country":"PH",
    "name:und_x_variant":[
        "Sinippit"
    ],
    "wof:name":"Sinappil",
    "wof:placetype":"locality"
},
  "geometry": {"coordinates":[121.51194,16.64056],"type":"Point"}
}