{
  "type": "Feature",
  "properties": {
    "gn:admin1_code":"08",
    "gn:admin2_code":"H9",
    "gn:admin3_code":"87806000.0",
    "gn:asciiname":"Mapuyo",
    "gn:country_code":"PH",
    "gn:dem":3,
    "gn:feature_class":"P",
    "gn:feature_code":"PPL",
    "gn:name":"Mapuyo",
    "gn:population":0,
    "gn:timezone":"Asia/Manila",
    "iso:country":"PH",
    "name:fil_x_preferred":[
        "Mapuyo"
    ],
    "wof:name":"Mapuyo",
    "wof:placetype":"locality"
},
  "geometry": {"coordinates":[124.4237,11.7058],"type":"Point"}
}