{
  "type": "Feature",
  "properties": {
    "gn:admin1_code":"08",
    "gn:admin2_code":"59",
    "gn:admin3_code":"86414000.0",
    "gn:asciiname":"Sua",
    "gn:country_code":"PH",
    "gn:dem":42,
    "gn:feature_class":"P",
    "gn:feature_code":"PPL",
    "gn:name":"Sua",
    "gn:population":0,
    "gn:timezone":"Asia/Manila",
    "iso:country":"PH",
    "name:fil_x_preferred":[
        "Sua"
    ],
    "wof:name":"Sua",
    "wof:placetype":"locality"
},
  "geometry": {"coordinates":[125.21666999999999,10.25],"type":"Point"}
}