{
  "type": "Feature",
  "properties": {
    "gn:admin1_code":"06",
    "gn:admin2_code":"04",
    "gn:admin3_code":"60401000.0",
    "gn:asciiname":"Talon Sur",
    "gn:country_code":"PH",
    "gn:dem":60,
    "gn:feature_class":"P",
    "gn:feature_code":"PPL",
    "gn:name":"Talon Sur",
    "gn:population":0,
    "gn:timezone":"Asia/Manila",
    "iso:country":"PH",
    "name:fil_x_preferred":[
        "Talon Sur"
    ],
    "wof:name":"Talon Sur",
    "wof:placetype":"locality"
},
  "geometry": {"coordinates":[122.45261000000001,11.4958],"type":"Point"}
}