{
  "type": "Feature",
  "properties": {
    "gn:country":"PH",
    "gn:fcode":"PPL",
    "gn:population":2384,
    "iso:country":"PH",
    "name:und_x_variant":[
        "Kulumpang"
    ],
    "qs:name":"Kulempang",
    "qs:photos_9r":0,
    "qs:photos_sr":0,
    "qs:pop_sr":"4",
    "wof:name":"Kulempang",
    "wof:placetype":"locality",
    "wof:population":2384
},
  "geometry": {"coordinates":[124.38972,7.51944],"type":"Point"}
}