{
  "type": "Feature",
  "properties": {
    "iso:country":"PH",
    "name:bcl_x_preferred":[
        "Pigkawayan"
    ],
    "name:cbk_zam_x_preferred":[
        "Pigkawayan"
    ],
    "name:ceb_x_preferred":[
        "Pigkawayan"
    ],
    "name:deu_x_preferred":[
        "Pigkawayan"
    ],
    "name:eng_x_preferred":[
        "Pigcawayan"
    ],
    "name:fra_x_preferred":[
        "Pigkawayan"
    ],
    "name:ilo_x_preferred":[
        "Pigkawayan"
    ],
    "name:ind_x_preferred":[
        "Pigkawayan"
    ],
    "name:ita_x_preferred":[
        "Pigkawayan"
    ],
    "name:nld_x_preferred":[
        "Pigkawayan"
    ],
    "name:pag_x_preferred":[
        "Pigkawayan"
    ],
    "name:pam_x_preferred":[
        "Pigkawayan"
    ],
    "name:spa_x_preferred":[
        "Pigcaguay\u00e1n"
    ],
    "name:swe_x_preferred":[
        "Pigkawayan"
    ],
    "name:tgl_x_preferred":[
        "Pigkawayan"
    ],
    "name:unk_x_variant":[
        "Pigcawayan"
    ],
    "name:vie_x_preferred":[
        "Pigkawayan"
    ],
    "name:war_x_preferred":[
        "Pigcawayan"
    ],
    "name:war_x_variant":[
        "Pigkawayan"
    ],
    "qs:gn_country":"PH",
    "qs:gn_fcode":"PPL",
    "qs:gn_pop":11420,
    "qs:name":"Pigkawayan",
    "qs:name_adm0":"Philippines",
    "qs:name_adm1":"Soccsksargen",
    "qs:photos":0,
    "qs:photos_1k":0,
    "qs:photos_9k":1,
    "qs:photos_9r":1,
    "qs:photos_all":4,
    "qs:photos_sr":0,
    "qs:placetype":"Town",
    "qs:pop_sr":"6",
    "qs:woe_adm0":23424934,
    "wd:wordcount":775,
    "wof:name":"Pigkawayan",
    "wof:placetype":"locality",
    "wof:population":11420
},
  "geometry": {"coordinates":[124.42556,7.27722],"type":"Point"}
}