{
  "type": "Feature",
  "properties": {
    "gn:country":"PH",
    "gn:fcode":"PPL",
    "gn:population":2444,
    "iso:country":"PH",
    "name:fil_x_preferred":[
        "Manikling"
    ],
    "qs:name":"Manikling",
    "qs:photos_9r":0,
    "qs:photos_sr":0,
    "qs:pop_sr":"4",
    "wof:name":"Manikling",
    "wof:placetype":"locality",
    "wof:population":2444
},
  "geometry": {"coordinates":[126.06063,6.87907],"type":"Point"}
}