{
  "type": "Feature",
  "properties": {
    "gn:admin1_code":"06",
    "gn:admin2_code":"J3",
    "gn:admin3_code":"67905000.0",
    "gn:asciiname":"Inampulungan",
    "gn:country_code":"PH",
    "gn:dem":13,
    "gn:feature_class":"P",
    "gn:feature_code":"PPL",
    "gn:name":"Inampulungan",
    "gn:population":0,
    "gn:timezone":"Asia/Manila",
    "iso:country":"PH",
    "name:fil_x_preferred":[
        "Inampulungan"
    ],
    "name:und_x_variant":[
        "Ynampalogan",
        "Inampulugan",
        "Inampologan"
    ],
    "wof:name":"Inampulungan",
    "wof:placetype":"locality"
},
  "geometry": {"coordinates":[122.7145,10.4647],"type":"Point"}
}