{
  "type": "Feature",
  "properties": {
    "gn:admin1_code":"41",
    "gn:admin2_code":"38",
    "gn:admin3_code":"174005000.0",
    "gn:asciiname":"Aturan",
    "gn:country_code":"PH",
    "gn:dem":48,
    "gn:feature_class":"P",
    "gn:feature_code":"PPL",
    "gn:name":"Aturan",
    "gn:population":0,
    "gn:timezone":"Asia/Manila",
    "iso:country":"PH",
    "name:fil_x_preferred":[
        "Aturan"
    ],
    "wof:name":"Aturan",
    "wof:placetype":"locality"
},
  "geometry": {"coordinates":[121.9924,13.49],"type":"Point"}
}