{
  "type": "Feature",
  "properties": {
    "gn:admin1_code":"15",
    "gn:admin2_code":"32",
    "gn:admin3_code":"143209000.0",
    "gn:asciiname":"Fulan",
    "gn:country_code":"PH",
    "gn:dem":248,
    "gn:feature_class":"P",
    "gn:feature_code":"PPL",
    "gn:name":"Fulan",
    "gn:population":0,
    "gn:timezone":"Asia/Manila",
    "iso:country":"PH",
    "name:fil_x_preferred":[
        "Fullan"
    ],
    "name:fil_x_variant":[
        "Fulan"
    ],
    "wof:name":"Fulan",
    "wof:placetype":"locality"
},
  "geometry": {"coordinates":[121.3734,17.4817],"type":"Point"}
}