{
  "type": "Feature",
  "properties": {
    "gn:admin1_code":"41",
    "gn:admin2_code":"49",
    "gn:admin3_code":"175301000.0",
    "gn:asciiname":"Tagpait",
    "gn:country_code":"PH",
    "gn:dem":7,
    "gn:feature_class":"P",
    "gn:feature_code":"PPL",
    "gn:name":"Tagpait",
    "gn:population":0,
    "gn:timezone":"Asia/Manila",
    "iso:country":"PH",
    "name:fil_x_preferred":[
        "Tagpait"
    ],
    "wof:name":"Tagpait",
    "wof:placetype":"locality"
},
  "geometry": {"coordinates":[118.54145,9.42818],"type":"Point"}
}