{
  "type": "Feature",
  "properties": {
    "iso:country":"PH",
    "name:fil_x_preferred":[
        "San Policarpo"
    ],
    "qs:gn_country":"PH",
    "qs:gn_fcode":"PPL",
    "qs:gn_pop":5616,
    "qs:name":"San Policarpio",
    "qs:name_adm0":"Philippines",
    "qs:name_adm1":"Eastern Visayas",
    "qs:photos":37,
    "qs:photos_1k":7,
    "qs:photos_9k":1,
    "qs:photos_9r":2,
    "qs:photos_all":37,
    "qs:photos_sr":2,
    "qs:placetype":"Town",
    "qs:pop_sr":"5",
    "qs:woe_adm0":23424934,
    "wof:name":"San Policarpio",
    "wof:placetype":"locality",
    "wof:population":5616
},
  "geometry": {"coordinates":[124.56950000000001,12.0686],"type":"Point"}
}