{
  "type": "Feature",
  "properties": {
    "gn:admin1_code":"01",
    "gn:admin2_code":"51",
    "gn:admin3_code":"15503000.0",
    "gn:asciiname":"Taytaybaques",
    "gn:country_code":"PH",
    "gn:dem":11,
    "gn:feature_class":"P",
    "gn:feature_code":"PPL",
    "gn:name":"Taytaybaques",
    "gn:population":0,
    "gn:timezone":"Asia/Manila",
    "iso:country":"PH",
    "name:fil_x_preferred":[
        "Taytaybaques"
    ],
    "name:und_x_variant":[
        "Taytaybacus"
    ],
    "wof:name":"Taytaybaques",
    "wof:placetype":"locality"
},
  "geometry": {"coordinates":[120.07894,16.16121],"type":"Point"}
}