{
  "type": "Feature",
  "properties": {
    "gn:admin1_code":"02",
    "gn:admin2_code":"48",
    "gn:admin3_code":"25011000.0",
    "gn:asciiname":"Runruno",
    "gn:country_code":"PH",
    "gn:dem":273,
    "gn:feature_class":"P",
    "gn:feature_code":"PPL",
    "gn:name":"Runruno",
    "gn:population":0,
    "gn:timezone":"Asia/Manila",
    "iso:country":"PH",
    "name:fil_x_preferred":[
        "Runruno"
    ],
    "wof:name":"Runruno",
    "wof:placetype":"locality"
},
  "geometry": {"coordinates":[121.2902,16.4927],"type":"Point"}
}