{
  "type": "Feature",
  "properties": {
    "gn:admin1_code":"07",
    "gn:admin2_code":"21",
    "gn:admin3_code":"72212000.0",
    "gn:asciiname":"Kaneki",
    "gn:country_code":"PH",
    "gn:dem":227,
    "gn:feature_class":"P",
    "gn:feature_code":"PPL",
    "gn:name":"Kaneki",
    "gn:population":0,
    "gn:timezone":"Asia/Manila",
    "iso:country":"PH",
    "name:fil_x_preferred":[
        "Kaneki"
    ],
    "wof:name":"Kaneki",
    "wof:placetype":"locality"
},
  "geometry": {"coordinates":[123.4392,9.6203],"type":"Point"}
}