{
  "type": "Feature",
  "properties": {
    "gn:admin1_code":"06",
    "gn:admin2_code":"H3",
    "gn:admin3_code":"64519000.0",
    "gn:asciiname":"Panaquiao",
    "gn:country_code":"PH",
    "gn:dem":40,
    "gn:feature_class":"P",
    "gn:feature_code":"PPL",
    "gn:name":"Panaquiao",
    "gn:population":0,
    "gn:timezone":"Asia/Manila",
    "iso:country":"PH",
    "name:fil_x_preferred":[
        "Panaquiao"
    ],
    "wof:name":"Panaquiao",
    "wof:placetype":"locality"
},
  "geometry": {"coordinates":[123.0748,10.262],"type":"Point"}
}