{
  "type": "Feature",
  "properties": {
    "gn:admin1_code":"40",
    "gn:admin2_code":"09",
    "gn:admin3_code":"41015000.0",
    "gn:asciiname":"Alitap",
    "gn:country_code":"PH",
    "gn:dem":28,
    "gn:feature_class":"P",
    "gn:feature_code":"PPL",
    "gn:name":"Alitap",
    "gn:population":0,
    "gn:timezone":"Asia/Manila",
    "iso:country":"PH",
    "name:fil_x_preferred":[
        "Alitap"
    ],
    "wof:name":"Alitap",
    "wof:placetype":"locality"
},
  "geometry": {"coordinates":[121.2749,13.5985],"type":"Point"}
}