{
  "type": "Feature",
  "properties": {
    "iso:country":"PH",
    "name:bcl_x_preferred":[
        "Matalam"
    ],
    "name:cbk_zam_x_preferred":[
        "Matalam"
    ],
    "name:ceb_x_preferred":[
        "Matalam"
    ],
    "name:deu_x_preferred":[
        "Matalam"
    ],
    "name:dut_x_preferred":[
        "Matalam"
    ],
    "name:eng_x_preferred":[
        "Matalam"
    ],
    "name:fre_x_preferred":[
        "Matalam"
    ],
    "name:ger_x_preferred":[
        "Matalam"
    ],
    "name:ilo_x_preferred":[
        "Matalam"
    ],
    "name:ind_x_preferred":[
        "Matalam"
    ],
    "name:ita_x_preferred":[
        "Matalam"
    ],
    "name:nld_x_preferred":[
        "Matalam"
    ],
    "name:pag_x_preferred":[
        "Matalam"
    ],
    "name:pam_x_preferred":[
        "Matalam"
    ],
    "name:spa_x_preferred":[
        "Matalam"
    ],
    "name:swe_x_preferred":[
        "Matalam"
    ],
    "name:tgl_x_preferred":[
        "Matalam"
    ],
    "name:unk_x_variant":[
        "Matalan"
    ],
    "name:vie_x_preferred":[
        "Matalam"
    ],
    "name:war_x_preferred":[
        "Matalam"
    ],
    "qs:gn_country":"PH",
    "qs:gn_fcode":"PPL",
    "qs:gn_pop":9783,
    "qs:name":"Matalam",
    "qs:name_adm0":"Philippines",
    "qs:name_adm1":"Soccsksargen",
    "qs:photos":0,
    "qs:photos_1k":0,
    "qs:photos_9k":0,
    "qs:photos_9r":0,
    "qs:photos_all":0,
    "qs:photos_sr":0,
    "qs:placetype":"Town",
    "qs:pop_sr":"5",
    "qs:woe_adm0":23424934,
    "wd:wordcount":531,
    "wof:name":"Matalam",
    "wof:placetype":"locality",
    "wof:population":9783
},
  "geometry": {"coordinates":[124.90056,7.08639],"type":"Point"}
}