{
  "type": "Feature",
  "properties": {
    "gn:admin1_code":"14",
    "gn:admin2_code":"56",
    "gn:admin3_code":"153815000.0",
    "gn:asciiname":"Kabakaba",
    "gn:country_code":"PH",
    "gn:dem":440,
    "gn:feature_class":"P",
    "gn:feature_code":"PPL",
    "gn:name":"Kabakaba",
    "gn:population":0,
    "gn:timezone":"Asia/Manila",
    "iso:country":"PH",
    "name:fil_x_preferred":[
        "Kabakaba"
    ],
    "wof:name":"Kabakaba",
    "wof:placetype":"locality"
},
  "geometry": {"coordinates":[124.11944,7.03833],"type":"Point"}
}