{
  "type": "Feature",
  "properties": {
    "gn:country":"PH",
    "gn:fcode":"ADM3",
    "gn:pop":22939,
    "iso:country":"PH",
    "name:fil_x_preferred":[
        "Burdeos"
    ],
    "qs:name":"Burdeos",
    "qs:photos_9r":0,
    "qs:photos_sr":0,
    "qs:pop_sr":"7",
    "wof:name":"Burdeos",
    "wof:placetype":"localadmin",
    "wof:population":22939
},
  "geometry": {"coordinates":[122.01667,14.91667],"type":"Point"}
}