{
  "type": "Feature",
  "properties": {
    "gn:country":"PH",
    "gn:fcode":"ADM3",
    "gn:population":22939,
    "iso:country":"PH",
    "name:bcl_x_preferred":[
        "Burdeos"
    ],
    "name:ceb_x_preferred":[
        "Burdeos"
    ],
    "name:deu_x_preferred":[
        "Burdeos"
    ],
    "name:fil_x_preferred":[
        "Burdeos"
    ],
    "name:fra_x_preferred":[
        "Burdeos"
    ],
    "name:ilo_x_preferred":[
        "Burdeos"
    ],
    "name:ind_x_preferred":[
        "Burdeos"
    ],
    "name:ita_x_preferred":[
        "Burdeos"
    ],
    "name:nld_x_preferred":[
        "Burdeos"
    ],
    "name:pag_x_preferred":[
        "Burdeos"
    ],
    "name:pam_x_preferred":[
        "Burdeos"
    ],
    "name:spa_x_preferred":[
        "Burdeos"
    ],
    "name:swe_x_preferred":[
        "Burdeos"
    ],
    "name:tgl_x_preferred":[
        "Burdeos"
    ],
    "name:vie_x_preferred":[
        "Burdeos"
    ],
    "name:war_x_preferred":[
        "Burdeos"
    ],
    "qs:name":"Burdeos",
    "qs:photos_9r":0,
    "qs:photos_sr":0,
    "qs:pop_sr":"7",
    "wof:name":"Burdeos",
    "wof:placetype":"localadmin",
    "wof:population":22939
},
  "geometry": {"coordinates":[122.01667,14.91667],"type":"Point"}
}