{
  "type": "Feature",
  "properties": {
    "gn:admin1_code":"40",
    "gn:admin2_code":"H2",
    "gn:admin3_code":"45622000.0",
    "gn:asciiname":"Dalagan",
    "gn:country_code":"PH",
    "gn:dem":8,
    "gn:feature_class":"P",
    "gn:feature_code":"PPL",
    "gn:name":"Dalagan",
    "gn:population":0,
    "gn:timezone":"Asia/Manila",
    "iso:country":"PH",
    "name:fil_x_preferred":[
        "Dalagan"
    ],
    "name:fil_x_variant":[
        "Danlagan"
    ],
    "wof:name":"Dalagan",
    "wof:placetype":"locality"
},
  "geometry": {"coordinates":[122.2667,13.8872],"type":"Point"}
}