{
  "type": "Feature",
  "properties": {
    "gn:admin1_code":"06",
    "gn:admin2_code":"H3",
    "gn:admin3_code":"64515000.0",
    "gn:asciiname":"Mananga",
    "gn:country_code":"PH",
    "gn:dem":180,
    "gn:feature_class":"P",
    "gn:feature_code":"PPL",
    "gn:name":"Mananga",
    "gn:population":0,
    "gn:timezone":"Asia/Manila",
    "iso:country":"PH",
    "name:afr_x_preferred":[
        "Mananga"
    ],
    "name:fil_x_preferred":[
        "Mananga"
    ],
    "wof:name":"Mananga",
    "wof:placetype":"locality"
},
  "geometry": {"coordinates":[122.8339,9.7691],"type":"Point"}
}