{
  "type": "Feature",
  "properties": {
    "gn:admin1_code":"11",
    "gn:admin2_code":"25",
    "gn:asciiname":"Talos",
    "gn:country_code":"PH",
    "gn:dem":145,
    "gn:feature_class":"P",
    "gn:feature_code":"PPL",
    "gn:name":"Talos",
    "gn:population":0,
    "gn:timezone":"Asia/Manila",
    "iso:country":"PH",
    "name:fil_x_preferred":[
        "Talos"
    ],
    "wof:name":"Talos",
    "wof:placetype":"locality"
},
  "geometry": {"coordinates":[125.30944,6.34083],"type":"Point"}
}