{
  "type": "Feature",
  "properties": {
    "gn:admin1_code":"05",
    "gn:admin2_code":"16",
    "gn:admin3_code":"51736000.0",
    "gn:asciiname":"Mayangayanga",
    "gn:country_code":"PH",
    "gn:dem":189,
    "gn:feature_class":"P",
    "gn:feature_code":"PPL",
    "gn:name":"Mayangayanga",
    "gn:population":0,
    "gn:timezone":"Asia/Manila",
    "iso:country":"PH",
    "name:fil_x_preferred":[
        "Mayangayanga"
    ],
    "name:und_x_variant":[
        "Mayangayana"
    ],
    "wof:name":"Mayangayanga",
    "wof:placetype":"locality"
},
  "geometry": {"coordinates":[123.435,13.6025],"type":"Point"}
}