{
  "type": "Feature",
  "properties": {
    "iso:country":"PH",
    "name:bcl_x_preferred":[
        "La Paz"
    ],
    "name:cat_x_preferred":[
        "La Paz"
    ],
    "name:cbk_zam_x_preferred":[
        "La Paz"
    ],
    "name:ceb_x_preferred":[
        "La Paz"
    ],
    "name:deu_x_preferred":[
        "La Paz"
    ],
    "name:eng_x_preferred":[
        "La Paz"
    ],
    "name:fil_x_preferred":[
        "La Paz"
    ],
    "name:fra_x_preferred":[
        "La Paz"
    ],
    "name:heb_x_preferred":[
        "\u05dc\u05d4 \u05e4\u05d0\u05e1"
    ],
    "name:ilo_x_preferred":[
        "La Paz"
    ],
    "name:ind_x_preferred":[
        "La Paz"
    ],
    "name:ita_x_preferred":[
        "La Paz"
    ],
    "name:mkd_x_preferred":[
        "\u041b\u0430 \u041f\u0430\u0441"
    ],
    "name:msa_x_preferred":[
        "La Paz"
    ],
    "name:nld_x_preferred":[
        "La Paz"
    ],
    "name:oci_x_preferred":[
        "La Paz"
    ],
    "name:pag_x_preferred":[
        "La Paz"
    ],
    "name:pam_x_preferred":[
        "La Paz"
    ],
    "name:spa_x_preferred":[
        "La Paz"
    ],
    "name:swe_x_preferred":[
        "La Paz"
    ],
    "name:tgl_x_preferred":[
        "La Paz"
    ],
    "name:urd_x_preferred":[
        "\u0644\u0627 \u067e\u0627\u0632"
    ],
    "name:vie_x_preferred":[
        "La Paz"
    ],
    "name:war_x_preferred":[
        "La Paz"
    ],
    "qs:gn_country":"PH",
    "qs:gn_fcode":"PPLA3",
    "qs:gn_pop":3405,
    "qs:name":"La Paz",
    "qs:name_adm0":"Philippines",
    "qs:name_adm1":"Cordillera Administrative Region",
    "qs:photos":0,
    "qs:photos_1k":0,
    "qs:photos_9k":0,
    "qs:photos_9r":0,
    "qs:photos_all":0,
    "qs:photos_sr":0,
    "qs:placetype":"Town",
    "qs:pop_sr":"4",
    "qs:woe_adm0":23424934,
    "wd:wordcount":102,
    "wof:name":"La Paz",
    "wof:placetype":"locality",
    "wof:population":3405
},
  "geometry": {"coordinates":[120.68640000000001,17.6746],"type":"Point"}
}