{
  "type": "Feature",
  "properties": {
    "gn:admin1_code":"11",
    "gn:admin2_code":"P3",
    "gn:admin3_code":"118605000.0",
    "gn:asciiname":"Bolay",
    "gn:country_code":"PH",
    "gn:dem":45,
    "gn:feature_class":"P",
    "gn:feature_code":"PPL",
    "gn:name":"Bolay",
    "gn:population":0,
    "gn:timezone":"Asia/Manila",
    "iso:country":"PH",
    "name:fil_x_preferred":[
        "Bolay"
    ],
    "wof:name":"Bolay",
    "wof:placetype":"locality"
},
  "geometry": {"coordinates":[125.45917,5.4325],"type":"Point"}
}