{
  "type": "Feature",
  "properties": {
    "gn:admin1_code":"03",
    "gn:admin2_code":"47",
    "gn:admin3_code":"34912000.0",
    "gn:asciiname":"Antonio",
    "gn:country_code":"PH",
    "gn:dem":29,
    "gn:feature_class":"P",
    "gn:feature_code":"PPL",
    "gn:name":"Antonio",
    "gn:population":0,
    "gn:timezone":"Asia/Manila",
    "iso:country":"PH",
    "wof:name":"Antonio",
    "wof:placetype":"locality"
},
  "geometry": {"coordinates":[120.91867999999999,15.33854],"type":"Point"}
}