{
  "type": "Feature",
  "properties": {
    "gn:admin1_code":"03",
    "gn:admin2_code":"47",
    "gn:admin3_code":"34912000.0",
    "gn:asciiname":"Antonio",
    "gn:country_code":"PH",
    "gn:dem":29,
    "gn:feature_class":"P",
    "gn:feature_code":"PPL",
    "gn:name":"Antonio",
    "gn:population":0,
    "gn:timezone":"Asia/Manila",
    "iso:country":"PH",
    "name:epo_x_preferred":[
        "Antonio"
    ],
    "name:fra_x_preferred":[
        "Antonio"
    ],
    "name:hye_x_preferred":[
        "\u0531\u0576\u057f\u0578\u0576\u056b\u0578"
    ],
    "name:ita_x_preferred":[
        "Antonio"
    ],
    "name:jpn_x_preferred":[
        "\u30a2\u30f3\u30c8\u30cb\u30aa"
    ],
    "name:nld_x_preferred":[
        "Antonio"
    ],
    "name:nor_x_preferred":[
        "Antonio"
    ],
    "name:slv_x_preferred":[
        "Antonio"
    ],
    "name:spa_x_preferred":[
        "Antonio"
    ],
    "wof:name":"Antonio",
    "wof:placetype":"locality"
},
  "geometry": {"coordinates":[120.91867999999999,15.33854],"type":"Point"}
}