{
  "type": "Feature",
  "properties": {
    "gn:country":"PH",
    "gn:fcode":"PPL",
    "gn:population":2306,
    "iso:country":"PH",
    "name:fil_x_preferred":[
        "Telafas"
    ],
    "qs_pg:aaroncc":"PH",
    "qs_pg:gn_country":"PH",
    "qs_pg:gn_fcode":"PPL",
    "qs_pg:gn_pop":2306,
    "qs_pg:name":"Telafas",
    "qs_pg:photos_9r":0,
    "qs_pg:photos_sr":0,
    "qs_pg:pop_sr":4,
    "qs_pg:qs_pg_placetype":"locality",
    "wof:name":"Telafas",
    "wof:placetype":"locality",
    "wof:population":2306
},
  "geometry": {"coordinates":[124.97499999999999,6.63528],"type":"Point"}
}