{
  "type": "Feature",
  "properties": {
    "gn:admin1_code":"11",
    "gn:admin2_code":"26",
    "gn:admin3_code":"112509000.0",
    "gn:asciiname":"Kamansi",
    "gn:country_code":"PH",
    "gn:dem":25,
    "gn:feature_class":"P",
    "gn:feature_code":"PPL",
    "gn:name":"Kamansi",
    "gn:population":0,
    "gn:timezone":"Asia/Manila",
    "iso:country":"PH",
    "name:und_x_variant":[
        "Camansi",
        "Kamansi"
    ],
    "wof:name":"Kamansi",
    "wof:placetype":"locality"
},
  "geometry": {"coordinates":[126.18297,6.93851],"type":"Point"}
}