{
  "type": "Feature",
  "properties": {
    "gn:admin1_code":"01",
    "gn:admin2_code":"51",
    "gn:admin3_code":"15526000.0",
    "gn:asciiname":"Bari",
    "gn:country_code":"PH",
    "gn:dem":6,
    "gn:feature_class":"P",
    "gn:feature_code":"PPL",
    "gn:name":"Bari",
    "gn:population":0,
    "gn:timezone":"Asia/Manila",
    "iso:country":"PH",
    "name:fil_x_preferred":[
        "Bari"
    ],
    "wof:name":"Bari",
    "wof:placetype":"locality"
},
  "geometry": {"coordinates":[120.39636000000002,16.05862],"type":"Point"}
}