{
  "type": "Feature",
  "properties": {
    "gn:admin1_code":"06",
    "gn:admin2_code":"H3",
    "gn:admin3_code":"64512000.0",
    "gn:asciiname":"Palasa-ron",
    "gn:country_code":"PH",
    "gn:dem":35,
    "gn:feature_class":"P",
    "gn:feature_code":"PPL",
    "gn:name":"Palasa-ron",
    "gn:population":0,
    "gn:timezone":"Asia/Manila",
    "iso:country":"PH",
    "name:fil_x_preferred":[
        "Palasa-ron"
    ],
    "wof:name":"Palasa-ron",
    "wof:placetype":"locality"
},
  "geometry": {"coordinates":[122.52549999999999,9.5334],"type":"Point"}
}