{
  "type": "Feature",
  "properties": {
    "gn:admin1_code":"06",
    "gn:admin2_code":"30",
    "gn:admin3_code":"63023000.0",
    "gn:asciiname":"Damires",
    "gn:country_code":"PH",
    "gn:dem":76,
    "gn:feature_class":"P",
    "gn:feature_code":"PPL",
    "gn:name":"Damires",
    "gn:population":0,
    "gn:timezone":"Asia/Manila",
    "iso:country":"PH",
    "name:fil_x_preferred":[
        "Damires"
    ],
    "wof:name":"Damires",
    "wof:placetype":"locality"
},
  "geometry": {"coordinates":[122.5227,10.964],"type":"Point"}
}