{
  "type": "Feature",
  "properties": {
    "iso:country":"PH",
    "name:bcl_x_preferred":[
        "Cuenca"
    ],
    "name:cat_x_preferred":[
        "Cuenca"
    ],
    "name:ceb_x_preferred":[
        "Cuenca"
    ],
    "name:deu_x_preferred":[
        "Cuenca"
    ],
    "name:eng_x_preferred":[
        "Cuenca"
    ],
    "name:fil_x_preferred":[
        "Cuenca"
    ],
    "name:fra_x_preferred":[
        "Cuenca"
    ],
    "name:ilo_x_preferred":[
        "Cuenca"
    ],
    "name:ind_x_preferred":[
        "Cuenca"
    ],
    "name:ita_x_preferred":[
        "Cuenca"
    ],
    "name:jpn_x_preferred":[
        "\u30af\u30a8\u30f3\u30ab"
    ],
    "name:nld_x_preferred":[
        "Cuenca"
    ],
    "name:oci_x_preferred":[
        "Cuenca"
    ],
    "name:pag_x_preferred":[
        "Cuenca"
    ],
    "name:pam_x_preferred":[
        "Cuenca"
    ],
    "name:rus_x_preferred":[
        "\u041a\u0443\u044d\u043d\u043a\u0430"
    ],
    "name:sco_x_preferred":[
        "Cuenca"
    ],
    "name:spa_x_preferred":[
        "Cuenca"
    ],
    "name:tgl_x_preferred":[
        "Cuenca"
    ],
    "name:urd_x_preferred":[
        "\u06a9\u0648\u0626\u0646\u06a9\u0627"
    ],
    "name:vie_x_preferred":[
        "Cuenca"
    ],
    "name:war_x_preferred":[
        "Cuenca"
    ],
    "qs:gn_pop":0,
    "qs:name":"Cuenca",
    "qs:name_adm0":"Philippines",
    "qs:name_adm1":"Calabarzon",
    "qs:photos":236,
    "qs:photos_1k":48,
    "qs:photos_9k":1,
    "qs:photos_9r":4,
    "qs:photos_all":236,
    "qs:photos_sr":4,
    "qs:placetype":"Town",
    "qs:pop_sr":"0",
    "qs:woe_adm0":23424934,
    "wof:name":"Cuenca",
    "wof:placetype":"locality"
},
  "geometry": {"coordinates":[121.034317,13.916405],"type":"Point"}
}