{
  "type": "Feature",
  "properties": {
    "gn:country":"PH",
    "gn:fcode":"PPL",
    "gn:population":6234,
    "iso:country":"PH",
    "name:ceb_x_preferred":[
        "Santo Rosario"
    ],
    "name:fil_x_preferred":[
        "Santo Rosario"
    ],
    "qs:name":"Santo Rosario",
    "qs:photos_9r":0,
    "qs:photos_sr":0,
    "qs:pop_sr":"5",
    "wof:name":"Santo Rosario",
    "wof:placetype":"locality",
    "wof:population":6234
},
  "geometry": {"coordinates":[120.8612,15.6447],"type":"Point"}
}