{
  "type": "Feature",
  "properties": {
    "gn:admin1_code":"01",
    "gn:admin2_code":"51",
    "gn:admin3_code":"15536000.0",
    "gn:asciiname":"Calopaan",
    "gn:country_code":"PH",
    "gn:dem":69,
    "gn:feature_class":"P",
    "gn:feature_code":"PPL",
    "gn:name":"Calopaan",
    "gn:population":0,
    "gn:timezone":"Asia/Manila",
    "iso:country":"PH",
    "name:fil_x_preferred":[
        "Calopaan"
    ],
    "wof:name":"Calopaan",
    "wof:placetype":"locality"
},
  "geometry": {"coordinates":[120.73333,16.06667],"type":"Point"}
}