{
  "type": "Feature",
  "properties": {
    "gn:admin1_code":"06",
    "gn:admin2_code":"06",
    "gn:admin3_code":"60618000.0",
    "gn:asciiname":"Valderrama",
    "gn:country_code":"PH",
    "gn:dem":68,
    "gn:feature_class":"P",
    "gn:feature_code":"PPL",
    "gn:name":"Valderrama",
    "gn:population":0,
    "gn:timezone":"Asia/Manila",
    "iso:country":"PH",
    "name:bcl_x_preferred":[
        "Valderrama"
    ],
    "name:ceb_x_preferred":[
        "Valderrama"
    ],
    "name:deu_x_preferred":[
        "Valderrama"
    ],
    "name:fil_x_preferred":[
        "Valderrama"
    ],
    "name:fra_x_preferred":[
        "Valderrama"
    ],
    "name:ilo_x_preferred":[
        "Valderrama"
    ],
    "name:ind_x_preferred":[
        "Valderrama"
    ],
    "name:ita_x_preferred":[
        "Valderrama"
    ],
    "name:nld_x_preferred":[
        "Valderrama"
    ],
    "name:pag_x_preferred":[
        "Valderrama"
    ],
    "name:pam_x_preferred":[
        "Valderrama"
    ],
    "name:spa_x_preferred":[
        "Valderrama"
    ],
    "name:swe_x_preferred":[
        "Valderrama"
    ],
    "name:tgl_x_preferred":[
        "Valderrama"
    ],
    "name:und_x_variant":[
        "Valderama"
    ],
    "name:urd_x_preferred":[
        "\u0648\u0627\u0644\u062f\u06cc\u0631\u0627\u0645\u0627"
    ],
    "name:vie_x_preferred":[
        "Valderrama"
    ],
    "name:war_x_preferred":[
        "Valderrama"
    ],
    "wof:name":"Valderrama",
    "wof:placetype":"locality"
},
  "geometry": {"coordinates":[122.12909999999999,11.0023],"type":"Point"}
}