{
  "type": "Feature",
  "properties": {
    "gn:admin1_code":"06",
    "gn:admin2_code":"06",
    "gn:admin3_code":"60618000.0",
    "gn:asciiname":"Valderrama",
    "gn:country_code":"PH",
    "gn:dem":68,
    "gn:feature_class":"P",
    "gn:feature_code":"PPL",
    "gn:name":"Valderrama",
    "gn:population":0,
    "gn:timezone":"Asia/Manila",
    "iso:country":"PH",
    "name:fil_x_preferred":[
        "Valderrama"
    ],
    "name:und_x_variant":[
        "Valderama"
    ],
    "wof:name":"Valderrama",
    "wof:placetype":"locality"
},
  "geometry": {"coordinates":[122.12909999999999,11.0023],"type":"Point"}
}