{
  "type": "Feature",
  "properties": {
    "gn:admin1_code":"03",
    "gn:admin2_code":"13",
    "gn:admin3_code":"31424000.0",
    "gn:asciiname":"Marowad",
    "gn:country_code":"PH",
    "gn:dem":219,
    "gn:feature_class":"P",
    "gn:feature_code":"PPL",
    "gn:name":"Marowad",
    "gn:population":0,
    "gn:timezone":"Asia/Manila",
    "iso:country":"PH",
    "name:fil_x_preferred":[
        "Marowad"
    ],
    "wof:name":"Marowad",
    "wof:placetype":"locality"
},
  "geometry": {"coordinates":[121.2032,14.98273],"type":"Point"}
}