{
  "type": "Feature",
  "properties": {
    "gn:admin1_code":"02",
    "gn:admin2_code":"31",
    "gn:admin3_code":"23125000.0",
    "gn:asciiname":"Macanao",
    "gn:country_code":"PH",
    "gn:dem":59,
    "gn:feature_class":"P",
    "gn:feature_code":"PPL",
    "gn:name":"Maca\u00f1ao",
    "gn:population":0,
    "gn:timezone":"Asia/Manila",
    "iso:country":"PH",
    "name:fil_x_preferred":[
        "Maca\u00f1ao"
    ],
    "wof:name":"Macanao",
    "wof:placetype":"locality"
},
  "geometry": {"coordinates":[121.74142000000001,16.99198],"type":"Point"}
}