{
  "type": "Feature",
  "properties": {
    "gn:admin1_code":"08",
    "gn:admin2_code":"67",
    "gn:admin3_code":"84803000.0",
    "gn:asciiname":"Salawad",
    "gn:country_code":"PH",
    "gn:dem":7,
    "gn:feature_class":"P",
    "gn:feature_code":"PPL",
    "gn:name":"Salawad",
    "gn:population":0,
    "gn:timezone":"Asia/Manila",
    "iso:country":"PH",
    "name:fil_x_preferred":[
        "Salawad"
    ],
    "wof:name":"Salawad",
    "wof:placetype":"locality"
},
  "geometry": {"coordinates":[124.54861,12.49611],"type":"Point"}
}