{
  "type": "Feature",
  "properties": {
    "gn:admin1_code":"13",
    "gn:admin2_code":"61",
    "gn:admin3_code":"166717000.0",
    "gn:asciiname":"Pahutongan",
    "gn:cc2":"PH",
    "gn:country_code":"PH",
    "gn:dem":10,
    "gn:feature_class":"P",
    "gn:feature_code":"PPL",
    "gn:name":"Pahutongan",
    "gn:population":0,
    "gn:timezone":"Asia/Manila",
    "iso:country":"PH",
    "name:und_x_variant":[
        "Bunoatungan",
        "Panhutungan",
        "Panjotungan",
        "Pahutongan"
    ],
    "wof:name":"Pahutongan",
    "wof:placetype":"locality"
},
  "geometry": {"coordinates":[125.61694,9.63167],"type":"Point"}
}