{
  "type": "Feature",
  "properties": {
    "gn:admin1_code":"05",
    "gn:admin2_code":"05",
    "gn:admin3_code":"50509000.0",
    "gn:asciiname":"Balete",
    "gn:country_code":"PH",
    "gn:dem":10,
    "gn:feature_class":"P",
    "gn:feature_code":"PPL",
    "gn:name":"Balete",
    "gn:population":0,
    "gn:timezone":"Asia/Manila",
    "iso:country":"PH",
    "name:fil_x_preferred":[
        "Balete"
    ],
    "wof:name":"Balete",
    "wof:placetype":"locality"
},
  "geometry": {"coordinates":[123.76439999999999,13.3158],"type":"Point"}
}