{
  "type": "Feature",
  "properties": {
    "gn:admin1_code":"40",
    "gn:admin2_code":"33",
    "gn:admin3_code":"43427000.0",
    "gn:asciiname":"Coralan",
    "gn:country_code":"PH",
    "gn:dem":117,
    "gn:feature_class":"P",
    "gn:feature_code":"PPL",
    "gn:name":"Coralan",
    "gn:population":0,
    "gn:timezone":"Asia/Manila",
    "iso:country":"PH",
    "name:fil_x_preferred":[
        "Coralan"
    ],
    "name:fil_x_variant":[
        "Corralan"
    ],
    "wof:name":"Coralan",
    "wof:placetype":"locality"
},
  "geometry": {"coordinates":[121.4037,14.4829],"type":"Point"}
}