{
  "type": "Feature",
  "properties": {
    "gn:admin1_code":"15",
    "gn:admin2_code":"01",
    "gn:admin3_code":"140122000.0",
    "gn:asciiname":"Gaang",
    "gn:country_code":"PH",
    "gn:dem":89,
    "gn:feature_class":"P",
    "gn:feature_code":"PPL",
    "gn:name":"Gaang",
    "gn:population":0,
    "gn:timezone":"Asia/Manila",
    "iso:country":"PH",
    "name:fil_x_preferred":[
        "Gaang"
    ],
    "wof:name":"Gaang",
    "wof:placetype":"locality"
},
  "geometry": {"coordinates":[120.71666999999999,17.68332999999999],"type":"Point"}
}