{
  "type": "Feature",
  "properties": {
    "gn:admin1_code":"40",
    "gn:admin2_code":"09",
    "gn:admin3_code":"41024000.0",
    "gn:asciiname":"Balagtasin",
    "gn:country_code":"PH",
    "gn:dem":162,
    "gn:feature_class":"P",
    "gn:feature_code":"PPL",
    "gn:name":"Balagtasin",
    "gn:population":0,
    "gn:timezone":"Asia/Manila",
    "iso:country":"PH",
    "name:und_x_variant":[
        "Balagtasan"
    ],
    "wof:name":"Balagtasin",
    "wof:placetype":"locality"
},
  "geometry": {"coordinates":[120.95265999999999,13.82863],"type":"Point"}
}