{
  "type": "Feature",
  "properties": {
    "gn:admin1_code":"06",
    "gn:admin2_code":"06",
    "gn:admin3_code":"60604000.0",
    "gn:asciiname":"Igbalangao",
    "gn:country_code":"PH",
    "gn:dem":25,
    "gn:feature_class":"P",
    "gn:feature_code":"PPL",
    "gn:name":"Igbalangao",
    "gn:population":0,
    "gn:timezone":"Asia/Manila",
    "iso:country":"PH",
    "name:fil_x_preferred":[
        "Igbalangao"
    ],
    "wof:name":"Igbalangao",
    "wof:placetype":"locality"
},
  "geometry": {"coordinates":[122.06319999999999,11.01],"type":"Point"}
}