{
  "type": "Feature",
  "properties": {
    "gn:admin1_code":"05",
    "gn:admin2_code":"39",
    "gn:admin3_code":"54119000.0",
    "gn:asciiname":"Labongan",
    "gn:country_code":"PH",
    "gn:dem":92,
    "gn:feature_class":"P",
    "gn:feature_code":"PPL",
    "gn:name":"Labongan",
    "gn:population":0,
    "gn:timezone":"Asia/Manila",
    "iso:country":"PH",
    "name:fil_x_preferred":[
        "Labongan"
    ],
    "wof:name":"Labongan",
    "wof:placetype":"locality"
},
  "geometry": {"coordinates":[123.67140000000001,12.5655],"type":"Point"}
}