{
  "type": "Feature",
  "properties": {
    "gn:admin1_code":"02",
    "gn:admin2_code":"14",
    "gn:admin3_code":"21505000.0",
    "gn:asciiname":"Plaza",
    "gn:country_code":"PH",
    "gn:dem":14,
    "gn:feature_class":"P",
    "gn:feature_code":"PPL",
    "gn:name":"Plaza",
    "gn:population":0,
    "gn:timezone":"Asia/Manila",
    "iso:country":"PH",
    "name:fil_x_preferred":[
        "Plaza"
    ],
    "wof:name":"Plaza",
    "wof:placetype":"locality"
},
  "geometry": {"coordinates":[121.5889,18.3094],"type":"Point"}
}