{
  "type": "Feature",
  "properties": {
    "gn:admin1_code":"15",
    "gn:admin2_code":"44",
    "gn:admin3_code":"144405000.0",
    "gn:asciiname":"Obfal",
    "gn:country_code":"PH",
    "gn:dem":588,
    "gn:feature_class":"P",
    "gn:feature_code":"PPL",
    "gn:name":"Obfal",
    "gn:population":0,
    "gn:timezone":"Asia/Manila",
    "iso:country":"PH",
    "name:fil_x_preferred":[
        "Obfal"
    ],
    "wof:name":"Obfal",
    "wof:placetype":"locality"
},
  "geometry": {"coordinates":[121.34763999999998,17.15694],"type":"Point"}
}