{
  "type": "Feature",
  "properties": {
    "gn:country":"PH",
    "gn:fcode":"PPL",
    "gn:pop":4066,
    "iso:country":"PH",
    "name:fil_x_preferred":[
        "Antagan Dos"
    ],
    "name:fil_x_variant":[
        "Antagan"
    ],
    "name:unk_x_variant":[
        "Antagan Segunda"
    ],
    "qs:name":"Antagan Dos",
    "qs:photos_9r":0,
    "qs:photos_sr":0,
    "qs:pop_sr":"4",
    "wof:name":"Antagan Dos",
    "wof:placetype":"locality",
    "wof:population":4066
},
  "geometry": {"coordinates":[121.90434,17.27643],"type":"Point"}
}