{
  "type": "Feature",
  "properties": {
    "gn:admin1_code":"07",
    "gn:admin2_code":"69",
    "gn:admin3_code":"76103000.0",
    "gn:asciiname":"Bolobolo",
    "gn:country_code":"PH",
    "gn:dem":69,
    "gn:feature_class":"P",
    "gn:feature_code":"PPL",
    "gn:name":"Bolobolo",
    "gn:population":0,
    "gn:timezone":"Asia/Manila",
    "iso:country":"PH",
    "name:fil_x_preferred":[
        "Bolobolo"
    ],
    "wof:name":"Bolobolo",
    "wof:placetype":"locality"
},
  "geometry": {"coordinates":[123.61667,9.13333],"type":"Point"}
}