{
  "type": "Feature",
  "properties": {
    "gn:admin1_code":"08",
    "gn:admin2_code":"37",
    "gn:admin3_code":"83717000.0",
    "gn:asciiname":"Bayug",
    "gn:country_code":"PH",
    "gn:dem":27,
    "gn:feature_class":"P",
    "gn:feature_code":"PPL",
    "gn:name":"Bayug",
    "gn:population":0,
    "gn:timezone":"Asia/Manila",
    "iso:country":"PH",
    "name:fil_x_preferred":[
        "Bayug"
    ],
    "wof:name":"Bayug",
    "wof:placetype":"locality"
},
  "geometry": {"coordinates":[124.91667,11.03333],"type":"Point"}
}