{
  "type": "Feature",
  "properties": {
    "gn:country":"PH",
    "gn:fcode":"PPL",
    "gn:pop":7398,
    "iso:country":"PH",
    "name:fil_x_preferred":[
        "Antipolo"
    ],
    "name:unk_x_variant":[
        "Anlipolo"
    ],
    "qs:name":"Antipolo",
    "qs:photos_9r":0,
    "qs:photos_sr":0,
    "qs:pop_sr":"5",
    "wd:wordcount":3130,
    "wof:name":"Antipolo",
    "wof:placetype":"locality",
    "wof:population":7398
},
  "geometry": {"coordinates":[122.9646,10.3565],"type":"Point"}
}