{
  "type": "Feature",
  "properties": {
    "gn:country":"PH",
    "gn:fcode":"PPL",
    "gn:population":7398,
    "iso:country":"PH",
    "name:ara_x_preferred":[
        "\u0623\u0646\u062a\u064a\u0628\u0648\u0644\u0648"
    ],
    "name:bcl_x_preferred":[
        "Antipolo"
    ],
    "name:cat_x_preferred":[
        "Antipolo"
    ],
    "name:ceb_x_preferred":[
        "Antipolo"
    ],
    "name:deu_x_preferred":[
        "Antipolo"
    ],
    "name:epo_x_preferred":[
        "Antipolo"
    ],
    "name:fas_x_preferred":[
        "\u0627\u0646\u062a\u06cc\u067e\u0644\u0648"
    ],
    "name:fil_x_preferred":[
        "Antipolo"
    ],
    "name:fra_x_preferred":[
        "Antipolo"
    ],
    "name:ilo_x_preferred":[
        "Antipolo"
    ],
    "name:ind_x_preferred":[
        "Antipolo"
    ],
    "name:ita_x_preferred":[
        "Antipolo"
    ],
    "name:jpn_x_preferred":[
        "\u30a2\u30f3\u30c6\u30a3\u30dd\u30ed"
    ],
    "name:kor_x_preferred":[
        "\uc548\ud2f0\ud3f4\ub85c"
    ],
    "name:lit_x_preferred":[
        "Antipolas"
    ],
    "name:mon_x_preferred":[
        "\u0410\u043d\u0442\u0438\u043f\u043e\u043b\u043e"
    ],
    "name:nld_x_preferred":[
        "Antipolo"
    ],
    "name:pag_x_preferred":[
        "Antipolo"
    ],
    "name:pam_x_preferred":[
        "Antipolo Lakanbalen"
    ],
    "name:pol_x_preferred":[
        "Antipolo"
    ],
    "name:por_x_preferred":[
        "Antipolo"
    ],
    "name:rus_x_preferred":[
        "\u0410\u043d\u0442\u0438\u043f\u043e\u043b\u043e"
    ],
    "name:spa_x_preferred":[
        "Antipolo"
    ],
    "name:swe_x_preferred":[
        "Antipolo"
    ],
    "name:tgl_x_preferred":[
        "Antipolo"
    ],
    "name:tha_x_preferred":[
        "\u0e2d\u0e31\u0e19\u0e15\u0e35\u0e42\u0e1b\u0e42\u0e25"
    ],
    "name:tur_x_preferred":[
        "Antipolo"
    ],
    "name:und_x_variant":[
        "Anlipolo"
    ],
    "name:urd_x_preferred":[
        "\u0627\u0646\u062a\u06cc\u067e\u0648\u0644\u0648"
    ],
    "name:vie_x_preferred":[
        "Antipolo"
    ],
    "name:war_x_preferred":[
        "Antipolo"
    ],
    "name:zho_x_preferred":[
        "\u5b89\u8482\u6ce2\u6d1b"
    ],
    "qs:name":"Antipolo",
    "qs:photos_9r":0,
    "qs:photos_sr":0,
    "qs:pop_sr":"5",
    "wd:wordcount":3130,
    "wof:name":"Antipolo",
    "wof:placetype":"locality",
    "wof:population":7398
},
  "geometry": {"coordinates":[122.9646,10.3565],"type":"Point"}
}