{
  "type": "Feature",
  "properties": {
    "gn:admin1_code":"06",
    "gn:admin2_code":"04",
    "gn:admin3_code":"60417000.0",
    "gn:asciiname":"Dumatud",
    "gn:country_code":"PH",
    "gn:dem":14,
    "gn:feature_class":"P",
    "gn:feature_code":"PPL",
    "gn:name":"Dumatud",
    "gn:population":0,
    "gn:timezone":"Asia/Manila",
    "iso:country":"PH",
    "name:fil_x_preferred":[
        "Dumatud"
    ],
    "name:und_x_variant":[
        "Dumatao",
        "Dumatad"
    ],
    "wof:name":"Dumatud",
    "wof:placetype":"locality"
},
  "geometry": {"coordinates":[122.2551,11.7882],"type":"Point"}
}