{
  "type": "Feature",
  "properties": {
    "gn:admin1_code":"15",
    "gn:admin2_code":"01",
    "gn:admin3_code":"140122000.0",
    "gn:asciiname":"Colabaoan",
    "gn:country_code":"PH",
    "gn:dem":82,
    "gn:feature_class":"P",
    "gn:feature_code":"PPL",
    "gn:name":"Colabaoan",
    "gn:population":0,
    "gn:timezone":"Asia/Manila",
    "iso:country":"PH",
    "name:fil_x_preferred":[
        "Colabaoan"
    ],
    "wof:name":"Colabaoan",
    "wof:placetype":"locality"
},
  "geometry": {"coordinates":[120.7236,17.6706],"type":"Point"}
}