{
  "type": "Feature",
  "properties": {
    "gn:admin1_code":"06",
    "gn:admin2_code":"30",
    "gn:admin3_code":"63001000.0",
    "gn:asciiname":"Pantalan Nabaye",
    "gn:cc2":"PH",
    "gn:country_code":"PH",
    "gn:dem":7,
    "gn:feature_class":"P",
    "gn:feature_code":"PPL",
    "gn:name":"Pantalan Nabaye",
    "gn:population":0,
    "gn:timezone":"Asia/Manila",
    "iso:country":"PH",
    "name:und_x_variant":[
        "Pantalan Navaye",
        "Pantalan Nabaye"
    ],
    "wof:name":"Pantalan Nabaye",
    "wof:placetype":"locality"
},
  "geometry": {"coordinates":[123.01667,11.16667],"type":"Point"}
}