{
  "type": "Feature",
  "properties": {
    "gn:admin1_code":"08",
    "gn:admin2_code":"55",
    "gn:admin3_code":"86005000.0",
    "gn:asciiname":"Canahauan",
    "gn:country_code":"PH",
    "gn:dem":66,
    "gn:feature_class":"P",
    "gn:feature_code":"PPL",
    "gn:name":"Canahauan",
    "gn:population":0,
    "gn:timezone":"Asia/Manila",
    "iso:country":"PH",
    "name:fil_x_preferred":[
        "Canahauan"
    ],
    "wof:name":"Canahauan",
    "wof:placetype":"locality"
},
  "geometry": {"coordinates":[124.68472,11.82694],"type":"Point"}
}