{
  "type": "Feature",
  "properties": {
    "gn:admin1_code":"02",
    "gn:admin2_code":"31",
    "gn:admin3_code":"23135000.0",
    "gn:asciiname":"Bayug",
    "gn:country_code":"PH",
    "gn:dem":91,
    "gn:feature_class":"P",
    "gn:feature_code":"PPL",
    "gn:name":"Bayug",
    "gn:population":0,
    "gn:timezone":"Asia/Manila",
    "iso:country":"PH",
    "name:fil_x_preferred":[
        "Bayug"
    ],
    "wof:name":"Bayug",
    "wof:placetype":"locality"
},
  "geometry": {"coordinates":[121.5124,16.6681],"type":"Point"}
}