{
  "type": "Feature",
  "properties": {
    "gn:admin1_code":"06",
    "gn:admin2_code":"06",
    "gn:admin3_code":"60610000.0",
    "gn:asciiname":"Bolho",
    "gn:country_code":"PH",
    "gn:dem":113,
    "gn:feature_class":"P",
    "gn:feature_code":"PPL",
    "gn:name":"Bolho",
    "gn:population":0,
    "gn:timezone":"Asia/Manila",
    "iso:country":"PH",
    "name:fil_x_preferred":[
        "Bolho"
    ],
    "wof:name":"Bolho",
    "wof:placetype":"locality"
},
  "geometry": {"coordinates":[121.8732,11.7633],"type":"Point"}
}