{
  "type": "Feature",
  "properties": {
    "gn:country":"PH",
    "gn:fcode":"PPL",
    "gn:pop":3607,
    "iso:country":"PH",
    "name:unk_x_variant":[
        "Bancosi"
    ],
    "qs:name":"Bancasi",
    "qs:photos_9r":0,
    "qs:photos_sr":0,
    "qs:pop_sr":"4",
    "wof:name":"Bancasi",
    "wof:placetype":"locality",
    "wof:population":3607
},
  "geometry": {"coordinates":[125.46666999999999,8.96667],"type":"Point"}
}