{
  "type": "Feature",
  "properties": {
    "gn:admin1_code":"15",
    "gn:admin2_code":"H6",
    "gn:admin3_code":"148104000.0",
    "gn:asciiname":"Nabnuang",
    "gn:country_code":"PH",
    "gn:dem":128,
    "gn:feature_class":"P",
    "gn:feature_code":"PPL",
    "gn:name":"Nabnuang",
    "gn:population":0,
    "gn:timezone":"Asia/Manila",
    "iso:country":"PH",
    "name:fil_x_preferred":[
        "Nabnuang"
    ],
    "wof:name":"Nabnuang",
    "wof:placetype":"locality"
},
  "geometry": {"coordinates":[121.13012000000001,18.01432999999999],"type":"Point"}
}