{
  "type": "Feature",
  "properties": {
    "gn:country":"PH",
    "gn:fcode":"PPL",
    "gn:population":4001,
    "iso:country":"PH",
    "name:fil_x_preferred":[
        "Pangian"
    ],
    "qs:name":"Pangian",
    "qs:photos_9r":0,
    "qs:photos_sr":0,
    "qs:pop_sr":"4",
    "wof:name":"Pangian",
    "wof:placetype":"locality",
    "wof:population":4001
},
  "geometry": {"coordinates":[125.54528000000001,6.46278],"type":"Point"}
}