{
  "type": "Feature",
  "properties": {
    "gn:admin1_code":"03",
    "gn:admin2_code":"50",
    "gn:admin3_code":"35408000.0",
    "gn:asciiname":"Bancal Sinubli",
    "gn:country_code":"PH",
    "gn:dem":6,
    "gn:feature_class":"P",
    "gn:feature_code":"PPL",
    "gn:name":"Bancal Sinubli",
    "gn:population":0,
    "gn:timezone":"Asia/Manila",
    "iso:country":"PH",
    "name:fil_x_preferred":[
        "Bancal Sinubli"
    ],
    "wof:name":"Bancal Sinubli",
    "wof:placetype":"locality"
},
  "geometry": {"coordinates":[120.59496,14.8566],"type":"Point"}
}