{
  "type": "Feature",
  "properties": {
    "gn:admin1_code":"12",
    "gn:admin2_code":"70",
    "gn:admin3_code":"126302000.0",
    "gn:asciiname":"Rizal",
    "gn:country_code":"PH",
    "gn:dem":139,
    "gn:feature_class":"P",
    "gn:feature_code":"PPL",
    "gn:name":"Rizal",
    "gn:population":0,
    "gn:timezone":"Asia/Manila",
    "iso:country":"PH",
    "name:fil_x_preferred":[
        "Rizal"
    ],
    "wof:name":"Rizal",
    "wof:placetype":"locality"
},
  "geometry": {"coordinates":[124.73254,6.45899],"type":"Point"}
}