{
  "type": "Feature",
  "properties": {
    "gn:admin1_code":"41",
    "gn:admin2_code":"38",
    "gn:asciiname":"Alijogan",
    "gn:country_code":"PH",
    "gn:dem":12,
    "gn:feature_class":"P",
    "gn:feature_code":"PPL",
    "gn:name":"Alijogan",
    "gn:population":0,
    "gn:timezone":"Asia/Manila",
    "iso:country":"PH",
    "name:fil_x_preferred":[
        "Alijogan"
    ],
    "wof:name":"Alijogan",
    "wof:placetype":"locality"
},
  "geometry": {"coordinates":[121.81667,13.41667],"type":"Point"}
}