{
  "type": "Feature",
  "properties": {
    "gn:country":"PH",
    "gn:fcode":"PPL",
    "gn:pop":13898,
    "iso:country":"PH",
    "name:eng_x_preferred":[
        "Oca\u00f1a"
    ],
    "qs:name":"Oca\u00f1a",
    "qs:photos_9r":0,
    "qs:photos_sr":0,
    "qs:pop_sr":"6",
    "wd:wordcount":182,
    "wof:name":"Oca\u00f1a",
    "wof:placetype":"locality",
    "wof:population":13898
},
  "geometry": {"coordinates":[123.62439999999999,10.0656],"type":"Point"}
}