{
  "type": "Feature",
  "properties": {
    "gn:country":"PH",
    "gn:fcode":"PPL",
    "gn:pop":13898,
    "iso:country":"PH",
    "name:bre_x_preferred":[
        "Oca\u00f1a"
    ],
    "name:cat_x_preferred":[
        "Oca\u00f1a"
    ],
    "name:ceb_x_preferred":[
        "Oca\u00f1a"
    ],
    "name:deu_x_preferred":[
        "Oca\u00f1a"
    ],
    "name:eng_x_preferred":[
        "Oca\u00f1a"
    ],
    "name:epo_x_preferred":[
        "Oca\u00f1a"
    ],
    "name:fra_x_preferred":[
        "Oca\u00f1a"
    ],
    "name:glg_x_preferred":[
        "Oca\u00f1a"
    ],
    "name:nds_x_preferred":[
        "Oca\u00f1a"
    ],
    "name:nld_x_preferred":[
        "Oca\u00f1a"
    ],
    "name:pol_x_preferred":[
        "Oca\u00f1a"
    ],
    "name:rus_x_preferred":[
        "\u041e\u043a\u0430\u043d\u044c\u044f"
    ],
    "name:spa_x_preferred":[
        "Oca\u00f1a"
    ],
    "name:swe_x_preferred":[
        "Oca\u00f1a"
    ],
    "name:vie_x_preferred":[
        "Oca\u00f1a"
    ],
    "qs:name":"Oca\u00f1a",
    "qs:photos_9r":0,
    "qs:photos_sr":0,
    "qs:pop_sr":"6",
    "wd:wordcount":182,
    "wof:name":"Oca\u00f1a",
    "wof:placetype":"locality",
    "wof:population":13898
},
  "geometry": {"coordinates":[123.62439999999999,10.0656],"type":"Point"}
}