{
  "type": "Feature",
  "properties": {
    "gn:country":"PH",
    "gn:fcode":"ADM3",
    "gn:population":74114,
    "iso:country":"PH",
    "name:bcl_x_preferred":[
        "Macabebe"
    ],
    "name:ceb_x_preferred":[
        "Macabebe"
    ],
    "name:deu_x_preferred":[
        "Macabebe"
    ],
    "name:fil_x_preferred":[
        "Macabebe"
    ],
    "name:ilo_x_preferred":[
        "Macabebe"
    ],
    "name:ind_x_preferred":[
        "Macabebe"
    ],
    "name:ita_x_preferred":[
        "Macabebe"
    ],
    "name:nld_x_preferred":[
        "Macabebe"
    ],
    "name:nor_x_preferred":[
        "Macabebe"
    ],
    "name:pag_x_preferred":[
        "Macabebe"
    ],
    "name:pam_x_preferred":[
        "Macabebe"
    ],
    "name:swe_x_preferred":[
        "Macabebe"
    ],
    "name:tgl_x_preferred":[
        "Macabebe"
    ],
    "name:vie_x_preferred":[
        "Macabebe"
    ],
    "name:war_x_preferred":[
        "Macabebe"
    ],
    "qs:name":"Macabebe",
    "qs:photos_9r":0,
    "qs:photos_sr":0,
    "qs:pop_sr":"8",
    "wof:name":"Macabebe",
    "wof:placetype":"localadmin",
    "wof:population":74114
},
  "geometry": {"coordinates":[120.71774000000001,14.89835],"type":"Point"}
}