{
  "type": "Feature",
  "properties": {
    "gn:admin1_code":"02",
    "gn:admin2_code":"14",
    "gn:admin3_code":"21502000.0",
    "gn:asciiname":"Agani",
    "gn:country_code":"PH",
    "gn:dem":23,
    "gn:feature_class":"P",
    "gn:feature_code":"PPL",
    "gn:name":"Agani",
    "gn:population":0,
    "gn:timezone":"Asia/Manila",
    "iso:country":"PH",
    "name:fil_x_preferred":[
        "Agani"
    ],
    "name:vie_x_preferred":[
        "Agani"
    ],
    "wof:name":"Agani",
    "wof:placetype":"locality"
},
  "geometry": {"coordinates":[121.7039,17.9178],"type":"Point"}
}