{
  "type": "Feature",
  "properties": {
    "gn:admin1_code":"06",
    "gn:admin2_code":"18",
    "gn:admin3_code":"61913000.0",
    "gn:asciiname":"Bo-ac",
    "gn:country_code":"PH",
    "gn:dem":13,
    "gn:feature_class":"P",
    "gn:feature_code":"PPL",
    "gn:name":"Bo-ac",
    "gn:population":0,
    "gn:timezone":"Asia/Manila",
    "iso:country":"PH",
    "name:fil_x_preferred":[
        "Bo-ac"
    ],
    "wof:name":"Bo-ac",
    "wof:placetype":"locality"
},
  "geometry": {"coordinates":[122.92619999999999,11.4182],"type":"Point"}
}