{
  "type": "Feature",
  "properties": {
    "gn:admin1_code":"15",
    "gn:admin2_code":"10",
    "gn:admin3_code":"141106000.0",
    "gn:asciiname":"Topside",
    "gn:country_code":"PH",
    "gn:dem":1323,
    "gn:feature_class":"P",
    "gn:feature_code":"PPL",
    "gn:name":"Topside",
    "gn:population":0,
    "gn:timezone":"Asia/Manila",
    "iso:country":"PH",
    "name:deu_x_preferred":[
        "Topside"
    ],
    "name:fil_x_preferred":[
        "Topside"
    ],
    "wof:name":"Topside",
    "wof:placetype":"locality"
},
  "geometry": {"coordinates":[120.63437,16.42181],"type":"Point"}
}