{
  "type": "Feature",
  "properties": {
    "gn:admin1_code":"05",
    "gn:admin2_code":"39",
    "gn:admin3_code":"54112000.0",
    "gn:asciiname":"Barra",
    "gn:country_code":"PH",
    "gn:dem":7,
    "gn:feature_class":"P",
    "gn:feature_code":"PPL",
    "gn:name":"Barra",
    "gn:population":2084,
    "gn:timezone":"Asia/Manila",
    "iso:country":"PH",
    "name:fil_x_preferred":[
        "Barra"
    ],
    "name:und_x_variant":[
        "Bara"
    ],
    "wof:name":"Barra",
    "wof:placetype":"locality",
    "wof:population":2084
},
  "geometry": {"coordinates":[123.6395,12.0717],"type":"Point"}
}