{
  "type": "Feature",
  "properties": {
    "gn:country":"PH",
    "gn:fcode":"PPL",
    "gn:population":2102,
    "iso:country":"PH",
    "name:eng_x_preferred":[
        "idio"
    ],
    "name:fil_x_preferred":[
        "Idio"
    ],
    "name:fin_x_preferred":[
        "Idio"
    ],
    "name:fra_x_preferred":[
        "Idio"
    ],
    "name:ita_x_preferred":[
        "Idio"
    ],
    "name:nld_x_preferred":[
        "Idio"
    ],
    "name:por_x_preferred":[
        "Idio"
    ],
    "name:spa_x_preferred":[
        "Idio"
    ],
    "qs:name":"Idio",
    "qs:photos_9r":0,
    "qs:photos_sr":0,
    "qs:pop_sr":"4",
    "wd:wordcount":471,
    "wof:name":"Idio",
    "wof:placetype":"locality",
    "wof:population":2102
},
  "geometry": {"coordinates":[122.0979,11.6238],"type":"Point"}
}