{
  "type": "Feature",
  "properties": {
    "gn:admin1_code":"40",
    "gn:admin2_code":"53",
    "gn:admin3_code":"45807000.0",
    "gn:asciiname":"Bayugo",
    "gn:country_code":"PH",
    "gn:dem":6,
    "gn:feature_class":"P",
    "gn:feature_code":"PPL",
    "gn:name":"Bayugo",
    "gn:population":0,
    "gn:timezone":"Asia/Manila",
    "iso:country":"PH",
    "name:fil_x_preferred":[
        "Bayugo"
    ],
    "wof:name":"Bayugo",
    "wof:placetype":"locality"
},
  "geometry": {"coordinates":[121.3062,14.326],"type":"Point"}
}