{
  "type": "Feature",
  "properties": {
    "gn:country":"PH",
    "gn:fcode":"ADM3",
    "gn:pop":12118,
    "iso:country":"PH",
    "name:ceb_x_preferred":[
        "Santol"
    ],
    "name:deu_x_preferred":[
        "Santol"
    ],
    "name:fil_x_preferred":[
        "Santol"
    ],
    "name:nld_x_preferred":[
        "Santol"
    ],
    "name:swe_x_preferred":[
        "Santol"
    ],
    "name:tgl_x_preferred":[
        "Santol"
    ],
    "name:war_x_preferred":[
        "Santol"
    ],
    "qs:name":"Santol",
    "qs:photos_9r":0,
    "qs:photos_sr":0,
    "qs:pop_sr":"6",
    "wd:wordcount":33,
    "wof:name":"Santol",
    "wof:placetype":"localadmin",
    "wof:population":12118
},
  "geometry": {"coordinates":[120.48333,16.76667],"type":"Point"}
}