{
  "type": "Feature",
  "properties": {
    "gn:admin1_code":"40",
    "gn:admin2_code":"20",
    "gn:admin3_code":"42111000.0",
    "gn:asciiname":"Panamitan",
    "gn:country_code":"PH",
    "gn:dem":6,
    "gn:feature_class":"P",
    "gn:feature_code":"PPL",
    "gn:name":"Panamitan",
    "gn:population":0,
    "gn:timezone":"Asia/Manila",
    "iso:country":"PH",
    "name:fil_x_preferred":[
        "Panamitan"
    ],
    "wof:name":"Panamitan",
    "wof:placetype":"locality"
},
  "geometry": {"coordinates":[120.89742,14.43851],"type":"Point"}
}