{
  "type": "Feature",
  "properties": {
    "gn:admin1_code":"12",
    "gn:admin2_code":"57",
    "gn:admin3_code":"124709000.0",
    "gn:asciiname":"Lagumbingan",
    "gn:country_code":"PH",
    "gn:dem":14,
    "gn:feature_class":"P",
    "gn:feature_code":"PPL",
    "gn:name":"Lagumbingan",
    "gn:population":0,
    "gn:timezone":"Asia/Manila",
    "iso:country":"PH",
    "name:fil_x_preferred":[
        "Lagumbingan"
    ],
    "wof:name":"Lagumbingan",
    "wof:placetype":"locality"
},
  "geometry": {"coordinates":[124.50167,7.19833],"type":"Point"}
}