{
  "type": "Feature",
  "properties": {
    "gn:admin1_code":"06",
    "gn:admin2_code":"06",
    "gn:admin3_code":"60607000.0",
    "gn:asciiname":"Lawigan",
    "gn:country_code":"PH",
    "gn:dem":204,
    "gn:feature_class":"P",
    "gn:feature_code":"PPL",
    "gn:name":"Lawigan",
    "gn:population":0,
    "gn:timezone":"Asia/Manila",
    "iso:country":"PH",
    "name:fil_x_preferred":[
        "Lawigan"
    ],
    "name:und_x_variant":[
        "Lauigan",
        "Lauigan North"
    ],
    "wof:name":"Lawigan",
    "wof:placetype":"locality"
},
  "geometry": {"coordinates":[121.9909,10.5729],"type":"Point"}
}