{
  "type": "Feature",
  "properties": {
    "iso:country":"PH",
    "name:bcl_x_preferred":[
        "Leganes"
    ],
    "name:cbk_zam_x_preferred":[
        "Leganes"
    ],
    "name:ceb_x_preferred":[
        "Leganes"
    ],
    "name:deu_x_preferred":[
        "Leganes"
    ],
    "name:eng_x_preferred":[
        "Leganes"
    ],
    "name:fra_x_preferred":[
        "Leganes"
    ],
    "name:ilo_x_preferred":[
        "Leganes"
    ],
    "name:ind_x_preferred":[
        "Leganes"
    ],
    "name:ita_x_preferred":[
        "Leganes"
    ],
    "name:ltz_x_preferred":[
        "Leganes"
    ],
    "name:nld_x_preferred":[
        "Leganes"
    ],
    "name:nob_x_preferred":[
        "Leganes"
    ],
    "name:pag_x_preferred":[
        "Leganes"
    ],
    "name:pam_x_preferred":[
        "Leganes"
    ],
    "name:spa_x_preferred":[
        "Legan\u00e9s"
    ],
    "name:swe_x_preferred":[
        "Leganes"
    ],
    "name:tgl_x_preferred":[
        "Leganes"
    ],
    "name:vie_x_preferred":[
        "Leganes"
    ],
    "name:war_x_preferred":[
        "Leganes"
    ],
    "qs:gn_country":"PH",
    "qs:gn_fcode":"PPLA3",
    "qs:gn_pop":2464,
    "qs:name":"Leganes",
    "qs:name_adm0":"Philippines",
    "qs:name_adm1":"Western Visayas",
    "qs:photos":119,
    "qs:photos_1k":24,
    "qs:photos_9k":1,
    "qs:photos_9r":3,
    "qs:photos_all":119,
    "qs:photos_sr":3,
    "qs:placetype":"Town",
    "qs:pop_sr":"4",
    "qs:woe_adm0":23424934,
    "wd:wordcount":173,
    "wof:name":"Leganes",
    "wof:placetype":"locality",
    "wof:population":2464
},
  "geometry": {"coordinates":[122.58917,10.78722],"type":"Point"}
}