{
  "type": "Feature",
  "properties": {
    "gn:admin1_code":"40",
    "gn:admin2_code":"F2",
    "gn:asciiname":"Ramon Magsaysay",
    "gn:country_code":"PH",
    "gn:dem":21,
    "gn:feature_class":"P",
    "gn:feature_code":"PPL",
    "gn:name":"Ramon Magsaysay",
    "gn:population":0,
    "gn:timezone":"Asia/Manila",
    "iso:country":"PH",
    "name:fil_x_preferred":[
        "Ramon Magsaysay"
    ],
    "wof:name":"Ramon Magsaysay",
    "wof:placetype":"locality"
},
  "geometry": {"coordinates":[121.0168,14.658],"type":"Point"}
}