{
  "type": "Feature",
  "properties": {
    "gn:admin1_code":"01",
    "gn:admin2_code":"29",
    "gn:asciiname":"Tabatab",
    "gn:country_code":"PH",
    "gn:dem":369,
    "gn:feature_class":"P",
    "gn:feature_code":"PPL",
    "gn:name":"Tabatab",
    "gn:population":0,
    "gn:timezone":"Asia/Manila",
    "iso:country":"PH",
    "name:fil_x_preferred":[
        "Tabatab"
    ],
    "wof:name":"Tabatab",
    "wof:placetype":"locality"
},
  "geometry": {"coordinates":[120.71111000000001,17.17833],"type":"Point"}
}