{
  "type": "Feature",
  "properties": {
    "gn:admin1_code":"07",
    "gn:admin2_code":"69",
    "gn:admin3_code":"76106000.0",
    "gn:asciiname":"Tambisan",
    "gn:country_code":"PH",
    "gn:dem":16,
    "gn:feature_class":"P",
    "gn:feature_code":"PPL",
    "gn:name":"Tambisan",
    "gn:population":0,
    "gn:timezone":"Asia/Manila",
    "iso:country":"PH",
    "name:fil_x_preferred":[
        "Tambisan"
    ],
    "wof:name":"Tambisan",
    "wof:placetype":"locality"
},
  "geometry": {"coordinates":[123.47750000000001,9.2025],"type":"Point"}
}