{
  "type": "Feature",
  "properties": {
    "gn:admin1_code":"01",
    "gn:admin2_code":"51",
    "gn:admin3_code":"15533000.0",
    "gn:asciiname":"Bulaoen West",
    "gn:country_code":"PH",
    "gn:dem":150,
    "gn:feature_class":"P",
    "gn:feature_code":"PPL",
    "gn:name":"Bulaoen West",
    "gn:population":0,
    "gn:timezone":"Asia/Manila",
    "iso:country":"PH",
    "name:eng_x_preferred":[
        "Bulaoen West"
    ],
    "wof:name":"Bulaoen West",
    "wof:placetype":"locality"
},
  "geometry": {"coordinates":[120.46302,16.18015],"type":"Point"}
}