{
  "type": "Feature",
  "properties": {
    "gn:country":"PH",
    "gn:fcode":"ADM3",
    "gn:pop":51742,
    "iso:country":"PH",
    "name:fil_x_preferred":[
        "Tagkawayan"
    ],
    "qs:name":"Tagkawayan",
    "qs:photos_9r":0,
    "qs:photos_sr":0,
    "qs:pop_sr":"8",
    "wd:wordcount":179,
    "wof:name":"Tagkawayan",
    "wof:placetype":"localadmin",
    "wof:population":51742
},
  "geometry": {"coordinates":[122.53333000000001,14.01667],"type":"Point"}
}