{
  "type": "Feature",
  "properties": {
    "gn:country":"PH",
    "gn:fcode":"ADM3",
    "gn:population":51742,
    "iso:country":"PH",
    "name:bcl_x_preferred":[
        "Tagkawayan"
    ],
    "name:cat_x_preferred":[
        "Tagkawayan"
    ],
    "name:ceb_x_preferred":[
        "Tagkawayan"
    ],
    "name:deu_x_preferred":[
        "Tagkawayan"
    ],
    "name:eng_x_preferred":[
        "Tagkawayan"
    ],
    "name:fil_x_preferred":[
        "Tagkawayan"
    ],
    "name:fra_x_preferred":[
        "Tagkawayan"
    ],
    "name:ilo_x_preferred":[
        "Tagkawayan"
    ],
    "name:ind_x_preferred":[
        "Tagkawayan"
    ],
    "name:ita_x_preferred":[
        "Tagkawayan"
    ],
    "name:nld_x_preferred":[
        "Tagkawayan"
    ],
    "name:oci_x_preferred":[
        "Tagkawayan"
    ],
    "name:pag_x_preferred":[
        "Tagkawayan"
    ],
    "name:pam_x_preferred":[
        "Tagkawayan"
    ],
    "name:swe_x_preferred":[
        "Tagkawayan"
    ],
    "name:tgl_x_preferred":[
        "Tagkawayan"
    ],
    "name:vie_x_preferred":[
        "Tagkawayan"
    ],
    "name:war_x_preferred":[
        "Tagkawayan"
    ],
    "qs:name":"Tagkawayan",
    "qs:photos_9r":0,
    "qs:photos_sr":0,
    "qs:pop_sr":"8",
    "wd:wordcount":179,
    "wof:name":"Tagkawayan",
    "wof:placetype":"localadmin",
    "wof:population":51742
},
  "geometry": {"coordinates":[122.53333000000001,14.01667],"type":"Point"}
}