{
  "type": "Feature",
  "properties": {
    "gn:admin1_code":"03",
    "gn:admin2_code":"63",
    "gn:admin3_code":"36903000.0",
    "gn:asciiname":"Camangaan",
    "gn:country_code":"PH",
    "gn:dem":26,
    "gn:feature_class":"P",
    "gn:feature_code":"PPL",
    "gn:name":"Camangaan",
    "gn:population":0,
    "gn:timezone":"Asia/Manila",
    "iso:country":"PH",
    "name:fil_x_preferred":[
        "Camangaan"
    ],
    "wof:name":"Camangaan",
    "wof:placetype":"locality"
},
  "geometry": {"coordinates":[120.4153,15.6717],"type":"Point"}
}