{
  "type": "Feature",
  "properties": {
    "gn:admin1_code":"41",
    "gn:admin2_code":"49",
    "gn:admin3_code":"175316000.0",
    "gn:asciiname":"Madaon",
    "gn:country_code":"PH",
    "gn:dem":71,
    "gn:feature_class":"P",
    "gn:feature_code":"PPL",
    "gn:name":"Madaon",
    "gn:population":0,
    "gn:timezone":"Asia/Manila",
    "iso:country":"PH",
    "wof:name":"Madaon",
    "wof:placetype":"locality"
},
  "geometry": {"coordinates":[118.81667,10.11667],"type":"Point"}
}