{
  "type": "Feature",
  "properties": {
    "gn:admin1_code":"01",
    "gn:admin2_code":"51",
    "gn:admin3_code":"15525000.0",
    "gn:asciiname":"Licsi",
    "gn:country_code":"PH",
    "gn:dem":29,
    "gn:feature_class":"P",
    "gn:feature_code":"PPL",
    "gn:name":"Licsi",
    "gn:population":0,
    "gn:timezone":"Asia/Manila",
    "iso:country":"PH",
    "name:fil_x_preferred":[
        "Licsi"
    ],
    "wof:name":"Licsi",
    "wof:placetype":"locality"
},
  "geometry": {"coordinates":[120.48947,16.04482999999999],"type":"Point"}
}