{
  "type": "Feature",
  "properties": {
    "gn:admin1_code":"02",
    "gn:admin2_code":"31",
    "gn:admin3_code":"23121000.0",
    "gn:asciiname":"Dibewan",
    "gn:country_code":"PH",
    "gn:dem":8,
    "gn:feature_class":"P",
    "gn:feature_code":"PPL",
    "gn:name":"Dibewan",
    "gn:population":0,
    "gn:timezone":"Asia/Manila",
    "iso:country":"PH",
    "name:fil_x_preferred":[
        "Dibcuan"
    ],
    "name:fil_x_variant":[
        "Dibewan"
    ],
    "wof:name":"Dibewan",
    "wof:placetype":"locality"
},
  "geometry": {"coordinates":[122.46523999999999,17.11004],"type":"Point"}
}