{
  "type": "Feature",
  "properties": {
    "gn:admin1_code":"02",
    "gn:admin2_code":"14",
    "gn:admin3_code":"21514000.0",
    "gn:asciiname":"Progressive",
    "gn:country_code":"PH",
    "gn:dem":20,
    "gn:feature_class":"P",
    "gn:feature_code":"PPL",
    "gn:name":"Progressive",
    "gn:population":0,
    "gn:timezone":"Asia/Manila",
    "iso:country":"PH",
    "name:bul_x_preferred":[
        "\u041f\u0440\u043e\u0433\u0440\u0435\u0441\u0438\u0432\u0435\u043d"
    ],
    "name:ces_x_preferred":[
        "Progres"
    ],
    "name:fra_x_preferred":[
        "Progressif"
    ],
    "name:ita_x_preferred":[
        "Progressive"
    ],
    "name:jpn_x_preferred":[
        "\u30d7\u30ed\u30b0\u30ec\u30c3\u30b7\u30d6"
    ],
    "name:kor_x_preferred":[
        "\ud504\ub85c\uadf8\ub808\uc2dc\ube0c"
    ],
    "name:lav_x_preferred":[
        "Progres\u012bvie"
    ],
    "name:por_x_preferred":[
        "Progressivo"
    ],
    "name:swe_x_preferred":[
        "Progressiv"
    ],
    "name:urd_x_preferred":[
        "\u0645\u062a\u0631\u0642"
    ],
    "wof:name":"Progressive",
    "wof:placetype":"locality"
},
  "geometry": {"coordinates":[121.99227,18.26277],"type":"Point"}
}