{
  "type": "Feature",
  "properties": {
    "gn:admin1_code":"01",
    "gn:admin2_code":"29",
    "gn:admin3_code":"12922000.0",
    "gn:asciiname":"Caniogan",
    "gn:country_code":"PH",
    "gn:dem":3,
    "gn:feature_class":"P",
    "gn:feature_code":"PPL",
    "gn:name":"Caniogan",
    "gn:population":0,
    "gn:timezone":"Asia/Manila",
    "iso:country":"PH",
    "name:und_x_variant":[
        "Canogan Daquel",
        "Caniogan Dacquel",
        "Caniogan"
    ],
    "wof:name":"Caniogan",
    "wof:placetype":"locality"
},
  "geometry": {"coordinates":[120.42536,17.50551],"type":"Point"}
}