{
  "type": "Feature",
  "properties": {
    "gn:admin1_code":"02",
    "gn:admin2_code":"14",
    "gn:admin3_code":"21505000.0",
    "gn:asciiname":"Nagbatabat",
    "gn:country_code":"PH",
    "gn:dem":158,
    "gn:feature_class":"P",
    "gn:feature_code":"PPL",
    "gn:name":"Nagbatabat",
    "gn:population":0,
    "gn:timezone":"Asia/Manila",
    "iso:country":"PH",
    "name:fil_x_preferred":[
        "Nagbatabat"
    ],
    "wof:name":"Nagbatabat",
    "wof:placetype":"locality"
},
  "geometry": {"coordinates":[121.3721,18.8782],"type":"Point"}
}