{
  "type": "Feature",
  "properties": {
    "gn:admin1_code":"01",
    "gn:admin2_code":"29",
    "gn:admin3_code":"12931000.0",
    "gn:asciiname":"Caoayan",
    "gn:country_code":"PH",
    "gn:dem":157,
    "gn:feature_class":"P",
    "gn:feature_code":"PPL",
    "gn:name":"Caoayan",
    "gn:population":0,
    "gn:timezone":"Asia/Manila",
    "iso:country":"PH",
    "name:bcl_x_preferred":[
        "Caoayan"
    ],
    "name:ceb_x_preferred":[
        "Caoayan"
    ],
    "name:deu_x_preferred":[
        "Caoayan"
    ],
    "name:fil_x_preferred":[
        "Caoayan"
    ],
    "name:fra_x_preferred":[
        "Caoayan"
    ],
    "name:ilo_x_preferred":[
        "Caoayan"
    ],
    "name:ind_x_preferred":[
        "Caoayan"
    ],
    "name:ita_x_preferred":[
        "Caoayan"
    ],
    "name:nld_x_preferred":[
        "Caoayan"
    ],
    "name:pag_x_preferred":[
        "Caoayan"
    ],
    "name:pam_x_preferred":[
        "Caoayan"
    ],
    "name:spa_x_preferred":[
        "Caoayan"
    ],
    "name:swe_x_preferred":[
        "Caoayan"
    ],
    "name:tgl_x_preferred":[
        "Caoayan"
    ],
    "name:vie_x_preferred":[
        "Caoayan"
    ],
    "name:war_x_preferred":[
        "Caoayan"
    ],
    "wof:name":"Caoayan",
    "wof:placetype":"locality"
},
  "geometry": {"coordinates":[120.51667,16.85],"type":"Point"}
}