{
  "type": "Feature",
  "properties": {
    "gn:admin1_code":"08",
    "gn:admin2_code":"59",
    "gn:admin3_code":"86412000.0",
    "gn:asciiname":"Catmon",
    "gn:country_code":"PH",
    "gn:dem":38,
    "gn:feature_class":"P",
    "gn:feature_code":"PPL",
    "gn:name":"Catmon",
    "gn:population":0,
    "gn:timezone":"Asia/Manila",
    "iso:country":"PH",
    "name:fil_x_preferred":[
        "Catmon"
    ],
    "wof:name":"Catmon",
    "wof:placetype":"locality"
},
  "geometry": {"coordinates":[125.11960000000001,10.3442],"type":"Point"}
}