{
  "type": "Feature",
  "properties": {
    "gn:admin1_code":"05",
    "gn:admin2_code":"19",
    "gn:admin3_code":"52010000.0",
    "gn:asciiname":"Tambognon",
    "gn:country_code":"PH",
    "gn:dem":6,
    "gn:feature_class":"P",
    "gn:feature_code":"PPL",
    "gn:name":"Tambognon",
    "gn:population":0,
    "gn:timezone":"Asia/Manila",
    "iso:country":"PH",
    "name:fil_x_preferred":[
        "Tambognon"
    ],
    "name:und_x_variant":[
        "Tambugnon"
    ],
    "wof:name":"Tambognon",
    "wof:placetype":"locality"
},
  "geometry": {"coordinates":[124.3723,13.894],"type":"Point"}
}