{
  "type": "Feature",
  "properties": {
    "gn:admin1_code":"08",
    "gn:admin2_code":"23",
    "gn:admin3_code":"82613000.0",
    "gn:asciiname":"Peleu",
    "gn:cc2":"PH",
    "gn:country_code":"PH",
    "gn:dem":19,
    "gn:feature_class":"P",
    "gn:feature_code":"PPL",
    "gn:name":"Peleu",
    "gn:population":0,
    "gn:timezone":"Asia/Manila",
    "iso:country":"PH",
    "name:und_x_variant":[
        "Piliw",
        "Peleu"
    ],
    "wof:name":"Peleu",
    "wof:placetype":"locality"
},
  "geometry": {"coordinates":[125.58972,11.38028],"type":"Point"}
}