{
  "type": "Feature",
  "properties": {
    "gn:admin1_code":"01",
    "gn:admin2_code":"51",
    "gn:admin3_code":"15508000.0",
    "gn:asciiname":"Buet Dalen",
    "gn:country_code":"PH",
    "gn:dem":148,
    "gn:feature_class":"P",
    "gn:feature_code":"PPL",
    "gn:name":"Buet Dalen",
    "gn:population":0,
    "gn:timezone":"Asia/Manila",
    "iso:country":"PH",
    "name:fil_x_preferred":[
        "Buet Dalen"
    ],
    "wof:name":"Buet Dalen",
    "wof:placetype":"locality"
},
  "geometry": {"coordinates":[119.81440000000001,16.1851],"type":"Point"}
}