{
  "type": "Feature",
  "properties": {
    "gn:admin1_code":"15",
    "gn:admin2_code":"01",
    "gn:admin3_code":"140119000.0",
    "gn:asciiname":"Pang-ot",
    "gn:country_code":"PH",
    "gn:dem":254,
    "gn:feature_class":"P",
    "gn:feature_code":"PPL",
    "gn:name":"Pang-ot",
    "gn:population":0,
    "gn:timezone":"Asia/Manila",
    "iso:country":"PH",
    "name:fil_x_preferred":[
        "Pang-ot"
    ],
    "wof:name":"Pang-ot",
    "wof:placetype":"locality"
},
  "geometry": {"coordinates":[120.5622,17.3349],"type":"Point"}
}