{
  "type": "Feature",
  "properties": {
    "gn:admin1_code":"01",
    "gn:admin2_code":"29",
    "gn:admin3_code":"12932000.0",
    "gn:asciiname":"Indadangan",
    "gn:country_code":"PH",
    "gn:dem":895,
    "gn:feature_class":"P",
    "gn:feature_code":"PPL",
    "gn:name":"Indadangan",
    "gn:population":0,
    "gn:timezone":"Asia/Manila",
    "iso:country":"PH",
    "name:fil_x_preferred":[
        "Indadangan"
    ],
    "wof:name":"Indadangan",
    "wof:placetype":"locality"
},
  "geometry": {"coordinates":[120.58199999999999,16.9365],"type":"Point"}
}