{
  "type": "Feature",
  "properties": {
    "gn:country":"PH",
    "gn:fcode":"ADM3",
    "gn:pop":0,
    "iso:country":"PH",
    "name:fil_x_preferred":[
        "Municipality of Impasug-ong"
    ],
    "name:unk_x_variant":[
        "Impasug-ong"
    ],
    "qs:name":"Municipality of Impasug-ong",
    "qs:photos_9r":0,
    "qs:photos_sr":0,
    "qs:pop_sr":"0",
    "wd:wordcount":424,
    "wof:name":"Municipality of Impasug-ong",
    "wof:placetype":"localadmin",
    "wof:population":0
},
  "geometry": {"coordinates":[125.11694,8.41222],"type":"Point"}
}