{
  "type": "Feature",
  "properties": {
    "gn:country":"PH",
    "gn:fcode":"ADM3",
    "gn:population":0,
    "iso:country":"PH",
    "name:bcl_x_preferred":[
        "Impasug-ong"
    ],
    "name:ceb_x_preferred":[
        "Impasugong"
    ],
    "name:deu_x_preferred":[
        "Impasug-ong"
    ],
    "name:eng_x_preferred":[
        "Impasugong"
    ],
    "name:fil_x_preferred":[
        "Municipality of Impasug-ong"
    ],
    "name:fra_x_preferred":[
        "Impasug-ong"
    ],
    "name:ilo_x_preferred":[
        "Impasug-Ong"
    ],
    "name:ind_x_preferred":[
        "Impasug-ong"
    ],
    "name:ita_x_preferred":[
        "Impasug-ong"
    ],
    "name:nld_x_preferred":[
        "Impasug-Ong"
    ],
    "name:pag_x_preferred":[
        "Impasug-Ong"
    ],
    "name:pam_x_preferred":[
        "Impasug-Ong"
    ],
    "name:spa_x_preferred":[
        "Impasug\u00f3n"
    ],
    "name:swe_x_preferred":[
        "Impasug-Ong"
    ],
    "name:tgl_x_preferred":[
        "Impasugong"
    ],
    "name:urd_x_preferred":[
        "\u0627\u0645\u067e\u0627\u0633\u0648\u06af\u0648\u0646\u06af"
    ],
    "name:vie_x_preferred":[
        "Impasug-ong"
    ],
    "name:war_x_preferred":[
        "Impasug-Ong"
    ],
    "qs:name":"Municipality of Impasug-ong",
    "qs:photos_9r":0,
    "qs:photos_sr":0,
    "qs:pop_sr":"0",
    "wd:wordcount":424,
    "wof:name":"Municipality of Impasug-ong",
    "wof:placetype":"localadmin",
    "wof:population":0
},
  "geometry": {"coordinates":[125.11694,8.41222],"type":"Point"}
}