{
  "type": "Feature",
  "properties": {
    "gn:admin1_code":"06",
    "gn:admin2_code":"30",
    "gn:admin3_code":"63013000.0",
    "gn:asciiname":"Tubod",
    "gn:country_code":"PH",
    "gn:dem":93,
    "gn:feature_class":"P",
    "gn:feature_code":"PPL",
    "gn:name":"Tubod",
    "gn:population":0,
    "gn:timezone":"Asia/Manila",
    "iso:country":"PH",
    "name:ceb_x_preferred":[
        "Tubod"
    ],
    "name:deu_x_preferred":[
        "Tubod"
    ],
    "name:fil_x_preferred":[
        "Tubod"
    ],
    "name:fra_x_preferred":[
        "Tubod"
    ],
    "name:ilo_x_preferred":[
        "Tubod"
    ],
    "name:ita_x_preferred":[
        "Tubod"
    ],
    "name:nld_x_preferred":[
        "Tubod"
    ],
    "name:spa_x_preferred":[
        "Tubod"
    ],
    "name:war_x_preferred":[
        "Tubod"
    ],
    "wof:name":"Tubod",
    "wof:placetype":"locality"
},
  "geometry": {"coordinates":[122.53333000000001,11.13333],"type":"Point"}
}