{
  "type": "Feature",
  "properties": {
    "gn:admin1_code":"40",
    "gn:admin2_code":"33",
    "gn:admin3_code":"43420000.0",
    "gn:asciiname":"Susong Dalaga",
    "gn:country_code":"PH",
    "gn:dem":175,
    "gn:feature_class":"P",
    "gn:feature_code":"PPL",
    "gn:name":"Susong Dalaga",
    "gn:population":0,
    "gn:timezone":"Asia/Manila",
    "iso:country":"PH",
    "name:fil_x_preferred":[
        "Susong Dalaga"
    ],
    "wof:name":"Susong Dalaga",
    "wof:placetype":"locality"
},
  "geometry": {"coordinates":[121.36667,14.36667],"type":"Point"}
}