{
  "type": "Feature",
  "properties": {
    "gn:admin1_code":"01",
    "gn:admin2_code":"51",
    "gn:admin3_code":"15517000.0",
    "gn:asciiname":"San Sebastian",
    "gn:country_code":"PH",
    "gn:dem":5,
    "gn:feature_class":"P",
    "gn:feature_code":"PPL",
    "gn:name":"San Sebastian",
    "gn:population":0,
    "gn:timezone":"Asia/Manila",
    "iso:country":"PH",
    "name:fil_x_preferred":[
        "San Sebastian"
    ],
    "wof:name":"San Sebastian",
    "wof:placetype":"locality"
},
  "geometry": {"coordinates":[120.34999999999999,16.01667],"type":"Point"}
}