{
  "type": "Feature",
  "properties": {
    "gn:country":"PH",
    "gn:fcode":"PPL",
    "gn:pop":4047,
    "iso:country":"PH",
    "name:fil_x_preferred":[
        "Puncan"
    ],
    "qs:name":"Puncan",
    "qs:photos_9r":0,
    "qs:photos_sr":0,
    "qs:pop_sr":"4",
    "wof:name":"Puncan",
    "wof:placetype":"locality",
    "wof:population":4047
},
  "geometry": {"coordinates":[120.9907,15.9071],"type":"Point"}
}