{
  "type": "Feature",
  "properties": {
    "gn:admin1_code":"08",
    "gn:admin2_code":"67",
    "gn:admin3_code":"84810000.0",
    "gn:asciiname":"Tahabiran",
    "gn:country_code":"PH",
    "gn:dem":9,
    "gn:feature_class":"P",
    "gn:feature_code":"PPL",
    "gn:name":"Tahabiran",
    "gn:population":0,
    "gn:timezone":"Asia/Manila",
    "iso:country":"PH",
    "name:fil_x_preferred":[
        "Tahabiran"
    ],
    "wof:name":"Tahabiran",
    "wof:placetype":"locality"
},
  "geometry": {"coordinates":[125.0168,12.294],"type":"Point"}
}