{
  "type": "Feature",
  "properties": {
    "gn:admin1_code":"12",
    "gn:admin2_code":"57",
    "gn:admin3_code":"124709000.0",
    "gn:asciiname":"Bakat",
    "gn:country_code":"PH",
    "gn:dem":19,
    "gn:feature_class":"P",
    "gn:feature_code":"PPL",
    "gn:name":"Bakat",
    "gn:population":0,
    "gn:timezone":"Asia/Manila",
    "iso:country":"PH",
    "name:fil_x_preferred":[
        "Bakat"
    ],
    "wof:name":"Bakat",
    "wof:placetype":"locality"
},
  "geometry": {"coordinates":[124.53333000000001,7.18333],"type":"Point"}
}