{
  "type": "Feature",
  "properties": {
    "gn:admin1_code":"41",
    "gn:admin2_code":"54",
    "gn:admin3_code":"175909000.0",
    "gn:asciiname":"Gajac",
    "gn:country_code":"PH",
    "gn:dem":25,
    "gn:feature_class":"P",
    "gn:feature_code":"PPL",
    "gn:name":"Gajac",
    "gn:population":0,
    "gn:timezone":"Asia/Manila",
    "iso:country":"PH",
    "name:bos_x_preferred":[
        "Gajac"
    ],
    "name:hrv_x_preferred":[
        "Gajac"
    ],
    "name:hun_x_preferred":[
        "Gajac"
    ],
    "name:slv_x_preferred":[
        "Gajac"
    ],
    "name:spa_x_preferred":[
        "Gajac"
    ],
    "name:srp_x_preferred":[
        "\u0413\u0430\u0458\u0430\u0446"
    ],
    "name:ukr_x_preferred":[
        "\u0413\u0430\u044f\u0446\u044c"
    ],
    "name:zho_x_preferred":[
        "\u52a0\u96c5\u514b"
    ],
    "wof:name":"Gajac",
    "wof:placetype":"locality"
},
  "geometry": {"coordinates":[121.94981,12.39215],"type":"Point"}
}