{
  "type": "Feature",
  "properties": {
    "gn:admin1_code":"15",
    "gn:admin2_code":"44",
    "gn:admin3_code":"144409000.0",
    "gn:asciiname":"Nacagang",
    "gn:country_code":"PH",
    "gn:dem":1246,
    "gn:feature_class":"P",
    "gn:feature_code":"PPL",
    "gn:name":"Nacagang",
    "gn:population":0,
    "gn:timezone":"Asia/Manila",
    "iso:country":"PH",
    "name:fil_x_preferred":[
        "Nacagang"
    ],
    "name:und_x_variant":[
        "Nacagan"
    ],
    "wof:name":"Nacagang",
    "wof:placetype":"locality"
},
  "geometry": {"coordinates":[120.9019,17.0392],"type":"Point"}
}