{
  "type": "Feature",
  "properties": {
    "gn:admin1_code":"40",
    "gn:admin2_code":"09",
    "gn:admin3_code":"41021000.0",
    "gn:asciiname":"Bayongpooc",
    "gn:country_code":"PH",
    "gn:dem":142,
    "gn:feature_class":"P",
    "gn:feature_code":"PPL",
    "gn:name":"Bayongpooc",
    "gn:population":0,
    "gn:timezone":"Asia/Manila",
    "iso:country":"PH",
    "name:fil_x_preferred":[
        "Bayongpooc"
    ],
    "wof:name":"Bayongpooc",
    "wof:placetype":"locality"
},
  "geometry": {"coordinates":[121.21666999999999,13.85],"type":"Point"}
}