{
  "type": "Feature",
  "properties": {
    "iso:country":"PH",
    "name:bcl_x_preferred":[
        "Lubao"
    ],
    "name:cat_x_preferred":[
        "Lubao"
    ],
    "name:dut_x_preferred":[
        "Lubao"
    ],
    "name:eng_x_preferred":[
        "Lubao"
    ],
    "name:fil_x_preferred":[
        "Lubao"
    ],
    "name:fre_x_preferred":[
        "Lubao"
    ],
    "name:ger_x_preferred":[
        "Lubao"
    ],
    "name:ilo_x_preferred":[
        "Lubao"
    ],
    "name:ind_x_preferred":[
        "Lubao"
    ],
    "name:ita_x_preferred":[
        "Lubao"
    ],
    "name:nob_x_preferred":[
        "Lubao"
    ],
    "name:oci_x_preferred":[
        "Lubao"
    ],
    "name:pag_x_preferred":[
        "Lubao"
    ],
    "name:pam_x_preferred":[
        "Lubao"
    ],
    "name:rus_x_preferred":[
        "\u041b\u0443\u0431\u0430\u043e"
    ],
    "name:swe_x_preferred":[
        "Lubao"
    ],
    "name:tgl_x_preferred":[
        "Lubao"
    ],
    "name:vie_x_preferred":[
        "Lubao"
    ],
    "name:war_x_preferred":[
        "Lubao"
    ],
    "qs:gn_country":"PH",
    "qs:gn_fcode":"PPLA3",
    "qs:gn_pop":55645,
    "qs:name":"Lubao",
    "qs:name_adm0":"Philippines",
    "qs:name_adm1":"Central Luzon",
    "qs:photos":170,
    "qs:photos_1k":34,
    "qs:photos_9k":1,
    "qs:photos_9r":4,
    "qs:photos_all":170,
    "qs:photos_sr":4,
    "qs:placetype":"Town",
    "qs:pop_sr":"8",
    "qs:woe_adm0":23424934,
    "wd:wordcount":1989,
    "wof:name":"Lubao",
    "wof:placetype":"locality",
    "wof:population":55645
},
  "geometry": {"coordinates":[120.6011,14.9405],"type":"Point"}
}