{
  "type": "Feature",
  "properties": {
    "gn:admin1_code":"03",
    "gn:admin2_code":"13",
    "gn:admin3_code":"31417000.0",
    "gn:asciiname":"Natungcab",
    "gn:country_code":"PH",
    "gn:dem":15,
    "gn:feature_class":"P",
    "gn:feature_code":"PPL",
    "gn:name":"Natungcab",
    "gn:population":0,
    "gn:timezone":"Asia/Manila",
    "iso:country":"PH",
    "name:fil_x_preferred":[
        "Natungcab"
    ],
    "wof:name":"Natungcab",
    "wof:placetype":"locality"
},
  "geometry": {"coordinates":[120.90000000000001,14.91667],"type":"Point"}
}