{
  "type": "Feature",
  "properties": {
    "gn:admin1_code":"15",
    "gn:admin2_code":"10",
    "gn:admin3_code":"141107000.0",
    "gn:asciiname":"Lebeng",
    "gn:country_code":"PH",
    "gn:dem":2412,
    "gn:feature_class":"P",
    "gn:feature_code":"PPL",
    "gn:name":"Lebeng",
    "gn:population":0,
    "gn:timezone":"Asia/Manila",
    "iso:country":"PH",
    "name:fil_x_preferred":[
        "Lebeng"
    ],
    "wof:name":"Lebeng",
    "wof:placetype":"locality"
},
  "geometry": {"coordinates":[120.88844,16.66787],"type":"Point"}
}