{
  "type": "Feature",
  "properties": {
    "gn:admin1_code":"05",
    "gn:admin2_code":"39",
    "gn:admin3_code":"54113000.0",
    "gn:asciiname":"Layong",
    "gn:country_code":"PH",
    "gn:dem":44,
    "gn:feature_class":"P",
    "gn:feature_code":"PPL",
    "gn:name":"Layong",
    "gn:population":0,
    "gn:timezone":"Asia/Manila",
    "iso:country":"PH",
    "name:eng_x_preferred":[
        "Layong"
    ],
    "wof:name":"Layong",
    "wof:placetype":"locality"
},
  "geometry": {"coordinates":[123.67700000000001,12.3429],"type":"Point"}
}