{
  "type": "Feature",
  "properties": {
    "gn:country":"PH",
    "gn:fcode":"PPL",
    "gn:population":2820,
    "iso:country":"PH",
    "name:fil_x_preferred":[
        "Yook"
    ],
    "name:fil_x_variant":[
        "Yooc"
    ],
    "qs:name":"Yook",
    "qs:photos_9r":0,
    "qs:photos_sr":0,
    "qs:pop_sr":"4",
    "wof:name":"Yook",
    "wof:placetype":"locality",
    "wof:population":2820
},
  "geometry": {"coordinates":[121.964,13.22608],"type":"Point"}
}