{
  "type": "Feature",
  "properties": {
    "gn:admin1_code":"15",
    "gn:admin2_code":"27",
    "gn:admin3_code":"142711000.0",
    "gn:asciiname":"Batang",
    "gn:country_code":"PH",
    "gn:dem":631,
    "gn:feature_class":"P",
    "gn:feature_code":"PPL",
    "gn:name":"Batang",
    "gn:population":0,
    "gn:timezone":"Asia/Manila",
    "iso:country":"PH",
    "name:fil_x_preferred":[
        "Batang"
    ],
    "wof:name":"Batang",
    "wof:placetype":"locality"
},
  "geometry": {"coordinates":[121.09999999999999,16.68333],"type":"Point"}
}