{
  "type": "Feature",
  "properties": {
    "gn:admin1_code":"06",
    "gn:admin2_code":"06",
    "gn:admin3_code":"60609000.0",
    "gn:asciiname":"Lindero",
    "gn:country_code":"PH",
    "gn:dem":6,
    "gn:feature_class":"P",
    "gn:feature_code":"PPL",
    "gn:name":"Lindero",
    "gn:population":0,
    "gn:timezone":"Asia/Manila",
    "iso:country":"PH",
    "name:fil_x_preferred":[
        "Lindero"
    ],
    "name:und_x_variant":[
        "Linolero"
    ],
    "wof:name":"Lindero",
    "wof:placetype":"locality"
},
  "geometry": {"coordinates":[122.041,11.1094],"type":"Point"}
}