{
  "type": "Feature",
  "properties": {
    "gn:admin1_code":"08",
    "gn:admin2_code":"67",
    "gn:admin3_code":"84810000.0",
    "gn:asciiname":"Bogtosan",
    "gn:country_code":"PH",
    "gn:dem":7,
    "gn:feature_class":"P",
    "gn:feature_code":"PPL",
    "gn:name":"Bogtosan",
    "gn:population":0,
    "gn:timezone":"Asia/Manila",
    "iso:country":"PH",
    "name:fil_x_preferred":[
        "Bogtosan"
    ],
    "wof:name":"Bogtosan",
    "wof:placetype":"locality"
},
  "geometry": {"coordinates":[125.01667,12.35],"type":"Point"}
}