{
  "type": "Feature",
  "properties": {
    "gn:admin1_code":"12",
    "gn:admin2_code":"57",
    "gn:admin3_code":"124705000.0",
    "gn:asciiname":"Upper Buayan",
    "gn:cc2":"PH",
    "gn:country_code":"PH",
    "gn:dem":48,
    "gn:feature_class":"P",
    "gn:feature_code":"PPL",
    "gn:name":"Upper Buayan",
    "gn:population":0,
    "gn:timezone":"Asia/Manila",
    "iso:country":"PH",
    "name:und_x_variant":[
        "Upper Boayan",
        "Upper Buayan"
    ],
    "wof:name":"Upper Buayan",
    "wof:placetype":"locality"
},
  "geometry": {"coordinates":[124.55,7.27778],"type":"Point"}
}