{
  "type": "Feature",
  "properties": {
    "gn:admin1_code":"02",
    "gn:admin2_code":"31",
    "gn:admin3_code":"23112000.0",
    "gn:asciiname":"Dicaraywan",
    "gn:country_code":"PH",
    "gn:dem":87,
    "gn:feature_class":"P",
    "gn:feature_code":"PPL",
    "gn:name":"Dicaraywan",
    "gn:population":0,
    "gn:timezone":"Asia/Manila",
    "iso:country":"PH",
    "name:fil_x_preferred":[
        "Dicaraywan"
    ],
    "wof:name":"Dicaraywan",
    "wof:placetype":"locality"
},
  "geometry": {"coordinates":[121.7448,16.689],"type":"Point"}
}