{
  "type": "Feature",
  "properties": {
    "gn:admin1_code":"40",
    "gn:admin2_code":"33",
    "gn:asciiname":"Silangan Talaongan",
    "gn:country_code":"PH",
    "gn:dem":299,
    "gn:feature_class":"P",
    "gn:feature_code":"PPL",
    "gn:name":"Sila\u00f1gan Talao\u00f1gan",
    "gn:population":0,
    "gn:timezone":"Asia/Manila",
    "iso:country":"PH",
    "name:fil_x_preferred":[
        "Sila\u00f1gan Talao\u00f1gan"
    ],
    "wof:name":"Silangan Talaongan",
    "wof:placetype":"locality"
},
  "geometry": {"coordinates":[121.56659999999999,14.26705],"type":"Point"}
}