{
  "type": "Feature",
  "properties": {
    "gn:admin1_code":"40",
    "gn:admin2_code":"H2",
    "gn:admin3_code":"45607000.0",
    "gn:asciiname":"Ipil",
    "gn:country_code":"PH",
    "gn:dem":11,
    "gn:feature_class":"P",
    "gn:feature_code":"PPL",
    "gn:name":"Ipil",
    "gn:population":0,
    "gn:timezone":"Asia/Manila",
    "iso:country":"PH",
    "name:ceb_x_preferred":[
        "Ipil"
    ],
    "name:deu_x_preferred":[
        "Ipil"
    ],
    "name:fil_x_preferred":[
        "Ipil"
    ],
    "name:tgl_x_preferred":[
        "Ipil"
    ],
    "wof:name":"Ipil",
    "wof:placetype":"locality"
},
  "geometry": {"coordinates":[122.28091000000001,14.07],"type":"Point"}
}