{
  "type": "Feature",
  "properties": {
    "gn:admin1_code":"03",
    "gn:admin2_code":"07",
    "gn:admin3_code":"30806000.0",
    "gn:asciiname":"Cuevas",
    "gn:country_code":"PH",
    "gn:dem":22,
    "gn:feature_class":"P",
    "gn:feature_code":"PPL",
    "gn:name":"Cuevas",
    "gn:population":0,
    "gn:timezone":"Asia/Manila",
    "iso:country":"PH",
    "name:ast_x_preferred":[
        "Cuevas"
    ],
    "name:cat_x_preferred":[
        "Cuevas"
    ],
    "name:ceb_x_preferred":[
        "Cuevas"
    ],
    "name:deu_x_preferred":[
        "Cuevas"
    ],
    "name:fil_x_preferred":[
        "Cuevas"
    ],
    "name:fra_x_preferred":[
        "Cuevas"
    ],
    "name:por_x_preferred":[
        "Cuevas"
    ],
    "name:rus_x_preferred":[
        "\u041a\u0443\u044d\u0432\u0430"
    ],
    "name:spa_x_preferred":[
        "Cuevas"
    ],
    "name:swe_x_preferred":[
        "Cuevas"
    ],
    "wof:name":"Cuevas",
    "wof:placetype":"locality"
},
  "geometry": {"coordinates":[120.605,14.52778],"type":"Point"}
}