{
  "type": "Feature",
  "properties": {
    "gn:admin1_code":"41",
    "gn:admin2_code":"49",
    "gn:admin3_code":"175301000.0",
    "gn:asciiname":"Tinagong Dagat",
    "gn:country_code":"PH",
    "gn:dem":14,
    "gn:feature_class":"P",
    "gn:feature_code":"PPL",
    "gn:name":"Tinagong Dagat",
    "gn:population":0,
    "gn:timezone":"Asia/Manila",
    "iso:country":"PH",
    "name:eng_x_preferred":[
        "Tinagong Dagat"
    ],
    "wof:name":"Tinagong Dagat",
    "wof:placetype":"locality"
},
  "geometry": {"coordinates":[118.4958,9.33357],"type":"Point"}
}