{
  "type": "Feature",
  "properties": {
    "gn:admin1_code":"01",
    "gn:admin2_code":"36",
    "gn:admin3_code":"13307000.0",
    "gn:asciiname":"Parian Oeste-Pudoc",
    "gn:country_code":"PH",
    "gn:dem":27,
    "gn:feature_class":"P",
    "gn:feature_code":"PPL",
    "gn:name":"Parian Oeste-Pudoc",
    "gn:population":0,
    "gn:timezone":"Asia/Manila",
    "iso:country":"PH",
    "name:fil_x_preferred":[
        "Parian Oeste-Pudoc"
    ],
    "wof:name":"Parian Oeste-Pudoc",
    "wof:placetype":"locality"
},
  "geometry": {"coordinates":[120.33333,16.53333],"type":"Point"}
}