{
  "type": "Feature",
  "properties": {
    "gn:admin1_code":"03",
    "gn:admin2_code":"63",
    "gn:admin3_code":"36903000.0",
    "gn:asciiname":"Sinilian Second",
    "gn:country_code":"PH",
    "gn:dem":38,
    "gn:feature_class":"P",
    "gn:feature_code":"PPL",
    "gn:name":"Sinilian Second",
    "gn:population":0,
    "gn:timezone":"Asia/Manila",
    "iso:country":"PH",
    "name:fil_x_preferred":[
        "Sinilian"
    ],
    "name:und_x_variant":[
        "Sinilian 2",
        "Sinilian Segundo",
        "Sinilian Second"
    ],
    "wof:name":"Sinilian Second",
    "wof:placetype":"locality"
},
  "geometry": {"coordinates":[120.45368000000001,15.70757],"type":"Point"}
}