{
  "type": "Feature",
  "properties": {
    "gn:admin1_code":"08",
    "gn:admin2_code":"37",
    "gn:admin3_code":"83701000.0",
    "gn:asciiname":"Paguite",
    "gn:country_code":"PH",
    "gn:dem":15,
    "gn:feature_class":"P",
    "gn:feature_code":"PPL",
    "gn:name":"Paguite",
    "gn:population":0,
    "gn:timezone":"Asia/Manila",
    "iso:country":"PH",
    "name:fil_x_preferred":[
        "Paguite"
    ],
    "name:und_x_variant":[
        "Paguiti",
        "Paquite"
    ],
    "wof:name":"Paguite",
    "wof:placetype":"locality"
},
  "geometry": {"coordinates":[124.95820000000001,10.699],"type":"Point"}
}