{
  "type": "Feature",
  "properties": {
    "gn:country":"PH",
    "gn:fcode":"PPLA3",
    "gn:pop":7506,
    "iso:country":"PH",
    "name:bcl_x_preferred":[
        "Sarangani"
    ],
    "name:ceb_x_preferred":[
        "Sarangani"
    ],
    "name:deu_x_preferred":[
        "Sarangani"
    ],
    "name:eng_x_preferred":[
        "Sarangani"
    ],
    "name:fil_x_preferred":[
        "Sarangani"
    ],
    "name:fra_x_preferred":[
        "Sarangani"
    ],
    "name:ilo_x_preferred":[
        "Sarangani"
    ],
    "name:ind_x_preferred":[
        "Sarangani"
    ],
    "name:ita_x_preferred":[
        "Sarangani"
    ],
    "name:jpn_x_preferred":[
        "\u30b5\u30e9\u30f3\u30ac\u30cb"
    ],
    "name:nld_x_preferred":[
        "Sarangani"
    ],
    "name:nob_x_preferred":[
        "Sarangani"
    ],
    "name:pag_x_preferred":[
        "Sarangani"
    ],
    "name:pam_x_preferred":[
        "Sarangani"
    ],
    "name:rus_x_preferred":[
        "\u0421\u0430\u0440\u0430\u043d\u0433\u0430\u043d\u0438"
    ],
    "name:spa_x_preferred":[
        "Sarangani"
    ],
    "name:swe_x_preferred":[
        "Sarangani"
    ],
    "name:tgl_x_preferred":[
        "Sarangani"
    ],
    "name:vie_x_preferred":[
        "Sarangani"
    ],
    "name:war_x_preferred":[
        "Sarangani"
    ],
    "name:zho_x_preferred":[
        "\u85a9\u862d\u52a0\u5c3c"
    ],
    "qs:name":"Sarangani",
    "qs:photos_9r":0,
    "qs:photos_sr":0,
    "qs:pop_sr":"5",
    "wd:wordcount":1094,
    "wof:name":"Sarangani",
    "wof:placetype":"locality",
    "wof:population":7506
},
  "geometry": {"coordinates":[125.46361,5.40333],"type":"Point"}
}