{
  "type": "Feature",
  "properties": {
    "gn:admin1_code":"08",
    "gn:admin2_code":"37",
    "gn:admin3_code":"83713000.0",
    "gn:asciiname":"Villalon",
    "gn:country_code":"PH",
    "gn:dem":6,
    "gn:feature_class":"P",
    "gn:feature_code":"PPL",
    "gn:name":"Villalon",
    "gn:population":0,
    "gn:timezone":"Asia/Manila",
    "iso:country":"PH",
    "name:fil_x_preferred":[
        "Villalon"
    ],
    "name:und_x_variant":[
        "Vilalon",
        "Villalon"
    ],
    "wof:name":"Villalon",
    "wof:placetype":"locality"
},
  "geometry": {"coordinates":[124.3653,11.5187],"type":"Point"}
}