{
  "type": "Feature",
  "properties": {
    "gn:admin1_code":"07",
    "gn:admin2_code":"11",
    "gn:admin3_code":"71215000.0",
    "gn:asciiname":"Cabonan",
    "gn:country_code":"PH",
    "gn:dem":101,
    "gn:feature_class":"P",
    "gn:feature_code":"PPL",
    "gn:name":"Cabonan",
    "gn:population":0,
    "gn:timezone":"Asia/Manila",
    "iso:country":"PH",
    "name:fil_x_preferred":[
        "Cabonan"
    ],
    "wof:name":"Cabonan",
    "wof:placetype":"locality"
},
  "geometry": {"coordinates":[123.9332,9.6673],"type":"Point"}
}