{
  "type": "Feature",
  "properties": {
    "gn:admin1_code":"06",
    "gn:admin2_code":"H3",
    "gn:admin3_code":"64524000.0",
    "gn:asciiname":"Linubagan",
    "gn:country_code":"PH",
    "gn:dem":794,
    "gn:feature_class":"P",
    "gn:feature_code":"PPL",
    "gn:name":"Linubagan",
    "gn:population":0,
    "gn:timezone":"Asia/Manila",
    "iso:country":"PH",
    "name:fil_x_preferred":[
        "Linubagan"
    ],
    "wof:name":"Linubagan",
    "wof:placetype":"locality"
},
  "geometry": {"coordinates":[123.3224,10.50676],"type":"Point"}
}