{
  "type": "Feature",
  "properties": {
    "gn:admin1_code":"05",
    "gn:admin2_code":"05",
    "gn:admin3_code":"50512000.0",
    "gn:asciiname":"Imacoto",
    "gn:country_code":"PH",
    "gn:dem":8,
    "gn:feature_class":"P",
    "gn:feature_code":"PPL",
    "gn:name":"Imacoto",
    "gn:population":0,
    "gn:timezone":"Asia/Manila",
    "iso:country":"PH",
    "name:fil_x_preferred":[
        "Imacoto"
    ],
    "wof:name":"Imacoto",
    "wof:placetype":"locality"
},
  "geometry": {"coordinates":[123.29222,13.06583],"type":"Point"}
}