{
  "type": "Feature",
  "properties": {
    "gn:admin1_code":"40",
    "gn:admin2_code":"20",
    "gn:admin3_code":"42111000.0",
    "gn:asciiname":"Madgalo",
    "gn:country_code":"PH",
    "gn:dem":7,
    "gn:feature_class":"P",
    "gn:feature_code":"PPL",
    "gn:name":"Madgalo",
    "gn:population":0,
    "gn:timezone":"Asia/Manila",
    "iso:country":"PH",
    "name:und_x_variant":[
        "Potol",
        "Putol",
        "Madgalo"
    ],
    "wof:name":"Madgalo",
    "wof:placetype":"locality"
},
  "geometry": {"coordinates":[120.88758,14.43339],"type":"Point"}
}