{
  "type": "Feature",
  "properties": {
    "gn:admin1_code":"01",
    "gn:admin2_code":"28",
    "gn:admin3_code":"12802000.0",
    "gn:asciiname":"San Alberto",
    "gn:country_code":"PH",
    "gn:dem":21,
    "gn:feature_class":"P",
    "gn:feature_code":"PPL",
    "gn:name":"San Alberto",
    "gn:population":0,
    "gn:timezone":"Asia/Manila",
    "iso:country":"PH",
    "name:ceb_x_preferred":[
        "San Alberto"
    ],
    "name:deu_x_preferred":[
        "San Alberto"
    ],
    "name:fil_x_preferred":[
        "San Alberto"
    ],
    "name:nld_x_preferred":[
        "San Alberto"
    ],
    "name:por_x_preferred":[
        "San Alberto"
    ],
    "name:spa_x_preferred":[
        "San Alberto"
    ],
    "name:srp_x_preferred":[
        "\u0421\u0430\u043d \u0410\u043b\u0431\u0435\u0440\u0442\u043e"
    ],
    "name:swe_x_preferred":[
        "San Alberto"
    ],
    "name:vie_x_preferred":[
        "San Alberto"
    ],
    "wof:name":"San Alberto",
    "wof:placetype":"locality"
},
  "geometry": {"coordinates":[120.63333,18.25],"type":"Point"}
}