{
  "type": "Feature",
  "properties": {
    "gn:admin1_code":"09",
    "gn:admin2_code":"ZSI",
    "gn:admin3_code":"98301000.0",
    "gn:asciiname":"Talaptap",
    "gn:country_code":"PH",
    "gn:dem":2,
    "gn:feature_class":"P",
    "gn:feature_code":"PPL",
    "gn:name":"Talaptap",
    "gn:population":0,
    "gn:timezone":"Asia/Manila",
    "iso:country":"PH",
    "name:fil_x_preferred":[
        "Talaptap"
    ],
    "wof:name":"Talaptap",
    "wof:placetype":"locality"
},
  "geometry": {"coordinates":[122.86667,7.51167],"type":"Point"}
}