{
  "type": "Feature",
  "properties": {
    "gn:admin1_code":"12",
    "gn:admin2_code":"57",
    "gn:admin3_code":"124712000.0",
    "gn:asciiname":"Panicupan",
    "gn:cc2":"PH",
    "gn:country_code":"PH",
    "gn:dem":10,
    "gn:feature_class":"P",
    "gn:feature_code":"PPL",
    "gn:name":"Panicupan",
    "gn:population":0,
    "gn:timezone":"Asia/Manila",
    "iso:country":"PH",
    "name:und_x_variant":[
        "Panicuan",
        "Panicupan"
    ],
    "wof:name":"Panicupan",
    "wof:placetype":"locality"
},
  "geometry": {"coordinates":[124.63861,7.07167],"type":"Point"}
}