{
  "type": "Feature",
  "properties": {
    "gn:admin1_code":"07",
    "gn:admin2_code":"69",
    "gn:admin3_code":"76102000.0",
    "gn:asciiname":"Cong-Bugsa",
    "gn:cc2":"PH",
    "gn:country_code":"PH",
    "gn:dem":12,
    "gn:feature_class":"P",
    "gn:feature_code":"PPL",
    "gn:name":"Cong-Bugsa",
    "gn:population":0,
    "gn:timezone":"Asia/Manila",
    "iso:country":"PH",
    "name:und_x_variant":[
        "Cangbagsa",
        "Kangbagsa",
        "Cong-Bugsa"
    ],
    "wof:name":"Cong-Bugsa",
    "wof:placetype":"locality"
},
  "geometry": {"coordinates":[123.57250000000001,9.24056],"type":"Point"}
}