{
  "type": "Feature",
  "properties": {
    "gn:admin1_code":"14",
    "gn:admin2_code":"35",
    "gn:admin3_code":"153602000.0",
    "gn:asciiname":"Lalabuan",
    "gn:country_code":"PH",
    "gn:dem":27,
    "gn:feature_class":"P",
    "gn:feature_code":"PPL",
    "gn:name":"Lalabuan",
    "gn:population":0,
    "gn:timezone":"Asia/Manila",
    "iso:country":"PH",
    "name:fil_x_preferred":[
        "Lalabuan"
    ],
    "wof:name":"Lalabuan",
    "wof:placetype":"locality"
},
  "geometry": {"coordinates":[124.10334,7.55058],"type":"Point"}
}