{
  "type": "Feature",
  "properties": {
    "gn:admin1_code":"10",
    "gn:admin2_code":"43",
    "gn:admin3_code":"104308000.0",
    "gn:asciiname":"Murallon",
    "gn:country_code":"PH",
    "gn:dem":81,
    "gn:feature_class":"P",
    "gn:feature_code":"PPL",
    "gn:name":"Murallon",
    "gn:population":0,
    "gn:timezone":"Asia/Manila",
    "iso:country":"PH",
    "name:fil_x_preferred":[
        "Murallon"
    ],
    "wof:name":"Murallon",
    "wof:placetype":"locality"
},
  "geometry": {"coordinates":[125.09083,8.80806],"type":"Point"}
}