{
  "type": "Feature",
  "properties": {
    "gn:admin1_code":"10",
    "gn:admin2_code":"12",
    "gn:admin3_code":"101312000.0",
    "gn:asciiname":"Ki-eto",
    "gn:country_code":"PH",
    "gn:dem":880,
    "gn:feature_class":"P",
    "gn:feature_code":"PPL",
    "gn:name":"Ki-eto",
    "gn:population":0,
    "gn:timezone":"Asia/Manila",
    "iso:country":"PH",
    "name:fil_x_preferred":[
        "Ki-eto"
    ],
    "wof:name":"Ki-eto",
    "wof:placetype":"locality"
},
  "geometry": {"coordinates":[125.2625,8.20028],"type":"Point"}
}