{
  "type": "Feature",
  "properties": {
    "gn:admin1_code":"11",
    "gn:admin2_code":"I7",
    "gn:admin3_code":"112305000.0",
    "gn:asciiname":"Suwaon",
    "gn:country_code":"PH",
    "gn:dem":84,
    "gn:feature_class":"P",
    "gn:feature_code":"PPL",
    "gn:name":"Suwaon",
    "gn:population":0,
    "gn:timezone":"Asia/Manila",
    "iso:country":"PH",
    "name:fil_x_preferred":[
        "Suwaon"
    ],
    "wof:name":"Suwaon",
    "wof:placetype":"locality"
},
  "geometry": {"coordinates":[125.60611000000002,7.78306],"type":"Point"}
}