{
  "type": "Feature",
  "properties": {
    "gn:admin1_code":"08",
    "gn:admin2_code":"37",
    "gn:admin3_code":"83724000.0",
    "gn:asciiname":"Calanipawan",
    "gn:country_code":"PH",
    "gn:dem":41,
    "gn:feature_class":"P",
    "gn:feature_code":"PPL",
    "gn:name":"Calanipawan",
    "gn:population":0,
    "gn:timezone":"Asia/Manila",
    "iso:country":"PH",
    "name:fil_x_preferred":[
        "Calanipawan"
    ],
    "wof:name":"Calanipawan",
    "wof:placetype":"locality"
},
  "geometry": {"coordinates":[124.9199,10.7595],"type":"Point"}
}