{
  "type": "Feature",
  "properties": {
    "gn:admin1_code":"07",
    "gn:admin2_code":"11",
    "gn:admin3_code":"71214000.0",
    "gn:asciiname":"Pondol",
    "gn:country_code":"PH",
    "gn:dem":26,
    "gn:feature_class":"P",
    "gn:feature_code":"PPL",
    "gn:name":"Pondol",
    "gn:population":0,
    "gn:timezone":"Asia/Manila",
    "iso:country":"PH",
    "name:fil_x_preferred":[
        "Pondol"
    ],
    "wof:name":"Pondol",
    "wof:placetype":"locality"
},
  "geometry": {"coordinates":[124.01667,9.95],"type":"Point"}
}