{
  "type": "Feature",
  "properties": {
    "gn:admin1_code":"01",
    "gn:admin2_code":"51",
    "gn:admin3_code":"15515000.0",
    "gn:asciiname":"Umanday Oeste",
    "gn:country_code":"PH",
    "gn:dem":15,
    "gn:feature_class":"P",
    "gn:feature_code":"PPL",
    "gn:name":"Umanday Oeste",
    "gn:population":0,
    "gn:timezone":"Asia/Manila",
    "iso:country":"PH",
    "name:fil_x_preferred":[
        "Umanday Oeste"
    ],
    "wof:name":"Umanday Oeste",
    "wof:placetype":"locality"
},
  "geometry": {"coordinates":[120.20999999999999,15.9335],"type":"Point"}
}