{
  "type": "Feature",
  "properties": {
    "gn:admin1_code":"10",
    "gn:admin2_code":"17",
    "gn:admin3_code":"101801000.0",
    "gn:asciiname":"Alga",
    "gn:country_code":"PH",
    "gn:dem":34,
    "gn:feature_class":"P",
    "gn:feature_code":"PPL",
    "gn:name":"Alga",
    "gn:population":0,
    "gn:timezone":"Asia/Manila",
    "iso:country":"PH",
    "name:fil_x_preferred":[
        "Alga"
    ],
    "wof:name":"Alga",
    "wof:placetype":"locality"
},
  "geometry": {"coordinates":[124.6825,9.12083],"type":"Point"}
}