{
  "type": "Feature",
  "properties": {
    "gn:admin1_code":"40",
    "gn:admin2_code":"H2",
    "gn:admin3_code":"45627000.0",
    "gn:asciiname":"Pinangalo",
    "gn:country_code":"PH",
    "gn:dem":7,
    "gn:feature_class":"P",
    "gn:feature_code":"PPL",
    "gn:name":"Pinangalo",
    "gn:population":0,
    "gn:timezone":"Asia/Manila",
    "iso:country":"PH",
    "name:fil_x_preferred":[
        "Pinangalo"
    ],
    "wof:name":"Pinangalo",
    "wof:placetype":"locality"
},
  "geometry": {"coordinates":[121.81001000000001,14.28537],"type":"Point"}
}