{
  "type": "Feature",
  "properties": {
    "gn:country":"PH",
    "gn:fcode":"PPL",
    "gn:pop":2349,
    "iso:country":"PH",
    "name:eng_x_preferred":[
        "Libertad"
    ],
    "qs:name":"Libertad",
    "qs:photos_9r":0,
    "qs:photos_sr":0,
    "qs:pop_sr":"4",
    "wd:wordcount":414,
    "wof:name":"Libertad",
    "wof:placetype":"locality",
    "wof:population":2349
},
  "geometry": {"coordinates":[123.8382,8.2755],"type":"Point"}
}