{
  "type": "Feature",
  "properties": {
    "gn:admin1_code":"40",
    "gn:admin2_code":"20",
    "gn:admin3_code":"42108000.0",
    "gn:asciiname":"Siniguelasan",
    "gn:country_code":"PH",
    "gn:dem":42,
    "gn:feature_class":"P",
    "gn:feature_code":"PPL",
    "gn:name":"Siniguelasan",
    "gn:population":0,
    "gn:timezone":"Asia/Manila",
    "iso:country":"PH",
    "name:fil_x_preferred":[
        "Siniguelasan"
    ],
    "wof:name":"Siniguelasan",
    "wof:placetype":"locality"
},
  "geometry": {"coordinates":[120.89115,14.35183],"type":"Point"}
}