{
  "type": "Feature",
  "properties": {
    "gn:admin1_code":"15",
    "gn:admin2_code":"27",
    "gn:admin3_code":"142703000.0",
    "gn:asciiname":"Abatan",
    "gn:country_code":"PH",
    "gn:dem":932,
    "gn:feature_class":"P",
    "gn:feature_code":"PPL",
    "gn:name":"Abatan",
    "gn:population":0,
    "gn:timezone":"Asia/Manila",
    "iso:country":"PH",
    "name:fil_x_preferred":[
        "Abatan"
    ],
    "wof:name":"Abatan",
    "wof:placetype":"locality"
},
  "geometry": {"coordinates":[121.06644,16.83676],"type":"Point"}
}