{
  "type": "Feature",
  "properties": {
    "gn:country":"PH",
    "gn:fcode":"PPL",
    "gn:population":2579,
    "iso:country":"PH",
    "name:fil_x_preferred":[
        "Mayngaran"
    ],
    "qs:name":"Mayngaran",
    "qs:photos_9r":0,
    "qs:photos_sr":0,
    "qs:pop_sr":"4",
    "wof:name":"Mayngaran",
    "wof:placetype":"locality",
    "wof:population":2579
},
  "geometry": {"coordinates":[123.5996,12.3492],"type":"Point"}
}