{
  "type": "Feature",
  "properties": {
    "gn:admin1_code":"03",
    "gn:admin2_code":"07",
    "gn:admin3_code":"30802000.0",
    "gn:asciiname":"Ibaba",
    "gn:country_code":"PH",
    "gn:dem":8,
    "gn:feature_class":"P",
    "gn:feature_code":"PPL",
    "gn:name":"Ibaba",
    "gn:population":0,
    "gn:timezone":"Asia/Manila",
    "iso:country":"PH",
    "name:fil_x_preferred":[
        "Ibaba"
    ],
    "name:swa_x_preferred":[
        "Ibaba"
    ],
    "wof:name":"Ibaba",
    "wof:placetype":"locality"
},
  "geometry": {"coordinates":[120.39109999999999,14.5948],"type":"Point"}
}