{
  "type": "Feature",
  "properties": {
    "iso:country":"PH",
    "name:bcl_x_preferred":[
        "Claveria"
    ],
    "name:ceb_x_preferred":[
        "Claveria"
    ],
    "name:deu_x_preferred":[
        "Claveria"
    ],
    "name:eng_x_preferred":[
        "Claveria"
    ],
    "name:fra_x_preferred":[
        "Claveria"
    ],
    "name:ilo_x_preferred":[
        "Claveria"
    ],
    "name:ind_x_preferred":[
        "Claveria"
    ],
    "name:ita_x_preferred":[
        "Claveria"
    ],
    "name:nld_x_preferred":[
        "Claveria"
    ],
    "name:pag_x_preferred":[
        "Claveria"
    ],
    "name:pam_x_preferred":[
        "Claveria"
    ],
    "name:swe_x_preferred":[
        "Claveria"
    ],
    "name:tgl_x_preferred":[
        "Claveria"
    ],
    "name:und_x_variant":[
        "Hinapalanan"
    ],
    "name:vie_x_preferred":[
        "Claveria"
    ],
    "name:war_x_preferred":[
        "Claveria"
    ],
    "qs:gn_country":"PH",
    "qs:gn_fcode":"PPL",
    "qs:gn_pop":2695,
    "qs:name":"Hinaplanan",
    "qs:name_adm0":"Philippines",
    "qs:name_adm1":"Northern Mindanao",
    "qs:photos":0,
    "qs:photos_1k":0,
    "qs:photos_9k":1,
    "qs:photos_9r":1,
    "qs:photos_all":1,
    "qs:photos_sr":0,
    "qs:placetype":"Town",
    "qs:pop_sr":"4",
    "qs:woe_adm0":23424934,
    "wd:wordcount":1371,
    "wof:name":"Hinaplanan",
    "wof:placetype":"locality",
    "wof:population":2695
},
  "geometry": {"coordinates":[124.87306,8.64028],"type":"Point"}
}