{
  "type": "Feature",
  "properties": {
    "gn:admin1_code":"01",
    "gn:admin2_code":"51",
    "gn:admin3_code":"15541000.0",
    "gn:asciiname":"Pinmilapil",
    "gn:country_code":"PH",
    "gn:dem":96,
    "gn:feature_class":"P",
    "gn:feature_code":"PPL",
    "gn:name":"Pinmilapil",
    "gn:population":0,
    "gn:timezone":"Asia/Manila",
    "iso:country":"PH",
    "name:fil_x_preferred":[
        "Pinmilapil"
    ],
    "name:fil_x_variant":[
        "Pimmilapil"
    ],
    "name:und_x_variant":[
        "Pimmilapil"
    ],
    "wof:name":"Pinmilapil",
    "wof:placetype":"locality"
},
  "geometry": {"coordinates":[120.46329,16.1986],"type":"Point"}
}