{
  "type": "Feature",
  "properties": {
    "gn:admin1_code":"05",
    "gn:admin2_code":"39",
    "gn:admin3_code":"54104000.0",
    "gn:asciiname":"Canbanis",
    "gn:country_code":"PH",
    "gn:dem":7,
    "gn:feature_class":"P",
    "gn:feature_code":"PPL",
    "gn:name":"Canbanis",
    "gn:population":0,
    "gn:timezone":"Asia/Manila",
    "iso:country":"PH",
    "name:fil_x_preferred":[
        "Canbanis"
    ],
    "wof:name":"Canbanis",
    "wof:placetype":"locality"
},
  "geometry": {"coordinates":[123.7777,12.4316],"type":"Point"}
}