{
  "type": "Feature",
  "properties": {
    "gn:admin1_code":"01",
    "gn:admin2_code":"51",
    "gn:admin3_code":"15514000.0",
    "gn:asciiname":"Luciente Uno",
    "gn:country_code":"PH",
    "gn:dem":10,
    "gn:feature_class":"P",
    "gn:feature_code":"PPL",
    "gn:name":"Luciente Uno",
    "gn:population":0,
    "gn:timezone":"Asia/Manila",
    "iso:country":"PH",
    "name:fil_x_preferred":[
        "Luciente"
    ],
    "wof:name":"Luciente Uno",
    "wof:placetype":"locality"
},
  "geometry": {"coordinates":[119.89848000000001,16.39124],"type":"Point"}
}