{
  "type": "Feature",
  "properties": {
    "gn:admin1_code":"NCR",
    "gn:admin2_code":"137400000",
    "gn:admin3_code":"137404000.0",
    "gn:asciiname":"Bungad",
    "gn:country_code":"PH",
    "gn:dem":32,
    "gn:feature_class":"P",
    "gn:feature_code":"PPL",
    "gn:name":"Bungad",
    "gn:population":0,
    "gn:timezone":"Asia/Manila",
    "iso:country":"PH",
    "name:fil_x_preferred":[
        "Bungad"
    ],
    "wof:name":"Bungad",
    "wof:placetype":"locality"
},
  "geometry": {"coordinates":[121.024,14.6481],"type":"Point"}
}