{
  "type": "Feature",
  "properties": {
    "gn:admin1_code":"40",
    "gn:admin2_code":"H2",
    "gn:admin3_code":"45628000.0",
    "gn:asciiname":"Canawep",
    "gn:country_code":"PH",
    "gn:dem":123,
    "gn:feature_class":"P",
    "gn:feature_code":"PPL",
    "gn:name":"Canawep",
    "gn:population":0,
    "gn:timezone":"Asia/Manila",
    "iso:country":"PH",
    "name:fil_x_preferred":[
        "Canawep"
    ],
    "name:und_x_variant":[
        "Canoyep",
        "Canuyep"
    ],
    "wof:name":"Canawep",
    "wof:placetype":"locality"
},
  "geometry": {"coordinates":[122.4341,13.4663],"type":"Point"}
}