{
  "type": "Feature",
  "properties": {
    "gn:country":"PH",
    "gn:fcode":"PPL",
    "gn:population":7269,
    "iso:country":"PH",
    "name:eng_x_preferred":[
        "Karungdong"
    ],
    "name:und_x_variant":[
        "Karungdung"
    ],
    "qs:name":"Karungdong",
    "qs:photos_9r":0,
    "qs:photos_sr":0,
    "qs:pop_sr":"5",
    "wof:name":"Karungdong",
    "wof:placetype":"locality",
    "wof:population":7269
},
  "geometry": {"coordinates":[121.26300000000001,5.8844],"type":"Point"}
}