{
  "type": "Feature",
  "properties": {
    "gn:admin1_code":"02",
    "gn:admin2_code":"68",
    "gn:admin3_code":"25705000.0",
    "gn:asciiname":"San Leonardo",
    "gn:country_code":"PH",
    "gn:dem":114,
    "gn:feature_class":"P",
    "gn:feature_code":"PPL",
    "gn:name":"San Leonardo",
    "gn:population":0,
    "gn:timezone":"Asia/Manila",
    "iso:country":"PH",
    "name:fil_x_preferred":[
        "San Leonardo"
    ],
    "wof:name":"San Leonardo",
    "wof:placetype":"locality"
},
  "geometry": {"coordinates":[121.57080000000001,16.509],"type":"Point"}
}