{
  "type": "Feature",
  "properties": {
    "gn:admin1_code":"40",
    "gn:admin2_code":"53",
    "gn:admin3_code":"45805000.0",
    "gn:asciiname":"Malapandan",
    "gn:country_code":"PH",
    "gn:dem":16,
    "gn:feature_class":"P",
    "gn:feature_code":"PPL",
    "gn:name":"Malapandan",
    "gn:population":0,
    "gn:timezone":"Asia/Manila",
    "iso:country":"PH",
    "name:fil_x_preferred":[
        "Malapandan"
    ],
    "wof:name":"Malapandan",
    "wof:placetype":"locality"
},
  "geometry": {"coordinates":[121.1297,14.591],"type":"Point"}
}