{
  "type": "Feature",
  "properties": {
    "gn:country":"PH",
    "gn:fcode":"ADM3",
    "gn:pop":22829,
    "iso:country":"PH",
    "name:eng_x_preferred":[
        "Municipality of Lopez Jaena"
    ],
    "name:unk_x_variant":[
        "Lopez Jaena"
    ],
    "qs:name":"Municipality of Lopez Jaena",
    "qs:photos_9r":0,
    "qs:photos_sr":0,
    "qs:pop_sr":"7",
    "wd:wordcount":1680,
    "wof:name":"Municipality of Lopez Jaena",
    "wof:placetype":"localadmin",
    "wof:population":22829
},
  "geometry": {"coordinates":[123.7197,8.5246],"type":"Point"}
}