{
  "type": "Feature",
  "properties": {
    "gn:admin1_code":"03",
    "gn:admin2_code":"G8",
    "gn:admin3_code":"37706000.0",
    "gn:asciiname":"Borlongan",
    "gn:country_code":"PH",
    "gn:dem":17,
    "gn:feature_class":"P",
    "gn:feature_code":"PPL",
    "gn:name":"Borlongan",
    "gn:population":0,
    "gn:timezone":"Asia/Manila",
    "iso:country":"PH",
    "name:fil_x_preferred":[
        "Borlongan"
    ],
    "wof:name":"Borlongan",
    "wof:placetype":"locality"
},
  "geometry": {"coordinates":[121.65170000000001,15.9841],"type":"Point"}
}