{
  "type": "Feature",
  "properties": {
    "gn:admin1_code":"40",
    "gn:admin2_code":"H2",
    "gn:admin3_code":"45617000.0",
    "gn:asciiname":"Mainit",
    "gn:country_code":"PH",
    "gn:dem":142,
    "gn:feature_class":"P",
    "gn:feature_code":"PPL",
    "gn:name":"Mainit",
    "gn:population":0,
    "gn:timezone":"Asia/Manila",
    "iso:country":"PH",
    "name:fil_x_preferred":[
        "Mainit"
    ],
    "wof:name":"Mainit",
    "wof:placetype":"locality"
},
  "geometry": {"coordinates":[121.46666999999999,14.61667],"type":"Point"}
}