{
  "type": "Feature",
  "properties": {
    "gn:admin1_code":"08",
    "gn:admin2_code":"59",
    "gn:admin3_code":"86402000.0",
    "gn:asciiname":"Higosoan",
    "gn:country_code":"PH",
    "gn:dem":10,
    "gn:feature_class":"P",
    "gn:feature_code":"PPL",
    "gn:name":"Higosoan",
    "gn:population":0,
    "gn:timezone":"Asia/Manila",
    "iso:country":"PH",
    "name:fil_x_preferred":[
        "Higosoan"
    ],
    "name:und_x_variant":[
        "Divisoria",
        "Higusuan",
        "Higosoan"
    ],
    "wof:name":"Higosoan",
    "wof:placetype":"locality"
},
  "geometry": {"coordinates":[124.9636,10.3436],"type":"Point"}
}