{
  "type": "Feature",
  "properties": {
    "gn:admin1_code":"03",
    "gn:admin2_code":"13",
    "gn:admin3_code":"31402000.0",
    "gn:asciiname":"Santol",
    "gn:country_code":"PH",
    "gn:dem":10,
    "gn:feature_class":"P",
    "gn:feature_code":"PPL",
    "gn:name":"Santol",
    "gn:population":0,
    "gn:timezone":"Asia/Manila",
    "iso:country":"PH",
    "name:ceb_x_preferred":[
        "Santol"
    ],
    "name:deu_x_preferred":[
        "Santol"
    ],
    "name:fil_x_preferred":[
        "Santol"
    ],
    "name:nld_x_preferred":[
        "Santol"
    ],
    "name:swe_x_preferred":[
        "Santol"
    ],
    "name:tgl_x_preferred":[
        "Santol"
    ],
    "name:war_x_preferred":[
        "Santol"
    ],
    "wof:name":"Santol",
    "wof:placetype":"locality"
},
  "geometry": {"coordinates":[120.91329,14.85104],"type":"Point"}
}