{
  "type": "Feature",
  "properties": {
    "gn:admin1_code":"05",
    "gn:admin2_code":"19",
    "gn:admin3_code":"52010000.0",
    "gn:asciiname":"Rizal",
    "gn:country_code":"PH",
    "gn:dem":24,
    "gn:feature_class":"P",
    "gn:feature_code":"PPL",
    "gn:name":"Rizal",
    "gn:population":0,
    "gn:timezone":"Asia/Manila",
    "iso:country":"PH",
    "name:fil_x_preferred":[
        "Rizal"
    ],
    "wof:name":"Rizal",
    "wof:placetype":"locality"
},
  "geometry": {"coordinates":[124.33880000000001,13.8579],"type":"Point"}
}