{
  "type": "Feature",
  "properties": {
    "gn:admin1_code":"40",
    "gn:admin2_code":"20",
    "gn:admin3_code":"42112000.0",
    "gn:asciiname":"Bendita",
    "gn:country_code":"PH",
    "gn:dem":161,
    "gn:feature_class":"P",
    "gn:feature_code":"PPL",
    "gn:name":"Bendita",
    "gn:population":0,
    "gn:timezone":"Asia/Manila",
    "iso:country":"PH",
    "name:fil_x_preferred":[
        "Bendita"
    ],
    "name:spa_x_preferred":[
        "Bendita"
    ],
    "wof:name":"Bendita",
    "wof:placetype":"locality"
},
  "geometry": {"coordinates":[120.74420000000001,14.1519],"type":"Point"}
}