{
  "type": "Feature",
  "properties": {
    "gn:admin1_code":"41",
    "gn:admin2_code":"40",
    "gn:admin3_code":"175110000.0",
    "gn:asciiname":"Cabirian",
    "gn:country_code":"PH",
    "gn:dem":26,
    "gn:feature_class":"P",
    "gn:feature_code":"PPL",
    "gn:name":"Cabirian",
    "gn:population":0,
    "gn:timezone":"Asia/Manila",
    "iso:country":"PH",
    "name:fil_x_preferred":[
        "Cabirian"
    ],
    "wof:name":"Cabirian",
    "wof:placetype":"locality"
},
  "geometry": {"coordinates":[121.10821,12.42794],"type":"Point"}
}