{
  "type": "Feature",
  "properties": {
    "gn:admin1_code":"08",
    "gn:admin2_code":"67",
    "gn:admin3_code":"84822000.0",
    "gn:asciiname":"Gebolu-gan",
    "gn:country_code":"PH",
    "gn:dem":37,
    "gn:feature_class":"P",
    "gn:feature_code":"PPL",
    "gn:name":"Gebolu-gan",
    "gn:population":0,
    "gn:timezone":"Asia/Manila",
    "iso:country":"PH",
    "name:fil_x_preferred":[
        "Gebolu-gan"
    ],
    "wof:name":"Gebolu-gan",
    "wof:placetype":"locality"
},
  "geometry": {"coordinates":[124.80549999999999,12.2862],"type":"Point"}
}