{
  "type": "Feature",
  "properties": {
    "gn:admin1_code":"08",
    "gn:admin2_code":"59",
    "gn:admin3_code":"86417000.0",
    "gn:asciiname":"Pangi",
    "gn:country_code":"PH",
    "gn:dem":58,
    "gn:feature_class":"P",
    "gn:feature_code":"PPL",
    "gn:name":"Pangi",
    "gn:population":0,
    "gn:timezone":"Asia/Manila",
    "iso:country":"PH",
    "name:ceb_x_preferred":[
        "Pangi"
    ],
    "name:fil_x_preferred":[
        "Pangi"
    ],
    "name:nld_x_preferred":[
        "Pangi"
    ],
    "name:swe_x_preferred":[
        "Pangi"
    ],
    "wof:name":"Pangi",
    "wof:placetype":"locality"
},
  "geometry": {"coordinates":[124.9312,10.3875],"type":"Point"}
}