{
  "type": "Feature",
  "properties": {
    "gn:admin1_code":"11",
    "gn:admin2_code":"I6",
    "gn:admin3_code":"118207000.0",
    "gn:asciiname":"Union",
    "gn:country_code":"PH",
    "gn:dem":57,
    "gn:feature_class":"P",
    "gn:feature_code":"PPL",
    "gn:name":"Union",
    "gn:population":0,
    "gn:timezone":"Asia/Manila",
    "iso:country":"PH",
    "name:fil_x_preferred":[
        "Union"
    ],
    "wof:name":"Union",
    "wof:placetype":"locality"
},
  "geometry": {"coordinates":[126.04971999999999,7.80722],"type":"Point"}
}