{
  "type": "Feature",
  "properties": {
    "gn:admin1_code":"08",
    "gn:admin2_code":"55",
    "gn:admin3_code":"86002000.0",
    "gn:asciiname":"Paras",
    "gn:country_code":"PH",
    "gn:dem":103,
    "gn:feature_class":"P",
    "gn:feature_code":"PPL",
    "gn:name":"Paras",
    "gn:population":0,
    "gn:timezone":"Asia/Manila",
    "iso:country":"PH",
    "name:ceb_x_preferred":[
        "Paras"
    ],
    "name:fil_x_preferred":[
        "Paras"
    ],
    "name:fin_x_preferred":[
        "Paras"
    ],
    "name:fra_x_preferred":[
        "Paras"
    ],
    "name:ind_x_preferred":[
        "Paras"
    ],
    "name:mar_x_preferred":[
        "\u092a\u093e\u0930\u0938"
    ],
    "name:nld_x_preferred":[
        "Paras"
    ],
    "name:rus_x_preferred":[
        "\u041f\u0430\u0440\u0430\u0441"
    ],
    "name:srp_x_preferred":[
        "\u041f\u0430\u0440\u0430\u0441"
    ],
    "name:swe_x_preferred":[
        "Paras"
    ],
    "wof:name":"Paras",
    "wof:placetype":"locality"
},
  "geometry": {"coordinates":[125.13333,11.41667],"type":"Point"}
}