{
  "type": "Feature",
  "properties": {
    "gn:country":"PH",
    "gn:fcode":"ADM3",
    "gn:population":45082,
    "iso:country":"PH",
    "name:bcl_x_preferred":[
        "Luuk"
    ],
    "name:ceb_x_preferred":[
        "Luuk"
    ],
    "name:deu_x_preferred":[
        "Luuk"
    ],
    "name:eng_x_preferred":[
        "Municipality of Luuk"
    ],
    "name:eng_x_variant":[
        "Luuk"
    ],
    "name:fra_x_preferred":[
        "Luuk"
    ],
    "name:ilo_x_preferred":[
        "Luuk"
    ],
    "name:ind_x_preferred":[
        "Luuk"
    ],
    "name:ita_x_preferred":[
        "Luuk"
    ],
    "name:nld_x_preferred":[
        "Luuk"
    ],
    "name:pag_x_preferred":[
        "Luuk"
    ],
    "name:pam_x_preferred":[
        "Luuk"
    ],
    "name:sco_x_preferred":[
        "Luuk"
    ],
    "name:swe_x_preferred":[
        "Luuk"
    ],
    "name:tgl_x_preferred":[
        "Luuk"
    ],
    "name:und_x_variant":[
        "Camp Andres"
    ],
    "name:urd_x_preferred":[
        "\u0644\u0648\u0648\u06a9"
    ],
    "name:vie_x_preferred":[
        "Luuk"
    ],
    "name:war_x_preferred":[
        "Luuk"
    ],
    "qs:name":"Municipality of Luuk",
    "qs:photos_9r":0,
    "qs:photos_sr":0,
    "qs:pop_sr":"7",
    "wd:wordcount":126,
    "wof:name":"Municipality of Luuk",
    "wof:placetype":"localadmin",
    "wof:population":45082
},
  "geometry": {"coordinates":[121.3456,5.9671],"type":"Point"}
}