{
  "type": "Feature",
  "properties": {
    "gn:country":"PH",
    "gn:fcode":"ADM3",
    "gn:pop":45082,
    "iso:country":"PH",
    "name:eng_x_preferred":[
        "Municipality of Luuk"
    ],
    "name:unk_x_variant":[
        "Camp Andres"
    ],
    "qs:name":"Municipality of Luuk",
    "qs:photos_9r":0,
    "qs:photos_sr":0,
    "qs:pop_sr":"7",
    "wd:wordcount":126,
    "wof:name":"Municipality of Luuk",
    "wof:placetype":"localadmin",
    "wof:population":45082
},
  "geometry": {"coordinates":[121.3456,5.9671],"type":"Point"}
}