{
  "type": "Feature",
  "properties": {
    "gn:admin1_code":"06",
    "gn:admin2_code":"30",
    "gn:admin3_code":"63020000.0",
    "gn:asciiname":"Cabasi",
    "gn:country_code":"PH",
    "gn:dem":11,
    "gn:feature_class":"P",
    "gn:feature_code":"PPL",
    "gn:name":"Cabasi",
    "gn:population":0,
    "gn:timezone":"Asia/Manila",
    "iso:country":"PH",
    "name:fil_x_preferred":[
        "Cabasi"
    ],
    "wof:name":"Cabasi",
    "wof:placetype":"locality"
},
  "geometry": {"coordinates":[122.3087,10.6573],"type":"Point"}
}