{
  "type": "Feature",
  "properties": {
    "gn:admin1_code":"06",
    "gn:admin2_code":"06",
    "gn:admin3_code":"60602000.0",
    "gn:asciiname":"Naroroc",
    "gn:country_code":"PH",
    "gn:dem":216,
    "gn:feature_class":"P",
    "gn:feature_code":"PPL",
    "gn:name":"Naroroc",
    "gn:population":0,
    "gn:timezone":"Asia/Manila",
    "iso:country":"PH",
    "name:fil_x_preferred":[
        "Naroroc"
    ],
    "wof:name":"Naroroc",
    "wof:placetype":"locality"
},
  "geometry": {"coordinates":[122.11331,11.26502],"type":"Point"}
}