{
  "type": "Feature",
  "properties": {
    "gn:admin1_code":"15",
    "gn:admin2_code":"10",
    "gn:admin3_code":"141107000.0",
    "gn:asciiname":"Ballay",
    "gn:country_code":"PH",
    "gn:dem":1980,
    "gn:feature_class":"P",
    "gn:feature_code":"PPL",
    "gn:name":"Ballay",
    "gn:population":0,
    "gn:timezone":"Asia/Manila",
    "iso:country":"PH",
    "name:fil_x_preferred":[
        "Ballay"
    ],
    "wof:name":"Ballay",
    "wof:placetype":"locality"
},
  "geometry": {"coordinates":[120.85024,16.67347],"type":"Point"}
}