{
  "type": "Feature",
  "properties": {
    "gn:admin1_code":"15",
    "gn:admin2_code":"10",
    "gn:admin3_code":"141107000.0",
    "gn:asciiname":"Ballay",
    "gn:country_code":"PH",
    "gn:dem":1980,
    "gn:feature_class":"P",
    "gn:feature_code":"PPL",
    "gn:name":"Ballay",
    "gn:population":0,
    "gn:timezone":"Asia/Manila",
    "iso:country":"PH",
    "name:bug_x_preferred":[
        "Ballay"
    ],
    "name:cat_x_preferred":[
        "Ballay"
    ],
    "name:ceb_x_preferred":[
        "Ballay"
    ],
    "name:deu_x_preferred":[
        "Ballay"
    ],
    "name:eus_x_preferred":[
        "Ballay"
    ],
    "name:fil_x_preferred":[
        "Ballay"
    ],
    "name:fra_x_preferred":[
        "Ballay"
    ],
    "name:hun_x_preferred":[
        "Ballay"
    ],
    "name:hye_x_preferred":[
        "\u0532\u0561\u056c\u0565"
    ],
    "name:ita_x_preferred":[
        "Ballay"
    ],
    "name:lat_x_preferred":[
        "Ballay"
    ],
    "name:ltz_x_preferred":[
        "Ballay"
    ],
    "name:mlg_x_preferred":[
        "Ballay"
    ],
    "name:msa_x_preferred":[
        "Ballay"
    ],
    "name:nld_x_preferred":[
        "Ballay"
    ],
    "name:oci_x_preferred":[
        "Ballay"
    ],
    "name:pms_x_preferred":[
        "Ballay"
    ],
    "name:pol_x_preferred":[
        "Ballay"
    ],
    "name:por_x_preferred":[
        "Ballay"
    ],
    "name:ron_x_preferred":[
        "Ballay"
    ],
    "name:rus_x_preferred":[
        "\u0411\u0430\u043b\u043b\u0435"
    ],
    "name:slk_x_preferred":[
        "Ballay"
    ],
    "name:spa_x_preferred":[
        "Ballay"
    ],
    "name:sqi_x_preferred":[
        "Ballay"
    ],
    "name:srp_x_preferred":[
        "\u0411\u0430\u043b\u0435"
    ],
    "name:swe_x_preferred":[
        "Ballay"
    ],
    "name:ukr_x_preferred":[
        "\u0411\u0430\u043b\u043b\u0435"
    ],
    "name:vie_x_preferred":[
        "Ballay"
    ],
    "name:vol_x_preferred":[
        "Ballay"
    ],
    "name:war_x_preferred":[
        "Ballay"
    ],
    "wof:name":"Ballay",
    "wof:placetype":"locality"
},
  "geometry": {"coordinates":[120.85024,16.67347],"type":"Point"}
}