{
  "type": "Feature",
  "properties": {
    "gn:admin1_code":"15",
    "gn:admin2_code":"32",
    "gn:admin3_code":"143215000.0",
    "gn:asciiname":"Basao",
    "gn:country_code":"PH",
    "gn:dem":823,
    "gn:feature_class":"P",
    "gn:feature_code":"PPL",
    "gn:name":"Basao",
    "gn:population":0,
    "gn:timezone":"Asia/Manila",
    "iso:country":"PH",
    "name:fil_x_preferred":[
        "Basao"
    ],
    "name:fil_x_variant":[
        "Baseo"
    ],
    "name:und_x_variant":[
        "Baseo",
        "Basao"
    ],
    "wof:name":"Basao",
    "wof:placetype":"locality"
},
  "geometry": {"coordinates":[121.12295,17.22354],"type":"Point"}
}