{
  "type": "Feature",
  "properties": {
    "gn:admin1_code":"09",
    "gn:admin2_code":"66",
    "gn:admin3_code":"97318000.0",
    "gn:asciiname":"Timoaboy",
    "gn:country_code":"PH",
    "gn:dem":596,
    "gn:feature_class":"P",
    "gn:feature_code":"PPL",
    "gn:name":"Timoaboy",
    "gn:population":0,
    "gn:timezone":"Asia/Manila",
    "iso:country":"PH",
    "name:eng_x_preferred":[
        "Timoaboy"
    ],
    "name:und_x_variant":[
        "Tombaboy"
    ],
    "wof:name":"Timoaboy",
    "wof:placetype":"locality"
},
  "geometry": {"coordinates":[123.2197,8.0166],"type":"Point"}
}