{
  "type": "Feature",
  "properties": {
    "gn:admin1_code":"05",
    "gn:admin2_code":"15",
    "gn:admin3_code":"51612000.0",
    "gn:asciiname":"Bulacan",
    "gn:country_code":"PH",
    "gn:dem":6,
    "gn:feature_class":"P",
    "gn:feature_code":"PPL",
    "gn:name":"Bulacan",
    "gn:population":0,
    "gn:timezone":"Asia/Manila",
    "iso:country":"PH",
    "name:ace_x_preferred":[
        "Propinsi Bulacan"
    ],
    "name:ara_x_preferred":[
        "\u0628\u0648\u0644\u0627\u0643\u0627\u0646"
    ],
    "name:azb_x_preferred":[
        "\u0628\u0648\u0644\u0627\u06a9\u0627\u0646"
    ],
    "name:bcl_x_preferred":[
        "Bulacan"
    ],
    "name:ceb_x_preferred":[
        "Bulacan"
    ],
    "name:ces_x_preferred":[
        "Bulacan"
    ],
    "name:deu_x_preferred":[
        "Bulacan"
    ],
    "name:epo_x_preferred":[
        "Bulakano"
    ],
    "name:fas_x_preferred":[
        "\u0628\u0648\u0644\u0627\u06a9\u0627\u0646"
    ],
    "name:fil_x_preferred":[
        "Bulacan"
    ],
    "name:fin_x_preferred":[
        "Bulacan"
    ],
    "name:fra_x_preferred":[
        "Bulacain"
    ],
    "name:hin_x_preferred":[
        "\u092c\u0941\u0932\u093e\u0915\u093e\u0928 \u092a\u094d\u0930\u093e\u0928\u094d\u0924"
    ],
    "name:ilo_x_preferred":[
        "Bulacan"
    ],
    "name:ind_x_preferred":[
        "Bulacan"
    ],
    "name:jpn_x_preferred":[
        "\u30d6\u30e9\u30ab\u30f3\u5dde"
    ],
    "name:kor_x_preferred":[
        "\ubd88\ub77c\uce78\uc8fc"
    ],
    "name:lat_x_preferred":[
        "Bulacan"
    ],
    "name:mkd_x_preferred":[
        "\u0411\u0443\u043b\u0430\u043a\u0430\u043d"
    ],
    "name:nld_x_preferred":[
        "Bulacan"
    ],
    "name:nor_x_preferred":[
        "Bulacan"
    ],
    "name:pag_x_preferred":[
        "Bulacan"
    ],
    "name:pam_x_preferred":[
        "Bulacan"
    ],
    "name:pol_x_preferred":[
        "Bulacan"
    ],
    "name:por_x_preferred":[
        "Bulac\u00e3o"
    ],
    "name:rus_x_preferred":[
        "\u0411\u0443\u043b\u0430\u043a\u0430\u043d"
    ],
    "name:swe_x_preferred":[
        "Bulacan"
    ],
    "name:tam_x_preferred":[
        "\u0baa\u0bc1\u0bb2\u0b95\u0ba9\u0bcd"
    ],
    "name:tgl_x_preferred":[
        "Bulacan"
    ],
    "name:tha_x_preferred":[
        "\u0e08\u0e31\u0e07\u0e2b\u0e27\u0e31\u0e14\u0e1a\u0e39\u0e25\u0e32\u0e04\u0e31\u0e19"
    ],
    "name:tur_x_preferred":[
        "Bulacan"
    ],
    "name:ukr_x_preferred":[
        "\u0411\u0443\u043b\u0430\u043a\u0430\u043d"
    ],
    "name:urd_x_preferred":[
        "\u0628\u0648\u0644\u0627\u06a9\u0627\u0646"
    ],
    "name:vie_x_preferred":[
        "Bulacan"
    ],
    "name:war_x_preferred":[
        "Bulacan"
    ],
    "name:zho_x_preferred":[
        "\u5e03\u62c9\u5e72\u7701"
    ],
    "wof:name":"Bulacan",
    "wof:placetype":"locality"
},
  "geometry": {"coordinates":[122.90689999999999,14.222],"type":"Point"}
}