{
  "type": "Feature",
  "properties": {
    "gn:admin1_code":"07",
    "gn:admin2_code":"21",
    "gn:admin3_code":"72251000.0",
    "gn:asciiname":"Talavera",
    "gn:country_code":"PH",
    "gn:dem":5,
    "gn:feature_class":"P",
    "gn:feature_code":"PPL",
    "gn:name":"Talavera",
    "gn:population":0,
    "gn:timezone":"Asia/Manila",
    "iso:country":"PH",
    "name:cat_x_preferred":[
        "Talavera"
    ],
    "name:ceb_x_preferred":[
        "Talavera"
    ],
    "name:deu_x_preferred":[
        "Talavera"
    ],
    "name:fil_x_preferred":[
        "Talavera"
    ],
    "name:fra_x_preferred":[
        "Talavera"
    ],
    "name:ita_x_preferred":[
        "Talavera"
    ],
    "name:jpn_x_preferred":[
        "\u30bf\u30e9\u30f4\u30a7\u30e9"
    ],
    "name:nld_x_preferred":[
        "Talavera"
    ],
    "name:pol_x_preferred":[
        "Talavera"
    ],
    "name:por_x_preferred":[
        "Talavera"
    ],
    "name:rus_x_preferred":[
        "\u0422\u0430\u043b\u0430\u0432\u0435\u0440\u0430"
    ],
    "name:spa_x_preferred":[
        "Talavera"
    ],
    "name:swe_x_preferred":[
        "Talavera"
    ],
    "name:ukr_x_preferred":[
        "\u0422\u0430\u043b\u0430\u0432\u0435\u0440\u0430"
    ],
    "name:und_x_variant":[
        "Kalavera",
        "Calavera"
    ],
    "name:war_x_preferred":[
        "Talavera"
    ],
    "wof:name":"Talavera",
    "wof:placetype":"locality"
},
  "geometry": {"coordinates":[123.66459999999999,10.40817],"type":"Point"}
}