{
  "type": "Feature",
  "properties": {
    "gn:admin1_code":"40",
    "gn:admin2_code":"H2",
    "gn:admin3_code":"45622000.0",
    "gn:asciiname":"Tigas",
    "gn:country_code":"PH",
    "gn:dem":82,
    "gn:feature_class":"P",
    "gn:feature_code":"PPL",
    "gn:name":"Tigas",
    "gn:population":0,
    "gn:timezone":"Asia/Manila",
    "iso:country":"PH",
    "name:fil_x_preferred":[
        "Tigas"
    ],
    "wof:name":"Tigas",
    "wof:placetype":"locality"
},
  "geometry": {"coordinates":[122.36667,13.86667],"type":"Point"}
}