{
  "type": "Feature",
  "properties": {
    "gn:admin1_code":"15",
    "gn:admin2_code":"01",
    "gn:admin3_code":"140127000.0",
    "gn:asciiname":"Lumaba",
    "gn:country_code":"PH",
    "gn:dem":154,
    "gn:feature_class":"P",
    "gn:feature_code":"PPL",
    "gn:name":"Lumaba",
    "gn:population":0,
    "gn:timezone":"Asia/Manila",
    "iso:country":"PH",
    "name:fil_x_preferred":[
        "Lumaba"
    ],
    "wof:name":"Lumaba",
    "wof:placetype":"locality"
},
  "geometry": {"coordinates":[120.62130000000001,17.4551],"type":"Point"}
}