{
  "type": "Feature",
  "properties": {
    "gn:admin1_code":"14",
    "gn:admin2_code":"72",
    "gn:admin3_code":"157006000.0",
    "gn:asciiname":"Tampacan",
    "gn:country_code":"PH",
    "gn:dem":6,
    "gn:feature_class":"P",
    "gn:feature_code":"PPL",
    "gn:name":"Tampacan",
    "gn:population":0,
    "gn:timezone":"Asia/Manila",
    "iso:country":"PH",
    "name:ceb_x_preferred":[
        "Tampacan"
    ],
    "name:epo_x_preferred":[
        "Tampac\u00e1n"
    ],
    "name:eus_x_preferred":[
        "Tampac\u00e1n"
    ],
    "name:ita_x_preferred":[
        "Tampac\u00e1n"
    ],
    "name:por_x_preferred":[
        "Tampac\u00e1n"
    ],
    "name:spa_x_preferred":[
        "Tampac\u00e1n"
    ],
    "name:srp_x_preferred":[
        "\u041e\u043f\u0448\u0442\u0438\u043d\u0430 \u0422\u0430\u043c\u043f\u0430\u043a\u0430\u043d"
    ],
    "name:swe_x_preferred":[
        "Tampacan"
    ],
    "wof:name":"Tampacan",
    "wof:placetype":"locality"
},
  "geometry": {"coordinates":[120.48333,5.18333],"type":"Point"}
}