{
  "type": "Feature",
  "properties": {
    "gn:admin1_code":"14",
    "gn:admin2_code":"72",
    "gn:admin3_code":"157006000.0",
    "gn:asciiname":"Tampacan",
    "gn:country_code":"PH",
    "gn:dem":6,
    "gn:feature_class":"P",
    "gn:feature_code":"PPL",
    "gn:name":"Tampacan",
    "gn:population":0,
    "gn:timezone":"Asia/Manila",
    "iso:country":"PH",
    "wof:name":"Tampacan",
    "wof:placetype":"locality"
},
  "geometry": {"coordinates":[120.48333,5.18333],"type":"Point"}
}