{
  "type": "Feature",
  "properties": {
    "gn:admin1_code":"14",
    "gn:admin2_code":"56",
    "gn:admin3_code":"153815000.0",
    "gn:asciiname":"Rifao",
    "gn:cc2":"PH",
    "gn:country_code":"PH",
    "gn:dem":562,
    "gn:feature_class":"P",
    "gn:feature_code":"PPL",
    "gn:name":"Rifao",
    "gn:population":0,
    "gn:timezone":"Asia/Manila",
    "iso:country":"PH",
    "name:und_x_variant":[
        "Ritao",
        "Rifao"
    ],
    "wof:name":"Rifao",
    "wof:placetype":"locality"
},
  "geometry": {"coordinates":[124.06528,6.86028],"type":"Point"}
}