{
  "type": "Feature",
  "properties": {
    "gn:country":"PH",
    "gn:fcode":"PPL",
    "gn:population":21901,
    "iso:country":"PH",
    "name:eng_x_preferred":[
        "Malanday"
    ],
    "name:fil_x_preferred":[
        "Malanday"
    ],
    "name:pag_x_preferred":[
        "Malanday"
    ],
    "qs:name":"Malanday",
    "qs:photos_9r":0,
    "qs:photos_sr":0,
    "qs:pop_sr":"7",
    "wd:wordcount":120,
    "wof:name":"Malanday",
    "wof:placetype":"locality",
    "wof:population":21901
},
  "geometry": {"coordinates":[121.1306,14.7069],"type":"Point"}
}