{
  "type": "Feature",
  "properties": {
    "gn:admin1_code":"14",
    "gn:admin2_code":"56",
    "gn:admin3_code":"153837000.0",
    "gn:asciiname":"Midtanda",
    "gn:country_code":"PH",
    "gn:dem":12,
    "gn:feature_class":"P",
    "gn:feature_code":"PPL",
    "gn:name":"Midtanda",
    "gn:population":0,
    "gn:timezone":"Asia/Manila",
    "iso:country":"PH",
    "name:fil_x_preferred":[
        "Midtanda"
    ],
    "wof:name":"Midtanda",
    "wof:placetype":"locality"
},
  "geometry": {"coordinates":[124.46693999999999,6.93222],"type":"Point"}
}