{
  "type": "Feature",
  "properties": {
    "gn:admin1_code":"02",
    "gn:admin2_code":"14",
    "gn:admin3_code":"21525000.0",
    "gn:asciiname":"Mabannag",
    "gn:country_code":"PH",
    "gn:dem":18,
    "gn:feature_class":"P",
    "gn:feature_code":"PPL",
    "gn:name":"Mabannag",
    "gn:population":0,
    "gn:timezone":"Asia/Manila",
    "iso:country":"PH",
    "name:fil_x_preferred":[
        "Mabannag"
    ],
    "wof:name":"Mabannag",
    "wof:placetype":"locality"
},
  "geometry": {"coordinates":[121.87139999999999,18.2165],"type":"Point"}
}