{
  "type": "Feature",
  "properties": {
    "gn:gn_country":"PH",
    "gn:gn_fcode":"PPL",
    "gn:gn_pop":4338,
    "gn:population":4338,
    "iso:country":"PH",
    "name:fil_x_preferred":[
        "Lambontong"
    ],
    "qs_pg:aaroncc":"PH",
    "qs_pg:gn_country":"PH",
    "qs_pg:gn_fcode":"PPL",
    "qs_pg:gn_pop":4338,
    "qs_pg:name":"Lambontong",
    "qs_pg:photos_9r":0,
    "qs_pg:photos_sr":0,
    "qs_pg:pop_sr":4,
    "qs_pg:qs_pg_placetype":"locality",
    "wof:name":"Lambontong",
    "wof:placetype":"locality",
    "wof:population":4338
},
  "geometry": {"coordinates":[124.81056,6.30833],"type":"Point"}
}