{
  "type": "Feature",
  "properties": {
    "gn:admin1_code":"08",
    "gn:admin2_code":"23",
    "gn:admin3_code":"82605000.0",
    "gn:asciiname":"Cagoras",
    "gn:cc2":"PH",
    "gn:country_code":"PH",
    "gn:dem":15,
    "gn:feature_class":"P",
    "gn:feature_code":"PPL",
    "gn:name":"Cagoras",
    "gn:population":0,
    "gn:timezone":"Asia/Manila",
    "iso:country":"PH",
    "name:und_x_variant":[
        "Cag-aras",
        "Cagoras"
    ],
    "wof:name":"Cagoras",
    "wof:placetype":"locality"
},
  "geometry": {"coordinates":[125.27500000000001,11.95861],"type":"Point"}
}