{
  "type": "Feature",
  "properties": {
    "gn:admin1_code":"09",
    "gn:admin2_code":"66",
    "gn:admin3_code":"97306000.0",
    "gn:asciiname":"Biray",
    "gn:country_code":"PH",
    "gn:dem":330,
    "gn:feature_class":"P",
    "gn:feature_code":"PPL",
    "gn:name":"Biray",
    "gn:population":0,
    "gn:timezone":"Asia/Manila",
    "iso:country":"PH",
    "wof:name":"Biray",
    "wof:placetype":"locality"
},
  "geometry": {"coordinates":[123.27472,7.63472],"type":"Point"}
}