{
  "type": "Feature",
  "properties": {
    "gn:admin1_code":"03",
    "gn:admin2_code":"13",
    "gn:admin3_code":"31421000.0",
    "gn:asciiname":"Tibagan",
    "gn:country_code":"PH",
    "gn:dem":38,
    "gn:feature_class":"P",
    "gn:feature_code":"PPL",
    "gn:name":"Tibagan",
    "gn:population":0,
    "gn:timezone":"Asia/Manila",
    "iso:country":"PH",
    "name:fil_x_preferred":[
        "Tibagan"
    ],
    "wof:name":"Tibagan",
    "wof:placetype":"locality"
},
  "geometry": {"coordinates":[120.99039,15.13185],"type":"Point"}
}