{
  "type": "Feature",
  "properties": {
    "gn:admin1_code":"03",
    "gn:admin2_code":"47",
    "gn:admin3_code":"34930000.0",
    "gn:asciiname":"Matingkis",
    "gn:country_code":"PH",
    "gn:dem":60,
    "gn:feature_class":"P",
    "gn:feature_code":"PPL",
    "gn:name":"Matingkis",
    "gn:population":0,
    "gn:timezone":"Asia/Manila",
    "iso:country":"PH",
    "name:fil_x_preferred":[
        "Matinguis"
    ],
    "name:fil_x_variant":[
        "Matinquis"
    ],
    "wof:name":"Matingkis",
    "wof:placetype":"locality"
},
  "geometry": {"coordinates":[120.88153,15.70265],"type":"Point"}
}