{
  "type": "Feature",
  "properties": {
    "gn:admin1_code":"12",
    "gn:admin2_code":"M9",
    "gn:admin3_code":"128002000.0",
    "gn:asciiname":"Malitao",
    "gn:country_code":"PH",
    "gn:dem":516,
    "gn:feature_class":"P",
    "gn:feature_code":"PPL",
    "gn:name":"Malitao",
    "gn:population":0,
    "gn:timezone":"Asia/Manila",
    "iso:country":"PH",
    "name:fil_x_preferred":[
        "Malitao"
    ],
    "wof:name":"Malitao",
    "wof:placetype":"locality"
},
  "geometry": {"coordinates":[125.41972,5.76639],"type":"Point"}
}