{
  "type": "Feature",
  "properties": {
    "gn:admin1_code":"14",
    "gn:admin2_code":"22",
    "gn:asciiname":"Balas",
    "gn:country":"PH",
    "gn:country_code":"PH",
    "gn:dem":-9999,
    "gn:fcode":"PPL",
    "gn:feature_class":"P",
    "gn:feature_code":"PPL",
    "gn:name":"Balas",
    "gn:population":2295,
    "gn:timezone":"Asia/Manila",
    "iso:country":"PH",
    "name:ceb_x_preferred":[
        "Bal\u016bs"
    ],
    "name:fas_x_preferred":[
        "\u0628\u0627\u0644\u0627\u0633"
    ],
    "name:fil_x_preferred":[
        "Balas"
    ],
    "name:swe_x_preferred":[
        "Bal\u016bs"
    ],
    "qs:name":"Balas",
    "qs:photos_9r":0,
    "qs:photos_sr":0,
    "qs:pop_sr":"4",
    "wd:wordcount":95,
    "wof:name":"Balas",
    "wof:placetype":"locality",
    "wof:population":2295
},
  "geometry": {"coordinates":[122.13806,6.6875],"type":"Point"}
}