{
  "type": "Feature",
  "properties": {
    "gn:admin1_code":"08",
    "gn:admin2_code":"67",
    "gn:admin3_code":"84810000.0",
    "gn:asciiname":"Dapdap",
    "gn:country_code":"PH",
    "gn:dem":11,
    "gn:feature_class":"P",
    "gn:feature_code":"PPL",
    "gn:name":"Dapdap",
    "gn:population":0,
    "gn:timezone":"Asia/Manila",
    "iso:country":"PH",
    "name:fil_x_preferred":[
        "Dapdap"
    ],
    "wof:name":"Dapdap",
    "wof:placetype":"locality"
},
  "geometry": {"coordinates":[125.04000000000001,12.28833],"type":"Point"}
}