{
  "type": "Feature",
  "properties": {
    "gn:country":"PH",
    "gn:fcode":"ADM3",
    "gn:population":42592,
    "iso:country":"PH",
    "name:bcl_x_preferred":[
        "Sibonga"
    ],
    "name:ceb_x_preferred":[
        "Sibonga"
    ],
    "name:deu_x_preferred":[
        "Sibonga"
    ],
    "name:fra_x_preferred":[
        "Sibonga"
    ],
    "name:ilo_x_preferred":[
        "Sibonga"
    ],
    "name:ind_x_preferred":[
        "Sibonga"
    ],
    "name:ita_x_preferred":[
        "Sibonga"
    ],
    "name:nld_x_preferred":[
        "Sibonga"
    ],
    "name:pag_x_preferred":[
        "Sibonga"
    ],
    "name:pam_x_preferred":[
        "Sibonga"
    ],
    "name:swe_x_preferred":[
        "Sibonga"
    ],
    "name:tgl_x_preferred":[
        "Sibonga"
    ],
    "name:vie_x_preferred":[
        "Sibonga"
    ],
    "name:war_x_preferred":[
        "Sibonga"
    ],
    "qs:name":"Sibonga",
    "qs:photos_9r":0,
    "qs:photos_sr":0,
    "qs:pop_sr":"7",
    "wof:name":"Sibonga",
    "wof:placetype":"localadmin",
    "wof:population":42592
},
  "geometry": {"coordinates":[123.56667,10.03333],"type":"Point"}
}