{
  "type": "Feature",
  "properties": {
    "gn:country":"PH",
    "gn:fcode":"ADM3",
    "gn:pop":42592,
    "iso:country":"PH",
    "qs:name":"Sibonga",
    "qs:photos_9r":0,
    "qs:photos_sr":0,
    "qs:pop_sr":"7",
    "wof:name":"Sibonga",
    "wof:placetype":"localadmin",
    "wof:population":42592
},
  "geometry": {"coordinates":[123.56667,10.03333],"type":"Point"}
}