{
  "type": "Feature",
  "properties": {
    "gn:admin1_code":"08",
    "gn:admin2_code":"59",
    "gn:admin3_code":"86414000.0",
    "gn:asciiname":"Timba",
    "gn:country_code":"PH",
    "gn:dem":65,
    "gn:feature_class":"P",
    "gn:feature_code":"PPL",
    "gn:name":"Timba",
    "gn:population":0,
    "gn:timezone":"Asia/Manila",
    "iso:country":"PH",
    "name:fil_x_preferred":[
        "Timba"
    ],
    "wof:name":"Timba",
    "wof:placetype":"locality"
},
  "geometry": {"coordinates":[125.21639,10.25222],"type":"Point"}
}