{
  "type": "Feature",
  "properties": {
    "gn:admin1_code":"40",
    "gn:admin2_code":"09",
    "gn:admin3_code":"41010000.0",
    "gn:asciiname":"Bilogo",
    "gn:country_code":"PH",
    "gn:dem":153,
    "gn:feature_class":"P",
    "gn:feature_code":"PPL",
    "gn:name":"Bilogo",
    "gn:population":0,
    "gn:timezone":"Asia/Manila",
    "iso:country":"PH",
    "name:fil_x_preferred":[
        "Bilogo"
    ],
    "name:tgl_x_preferred":[
        "Bilogo"
    ],
    "wof:name":"Bilogo",
    "wof:placetype":"locality"
},
  "geometry": {"coordinates":[121.1771,13.7636],"type":"Point"}
}