{
  "type": "Feature",
  "properties": {
    "gn:country":"PH",
    "gn:fcode":"ADM3",
    "gn:pop":8933,
    "iso:country":"PH",
    "name:fil_x_preferred":[
        "Balingoan"
    ],
    "qs:name":"Balingoan",
    "qs:photos_9r":0,
    "qs:photos_sr":0,
    "qs:pop_sr":"5",
    "wof:name":"Balingoan",
    "wof:placetype":"localadmin",
    "wof:population":8933
},
  "geometry": {"coordinates":[124.86667,8.95],"type":"Point"}
}