{
  "type": "Feature",
  "properties": {
    "gn:country":"PH",
    "gn:fcode":"PPLA3",
    "gn:pop":0,
    "iso:country":"PH",
    "name:fil_x_preferred":[
        "San Manuel"
    ],
    "name:spa_x_preferred":[
        "San Manuel de Pangasin\u00e1n"
    ],
    "qs:name":"San Manuel",
    "qs:photos_9r":0,
    "qs:photos_sr":0,
    "qs:pop_sr":"0",
    "wd:wordcount":48,
    "wof:name":"San Manuel",
    "wof:placetype":"locality",
    "wof:population":0
},
  "geometry": {"coordinates":[120.6687,16.0647],"type":"Point"}
}