{
  "type": "Feature",
  "properties": {
    "iso:country":"PH",
    "name:bcl_x_preferred":[
        "Dangcagan"
    ],
    "name:cbk_zam_x_preferred":[
        "Dangcagan"
    ],
    "name:ceb_x_preferred":[
        "Dangcagan"
    ],
    "name:deu_x_preferred":[
        "Dangcagan"
    ],
    "name:eng_x_preferred":[
        "Dangcagan"
    ],
    "name:fra_x_preferred":[
        "Dangcagan"
    ],
    "name:ilo_x_preferred":[
        "Dangcagan"
    ],
    "name:ind_x_preferred":[
        "Dangcagan"
    ],
    "name:ita_x_preferred":[
        "Dangcagan"
    ],
    "name:nld_x_preferred":[
        "Dangcagan"
    ],
    "name:pag_x_preferred":[
        "Dangcagan"
    ],
    "name:pam_x_preferred":[
        "Dangcagan"
    ],
    "name:spa_x_preferred":[
        "Dangcag\u00e1n"
    ],
    "name:swe_x_preferred":[
        "Dangcagan"
    ],
    "name:tgl_x_preferred":[
        "Dangcagan"
    ],
    "name:unk_x_variant":[
        "Dancagan"
    ],
    "name:vie_x_preferred":[
        "Dangcagan"
    ],
    "name:war_x_preferred":[
        "Dangcagan"
    ],
    "qs:gn_country":"PH",
    "qs:gn_fcode":"PPL",
    "qs:gn_pop":4864,
    "qs:name":"Dangcagan",
    "qs:name_adm0":"Philippines",
    "qs:name_adm1":"Northern Mindanao",
    "qs:photos":0,
    "qs:photos_1k":0,
    "qs:photos_9k":0,
    "qs:photos_9r":0,
    "qs:photos_all":0,
    "qs:photos_sr":0,
    "qs:placetype":"Town",
    "qs:pop_sr":"4",
    "qs:woe_adm0":23424934,
    "wd:wordcount":645,
    "wof:name":"Dangcagan",
    "wof:placetype":"locality",
    "wof:population":4864
},
  "geometry": {"coordinates":[125.00417,7.60917],"type":"Point"}
}