{
  "type": "Feature",
  "properties": {
    "gn:admin1_code":"15",
    "gn:admin2_code":"10",
    "gn:admin3_code":"141107000.0",
    "gn:asciiname":"Tamangan",
    "gn:country_code":"PH",
    "gn:dem":2282,
    "gn:feature_class":"P",
    "gn:feature_code":"PPL",
    "gn:name":"Tamangan",
    "gn:population":0,
    "gn:timezone":"Asia/Manila",
    "iso:country":"PH",
    "name:fil_x_preferred":[
        "Tamangan"
    ],
    "wof:name":"Tamangan",
    "wof:placetype":"locality"
},
  "geometry": {"coordinates":[120.87614000000001,16.67927],"type":"Point"}
}