{
  "type": "Feature",
  "properties": {
    "gn:admin1_code":"10",
    "gn:admin2_code":"42",
    "gn:admin3_code":"104205000.0",
    "gn:asciiname":"Gata",
    "gn:country_code":"PH",
    "gn:dem":11,
    "gn:feature_class":"P",
    "gn:feature_code":"PPL",
    "gn:name":"Gata",
    "gn:population":0,
    "gn:timezone":"Asia/Manila",
    "iso:country":"PH",
    "name:eng_x_preferred":[
        "Gata"
    ],
    "wof:name":"Gata",
    "wof:placetype":"locality"
},
  "geometry": {"coordinates":[123.85039999999999,8.1942],"type":"Point"}
}