{
  "type": "Feature",
  "properties": {
    "gn:admin1_code":"01",
    "gn:admin2_code":"29",
    "gn:admin3_code":"12929000.0",
    "gn:asciiname":"Abaccan",
    "gn:cc2":"PH",
    "gn:country_code":"PH",
    "gn:dem":675,
    "gn:feature_class":"P",
    "gn:feature_code":"PPL",
    "gn:name":"Abaccan",
    "gn:population":0,
    "gn:timezone":"Asia/Manila",
    "iso:country":"PH",
    "name:und_x_variant":[
        "Abacca",
        "Abaccan"
    ],
    "wof:name":"Abaccan",
    "wof:placetype":"locality"
},
  "geometry": {"coordinates":[120.56667,17.03333],"type":"Point"}
}