{
  "type": "Feature",
  "properties": {
    "gn:admin1_code":"03",
    "gn:admin2_code":"47",
    "gn:admin3_code":"34908000.0",
    "gn:asciiname":"Mahipon",
    "gn:country_code":"PH",
    "gn:dem":33,
    "gn:feature_class":"P",
    "gn:feature_code":"PPL",
    "gn:name":"Mahipon",
    "gn:population":0,
    "gn:timezone":"Asia/Manila",
    "iso:country":"PH",
    "name:fil_x_preferred":[
        "Mahipon"
    ],
    "wof:name":"Mahipon",
    "wof:placetype":"locality"
},
  "geometry": {"coordinates":[120.99898,15.24927],"type":"Point"}
}