{
  "type": "Feature",
  "properties": {
    "gn:country":"PH",
    "gn:fcode":"PPL",
    "gn:pop":4224,
    "iso:country":"PH",
    "name:fil_x_preferred":[
        "Santa Lucia"
    ],
    "qs:name":"Santa Lucia",
    "qs:photos_9r":0,
    "qs:photos_sr":0,
    "qs:pop_sr":"4",
    "wd:wordcount":1106,
    "wof:name":"Santa Lucia",
    "wof:placetype":"locality",
    "wof:population":4224
},
  "geometry": {"coordinates":[121.4312,14.0349],"type":"Point"}
}