{
  "type": "Feature",
  "properties": {
    "gn:country":"PH",
    "gn:fcode":"PPL",
    "gn:population":4224,
    "iso:country":"PH",
    "name:arg_x_preferred":[
        "Santa Lucia"
    ],
    "name:ast_x_preferred":[
        "Santa Lucia"
    ],
    "name:bre_x_preferred":[
        "Santa Lucia"
    ],
    "name:ces_x_preferred":[
        "Santa Lucia"
    ],
    "name:dan_x_preferred":[
        "Santa Lucia"
    ],
    "name:deu_x_preferred":[
        "Santa Lucia"
    ],
    "name:eml_x_preferred":[
        "Santa Lucia"
    ],
    "name:eng_x_preferred":[
        "Santa Lucia"
    ],
    "name:fil_x_preferred":[
        "Santa Lucia"
    ],
    "name:fin_x_preferred":[
        "Santa Lucia"
    ],
    "name:fra_x_preferred":[
        "Santa Lucia"
    ],
    "name:heb_x_preferred":[
        "\u05e1\u05e0\u05d8\u05d4 \u05dc\u05d5\u05e6'\u05d9\u05d4"
    ],
    "name:ita_x_preferred":[
        "Santa Lucia"
    ],
    "name:jpn_x_preferred":[
        "\u30b5\u30f3\u30bf\u30fb\u30eb\u30c1\u30a2"
    ],
    "name:nap_x_preferred":[
        "Santa Lucia"
    ],
    "name:nld_x_preferred":[
        "Santa Lucia"
    ],
    "name:nno_x_preferred":[
        "Luciasongen"
    ],
    "name:nob_x_preferred":[
        "Luciasangen"
    ],
    "name:pol_x_preferred":[
        "Santa Lucia"
    ],
    "name:por_x_preferred":[
        "Santa Lucia"
    ],
    "name:rus_x_preferred":[
        "\u0421\u0430\u043d\u0442\u0430 \u041b\u044e\u0447\u0438\u044f"
    ],
    "name:sco_x_preferred":[
        "Santa Lucia"
    ],
    "name:srp_x_preferred":[
        "Santa Lucia"
    ],
    "name:swe_x_preferred":[
        "Lucias\u00e5ngen"
    ],
    "name:tha_x_preferred":[
        "\u0e0b\u0e32\u0e19\u0e15\u0e32\u0e25\u0e39\u0e0a\u0e35\u0e2d\u0e32"
    ],
    "name:ukr_x_preferred":[
        "Santa Lucia"
    ],
    "name:zho_x_preferred":[
        "\u6851\u5854\u9732\u742a\u5a05"
    ],
    "qs:name":"Santa Lucia",
    "qs:photos_9r":0,
    "qs:photos_sr":0,
    "qs:pop_sr":"4",
    "wd:wordcount":1106,
    "wof:name":"Santa Lucia",
    "wof:placetype":"locality",
    "wof:population":4224
},
  "geometry": {"coordinates":[121.4312,14.0349],"type":"Point"}
}