{
  "type": "Feature",
  "properties": {
    "gn:admin1_code":"07",
    "gn:admin2_code":"11",
    "gn:admin3_code":"71213000.0",
    "gn:asciiname":"Kang iras",
    "gn:country_code":"PH",
    "gn:dem":249,
    "gn:feature_class":"P",
    "gn:feature_code":"PPL",
    "gn:name":"Kang iras",
    "gn:population":0,
    "gn:timezone":"Asia/Manila",
    "iso:country":"PH",
    "name:fil_x_preferred":[
        "Kang iras"
    ],
    "wof:name":"Kang iras",
    "wof:placetype":"locality"
},
  "geometry": {"coordinates":[124.0645,9.8333],"type":"Point"}
}