{
  "type": "Feature",
  "properties": {
    "gn:country":"PH",
    "gn:fcode":"PPL",
    "gn:population":3131,
    "iso:country":"PH",
    "name:fil_x_preferred":[
        "San Juan de Mata"
    ],
    "name:und_x_variant":[
        "San Juan de Maja"
    ],
    "qs:name":"San Juan de Mata",
    "qs:photos_9r":0,
    "qs:photos_sr":0,
    "qs:pop_sr":"4",
    "wof:name":"San Juan de Mata",
    "wof:placetype":"locality",
    "wof:population":3131
},
  "geometry": {"coordinates":[120.53019999999999,15.5352],"type":"Point"}
}