{
  "type": "Feature",
  "properties": {
    "gn:admin1_code":"01",
    "gn:admin2_code":"51",
    "gn:admin3_code":"15541000.0",
    "gn:asciiname":"Inmalog",
    "gn:country_code":"PH",
    "gn:dem":131,
    "gn:feature_class":"P",
    "gn:feature_code":"PPL",
    "gn:name":"Inmalog",
    "gn:population":0,
    "gn:timezone":"Asia/Manila",
    "iso:country":"PH",
    "name:fil_x_preferred":[
        "Immalog"
    ],
    "wof:name":"Inmalog",
    "wof:placetype":"locality"
},
  "geometry": {"coordinates":[120.5548,16.1677],"type":"Point"}
}