{
  "type": "Feature",
  "properties": {
    "gn:admin1_code":"03",
    "gn:admin2_code":"47",
    "gn:admin3_code":"34915000.0",
    "gn:asciiname":"Caanistaman",
    "gn:country_code":"PH",
    "gn:dem":53,
    "gn:feature_class":"P",
    "gn:feature_code":"PPL",
    "gn:name":"Caanistaman",
    "gn:population":0,
    "gn:timezone":"Asia/Manila",
    "iso:country":"PH",
    "wof:name":"Caanistaman",
    "wof:placetype":"locality"
},
  "geometry": {"coordinates":[120.96666999999999,15.61667],"type":"Point"}
}