{
  "type": "Feature",
  "properties": {
    "gn:country":"PH",
    "gn:fcode":"PPL",
    "gn:pop":5276,
    "iso:country":"PH",
    "name:fil_x_preferred":[
        "Ibabang Tayuman"
    ],
    "qs:name":"Ibabang Tayuman",
    "qs:photos_9r":0,
    "qs:photos_sr":0,
    "qs:pop_sr":"5",
    "wof:name":"Ibabang Tayuman",
    "wof:placetype":"locality",
    "wof:population":5276
},
  "geometry": {"coordinates":[122.51649999999999,13.4042],"type":"Point"}
}