{
  "type": "Feature",
  "properties": {
    "gn:admin1_code":"10",
    "gn:admin2_code":"34",
    "gn:asciiname":"Caromatan",
    "gn:country_code":"PH",
    "gn:dem":2,
    "gn:feature_class":"P",
    "gn:feature_code":"PPL",
    "gn:name":"Caromatan",
    "gn:population":0,
    "gn:timezone":"Asia/Manila",
    "iso:country":"PH",
    "name:eng_x_preferred":[
        "Caromatan"
    ],
    "wof:name":"Caromatan",
    "wof:placetype":"locality"
},
  "geometry": {"coordinates":[123.8669,8.104],"type":"Point"}
}