{
  "type": "Feature",
  "properties": {
    "gn:admin1_code":"15",
    "gn:admin2_code":"44",
    "gn:admin3_code":"144403000.0",
    "gn:asciiname":"Agawa",
    "gn:country_code":"PH",
    "gn:dem":1087,
    "gn:feature_class":"P",
    "gn:feature_code":"PPL",
    "gn:name":"Agawa",
    "gn:population":0,
    "gn:timezone":"Asia/Manila",
    "iso:country":"PH",
    "name:fil_x_preferred":[
        "Agawa"
    ],
    "wof:name":"Agawa",
    "wof:placetype":"locality"
},
  "geometry": {"coordinates":[120.8533,17.1076],"type":"Point"}
}