{
  "type": "Feature",
  "properties": {
    "gn:admin1_code":"06",
    "gn:admin2_code":"H3",
    "gn:admin3_code":"64516000.0",
    "gn:asciiname":"Ayongon",
    "gn:country_code":"PH",
    "gn:dem":16,
    "gn:feature_class":"P",
    "gn:feature_code":"PPL",
    "gn:name":"Ayongon",
    "gn:population":0,
    "gn:timezone":"Asia/Manila",
    "iso:country":"PH",
    "name:fil_x_preferred":[
        "Ayongon"
    ],
    "name:fil_x_variant":[
        "Ayu\u00f1gon"
    ],
    "wof:name":"Ayongon",
    "wof:placetype":"locality"
},
  "geometry": {"coordinates":[122.9075,10.4511],"type":"Point"}
}