{
  "type": "Feature",
  "properties": {
    "gn:admin1_code":"01",
    "gn:admin2_code":"51",
    "gn:admin3_code":"15531000.0",
    "gn:asciiname":"Capitan Tomas",
    "gn:country_code":"PH",
    "gn:dem":36,
    "gn:feature_class":"P",
    "gn:feature_code":"PPL",
    "gn:name":"Capitan Tomas",
    "gn:population":0,
    "gn:timezone":"Asia/Manila",
    "iso:country":"PH",
    "name:fil_x_preferred":[
        "Capitan Tomas"
    ],
    "wof:name":"Capitan Tomas",
    "wof:placetype":"locality"
},
  "geometry": {"coordinates":[120.65052,15.90924],"type":"Point"}
}