{
  "type": "Feature",
  "properties": {
    "gn:admin1_code":"15",
    "gn:admin2_code":"10",
    "gn:asciiname":"Awing",
    "gn:country_code":"PH",
    "gn:dem":1618,
    "gn:feature_class":"P",
    "gn:feature_code":"PPL",
    "gn:name":"Awing",
    "gn:population":0,
    "gn:timezone":"Asia/Manila",
    "iso:country":"PH",
    "name:fil_x_preferred":[
        "Awing"
    ],
    "wof:name":"Awing",
    "wof:placetype":"locality"
},
  "geometry": {"coordinates":[120.95253999999998,16.57278],"type":"Point"}
}