{
  "type": "Feature",
  "properties": {
    "gn:admin1_code":"10",
    "gn:admin2_code":"12",
    "gn:admin3_code":"101320000.0",
    "gn:asciiname":"Malinao",
    "gn:country_code":"PH",
    "gn:dem":1026,
    "gn:feature_class":"P",
    "gn:feature_code":"PPL",
    "gn:name":"Malinao",
    "gn:population":0,
    "gn:timezone":"Asia/Manila",
    "iso:country":"PH",
    "name:ceb_x_preferred":[
        "Malinao"
    ],
    "name:deu_x_preferred":[
        "Malinao"
    ],
    "name:fil_x_preferred":[
        "Malinao"
    ],
    "name:fra_x_preferred":[
        "Malinao"
    ],
    "name:ita_x_preferred":[
        "Malinao"
    ],
    "name:nld_x_preferred":[
        "Malinao"
    ],
    "name:war_x_preferred":[
        "Malinao"
    ],
    "wof:name":"Malinao",
    "wof:placetype":"locality"
},
  "geometry": {"coordinates":[124.70667,8.04972],"type":"Point"}
}