{
  "type": "Feature",
  "properties": {
    "gn:admin1_code":"06",
    "gn:admin2_code":"H3",
    "gn:admin3_code":"64502000.0",
    "gn:asciiname":"Santo Boragwac",
    "gn:country_code":"PH",
    "gn:dem":562,
    "gn:elevation":"0.0",
    "gn:feature_class":"P",
    "gn:feature_code":"PPL",
    "gn:name":"Santo Boragwac",
    "gn:population":0,
    "gn:timezone":"Asia/Manila",
    "iso:country":"PH",
    "name:fil_x_preferred":[
        "Santo Boragwac"
    ],
    "wof:name":"Santo Boragwac",
    "wof:placetype":"locality"
},
  "geometry": {"coordinates":[123.0891,10.4647],"type":"Point"}
}