{
  "type": "Feature",
  "properties": {
    "gn:admin1_code":"09",
    "gn:admin2_code":"ZSI",
    "gn:admin3_code":"98316000.0",
    "gn:asciiname":"Batungan",
    "gn:country_code":"PH",
    "gn:dem":128,
    "gn:feature_class":"P",
    "gn:feature_code":"PPL",
    "gn:name":"Batungan",
    "gn:population":0,
    "gn:timezone":"Asia/Manila",
    "iso:country":"PH",
    "name:fil_x_preferred":[
        "Batungan"
    ],
    "wof:name":"Batungan",
    "wof:placetype":"locality"
},
  "geometry": {"coordinates":[122.38468,7.60884],"type":"Point"}
}