{
  "type": "Feature",
  "properties": {
    "gn:admin1_code":"03",
    "gn:admin2_code":"64",
    "gn:admin3_code":"37103000.0",
    "gn:asciiname":"Tala",
    "gn:country_code":"PH",
    "gn:dem":186,
    "gn:feature_class":"P",
    "gn:feature_code":"PPL",
    "gn:name":"Tala",
    "gn:population":0,
    "gn:timezone":"Asia/Manila",
    "iso:country":"PH",
    "name:fil_x_preferred":[
        "Tala"
    ],
    "wof:name":"Tala",
    "wof:placetype":"locality"
},
  "geometry": {"coordinates":[120.09099999999999,15.5748],"type":"Point"}
}