{
  "type": "Feature",
  "properties": {
    "gn:admin1_code":"15",
    "gn:admin2_code":"10",
    "gn:admin3_code":"141111000.0",
    "gn:asciiname":"Lumog",
    "gn:country_code":"PH",
    "gn:dem":1699,
    "gn:feature_class":"P",
    "gn:feature_code":"PPL",
    "gn:name":"Lumog",
    "gn:population":0,
    "gn:timezone":"Asia/Manila",
    "iso:country":"PH",
    "name:fil_x_preferred":[
        "Lumog"
    ],
    "wof:name":"Lumog",
    "wof:placetype":"locality"
},
  "geometry": {"coordinates":[120.81140000000001,16.7915],"type":"Point"}
}