{
  "type": "Feature",
  "properties": {
    "gn:admin1_code":"40",
    "gn:admin2_code":"20",
    "gn:admin3_code":"42104000.0",
    "gn:asciiname":"Maduya",
    "gn:country_code":"PH",
    "gn:dem":24,
    "gn:feature_class":"P",
    "gn:feature_code":"PPL",
    "gn:name":"Maduya",
    "gn:population":0,
    "gn:timezone":"Asia/Manila",
    "iso:country":"PH",
    "name:fil_x_preferred":[
        "Maduya"
    ],
    "name:urd_x_preferred":[
        "\u0645\u06cc\u0688\u0648\u06cc\u0627"
    ],
    "wof:name":"Maduya",
    "wof:placetype":"locality"
},
  "geometry": {"coordinates":[121.06529999999999,14.3222],"type":"Point"}
}