{
  "type": "Feature",
  "properties": {
    "gn:admin1_code":"40",
    "gn:admin2_code":"H2",
    "gn:admin3_code":"45631000.0",
    "gn:asciiname":"Calasumanga",
    "gn:country_code":"PH",
    "gn:dem":4,
    "gn:feature_class":"P",
    "gn:feature_code":"PPL",
    "gn:name":"Calasumanga",
    "gn:population":0,
    "gn:timezone":"Asia/Manila",
    "iso:country":"PH",
    "name:fil_x_preferred":[
        "Calasumanga"
    ],
    "name:fil_x_variant":[
        "Kalasumanga"
    ],
    "wof:name":"Calasumanga",
    "wof:placetype":"locality"
},
  "geometry": {"coordinates":[121.85344000000001,14.92239],"type":"Point"}
}