{
  "type": "Feature",
  "properties": {
    "gn:admin1_code":"01",
    "gn:admin2_code":"51",
    "gn:admin3_code":"15512000.0",
    "gn:asciiname":"Linmansangan",
    "gn:country_code":"PH",
    "gn:dem":36,
    "gn:feature_class":"P",
    "gn:feature_code":"PPL",
    "gn:name":"Linmansangan",
    "gn:population":0,
    "gn:timezone":"Asia/Manila",
    "iso:country":"PH",
    "name:fil_x_preferred":[
        "Linmansangan"
    ],
    "name:fil_x_variant":[
        "Linmanzangan"
    ],
    "wof:name":"Linmansangan",
    "wof:placetype":"locality"
},
  "geometry": {"coordinates":[120.5692,16.0502],"type":"Point"}
}