{
  "type": "Feature",
  "properties": {
    "gn:admin1_code":"40",
    "gn:admin2_code":"09",
    "gn:admin3_code":"41017000.0",
    "gn:asciiname":"Bituca",
    "gn:country_code":"PH",
    "gn:dem":127,
    "gn:feature_class":"P",
    "gn:feature_code":"PPL",
    "gn:name":"Bituca",
    "gn:population":0,
    "gn:timezone":"Asia/Manila",
    "iso:country":"PH",
    "name:fil_x_preferred":[
        "Bituca"
    ],
    "wof:name":"Bituca",
    "wof:placetype":"locality"
},
  "geometry": {"coordinates":[121.11667,14.03333],"type":"Point"}
}