{
  "type": "Feature",
  "properties": {
    "gn:admin1_code":"01",
    "gn:admin2_code":"29",
    "gn:admin3_code":"12906000.0",
    "gn:asciiname":"Dagupan",
    "gn:country_code":"PH",
    "gn:dem":25,
    "gn:feature_class":"P",
    "gn:feature_code":"PPL",
    "gn:name":"Dagupan",
    "gn:population":0,
    "gn:timezone":"Asia/Manila",
    "iso:country":"PH",
    "name:fil_x_preferred":[
        "Dagupan"
    ],
    "wof:name":"Dagupan",
    "wof:placetype":"locality"
},
  "geometry": {"coordinates":[120.48278000000001,17.16517],"type":"Point"}
}