{
  "type": "Feature",
  "properties": {
    "gn:country":"PH",
    "gn:fcode":"PPL",
    "gn:pop":2878,
    "iso:country":"PH",
    "name:fil_x_preferred":[
        "Tabon"
    ],
    "qs:name":"Tabon",
    "qs:photos_9r":0,
    "qs:photos_sr":0,
    "qs:pop_sr":"4",
    "wof:name":"Tabon",
    "wof:placetype":"locality",
    "wof:population":2878
},
  "geometry": {"coordinates":[123.32599999999999,10.3019],"type":"Point"}
}