{
  "type": "Feature",
  "properties": {
    "iso:country":"PH",
    "name:bcl_x_preferred":[
        "Real"
    ],
    "name:cat_x_preferred":[
        "Real"
    ],
    "name:cbk_zam_x_preferred":[
        "Real"
    ],
    "name:ceb_x_preferred":[
        "Real"
    ],
    "name:deu_x_preferred":[
        "Real"
    ],
    "name:eng_x_preferred":[
        "Real"
    ],
    "name:fil_x_preferred":[
        "Real"
    ],
    "name:fra_x_preferred":[
        "Real"
    ],
    "name:ilo_x_preferred":[
        "Real"
    ],
    "name:ind_x_preferred":[
        "Real"
    ],
    "name:ita_x_preferred":[
        "Real"
    ],
    "name:nld_x_preferred":[
        "Real"
    ],
    "name:oci_x_preferred":[
        "Real"
    ],
    "name:pag_x_preferred":[
        "Real"
    ],
    "name:pam_x_preferred":[
        "Real"
    ],
    "name:swe_x_preferred":[
        "Real"
    ],
    "name:tgl_x_preferred":[
        "Real"
    ],
    "name:unk_x_variant":[
        "Puerto Real"
    ],
    "name:vie_x_preferred":[
        "Real"
    ],
    "name:war_x_preferred":[
        "Real"
    ],
    "name:zho_x_preferred":[
        "\u96f7\u4e9e\u723e"
    ],
    "qs:gn_country":"PH",
    "qs:gn_fcode":"PPL",
    "qs:gn_pop":9163,
    "qs:name":"Real",
    "qs:name_adm0":"Philippines",
    "qs:name_adm1":"Calabarzon",
    "qs:photos":167,
    "qs:photos_1k":34,
    "qs:photos_9k":1,
    "qs:photos_9r":4,
    "qs:photos_all":167,
    "qs:photos_sr":4,
    "qs:placetype":"Town",
    "qs:pop_sr":"5",
    "qs:woe_adm0":23424934,
    "wd:wordcount":359,
    "wof:name":"Real",
    "wof:placetype":"locality",
    "wof:population":9163
},
  "geometry": {"coordinates":[121.60411999999999,14.66397],"type":"Point"}
}