{
  "type": "Feature",
  "properties": {
    "gn:admin1_code":"08",
    "gn:admin2_code":"55",
    "gn:admin3_code":"86021000.0",
    "gn:asciiname":"Burac",
    "gn:country_code":"PH",
    "gn:dem":57,
    "gn:feature_class":"P",
    "gn:feature_code":"PPL",
    "gn:name":"Burac",
    "gn:population":0,
    "gn:timezone":"Asia/Manila",
    "iso:country":"PH",
    "name:fil_x_preferred":[
        "Burac"
    ],
    "wof:name":"Burac",
    "wof:placetype":"locality"
},
  "geometry": {"coordinates":[124.926,11.5437],"type":"Point"}
}