{
  "type": "Feature",
  "properties": {
    "gn:admin1_code":"14",
    "gn:admin2_code":"60",
    "gn:admin3_code":"156613000.0",
    "gn:asciiname":"Binuang",
    "gn:country_code":"PH",
    "gn:dem":113,
    "gn:feature_class":"P",
    "gn:feature_code":"PPL",
    "gn:name":"Binuang",
    "gn:population":0,
    "gn:timezone":"Asia/Manila",
    "iso:country":"PH",
    "name:fil_x_preferred":[
        "Binuang"
    ],
    "wof:name":"Binuang",
    "wof:placetype":"locality"
},
  "geometry": {"coordinates":[121.15000000000001,5.98333],"type":"Point"}
}