{
  "type": "Feature",
  "properties": {
    "gn:admin1_code":"01",
    "gn:admin2_code":"29",
    "gn:admin3_code":"12918000.0",
    "gn:asciiname":"Cabaroan",
    "gn:country_code":"PH",
    "gn:dem":39,
    "gn:feature_class":"P",
    "gn:feature_code":"PPL",
    "gn:name":"Cabaroan",
    "gn:population":0,
    "gn:timezone":"Asia/Manila",
    "iso:country":"PH",
    "name:fil_x_preferred":[
        "Cabaroan"
    ],
    "name:fil_x_variant":[
        "Cabaruan"
    ],
    "wof:name":"Cabaroan",
    "wof:placetype":"locality"
},
  "geometry": {"coordinates":[120.4696,17.3187],"type":"Point"}
}