{
  "type": "Feature",
  "properties": {
    "gn:admin1_code":"06",
    "gn:admin2_code":"H3",
    "gn:admin3_code":"64514000.0",
    "gn:asciiname":"Camp Lark",
    "gn:country_code":"PH",
    "gn:dem":85,
    "gn:feature_class":"P",
    "gn:feature_code":"PPL",
    "gn:name":"Camp Lark",
    "gn:population":0,
    "gn:timezone":"Asia/Manila",
    "iso:country":"PH",
    "name:eng_x_preferred":[
        "Camp Lark"
    ],
    "name:und_x_variant":[
        "Camp Clark"
    ],
    "wof:name":"Camp Lark",
    "wof:placetype":"locality"
},
  "geometry": {"coordinates":[123.08499999999999,10.2265],"type":"Point"}
}