{
  "type": "Feature",
  "properties": {
    "gn:admin1_code":"05",
    "gn:admin2_code":"05",
    "gn:admin3_code":"50503000.0",
    "gn:asciiname":"Cituinan",
    "gn:country_code":"PH",
    "gn:dem":284,
    "gn:feature_class":"P",
    "gn:feature_code":"PPL",
    "gn:name":"Cituinan",
    "gn:population":0,
    "gn:timezone":"Asia/Manila",
    "iso:country":"PH",
    "name:fil_x_preferred":[
        "Cituinan"
    ],
    "wof:name":"Cituinan",
    "wof:placetype":"locality"
},
  "geometry": {"coordinates":[123.66667,13.16667],"type":"Point"}
}