{
  "type": "Feature",
  "properties": {
    "gn:admin1_code":"40",
    "gn:admin2_code":"09",
    "gn:admin3_code":"41016000.0",
    "gn:asciiname":"Nagiba",
    "gn:country_code":"PH",
    "gn:dem":153,
    "gn:feature_class":"P",
    "gn:feature_code":"PPL",
    "gn:name":"Nagiba",
    "gn:population":0,
    "gn:timezone":"Asia/Manila",
    "iso:country":"PH",
    "name:fil_x_preferred":[
        "Nagiba"
    ],
    "name:und_x_variant":[
        "Nagaba"
    ],
    "wof:name":"Nagiba",
    "wof:placetype":"locality"
},
  "geometry": {"coordinates":[120.91245000000001,13.70626],"type":"Point"}
}