{
  "type": "Feature",
  "properties": {
    "gn:admin1_code":"10",
    "gn:admin2_code":"42",
    "gn:admin3_code":"104215000.0",
    "gn:asciiname":"Migcanauay",
    "gn:country_code":"PH",
    "gn:dem":2,
    "gn:feature_class":"P",
    "gn:feature_code":"PPL",
    "gn:name":"Migcanauay",
    "gn:population":0,
    "gn:timezone":"Asia/Manila",
    "iso:country":"PH",
    "name:fil_x_preferred":[
        "Migcanauay"
    ],
    "wof:name":"Migcanauay",
    "wof:placetype":"locality"
},
  "geometry": {"coordinates":[123.7572,8.0616],"type":"Point"}
}