{
  "type": "Feature",
  "properties": {
    "gn:admin1_code":"06",
    "gn:admin2_code":"H3",
    "gn:admin3_code":"64517000.0",
    "gn:asciiname":"Ronggo",
    "gn:country_code":"PH",
    "gn:dem":41,
    "gn:feature_class":"P",
    "gn:feature_code":"PPL",
    "gn:name":"Ronggo",
    "gn:population":0,
    "gn:timezone":"Asia/Manila",
    "iso:country":"PH",
    "name:fil_x_preferred":[
        "Ronggo"
    ],
    "wof:name":"Ronggo",
    "wof:placetype":"locality"
},
  "geometry": {"coordinates":[123.009,10.3009],"type":"Point"}
}