{
  "type": "Feature",
  "properties": {
    "gn:admin1_code":"15",
    "gn:admin2_code":"27",
    "gn:admin3_code":"142710000.0",
    "gn:asciiname":"Rasan",
    "gn:country_code":"PH",
    "gn:dem":1633,
    "gn:feature_class":"P",
    "gn:feature_code":"PPL",
    "gn:name":"Rasan",
    "gn:population":0,
    "gn:timezone":"Asia/Manila",
    "iso:country":"PH",
    "name:ceb_x_preferred":[
        "Rasan"
    ],
    "name:fas_x_preferred":[
        "\u0631\u0633\u0646"
    ],
    "name:fil_x_preferred":[
        "Rasan"
    ],
    "wof:name":"Rasan",
    "wof:placetype":"locality"
},
  "geometry": {"coordinates":[120.91884,16.66418],"type":"Point"}
}