{
  "type": "Feature",
  "properties": {
    "gn:admin1_code":"09",
    "gn:admin2_code":"66",
    "gn:admin3_code":"97308000.0",
    "gn:asciiname":"Dipalo",
    "gn:country_code":"PH",
    "gn:dem":58,
    "gn:feature_class":"P",
    "gn:feature_code":"PPL",
    "gn:name":"Dipalo",
    "gn:population":0,
    "gn:timezone":"Asia/Manila",
    "iso:country":"PH",
    "name:eng_x_preferred":[
        "Dipalo"
    ],
    "wof:name":"Dipalo",
    "wof:placetype":"locality"
},
  "geometry": {"coordinates":[123.33750000000001,8.1524],"type":"Point"}
}