{
  "type": "Feature",
  "properties": {
    "gn:admin1_code":"05",
    "gn:admin2_code":"16",
    "gn:admin3_code":"51730000.0",
    "gn:asciiname":"Pugod",
    "gn:country_code":"PH",
    "gn:dem":11,
    "gn:feature_class":"P",
    "gn:feature_code":"PPL",
    "gn:name":"Pugod",
    "gn:population":0,
    "gn:timezone":"Asia/Manila",
    "iso:country":"PH",
    "name:fil_x_preferred":[
        "Pugod"
    ],
    "wof:name":"Pugod",
    "wof:placetype":"locality"
},
  "geometry": {"coordinates":[122.6973,13.8445],"type":"Point"}
}