{
  "type": "Feature",
  "properties": {
    "gn:admin1_code":"02",
    "gn:admin2_code":"31",
    "gn:admin3_code":"23102000.0",
    "gn:asciiname":"Ingud Norte",
    "gn:country_code":"PH",
    "gn:dem":65,
    "gn:feature_class":"P",
    "gn:feature_code":"PPL",
    "gn:name":"Ingud Norte",
    "gn:population":0,
    "gn:timezone":"Asia/Manila",
    "iso:country":"PH",
    "name:fil_x_preferred":[
        "Ingud Norte"
    ],
    "wof:name":"Ingud Norte",
    "wof:placetype":"locality"
},
  "geometry": {"coordinates":[121.76188,16.80852],"type":"Point"}
}