{
  "type": "Feature",
  "properties": {
    "gn:country":"PH",
    "gn:fcode":"PPL",
    "gn:pop":4566,
    "iso:country":"PH",
    "name:fil_x_preferred":[
        "Palsong"
    ],
    "qs:name":"Palsong",
    "qs:photos_9r":0,
    "qs:photos_sr":0,
    "qs:pop_sr":"4",
    "wof:name":"Palsong",
    "wof:placetype":"locality",
    "wof:population":4566
},
  "geometry": {"coordinates":[123.2963,13.4248],"type":"Point"}
}