{
  "type": "Feature",
  "properties": {
    "gn:admin1_code":"15",
    "gn:admin2_code":"01",
    "gn:admin3_code":"140121000.0",
    "gn:asciiname":"Cagutungan",
    "gn:cc2":"PH",
    "gn:country_code":"PH",
    "gn:dem":161,
    "gn:feature_class":"P",
    "gn:feature_code":"PPL",
    "gn:name":"Cagutu\u00f1gan",
    "gn:population":0,
    "gn:timezone":"Asia/Manila",
    "iso:country":"PH",
    "name:und_x_variant":[
        "Kagotungan",
        "Cagutu\u00f1gan"
    ],
    "wof:name":"Cagutungan",
    "wof:placetype":"locality"
},
  "geometry": {"coordinates":[120.59999999999999,17.46667],"type":"Point"}
}