{
  "type": "Feature",
  "properties": {
    "gn:admin1_code":"01",
    "gn:admin2_code":"51",
    "gn:admin3_code":"15524000.0",
    "gn:asciiname":"Tabo-Sili",
    "gn:country_code":"PH",
    "gn:dem":19,
    "gn:feature_class":"P",
    "gn:feature_code":"PPL",
    "gn:name":"Tabo-Sili",
    "gn:population":0,
    "gn:timezone":"Asia/Manila",
    "iso:country":"PH",
    "name:fil_x_preferred":[
        "Sili"
    ],
    "name:und_x_variant":[
        "Tabo-Sili"
    ],
    "wof:name":"Tabo-Sili",
    "wof:placetype":"locality"
},
  "geometry": {"coordinates":[120.4517,15.93477],"type":"Point"}
}