{
  "type": "Feature",
  "properties": {
    "gn:admin1_code":"06",
    "gn:admin2_code":"30",
    "gn:admin3_code":"63003000.0",
    "gn:asciiname":"Batuan",
    "gn:country_code":"PH",
    "gn:dem":9,
    "gn:feature_class":"P",
    "gn:feature_code":"PPL",
    "gn:name":"Batuan",
    "gn:population":0,
    "gn:timezone":"Asia/Manila",
    "iso:country":"PH",
    "name:fil_x_preferred":[
        "Batuan"
    ],
    "wof:name":"Batuan",
    "wof:placetype":"locality"
},
  "geometry": {"coordinates":[122.72499999999999,10.955],"type":"Point"}
}