{
  "type": "Feature",
  "properties": {
    "gn:admin1_code":"06",
    "gn:admin2_code":"18",
    "gn:admin3_code":"61909000.0",
    "gn:asciiname":"Bunga",
    "gn:country_code":"PH",
    "gn:dem":2,
    "gn:feature_class":"P",
    "gn:feature_code":"PPL",
    "gn:name":"Bunga",
    "gn:population":0,
    "gn:timezone":"Asia/Manila",
    "iso:country":"PH",
    "name:und_x_variant":[
        "Bo\u00f1ga",
        "Bungo",
        "Bu\u00f1ga",
        "Bunga"
    ],
    "wof:name":"Bunga",
    "wof:placetype":"locality"
},
  "geometry": {"coordinates":[122.82028,11.56639],"type":"Point"}
}