{
  "type": "Feature",
  "properties": {
    "gn:admin1_code":"02",
    "gn:admin2_code":"14",
    "gn:admin3_code":"21503000.0",
    "gn:asciiname":"Cabaritan",
    "gn:cc2":"PH",
    "gn:country_code":"PH",
    "gn:dem":20,
    "gn:feature_class":"P",
    "gn:feature_code":"PPL",
    "gn:name":"Cabaritan",
    "gn:population":0,
    "gn:timezone":"Asia/Manila",
    "iso:country":"PH",
    "name:und_x_variant":[
        "Caratan",
        "Cabaritan"
    ],
    "wof:name":"Cabaritan",
    "wof:placetype":"locality"
},
  "geometry": {"coordinates":[121.58333,18.23333],"type":"Point"}
}