{
  "type": "Feature",
  "properties": {
    "gn:admin1_code":"03",
    "gn:admin2_code":"63",
    "gn:admin3_code":"36912000.0",
    "gn:asciiname":"Serrano",
    "gn:country_code":"PH",
    "gn:dem":23,
    "gn:feature_class":"P",
    "gn:feature_code":"PPL",
    "gn:name":"Serrano",
    "gn:population":0,
    "gn:timezone":"Asia/Manila",
    "iso:country":"PH",
    "name:cat_x_preferred":[
        "Serrano"
    ],
    "name:ceb_x_preferred":[
        "Serrano"
    ],
    "name:ces_x_preferred":[
        "Serrano"
    ],
    "name:deu_x_preferred":[
        "Serrano"
    ],
    "name:fil_x_preferred":[
        "Serrano"
    ],
    "name:fin_x_preferred":[
        "Serrano"
    ],
    "name:fra_x_preferred":[
        "Serrano"
    ],
    "name:heb_x_preferred":[
        "\u05e1\u05e8\u05d0\u05e0\u05d5"
    ],
    "name:hrv_x_preferred":[
        "Serrano"
    ],
    "name:ita_x_preferred":[
        "Serrano"
    ],
    "name:por_x_preferred":[
        "Serrano"
    ],
    "name:rus_x_preferred":[
        "\u0421\u0435\u0440\u0440\u0430\u043d\u043e"
    ],
    "name:spa_x_preferred":[
        "Serrano"
    ],
    "name:swe_x_preferred":[
        "Serrano"
    ],
    "wof:name":"Serrano",
    "wof:placetype":"locality"
},
  "geometry": {"coordinates":[120.6375,15.6696],"type":"Point"}
}