{
  "type": "Feature",
  "properties": {
    "iso:country":"PH",
    "name:bcl_x_preferred":[
        "Capoocan"
    ],
    "name:cbk_zam_x_preferred":[
        "Capoocan"
    ],
    "name:ceb_x_preferred":[
        "Capoocan"
    ],
    "name:deu_x_preferred":[
        "Capoocan"
    ],
    "name:dut_x_preferred":[
        "Capoocan"
    ],
    "name:eng_x_preferred":[
        "Capoocan"
    ],
    "name:fra_x_preferred":[
        "Capoocan"
    ],
    "name:fre_x_preferred":[
        "Capoocan"
    ],
    "name:ger_x_preferred":[
        "Capoocan"
    ],
    "name:ilo_x_preferred":[
        "Capoocan"
    ],
    "name:ind_x_preferred":[
        "Capoocan"
    ],
    "name:ita_x_preferred":[
        "Capoocan"
    ],
    "name:nld_x_preferred":[
        "Capoocan"
    ],
    "name:pag_x_preferred":[
        "Capoocan"
    ],
    "name:pam_x_preferred":[
        "Capoocan"
    ],
    "name:swe_x_preferred":[
        "Capoocan"
    ],
    "name:tgl_x_preferred":[
        "Capoocan"
    ],
    "name:vie_x_preferred":[
        "Capoocan"
    ],
    "name:war_x_preferred":[
        "Capoocan"
    ],
    "qs:gn_country":"PH",
    "qs:gn_fcode":"PPLA3",
    "qs:gn_pop":8473,
    "qs:name":"Capoocan",
    "qs:name_adm0":"Philippines",
    "qs:name_adm1":"Eastern Visayas",
    "qs:photos":7,
    "qs:photos_1k":1,
    "qs:photos_9k":1,
    "qs:photos_9r":1,
    "qs:photos_all":7,
    "qs:photos_sr":1,
    "qs:placetype":"Town",
    "qs:pop_sr":"5",
    "qs:woe_adm0":23424934,
    "wd:wordcount":132,
    "wof:name":"Capoocan",
    "wof:placetype":"locality",
    "wof:population":8473
},
  "geometry": {"coordinates":[124.64194000000001,11.29333],"type":"Point"}
}