{
  "type": "Feature",
  "properties": {
    "gn:admin1_code":"06",
    "gn:admin2_code":"J3",
    "gn:admin3_code":"67904000.0",
    "gn:asciiname":"Libas",
    "gn:country_code":"PH",
    "gn:dem":10,
    "gn:feature_class":"P",
    "gn:feature_code":"PPL",
    "gn:name":"Libas",
    "gn:population":0,
    "gn:timezone":"Asia/Manila",
    "iso:country":"PH",
    "name:fil_x_preferred":[
        "Libas"
    ],
    "wof:name":"Libas",
    "wof:placetype":"locality"
},
  "geometry": {"coordinates":[122.7223,10.639],"type":"Point"}
}