{
  "type": "Feature",
  "properties": {
    "gn:admin1_code":"15",
    "gn:admin2_code":"01",
    "gn:admin3_code":"140114000.0",
    "gn:asciiname":"Domagas",
    "gn:country_code":"PH",
    "gn:dem":461,
    "gn:feature_class":"P",
    "gn:feature_code":"PPL",
    "gn:name":"Domagas",
    "gn:population":0,
    "gn:timezone":"Asia/Manila",
    "iso:country":"PH",
    "name:fil_x_preferred":[
        "Domagas"
    ],
    "wof:name":"Domagas",
    "wof:placetype":"locality"
},
  "geometry": {"coordinates":[120.75,17.36667000000001],"type":"Point"}
}