{
  "type": "Feature",
  "properties": {
    "gn:admin1_code":"03",
    "gn:admin2_code":"47",
    "gn:admin3_code":"34922000.0",
    "gn:asciiname":"Bantog",
    "gn:country_code":"PH",
    "gn:dem":30,
    "gn:feature_class":"P",
    "gn:feature_code":"PPL",
    "gn:name":"Bantog",
    "gn:population":0,
    "gn:timezone":"Asia/Manila",
    "iso:country":"PH",
    "name:fil_x_preferred":[
        "Bantog"
    ],
    "name:fil_x_variant":[
        "Bantog Primero"
    ],
    "wof:name":"Bantog",
    "wof:placetype":"locality"
},
  "geometry": {"coordinates":[120.8036,15.5416],"type":"Point"}
}