{
  "type": "Feature",
  "properties": {
    "gn:admin1_code":"07",
    "gn:admin2_code":"46",
    "gn:asciiname":"Cantupa",
    "gn:country_code":"PH",
    "gn:dem":9,
    "gn:feature_class":"P",
    "gn:feature_code":"PPL",
    "gn:name":"Cantupa",
    "gn:population":0,
    "gn:timezone":"Asia/Manila",
    "iso:country":"PH",
    "name:fil_x_preferred":[
        "Cantupa"
    ],
    "wof:name":"Cantupa",
    "wof:placetype":"locality"
},
  "geometry": {"coordinates":[123.2278,10.0192],"type":"Point"}
}