{
  "type": "Feature",
  "properties": {
    "gn:admin1_code":"03",
    "gn:admin2_code":"50",
    "gn:admin3_code":"35403000.0",
    "gn:asciiname":"Santo Nino Tabuan",
    "gn:country_code":"PH",
    "gn:dem":12,
    "gn:feature_class":"P",
    "gn:feature_code":"PPL",
    "gn:name":"Santo Ni\u00f1o Tabuan",
    "gn:population":0,
    "gn:timezone":"Asia/Manila",
    "iso:country":"PH",
    "name:fil_x_preferred":[
        "Tabuan"
    ],
    "name:und_x_variant":[
        "Santo Ni\u00f1o Tabuan"
    ],
    "wof:name":"Santo Nino Tabuan",
    "wof:placetype":"locality"
},
  "geometry": {"coordinates":[120.79957,15.18152],"type":"Point"}
}