{
  "type": "Feature",
  "properties": {
    "gn:admin1_code":"08",
    "gn:admin2_code":"37",
    "gn:admin3_code":"83726000.0",
    "gn:asciiname":"Tonoy",
    "gn:country_code":"PH",
    "gn:dem":61,
    "gn:feature_class":"P",
    "gn:feature_code":"PPL",
    "gn:name":"Tonoy",
    "gn:population":0,
    "gn:timezone":"Asia/Manila",
    "iso:country":"PH",
    "name:eng_x_preferred":[
        "Tonoy"
    ],
    "name:und_x_variant":[
        "Lonoy"
    ],
    "wof:name":"Tonoy",
    "wof:placetype":"locality"
},
  "geometry": {"coordinates":[124.57040000000001,11.2166],"type":"Point"}
}