{
  "type": "Feature",
  "properties": {
    "gn:country":"PH",
    "gn:fcode":"ADM3",
    "gn:pop":19450,
    "iso:country":"PH",
    "name:bcl_x_preferred":[
        "Pi\u00f1an"
    ],
    "name:ceb_x_preferred":[
        "Pi\u00f1an"
    ],
    "name:deu_x_preferred":[
        "Pi\u00f1an"
    ],
    "name:eng_x_preferred":[
        "Municipality of Pi\u00f1an"
    ],
    "name:eng_x_variant":[
        "Pi\u00f1an"
    ],
    "name:fas_x_preferred":[
        "\u067e\u06cc\u0646\u0627\u0646"
    ],
    "name:fra_x_preferred":[
        "Pi\u00f1an"
    ],
    "name:ilo_x_preferred":[
        "Pi\u00f1an"
    ],
    "name:ind_x_preferred":[
        "Pi\u00f1an"
    ],
    "name:ita_x_preferred":[
        "Pi\u00f1an"
    ],
    "name:nld_x_preferred":[
        "Pi\u00f1an"
    ],
    "name:pag_x_preferred":[
        "Pi\u00f1an"
    ],
    "name:pam_x_preferred":[
        "Pi\u00f1an"
    ],
    "name:spa_x_preferred":[
        "Pi\u00f1\u00e1n"
    ],
    "name:swe_x_preferred":[
        "Pi\u00f1an"
    ],
    "name:tgl_x_preferred":[
        "Pi\u00f1an"
    ],
    "name:unk_x_variant":[
        "New Pi\u00f1an"
    ],
    "name:vie_x_preferred":[
        "Pi\u00f1an"
    ],
    "name:war_x_preferred":[
        "Pi\u00f1an"
    ],
    "qs:name":"Municipality of Pi\u00f1an",
    "qs:photos_9r":0,
    "qs:photos_sr":0,
    "qs:pop_sr":"6",
    "wd:wordcount":135,
    "wof:name":"Municipality of Pi\u00f1an",
    "wof:placetype":"localadmin",
    "wof:population":19450
},
  "geometry": {"coordinates":[123.43810000000001,8.4025],"type":"Point"}
}