{
  "type": "Feature",
  "properties": {
    "gn:country":"PH",
    "gn:fcode":"ADM3",
    "gn:pop":19450,
    "iso:country":"PH",
    "name:eng_x_preferred":[
        "Municipality of Pi\u00f1an"
    ],
    "name:unk_x_variant":[
        "New Pi\u00f1an"
    ],
    "qs:name":"Municipality of Pi\u00f1an",
    "qs:photos_9r":0,
    "qs:photos_sr":0,
    "qs:pop_sr":"6",
    "wd:wordcount":135,
    "wof:name":"Municipality of Pi\u00f1an",
    "wof:placetype":"localadmin",
    "wof:population":19450
},
  "geometry": {"coordinates":[123.43810000000001,8.4025],"type":"Point"}
}