{
  "type": "Feature",
  "properties": {
    "gn:admin1_code":"15",
    "gn:admin2_code":"32",
    "gn:admin3_code":"143211000.0",
    "gn:asciiname":"Calaocan",
    "gn:country_code":"PH",
    "gn:dem":80,
    "gn:feature_class":"P",
    "gn:feature_code":"PPL",
    "gn:name":"Calaocan",
    "gn:population":0,
    "gn:timezone":"Asia/Manila",
    "iso:country":"PH",
    "wof:name":"Calaocan",
    "wof:placetype":"locality"
},
  "geometry": {"coordinates":[121.60212,17.50372999999999],"type":"Point"}
}