{
  "type": "Feature",
  "properties": {
    "gn:admin1_code":"07",
    "gn:admin2_code":"21",
    "gn:admin3_code":"72225000.0",
    "gn:asciiname":"Guiwanon",
    "gn:country_code":"PH",
    "gn:dem":66,
    "gn:feature_class":"P",
    "gn:feature_code":"PPL",
    "gn:name":"Guiwanon",
    "gn:population":0,
    "gn:timezone":"Asia/Manila",
    "iso:country":"PH",
    "name:fil_x_preferred":[
        "Guiwanon"
    ],
    "name:und_x_variant":[
        "Givanon",
        "Giwanon"
    ],
    "wof:name":"Guiwanon",
    "wof:placetype":"locality"
},
  "geometry": {"coordinates":[123.32080000000001,9.6017],"type":"Point"}
}