{
  "type": "Feature",
  "properties": {
    "gn:admin1_code":"11",
    "gn:admin2_code":"25",
    "gn:admin3_code":"112402000.0",
    "gn:asciiname":"Ipuan",
    "gn:country_code":"PH",
    "gn:dem":379,
    "gn:feature_class":"P",
    "gn:feature_code":"PPL",
    "gn:name":"Ipuan",
    "gn:population":0,
    "gn:timezone":"Asia/Manila",
    "iso:country":"PH",
    "name:fil_x_preferred":[
        "Ipuan"
    ],
    "wof:name":"Ipuan",
    "wof:placetype":"locality"
},
  "geometry": {"coordinates":[125.35111000000001,7.46694],"type":"Point"}
}