{
  "type": "Feature",
  "properties": {
    "gn:admin1_code":"14",
    "gn:admin2_code":"60",
    "gn:asciiname":"Huithuit",
    "gn:country_code":"PH",
    "gn:dem":4,
    "gn:feature_class":"P",
    "gn:feature_code":"PPL",
    "gn:name":"Huithuit",
    "gn:population":0,
    "gn:timezone":"Asia/Manila",
    "iso:country":"PH",
    "name:eng_x_preferred":[
        "Huithuit"
    ],
    "name:und_x_variant":[
        "Howit Howit"
    ],
    "wof:name":"Huithuit",
    "wof:placetype":"locality"
},
  "geometry": {"coordinates":[120.82288,5.70648],"type":"Point"}
}