{
  "type": "Feature",
  "properties": {
    "gn:admin1_code":"01",
    "gn:admin2_code":"28",
    "gn:admin3_code":"12803000.0",
    "gn:asciiname":"Palisen",
    "gn:country_code":"PH",
    "gn:dem":42,
    "gn:feature_class":"P",
    "gn:feature_code":"PPL",
    "gn:name":"Palisen",
    "gn:population":0,
    "gn:timezone":"Asia/Manila",
    "iso:country":"PH",
    "name:fil_x_preferred":[
        "Palisen"
    ],
    "wof:name":"Palisen",
    "wof:placetype":"locality"
},
  "geometry": {"coordinates":[120.4739,17.906],"type":"Point"}
}