{
  "type": "Feature",
  "properties": {
    "gn:country":"PH",
    "gn:fcode":"PPL",
    "gn:population":2637,
    "iso:country":"PH",
    "name:fil_x_preferred":[
        "Kabulohan"
    ],
    "name:und_x_variant":[
        "Cabulohan"
    ],
    "qs:name":"Kabulohan",
    "qs:photos_9r":0,
    "qs:photos_sr":0,
    "qs:pop_sr":"4",
    "wof:name":"Kabulohan",
    "wof:placetype":"locality",
    "wof:population":2637
},
  "geometry": {"coordinates":[125.27667,8.04333],"type":"Point"}
}