{
  "type": "Feature",
  "properties": {
    "gn:admin1_code":"41",
    "gn:admin2_code":"38",
    "gn:admin3_code":"174001000.0",
    "gn:asciiname":"Amdingon",
    "gn:country_code":"PH",
    "gn:dem":19,
    "gn:feature_class":"P",
    "gn:feature_code":"PPL",
    "gn:name":"Amdingon",
    "gn:population":0,
    "gn:timezone":"Asia/Manila",
    "iso:country":"PH",
    "name:fil_x_preferred":[
        "AmoiNgan"
    ],
    "name:fil_x_variant":[
        "Amdingon",
        "Amoingon"
    ],
    "wof:name":"Amdingon",
    "wof:placetype":"locality"
},
  "geometry": {"coordinates":[121.8271,13.3974],"type":"Point"}
}