{
  "type": "Feature",
  "properties": {
    "gn:country":"PH",
    "gn:fcode":"PPL",
    "gn:pop":2112,
    "iso:country":"PH",
    "name:fil_x_preferred":[
        "Patindeguen"
    ],
    "qs:name":"Patindeguen",
    "qs:photos_9r":0,
    "qs:photos_sr":0,
    "qs:pop_sr":"4",
    "wof:name":"Patindeguen",
    "wof:placetype":"locality",
    "wof:population":2112
},
  "geometry": {"coordinates":[124.49833,7.21972],"type":"Point"}
}