{
  "type": "Feature",
  "properties": {
    "gn:gn_country":"PH",
    "gn:gn_fcode":"PPLA3",
    "gn:gn_pop":3573,
    "gn:population":3573,
    "iso:country":"PH",
    "name:bcl_x_preferred":[
        "Tumauini"
    ],
    "name:cat_x_preferred":[
        "Tumauini"
    ],
    "name:dut_x_preferred":[
        "Tumauini"
    ],
    "name:eng_x_preferred":[
        "Tumauini"
    ],
    "name:fil_x_preferred":[
        "Tumauini"
    ],
    "name:fre_x_preferred":[
        "Tumauini"
    ],
    "name:ger_x_preferred":[
        "Tumauini"
    ],
    "name:ilo_x_preferred":[
        "Tumauini"
    ],
    "name:ind_x_preferred":[
        "Tumauini"
    ],
    "name:ita_x_preferred":[
        "Tumauini"
    ],
    "name:oci_x_preferred":[
        "Tumauini"
    ],
    "name:pag_x_preferred":[
        "Tumauini"
    ],
    "name:pam_x_preferred":[
        "Tumauini"
    ],
    "name:spa_x_preferred":[
        "Tamauini"
    ],
    "name:swe_x_preferred":[
        "Tumauini"
    ],
    "name:tgl_x_preferred":[
        "Tumauini"
    ],
    "name:vie_x_preferred":[
        "Tumauini"
    ],
    "name:war_x_preferred":[
        "Tumauini"
    ],
    "qs_pg:aaroncc":"PH",
    "qs_pg:gn_country":"PH",
    "qs_pg:gn_fcode":"PPLA3",
    "qs_pg:gn_pop":3573,
    "qs_pg:name":"Tumauini",
    "qs_pg:photos_9r":0,
    "qs_pg:photos_sr":0,
    "qs_pg:pop_sr":4,
    "qs_pg:qs_pg_placetype":"locality",
    "wof:name":"Tumauini",
    "wof:placetype":"locality",
    "wof:population":3573
},
  "geometry": {"coordinates":[121.80853999999999,17.27663],"type":"Point"}
}