{
  "type": "Feature",
  "properties": {
    "gn:admin1_code":"11",
    "gn:admin2_code":"P3",
    "gn:admin3_code":"118603000.0",
    "gn:asciiname":"Kabanga",
    "gn:country_code":"PH",
    "gn:dem":46,
    "gn:feature_class":"P",
    "gn:feature_code":"PPL",
    "gn:name":"Kabanga",
    "gn:population":0,
    "gn:timezone":"Asia/Manila",
    "iso:country":"PH",
    "name:ceb_x_preferred":[
        "Kabanga"
    ],
    "name:fil_x_preferred":[
        "Kabanga"
    ],
    "name:fra_x_preferred":[
        "Kabanga"
    ],
    "name:swe_x_preferred":[
        "Kabanga"
    ],
    "wof:name":"Kabanga",
    "wof:placetype":"locality"
},
  "geometry": {"coordinates":[125.63306,6.31],"type":"Point"}
}