{
  "type": "Feature",
  "properties": {
    "gn:admin1_code":"06",
    "gn:admin2_code":"18",
    "gn:admin3_code":"61905000.0",
    "gn:asciiname":"Cabugao",
    "gn:country_code":"PH",
    "gn:dem":32,
    "gn:feature_class":"P",
    "gn:feature_code":"PPL",
    "gn:name":"Cabugao",
    "gn:population":0,
    "gn:timezone":"Asia/Manila",
    "iso:country":"PH",
    "name:fil_x_preferred":[
        "Cabugao"
    ],
    "wof:name":"Cabugao",
    "wof:placetype":"locality"
},
  "geometry": {"coordinates":[122.65833000000001,11.53833],"type":"Point"}
}