{
  "type": "Feature",
  "properties": {
    "gn:admin1_code":"06",
    "gn:admin2_code":"18",
    "gn:admin3_code":"61905000.0",
    "gn:asciiname":"Cabugao",
    "gn:country_code":"PH",
    "gn:dem":32,
    "gn:feature_class":"P",
    "gn:feature_code":"PPL",
    "gn:name":"Cabugao",
    "gn:population":0,
    "gn:timezone":"Asia/Manila",
    "iso:country":"PH",
    "name:bcl_x_preferred":[
        "Cabugao"
    ],
    "name:ceb_x_preferred":[
        "Cabugao"
    ],
    "name:deu_x_preferred":[
        "Cabugao"
    ],
    "name:fil_x_preferred":[
        "Cabugao"
    ],
    "name:fra_x_preferred":[
        "Cabugao"
    ],
    "name:ilo_x_preferred":[
        "Cabugao"
    ],
    "name:ind_x_preferred":[
        "Cabugao"
    ],
    "name:ita_x_preferred":[
        "Cabugao"
    ],
    "name:nld_x_preferred":[
        "Cabugao"
    ],
    "name:pag_x_preferred":[
        "Cabugao"
    ],
    "name:pam_x_preferred":[
        "Cabugao"
    ],
    "name:spa_x_preferred":[
        "Cabugao"
    ],
    "name:swe_x_preferred":[
        "Cabugao"
    ],
    "name:tgl_x_preferred":[
        "Cabugao"
    ],
    "name:vie_x_preferred":[
        "Cabugao"
    ],
    "name:war_x_preferred":[
        "Cabugao"
    ],
    "wof:name":"Cabugao",
    "wof:placetype":"locality"
},
  "geometry": {"coordinates":[122.65833000000001,11.53833],"type":"Point"}
}