{
  "type": "Feature",
  "properties": {
    "gn:admin1_code":"40",
    "gn:admin2_code":"H2",
    "gn:admin3_code":"45636000.0",
    "gn:asciiname":"Tambangin",
    "gn:country_code":"PH",
    "gn:dem":5,
    "gn:feature_class":"P",
    "gn:feature_code":"PPL",
    "gn:name":"Tambangin",
    "gn:population":0,
    "gn:timezone":"Asia/Manila",
    "iso:country":"PH",
    "wof:name":"Tambangin",
    "wof:placetype":"locality"
},
  "geometry": {"coordinates":[121.93228999999999,14.73999],"type":"Point"}
}