{
  "type": "Feature",
  "properties": {
    "gn:admin1_code":"07",
    "gn:admin2_code":"11",
    "gn:admin3_code":"71230000.0",
    "gn:asciiname":"Catagbacon",
    "gn:country_code":"PH",
    "gn:dem":47,
    "gn:feature_class":"P",
    "gn:feature_code":"PPL",
    "gn:name":"Catagbacon",
    "gn:population":0,
    "gn:timezone":"Asia/Manila",
    "iso:country":"PH",
    "name:fil_x_preferred":[
        "Catagbacon"
    ],
    "name:und_x_variant":[
        "Catagbacan",
        "Catagbacan Jandig"
    ],
    "wof:name":"Catagbacon",
    "wof:placetype":"locality"
},
  "geometry": {"coordinates":[123.8134,9.8249],"type":"Point"}
}