{
  "type": "Feature",
  "properties": {
    "gn:admin1_code":"03",
    "gn:admin2_code":"64",
    "gn:admin3_code":"37111000.0",
    "gn:asciiname":"Payodpod",
    "gn:country_code":"PH",
    "gn:dem":157,
    "gn:feature_class":"P",
    "gn:feature_code":"PPL",
    "gn:name":"Payodpod",
    "gn:population":0,
    "gn:timezone":"Asia/Manila",
    "iso:country":"PH",
    "name:eng_x_preferred":[
        "Payodpod"
    ],
    "name:und_x_variant":[
        "Payubug",
        "Payugbug",
        "Paudpud",
        "Payodpod"
    ],
    "wof:name":"Payodpod",
    "wof:placetype":"locality"
},
  "geometry": {"coordinates":[120.2299,15.0696],"type":"Point"}
}