{
  "type": "Feature",
  "properties": {
    "gn:admin1_code":"11",
    "gn:admin2_code":"I7",
    "gn:admin3_code":"112319000.0",
    "gn:asciiname":"Lamita",
    "gn:country_code":"PH",
    "gn:dem":19,
    "gn:feature_class":"P",
    "gn:feature_code":"PPL",
    "gn:name":"Lamita",
    "gn:population":0,
    "gn:timezone":"Asia/Manila",
    "iso:country":"PH",
    "name:fil_x_preferred":[
        "Lamita"
    ],
    "wof:name":"Lamita",
    "wof:placetype":"locality"
},
  "geometry": {"coordinates":[125.7663,7.4347],"type":"Point"}
}