{
  "type": "Feature",
  "properties": {
    "gn:admin1_code":"09",
    "gn:admin2_code":"65",
    "gn:admin3_code":"97219000.0",
    "gn:asciiname":"Sikanan",
    "gn:cc2":"PH",
    "gn:country_code":"PH",
    "gn:dem":6,
    "gn:feature_class":"P",
    "gn:feature_code":"PPL",
    "gn:name":"Sikanan",
    "gn:population":0,
    "gn:timezone":"Asia/Manila",
    "iso:country":"PH",
    "name:und_x_variant":[
        "Sicanan",
        "Sikanan"
    ],
    "wof:name":"Sikanan",
    "wof:placetype":"locality"
},
  "geometry": {"coordinates":[122.14028,7.64472],"type":"Point"}
}