{
  "type": "Feature",
  "properties": {
    "gn:admin1_code":"05",
    "gn:admin2_code":"15",
    "gn:admin3_code":"51608000.0",
    "gn:asciiname":"Magkadugyong",
    "gn:country_code":"PH",
    "gn:dem":57,
    "gn:feature_class":"P",
    "gn:feature_code":"PPL",
    "gn:name":"Magkadugyong",
    "gn:population":0,
    "gn:timezone":"Asia/Manila",
    "iso:country":"PH",
    "name:fil_x_preferred":[
        "Magkadugyong"
    ],
    "name:und_x_variant":[
        "Magkadugyung"
    ],
    "wof:name":"Magkadugyong",
    "wof:placetype":"locality"
},
  "geometry": {"coordinates":[122.73399999999999,14.2668],"type":"Point"}
}