{
  "type": "Feature",
  "properties": {
    "gn:country":"PH",
    "gn:fcode":"PPL",
    "gn:pop":2709,
    "iso:country":"PH",
    "name:eng_x_preferred":[
        "Vista Alegre"
    ],
    "qs:name":"Vista Alegre",
    "qs:photos_9r":0,
    "qs:photos_sr":0,
    "qs:pop_sr":"4",
    "wd:wordcount":163,
    "wof:name":"Vista Alegre",
    "wof:placetype":"locality",
    "wof:population":2709
},
  "geometry": {"coordinates":[122.7663,9.9984],"type":"Point"}
}