{
  "type": "Feature",
  "properties": {
    "gn:admin1_code":"06",
    "gn:admin2_code":"30",
    "gn:admin3_code":"63037000.0",
    "gn:asciiname":"Lua Ilya",
    "gn:country_code":"PH",
    "gn:dem":30,
    "gn:feature_class":"P",
    "gn:feature_code":"PPL",
    "gn:name":"Lua Ilya",
    "gn:population":0,
    "gn:timezone":"Asia/Manila",
    "iso:country":"PH",
    "name:fil_x_preferred":[
        "Lua Ilya"
    ],
    "name:und_x_variant":[
        "Iua Ilaya",
        "Iwa Ilaya"
    ],
    "wof:name":"Lua Ilya",
    "wof:placetype":"locality"
},
  "geometry": {"coordinates":[122.6298,10.9866],"type":"Point"}
}