{
  "type": "Feature",
  "properties": {
    "gn:admin1_code":"40",
    "gn:admin2_code":"33",
    "gn:admin3_code":"43416000.0",
    "gn:asciiname":"Santa Catalina",
    "gn:country_code":"PH",
    "gn:dem":171,
    "gn:feature_class":"P",
    "gn:feature_code":"PPL",
    "gn:name":"Santa Catalina",
    "gn:population":0,
    "gn:timezone":"Asia/Manila",
    "iso:country":"PH",
    "name:fil_x_preferred":[
        "Santa Catalina"
    ],
    "wof:name":"Santa Catalina",
    "wof:placetype":"locality"
},
  "geometry": {"coordinates":[121.45780000000001,14.1644],"type":"Point"}
}