{
  "type": "Feature",
  "properties": {
    "gn:admin1_code":"40",
    "gn:admin2_code":"09",
    "gn:admin3_code":"41012000.0",
    "gn:asciiname":"Arumahan",
    "gn:country_code":"PH",
    "gn:dem":82,
    "gn:feature_class":"P",
    "gn:feature_code":"PPL",
    "gn:name":"Arumahan",
    "gn:population":0,
    "gn:timezone":"Asia/Manila",
    "iso:country":"PH",
    "name:und_x_variant":[
        "Arumaha",
        "Arumahan"
    ],
    "wof:name":"Arumahan",
    "wof:placetype":"locality"
},
  "geometry": {"coordinates":[120.85787000000001,13.93185],"type":"Point"}
}