{
  "type": "Feature",
  "properties": {
    "gn:admin1_code":"03",
    "gn:admin2_code":"13",
    "gn:admin3_code":"31404000.0",
    "gn:asciiname":"Taal",
    "gn:country_code":"PH",
    "gn:dem":7,
    "gn:feature_class":"P",
    "gn:feature_code":"PPL",
    "gn:name":"Taal",
    "gn:population":0,
    "gn:timezone":"Asia/Manila",
    "iso:country":"PH",
    "name:cat_x_preferred":[
        "Taal"
    ],
    "name:ceb_x_preferred":[
        "Taal"
    ],
    "name:ces_x_preferred":[
        "Taal"
    ],
    "name:deu_x_preferred":[
        "Taal"
    ],
    "name:est_x_preferred":[
        "Taal"
    ],
    "name:fil_x_preferred":[
        "Taal"
    ],
    "name:fra_x_preferred":[
        "Taal"
    ],
    "name:ind_x_preferred":[
        "Taal"
    ],
    "name:nld_x_preferred":[
        "Taal"
    ],
    "name:pol_x_preferred":[
        "Taal"
    ],
    "name:sco_x_preferred":[
        "Taal"
    ],
    "name:spa_x_preferred":[
        "Taal"
    ],
    "name:swe_x_preferred":[
        "Taal"
    ],
    "name:tgl_x_preferred":[
        "Taal"
    ],
    "wof:name":"Taal",
    "wof:placetype":"locality"
},
  "geometry": {"coordinates":[120.92686,14.81178],"type":"Point"}
}