{
  "type": "Feature",
  "properties": {
    "gn:admin1_code":"11",
    "gn:admin2_code":"I6",
    "gn:admin3_code":"118201000.0",
    "gn:asciiname":"Taali",
    "gn:country_code":"PH",
    "gn:dem":68,
    "gn:feature_class":"P",
    "gn:feature_code":"PPL",
    "gn:name":"Taali",
    "gn:population":0,
    "gn:timezone":"Asia/Manila",
    "iso:country":"PH",
    "name:ceb_x_preferred":[
        "Taali"
    ],
    "name:est_x_preferred":[
        "Taali"
    ],
    "name:fil_x_preferred":[
        "Taali"
    ],
    "name:hye_x_preferred":[
        "\u054f\u0561\u0561\u056c\u056b"
    ],
    "name:pol_x_preferred":[
        "Taali"
    ],
    "name:spa_x_preferred":[
        "Taali"
    ],
    "name:swe_x_preferred":[
        "Taali"
    ],
    "name:ukr_x_preferred":[
        "\u0422\u0430\u0430\u043b\u0456"
    ],
    "name:vol_x_preferred":[
        "Taali"
    ],
    "wof:name":"Taali",
    "wof:placetype":"locality"
},
  "geometry": {"coordinates":[126.06667,7.71667],"type":"Point"}
}