{
  "type": "Feature",
  "properties": {
    "gn:admin1_code":"11",
    "gn:admin2_code":"I6",
    "gn:admin3_code":"118201000.0",
    "gn:asciiname":"Taali",
    "gn:country_code":"PH",
    "gn:dem":68,
    "gn:feature_class":"P",
    "gn:feature_code":"PPL",
    "gn:name":"Taali",
    "gn:population":0,
    "gn:timezone":"Asia/Manila",
    "iso:country":"PH",
    "name:fil_x_preferred":[
        "Taali"
    ],
    "wof:name":"Taali",
    "wof:placetype":"locality"
},
  "geometry": {"coordinates":[126.06667,7.71667],"type":"Point"}
}