{
  "type": "Feature",
  "properties": {
    "gn:gn_country":"PH",
    "gn:gn_fcode":"PPL",
    "gn:gn_pop":6919,
    "gn:population":6919,
    "iso:country":"PH",
    "name:fil_x_preferred":[
        "Gibong"
    ],
    "name:unk_x_variant":[
        "Hibung"
    ],
    "qs_pg:aaroncc":"PH",
    "qs_pg:gn_country":"PH",
    "qs_pg:gn_fcode":"PPL",
    "qs_pg:gn_pop":6919,
    "qs_pg:name":"Gibong",
    "qs_pg:photos_9r":0,
    "qs_pg:photos_sr":0,
    "qs_pg:pop_sr":5,
    "qs_pg:qs_pg_placetype":"locality",
    "wof:name":"Gibong",
    "wof:placetype":"locality",
    "wof:population":6919
},
  "geometry": {"coordinates":[122.03941,11.86338],"type":"Point"}
}