{
  "type": "Feature",
  "properties": {
    "gn:admin1_code":"40",
    "gn:admin2_code":"53",
    "gn:admin3_code":"45801000.0",
    "gn:asciiname":"Poblacion Itaas",
    "gn:country_code":"PH",
    "gn:dem":11,
    "gn:feature_class":"P",
    "gn:feature_code":"PPL",
    "gn:name":"Poblacion Itaas",
    "gn:population":0,
    "gn:timezone":"Asia/Manila",
    "iso:country":"PH",
    "name:fil_x_preferred":[
        "Poblacion Itaas"
    ],
    "wof:name":"Poblacion Itaas",
    "wof:placetype":"locality"
},
  "geometry": {"coordinates":[121.1559,14.5251],"type":"Point"}
}