{
  "type": "Feature",
  "properties": {
    "gn:admin1_code":"07",
    "gn:admin2_code":"11",
    "gn:admin3_code":"71240000.0",
    "gn:asciiname":"La Union",
    "gn:country_code":"PH",
    "gn:dem":235,
    "gn:feature_class":"P",
    "gn:feature_code":"PPL",
    "gn:name":"La Union",
    "gn:population":0,
    "gn:timezone":"Asia/Manila",
    "iso:country":"PH",
    "name:fil_x_preferred":[
        "La Union"
    ],
    "wof:name":"La Union",
    "wof:placetype":"locality"
},
  "geometry": {"coordinates":[124.2567,9.7895],"type":"Point"}
}