{
  "type": "Feature",
  "properties": {
    "gn:admin1_code":"06",
    "gn:admin2_code":"18",
    "gn:admin3_code":"61913000.0",
    "gn:asciiname":"Pondol",
    "gn:country_code":"PH",
    "gn:dem":10,
    "gn:feature_class":"P",
    "gn:feature_code":"PPL",
    "gn:name":"Pondol",
    "gn:population":0,
    "gn:timezone":"Asia/Manila",
    "iso:country":"PH",
    "name:fil_x_preferred":[
        "Pondol"
    ],
    "wof:name":"Pondol",
    "wof:placetype":"locality"
},
  "geometry": {"coordinates":[122.9226,11.4404],"type":"Point"}
}