{
  "type": "Feature",
  "properties": {
    "gn:admin1_code":"06",
    "gn:admin2_code":"06",
    "gn:admin3_code":"60606000.0",
    "gn:asciiname":"Mararison",
    "gn:country_code":"PH",
    "gn:dem":8,
    "gn:feature_class":"P",
    "gn:feature_code":"PPL",
    "gn:name":"Mararison",
    "gn:population":0,
    "gn:timezone":"Asia/Manila",
    "iso:country":"PH",
    "name:fil_x_preferred":[
        "Mararison"
    ],
    "wof:name":"Mararison",
    "wof:placetype":"locality"
},
  "geometry": {"coordinates":[122.02589999999999,11.41578],"type":"Point"}
}