{
  "type": "Feature",
  "properties": {
    "gn:admin1_code":"06",
    "gn:admin2_code":"30",
    "gn:admin3_code":"63015000.0",
    "gn:asciiname":"Nipa",
    "gn:country_code":"PH",
    "gn:dem":25,
    "gn:feature_class":"P",
    "gn:feature_code":"PPL",
    "gn:name":"Nipa",
    "gn:population":0,
    "gn:timezone":"Asia/Manila",
    "iso:country":"PH",
    "name:fil_x_preferred":[
        "Nipa"
    ],
    "wof:name":"Nipa",
    "wof:placetype":"locality"
},
  "geometry": {"coordinates":[123.1191,11.1446],"type":"Point"}
}