{
  "type": "Feature",
  "properties": {
    "gn:admin1_code":"15",
    "gn:admin2_code":"32",
    "gn:admin3_code":"143214000.0",
    "gn:asciiname":"Bogui",
    "gn:country_code":"PH",
    "gn:dem":459,
    "gn:feature_class":"P",
    "gn:feature_code":"PPL",
    "gn:name":"Bogui",
    "gn:population":0,
    "gn:timezone":"Asia/Manila",
    "iso:country":"PH",
    "name:fil_x_preferred":[
        "Bogui"
    ],
    "wof:name":"Bogui",
    "wof:placetype":"locality"
},
  "geometry": {"coordinates":[121.3472,17.2584],"type":"Point"}
}