{
  "type": "Feature",
  "properties": {
    "iso:country":"PH",
    "qs:gn_country":"PH",
    "qs:gn_fcode":"PPL",
    "qs:gn_pop":0,
    "qs:name":"Ususan",
    "qs:name_adm0":"Philippines",
    "qs:name_adm1":"National Capital Region",
    "qs:photos":0,
    "qs:photos_1k":0,
    "qs:photos_9k":0,
    "qs:photos_9r":0,
    "qs:photos_all":0,
    "qs:photos_sr":0,
    "qs:placetype":"Town",
    "qs:pop_sr":"0",
    "qs:woe_adm0":23424934,
    "wof:name":"Ususan",
    "wof:placetype":"locality"
},
  "geometry": {"coordinates":[121.07389999999999,14.5339],"type":"Point"}
}