{
  "type": "Feature",
  "properties": {
    "gn:admin1_code":"06",
    "gn:admin2_code":"18",
    "gn:admin3_code":"61904000.0",
    "gn:asciiname":"Tina",
    "gn:country_code":"PH",
    "gn:dem":75,
    "gn:feature_class":"P",
    "gn:feature_code":"PPL",
    "gn:name":"Tina",
    "gn:population":0,
    "gn:timezone":"Asia/Manila",
    "iso:country":"PH",
    "name:bre_x_preferred":[
        "Tina"
    ],
    "name:cat_x_preferred":[
        "Tina"
    ],
    "name:ceb_x_preferred":[
        "Tina"
    ],
    "name:ces_x_preferred":[
        "Tina"
    ],
    "name:deu_x_preferred":[
        "Tina"
    ],
    "name:eus_x_preferred":[
        "Tina"
    ],
    "name:fra_x_preferred":[
        "Tina"
    ],
    "name:heb_x_preferred":[
        "\u05d8\u05d9\u05e0\u05d4"
    ],
    "name:ita_x_preferred":[
        "Tina"
    ],
    "name:jpn_x_preferred":[
        "\u30c6\u30a3\u30ca"
    ],
    "name:lav_x_preferred":[
        "T\u012bna"
    ],
    "name:nld_x_preferred":[
        "Tina"
    ],
    "name:pol_x_preferred":[
        "Tina"
    ],
    "name:por_x_preferred":[
        "Tina"
    ],
    "name:rus_x_preferred":[
        "\u0422\u0438\u043d\u0430"
    ],
    "name:slk_x_preferred":[
        "Tina"
    ],
    "name:swe_x_preferred":[
        "Tina"
    ],
    "name:tgl_x_preferred":[
        "Tina"
    ],
    "name:ukr_x_preferred":[
        "\u0422\u0456\u043d\u0430"
    ],
    "wof:name":"Tina",
    "wof:placetype":"locality"
},
  "geometry": {"coordinates":[122.86667,11.23389],"type":"Point"}
}