{
  "type": "Feature",
  "properties": {
    "gn:admin1_code":"08",
    "gn:admin2_code":"37",
    "gn:admin3_code":"83715000.0",
    "gn:asciiname":"Bisoria",
    "gn:cc2":"PH",
    "gn:country_code":"PH",
    "gn:dem":4,
    "gn:feature_class":"P",
    "gn:feature_code":"PPL",
    "gn:name":"Bisoria",
    "gn:population":0,
    "gn:timezone":"Asia/Manila",
    "iso:country":"PH",
    "name:und_x_variant":[
        "Visoria",
        "Bisoria"
    ],
    "wof:name":"Bisoria",
    "wof:placetype":"locality"
},
  "geometry": {"coordinates":[124.66943999999999,11.29778],"type":"Point"}
}