{
  "type": "Feature",
  "properties": {
    "gn:admin1_code":"09",
    "gn:admin2_code":"66",
    "gn:admin3_code":"97313000.0",
    "gn:asciiname":"Karpok",
    "gn:country_code":"PH",
    "gn:dem":253,
    "gn:feature_class":"P",
    "gn:feature_code":"PPL",
    "gn:name":"Karpok",
    "gn:population":0,
    "gn:timezone":"Asia/Manila",
    "iso:country":"PH",
    "wof:name":"Karpok",
    "wof:placetype":"locality"
},
  "geometry": {"coordinates":[123.20139,7.67917],"type":"Point"}
}