{
  "type": "Feature",
  "properties": {
    "gn:admin1_code":"01",
    "gn:admin2_code":"51",
    "gn:admin3_code":"15544000.0",
    "gn:asciiname":"Beltran",
    "gn:country_code":"PH",
    "gn:dem":69,
    "gn:feature_class":"P",
    "gn:feature_code":"PPL",
    "gn:name":"Beltran",
    "gn:population":0,
    "gn:timezone":"Asia/Manila",
    "iso:country":"PH",
    "name:fil_x_preferred":[
        "Beltran"
    ],
    "wof:name":"Beltran",
    "wof:placetype":"locality"
},
  "geometry": {"coordinates":[120.78333000000001,15.95],"type":"Point"}
}