{
  "type": "Feature",
  "properties": {
    "gn:admin1_code":"02",
    "gn:admin2_code":"31",
    "gn:admin3_code":"23106000.0",
    "gn:asciiname":"Tallag",
    "gn:country_code":"PH",
    "gn:dem":30,
    "gn:feature_class":"P",
    "gn:feature_code":"PPL",
    "gn:name":"Tallag",
    "gn:population":0,
    "gn:timezone":"Asia/Manila",
    "iso:country":"PH",
    "name:fil_x_preferred":[
        "Dallag"
    ],
    "name:fil_x_variant":[
        "Tallag"
    ],
    "wof:name":"Tallag",
    "wof:placetype":"locality"
},
  "geometry": {"coordinates":[121.72163,17.42826],"type":"Point"}
}