{
  "type": "Feature",
  "properties": {
    "gn:country":"PH",
    "gn:fcode":"PPL",
    "gn:population":2649,
    "iso:country":"PH",
    "name:fil_x_preferred":[
        "Bagahanlad"
    ],
    "name:und_x_variant":[
        "Bagahanglad"
    ],
    "qs:name":"Bagahanlad",
    "qs:photos_9r":0,
    "qs:photos_sr":0,
    "qs:pop_sr":"4",
    "wof:name":"Bagahanlad",
    "wof:placetype":"locality",
    "wof:population":2649
},
  "geometry": {"coordinates":[123.6688,12.5797],"type":"Point"}
}