{
  "type": "Feature",
  "properties": {
    "gn:admin1_code":"05",
    "gn:admin2_code":"05",
    "gn:admin3_code":"50512000.0",
    "gn:asciiname":"Banao",
    "gn:country_code":"PH",
    "gn:dem":76,
    "gn:feature_class":"P",
    "gn:feature_code":"PPL",
    "gn:name":"Banao",
    "gn:population":0,
    "gn:timezone":"Asia/Manila",
    "iso:country":"PH",
    "name:fil_x_preferred":[
        "Banao"
    ],
    "wof:name":"Banao",
    "wof:placetype":"locality"
},
  "geometry": {"coordinates":[123.46637,13.23452],"type":"Point"}
}