{
  "type": "Feature",
  "properties": {
    "gn:admin1_code":"12",
    "gn:admin2_code":"71",
    "gn:admin3_code":"126509000.0",
    "gn:asciiname":"Sugco",
    "gn:country_code":"PH",
    "gn:dem":67,
    "gn:feature_class":"P",
    "gn:feature_code":"PPL",
    "gn:name":"Sugco",
    "gn:population":0,
    "gn:timezone":"Asia/Manila",
    "iso:country":"PH",
    "name:fil_x_preferred":[
        "Sugco"
    ],
    "name:und_x_variant":[
        "Sugca",
        "Sugko"
    ],
    "wof:name":"Sugco",
    "wof:placetype":"locality"
},
  "geometry": {"coordinates":[124.04361000000002,6.4225],"type":"Point"}
}