{
  "type": "Feature",
  "properties": {
    "gn:admin1_code":"01",
    "gn:admin2_code":"29",
    "gn:admin3_code":"12901000.0",
    "gn:asciiname":"Amilongon",
    "gn:country_code":"PH",
    "gn:dem":87,
    "gn:feature_class":"P",
    "gn:feature_code":"PPL",
    "gn:name":"Amilongon",
    "gn:population":0,
    "gn:timezone":"Asia/Manila",
    "iso:country":"PH",
    "name:fil_x_preferred":[
        "Amilongon"
    ],
    "wof:name":"Amilongon",
    "wof:placetype":"locality"
},
  "geometry": {"coordinates":[120.5457,16.8758],"type":"Point"}
}