{
  "type": "Feature",
  "properties": {
    "gn:admin1_code":"01",
    "gn:admin2_code":"29",
    "gn:admin3_code":"12917000.0",
    "gn:asciiname":"Sibsibbo",
    "gn:country_code":"PH",
    "gn:dem":153,
    "gn:feature_class":"P",
    "gn:feature_code":"PPL",
    "gn:name":"Sibsibbo",
    "gn:population":0,
    "gn:timezone":"Asia/Manila",
    "iso:country":"PH",
    "name:fil_x_preferred":[
        "Sibsibbo"
    ],
    "name:fil_x_variant":[
        "Sibsibo",
        "Sibsibu",
        "Sibsibbu",
        "Sibsibbe"
    ],
    "name:und_x_variant":[
        "Sibsibbu",
        "Sibsibu",
        "Sibsibbe"
    ],
    "wof:name":"Sibsibbo",
    "wof:placetype":"locality"
},
  "geometry": {"coordinates":[120.57510000000001,17.2972],"type":"Point"}
}