{
  "type": "Feature",
  "properties": {
    "iso:country":"PH",
    "name:bcl_x_preferred":[
        "Bayombong"
    ],
    "name:cat_x_preferred":[
        "Bayombong"
    ],
    "name:cbk_zam_x_preferred":[
        "Bayombong"
    ],
    "name:ceb_x_preferred":[
        "Bayombong"
    ],
    "name:deu_x_preferred":[
        "Bayombong"
    ],
    "name:eng_x_preferred":[
        "Bayombong"
    ],
    "name:fil_x_preferred":[
        "Bayombong"
    ],
    "name:fra_x_preferred":[
        "Bayombong"
    ],
    "name:ilo_x_preferred":[
        "Bayombong"
    ],
    "name:ind_x_preferred":[
        "Bayombong"
    ],
    "name:ita_x_preferred":[
        "Bayombong"
    ],
    "name:nld_x_preferred":[
        "Bayombong"
    ],
    "name:oci_x_preferred":[
        "Bayombong"
    ],
    "name:pag_x_preferred":[
        "Bayombong"
    ],
    "name:pam_x_preferred":[
        "Bayombong"
    ],
    "name:spa_x_preferred":[
        "Bayombong"
    ],
    "name:swe_x_preferred":[
        "Bayombong"
    ],
    "name:tgl_x_preferred":[
        "Bayombong"
    ],
    "name:urd_x_preferred":[
        "\u0628\u0627\u0626\u0648\u0645\u0628\u0648\u0646\u06af"
    ],
    "name:vie_x_preferred":[
        "Bayombong"
    ],
    "name:war_x_preferred":[
        "Bayombong"
    ],
    "qs:gn_country":"PH",
    "qs:gn_fcode":"PPLA3",
    "qs:gn_pop":48199,
    "qs:name":"Bayombong",
    "qs:name_adm0":"Philippines",
    "qs:name_adm1":"Cagayan Valley",
    "qs:photos":129,
    "qs:photos_1k":26,
    "qs:photos_9k":1,
    "qs:photos_9r":3,
    "qs:photos_all":129,
    "qs:photos_sr":3,
    "qs:placetype":"Town",
    "qs:pop_sr":"7",
    "qs:woe_adm0":23424934,
    "wd:wordcount":1430,
    "wof:name":"Bayombong",
    "wof:placetype":"locality",
    "wof:population":48199
},
  "geometry": {"coordinates":[121.1497,16.4812],"type":"Point"}
}