{
  "type": "Feature",
  "properties": {
    "gn:admin1_code":"40",
    "gn:admin2_code":"33",
    "gn:admin3_code":"43429000.0",
    "gn:asciiname":"Salubungan",
    "gn:country_code":"PH",
    "gn:dem":6,
    "gn:feature_class":"P",
    "gn:feature_code":"PPL",
    "gn:name":"Salubungan",
    "gn:population":0,
    "gn:timezone":"Asia/Manila",
    "iso:country":"PH",
    "name:fil_x_preferred":[
        "Salubungan"
    ],
    "wof:name":"Salubungan",
    "wof:placetype":"locality"
},
  "geometry": {"coordinates":[121.447,14.4212],"type":"Point"}
}