{
  "type": "Feature",
  "properties": {
    "gn:admin1_code":"03",
    "gn:admin2_code":"07",
    "gn:admin3_code":"30812000.0",
    "gn:asciiname":"Tabing Ilog",
    "gn:country_code":"PH",
    "gn:dem":8,
    "gn:feature_class":"P",
    "gn:feature_code":"PPL",
    "gn:name":"Tabing Ilog",
    "gn:population":0,
    "gn:timezone":"Asia/Manila",
    "iso:country":"PH",
    "name:fil_x_preferred":[
        "Tabing Ilog"
    ],
    "wof:name":"Tabing Ilog",
    "wof:placetype":"locality"
},
  "geometry": {"coordinates":[120.54214,14.77715],"type":"Point"}
}