{
  "type": "Feature",
  "properties": {
    "gn:admin1_code":"02",
    "gn:admin2_code":"14",
    "gn:admin3_code":"21510000.0",
    "gn:asciiname":"Ziminila",
    "gn:country_code":"PH",
    "gn:dem":4,
    "gn:feature_class":"P",
    "gn:feature_code":"PPL",
    "gn:name":"Ziminila",
    "gn:population":0,
    "gn:timezone":"Asia/Manila",
    "iso:country":"PH",
    "name:fil_x_preferred":[
        "Ziminila"
    ],
    "wof:name":"Ziminila",
    "wof:placetype":"locality"
},
  "geometry": {"coordinates":[121.72532,18.26508],"type":"Point"}
}