{
  "type": "Feature",
  "properties": {
    "gn:admin1_code":"01",
    "gn:admin2_code":"51",
    "gn:admin3_code":"15520000.0",
    "gn:asciiname":"Babuyan",
    "gn:country_code":"PH",
    "gn:dem":107,
    "gn:feature_class":"P",
    "gn:feature_code":"PPL",
    "gn:name":"Babuyan",
    "gn:population":0,
    "gn:timezone":"Asia/Manila",
    "iso:country":"PH",
    "name:fil_x_preferred":[
        "Babuyan"
    ],
    "name:und_x_variant":[
        "Babuyon"
    ],
    "wof:name":"Babuyan",
    "wof:placetype":"locality"
},
  "geometry": {"coordinates":[120.05500000000001,15.8823],"type":"Point"}
}