{
  "type": "Feature",
  "properties": {
    "gn:admin1_code":"03",
    "gn:admin2_code":"13",
    "gn:admin3_code":"31423000.0",
    "gn:asciiname":"Tindalo",
    "gn:country_code":"PH",
    "gn:dem":19,
    "gn:feature_class":"P",
    "gn:feature_code":"PPL",
    "gn:name":"Tindalo",
    "gn:population":0,
    "gn:timezone":"Asia/Manila",
    "iso:country":"PH",
    "wof:name":"Tindalo",
    "wof:placetype":"locality"
},
  "geometry": {"coordinates":[120.95459,14.83004],"type":"Point"}
}