{
  "type": "Feature",
  "properties": {
    "gn:admin1_code":"05",
    "gn:admin2_code":"39",
    "gn:admin3_code":"54111000.0",
    "gn:asciiname":"Tagbon",
    "gn:country_code":"PH",
    "gn:dem":66,
    "gn:feature_class":"P",
    "gn:feature_code":"PPL",
    "gn:name":"Tagbon",
    "gn:population":0,
    "gn:timezone":"Asia/Manila",
    "iso:country":"PH",
    "name:fil_x_preferred":[
        "Tagbon"
    ],
    "wof:name":"Tagbon",
    "wof:placetype":"locality"
},
  "geometry": {"coordinates":[123.60460999999999,12.25924],"type":"Point"}
}