{
  "type": "Feature",
  "properties": {
    "gn:admin1_code":"07",
    "gn:admin2_code":"21",
    "gn:admin3_code":"72235000.0",
    "gn:asciiname":"Manlum",
    "gn:country_code":"PH",
    "gn:dem":706,
    "gn:feature_class":"P",
    "gn:feature_code":"PPL",
    "gn:name":"Manlum",
    "gn:population":0,
    "gn:timezone":"Asia/Manila",
    "iso:country":"PH",
    "name:fil_x_preferred":[
        "Manlum"
    ],
    "wof:name":"Manlum",
    "wof:placetype":"locality"
},
  "geometry": {"coordinates":[123.3724,9.5535],"type":"Point"}
}