{
  "type": "Feature",
  "properties": {
    "gn:admin1_code":"02",
    "gn:admin2_code":"14",
    "gn:admin3_code":"21518000.0",
    "gn:asciiname":"Nagattatan",
    "gn:country_code":"PH",
    "gn:dem":8,
    "gn:feature_class":"P",
    "gn:feature_code":"PPL",
    "gn:name":"Nagattatan",
    "gn:population":0,
    "gn:timezone":"Asia/Manila",
    "iso:country":"PH",
    "wof:name":"Nagattatan",
    "wof:placetype":"locality"
},
  "geometry": {"coordinates":[121.29616,18.5248],"type":"Point"}
}