{
  "type": "Feature",
  "properties": {
    "gn:admin1_code":"02",
    "gn:admin2_code":"31",
    "gn:admin3_code":"23102000.0",
    "gn:asciiname":"Ramona",
    "gn:country_code":"PH",
    "gn:dem":65,
    "gn:feature_class":"P",
    "gn:feature_code":"PPL",
    "gn:name":"Ramona",
    "gn:population":0,
    "gn:timezone":"Asia/Manila",
    "iso:country":"PH",
    "name:fil_x_preferred":[
        "Ramona"
    ],
    "wof:name":"Ramona",
    "wof:placetype":"locality"
},
  "geometry": {"coordinates":[121.76888,16.81826],"type":"Point"}
}