{
  "type": "Feature",
  "properties": {
    "gn:country":"PH",
    "gn:fcode":"PPL",
    "gn:population":2708,
    "iso:country":"PH",
    "name:fil_x_preferred":[
        "Alimono"
    ],
    "qs:name":"Alimono",
    "qs:photos_9r":0,
    "qs:photos_sr":0,
    "qs:pop_sr":"4",
    "wof:name":"Alimono",
    "wof:placetype":"locality",
    "wof:population":2708
},
  "geometry": {"coordinates":[122.7129,11.1855],"type":"Point"}
}