{
  "type": "Feature",
  "properties": {
    "gn:admin1_code":"03",
    "gn:admin2_code":"47",
    "gn:admin3_code":"34930000.0",
    "gn:asciiname":"Bakal Uno",
    "gn:country_code":"PH",
    "gn:dem":65,
    "gn:feature_class":"P",
    "gn:feature_code":"PPL",
    "gn:name":"Bakal Uno",
    "gn:population":0,
    "gn:timezone":"Asia/Manila",
    "iso:country":"PH",
    "name:fil_x_preferred":[
        "Bacal I"
    ],
    "name:fil_x_variant":[
        "Bacal"
    ],
    "wof:name":"Bakal Uno",
    "wof:placetype":"locality"
},
  "geometry": {"coordinates":[120.90009999999999,15.6905],"type":"Point"}
}