{
  "type": "Feature",
  "properties": {
    "gn:admin1_code":"15",
    "gn:admin2_code":"27",
    "gn:admin3_code":"142711000.0",
    "gn:asciiname":"Joya",
    "gn:country_code":"PH",
    "gn:dem":1254,
    "gn:feature_class":"P",
    "gn:feature_code":"PPL",
    "gn:name":"Joya",
    "gn:population":0,
    "gn:timezone":"Asia/Manila",
    "iso:country":"PH",
    "name:ceb_x_preferred":[
        "Joya"
    ],
    "name:deu_x_preferred":[
        "Joya"
    ],
    "name:fil_x_preferred":[
        "Joya"
    ],
    "name:fil_x_variant":[
        "Joyo"
    ],
    "name:ita_x_preferred":[
        "Joya"
    ],
    "name:nld_x_preferred":[
        "Joya"
    ],
    "name:por_x_preferred":[
        "Joya"
    ],
    "name:swe_x_preferred":[
        "Joya"
    ],
    "name:und_x_variant":[
        "Joyo"
    ],
    "wof:name":"Joya",
    "wof:placetype":"locality"
},
  "geometry": {"coordinates":[121.02964,16.69327],"type":"Point"}
}