{
  "type": "Feature",
  "properties": {
    "gn:country":"PH",
    "gn:fcode":"ADM3",
    "gn:population":14542,
    "iso:country":"PH",
    "name:ceb_x_preferred":[
        "Pugo"
    ],
    "name:deu_x_preferred":[
        "Pugo"
    ],
    "name:fil_x_preferred":[
        "Bayan ng Pugo"
    ],
    "name:tgl_x_preferred":[
        "Pugo"
    ],
    "qs:name":"Pugo",
    "qs:photos_9r":0,
    "qs:photos_sr":0,
    "qs:pop_sr":"6",
    "wd:wordcount":59,
    "wof:name":"Pugo",
    "wof:placetype":"localadmin",
    "wof:population":14542
},
  "geometry": {"coordinates":[120.48124,16.32467],"type":"Point"}
}