{
  "type": "Feature",
  "properties": {
    "gn:admin1_code":"06",
    "gn:admin2_code":"30",
    "gn:admin3_code":"63013000.0",
    "gn:asciiname":"Malitbog Ilaud",
    "gn:country_code":"PH",
    "gn:dem":72,
    "gn:feature_class":"P",
    "gn:feature_code":"PPL",
    "gn:name":"Malitbog Ilaud",
    "gn:population":0,
    "gn:timezone":"Asia/Manila",
    "iso:country":"PH",
    "name:fil_x_preferred":[
        "Malitbog Ilaud"
    ],
    "wof:name":"Malitbog Ilaud",
    "wof:placetype":"locality"
},
  "geometry": {"coordinates":[122.515,11.1833],"type":"Point"}
}