{
  "type": "Feature",
  "properties": {
    "gn:admin1_code":"05",
    "gn:admin2_code":"16",
    "gn:admin3_code":"51730000.0",
    "gn:asciiname":"Bayaao",
    "gn:country_code":"PH",
    "gn:dem":109,
    "gn:feature_class":"P",
    "gn:feature_code":"PPL",
    "gn:name":"Bayaao",
    "gn:population":0,
    "gn:timezone":"Asia/Manila",
    "iso:country":"PH",
    "name:fil_x_preferred":[
        "Bayaao"
    ],
    "wof:name":"Bayaao",
    "wof:placetype":"locality"
},
  "geometry": {"coordinates":[122.7266,13.8563],"type":"Point"}
}