{
  "type": "Feature",
  "properties": {
    "gn:admin1_code":"06",
    "gn:admin2_code":"06",
    "gn:admin3_code":"60611000.0",
    "gn:asciiname":"Idiacacan",
    "gn:country_code":"PH",
    "gn:dem":7,
    "gn:feature_class":"P",
    "gn:feature_code":"PPL",
    "gn:name":"Idiacacan",
    "gn:population":0,
    "gn:timezone":"Asia/Manila",
    "iso:country":"PH",
    "name:fil_x_preferred":[
        "Idiacacan"
    ],
    "wof:name":"Idiacacan",
    "wof:placetype":"locality"
},
  "geometry": {"coordinates":[122.1014,11.6884],"type":"Point"}
}