{
  "type": "Feature",
  "properties": {
    "gn:admin1_code":"09",
    "gn:admin2_code":"66",
    "gn:admin3_code":"97307000.0",
    "gn:asciiname":"San Augustin",
    "gn:country_code":"PH",
    "gn:dem":46,
    "gn:feature_class":"P",
    "gn:feature_code":"PPL",
    "gn:name":"San Augustin",
    "gn:population":0,
    "gn:timezone":"Asia/Manila",
    "iso:country":"PH",
    "wof:name":"San Augustin",
    "wof:placetype":"locality"
},
  "geometry": {"coordinates":[123.41361000000001,7.765],"type":"Point"}
}