{
  "type": "Feature",
  "properties": {
    "gn:admin1_code":"07",
    "gn:admin2_code":"21",
    "gn:admin3_code":"72252000.0",
    "gn:asciiname":"Daan Lungsod",
    "gn:country_code":"PH",
    "gn:dem":6,
    "gn:feature_class":"P",
    "gn:feature_code":"PPL",
    "gn:name":"Daan Lungsod",
    "gn:population":0,
    "gn:timezone":"Asia/Manila",
    "iso:country":"PH",
    "name:fil_x_preferred":[
        "Daan Lungsod"
    ],
    "wof:name":"Daan Lungsod",
    "wof:placetype":"locality"
},
  "geometry": {"coordinates":[123.8334,10.7347],"type":"Point"}
}