{
  "type": "Feature",
  "properties": {
    "gn:admin1_code":"01",
    "gn:admin2_code":"51",
    "gn:admin3_code":"15542000.0",
    "gn:asciiname":"Agou",
    "gn:country_code":"PH",
    "gn:dem":23,
    "gn:feature_class":"P",
    "gn:feature_code":"PPL",
    "gn:name":"Agou",
    "gn:population":0,
    "gn:timezone":"Asia/Manila",
    "iso:country":"PH",
    "name:fil_x_preferred":[
        "Agou"
    ],
    "wof:name":"Agou",
    "wof:placetype":"locality"
},
  "geometry": {"coordinates":[120.09304,16.07442],"type":"Point"}
}