{
  "type": "Feature",
  "properties": {
    "gn:admin1_code":"08",
    "gn:admin2_code":"37",
    "gn:admin3_code":"83743000.0",
    "gn:asciiname":"Cansapanid",
    "gn:cc2":"PH",
    "gn:country_code":"PH",
    "gn:dem":13,
    "gn:feature_class":"P",
    "gn:feature_code":"PPL",
    "gn:name":"Cansapanid",
    "gn:population":0,
    "gn:timezone":"Asia/Manila",
    "iso:country":"PH",
    "name:und_x_variant":[
        "Kansapanig",
        "Cansapanid"
    ],
    "wof:name":"Cansapanid",
    "wof:placetype":"locality"
},
  "geometry": {"coordinates":[124.83944,11.30667],"type":"Point"}
}