{
  "type": "Feature",
  "properties": {
    "gn:admin1_code":"15",
    "gn:admin2_code":"44",
    "gn:admin3_code":"144406000.0",
    "gn:asciiname":"Canakgak",
    "gn:country_code":"PH",
    "gn:dem":236,
    "gn:feature_class":"P",
    "gn:feature_code":"PPL",
    "gn:name":"Canakgak",
    "gn:population":0,
    "gn:timezone":"Asia/Manila",
    "iso:country":"PH",
    "name:fil_x_preferred":[
        "Canakgak"
    ],
    "name:fil_x_variant":[
        "Ganakgak"
    ],
    "wof:name":"Canakgak",
    "wof:placetype":"locality"
},
  "geometry": {"coordinates":[121.37663999999999,17.23254],"type":"Point"}
}