{
  "type": "Feature",
  "properties": {
    "iso:country":"PH",
    "name:bcl_x_preferred":[
        "Botolan"
    ],
    "name:cat_x_preferred":[
        "Botolan"
    ],
    "name:cbk_zam_x_preferred":[
        "Botolan"
    ],
    "name:ceb_x_preferred":[
        "Botolan"
    ],
    "name:deu_x_preferred":[
        "Botolan"
    ],
    "name:eng_x_preferred":[
        "Botolan"
    ],
    "name:fil_x_preferred":[
        "Botolan"
    ],
    "name:fra_x_preferred":[
        "Botolan"
    ],
    "name:ilo_x_preferred":[
        "Botolan"
    ],
    "name:ind_x_preferred":[
        "Botolan"
    ],
    "name:ita_x_preferred":[
        "Botolan"
    ],
    "name:msa_x_preferred":[
        "Botolan"
    ],
    "name:nld_x_preferred":[
        "Botolan"
    ],
    "name:oci_x_preferred":[
        "Botolan"
    ],
    "name:pag_x_preferred":[
        "Botolan"
    ],
    "name:pam_x_preferred":[
        "Botolan"
    ],
    "name:spa_x_preferred":[
        "Botolan"
    ],
    "name:swe_x_preferred":[
        "Botolan"
    ],
    "name:tgl_x_preferred":[
        "Botolan"
    ],
    "name:vie_x_preferred":[
        "Botolan"
    ],
    "name:war_x_preferred":[
        "Botolan"
    ],
    "qs:gn_country":"PH",
    "qs:gn_fcode":"PPL",
    "qs:gn_pop":22994,
    "qs:name":"Botolan",
    "qs:name_adm0":"Philippines",
    "qs:name_adm1":"Central Luzon",
    "qs:photos":0,
    "qs:photos_1k":0,
    "qs:photos_9k":0,
    "qs:photos_9r":0,
    "qs:photos_all":0,
    "qs:photos_sr":0,
    "qs:placetype":"Town",
    "qs:pop_sr":"7",
    "qs:woe_adm0":23424934,
    "wd:wordcount":684,
    "wof:name":"Botolan",
    "wof:placetype":"locality",
    "wof:population":22994
},
  "geometry": {"coordinates":[120.0245,15.2896],"type":"Point"}
}