{
  "type": "Feature",
  "properties": {
    "gn:country":"PH",
    "gn:fcode":"PPL",
    "gn:pop":2151,
    "iso:country":"PH",
    "name:fil_x_preferred":[
        "Capalayan"
    ],
    "qs:name":"Capalayan",
    "qs:photos_9r":0,
    "qs:photos_sr":0,
    "qs:pop_sr":"4",
    "wof:name":"Capalayan",
    "wof:placetype":"locality",
    "wof:population":2151
},
  "geometry": {"coordinates":[125.54443999999999,9.74056],"type":"Point"}
}