{
  "type": "Feature",
  "properties": {
    "gn:admin1_code":"02",
    "gn:admin2_code":"31",
    "gn:admin3_code":"23120000.0",
    "gn:asciiname":"Nabaculan",
    "gn:country_code":"PH",
    "gn:dem":66,
    "gn:feature_class":"P",
    "gn:feature_code":"PPL",
    "gn:name":"Nabaculan",
    "gn:population":0,
    "gn:timezone":"Asia/Manila",
    "iso:country":"PH",
    "name:fil_x_preferred":[
        "Nabaculan"
    ],
    "wof:name":"Nabaculan",
    "wof:placetype":"locality"
},
  "geometry": {"coordinates":[121.89454000000001,16.97395],"type":"Point"}
}