{
  "type": "Feature",
  "properties": {
    "gn:admin1_code":"12",
    "gn:admin2_code":"70",
    "gn:admin3_code":"126316000.0",
    "gn:asciiname":"Siguil",
    "gn:country_code":"PH",
    "gn:dem":597,
    "gn:feature_class":"P",
    "gn:feature_code":"PPL",
    "gn:name":"Siguil",
    "gn:population":0,
    "gn:timezone":"Asia/Manila",
    "iso:country":"PH",
    "name:fil_x_preferred":[
        "Siguil"
    ],
    "wof:name":"Siguil",
    "wof:placetype":"locality"
},
  "geometry": {"coordinates":[124.81139,6.19139],"type":"Point"}
}