{
  "type": "Feature",
  "properties": {
    "gn:admin1_code":"09",
    "gn:admin2_code":"66",
    "gn:admin3_code":"97319000.0",
    "gn:asciiname":"Bagong Tudela",
    "gn:country_code":"PH",
    "gn:dem":239,
    "gn:feature_class":"P",
    "gn:feature_code":"PPL",
    "gn:name":"Bagong Tudela",
    "gn:population":0,
    "gn:timezone":"Asia/Manila",
    "iso:country":"PH",
    "name:eng_x_preferred":[
        "Bagong Tudela"
    ],
    "wof:name":"Bagong Tudela",
    "wof:placetype":"locality"
},
  "geometry": {"coordinates":[123.46639999999999,8.19],"type":"Point"}
}