{
  "type": "Feature",
  "properties": {
    "iso:country":"PH",
    "name:bcl_x_preferred":[
        "Kalibo"
    ],
    "name:cbk_zam_x_preferred":[
        "Kalibo"
    ],
    "name:ceb_x_preferred":[
        "Kalibo"
    ],
    "name:deu_x_preferred":[
        "Kalibo"
    ],
    "name:eng_x_preferred":[
        "Kalibo"
    ],
    "name:fra_x_preferred":[
        "Kalibo"
    ],
    "name:ilo_x_preferred":[
        "Kalibo"
    ],
    "name:ind_x_preferred":[
        "Kalibo"
    ],
    "name:ita_x_preferred":[
        "Kalibo"
    ],
    "name:jpn_x_preferred":[
        "\u30ab\u30ea\u30dc"
    ],
    "name:kor_x_preferred":[
        "\uce7c\ub9ac\ubcf4"
    ],
    "name:msa_x_preferred":[
        "Kalibo"
    ],
    "name:nld_x_preferred":[
        "Kalibo"
    ],
    "name:pag_x_preferred":[
        "Kalibo"
    ],
    "name:pam_x_preferred":[
        "Kalibo"
    ],
    "name:pnb_x_preferred":[
        "\u06a9\u0627\u0644\u06cc\u0628\u0648"
    ],
    "name:rus_x_preferred":[
        "\u041a\u0430\u043b\u0438\u0431\u043e"
    ],
    "name:swe_x_preferred":[
        "Kalibo"
    ],
    "name:tgl_x_preferred":[
        "Kalibo"
    ],
    "name:tha_x_preferred":[
        "\u0e04\u0e32\u0e25\u0e35\u0e42\u0e1a"
    ],
    "name:ukr_x_preferred":[
        "\u041a\u0430\u043b\u0456\u0431\u043e"
    ],
    "name:urd_x_preferred":[
        "\u06a9\u0627\u0644\u06cc\u0628\u0648\u060c \u0627\u06a9\u0644\u0627\u0646"
    ],
    "name:urd_x_variant":[
        "\u06a9\u0627\u0644\u06cc\u0628\u0648"
    ],
    "name:vie_x_preferred":[
        "Kalibo"
    ],
    "name:war_x_preferred":[
        "Kalibo"
    ],
    "name:zho_x_preferred":[
        "\u5361\u5229\u535a"
    ],
    "qs:gn_pop":0,
    "qs:name":"Kalibo",
    "qs:name_adm0":"Philippines",
    "qs:name_adm1":"Western Visayas",
    "qs:photos":3555,
    "qs:photos_1k":720,
    "qs:photos_9k":16,
    "qs:photos_9r":12,
    "qs:photos_all":3555,
    "qs:photos_sr":21,
    "qs:placetype":"Town",
    "qs:pop_sr":"0",
    "qs:woe_adm0":23424934,
    "wd:wordcount":1512,
    "wof:name":"Kalibo",
    "wof:placetype":"locality"
},
  "geometry": {"coordinates":[122.36366200000001,11.712754],"type":"Point"}
}