{
  "type": "Feature",
  "properties": {
    "gn:admin1_code":"15",
    "gn:admin2_code":"10",
    "gn:admin3_code":"141101000.0",
    "gn:asciiname":"Sayet",
    "gn:country_code":"PH",
    "gn:dem":1662,
    "gn:feature_class":"P",
    "gn:feature_code":"PPL",
    "gn:name":"Sayet",
    "gn:population":0,
    "gn:timezone":"Asia/Manila",
    "iso:country":"PH",
    "name:fil_x_preferred":[
        "Sayet"
    ],
    "wof:name":"Sayet",
    "wof:placetype":"locality"
},
  "geometry": {"coordinates":[120.68859999999999,16.5197],"type":"Point"}
}