{
  "type": "Feature",
  "properties": {
    "gn:admin1_code":"06",
    "gn:admin2_code":"H3",
    "gn:admin3_code":"64524000.0",
    "gn:asciiname":"Lamisa",
    "gn:country_code":"PH",
    "gn:dem":103,
    "gn:feature_class":"P",
    "gn:feature_code":"PPL",
    "gn:name":"Lamisa",
    "gn:population":0,
    "gn:timezone":"Asia/Manila",
    "iso:country":"PH",
    "name:fil_x_preferred":[
        "Lamisa"
    ],
    "wof:name":"Lamisa",
    "wof:placetype":"locality"
},
  "geometry": {"coordinates":[123.3155,10.43777],"type":"Point"}
}