{
  "type": "Feature",
  "properties": {
    "gn:admin1_code":"40",
    "gn:admin2_code":"H2",
    "gn:admin3_code":"45640000.0",
    "gn:asciiname":"Banco",
    "gn:country_code":"PH",
    "gn:dem":231,
    "gn:feature_class":"P",
    "gn:feature_code":"PPL",
    "gn:name":"Banco",
    "gn:population":0,
    "gn:timezone":"Asia/Manila",
    "iso:country":"PH",
    "name:fil_x_preferred":[
        "Banco"
    ],
    "wof:name":"Banco",
    "wof:placetype":"locality"
},
  "geometry": {"coordinates":[122.6508,13.2949],"type":"Point"}
}