{
  "type": "Feature",
  "properties": {
    "gn:admin1_code":"40",
    "gn:admin2_code":"H2",
    "gn:admin3_code":"45640000.0",
    "gn:asciiname":"Banco",
    "gn:country_code":"PH",
    "gn:dem":231,
    "gn:feature_class":"P",
    "gn:feature_code":"PPL",
    "gn:name":"Banco",
    "gn:population":0,
    "gn:timezone":"Asia/Manila",
    "iso:country":"PH",
    "name:bul_x_preferred":[
        "\u0411\u0430\u043d\u043a\u043e"
    ],
    "name:ceb_x_preferred":[
        "Banco"
    ],
    "name:deu_x_preferred":[
        "Banco"
    ],
    "name:epo_x_preferred":[
        "Benko"
    ],
    "name:fil_x_preferred":[
        "Banco"
    ],
    "name:fra_x_preferred":[
        "Banco"
    ],
    "name:ita_x_preferred":[
        "Banco"
    ],
    "name:nld_x_preferred":[
        "Banco"
    ],
    "name:por_x_preferred":[
        "Banco"
    ],
    "name:rus_x_preferred":[
        "\u0411\u0430\u043d\u043a\u043e"
    ],
    "name:spa_x_preferred":[
        "Banco"
    ],
    "name:swe_x_preferred":[
        "Banco"
    ],
    "wof:name":"Banco",
    "wof:placetype":"locality"
},
  "geometry": {"coordinates":[122.6508,13.2949],"type":"Point"}
}