{
  "type": "Feature",
  "properties": {
    "gn:admin1_code":"10",
    "gn:admin2_code":"34",
    "gn:admin3_code":"103519000.0",
    "gn:asciiname":"Maitum-a-ig",
    "gn:country_code":"PH",
    "gn:dem":30,
    "gn:feature_class":"P",
    "gn:feature_code":"PPL",
    "gn:name":"Maitum-a-ig",
    "gn:population":0,
    "gn:timezone":"Asia/Manila",
    "iso:country":"PH",
    "name:und_x_variant":[
        "Mailumaig",
        "Maitum-a-ig"
    ],
    "wof:name":"Maitum-a-ig",
    "wof:placetype":"locality"
},
  "geometry": {"coordinates":[123.81667,7.86667],"type":"Point"}
}