{
  "type": "Feature",
  "properties": {
    "gn:admin1_code":"14",
    "gn:admin2_code":"56",
    "gn:admin3_code":"153811000.0",
    "gn:asciiname":"Pinantao",
    "gn:country_code":"PH",
    "gn:dem":112,
    "gn:feature_class":"P",
    "gn:feature_code":"PPL",
    "gn:name":"Pinantao",
    "gn:population":0,
    "gn:timezone":"Asia/Manila",
    "iso:country":"PH",
    "name:fil_x_preferred":[
        "Pinantao"
    ],
    "wof:name":"Pinantao",
    "wof:placetype":"locality"
},
  "geometry": {"coordinates":[124.25611000000001,7.4275],"type":"Point"}
}