{
  "type": "Feature",
  "properties": {
    "gn:admin1_code":"14",
    "gn:admin2_code":"60",
    "gn:admin3_code":"156619000.0",
    "gn:asciiname":"Pangdan",
    "gn:country_code":"PH",
    "gn:dem":21,
    "gn:feature_class":"P",
    "gn:feature_code":"PPL",
    "gn:name":"Pangdan",
    "gn:population":0,
    "gn:timezone":"Asia/Manila",
    "iso:country":"PH",
    "name:fil_x_preferred":[
        "Pangdan"
    ],
    "name:zho_x_preferred":[
        "\u5f6d\u4e39\u93ae"
    ],
    "wof:name":"Pangdan",
    "wof:placetype":"locality"
},
  "geometry": {"coordinates":[121.38806,6.00806],"type":"Point"}
}