{
  "type": "Feature",
  "properties": {
    "gn:admin1_code":"02",
    "gn:admin2_code":"68",
    "gn:admin3_code":"25705000.0",
    "gn:asciiname":"Ligaya",
    "gn:country_code":"PH",
    "gn:dem":109,
    "gn:feature_class":"P",
    "gn:feature_code":"PPL",
    "gn:name":"Ligaya",
    "gn:population":0,
    "gn:timezone":"Asia/Manila",
    "iso:country":"PH",
    "name:fil_x_preferred":[
        "Ligaya"
    ],
    "wof:name":"Ligaya",
    "wof:placetype":"locality"
},
  "geometry": {"coordinates":[121.5701,16.5117],"type":"Point"}
}