{
  "type": "Feature",
  "properties": {
    "gn:admin1_code":"08",
    "gn:admin2_code":"59",
    "gn:admin3_code":"86415000.0",
    "gn:asciiname":"Cabutan",
    "gn:cc2":"PH",
    "gn:country_code":"PH",
    "gn:dem":77,
    "gn:feature_class":"P",
    "gn:feature_code":"PPL",
    "gn:name":"Cabutan",
    "gn:population":0,
    "gn:timezone":"Asia/Manila",
    "iso:country":"PH",
    "name:und_x_variant":[
        "Kabutan",
        "Cabutan"
    ],
    "wof:name":"Cabutan",
    "wof:placetype":"locality"
},
  "geometry": {"coordinates":[125.28333000000001,9.91667],"type":"Point"}
}