{
  "type": "Feature",
  "properties": {
    "gn:admin1_code":"40",
    "gn:admin2_code":"H2",
    "gn:admin3_code":"45641000.0",
    "gn:asciiname":"Pulo",
    "gn:country_code":"PH",
    "gn:dem":35,
    "gn:feature_class":"P",
    "gn:feature_code":"PPL",
    "gn:name":"Pulo",
    "gn:population":0,
    "gn:timezone":"Asia/Manila",
    "iso:country":"PH",
    "name:ceb_x_preferred":[
        "Pulo"
    ],
    "name:fil_x_preferred":[
        "Pulo"
    ],
    "name:fil_x_variant":[
        "Polo"
    ],
    "name:ind_x_preferred":[
        "Pulo"
    ],
    "name:ita_x_preferred":[
        "Pulo"
    ],
    "name:nld_x_preferred":[
        "Pulo"
    ],
    "name:swe_x_preferred":[
        "Pulo"
    ],
    "wof:name":"Pulo",
    "wof:placetype":"locality"
},
  "geometry": {"coordinates":[121.32675,13.92268],"type":"Point"}
}