{
  "type": "Feature",
  "properties": {
    "gn:admin1_code":"41",
    "gn:admin2_code":"49",
    "gn:admin3_code":"175312000.0",
    "gn:asciiname":"Sibaltan",
    "gn:country_code":"PH",
    "gn:dem":5,
    "gn:feature_class":"P",
    "gn:feature_code":"PPL",
    "gn:name":"Sibaltan",
    "gn:population":0,
    "gn:timezone":"Asia/Manila",
    "iso:country":"PH",
    "name:fil_x_preferred":[
        "Sibaltan"
    ],
    "wof:name":"Sibaltan",
    "wof:placetype":"locality"
},
  "geometry": {"coordinates":[119.559,11.2647],"type":"Point"}
}