{
  "type": "Feature",
  "properties": {
    "gn:admin1_code":"08",
    "gn:admin2_code":"E4",
    "gn:asciiname":"Alegria",
    "gn:cc2":"PH",
    "gn:country_code":"PH",
    "gn:dem":5,
    "gn:feature_class":"P",
    "gn:feature_code":"PPL",
    "gn:name":"Alegria",
    "gn:population":0,
    "gn:timezone":"Asia/Manila",
    "iso:country":"PH",
    "name:bul_x_preferred":[
        "\u0410\u043b\u0435\u0433\u0440\u0438\u044f"
    ],
    "name:ceb_x_preferred":[
        "Alegria"
    ],
    "name:ita_x_preferred":[
        "Alegria"
    ],
    "name:nld_x_preferred":[
        "Alegria"
    ],
    "name:por_x_preferred":[
        "Alegria"
    ],
    "name:rus_x_preferred":[
        "\u0410\u043b\u0435\u0433\u0440\u0438\u044f"
    ],
    "name:scn_x_preferred":[
        "Alligrizza"
    ],
    "name:swe_x_preferred":[
        "Alegria"
    ],
    "name:und_x_variant":[
        "Alegeria"
    ],
    "name:war_x_preferred":[
        "Alegria"
    ],
    "wof:name":"Alegria",
    "wof:placetype":"locality"
},
  "geometry": {"coordinates":[124.59721999999999,11.01139],"type":"Point"}
}