{
  "type": "Feature",
  "properties": {
    "gn:admin1_code":"01",
    "gn:admin2_code":"51",
    "gn:admin3_code":"15520000.0",
    "gn:asciiname":"Pantol",
    "gn:country_code":"PH",
    "gn:dem":13,
    "gn:feature_class":"P",
    "gn:feature_code":"PPL",
    "gn:name":"Pantol",
    "gn:population":0,
    "gn:timezone":"Asia/Manila",
    "iso:country":"PH",
    "name:fil_x_preferred":[
        "Pantol"
    ],
    "wof:name":"Pantol",
    "wof:placetype":"locality"
},
  "geometry": {"coordinates":[119.9097,15.8884],"type":"Point"}
}