{
  "type": "Feature",
  "properties": {
    "gn:admin1_code":"02",
    "gn:admin2_code":"14",
    "gn:admin3_code":"21521000.0",
    "gn:asciiname":"Liwan",
    "gn:country_code":"PH",
    "gn:dem":39,
    "gn:feature_class":"P",
    "gn:feature_code":"PPL",
    "gn:name":"Liwan",
    "gn:population":0,
    "gn:timezone":"Asia/Manila",
    "iso:country":"PH",
    "name:fil_x_preferred":[
        "Liwan"
    ],
    "name:fil_x_variant":[
        "Liuan",
        "Livan"
    ],
    "name:und_x_variant":[
        "Livan"
    ],
    "wof:name":"Liwan",
    "wof:placetype":"locality"
},
  "geometry": {"coordinates":[121.4426,17.8093],"type":"Point"}
}