{
  "type": "Feature",
  "properties": {
    "gn:admin1_code":"02",
    "gn:admin2_code":"14",
    "gn:admin3_code":"21521000.0",
    "gn:asciiname":"Liwan",
    "gn:country_code":"PH",
    "gn:dem":39,
    "gn:feature_class":"P",
    "gn:feature_code":"PPL",
    "gn:name":"Liwan",
    "gn:population":0,
    "gn:timezone":"Asia/Manila",
    "iso:country":"PH",
    "name:ara_x_preferred":[
        "\u0644\u064a\u0648\u0627\u0646"
    ],
    "name:fil_x_preferred":[
        "Liwan"
    ],
    "name:fil_x_variant":[
        "Liuan",
        "Livan"
    ],
    "name:heb_x_preferred":[
        "\u05dc\u05d9\u05d5\u05d5\u05d0\u05df"
    ],
    "name:ita_x_preferred":[
        "L\u012bw\u0101n"
    ],
    "name:spa_x_preferred":[
        "Liwan"
    ],
    "name:urd_x_preferred":[
        "\u0644\u06cc\u0648\u0627\u0646"
    ],
    "wof:name":"Liwan",
    "wof:placetype":"locality"
},
  "geometry": {"coordinates":[121.4426,17.8093],"type":"Point"}
}