{
  "type": "Feature",
  "properties": {
    "gn:admin1_code":"06",
    "gn:admin2_code":"18",
    "gn:admin3_code":"61911000.0",
    "gn:asciiname":"Pinlabuan",
    "gn:country_code":"PH",
    "gn:dem":11,
    "gn:feature_class":"P",
    "gn:feature_code":"PPL",
    "gn:name":"Pinlabuan",
    "gn:population":0,
    "gn:timezone":"Asia/Manila",
    "iso:country":"PH",
    "name:fil_x_preferred":[
        "Pinlabuan"
    ],
    "name:und_x_variant":[
        "Pinanlabuan"
    ],
    "wof:name":"Pinlabuan",
    "wof:placetype":"locality"
},
  "geometry": {"coordinates":[123.08799999999999,11.5337],"type":"Point"}
}