{
  "type": "Feature",
  "properties": {
    "gn:admin1_code":"06",
    "gn:admin2_code":"06",
    "gn:admin3_code":"60602000.0",
    "gn:asciiname":"Igtunarum",
    "gn:country_code":"PH",
    "gn:dem":142,
    "gn:feature_class":"P",
    "gn:feature_code":"PPL",
    "gn:name":"Igtunarum",
    "gn:population":0,
    "gn:timezone":"Asia/Manila",
    "iso:country":"PH",
    "name:fil_x_preferred":[
        "Igtunarum"
    ],
    "wof:name":"Igtunarum",
    "wof:placetype":"locality"
},
  "geometry": {"coordinates":[122.09121,11.24792],"type":"Point"}
}