{
  "type": "Feature",
  "properties": {
    "gn:admin1_code":"09",
    "gn:admin2_code":"65",
    "gn:admin3_code":"97219000.0",
    "gn:asciiname":"Pina",
    "gn:country_code":"PH",
    "gn:dem":217,
    "gn:feature_class":"P",
    "gn:feature_code":"PPL",
    "gn:name":"Pi\u00f1a",
    "gn:population":0,
    "gn:timezone":"Asia/Manila",
    "iso:country":"PH",
    "name:arg_x_preferred":[
        "Pina"
    ],
    "name:bre_x_preferred":[
        "Pina"
    ],
    "name:cat_x_preferred":[
        "Pina"
    ],
    "name:ceb_x_preferred":[
        "Pina"
    ],
    "name:ces_x_preferred":[
        "Pina"
    ],
    "name:deu_x_preferred":[
        "Pina"
    ],
    "name:fas_x_preferred":[
        "\u067e\u06cc\u0646\u0627"
    ],
    "name:fil_x_preferred":[
        "Pi\u00f1a"
    ],
    "name:fra_x_preferred":[
        "Pina"
    ],
    "name:hun_x_preferred":[
        "Pina"
    ],
    "name:pol_x_preferred":[
        "Pina"
    ],
    "name:por_x_preferred":[
        "Pina"
    ],
    "name:spa_x_preferred":[
        "Pina"
    ],
    "name:swe_x_preferred":[
        "Pina"
    ],
    "wof:name":"Pina",
    "wof:placetype":"locality"
},
  "geometry": {"coordinates":[122.13861,7.60944],"type":"Point"}
}