{
  "type": "Feature",
  "properties": {
    "gn:admin1_code":"03",
    "gn:admin2_code":"47",
    "gn:admin3_code":"34903000.0",
    "gn:asciiname":"Kalikid Sur",
    "gn:country_code":"PH",
    "gn:dem":68,
    "gn:feature_class":"P",
    "gn:feature_code":"PPL",
    "gn:name":"Kalikid Sur",
    "gn:population":0,
    "gn:timezone":"Asia/Manila",
    "iso:country":"PH",
    "name:und_x_variant":[
        "South Calqued",
        "South Calikid",
        "Kalikid",
        "Kalikid Sur"
    ],
    "wof:name":"Kalikid Sur",
    "wof:placetype":"locality"
},
  "geometry": {"coordinates":[121.04968999999998,15.47962],"type":"Point"}
}