{
  "type": "Feature",
  "properties": {
    "gn:admin1_code":"01",
    "gn:admin2_code":"29",
    "gn:admin3_code":"12930000.0",
    "gn:asciiname":"Santa Cruz West",
    "gn:country_code":"PH",
    "gn:dem":9,
    "gn:feature_class":"P",
    "gn:feature_code":"PPL",
    "gn:name":"Santa Cruz West",
    "gn:population":0,
    "gn:timezone":"Asia/Manila",
    "iso:country":"PH",
    "name:eng_x_preferred":[
        "Santa Cruz West"
    ],
    "wof:name":"Santa Cruz West",
    "wof:placetype":"locality"
},
  "geometry": {"coordinates":[120.44880000000001,17.8785],"type":"Point"}
}