{
  "type": "Feature",
  "properties": {
    "gn:admin1_code":"10",
    "gn:admin2_code":"42",
    "gn:admin3_code":"104214000.0",
    "gn:asciiname":"Maikay",
    "gn:country_code":"PH",
    "gn:dem":44,
    "gn:feature_class":"P",
    "gn:feature_code":"PPL",
    "gn:name":"Maikay",
    "gn:population":0,
    "gn:timezone":"Asia/Manila",
    "iso:country":"PH",
    "name:eng_x_preferred":[
        "Maikay"
    ],
    "name:und_x_variant":[
        "Maicay"
    ],
    "wof:name":"Maikay",
    "wof:placetype":"locality"
},
  "geometry": {"coordinates":[123.8361,8.2715],"type":"Point"}
}