{
  "type": "Feature",
  "properties": {
    "gn:admin1_code":"40",
    "gn:admin2_code":"33",
    "gn:admin3_code":"43421000.0",
    "gn:asciiname":"Natividad",
    "gn:country_code":"PH",
    "gn:dem":6,
    "gn:feature_class":"P",
    "gn:feature_code":"PPL",
    "gn:name":"Natividad",
    "gn:population":0,
    "gn:timezone":"Asia/Manila",
    "iso:country":"PH",
    "name:fil_x_preferred":[
        "Natividad"
    ],
    "wof:name":"Natividad",
    "wof:placetype":"locality"
},
  "geometry": {"coordinates":[121.46720000000001,14.3991],"type":"Point"}
}