{
  "type": "Feature",
  "properties": {
    "gn:admin1_code":"07",
    "gn:admin2_code":"46",
    "gn:admin3_code":"74607000.0",
    "gn:asciiname":"Cambayin",
    "gn:country_code":"PH",
    "gn:dem":81,
    "gn:feature_class":"P",
    "gn:feature_code":"PPL",
    "gn:name":"Cambayin",
    "gn:population":0,
    "gn:timezone":"Asia/Manila",
    "iso:country":"PH",
    "name:fil_x_preferred":[
        "Cambayin"
    ],
    "wof:name":"Cambayin",
    "wof:placetype":"locality"
},
  "geometry": {"coordinates":[123.1114,9.7512],"type":"Point"}
}