{
  "type": "Feature",
  "properties": {
    "gn:admin1_code":"05",
    "gn:admin2_code":"19",
    "gn:admin3_code":"52008000.0",
    "gn:asciiname":"Comagaycay",
    "gn:country_code":"PH",
    "gn:dem":4,
    "gn:feature_class":"P",
    "gn:feature_code":"PPL",
    "gn:name":"Comagaycay",
    "gn:population":0,
    "gn:timezone":"Asia/Manila",
    "iso:country":"PH",
    "name:fil_x_preferred":[
        "Comagaycay"
    ],
    "wof:name":"Comagaycay",
    "wof:placetype":"locality"
},
  "geometry": {"coordinates":[124.0731,13.6043],"type":"Point"}
}