{
  "type": "Feature",
  "properties": {
    "gn:country":"PH",
    "gn:fcode":"PPL",
    "gn:pop":3011,
    "iso:country":"PH",
    "name:eng_x_preferred":[
        "Manaul"
    ],
    "name:fil_x_preferred":[
        "Manaul"
    ],
    "name:nld_x_preferred":[
        "Manaul"
    ],
    "name:por_x_preferred":[
        "Manaul"
    ],
    "name:spa_x_preferred":[
        "Manaul"
    ],
    "name:tgl_x_preferred":[
        "Manaul"
    ],
    "qs:name":"Manaul",
    "qs:photos_9r":0,
    "qs:photos_sr":0,
    "qs:pop_sr":"4",
    "wd:wordcount":146,
    "wof:name":"Manaul",
    "wof:placetype":"locality",
    "wof:population":3011
},
  "geometry": {"coordinates":[121.41070000000001,12.453],"type":"Point"}
}