{
  "type": "Feature",
  "properties": {
    "gn:admin1_code":"14",
    "gn:admin2_code":"60",
    "gn:admin3_code":"156605000.0",
    "gn:asciiname":"Darol-Gambangan",
    "gn:country_code":"PH",
    "gn:dem":33,
    "gn:feature_class":"P",
    "gn:feature_code":"PPL",
    "gn:name":"Darol-Gambangan",
    "gn:population":0,
    "gn:timezone":"Asia/Manila",
    "iso:country":"PH",
    "name:fil_x_preferred":[
        "Darol-Gambangan"
    ],
    "wof:name":"Darol-Gambangan",
    "wof:placetype":"locality"
},
  "geometry": {"coordinates":[121.02284,5.94496],"type":"Point"}
}