{
  "type": "Feature",
  "properties": {
    "gn:admin1_code":"07",
    "gn:admin2_code":"11",
    "gn:admin3_code":"71222000.0",
    "gn:asciiname":"Sacaon",
    "gn:country_code":"PH",
    "gn:dem":257,
    "gn:feature_class":"P",
    "gn:feature_code":"PPL",
    "gn:name":"Sacaon",
    "gn:population":0,
    "gn:timezone":"Asia/Manila",
    "iso:country":"PH",
    "name:fil_x_preferred":[
        "Sacaon"
    ],
    "wof:name":"Sacaon",
    "wof:placetype":"locality"
},
  "geometry": {"coordinates":[124.2897,9.653],"type":"Point"}
}