{
  "type": "Feature",
  "properties": {
    "gn:admin1_code":"41",
    "gn:admin2_code":"41",
    "gn:admin3_code":"175208000.0",
    "gn:asciiname":"Garis",
    "gn:country_code":"PH",
    "gn:dem":22,
    "gn:feature_class":"P",
    "gn:feature_code":"PPL",
    "gn:name":"Garis",
    "gn:population":0,
    "gn:timezone":"Asia/Manila",
    "iso:country":"PH",
    "name:fil_x_preferred":[
        "Garis"
    ],
    "wof:name":"Garis",
    "wof:placetype":"locality"
},
  "geometry": {"coordinates":[121.2349,13.2644],"type":"Point"}
}