{
  "type": "Feature",
  "properties": {
    "gn:admin1_code":"40",
    "gn:admin2_code":"H2",
    "gn:admin3_code":"45632000.0",
    "gn:asciiname":"Palaypayan",
    "gn:country_code":"PH",
    "gn:dem":11,
    "gn:feature_class":"P",
    "gn:feature_code":"PPL",
    "gn:name":"Palaypayan",
    "gn:population":0,
    "gn:timezone":"Asia/Manila",
    "iso:country":"PH",
    "name:fil_x_preferred":[
        "Palaypayan"
    ],
    "wof:name":"Palaypayan",
    "wof:placetype":"locality"
},
  "geometry": {"coordinates":[122.11669999999999,14.8009],"type":"Point"}
}