{
  "type": "Feature",
  "properties": {
    "gn:admin1_code":"09",
    "gn:admin2_code":"66",
    "gn:admin3_code":"97328000.0",
    "gn:asciiname":"Ludiong",
    "gn:country_code":"PH",
    "gn:dem":177,
    "gn:feature_class":"P",
    "gn:feature_code":"PPL",
    "gn:name":"Ludiong",
    "gn:population":0,
    "gn:timezone":"Asia/Manila",
    "iso:country":"PH",
    "name:eng_x_preferred":[
        "Ludiong"
    ],
    "wof:name":"Ludiong",
    "wof:placetype":"locality"
},
  "geometry": {"coordinates":[123.55200000000001,8.0928],"type":"Point"}
}