{
  "type": "Feature",
  "properties": {
    "gn:admin1_code":"15",
    "gn:admin2_code":"01",
    "gn:admin3_code":"140115000.0",
    "gn:asciiname":"Packed",
    "gn:country_code":"PH",
    "gn:dem":1075,
    "gn:feature_class":"P",
    "gn:feature_code":"PPL",
    "gn:name":"Packed",
    "gn:population":0,
    "gn:timezone":"Asia/Manila",
    "iso:country":"PH",
    "name:fil_x_preferred":[
        "Packed"
    ],
    "wof:name":"Packed",
    "wof:placetype":"locality"
},
  "geometry": {"coordinates":[121.06667,17.63332999999999],"type":"Point"}
}