{
  "type": "Feature",
  "properties": {
    "gn:admin1_code":"09",
    "gn:admin2_code":"65",
    "gn:admin3_code":"97214000.0",
    "gn:asciiname":"Tuboy",
    "gn:country_code":"PH",
    "gn:dem":442,
    "gn:feature_class":"P",
    "gn:feature_code":"PPL",
    "gn:name":"Tuboy",
    "gn:population":0,
    "gn:timezone":"Asia/Manila",
    "iso:country":"PH",
    "name:eng_x_preferred":[
        "Tuboy"
    ],
    "wof:name":"Tuboy",
    "wof:placetype":"locality"
},
  "geometry": {"coordinates":[123.2877,8.2837],"type":"Point"}
}