{
  "type": "Feature",
  "properties": {
    "gn:admin1_code":"13",
    "gn:admin2_code":"61",
    "gn:admin3_code":"166724000.0",
    "gn:asciiname":"Lungon",
    "gn:country_code":"PH",
    "gn:dem":85,
    "gn:feature_class":"P",
    "gn:feature_code":"PPL",
    "gn:name":"Lungon",
    "gn:population":0,
    "gn:timezone":"Asia/Manila",
    "iso:country":"PH",
    "name:fil_x_preferred":[
        "Lungon"
    ],
    "wof:name":"Lungon",
    "wof:placetype":"locality"
},
  "geometry": {"coordinates":[125.4739,9.6972],"type":"Point"}
}