{
  "type": "Feature",
  "properties": {
    "gn:country":"PH",
    "gn:fcode":"PPLA3",
    "gn:pop":4847,
    "iso:country":"PH",
    "name:rus_x_preferred":[
        "\u041a\u0430\u0440\u043c\u0435\u043d"
    ],
    "qs:name":"Carmen",
    "qs:photos_9r":0,
    "qs:photos_sr":0,
    "qs:pop_sr":"4",
    "wd:wordcount":7843,
    "wof:name":"Carmen",
    "wof:placetype":"locality",
    "wof:population":4847
},
  "geometry": {"coordinates":[125.2925,8.98861],"type":"Point"}
}