{
  "type": "Feature",
  "properties": {
    "gn:admin1_code":"15",
    "gn:admin2_code":"H6",
    "gn:admin3_code":"148102000.0",
    "gn:asciiname":"Bagumbong",
    "gn:country_code":"PH",
    "gn:dem":136,
    "gn:feature_class":"P",
    "gn:feature_code":"PPL",
    "gn:name":"Bagumbong",
    "gn:population":0,
    "gn:timezone":"Asia/Manila",
    "iso:country":"PH",
    "name:fil_x_preferred":[
        "Bagumbong"
    ],
    "wof:name":"Bagumbong",
    "wof:placetype":"locality"
},
  "geometry": {"coordinates":[121.31019999999999,17.7903],"type":"Point"}
}