{
  "type": "Feature",
  "properties": {
    "gn:admin1_code":"07",
    "gn:admin2_code":"21",
    "gn:admin3_code":"72241000.0",
    "gn:asciiname":"Poblacion South",
    "gn:country_code":"PH",
    "gn:dem":26,
    "gn:feature_class":"P",
    "gn:feature_code":"PPL",
    "gn:name":"Poblacion South",
    "gn:population":0,
    "gn:timezone":"Asia/Manila",
    "iso:country":"PH",
    "name:eng_x_preferred":[
        "Poblacion South"
    ],
    "wof:name":"Poblacion South",
    "wof:placetype":"locality"
},
  "geometry": {"coordinates":[123.702,10.1585],"type":"Point"}
}