{
  "type": "Feature",
  "properties": {
    "gn:admin1_code":"14",
    "gn:admin2_code":"56",
    "gn:admin3_code":"153824000.0",
    "gn:asciiname":"Bolloc",
    "gn:country_code":"PH",
    "gn:dem":14,
    "gn:feature_class":"P",
    "gn:feature_code":"PPL",
    "gn:name":"Bolloc",
    "gn:population":0,
    "gn:timezone":"Asia/Manila",
    "iso:country":"PH",
    "name:fil_x_preferred":[
        "Bolloc"
    ],
    "wof:name":"Bolloc",
    "wof:placetype":"locality"
},
  "geometry": {"coordinates":[124.25528,7.30639],"type":"Point"}
}