{
  "type": "Feature",
  "properties": {
    "gn:country":"PH",
    "gn:fcode":"ADM3",
    "gn:pop":0,
    "iso:country":"PH",
    "name:ceb_x_preferred":[
        "Naguilian"
    ],
    "name:deu_x_preferred":[
        "Naguilian"
    ],
    "name:fil_x_preferred":[
        "Naguilian"
    ],
    "name:fra_x_preferred":[
        "Naguilian"
    ],
    "name:ilo_x_preferred":[
        "Naguilian"
    ],
    "name:ita_x_preferred":[
        "Naguilian"
    ],
    "name:nld_x_preferred":[
        "Naguilian"
    ],
    "name:war_x_preferred":[
        "Naguilian"
    ],
    "qs:name":"Naguilian",
    "qs:photos_9r":0,
    "qs:photos_sr":0,
    "qs:pop_sr":"0",
    "wd:wordcount":15,
    "wof:name":"Naguilian",
    "wof:placetype":"localadmin",
    "wof:population":0
},
  "geometry": {"coordinates":[120.41667,16.53333],"type":"Point"}
}