{
  "type": "Feature",
  "properties": {
    "gn:admin1_code":"08",
    "gn:admin2_code":"37",
    "gn:admin3_code":"83749000.0",
    "gn:asciiname":"Tanghas",
    "gn:country_code":"PH",
    "gn:dem":11,
    "gn:feature_class":"P",
    "gn:feature_code":"PPL",
    "gn:name":"Tanghas",
    "gn:population":0,
    "gn:timezone":"Asia/Manila",
    "iso:country":"PH",
    "name:fil_x_preferred":[
        "Tanghas"
    ],
    "wof:name":"Tanghas",
    "wof:placetype":"locality"
},
  "geometry": {"coordinates":[125.03306000000001,11.04972],"type":"Point"}
}