{
  "type": "Feature",
  "properties": {
    "gn:admin1_code":"NCR",
    "gn:admin2_code":"137600000",
    "gn:admin3_code":"137606000.0",
    "gn:asciiname":"Martirez Del Noventa y Seis",
    "gn:country_code":"PH",
    "gn:dem":7,
    "gn:feature_class":"P",
    "gn:feature_code":"PPL",
    "gn:name":"Martirez Del Noventa y Seis",
    "gn:population":0,
    "gn:timezone":"Asia/Manila",
    "iso:country":"PH",
    "name:fil_x_preferred":[
        "Martires Del \u201996"
    ],
    "wof:name":"Martirez Del Noventa y Seis",
    "wof:placetype":"locality"
},
  "geometry": {"coordinates":[121.06896999999999,14.53989],"type":"Point"}
}