{
  "type": "Feature",
  "properties": {
    "gn:admin1_code":"09",
    "gn:admin2_code":"66",
    "gn:admin3_code":"97325000.0",
    "gn:asciiname":"Mabulay",
    "gn:country_code":"PH",
    "gn:dem":319,
    "gn:feature_class":"P",
    "gn:feature_code":"PPL",
    "gn:name":"Mabulay",
    "gn:population":0,
    "gn:timezone":"Asia/Manila",
    "iso:country":"PH",
    "wof:name":"Mabulay",
    "wof:placetype":"locality"
},
  "geometry": {"coordinates":[123.41222,7.69611],"type":"Point"}
}