{
  "type": "Feature",
  "properties": {
    "iso:country":"PH",
    "name:bcl_x_preferred":[
        "Masantol"
    ],
    "name:cat_x_preferred":[
        "Masantol"
    ],
    "name:cbk_zam_x_preferred":[
        "Masantol"
    ],
    "name:ceb_x_preferred":[
        "Masantol"
    ],
    "name:deu_x_preferred":[
        "Masantol"
    ],
    "name:eng_x_preferred":[
        "Masantol"
    ],
    "name:fil_x_preferred":[
        "Masantol"
    ],
    "name:fra_x_preferred":[
        "Masantol"
    ],
    "name:ilo_x_preferred":[
        "Masantol"
    ],
    "name:ind_x_preferred":[
        "Masantol"
    ],
    "name:ita_x_preferred":[
        "Masantol"
    ],
    "name:nld_x_preferred":[
        "Masantol"
    ],
    "name:nob_x_preferred":[
        "Masantol"
    ],
    "name:oci_x_preferred":[
        "Masantol"
    ],
    "name:pag_x_preferred":[
        "Masantol"
    ],
    "name:pam_x_preferred":[
        "Masantol"
    ],
    "name:swe_x_preferred":[
        "Masantol"
    ],
    "name:tgl_x_preferred":[
        "Masantol"
    ],
    "name:vie_x_preferred":[
        "Masantol"
    ],
    "name:war_x_preferred":[
        "Masantol"
    ],
    "qs:gn_country":"PH",
    "qs:gn_fcode":"PPLA3",
    "qs:gn_pop":41278,
    "qs:name":"Masantol",
    "qs:name_adm0":"Philippines",
    "qs:name_adm1":"Central Luzon",
    "qs:photos":5,
    "qs:photos_1k":1,
    "qs:photos_9k":1,
    "qs:photos_9r":1,
    "qs:photos_all":5,
    "qs:photos_sr":1,
    "qs:placetype":"Town",
    "qs:pop_sr":"7",
    "qs:woe_adm0":23424934,
    "wd:wordcount":1027,
    "wof:name":"Masantol",
    "wof:placetype":"locality",
    "wof:population":41278
},
  "geometry": {"coordinates":[120.7092,14.896],"type":"Point"}
}