{
  "type": "Feature",
  "properties": {
    "gn:admin1_code":"07",
    "gn:admin2_code":"11",
    "gn:admin3_code":"71209000.0",
    "gn:asciiname":"Cawag",
    "gn:country_code":"PH",
    "gn:dem":79,
    "gn:feature_class":"P",
    "gn:feature_code":"PPL",
    "gn:name":"Cawag",
    "gn:population":0,
    "gn:timezone":"Asia/Manila",
    "iso:country":"PH",
    "name:fil_x_preferred":[
        "Cawag"
    ],
    "wof:name":"Cawag",
    "wof:placetype":"locality"
},
  "geometry": {"coordinates":[124.16639000000001,10.04013],"type":"Point"}
}