{
  "type": "Feature",
  "properties": {
    "gn:admin1_code":"05",
    "gn:admin2_code":"58",
    "gn:asciiname":"Esmerada",
    "gn:country_code":"PH",
    "gn:dem":1,
    "gn:feature_class":"P",
    "gn:feature_code":"PPL",
    "gn:name":"Esmerada",
    "gn:population":0,
    "gn:timezone":"Asia/Manila",
    "iso:country":"PH",
    "name:fil_x_preferred":[
        "Esmerada"
    ],
    "wof:name":"Esmerada",
    "wof:placetype":"locality"
},
  "geometry": {"coordinates":[123.66667,12.91667],"type":"Point"}
}