{
  "type": "Feature",
  "properties": {
    "gn:admin1_code":"15",
    "gn:admin2_code":"H6",
    "gn:admin3_code":"148107000.0",
    "gn:asciiname":"Pilig",
    "gn:country_code":"PH",
    "gn:dem":15,
    "gn:feature_class":"P",
    "gn:feature_code":"PPL",
    "gn:name":"Pilig",
    "gn:population":0,
    "gn:timezone":"Asia/Manila",
    "iso:country":"PH",
    "name:fil_x_preferred":[
        "Pilig"
    ],
    "wof:name":"Pilig",
    "wof:placetype":"locality"
},
  "geometry": {"coordinates":[121.43486,18.25722],"type":"Point"}
}