{
  "type": "Feature",
  "properties": {
    "gn:admin1_code":"15",
    "gn:admin2_code":"44",
    "gn:admin3_code":"144402000.0",
    "gn:asciiname":"Banao",
    "gn:country_code":"PH",
    "gn:dem":1367,
    "gn:feature_class":"P",
    "gn:feature_code":"PPL",
    "gn:name":"Banao",
    "gn:population":0,
    "gn:timezone":"Asia/Manila",
    "iso:country":"PH",
    "name:fil_x_preferred":[
        "Banao"
    ],
    "wof:name":"Banao",
    "wof:placetype":"locality"
},
  "geometry": {"coordinates":[120.8763,16.9723],"type":"Point"}
}