{
  "type": "Feature",
  "properties": {
    "gn:admin1_code":"02",
    "gn:admin2_code":"48",
    "gn:admin3_code":"25002000.0",
    "gn:asciiname":"Baan",
    "gn:country_code":"PH",
    "gn:dem":510,
    "gn:feature_class":"P",
    "gn:feature_code":"PPL",
    "gn:name":"Baan",
    "gn:population":0,
    "gn:timezone":"Asia/Manila",
    "iso:country":"PH",
    "name:deu_x_preferred":[
        "Baan"
    ],
    "name:eng_x_preferred":[
        "Baan"
    ],
    "name:fry_x_preferred":[
        "Baan"
    ],
    "name:nld_x_preferred":[
        "Baan"
    ],
    "wof:name":"Baan",
    "wof:placetype":"locality"
},
  "geometry": {"coordinates":[120.9752,16.3064],"type":"Point"}
}