{
  "type": "Feature",
  "properties": {
    "gn:admin1_code":"40",
    "gn:admin2_code":"33",
    "gn:admin3_code":"43407000.0",
    "gn:asciiname":"Layog",
    "gn:country_code":"PH",
    "gn:dem":304,
    "gn:feature_class":"P",
    "gn:feature_code":"PPL",
    "gn:name":"Layog",
    "gn:population":0,
    "gn:timezone":"Asia/Manila",
    "iso:country":"PH",
    "name:fil_x_preferred":[
        "Layog"
    ],
    "wof:name":"Layog",
    "wof:placetype":"locality"
},
  "geometry": {"coordinates":[121.5378,14.2267],"type":"Point"}
}