{
  "type": "Feature",
  "properties": {
    "gn:admin1_code":"06",
    "gn:admin2_code":"30",
    "gn:admin3_code":"63028000.0",
    "gn:asciiname":"Bulad",
    "gn:country_code":"PH",
    "gn:dem":234,
    "gn:feature_class":"P",
    "gn:feature_code":"PPL",
    "gn:name":"Bulad",
    "gn:population":0,
    "gn:timezone":"Asia/Manila",
    "iso:country":"PH",
    "name:fil_x_preferred":[
        "Bulad"
    ],
    "name:und_x_variant":[
        "Maglapay",
        "Bulad-Magcapay"
    ],
    "wof:name":"Bulad",
    "wof:placetype":"locality"
},
  "geometry": {"coordinates":[122.35899999999999,10.80365],"type":"Point"}
}