{
  "type": "Feature",
  "properties": {
    "gn:admin1_code":"07",
    "gn:admin2_code":"46",
    "gn:admin3_code":"74609000.0",
    "gn:asciiname":"Baslay",
    "gn:country_code":"PH",
    "gn:dem":585,
    "gn:feature_class":"P",
    "gn:feature_code":"PPL",
    "gn:name":"Baslay",
    "gn:population":0,
    "gn:timezone":"Asia/Manila",
    "iso:country":"PH",
    "name:fil_x_preferred":[
        "Baslay"
    ],
    "wof:name":"Baslay",
    "wof:placetype":"locality"
},
  "geometry": {"coordinates":[123.2022,9.2134],"type":"Point"}
}