{
  "type": "Feature",
  "properties": {
    "gn:admin1_code":"41",
    "gn:admin2_code":"49",
    "gn:admin3_code":"175322000.0",
    "gn:asciiname":"Lasos",
    "gn:country_code":"PH",
    "gn:dem":21,
    "gn:feature_class":"P",
    "gn:feature_code":"PPL",
    "gn:name":"Lasos",
    "gn:population":0,
    "gn:timezone":"Asia/Manila",
    "iso:country":"PH",
    "name:eng_x_preferred":[
        "Lasos"
    ],
    "wof:name":"Lasos",
    "wof:placetype":"locality"
},
  "geometry": {"coordinates":[120.12949999999999,11.8186],"type":"Point"}
}