{
  "type": "Feature",
  "properties": {
    "gn:admin1_code":"15",
    "gn:admin2_code":"10",
    "gn:admin3_code":"141104000.0",
    "gn:asciiname":"Canibong",
    "gn:country_code":"PH",
    "gn:dem":999,
    "gn:feature_class":"P",
    "gn:feature_code":"PPL",
    "gn:name":"Canibong",
    "gn:population":0,
    "gn:timezone":"Asia/Manila",
    "iso:country":"PH",
    "name:eng_x_preferred":[
        "Canibong"
    ],
    "wof:name":"Canibong",
    "wof:placetype":"locality"
},
  "geometry": {"coordinates":[120.79940000000001,16.4829],"type":"Point"}
}