{
  "type": "Feature",
  "properties": {
    "gn:admin1_code":"05",
    "gn:admin2_code":"16",
    "gn:admin3_code":"51737000.0",
    "gn:asciiname":"Gongonan",
    "gn:country_code":"PH",
    "gn:dem":76,
    "gn:feature_class":"P",
    "gn:feature_code":"PPL",
    "gn:name":"Gongonan",
    "gn:population":0,
    "gn:timezone":"Asia/Manila",
    "iso:country":"PH",
    "name:fil_x_preferred":[
        "Gongonan"
    ],
    "wof:name":"Gongonan",
    "wof:placetype":"locality"
},
  "geometry": {"coordinates":[123.3801,13.938],"type":"Point"}
}