{
  "type": "Feature",
  "properties": {
    "gn:admin1_code":"06",
    "gn:admin2_code":"H3",
    "gn:admin3_code":"64511000.0",
    "gn:asciiname":"Duran",
    "gn:country_code":"PH",
    "gn:dem":21,
    "gn:feature_class":"P",
    "gn:feature_code":"PPL",
    "gn:name":"Duran",
    "gn:population":0,
    "gn:timezone":"Asia/Manila",
    "iso:country":"PH",
    "name:cat_x_preferred":[
        "Duran"
    ],
    "name:ceb_x_preferred":[
        "Duran"
    ],
    "name:deu_x_preferred":[
        "Duran"
    ],
    "name:epo_x_preferred":[
        "Duran"
    ],
    "name:fil_x_preferred":[
        "Duran"
    ],
    "name:fra_x_preferred":[
        "Duran"
    ],
    "name:heb_x_preferred":[
        "\u05d3\u05d5\u05e8\u05d0\u05df"
    ],
    "name:ita_x_preferred":[
        "Duran"
    ],
    "name:pol_x_preferred":[
        "Duran"
    ],
    "name:por_x_preferred":[
        "Duran"
    ],
    "name:rus_x_preferred":[
        "\u0414\u0443\u0440\u0430\u043d"
    ],
    "name:swe_x_preferred":[
        "Duran"
    ],
    "name:tur_x_preferred":[
        "Duran"
    ],
    "wof:name":"Duran",
    "wof:placetype":"locality"
},
  "geometry": {"coordinates":[122.9075,10.3168],"type":"Point"}
}