{
  "type": "Feature",
  "properties": {
    "gn:admin1_code":"10",
    "gn:admin2_code":"12",
    "gn:admin3_code":"101314000.0",
    "gn:asciiname":"Minsuro",
    "gn:country_code":"PH",
    "gn:dem":76,
    "gn:feature_class":"P",
    "gn:feature_code":"PPL",
    "gn:name":"Minsuro",
    "gn:population":0,
    "gn:timezone":"Asia/Manila",
    "iso:country":"PH",
    "name:fil_x_preferred":[
        "Minsuro"
    ],
    "wof:name":"Minsuro",
    "wof:placetype":"locality"
},
  "geometry": {"coordinates":[124.83,8.50222],"type":"Point"}
}