{
  "type": "Feature",
  "properties": {
    "gn:admin1_code":"41",
    "gn:admin2_code":"54",
    "gn:admin3_code":"175901000.0",
    "gn:asciiname":"Lauan",
    "gn:country_code":"PH",
    "gn:dem":13,
    "gn:feature_class":"P",
    "gn:feature_code":"PPL",
    "gn:name":"Lauan",
    "gn:population":0,
    "gn:timezone":"Asia/Manila",
    "iso:country":"PH",
    "name:fil_x_preferred":[
        "Lauan"
    ],
    "name:und_x_variant":[
        "Lanan"
    ],
    "wof:name":"Lauan",
    "wof:placetype":"locality"
},
  "geometry": {"coordinates":[122.0654,12.2776],"type":"Point"}
}