{
  "type": "Feature",
  "properties": {
    "gn:admin1_code":"06",
    "gn:admin2_code":"30",
    "gn:admin3_code":"63027000.0",
    "gn:asciiname":"Talaytay",
    "gn:country_code":"PH",
    "gn:dem":90,
    "gn:feature_class":"P",
    "gn:feature_code":"PPL",
    "gn:name":"Talaytay",
    "gn:population":0,
    "gn:timezone":"Asia/Manila",
    "iso:country":"PH",
    "name:fil_x_preferred":[
        "Talaytay"
    ],
    "wof:name":"Talaytay",
    "wof:placetype":"locality"
},
  "geometry": {"coordinates":[122.92919999999999,11.2174],"type":"Point"}
}