{
  "type": "Feature",
  "properties": {
    "gn:admin1_code":"01",
    "gn:admin2_code":"28",
    "gn:admin3_code":"12817000.0",
    "gn:asciiname":"Sulbec",
    "gn:country_code":"PH",
    "gn:dem":45,
    "gn:feature_class":"P",
    "gn:feature_code":"PPL",
    "gn:name":"Sulbec",
    "gn:population":0,
    "gn:timezone":"Asia/Manila",
    "iso:country":"PH",
    "name:fil_x_preferred":[
        "Sulbec"
    ],
    "wof:name":"Sulbec",
    "wof:placetype":"locality"
},
  "geometry": {"coordinates":[120.63890000000001,18.3491],"type":"Point"}
}