{
  "type": "Feature",
  "properties": {
    "gn:admin1_code":"10",
    "gn:admin2_code":"34",
    "gn:admin3_code":"103509000.0",
    "gn:asciiname":"Matampay",
    "gn:country_code":"PH",
    "gn:dem":4,
    "gn:feature_class":"P",
    "gn:feature_code":"PPL",
    "gn:name":"Matampay",
    "gn:population":0,
    "gn:timezone":"Asia/Manila",
    "iso:country":"PH",
    "name:eng_x_preferred":[
        "Matampay"
    ],
    "wof:name":"Matampay",
    "wof:placetype":"locality"
},
  "geometry": {"coordinates":[123.7351,7.9753],"type":"Point"}
}