{
  "type": "Feature",
  "properties": {
    "gn:admin1_code":"01",
    "gn:admin2_code":"36",
    "gn:admin3_code":"13303000.0",
    "gn:asciiname":"Mabanengbeng Second",
    "gn:country_code":"PH",
    "gn:dem":182,
    "gn:feature_class":"P",
    "gn:feature_code":"PPL",
    "gn:name":"Mabanengbeng Second",
    "gn:population":0,
    "gn:timezone":"Asia/Manila",
    "iso:country":"PH",
    "name:fil_x_preferred":[
        "Mabanengbeng Second"
    ],
    "wof:name":"Mabanengbeng Second",
    "wof:placetype":"locality"
},
  "geometry": {"coordinates":[120.36667,16.78333],"type":"Point"}
}