{
  "type": "Feature",
  "properties": {
    "gn:admin1_code":"06",
    "gn:admin2_code":"H3",
    "gn:admin3_code":"64517000.0",
    "gn:asciiname":"Mansilingan",
    "gn:country_code":"PH",
    "gn:dem":243,
    "gn:feature_class":"P",
    "gn:feature_code":"PPL",
    "gn:name":"Mansilingan",
    "gn:population":0,
    "gn:timezone":"Asia/Manila",
    "iso:country":"PH",
    "name:fil_x_preferred":[
        "Mansilingan"
    ],
    "wof:name":"Mansilingan",
    "wof:placetype":"locality"
},
  "geometry": {"coordinates":[123.0706,10.3514],"type":"Point"}
}