{
  "type": "Feature",
  "properties": {
    "gn:admin1_code":"01",
    "gn:admin2_code":"36",
    "gn:admin3_code":"13310000.0",
    "gn:asciiname":"Nalvo Sur",
    "gn:country_code":"PH",
    "gn:dem":16,
    "gn:feature_class":"P",
    "gn:feature_code":"PPL",
    "gn:name":"Nalvo Sur",
    "gn:population":0,
    "gn:timezone":"Asia/Manila",
    "iso:country":"PH",
    "name:fil_x_preferred":[
        "Nalvo Sur"
    ],
    "wof:name":"Nalvo Sur",
    "wof:placetype":"locality"
},
  "geometry": {"coordinates":[120.3541,16.8379],"type":"Point"}
}