{
  "type": "Feature",
  "properties": {
    "gn:admin1_code":"03",
    "gn:admin2_code":"47",
    "gn:admin3_code":"34908000.0",
    "gn:asciiname":"Marelo",
    "gn:country_code":"PH",
    "gn:dem":14,
    "gn:feature_class":"P",
    "gn:feature_code":"PPL",
    "gn:name":"Marelo",
    "gn:population":0,
    "gn:timezone":"Asia/Manila",
    "iso:country":"PH",
    "name:fil_x_preferred":[
        "Marelo"
    ],
    "wof:name":"Marelo",
    "wof:placetype":"locality"
},
  "geometry": {"coordinates":[120.93142,15.22166],"type":"Point"}
}