{
  "type": "Feature",
  "properties": {
    "gn:admin1_code":"14",
    "gn:admin2_code":"22",
    "gn:asciiname":"Isla de Linungan",
    "gn:country_code":"PH",
    "gn:dem":-9999,
    "gn:feature_class":"P",
    "gn:feature_code":"PPL",
    "gn:name":"Isla de Linungan",
    "gn:population":0,
    "gn:timezone":"Asia/Manila",
    "iso:country":"PH",
    "name:fil_x_preferred":[
        "Isla de Linungan"
    ],
    "wof:name":"Isla de Linungan",
    "wof:placetype":"locality"
},
  "geometry": {"coordinates":[122.25,6.73333],"type":"Point"}
}