{
  "type": "Feature",
  "properties": {
    "gn:admin1_code":"02",
    "gn:admin2_code":"31",
    "gn:admin3_code":"23102000.0",
    "gn:asciiname":"Bunnay",
    "gn:country_code":"PH",
    "gn:dem":63,
    "gn:feature_class":"P",
    "gn:feature_code":"PPL",
    "gn:name":"Bunnay",
    "gn:population":0,
    "gn:timezone":"Asia/Manila",
    "iso:country":"PH",
    "name:fil_x_preferred":[
        "Bunnay"
    ],
    "name:fil_x_variant":[
        "Burnay"
    ],
    "name:und_x_variant":[
        "Burnay"
    ],
    "wof:name":"Bunnay",
    "wof:placetype":"locality"
},
  "geometry": {"coordinates":[121.77034,16.76023],"type":"Point"}
}