{
  "type": "Feature",
  "properties": {
    "gn:admin1_code":"05",
    "gn:admin2_code":"05",
    "gn:admin3_code":"50507000.0",
    "gn:asciiname":"East Carisac",
    "gn:country_code":"PH",
    "gn:dem":18,
    "gn:feature_class":"P",
    "gn:feature_code":"PPL",
    "gn:name":"East Carisac",
    "gn:population":0,
    "gn:timezone":"Asia/Manila",
    "iso:country":"PH",
    "name:eng_x_preferred":[
        "East Carisac"
    ],
    "name:und_x_variant":[
        "Carisac"
    ],
    "wof:name":"East Carisac",
    "wof:placetype":"locality"
},
  "geometry": {"coordinates":[123.4442,13.3084],"type":"Point"}
}