{
  "type": "Feature",
  "properties": {
    "gn:admin1_code":"15",
    "gn:admin2_code":"44",
    "gn:admin3_code":"144410000.0",
    "gn:asciiname":"Mantiba",
    "gn:country_code":"PH",
    "gn:dem":795,
    "gn:feature_class":"P",
    "gn:feature_code":"PPL",
    "gn:name":"Mantiba",
    "gn:population":0,
    "gn:timezone":"Asia/Manila",
    "iso:country":"PH",
    "name:fil_x_preferred":[
        "Mantiba"
    ],
    "wof:name":"Mantiba",
    "wof:placetype":"locality"
},
  "geometry": {"coordinates":[120.7833,16.95],"type":"Point"}
}