{
  "type": "Feature",
  "properties": {
    "gn:admin1_code":"14",
    "gn:admin2_code":"72",
    "gn:admin3_code":"157002000.0",
    "gn:asciiname":"Pababag",
    "gn:cc2":"PH",
    "gn:country_code":"PH",
    "gn:dem":0,
    "gn:feature_class":"P",
    "gn:feature_code":"PPL",
    "gn:name":"Pababag",
    "gn:population":0,
    "gn:timezone":"Asia/Manila",
    "iso:country":"PH",
    "name:und_x_variant":[
        "Pabahag",
        "Papahag",
        "Pababag"
    ],
    "wof:name":"Pababag",
    "wof:placetype":"locality"
},
  "geometry": {"coordinates":[119.79222,5.03167],"type":"Point"}
}