{
  "type": "Feature",
  "properties": {
    "gn:admin1_code":"02",
    "gn:admin2_code":"31",
    "gn:admin3_code":"23105000.0",
    "gn:asciiname":"Malasin",
    "gn:country_code":"PH",
    "gn:dem":56,
    "gn:feature_class":"P",
    "gn:feature_code":"PPL",
    "gn:name":"Malasin",
    "gn:population":0,
    "gn:timezone":"Asia/Manila",
    "iso:country":"PH",
    "name:fil_x_preferred":[
        "Malasin"
    ],
    "wof:name":"Malasin",
    "wof:placetype":"locality"
},
  "geometry": {"coordinates":[121.69873,17.05148],"type":"Point"}
}