{
  "type": "Feature",
  "properties": {
    "gn:admin1_code":"03",
    "gn:admin2_code":"47",
    "gn:admin3_code":"34910000.0",
    "gn:asciiname":"Poblacion West",
    "gn:country_code":"PH",
    "gn:dem":46,
    "gn:feature_class":"P",
    "gn:feature_code":"PPL",
    "gn:name":"Poblacion West",
    "gn:population":0,
    "gn:timezone":"Asia/Manila",
    "iso:country":"PH",
    "wof:name":"Poblacion West",
    "wof:placetype":"locality"
},
  "geometry": {"coordinates":[121.02628,15.34367],"type":"Point"}
}