{
  "type": "Feature",
  "properties": {
    "gn:admin1_code":"12",
    "gn:admin2_code":"71",
    "gn:admin3_code":"126511000.0",
    "gn:asciiname":"New Passi",
    "gn:country_code":"PH",
    "gn:dem":80,
    "gn:feature_class":"P",
    "gn:feature_code":"PPL",
    "gn:name":"New Passi",
    "gn:population":0,
    "gn:timezone":"Asia/Manila",
    "iso:country":"PH",
    "name:fil_x_preferred":[
        "New Passi"
    ],
    "wof:name":"New Passi",
    "wof:placetype":"locality"
},
  "geometry": {"coordinates":[124.67776000000001,6.60587],"type":"Point"}
}