{
  "type": "Feature",
  "properties": {
    "gn:admin1_code":"40",
    "gn:admin2_code":"53",
    "gn:admin3_code":"45802000.0",
    "gn:asciiname":"Upper Bosoboso",
    "gn:country_code":"PH",
    "gn:dem":183,
    "gn:feature_class":"P",
    "gn:feature_code":"PPL",
    "gn:name":"Upper Bosoboso",
    "gn:population":0,
    "gn:timezone":"Asia/Manila",
    "iso:country":"PH",
    "name:fil_x_preferred":[
        "Upper Bosoboso"
    ],
    "name:und_x_variant":[
        "Bosoboso",
        "New Bosoboso"
    ],
    "wof:name":"Upper Bosoboso",
    "wof:placetype":"locality"
},
  "geometry": {"coordinates":[121.24769999999999,14.628],"type":"Point"}
}