{
  "type": "Feature",
  "properties": {
    "gn:admin1_code":"06",
    "gn:admin2_code":"30",
    "gn:admin3_code":"63040000.0",
    "gn:asciiname":"Domaran",
    "gn:country_code":"PH",
    "gn:dem":331,
    "gn:feature_class":"P",
    "gn:feature_code":"PPL",
    "gn:name":"Domaran",
    "gn:population":0,
    "gn:timezone":"Asia/Manila",
    "iso:country":"PH",
    "name:fil_x_preferred":[
        "Domaran"
    ],
    "wof:name":"Domaran",
    "wof:placetype":"locality"
},
  "geometry": {"coordinates":[122.0672,10.6177],"type":"Point"}
}