{
  "type": "Feature",
  "properties": {
    "gn:admin1_code":"40",
    "gn:admin2_code":"H2",
    "gn:admin3_code":"45603000.0",
    "gn:asciiname":"Tagbakin",
    "gn:country_code":"PH",
    "gn:dem":8,
    "gn:feature_class":"P",
    "gn:feature_code":"PPL",
    "gn:name":"Tagbakin",
    "gn:population":0,
    "gn:timezone":"Asia/Manila",
    "iso:country":"PH",
    "name:fil_x_preferred":[
        "Tagbakin"
    ],
    "wof:name":"Tagbakin",
    "wof:placetype":"locality"
},
  "geometry": {"coordinates":[121.91083,13.9973],"type":"Point"}
}