{
  "type": "Feature",
  "properties": {
    "gn:admin1_code":"07",
    "gn:admin2_code":"11",
    "gn:admin3_code":"71244000.0",
    "gn:asciiname":"Kinan-oan",
    "gn:country_code":"PH",
    "gn:dem":18,
    "gn:feature_class":"P",
    "gn:feature_code":"PPL",
    "gn:name":"Kinan-oan",
    "gn:population":0,
    "gn:timezone":"Asia/Manila",
    "iso:country":"PH",
    "name:und_x_variant":[
        "Kinanuan",
        "Kinanoan",
        "Kinan-oan"
    ],
    "wof:name":"Kinan-oan",
    "wof:placetype":"locality"
},
  "geometry": {"coordinates":[124.32708999999998,10.06077],"type":"Point"}
}