{
  "type": "Feature",
  "properties": {
    "gn:admin1_code":"15",
    "gn:admin2_code":"44",
    "gn:admin3_code":"144406000.0",
    "gn:asciiname":"Masablang",
    "gn:country_code":"PH",
    "gn:dem":170,
    "gn:feature_class":"P",
    "gn:feature_code":"PPL",
    "gn:name":"Masablang",
    "gn:population":0,
    "gn:timezone":"Asia/Manila",
    "iso:country":"PH",
    "name:fil_x_preferred":[
        "Masablang"
    ],
    "name:fil_x_variant":[
        "Masundang",
        "Masudang"
    ],
    "name:und_x_variant":[
        "Masundang",
        "Masudang"
    ],
    "wof:name":"Masablang",
    "wof:placetype":"locality"
},
  "geometry": {"coordinates":[121.43053999999999,17.18884],"type":"Point"}
}