{
  "type": "Feature",
  "properties": {
    "gn:admin1_code":"06",
    "gn:admin2_code":"06",
    "gn:admin3_code":"60601000.0",
    "gn:asciiname":"Bariri",
    "gn:country_code":"PH",
    "gn:dem":84,
    "gn:feature_class":"P",
    "gn:feature_code":"PPL",
    "gn:name":"Bariri",
    "gn:population":0,
    "gn:timezone":"Asia/Manila",
    "iso:country":"PH",
    "name:bpy_x_preferred":[
        "\u09ac\u09be\u09b0\u09bf\u09b0\u09bf"
    ],
    "name:ceb_x_preferred":[
        "Bariri"
    ],
    "name:epo_x_preferred":[
        "Bariri"
    ],
    "name:eus_x_preferred":[
        "Bariri"
    ],
    "name:fil_x_preferred":[
        "Bariri"
    ],
    "name:fra_x_preferred":[
        "Bariri"
    ],
    "name:ita_x_preferred":[
        "Bariri"
    ],
    "name:kaz_x_preferred":[
        "\u0411\u0430\u0440\u0438\u0440\u0438"
    ],
    "name:mlg_x_preferred":[
        "Bariri"
    ],
    "name:nld_x_preferred":[
        "Bariri"
    ],
    "name:nor_x_preferred":[
        "Bariri"
    ],
    "name:pol_x_preferred":[
        "Bariri"
    ],
    "name:por_x_preferred":[
        "Bariri"
    ],
    "name:ron_x_preferred":[
        "Bariri"
    ],
    "name:rus_x_preferred":[
        "\u0411\u0430\u0440\u0438\u0440\u0438"
    ],
    "name:swe_x_preferred":[
        "Bariri"
    ],
    "name:vie_x_preferred":[
        "Bariri"
    ],
    "name:vol_x_preferred":[
        "Bariri"
    ],
    "name:war_x_preferred":[
        "Bariri"
    ],
    "name:zho_x_preferred":[
        "\u5df4\u91cc\u91cc"
    ],
    "wof:name":"Bariri",
    "wof:placetype":"locality"
},
  "geometry": {"coordinates":[121.9723,10.4354],"type":"Point"}
}