{
  "type": "Feature",
  "properties": {
    "gn:admin1_code":"06",
    "gn:admin2_code":"06",
    "gn:admin3_code":"60601000.0",
    "gn:asciiname":"Bariri",
    "gn:country_code":"PH",
    "gn:dem":84,
    "gn:feature_class":"P",
    "gn:feature_code":"PPL",
    "gn:name":"Bariri",
    "gn:population":0,
    "gn:timezone":"Asia/Manila",
    "iso:country":"PH",
    "name:fil_x_preferred":[
        "Bariri"
    ],
    "wof:name":"Bariri",
    "wof:placetype":"locality"
},
  "geometry": {"coordinates":[121.9723,10.4354],"type":"Point"}
}