{
  "type": "Feature",
  "properties": {
    "gn:admin1_code":"06",
    "gn:admin2_code":"06",
    "gn:admin3_code":"60601000.0",
    "gn:asciiname":"Bariri",
    "gn:country_code":"PH",
    "gn:dem":84,
    "gn:feature_class":"P",
    "gn:feature_code":"PPL",
    "gn:name":"Bariri",
    "gn:population":0,
    "gn:timezone":"Asia/Manila",
    "iso:country":"PH",
    "name:ara_x_preferred":[
        "\u0628\u0627\u0631\u064a\u0631\u064a"
    ],
    "name:ben_x_preferred":[
        "\u09ac\u09be\u09b0\u09bf\u09b0\u09bf"
    ],
    "name:bpy_x_preferred":[
        "\u09ac\u09be\u09b0\u09bf\u09b0\u09bf"
    ],
    "name:ceb_x_preferred":[
        "Bariri"
    ],
    "name:deu_x_preferred":[
        "Bariri"
    ],
    "name:ell_x_preferred":[
        "\u039c\u03c0\u03b1\u03c1\u03af\u03c1\u03b9"
    ],
    "name:epo_x_preferred":[
        "Bariri"
    ],
    "name:eus_x_preferred":[
        "Bariri"
    ],
    "name:fas_x_preferred":[
        "\u0628\u0627\u0631\u06cc\u0631\u06cc"
    ],
    "name:fil_x_preferred":[
        "Bariri"
    ],
    "name:fra_x_preferred":[
        "Power Plant Bariri"
    ],
    "name:fra_x_variant":[
        "Bariri"
    ],
    "name:heb_x_preferred":[
        "\u05d1\u05d0\u05e8\u05d9\u05e8\u05d9"
    ],
    "name:hin_x_preferred":[
        "\u092c\u0930\u093f\u0930\u0940"
    ],
    "name:hun_x_preferred":[
        "Bariri"
    ],
    "name:ind_x_preferred":[
        "Bariri"
    ],
    "name:ita_x_preferred":[
        "Bariri"
    ],
    "name:jpn_x_preferred":[
        "\u30d0\u30ea\u30ea\u8caf\u6c34\u6e56"
    ],
    "name:kaz_x_preferred":[
        "\u0411\u0430\u0440\u0438\u0440\u0438"
    ],
    "name:kor_x_preferred":[
        "\ubc14\ub9ac\ub9ac"
    ],
    "name:mlg_x_preferred":[
        "Bariri"
    ],
    "name:nld_x_preferred":[
        "Bariri"
    ],
    "name:nor_x_preferred":[
        "Bariri"
    ],
    "name:pol_x_preferred":[
        "Bariri"
    ],
    "name:por_x_preferred":[
        "Bariri"
    ],
    "name:ron_x_preferred":[
        "Bariri"
    ],
    "name:rus_x_preferred":[
        "\u0411\u0430\u0440\u0438\u0440\u0438"
    ],
    "name:spa_x_preferred":[
        "Bariri"
    ],
    "name:swe_x_preferred":[
        "Bariri"
    ],
    "name:tur_x_preferred":[
        "Bariri"
    ],
    "name:ukr_x_preferred":[
        "\u0411\u0430\u0440\u0456\u0440\u0456"
    ],
    "name:urd_x_preferred":[
        "\u0628\u0627\u0631\u06cc\u0631\u06cc"
    ],
    "name:vie_x_preferred":[
        "H\u1ed3 Bariri"
    ],
    "name:vie_x_variant":[
        "Bariri"
    ],
    "name:vol_x_preferred":[
        "Bariri"
    ],
    "name:war_x_preferred":[
        "Bariri"
    ],
    "name:zho_cn_x_preferred":[
        "\u5df4\u91cc\u91cc\u6c34\u5e93"
    ],
    "name:zho_tw_x_preferred":[
        "\u5df4\u5229\u5229"
    ],
    "name:zho_x_preferred":[
        "\u5df4\u91cc\u91cc"
    ],
    "wof:name":"Bariri",
    "wof:placetype":"locality"
},
  "geometry": {"coordinates":[121.9723,10.4354],"type":"Point"}
}