{
  "type": "Feature",
  "properties": {
    "gn:admin1_code":"08",
    "gn:admin2_code":"59",
    "gn:admin3_code":"86404000.0",
    "gn:asciiname":"Navalita",
    "gn:country_code":"PH",
    "gn:dem":65,
    "gn:feature_class":"P",
    "gn:feature_code":"PPL",
    "gn:name":"Navalita",
    "gn:population":0,
    "gn:timezone":"Asia/Manila",
    "iso:country":"PH",
    "name:fil_x_preferred":[
        "Navalita"
    ],
    "wof:name":"Navalita",
    "wof:placetype":"locality"
},
  "geometry": {"coordinates":[125.25,10.36667],"type":"Point"}
}