{
  "type": "Feature",
  "properties": {
    "gn:admin1_code":"41",
    "gn:admin2_code":"41",
    "gn:admin3_code":"175207000.0",
    "gn:asciiname":"Batobulawan",
    "gn:country_code":"PH",
    "gn:dem":35,
    "gn:feature_class":"P",
    "gn:feature_code":"PPL",
    "gn:name":"Batobulawan",
    "gn:population":0,
    "gn:timezone":"Asia/Manila",
    "iso:country":"PH",
    "name:fil_x_preferred":[
        "Batobulawan"
    ],
    "name:und_x_variant":[
        "Batobalawan"
    ],
    "wof:name":"Batobulawan",
    "wof:placetype":"locality"
},
  "geometry": {"coordinates":[121.41961000000001,12.50354],"type":"Point"}
}