{
  "type": "Feature",
  "properties": {
    "gn:admin1_code":"02",
    "gn:admin2_code":"48",
    "gn:admin3_code":"25003000.0",
    "gn:asciiname":"Paniqui",
    "gn:country_code":"PH",
    "gn:dem":226,
    "gn:feature_class":"P",
    "gn:feature_code":"PPL",
    "gn:name":"Paniqui",
    "gn:population":0,
    "gn:timezone":"Asia/Manila",
    "iso:country":"PH",
    "name:fil_x_preferred":[
        "Paniqui"
    ],
    "name:fil_x_variant":[
        "Paniki"
    ],
    "wof:name":"Paniqui",
    "wof:placetype":"locality"
},
  "geometry": {"coordinates":[121.21523999999999,16.62908],"type":"Point"}
}