{
  "type": "Feature",
  "properties": {
    "gn:admin1_code":"06",
    "gn:admin2_code":"H3",
    "gn:admin3_code":"64508000.0",
    "gn:asciiname":"Sinaypanan",
    "gn:country_code":"PH",
    "gn:dem":194,
    "gn:feature_class":"P",
    "gn:feature_code":"PPL",
    "gn:name":"Sinaypanan",
    "gn:population":0,
    "gn:timezone":"Asia/Manila",
    "iso:country":"PH",
    "name:fil_x_preferred":[
        "Sinaypanan"
    ],
    "wof:name":"Sinaypanan",
    "wof:placetype":"locality"
},
  "geometry": {"coordinates":[123.1482,10.7956],"type":"Point"}
}