{
  "type": "Feature",
  "properties": {
    "gn:admin1_code":"03",
    "gn:admin2_code":"50",
    "gn:admin3_code":"35406000.0",
    "gn:asciiname":"Maligaya",
    "gn:country_code":"PH",
    "gn:dem":26,
    "gn:feature_class":"P",
    "gn:feature_code":"PPL",
    "gn:name":"Maligaya",
    "gn:population":0,
    "gn:timezone":"Asia/Manila",
    "iso:country":"PH",
    "wof:name":"Maligaya",
    "wof:placetype":"locality"
},
  "geometry": {"coordinates":[120.52265,14.97572],"type":"Point"}
}