{
  "type": "Feature",
  "properties": {
    "gn:admin1_code":"14",
    "gn:admin2_code":"60",
    "gn:admin3_code":"156613000.0",
    "gn:asciiname":"Datag-Buntod",
    "gn:country_code":"PH",
    "gn:dem":130,
    "gn:feature_class":"P",
    "gn:feature_code":"PPL",
    "gn:name":"Datag-Buntod",
    "gn:population":0,
    "gn:timezone":"Asia/Manila",
    "iso:country":"PH",
    "name:und_x_variant":[
        "Datag"
    ],
    "wof:name":"Datag-Buntod",
    "wof:placetype":"locality"
},
  "geometry": {"coordinates":[121.11769,5.98176],"type":"Point"}
}