{
  "type": "Feature",
  "properties": {
    "gn:admin1_code":"01",
    "gn:admin2_code":"51",
    "gn:admin3_code":"15543000.0",
    "gn:asciiname":"Capalpaliaan",
    "gn:country_code":"PH",
    "gn:dem":61,
    "gn:feature_class":"P",
    "gn:feature_code":"PPL",
    "gn:name":"Capalpaliaan",
    "gn:population":0,
    "gn:timezone":"Asia/Manila",
    "iso:country":"PH",
    "name:fil_x_preferred":[
        "Capalpaliaan"
    ],
    "wof:name":"Capalpaliaan",
    "wof:placetype":"locality"
},
  "geometry": {"coordinates":[120.76130000000001,15.9789],"type":"Point"}
}