{
  "type": "Feature",
  "properties": {
    "gn:admin1_code":"40",
    "gn:admin2_code":"20",
    "gn:admin3_code":"42122000.0",
    "gn:asciiname":"Lapidario",
    "gn:country_code":"PH",
    "gn:dem":121,
    "gn:feature_class":"P",
    "gn:feature_code":"PPL",
    "gn:name":"Lapidario",
    "gn:population":0,
    "gn:timezone":"Asia/Manila",
    "iso:country":"PH",
    "name:fil_x_preferred":[
        "Lapidario"
    ],
    "name:und_x_variant":[
        "Bayog"
    ],
    "wof:name":"Lapidario",
    "wof:placetype":"locality"
},
  "geometry": {"coordinates":[120.86391999999999,14.27571],"type":"Point"}
}