{
  "type": "Feature",
  "properties": {
    "iso:country":"PH",
    "name:bcl_x_preferred":[
        "Katipunan"
    ],
    "name:dut_x_preferred":[
        "Katipunan"
    ],
    "name:eng_x_preferred":[
        "Katipunan"
    ],
    "name:fre_x_preferred":[
        "Katipunan"
    ],
    "name:ger_x_preferred":[
        "Katipunan"
    ],
    "name:ilo_x_preferred":[
        "Katipunan"
    ],
    "name:ind_x_preferred":[
        "Katipunan"
    ],
    "name:ita_x_preferred":[
        "Katipunan"
    ],
    "name:pag_x_preferred":[
        "Katipunan"
    ],
    "name:pam_x_preferred":[
        "Katipunan"
    ],
    "name:spa_x_preferred":[
        "Katipunan"
    ],
    "name:swe_x_preferred":[
        "Katipunan"
    ],
    "name:tgl_x_preferred":[
        "Katipunan"
    ],
    "name:unk_x_variant":[
        "Lubangan"
    ],
    "name:vie_x_preferred":[
        "Katipunan"
    ],
    "name:war_x_preferred":[
        "Katipunan"
    ],
    "qs:gn_country":"PH",
    "qs:gn_fcode":"PPL",
    "qs:gn_pop":4172,
    "qs:name":"Katipunan",
    "qs:name_adm0":"Philippines",
    "qs:name_adm1":"Zamboanga Peninsula",
    "qs:photos":0,
    "qs:photos_1k":0,
    "qs:photos_9k":0,
    "qs:photos_9r":0,
    "qs:photos_all":0,
    "qs:photos_sr":0,
    "qs:placetype":"Town",
    "qs:pop_sr":"4",
    "qs:woe_adm0":23424934,
    "wd:wordcount":10246,
    "wof:name":"Katipunan",
    "wof:placetype":"locality",
    "wof:population":4172
},
  "geometry": {"coordinates":[123.2829,8.514],"type":"Point"}
}