{
  "type": "Feature",
  "properties": {
    "gn:admin1_code":"06",
    "gn:admin2_code":"18",
    "gn:admin3_code":"61913000.0",
    "gn:asciiname":"Badyongon",
    "gn:country_code":"PH",
    "gn:dem":59,
    "gn:feature_class":"P",
    "gn:feature_code":"PPL",
    "gn:name":"Badyongon",
    "gn:population":0,
    "gn:timezone":"Asia/Manila",
    "iso:country":"PH",
    "name:fil_x_preferred":[
        "Badyongon"
    ],
    "name:und_x_variant":[
        "Badiangon"
    ],
    "wof:name":"Badyongon",
    "wof:placetype":"locality"
},
  "geometry": {"coordinates":[122.95189999999999,11.3867],"type":"Point"}
}