{
  "type": "Feature",
  "properties": {
    "gn:admin1_code":"40",
    "gn:admin2_code":"H2",
    "gn:admin3_code":"45634000.0",
    "gn:asciiname":"Ilayang Saliyao",
    "gn:country_code":"PH",
    "gn:dem":23,
    "gn:feature_class":"P",
    "gn:feature_code":"PPL",
    "gn:name":"Ilayang Saliyao",
    "gn:population":0,
    "gn:timezone":"Asia/Manila",
    "iso:country":"PH",
    "name:fil_x_preferred":[
        "Ilayang Saliyao"
    ],
    "wof:name":"Ilayang Saliyao",
    "wof:placetype":"locality"
},
  "geometry": {"coordinates":[122.1289,13.7915],"type":"Point"}
}