{
  "type": "Feature",
  "properties": {
    "gn:admin1_code":"14",
    "gn:admin2_code":"60",
    "gn:admin3_code":"156605000.0",
    "gn:asciiname":"Lungagas",
    "gn:country_code":"PH",
    "gn:dem":106,
    "gn:feature_class":"P",
    "gn:feature_code":"PPL",
    "gn:name":"Lungagas",
    "gn:population":0,
    "gn:timezone":"Asia/Manila",
    "iso:country":"PH",
    "name:eng_x_preferred":[
        "Lungagas"
    ],
    "wof:name":"Lungagas",
    "wof:placetype":"locality"
},
  "geometry": {"coordinates":[120.99120000000001,5.9498],"type":"Point"}
}