{
  "type": "Feature",
  "properties": {
    "gn:admin1_code":"02",
    "gn:admin2_code":"31",
    "gn:admin3_code":"23114000.0",
    "gn:asciiname":"Lullutan",
    "gn:country_code":"PH",
    "gn:dem":44,
    "gn:feature_class":"P",
    "gn:feature_code":"PPL",
    "gn:name":"Lullutan",
    "gn:population":0,
    "gn:timezone":"Asia/Manila",
    "iso:country":"PH",
    "name:fil_x_preferred":[
        "Lullutan"
    ],
    "wof:name":"Lullutan",
    "wof:placetype":"locality"
},
  "geometry": {"coordinates":[121.86293999999999,17.14824],"type":"Point"}
}