{
  "type": "Feature",
  "properties": {
    "gn:admin1_code":"01",
    "gn:admin2_code":"51",
    "gn:admin3_code":"15532000.0",
    "gn:asciiname":"Lilimasan",
    "gn:country_code":"PH",
    "gn:dem":14,
    "gn:feature_class":"P",
    "gn:feature_code":"PPL",
    "gn:name":"Lilimasan",
    "gn:population":0,
    "gn:timezone":"Asia/Manila",
    "iso:country":"PH",
    "name:und_x_variant":[
        "Limasan",
        "Lilimasan"
    ],
    "wof:name":"Lilimasan",
    "wof:placetype":"locality"
},
  "geometry": {"coordinates":[120.37135000000001,15.94444],"type":"Point"}
}