{
  "type": "Feature",
  "properties": {
    "gn:admin1_code":"40",
    "gn:admin2_code":"33",
    "gn:admin3_code":"43426000.0",
    "gn:asciiname":"San Pablo Norte",
    "gn:country_code":"PH",
    "gn:dem":3,
    "gn:feature_class":"P",
    "gn:feature_code":"PPL",
    "gn:name":"San Pablo Norte",
    "gn:population":0,
    "gn:timezone":"Asia/Manila",
    "iso:country":"PH",
    "name:fil_x_preferred":[
        "San Pablo Norte"
    ],
    "wof:name":"San Pablo Norte",
    "wof:placetype":"locality"
},
  "geometry": {"coordinates":[121.41249999999999,14.2902],"type":"Point"}
}