{
  "type": "Feature",
  "properties": {
    "gn:country":"PH",
    "gn:fcode":"PPL",
    "gn:pop":4108,
    "iso:country":"PH",
    "name:fil_x_preferred":[
        "Arenas"
    ],
    "qs:name":"Arenas",
    "qs:photos_9r":0,
    "qs:photos_sr":0,
    "qs:pop_sr":"4",
    "wd:wordcount":201,
    "wof:name":"Arenas",
    "wof:placetype":"locality",
    "wof:population":4108
},
  "geometry": {"coordinates":[120.68571,15.17042],"type":"Point"}
}