{
  "type": "Feature",
  "properties": {
    "gn:country":"PH",
    "gn:fcode":"PPL",
    "gn:population":4108,
    "iso:country":"PH",
    "name:ceb_x_preferred":[
        "Arenas"
    ],
    "name:deu_x_preferred":[
        "Arenas"
    ],
    "name:fil_x_preferred":[
        "Arenas"
    ],
    "name:heb_x_preferred":[
        "\u05d0\u05e8\u05e0\u05e1"
    ],
    "name:ita_x_preferred":[
        "Arenas"
    ],
    "name:jpn_x_preferred":[
        "\u30a2\u30ec\u30ca\u30b9"
    ],
    "name:pol_x_preferred":[
        "Arenas"
    ],
    "name:rus_x_preferred":[
        "\u0410\u0440\u0435\u043d\u0430\u0441"
    ],
    "name:spa_x_preferred":[
        "Arenas"
    ],
    "name:swe_x_preferred":[
        "Arenas"
    ],
    "qs:name":"Arenas",
    "qs:photos_9r":0,
    "qs:photos_sr":0,
    "qs:pop_sr":"4",
    "wd:wordcount":201,
    "wof:name":"Arenas",
    "wof:placetype":"locality",
    "wof:population":4108
},
  "geometry": {"coordinates":[120.68571,15.17042],"type":"Point"}
}