{
  "type": "Feature",
  "properties": {
    "gn:admin1_code":"06",
    "gn:admin2_code":"18",
    "gn:admin3_code":"61904000.0",
    "gn:asciiname":"Tumalalud",
    "gn:country_code":"PH",
    "gn:dem":49,
    "gn:feature_class":"P",
    "gn:feature_code":"PPL",
    "gn:name":"Tumalalud",
    "gn:population":0,
    "gn:timezone":"Asia/Manila",
    "iso:country":"PH",
    "name:fil_x_preferred":[
        "Tumalalud"
    ],
    "name:und_x_variant":[
        "Tamulalud"
    ],
    "wof:name":"Tumalalud",
    "wof:placetype":"locality"
},
  "geometry": {"coordinates":[122.7051,11.2492],"type":"Point"}
}