{
  "type": "Feature",
  "properties": {
    "gn:country":"PH",
    "gn:fcode":"PPL",
    "gn:pop":4548,
    "iso:country":"PH",
    "name:bcl_x_preferred":[
        "Burdeos"
    ],
    "name:cat_x_preferred":[
        "Burdeos"
    ],
    "name:dut_x_preferred":[
        "Burdeos"
    ],
    "name:eng_x_preferred":[
        "Burdeos"
    ],
    "name:fil_x_preferred":[
        "Burdeos"
    ],
    "name:fre_x_preferred":[
        "Burdeos"
    ],
    "name:ger_x_preferred":[
        "Burdeos"
    ],
    "name:ilo_x_preferred":[
        "Burdeos"
    ],
    "name:ind_x_preferred":[
        "Burdeos"
    ],
    "name:ita_x_preferred":[
        "Burdeos"
    ],
    "name:jpn_x_preferred":[
        "\u30d6\u30eb\u30c7\u30aa\u30b9"
    ],
    "name:oci_x_preferred":[
        "Burdeos"
    ],
    "name:pag_x_preferred":[
        "Burdeos"
    ],
    "name:pam_x_preferred":[
        "Burdeos"
    ],
    "name:spa_x_preferred":[
        "Burdeos"
    ],
    "name:swe_x_preferred":[
        "Burdeos"
    ],
    "name:tgl_x_preferred":[
        "Burdeos"
    ],
    "name:unk_x_variant":[
        "Burdoes"
    ],
    "name:vie_x_preferred":[
        "Burdeos"
    ],
    "name:war_x_preferred":[
        "Burdeos"
    ],
    "qs:name":"Burdeos",
    "qs:photos_9r":0,
    "qs:photos_sr":0,
    "qs:pop_sr":"4",
    "wof:name":"Burdeos",
    "wof:placetype":"locality",
    "wof:population":4548
},
  "geometry": {"coordinates":[121.96906,14.84302],"type":"Point"}
}