{
  "type": "Feature",
  "properties": {
    "gn:admin1_code":"41",
    "gn:admin2_code":"41",
    "gn:admin3_code":"175204000.0",
    "gn:asciiname":"Bangkal",
    "gn:country_code":"PH",
    "gn:dem":21,
    "gn:feature_class":"P",
    "gn:feature_code":"PPL",
    "gn:name":"Bangkal",
    "gn:population":0,
    "gn:timezone":"Asia/Manila",
    "iso:country":"PH",
    "name:fil_x_preferred":[
        "Bangkal"
    ],
    "wof:name":"Bangkal",
    "wof:placetype":"locality"
},
  "geometry": {"coordinates":[121.38339999999999,12.368],"type":"Point"}
}