{
  "type": "Feature",
  "properties": {
    "gn:country":"PH",
    "gn:fcode":"PPL",
    "gn:population":9040,
    "iso:country":"PH",
    "name:fil_x_preferred":[
        "Bangkirohan"
    ],
    "name:fil_x_variant":[
        "Banquerohan"
    ],
    "name:und_x_variant":[
        "Banquarohan"
    ],
    "qs:name":"Bangkirohan",
    "qs:photos_9r":0,
    "qs:photos_sr":0,
    "qs:pop_sr":"5",
    "wof:name":"Bangkirohan",
    "wof:placetype":"locality",
    "wof:population":9040
},
  "geometry": {"coordinates":[123.74679999999999,13.0553],"type":"Point"}
}