{
  "type": "Feature",
  "properties": {
    "gn:country":"PH",
    "gn:fcode":"PPL",
    "gn:pop":2473,
    "iso:country":"PH",
    "name:fil_x_preferred":[
        "Malusay"
    ],
    "qs:name":"Malusay",
    "qs:photos_9r":0,
    "qs:photos_sr":0,
    "qs:pop_sr":"4",
    "wof:name":"Malusay",
    "wof:placetype":"locality",
    "wof:population":2473
},
  "geometry": {"coordinates":[123.2717,10.1439],"type":"Point"}
}