{
  "type": "Feature",
  "properties": {
    "gn:admin1_code":"15",
    "gn:admin2_code":"32",
    "gn:admin3_code":"143209000.0",
    "gn:asciiname":"Maccot",
    "gn:country_code":"PH",
    "gn:dem":149,
    "gn:feature_class":"P",
    "gn:feature_code":"PPL",
    "gn:name":"Maccot",
    "gn:population":0,
    "gn:timezone":"Asia/Manila",
    "iso:country":"PH",
    "name:fil_x_preferred":[
        "Maccot"
    ],
    "wof:name":"Maccot",
    "wof:placetype":"locality"
},
  "geometry": {"coordinates":[121.33505,17.59152000000001],"type":"Point"}
}