{
  "type": "Feature",
  "properties": {
    "gn:admin1_code":"06",
    "gn:admin2_code":"30",
    "gn:admin3_code":"63040000.0",
    "gn:asciiname":"Nadsalan",
    "gn:country_code":"PH",
    "gn:dem":476,
    "gn:feature_class":"P",
    "gn:feature_code":"PPL",
    "gn:name":"Nadsalan",
    "gn:population":0,
    "gn:timezone":"Asia/Manila",
    "iso:country":"PH",
    "name:fil_x_preferred":[
        "Nadsalan"
    ],
    "name:und_x_variant":[
        "Nadsadan"
    ],
    "wof:name":"Nadsalan",
    "wof:placetype":"locality"
},
  "geometry": {"coordinates":[122.1039,10.6575],"type":"Point"}
}