{
  "type": "Feature",
  "properties": {
    "gn:admin1_code":"06",
    "gn:admin2_code":"18",
    "gn:asciiname":"Lanupa",
    "gn:country_code":"PH",
    "gn:dem":0,
    "gn:feature_class":"P",
    "gn:feature_code":"PPL",
    "gn:name":"Lanupa",
    "gn:population":0,
    "gn:timezone":"Asia/Manila",
    "iso:country":"PH",
    "name:fil_x_preferred":[
        "Lanupa"
    ],
    "wof:name":"Lanupa",
    "wof:placetype":"locality"
},
  "geometry": {"coordinates":[122.9175,11.4701],"type":"Point"}
}