{
  "type": "Feature",
  "properties": {
    "gn:admin1_code":"15",
    "gn:admin2_code":"H6",
    "gn:admin3_code":"148105000.0",
    "gn:asciiname":"Turatoc",
    "gn:country_code":"PH",
    "gn:dem":30,
    "gn:feature_class":"P",
    "gn:feature_code":"PPL",
    "gn:name":"Turatoc",
    "gn:population":0,
    "gn:timezone":"Asia/Manila",
    "iso:country":"PH",
    "name:fil_x_preferred":[
        "Turatoc"
    ],
    "name:und_x_variant":[
        "Isneg"
    ],
    "wof:name":"Turatoc",
    "wof:placetype":"locality"
},
  "geometry": {"coordinates":[121.24822,18.32959],"type":"Point"}
}