{
  "type": "Feature",
  "properties": {
    "gn:admin1_code":"10",
    "gn:admin2_code":"42",
    "gn:admin3_code":"104216000.0",
    "gn:asciiname":"Senor",
    "gn:country_code":"PH",
    "gn:dem":126,
    "gn:feature_class":"P",
    "gn:feature_code":"PPL",
    "gn:name":"Se\u00f1or",
    "gn:population":0,
    "gn:timezone":"Asia/Manila",
    "iso:country":"PH",
    "name:eng_x_preferred":[
        "Se\u00f1or"
    ],
    "wof:name":"Senor",
    "wof:placetype":"locality"
},
  "geometry": {"coordinates":[123.8177,8.2682],"type":"Point"}
}