{
  "type": "Feature",
  "properties": {
    "gn:admin1_code":"12",
    "gn:admin2_code":"71",
    "gn:admin3_code":"126509000.0",
    "gn:asciiname":"Repolun",
    "gn:country_code":"PH",
    "gn:dem":8,
    "gn:feature_class":"P",
    "gn:feature_code":"PPL",
    "gn:name":"Repolun",
    "gn:population":0,
    "gn:timezone":"Asia/Manila",
    "iso:country":"PH",
    "name:fil_x_preferred":[
        "Repolun"
    ],
    "wof:name":"Repolun",
    "wof:placetype":"locality"
},
  "geometry": {"coordinates":[124.21722,6.19306],"type":"Point"}
}