{
  "type": "Feature",
  "properties": {
    "gn:admin1_code":"14",
    "gn:admin2_code":"22",
    "gn:admin3_code":"150702000.0",
    "gn:asciiname":"Guibauan",
    "gn:country_code":"PH",
    "gn:dem":17,
    "gn:feature_class":"P",
    "gn:feature_code":"PPL",
    "gn:name":"Guibauan",
    "gn:population":0,
    "gn:timezone":"Asia/Manila",
    "iso:country":"PH",
    "name:und_x_variant":[
        "Gubawan",
        "Guibauan"
    ],
    "wof:name":"Guibauan",
    "wof:placetype":"locality"
},
  "geometry": {"coordinates":[122.13694,6.65083],"type":"Point"}
}