{
  "type": "Feature",
  "properties": {
    "gn:country":"PH",
    "gn:fcode":"ADM3",
    "gn:pop":62101,
    "iso:country":"PH",
    "name:fil_x_preferred":[
        "Camalig"
    ],
    "qs:name":"Camalig",
    "qs:photos_9r":0,
    "qs:photos_sr":0,
    "qs:pop_sr":"8",
    "wof:name":"Camalig",
    "wof:placetype":"localadmin",
    "wof:population":62101
},
  "geometry": {"coordinates":[123.59999999999999,13.15],"type":"Point"}
}