{
  "type": "Feature",
  "properties": {
    "gn:country":"PH",
    "gn:fcode":"ADM3",
    "gn:population":62101,
    "iso:country":"PH",
    "name:bcl_x_preferred":[
        "Camalig"
    ],
    "name:ceb_x_preferred":[
        "Camalig"
    ],
    "name:deu_x_preferred":[
        "Camalig"
    ],
    "name:fil_x_preferred":[
        "Camalig"
    ],
    "name:fra_x_preferred":[
        "Camalig"
    ],
    "name:gor_x_preferred":[
        "Camalig"
    ],
    "name:ilo_x_preferred":[
        "Camalig"
    ],
    "name:ind_x_preferred":[
        "Camalig"
    ],
    "name:ita_x_preferred":[
        "Camalig"
    ],
    "name:nld_x_preferred":[
        "Camalig"
    ],
    "name:nor_x_preferred":[
        "Camalig"
    ],
    "name:pag_x_preferred":[
        "Camalig"
    ],
    "name:pam_x_preferred":[
        "Camalig"
    ],
    "name:swe_x_preferred":[
        "Camalig"
    ],
    "name:tgl_x_preferred":[
        "Camalig"
    ],
    "name:urd_x_preferred":[
        "\u06a9\u0627\u0645\u0627\u0644\u06cc\u06af"
    ],
    "name:vie_x_preferred":[
        "Camalig"
    ],
    "name:war_x_preferred":[
        "Camalig"
    ],
    "qs:name":"Camalig",
    "qs:photos_9r":0,
    "qs:photos_sr":0,
    "qs:pop_sr":"8",
    "wof:name":"Camalig",
    "wof:placetype":"localadmin",
    "wof:population":62101
},
  "geometry": {"coordinates":[123.59999999999999,13.15],"type":"Point"}
}