{
  "type": "Feature",
  "properties": {
    "gn:admin1_code":"01",
    "gn:admin2_code":"51",
    "gn:admin3_code":"15524000.0",
    "gn:asciiname":"Curareng",
    "gn:country_code":"PH",
    "gn:dem":24,
    "gn:feature_class":"P",
    "gn:feature_code":"PPL",
    "gn:name":"Curareng",
    "gn:population":0,
    "gn:timezone":"Asia/Manila",
    "iso:country":"PH",
    "name:fil_x_preferred":[
        "Corareng"
    ],
    "wof:name":"Curareng",
    "wof:placetype":"locality"
},
  "geometry": {"coordinates":[120.48454,15.85891],"type":"Point"}
}