{
  "type": "Feature",
  "properties": {
    "gn:admin1_code":"11",
    "gn:admin2_code":"I7",
    "gn:admin3_code":"112317000.0",
    "gn:asciiname":"Turil",
    "gn:country_code":"PH",
    "gn:dem":104,
    "gn:feature_class":"P",
    "gn:feature_code":"PPL",
    "gn:name":"Turil",
    "gn:population":0,
    "gn:timezone":"Asia/Manila",
    "iso:country":"PH",
    "name:fil_x_preferred":[
        "Turil"
    ],
    "wof:name":"Turil",
    "wof:placetype":"locality"
},
  "geometry": {"coordinates":[125.72638999999999,7.12528],"type":"Point"}
}