{
  "type": "Feature",
  "properties": {
    "gn:admin1_code":"40",
    "gn:admin2_code":"20",
    "gn:admin3_code":"42106000.0",
    "gn:asciiname":"San Nicolas Segundo",
    "gn:country_code":"PH",
    "gn:dem":129,
    "gn:feature_class":"P",
    "gn:feature_code":"PPL",
    "gn:name":"San Nicolas Segundo",
    "gn:population":0,
    "gn:timezone":"Asia/Manila",
    "iso:country":"PH",
    "name:und_x_variant":[
        "San Nicholas Segundo"
    ],
    "wof:name":"San Nicolas Segundo",
    "wof:placetype":"locality"
},
  "geometry": {"coordinates":[120.97165,14.31733],"type":"Point"}
}