{
  "type": "Feature",
  "properties": {
    "gn:gn_country":"PH",
    "gn:gn_fcode":"PPL",
    "gn:gn_pop":5770,
    "gn:population":5770,
    "iso:country":"PH",
    "name:fil_x_preferred":[
        "Magatos"
    ],
    "qs_pg:aaroncc":"PH",
    "qs_pg:gn_country":"PH",
    "qs_pg:gn_fcode":"PPL",
    "qs_pg:gn_pop":5770,
    "qs_pg:name":"Magatos",
    "qs_pg:photos_9r":0,
    "qs_pg:photos_sr":0,
    "qs_pg:pop_sr":5,
    "qs_pg:qs_pg_placetype":"locality",
    "wof:name":"Magatos",
    "wof:placetype":"locality",
    "wof:population":5770
},
  "geometry": {"coordinates":[125.72667,7.55556],"type":"Point"}
}