{
  "type": "Feature",
  "properties": {
    "gn:admin1_code":"14",
    "gn:admin2_code":"56",
    "gn:admin3_code":"153809000.0",
    "gn:asciiname":"Dagurungan",
    "gn:cc2":"PH",
    "gn:country_code":"PH",
    "gn:dem":137,
    "gn:feature_class":"P",
    "gn:feature_code":"PPL",
    "gn:name":"Daguru\u00f1gan",
    "gn:population":0,
    "gn:timezone":"Asia/Manila",
    "iso:country":"PH",
    "name:und_x_variant":[
        "Daguru\u00f1gan Subpa\u00f1gan",
        "Daguru\u00f1gan"
    ],
    "wof:name":"Dagurungan",
    "wof:placetype":"locality"
},
  "geometry": {"coordinates":[124.21666999999999,7.43333],"type":"Point"}
}