{
  "type": "Feature",
  "properties": {
    "gn:admin1_code":"06",
    "gn:admin2_code":"H3",
    "gn:admin3_code":"64502000.0",
    "gn:asciiname":"Hacienda Daguan",
    "gn:country_code":"PH",
    "gn:dem":103,
    "gn:feature_class":"P",
    "gn:feature_code":"PPL",
    "gn:name":"Hacienda Daguan",
    "gn:population":0,
    "gn:timezone":"Asia/Manila",
    "iso:country":"PH",
    "name:fil_x_preferred":[
        "Hacienda Daguan"
    ],
    "name:fil_x_variant":[
        "Daguan Hacienda"
    ],
    "wof:name":"Hacienda Daguan",
    "wof:placetype":"locality"
},
  "geometry": {"coordinates":[123.0352,10.51246],"type":"Point"}
}