{
  "type": "Feature",
  "properties": {
    "gn:admin1_code":"05",
    "gn:admin2_code":"16",
    "gn:admin3_code":"51736000.0",
    "gn:asciiname":"Caodiocan",
    "gn:country_code":"PH",
    "gn:dem":191,
    "gn:feature_class":"P",
    "gn:feature_code":"PPL",
    "gn:name":"Caodiocan",
    "gn:population":0,
    "gn:timezone":"Asia/Manila",
    "iso:country":"PH",
    "name:fil_x_preferred":[
        "Caodiocan"
    ],
    "wof:name":"Caodiocan",
    "wof:placetype":"locality"
},
  "geometry": {"coordinates":[123.45,13.61667],"type":"Point"}
}