{
  "type": "Feature",
  "properties": {
    "gn:admin1_code":"40",
    "gn:admin2_code":"33",
    "gn:admin3_code":"43415000.0",
    "gn:asciiname":"Ybabang Atingay",
    "gn:country_code":"PH",
    "gn:dem":67,
    "gn:feature_class":"P",
    "gn:feature_code":"PPL",
    "gn:name":"Ybabang Atingay",
    "gn:population":0,
    "gn:timezone":"Asia/Manila",
    "iso:country":"PH",
    "name:fil_x_preferred":[
        "Ybabang Atingay"
    ],
    "wof:name":"Ybabang Atingay",
    "wof:placetype":"locality"
},
  "geometry": {"coordinates":[121.453,14.1938],"type":"Point"}
}