{
  "type": "Feature",
  "properties": {
    "gn:admin1_code":"06",
    "gn:admin2_code":"04",
    "gn:admin3_code":"60406000.0",
    "gn:asciiname":"Agbago",
    "gn:country_code":"PH",
    "gn:dem":5,
    "gn:feature_class":"P",
    "gn:feature_code":"PPL",
    "gn:name":"Agbago",
    "gn:population":0,
    "gn:timezone":"Asia/Manila",
    "iso:country":"PH",
    "name:fil_x_preferred":[
        "Agbago"
    ],
    "wof:name":"Agbago",
    "wof:placetype":"locality"
},
  "geometry": {"coordinates":[122.1503,11.809],"type":"Point"}
}