{
  "type": "Feature",
  "properties": {
    "gn:admin1_code":"40",
    "gn:admin2_code":"20",
    "gn:admin3_code":"42103000.0",
    "gn:asciiname":"Paltoc",
    "gn:country_code":"PH",
    "gn:dem":13,
    "gn:feature_class":"P",
    "gn:feature_code":"PPL",
    "gn:name":"Paltoc",
    "gn:population":0,
    "gn:timezone":"Asia/Manila",
    "iso:country":"PH",
    "name:fil_x_preferred":[
        "Paltoc"
    ],
    "wof:name":"Paltoc",
    "wof:placetype":"locality"
},
  "geometry": {"coordinates":[120.95,14.43333],"type":"Point"}
}