{
  "type": "Feature",
  "properties": {
    "gn:admin1_code":"06",
    "gn:admin2_code":"30",
    "gn:admin3_code":"63040000.0",
    "gn:asciiname":"Iglawa",
    "gn:country_code":"PH",
    "gn:dem":98,
    "gn:feature_class":"P",
    "gn:feature_code":"PPL",
    "gn:name":"Iglawa",
    "gn:population":0,
    "gn:timezone":"Asia/Manila",
    "iso:country":"PH",
    "name:fil_x_preferred":[
        "Iglawa"
    ],
    "name:fil_x_variant":[
        "Tiglaw\u00e1"
    ],
    "wof:name":"Iglawa",
    "wof:placetype":"locality"
},
  "geometry": {"coordinates":[122.0466,10.5964],"type":"Point"}
}