{
  "type": "Feature",
  "properties": {
    "gn:admin1_code":"07",
    "gn:admin2_code":"46",
    "gn:admin3_code":"74609000.0",
    "gn:asciiname":"Nabago",
    "gn:country_code":"PH",
    "gn:dem":168,
    "gn:feature_class":"P",
    "gn:feature_code":"PPL",
    "gn:name":"Nabago",
    "gn:population":0,
    "gn:timezone":"Asia/Manila",
    "iso:country":"PH",
    "name:fil_x_preferred":[
        "Nabago"
    ],
    "wof:name":"Nabago",
    "wof:placetype":"locality"
},
  "geometry": {"coordinates":[123.2159,9.1648],"type":"Point"}
}