{
  "type": "Feature",
  "properties": {
    "gn:admin1_code":"08",
    "gn:admin2_code":"67",
    "gn:admin3_code":"84811000.0",
    "gn:asciiname":"Sumisip",
    "gn:country_code":"PH",
    "gn:dem":14,
    "gn:feature_class":"P",
    "gn:feature_code":"PPL",
    "gn:name":"Sumisip",
    "gn:population":0,
    "gn:timezone":"Asia/Manila",
    "iso:country":"PH",
    "name:bcl_x_preferred":[
        "Sumisip"
    ],
    "name:ceb_x_preferred":[
        "Sumisip"
    ],
    "name:deu_x_preferred":[
        "Sumisip"
    ],
    "name:fil_x_preferred":[
        "Sumisip"
    ],
    "name:fra_x_preferred":[
        "Sumisip"
    ],
    "name:ilo_x_preferred":[
        "Sumisip"
    ],
    "name:ind_x_preferred":[
        "Sumisip"
    ],
    "name:ita_x_preferred":[
        "Sumisip"
    ],
    "name:msa_x_preferred":[
        "Sumisip"
    ],
    "name:nld_x_preferred":[
        "Sumisip"
    ],
    "name:nor_x_preferred":[
        "Sumisip"
    ],
    "name:pag_x_preferred":[
        "Sumisip"
    ],
    "name:pam_x_preferred":[
        "Sumisip"
    ],
    "name:swe_x_preferred":[
        "Sumisip"
    ],
    "name:tgl_x_preferred":[
        "Sumisip"
    ],
    "name:urd_x_preferred":[
        "\u0633\u0648\u0645\u06cc\u0633\u06cc\u067e"
    ],
    "name:vie_x_preferred":[
        "Sumisip"
    ],
    "name:war_x_preferred":[
        "Sumisip"
    ],
    "wof:name":"Sumisip",
    "wof:placetype":"locality"
},
  "geometry": {"coordinates":[124.3784,12.5156],"type":"Point"}
}