{
  "type": "Feature",
  "properties": {
    "gn:admin1_code":"40",
    "gn:admin2_code":"H2",
    "gn:admin3_code":"45641000.0",
    "gn:asciiname":"Matipunso",
    "gn:country_code":"PH",
    "gn:dem":126,
    "gn:feature_class":"P",
    "gn:feature_code":"PPL",
    "gn:name":"Matipunso",
    "gn:population":0,
    "gn:timezone":"Asia/Manila",
    "iso:country":"PH",
    "wof:name":"Matipunso",
    "wof:placetype":"locality"
},
  "geometry": {"coordinates":[121.26243999999998,13.89749],"type":"Point"}
}