{
  "type": "Feature",
  "properties": {
    "gn:country":"PH",
    "gn:fcode":"PPLA3",
    "gn:pop":5958,
    "iso:country":"PH",
    "name:bcl_x_preferred":[
        "Piat"
    ],
    "name:cat_x_preferred":[
        "Piat"
    ],
    "name:deu_x_preferred":[
        "Piat"
    ],
    "name:eng_x_preferred":[
        "Piat"
    ],
    "name:fil_x_preferred":[
        "Piat"
    ],
    "name:fra_x_preferred":[
        "Piat"
    ],
    "name:ilo_x_preferred":[
        "Piat"
    ],
    "name:ind_x_preferred":[
        "Piat"
    ],
    "name:ita_x_preferred":[
        "Piat"
    ],
    "name:nld_x_preferred":[
        "Piat"
    ],
    "name:oci_x_preferred":[
        "Piat"
    ],
    "name:pag_x_preferred":[
        "Piat"
    ],
    "name:pam_x_preferred":[
        "Piat"
    ],
    "name:spa_x_preferred":[
        "Piat"
    ],
    "name:swe_x_preferred":[
        "Piat"
    ],
    "name:tgl_x_preferred":[
        "Piat"
    ],
    "name:vie_x_preferred":[
        "Piat"
    ],
    "name:war_x_preferred":[
        "Piat"
    ],
    "qs:name":"Piat",
    "qs:photos_9r":0,
    "qs:photos_sr":0,
    "qs:pop_sr":"5",
    "wof:name":"Piat",
    "wof:placetype":"locality",
    "wof:population":5958
},
  "geometry": {"coordinates":[121.47799999999999,17.7905],"type":"Point"}
}