{
  "type": "Feature",
  "properties": {
    "gn:country":"PH",
    "gn:fcode":"PPLA3",
    "gn:pop":3998,
    "iso:country":"PH",
    "name:bcl_x_preferred":[
        "Madridejos"
    ],
    "name:deu_x_preferred":[
        "Madridejos"
    ],
    "name:eng_x_preferred":[
        "Madridejos"
    ],
    "name:fil_x_preferred":[
        "Madridejos"
    ],
    "name:fra_x_preferred":[
        "Madridejos"
    ],
    "name:ilo_x_preferred":[
        "Madridejos"
    ],
    "name:ind_x_preferred":[
        "Madridejos"
    ],
    "name:ita_x_preferred":[
        "Madridejos"
    ],
    "name:jpn_x_preferred":[
        "\u30de\u30c9\u30ea\u30c7\u30fc\u30b8\u30e7\u30ba"
    ],
    "name:nld_x_preferred":[
        "Madridejos"
    ],
    "name:pag_x_preferred":[
        "Madridejos"
    ],
    "name:pam_x_preferred":[
        "Madridejos"
    ],
    "name:spa_x_preferred":[
        "Madridejos"
    ],
    "name:swe_x_preferred":[
        "Madridejos"
    ],
    "name:tgl_x_preferred":[
        "Madridejos"
    ],
    "name:vie_x_preferred":[
        "Madridejos"
    ],
    "name:war_x_preferred":[
        "Madridejos"
    ],
    "qs:name":"Madridejos",
    "qs:photos_9r":0,
    "qs:photos_sr":0,
    "qs:pop_sr":"4",
    "wd:wordcount":26,
    "wof:name":"Madridejos",
    "wof:placetype":"locality",
    "wof:population":3998
},
  "geometry": {"coordinates":[123.73390000000001,11.298],"type":"Point"}
}