{
  "type": "Feature",
  "properties": {
    "gn:country":"PH",
    "gn:fcode":"ADM3",
    "gn:pop":75667,
    "iso:country":"PH",
    "name:fil_x_preferred":[
        "Prosperidad"
    ],
    "qs:name":"Prosperidad",
    "qs:photos_9r":0,
    "qs:photos_sr":0,
    "qs:pop_sr":"8",
    "wof:name":"Prosperidad",
    "wof:placetype":"localadmin",
    "wof:population":75667
},
  "geometry": {"coordinates":[125.86667,8.41667],"type":"Point"}
}