{
  "type": "Feature",
  "properties": {
    "gn:gn_country":"PH",
    "gn:gn_fcode":"PPLA3",
    "gn:gn_pop":4387,
    "gn:population":4387,
    "iso:country":"PH",
    "name:bcl_x_preferred":[
        "Dagami"
    ],
    "name:dut_x_preferred":[
        "Dagami"
    ],
    "name:eng_x_preferred":[
        "Dagami"
    ],
    "name:fre_x_preferred":[
        "Dagami"
    ],
    "name:ger_x_preferred":[
        "Dagami"
    ],
    "name:ilo_x_preferred":[
        "Dagami"
    ],
    "name:ind_x_preferred":[
        "Dagami"
    ],
    "name:ita_x_preferred":[
        "Dagami"
    ],
    "name:pag_x_preferred":[
        "Dagami"
    ],
    "name:pam_x_preferred":[
        "Dagami"
    ],
    "name:swe_x_preferred":[
        "Dagami"
    ],
    "name:tgl_x_preferred":[
        "Dagami"
    ],
    "name:vie_x_preferred":[
        "Dagami"
    ],
    "name:war_x_preferred":[
        "Dagami"
    ],
    "qs_pg:aaroncc":"PH",
    "qs_pg:gn_country":"PH",
    "qs_pg:gn_fcode":"PPLA3",
    "qs_pg:gn_pop":4387,
    "qs_pg:name":"Dagami",
    "qs_pg:photos_9r":0,
    "qs_pg:photos_sr":0,
    "qs_pg:pop_sr":4,
    "qs_pg:qs_pg_placetype":"locality",
    "wof:name":"Dagami",
    "wof:placetype":"locality",
    "wof:population":4387
},
  "geometry": {"coordinates":[124.90278000000001,11.06083],"type":"Point"}
}