{
  "type": "Feature",
  "properties": {
    "gn:admin1_code":"06",
    "gn:admin2_code":"30",
    "gn:admin3_code":"63015000.0",
    "gn:asciiname":"Macatunao",
    "gn:country_code":"PH",
    "gn:dem":12,
    "gn:feature_class":"P",
    "gn:feature_code":"PPL",
    "gn:name":"Macatunao",
    "gn:population":0,
    "gn:timezone":"Asia/Manila",
    "iso:country":"PH",
    "name:fil_x_preferred":[
        "Macatunao"
    ],
    "wof:name":"Macatunao",
    "wof:placetype":"locality"
},
  "geometry": {"coordinates":[123.18277999999999,11.30167],"type":"Point"}
}