{
  "type": "Feature",
  "properties": {
    "gn:gn_country":"PH",
    "gn:gn_fcode":"PPLA3",
    "gn:gn_pop":9484,
    "gn:population":9484,
    "iso:country":"PH",
    "name:bcl_x_preferred":[
        "Loon"
    ],
    "name:dut_x_preferred":[
        "Loon"
    ],
    "name:eng_x_preferred":[
        "Loon"
    ],
    "name:fil_x_preferred":[
        "Loon"
    ],
    "name:fre_x_preferred":[
        "Loon"
    ],
    "name:ger_x_preferred":[
        "Loon"
    ],
    "name:ilo_x_preferred":[
        "Loon"
    ],
    "name:ind_x_preferred":[
        "Loon"
    ],
    "name:ita_x_preferred":[
        "Loon"
    ],
    "name:pag_x_preferred":[
        "Loon"
    ],
    "name:pam_x_preferred":[
        "Loon"
    ],
    "name:rus_x_preferred":[
        "\u041b\u0443\u043d"
    ],
    "name:swe_x_preferred":[
        "Loon"
    ],
    "name:tgl_x_preferred":[
        "Loon"
    ],
    "name:vie_x_preferred":[
        "Loon"
    ],
    "name:war_x_preferred":[
        "Loon"
    ],
    "qs_pg:aaroncc":"PH",
    "qs_pg:gn_country":"PH",
    "qs_pg:gn_fcode":"PPLA3",
    "qs_pg:gn_pop":9484,
    "qs_pg:name":"Loon",
    "qs_pg:photos_9r":0,
    "qs_pg:photos_sr":0,
    "qs_pg:pop_sr":5,
    "qs_pg:qs_pg_placetype":"locality",
    "wof:name":"Loon",
    "wof:placetype":"locality",
    "wof:population":9484
},
  "geometry": {"coordinates":[123.7929,9.7998],"type":"Point"}
}