{
  "type": "Feature",
  "properties": {
    "gn:admin1_code":"11",
    "gn:admin2_code":"25",
    "gn:admin3_code":"112402000.0",
    "gn:asciiname":"Matina-Biao",
    "gn:country_code":"PH",
    "gn:dem":118,
    "gn:feature_class":"P",
    "gn:feature_code":"PPL",
    "gn:name":"Matina-Biao",
    "gn:population":0,
    "gn:timezone":"Asia/Manila",
    "iso:country":"PH",
    "wof:name":"Matina-Biao",
    "wof:placetype":"locality"
},
  "geometry": {"coordinates":[125.53943999999998,7.13861],"type":"Point"}
}