{
  "type": "Feature",
  "properties": {
    "gn:admin1_code":"07",
    "gn:admin2_code":"11",
    "gn:admin3_code":"71208000.0",
    "gn:asciiname":"Calapian",
    "gn:country_code":"PH",
    "gn:dem":352,
    "gn:feature_class":"P",
    "gn:feature_code":"PPL",
    "gn:name":"Calapian",
    "gn:population":0,
    "gn:timezone":"Asia/Manila",
    "iso:country":"PH",
    "name:fil_x_preferred":[
        "Calapian"
    ],
    "wof:name":"Calapian",
    "wof:placetype":"locality"
},
  "geometry": {"coordinates":[124.15000000000001,9.75],"type":"Point"}
}