{
  "type": "Feature",
  "properties": {
    "gn:admin1_code":"05",
    "gn:admin2_code":"16",
    "gn:admin3_code":"51716000.0",
    "gn:asciiname":"Nino Jesus",
    "gn:country_code":"PH",
    "gn:dem":167,
    "gn:feature_class":"P",
    "gn:feature_code":"PPL",
    "gn:name":"Ni\u00f1o Jesus",
    "gn:population":0,
    "gn:timezone":"Asia/Manila",
    "iso:country":"PH",
    "name:fil_x_preferred":[
        "Ni\u00f1o Jesus"
    ],
    "wof:name":"Nino Jesus",
    "wof:placetype":"locality"
},
  "geometry": {"coordinates":[123.44799999999999,13.4929],"type":"Point"}
}