{
  "type": "Feature",
  "properties": {
    "gn:admin1_code":"05",
    "gn:admin2_code":"05",
    "gn:admin3_code":"50501000.0",
    "gn:asciiname":"Gindi",
    "gn:country_code":"PH",
    "gn:dem":39,
    "gn:feature_class":"P",
    "gn:feature_code":"PPL",
    "gn:name":"Gindi",
    "gn:population":0,
    "gn:timezone":"Asia/Manila",
    "iso:country":"PH",
    "name:fil_x_preferred":[
        "Gindi"
    ],
    "name:und_x_variant":[
        "Hindi"
    ],
    "wof:name":"Gindi",
    "wof:placetype":"locality"
},
  "geometry": {"coordinates":[123.7754,13.2946],"type":"Point"}
}