{
  "type": "Feature",
  "properties": {
    "gn:admin1_code":"01",
    "gn:admin2_code":"51",
    "gn:admin3_code":"15508000.0",
    "gn:asciiname":"Ambabaay",
    "gn:country_code":"PH",
    "gn:dem":8,
    "gn:feature_class":"P",
    "gn:feature_code":"PPL",
    "gn:name":"Ambabaay",
    "gn:population":0,
    "gn:timezone":"Asia/Manila",
    "iso:country":"PH",
    "name:fil_x_preferred":[
        "Ambabaay"
    ],
    "wof:name":"Ambabaay",
    "wof:placetype":"locality"
},
  "geometry": {"coordinates":[119.87965,16.1832],"type":"Point"}
}