{
  "type": "Feature",
  "properties": {
    "gn:admin1_code":"12",
    "gn:admin2_code":"57",
    "gn:admin3_code":"124718000.0",
    "gn:asciiname":"Duldulumon",
    "gn:country_code":"PH",
    "gn:dem":152,
    "gn:feature_class":"P",
    "gn:feature_code":"PPL",
    "gn:name":"Duldulumon",
    "gn:population":0,
    "gn:timezone":"Asia/Manila",
    "iso:country":"PH",
    "name:fil_x_preferred":[
        "Duldulumon"
    ],
    "wof:name":"Duldulumon",
    "wof:placetype":"locality"
},
  "geometry": {"coordinates":[125.09472,7.34722],"type":"Point"}
}