{
  "type": "Feature",
  "properties": {
    "gn:admin1_code":"03",
    "gn:admin2_code":"64",
    "gn:admin3_code":"37112000.0",
    "gn:asciiname":"Kapanikian",
    "gn:country_code":"PH",
    "gn:dem":12,
    "gn:feature_class":"P",
    "gn:feature_code":"PPL",
    "gn:name":"Kapanikian",
    "gn:population":0,
    "gn:timezone":"Asia/Manila",
    "iso:country":"PH",
    "name:fil_x_preferred":[
        "Kapanikian"
    ],
    "wof:name":"Kapanikian",
    "wof:placetype":"locality"
},
  "geometry": {"coordinates":[120.08333,14.98333],"type":"Point"}
}