{
  "type": "Feature",
  "properties": {
    "gn:admin1_code":"13",
    "gn:admin2_code":"62",
    "gn:admin3_code":"166810000.0",
    "gn:asciiname":"Cagoncogan",
    "gn:country_code":"PH",
    "gn:dem":73,
    "gn:feature_class":"P",
    "gn:feature_code":"PPL",
    "gn:name":"Cagoncogan",
    "gn:population":0,
    "gn:timezone":"Asia/Manila",
    "iso:country":"PH",
    "name:fil_x_preferred":[
        "Cagoncogan"
    ],
    "wof:name":"Cagoncogan",
    "wof:placetype":"locality"
},
  "geometry": {"coordinates":[126.06999999999999,9.22056],"type":"Point"}
}