{
  "type": "Feature",
  "properties": {
    "gn:admin1_code":"02",
    "gn:admin2_code":"68",
    "gn:admin3_code":"25704000.0",
    "gn:asciiname":"Dumabatu",
    "gn:cc2":"PH",
    "gn:country_code":"PH",
    "gn:dem":206,
    "gn:feature_class":"P",
    "gn:feature_code":"PPL",
    "gn:name":"Dumabatu",
    "gn:population":0,
    "gn:timezone":"Asia/Manila",
    "iso:country":"PH",
    "name:und_x_variant":[
        "Dumbato",
        "Dumabatu"
    ],
    "wof:name":"Dumabatu",
    "wof:placetype":"locality"
},
  "geometry": {"coordinates":[121.71666999999999,16.35],"type":"Point"}
}