{
  "type": "Feature",
  "properties": {
    "gn:admin1_code":"01",
    "gn:admin2_code":"51",
    "gn:admin3_code":"15523000.0",
    "gn:asciiname":"Caliwaing",
    "gn:country_code":"PH",
    "gn:dem":130,
    "gn:feature_class":"P",
    "gn:feature_code":"PPL",
    "gn:name":"Caliwaing",
    "gn:population":0,
    "gn:timezone":"Asia/Manila",
    "iso:country":"PH",
    "name:fil_x_preferred":[
        "Caliwaing"
    ],
    "wof:name":"Caliwaing",
    "wof:placetype":"locality"
},
  "geometry": {"coordinates":[119.95556000000001,15.97444],"type":"Point"}
}