{
  "type": "Feature",
  "properties": {
    "gn:admin1_code":"08",
    "gn:admin2_code":"37",
    "gn:admin3_code":"83741000.0",
    "gn:asciiname":"Longbiahay",
    "gn:country_code":"PH",
    "gn:dem":109,
    "gn:feature_class":"P",
    "gn:feature_code":"PPL",
    "gn:name":"Longbiahay",
    "gn:population":0,
    "gn:timezone":"Asia/Manila",
    "iso:country":"PH",
    "name:fil_x_preferred":[
        "Longbiahay"
    ],
    "wof:name":"Longbiahay",
    "wof:placetype":"locality"
},
  "geometry": {"coordinates":[124.81667,11.11667],"type":"Point"}
}