{
  "type": "Feature",
  "properties": {
    "gn:admin1_code":"14",
    "gn:admin2_code":"60",
    "gn:asciiname":"Patukon",
    "gn:country_code":"PH",
    "gn:dem":1,
    "gn:feature_class":"P",
    "gn:feature_code":"PPL",
    "gn:name":"Patukon",
    "gn:population":0,
    "gn:timezone":"Asia/Manila",
    "iso:country":"PH",
    "name:fil_x_preferred":[
        "Patukon"
    ],
    "wof:name":"Patukon",
    "wof:placetype":"locality"
},
  "geometry": {"coordinates":[120.50722,6.2625],"type":"Point"}
}