{
  "type": "Feature",
  "properties": {
    "gn:admin1_code":"06",
    "gn:admin2_code":"30",
    "gn:admin3_code":"63012000.0",
    "gn:asciiname":"Araman",
    "gn:country_code":"PH",
    "gn:dem":62,
    "gn:feature_class":"P",
    "gn:feature_code":"PPL",
    "gn:name":"Araman",
    "gn:population":0,
    "gn:timezone":"Asia/Manila",
    "iso:country":"PH",
    "name:fil_x_preferred":[
        "Araman"
    ],
    "wof:name":"Araman",
    "wof:placetype":"locality"
},
  "geometry": {"coordinates":[122.4879,10.8863],"type":"Point"}
}