{
  "type": "Feature",
  "properties": {
    "gn:admin1_code":"06",
    "gn:admin2_code":"30",
    "gn:admin3_code":"63037000.0",
    "gn:asciiname":"Ilaya",
    "gn:country_code":"PH",
    "gn:dem":34,
    "gn:feature_class":"P",
    "gn:feature_code":"PPL",
    "gn:name":"Ilaya",
    "gn:population":0,
    "gn:timezone":"Asia/Manila",
    "iso:country":"PH",
    "name:fil_x_preferred":[
        "Ilaya"
    ],
    "wof:name":"Ilaya",
    "wof:placetype":"locality"
},
  "geometry": {"coordinates":[122.6074,10.9448],"type":"Point"}
}