{
  "type": "Feature",
  "properties": {
    "gn:admin1_code":"08",
    "gn:admin2_code":"59",
    "gn:admin3_code":"86401000.0",
    "gn:asciiname":"Kamagong",
    "gn:country_code":"PH",
    "gn:dem":330,
    "gn:feature_class":"P",
    "gn:feature_code":"PPL",
    "gn:name":"Kamagong",
    "gn:population":0,
    "gn:timezone":"Asia/Manila",
    "iso:country":"PH",
    "name:fil_x_preferred":[
        "Kamagong"
    ],
    "wof:name":"Kamagong",
    "wof:placetype":"locality"
},
  "geometry": {"coordinates":[125.23333,10.28333],"type":"Point"}
}