{
  "type": "Feature",
  "properties": {
    "gn:admin1_code":"02",
    "gn:admin2_code":"48",
    "gn:admin3_code":"25010000.0",
    "gn:asciiname":"Tidap",
    "gn:country_code":"PH",
    "gn:dem":1442,
    "gn:feature_class":"P",
    "gn:feature_code":"PPL",
    "gn:name":"Tidap",
    "gn:population":0,
    "gn:timezone":"Asia/Manila",
    "iso:country":"PH",
    "name:fil_x_preferred":[
        "Tidap"
    ],
    "wof:name":"Tidap",
    "wof:placetype":"locality"
},
  "geometry": {"coordinates":[120.95,16.38332999999999],"type":"Point"}
}