{
  "type": "Feature",
  "properties": {
    "gn:admin1_code":"11",
    "gn:admin2_code":"25",
    "gn:admin3_code":"112403000.0",
    "gn:asciiname":"Igpit",
    "gn:country_code":"PH",
    "gn:dem":19,
    "gn:feature_class":"P",
    "gn:feature_code":"PPL",
    "gn:name":"Igpit",
    "gn:population":0,
    "gn:timezone":"Asia/Manila",
    "iso:country":"PH",
    "name:fil_x_preferred":[
        "Igpit"
    ],
    "wof:name":"Igpit",
    "wof:placetype":"locality"
},
  "geometry": {"coordinates":[125.32444,6.73472],"type":"Point"}
}