{
  "type": "Feature",
  "properties": {
    "gn:admin1_code":"40",
    "gn:admin2_code":"09",
    "gn:admin3_code":"41029000.0",
    "gn:asciiname":"Calampan",
    "gn:country_code":"PH",
    "gn:dem":106,
    "gn:feature_class":"P",
    "gn:feature_code":"PPL",
    "gn:name":"Calampan",
    "gn:population":0,
    "gn:timezone":"Asia/Manila",
    "iso:country":"PH",
    "name:fil_x_preferred":[
        "Calampan"
    ],
    "wof:name":"Calampan",
    "wof:placetype":"locality"
},
  "geometry": {"coordinates":[120.95139,13.89861],"type":"Point"}
}