{
  "type": "Feature",
  "properties": {
    "gn:admin1_code":"41",
    "gn:admin2_code":"49",
    "gn:admin3_code":"175318000.0",
    "gn:asciiname":"Del Pilar",
    "gn:country_code":"PH",
    "gn:dem":7,
    "gn:feature_class":"P",
    "gn:feature_code":"PPL",
    "gn:name":"Del Pilar",
    "gn:population":0,
    "gn:timezone":"Asia/Manila",
    "iso:country":"PH",
    "name:fil_x_preferred":[
        "Del Pilar"
    ],
    "wof:name":"Del Pilar",
    "wof:placetype":"locality"
},
  "geometry": {"coordinates":[119.34059999999999,10.3177],"type":"Point"}
}