{
  "type": "Feature",
  "properties": {
    "gn:admin1_code":"12",
    "gn:admin2_code":"57",
    "gn:asciiname":"Midsungan",
    "gn:country_code":"PH",
    "gn:dem":897,
    "gn:feature_class":"P",
    "gn:feature_code":"PPL",
    "gn:name":"Midsungan",
    "gn:population":0,
    "gn:timezone":"Asia/Manila",
    "iso:country":"PH",
    "name:fil_x_preferred":[
        "Midsungan"
    ],
    "wof:name":"Midsungan",
    "wof:placetype":"locality"
},
  "geometry": {"coordinates":[125.21611,7.54778],"type":"Point"}
}