{
  "type": "Feature",
  "properties": {
    "gn:admin1_code":"14",
    "gn:admin2_code":"72",
    "gn:admin3_code":"157002000.0",
    "gn:asciiname":"Tong Pettong",
    "gn:country_code":"PH",
    "gn:dem":8,
    "gn:feature_class":"P",
    "gn:feature_code":"PPL",
    "gn:name":"Tong Pettong",
    "gn:population":0,
    "gn:timezone":"Asia/Manila",
    "iso:country":"PH",
    "wof:name":"Tong Pettong",
    "wof:placetype":"locality"
},
  "geometry": {"coordinates":[119.85278,5.04806],"type":"Point"}
}