{
  "type": "Feature",
  "properties": {
    "gn:admin1_code":"07",
    "gn:admin2_code":"21",
    "gn:admin3_code":"72209000.0",
    "gn:asciiname":"Humayhumay",
    "gn:country_code":"PH",
    "gn:dem":11,
    "gn:feature_class":"P",
    "gn:feature_code":"PPL",
    "gn:name":"Humayhumay",
    "gn:population":0,
    "gn:timezone":"Asia/Manila",
    "iso:country":"PH",
    "name:fil_x_preferred":[
        "Humayhumay"
    ],
    "wof:name":"Humayhumay",
    "wof:placetype":"locality"
},
  "geometry": {"coordinates":[123.77388999999999,11.195],"type":"Point"}
}