{
  "type": "Feature",
  "properties": {
    "gn:admin1_code":"02",
    "gn:admin2_code":"48",
    "gn:admin3_code":"25004000.0",
    "gn:asciiname":"Homestead",
    "gn:country_code":"PH",
    "gn:dem":326,
    "gn:feature_class":"P",
    "gn:feature_code":"PPL",
    "gn:name":"Homestead",
    "gn:population":0,
    "gn:timezone":"Asia/Manila",
    "iso:country":"PH",
    "name:cat_x_preferred":[
        "Homestead"
    ],
    "name:ceb_x_preferred":[
        "Homestead"
    ],
    "name:deu_x_preferred":[
        "Homestead"
    ],
    "name:fil_x_preferred":[
        "Homestead"
    ],
    "name:fra_x_preferred":[
        "Homestead"
    ],
    "name:hat_x_preferred":[
        "Homestead"
    ],
    "name:ita_x_preferred":[
        "Homestead"
    ],
    "name:jpn_x_preferred":[
        "\u30db\u30fc\u30e0\u30b9\u30c6\u30c3\u30c9"
    ],
    "name:nld_x_preferred":[
        "Homestead"
    ],
    "name:pol_x_preferred":[
        "Homestead"
    ],
    "name:por_x_preferred":[
        "Homestead"
    ],
    "name:spa_x_preferred":[
        "Homestead"
    ],
    "name:srp_x_preferred":[
        "\u0425\u043e\u043c\u0441\u0442\u0435\u0434"
    ],
    "name:ukr_x_preferred":[
        "\u0413\u043e\u043c\u0441\u0442\u0435\u0434"
    ],
    "name:uzb_x_preferred":[
        "Homestead"
    ],
    "name:vie_x_preferred":[
        "Homestead"
    ],
    "name:vol_x_preferred":[
        "Homestead"
    ],
    "wof:name":"Homestead",
    "wof:placetype":"locality"
},
  "geometry": {"coordinates":[121.1086,16.3922],"type":"Point"}
}