{
  "type": "Feature",
  "properties": {
    "gn:admin1_code":"02",
    "gn:admin2_code":"48",
    "gn:admin3_code":"25004000.0",
    "gn:asciiname":"Homestead",
    "gn:country_code":"PH",
    "gn:dem":326,
    "gn:feature_class":"P",
    "gn:feature_code":"PPL",
    "gn:name":"Homestead",
    "gn:population":0,
    "gn:timezone":"Asia/Manila",
    "iso:country":"PH",
    "name:ben_x_preferred":[
        "\u09b9\u09cb\u09ae\u09b8\u09cd\u099f\u09c7\u09a1"
    ],
    "name:cat_x_preferred":[
        "Homestead"
    ],
    "name:ceb_x_preferred":[
        "Homestead"
    ],
    "name:deu_x_preferred":[
        "Homestead"
    ],
    "name:ell_x_preferred":[
        "\u03a7\u03cc\u03bf\u03c5\u03bc\u03c3\u03c4\u03b5\u03bd\u03c4"
    ],
    "name:fil_x_preferred":[
        "Homestead"
    ],
    "name:fra_x_preferred":[
        "Homestead"
    ],
    "name:hat_x_preferred":[
        "Homestead"
    ],
    "name:hin_x_preferred":[
        "\u0939\u094b\u092e\u0938\u094d\u091f\u0947\u0921"
    ],
    "name:ind_x_preferred":[
        "Homestead"
    ],
    "name:ita_x_preferred":[
        "Homestead"
    ],
    "name:jpn_x_preferred":[
        "\u30db\u30fc\u30e0\u30b9\u30c6\u30c3\u30c9"
    ],
    "name:kor_x_preferred":[
        "\ud648\uc2a4\ud14c\ub4dc"
    ],
    "name:nld_x_preferred":[
        "Homestead"
    ],
    "name:pol_x_preferred":[
        "Homestead"
    ],
    "name:por_x_preferred":[
        "Homestead"
    ],
    "name:spa_x_preferred":[
        "Homestead"
    ],
    "name:srp_x_preferred":[
        "\u0425\u043e\u043c\u0441\u0442\u0435\u0434"
    ],
    "name:ukr_x_preferred":[
        "\u0413\u043e\u043c\u0441\u0442\u0435\u0434"
    ],
    "name:urd_x_preferred":[
        "\u06c1\u0648\u0645\u0633\u0679\u06cc\u0688"
    ],
    "name:uzb_x_preferred":[
        "Homestead"
    ],
    "name:vie_x_preferred":[
        "Homestead"
    ],
    "name:vol_x_preferred":[
        "Homestead"
    ],
    "wof:name":"Homestead",
    "wof:placetype":"locality"
},
  "geometry": {"coordinates":[121.1086,16.3922],"type":"Point"}
}