{
  "type": "Feature",
  "properties": {
    "gn:admin1_code":"02",
    "gn:admin2_code":"48",
    "gn:admin3_code":"25004000.0",
    "gn:asciiname":"Homestead",
    "gn:country_code":"PH",
    "gn:dem":326,
    "gn:feature_class":"P",
    "gn:feature_code":"PPL",
    "gn:name":"Homestead",
    "gn:population":0,
    "gn:timezone":"Asia/Manila",
    "iso:country":"PH",
    "name:fil_x_preferred":[
        "Homestead"
    ],
    "wof:name":"Homestead",
    "wof:placetype":"locality"
},
  "geometry": {"coordinates":[121.1086,16.3922],"type":"Point"}
}