{
  "type": "Feature",
  "properties": {
    "gn:admin1_code":"05",
    "gn:admin2_code":"15",
    "gn:admin3_code":"51608000.0",
    "gn:asciiname":"Calabornay",
    "gn:country_code":"PH",
    "gn:dem":33,
    "gn:feature_class":"P",
    "gn:feature_code":"PPL",
    "gn:name":"Calabornay",
    "gn:population":0,
    "gn:timezone":"Asia/Manila",
    "iso:country":"PH",
    "name:fil_x_preferred":[
        "Calabornay"
    ],
    "name:und_x_variant":[
        "Calaburnay"
    ],
    "wof:name":"Calabornay",
    "wof:placetype":"locality"
},
  "geometry": {"coordinates":[122.80670000000001,14.2575],"type":"Point"}
}