{
  "type": "Feature",
  "properties": {
    "gn:admin1_code":"02",
    "gn:admin2_code":"48",
    "gn:admin3_code":"25004000.0",
    "gn:asciiname":"Dullao",
    "gn:country_code":"PH",
    "gn:dem":342,
    "gn:feature_class":"P",
    "gn:feature_code":"PPL",
    "gn:name":"Dullao",
    "gn:population":0,
    "gn:timezone":"Asia/Manila",
    "iso:country":"PH",
    "name:fil_x_preferred":[
        "Dullao"
    ],
    "wof:name":"Dullao",
    "wof:placetype":"locality"
},
  "geometry": {"coordinates":[121.16030000000001,16.373],"type":"Point"}
}