{
  "type": "Feature",
  "properties": {
    "gn:admin1_code":"08",
    "gn:admin2_code":"37",
    "gn:admin3_code":"83730000.0",
    "gn:asciiname":"Tarrogona",
    "gn:country_code":"PH",
    "gn:dem":6,
    "gn:feature_class":"P",
    "gn:feature_code":"PPL",
    "gn:name":"Tarrogona",
    "gn:population":0,
    "gn:timezone":"Asia/Manila",
    "iso:country":"PH",
    "name:fil_x_preferred":[
        "Tarrogona"
    ],
    "name:und_x_variant":[
        "Mcarthur",
        "Tarraguna",
        "Macarthur",
        "Tarragona"
    ],
    "wof:name":"Tarrogona",
    "wof:placetype":"locality"
},
  "geometry": {"coordinates":[124.9961,10.8308],"type":"Point"}
}