{
  "type": "Feature",
  "properties": {
    "gn:country":"PH",
    "gn:fcode":"PPL",
    "gn:pop":2165,
    "iso:country":"PH",
    "name:fil_x_preferred":[
        "Estefania"
    ],
    "name:fil_x_variant":[
        "Estafania"
    ],
    "name:unk_x_variant":[
        "Estafania"
    ],
    "qs:name":"Estefania",
    "qs:photos_9r":0,
    "qs:photos_sr":0,
    "qs:pop_sr":"4",
    "wd:wordcount":499,
    "wof:name":"Estefania",
    "wof:placetype":"locality",
    "wof:population":2165
},
  "geometry": {"coordinates":[121.72535000000001,17.7976],"type":"Point"}
}