{
  "type": "Feature",
  "properties": {
    "gn:admin1_code":"15",
    "gn:admin2_code":"H6",
    "gn:admin3_code":"148101000.0",
    "gn:asciiname":"Marag",
    "gn:country_code":"PH",
    "gn:dem":215,
    "gn:feature_class":"P",
    "gn:feature_code":"PPL",
    "gn:name":"Marag",
    "gn:population":0,
    "gn:timezone":"Asia/Manila",
    "iso:country":"PH",
    "name:fil_x_preferred":[
        "Marag"
    ],
    "wof:name":"Marag",
    "wof:placetype":"locality"
},
  "geometry": {"coordinates":[121.20440000000001,18.3143],"type":"Point"}
}