{
  "type": "Feature",
  "properties": {
    "gn:admin1_code":"15",
    "gn:admin2_code":"H6",
    "gn:admin3_code":"148105000.0",
    "gn:asciiname":"Luna",
    "gn:country_code":"PH",
    "gn:dem":90,
    "gn:feature_class":"P",
    "gn:feature_code":"PPLA3",
    "gn:name":"Luna",
    "gn:population":0,
    "gn:timezone":"Asia/Manila",
    "iso:country":"PH",
    "name:bcl_x_preferred":[
        "Luna"
    ],
    "name:ceb_x_preferred":[
        "Luna"
    ],
    "name:deu_x_preferred":[
        "Luna"
    ],
    "name:fra_x_preferred":[
        "Luna"
    ],
    "name:ilo_x_preferred":[
        "Luna"
    ],
    "name:ind_x_preferred":[
        "Luna"
    ],
    "name:ita_x_preferred":[
        "Luna"
    ],
    "name:msa_x_preferred":[
        "Luna"
    ],
    "name:nld_x_preferred":[
        "Luna"
    ],
    "name:pag_x_preferred":[
        "Luna"
    ],
    "name:pam_x_preferred":[
        "Luna"
    ],
    "name:spa_x_preferred":[
        "Luna"
    ],
    "name:swe_x_preferred":[
        "Luna"
    ],
    "name:tgl_x_preferred":[
        "Luna"
    ],
    "name:urd_x_preferred":[
        "\u0644\u0648\u0646\u0627"
    ],
    "name:vie_x_preferred":[
        "Luna"
    ],
    "name:war_x_preferred":[
        "Luna"
    ],
    "wof:name":"Luna",
    "wof:placetype":"locality"
},
  "geometry": {"coordinates":[121.35361,18.32583],"type":"Point"}
}