{
  "type": "Feature",
  "properties": {
    "gn:country":"PH",
    "gn:fcode":"PPL",
    "gn:pop":3236,
    "iso:country":"PH",
    "name:fil_x_preferred":[
        "Nanyo"
    ],
    "qs:name":"Nanyo",
    "qs:photos_9r":0,
    "qs:photos_sr":0,
    "qs:pop_sr":"4",
    "wof:name":"Nanyo",
    "wof:placetype":"locality",
    "wof:population":3236
},
  "geometry": {"coordinates":[125.63778000000001,7.33306],"type":"Point"}
}