{
  "type": "Feature",
  "properties": {
    "gn:country":"PH",
    "gn:fcode":"PPL",
    "gn:population":2803,
    "iso:country":"PH",
    "name:fil_x_preferred":[
        "Sabang Indan"
    ],
    "name:und_x_variant":[
        "Sabang"
    ],
    "qs:name":"Sabang Indan",
    "qs:photos_9r":0,
    "qs:photos_sr":0,
    "qs:pop_sr":"4",
    "wof:name":"Sabang Indan",
    "wof:placetype":"locality",
    "wof:population":2803
},
  "geometry": {"coordinates":[122.9151,14.2194],"type":"Point"}
}