{
  "type": "Feature",
  "properties": {
    "gn:admin1_code":"07",
    "gn:admin2_code":"21",
    "gn:admin3_code":"72236000.0",
    "gn:asciiname":"Kawit",
    "gn:country_code":"PH",
    "gn:dem":7,
    "gn:feature_class":"P",
    "gn:feature_code":"PPL",
    "gn:name":"Kawit",
    "gn:population":0,
    "gn:timezone":"Asia/Manila",
    "iso:country":"PH",
    "name:fil_x_preferred":[
        "Kawit"
    ],
    "name:und_x_variant":[
        "Cawit",
        "Kawit"
    ],
    "wof:name":"Kawit",
    "wof:placetype":"locality"
},
  "geometry": {"coordinates":[124.5018,10.7316],"type":"Point"}
}