{
  "type": "Feature",
  "properties": {
    "gn:admin1_code":"08",
    "gn:admin2_code":"37",
    "gn:admin3_code":"83742000.0",
    "gn:asciiname":"Bangon",
    "gn:country_code":"PH",
    "gn:dem":28,
    "gn:feature_class":"P",
    "gn:feature_code":"PPL",
    "gn:name":"Bangon",
    "gn:population":0,
    "gn:timezone":"Asia/Manila",
    "iso:country":"PH",
    "name:fil_x_preferred":[
        "Bangon"
    ],
    "wof:name":"Bangon",
    "wof:placetype":"locality"
},
  "geometry": {"coordinates":[124.36667,11.38333],"type":"Point"}
}