{
  "type": "Feature",
  "properties": {
    "gn:admin1_code":"15",
    "gn:admin2_code":"10",
    "gn:admin3_code":"141107000.0",
    "gn:asciiname":"Caling",
    "gn:country_code":"PH",
    "gn:dem":1130,
    "gn:feature_class":"P",
    "gn:feature_code":"PPL",
    "gn:name":"Caling",
    "gn:population":0,
    "gn:timezone":"Asia/Manila",
    "iso:country":"PH",
    "name:fil_x_preferred":[
        "Caling"
    ],
    "wof:name":"Caling",
    "wof:placetype":"locality"
},
  "geometry": {"coordinates":[120.84034,16.56707999999999],"type":"Point"}
}