{
  "type": "Feature",
  "properties": {
    "gn:country":"PH",
    "gn:fcode":"ADM3",
    "gn:population":92675,
    "iso:country":"PH",
    "name:ceb_x_preferred":[
        "Glan"
    ],
    "name:deu_x_preferred":[
        "Glan"
    ],
    "name:hye_x_preferred":[
        "\u0533\u056c\u0561\u0576"
    ],
    "name:ita_x_preferred":[
        "Glan"
    ],
    "name:nld_x_preferred":[
        "Glan"
    ],
    "name:nor_x_preferred":[
        "Glan"
    ],
    "name:pol_x_preferred":[
        "Glan"
    ],
    "name:rus_x_preferred":[
        "\u0413\u043b\u0430\u043d"
    ],
    "name:srp_x_preferred":[
        "\u0413\u043b\u0430\u043d"
    ],
    "name:swe_x_preferred":[
        "Glan"
    ],
    "name:ukr_x_preferred":[
        "\u0413\u043b\u0430\u043d"
    ],
    "qs:name":"Glan",
    "qs:photos_9r":0,
    "qs:photos_sr":0,
    "qs:pop_sr":"8",
    "wd:wordcount":48,
    "wof:name":"Glan",
    "wof:placetype":"localadmin",
    "wof:population":92675
},
  "geometry": {"coordinates":[125.33333,5.78333],"type":"Point"}
}