{
  "type": "Feature",
  "properties": {
    "gn:admin1_code":"08",
    "gn:admin2_code":"59",
    "gn:admin3_code":"86414000.0",
    "gn:asciiname":"Santa Filomena",
    "gn:country_code":"PH",
    "gn:dem":64,
    "gn:feature_class":"P",
    "gn:feature_code":"PPL",
    "gn:name":"Santa Filomena",
    "gn:population":0,
    "gn:timezone":"Asia/Manila",
    "iso:country":"PH",
    "name:ceb_x_preferred":[
        "Santa Filomena"
    ],
    "name:deu_x_preferred":[
        "Santa Filomena"
    ],
    "name:fil_x_preferred":[
        "Santa Filomena"
    ],
    "name:fra_x_preferred":[
        "Santa Filomena"
    ],
    "name:ita_x_preferred":[
        "Santa Filomena"
    ],
    "name:nld_x_preferred":[
        "Santa Filomena"
    ],
    "name:nor_x_preferred":[
        "Santa Filomena"
    ],
    "name:por_x_preferred":[
        "Santa Filomena"
    ],
    "name:rus_x_preferred":[
        "\u0421\u0430\u043d\u0442\u0430-\u0424\u0438\u043b\u043e\u043c\u0435\u043d\u0430"
    ],
    "name:spa_x_preferred":[
        "Santa Filomena"
    ],
    "name:srp_x_preferred":[
        "\u0421\u0430\u043d\u0442\u0430 \u0424\u0438\u043b\u043e\u043c\u0435\u043d\u0430"
    ],
    "name:swe_x_preferred":[
        "Santa Filomena"
    ],
    "name:vie_x_preferred":[
        "Santa Filomena"
    ],
    "name:vol_x_preferred":[
        "Santa Filomena"
    ],
    "wof:name":"Santa Filomena",
    "wof:placetype":"locality"
},
  "geometry": {"coordinates":[125.18333,10.26667],"type":"Point"}
}