{
  "type": "Feature",
  "properties": {
    "gn:admin1_code":"40",
    "gn:admin2_code":"H2",
    "gn:admin3_code":"45645000.0",
    "gn:asciiname":"Lagnas",
    "gn:country_code":"PH",
    "gn:dem":36,
    "gn:feature_class":"P",
    "gn:feature_code":"PPL",
    "gn:name":"Lagnas",
    "gn:population":0,
    "gn:timezone":"Asia/Manila",
    "iso:country":"PH",
    "name:fil_x_preferred":[
        "Lagnas"
    ],
    "wof:name":"Lagnas",
    "wof:placetype":"locality"
},
  "geometry": {"coordinates":[121.46217,13.87884],"type":"Point"}
}