{
  "type": "Feature",
  "properties": {
    "gn:admin1_code":"09",
    "gn:admin2_code":"65",
    "gn:admin3_code":"97207000.0",
    "gn:asciiname":"Manucan",
    "gn:country_code":"PH",
    "gn:dem":5,
    "gn:feature_class":"P",
    "gn:feature_code":"PPL",
    "gn:name":"Manucan",
    "gn:population":0,
    "gn:timezone":"Asia/Manila",
    "iso:country":"PH",
    "name:eng_x_preferred":[
        "Manucan"
    ],
    "name:und_x_variant":[
        "Manukan"
    ],
    "wof:name":"Manucan",
    "wof:placetype":"locality"
},
  "geometry": {"coordinates":[123.0933,8.5184],"type":"Point"}
}