{
  "type": "Feature",
  "properties": {
    "gn:admin1_code":"15",
    "gn:admin2_code":"01",
    "gn:admin3_code":"140107000.0",
    "gn:asciiname":"Quimmalaba",
    "gn:country_code":"PH",
    "gn:dem":147,
    "gn:feature_class":"P",
    "gn:feature_code":"PPL",
    "gn:name":"Quimmalaba",
    "gn:population":0,
    "gn:timezone":"Asia/Manila",
    "iso:country":"PH",
    "name:fil_x_preferred":[
        "Quimmalaba"
    ],
    "wof:name":"Quimmalaba",
    "wof:placetype":"locality"
},
  "geometry": {"coordinates":[120.74469999999999,17.6464],"type":"Point"}
}