{
  "type": "Feature",
  "properties": {
    "gn:admin1_code":"40",
    "gn:admin2_code":"20",
    "gn:admin3_code":"42105000.0",
    "gn:asciiname":"Caridad",
    "gn:country_code":"PH",
    "gn:dem":5,
    "gn:feature_class":"P",
    "gn:feature_code":"PPL",
    "gn:name":"Caridad",
    "gn:population":0,
    "gn:timezone":"Asia/Manila",
    "iso:country":"PH",
    "name:fil_x_preferred":[
        "Caridad"
    ],
    "wof:name":"Caridad",
    "wof:placetype":"locality"
},
  "geometry": {"coordinates":[120.89041,14.47838],"type":"Point"}
}