{
  "type": "Feature",
  "properties": {
    "gn:admin1_code":"05",
    "gn:admin2_code":"39",
    "gn:admin3_code":"54110000.0",
    "gn:asciiname":"Manapnap",
    "gn:country_code":"PH",
    "gn:dem":7,
    "gn:feature_class":"P",
    "gn:feature_code":"PPL",
    "gn:name":"Manapnap",
    "gn:population":0,
    "gn:timezone":"Asia/Manila",
    "iso:country":"PH",
    "name:fil_x_preferred":[
        "Manapnap"
    ],
    "name:und_x_variant":[
        "Mandapnad",
        "Mandapnap"
    ],
    "wof:name":"Manapnap",
    "wof:placetype":"locality"
},
  "geometry": {"coordinates":[123.24641,12.14015],"type":"Point"}
}