{
  "type": "Feature",
  "properties": {
    "gn:admin1_code":"08",
    "gn:admin2_code":"67",
    "gn:admin3_code":"84808000.0",
    "gn:asciiname":"Candawid",
    "gn:country_code":"PH",
    "gn:dem":15,
    "gn:feature_class":"P",
    "gn:feature_code":"PPL",
    "gn:name":"Candawid",
    "gn:population":0,
    "gn:timezone":"Asia/Manila",
    "iso:country":"PH",
    "name:fil_x_preferred":[
        "Candawid"
    ],
    "wof:name":"Candawid",
    "wof:placetype":"locality"
},
  "geometry": {"coordinates":[125.0568,12.6414],"type":"Point"}
}