{
  "type": "Feature",
  "properties": {
    "gn:admin1_code":"15",
    "gn:admin2_code":"01",
    "gn:admin3_code":"140120000.0",
    "gn:asciiname":"Ududiao",
    "gn:country_code":"PH",
    "gn:dem":292,
    "gn:feature_class":"P",
    "gn:feature_code":"PPL",
    "gn:name":"Ududiao",
    "gn:population":0,
    "gn:timezone":"Asia/Manila",
    "iso:country":"PH",
    "name:fil_x_preferred":[
        "Ududiao"
    ],
    "name:fil_x_variant":[
        "Ududiaw",
        "Udiao"
    ],
    "name:und_x_variant":[
        "Ududiaw",
        "Udiao"
    ],
    "wof:name":"Ududiao",
    "wof:placetype":"locality"
},
  "geometry": {"coordinates":[120.81185000000001,17.46572999999999],"type":"Point"}
}