{
  "type": "Feature",
  "properties": {
    "gn:admin1_code":"12",
    "gn:admin2_code":"70",
    "gn:admin3_code":"126303000.0",
    "gn:asciiname":"Supu",
    "gn:cc2":"PH",
    "gn:country_code":"PH",
    "gn:dem":27,
    "gn:feature_class":"P",
    "gn:feature_code":"PPL",
    "gn:name":"Supu",
    "gn:population":0,
    "gn:timezone":"Asia/Manila",
    "iso:country":"PH",
    "name:und_x_variant":[
        "Sapu"
    ],
    "wof:name":"Supu",
    "wof:placetype":"locality"
},
  "geometry": {"coordinates":[125.14,6.03194],"type":"Point"}
}