{
  "type": "Feature",
  "properties": {
    "gn:admin1_code":"07",
    "gn:admin2_code":"46",
    "gn:admin3_code":"74610000.0",
    "gn:asciiname":"Mojon",
    "gn:country_code":"PH",
    "gn:dem":13,
    "gn:feature_class":"P",
    "gn:feature_code":"PPL",
    "gn:name":"Mojon",
    "gn:population":0,
    "gn:timezone":"Asia/Manila",
    "iso:country":"PH",
    "name:fil_x_preferred":[
        "Mojon"
    ],
    "wof:name":"Mojon",
    "wof:placetype":"locality"
},
  "geometry": {"coordinates":[123.3043,9.3281],"type":"Point"}
}