{
  "type": "Feature",
  "properties": {
    "gn:admin1_code":"03",
    "gn:admin2_code":"47",
    "gn:admin3_code":"34913000.0",
    "gn:asciiname":"Panaulo",
    "gn:country_code":"PH",
    "gn:dem":86,
    "gn:feature_class":"P",
    "gn:feature_code":"PPL",
    "gn:name":"Panaulo",
    "gn:population":0,
    "gn:timezone":"Asia/Manila",
    "iso:country":"PH",
    "name:fil_x_preferred":[
        "Panaulo"
    ],
    "wof:name":"Panaulo",
    "wof:placetype":"locality"
},
  "geometry": {"coordinates":[121.1489,15.5261],"type":"Point"}
}