{
  "type": "Feature",
  "properties": {
    "iso:country":"PH",
    "name:fil_x_preferred":[
        "O\u2019Donnell"
    ],
    "qs:gn_country":"PH",
    "qs:gn_fcode":"PPL",
    "qs:gn_pop":0,
    "qs:name":"O'Donnell",
    "qs:name_adm0":"Philippines",
    "qs:name_adm1":"Central Luzon",
    "qs:photos":42,
    "qs:photos_1k":9,
    "qs:photos_9k":1,
    "qs:photos_9r":2,
    "qs:photos_all":42,
    "qs:photos_sr":2,
    "qs:placetype":"Town",
    "qs:pop_sr":"0",
    "qs:woe_adm0":23424934,
    "wof:name":"O'Donnell",
    "wof:placetype":"locality"
},
  "geometry": {"coordinates":[120.45943,15.35196],"type":"Point"}
}