{
  "type": "Feature",
  "properties": {
    "gn:country":"PH",
    "gn:fcode":"PPL",
    "gn:population":3389,
    "iso:country":"PH",
    "name:und_x_variant":[
        "Sandayong Norte"
    ],
    "qs:name":"Sandayong Sur",
    "qs:photos_9r":0,
    "qs:photos_sr":0,
    "qs:pop_sr":"4",
    "wof:name":"Sandayong Sur",
    "wof:placetype":"locality",
    "wof:population":3389
},
  "geometry": {"coordinates":[123.99889,10.49583],"type":"Point"}
}