{
  "type": "Feature",
  "properties": {
    "gn:country":"PH",
    "gn:fcode":"PPL",
    "gn:pop":5390,
    "iso:country":"PH",
    "name:fil_x_preferred":[
        "Tabuan"
    ],
    "name:urd_x_preferred":[
        "\u062a\u0628\u0648\u0639\u0627\u0646"
    ],
    "qs:name":"Tabuan",
    "qs:photos_9r":0,
    "qs:photos_sr":0,
    "qs:pop_sr":"5",
    "wd:wordcount":53,
    "wof:name":"Tabuan",
    "wof:placetype":"locality",
    "wof:population":5390
},
  "geometry": {"coordinates":[122.85056,9.51556],"type":"Point"}
}