{
  "type": "Feature",
  "properties": {
    "gn:admin1_code":"02",
    "gn:admin2_code":"48",
    "gn:asciiname":"Daowegon",
    "gn:country_code":"PH",
    "gn:dem":320,
    "gn:feature_class":"P",
    "gn:feature_code":"PPL",
    "gn:name":"Daowegon",
    "gn:population":0,
    "gn:timezone":"Asia/Manila",
    "iso:country":"PH",
    "name:fil_x_preferred":[
        "Daowegon"
    ],
    "wof:name":"Daowegon",
    "wof:placetype":"locality"
},
  "geometry": {"coordinates":[120.7727,16.2208],"type":"Point"}
}