{
  "type": "Feature",
  "properties": {
    "gn:country":"PH",
    "gn:fcode":"ADM3",
    "gn:population":67558,
    "iso:country":"PH",
    "name:fil_x_preferred":[
        "Nabunturan"
    ],
    "qs:name":"Nabunturan",
    "qs:photos_9r":0,
    "qs:photos_sr":0,
    "qs:pop_sr":"8",
    "wof:name":"Nabunturan",
    "wof:placetype":"localadmin",
    "wof:population":67558
},
  "geometry": {"coordinates":[126.01667,7.58333],"type":"Point"}
}