{
  "type": "Feature",
  "properties": {
    "gn:admin1_code":"02",
    "gn:admin2_code":"31",
    "gn:admin3_code":"23134000.0",
    "gn:asciiname":"Naganacan",
    "gn:country_code":"PH",
    "gn:dem":61,
    "gn:feature_class":"P",
    "gn:feature_code":"PPL",
    "gn:name":"Naganacan",
    "gn:population":0,
    "gn:timezone":"Asia/Manila",
    "iso:country":"PH",
    "name:fil_x_preferred":[
        "Naganacan"
    ],
    "wof:name":"Naganacan",
    "wof:placetype":"locality"
},
  "geometry": {"coordinates":[121.67921,17.45952999999999],"type":"Point"}
}