{
  "type": "Feature",
  "properties": {
    "gn:admin1_code":"41",
    "gn:admin2_code":"54",
    "gn:admin3_code":"175907000.0",
    "gn:asciiname":"Guimpasilan",
    "gn:country_code":"PH",
    "gn:dem":0,
    "gn:feature_class":"P",
    "gn:feature_code":"PPL",
    "gn:name":"Guimpasilan",
    "gn:population":0,
    "gn:timezone":"Asia/Manila",
    "iso:country":"PH",
    "name:fil_x_preferred":[
        "Guimpasilan"
    ],
    "wof:name":"Guimpasilan",
    "wof:placetype":"locality"
},
  "geometry": {"coordinates":[121.9769,12.2037],"type":"Point"}
}