{
  "type": "Feature",
  "properties": {
    "gn:admin1_code":"10",
    "gn:admin2_code":"42",
    "gn:admin3_code":"104209000.0",
    "gn:asciiname":"Senote",
    "gn:country_code":"PH",
    "gn:dem":113,
    "gn:feature_class":"P",
    "gn:feature_code":"PPL",
    "gn:name":"Senote",
    "gn:population":0,
    "gn:timezone":"Asia/Manila",
    "iso:country":"PH",
    "name:fil_x_preferred":[
        "Senote"
    ],
    "wof:name":"Senote",
    "wof:placetype":"locality"
},
  "geometry": {"coordinates":[123.76667,8.46667],"type":"Point"}
}