{
  "type": "Feature",
  "properties": {
    "gn:admin1_code":"40",
    "gn:admin2_code":"H2",
    "gn:admin3_code":"45630000.0",
    "gn:asciiname":"Ibabang Bagumbungan",
    "gn:country_code":"PH",
    "gn:dem":147,
    "gn:feature_class":"P",
    "gn:feature_code":"PPL",
    "gn:name":"Ibabang Bagumbungan",
    "gn:population":0,
    "gn:timezone":"Asia/Manila",
    "iso:country":"PH",
    "name:fil_x_preferred":[
        "Ibabang Bagumbungan"
    ],
    "wof:name":"Ibabang Bagumbungan",
    "wof:placetype":"locality"
},
  "geometry": {"coordinates":[121.69589999999999,14.0045],"type":"Point"}
}