{
  "type": "Feature",
  "properties": {
    "gn:country":"PH",
    "gn:fcode":"PPL",
    "gn:population":4599,
    "iso:country":"PH",
    "name:fil_x_preferred":[
        "Salaza"
    ],
    "name:und_x_variant":[
        "Salasa"
    ],
    "qs:name":"Salaza",
    "qs:photos_9r":0,
    "qs:photos_sr":0,
    "qs:pop_sr":"4",
    "wof:name":"Salaza",
    "wof:placetype":"locality",
    "wof:population":4599
},
  "geometry": {"coordinates":[119.95529999999999,15.4541],"type":"Point"}
}