{
  "type": "Feature",
  "properties": {
    "iso:country":"PH",
    "name:bcl_x_preferred":[
        "Palompon"
    ],
    "name:cbk_zam_x_preferred":[
        "Palompon"
    ],
    "name:ceb_x_preferred":[
        "Palompon"
    ],
    "name:deu_x_preferred":[
        "Palompon"
    ],
    "name:eng_x_preferred":[
        "Palompon"
    ],
    "name:fra_x_preferred":[
        "Palompon"
    ],
    "name:ilo_x_preferred":[
        "Palompon"
    ],
    "name:ind_x_preferred":[
        "Palompon"
    ],
    "name:ita_x_preferred":[
        "Palompon"
    ],
    "name:nld_x_preferred":[
        "Palompon"
    ],
    "name:nob_x_preferred":[
        "Palompon"
    ],
    "name:nor_x_preferred":[
        "Palompon"
    ],
    "name:pag_x_preferred":[
        "Palompon"
    ],
    "name:pam_x_preferred":[
        "Palompon"
    ],
    "name:swe_x_preferred":[
        "Palompon"
    ],
    "name:tgl_x_preferred":[
        "Palompon"
    ],
    "name:vie_x_preferred":[
        "Palompon"
    ],
    "name:war_x_preferred":[
        "Palompon"
    ],
    "qs:gn_country":"PH",
    "qs:gn_fcode":"PPL",
    "qs:gn_pop":0,
    "qs:name":"Palompon",
    "qs:name_adm0":"Philippines",
    "qs:name_adm1":"Eastern Visayas",
    "qs:photos":166,
    "qs:photos_1k":34,
    "qs:photos_9k":1,
    "qs:photos_9r":4,
    "qs:photos_all":166,
    "qs:photos_sr":4,
    "qs:placetype":"Town",
    "qs:pop_sr":"0",
    "qs:woe_adm0":23424934,
    "wd:wordcount":2902,
    "wof:name":"Palompon",
    "wof:placetype":"locality"
},
  "geometry": {"coordinates":[124.54222,11.17028],"type":"Point"}
}