{
  "type": "Feature",
  "properties": {
    "gn:admin1_code":"08",
    "gn:admin2_code":"59",
    "gn:admin3_code":"86405000.0",
    "gn:asciiname":"Pinamosilan",
    "gn:country_code":"PH",
    "gn:dem":2,
    "gn:feature_class":"P",
    "gn:feature_code":"PPL",
    "gn:name":"Pinamosilan",
    "gn:population":0,
    "gn:timezone":"Asia/Manila",
    "iso:country":"PH",
    "name:fil_x_preferred":[
        "Pinamosilan"
    ],
    "name:und_x_variant":[
        "Pinamasilan"
    ],
    "wof:name":"Pinamosilan",
    "wof:placetype":"locality"
},
  "geometry": {"coordinates":[125.02509999999999,10.368],"type":"Point"}
}