{
  "type": "Feature",
  "properties": {
    "gn:country":"PH",
    "gn:fcode":"PPL",
    "gn:pop":3641,
    "iso:country":"PH",
    "name:unk_x_variant":[
        "Sandulot"
    ],
    "qs:name":"Sandolot",
    "qs:photos_9r":0,
    "qs:photos_sr":0,
    "qs:pop_sr":"4",
    "wof:name":"Sandolot",
    "wof:placetype":"locality",
    "wof:population":3641
},
  "geometry": {"coordinates":[123.01944,9.10472],"type":"Point"}
}