{
  "type": "Feature",
  "properties": {
    "gn:admin1_code":"01",
    "gn:admin2_code":"51",
    "gn:admin3_code":"15525000.0",
    "gn:asciiname":"Inamotan",
    "gn:country_code":"PH",
    "gn:dem":22,
    "gn:feature_class":"P",
    "gn:feature_code":"PPL",
    "gn:name":"Inamotan",
    "gn:population":0,
    "gn:timezone":"Asia/Manila",
    "iso:country":"PH",
    "name:fil_x_preferred":[
        "Inamotan"
    ],
    "name:fil_x_variant":[
        "Inamutan"
    ],
    "wof:name":"Inamotan",
    "wof:placetype":"locality"
},
  "geometry": {"coordinates":[120.5284,16.0088],"type":"Point"}
}