{
  "type": "Feature",
  "properties": {
    "gn:admin1_code":"01",
    "gn:admin2_code":"36",
    "gn:admin3_code":"13306000.0",
    "gn:asciiname":"Sinapangan",
    "gn:country_code":"PH",
    "gn:dem":62,
    "gn:feature_class":"P",
    "gn:feature_code":"PPL",
    "gn:name":"Sinapangan",
    "gn:population":0,
    "gn:timezone":"Asia/Manila",
    "iso:country":"PH",
    "name:fil_x_preferred":[
        "Sinapangan"
    ],
    "wof:name":"Sinapangan",
    "wof:placetype":"locality"
},
  "geometry": {"coordinates":[120.45,16.86667000000001],"type":"Point"}
}