{
  "type": "Feature",
  "properties": {
    "gn:admin1_code":"40",
    "gn:admin2_code":"09",
    "gn:asciiname":"Sugod",
    "gn:country_code":"PH",
    "gn:dem":5,
    "gn:feature_class":"P",
    "gn:feature_code":"PPL",
    "gn:name":"Sugod",
    "gn:population":0,
    "gn:timezone":"Asia/Manila",
    "iso:country":"PH",
    "name:fil_x_preferred":[
        "Sugod"
    ],
    "wof:name":"Sugod",
    "wof:placetype":"locality"
},
  "geometry": {"coordinates":[120.96666999999999,14.08333],"type":"Point"}
}