{
  "type": "Feature",
  "properties": {
    "gn:admin1_code":"01",
    "gn:admin2_code":"29",
    "gn:admin3_code":"12906000.0",
    "gn:asciiname":"Patpata",
    "gn:country_code":"PH",
    "gn:dem":3,
    "gn:feature_class":"P",
    "gn:feature_code":"PPL",
    "gn:name":"Patpata",
    "gn:population":0,
    "gn:timezone":"Asia/Manila",
    "iso:country":"PH",
    "name:fil_x_preferred":[
        "Patpata"
    ],
    "name:und_x_variant":[
        "Patpata Primero"
    ],
    "wof:name":"Patpata",
    "wof:placetype":"locality"
},
  "geometry": {"coordinates":[120.43164,17.1576],"type":"Point"}
}