{
  "type": "Feature",
  "properties": {
    "gn:admin1_code":"12",
    "gn:admin2_code":"M9",
    "gn:admin3_code":"128006000.0",
    "gn:asciiname":"Lun Grande",
    "gn:country_code":"PH",
    "gn:dem":20,
    "gn:feature_class":"P",
    "gn:feature_code":"PPL",
    "gn:name":"Lun Grande",
    "gn:population":0,
    "gn:timezone":"Asia/Manila",
    "iso:country":"PH",
    "name:fil_x_preferred":[
        "Lun Grande"
    ],
    "name:und_x_variant":[
        "Lun",
        "Lun Masla",
        "Lun Masala"
    ],
    "wof:name":"Lun Grande",
    "wof:placetype":"locality"
},
  "geometry": {"coordinates":[125.29806000000001,6.03556],"type":"Point"}
}