{
  "type": "Feature",
  "properties": {
    "gn:admin1_code":"01",
    "gn:admin2_code":"29",
    "gn:admin3_code":"12920000.0",
    "gn:asciiname":"Gimutsyr",
    "gn:country_code":"PH",
    "gn:dem":4,
    "gn:feature_class":"P",
    "gn:feature_code":"PPL",
    "gn:name":"Gimutsyr",
    "gn:population":0,
    "gn:timezone":"Asia/Manila",
    "iso:country":"PH",
    "name:fil_x_preferred":[
        "Gimutsyr"
    ],
    "name:und_x_variant":[
        "Guimud Sur",
        "Guimod Sur"
    ],
    "wof:name":"Gimutsyr",
    "wof:placetype":"locality"
},
  "geometry": {"coordinates":[120.42102,17.71692999999999],"type":"Point"}
}