{
  "type": "Feature",
  "properties": {
    "gn:admin1_code":"01",
    "gn:admin2_code":"36",
    "gn:admin3_code":"13317000.0",
    "gn:asciiname":"Santo Tomas",
    "gn:country_code":"PH",
    "gn:dem":8,
    "gn:feature_class":"P",
    "gn:feature_code":"PPLA3",
    "gn:name":"Santo Tomas",
    "gn:population":0,
    "gn:timezone":"Asia/Manila",
    "iso:country":"PH",
    "name:bcl_x_preferred":[
        "Santo Tomas"
    ],
    "name:ceb_x_preferred":[
        "Santo Tomas"
    ],
    "name:deu_x_preferred":[
        "Santo Tomas"
    ],
    "name:fil_x_preferred":[
        "Santo Tomas"
    ],
    "name:fil_x_variant":[
        "Santo Thomas",
        "Santa Tomas"
    ],
    "name:fra_x_preferred":[
        "Santo Tomas"
    ],
    "name:ilo_x_preferred":[
        "Santo Tomas"
    ],
    "name:ind_x_preferred":[
        "Santo Tomas"
    ],
    "name:ita_x_preferred":[
        "Santo Tomas"
    ],
    "name:nld_x_preferred":[
        "Santo Tomas"
    ],
    "name:pag_x_preferred":[
        "Santo Tomas"
    ],
    "name:pam_x_preferred":[
        "Santo Tomas"
    ],
    "name:sco_x_preferred":[
        "Santo Tomas"
    ],
    "name:spa_x_preferred":[
        "Santo Tom\u00e1s"
    ],
    "name:swe_x_preferred":[
        "Santo Tomas"
    ],
    "name:tgl_x_preferred":[
        "Santo Tomas"
    ],
    "name:und_x_variant":[
        "Santo Thomas",
        "Santa Tomas",
        "Santo Tomas"
    ],
    "name:vie_x_preferred":[
        "Santo Tomas"
    ],
    "name:war_x_preferred":[
        "Santo Tomas"
    ],
    "wof:name":"Santo Tomas",
    "wof:placetype":"locality"
},
  "geometry": {"coordinates":[120.3792,16.2798],"type":"Point"}
}