{
  "type": "Feature",
  "properties": {
    "gn:admin1_code":"41",
    "gn:admin2_code":"41",
    "gn:admin3_code":"175211000.0",
    "gn:asciiname":"Paniguian",
    "gn:country_code":"PH",
    "gn:dem":10,
    "gn:feature_class":"P",
    "gn:feature_code":"PPL",
    "gn:name":"Paniguian",
    "gn:population":0,
    "gn:timezone":"Asia/Manila",
    "iso:country":"PH",
    "name:eng_x_preferred":[
        "Paniguian"
    ],
    "wof:name":"Paniguian",
    "wof:placetype":"locality"
},
  "geometry": {"coordinates":[120.9516,13.5237],"type":"Point"}
}