{
  "type": "Feature",
  "properties": {
    "gn:admin1_code":"05",
    "gn:admin2_code":"15",
    "gn:admin3_code":"51608000.0",
    "gn:asciiname":"Talusan",
    "gn:country_code":"PH",
    "gn:dem":108,
    "gn:feature_class":"P",
    "gn:feature_code":"PPL",
    "gn:name":"Talusan",
    "gn:population":0,
    "gn:timezone":"Asia/Manila",
    "iso:country":"PH",
    "name:fil_x_preferred":[
        "Talusan"
    ],
    "wof:name":"Talusan",
    "wof:placetype":"locality"
},
  "geometry": {"coordinates":[122.78333000000001,14.26667],"type":"Point"}
}