{
  "type": "Feature",
  "properties": {
    "gn:admin1_code":"10",
    "gn:admin2_code":"43",
    "gn:admin3_code":"104312000.0",
    "gn:asciiname":"Kinogitan",
    "gn:country_code":"PH",
    "gn:dem":-9999,
    "gn:feature_class":"P",
    "gn:feature_code":"PPLA3",
    "gn:name":"Kinogitan",
    "gn:population":0,
    "gn:timezone":"Asia/Manila",
    "iso:country":"PH",
    "wof:name":"Kinogitan",
    "wof:placetype":"locality"
},
  "geometry": {"coordinates":[124.79277999999999,8.98556],"type":"Point"}
}