{
  "type": "Feature",
  "properties": {
    "gn:admin1_code":"05",
    "gn:admin2_code":"05",
    "gn:admin3_code":"50502000.0",
    "gn:asciiname":"Taladong",
    "gn:country_code":"PH",
    "gn:dem":101,
    "gn:feature_class":"P",
    "gn:feature_code":"PPL",
    "gn:name":"Taladong",
    "gn:population":0,
    "gn:timezone":"Asia/Manila",
    "iso:country":"PH",
    "name:fil_x_preferred":[
        "Taladong"
    ],
    "wof:name":"Taladong",
    "wof:placetype":"locality"
},
  "geometry": {"coordinates":[123.65260000000001,13.138],"type":"Point"}
}