{
  "type": "Feature",
  "properties": {
    "gn:admin1_code":"06",
    "gn:admin2_code":"H3",
    "gn:admin3_code":"64506000.0",
    "gn:asciiname":"Cabadiangan",
    "gn:country_code":"PH",
    "gn:dem":181,
    "gn:feature_class":"P",
    "gn:feature_code":"PPL",
    "gn:name":"Cabadia\u00f1gan",
    "gn:population":0,
    "gn:timezone":"Asia/Manila",
    "iso:country":"PH",
    "name:fil_x_preferred":[
        "Cabadia\u00f1gan"
    ],
    "wof:name":"Cabadiangan",
    "wof:placetype":"locality"
},
  "geometry": {"coordinates":[122.63306,9.81917],"type":"Point"}
}