{
  "type": "Feature",
  "properties": {
    "gn:admin1_code":"09",
    "gn:admin2_code":"ZSI",
    "gn:admin3_code":"98302000.0",
    "gn:asciiname":"Basalem",
    "gn:country_code":"PH",
    "gn:dem":146,
    "gn:feature_class":"P",
    "gn:feature_code":"PPL",
    "gn:name":"Basalem",
    "gn:population":0,
    "gn:timezone":"Asia/Manila",
    "iso:country":"PH",
    "name:fil_x_preferred":[
        "Basalem"
    ],
    "wof:name":"Basalem",
    "wof:placetype":"locality"
},
  "geometry": {"coordinates":[123.07832999999999,7.73944],"type":"Point"}
}