{
  "type": "Feature",
  "properties": {
    "gn:admin1_code":"03",
    "gn:admin2_code":"47",
    "gn:admin3_code":"34912000.0",
    "gn:asciiname":"Dampulan",
    "gn:country_code":"PH",
    "gn:dem":26,
    "gn:feature_class":"P",
    "gn:feature_code":"PPL",
    "gn:name":"Dampulan",
    "gn:population":0,
    "gn:timezone":"Asia/Manila",
    "iso:country":"PH",
    "name:fil_x_preferred":[
        "Dampulan"
    ],
    "wof:name":"Dampulan",
    "wof:placetype":"locality"
},
  "geometry": {"coordinates":[120.90519999999999,15.34078],"type":"Point"}
}