{
  "type": "Feature",
  "properties": {
    "gn:admin1_code":"06",
    "gn:admin2_code":"30",
    "gn:admin3_code":"63034000.0",
    "gn:asciiname":"Santa Rita",
    "gn:country_code":"PH",
    "gn:dem":20,
    "gn:feature_class":"P",
    "gn:feature_code":"PPL",
    "gn:name":"Santa Rita",
    "gn:population":0,
    "gn:timezone":"Asia/Manila",
    "iso:country":"PH",
    "name:fil_x_preferred":[
        "Santa Rita"
    ],
    "wof:name":"Santa Rita",
    "wof:placetype":"locality"
},
  "geometry": {"coordinates":[122.45638999999998,10.71972],"type":"Point"}
}