{
  "type": "Feature",
  "properties": {
    "gn:admin1_code":"05",
    "gn:admin2_code":"15",
    "gn:admin3_code":"51608000.0",
    "gn:asciiname":"Daguit Number Two",
    "gn:country_code":"PH",
    "gn:dem":63,
    "gn:feature_class":"P",
    "gn:feature_code":"PPL",
    "gn:name":"Daguit Number Two",
    "gn:population":0,
    "gn:timezone":"Asia/Manila",
    "iso:country":"PH",
    "name:eng_x_preferred":[
        "Daguit Number Two"
    ],
    "wof:name":"Daguit Number Two",
    "wof:placetype":"locality"
},
  "geometry": {"coordinates":[122.6824,14.191],"type":"Point"}
}