{
  "type": "Feature",
  "properties": {
    "gn:admin1_code":"41",
    "gn:admin2_code":"49",
    "gn:admin3_code":"175316000.0",
    "gn:asciiname":"San Rafael",
    "gn:country_code":"PH",
    "gn:dem":5,
    "gn:feature_class":"P",
    "gn:feature_code":"PPL",
    "gn:name":"San Rafael",
    "gn:population":0,
    "gn:timezone":"Asia/Manila",
    "iso:country":"PH",
    "name:fil_x_preferred":[
        "San Rafael"
    ],
    "wof:name":"San Rafael",
    "wof:placetype":"locality"
},
  "geometry": {"coordinates":[118.9654,9.9854],"type":"Point"}
}