{
  "type": "Feature",
  "properties": {
    "gn:admin1_code":"02",
    "gn:admin2_code":"68",
    "gn:admin3_code":"25703000.0",
    "gn:asciiname":"Guinagat",
    "gn:country_code":"PH",
    "gn:dem":490,
    "gn:feature_class":"P",
    "gn:feature_code":"PPL",
    "gn:name":"Guinagat",
    "gn:population":0,
    "gn:timezone":"Asia/Manila",
    "iso:country":"PH",
    "name:fil_x_preferred":[
        "Guinagat"
    ],
    "wof:name":"Guinagat",
    "wof:placetype":"locality"
},
  "geometry": {"coordinates":[121.4286,16.5911],"type":"Point"}
}