{
  "type": "Feature",
  "properties": {
    "gn:country":"PH",
    "gn:fcode":"PPL",
    "gn:population":2350,
    "iso:country":"PH",
    "name:fil_x_preferred":[
        "Batung"
    ],
    "name:fil_x_variant":[
        "Battung"
    ],
    "qs:name":"Battung",
    "qs:photos_9r":0,
    "qs:photos_sr":0,
    "qs:pop_sr":"4",
    "wof:name":"Battung",
    "wof:placetype":"locality",
    "wof:population":2350
},
  "geometry": {"coordinates":[121.45914,17.72261],"type":"Point"}
}