{
  "type": "Feature",
  "properties": {
    "iso:country":"PH",
    "name:bcl_x_preferred":[
        "Borbon"
    ],
    "name:cbk_zam_x_preferred":[
        "Borbon"
    ],
    "name:ceb_x_preferred":[
        "Borbon"
    ],
    "name:deu_x_preferred":[
        "Borbon"
    ],
    "name:dut_x_preferred":[
        "Borbon"
    ],
    "name:eng_x_preferred":[
        "Borbon"
    ],
    "name:fil_x_preferred":[
        "Borbon"
    ],
    "name:fra_x_preferred":[
        "Borbon"
    ],
    "name:fre_x_preferred":[
        "Borbon"
    ],
    "name:ger_x_preferred":[
        "Borbon"
    ],
    "name:ilo_x_preferred":[
        "Borbon"
    ],
    "name:ind_x_preferred":[
        "Borbon"
    ],
    "name:ita_x_preferred":[
        "Borbon"
    ],
    "name:nld_x_preferred":[
        "Borbon"
    ],
    "name:pag_x_preferred":[
        "Borbon"
    ],
    "name:pam_x_preferred":[
        "Borbon"
    ],
    "name:per_x_preferred":[
        "\u0628\u0648\u0631\u0628\u0646\u060c \u0633\u0628\u0648"
    ],
    "name:spa_x_preferred":[
        "Borb\u00f3n"
    ],
    "name:swe_x_preferred":[
        "Borbon"
    ],
    "name:tgl_x_preferred":[
        "Borbon"
    ],
    "name:vie_x_preferred":[
        "Borbon"
    ],
    "name:war_x_preferred":[
        "Borbon"
    ],
    "qs:gn_country":"PH",
    "qs:gn_fcode":"PPLA3",
    "qs:gn_pop":4703,
    "qs:name":"Borbon",
    "qs:name_adm0":"Philippines",
    "qs:name_adm1":"Central Visayas",
    "qs:photos":32,
    "qs:photos_1k":6,
    "qs:photos_9k":1,
    "qs:photos_9r":2,
    "qs:photos_all":32,
    "qs:photos_sr":2,
    "qs:placetype":"Town",
    "qs:pop_sr":"4",
    "qs:woe_adm0":23424934,
    "wd:wordcount":541,
    "wof:name":"Borbon",
    "wof:placetype":"locality",
    "wof:population":4703
},
  "geometry": {"coordinates":[124.02970000000001,10.838],"type":"Point"}
}