{
  "type": "Feature",
  "properties": {
    "gn:admin1_code":"06",
    "gn:admin2_code":"H3",
    "gn:admin3_code":"64517000.0",
    "gn:asciiname":"Bato",
    "gn:country_code":"PH",
    "gn:dem":97,
    "gn:feature_class":"P",
    "gn:feature_code":"PPL",
    "gn:name":"Bato",
    "gn:population":0,
    "gn:timezone":"Asia/Manila",
    "iso:country":"PH",
    "name:cat_x_preferred":[
        "Bat\u00f3"
    ],
    "name:ceb_x_preferred":[
        "Bato"
    ],
    "name:deu_x_preferred":[
        "Bato"
    ],
    "name:fil_x_preferred":[
        "Bato"
    ],
    "name:fra_x_preferred":[
        "Bato"
    ],
    "name:ind_x_preferred":[
        "Bato"
    ],
    "name:ita_x_preferred":[
        "Bato"
    ],
    "name:nld_x_preferred":[
        "Bato"
    ],
    "name:spa_x_preferred":[
        "Bato"
    ],
    "name:swe_x_preferred":[
        "Bato"
    ],
    "name:tgl_x_preferred":[
        "Bato"
    ],
    "name:war_x_preferred":[
        "Bato"
    ],
    "wof:name":"Bato",
    "wof:placetype":"locality"
},
  "geometry": {"coordinates":[123.06480000000001,10.3173],"type":"Point"}
}