{
  "type": "Feature",
  "properties": {
    "gn:country":"PH",
    "gn:fcode":"PPLA3",
    "gn:pop":5232,
    "iso:country":"PH",
    "name:bcl_x_preferred":[
        "Basud"
    ],
    "name:dut_x_preferred":[
        "Basud"
    ],
    "name:eng_x_preferred":[
        "Basud"
    ],
    "name:fil_x_preferred":[
        "Basud"
    ],
    "name:fre_x_preferred":[
        "Basud"
    ],
    "name:ger_x_preferred":[
        "Basud"
    ],
    "name:ilo_x_preferred":[
        "Basud"
    ],
    "name:ind_x_preferred":[
        "Basud"
    ],
    "name:ita_x_preferred":[
        "Basud"
    ],
    "name:pag_x_preferred":[
        "Basud"
    ],
    "name:pam_x_preferred":[
        "Basud"
    ],
    "name:spa_x_preferred":[
        "Bas\u00fad"
    ],
    "name:swe_x_preferred":[
        "Basud"
    ],
    "name:tgl_x_preferred":[
        "Basud"
    ],
    "name:unk_x_variant":[
        "Busod"
    ],
    "name:war_x_preferred":[
        "Basud"
    ],
    "qs:name":"Basud",
    "qs:photos_9r":0,
    "qs:photos_sr":0,
    "qs:pop_sr":"5",
    "wof:name":"Basud",
    "wof:placetype":"locality",
    "wof:population":5232
},
  "geometry": {"coordinates":[122.96420000000001,14.065],"type":"Point"}
}