{
  "type": "Feature",
  "properties": {
    "gn:admin1_code":"15",
    "gn:admin2_code":"10",
    "gn:admin3_code":"141107000.0",
    "gn:asciiname":"Lamayan",
    "gn:country_code":"PH",
    "gn:dem":2314,
    "gn:feature_class":"P",
    "gn:feature_code":"PPL",
    "gn:name":"Lamayan",
    "gn:population":0,
    "gn:timezone":"Asia/Manila",
    "iso:country":"PH",
    "name:fil_x_preferred":[
        "Lamayan"
    ],
    "wof:name":"Lamayan",
    "wof:placetype":"locality"
},
  "geometry": {"coordinates":[120.88943999999999,16.64958],"type":"Point"}
}