{
  "type": "Feature",
  "properties": {
    "gn:country":"PH",
    "gn:fcode":"PPL",
    "gn:population":15589,
    "iso:country":"PH",
    "name:ceb_x_preferred":[
        "Calumpang"
    ],
    "name:fil_x_preferred":[
        "Kalumpang"
    ],
    "name:fil_x_variant":[
        "Calumpang"
    ],
    "name:und_x_variant":[
        "Calumbang"
    ],
    "qs:name":"Calumpang",
    "qs:photos_9r":0,
    "qs:photos_sr":0,
    "qs:pop_sr":"6",
    "wd:wordcount":16,
    "wof:name":"Calumpang",
    "wof:placetype":"locality",
    "wof:population":15589
},
  "geometry": {"coordinates":[121.08969999999999,14.6228],"type":"Point"}
}