{
  "type": "Feature",
  "properties": {
    "gn:admin1_code":"05",
    "gn:admin2_code":"15",
    "gn:admin3_code":"51603000.0",
    "gn:asciiname":"Carumpit",
    "gn:country_code":"PH",
    "gn:dem":9,
    "gn:feature_class":"P",
    "gn:feature_code":"PPL",
    "gn:name":"Carumpit",
    "gn:population":0,
    "gn:timezone":"Asia/Manila",
    "iso:country":"PH",
    "name:fil_x_preferred":[
        "Carumpit"
    ],
    "name:und_x_variant":[
        "Carompit"
    ],
    "wof:name":"Carumpit",
    "wof:placetype":"locality"
},
  "geometry": {"coordinates":[122.95950000000001,14.1091],"type":"Point"}
}