{
  "type": "Feature",
  "properties": {
    "gn:admin1_code":"11",
    "gn:admin2_code":"25",
    "gn:admin3_code":"112414000.0",
    "gn:asciiname":"Kotipunan",
    "gn:country_code":"PH",
    "gn:dem":33,
    "gn:feature_class":"P",
    "gn:feature_code":"PPL",
    "gn:name":"Kotipunan",
    "gn:population":0,
    "gn:timezone":"Asia/Manila",
    "iso:country":"PH",
    "name:fil_x_preferred":[
        "Kotipunan"
    ],
    "wof:name":"Kotipunan",
    "wof:placetype":"locality"
},
  "geometry": {"coordinates":[125.29083,6.64639],"type":"Point"}
}