{
  "type": "Feature",
  "properties": {
    "gn:admin1_code":"02",
    "gn:admin2_code":"31",
    "gn:admin3_code":"23135000.0",
    "gn:asciiname":"Capaltitan",
    "gn:country_code":"PH",
    "gn:dem":106,
    "gn:feature_class":"P",
    "gn:feature_code":"PPL",
    "gn:name":"Capaltitan",
    "gn:population":0,
    "gn:timezone":"Asia/Manila",
    "iso:country":"PH",
    "name:fil_x_preferred":[
        "Capaltitan"
    ],
    "wof:name":"Capaltitan",
    "wof:placetype":"locality"
},
  "geometry": {"coordinates":[121.5286,16.6705],"type":"Point"}
}