{
  "type": "Feature",
  "properties": {
    "gn:admin1_code":"06",
    "gn:admin2_code":"H3",
    "gn:admin3_code":"64520000.0",
    "gn:asciiname":"Dato",
    "gn:country_code":"PH",
    "gn:dem":228,
    "gn:feature_class":"P",
    "gn:feature_code":"PPL",
    "gn:name":"Dato",
    "gn:population":0,
    "gn:timezone":"Asia/Manila",
    "iso:country":"PH",
    "name:ceb_x_preferred":[
        "Dato"
    ],
    "name:dan_x_preferred":[
        "Dato"
    ],
    "name:deu_x_preferred":[
        "Dato"
    ],
    "name:fil_x_preferred":[
        "Dato"
    ],
    "name:fra_x_preferred":[
        "Dato"
    ],
    "name:rus_x_preferred":[
        "\u0414\u0430\u0442\u043e"
    ],
    "name:swe_x_preferred":[
        "Dato"
    ],
    "wof:name":"Dato",
    "wof:placetype":"locality"
},
  "geometry": {"coordinates":[123.1236,10.54796],"type":"Point"}
}