{
  "type": "Feature",
  "properties": {
    "gn:admin1_code":"41",
    "gn:admin2_code":"38",
    "gn:admin3_code":"174004000.0",
    "gn:asciiname":"Anapog-Sibucao",
    "gn:country_code":"PH",
    "gn:dem":26,
    "gn:feature_class":"P",
    "gn:feature_code":"PPL",
    "gn:name":"Anapog-Sibucao",
    "gn:population":0,
    "gn:timezone":"Asia/Manila",
    "iso:country":"PH",
    "name:fil_x_preferred":[
        "Anapog-Sibucao"
    ],
    "wof:name":"Anapog-Sibucao",
    "wof:placetype":"locality"
},
  "geometry": {"coordinates":[121.86667,13.48333],"type":"Point"}
}