{
  "type": "Feature",
  "properties": {
    "gn:country":"PH",
    "gn:fcode":"PPL",
    "gn:pop":2182,
    "iso:country":"PH",
    "name:bel_x_preferred":[
        "\u0421\u0430\u043b\u044c\u0447\u044d\u0434\u0430"
    ],
    "name:cat_x_preferred":[
        "Salcedo"
    ],
    "name:ceb_x_preferred":[
        "Salcedo"
    ],
    "name:deu_x_preferred":[
        "Salcedo"
    ],
    "name:eus_x_preferred":[
        "Salcedo"
    ],
    "name:fil_x_preferred":[
        "Salcedo"
    ],
    "name:fra_x_preferred":[
        "Salcedo"
    ],
    "name:glg_x_preferred":[
        "Salcedo"
    ],
    "name:ilo_x_preferred":[
        "Salcedo"
    ],
    "name:ita_x_preferred":[
        "Salcedo"
    ],
    "name:nld_x_preferred":[
        "Salcedo"
    ],
    "name:pms_x_preferred":[
        "Salcedo"
    ],
    "name:pol_x_preferred":[
        "Salcedo"
    ],
    "name:por_x_preferred":[
        "Salcedo"
    ],
    "name:rus_x_preferred":[
        "\u0421\u0430\u043b\u044c\u0441\u0435\u0434\u043e"
    ],
    "name:spa_x_preferred":[
        "Salcedo"
    ],
    "name:swe_x_preferred":[
        "Salcedo"
    ],
    "name:war_x_preferred":[
        "Salcedo"
    ],
    "qs:name":"Salcedo",
    "qs:photos_9r":0,
    "qs:photos_sr":0,
    "qs:pop_sr":"4",
    "wd:wordcount":214,
    "wof:name":"Salcedo",
    "wof:placetype":"locality",
    "wof:population":2182
},
  "geometry": {"coordinates":[120.59999999999999,15.85722],"type":"Point"}
}