{
  "type": "Feature",
  "properties": {
    "gn:admin1_code":"15",
    "gn:admin2_code":"32",
    "gn:admin3_code":"143213000.0",
    "gn:asciiname":"Malalao",
    "gn:country_code":"PH",
    "gn:dem":123,
    "gn:feature_class":"P",
    "gn:feature_code":"PPL",
    "gn:name":"Malalao",
    "gn:population":0,
    "gn:timezone":"Asia/Manila",
    "iso:country":"PH",
    "wof:name":"Malalao",
    "wof:placetype":"locality"
},
  "geometry": {"coordinates":[121.54546000000001,17.32656],"type":"Point"}
}