{
  "type": "Feature",
  "properties": {
    "gn:admin1_code":"09",
    "gn:admin2_code":"66",
    "gn:admin3_code":"97322000.0",
    "gn:asciiname":"Sibatang Lower",
    "gn:country_code":"PH",
    "gn:dem":359,
    "gn:feature_class":"P",
    "gn:feature_code":"PPL",
    "gn:name":"Sibatang Lower",
    "gn:population":0,
    "gn:timezone":"Asia/Manila",
    "iso:country":"PH",
    "name:eng_x_preferred":[
        "Sibatang Lower"
    ],
    "name:und_x_variant":[
        "Sipatang Lower"
    ],
    "wof:name":"Sibatang Lower",
    "wof:placetype":"locality"
},
  "geometry": {"coordinates":[123.3287,7.8406],"type":"Point"}
}