{
  "type": "Feature",
  "properties": {
    "gn:admin1_code":"05",
    "gn:admin2_code":"15",
    "gn:admin3_code":"51601000.0",
    "gn:asciiname":"Manpili",
    "gn:country_code":"PH",
    "gn:dem":1,
    "gn:feature_class":"P",
    "gn:feature_code":"PPL",
    "gn:name":"Manpili",
    "gn:population":0,
    "gn:timezone":"Asia/Manila",
    "iso:country":"PH",
    "name:fil_x_preferred":[
        "Manpili"
    ],
    "wof:name":"Manpili",
    "wof:placetype":"locality"
},
  "geometry": {"coordinates":[122.98333,14.08333],"type":"Point"}
}