{
  "type": "Feature",
  "properties": {
    "gn:admin1_code":"40",
    "gn:admin2_code":"33",
    "gn:admin3_code":"43411000.0",
    "gn:asciiname":"Tadlak",
    "gn:country_code":"PH",
    "gn:dem":12,
    "gn:feature_class":"P",
    "gn:feature_code":"PPL",
    "gn:name":"Tadlak",
    "gn:population":0,
    "gn:timezone":"Asia/Manila",
    "iso:country":"PH",
    "name:fil_x_preferred":[
        "Tarlac"
    ],
    "name:und_x_variant":[
        "Tarlac",
        "Tadlok",
        "Tadloc",
        "Tadlak"
    ],
    "wof:name":"Tadlak",
    "wof:placetype":"locality"
},
  "geometry": {"coordinates":[121.20576,14.17935],"type":"Point"}
}