{
  "type": "Feature",
  "properties": {
    "gn:admin1_code":"03",
    "gn:admin2_code":"G8",
    "gn:admin3_code":"37705000.0",
    "gn:asciiname":"Davildavilan",
    "gn:country_code":"PH",
    "gn:dem":46,
    "gn:feature_class":"P",
    "gn:feature_code":"PPL",
    "gn:name":"Davildavilan",
    "gn:population":0,
    "gn:timezone":"Asia/Manila",
    "iso:country":"PH",
    "name:fil_x_preferred":[
        "Davildavilan"
    ],
    "wof:name":"Davildavilan",
    "wof:placetype":"locality"
},
  "geometry": {"coordinates":[121.39149999999999,15.3921],"type":"Point"}
}