{
  "type": "Feature",
  "properties": {
    "gn:admin1_code":"15",
    "gn:admin2_code":"01",
    "gn:admin3_code":"140114000.0",
    "gn:asciiname":"Omli",
    "gn:country_code":"PH",
    "gn:dem":176,
    "gn:feature_class":"P",
    "gn:feature_code":"PPL",
    "gn:name":"Omli",
    "gn:population":0,
    "gn:timezone":"Asia/Manila",
    "iso:country":"PH",
    "name:fil_x_preferred":[
        "Omli"
    ],
    "wof:name":"Omli",
    "wof:placetype":"locality"
},
  "geometry": {"coordinates":[120.7195,17.3701],"type":"Point"}
}