{
  "type": "Feature",
  "properties": {
    "gn:admin1_code":"07",
    "gn:admin2_code":"11",
    "gn:admin3_code":"71215000.0",
    "gn:asciiname":"Canlauan",
    "gn:country_code":"PH",
    "gn:dem":104,
    "gn:feature_class":"P",
    "gn:feature_code":"PPL",
    "gn:name":"Canlauan",
    "gn:population":0,
    "gn:timezone":"Asia/Manila",
    "iso:country":"PH",
    "name:fil_x_preferred":[
        "Canlauan"
    ],
    "wof:name":"Canlauan",
    "wof:placetype":"locality"
},
  "geometry": {"coordinates":[123.92440000000001,9.6712],"type":"Point"}
}