{
  "type": "Feature",
  "properties": {
    "gn:admin1_code":"08",
    "gn:admin2_code":"37",
    "gn:admin3_code":"83740000.0",
    "gn:asciiname":"Tinobdan",
    "gn:country_code":"PH",
    "gn:dem":51,
    "gn:feature_class":"P",
    "gn:feature_code":"PPL",
    "gn:name":"Tinobdan",
    "gn:population":0,
    "gn:timezone":"Asia/Manila",
    "iso:country":"PH",
    "name:fil_x_preferred":[
        "Tinobdan"
    ],
    "wof:name":"Tinobdan",
    "wof:placetype":"locality"
},
  "geometry": {"coordinates":[124.42449999999999,11.0735],"type":"Point"}
}