{
  "type": "Feature",
  "properties": {
    "gn:admin1_code":"06",
    "gn:admin2_code":"H3",
    "gn:admin3_code":"64516000.0",
    "gn:asciiname":"Hacienda Maslog",
    "gn:country_code":"PH",
    "gn:dem":462,
    "gn:feature_class":"P",
    "gn:feature_code":"PPL",
    "gn:name":"Hacienda Maslog",
    "gn:population":0,
    "gn:timezone":"Asia/Manila",
    "iso:country":"PH",
    "name:fil_x_preferred":[
        "Hacienda Maslog"
    ],
    "wof:name":"Hacienda Maslog",
    "wof:placetype":"locality"
},
  "geometry": {"coordinates":[123.0453,10.4093],"type":"Point"}
}