{
  "type": "Feature",
  "properties": {
    "gn:admin1_code":"06",
    "gn:admin2_code":"30",
    "gn:asciiname":"Bolbugan",
    "gn:country_code":"PH",
    "gn:dem":-9999,
    "gn:feature_class":"P",
    "gn:feature_code":"PPL",
    "gn:name":"Bolbugan",
    "gn:population":0,
    "gn:timezone":"Asia/Manila",
    "iso:country":"PH",
    "name:fil_x_preferred":[
        "Bolbugan"
    ],
    "wof:name":"Bolbugan",
    "wof:placetype":"locality"
},
  "geometry": {"coordinates":[122.13333,10.58333],"type":"Point"}
}