{
  "type": "Feature",
  "properties": {
    "gn:admin1_code":"08",
    "gn:admin2_code":"37",
    "gn:admin3_code":"83736000.0",
    "gn:asciiname":"Quinayaban",
    "gn:country_code":"PH",
    "gn:dem":40,
    "gn:feature_class":"P",
    "gn:feature_code":"PPL",
    "gn:name":"Quinayaban",
    "gn:population":0,
    "gn:timezone":"Asia/Manila",
    "iso:country":"PH",
    "name:fil_x_preferred":[
        "Quinayaban"
    ],
    "wof:name":"Quinayaban",
    "wof:placetype":"locality"
},
  "geometry": {"coordinates":[124.54730000000001,10.9579],"type":"Point"}
}