{
  "type": "Feature",
  "properties": {
    "gn:country":"PH",
    "gn:fcode":"ADM3",
    "gn:pop":30088,
    "iso:country":"PH",
    "name:fil_x_preferred":[
        "Pagalungan"
    ],
    "qs:name":"Pagalungan",
    "qs:photos_9r":0,
    "qs:photos_sr":0,
    "qs:pop_sr":"7",
    "wof:name":"Pagalungan",
    "wof:placetype":"localadmin",
    "wof:population":30088
},
  "geometry": {"coordinates":[124.75,7.05],"type":"Point"}
}