{
  "type": "Feature",
  "properties": {
    "gn:country":"PH",
    "gn:fcode":"ADM3",
    "gn:population":30088,
    "iso:country":"PH",
    "name:bcl_x_preferred":[
        "Pagalungan"
    ],
    "name:ceb_x_preferred":[
        "Pagalungan"
    ],
    "name:deu_x_preferred":[
        "Pagalungan"
    ],
    "name:fil_x_preferred":[
        "Pagalungan"
    ],
    "name:fra_x_preferred":[
        "Pagalungan"
    ],
    "name:ilo_x_preferred":[
        "Pagalungan"
    ],
    "name:ind_x_preferred":[
        "Pagalungan"
    ],
    "name:ita_x_preferred":[
        "Pagalungan"
    ],
    "name:nld_x_preferred":[
        "Pagalungan"
    ],
    "name:pag_x_preferred":[
        "Pagalungan"
    ],
    "name:pam_x_preferred":[
        "Pagalungan"
    ],
    "name:spa_x_preferred":[
        "Pagalung\u00e1n"
    ],
    "name:swe_x_preferred":[
        "Pagalungan"
    ],
    "name:tgl_x_preferred":[
        "Pagalungan"
    ],
    "name:urd_x_preferred":[
        "\u067e\u0627\u06af\u0627\u0644\u0648\u0646\u06af\u0627\u0646"
    ],
    "name:vie_x_preferred":[
        "Pagalungan"
    ],
    "name:war_x_preferred":[
        "Pagalungan"
    ],
    "qs:name":"Pagalungan",
    "qs:photos_9r":0,
    "qs:photos_sr":0,
    "qs:pop_sr":"7",
    "wof:name":"Pagalungan",
    "wof:placetype":"localadmin",
    "wof:population":30088
},
  "geometry": {"coordinates":[124.75,7.05],"type":"Point"}
}