{
  "type": "Feature",
  "properties": {
    "gn:admin1_code":"11",
    "gn:admin2_code":"I6",
    "gn:admin3_code":"118211000.0",
    "gn:asciiname":"Magdagasang",
    "gn:country_code":"PH",
    "gn:dem":1294,
    "gn:feature_class":"P",
    "gn:feature_code":"PPL",
    "gn:name":"Magdagasang",
    "gn:population":0,
    "gn:timezone":"Asia/Manila",
    "iso:country":"PH",
    "name:fil_x_preferred":[
        "Magdagasang"
    ],
    "wof:name":"Magdagasang",
    "wof:placetype":"locality"
},
  "geometry": {"coordinates":[126.26667,7.26667],"type":"Point"}
}