{
  "type": "Feature",
  "properties": {
    "gn:admin1_code":"01",
    "gn:admin2_code":"28",
    "gn:admin3_code":"12804000.0",
    "gn:asciiname":"Malasin",
    "gn:country_code":"PH",
    "gn:dem":41,
    "gn:feature_class":"P",
    "gn:feature_code":"PPL",
    "gn:name":"Malasin",
    "gn:population":0,
    "gn:timezone":"Asia/Manila",
    "iso:country":"PH",
    "name:eng_x_preferred":[
        "Malasin"
    ],
    "wof:name":"Malasin",
    "wof:placetype":"locality"
},
  "geometry": {"coordinates":[120.79649999999999,18.5254],"type":"Point"}
}