{
  "type": "Feature",
  "properties": {
    "gn:country":"PH",
    "gn:fcode":"PPLA3",
    "gn:population":36520,
    "iso:country":"PH",
    "name:bcl_x_preferred":[
        "Pantukan"
    ],
    "name:ceb_x_preferred":[
        "Pantukan"
    ],
    "name:deu_x_preferred":[
        "Pantukan"
    ],
    "name:eng_x_preferred":[
        "Pantukan"
    ],
    "name:fas_x_preferred":[
        "\u067e\u0646\u062a\u0648\u06a9\u0646\u060c \u06a9\u0627\u0645\u067e\u0648\u0633\u062a\u0644\u0627 \u062f\u0631\u0647"
    ],
    "name:fas_x_variant":[
        "\u067e\u0646\u062a\u0648\u06a9\u0646"
    ],
    "name:fra_x_preferred":[
        "Pantukan"
    ],
    "name:ilo_x_preferred":[
        "Pantukan"
    ],
    "name:ind_x_preferred":[
        "Pantukan"
    ],
    "name:ita_x_preferred":[
        "Pantukan"
    ],
    "name:nld_x_preferred":[
        "Pantukan"
    ],
    "name:pag_x_preferred":[
        "Pantukan"
    ],
    "name:pam_x_preferred":[
        "Pantukan"
    ],
    "name:spa_x_preferred":[
        "Pantukan"
    ],
    "name:swe_x_preferred":[
        "Pantukan"
    ],
    "name:tgl_x_preferred":[
        "Pantukan"
    ],
    "name:vie_x_preferred":[
        "Pantukan"
    ],
    "name:war_x_preferred":[
        "Pantukan"
    ],
    "qs:name":"Pantukan",
    "qs:photos_9r":0,
    "qs:photos_sr":0,
    "qs:pop_sr":"7",
    "wof:name":"Pantukan",
    "wof:placetype":"locality",
    "wof:population":36520
},
  "geometry": {"coordinates":[125.88972,7.13528],"type":"Point"}
}