{
  "type": "Feature",
  "properties": {
    "gn:admin1_code":"08",
    "gn:admin2_code":"67",
    "gn:admin3_code":"84823000.0",
    "gn:asciiname":"Taboc",
    "gn:country_code":"PH",
    "gn:dem":74,
    "gn:feature_class":"P",
    "gn:feature_code":"PPL",
    "gn:name":"Taboc",
    "gn:population":0,
    "gn:timezone":"Asia/Manila",
    "iso:country":"PH",
    "name:fil_x_preferred":[
        "Taboc"
    ],
    "wof:name":"Taboc",
    "wof:placetype":"locality"
},
  "geometry": {"coordinates":[124.3258,12.4382],"type":"Point"}
}