{
  "type": "Feature",
  "properties": {
    "gn:admin1_code":"15",
    "gn:admin2_code":"10",
    "gn:admin3_code":"141101000.0",
    "gn:asciiname":"Adoyunan",
    "gn:country_code":"PH",
    "gn:dem":1509,
    "gn:feature_class":"P",
    "gn:feature_code":"PPL",
    "gn:name":"Adoyunan",
    "gn:population":0,
    "gn:timezone":"Asia/Manila",
    "iso:country":"PH",
    "name:fil_x_preferred":[
        "Adoyunan"
    ],
    "wof:name":"Adoyunan",
    "wof:placetype":"locality"
},
  "geometry": {"coordinates":[120.73090000000001,16.6005],"type":"Point"}
}