{
  "type": "Feature",
  "properties": {
    "gn:country":"PH",
    "gn:fcode":"PPL",
    "gn:population":2831,
    "iso:country":"PH",
    "name:fil_x_preferred":[
        "Inabaan Sur"
    ],
    "name:fil_x_variant":[
        "Inabaan"
    ],
    "qs:name":"Inabaan Sur",
    "qs:photos_9r":0,
    "qs:photos_sr":0,
    "qs:pop_sr":"4",
    "wof:name":"Inabaan Sur",
    "wof:placetype":"locality",
    "wof:population":2831
},
  "geometry": {"coordinates":[120.4781,16.263],"type":"Point"}
}