{
  "type": "Feature",
  "properties": {
    "gn:admin1_code":"01",
    "gn:admin2_code":"51",
    "gn:admin3_code":"15533000.0",
    "gn:asciiname":"Butao",
    "gn:country_code":"PH",
    "gn:dem":3,
    "gn:feature_class":"P",
    "gn:feature_code":"PPL",
    "gn:name":"Butao",
    "gn:population":0,
    "gn:timezone":"Asia/Manila",
    "iso:country":"PH",
    "name:fil_x_preferred":[
        "Butao"
    ],
    "name:fil_x_variant":[
        "Buetao"
    ],
    "wof:name":"Butao",
    "wof:placetype":"locality"
},
  "geometry": {"coordinates":[120.40903,16.11778],"type":"Point"}
}