{
  "type": "Feature",
  "properties": {
    "gn:admin1_code":"03",
    "gn:admin2_code":"13",
    "gn:asciiname":"Gasak",
    "gn:cc2":"PH",
    "gn:country_code":"PH",
    "gn:dem":5,
    "gn:feature_class":"P",
    "gn:feature_code":"PPL",
    "gn:name":"Gasak",
    "gn:population":0,
    "gn:timezone":"Asia/Manila",
    "iso:country":"PH",
    "name:und_x_variant":[
        "Gasac",
        "Gasak"
    ],
    "wof:name":"Gasak",
    "wof:placetype":"locality"
},
  "geometry": {"coordinates":[120.93472,14.67972],"type":"Point"}
}