{
  "type": "Feature",
  "properties": {
    "gn:admin1_code":"15",
    "gn:admin2_code":"44",
    "gn:admin3_code":"144405000.0",
    "gn:asciiname":"Iyahan",
    "gn:country_code":"PH",
    "gn:dem":786,
    "gn:feature_class":"P",
    "gn:feature_code":"PPL",
    "gn:name":"Iyahan",
    "gn:population":0,
    "gn:timezone":"Asia/Manila",
    "iso:country":"PH",
    "name:fil_x_preferred":[
        "Iyahan"
    ],
    "wof:name":"Iyahan",
    "wof:placetype":"locality"
},
  "geometry": {"coordinates":[121.24063999999998,17.08635],"type":"Point"}
}