{
  "type": "Feature",
  "properties": {
    "gn:admin1_code":"06",
    "gn:admin2_code":"06",
    "gn:admin3_code":"60617000.0",
    "gn:asciiname":"Taratara",
    "gn:country_code":"PH",
    "gn:dem":121,
    "gn:feature_class":"P",
    "gn:feature_code":"PPL",
    "gn:name":"Taratara",
    "gn:population":0,
    "gn:timezone":"Asia/Manila",
    "iso:country":"PH",
    "name:fil_x_preferred":[
        "Taratara"
    ],
    "wof:name":"Taratara",
    "wof:placetype":"locality"
},
  "geometry": {"coordinates":[122.06901000000001,11.34361],"type":"Point"}
}