{
  "type": "Feature",
  "properties": {
    "gn:country":"PH",
    "gn:fcode":"PPL",
    "gn:pop":5686,
    "iso:country":"PH",
    "name:fil_x_preferred":[
        "San Mariano"
    ],
    "name:unk_x_variant":[
        "Mariano"
    ],
    "qs:name":"San Mariano",
    "qs:photos_9r":0,
    "qs:photos_sr":0,
    "qs:pop_sr":"5",
    "wof:name":"San Mariano",
    "wof:placetype":"locality",
    "wof:population":5686
},
  "geometry": {"coordinates":[120.87609,15.32083],"type":"Point"}
}