{
  "type": "Feature",
  "properties": {
    "gn:admin1_code":"06",
    "gn:admin2_code":"30",
    "gn:admin3_code":"63030000.0",
    "gn:asciiname":"Banga",
    "gn:country_code":"PH",
    "gn:dem":28,
    "gn:feature_class":"P",
    "gn:feature_code":"PPL",
    "gn:name":"Banga",
    "gn:population":0,
    "gn:timezone":"Asia/Manila",
    "iso:country":"PH",
    "name:ceb_x_preferred":[
        "Banga"
    ],
    "name:deu_x_preferred":[
        "Banga"
    ],
    "name:fil_x_preferred":[
        "Banga"
    ],
    "name:fra_x_preferred":[
        "Banga"
    ],
    "name:hin_x_preferred":[
        "\u092c\u0902\u0917\u093e"
    ],
    "name:ita_x_preferred":[
        "Banga"
    ],
    "name:lav_x_preferred":[
        "Banga"
    ],
    "name:lit_x_preferred":[
        "Banga"
    ],
    "name:nld_x_preferred":[
        "Banga"
    ],
    "name:por_x_preferred":[
        "Banga"
    ],
    "name:spa_x_preferred":[
        "Banga"
    ],
    "name:swe_x_preferred":[
        "Banga"
    ],
    "name:war_x_preferred":[
        "Banga"
    ],
    "wof:name":"Banga",
    "wof:placetype":"locality"
},
  "geometry": {"coordinates":[122.2496,10.67056],"type":"Point"}
}