{
  "type": "Feature",
  "properties": {
    "gn:country":"PH",
    "gn:fcode":"PPL",
    "gn:population":2424,
    "iso:country":"PH",
    "name:fil_x_preferred":[
        "Tucdao"
    ],
    "name:und_x_variant":[
        "Tucdaw"
    ],
    "qs:name":"Tucdao",
    "qs:photos_9r":0,
    "qs:photos_sr":0,
    "qs:pop_sr":"4",
    "wof:name":"Tucdao",
    "wof:placetype":"locality",
    "wof:population":2424
},
  "geometry": {"coordinates":[124.47190000000001,11.7011],"type":"Point"}
}