{
  "type": "Feature",
  "properties": {
    "gn:admin1_code":"05",
    "gn:admin2_code":"58",
    "gn:admin3_code":"56206000.0",
    "gn:asciiname":"Burabod",
    "gn:country_code":"PH",
    "gn:dem":41,
    "gn:feature_class":"P",
    "gn:feature_code":"PPL",
    "gn:name":"Burabod",
    "gn:population":0,
    "gn:timezone":"Asia/Manila",
    "iso:country":"PH",
    "name:fil_x_preferred":[
        "Burabod"
    ],
    "wof:name":"Burabod",
    "wof:placetype":"locality"
},
  "geometry": {"coordinates":[123.78333000000001,12.95],"type":"Point"}
}