{
  "type": "Feature",
  "properties": {
    "gn:admin1_code":"03",
    "gn:admin2_code":"G8",
    "gn:admin3_code":"37702000.0",
    "gn:asciiname":"Parang",
    "gn:country_code":"PH",
    "gn:dem":238,
    "gn:feature_class":"P",
    "gn:feature_code":"PPL",
    "gn:name":"Parang",
    "gn:population":0,
    "gn:timezone":"Asia/Manila",
    "iso:country":"PH",
    "name:deu_x_preferred":[
        "Parang"
    ],
    "name:fil_x_preferred":[
        "Parang"
    ],
    "name:nno_x_preferred":[
        "Parang"
    ],
    "name:por_x_preferred":[
        "Parang"
    ],
    "wof:name":"Parang",
    "wof:placetype":"locality"
},
  "geometry": {"coordinates":[122.21666999999999,16.28333],"type":"Point"}
}