{
  "type": "Feature",
  "properties": {
    "gn:admin1_code":"05",
    "gn:admin2_code":"15",
    "gn:admin3_code":"51602000.0",
    "gn:asciiname":"Del Pilar",
    "gn:country_code":"PH",
    "gn:dem":1,
    "gn:feature_class":"P",
    "gn:feature_code":"PPL",
    "gn:name":"Del Pilar",
    "gn:population":0,
    "gn:timezone":"Asia/Manila",
    "iso:country":"PH",
    "name:fil_x_preferred":[
        "Del Pilar"
    ],
    "wof:name":"Del Pilar",
    "wof:placetype":"locality"
},
  "geometry": {"coordinates":[122.38278,14.28072],"type":"Point"}
}