{
  "type": "Feature",
  "properties": {
    "gn:admin1_code":"05",
    "gn:admin2_code":"39",
    "gn:admin3_code":"54105000.0",
    "gn:asciiname":"San Pedro Gustusan",
    "gn:country_code":"PH",
    "gn:dem":92,
    "gn:feature_class":"P",
    "gn:feature_code":"PPL",
    "gn:name":"San Pedro Gustusan",
    "gn:population":0,
    "gn:timezone":"Asia/Manila",
    "iso:country":"PH",
    "name:fil_x_preferred":[
        "San Pedro Gustusan"
    ],
    "wof:name":"San Pedro Gustusan",
    "wof:placetype":"locality"
},
  "geometry": {"coordinates":[123.9849,12.0233],"type":"Point"}
}