{
  "type": "Feature",
  "properties": {
    "gn:admin1_code":"01",
    "gn:admin2_code":"29",
    "gn:admin3_code":"12914000.0",
    "gn:asciiname":"Turod",
    "gn:country_code":"PH",
    "gn:dem":6,
    "gn:feature_class":"P",
    "gn:feature_code":"PPL",
    "gn:name":"Turod",
    "gn:population":0,
    "gn:timezone":"Asia/Manila",
    "iso:country":"PH",
    "name:fil_x_preferred":[
        "Turod"
    ],
    "wof:name":"Turod",
    "wof:placetype":"locality"
},
  "geometry": {"coordinates":[120.46129999999999,17.4191],"type":"Point"}
}