{
  "type": "Feature",
  "properties": {
    "gn:country":"PH",
    "gn:fcode":"ADM3",
    "gn:population":36433,
    "iso:country":"PH",
    "name:bcl_x_preferred":[
        "Buug"
    ],
    "name:ceb_x_preferred":[
        "Buug"
    ],
    "name:deu_x_preferred":[
        "Buug"
    ],
    "name:eng_x_preferred":[
        "Municipality of Buug"
    ],
    "name:eng_x_variant":[
        "Buug"
    ],
    "name:fra_x_preferred":[
        "Buug"
    ],
    "name:ilo_x_preferred":[
        "Buug"
    ],
    "name:ita_x_preferred":[
        "Buug"
    ],
    "name:nld_x_preferred":[
        "Buug"
    ],
    "name:pag_x_preferred":[
        "Buug"
    ],
    "name:pam_x_preferred":[
        "Buug"
    ],
    "name:swe_x_preferred":[
        "Buug"
    ],
    "name:tgl_x_preferred":[
        "Buug"
    ],
    "name:vie_x_preferred":[
        "Buug"
    ],
    "name:war_x_preferred":[
        "Buug"
    ],
    "qs:name":"Municipality of Buug",
    "qs:photos_9r":0,
    "qs:photos_sr":0,
    "qs:pop_sr":"7",
    "wd:wordcount":815,
    "wof:name":"Municipality of Buug",
    "wof:placetype":"localadmin",
    "wof:population":36433
},
  "geometry": {"coordinates":[123.05,7.7541],"type":"Point"}
}