{
  "type": "Feature",
  "properties": {
    "gn:country":"PH",
    "gn:fcode":"ADM3",
    "gn:pop":36433,
    "iso:country":"PH",
    "name:eng_x_preferred":[
        "Municipality of Buug"
    ],
    "name:unk_x_variant":[
        "Buug"
    ],
    "qs:name":"Municipality of Buug",
    "qs:photos_9r":0,
    "qs:photos_sr":0,
    "qs:pop_sr":"7",
    "wd:wordcount":815,
    "wof:name":"Municipality of Buug",
    "wof:placetype":"localadmin",
    "wof:population":36433
},
  "geometry": {"coordinates":[123.05,7.7541],"type":"Point"}
}