{
  "type": "Feature",
  "properties": {
    "gn:admin1_code":"07",
    "gn:admin2_code":"11",
    "gn:admin3_code":"71208000.0",
    "gn:asciiname":"Tooc",
    "gn:cc2":"PH",
    "gn:country_code":"PH",
    "gn:dem":462,
    "gn:feature_class":"P",
    "gn:feature_code":"PPL",
    "gn:name":"Tooc",
    "gn:population":0,
    "gn:timezone":"Asia/Manila",
    "iso:country":"PH",
    "name:und_x_variant":[
        "Toog",
        "Tooc"
    ],
    "wof:name":"Tooc",
    "wof:placetype":"locality"
},
  "geometry": {"coordinates":[124.12778,9.68944],"type":"Point"}
}