{
  "type": "Feature",
  "properties": {
    "gn:country":"PH",
    "gn:fcode":"PPL",
    "gn:population":3557,
    "iso:country":"PH",
    "name:fil_x_preferred":[
        "Yeban"
    ],
    "name:und_x_variant":[
        "Yeban Norte"
    ],
    "qs:name":"Yeban",
    "qs:photos_9r":0,
    "qs:photos_sr":0,
    "qs:pop_sr":"4",
    "wof:name":"Yeban",
    "wof:placetype":"locality",
    "wof:population":3557
},
  "geometry": {"coordinates":[121.94194,17.02195],"type":"Point"}
}