{
  "type": "Feature",
  "properties": {
    "gn:admin1_code":"07",
    "gn:admin2_code":"21",
    "gn:admin3_code":"72216000.0",
    "gn:asciiname":"Sagpon",
    "gn:country_code":"PH",
    "gn:dem":96,
    "gn:feature_class":"P",
    "gn:feature_code":"PPL",
    "gn:name":"Sagpon",
    "gn:population":0,
    "gn:timezone":"Asia/Manila",
    "iso:country":"PH",
    "name:fil_x_preferred":[
        "Sagpon"
    ],
    "wof:name":"Sagpon",
    "wof:placetype":"locality"
},
  "geometry": {"coordinates":[124.01667,10.63333],"type":"Point"}
}