{
  "type": "Feature",
  "properties": {
    "gn:country":"PH",
    "gn:fcode":"PPL",
    "gn:population":2569,
    "iso:country":"PH",
    "name:fil_x_preferred":[
        "Magsaysay"
    ],
    "qs:name":"Magsaysay",
    "qs:photos_9r":0,
    "qs:photos_sr":0,
    "qs:pop_sr":"4",
    "wof:name":"Magsaysay",
    "wof:placetype":"locality",
    "wof:population":2569
},
  "geometry": {"coordinates":[121.0341,14.3388],"type":"Point"}
}