{
  "type": "Feature",
  "properties": {
    "gn:admin1_code":"02",
    "gn:admin2_code":"14",
    "gn:admin3_code":"21503000.0",
    "gn:asciiname":"Maluyo",
    "gn:country_code":"PH",
    "gn:dem":12,
    "gn:feature_class":"P",
    "gn:feature_code":"PPL",
    "gn:name":"Maluyo",
    "gn:population":0,
    "gn:timezone":"Asia/Manila",
    "iso:country":"PH",
    "name:fil_x_preferred":[
        "Maluyo"
    ],
    "wof:name":"Maluyo",
    "wof:placetype":"locality"
},
  "geometry": {"coordinates":[121.57406,18.18286],"type":"Point"}
}