{
  "type": "Feature",
  "properties": {
    "gn:admin1_code":"08",
    "gn:admin2_code":"59",
    "gn:admin3_code":"86403000.0",
    "gn:asciiname":"Calagitan",
    "gn:country_code":"PH",
    "gn:dem":13,
    "gn:feature_class":"P",
    "gn:feature_code":"PPL",
    "gn:name":"Calagitan",
    "gn:population":0,
    "gn:timezone":"Asia/Manila",
    "iso:country":"PH",
    "name:fil_x_preferred":[
        "Calagitan"
    ],
    "wof:name":"Calagitan",
    "wof:placetype":"locality"
},
  "geometry": {"coordinates":[125.17740000000001,10.4339],"type":"Point"}
}