{
  "type": "Feature",
  "properties": {
    "gn:admin1_code":"06",
    "gn:admin2_code":"30",
    "gn:admin3_code":"63013000.0",
    "gn:asciiname":"Dap",
    "gn:country_code":"PH",
    "gn:dem":159,
    "gn:feature_class":"P",
    "gn:feature_code":"PPL",
    "gn:name":"Dap",
    "gn:population":0,
    "gn:timezone":"Asia/Manila",
    "iso:country":"PH",
    "name:fil_x_preferred":[
        "Dap"
    ],
    "wof:name":"Dap",
    "wof:placetype":"locality"
},
  "geometry": {"coordinates":[122.44171,11.15102],"type":"Point"}
}