{
  "type": "Feature",
  "properties": {
    "gn:admin1_code":"07",
    "gn:admin2_code":"21",
    "gn:admin3_code":"72222000.0",
    "gn:asciiname":"Balisong",
    "gn:country_code":"PH",
    "gn:dem":66,
    "gn:feature_class":"P",
    "gn:feature_code":"PPL",
    "gn:name":"Balisong",
    "gn:population":0,
    "gn:timezone":"Asia/Manila",
    "iso:country":"PH",
    "wof:name":"Balisong",
    "wof:placetype":"locality"
},
  "geometry": {"coordinates":[123.54353999999999,9.82527],"type":"Point"}
}