{
  "type": "Feature",
  "properties": {
    "gn:admin1_code":"08",
    "gn:admin2_code":"37",
    "gn:admin3_code":"83708000.0",
    "gn:asciiname":"Caniagnos",
    "gn:country_code":"PH",
    "gn:dem":30,
    "gn:feature_class":"P",
    "gn:feature_code":"PPL",
    "gn:name":"Caniagnos",
    "gn:population":0,
    "gn:timezone":"Asia/Manila",
    "iso:country":"PH",
    "name:fil_x_preferred":[
        "Caniagnos"
    ],
    "name:und_x_variant":[
        "Cantagnos"
    ],
    "wof:name":"Caniagnos",
    "wof:placetype":"locality"
},
  "geometry": {"coordinates":[124.8514,10.6709],"type":"Point"}
}