{
  "type": "Feature",
  "properties": {
    "gn:country":"PH",
    "gn:fcode":"PPLA3",
    "gn:population":4487,
    "iso:country":"PH",
    "name:bcl_x_preferred":[
        "Angadanan"
    ],
    "name:cat_x_preferred":[
        "Angadanan"
    ],
    "name:ceb_x_preferred":[
        "Angadanan"
    ],
    "name:deu_x_preferred":[
        "Angadanan"
    ],
    "name:eng_x_preferred":[
        "Angadanan"
    ],
    "name:fil_x_preferred":[
        "Angadanan"
    ],
    "name:fil_x_variant":[
        "Angadauan",
        "Angadangan"
    ],
    "name:fra_x_preferred":[
        "Angadanan"
    ],
    "name:ilo_x_preferred":[
        "Angadanan"
    ],
    "name:ind_x_preferred":[
        "Angadanan"
    ],
    "name:ita_x_preferred":[
        "Angadanan"
    ],
    "name:nld_x_preferred":[
        "Angadanan"
    ],
    "name:oci_x_preferred":[
        "Angadanan"
    ],
    "name:pag_x_preferred":[
        "Angadanan"
    ],
    "name:pam_x_preferred":[
        "Angadanan"
    ],
    "name:spa_x_preferred":[
        "Angadanan"
    ],
    "name:swe_x_preferred":[
        "Angadanan"
    ],
    "name:tgl_x_preferred":[
        "Angadanan"
    ],
    "name:vie_x_preferred":[
        "Angadanan"
    ],
    "name:war_x_preferred":[
        "Angadanan"
    ],
    "qs:name":"Angadanan",
    "qs:photos_9r":0,
    "qs:photos_sr":0,
    "qs:pop_sr":"4",
    "wof:name":"Angadanan",
    "wof:placetype":"locality",
    "wof:population":4487
},
  "geometry": {"coordinates":[121.74834,16.75526],"type":"Point"}
}