{
  "type": "Feature",
  "properties": {
    "gn:country":"PH",
    "gn:fcode":"ADM3",
    "gn:population":16389,
    "iso:country":"PH",
    "name:und_x_variant":[
        "Tomas Cabili"
    ],
    "qs:name":"Linamon",
    "qs:photos_9r":0,
    "qs:photos_sr":0,
    "qs:pop_sr":"6",
    "wof:name":"Linamon",
    "wof:placetype":"localadmin",
    "wof:population":16389
},
  "geometry": {"coordinates":[124.16667,8.18333],"type":"Point"}
}