{
  "type": "Feature",
  "properties": {
    "gn:admin1_code":"12",
    "gn:admin2_code":"M9",
    "gn:admin3_code":"128007000.0",
    "gn:asciiname":"Dumlok",
    "gn:country_code":"PH",
    "gn:dem":113,
    "gn:feature_class":"P",
    "gn:feature_code":"PPL",
    "gn:name":"Dumlok",
    "gn:population":0,
    "gn:timezone":"Asia/Manila",
    "iso:country":"PH",
    "name:fil_x_preferred":[
        "Dumlok"
    ],
    "wof:name":"Dumlok",
    "wof:placetype":"locality"
},
  "geometry": {"coordinates":[125.28111,6.29639],"type":"Point"}
}