{
  "type": "Feature",
  "properties": {
    "gn:country":"PH",
    "gn:fcode":"PPL",
    "gn:population":3957,
    "iso:country":"PH",
    "name:fil_x_preferred":[
        "Malabog"
    ],
    "qs:name":"Malabog",
    "qs:photos_9r":0,
    "qs:photos_sr":0,
    "qs:pop_sr":"4",
    "wof:name":"Malabog",
    "wof:placetype":"locality",
    "wof:population":3957
},
  "geometry": {"coordinates":[123.6865,13.1738],"type":"Point"}
}