{
  "type": "Feature",
  "properties": {
    "gn:admin1_code":"07",
    "gn:admin2_code":"11",
    "gn:admin3_code":"71226000.0",
    "gn:asciiname":"Lapad",
    "gn:country_code":"PH",
    "gn:dem":114,
    "gn:feature_class":"P",
    "gn:feature_code":"PPL",
    "gn:name":"Lapad",
    "gn:population":0,
    "gn:timezone":"Asia/Manila",
    "iso:country":"PH",
    "name:fil_x_preferred":[
        "Lapad"
    ],
    "wof:name":"Lapad",
    "wof:placetype":"locality"
},
  "geometry": {"coordinates":[124.18333,10.08333],"type":"Point"}
}