{
  "type": "Feature",
  "properties": {
    "gn:admin1_code":"40",
    "gn:admin2_code":"09",
    "gn:admin3_code":"41013000.0",
    "gn:asciiname":"Capito",
    "gn:country_code":"PH",
    "gn:dem":56,
    "gn:feature_class":"P",
    "gn:feature_code":"PPL",
    "gn:name":"Capito",
    "gn:population":0,
    "gn:timezone":"Asia/Manila",
    "iso:country":"PH",
    "name:fil_x_preferred":[
        "Capito"
    ],
    "wof:name":"Capito",
    "wof:placetype":"locality"
},
  "geometry": {"coordinates":[120.66970000000001,14.0043],"type":"Point"}
}