{
  "type": "Feature",
  "properties": {
    "gn:admin1_code":"40",
    "gn:admin2_code":"09",
    "gn:admin3_code":"41013000.0",
    "gn:asciiname":"Capito",
    "gn:country_code":"PH",
    "gn:dem":56,
    "gn:feature_class":"P",
    "gn:feature_code":"PPL",
    "gn:name":"Capito",
    "gn:population":0,
    "gn:timezone":"Asia/Manila",
    "iso:country":"PH",
    "name:ara_x_preferred":[
        "\u0628\u0631\u0628\u064a\u062a"
    ],
    "name:bre_x_preferred":[
        "Capito"
    ],
    "name:cat_x_preferred":[
        "Capito"
    ],
    "name:ceb_x_preferred":[
        "Capito"
    ],
    "name:deu_x_preferred":[
        "Buntb\u00e4rtlinge"
    ],
    "name:epo_x_preferred":[
        "Kapitoj"
    ],
    "name:fil_x_preferred":[
        "Capito"
    ],
    "name:fin_x_preferred":[
        "Kruunusep\u00e4t"
    ],
    "name:fra_x_preferred":[
        "Capito"
    ],
    "name:hun_x_preferred":[
        "Capito"
    ],
    "name:nld_x_preferred":[
        "Capito"
    ],
    "name:pol_x_preferred":[
        "Capito"
    ],
    "name:por_x_preferred":[
        "Capito"
    ],
    "name:spa_x_preferred":[
        "Capito"
    ],
    "name:swe_x_preferred":[
        "Capito"
    ],
    "name:vie_x_preferred":[
        "Capito"
    ],
    "name:war_x_preferred":[
        "Capito"
    ],
    "wof:name":"Capito",
    "wof:placetype":"locality"
},
  "geometry": {"coordinates":[120.66970000000001,14.0043],"type":"Point"}
}