{
  "type": "Feature",
  "properties": {
    "gn:admin1_code":"06",
    "gn:admin2_code":"18",
    "gn:admin3_code":"61914000.0",
    "gn:asciiname":"Humagikhik",
    "gn:country_code":"PH",
    "gn:dem":33,
    "gn:feature_class":"P",
    "gn:feature_code":"PPL",
    "gn:name":"Humagikhik",
    "gn:population":0,
    "gn:timezone":"Asia/Manila",
    "iso:country":"PH",
    "name:fil_x_preferred":[
        "Jumagicjic"
    ],
    "wof:name":"Humagikhik",
    "wof:placetype":"locality"
},
  "geometry": {"coordinates":[122.7377,11.4863],"type":"Point"}
}