{
  "type": "Feature",
  "properties": {
    "gn:admin1_code":"13",
    "gn:admin2_code":"61",
    "gn:admin3_code":"166706000.0",
    "gn:asciiname":"Panatao",
    "gn:country_code":"PH",
    "gn:dem":14,
    "gn:feature_class":"P",
    "gn:feature_code":"PPL",
    "gn:name":"Panatao",
    "gn:population":0,
    "gn:timezone":"Asia/Manila",
    "iso:country":"PH",
    "name:fil_x_preferred":[
        "Panatao"
    ],
    "wof:name":"Panatao",
    "wof:placetype":"locality"
},
  "geometry": {"coordinates":[125.747,9.5628],"type":"Point"}
}