{
  "type": "Feature",
  "properties": {
    "gn:admin1_code":"05",
    "gn:admin2_code":"39",
    "gn:admin3_code":"54115000.0",
    "gn:asciiname":"Siguinon",
    "gn:country_code":"PH",
    "gn:dem":34,
    "gn:feature_class":"P",
    "gn:feature_code":"PPL",
    "gn:name":"Siguinon",
    "gn:population":0,
    "gn:timezone":"Asia/Manila",
    "iso:country":"PH",
    "name:fil_x_preferred":[
        "Siguinon"
    ],
    "wof:name":"Siguinon",
    "wof:placetype":"locality"
},
  "geometry": {"coordinates":[123.93559999999999,12.1305],"type":"Point"}
}