{
  "type": "Feature",
  "properties": {
    "gn:admin1_code":"41",
    "gn:admin2_code":"41",
    "gn:admin3_code":"175206000.0",
    "gn:asciiname":"Malubay",
    "gn:country_code":"PH",
    "gn:dem":38,
    "gn:feature_class":"P",
    "gn:feature_code":"PPL",
    "gn:name":"Malubay",
    "gn:population":0,
    "gn:timezone":"Asia/Manila",
    "iso:country":"PH",
    "name:fil_x_preferred":[
        "Malubay"
    ],
    "name:und_x_variant":[
        "Maubay"
    ],
    "wof:name":"Malubay",
    "wof:placetype":"locality"
},
  "geometry": {"coordinates":[121.41812,12.94771],"type":"Point"}
}