{
  "type": "Feature",
  "properties": {
    "gn:admin1_code":"02",
    "gn:admin2_code":"31",
    "gn:admin3_code":"23131000.0",
    "gn:asciiname":"Divisoria",
    "gn:country_code":"PH",
    "gn:dem":178,
    "gn:feature_class":"P",
    "gn:feature_code":"PPL",
    "gn:name":"Divisoria",
    "gn:population":0,
    "gn:timezone":"Asia/Manila",
    "iso:country":"PH",
    "name:eng_x_preferred":[
        "Divisoria"
    ],
    "wof:name":"Divisoria",
    "wof:placetype":"locality"
},
  "geometry": {"coordinates":[122.17394,17.02264],"type":"Point"}
}