{
  "type": "Feature",
  "properties": {
    "gn:admin1_code":"40",
    "gn:admin2_code":"H2",
    "gn:admin3_code":"45608000.0",
    "gn:asciiname":"Bukal Norte",
    "gn:country_code":"PH",
    "gn:dem":136,
    "gn:feature_class":"P",
    "gn:feature_code":"PPL",
    "gn:name":"Bukal Norte",
    "gn:population":0,
    "gn:timezone":"Asia/Manila",
    "iso:country":"PH",
    "name:fil_x_preferred":[
        "Bukal Norte"
    ],
    "name:und_x_variant":[
        "Bukal"
    ],
    "wof:name":"Bukal Norte",
    "wof:placetype":"locality"
},
  "geometry": {"coordinates":[121.41219,13.96564],"type":"Point"}
}