{
  "type": "Feature",
  "properties": {
    "gn:admin1_code":"03",
    "gn:admin2_code":"G8",
    "gn:admin3_code":"37701000.0",
    "gn:asciiname":"Reserva",
    "gn:country_code":"PH",
    "gn:dem":12,
    "gn:feature_class":"P",
    "gn:feature_code":"PPL",
    "gn:name":"Reserva",
    "gn:population":0,
    "gn:timezone":"Asia/Manila",
    "iso:country":"PH",
    "name:fil_x_preferred":[
        "Reserva"
    ],
    "wof:name":"Reserva",
    "wof:placetype":"locality"
},
  "geometry": {"coordinates":[121.5406,15.803],"type":"Point"}
}