{
  "type": "Feature",
  "properties": {
    "gn:admin1_code":"03",
    "gn:admin2_code":"47",
    "gn:admin3_code":"34932000.0",
    "gn:asciiname":"Batang",
    "gn:country_code":"PH",
    "gn:dem":17,
    "gn:feature_class":"P",
    "gn:feature_code":"PPL",
    "gn:name":"Batang",
    "gn:population":0,
    "gn:timezone":"Asia/Manila",
    "iso:country":"PH",
    "name:ceb_x_preferred":[
        "Batang"
    ],
    "name:deu_x_preferred":[
        "Batang"
    ],
    "name:fil_x_preferred":[
        "Batang"
    ],
    "name:fra_x_preferred":[
        "Batang"
    ],
    "name:jpn_x_preferred":[
        "\u30d0\u30bf\u30f3"
    ],
    "name:mlg_x_preferred":[
        "Batang"
    ],
    "name:nld_x_preferred":[
        "Batang"
    ],
    "name:nor_x_preferred":[
        "Batang"
    ],
    "name:sun_x_preferred":[
        "Batang"
    ],
    "name:swe_x_preferred":[
        "Batang"
    ],
    "wof:name":"Batang",
    "wof:placetype":"locality"
},
  "geometry": {"coordinates":[120.7637,15.4081],"type":"Point"}
}