{
  "type": "Feature",
  "properties": {
    "gn:admin1_code":"02",
    "gn:admin2_code":"14",
    "gn:admin3_code":"21527000.0",
    "gn:asciiname":"Malallabo",
    "gn:country_code":"PH",
    "gn:dem":30,
    "gn:feature_class":"P",
    "gn:feature_code":"PPL",
    "gn:name":"Malallabo",
    "gn:population":0,
    "gn:timezone":"Asia/Manila",
    "iso:country":"PH",
    "name:fil_x_preferred":[
        "Malallabo"
    ],
    "name:fil_x_variant":[
        "Malallabu"
    ],
    "wof:name":"Malallabo",
    "wof:placetype":"locality"
},
  "geometry": {"coordinates":[121.651,17.67900000000001],"type":"Point"}
}