{
  "type": "Feature",
  "properties": {
    "gn:admin1_code":"08",
    "gn:admin2_code":"55",
    "gn:admin3_code":"86021000.0",
    "gn:asciiname":"Plaridel",
    "gn:country_code":"PH",
    "gn:dem":7,
    "gn:feature_class":"P",
    "gn:feature_code":"PPL",
    "gn:name":"Plaridel",
    "gn:population":0,
    "gn:timezone":"Asia/Manila",
    "iso:country":"PH",
    "name:ceb_x_preferred":[
        "Plaridel"
    ],
    "name:deu_x_preferred":[
        "Plaridel"
    ],
    "name:eng_x_preferred":[
        "Plaridel"
    ],
    "name:fra_x_preferred":[
        "Plaridel"
    ],
    "name:ita_x_preferred":[
        "Plaridel"
    ],
    "name:nld_x_preferred":[
        "Plaridel"
    ],
    "name:und_x_variant":[
        "Plaredel"
    ],
    "name:war_x_preferred":[
        "Plaridel"
    ],
    "wof:name":"Plaridel",
    "wof:placetype":"locality"
},
  "geometry": {"coordinates":[124.91589999999999,11.5092],"type":"Point"}
}