{
  "type": "Feature",
  "properties": {
    "gn:country":"PH",
    "gn:fcode":"PPLA3",
    "gn:pop":15079,
    "iso:country":"PH",
    "name:bcl_x_preferred":[
        "Virac"
    ],
    "name:ceb_x_preferred":[
        "Virac"
    ],
    "name:deu_x_preferred":[
        "Virac"
    ],
    "name:eng_x_preferred":[
        "Virac"
    ],
    "name:fil_x_preferred":[
        "Virac"
    ],
    "name:fra_x_preferred":[
        "Virac"
    ],
    "name:gor_x_preferred":[
        "Virac"
    ],
    "name:ilo_x_preferred":[
        "Virac"
    ],
    "name:ind_x_preferred":[
        "Virac"
    ],
    "name:ita_x_preferred":[
        "Virac"
    ],
    "name:jpn_x_preferred":[
        "\u30f4\u30a3\u30e9\u30af"
    ],
    "name:nld_x_preferred":[
        "Virac"
    ],
    "name:pag_x_preferred":[
        "Virac"
    ],
    "name:pam_x_preferred":[
        "Virac"
    ],
    "name:rus_x_preferred":[
        "\u0412\u0438\u0440\u0430\u043a"
    ],
    "name:swe_x_preferred":[
        "Virac"
    ],
    "name:tgl_x_preferred":[
        "Virac"
    ],
    "name:tha_x_preferred":[
        "\u0e1a\u0e35\u0e23\u0e31\u0e01"
    ],
    "name:urd_x_preferred":[
        "\u0648\u06cc\u0631\u0627\u06a9\u060c \u06a9\u0627\u062a\u0627\u0646\u062f\u0648\u0627\u0646\u06cc\u0633"
    ],
    "name:urd_x_variant":[
        "\u0648\u06cc\u0631\u0627\u06a9"
    ],
    "name:war_x_preferred":[
        "Virac"
    ],
    "name:zho_x_preferred":[
        "\u7dad\u62c9\u514b"
    ],
    "qs:name":"Virac",
    "qs:photos_9r":0,
    "qs:photos_sr":0,
    "qs:pop_sr":"6",
    "wd:wordcount":65,
    "wof:name":"Virac",
    "wof:placetype":"locality",
    "wof:population":15079
},
  "geometry": {"coordinates":[124.23739999999999,13.5848],"type":"Point"}
}