{
  "type": "Feature",
  "properties": {
    "gn:admin1_code":"06",
    "gn:admin2_code":"30",
    "gn:admin3_code":"63027000.0",
    "gn:asciiname":"Girongan",
    "gn:country_code":"PH",
    "gn:dem":101,
    "gn:feature_class":"P",
    "gn:feature_code":"PPL",
    "gn:name":"Girongan",
    "gn:population":0,
    "gn:timezone":"Asia/Manila",
    "iso:country":"PH",
    "name:fil_x_preferred":[
        "Girongan"
    ],
    "name:und_x_variant":[
        "Gerongan"
    ],
    "wof:name":"Girongan",
    "wof:placetype":"locality"
},
  "geometry": {"coordinates":[122.91160000000001,11.2097],"type":"Point"}
}