{
  "type": "Feature",
  "properties": {
    "gn:admin1_code":"12",
    "gn:admin2_code":"57",
    "gn:admin3_code":"124701000.0",
    "gn:asciiname":"Ratabur",
    "gn:country_code":"PH",
    "gn:dem":255,
    "gn:feature_class":"P",
    "gn:feature_code":"PPL",
    "gn:name":"Ratabur",
    "gn:population":0,
    "gn:timezone":"Asia/Manila",
    "iso:country":"PH",
    "name:fil_x_preferred":[
        "Ratabur"
    ],
    "wof:name":"Ratabur",
    "wof:placetype":"locality"
},
  "geometry": {"coordinates":[124.64722,7.43972],"type":"Point"}
}