{
  "type": "Feature",
  "properties": {
    "gn:admin1_code":"05",
    "gn:admin2_code":"16",
    "gn:admin3_code":"51730000.0",
    "gn:asciiname":"Pagukin",
    "gn:country_code":"PH",
    "gn:dem":220,
    "gn:feature_class":"P",
    "gn:feature_code":"PPL",
    "gn:name":"Pagukin",
    "gn:population":0,
    "gn:timezone":"Asia/Manila",
    "iso:country":"PH",
    "name:fil_x_preferred":[
        "Pagukin"
    ],
    "wof:name":"Pagukin",
    "wof:placetype":"locality"
},
  "geometry": {"coordinates":[122.8265,13.877],"type":"Point"}
}