{
  "type": "Feature",
  "properties": {
    "gn:admin1_code":"01",
    "gn:admin2_code":"51",
    "gn:admin3_code":"15508000.0",
    "gn:asciiname":"Tugui Grande",
    "gn:country_code":"PH",
    "gn:dem":82,
    "gn:feature_class":"P",
    "gn:feature_code":"PPL",
    "gn:name":"Tugui Grande",
    "gn:population":0,
    "gn:timezone":"Asia/Manila",
    "iso:country":"PH",
    "name:fil_x_preferred":[
        "Tugui Grande"
    ],
    "name:und_x_variant":[
        "Tugui",
        "Tugue",
        "Tuqui"
    ],
    "wof:name":"Tugui Grande",
    "wof:placetype":"locality"
},
  "geometry": {"coordinates":[119.85809999999999,16.2105],"type":"Point"}
}