{
  "type": "Feature",
  "properties": {
    "gn:admin1_code":"02",
    "gn:admin2_code":"14",
    "gn:admin3_code":"21506000.0",
    "gn:asciiname":"Bitag Pequeno",
    "gn:country_code":"PH",
    "gn:dem":32,
    "gn:feature_class":"P",
    "gn:feature_code":"PPL",
    "gn:name":"Bitag Peque\u00f1o",
    "gn:population":0,
    "gn:timezone":"Asia/Manila",
    "iso:country":"PH",
    "name:fil_x_preferred":[
        "Bitag Peque\u00f1o"
    ],
    "wof:name":"Bitag Pequeno",
    "wof:placetype":"locality"
},
  "geometry": {"coordinates":[121.86964999999999,17.84543],"type":"Point"}
}