{
  "type": "Feature",
  "properties": {
    "gn:admin1_code":"08",
    "gn:admin2_code":"59",
    "gn:admin3_code":"86412000.0",
    "gn:asciiname":"Mantico",
    "gn:country_code":"PH",
    "gn:dem":271,
    "gn:feature_class":"P",
    "gn:feature_code":"PPL",
    "gn:name":"Mantico",
    "gn:population":0,
    "gn:timezone":"Asia/Manila",
    "iso:country":"PH",
    "name:fil_x_preferred":[
        "Mantico"
    ],
    "name:und_x_variant":[
        "Manlico"
    ],
    "wof:name":"Mantico",
    "wof:placetype":"locality"
},
  "geometry": {"coordinates":[125.1045,10.3898],"type":"Point"}
}