{
  "type": "Feature",
  "properties": {
    "gn:admin1_code":"05",
    "gn:admin2_code":"15",
    "gn:admin3_code":"51608000.0",
    "gn:asciiname":"Tabas",
    "gn:country_code":"PH",
    "gn:dem":15,
    "gn:feature_class":"P",
    "gn:feature_code":"PPL",
    "gn:name":"Tabas",
    "gn:population":0,
    "gn:timezone":"Asia/Manila",
    "iso:country":"PH",
    "name:fil_x_preferred":[
        "Tabas"
    ],
    "wof:name":"Tabas",
    "wof:placetype":"locality"
},
  "geometry": {"coordinates":[122.8357,14.2552],"type":"Point"}
}