{
  "type": "Feature",
  "properties": {
    "gn:admin1_code":"05",
    "gn:admin2_code":"15",
    "gn:admin3_code":"51608000.0",
    "gn:asciiname":"Tabas",
    "gn:country_code":"PH",
    "gn:dem":15,
    "gn:feature_class":"P",
    "gn:feature_code":"PPL",
    "gn:name":"Tabas",
    "gn:population":0,
    "gn:timezone":"Asia/Manila",
    "iso:country":"PH",
    "name:ara_x_preferred":[
        "\u0637\u0628\u0633"
    ],
    "name:aze_x_preferred":[
        "T\u0259b\u0259s"
    ],
    "name:cat_x_preferred":[
        "Tabas Gilaki"
    ],
    "name:deu_x_preferred":[
        "Tabas"
    ],
    "name:epo_x_preferred":[
        "Tabas"
    ],
    "name:fas_x_preferred":[
        "\u0637\u0628\u0633"
    ],
    "name:fil_x_preferred":[
        "Tabas"
    ],
    "name:fra_x_preferred":[
        "Tabas"
    ],
    "name:ita_x_preferred":[
        "Tabas"
    ],
    "name:mal_x_preferred":[
        "\u0d24\u0d2c\u0d38\u0d4d"
    ],
    "name:mlg_x_preferred":[
        "Tabas"
    ],
    "name:nld_x_preferred":[
        "Tabas"
    ],
    "name:pnb_x_preferred":[
        "\u0634\u06c1\u0631\u0633\u062a\u0627\u0646 \u0637\u0628\u0633"
    ],
    "name:pol_x_preferred":[
        "Tabas"
    ],
    "name:ron_x_preferred":[
        "Tabas"
    ],
    "name:rus_x_preferred":[
        "\u0422\u0435\u0431\u0435\u0441"
    ],
    "name:tur_x_preferred":[
        "Tebes"
    ],
    "name:urd_x_preferred":[
        "\u0637\u0628\u0633"
    ],
    "name:zho_x_preferred":[
        "\u5854\u5df4\u65af"
    ],
    "wof:name":"Tabas",
    "wof:placetype":"locality"
},
  "geometry": {"coordinates":[122.8357,14.2552],"type":"Point"}
}