{
  "type": "Feature",
  "properties": {
    "gn:gn_country":"PH",
    "gn:gn_fcode":"PPLA3",
    "gn:gn_pop":19612,
    "gn:population":19612,
    "iso:country":"PH",
    "name:bcl_x_preferred":[
        "Baao"
    ],
    "name:ceb_x_preferred":[
        "Baao"
    ],
    "name:deu_x_preferred":[
        "Baao"
    ],
    "name:eng_x_preferred":[
        "Baao"
    ],
    "name:fil_x_preferred":[
        "Baao"
    ],
    "name:fra_x_preferred":[
        "Baao"
    ],
    "name:gor_x_preferred":[
        "Baao"
    ],
    "name:ilo_x_preferred":[
        "Baao"
    ],
    "name:ind_x_preferred":[
        "Baao"
    ],
    "name:ita_x_preferred":[
        "Baao"
    ],
    "name:nld_x_preferred":[
        "Baao"
    ],
    "name:oci_x_preferred":[
        "Baao"
    ],
    "name:pag_x_preferred":[
        "Baao"
    ],
    "name:pam_x_preferred":[
        "Baao"
    ],
    "name:swe_x_preferred":[
        "Baao"
    ],
    "name:tgl_x_preferred":[
        "Baao"
    ],
    "name:vie_x_preferred":[
        "Baao"
    ],
    "name:war_x_preferred":[
        "Baao"
    ],
    "qs_pg:aaroncc":"PH",
    "qs_pg:gn_country":"PH",
    "qs_pg:gn_fcode":"PPLA3",
    "qs_pg:gn_pop":19612,
    "qs_pg:name":"Baao",
    "qs_pg:photos_9r":0,
    "qs_pg:photos_sr":0,
    "qs_pg:pop_sr":6,
    "qs_pg:qs_pg_placetype":"locality",
    "wof:name":"Baao",
    "wof:placetype":"locality",
    "wof:population":19612
},
  "geometry": {"coordinates":[123.3653,13.4549],"type":"Point"}
}