{
  "type": "Feature",
  "properties": {
    "gn:admin1_code":"03",
    "gn:admin2_code":"64",
    "gn:admin3_code":"37101000.0",
    "gn:asciiname":"Tila",
    "gn:country_code":"PH",
    "gn:dem":204,
    "gn:feature_class":"P",
    "gn:feature_code":"PPL",
    "gn:name":"Tila",
    "gn:population":0,
    "gn:timezone":"Asia/Manila",
    "iso:country":"PH",
    "name:ceb_x_preferred":[
        "Tila"
    ],
    "name:deu_x_preferred":[
        "Tila"
    ],
    "name:fil_x_preferred":[
        "Tila"
    ],
    "name:fin_x_preferred":[
        "Tila"
    ],
    "name:fra_x_preferred":[
        "Tila"
    ],
    "name:por_x_preferred":[
        "Tila"
    ],
    "name:rus_x_preferred":[
        "\u0422\u0438\u043b\u0430"
    ],
    "name:sco_x_preferred":[
        "Tila"
    ],
    "name:srp_x_preferred":[
        "\u0422\u0438\u043b\u0430"
    ],
    "name:swe_x_preferred":[
        "Tila"
    ],
    "wof:name":"Tila",
    "wof:placetype":"locality"
},
  "geometry": {"coordinates":[120.25,15.26667],"type":"Point"}
}