{
  "type": "Feature",
  "properties": {
    "gn:admin1_code":"02",
    "gn:admin2_code":"14",
    "gn:admin3_code":"21505000.0",
    "gn:asciiname":"Bangag",
    "gn:country_code":"PH",
    "gn:dem":3,
    "gn:feature_class":"P",
    "gn:feature_code":"PPL",
    "gn:name":"Bangag",
    "gn:population":0,
    "gn:timezone":"Asia/Manila",
    "iso:country":"PH",
    "name:fil_x_preferred":[
        "Bangag"
    ],
    "wof:name":"Bangag",
    "wof:placetype":"locality"
},
  "geometry": {"coordinates":[121.5612,18.2975],"type":"Point"}
}