{
  "type": "Feature",
  "properties": {
    "gn:admin1_code":"41",
    "gn:admin2_code":"40",
    "gn:admin3_code":"175105000.0",
    "gn:asciiname":"Sulputon",
    "gn:country_code":"PH",
    "gn:dem":61,
    "gn:feature_class":"P",
    "gn:feature_code":"PPL",
    "gn:name":"Sulputon",
    "gn:population":0,
    "gn:timezone":"Asia/Manila",
    "iso:country":"PH",
    "name:fil_x_preferred":[
        "Sulputon"
    ],
    "wof:name":"Sulputon",
    "wof:placetype":"locality"
},
  "geometry": {"coordinates":[121.12361,12.25825],"type":"Point"}
}