{
  "type": "Feature",
  "properties": {
    "gn:admin1_code":"07",
    "gn:admin2_code":"11",
    "gn:admin3_code":"71239000.0",
    "gn:asciiname":"Guinob-an",
    "gn:country_code":"PH",
    "gn:dem":119,
    "gn:feature_class":"P",
    "gn:feature_code":"PPL",
    "gn:name":"Guinob-an",
    "gn:population":0,
    "gn:timezone":"Asia/Manila",
    "iso:country":"PH",
    "name:fil_x_preferred":[
        "Guinob-an"
    ],
    "name:und_x_variant":[
        "Ginoban"
    ],
    "wof:name":"Guinob-an",
    "wof:placetype":"locality"
},
  "geometry": {"coordinates":[124.05783,9.6951],"type":"Point"}
}