{
  "type": "Feature",
  "properties": {
    "gn:admin1_code":"12",
    "gn:admin2_code":"70",
    "gn:admin3_code":"126317000.0",
    "gn:asciiname":"Basak Pagalongan",
    "gn:country_code":"PH",
    "gn:dem":361,
    "gn:feature_class":"P",
    "gn:feature_code":"PPL",
    "gn:name":"Basak Pagalongan",
    "gn:population":0,
    "gn:timezone":"Asia/Manila",
    "iso:country":"PH",
    "name:und_x_variant":[
        "Basak",
        "Basack Pagalo\u00f1gan",
        "Basak Pagalongan"
    ],
    "wof:name":"Basak Pagalongan",
    "wof:placetype":"locality"
},
  "geometry": {"coordinates":[124.97541,6.26943],"type":"Point"}
}