{
  "type": "Feature",
  "properties": {
    "gn:admin1_code":"05",
    "gn:admin2_code":"05",
    "gn:admin3_code":"50503000.0",
    "gn:asciiname":"San Vicente",
    "gn:country_code":"PH",
    "gn:dem":68,
    "gn:feature_class":"P",
    "gn:feature_code":"PPL",
    "gn:name":"San Vicente",
    "gn:population":0,
    "gn:timezone":"Asia/Manila",
    "iso:country":"PH",
    "name:fil_x_preferred":[
        "San Vicente"
    ],
    "wof:name":"San Vicente",
    "wof:placetype":"locality"
},
  "geometry": {"coordinates":[123.68333,13.05],"type":"Point"}
}