{
  "type": "Feature",
  "properties": {
    "gn:admin1_code":"05",
    "gn:admin2_code":"05",
    "gn:admin3_code":"50506000.0",
    "gn:asciiname":"Agna",
    "gn:country_code":"PH",
    "gn:dem":20,
    "gn:feature_class":"P",
    "gn:feature_code":"PPL",
    "gn:name":"Agna",
    "gn:population":0,
    "gn:timezone":"Asia/Manila",
    "iso:country":"PH",
    "name:fil_x_preferred":[
        "Agna"
    ],
    "wof:name":"Agna",
    "wof:placetype":"locality"
},
  "geometry": {"coordinates":[123.73333,13.08333],"type":"Point"}
}