{
  "type": "Feature",
  "properties": {
    "gn:admin1_code":"05",
    "gn:admin2_code":"05",
    "gn:admin3_code":"50506000.0",
    "gn:asciiname":"Agna",
    "gn:country_code":"PH",
    "gn:dem":20,
    "gn:feature_class":"P",
    "gn:feature_code":"PPL",
    "gn:name":"Agna",
    "gn:population":0,
    "gn:timezone":"Asia/Manila",
    "iso:country":"PH",
    "name:azb_x_preferred":[
        "\u0627\u0642\u0646\u0627"
    ],
    "name:bul_x_preferred":[
        "\u0410\u043d\u044f"
    ],
    "name:ceb_x_preferred":[
        "Agna"
    ],
    "name:deu_x_preferred":[
        "Agna"
    ],
    "name:epo_x_preferred":[
        "Agna"
    ],
    "name:eus_x_preferred":[
        "Agna"
    ],
    "name:fas_x_preferred":[
        "\u0627\u06af\u0646\u0627"
    ],
    "name:fil_x_preferred":[
        "Agna"
    ],
    "name:fra_x_preferred":[
        "Agna"
    ],
    "name:hun_x_preferred":[
        "Agna"
    ],
    "name:hye_x_preferred":[
        "\u0531\u0576\u0575\u0561"
    ],
    "name:ind_x_preferred":[
        "Agna"
    ],
    "name:ita_x_preferred":[
        "Agna"
    ],
    "name:jpn_x_preferred":[
        "\u30a2\u30fc\u30cb\u30e3"
    ],
    "name:kaz_x_preferred":[
        "\u0410\u043d\u044c\u044f"
    ],
    "name:lat_x_preferred":[
        "Agna"
    ],
    "name:lmo_x_preferred":[
        "Agna"
    ],
    "name:msa_x_preferred":[
        "Agna"
    ],
    "name:nap_x_preferred":[
        "Agna"
    ],
    "name:nld_x_preferred":[
        "Agna"
    ],
    "name:pms_x_preferred":[
        "Agna"
    ],
    "name:pol_x_preferred":[
        "Agna"
    ],
    "name:por_x_preferred":[
        "Agna"
    ],
    "name:ron_x_preferred":[
        "Agna"
    ],
    "name:rus_x_preferred":[
        "\u0410\u043d\u044c\u044f"
    ],
    "name:scn_x_preferred":[
        "Agna"
    ],
    "name:spa_x_preferred":[
        "Agna"
    ],
    "name:srp_x_preferred":[
        "\u0410\u045a\u0430"
    ],
    "name:tgl_x_preferred":[
        "Agna"
    ],
    "name:ukr_x_preferred":[
        "\u0410\u043d\u044c\u044f"
    ],
    "name:urd_x_preferred":[
        "\u0627\u06af\u0646\u0627"
    ],
    "name:uzb_x_preferred":[
        "Agna"
    ],
    "name:vec_x_preferred":[
        "Agna"
    ],
    "name:vie_x_preferred":[
        "Agna"
    ],
    "name:vol_x_preferred":[
        "Agna"
    ],
    "name:war_x_preferred":[
        "Agna"
    ],
    "name:zho_x_preferred":[
        "\u963f\u5c3c\u4e9a"
    ],
    "wof:name":"Agna",
    "wof:placetype":"locality"
},
  "geometry": {"coordinates":[123.73333,13.08333],"type":"Point"}
}