{
  "type": "Feature",
  "properties": {
    "gn:country":"PH",
    "gn:fcode":"ADM3",
    "gn:pop":60244,
    "iso:country":"PH",
    "qs:name":"Talibon",
    "qs:photos_9r":0,
    "qs:photos_sr":0,
    "qs:pop_sr":"8",
    "wof:name":"Talibon",
    "wof:placetype":"localadmin",
    "wof:population":60244
},
  "geometry": {"coordinates":[124.28333000000001,10.11667],"type":"Point"}
}