{
  "type": "Feature",
  "properties": {
    "gn:admin1_code":"05",
    "gn:admin2_code":"19",
    "gn:admin3_code":"52010000.0",
    "gn:asciiname":"Soboc",
    "gn:country_code":"PH",
    "gn:dem":4,
    "gn:feature_class":"P",
    "gn:feature_code":"PPL",
    "gn:name":"Soboc",
    "gn:population":0,
    "gn:timezone":"Asia/Manila",
    "iso:country":"PH",
    "name:fil_x_preferred":[
        "Soboc"
    ],
    "wof:name":"Soboc",
    "wof:placetype":"locality"
},
  "geometry": {"coordinates":[124.3887,13.8704],"type":"Point"}
}