{
  "type": "Feature",
  "properties": {
    "gn:admin1_code":"41",
    "gn:admin2_code":"40",
    "gn:admin3_code":"175110000.0",
    "gn:asciiname":"Buri",
    "gn:country_code":"PH",
    "gn:dem":146,
    "gn:feature_class":"P",
    "gn:feature_code":"PPL",
    "gn:name":"Buri",
    "gn:population":0,
    "gn:timezone":"Asia/Manila",
    "iso:country":"PH",
    "name:bos_x_preferred":[
        "Buri"
    ],
    "name:cat_x_preferred":[
        "Buri"
    ],
    "name:ceb_x_preferred":[
        "Buri"
    ],
    "name:deu_x_preferred":[
        "Buri"
    ],
    "name:fil_x_preferred":[
        "Buri"
    ],
    "name:fra_x_preferred":[
        "Buri"
    ],
    "name:hrv_x_preferred":[
        "Buri"
    ],
    "name:ita_x_preferred":[
        "Buri"
    ],
    "name:lav_x_preferred":[
        "B\u016bri"
    ],
    "name:nld_x_preferred":[
        "Buri"
    ],
    "name:pol_x_preferred":[
        "Buri"
    ],
    "name:ron_x_preferred":[
        "Buri"
    ],
    "name:rus_x_preferred":[
        "\u0411\u0443\u0440\u0438"
    ],
    "name:swe_x_preferred":[
        "Buri"
    ],
    "name:ukr_x_preferred":[
        "\u0411\u0443\u0440\u0456"
    ],
    "wof:name":"Buri",
    "wof:placetype":"locality"
},
  "geometry": {"coordinates":[121.08417,12.23167],"type":"Point"}
}