{
  "type": "Feature",
  "properties": {
    "gn:admin1_code":"41",
    "gn:admin2_code":"40",
    "gn:admin3_code":"175110000.0",
    "gn:asciiname":"Buri",
    "gn:country_code":"PH",
    "gn:dem":146,
    "gn:feature_class":"P",
    "gn:feature_code":"PPL",
    "gn:name":"Buri",
    "gn:population":0,
    "gn:timezone":"Asia/Manila",
    "iso:country":"PH",
    "name:fil_x_preferred":[
        "Buri"
    ],
    "wof:name":"Buri",
    "wof:placetype":"locality"
},
  "geometry": {"coordinates":[121.08417,12.23167],"type":"Point"}
}