{
  "type": "Feature",
  "properties": {
    "gn:admin1_code":"13",
    "gn:admin2_code":"62",
    "gn:admin3_code":"166803000.0",
    "gn:asciiname":"Fudela",
    "gn:country_code":"PH",
    "gn:dem":10,
    "gn:feature_class":"P",
    "gn:feature_code":"PPL",
    "gn:name":"Fudela",
    "gn:population":0,
    "gn:timezone":"Asia/Manila",
    "iso:country":"PH",
    "name:fil_x_preferred":[
        "Fudela"
    ],
    "wof:name":"Fudela",
    "wof:placetype":"locality"
},
  "geometry": {"coordinates":[126.26246,8.18533],"type":"Point"}
}