{
  "type": "Feature",
  "properties": {
    "gn:admin1_code":"40",
    "gn:admin2_code":"H2",
    "gn:admin3_code":"45605000.0",
    "gn:asciiname":"Kadlit",
    "gn:country_code":"PH",
    "gn:dem":17,
    "gn:feature_class":"P",
    "gn:feature_code":"PPL",
    "gn:name":"Kadlit",
    "gn:population":0,
    "gn:timezone":"Asia/Manila",
    "iso:country":"PH",
    "name:fil_x_preferred":[
        "Kadlit"
    ],
    "name:und_x_variant":[
        "Cadlit"
    ],
    "wof:name":"Kadlit",
    "wof:placetype":"locality"
},
  "geometry": {"coordinates":[122.4975,13.7412],"type":"Point"}
}