{
  "type": "Feature",
  "properties": {
    "gn:admin1_code":"02",
    "gn:admin2_code":"31",
    "gn:admin3_code":"23103000.0",
    "gn:asciiname":"Camarunggayan",
    "gn:country_code":"PH",
    "gn:dem":64,
    "gn:feature_class":"P",
    "gn:feature_code":"PPL",
    "gn:name":"Camarunggayan",
    "gn:population":0,
    "gn:timezone":"Asia/Manila",
    "iso:country":"PH",
    "name:fil_x_preferred":[
        "Camarungayan"
    ],
    "wof:name":"Camarunggayan",
    "wof:placetype":"locality"
},
  "geometry": {"coordinates":[121.64973999999999,16.97515],"type":"Point"}
}