{
  "type": "Feature",
  "properties": {
    "gn:admin1_code":"01",
    "gn:admin2_code":"51",
    "gn:admin3_code":"15534000.0",
    "gn:asciiname":"Santo Tomas",
    "gn:country_code":"PH",
    "gn:dem":9,
    "gn:feature_class":"P",
    "gn:feature_code":"PPL",
    "gn:name":"Santo Tomas",
    "gn:population":0,
    "gn:timezone":"Asia/Manila",
    "iso:country":"PH",
    "name:ceb_x_preferred":[
        "Santo Tomas"
    ],
    "name:deu_x_preferred":[
        "Santo Tomas"
    ],
    "name:fil_x_preferred":[
        "Santo Tomas"
    ],
    "name:ilo_x_preferred":[
        "Santo Tomas"
    ],
    "name:lit_x_preferred":[
        "Santo Tomas"
    ],
    "name:nld_x_preferred":[
        "Santo Tomas"
    ],
    "name:sco_x_preferred":[
        "Santo Tomas"
    ],
    "name:srp_x_preferred":[
        "\u0421\u0430\u043d\u0442\u043e \u0422\u043e\u043c\u0430\u0441"
    ],
    "name:swe_x_preferred":[
        "Santo Tomas"
    ],
    "name:war_x_preferred":[
        "Santo Tomas"
    ],
    "wof:name":"Santo Tomas",
    "wof:placetype":"locality"
},
  "geometry": {"coordinates":[120.43300000000001,16.07459],"type":"Point"}
}