{
  "type": "Feature",
  "properties": {
    "gn:admin1_code":"07",
    "gn:admin2_code":"21",
    "gn:admin3_code":"72238000.0",
    "gn:asciiname":"Paz",
    "gn:country_code":"PH",
    "gn:dem":36,
    "gn:feature_class":"P",
    "gn:feature_code":"PPL",
    "gn:name":"Paz",
    "gn:population":0,
    "gn:timezone":"Asia/Manila",
    "iso:country":"PH",
    "name:fil_x_preferred":[
        "Paz"
    ],
    "name:und_x_variant":[
        "Pazo",
        "Paz",
        "Daan Paz"
    ],
    "wof:name":"Paz",
    "wof:placetype":"locality"
},
  "geometry": {"coordinates":[124.4726,10.6948],"type":"Point"}
}