{
  "type": "Feature",
  "properties": {
    "gn:admin1_code":"14",
    "gn:admin2_code":"72",
    "gn:admin3_code":"157011000.0",
    "gn:asciiname":"Nonokon",
    "gn:cc2":"PH",
    "gn:country_code":"PH",
    "gn:dem":13,
    "gn:feature_class":"P",
    "gn:feature_code":"PPL",
    "gn:name":"Nonokon",
    "gn:population":0,
    "gn:timezone":"Asia/Manila",
    "iso:country":"PH",
    "name:und_x_variant":[
        "Nunukan",
        "Nonokon"
    ],
    "wof:name":"Nonokon",
    "wof:placetype":"locality"
},
  "geometry": {"coordinates":[119.46861,4.79972],"type":"Point"}
}