{
  "type": "Feature",
  "properties": {
    "gn:admin1_code":"06",
    "gn:admin2_code":"H3",
    "gn:admin3_code":"64508000.0",
    "gn:asciiname":"Hacienda Pilar",
    "gn:country_code":"PH",
    "gn:dem":5,
    "gn:feature_class":"P",
    "gn:feature_code":"PPL",
    "gn:name":"Hacienda Pilar",
    "gn:population":0,
    "gn:timezone":"Asia/Manila",
    "iso:country":"PH",
    "name:fil_x_preferred":[
        "Hacienda Pilar"
    ],
    "wof:name":"Hacienda Pilar",
    "wof:placetype":"locality"
},
  "geometry": {"coordinates":[123.01260000000001,10.89834],"type":"Point"}
}