{
  "type": "Feature",
  "properties": {
    "gn:admin1_code":"06",
    "gn:admin2_code":"18",
    "gn:admin3_code":"61906000.0",
    "gn:asciiname":"Badlan Hills",
    "gn:country_code":"PH",
    "gn:dem":147,
    "gn:feature_class":"P",
    "gn:feature_code":"PPL",
    "gn:name":"Badlan Hills",
    "gn:population":0,
    "gn:timezone":"Asia/Manila",
    "iso:country":"PH",
    "name:fil_x_preferred":[
        "Badlan Hills"
    ],
    "wof:name":"Badlan Hills",
    "wof:placetype":"locality"
},
  "geometry": {"coordinates":[122.5102,11.4578],"type":"Point"}
}