{
  "type": "Feature",
  "properties": {
    "gn:admin1_code":"14",
    "gn:admin2_code":"56",
    "gn:admin3_code":"153811000.0",
    "gn:asciiname":"Pangacat",
    "gn:country_code":"PH",
    "gn:dem":23,
    "gn:feature_class":"P",
    "gn:feature_code":"PPL",
    "gn:name":"Pangacat",
    "gn:population":0,
    "gn:timezone":"Asia/Manila",
    "iso:country":"PH",
    "name:fil_x_preferred":[
        "Pangacat"
    ],
    "wof:name":"Pangacat",
    "wof:placetype":"locality"
},
  "geometry": {"coordinates":[124.30417,7.31944],"type":"Point"}
}