{
  "type": "Feature",
  "properties": {
    "gn:admin1_code":"08",
    "gn:admin2_code":"37",
    "gn:admin3_code":"83710000.0",
    "gn:asciiname":"Villa Aurora",
    "gn:country_code":"PH",
    "gn:dem":64,
    "gn:feature_class":"P",
    "gn:feature_code":"PPL",
    "gn:name":"Villa Aurora",
    "gn:population":0,
    "gn:timezone":"Asia/Manila",
    "iso:country":"PH",
    "name:fil_x_preferred":[
        "Villa Aurora"
    ],
    "wof:name":"Villa Aurora",
    "wof:placetype":"locality"
},
  "geometry": {"coordinates":[124.88333,10.98333],"type":"Point"}
}