{
  "type": "Feature",
  "properties": {
    "gn:admin1_code":"13",
    "gn:admin2_code":"03",
    "gn:admin3_code":"160307000.0",
    "gn:asciiname":"Mabtay",
    "gn:country_code":"PH",
    "gn:dem":34,
    "gn:feature_class":"P",
    "gn:feature_code":"PPL",
    "gn:name":"Mabtay",
    "gn:population":0,
    "gn:timezone":"Asia/Manila",
    "iso:country":"PH",
    "name:fil_x_preferred":[
        "Mabtay"
    ],
    "wof:name":"Mabtay",
    "wof:placetype":"locality"
},
  "geometry": {"coordinates":[126.03389,8.39222],"type":"Point"}
}