{
  "type": "Feature",
  "properties": {
    "gn:admin1_code":"06",
    "gn:admin2_code":"H3",
    "gn:admin3_code":"64516000.0",
    "gn:asciiname":"Linao Landong",
    "gn:country_code":"PH",
    "gn:dem":57,
    "gn:feature_class":"P",
    "gn:feature_code":"PPL",
    "gn:name":"Linao Landong",
    "gn:population":0,
    "gn:timezone":"Asia/Manila",
    "iso:country":"PH",
    "name:fil_x_preferred":[
        "Linao Landong"
    ],
    "wof:name":"Linao Landong",
    "wof:placetype":"locality"
},
  "geometry": {"coordinates":[122.9606,10.3993],"type":"Point"}
}