{
  "type": "Feature",
  "properties": {
    "gn:admin1_code":"14",
    "gn:admin2_code":"60",
    "gn:admin3_code":"156608000.0",
    "gn:asciiname":"Parian Sai",
    "gn:country_code":"PH",
    "gn:dem":13,
    "gn:feature_class":"P",
    "gn:feature_code":"PPL",
    "gn:name":"Parian Sai",
    "gn:population":0,
    "gn:timezone":"Asia/Manila",
    "iso:country":"PH",
    "name:eng_x_preferred":[
        "Parian Sai"
    ],
    "wof:name":"Parian Sai",
    "wof:placetype":"locality"
},
  "geometry": {"coordinates":[120.53,6.2861],"type":"Point"}
}