{
  "type": "Feature",
  "properties": {
    "gn:admin1_code":"07",
    "gn:admin2_code":"21",
    "gn:admin3_code":"72235000.0",
    "gn:asciiname":"Palamina",
    "gn:country_code":"PH",
    "gn:dem":69,
    "gn:feature_class":"P",
    "gn:feature_code":"PPL",
    "gn:name":"Palamina",
    "gn:population":0,
    "gn:timezone":"Asia/Manila",
    "iso:country":"PH",
    "name:fil_x_preferred":[
        "Palamina"
    ],
    "wof:name":"Palamina",
    "wof:placetype":"locality"
},
  "geometry": {"coordinates":[123.364,9.4404],"type":"Point"}
}