{
  "type": "Feature",
  "properties": {
    "gn:country":"PH",
    "gn:fcode":"PPL",
    "gn:pop":2288,
    "iso:country":"PH",
    "name:fil_x_preferred":[
        "Bangkal"
    ],
    "qs:name":"Bangkal",
    "qs:photos_9r":0,
    "qs:photos_sr":0,
    "qs:pop_sr":"4",
    "wof:name":"Bangkal",
    "wof:placetype":"locality",
    "wof:population":2288
},
  "geometry": {"coordinates":[121.06667,6.06667],"type":"Point"}
}