{
  "type": "Feature",
  "properties": {
    "gn:admin1_code":"05",
    "gn:admin2_code":"16",
    "gn:admin3_code":"51707000.0",
    "gn:asciiname":"Calancaan",
    "gn:country_code":"PH",
    "gn:dem":46,
    "gn:feature_class":"P",
    "gn:feature_code":"PPL",
    "gn:name":"Calancaan",
    "gn:population":0,
    "gn:timezone":"Asia/Manila",
    "iso:country":"PH",
    "name:fil_x_preferred":[
        "Calancaan"
    ],
    "wof:name":"Calancaan",
    "wof:placetype":"locality"
},
  "geometry": {"coordinates":[123.0218,13.7672],"type":"Point"}
}