{
  "type": "Feature",
  "properties": {
    "gn:admin1_code":"03",
    "gn:admin2_code":"13",
    "gn:admin3_code":"31419000.0",
    "gn:asciiname":"Palanas",
    "gn:country_code":"PH",
    "gn:dem":29,
    "gn:feature_class":"P",
    "gn:feature_code":"PPL",
    "gn:name":"Palanas",
    "gn:population":0,
    "gn:timezone":"Asia/Manila",
    "iso:country":"PH",
    "name:fil_x_preferred":[
        "Palanas"
    ],
    "wof:name":"Palanas",
    "wof:placetype":"locality"
},
  "geometry": {"coordinates":[120.9517,15.0431],"type":"Point"}
}