{
  "type": "Feature",
  "properties": {
    "gn:admin1_code":"06",
    "gn:admin2_code":"H3",
    "gn:admin3_code":"64512000.0",
    "gn:asciiname":"Pook",
    "gn:country_code":"PH",
    "gn:dem":15,
    "gn:feature_class":"P",
    "gn:feature_code":"PPL",
    "gn:name":"Pook",
    "gn:population":0,
    "gn:timezone":"Asia/Manila",
    "iso:country":"PH",
    "name:fil_x_preferred":[
        "Pook"
    ],
    "name:und_x_variant":[
        "Po-oo",
        "Po-oc"
    ],
    "wof:name":"Pook",
    "wof:placetype":"locality"
},
  "geometry": {"coordinates":[122.47280000000001,9.5881],"type":"Point"}
}