{
  "type": "Feature",
  "properties": {
    "gn:admin1_code":"03",
    "gn:admin2_code":"63",
    "gn:admin3_code":"36916000.0",
    "gn:asciiname":"Tabani",
    "gn:country_code":"PH",
    "gn:dem":47,
    "gn:feature_class":"P",
    "gn:feature_code":"PPL",
    "gn:name":"Tabani",
    "gn:population":0,
    "gn:timezone":"Asia/Manila",
    "iso:country":"PH",
    "name:fil_x_preferred":[
        "Tabani"
    ],
    "wof:name":"Tabani",
    "wof:placetype":"locality"
},
  "geometry": {"coordinates":[120.596,15.5158],"type":"Point"}
}