{
  "type": "Feature",
  "properties": {
    "gn:admin1_code":"06",
    "gn:admin2_code":"H3",
    "gn:admin3_code":"64530000.0",
    "gn:asciiname":"Hacienda Alijis",
    "gn:country_code":"PH",
    "gn:dem":11,
    "gn:feature_class":"P",
    "gn:feature_code":"PPL",
    "gn:name":"Hacienda Alijis",
    "gn:population":0,
    "gn:timezone":"Asia/Manila",
    "iso:country":"PH",
    "name:fil_x_preferred":[
        "Hacienda Alijis"
    ],
    "name:und_x_variant":[
        "Alijis",
        "Alijis Hacienda"
    ],
    "wof:name":"Hacienda Alijis",
    "wof:placetype":"locality"
},
  "geometry": {"coordinates":[122.8599,10.4459],"type":"Point"}
}