{
  "type": "Feature",
  "properties": {
    "gn:admin1_code":"11",
    "gn:admin2_code":"25",
    "gn:admin3_code":"112402000.0",
    "gn:asciiname":"Catalunan",
    "gn:country_code":"PH",
    "gn:dem":83,
    "gn:feature_class":"P",
    "gn:feature_code":"PPL",
    "gn:name":"Catalunan",
    "gn:population":0,
    "gn:timezone":"Asia/Manila",
    "iso:country":"PH",
    "wof:name":"Catalunan",
    "wof:placetype":"locality"
},
  "geometry": {"coordinates":[125.54443999999999,7.08028],"type":"Point"}
}