{
  "type": "Feature",
  "properties": {
    "gn:admin1_code":"10",
    "gn:admin2_code":"12",
    "gn:admin3_code":"101309000.0",
    "gn:asciiname":"Balangigay",
    "gn:country_code":"PH",
    "gn:dem":331,
    "gn:feature_class":"P",
    "gn:feature_code":"PPL",
    "gn:name":"Balangigay",
    "gn:population":0,
    "gn:timezone":"Asia/Manila",
    "iso:country":"PH",
    "name:fil_x_preferred":[
        "Balangigay"
    ],
    "wof:name":"Balangigay",
    "wof:placetype":"locality"
},
  "geometry": {"coordinates":[125.08222000000001,7.61],"type":"Point"}
}