{
  "type": "Feature",
  "properties": {
    "gn:admin1_code":"41",
    "gn:admin2_code":"38",
    "gn:admin3_code":"174002000.0",
    "gn:asciiname":"Sihi",
    "gn:country_code":"PH",
    "gn:dem":381,
    "gn:feature_class":"P",
    "gn:feature_code":"PPL",
    "gn:name":"Sihi",
    "gn:population":0,
    "gn:timezone":"Asia/Manila",
    "iso:country":"PH",
    "name:fil_x_preferred":[
        "Sihi"
    ],
    "wof:name":"Sihi",
    "wof:placetype":"locality"
},
  "geometry": {"coordinates":[121.99644000000001,13.26332],"type":"Point"}
}