{
  "type": "Feature",
  "properties": {
    "gn:admin1_code":"40",
    "gn:admin2_code":"33",
    "gn:admin3_code":"43429000.0",
    "gn:asciiname":"Liyang",
    "gn:country_code":"PH",
    "gn:dem":222,
    "gn:feature_class":"P",
    "gn:feature_code":"PPL",
    "gn:name":"Liyang",
    "gn:population":0,
    "gn:timezone":"Asia/Manila",
    "iso:country":"PH",
    "name:fil_x_preferred":[
        "Liyang"
    ],
    "wof:name":"Liyang",
    "wof:placetype":"locality"
},
  "geometry": {"coordinates":[121.47880000000001,14.463],"type":"Point"}
}