{
  "type": "Feature",
  "properties": {
    "gn:admin1_code":"40",
    "gn:admin2_code":"33",
    "gn:admin3_code":"43429000.0",
    "gn:asciiname":"Liyang",
    "gn:country_code":"PH",
    "gn:dem":222,
    "gn:feature_class":"P",
    "gn:feature_code":"PPL",
    "gn:name":"Liyang",
    "gn:population":0,
    "gn:timezone":"Asia/Manila",
    "iso:country":"PH",
    "name:cym_x_preferred":[
        "Liyang"
    ],
    "name:deu_x_preferred":[
        "Liyang"
    ],
    "name:fil_x_preferred":[
        "Liyang"
    ],
    "name:fra_x_preferred":[
        "Liyang"
    ],
    "name:ita_x_preferred":[
        "Liyang"
    ],
    "name:jpn_x_preferred":[
        "\u30ea\u30c4\u967d\u5e02"
    ],
    "name:kik_x_preferred":[
        "Liyang"
    ],
    "name:kor_x_preferred":[
        "\ub9ac\uc591\uc2dc"
    ],
    "name:nld_x_preferred":[
        "Liyang"
    ],
    "name:nor_x_preferred":[
        "Liyang"
    ],
    "name:rus_x_preferred":[
        "\u041b\u0438\u044f\u043d"
    ],
    "name:swe_x_preferred":[
        "Liyang"
    ],
    "name:tgl_x_preferred":[
        "Liyang"
    ],
    "name:urd_x_preferred":[
        "\u0644\u06cc\u0626\u0627\u0646\u06af"
    ],
    "name:vie_x_preferred":[
        "L\u1eadt D\u01b0\u01a1ng"
    ],
    "name:wuu_x_preferred":[
        "\u6ea7\u9633\u5e02"
    ],
    "name:zho_x_preferred":[
        "\u6ea7\u9633\u5e02"
    ],
    "wof:name":"Liyang",
    "wof:placetype":"locality"
},
  "geometry": {"coordinates":[121.47880000000001,14.463],"type":"Point"}
}