{
  "type": "Feature",
  "properties": {
    "gn:admin1_code":"03",
    "gn:admin2_code":"64",
    "gn:admin3_code":"37103000.0",
    "gn:asciiname":"Cakalanan",
    "gn:country_code":"PH",
    "gn:dem":43,
    "gn:feature_class":"P",
    "gn:feature_code":"PPL",
    "gn:name":"Cakalanan",
    "gn:population":0,
    "gn:timezone":"Asia/Manila",
    "iso:country":"PH",
    "name:fil_x_preferred":[
        "Cakalanan"
    ],
    "wof:name":"Cakalanan",
    "wof:placetype":"locality"
},
  "geometry": {"coordinates":[119.9507,15.6068],"type":"Point"}
}