{
  "type": "Feature",
  "properties": {
    "gn:admin1_code":"08",
    "gn:admin2_code":"59",
    "gn:admin3_code":"86411000.0",
    "gn:asciiname":"Badiang",
    "gn:country_code":"PH",
    "gn:dem":39,
    "gn:feature_class":"P",
    "gn:feature_code":"PPL",
    "gn:name":"Badiang",
    "gn:population":0,
    "gn:timezone":"Asia/Manila",
    "iso:country":"PH",
    "name:fil_x_preferred":[
        "Badiang"
    ],
    "wof:name":"Badiang",
    "wof:placetype":"locality"
},
  "geometry": {"coordinates":[125.25118000000001,9.93431],"type":"Point"}
}