{
  "type": "Feature",
  "properties": {
    "gn:admin1_code":"05",
    "gn:admin2_code":"39",
    "gn:admin3_code":"54106000.0",
    "gn:asciiname":"Letada",
    "gn:country_code":"PH",
    "gn:dem":4,
    "gn:feature_class":"P",
    "gn:feature_code":"PPL",
    "gn:name":"Letada",
    "gn:population":0,
    "gn:timezone":"Asia/Manila",
    "iso:country":"PH",
    "name:fil_x_preferred":[
        "Letada"
    ],
    "wof:name":"Letada",
    "wof:placetype":"locality"
},
  "geometry": {"coordinates":[123.6583,12.0421],"type":"Point"}
}