{
  "type": "Feature",
  "properties": {
    "gn:admin1_code":"15",
    "gn:admin2_code":"01",
    "gn:admin3_code":"140108000.0",
    "gn:asciiname":"Pidducal",
    "gn:country_code":"PH",
    "gn:dem":88,
    "gn:feature_class":"P",
    "gn:feature_code":"PPL",
    "gn:name":"Pidducal",
    "gn:population":0,
    "gn:timezone":"Asia/Manila",
    "iso:country":"PH",
    "name:fil_x_preferred":[
        "Piducal"
    ],
    "name:fil_x_variant":[
        "Pidducal"
    ],
    "wof:name":"Pidducal",
    "wof:placetype":"locality"
},
  "geometry": {"coordinates":[120.7022,17.7023],"type":"Point"}
}