{
  "type": "Feature",
  "properties": {
    "gn:admin1_code":"02",
    "gn:admin2_code":"14",
    "gn:admin3_code":"21506000.0",
    "gn:asciiname":"Intal",
    "gn:country_code":"PH",
    "gn:dem":232,
    "gn:feature_class":"P",
    "gn:feature_code":"PPL",
    "gn:name":"Intal",
    "gn:population":0,
    "gn:timezone":"Asia/Manila",
    "iso:country":"PH",
    "name:fil_x_preferred":[
        "Intal"
    ],
    "wof:name":"Intal",
    "wof:placetype":"locality"
},
  "geometry": {"coordinates":[121.98333,17.95],"type":"Point"}
}