{
  "type": "Feature",
  "properties": {
    "gn:admin1_code":"08",
    "gn:admin2_code":"67",
    "gn:admin3_code":"84813000.0",
    "gn:asciiname":"Saguitantuyan",
    "gn:cc2":"PH",
    "gn:country_code":"PH",
    "gn:dem":182,
    "gn:feature_class":"P",
    "gn:feature_code":"PPL",
    "gn:name":"Saguitantuyan",
    "gn:population":0,
    "gn:timezone":"Asia/Manila",
    "iso:country":"PH",
    "name:und_x_variant":[
        "Saguitantuvan",
        "Saguitantuyan"
    ],
    "wof:name":"Saguitantuyan",
    "wof:placetype":"locality"
},
  "geometry": {"coordinates":[124.81667,12.36667],"type":"Point"}
}