{
  "type": "Feature",
  "properties": {
    "gn:admin1_code":"01",
    "gn:admin2_code":"29",
    "gn:admin3_code":"12934000.0",
    "gn:asciiname":"Pong-ol",
    "gn:country_code":"PH",
    "gn:dem":6,
    "gn:feature_class":"P",
    "gn:feature_code":"PPL",
    "gn:name":"Pong-ol",
    "gn:population":0,
    "gn:timezone":"Asia/Manila",
    "iso:country":"PH",
    "name:fil_x_preferred":[
        "Pong-ol"
    ],
    "wof:name":"Pong-ol",
    "wof:placetype":"locality"
},
  "geometry": {"coordinates":[120.36667,17.55],"type":"Point"}
}