{
  "type": "Feature",
  "properties": {
    "gn:admin1_code":"02",
    "gn:admin2_code":"48",
    "gn:asciiname":"Bolong",
    "gn:country_code":"PH",
    "gn:dem":896,
    "gn:feature_class":"P",
    "gn:feature_code":"PPL",
    "gn:name":"Bolong",
    "gn:population":0,
    "gn:timezone":"Asia/Manila",
    "iso:country":"PH",
    "name:ces_x_preferred":[
        "Bolong"
    ],
    "name:fas_x_preferred":[
        "\u0627\u0698\u062f\u0647\u0627\u0686\u0647"
    ],
    "name:fil_x_preferred":[
        "Bolong"
    ],
    "name:fra_x_preferred":[
        "Bolong"
    ],
    "name:mal_x_preferred":[
        "\u0d2c\u0d4b\u0d32\u0d4b\u0d19\u0d4d"
    ],
    "name:nld_x_preferred":[
        "Bolong"
    ],
    "name:ori_x_preferred":[
        "Bolong"
    ],
    "name:pol_x_preferred":[
        "Bolong"
    ],
    "name:rus_x_preferred":[
        "Bolong"
    ],
    "name:vie_x_preferred":[
        "Bolong"
    ],
    "name:zho_x_preferred":[
        "\u8584\u6c0f\u9f8d\u5c6c"
    ],
    "wof:name":"Bolong",
    "wof:placetype":"locality"
},
  "geometry": {"coordinates":[120.93333,16.13332999999999],"type":"Point"}
}