{
  "type": "Feature",
  "properties": {
    "gn:admin1_code":"02",
    "gn:admin2_code":"48",
    "gn:asciiname":"Bolong",
    "gn:country_code":"PH",
    "gn:dem":896,
    "gn:feature_class":"P",
    "gn:feature_code":"PPL",
    "gn:name":"Bolong",
    "gn:population":0,
    "gn:timezone":"Asia/Manila",
    "iso:country":"PH",
    "name:fil_x_preferred":[
        "Bolong"
    ],
    "wof:name":"Bolong",
    "wof:placetype":"locality"
},
  "geometry": {"coordinates":[120.93333,16.13332999999999],"type":"Point"}
}