{
  "type": "Feature",
  "properties": {
    "gn:admin1_code":"05",
    "gn:admin2_code":"16",
    "gn:admin3_code":"51710000.0",
    "gn:asciiname":"Taligtig",
    "gn:country_code":"PH",
    "gn:dem":4,
    "gn:feature_class":"P",
    "gn:feature_code":"PPL",
    "gn:name":"Taligtig",
    "gn:population":0,
    "gn:timezone":"Asia/Manila",
    "iso:country":"PH",
    "name:fil_x_preferred":[
        "Taligtig"
    ],
    "name:und_x_variant":[
        "Talidtid"
    ],
    "wof:name":"Taligtig",
    "wof:placetype":"locality"
},
  "geometry": {"coordinates":[123.16330000000001,13.6607],"type":"Point"}
}