{
  "type": "Feature",
  "properties": {
    "gn:admin1_code":"03",
    "gn:admin2_code":"47",
    "gn:admin3_code":"34926000.0",
    "gn:asciiname":"Parilla",
    "gn:country_code":"PH",
    "gn:dem":112,
    "gn:feature_class":"P",
    "gn:feature_code":"PPL",
    "gn:name":"Parilla",
    "gn:population":0,
    "gn:timezone":"Asia/Manila",
    "iso:country":"PH",
    "name:fil_x_preferred":[
        "Parilla"
    ],
    "wof:name":"Parilla",
    "wof:placetype":"locality"
},
  "geometry": {"coordinates":[121.0539,15.746],"type":"Point"}
}