{
  "type": "Feature",
  "properties": {
    "gn:admin1_code":"03",
    "gn:admin2_code":"63",
    "gn:admin3_code":"36910000.0",
    "gn:asciiname":"Samput",
    "gn:country_code":"PH",
    "gn:dem":26,
    "gn:feature_class":"P",
    "gn:feature_code":"PPL",
    "gn:name":"Samput",
    "gn:population":0,
    "gn:timezone":"Asia/Manila",
    "iso:country":"PH",
    "name:fil_x_preferred":[
        "Samput"
    ],
    "name:fil_x_variant":[
        "Sampot"
    ],
    "wof:name":"Samput",
    "wof:placetype":"locality"
},
  "geometry": {"coordinates":[120.58126,15.66163],"type":"Point"}
}