{
  "type": "Feature",
  "properties": {
    "gn:admin1_code":"07",
    "gn:admin2_code":"21",
    "gn:admin3_code":"72246000.0",
    "gn:asciiname":"Sabang",
    "gn:country_code":"PH",
    "gn:dem":69,
    "gn:feature_class":"P",
    "gn:feature_code":"PPL",
    "gn:name":"Sabang",
    "gn:population":0,
    "gn:timezone":"Asia/Manila",
    "iso:country":"PH",
    "name:fil_x_preferred":[
        "Sabang"
    ],
    "wof:name":"Sabang",
    "wof:placetype":"locality"
},
  "geometry": {"coordinates":[123.6143,10.0327],"type":"Point"}
}