{
  "type": "Feature",
  "properties": {
    "gn:country":"PH",
    "gn:fcode":"PPL",
    "gn:pop":5257,
    "iso:country":"PH",
    "name:fil_x_preferred":[
        "Esperanza"
    ],
    "name:unk_x_variant":[
        "Esperanzo"
    ],
    "qs:name":"Esperanza",
    "qs:photos_9r":0,
    "qs:photos_sr":0,
    "qs:pop_sr":"5",
    "wd:wordcount":349,
    "wof:name":"Esperanza",
    "wof:placetype":"locality",
    "wof:population":5257
},
  "geometry": {"coordinates":[124.3143,10.6995],"type":"Point"}
}