{
  "type": "Feature",
  "properties": {
    "gn:admin1_code":"01",
    "gn:admin2_code":"51",
    "gn:admin3_code":"15508000.0",
    "gn:asciiname":"Okcuanan",
    "gn:country_code":"PH",
    "gn:dem":132,
    "gn:feature_class":"P",
    "gn:feature_code":"PPL",
    "gn:name":"Okcuanan",
    "gn:population":0,
    "gn:timezone":"Asia/Manila",
    "iso:country":"PH",
    "name:fil_x_preferred":[
        "Okcuanan"
    ],
    "wof:name":"Okcuanan",
    "wof:placetype":"locality"
},
  "geometry": {"coordinates":[119.8329,16.243],"type":"Point"}
}