{
  "type": "Feature",
  "properties": {
    "gn:admin1_code":"09",
    "gn:admin2_code":"65",
    "gn:admin3_code":"97207000.0",
    "gn:asciiname":"Loquilos",
    "gn:country_code":"PH",
    "gn:dem":64,
    "gn:feature_class":"P",
    "gn:feature_code":"PPL",
    "gn:name":"Loquilos",
    "gn:population":0,
    "gn:timezone":"Asia/Manila",
    "iso:country":"PH",
    "name:eng_x_preferred":[
        "Loquilos"
    ],
    "wof:name":"Loquilos",
    "wof:placetype":"locality"
},
  "geometry": {"coordinates":[123.1138,8.5168],"type":"Point"}
}