{
  "type": "Feature",
  "properties": {
    "gn:admin1_code":"14",
    "gn:admin2_code":"35",
    "gn:admin3_code":"153611000.0",
    "gn:asciiname":"Talu-an",
    "gn:cc2":"PH",
    "gn:country_code":"PH",
    "gn:dem":715,
    "gn:feature_class":"P",
    "gn:feature_code":"PPL",
    "gn:name":"Talu-an",
    "gn:population":0,
    "gn:timezone":"Asia/Manila",
    "iso:country":"PH",
    "name:und_x_variant":[
        "Taiu-an",
        "Talu-an"
    ],
    "wof:name":"Talu-an",
    "wof:placetype":"locality"
},
  "geometry": {"coordinates":[124.34944,7.85639],"type":"Point"}
}