{
  "type": "Feature",
  "properties": {
    "gn:admin1_code":"09",
    "gn:admin2_code":"65",
    "gn:admin3_code":"97219000.0",
    "gn:asciiname":"Latabon",
    "gn:cc2":"PH",
    "gn:country_code":"PH",
    "gn:dem":11,
    "gn:feature_class":"P",
    "gn:feature_code":"PPL",
    "gn:name":"Latabon",
    "gn:population":0,
    "gn:timezone":"Asia/Manila",
    "iso:country":"PH",
    "name:und_x_variant":[
        "Litoban",
        "Lataban",
        "Latabon"
    ],
    "wof:name":"Latabon",
    "wof:placetype":"locality"
},
  "geometry": {"coordinates":[122.12306,7.61778],"type":"Point"}
}