{
  "type": "Feature",
  "properties": {
    "iso:country":"PH",
    "name:bcl_x_preferred":[
        "Cardona"
    ],
    "name:cat_x_preferred":[
        "Cardona"
    ],
    "name:cbk_zam_x_preferred":[
        "Cardona"
    ],
    "name:ceb_x_preferred":[
        "Cardona"
    ],
    "name:deu_x_preferred":[
        "Cardona"
    ],
    "name:dut_x_preferred":[
        "Cardona"
    ],
    "name:eng_x_preferred":[
        "Cardona"
    ],
    "name:fil_x_preferred":[
        "Cardona"
    ],
    "name:fra_x_preferred":[
        "Cardona"
    ],
    "name:fre_x_preferred":[
        "Cardona"
    ],
    "name:ger_x_preferred":[
        "Cardona"
    ],
    "name:ilo_x_preferred":[
        "Cardona"
    ],
    "name:ind_x_preferred":[
        "Cardona"
    ],
    "name:ita_x_preferred":[
        "Cardona"
    ],
    "name:jpn_x_preferred":[
        "\u30ab\u30eb\u30c9\u30ca"
    ],
    "name:nld_x_preferred":[
        "Cardona"
    ],
    "name:oci_x_preferred":[
        "Cardona"
    ],
    "name:pag_x_preferred":[
        "Cardona"
    ],
    "name:pam_x_preferred":[
        "Cardona"
    ],
    "name:rus_x_preferred":[
        "\u041a\u0430\u0440\u0434\u043e\u043d\u0430"
    ],
    "name:spa_x_preferred":[
        "Cardona"
    ],
    "name:swe_x_preferred":[
        "Cardona"
    ],
    "name:tgl_x_preferred":[
        "Cardona"
    ],
    "name:vie_x_preferred":[
        "Cardona"
    ],
    "name:war_x_preferred":[
        "Cardona"
    ],
    "qs:gn_country":"PH",
    "qs:gn_fcode":"PPLA3",
    "qs:gn_pop":30222,
    "qs:name":"Cardona",
    "qs:name_adm0":"Philippines",
    "qs:name_adm1":"Calabarzon",
    "qs:photos":71,
    "qs:photos_1k":14,
    "qs:photos_9k":1,
    "qs:photos_9r":2,
    "qs:photos_all":71,
    "qs:photos_sr":2,
    "qs:placetype":"Town",
    "qs:pop_sr":"7",
    "qs:woe_adm0":23424934,
    "wd:wordcount":148,
    "wof:name":"Cardona",
    "wof:placetype":"locality",
    "wof:population":30222
},
  "geometry": {"coordinates":[121.2289,14.486],"type":"Point"}
}