{
  "type": "Feature",
  "properties": {
    "gn:admin1_code":"11",
    "gn:admin2_code":"26",
    "gn:admin3_code":"112509000.0",
    "gn:asciiname":"Silad",
    "gn:country_code":"PH",
    "gn:dem":17,
    "gn:feature_class":"P",
    "gn:feature_code":"PPL",
    "gn:name":"Silad",
    "gn:population":0,
    "gn:timezone":"Asia/Manila",
    "iso:country":"PH",
    "name:fil_x_preferred":[
        "Silad"
    ],
    "wof:name":"Silad",
    "wof:placetype":"locality"
},
  "geometry": {"coordinates":[126.16629,6.88214],"type":"Point"}
}