{
  "type": "Feature",
  "properties": {
    "gn:admin1_code":"15",
    "gn:admin2_code":"H6",
    "gn:admin3_code":"148104000.0",
    "gn:asciiname":"Amugao",
    "gn:country_code":"PH",
    "gn:dem":312,
    "gn:feature_class":"P",
    "gn:feature_code":"PPL",
    "gn:name":"Amugao",
    "gn:population":0,
    "gn:timezone":"Asia/Manila",
    "iso:country":"PH",
    "name:fil_x_preferred":[
        "Amugao"
    ],
    "wof:name":"Amugao",
    "wof:placetype":"locality"
},
  "geometry": {"coordinates":[121.14225,18.1256],"type":"Point"}
}