{
  "type": "Feature",
  "properties": {
    "gn:admin1_code":"02",
    "gn:admin2_code":"14",
    "gn:admin3_code":"21510000.0",
    "gn:asciiname":"Dammang Sur",
    "gn:country_code":"PH",
    "gn:dem":8,
    "gn:feature_class":"P",
    "gn:feature_code":"PPL",
    "gn:name":"Dammang Sur",
    "gn:population":0,
    "gn:timezone":"Asia/Manila",
    "iso:country":"PH",
    "name:fil_x_preferred":[
        "Dammang Sur"
    ],
    "wof:name":"Dammang Sur",
    "wof:placetype":"locality"
},
  "geometry": {"coordinates":[121.6628,18.2637],"type":"Point"}
}