{
  "type": "Feature",
  "properties": {
    "gn:country":"PH",
    "gn:fcode":"PPL",
    "gn:pop":3771,
    "iso:country":"PH",
    "name:fil_x_preferred":[
        "San Jose"
    ],
    "qs:name":"San Jose",
    "qs:photos_9r":0,
    "qs:photos_sr":0,
    "qs:pop_sr":"4",
    "wd:wordcount":802,
    "wof:name":"San Jose",
    "wof:placetype":"locality",
    "wof:population":3771
},
  "geometry": {"coordinates":[122.53389,10.77028],"type":"Point"}
}