{
  "type": "Feature",
  "properties": {
    "gn:admin1_code":"05",
    "gn:admin2_code":"39",
    "gn:admin3_code":"54121000.0",
    "gn:asciiname":"Canlaorente",
    "gn:country_code":"PH",
    "gn:dem":103,
    "gn:feature_class":"P",
    "gn:feature_code":"PPL",
    "gn:name":"Canlaorente",
    "gn:population":0,
    "gn:timezone":"Asia/Manila",
    "iso:country":"PH",
    "name:fil_x_preferred":[
        "Canlaorente"
    ],
    "wof:name":"Canlaorente",
    "wof:placetype":"locality"
},
  "geometry": {"coordinates":[123.73333,12.25],"type":"Point"}
}