{
  "type": "Feature",
  "properties": {
    "gn:admin1_code":"06",
    "gn:admin2_code":"06",
    "gn:admin3_code":"60604000.0",
    "gn:asciiname":"Calog",
    "gn:country_code":"PH",
    "gn:dem":15,
    "gn:feature_class":"P",
    "gn:feature_code":"PPL",
    "gn:name":"Calog",
    "gn:population":0,
    "gn:timezone":"Asia/Manila",
    "iso:country":"PH",
    "name:fil_x_preferred":[
        "Calog"
    ],
    "wof:name":"Calog",
    "wof:placetype":"locality"
},
  "geometry": {"coordinates":[122.06910000000001,11.0549],"type":"Point"}
}