{
  "type": "Feature",
  "properties": {
    "gn:admin1_code":"03",
    "gn:admin2_code":"63",
    "gn:admin3_code":"36910000.0",
    "gn:asciiname":"Rang-Ayan",
    "gn:country_code":"PH",
    "gn:dem":27,
    "gn:feature_class":"P",
    "gn:feature_code":"PPL",
    "gn:name":"Rang-Ayan",
    "gn:population":0,
    "gn:timezone":"Asia/Manila",
    "iso:country":"PH",
    "wof:name":"Rang-Ayan",
    "wof:placetype":"locality"
},
  "geometry": {"coordinates":[120.52938,15.65418],"type":"Point"}
}