{
  "type": "Feature",
  "properties": {
    "gn:admin1_code":"10",
    "gn:admin2_code":"34",
    "gn:admin3_code":"103517000.0",
    "gn:asciiname":"Poona-Piagapo",
    "gn:country_code":"PH",
    "gn:dem":523,
    "gn:feature_class":"P",
    "gn:feature_code":"PPLA3",
    "gn:name":"Poona-Piagapo",
    "gn:population":0,
    "gn:timezone":"Asia/Manila",
    "iso:country":"PH",
    "wof:name":"Poona-Piagapo",
    "wof:placetype":"locality"
},
  "geometry": {"coordinates":[124.11667,8.08333],"type":"Point"}
}