{
  "type": "Feature",
  "properties": {
    "gn:admin1_code":"09",
    "gn:admin2_code":"ZSI",
    "gn:admin3_code":"98311000.0",
    "gn:asciiname":"Balian",
    "gn:country_code":"PH",
    "gn:dem":31,
    "gn:feature_class":"P",
    "gn:feature_code":"PPL",
    "gn:name":"Balian",
    "gn:population":0,
    "gn:timezone":"Asia/Manila",
    "iso:country":"PH",
    "name:deu_x_preferred":[
        "Balian"
    ],
    "name:fil_x_preferred":[
        "Balian"
    ],
    "wof:name":"Balian",
    "wof:placetype":"locality"
},
  "geometry": {"coordinates":[122.8425,7.55639],"type":"Point"}
}