{
  "type": "Feature",
  "properties": {
    "gn:admin1_code":"40",
    "gn:admin2_code":"33",
    "gn:admin3_code":"43425000.0",
    "gn:asciiname":"Bagong Silang",
    "gn:country_code":"PH",
    "gn:dem":60,
    "gn:feature_class":"P",
    "gn:feature_code":"PPL",
    "gn:name":"Bagong Silang",
    "gn:population":0,
    "gn:timezone":"Asia/Manila",
    "iso:country":"PH",
    "name:fil_x_preferred":[
        "Bagong Silang"
    ],
    "wof:name":"Bagong Silang",
    "wof:placetype":"locality"
},
  "geometry": {"coordinates":[121.0284,14.3363],"type":"Point"}
}