{
  "type": "Feature",
  "properties": {
    "gn:admin1_code":"00",
    "gn:admin2_code":"C8",
    "gn:asciiname":"Magoon",
    "gn:country_code":"PH",
    "gn:dem":-9999,
    "gn:feature_class":"P",
    "gn:feature_code":"PPL",
    "gn:name":"Magoon",
    "gn:population":0,
    "gn:timezone":"Asia/Manila",
    "iso:country":"PH",
    "wof:name":"Magoon",
    "wof:placetype":"locality"
},
  "geometry": {"coordinates":[124.25,8.28333],"type":"Point"}
}