{
  "type": "Feature",
  "properties": {
    "gn:admin1_code":"01",
    "gn:admin2_code":"51",
    "gn:admin3_code":"15532000.0",
    "gn:asciiname":"Pangoloan",
    "gn:country_code":"PH",
    "gn:dem":12,
    "gn:feature_class":"P",
    "gn:feature_code":"PPL",
    "gn:name":"Pangoloan",
    "gn:population":0,
    "gn:timezone":"Asia/Manila",
    "iso:country":"PH",
    "name:fil_x_preferred":[
        "Pangoloan"
    ],
    "name:und_x_variant":[
        "Pangolonan",
        "Panglaoan"
    ],
    "wof:name":"Pangoloan",
    "wof:placetype":"locality"
},
  "geometry": {"coordinates":[120.31485000000001,15.92657],"type":"Point"}
}