{
  "type": "Feature",
  "properties": {
    "gn:country":"PH",
    "gn:fcode":"PPL",
    "gn:pop":3751,
    "iso:country":"PH",
    "qs:name":"Limpapa",
    "qs:photos_9r":0,
    "qs:photos_sr":0,
    "qs:pop_sr":"4",
    "wof:name":"Limpapa",
    "wof:placetype":"locality",
    "wof:population":3751
},
  "geometry": {"coordinates":[121.91056,7.11972],"type":"Point"}
}