{
  "type": "Feature",
  "properties": {
    "gn:admin1_code":"09",
    "gn:admin2_code":"65",
    "gn:admin3_code":"97218000.0",
    "gn:asciiname":"Gusa",
    "gn:country_code":"PH",
    "gn:dem":16,
    "gn:feature_class":"P",
    "gn:feature_code":"PPL",
    "gn:name":"Gusa",
    "gn:population":0,
    "gn:timezone":"Asia/Manila",
    "iso:country":"PH",
    "name:eng_x_preferred":[
        "Gusa"
    ],
    "wof:name":"Gusa",
    "wof:placetype":"locality"
},
  "geometry": {"coordinates":[122.97790000000001,8.2583],"type":"Point"}
}