{
  "type": "Feature",
  "properties": {
    "gn:admin1_code":"02",
    "gn:admin2_code":"31",
    "gn:admin3_code":"23121000.0",
    "gn:asciiname":"Dioanga",
    "gn:country_code":"PH",
    "gn:dem":12,
    "gn:feature_class":"P",
    "gn:feature_code":"PPL",
    "gn:name":"Dioanga",
    "gn:population":0,
    "gn:timezone":"Asia/Manila",
    "iso:country":"PH",
    "name:fil_x_preferred":[
        "Dioanga"
    ],
    "wof:name":"Dioanga",
    "wof:placetype":"locality"
},
  "geometry": {"coordinates":[122.43634,17.08214],"type":"Point"}
}