{
  "type": "Feature",
  "properties": {
    "gn:admin1_code":"05",
    "gn:admin2_code":"15",
    "gn:admin3_code":"51610000.0",
    "gn:asciiname":"Cagtalaba",
    "gn:country_code":"PH",
    "gn:dem":27,
    "gn:feature_class":"P",
    "gn:feature_code":"PPL",
    "gn:name":"Cagtalaba",
    "gn:population":0,
    "gn:timezone":"Asia/Manila",
    "iso:country":"PH",
    "name:fil_x_preferred":[
        "Cagtalaba"
    ],
    "wof:name":"Cagtalaba",
    "wof:placetype":"locality"
},
  "geometry": {"coordinates":[122.38012000000001,14.16146],"type":"Point"}
}