{
  "type": "Feature",
  "properties": {
    "gn:admin1_code":"05",
    "gn:admin2_code":"39",
    "gn:admin3_code":"54120000.0",
    "gn:asciiname":"Aguho",
    "gn:country_code":"PH",
    "gn:dem":15,
    "gn:feature_class":"P",
    "gn:feature_code":"PPL",
    "gn:name":"Aguho",
    "gn:population":0,
    "gn:timezone":"Asia/Manila",
    "iso:country":"PH",
    "name:fil_x_preferred":[
        "Aguho"
    ],
    "wof:name":"Aguho",
    "wof:placetype":"locality"
},
  "geometry": {"coordinates":[122.86944,13.16],"type":"Point"}
}