{
  "type": "Feature",
  "properties": {
    "gn:country":"PH",
    "gn:fcode":"PPL",
    "gn:population":2644,
    "iso:country":"PH",
    "name:fil_x_preferred":[
        "Pangascasan"
    ],
    "name:und_x_variant":[
        "Panasgasan"
    ],
    "qs:name":"Pangascasan",
    "qs:photos_9r":0,
    "qs:photos_sr":0,
    "qs:pop_sr":"4",
    "wof:name":"Pangascasan",
    "wof:placetype":"locality",
    "wof:population":2644
},
  "geometry": {"coordinates":[120.08664,16.11691],"type":"Point"}
}