{
  "type": "Feature",
  "properties": {
    "gn:admin1_code":"40",
    "gn:admin2_code":"33",
    "gn:admin3_code":"43417000.0",
    "gn:asciiname":"Labangan",
    "gn:country_code":"PH",
    "gn:dem":138,
    "gn:feature_class":"P",
    "gn:feature_code":"PPL",
    "gn:name":"Labangan",
    "gn:population":0,
    "gn:timezone":"Asia/Manila",
    "iso:country":"PH",
    "name:fil_x_preferred":[
        "Labangan"
    ],
    "wof:name":"Labangan",
    "wof:placetype":"locality"
},
  "geometry": {"coordinates":[121.39319999999999,14.1638],"type":"Point"}
}