{
  "type": "Feature",
  "properties": {
    "gn:admin1_code":"14",
    "gn:admin2_code":"56",
    "gn:admin3_code":"153814000.0",
    "gn:asciiname":"Tumbao",
    "gn:cc2":"PH",
    "gn:country_code":"PH",
    "gn:dem":6,
    "gn:feature_class":"P",
    "gn:feature_code":"PPL",
    "gn:name":"Tumbao",
    "gn:population":0,
    "gn:timezone":"Asia/Manila",
    "iso:country":"PH",
    "name:und_x_variant":[
        "Kabuntalan",
        "Tumbo",
        "Tumbao"
    ],
    "wof:name":"Tumbao",
    "wof:placetype":"locality"
},
  "geometry": {"coordinates":[124.38861,7.11556],"type":"Point"}
}