{
  "type": "Feature",
  "properties": {
    "gn:admin1_code":"01",
    "gn:admin2_code":"51",
    "gn:admin3_code":"15519000.0",
    "gn:asciiname":"Alilao",
    "gn:country_code":"PH",
    "gn:dem":12,
    "gn:feature_class":"P",
    "gn:feature_code":"PPL",
    "gn:name":"Alilao",
    "gn:population":0,
    "gn:timezone":"Asia/Manila",
    "iso:country":"PH",
    "name:fil_x_preferred":[
        "Alilao"
    ],
    "wof:name":"Alilao",
    "wof:placetype":"locality"
},
  "geometry": {"coordinates":[119.88039999999999,15.9808],"type":"Point"}
}