{
  "type": "Feature",
  "properties": {
    "gn:country":"PH",
    "gn:fcode":"PPL",
    "gn:population":2289,
    "iso:country":"PH",
    "name:fil_x_preferred":[
        "Hacienda Refugio"
    ],
    "name:und_x_variant":[
        "Refugio"
    ],
    "qs:name":"Hacienda Refugio",
    "qs:photos_9r":0,
    "qs:photos_sr":0,
    "qs:pop_sr":"4",
    "wof:name":"Hacienda Refugio",
    "wof:placetype":"locality",
    "wof:population":2289
},
  "geometry": {"coordinates":[123.44450000000001,10.52166],"type":"Point"}
}