{
  "type": "Feature",
  "properties": {
    "gn:admin1_code":"03",
    "gn:admin2_code":"13",
    "gn:admin3_code":"31422000.0",
    "gn:asciiname":"Pasong Intsik",
    "gn:country_code":"PH",
    "gn:dem":48,
    "gn:feature_class":"P",
    "gn:feature_code":"PPL",
    "gn:name":"Pasong Intsik",
    "gn:population":0,
    "gn:timezone":"Asia/Manila",
    "iso:country":"PH",
    "name:fil_x_preferred":[
        "Pasong Insik"
    ],
    "wof:name":"Pasong Intsik",
    "wof:placetype":"locality"
},
  "geometry": {"coordinates":[120.97202,15.00618],"type":"Point"}
}