{
  "type": "Feature",
  "properties": {
    "gn:country":"PH",
    "gn:fcode":"PPL",
    "gn:population":3246,
    "iso:country":"PH",
    "name:fil_x_preferred":[
        "Mangarine"
    ],
    "name:und_x_variant":[
        "Mangaran"
    ],
    "qs:name":"Mangarine",
    "qs:photos_9r":0,
    "qs:photos_sr":0,
    "qs:pop_sr":"4",
    "wof:name":"Mangarine",
    "wof:placetype":"locality",
    "wof:population":3246
},
  "geometry": {"coordinates":[121.09801,12.35115],"type":"Point"}
}