{
  "type": "Feature",
  "properties": {
    "gn:admin1_code":"01",
    "gn:admin2_code":"29",
    "gn:admin3_code":"12919000.0",
    "gn:asciiname":"Ibay",
    "gn:country_code":"PH",
    "gn:dem":10,
    "gn:feature_class":"P",
    "gn:feature_code":"PPL",
    "gn:name":"Ibay",
    "gn:population":0,
    "gn:timezone":"Asia/Manila",
    "iso:country":"PH",
    "name:fil_x_preferred":[
        "Iboy"
    ],
    "name:fil_x_variant":[
        "Ibay"
    ],
    "wof:name":"Ibay",
    "wof:placetype":"locality"
},
  "geometry": {"coordinates":[120.38518999999999,17.62565],"type":"Point"}
}