{
  "type": "Feature",
  "properties": {
    "gn:admin1_code":"05",
    "gn:admin2_code":"19",
    "gn:admin3_code":"52002000.0",
    "gn:asciiname":"Macatol",
    "gn:country_code":"PH",
    "gn:dem":16,
    "gn:feature_class":"P",
    "gn:feature_code":"PPL",
    "gn:name":"Macatol",
    "gn:population":0,
    "gn:timezone":"Asia/Manila",
    "iso:country":"PH",
    "name:fil_x_preferred":[
        "Macatol"
    ],
    "name:und_x_variant":[
        "Macutal"
    ],
    "wof:name":"Macatol",
    "wof:placetype":"locality"
},
  "geometry": {"coordinates":[124.3818,13.6722],"type":"Point"}
}