{
  "type": "Feature",
  "properties": {
    "gn:admin1_code":"06",
    "gn:admin2_code":"30",
    "gn:admin3_code":"63045000.0",
    "gn:asciiname":"Baroc",
    "gn:country_code":"PH",
    "gn:dem":8,
    "gn:feature_class":"P",
    "gn:feature_code":"PPL",
    "gn:name":"Baroc",
    "gn:population":0,
    "gn:timezone":"Asia/Manila",
    "iso:country":"PH",
    "name:fil_x_preferred":[
        "Baroc"
    ],
    "wof:name":"Baroc",
    "wof:placetype":"locality"
},
  "geometry": {"coordinates":[122.41667,10.68333],"type":"Point"}
}