{
  "type": "Feature",
  "properties": {
    "gn:admin1_code":"41",
    "gn:admin2_code":"49",
    "gn:admin3_code":"175304000.0",
    "gn:asciiname":"Bacabaca",
    "gn:country_code":"PH",
    "gn:dem":20,
    "gn:feature_class":"P",
    "gn:feature_code":"PPL",
    "gn:name":"Bacabaca",
    "gn:population":0,
    "gn:timezone":"Asia/Manila",
    "iso:country":"PH",
    "name:eng_x_preferred":[
        "Bacabaca"
    ],
    "wof:name":"Bacabaca",
    "wof:placetype":"locality"
},
  "geometry": {"coordinates":[117.23069,8.28114],"type":"Point"}
}