{
  "type": "Feature",
  "properties": {
    "gn:admin1_code":"41",
    "gn:admin2_code":"41",
    "gn:admin3_code":"175206000.0",
    "gn:asciiname":"Malusac",
    "gn:country_code":"PH",
    "gn:dem":16,
    "gn:feature_class":"P",
    "gn:feature_code":"PPL",
    "gn:name":"Malusac",
    "gn:population":0,
    "gn:timezone":"Asia/Manila",
    "iso:country":"PH",
    "name:fil_x_preferred":[
        "Malusac"
    ],
    "name:und_x_variant":[
        "Malusak"
    ],
    "wof:name":"Malusac",
    "wof:placetype":"locality"
},
  "geometry": {"coordinates":[121.47772000000001,12.95741],"type":"Point"}
}