{
  "type": "Feature",
  "properties": {
    "gn:admin1_code":"09",
    "gn:admin2_code":"ZSI",
    "gn:admin3_code":"98307000.0",
    "gn:asciiname":"Sumangul",
    "gn:country_code":"PH",
    "gn:dem":36,
    "gn:feature_class":"P",
    "gn:feature_code":"PPL",
    "gn:name":"Sumangul",
    "gn:population":0,
    "gn:timezone":"Asia/Manila",
    "iso:country":"PH",
    "name:fil_x_preferred":[
        "Sumangul"
    ],
    "wof:name":"Sumangul",
    "wof:placetype":"locality"
},
  "geometry": {"coordinates":[122.90000000000001,7.43333],"type":"Point"}
}