{
  "type": "Feature",
  "properties": {
    "gn:admin1_code":"09",
    "gn:admin2_code":"ZSI",
    "gn:admin3_code":"98316000.0",
    "gn:asciiname":"Dicul",
    "gn:country_code":"PH",
    "gn:dem":103,
    "gn:feature_class":"P",
    "gn:feature_code":"PPL",
    "gn:name":"Dicul",
    "gn:population":0,
    "gn:timezone":"Asia/Manila",
    "iso:country":"PH",
    "name:und_x_variant":[
        "Dicut",
        "Dicul"
    ],
    "wof:name":"Dicul",
    "wof:placetype":"locality"
},
  "geometry": {"coordinates":[122.40132,7.56967],"type":"Point"}
}