{
  "type": "Feature",
  "properties": {
    "gn:admin1_code":"05",
    "gn:admin2_code":"39",
    "gn:admin3_code":"54109000.0",
    "gn:asciiname":"Tawad",
    "gn:country_code":"PH",
    "gn:dem":64,
    "gn:feature_class":"P",
    "gn:feature_code":"PPL",
    "gn:name":"Tawad",
    "gn:population":0,
    "gn:timezone":"Asia/Manila",
    "iso:country":"PH",
    "name:fil_x_preferred":[
        "Tawad"
    ],
    "wof:name":"Tawad",
    "wof:placetype":"locality"
},
  "geometry": {"coordinates":[124.0547,11.7484],"type":"Point"}
}