{
  "type": "Feature",
  "properties": {
    "gn:country":"PH",
    "gn:fcode":"ADM3",
    "gn:pop":15500,
    "iso:country":"PH",
    "name:fil_x_preferred":[
        "Bangui"
    ],
    "name:fil_x_variant":[
        "Bayan ng Bangui"
    ],
    "qs:name":"Bangui",
    "qs:photos_9r":0,
    "qs:photos_sr":0,
    "qs:pop_sr":"6",
    "wof:name":"Bangui",
    "wof:placetype":"localadmin",
    "wof:population":15500
},
  "geometry": {"coordinates":[120.75321,18.47045],"type":"Point"}
}