{
  "type": "Feature",
  "properties": {
    "gn:country":"PH",
    "gn:fcode":"PPLA3",
    "gn:pop":2576,
    "iso:country":"PH",
    "name:bcl_x_preferred":[
        "Santa Teresita"
    ],
    "name:cat_x_preferred":[
        "Santa Teresita"
    ],
    "name:ceb_x_preferred":[
        "Santa Teresita"
    ],
    "name:deu_x_preferred":[
        "Santa Teresita"
    ],
    "name:eng_x_preferred":[
        "Santa Teresita"
    ],
    "name:fil_x_preferred":[
        "Santa Teresita"
    ],
    "name:fra_x_preferred":[
        "Santa Teresita"
    ],
    "name:ilo_x_preferred":[
        "Santa Teresita"
    ],
    "name:ind_x_preferred":[
        "Santa Teresita"
    ],
    "name:ita_x_preferred":[
        "Santa Teresita"
    ],
    "name:nld_x_preferred":[
        "Santa Teresita"
    ],
    "name:oci_x_preferred":[
        "Santa Teresita"
    ],
    "name:pag_x_preferred":[
        "Santa Teresita"
    ],
    "name:pam_x_preferred":[
        "Santa Teresita"
    ],
    "name:spa_x_preferred":[
        "Santa Teresita de Cagay\u00e1n"
    ],
    "name:swe_x_preferred":[
        "Santa Teresita"
    ],
    "name:tgl_x_preferred":[
        "Santa Teresita"
    ],
    "name:vie_x_preferred":[
        "Santa Teresita"
    ],
    "name:war_x_preferred":[
        "Santa Teresita"
    ],
    "qs:name":"Santa Teresita",
    "qs:photos_9r":0,
    "qs:photos_sr":0,
    "qs:pop_sr":"4",
    "wd:wordcount":43,
    "wof:name":"Santa Teresita",
    "wof:placetype":"locality",
    "wof:population":2576
},
  "geometry": {"coordinates":[121.9127,18.2472],"type":"Point"}
}