{
  "type": "Feature",
  "properties": {
    "gn:country":"PH",
    "gn:fcode":"PPL",
    "gn:population":3804,
    "iso:country":"PH",
    "name:und_x_variant":[
        "Baclayon"
    ],
    "qs_pg:aaroncc":"PH",
    "qs_pg:gn_country":"PH",
    "qs_pg:gn_fcode":"PPL",
    "qs_pg:gn_pop":3804,
    "qs_pg:name":"New Baclayon",
    "qs_pg:photos_9r":0,
    "qs_pg:photos_sr":0,
    "qs_pg:pop_sr":4,
    "qs_pg:qs_pg_placetype":"locality",
    "wof:name":"New Baclayon",
    "wof:placetype":"locality",
    "wof:population":3804
},
  "geometry": {"coordinates":[125.36944,6.58417],"type":"Point"}
}