{
  "type": "Feature",
  "properties": {
    "iso:country":"PH",
    "name:bcl_x_preferred":[
        "San Roque"
    ],
    "name:deu_x_preferred":[
        "San Roque"
    ],
    "name:eng_x_preferred":[
        "San Roque"
    ],
    "name:fra_x_preferred":[
        "San Roque"
    ],
    "name:ilo_x_preferred":[
        "San Roque"
    ],
    "name:ind_x_preferred":[
        "San Roque"
    ],
    "name:ita_x_preferred":[
        "San Roque"
    ],
    "name:jpn_x_preferred":[
        "\u30b5\u30f3\u30fb\u30ed\u30b1"
    ],
    "name:nld_x_preferred":[
        "San Roque"
    ],
    "name:pag_x_preferred":[
        "San Roque"
    ],
    "name:pam_x_preferred":[
        "San Roque"
    ],
    "name:swe_x_preferred":[
        "San Roque"
    ],
    "name:tgl_x_preferred":[
        "San Roque"
    ],
    "name:vie_x_preferred":[
        "San Roque"
    ],
    "name:war_x_preferred":[
        "San Roque"
    ],
    "qs:gn_country":"PH",
    "qs:gn_fcode":"PPLA3",
    "qs:gn_pop":0,
    "qs:name":"San Roque",
    "qs:name_adm0":"Philippines",
    "qs:name_adm1":"Eastern Visayas",
    "qs:photos":15,
    "qs:photos_1k":3,
    "qs:photos_9k":1,
    "qs:photos_9r":1,
    "qs:photos_all":15,
    "qs:photos_sr":1,
    "qs:placetype":"Town",
    "qs:pop_sr":"0",
    "qs:woe_adm0":23424934,
    "wof:name":"San Roque",
    "wof:placetype":"locality"
},
  "geometry": {"coordinates":[124.86667,12.53333],"type":"Point"}
}