{
  "type": "Feature",
  "properties": {
    "gn:admin1_code":"41",
    "gn:admin2_code":"49",
    "gn:admin3_code":"175309000.0",
    "gn:asciiname":"Anapla",
    "gn:country_code":"PH",
    "gn:dem":29,
    "gn:feature_class":"P",
    "gn:feature_code":"PPL",
    "gn:name":"Anapla",
    "gn:population":0,
    "gn:timezone":"Asia/Manila",
    "iso:country":"PH",
    "name:fil_x_preferred":[
        "Anapla"
    ],
    "wof:name":"Anapla",
    "wof:placetype":"locality"
},
  "geometry": {"coordinates":[120.02589999999999,12.143],"type":"Point"}
}