{
  "type": "Feature",
  "properties": {
    "gn:admin1_code":"NCR",
    "gn:admin2_code":"137400000",
    "gn:admin3_code":"137404000.0",
    "gn:asciiname":"Batasan Hills",
    "gn:country_code":"PH",
    "gn:dem":92,
    "gn:feature_class":"P",
    "gn:feature_code":"PPL",
    "gn:name":"Batasan Hills",
    "gn:population":0,
    "gn:timezone":"Asia/Manila",
    "iso:country":"PH",
    "name:eng_x_preferred":[
        "Batasan Hills"
    ],
    "name:fra_x_preferred":[
        "Batasan Hills"
    ],
    "wof:name":"Batasan Hills",
    "wof:placetype":"locality"
},
  "geometry": {"coordinates":[121.09547000000001,14.68469],"type":"Point"}
}