{
  "type": "Feature",
  "properties": {
    "gn:admin1_code":"41",
    "gn:admin2_code":"54",
    "gn:admin3_code":"175904000.0",
    "gn:asciiname":"Bangquiling",
    "gn:country_code":"PH",
    "gn:dem":17,
    "gn:feature_class":"P",
    "gn:feature_code":"PPL",
    "gn:name":"Bangquiling",
    "gn:population":0,
    "gn:timezone":"Asia/Manila",
    "iso:country":"PH",
    "name:fil_x_preferred":[
        "Bangquiling"
    ],
    "wof:name":"Bangquiling",
    "wof:placetype":"locality"
},
  "geometry": {"coordinates":[122.0339,12.6091],"type":"Point"}
}