{
  "type": "Feature",
  "properties": {
    "gn:admin1_code":"15",
    "gn:admin2_code":"27",
    "gn:admin3_code":"142708000.0",
    "gn:asciiname":"Bunhian",
    "gn:country_code":"PH",
    "gn:dem":737,
    "gn:feature_class":"P",
    "gn:feature_code":"PPL",
    "gn:name":"Bunhian",
    "gn:population":0,
    "gn:timezone":"Asia/Manila",
    "iso:country":"PH",
    "name:fil_x_preferred":[
        "Bunhian"
    ],
    "wof:name":"Bunhian",
    "wof:placetype":"locality"
},
  "geometry": {"coordinates":[121.31524,16.98125],"type":"Point"}
}