{
  "type": "Feature",
  "properties": {
    "gn:admin1_code":"14",
    "gn:admin2_code":"60",
    "gn:admin3_code":"156613000.0",
    "gn:asciiname":"Bilaan",
    "gn:country_code":"PH",
    "gn:dem":91,
    "gn:feature_class":"P",
    "gn:feature_code":"PPL",
    "gn:name":"Bilaan",
    "gn:population":0,
    "gn:timezone":"Asia/Manila",
    "iso:country":"PH",
    "name:fil_x_preferred":[
        "Bilaan"
    ],
    "wof:name":"Bilaan",
    "wof:placetype":"locality"
},
  "geometry": {"coordinates":[121.11772000000001,5.97772],"type":"Point"}
}