{
  "type": "Feature",
  "properties": {
    "gn:admin1_code":"01",
    "gn:admin2_code":"28",
    "gn:admin3_code":"12805000.0",
    "gn:asciiname":"Mariit",
    "gn:country_code":"PH",
    "gn:dem":43,
    "gn:feature_class":"P",
    "gn:feature_code":"PPL",
    "gn:name":"Mariit",
    "gn:population":0,
    "gn:timezone":"Asia/Manila",
    "iso:country":"PH",
    "name:fil_x_preferred":[
        "Mariit"
    ],
    "wof:name":"Mariit",
    "wof:placetype":"locality"
},
  "geometry": {"coordinates":[120.57380000000001,18.0973],"type":"Point"}
}