{
  "type": "Feature",
  "properties": {
    "gn:admin1_code":"06",
    "gn:admin2_code":"06",
    "gn:admin3_code":"60607000.0",
    "gn:asciiname":"Banos",
    "gn:country_code":"PH",
    "gn:dem":192,
    "gn:feature_class":"P",
    "gn:feature_code":"PPL",
    "gn:name":"Banos",
    "gn:population":0,
    "gn:timezone":"Asia/Manila",
    "iso:country":"PH",
    "name:fil_x_preferred":[
        "Banos"
    ],
    "wof:name":"Banos",
    "wof:placetype":"locality"
},
  "geometry": {"coordinates":[121.9956,10.5863],"type":"Point"}
}