{
  "type": "Feature",
  "properties": {
    "gn:admin1_code":"41",
    "gn:admin2_code":"49",
    "gn:admin3_code":"175302000.0",
    "gn:asciiname":"Villasol",
    "gn:country_code":"PH",
    "gn:dem":23,
    "gn:feature_class":"P",
    "gn:feature_code":"PPL",
    "gn:name":"Villasol",
    "gn:population":0,
    "gn:timezone":"Asia/Manila",
    "iso:country":"PH",
    "name:eng_x_preferred":[
        "Villasol"
    ],
    "name:und_x_variant":[
        "Viallasol"
    ],
    "wof:name":"Villasol",
    "wof:placetype":"locality"
},
  "geometry": {"coordinates":[120.9692,11.1408],"type":"Point"}
}