{
  "type": "Feature",
  "properties": {
    "gn:admin1_code":"40",
    "gn:admin2_code":"H2",
    "gn:admin3_code":"45607000.0",
    "gn:asciiname":"Yaganak",
    "gn:country_code":"PH",
    "gn:dem":48,
    "gn:feature_class":"P",
    "gn:feature_code":"PPL",
    "gn:name":"Yaganak",
    "gn:population":0,
    "gn:timezone":"Asia/Manila",
    "iso:country":"PH",
    "name:fil_x_preferred":[
        "Yaganak"
    ],
    "wof:name":"Yaganak",
    "wof:placetype":"locality"
},
  "geometry": {"coordinates":[122.3627,13.9215],"type":"Point"}
}