{
  "type": "Feature",
  "properties": {
    "gn:admin1_code":"40",
    "gn:admin2_code":"H2",
    "gn:admin3_code":"45622000.0",
    "gn:asciiname":"Sumalang",
    "gn:country_code":"PH",
    "gn:dem":115,
    "gn:feature_class":"P",
    "gn:feature_code":"PPL",
    "gn:name":"Sumalang",
    "gn:population":0,
    "gn:timezone":"Asia/Manila",
    "iso:country":"PH",
    "name:fil_x_preferred":[
        "Sumalang"
    ],
    "name:fil_x_variant":[
        "Sumilahg"
    ],
    "wof:name":"Sumalang",
    "wof:placetype":"locality"
},
  "geometry": {"coordinates":[122.3335,13.8099],"type":"Point"}
}