{
  "type": "Feature",
  "properties": {
    "gn:admin1_code":"01",
    "gn:admin2_code":"29",
    "gn:admin3_code":"12933000.0",
    "gn:asciiname":"Viejo",
    "gn:country_code":"PH",
    "gn:dem":33,
    "gn:feature_class":"P",
    "gn:feature_code":"PPL",
    "gn:name":"Viejo",
    "gn:population":0,
    "gn:timezone":"Asia/Manila",
    "iso:country":"PH",
    "name:fil_x_preferred":[
        "Viejo"
    ],
    "name:fil_x_variant":[
        "Biejo"
    ],
    "wof:name":"Viejo",
    "wof:placetype":"locality"
},
  "geometry": {"coordinates":[120.461,16.9157],"type":"Point"}
}