{
  "type": "Feature",
  "properties": {
    "gn:country":"PH",
    "gn:fcode":"PPL",
    "gn:pop":2698,
    "iso:country":"PH",
    "name:fil_x_preferred":[
        "Inapatan"
    ],
    "qs:name":"Inapatan",
    "qs:photos_9r":0,
    "qs:photos_sr":0,
    "qs:pop_sr":"4",
    "wof:name":"Inapatan",
    "wof:placetype":"locality",
    "wof:population":2698
},
  "geometry": {"coordinates":[123.3227,13.3964],"type":"Point"}
}