{
  "type": "Feature",
  "properties": {
    "gn:admin1_code":"05",
    "gn:admin2_code":"16",
    "gn:admin3_code":"51703000.0",
    "gn:asciiname":"Palo",
    "gn:country_code":"PH",
    "gn:dem":9,
    "gn:feature_class":"P",
    "gn:feature_code":"PPL",
    "gn:name":"Palo",
    "gn:population":0,
    "gn:timezone":"Asia/Manila",
    "iso:country":"PH",
    "name:ceb_x_preferred":[
        "Palo"
    ],
    "name:deu_x_preferred":[
        "Palo"
    ],
    "name:fil_x_preferred":[
        "Palo"
    ],
    "name:fin_x_preferred":[
        "Palo"
    ],
    "name:ita_x_preferred":[
        "Palo"
    ],
    "name:nld_x_preferred":[
        "Palo"
    ],
    "name:pol_x_preferred":[
        "Palo"
    ],
    "name:slk_x_preferred":[
        "Palo"
    ],
    "name:spa_x_preferred":[
        "Palo"
    ],
    "name:swe_x_preferred":[
        "Palo"
    ],
    "name:tgl_x_preferred":[
        "Palo"
    ],
    "name:vol_x_preferred":[
        "Palo"
    ],
    "name:war_x_preferred":[
        "Palo"
    ],
    "wof:name":"Palo",
    "wof:placetype":"locality"
},
  "geometry": {"coordinates":[123.2782,13.2625],"type":"Point"}
}