{
  "type": "Feature",
  "properties": {
    "gn:admin1_code":"12",
    "gn:admin2_code":"71",
    "gn:admin3_code":"126508000.0",
    "gn:asciiname":"Capincong",
    "gn:country_code":"PH",
    "gn:dem":25,
    "gn:feature_class":"P",
    "gn:feature_code":"PPL",
    "gn:name":"Capincong",
    "gn:population":0,
    "gn:timezone":"Asia/Manila",
    "iso:country":"PH",
    "name:fil_x_preferred":[
        "Capincong"
    ],
    "wof:name":"Capincong",
    "wof:placetype":"locality"
},
  "geometry": {"coordinates":[124.60198,6.77037],"type":"Point"}
}