{
  "type": "Feature",
  "properties": {
    "gn:admin1_code":"07",
    "gn:admin2_code":"11",
    "gn:admin3_code":"71234000.0",
    "gn:asciiname":"Waig",
    "gn:country_code":"PH",
    "gn:dem":242,
    "gn:feature_class":"P",
    "gn:feature_code":"PPL",
    "gn:name":"Waig",
    "gn:population":0,
    "gn:timezone":"Asia/Manila",
    "iso:country":"PH",
    "name:fil_x_preferred":[
        "Waig"
    ],
    "wof:name":"Waig",
    "wof:placetype":"locality"
},
  "geometry": {"coordinates":[124.33611000000001,9.795],"type":"Point"}
}