{
  "type": "Feature",
  "properties": {
    "gn:admin1_code":"40",
    "gn:admin2_code":"33",
    "gn:admin3_code":"43413000.0",
    "gn:asciiname":"Halang",
    "gn:country_code":"PH",
    "gn:dem":301,
    "gn:feature_class":"P",
    "gn:feature_code":"PPL",
    "gn:name":"Halang",
    "gn:population":0,
    "gn:timezone":"Asia/Manila",
    "iso:country":"PH",
    "name:fil_x_preferred":[
        "Halang"
    ],
    "wof:name":"Halang",
    "wof:placetype":"locality"
},
  "geometry": {"coordinates":[121.48,14.3024],"type":"Point"}
}