{
  "type": "Feature",
  "properties": {
    "gn:admin1_code":"15",
    "gn:admin2_code":"27",
    "gn:admin3_code":"142703000.0",
    "gn:asciiname":"Hulyaban",
    "gn:country_code":"PH",
    "gn:dem":766,
    "gn:feature_class":"P",
    "gn:feature_code":"PPL",
    "gn:name":"Hulyaban",
    "gn:population":0,
    "gn:timezone":"Asia/Manila",
    "iso:country":"PH",
    "name:fil_x_preferred":[
        "Hulyaban"
    ],
    "wof:name":"Hulyaban",
    "wof:placetype":"locality"
},
  "geometry": {"coordinates":[121.09153999999999,16.77067000000001],"type":"Point"}
}