{
  "type": "Feature",
  "properties": {
    "gn:admin1_code":"11",
    "gn:admin2_code":"25",
    "gn:admin3_code":"112402000.0",
    "gn:asciiname":"Mandog",
    "gn:cc2":"PH",
    "gn:country_code":"PH",
    "gn:dem":39,
    "gn:feature_class":"P",
    "gn:feature_code":"PPL",
    "gn:name":"Mandog",
    "gn:population":0,
    "gn:timezone":"Asia/Manila",
    "iso:country":"PH",
    "name:und_x_variant":[
        "Mandug"
    ],
    "wof:name":"Mandog",
    "wof:placetype":"locality"
},
  "geometry": {"coordinates":[125.57944000000001,7.16833],"type":"Point"}
}