{
  "type": "Feature",
  "properties": {
    "gn:country":"PH",
    "gn:fcode":"PPL",
    "gn:pop":4782,
    "iso:country":"PH",
    "name:fil_x_preferred":[
        "Taclobo"
    ],
    "qs:name":"Taclobo",
    "qs:photos_9r":0,
    "qs:photos_sr":0,
    "qs:pop_sr":"4",
    "wof:name":"Taclobo",
    "wof:placetype":"locality",
    "wof:population":4782
},
  "geometry": {"coordinates":[122.58601,12.30744],"type":"Point"}
}