{
  "type": "Feature",
  "properties": {
    "gn:country":"PH",
    "gn:fcode":"ADM3",
    "gn:population":6171,
    "iso:country":"PH",
    "name:und_x_variant":[
        "Bangngas"
    ],
    "qs:name":"Marunggas",
    "qs:photos_9r":0,
    "qs:photos_sr":0,
    "qs:pop_sr":"5",
    "wof:name":"Marunggas",
    "wof:placetype":"localadmin",
    "wof:population":6171
},
  "geometry": {"coordinates":[120.96666999999999,6.11667],"type":"Point"}
}