{
  "type": "Feature",
  "properties": {
    "gn:country":"PH",
    "gn:fcode":"PPL",
    "gn:pop":2814,
    "iso:country":"PH",
    "qs:name":"Mahayag",
    "qs:photos_9r":0,
    "qs:photos_sr":0,
    "qs:pop_sr":"4",
    "wof:name":"Mahayag",
    "wof:placetype":"locality",
    "wof:population":2814
},
  "geometry": {"coordinates":[125.61944,7.21667],"type":"Point"}
}