{
  "type": "Feature",
  "properties": {
    "gn:admin1_code":"08",
    "gn:admin2_code":"37",
    "gn:admin3_code":"83717000.0",
    "gn:asciiname":"Tagkip",
    "gn:cc2":"PH",
    "gn:country_code":"PH",
    "gn:dem":47,
    "gn:feature_class":"P",
    "gn:feature_code":"PPL",
    "gn:name":"Tagkip",
    "gn:population":0,
    "gn:timezone":"Asia/Manila",
    "iso:country":"PH",
    "name:und_x_variant":[
        "Tapkip",
        "Tagkip"
    ],
    "wof:name":"Tagkip",
    "wof:placetype":"locality"
},
  "geometry": {"coordinates":[124.87667,11.09389],"type":"Point"}
}