{
  "type": "Feature",
  "properties": {
    "gn:admin1_code":"15",
    "gn:admin2_code":"27",
    "gn:admin3_code":"142710000.0",
    "gn:asciiname":"Bawi",
    "gn:country_code":"PH",
    "gn:dem":1546,
    "gn:feature_class":"P",
    "gn:feature_code":"PPL",
    "gn:name":"Bawi",
    "gn:population":0,
    "gn:timezone":"Asia/Manila",
    "iso:country":"PH",
    "name:aze_x_preferred":[
        "Bavi"
    ],
    "name:fas_x_preferred":[
        "\u0628\u0627\u0648\u06cc"
    ],
    "name:fil_x_preferred":[
        "Bawi"
    ],
    "name:por_x_preferred":[
        "Aspebedes"
    ],
    "wof:name":"Bawi",
    "wof:placetype":"locality"
},
  "geometry": {"coordinates":[120.92113999999999,16.66187],"type":"Point"}
}