{
  "type": "Feature",
  "properties": {
    "gn:admin1_code":"40",
    "gn:admin2_code":"20",
    "gn:admin3_code":"42118000.0",
    "gn:asciiname":"Paligawan",
    "gn:country_code":"PH",
    "gn:dem":175,
    "gn:feature_class":"P",
    "gn:feature_code":"PPL",
    "gn:name":"Paligawan",
    "gn:population":0,
    "gn:timezone":"Asia/Manila",
    "iso:country":"PH",
    "name:fil_x_preferred":[
        "Paligawan"
    ],
    "name:und_x_variant":[
        "Paliguan"
    ],
    "wof:name":"Paligawan",
    "wof:placetype":"locality"
},
  "geometry": {"coordinates":[121.03091999999999,14.26484],"type":"Point"}
}