{
  "type": "Feature",
  "properties": {
    "gn:admin1_code":"08",
    "gn:admin2_code":"67",
    "gn:admin3_code":"84808000.0",
    "gn:asciiname":"Salingcol",
    "gn:country_code":"PH",
    "gn:dem":13,
    "gn:feature_class":"P",
    "gn:feature_code":"PPL",
    "gn:name":"Salingcol",
    "gn:population":0,
    "gn:timezone":"Asia/Manila",
    "iso:country":"PH",
    "name:fil_x_preferred":[
        "Salingcol"
    ],
    "name:und_x_variant":[
        "Sangcol"
    ],
    "wof:name":"Salingcol",
    "wof:placetype":"locality"
},
  "geometry": {"coordinates":[125.0326,12.5572],"type":"Point"}
}