{
  "type": "Feature",
  "properties": {
    "gn:admin1_code":"01",
    "gn:admin2_code":"51",
    "gn:admin3_code":"15529000.0",
    "gn:asciiname":"San Eugenio",
    "gn:country_code":"PH",
    "gn:dem":95,
    "gn:feature_class":"P",
    "gn:feature_code":"PPL",
    "gn:name":"San Euge\u00f1io",
    "gn:population":0,
    "gn:timezone":"Asia/Manila",
    "iso:country":"PH",
    "name:fil_x_preferred":[
        "San Euge\u00f1io"
    ],
    "wof:name":"San Eugenio",
    "wof:placetype":"locality"
},
  "geometry": {"coordinates":[120.79349999999999,16.0616],"type":"Point"}
}