{
  "type": "Feature",
  "properties": {
    "gn:admin1_code":"05",
    "gn:admin2_code":"15",
    "gn:admin3_code":"51606000.0",
    "gn:asciiname":"Dalas",
    "gn:country_code":"PH",
    "gn:dem":40,
    "gn:feature_class":"P",
    "gn:feature_code":"PPL",
    "gn:name":"Dalas",
    "gn:population":0,
    "gn:timezone":"Asia/Manila",
    "iso:country":"PH",
    "name:azb_x_preferred":[
        "\u062f\u0644\u0633(\u0628\u0646\u062f\u0631\u0645\u0627\u0647\u0634\u0647\u0631)"
    ],
    "name:fil_x_preferred":[
        "Dalas"
    ],
    "wof:name":"Dalas",
    "wof:placetype":"locality"
},
  "geometry": {"coordinates":[122.81667,14.15],"type":"Point"}
}