{
  "type": "Feature",
  "properties": {
    "gn:admin1_code":"06",
    "gn:admin2_code":"30",
    "gn:admin3_code":"63021000.0",
    "gn:asciiname":"Riray",
    "gn:country_code":"PH",
    "gn:dem":342,
    "gn:feature_class":"P",
    "gn:feature_code":"PPL",
    "gn:name":"Riray",
    "gn:population":0,
    "gn:timezone":"Asia/Manila",
    "iso:country":"PH",
    "name:fil_x_preferred":[
        "Riray"
    ],
    "wof:name":"Riray",
    "wof:placetype":"locality"
},
  "geometry": {"coordinates":[122.22580000000001,10.78295],"type":"Point"}
}