{
  "type": "Feature",
  "properties": {
    "gn:admin1_code":"02",
    "gn:admin2_code":"14",
    "gn:admin3_code":"21509000.0",
    "gn:asciiname":"Suryo",
    "gn:country_code":"PH",
    "gn:dem":50,
    "gn:feature_class":"P",
    "gn:feature_code":"PPL",
    "gn:name":"Suryo",
    "gn:population":0,
    "gn:timezone":"Asia/Manila",
    "iso:country":"PH",
    "name:fil_x_preferred":[
        "Suryo"
    ],
    "wof:name":"Suryo",
    "wof:placetype":"locality"
},
  "geometry": {"coordinates":[121.40928999999998,19.38383],"type":"Point"}
}