{
  "type": "Feature",
  "properties": {
    "gn:admin1_code":"01",
    "gn:admin2_code":"29",
    "gn:admin3_code":"12926000.0",
    "gn:asciiname":"Pinsal",
    "gn:country_code":"PH",
    "gn:dem":21,
    "gn:feature_class":"P",
    "gn:feature_code":"PPL",
    "gn:name":"Pinsal",
    "gn:population":0,
    "gn:timezone":"Asia/Manila",
    "iso:country":"PH",
    "name:fil_x_preferred":[
        "Pinsal"
    ],
    "wof:name":"Pinsal",
    "wof:placetype":"locality"
},
  "geometry": {"coordinates":[120.5348,17.39],"type":"Point"}
}