{
  "type": "Feature",
  "properties": {
    "gn:admin1_code":"01",
    "gn:admin2_code":"51",
    "gn:admin3_code":"15510000.0",
    "gn:asciiname":"Sinabaan",
    "gn:country_code":"PH",
    "gn:dem":21,
    "gn:feature_class":"P",
    "gn:feature_code":"PPL",
    "gn:name":"Sinabaan",
    "gn:population":0,
    "gn:timezone":"Asia/Manila",
    "iso:country":"PH",
    "name:fil_x_preferred":[
        "Sinabaan"
    ],
    "wof:name":"Sinabaan",
    "wof:placetype":"locality"
},
  "geometry": {"coordinates":[120.46210000000001,15.8157],"type":"Point"}
}