{
  "type": "Feature",
  "properties": {
    "gn:admin1_code":"14",
    "gn:admin2_code":"35",
    "gn:admin3_code":"153632000.0",
    "gn:asciiname":"Kalalanoan",
    "gn:country_code":"PH",
    "gn:dem":759,
    "gn:feature_class":"P",
    "gn:feature_code":"PPL",
    "gn:name":"Kalalanoan",
    "gn:population":0,
    "gn:timezone":"Asia/Manila",
    "iso:country":"PH",
    "name:fil_x_preferred":[
        "Kalalanoan"
    ],
    "wof:name":"Kalalanoan",
    "wof:placetype":"locality"
},
  "geometry": {"coordinates":[124.09193999999999,7.74806],"type":"Point"}
}