{
  "type": "Feature",
  "properties": {
    "gn:admin1_code":"06",
    "gn:admin2_code":"06",
    "gn:admin3_code":"60611000.0",
    "gn:asciiname":"Matat",
    "gn:country_code":"PH",
    "gn:dem":126,
    "gn:feature_class":"P",
    "gn:feature_code":"PPL",
    "gn:name":"Matat",
    "gn:population":0,
    "gn:timezone":"Asia/Manila",
    "iso:country":"PH",
    "name:fil_x_preferred":[
        "Matat"
    ],
    "wof:name":"Matat",
    "wof:placetype":"locality"
},
  "geometry": {"coordinates":[122.0039,11.7653],"type":"Point"}
}