{
  "type": "Feature",
  "properties": {
    "gn:admin1_code":"11",
    "gn:admin2_code":"I6",
    "gn:admin3_code":"118202000.0",
    "gn:asciiname":"Bulliocan",
    "gn:country_code":"PH",
    "gn:dem":149,
    "gn:feature_class":"P",
    "gn:feature_code":"PPL",
    "gn:name":"Bulliocan",
    "gn:population":0,
    "gn:timezone":"Asia/Manila",
    "iso:country":"PH",
    "name:fil_x_preferred":[
        "Bulliocan"
    ],
    "wof:name":"Bulliocan",
    "wof:placetype":"locality"
},
  "geometry": {"coordinates":[125.72333,7.84278],"type":"Point"}
}