{
  "type": "Feature",
  "properties": {
    "gn:admin1_code":"01",
    "gn:admin2_code":"51",
    "gn:admin3_code":"15514000.0",
    "gn:asciiname":"Kapas",
    "gn:country_code":"PH",
    "gn:dem":140,
    "gn:feature_class":"P",
    "gn:feature_code":"PPL",
    "gn:name":"Kapas",
    "gn:population":0,
    "gn:timezone":"Asia/Manila",
    "iso:country":"PH",
    "name:ceb_x_preferred":[
        "Kapas"
    ],
    "name:fil_x_preferred":[
        "Kapas"
    ],
    "name:hun_x_preferred":[
        "Kap\u00e1s"
    ],
    "name:nld_x_preferred":[
        "Kapas"
    ],
    "name:swe_x_preferred":[
        "Kapas"
    ],
    "wof:name":"Kapas",
    "wof:placetype":"locality"
},
  "geometry": {"coordinates":[119.7992,16.3078],"type":"Point"}
}