{
  "type": "Feature",
  "properties": {
    "gn:admin1_code":"11",
    "gn:admin2_code":"I7",
    "gn:admin3_code":"112317000.0",
    "gn:asciiname":"Tabang",
    "gn:country_code":"PH",
    "gn:dem":17,
    "gn:feature_class":"P",
    "gn:feature_code":"PPL",
    "gn:name":"Tabang",
    "gn:population":0,
    "gn:timezone":"Asia/Manila",
    "iso:country":"PH",
    "name:fil_x_preferred":[
        "Tabang"
    ],
    "name:ind_x_preferred":[
        "Tabang"
    ],
    "name:jav_x_preferred":[
        "Tabang"
    ],
    "name:msa_x_preferred":[
        "Tabang"
    ],
    "wof:name":"Tabang",
    "wof:placetype":"locality"
},
  "geometry": {"coordinates":[125.72722,7.00056],"type":"Point"}
}