{
  "type": "Feature",
  "properties": {
    "gn:admin1_code":"03",
    "gn:admin2_code":"47",
    "gn:admin3_code":"34930000.0",
    "gn:asciiname":"Picon",
    "gn:country_code":"PH",
    "gn:dem":51,
    "gn:feature_class":"P",
    "gn:feature_code":"PPL",
    "gn:name":"Picon",
    "gn:population":0,
    "gn:timezone":"Asia/Manila",
    "iso:country":"PH",
    "name:deu_x_preferred":[
        "Picon"
    ],
    "name:fra_x_preferred":[
        "Picon"
    ],
    "name:ita_x_preferred":[
        "Picon"
    ],
    "name:spa_x_preferred":[
        "Picon"
    ],
    "wof:name":"Picon",
    "wof:placetype":"locality"
},
  "geometry": {"coordinates":[120.95,15.61667],"type":"Point"}
}