{
  "type": "Feature",
  "properties": {
    "gn:admin1_code":"05",
    "gn:admin2_code":"16",
    "gn:admin3_code":"51726000.0",
    "gn:asciiname":"Tampodong",
    "gn:country_code":"PH",
    "gn:dem":17,
    "gn:feature_class":"P",
    "gn:feature_code":"PPL",
    "gn:name":"Tampodong",
    "gn:population":0,
    "gn:timezone":"Asia/Manila",
    "iso:country":"PH",
    "name:fil_x_preferred":[
        "Tampodong"
    ],
    "name:und_x_variant":[
        "Tampadong"
    ],
    "wof:name":"Tampodong",
    "wof:placetype":"locality"
},
  "geometry": {"coordinates":[123.0543,13.5711],"type":"Point"}
}