{
  "type": "Feature",
  "properties": {
    "gn:admin1_code":"10",
    "gn:admin2_code":"34",
    "gn:admin3_code":"103504000.0",
    "gn:asciiname":"Bayug",
    "gn:country_code":"PH",
    "gn:dem":4,
    "gn:feature_class":"P",
    "gn:feature_code":"PPL",
    "gn:name":"Bayug",
    "gn:population":0,
    "gn:timezone":"Asia/Manila",
    "iso:country":"PH",
    "wof:name":"Bayug",
    "wof:placetype":"locality"
},
  "geometry": {"coordinates":[124.25082999999999,8.25056],"type":"Point"}
}