{
  "type": "Feature",
  "properties": {
    "gn:admin1_code":"10",
    "gn:admin2_code":"12",
    "gn:admin3_code":"101309000.0",
    "gn:asciiname":"Kisawa",
    "gn:country_code":"PH",
    "gn:dem":241,
    "gn:feature_class":"P",
    "gn:feature_code":"PPL",
    "gn:name":"Kisawa",
    "gn:population":0,
    "gn:timezone":"Asia/Manila",
    "iso:country":"PH",
    "name:fil_x_preferred":[
        "Kisawa"
    ],
    "wof:name":"Kisawa",
    "wof:placetype":"locality"
},
  "geometry": {"coordinates":[125.12694,7.50194],"type":"Point"}
}