{
  "type": "Feature",
  "properties": {
    "gn:admin1_code":"08",
    "gn:admin2_code":"67",
    "gn:admin3_code":"84814000.0",
    "gn:asciiname":"Osmena",
    "gn:country_code":"PH",
    "gn:dem":46,
    "gn:feature_class":"P",
    "gn:feature_code":"PPL",
    "gn:name":"Osme\u00f1a",
    "gn:population":0,
    "gn:timezone":"Asia/Manila",
    "iso:country":"PH",
    "name:fil_x_preferred":[
        "Osme\u00f1a"
    ],
    "wof:name":"Osmena",
    "wof:placetype":"locality"
},
  "geometry": {"coordinates":[125.15000000000001,12.51667],"type":"Point"}
}