{
  "type": "Feature",
  "properties": {
    "gn:admin1_code":"06",
    "gn:admin2_code":"18",
    "gn:admin3_code":"61917000.0",
    "gn:asciiname":"Quinalian",
    "gn:country_code":"PH",
    "gn:dem":90,
    "gn:feature_class":"P",
    "gn:feature_code":"PPL",
    "gn:name":"Quinalian",
    "gn:population":0,
    "gn:timezone":"Asia/Manila",
    "iso:country":"PH",
    "name:fil_x_preferred":[
        "Quinalian"
    ],
    "wof:name":"Quinalian",
    "wof:placetype":"locality"
},
  "geometry": {"coordinates":[122.4914,11.2857],"type":"Point"}
}