{
  "type": "Feature",
  "properties": {
    "gn:country":"PH",
    "gn:fcode":"PPL",
    "gn:pop":3463,
    "iso:country":"PH",
    "name:fil_x_preferred":[
        "Busok"
    ],
    "qs:name":"Busok",
    "qs:photos_9r":0,
    "qs:photos_sr":0,
    "qs:pop_sr":"4",
    "wof:name":"Busok",
    "wof:placetype":"locality",
    "wof:population":3463
},
  "geometry": {"coordinates":[124.59889,6.50611],"type":"Point"}
}