{
  "type": "Feature",
  "properties": {
    "gn:admin1_code":"14",
    "gn:admin2_code":"35",
    "gn:admin3_code":"153609000.0",
    "gn:asciiname":"Gadungan",
    "gn:country_code":"PH",
    "gn:dem":851,
    "gn:feature_class":"P",
    "gn:feature_code":"PPL",
    "gn:name":"Gadungan",
    "gn:population":0,
    "gn:timezone":"Asia/Manila",
    "iso:country":"PH",
    "name:fil_x_preferred":[
        "Gadungan"
    ],
    "wof:name":"Gadungan",
    "wof:placetype":"locality"
},
  "geometry": {"coordinates":[124.08717,7.80053],"type":"Point"}
}