{
  "type": "Feature",
  "properties": {
    "gn:admin1_code":"41",
    "gn:admin2_code":"49",
    "gn:admin3_code":"175323000.0",
    "gn:asciiname":"Banua",
    "gn:country_code":"PH",
    "gn:dem":12,
    "gn:feature_class":"P",
    "gn:feature_code":"PPL",
    "gn:name":"Banua",
    "gn:population":0,
    "gn:timezone":"Asia/Manila",
    "iso:country":"PH",
    "name:eng_x_preferred":[
        "Banua"
    ],
    "wof:name":"Banua",
    "wof:placetype":"locality"
},
  "geometry": {"coordinates":[117.48350000000001,8.8383],"type":"Point"}
}