{
  "type": "Feature",
  "properties": {
    "gn:admin1_code":"07",
    "gn:admin2_code":"11",
    "gn:admin3_code":"71231000.0",
    "gn:asciiname":"Lungsoda-an",
    "gn:country_code":"PH",
    "gn:dem":15,
    "gn:feature_class":"P",
    "gn:feature_code":"PPL",
    "gn:name":"Lungsoda-an",
    "gn:population":0,
    "gn:timezone":"Asia/Manila",
    "iso:country":"PH",
    "name:fil_x_preferred":[
        "Lungsoda-an"
    ],
    "wof:name":"Lungsoda-an",
    "wof:placetype":"locality"
},
  "geometry": {"coordinates":[124.54306,9.93111],"type":"Point"}
}