{
  "type": "Feature",
  "properties": {
    "gn:admin1_code":"02",
    "gn:admin2_code":"14",
    "gn:admin3_code":"21529000.0",
    "gn:asciiname":"Tanza",
    "gn:country_code":"PH",
    "gn:dem":25,
    "gn:feature_class":"P",
    "gn:feature_code":"PPL",
    "gn:name":"Tanza",
    "gn:population":0,
    "gn:timezone":"Asia/Manila",
    "iso:country":"PH",
    "wof:name":"Tanza",
    "wof:placetype":"locality"
},
  "geometry": {"coordinates":[121.73621,17.62973999999999],"type":"Point"}
}