{
  "type": "Feature",
  "properties": {
    "gn:admin1_code":"03",
    "gn:admin2_code":"64",
    "gn:admin3_code":"37107000.0",
    "gn:asciiname":"Barretto",
    "gn:country_code":"PH",
    "gn:dem":12,
    "gn:feature_class":"P",
    "gn:feature_code":"PPL",
    "gn:name":"Barretto",
    "gn:population":0,
    "gn:timezone":"Asia/Manila",
    "iso:country":"PH",
    "name:fil_x_preferred":[
        "Barretto"
    ],
    "name:und_x_variant":[
        "Barreto"
    ],
    "wof:name":"Barretto",
    "wof:placetype":"locality"
},
  "geometry": {"coordinates":[120.26232,14.85212],"type":"Point"}
}