{
  "type": "Feature",
  "properties": {
    "gn:admin1_code":"13",
    "gn:admin2_code":"62",
    "gn:admin3_code":"166817000.0",
    "gn:asciiname":"Quezon",
    "gn:country_code":"PH",
    "gn:dem":45,
    "gn:feature_class":"P",
    "gn:feature_code":"PPL",
    "gn:name":"Quezon",
    "gn:population":0,
    "gn:timezone":"Asia/Manila",
    "iso:country":"PH",
    "name:fil_x_preferred":[
        "Quezon"
    ],
    "wof:name":"Quezon",
    "wof:placetype":"locality"
},
  "geometry": {"coordinates":[126.14111,8.49417],"type":"Point"}
}