{
  "type": "Feature",
  "properties": {
    "gn:country":"PH",
    "gn:fcode":"PPL",
    "gn:pop":2200,
    "iso:country":"PH",
    "qs:name":"Talisay",
    "qs:photos_9r":0,
    "qs:photos_sr":0,
    "qs:pop_sr":"4",
    "wd:wordcount":30,
    "wof:name":"Talisay",
    "wof:placetype":"locality",
    "wof:population":2200
},
  "geometry": {"coordinates":[125.61556,9.81889],"type":"Point"}
}