{
  "type": "Feature",
  "properties": {
    "gn:admin1_code":"06",
    "gn:admin2_code":"18",
    "gn:admin3_code":"61915000.0",
    "gn:asciiname":"Mamang-Mambusao School",
    "gn:country_code":"PH",
    "gn:dem":2,
    "gn:feature_class":"P",
    "gn:feature_code":"PPL",
    "gn:name":"Mamang-Mambusao School",
    "gn:population":0,
    "gn:timezone":"Asia/Manila",
    "iso:country":"PH",
    "name:fil_x_preferred":[
        "Mamang-Mambusao School"
    ],
    "wof:name":"Mamang-Mambusao School",
    "wof:placetype":"locality"
},
  "geometry": {"coordinates":[122.58068,11.48404],"type":"Point"}
}