{
  "type": "Feature",
  "properties": {
    "gn:admin1_code":"07",
    "gn:admin2_code":"11",
    "gn:admin3_code":"71224000.0",
    "gn:asciiname":"Baogo",
    "gn:country_code":"PH",
    "gn:dem":23,
    "gn:feature_class":"P",
    "gn:feature_code":"PPL",
    "gn:name":"Baogo",
    "gn:population":0,
    "gn:timezone":"Asia/Manila",
    "iso:country":"PH",
    "name:fil_x_preferred":[
        "Baogo"
    ],
    "wof:name":"Baogo",
    "wof:placetype":"locality"
},
  "geometry": {"coordinates":[124.1153,10.03268],"type":"Point"}
}