{
  "type": "Feature",
  "properties": {
    "gn:admin1_code":"07",
    "gn:admin2_code":"46",
    "gn:admin3_code":"74624000.0",
    "gn:asciiname":"Olay",
    "gn:country_code":"PH",
    "gn:dem":65,
    "gn:feature_class":"P",
    "gn:feature_code":"PPL",
    "gn:name":"Olay",
    "gn:population":0,
    "gn:timezone":"Asia/Manila",
    "iso:country":"PH",
    "name:fil_x_preferred":[
        "Olay"
    ],
    "wof:name":"Olay",
    "wof:placetype":"locality"
},
  "geometry": {"coordinates":[123.2993,10.35907],"type":"Point"}
}