{
  "type": "Feature",
  "properties": {
    "gn:admin1_code":"02",
    "gn:admin2_code":"31",
    "gn:admin3_code":"23126000.0",
    "gn:asciiname":"Anao",
    "gn:country_code":"PH",
    "gn:dem":55,
    "gn:feature_class":"P",
    "gn:feature_code":"PPL",
    "gn:name":"Anao",
    "gn:population":0,
    "gn:timezone":"Asia/Manila",
    "iso:country":"PH",
    "name:fil_x_preferred":[
        "Anao"
    ],
    "wof:name":"Anao",
    "wof:placetype":"locality"
},
  "geometry": {"coordinates":[121.64144,17.13174],"type":"Point"}
}