{
  "type": "Feature",
  "properties": {
    "gn:admin1_code":"06",
    "gn:admin2_code":"30",
    "gn:admin3_code":"63027000.0",
    "gn:asciiname":"Yawyawan",
    "gn:country_code":"PH",
    "gn:dem":115,
    "gn:feature_class":"P",
    "gn:feature_code":"PPL",
    "gn:name":"Yawyawan",
    "gn:population":0,
    "gn:timezone":"Asia/Manila",
    "iso:country":"PH",
    "name:fil_x_preferred":[
        "Yawyawan"
    ],
    "wof:name":"Yawyawan",
    "wof:placetype":"locality"
},
  "geometry": {"coordinates":[122.8942,11.2753],"type":"Point"}
}