{
  "type": "Feature",
  "properties": {
    "gn:country":"PH",
    "gn:fcode":"PPLA3",
    "gn:population":14395,
    "iso:country":"PH",
    "name:bcl_x_preferred":[
        "Oton"
    ],
    "name:ceb_x_preferred":[
        "Oton"
    ],
    "name:deu_x_preferred":[
        "Oton"
    ],
    "name:eng_x_preferred":[
        "Oton"
    ],
    "name:fra_x_preferred":[
        "Oton"
    ],
    "name:ilo_x_preferred":[
        "Oton"
    ],
    "name:ind_x_preferred":[
        "Oton"
    ],
    "name:ita_x_preferred":[
        "Oton"
    ],
    "name:jpn_x_preferred":[
        "\u30aa\u30c8\u30f3"
    ],
    "name:nld_x_preferred":[
        "Oton"
    ],
    "name:pag_x_preferred":[
        "Oton"
    ],
    "name:pam_x_preferred":[
        "Oton"
    ],
    "name:spa_x_preferred":[
        "Oton"
    ],
    "name:swe_x_preferred":[
        "Oton"
    ],
    "name:tgl_x_preferred":[
        "Oton"
    ],
    "name:und_x_variant":[
        "Oton Town"
    ],
    "name:vie_x_preferred":[
        "Oton"
    ],
    "name:war_x_preferred":[
        "Oton"
    ],
    "qs:name":"Oton",
    "qs:photos_9r":0,
    "qs:photos_sr":0,
    "qs:pop_sr":"6",
    "wof:name":"Oton",
    "wof:placetype":"locality",
    "wof:population":14395
},
  "geometry": {"coordinates":[122.47360999999999,10.69306],"type":"Point"}
}