{
  "type": "Feature",
  "properties": {
    "gn:admin1_code":"05",
    "gn:admin2_code":"39",
    "gn:admin3_code":"54114000.0",
    "gn:asciiname":"Dobdob",
    "gn:country_code":"PH",
    "gn:dem":62,
    "gn:feature_class":"P",
    "gn:feature_code":"PPL",
    "gn:name":"Dobdob",
    "gn:population":0,
    "gn:timezone":"Asia/Manila",
    "iso:country":"PH",
    "name:fil_x_preferred":[
        "Dobdob"
    ],
    "name:und_x_variant":[
        "Dabdob",
        "Dobdob",
        "Dobdoh"
    ],
    "wof:name":"Dobdob",
    "wof:placetype":"locality"
},
  "geometry": {"coordinates":[123.6777,12.6078],"type":"Point"}
}