{
  "type": "Feature",
  "properties": {
    "gn:admin1_code":"15",
    "gn:admin2_code":"H6",
    "gn:admin3_code":"148107000.0",
    "gn:asciiname":"Barocboc",
    "gn:country_code":"PH",
    "gn:dem":13,
    "gn:feature_class":"P",
    "gn:feature_code":"PPL",
    "gn:name":"Barocboc",
    "gn:population":0,
    "gn:timezone":"Asia/Manila",
    "iso:country":"PH",
    "name:fil_x_preferred":[
        "Barucbuc"
    ],
    "wof:name":"Barocboc",
    "wof:placetype":"locality"
},
  "geometry": {"coordinates":[121.42542,18.2951],"type":"Point"}
}