{
  "type": "Feature",
  "properties": {
    "gn:country":"PH",
    "gn:fcode":"PPL",
    "gn:pop":2563,
    "iso:country":"PH",
    "name:ceb_x_preferred":[
        "Sabang"
    ],
    "name:fil_x_preferred":[
        "Sabang"
    ],
    "name:fra_x_preferred":[
        "Sabang"
    ],
    "name:swe_x_preferred":[
        "Sabang"
    ],
    "qs:name":"Sabang",
    "qs:photos_9r":0,
    "qs:photos_sr":0,
    "qs:pop_sr":"4",
    "wd:wordcount":86,
    "wof:name":"Sabang",
    "wof:placetype":"locality",
    "wof:population":2563
},
  "geometry": {"coordinates":[120.71111000000001,14.06333],"type":"Point"}
}