{
  "type": "Feature",
  "properties": {
    "gn:admin1_code":"40",
    "gn:admin2_code":"09",
    "gn:admin3_code":"41019000.0",
    "gn:asciiname":"Sabang",
    "gn:country":"PH",
    "gn:country_code":"PH",
    "gn:dem":47,
    "gn:fcode":"PPL",
    "gn:feature_class":"P",
    "gn:feature_code":"PPL",
    "gn:name":"Sabang",
    "gn:population":2563,
    "gn:timezone":"Asia/Manila",
    "iso:country":"PH",
    "name:ceb_x_preferred":[
        "Sabang"
    ],
    "name:fil_x_preferred":[
        "Sabang"
    ],
    "name:fra_x_preferred":[
        "Sabang"
    ],
    "name:swe_x_preferred":[
        "Sabang"
    ],
    "qs:name":"Sabang",
    "qs:photos_9r":0,
    "qs:photos_sr":0,
    "qs:pop_sr":"4",
    "wd:wordcount":86,
    "wof:name":"Sabang",
    "wof:placetype":"locality",
    "wof:population":2563
},
  "geometry": {"coordinates":[120.71111000000001,14.06333],"type":"Point"}
}