{
  "type": "Feature",
  "properties": {
    "gn:country":"PH",
    "gn:fcode":"PPL",
    "gn:pop":3503,
    "iso:country":"PH",
    "name:fil_x_preferred":[
        "Dicabisagan"
    ],
    "name:fil_x_variant":[
        "Dicaoisagan"
    ],
    "name:unk_x_variant":[
        "Dicaoisagan"
    ],
    "qs:name":"Dicabisagan",
    "qs:photos_9r":0,
    "qs:photos_sr":0,
    "qs:pop_sr":"4",
    "wof:name":"Dicabisagan",
    "wof:placetype":"locality",
    "wof:population":3503
},
  "geometry": {"coordinates":[122.41574,17.08184],"type":"Point"}
}