{
  "type": "Feature",
  "properties": {
    "gn:admin1_code":"14",
    "gn:admin2_code":"35",
    "gn:admin3_code":"153621000.0",
    "gn:asciiname":"Sapingit",
    "gn:country_code":"PH",
    "gn:dem":704,
    "gn:feature_class":"P",
    "gn:feature_code":"PPL",
    "gn:name":"Sapingit",
    "gn:population":0,
    "gn:timezone":"Asia/Manila",
    "iso:country":"PH",
    "name:fil_x_preferred":[
        "Sapingit"
    ],
    "wof:name":"Sapingit",
    "wof:placetype":"locality"
},
  "geometry": {"coordinates":[124.23333,8.01667],"type":"Point"}
}