{
  "type": "Feature",
  "properties": {
    "gn:admin1_code":"40",
    "gn:admin2_code":"09",
    "gn:admin3_code":"41010000.0",
    "gn:asciiname":"Catandala",
    "gn:country_code":"PH",
    "gn:dem":104,
    "gn:feature_class":"P",
    "gn:feature_code":"PPL",
    "gn:name":"Catandala",
    "gn:population":0,
    "gn:timezone":"Asia/Manila",
    "iso:country":"PH",
    "name:fil_x_preferred":[
        "Catandala"
    ],
    "wof:name":"Catandala",
    "wof:placetype":"locality"
},
  "geometry": {"coordinates":[121.1521,13.7865],"type":"Point"}
}