{
  "type": "Feature",
  "properties": {
    "gn:admin1_code":"03",
    "gn:admin2_code":"63",
    "gn:admin3_code":"36914000.0",
    "gn:asciiname":"San Manuel",
    "gn:country_code":"PH",
    "gn:dem":27,
    "gn:feature_class":"P",
    "gn:feature_code":"PPLA3",
    "gn:name":"San Manuel",
    "gn:population":0,
    "gn:timezone":"Asia/Manila",
    "iso:country":"PH",
    "name:bcl_x_preferred":[
        "San Manuel"
    ],
    "name:ceb_x_preferred":[
        "San Manuel"
    ],
    "name:deu_x_preferred":[
        "San Manuel"
    ],
    "name:fra_x_preferred":[
        "San Manuel"
    ],
    "name:ilo_x_preferred":[
        "San Manuel"
    ],
    "name:ind_x_preferred":[
        "San Manuel"
    ],
    "name:ita_x_preferred":[
        "San Manuel"
    ],
    "name:nld_x_preferred":[
        "San Manuel"
    ],
    "name:pag_x_preferred":[
        "San Manuel"
    ],
    "name:pam_x_preferred":[
        "San Manuel"
    ],
    "name:spa_x_preferred":[
        "San Manuel"
    ],
    "name:swe_x_preferred":[
        "San Manuel"
    ],
    "name:tgl_x_preferred":[
        "San Manuel"
    ],
    "name:vie_x_preferred":[
        "San Manuel"
    ],
    "name:war_x_preferred":[
        "San Manuel"
    ],
    "wof:name":"San Manuel",
    "wof:placetype":"locality"
},
  "geometry": {"coordinates":[120.60861,15.79917],"type":"Point"}
}