{
  "type": "Feature",
  "properties": {
    "gn:admin1_code":"15",
    "gn:admin2_code":"10",
    "gn:admin3_code":"141104000.0",
    "gn:asciiname":"Inticak",
    "gn:country_code":"PH",
    "gn:dem":1311,
    "gn:feature_class":"P",
    "gn:feature_code":"PPL",
    "gn:name":"Inticak",
    "gn:population":0,
    "gn:timezone":"Asia/Manila",
    "iso:country":"PH",
    "name:fil_x_preferred":[
        "Inticak"
    ],
    "wof:name":"Inticak",
    "wof:placetype":"locality"
},
  "geometry": {"coordinates":[120.81667,16.48333],"type":"Point"}
}