{
  "type": "Feature",
  "properties": {
    "gn:admin1_code":"41",
    "gn:admin2_code":"41",
    "gn:admin3_code":"175208000.0",
    "gn:asciiname":"Papanguil",
    "gn:country_code":"PH",
    "gn:dem":11,
    "gn:feature_class":"P",
    "gn:feature_code":"PPL",
    "gn:name":"Papanguil",
    "gn:population":0,
    "gn:timezone":"Asia/Manila",
    "iso:country":"PH",
    "name:eng_x_preferred":[
        "Papanguil"
    ],
    "wof:name":"Papanguil",
    "wof:placetype":"locality"
},
  "geometry": {"coordinates":[121.37032000000001,13.25739],"type":"Point"}
}