{
  "type": "Feature",
  "properties": {
    "gn:admin1_code":"07",
    "gn:admin2_code":"46",
    "gn:admin3_code":"74606000.0",
    "gn:asciiname":"Boliboli",
    "gn:country_code":"PH",
    "gn:dem":54,
    "gn:feature_class":"P",
    "gn:feature_code":"PPL",
    "gn:name":"Boliboli",
    "gn:population":0,
    "gn:timezone":"Asia/Manila",
    "iso:country":"PH",
    "name:fil_x_preferred":[
        "Boliboli"
    ],
    "wof:name":"Boliboli",
    "wof:placetype":"locality"
},
  "geometry": {"coordinates":[122.794,9.3906],"type":"Point"}
}