{
  "type": "Feature",
  "properties": {
    "gn:admin1_code":"07",
    "gn:admin2_code":"11",
    "gn:admin3_code":"71230000.0",
    "gn:asciiname":"Cabacongan",
    "gn:country_code":"PH",
    "gn:dem":153,
    "gn:feature_class":"P",
    "gn:feature_code":"PPL",
    "gn:name":"Cabacongan",
    "gn:population":0,
    "gn:timezone":"Asia/Manila",
    "iso:country":"PH",
    "name:fil_x_preferred":[
        "Cabacongan"
    ],
    "wof:name":"Cabacongan",
    "wof:placetype":"locality"
},
  "geometry": {"coordinates":[123.83333,9.83333],"type":"Point"}
}