{
  "type": "Feature",
  "properties": {
    "gn:admin1_code":"01",
    "gn:admin2_code":"51",
    "gn:admin3_code":"15532000.0",
    "gn:asciiname":"Baldog",
    "gn:country_code":"PH",
    "gn:dem":8,
    "gn:feature_class":"P",
    "gn:feature_code":"PPL",
    "gn:name":"Baldog",
    "gn:population":0,
    "gn:timezone":"Asia/Manila",
    "iso:country":"PH",
    "name:fil_x_preferred":[
        "Baldog"
    ],
    "wof:name":"Baldog",
    "wof:placetype":"locality"
},
  "geometry": {"coordinates":[120.32971999999999,15.95722],"type":"Point"}
}