{
  "type": "Feature",
  "properties": {
    "gn:admin1_code":"14",
    "gn:admin2_code":"56",
    "gn:admin3_code":"153824000.0",
    "gn:asciiname":"Tarikan",
    "gn:country_code":"PH",
    "gn:dem":12,
    "gn:feature_class":"P",
    "gn:feature_code":"PPL",
    "gn:name":"Tarikan",
    "gn:population":0,
    "gn:timezone":"Asia/Manila",
    "iso:country":"PH",
    "wof:name":"Tarikan",
    "wof:placetype":"locality"
},
  "geometry": {"coordinates":[124.22806,7.30528],"type":"Point"}
}