{
  "type": "Feature",
  "properties": {
    "gn:admin1_code":"14",
    "gn:admin2_code":"56",
    "gn:admin3_code":"153814000.0",
    "gn:asciiname":"Liong",
    "gn:country_code":"PH",
    "gn:dem":4,
    "gn:feature_class":"P",
    "gn:feature_code":"PPL",
    "gn:name":"Liong",
    "gn:population":0,
    "gn:timezone":"Asia/Manila",
    "iso:country":"PH",
    "name:fil_x_preferred":[
        "Liong"
    ],
    "wof:name":"Liong",
    "wof:placetype":"locality"
},
  "geometry": {"coordinates":[124.39,7.10944],"type":"Point"}
}