{
  "type": "Feature",
  "properties": {
    "gn:admin1_code":"01",
    "gn:admin2_code":"29",
    "gn:admin3_code":"12921000.0",
    "gn:asciiname":"Pudoc Sur",
    "gn:country_code":"PH",
    "gn:dem":9,
    "gn:feature_class":"P",
    "gn:feature_code":"PPL",
    "gn:name":"Pudoc Sur",
    "gn:population":0,
    "gn:timezone":"Asia/Manila",
    "iso:country":"PH",
    "name:fil_x_preferred":[
        "Pudoc Sur"
    ],
    "wof:name":"Pudoc Sur",
    "wof:placetype":"locality"
},
  "geometry": {"coordinates":[120.3673,17.60506],"type":"Point"}
}