{
  "type": "Feature",
  "properties": {
    "gn:admin1_code":"01",
    "gn:admin2_code":"28",
    "gn:admin3_code":"12802000.0",
    "gn:asciiname":"Pasiocan",
    "gn:country_code":"PH",
    "gn:dem":15,
    "gn:feature_class":"P",
    "gn:feature_code":"PPL",
    "gn:name":"Pasiocan",
    "gn:population":0,
    "gn:timezone":"Asia/Manila",
    "iso:country":"PH",
    "name:fil_x_preferred":[
        "Pasiocan"
    ],
    "wof:name":"Pasiocan",
    "wof:placetype":"locality"
},
  "geometry": {"coordinates":[120.60599999999999,18.2364],"type":"Point"}
}