{
  "type": "Feature",
  "properties": {
    "gn:admin1_code":"01",
    "gn:admin2_code":"51",
    "gn:admin3_code":"15511000.0",
    "gn:asciiname":"Tambac",
    "gn:country_code":"PH",
    "gn:dem":22,
    "gn:feature_class":"P",
    "gn:feature_code":"PPL",
    "gn:name":"Tambac",
    "gn:population":0,
    "gn:timezone":"Asia/Manila",
    "iso:country":"PH",
    "name:fil_x_preferred":[
        "Tambac"
    ],
    "wof:name":"Tambac",
    "wof:placetype":"locality"
},
  "geometry": {"coordinates":[120.4573,15.82158],"type":"Point"}
}