{
  "type": "Feature",
  "properties": {
    "gn:admin1_code":"12",
    "gn:admin2_code":"71",
    "gn:admin3_code":"126503000.0",
    "gn:asciiname":"Banaga",
    "gn:country_code":"PH",
    "gn:dem":47,
    "gn:feature_class":"P",
    "gn:feature_code":"PPLL",
    "gn:name":"Banaga",
    "gn:population":0,
    "gn:timezone":"Asia/Manila",
    "iso:country":"PH",
    "name:fil_x_preferred":[
        "Banaga"
    ],
    "wof:name":"Banaga",
    "wof:placetype":"locality"
},
  "geometry": {"coordinates":[124.56528,6.71778],"type":"Point"}
}