{
  "type": "Feature",
  "properties": {
    "gn:admin1_code":"08",
    "gn:admin2_code":"37",
    "gn:admin3_code":"83740000.0",
    "gn:asciiname":"Duljugan",
    "gn:country_code":"PH",
    "gn:dem":4,
    "gn:feature_class":"P",
    "gn:feature_code":"PPL",
    "gn:name":"Duljugan",
    "gn:population":0,
    "gn:timezone":"Asia/Manila",
    "iso:country":"PH",
    "name:fil_x_preferred":[
        "Duljugan"
    ],
    "name:und_x_variant":[
        "Duliugan"
    ],
    "wof:name":"Duljugan",
    "wof:placetype":"locality"
},
  "geometry": {"coordinates":[124.3852,10.9164],"type":"Point"}
}