{
  "type": "Feature",
  "properties": {
    "gn:admin1_code":"07",
    "gn:admin2_code":"11",
    "gn:admin3_code":"71212000.0",
    "gn:asciiname":"La Salvacion",
    "gn:country_code":"PH",
    "gn:dem":311,
    "gn:feature_class":"P",
    "gn:feature_code":"PPL",
    "gn:name":"La Salvacion",
    "gn:population":0,
    "gn:timezone":"Asia/Manila",
    "iso:country":"PH",
    "name:fil_x_preferred":[
        "La Salvacion"
    ],
    "wof:name":"La Salvacion",
    "wof:placetype":"locality"
},
  "geometry": {"coordinates":[124.2103,9.7818],"type":"Point"}
}