{
  "type": "Feature",
  "properties": {
    "gn:admin1_code":"01",
    "gn:admin2_code":"51",
    "gn:admin3_code":"15522000.0",
    "gn:asciiname":"Talogtog",
    "gn:country_code":"PH",
    "gn:dem":6,
    "gn:feature_class":"P",
    "gn:feature_code":"PPL",
    "gn:name":"Talogtog",
    "gn:population":0,
    "gn:timezone":"Asia/Manila",
    "iso:country":"PH",
    "name:fil_x_preferred":[
        "Talogtog"
    ],
    "wof:name":"Talogtog",
    "wof:placetype":"locality"
},
  "geometry": {"coordinates":[120.23884,16.00092],"type":"Point"}
}