{
  "type": "Feature",
  "properties": {
    "gn:admin1_code":"40",
    "gn:admin2_code":"33",
    "gn:admin3_code":"43401000.0",
    "gn:asciiname":"San Ildefonso",
    "gn:country_code":"PH",
    "gn:dem":245,
    "gn:feature_class":"P",
    "gn:feature_code":"PPL",
    "gn:name":"San Ildefonso",
    "gn:population":0,
    "gn:timezone":"Asia/Manila",
    "iso:country":"PH",
    "name:fil_x_preferred":[
        "San Ildefonso"
    ],
    "wof:name":"San Ildefonso",
    "wof:placetype":"locality"
},
  "geometry": {"coordinates":[121.21861,14.04528],"type":"Point"}
}