{
  "type": "Feature",
  "properties": {
    "gn:admin1_code":"15",
    "gn:admin2_code":"01",
    "gn:admin3_code":"140106000.0",
    "gn:asciiname":"Bilbila",
    "gn:country_code":"PH",
    "gn:dem":81,
    "gn:feature_class":"P",
    "gn:feature_code":"PPL",
    "gn:name":"Bilbila",
    "gn:population":0,
    "gn:timezone":"Asia/Manila",
    "iso:country":"PH",
    "name:fil_x_preferred":[
        "Bilbila"
    ],
    "wof:name":"Bilbila",
    "wof:placetype":"locality"
},
  "geometry": {"coordinates":[120.6674,17.6843],"type":"Point"}
}