{
  "type": "Feature",
  "properties": {
    "gn:admin1_code":"09",
    "gn:admin2_code":"ZSI",
    "gn:admin3_code":"98305000.0",
    "gn:asciiname":"Caparan",
    "gn:country_code":"PH",
    "gn:dem":11,
    "gn:feature_class":"P",
    "gn:feature_code":"PPL",
    "gn:name":"Caparan",
    "gn:population":0,
    "gn:timezone":"Asia/Manila",
    "iso:country":"PH",
    "name:fil_x_preferred":[
        "Caparan"
    ],
    "wof:name":"Caparan",
    "wof:placetype":"locality"
},
  "geometry": {"coordinates":[122.5472,7.74518],"type":"Point"}
}