{
  "type": "Feature",
  "properties": {
    "gn:admin1_code":"05",
    "gn:admin2_code":"39",
    "gn:admin3_code":"54114000.0",
    "gn:asciiname":"Lenabungan",
    "gn:country_code":"PH",
    "gn:dem":4,
    "gn:feature_class":"P",
    "gn:feature_code":"PPL",
    "gn:name":"Lenabungan",
    "gn:population":0,
    "gn:timezone":"Asia/Manila",
    "iso:country":"PH",
    "name:fil_x_preferred":[
        "Lenabungan"
    ],
    "wof:name":"Lenabungan",
    "wof:placetype":"locality"
},
  "geometry": {"coordinates":[123.655,12.6484],"type":"Point"}
}