{
  "type": "Feature",
  "properties": {
    "gn:admin1_code":"02",
    "gn:admin2_code":"48",
    "gn:admin3_code":"25008000.0",
    "gn:asciiname":"I-iyo",
    "gn:country_code":"PH",
    "gn:dem":387,
    "gn:feature_class":"P",
    "gn:feature_code":"PPL",
    "gn:name":"I-iyo",
    "gn:population":0,
    "gn:timezone":"Asia/Manila",
    "iso:country":"PH",
    "name:fil_x_preferred":[
        "I-iyo"
    ],
    "wof:name":"I-iyo",
    "wof:placetype":"locality"
},
  "geometry": {"coordinates":[121.10556,16.26806],"type":"Point"}
}