{
  "type": "Feature",
  "properties": {
    "iso:country":"PH",
    "name:ace_x_preferred":[
        "Propinsi Biliran"
    ],
    "name:ara_x_preferred":[
        "\u0628\u064a\u0644\u064a\u0631\u0627\u0646"
    ],
    "name:bcl_x_preferred":[
        "Biliran"
    ],
    "name:dut_x_preferred":[
        "Biliran"
    ],
    "name:eng_x_preferred":[
        "Biliran"
    ],
    "name:epo_x_preferred":[
        "Bilirano"
    ],
    "name:fas_x_preferred":[
        "\u0628\u06cc\u0644\u06cc\u0631\u0627\u0646"
    ],
    "name:fre_x_preferred":[
        "Biliran"
    ],
    "name:ger_x_preferred":[
        "Biliran"
    ],
    "name:ilo_x_preferred":[
        "Biliran"
    ],
    "name:ind_x_preferred":[
        "Biliran"
    ],
    "name:ita_x_preferred":[
        "Provincia di Biliran"
    ],
    "name:jpn_x_preferred":[
        "\u30d3\u30ea\u30e9\u30f3\u5dde"
    ],
    "name:kor_x_preferred":[
        "\ube4c\ub9ac\ub780 \uc8fc"
    ],
    "name:mkd_x_preferred":[
        "\u0411\u0438\u043b\u0438\u0440\u0430\u043d"
    ],
    "name:pag_x_preferred":[
        "Biliran"
    ],
    "name:pam_x_preferred":[
        "Biliran"
    ],
    "name:per_x_preferred":[
        "\u0628\u06cc\u0644\u06cc\u0631\u0627\u0646\u060c \u0628\u06cc\u0644\u06cc\u0631\u0627\u0646"
    ],
    "name:rus_x_preferred":[
        "\u0411\u0438\u043b\u0438\u0440\u0430\u043d"
    ],
    "name:spa_x_preferred":[
        "Provincia de Bilir\u00e1n"
    ],
    "name:swe_x_preferred":[
        "Biliran"
    ],
    "name:tgl_x_preferred":[
        "Biliran"
    ],
    "name:urd_x_preferred":[
        "\u0628\u06cc\u0644\u06cc\u0631\u0627\u0646"
    ],
    "name:vie_x_preferred":[
        "Biliran"
    ],
    "name:war_x_preferred":[
        "Biliran"
    ],
    "name:zho_x_preferred":[
        "\u6bd4\u5229\u5170\u7701"
    ],
    "qs:gn_country":"PH",
    "qs:gn_fcode":"PPLA3",
    "qs:gn_pop":4699,
    "qs:name":"Biliran",
    "qs:name_adm0":"Philippines",
    "qs:name_adm1":"Eastern Visayas",
    "qs:photos":0,
    "qs:photos_1k":0,
    "qs:photos_9k":1,
    "qs:photos_9r":1,
    "qs:photos_all":3,
    "qs:photos_sr":0,
    "qs:placetype":"Town",
    "qs:pop_sr":"4",
    "qs:woe_adm0":23424934,
    "wof:name":"Biliran",
    "wof:placetype":"locality",
    "wof:population":4699
},
  "geometry": {"coordinates":[124.47528,11.46667],"type":"Point"}
}