{
  "type": "Feature",
  "properties": {
    "gn:admin1_code":"14",
    "gn:admin2_code":"60",
    "gn:admin3_code":"156609000.0",
    "gn:asciiname":"Kampo Naga",
    "gn:country_code":"PH",
    "gn:dem":47,
    "gn:feature_class":"P",
    "gn:feature_code":"PPL",
    "gn:name":"Kampo Naga",
    "gn:population":0,
    "gn:timezone":"Asia/Manila",
    "iso:country":"PH",
    "name:eng_x_preferred":[
        "Kampo Naga"
    ],
    "name:und_x_variant":[
        "Piahan",
        "Alu"
    ],
    "wof:name":"Kampo Naga",
    "wof:placetype":"locality"
},
  "geometry": {"coordinates":[120.8984,5.9568],"type":"Point"}
}