{
  "type": "Feature",
  "properties": {
    "gn:admin1_code":"03",
    "gn:admin2_code":"47",
    "gn:admin3_code":"34917000.0",
    "gn:asciiname":"Bantug",
    "gn:country_code":"PH",
    "gn:dem":72,
    "gn:feature_class":"P",
    "gn:feature_code":"PPL",
    "gn:name":"Bantug",
    "gn:population":0,
    "gn:timezone":"Asia/Manila",
    "iso:country":"PH",
    "name:fil_x_preferred":[
        "Bantug"
    ],
    "wof:name":"Bantug",
    "wof:placetype":"locality"
},
  "geometry": {"coordinates":[120.9181,15.7183],"type":"Point"}
}