{
  "type": "Feature",
  "properties": {
    "iso:country":"PH",
    "name:bcl_x_preferred":[
        "Rizal"
    ],
    "name:cat_x_preferred":[
        "Rizal"
    ],
    "name:cbk_zam_x_preferred":[
        "Rizal"
    ],
    "name:ceb_x_preferred":[
        "Rizal"
    ],
    "name:deu_x_preferred":[
        "Rizal"
    ],
    "name:eng_x_preferred":[
        "Rizal"
    ],
    "name:fil_x_preferred":[
        "Rizal"
    ],
    "name:fra_x_preferred":[
        "Rizal"
    ],
    "name:ilo_x_preferred":[
        "Rizal"
    ],
    "name:ind_x_preferred":[
        "Rizal"
    ],
    "name:ita_x_preferred":[
        "Rizal"
    ],
    "name:jpn_x_preferred":[
        "\u30ea\u30b5\u30fc\u30eb"
    ],
    "name:nld_x_preferred":[
        "Rizal"
    ],
    "name:oci_x_preferred":[
        "Rizal"
    ],
    "name:pag_x_preferred":[
        "Rizal"
    ],
    "name:pam_x_preferred":[
        "Rizal"
    ],
    "name:tgl_x_preferred":[
        "Rizal"
    ],
    "name:vie_x_preferred":[
        "Rizal"
    ],
    "name:war_x_preferred":[
        "Rizal"
    ],
    "qs:gn_country":"PH",
    "qs:gn_fcode":"PPLA3",
    "qs:gn_pop":4959,
    "qs:name":"Rizal",
    "qs:name_adm0":"Philippines",
    "qs:name_adm1":"Calabarzon",
    "qs:photos":20,
    "qs:photos_1k":4,
    "qs:photos_9k":1,
    "qs:photos_9r":1,
    "qs:photos_all":20,
    "qs:photos_sr":1,
    "qs:placetype":"Town",
    "qs:pop_sr":"4",
    "qs:woe_adm0":23424934,
    "wd:wordcount":772,
    "wof:name":"Rizal",
    "wof:placetype":"locality",
    "wof:population":4959
},
  "geometry": {"coordinates":[121.3913,14.1095],"type":"Point"}
}