{
  "type": "Feature",
  "properties": {
    "gn:admin1_code":"03",
    "gn:admin2_code":"47",
    "gn:admin3_code":"34922000.0",
    "gn:asciiname":"Santo Tomas Feria",
    "gn:country_code":"PH",
    "gn:dem":33,
    "gn:feature_class":"P",
    "gn:feature_code":"PPL",
    "gn:name":"Santo Tomas Feria",
    "gn:population":0,
    "gn:timezone":"Asia/Manila",
    "iso:country":"PH",
    "name:fil_x_preferred":[
        "Santo Tomas Feria"
    ],
    "wof:name":"Santo Tomas Feria",
    "wof:placetype":"locality"
},
  "geometry": {"coordinates":[120.83459999999999,15.5655],"type":"Point"}
}