{
  "type": "Feature",
  "properties": {
    "gn:admin1_code":"08",
    "gn:admin2_code":"59",
    "gn:admin3_code":"86407000.0",
    "gn:asciiname":"Nati",
    "gn:country_code":"PH",
    "gn:dem":382,
    "gn:feature_class":"P",
    "gn:feature_code":"PPL",
    "gn:name":"Nati",
    "gn:population":0,
    "gn:timezone":"Asia/Manila",
    "iso:country":"PH",
    "name:ceb_x_preferred":[
        "Nati"
    ],
    "name:deu_x_preferred":[
        "Nati"
    ],
    "name:fil_x_preferred":[
        "Nati"
    ],
    "name:fra_x_preferred":[
        "Nati"
    ],
    "name:swe_x_preferred":[
        "Nati"
    ],
    "wof:name":"Nati",
    "wof:placetype":"locality"
},
  "geometry": {"coordinates":[124.89536,10.21571],"type":"Point"}
}