{
  "type": "Feature",
  "properties": {
    "gn:admin1_code":"08",
    "gn:admin2_code":"37",
    "gn:admin3_code":"83706000.0",
    "gn:asciiname":"Balud",
    "gn:country_code":"PH",
    "gn:dem":7,
    "gn:feature_class":"P",
    "gn:feature_code":"PPL",
    "gn:name":"Balud",
    "gn:population":0,
    "gn:timezone":"Asia/Manila",
    "iso:country":"PH",
    "name:fil_x_preferred":[
        "Balud"
    ],
    "wof:name":"Balud",
    "wof:placetype":"locality"
},
  "geometry": {"coordinates":[124.7675,11.32694],"type":"Point"}
}