{
  "type": "Feature",
  "properties": {
    "gn:admin1_code":"13",
    "gn:admin2_code":"62",
    "gn:admin3_code":"166808000.0",
    "gn:asciiname":"Apuang",
    "gn:country_code":"PH",
    "gn:dem":27,
    "gn:feature_class":"P",
    "gn:feature_code":"PPL",
    "gn:name":"Apuang",
    "gn:population":0,
    "gn:timezone":"Asia/Manila",
    "iso:country":"PH",
    "name:fil_x_preferred":[
        "Apuang"
    ],
    "wof:name":"Apuang",
    "wof:placetype":"locality"
},
  "geometry": {"coordinates":[126.17055999999999,9.25778],"type":"Point"}
}