{
  "type": "Feature",
  "properties": {
    "gn:admin1_code":"08",
    "gn:admin2_code":"67",
    "gn:admin3_code":"84808000.0",
    "gn:asciiname":"Sibonot",
    "gn:country_code":"PH",
    "gn:dem":19,
    "gn:feature_class":"P",
    "gn:feature_code":"PPL",
    "gn:name":"Sibonot",
    "gn:population":0,
    "gn:timezone":"Asia/Manila",
    "iso:country":"PH",
    "name:fil_x_preferred":[
        "Sibonot"
    ],
    "wof:name":"Sibonot",
    "wof:placetype":"locality"
},
  "geometry": {"coordinates":[124.97972,12.47111],"type":"Point"}
}