{
  "type": "Feature",
  "properties": {
    "gn:admin1_code":"09",
    "gn:admin2_code":"ZSI",
    "gn:admin3_code":"98301000.0",
    "gn:asciiname":"Kauswagan",
    "gn:country_code":"PH",
    "gn:dem":220,
    "gn:feature_class":"P",
    "gn:feature_code":"PPL",
    "gn:name":"Kauswagan",
    "gn:population":0,
    "gn:timezone":"Asia/Manila",
    "iso:country":"PH",
    "name:fil_x_preferred":[
        "Kauswagan"
    ],
    "wof:name":"Kauswagan",
    "wof:placetype":"locality"
},
  "geometry": {"coordinates":[122.96556,7.54806],"type":"Point"}
}