{
  "type": "Feature",
  "properties": {
    "gn:admin1_code":"07",
    "gn:admin2_code":"46",
    "gn:admin3_code":"74623000.0",
    "gn:asciiname":"Balili",
    "gn:country_code":"PH",
    "gn:dem":177,
    "gn:feature_class":"P",
    "gn:feature_code":"PPL",
    "gn:name":"Balili",
    "gn:population":0,
    "gn:timezone":"Asia/Manila",
    "iso:country":"PH",
    "name:fil_x_preferred":[
        "Balili"
    ],
    "wof:name":"Balili",
    "wof:placetype":"locality"
},
  "geometry": {"coordinates":[123.25,9.28333],"type":"Point"}
}