{
  "type": "Feature",
  "properties": {
    "gn:admin1_code":"13",
    "gn:admin2_code":"61",
    "gn:admin3_code":"166706000.0",
    "gn:asciiname":"Daywan",
    "gn:country_code":"PH",
    "gn:dem":36,
    "gn:feature_class":"P",
    "gn:feature_code":"PPL",
    "gn:name":"Daywan",
    "gn:population":0,
    "gn:timezone":"Asia/Manila",
    "iso:country":"PH",
    "name:fil_x_preferred":[
        "Daywan"
    ],
    "wof:name":"Daywan",
    "wof:placetype":"locality"
},
  "geometry": {"coordinates":[125.72020000000001,9.557],"type":"Point"}
}