{
  "type": "Feature",
  "properties": {
    "gn:admin1_code":"15",
    "gn:admin2_code":"10",
    "gn:admin3_code":"141110000.0",
    "gn:asciiname":"Anneng",
    "gn:country_code":"PH",
    "gn:dem":1069,
    "gn:feature_class":"P",
    "gn:feature_code":"PPL",
    "gn:name":"Anneng",
    "gn:population":0,
    "gn:timezone":"Asia/Manila",
    "iso:country":"PH",
    "name:fil_x_preferred":[
        "Anneng"
    ],
    "wof:name":"Anneng",
    "wof:placetype":"locality"
},
  "geometry": {"coordinates":[120.58723000000001,16.48848],"type":"Point"}
}