{
  "type": "Feature",
  "properties": {
    "iso:country":"PH",
    "name:bcl_x_preferred":[
        "Baganga"
    ],
    "name:cbk_zam_x_preferred":[
        "Baganga"
    ],
    "name:ceb_x_preferred":[
        "Baganga"
    ],
    "name:deu_x_preferred":[
        "Baganga"
    ],
    "name:eng_x_preferred":[
        "Baganga"
    ],
    "name:fra_x_preferred":[
        "Baganga"
    ],
    "name:ilo_x_preferred":[
        "Baganga"
    ],
    "name:ind_x_preferred":[
        "Baganga"
    ],
    "name:ita_x_preferred":[
        "Baganga"
    ],
    "name:nld_x_preferred":[
        "Baganga"
    ],
    "name:nob_x_preferred":[
        "Baganga"
    ],
    "name:nor_x_preferred":[
        "Baganga"
    ],
    "name:pag_x_preferred":[
        "Baganga"
    ],
    "name:pam_x_preferred":[
        "Baganga"
    ],
    "name:spa_x_preferred":[
        "Baganga"
    ],
    "name:swe_x_preferred":[
        "Baganga"
    ],
    "name:tgl_x_preferred":[
        "Baganga"
    ],
    "name:ukr_x_preferred":[
        "\u0411\u0430\u0491\u0430\u043d\u0491\u0430"
    ],
    "name:und_x_variant":[
        "Central"
    ],
    "name:vie_x_preferred":[
        "Baganga"
    ],
    "name:war_x_preferred":[
        "Baganga"
    ],
    "name:zho_x_preferred":[
        "\u5df4\u5ca1\u963f"
    ],
    "qs:gn_country":"PH",
    "qs:gn_fcode":"PPL",
    "qs:gn_pop":10106,
    "qs:name":"Baganga",
    "qs:name_adm0":"Philippines",
    "qs:name_adm1":"Davao Region",
    "qs:photos":0,
    "qs:photos_1k":0,
    "qs:photos_9k":1,
    "qs:photos_9r":1,
    "qs:photos_all":12,
    "qs:photos_sr":0,
    "qs:placetype":"Town",
    "qs:pop_sr":"6",
    "qs:woe_adm0":23424934,
    "wd:wordcount":948,
    "wof:name":"Baganga",
    "wof:placetype":"locality",
    "wof:population":10106
},
  "geometry": {"coordinates":[126.56,7.57389],"type":"Point"}
}