{
  "type": "Feature",
  "properties": {
    "gn:admin1_code":"03",
    "gn:admin2_code":"G8",
    "gn:admin3_code":"37704000.0",
    "gn:asciiname":"Dilebsong",
    "gn:country_code":"PH",
    "gn:dem":8,
    "gn:feature_class":"P",
    "gn:feature_code":"PPL",
    "gn:name":"Dilebsong",
    "gn:population":0,
    "gn:timezone":"Asia/Manila",
    "iso:country":"PH",
    "name:fil_x_preferred":[
        "Dilebsong"
    ],
    "wof:name":"Dilebsong",
    "wof:placetype":"locality"
},
  "geometry": {"coordinates":[121.96639999999999,16.1374],"type":"Point"}
}