{
  "type": "Feature",
  "properties": {
    "gn:admin1_code":"40",
    "gn:admin2_code":"20",
    "gn:admin3_code":"42120000.0",
    "gn:asciiname":"Sahod Ulan",
    "gn:country_code":"PH",
    "gn:dem":14,
    "gn:feature_class":"P",
    "gn:feature_code":"PPL",
    "gn:name":"Sahod Ulan",
    "gn:population":0,
    "gn:timezone":"Asia/Manila",
    "iso:country":"PH",
    "name:fil_x_preferred":[
        "Sahod Ulan"
    ],
    "wof:name":"Sahod Ulan",
    "wof:placetype":"locality"
},
  "geometry": {"coordinates":[120.82122,14.36868],"type":"Point"}
}