{
  "type": "Feature",
  "properties": {
    "gn:admin1_code":"13",
    "gn:admin2_code":"02",
    "gn:admin3_code":"160202000.0",
    "gn:asciiname":"Bobon",
    "gn:country_code":"PH",
    "gn:dem":8,
    "gn:feature_class":"P",
    "gn:feature_code":"PPL",
    "gn:name":"Bobon",
    "gn:population":0,
    "gn:timezone":"Asia/Manila",
    "iso:country":"PH",
    "name:bcl_x_preferred":[
        "Bobon"
    ],
    "name:ceb_x_preferred":[
        "Bobon"
    ],
    "name:deu_x_preferred":[
        "Bobon"
    ],
    "name:fra_x_preferred":[
        "Bobon"
    ],
    "name:ilo_x_preferred":[
        "Bobon"
    ],
    "name:ind_x_preferred":[
        "Bobon"
    ],
    "name:ita_x_preferred":[
        "Bobon"
    ],
    "name:nld_x_preferred":[
        "Bobon"
    ],
    "name:pag_x_preferred":[
        "Bobon"
    ],
    "name:pam_x_preferred":[
        "Bobon"
    ],
    "name:swe_x_preferred":[
        "Bobon"
    ],
    "name:tgl_x_preferred":[
        "Bobon"
    ],
    "name:vie_x_preferred":[
        "Bobon"
    ],
    "name:war_x_preferred":[
        "Bobon"
    ],
    "wof:name":"Bobon",
    "wof:placetype":"locality"
},
  "geometry": {"coordinates":[125.55861000000002,8.99083],"type":"Point"}
}