{
  "type": "Feature",
  "properties": {
    "gn:admin1_code":"01",
    "gn:admin2_code":"28",
    "gn:admin3_code":"12817000.0",
    "gn:asciiname":"Madalayap",
    "gn:country_code":"PH",
    "gn:dem":228,
    "gn:feature_class":"P",
    "gn:feature_code":"PPL",
    "gn:name":"Madalayap",
    "gn:population":0,
    "gn:timezone":"Asia/Manila",
    "iso:country":"PH",
    "name:fil_x_preferred":[
        "Madalayap"
    ],
    "wof:name":"Madalayap",
    "wof:placetype":"locality"
},
  "geometry": {"coordinates":[120.68680000000001,18.3221],"type":"Point"}
}