{
  "type": "Feature",
  "properties": {
    "gn:admin1_code":"08",
    "gn:admin2_code":"59",
    "gn:asciiname":"Ik-ican",
    "gn:country_code":"PH",
    "gn:dem":121,
    "gn:feature_class":"P",
    "gn:feature_code":"PPL",
    "gn:name":"Ik-ican",
    "gn:population":0,
    "gn:timezone":"Asia/Manila",
    "iso:country":"PH",
    "name:fil_x_preferred":[
        "Ik-ican"
    ],
    "wof:name":"Ik-ican",
    "wof:placetype":"locality"
},
  "geometry": {"coordinates":[122.428,10.9238],"type":"Point"}
}