{
  "type": "Feature",
  "properties": {
    "gn:admin1_code":"06",
    "gn:admin2_code":"18",
    "gn:admin3_code":"61912000.0",
    "gn:asciiname":"Batabat",
    "gn:country_code":"PH",
    "gn:dem":4,
    "gn:feature_class":"P",
    "gn:feature_code":"PPL",
    "gn:name":"Batabat",
    "gn:population":0,
    "gn:timezone":"Asia/Manila",
    "iso:country":"PH",
    "name:aze_x_preferred":[
        "Batabat g\u00f6l\u00fc"
    ],
    "name:ceb_x_preferred":[
        "Batabat G\u00f6l\u00fc"
    ],
    "name:chv_x_preferred":[
        "\u0411\u0430\u0442\u0430\u0431\u0430\u0442"
    ],
    "name:fil_x_preferred":[
        "Batabat"
    ],
    "name:kat_x_preferred":[
        "\u10d1\u10d0\u10d7\u10d0\u10d1\u10d0\u10d7\u10d8"
    ],
    "name:rus_x_preferred":[
        "\u0411\u0430\u0442\u0430\u0431\u0430\u0442"
    ],
    "name:swe_x_preferred":[
        "Batabat G\u00f6l\u00fc"
    ],
    "name:ukr_x_preferred":[
        "\u0411\u0430\u0442\u0430\u0431\u0430\u0442"
    ],
    "wof:name":"Batabat",
    "wof:placetype":"locality"
},
  "geometry": {"coordinates":[122.81667,11.48333],"type":"Point"}
}