{
  "type": "Feature",
  "properties": {
    "gn:admin1_code":"40",
    "gn:admin2_code":"20",
    "gn:admin3_code":"42120000.0",
    "gn:asciiname":"Pasalada",
    "gn:country_code":"PH",
    "gn:dem":36,
    "gn:feature_class":"P",
    "gn:feature_code":"PPL",
    "gn:name":"Pasalada",
    "gn:population":0,
    "gn:timezone":"Asia/Manila",
    "iso:country":"PH",
    "name:fil_x_preferred":[
        "Pasalada"
    ],
    "wof:name":"Pasalada",
    "wof:placetype":"locality"
},
  "geometry": {"coordinates":[120.83056000000001,14.33361],"type":"Point"}
}