{
  "type": "Feature",
  "properties": {
    "gn:admin1_code":"01",
    "gn:admin2_code":"51",
    "gn:admin3_code":"15516000.0",
    "gn:asciiname":"Don Matias",
    "gn:country_code":"PH",
    "gn:dem":97,
    "gn:feature_class":"P",
    "gn:feature_code":"PPL",
    "gn:name":"Don Matias",
    "gn:population":0,
    "gn:timezone":"Asia/Manila",
    "iso:country":"PH",
    "name:fil_x_preferred":[
        "Don Matias"
    ],
    "wof:name":"Don Matias",
    "wof:placetype":"locality"
},
  "geometry": {"coordinates":[119.87949999999999,16.0604],"type":"Point"}
}