{
  "type": "Feature",
  "properties": {
    "gn:admin1_code":"11",
    "gn:admin2_code":"I6",
    "gn:admin3_code":"118211000.0",
    "gn:asciiname":"Ayon",
    "gn:country_code":"PH",
    "gn:dem":37,
    "gn:feature_class":"P",
    "gn:feature_code":"PPL",
    "gn:name":"Ayon",
    "gn:population":0,
    "gn:timezone":"Asia/Manila",
    "iso:country":"PH",
    "name:fil_x_preferred":[
        "Ayon"
    ],
    "wof:name":"Ayon",
    "wof:placetype":"locality"
},
  "geometry": {"coordinates":[125.9243,7.1381],"type":"Point"}
}