{
  "type": "Feature",
  "properties": {
    "gn:admin1_code":"15",
    "gn:admin2_code":"01",
    "gn:admin3_code":"140117000.0",
    "gn:asciiname":"Lapga",
    "gn:country_code":"PH",
    "gn:dem":106,
    "gn:feature_class":"P",
    "gn:feature_code":"PPL",
    "gn:name":"Lapga",
    "gn:population":0,
    "gn:timezone":"Asia/Manila",
    "iso:country":"PH",
    "name:fil_x_preferred":[
        "Lapga"
    ],
    "wof:name":"Lapga",
    "wof:placetype":"locality"
},
  "geometry": {"coordinates":[120.6604,17.5503],"type":"Point"}
}