{
  "type": "Feature",
  "properties": {
    "gn:admin1_code":"01",
    "gn:admin2_code":"36",
    "gn:admin3_code":"13314000.0",
    "gn:asciiname":"Dalumpinas Este",
    "gn:country_code":"PH",
    "gn:dem":33,
    "gn:feature_class":"P",
    "gn:feature_code":"PPL",
    "gn:name":"Dalumpinas Este",
    "gn:population":0,
    "gn:timezone":"Asia/Manila",
    "iso:country":"PH",
    "name:fil_x_preferred":[
        "Dalumpinas Este"
    ],
    "wof:name":"Dalumpinas Este",
    "wof:placetype":"locality"
},
  "geometry": {"coordinates":[120.33333,16.65],"type":"Point"}
}