{
  "type": "Feature",
  "properties": {
    "gn:admin1_code":"02",
    "gn:admin2_code":"31",
    "gn:admin3_code":"23120000.0",
    "gn:asciiname":"Blacar",
    "gn:country_code":"PH",
    "gn:dem":87,
    "gn:feature_class":"P",
    "gn:feature_code":"PPL",
    "gn:name":"Blacar",
    "gn:population":0,
    "gn:timezone":"Asia/Manila",
    "iso:country":"PH",
    "name:fil_x_preferred":[
        "Blacar"
    ],
    "name:fil_x_variant":[
        "Blaclar"
    ],
    "wof:name":"Blacar",
    "wof:placetype":"locality"
},
  "geometry": {"coordinates":[121.92404000000001,17.00205],"type":"Point"}
}