{
  "type": "Feature",
  "properties": {
    "gn:admin1_code":"02",
    "gn:admin2_code":"48",
    "gn:admin3_code":"25010000.0",
    "gn:asciiname":"Banao",
    "gn:country_code":"PH",
    "gn:dem":1282,
    "gn:feature_class":"P",
    "gn:feature_code":"PPL",
    "gn:name":"Banao",
    "gn:population":0,
    "gn:timezone":"Asia/Manila",
    "iso:country":"PH",
    "name:eng_x_preferred":[
        "Banao"
    ],
    "wof:name":"Banao",
    "wof:placetype":"locality"
},
  "geometry": {"coordinates":[120.8981,16.4125],"type":"Point"}
}