{
  "type": "Feature",
  "properties": {
    "iso:country":"PH",
    "name:bcl_x_preferred":[
        "Matanao"
    ],
    "name:dut_x_preferred":[
        "Matanao"
    ],
    "name:eng_x_preferred":[
        "Matanao"
    ],
    "name:fil_x_preferred":[
        "Matan-ao"
    ],
    "name:fre_x_preferred":[
        "Matanao"
    ],
    "name:ger_x_preferred":[
        "Matanao"
    ],
    "name:ilo_x_preferred":[
        "Matanao"
    ],
    "name:ind_x_preferred":[
        "Matanao"
    ],
    "name:ita_x_preferred":[
        "Matanao"
    ],
    "name:nob_x_preferred":[
        "Matanao"
    ],
    "name:pag_x_preferred":[
        "Matanao"
    ],
    "name:pam_x_preferred":[
        "Matanao"
    ],
    "name:spa_x_preferred":[
        "Matanao"
    ],
    "name:swe_x_preferred":[
        "Matanao"
    ],
    "name:tgl_x_preferred":[
        "Matanao"
    ],
    "name:unk_x_variant":[
        "Matinao"
    ],
    "name:vie_x_preferred":[
        "Matanao"
    ],
    "name:war_x_preferred":[
        "Matanao"
    ],
    "qs:gn_country":"PH",
    "qs:gn_fcode":"PPL",
    "qs:gn_pop":0,
    "qs:name":"Matan-ao",
    "qs:name_adm0":"Philippines",
    "qs:name_adm1":"Davao Region",
    "qs:photos":241,
    "qs:photos_1k":49,
    "qs:photos_9k":1,
    "qs:photos_9r":4,
    "qs:photos_all":241,
    "qs:photos_sr":4,
    "qs:placetype":"Town",
    "qs:pop_sr":"0",
    "qs:woe_adm0":23424934,
    "wof:name":"Matan-ao",
    "wof:placetype":"locality"
},
  "geometry": {"coordinates":[125.21639,6.70611],"type":"Point"}
}