{
  "type": "Feature",
  "properties": {
    "gn:admin1_code":"01",
    "gn:admin2_code":"29",
    "gn:admin3_code":"12933000.0",
    "gn:asciiname":"Ambalayan",
    "gn:country_code":"PH",
    "gn:dem":37,
    "gn:feature_class":"P",
    "gn:feature_code":"PPL",
    "gn:name":"Ambalayan",
    "gn:population":0,
    "gn:timezone":"Asia/Manila",
    "iso:country":"PH",
    "name:fil_x_preferred":[
        "Ambalayan"
    ],
    "name:fil_x_variant":[
        "Ambalayat"
    ],
    "wof:name":"Ambalayan",
    "wof:placetype":"locality"
},
  "geometry": {"coordinates":[120.4935,16.92],"type":"Point"}
}