{
  "type": "Feature",
  "properties": {
    "gn:admin1_code":"40",
    "gn:admin2_code":"H2",
    "gn:admin3_code":"45647000.0",
    "gn:asciiname":"Bukal Ilaya",
    "gn:country_code":"PH",
    "gn:dem":459,
    "gn:feature_class":"P",
    "gn:feature_code":"PPL",
    "gn:name":"Bukal Ilaya",
    "gn:population":0,
    "gn:timezone":"Asia/Manila",
    "iso:country":"PH",
    "name:fil_x_preferred":[
        "Bukal Ilaya"
    ],
    "name:und_x_variant":[
        "Bukul Ilaya",
        "Bukal Norte"
    ],
    "wof:name":"Bukal Ilaya",
    "wof:placetype":"locality"
},
  "geometry": {"coordinates":[121.53806000000002,14.01139],"type":"Point"}
}