{
  "type": "Feature",
  "properties": {
    "gn:admin1_code":"03",
    "gn:admin2_code":"07",
    "gn:admin3_code":"30809000.0",
    "gn:asciiname":"Parang Parang",
    "gn:country_code":"PH",
    "gn:dem":12,
    "gn:feature_class":"P",
    "gn:feature_code":"PPL",
    "gn:name":"Parang Parang",
    "gn:population":0,
    "gn:timezone":"Asia/Manila",
    "iso:country":"PH",
    "name:fil_x_preferred":[
        "Parang"
    ],
    "wof:name":"Parang Parang",
    "wof:placetype":"locality"
},
  "geometry": {"coordinates":[120.53848000000001,14.79506],"type":"Point"}
}