{
  "type": "Feature",
  "properties": {
    "gn:admin1_code":"14",
    "gn:admin2_code":"60",
    "gn:admin3_code":"156603000.0",
    "gn:asciiname":"Timbayan",
    "gn:country_code":"PH",
    "gn:dem":77,
    "gn:feature_class":"P",
    "gn:feature_code":"PPL",
    "gn:name":"Timbayan",
    "gn:population":0,
    "gn:timezone":"Asia/Manila",
    "iso:country":"PH",
    "name:fil_x_preferred":[
        "Timbayan"
    ],
    "wof:name":"Timbayan",
    "wof:placetype":"locality"
},
  "geometry": {"coordinates":[121.315,5.89639],"type":"Point"}
}