{
  "type": "Feature",
  "properties": {
    "gn:country":"PH",
    "gn:fcode":"PPL",
    "gn:pop":5445,
    "iso:country":"PH",
    "qs:name":"Talisayan",
    "qs:photos_9r":0,
    "qs:photos_sr":0,
    "qs:pop_sr":"5",
    "wof:name":"Talisayan",
    "wof:placetype":"locality",
    "wof:population":5445
},
  "geometry": {"coordinates":[121.92722000000001,6.98722],"type":"Point"}
}