{
  "type": "Feature",
  "properties": {
    "gn:admin1_code":"41",
    "gn:admin2_code":"54",
    "gn:admin3_code":"175909000.0",
    "gn:asciiname":"Progreso Este",
    "gn:country_code":"PH",
    "gn:dem":67,
    "gn:feature_class":"P",
    "gn:feature_code":"PPL",
    "gn:name":"Progreso Este",
    "gn:population":0,
    "gn:timezone":"Asia/Manila",
    "iso:country":"PH",
    "name:fil_x_preferred":[
        "Progreso Este"
    ],
    "wof:name":"Progreso Este",
    "wof:placetype":"locality"
},
  "geometry": {"coordinates":[122.02388999999999,12.35083],"type":"Point"}
}