{
  "type": "Feature",
  "properties": {
    "gn:country":"PH",
    "gn:fcode":"ADM3",
    "gn:pop":43050,
    "iso:country":"PH",
    "name:fil_x_preferred":[
        "Titay"
    ],
    "qs:name":"Titay",
    "qs:photos_9r":0,
    "qs:photos_sr":0,
    "qs:pop_sr":"7",
    "wof:name":"Titay",
    "wof:placetype":"localadmin",
    "wof:population":43050
},
  "geometry": {"coordinates":[122.43333,7.78333],"type":"Point"}
}