{
  "type": "Feature",
  "properties": {
    "gn:admin1_code":"08",
    "gn:admin2_code":"37",
    "gn:admin3_code":"83705000.0",
    "gn:asciiname":"Magsaigad",
    "gn:country_code":"PH",
    "gn:dem":7,
    "gn:feature_class":"P",
    "gn:feature_code":"PPL",
    "gn:name":"Magsaigad",
    "gn:population":0,
    "gn:timezone":"Asia/Manila",
    "iso:country":"PH",
    "name:fil_x_preferred":[
        "Magsaigad"
    ],
    "wof:name":"Magsaigad",
    "wof:placetype":"locality"
},
  "geometry": {"coordinates":[124.84056,11.42222],"type":"Point"}
}