{
  "type": "Feature",
  "properties": {
    "gn:admin1_code":"05",
    "gn:admin2_code":"05",
    "gn:admin3_code":"50506000.0",
    "gn:asciiname":"Mercedes",
    "gn:country_code":"PH",
    "gn:dem":113,
    "gn:feature_class":"P",
    "gn:feature_code":"PPL",
    "gn:name":"Mercedes",
    "gn:population":0,
    "gn:timezone":"Asia/Manila",
    "iso:country":"PH",
    "name:fil_x_preferred":[
        "Mercedes"
    ],
    "wof:name":"Mercedes",
    "wof:placetype":"locality"
},
  "geometry": {"coordinates":[123.78333000000001,13.01667],"type":"Point"}
}