{
  "type": "Feature",
  "properties": {
    "gn:admin1_code":"10",
    "gn:admin2_code":"43",
    "gn:admin3_code":"104314000.0",
    "gn:asciiname":"Tombo",
    "gn:country_code":"PH",
    "gn:dem":84,
    "gn:feature_class":"P",
    "gn:feature_code":"PPL",
    "gn:name":"Tombo",
    "gn:population":0,
    "gn:timezone":"Asia/Manila",
    "iso:country":"PH",
    "name:fil_x_preferred":[
        "Tombo"
    ],
    "wof:name":"Tombo",
    "wof:placetype":"locality"
},
  "geometry": {"coordinates":[124.45305999999999,8.5725],"type":"Point"}
}