{
  "type": "Feature",
  "properties": {
    "gn:admin1_code":"01",
    "gn:admin2_code":"29",
    "gn:admin3_code":"12901000.0",
    "gn:asciiname":"Singa",
    "gn:country_code":"PH",
    "gn:dem":1089,
    "gn:feature_class":"P",
    "gn:feature_code":"PPL",
    "gn:name":"Singa",
    "gn:population":0,
    "gn:timezone":"Asia/Manila",
    "iso:country":"PH",
    "name:ceb_x_preferred":[
        "Singa"
    ],
    "name:deu_x_preferred":[
        "Singa"
    ],
    "name:fil_x_preferred":[
        "Singa"
    ],
    "name:fra_x_preferred":[
        "Singa"
    ],
    "name:ita_x_preferred":[
        "Singa"
    ],
    "name:new_x_preferred":[
        "\u0938\u093f\u0902\u0917\u093e"
    ],
    "name:nld_x_preferred":[
        "Singa"
    ],
    "name:por_x_preferred":[
        "Singa"
    ],
    "name:swe_x_preferred":[
        "Singa"
    ],
    "wof:name":"Singa",
    "wof:placetype":"locality"
},
  "geometry": {"coordinates":[120.6031,16.8865],"type":"Point"}
}