{
  "type": "Feature",
  "properties": {
    "gn:admin1_code":"40",
    "gn:admin2_code":"20",
    "gn:admin3_code":"42110000.0",
    "gn:asciiname":"Buna Cerca",
    "gn:country_code":"PH",
    "gn:dem":342,
    "gn:feature_class":"P",
    "gn:feature_code":"PPL",
    "gn:name":"Buna Cerca",
    "gn:population":0,
    "gn:timezone":"Asia/Manila",
    "iso:country":"PH",
    "name:und_x_variant":[
        "Bona",
        "Bunacerca",
        "Bona Cerca",
        "Buna Cerca"
    ],
    "wof:name":"Buna Cerca",
    "wof:placetype":"locality"
},
  "geometry": {"coordinates":[120.88692,14.18585],"type":"Point"}
}