{
  "type": "Feature",
  "properties": {
    "gn:admin1_code":"02",
    "gn:admin2_code":"14",
    "gn:admin3_code":"21510000.0",
    "gn:asciiname":"Abagao",
    "gn:country_code":"PH",
    "gn:dem":3,
    "gn:feature_class":"P",
    "gn:feature_code":"PPL",
    "gn:name":"Abagao",
    "gn:population":0,
    "gn:timezone":"Asia/Manila",
    "iso:country":"PH",
    "name:fil_x_preferred":[
        "Abbagao"
    ],
    "name:fil_x_variant":[
        "Abagao"
    ],
    "wof:name":"Abagao",
    "wof:placetype":"locality"
},
  "geometry": {"coordinates":[121.75379,18.25578],"type":"Point"}
}