{
  "type": "Feature",
  "properties": {
    "gn:admin1_code":"08",
    "gn:admin2_code":"37",
    "gn:admin3_code":"83743000.0",
    "gn:asciiname":"Guinciana",
    "gn:country_code":"PH",
    "gn:dem":3,
    "gn:feature_class":"P",
    "gn:feature_code":"PPL",
    "gn:name":"Guinciana",
    "gn:population":0,
    "gn:timezone":"Asia/Manila",
    "iso:country":"PH",
    "name:fil_x_preferred":[
        "Guinciana"
    ],
    "name:und_x_variant":[
        "Guincinana",
        "Guinciana"
    ],
    "wof:name":"Guinciana",
    "wof:placetype":"locality"
},
  "geometry": {"coordinates":[124.8096,11.357],"type":"Point"}
}