{
  "type": "Feature",
  "properties": {
    "gn:admin1_code":"01",
    "gn:admin2_code":"29",
    "gn:admin3_code":"12916000.0",
    "gn:asciiname":"Arangin-Dinaratan",
    "gn:cc2":"PH",
    "gn:country_code":"PH",
    "gn:dem":23,
    "gn:feature_class":"P",
    "gn:feature_code":"PPL",
    "gn:name":"Arangin-Dinaratan",
    "gn:population":0,
    "gn:timezone":"Asia/Manila",
    "iso:country":"PH",
    "name:und_x_variant":[
        "Arangin",
        "Arangin-Dinaratan"
    ],
    "wof:name":"Arangin-Dinaratan",
    "wof:placetype":"locality"
},
  "geometry": {"coordinates":[120.51667,17.11667000000001],"type":"Point"}
}