{
  "type": "Feature",
  "properties": {
    "gn:country":"PH",
    "gn:fcode":"PPL",
    "gn:pop":2543,
    "iso:country":"PH",
    "name:fil_x_preferred":[
        "Piape I"
    ],
    "name:unk_x_variant":[
        "Piapi"
    ],
    "qs:name":"Piape I",
    "qs:photos_9r":0,
    "qs:photos_sr":0,
    "qs:pop_sr":"4",
    "wof:name":"Piape I",
    "wof:placetype":"locality",
    "wof:population":2543
},
  "geometry": {"coordinates":[121.97239999999999,10.7288],"type":"Point"}
}