{
  "type": "Feature",
  "properties": {
    "gn:admin1_code":"08",
    "gn:admin2_code":"23",
    "gn:admin3_code":"82617000.0",
    "gn:asciiname":"Sinalugsogan",
    "gn:country_code":"PH",
    "gn:dem":13,
    "gn:feature_class":"P",
    "gn:feature_code":"PPL",
    "gn:name":"Sinalugsogan",
    "gn:population":0,
    "gn:timezone":"Asia/Manila",
    "iso:country":"PH",
    "name:fil_x_preferred":[
        "Sinalugsogan"
    ],
    "name:und_x_variant":[
        "Sinalugsucon"
    ],
    "wof:name":"Sinalugsogan",
    "wof:placetype":"locality"
},
  "geometry": {"coordinates":[125.4053,12.181],"type":"Point"}
}