{
  "type": "Feature",
  "properties": {
    "gn:admin1_code":"05",
    "gn:admin2_code":"16",
    "gn:admin3_code":"51719000.0",
    "gn:asciiname":"San Rafael",
    "gn:country_code":"PH",
    "gn:dem":54,
    "gn:feature_class":"P",
    "gn:feature_code":"PPL",
    "gn:name":"San Rafael",
    "gn:population":0,
    "gn:timezone":"Asia/Manila",
    "iso:country":"PH",
    "name:fil_x_preferred":[
        "San Rafael"
    ],
    "name:und_x_variant":[
        "San Rafaet"
    ],
    "wof:name":"San Rafael",
    "wof:placetype":"locality"
},
  "geometry": {"coordinates":[122.8935,13.7953],"type":"Point"}
}