{
  "type": "Feature",
  "properties": {
    "gn:country":"PH",
    "gn:fcode":"PPL",
    "gn:population":3399,
    "iso:country":"PH",
    "name:fil_x_preferred":[
        "Marbel"
    ],
    "qs:name":"Marbel",
    "qs:photos_9r":0,
    "qs:photos_sr":0,
    "qs:pop_sr":"4",
    "wof:name":"Marbel",
    "wof:placetype":"locality",
    "wof:population":3399
},
  "geometry": {"coordinates":[124.91249999999999,7.11583],"type":"Point"}
}