{
  "type": "Feature",
  "properties": {
    "gn:admin1_code":"11",
    "gn:admin2_code":"25",
    "gn:admin3_code":"112412000.0",
    "gn:asciiname":"Melilia",
    "gn:country_code":"PH",
    "gn:dem":12,
    "gn:feature_class":"P",
    "gn:feature_code":"PPL",
    "gn:name":"Melilia",
    "gn:population":0,
    "gn:timezone":"Asia/Manila",
    "iso:country":"PH",
    "name:fil_x_preferred":[
        "Melilia"
    ],
    "wof:name":"Melilia",
    "wof:placetype":"locality"
},
  "geometry": {"coordinates":[125.39417,6.81611],"type":"Point"}
}