{
  "type": "Feature",
  "properties": {
    "gn:admin1_code":"15",
    "gn:admin2_code":"32",
    "gn:admin3_code":"143206000.0",
    "gn:asciiname":"Tanap",
    "gn:country_code":"PH",
    "gn:dem":416,
    "gn:feature_class":"P",
    "gn:feature_code":"PPL",
    "gn:name":"Tanap",
    "gn:population":0,
    "gn:timezone":"Asia/Manila",
    "iso:country":"PH",
    "name:fil_x_preferred":[
        "Tanap"
    ],
    "wof:name":"Tanap",
    "wof:placetype":"locality"
},
  "geometry": {"coordinates":[121.20050000000001,17.3649],"type":"Point"}
}