{
  "type": "Feature",
  "properties": {
    "gn:admin1_code":"06",
    "gn:admin2_code":"04",
    "gn:admin3_code":"60406000.0",
    "gn:asciiname":"Jawili",
    "gn:country_code":"PH",
    "gn:dem":27,
    "gn:feature_class":"P",
    "gn:feature_code":"PPL",
    "gn:name":"Jawili",
    "gn:population":0,
    "gn:timezone":"Asia/Manila",
    "iso:country":"PH",
    "name:fil_x_preferred":[
        "Jawili"
    ],
    "wof:name":"Jawili",
    "wof:placetype":"locality"
},
  "geometry": {"coordinates":[122.17861000000001,11.79972],"type":"Point"}
}