{
  "type": "Feature",
  "properties": {
    "gn:admin1_code":"05",
    "gn:admin2_code":"16",
    "gn:admin3_code":"51734000.0",
    "gn:asciiname":"Taisan",
    "gn:country_code":"PH",
    "gn:dem":24,
    "gn:feature_class":"P",
    "gn:feature_code":"PPL",
    "gn:name":"Taisan",
    "gn:population":0,
    "gn:timezone":"Asia/Manila",
    "iso:country":"PH",
    "name:fil_x_preferred":[
        "Taisan"
    ],
    "wof:name":"Taisan",
    "wof:placetype":"locality"
},
  "geometry": {"coordinates":[123.0047,13.7645],"type":"Point"}
}