{
  "type": "Feature",
  "properties": {
    "gn:admin1_code":"01",
    "gn:admin2_code":"51",
    "gn:admin3_code":"15502000.0",
    "gn:asciiname":"Banaybayan",
    "gn:country_code":"PH",
    "gn:dem":24,
    "gn:feature_class":"P",
    "gn:feature_code":"PPL",
    "gn:name":"Banaybayan",
    "gn:population":0,
    "gn:timezone":"Asia/Manila",
    "iso:country":"PH",
    "name:fil_x_preferred":[
        "Banaybayan"
    ],
    "wof:name":"Banaybayan",
    "wof:placetype":"locality"
},
  "geometry": {"coordinates":[120.2543,15.8366],"type":"Point"}
}