{
  "type": "Feature",
  "properties": {
    "gn:admin1_code":"41",
    "gn:admin2_code":"49",
    "gn:admin3_code":"175310000.0",
    "gn:asciiname":"Maringian",
    "gn:country_code":"PH",
    "gn:dem":11,
    "gn:feature_class":"P",
    "gn:feature_code":"PPL",
    "gn:name":"Maringian",
    "gn:population":0,
    "gn:timezone":"Asia/Manila",
    "iso:country":"PH",
    "name:eng_x_preferred":[
        "Maringian"
    ],
    "name:und_x_variant":[
        "Maringlan"
    ],
    "wof:name":"Maringian",
    "wof:placetype":"locality"
},
  "geometry": {"coordinates":[121.01953,10.86088],"type":"Point"}
}