{
  "type": "Feature",
  "properties": {
    "gn:admin1_code":"14",
    "gn:admin2_code":"60",
    "gn:admin3_code":"156601000.0",
    "gn:asciiname":"Potat",
    "gn:country_code":"PH",
    "gn:dem":193,
    "gn:feature_class":"P",
    "gn:feature_code":"PPL",
    "gn:name":"Potat",
    "gn:population":0,
    "gn:timezone":"Asia/Manila",
    "iso:country":"PH",
    "name:fil_x_preferred":[
        "Potat"
    ],
    "wof:name":"Potat",
    "wof:placetype":"locality"
},
  "geometry": {"coordinates":[120.98833,6.01583],"type":"Point"}
}