{
  "type": "Feature",
  "properties": {
    "gn:admin1_code":"08",
    "gn:admin2_code":"59",
    "gn:admin3_code":"86417000.0",
    "gn:asciiname":"Bonbon",
    "gn:country_code":"PH",
    "gn:dem":364,
    "gn:feature_class":"P",
    "gn:feature_code":"PPL",
    "gn:name":"Bonbon",
    "gn:population":0,
    "gn:timezone":"Asia/Manila",
    "iso:country":"PH",
    "name:fil_x_preferred":[
        "Bonbon"
    ],
    "wof:name":"Bonbon",
    "wof:placetype":"locality"
},
  "geometry": {"coordinates":[124.98909999999999,10.4442],"type":"Point"}
}