{
  "type": "Feature",
  "properties": {
    "gn:admin1_code":"07",
    "gn:admin2_code":"46",
    "gn:admin3_code":"74612000.0",
    "gn:asciiname":"Camancog",
    "gn:country_code":"PH",
    "gn:dem":32,
    "gn:feature_class":"P",
    "gn:feature_code":"PPL",
    "gn:name":"Camancog",
    "gn:population":0,
    "gn:timezone":"Asia/Manila",
    "iso:country":"PH",
    "name:fil_x_preferred":[
        "Camancog"
    ],
    "wof:name":"Camancog",
    "wof:placetype":"locality"
},
  "geometry": {"coordinates":[123.1956,9.993],"type":"Point"}
}