{
  "type": "Feature",
  "properties": {
    "gn:admin1_code":"05",
    "gn:admin2_code":"39",
    "gn:admin3_code":"54112000.0",
    "gn:asciiname":"Taberna",
    "gn:country_code":"PH",
    "gn:dem":22,
    "gn:feature_class":"P",
    "gn:feature_code":"PPL",
    "gn:name":"Taberna",
    "gn:population":0,
    "gn:timezone":"Asia/Manila",
    "iso:country":"PH",
    "name:cat_x_preferred":[
        "Taverna romana"
    ],
    "name:deu_x_preferred":[
        "Taberna"
    ],
    "name:eus_x_preferred":[
        "Taberna erromatar"
    ],
    "name:fil_x_preferred":[
        "Taberna"
    ],
    "name:fin_x_preferred":[
        "Taberna"
    ],
    "name:fra_x_preferred":[
        "Taberna"
    ],
    "name:hun_x_preferred":[
        "Taberna"
    ],
    "name:ita_x_preferred":[
        "Taberna"
    ],
    "name:nld_x_preferred":[
        "Taberna"
    ],
    "name:por_x_preferred":[
        "Taberna"
    ],
    "name:spa_x_preferred":[
        "Taberna romana"
    ],
    "wof:name":"Taberna",
    "wof:placetype":"locality"
},
  "geometry": {"coordinates":[123.7059,12.1306],"type":"Point"}
}