{
  "type": "Feature",
  "properties": {
    "gn:admin1_code":"07",
    "gn:admin2_code":"11",
    "gn:admin3_code":"71246000.0",
    "gn:asciiname":"Cahoring",
    "gn:country_code":"PH",
    "gn:dem":13,
    "gn:feature_class":"P",
    "gn:feature_code":"PPL",
    "gn:name":"Cahoring",
    "gn:population":0,
    "gn:timezone":"Asia/Manila",
    "iso:country":"PH",
    "name:fil_x_preferred":[
        "Cahoring"
    ],
    "wof:name":"Cahoring",
    "wof:placetype":"locality"
},
  "geometry": {"coordinates":[124.4954,10.0454],"type":"Point"}
}