{
  "type": "Feature",
  "properties": {
    "gn:admin1_code":"14",
    "gn:admin2_code":"56",
    "gn:admin3_code":"153812000.0",
    "gn:asciiname":"Lanosan",
    "gn:country_code":"PH",
    "gn:dem":17,
    "gn:feature_class":"P",
    "gn:feature_code":"PPL",
    "gn:name":"Lanosan",
    "gn:population":0,
    "gn:timezone":"Asia/Manila",
    "iso:country":"PH",
    "name:fil_x_preferred":[
        "Lanosan"
    ],
    "wof:name":"Lanosan",
    "wof:placetype":"locality"
},
  "geometry": {"coordinates":[124.27028,7.265],"type":"Point"}
}