{
  "type": "Feature",
  "properties": {
    "gn:admin1_code":"07",
    "gn:admin2_code":"11",
    "gn:admin3_code":"71238000.0",
    "gn:asciiname":"Tomoc",
    "gn:country_code":"PH",
    "gn:dem":128,
    "gn:feature_class":"P",
    "gn:feature_code":"PPL",
    "gn:name":"Tomoc",
    "gn:population":0,
    "gn:timezone":"Asia/Manila",
    "iso:country":"PH",
    "name:fil_x_preferred":[
        "Tomoc"
    ],
    "wof:name":"Tomoc",
    "wof:placetype":"locality"
},
  "geometry": {"coordinates":[124.2901,9.9849],"type":"Point"}
}