{
  "type": "Feature",
  "properties": {
    "gn:country":"PH",
    "gn:fcode":"PPL",
    "gn:pop":46365,
    "iso:country":"PH",
    "name:fil_x_preferred":[
        "Pag-Asa"
    ],
    "name:fil_x_variant":[
        "Bagong Pagasa"
    ],
    "qs:name":"Bagong Pagasa",
    "qs:photos_9r":0,
    "qs:photos_sr":0,
    "qs:pop_sr":"7",
    "wof:name":"Bagong Pagasa",
    "wof:placetype":"locality",
    "wof:population":46365
},
  "geometry": {"coordinates":[121.03279999999999,14.6627],"type":"Point"}
}