{
  "type": "Feature",
  "properties": {
    "gn:admin1_code":"14",
    "gn:admin2_code":"56",
    "gn:admin3_code":"153808000.0",
    "gn:asciiname":"Bagong",
    "gn:country_code":"PH",
    "gn:dem":21,
    "gn:feature_class":"P",
    "gn:feature_code":"PPL",
    "gn:name":"Bagong",
    "gn:population":0,
    "gn:timezone":"Asia/Manila",
    "iso:country":"PH",
    "name:fil_x_preferred":[
        "Bagong"
    ],
    "wof:name":"Bagong",
    "wof:placetype":"locality"
},
  "geometry": {"coordinates":[124.45222,6.90528],"type":"Point"}
}