{
  "type": "Feature",
  "properties": {
    "gn:admin1_code":"06",
    "gn:admin2_code":"18",
    "gn:admin3_code":"61909000.0",
    "gn:asciiname":"Pili",
    "gn:country_code":"PH",
    "gn:dem":4,
    "gn:feature_class":"P",
    "gn:feature_code":"PPL",
    "gn:name":"Pili",
    "gn:population":0,
    "gn:timezone":"Asia/Manila",
    "iso:country":"PH",
    "wof:name":"Pili",
    "wof:placetype":"locality"
},
  "geometry": {"coordinates":[122.81885,11.54404],"type":"Point"}
}