{
  "type": "Feature",
  "properties": {
    "gn:admin1_code":"11",
    "gn:admin2_code":"I7",
    "gn:admin3_code":"112324000.0",
    "gn:asciiname":"Madgao",
    "gn:country_code":"PH",
    "gn:dem":38,
    "gn:feature_class":"P",
    "gn:feature_code":"PPL",
    "gn:name":"Madgao",
    "gn:population":0,
    "gn:timezone":"Asia/Manila",
    "iso:country":"PH",
    "name:fil_x_preferred":[
        "Madgao"
    ],
    "wof:name":"Madgao",
    "wof:placetype":"locality"
},
  "geometry": {"coordinates":[125.7831,7.6931],"type":"Point"}
}