{
  "type": "Feature",
  "properties": {
    "gn:admin1_code":"03",
    "gn:admin2_code":"63",
    "gn:admin3_code":"36901000.0",
    "gn:asciiname":"Don Ramon",
    "gn:country_code":"PH",
    "gn:dem":24,
    "gn:feature_class":"P",
    "gn:feature_code":"PPL",
    "gn:name":"Don Ramon",
    "gn:population":0,
    "gn:timezone":"Asia/Manila",
    "iso:country":"PH",
    "wof:name":"Don Ramon",
    "wof:placetype":"locality"
},
  "geometry": {"coordinates":[120.62748999999999,15.72862],"type":"Point"}
}