{
  "type": "Feature",
  "properties": {
    "gn:country":"PH",
    "gn:fcode":"PPLA3",
    "gn:population":10195,
    "iso:country":"PH",
    "name:bcl_x_preferred":[
        "Pototan"
    ],
    "name:ceb_x_preferred":[
        "Pototan"
    ],
    "name:deu_x_preferred":[
        "Pototan"
    ],
    "name:eng_x_preferred":[
        "Pototan"
    ],
    "name:fil_x_preferred":[
        "Pototan"
    ],
    "name:fra_x_preferred":[
        "Pototan"
    ],
    "name:ilo_x_preferred":[
        "Pototan"
    ],
    "name:ind_x_preferred":[
        "Pototan"
    ],
    "name:ita_x_preferred":[
        "Pototan"
    ],
    "name:nld_x_preferred":[
        "Pototan"
    ],
    "name:pag_x_preferred":[
        "Pototan"
    ],
    "name:pam_x_preferred":[
        "Pototan"
    ],
    "name:spa_x_preferred":[
        "Pototan"
    ],
    "name:swe_x_preferred":[
        "Pototan"
    ],
    "name:tgl_x_preferred":[
        "Pototan"
    ],
    "name:vie_x_preferred":[
        "Pototan"
    ],
    "name:war_x_preferred":[
        "Pototan"
    ],
    "qs:name":"Pototan",
    "qs:photos_9r":0,
    "qs:photos_sr":0,
    "qs:pop_sr":"6",
    "wof:name":"Pototan",
    "wof:placetype":"locality",
    "wof:population":10195
},
  "geometry": {"coordinates":[122.6352,10.9437],"type":"Point"}
}