{
  "type": "Feature",
  "properties": {
    "gn:admin1_code":"06",
    "gn:admin2_code":"30",
    "gn:admin3_code":"63012000.0",
    "gn:asciiname":"Maraguit",
    "gn:country_code":"PH",
    "gn:dem":97,
    "gn:feature_class":"P",
    "gn:feature_code":"PPL",
    "gn:name":"Maraguit",
    "gn:population":0,
    "gn:timezone":"Asia/Manila",
    "iso:country":"PH",
    "name:fil_x_preferred":[
        "Maraguit"
    ],
    "wof:name":"Maraguit",
    "wof:placetype":"locality"
},
  "geometry": {"coordinates":[122.4486,10.8451],"type":"Point"}
}