{
  "type": "Feature",
  "properties": {
    "gn:country":"PH",
    "gn:fcode":"PPLA3",
    "gn:population":0,
    "iso:country":"PH",
    "name:bcl_x_preferred":[
        "General Luna"
    ],
    "name:ceb_x_preferred":[
        "General Luna"
    ],
    "name:deu_x_preferred":[
        "General Luna"
    ],
    "name:eng_x_preferred":[
        "General Luna"
    ],
    "name:fil_x_preferred":[
        "Lunas"
    ],
    "name:fra_x_preferred":[
        "General Luna"
    ],
    "name:ilo_x_preferred":[
        "General Luna"
    ],
    "name:ind_x_preferred":[
        "General Luna"
    ],
    "name:ita_x_preferred":[
        "General Luna"
    ],
    "name:jpn_x_preferred":[
        "\u30b8\u30a7\u30cd\u30e9\u30eb\u30fb\u30eb\u30ca"
    ],
    "name:nld_x_preferred":[
        "General Luna"
    ],
    "name:nob_x_preferred":[
        "General Luna"
    ],
    "name:pag_x_preferred":[
        "General Luna"
    ],
    "name:pam_x_preferred":[
        "General Luna"
    ],
    "name:spa_x_preferred":[
        "General Luna de Cabuntug"
    ],
    "name:swe_x_preferred":[
        "General Luna"
    ],
    "name:tgl_x_preferred":[
        "General Luna"
    ],
    "name:und_x_variant":[
        "Cabuntug"
    ],
    "name:vie_x_preferred":[
        "General Luna"
    ],
    "name:war_x_preferred":[
        "General Luna"
    ],
    "qs:name":"General Luna",
    "qs:photos_9r":0,
    "qs:photos_sr":0,
    "qs:pop_sr":"4",
    "wd:wordcount":43,
    "wof:name":"General Luna",
    "wof:placetype":"locality",
    "wof:population":0
},
  "geometry": {"coordinates":[126.15889,9.78417],"type":"Point"}
}