{
  "type": "Feature",
  "properties": {
    "gn:admin1_code":"40",
    "gn:admin2_code":"H2",
    "gn:admin3_code":"45622000.0",
    "gn:asciiname":"Matinik",
    "gn:country_code":"PH",
    "gn:dem":48,
    "gn:feature_class":"P",
    "gn:feature_code":"PPL",
    "gn:name":"Matinik",
    "gn:population":0,
    "gn:timezone":"Asia/Manila",
    "iso:country":"PH",
    "name:fil_x_preferred":[
        "Matinik"
    ],
    "wof:name":"Matinik",
    "wof:placetype":"locality"
},
  "geometry": {"coordinates":[122.2467,13.941],"type":"Point"}
}