{
  "type": "Feature",
  "properties": {
    "gn:country":"PH",
    "gn:fcode":"PPLA3",
    "gn:pop":0,
    "iso:country":"PH",
    "name:bcl_x_preferred":[
        "Santo Domingo"
    ],
    "name:cat_x_preferred":[
        "Santo Domingo"
    ],
    "name:deu_x_preferred":[
        "Santo Domingo"
    ],
    "name:eng_x_preferred":[
        "Santo Domingo"
    ],
    "name:fra_x_preferred":[
        "Santo Domingo"
    ],
    "name:ilo_x_preferred":[
        "Santo Domingo"
    ],
    "name:ind_x_preferred":[
        "Santo Domingo"
    ],
    "name:ita_x_preferred":[
        "Santo Domingo"
    ],
    "name:nld_x_preferred":[
        "Santo Domingo"
    ],
    "name:oci_x_preferred":[
        "Santo Domingo"
    ],
    "name:pag_x_preferred":[
        "Santo Domingo"
    ],
    "name:pam_x_preferred":[
        "Santo Domingo"
    ],
    "name:spa_x_preferred":[
        "Santo Domingo"
    ],
    "name:swe_x_preferred":[
        "Santo Domingo"
    ],
    "name:tgl_x_preferred":[
        "Santo Domingo"
    ],
    "name:war_x_preferred":[
        "Santo Domingo"
    ],
    "name:zho_x_preferred":[
        "\u8056\u591a\u660e\u54e5"
    ],
    "qs:name":"Santo Domingo",
    "qs:photos_9r":0,
    "qs:photos_sr":0,
    "qs:pop_sr":"0",
    "wd:elevation":14.0,
    "wd:wordcount":5634,
    "wof:name":"Santo Domingo",
    "wof:placetype":"locality",
    "wof:population":0
},
  "geometry": {"coordinates":[120.41083,17.63528],"type":"Point"}
}