{
  "type": "Feature",
  "properties": {
    "gn:admin1_code":"03",
    "gn:admin2_code":"07",
    "gn:admin3_code":"30801000.0",
    "gn:asciiname":"Capitangan",
    "gn:country_code":"PH",
    "gn:dem":6,
    "gn:feature_class":"P",
    "gn:feature_code":"PPL",
    "gn:name":"Capita\u00f1gan",
    "gn:population":0,
    "gn:timezone":"Asia/Manila",
    "iso:country":"PH",
    "name:fil_x_preferred":[
        "Capita\u00f1gan"
    ],
    "wof:name":"Capitangan",
    "wof:placetype":"locality"
},
  "geometry": {"coordinates":[120.53610999999999,14.70778],"type":"Point"}
}