{
  "type": "Feature",
  "properties": {
    "gn:admin1_code":"12",
    "gn:admin2_code":"57",
    "gn:admin3_code":"124701000.0",
    "gn:asciiname":"Malitubog",
    "gn:country_code":"PH",
    "gn:dem":133,
    "gn:feature_class":"P",
    "gn:feature_code":"PPL",
    "gn:name":"Malitubog",
    "gn:population":0,
    "gn:timezone":"Asia/Manila",
    "iso:country":"PH",
    "name:fil_x_preferred":[
        "Malitubog"
    ],
    "wof:name":"Malitubog",
    "wof:placetype":"locality"
},
  "geometry": {"coordinates":[124.54083,7.40583],"type":"Point"}
}