{
  "type": "Feature",
  "properties": {
    "gn:country":"PH",
    "gn:fcode":"ADM3",
    "gn:population":49201,
    "iso:country":"PH",
    "name:bcl_x_preferred":[
        "Jose Maria Panganiban"
    ],
    "name:deu_x_preferred":[
        "Jose Maria Panganiban"
    ],
    "name:eng_x_preferred":[
        "Jos\u00e9 Mar\u00eda Panganiban"
    ],
    "name:fil_x_preferred":[
        "Jose Panganiban"
    ],
    "name:nld_x_preferred":[
        "Jose Maria Panganiban"
    ],
    "name:slv_x_preferred":[
        "Jose Maria Panganiban"
    ],
    "name:spa_x_preferred":[
        "Jos\u00e9 Mar\u00eda Panganiban"
    ],
    "name:tgl_x_preferred":[
        "Jos\u00e9 Mar\u00eda Panganiban"
    ],
    "name:und_x_variant":[
        "Mambulao"
    ],
    "name:vie_x_preferred":[
        "Jos\u00e9 Maria Panganiban"
    ],
    "qs:name":"Jose Panganiban",
    "qs:photos_9r":0,
    "qs:photos_sr":0,
    "qs:pop_sr":"7",
    "wd:wordcount":1401,
    "wof:name":"Jose Panganiban",
    "wof:placetype":"localadmin",
    "wof:population":49201
},
  "geometry": {"coordinates":[122.65954000000001,14.25316],"type":"Point"}
}