{
  "type": "Feature",
  "properties": {
    "gn:country":"PH",
    "gn:fcode":"ADM3",
    "gn:pop":12823,
    "iso:country":"PH",
    "name:ceb_x_preferred":[
        "Julita"
    ],
    "name:swe_x_preferred":[
        "Julita"
    ],
    "qs:name":"Julita",
    "qs:photos_9r":0,
    "qs:photos_sr":0,
    "qs:pop_sr":"6",
    "wd:wordcount":46,
    "wof:name":"Julita",
    "wof:placetype":"localadmin",
    "wof:population":12823
},
  "geometry": {"coordinates":[124.96666999999999,10.96667],"type":"Point"}
}