{
  "type": "Feature",
  "properties": {
    "iso:country":"PH",
    "name:bcl_x_preferred":[
        "Banga"
    ],
    "name:deu_x_preferred":[
        "Banga"
    ],
    "name:eng_x_preferred":[
        "Banga"
    ],
    "name:fas_x_preferred":[
        "\u0628\u0646\u06af\u0627\u060c \u06a9\u0648\u062a\u0627\u0628\u0627\u062a\u0648 \u062c\u0646\u0648\u0628\u06cc"
    ],
    "name:fil_x_preferred":[
        "Ba\u00f1ga"
    ],
    "name:fra_x_preferred":[
        "Banga"
    ],
    "name:ilo_x_preferred":[
        "Banga"
    ],
    "name:ind_x_preferred":[
        "Banga"
    ],
    "name:ita_x_preferred":[
        "Banga"
    ],
    "name:msa_x_preferred":[
        "Banga"
    ],
    "name:nld_x_preferred":[
        "Banga"
    ],
    "name:pag_x_preferred":[
        "Banga"
    ],
    "name:pam_x_preferred":[
        "Banga"
    ],
    "name:spa_x_preferred":[
        "Banga de Cotabato"
    ],
    "name:swe_x_preferred":[
        "Banga"
    ],
    "name:tgl_x_preferred":[
        "Banga"
    ],
    "name:vie_x_preferred":[
        "Banga"
    ],
    "name:war_x_preferred":[
        "Banga"
    ],
    "qs:gn_country":"PH",
    "qs:gn_fcode":"PPL",
    "qs:gn_pop":58855,
    "qs:name":"Ba\u00f1ga",
    "qs:name_adm0":"Philippines",
    "qs:name_adm1":"Soccsksargen",
    "qs:photos":0,
    "qs:photos_1k":0,
    "qs:photos_9k":1,
    "qs:photos_9r":1,
    "qs:photos_all":9,
    "qs:photos_sr":0,
    "qs:placetype":"Town",
    "qs:pop_sr":"8",
    "qs:woe_adm0":23424934,
    "wof:name":"Ba\u00f1ga",
    "wof:placetype":"locality",
    "wof:population":58855
},
  "geometry": {"coordinates":[124.77833,6.42389],"type":"Point"}
}