{
  "type": "Feature",
  "properties": {
    "gn:admin1_code":"05",
    "gn:admin2_code":"16",
    "gn:admin3_code":"51705000.0",
    "gn:asciiname":"San Jose",
    "gn:country_code":"PH",
    "gn:dem":289,
    "gn:feature_class":"P",
    "gn:feature_code":"PPL",
    "gn:name":"San Jose",
    "gn:population":0,
    "gn:timezone":"Asia/Manila",
    "iso:country":"PH",
    "name:fil_x_preferred":[
        "San Jose"
    ],
    "wof:name":"San Jose",
    "wof:placetype":"locality"
},
  "geometry": {"coordinates":[123.55,13.36667],"type":"Point"}
}