{
  "type": "Feature",
  "properties": {
    "gn:admin1_code":"13",
    "gn:admin2_code":"02",
    "gn:admin3_code":"160207000.0",
    "gn:asciiname":"Mat-i",
    "gn:country_code":"PH",
    "gn:dem":18,
    "gn:feature_class":"P",
    "gn:feature_code":"PPL",
    "gn:name":"Mat-i",
    "gn:population":0,
    "gn:timezone":"Asia/Manila",
    "iso:country":"PH",
    "name:fil_x_preferred":[
        "Mat-i"
    ],
    "wof:name":"Mat-i",
    "wof:placetype":"locality"
},
  "geometry": {"coordinates":[125.58861,8.70833],"type":"Point"}
}