{
  "type": "Feature",
  "properties": {
    "gn:admin1_code":"08",
    "gn:admin2_code":"37",
    "gn:admin3_code":"83739000.0",
    "gn:asciiname":"Anahaway",
    "gn:cc2":"PH",
    "gn:country_code":"PH",
    "gn:dem":22,
    "gn:feature_class":"P",
    "gn:feature_code":"PPL",
    "gn:name":"Anahaway",
    "gn:population":0,
    "gn:timezone":"Asia/Manila",
    "iso:country":"PH",
    "name:und_x_variant":[
        "Anahauay",
        "Anahaway"
    ],
    "wof:name":"Anahaway",
    "wof:placetype":"locality"
},
  "geometry": {"coordinates":[124.94777999999999,11.15278],"type":"Point"}
}