{
  "type": "Feature",
  "properties": {
    "gn:admin1_code":"41",
    "gn:admin2_code":"49",
    "gn:admin3_code":"175301000.0",
    "gn:asciiname":"Bay",
    "gn:country_code":"PH",
    "gn:dem":8,
    "gn:feature_class":"P",
    "gn:feature_code":"PPL",
    "gn:name":"Bay",
    "gn:population":0,
    "gn:timezone":"Asia/Manila",
    "iso:country":"PH",
    "name:fil_x_preferred":[
        "Bay"
    ],
    "wof:name":"Bay",
    "wof:placetype":"locality"
},
  "geometry": {"coordinates":[118.5984,9.49435],"type":"Point"}
}