{
  "type": "Feature",
  "properties": {
    "gn:admin1_code":"01",
    "gn:admin2_code":"51",
    "gn:admin3_code":"15531000.0",
    "gn:asciiname":"Balincanaway",
    "gn:country_code":"PH",
    "gn:dem":35,
    "gn:feature_class":"P",
    "gn:feature_code":"PPL",
    "gn:name":"Balincanaway",
    "gn:population":0,
    "gn:timezone":"Asia/Manila",
    "iso:country":"PH",
    "name:fil_x_preferred":[
        "Balincanaway"
    ],
    "wof:name":"Balincanaway",
    "wof:placetype":"locality"
},
  "geometry": {"coordinates":[120.65797999999999,15.89181],"type":"Point"}
}