{
  "type": "Feature",
  "properties": {
    "gn:admin1_code":"41",
    "gn:admin2_code":"40",
    "gn:admin3_code":"175104000.0",
    "gn:asciiname":"Malonglong",
    "gn:country_code":"PH",
    "gn:dem":9,
    "gn:feature_class":"P",
    "gn:feature_code":"PPL",
    "gn:name":"Malonglong",
    "gn:population":0,
    "gn:timezone":"Asia/Manila",
    "iso:country":"PH",
    "name:fil_x_preferred":[
        "Malonglong"
    ],
    "wof:name":"Malonglong",
    "wof:placetype":"locality"
},
  "geometry": {"coordinates":[120.09999999999999,13.85],"type":"Point"}
}