{
  "type": "Feature",
  "properties": {
    "gn:admin1_code":"05",
    "gn:admin2_code":"15",
    "gn:admin3_code":"51603000.0",
    "gn:asciiname":"Pininganan",
    "gn:country_code":"PH",
    "gn:dem":24,
    "gn:feature_class":"P",
    "gn:feature_code":"PPL",
    "gn:name":"Pininganan",
    "gn:population":0,
    "gn:timezone":"Asia/Manila",
    "iso:country":"PH",
    "name:fil_x_preferred":[
        "Pininganan"
    ],
    "wof:name":"Pininganan",
    "wof:placetype":"locality"
},
  "geometry": {"coordinates":[122.9148,14.1067],"type":"Point"}
}