{
  "type": "Feature",
  "properties": {
    "gn:admin1_code":"40",
    "gn:admin2_code":"53",
    "gn:admin3_code":"45814000.0",
    "gn:asciiname":"Pantay",
    "gn:country_code":"PH",
    "gn:dem":53,
    "gn:feature_class":"P",
    "gn:feature_code":"PPL",
    "gn:name":"Pantay",
    "gn:population":0,
    "gn:timezone":"Asia/Manila",
    "iso:country":"PH",
    "name:fil_x_preferred":[
        "Pantay"
    ],
    "wof:name":"Pantay",
    "wof:placetype":"locality"
},
  "geometry": {"coordinates":[121.23,14.56111],"type":"Point"}
}