{
  "type": "Feature",
  "properties": {
    "gn:admin1_code":"05",
    "gn:admin2_code":"16",
    "gn:admin3_code":"51711000.0",
    "gn:asciiname":"Pagolinan",
    "gn:country_code":"PH",
    "gn:dem":9,
    "gn:feature_class":"P",
    "gn:feature_code":"PPL",
    "gn:name":"Pagolinan",
    "gn:population":0,
    "gn:timezone":"Asia/Manila",
    "iso:country":"PH",
    "name:fil_x_preferred":[
        "Pagolinan"
    ],
    "wof:name":"Pagolinan",
    "wof:placetype":"locality"
},
  "geometry": {"coordinates":[123.85039999999999,13.7174],"type":"Point"}
}