{
  "type": "Feature",
  "properties": {
    "gn:admin1_code":"13",
    "gn:admin2_code":"61",
    "gn:admin3_code":"166706000.0",
    "gn:asciiname":"Nuevo Campo",
    "gn:country_code":"PH",
    "gn:dem":26,
    "gn:feature_class":"P",
    "gn:feature_code":"PPL",
    "gn:name":"Nuevo Campo",
    "gn:population":0,
    "gn:timezone":"Asia/Manila",
    "iso:country":"PH",
    "name:und_x_variant":[
        "Nuevo Camp",
        "Nuero Campo",
        "Nuevo Campo",
        "Nuevo Campo Inferior"
    ],
    "wof:name":"Nuevo Campo",
    "wof:placetype":"locality"
},
  "geometry": {"coordinates":[125.7308,9.5337],"type":"Point"}
}