{
  "type": "Feature",
  "properties": {
    "gn:admin1_code":"15",
    "gn:admin2_code":"27",
    "gn:admin3_code":"142705000.0",
    "gn:asciiname":"Payawan",
    "gn:country_code":"PH",
    "gn:dem":276,
    "gn:feature_class":"P",
    "gn:feature_code":"PPL",
    "gn:name":"Payawan",
    "gn:population":0,
    "gn:timezone":"Asia/Manila",
    "iso:country":"PH",
    "name:fil_x_preferred":[
        "Payawan"
    ],
    "wof:name":"Payawan",
    "wof:placetype":"locality"
},
  "geometry": {"coordinates":[121.19183999999998,16.68987000000001],"type":"Point"}
}