{
  "type": "Feature",
  "properties": {
    "gn:admin1_code":"08",
    "gn:admin2_code":"67",
    "gn:admin3_code":"84822000.0",
    "gn:asciiname":"Giparayan",
    "gn:country_code":"PH",
    "gn:dem":33,
    "gn:feature_class":"P",
    "gn:feature_code":"PPL",
    "gn:name":"Giparayan",
    "gn:population":0,
    "gn:timezone":"Asia/Manila",
    "iso:country":"PH",
    "name:fil_x_preferred":[
        "Giparayan"
    ],
    "wof:name":"Giparayan",
    "wof:placetype":"locality"
},
  "geometry": {"coordinates":[124.8931,12.3209],"type":"Point"}
}