{
  "type": "Feature",
  "properties": {
    "gn:gn_country":"PH",
    "gn:gn_fcode":"ADM3",
    "gn:gn_pop":193996,
    "gn:population":193996,
    "iso:country":"PH",
    "name:fil_x_preferred":[
        "Mabalacat"
    ],
    "qs_pg:aaroncc":"PH",
    "qs_pg:gn_country":"PH",
    "qs_pg:gn_fcode":"ADM3",
    "qs_pg:gn_pop":193996,
    "qs_pg:name":"Mabalacat",
    "qs_pg:photos_9r":0,
    "qs_pg:photos_sr":0,
    "qs_pg:pop_sr":9,
    "qs_pg:qs_pg_placetype":"localadmin",
    "wof:name":"Mabalacat",
    "wof:placetype":"localadmin",
    "wof:population":193996
},
  "geometry": {"coordinates":[120.55,15.21667],"type":"Point"}
}