{
  "type": "Feature",
  "properties": {
    "gn:gn_country":"PH",
    "gn:gn_fcode":"ADM3",
    "gn:gn_pop":193996,
    "gn:population":193996,
    "iso:country":"PH",
    "name:ara_x_preferred":[
        "\u0645\u0627\u0628\u0627\u0644\u0627\u0643\u0627\u062a"
    ],
    "name:bcl_x_preferred":[
        "Mabalacat"
    ],
    "name:ceb_x_preferred":[
        "Mabalacat"
    ],
    "name:deu_x_preferred":[
        "Mabalacat"
    ],
    "name:ell_x_preferred":[
        "\u039c\u03b1\u03bc\u03c0\u03b1\u03bb\u03b1\u03ba\u03ac\u03c4"
    ],
    "name:fil_x_preferred":[
        "Mabalacat"
    ],
    "name:fra_x_preferred":[
        "Mabalacat"
    ],
    "name:ilo_x_preferred":[
        "Mabalacat"
    ],
    "name:ind_x_preferred":[
        "Mabalacat"
    ],
    "name:ita_x_preferred":[
        "Mabalacat"
    ],
    "name:jpn_x_preferred":[
        "\u30de\u30d0\u30e9\u30ab\u30c3\u30c8"
    ],
    "name:nld_x_preferred":[
        "Mabalacat"
    ],
    "name:nor_x_preferred":[
        "Mabalacat"
    ],
    "name:pag_x_preferred":[
        "Mabalacat"
    ],
    "name:pam_x_preferred":[
        "Mabalacat"
    ],
    "name:pol_x_preferred":[
        "Mabalacat"
    ],
    "name:spa_x_preferred":[
        "Mabal\u00e1cat"
    ],
    "name:swe_x_preferred":[
        "Mabalacat"
    ],
    "name:tgl_x_preferred":[
        "Mabalacat"
    ],
    "name:urd_x_preferred":[
        "\u0645\u0627\u0628\u0627\u0644\u0627\u06a9\u0627\u062a"
    ],
    "name:vie_x_preferred":[
        "Mabalacat"
    ],
    "name:war_x_preferred":[
        "Mabalacat"
    ],
    "qs_pg:aaroncc":"PH",
    "qs_pg:gn_country":"PH",
    "qs_pg:gn_fcode":"ADM3",
    "qs_pg:gn_pop":193996,
    "qs_pg:name":"Mabalacat",
    "qs_pg:photos_9r":0,
    "qs_pg:photos_sr":0,
    "qs_pg:pop_sr":9,
    "qs_pg:qs_pg_placetype":"localadmin",
    "wof:name":"Mabalacat",
    "wof:placetype":"localadmin",
    "wof:population":193996
},
  "geometry": {"coordinates":[120.55,15.21667],"type":"Point"}
}