{
  "type": "Feature",
  "properties": {
    "gn:admin1_code":"08",
    "gn:admin2_code":"23",
    "gn:admin3_code":"82619000.0",
    "gn:asciiname":"Jagnaya",
    "gn:country_code":"PH",
    "gn:dem":19,
    "gn:feature_class":"P",
    "gn:feature_code":"PPL",
    "gn:name":"Jagnaya",
    "gn:population":0,
    "gn:timezone":"Asia/Manila",
    "iso:country":"PH",
    "name:fil_x_preferred":[
        "Jagnaya"
    ],
    "wof:name":"Jagnaya",
    "wof:placetype":"locality"
},
  "geometry": {"coordinates":[125.68389000000001,11.1575],"type":"Point"}
}