{
  "type": "Feature",
  "properties": {
    "gn:admin1_code":"01",
    "gn:admin2_code":"36",
    "gn:admin3_code":"13314000.0",
    "gn:asciiname":"Pacpaco",
    "gn:country_code":"PH",
    "gn:dem":336,
    "gn:feature_class":"P",
    "gn:feature_code":"PPL",
    "gn:name":"Pacpaco",
    "gn:population":0,
    "gn:timezone":"Asia/Manila",
    "iso:country":"PH",
    "name:fil_x_preferred":[
        "Pacpaco"
    ],
    "wof:name":"Pacpaco",
    "wof:placetype":"locality"
},
  "geometry": {"coordinates":[120.41667,16.61667000000001],"type":"Point"}
}