{
  "type": "Feature",
  "properties": {
    "gn:admin1_code":"10",
    "gn:admin2_code":"34",
    "gn:admin3_code":"103502000.0",
    "gn:asciiname":"Batangan",
    "gn:country_code":"PH",
    "gn:dem":371,
    "gn:feature_class":"P",
    "gn:feature_code":"PPL",
    "gn:name":"Batangan",
    "gn:population":0,
    "gn:timezone":"Asia/Manila",
    "iso:country":"PH",
    "name:fil_x_preferred":[
        "Batangan"
    ],
    "wof:name":"Batangan",
    "wof:placetype":"locality"
},
  "geometry": {"coordinates":[124.19722,8.11861],"type":"Point"}
}