{
  "type": "Feature",
  "properties": {
    "gn:admin1_code":"41",
    "gn:admin2_code":"49",
    "gn:admin3_code":"175307000.0",
    "gn:asciiname":"Longon",
    "gn:country_code":"PH",
    "gn:dem":17,
    "gn:feature_class":"P",
    "gn:feature_code":"PPL",
    "gn:name":"Longon",
    "gn:population":0,
    "gn:timezone":"Asia/Manila",
    "iso:country":"PH",
    "name:eng_x_preferred":[
        "Longon"
    ],
    "wof:name":"Longon",
    "wof:placetype":"locality"
},
  "geometry": {"coordinates":[120.00711,12.24106],"type":"Point"}
}