{
  "type": "Feature",
  "properties": {
    "gn:admin1_code":"11",
    "gn:admin2_code":"I7",
    "gn:admin3_code":"112317000.0",
    "gn:asciiname":"Basao",
    "gn:cc2":"PH",
    "gn:country_code":"PH",
    "gn:dem":37,
    "gn:feature_class":"P",
    "gn:feature_code":"PPL",
    "gn:name":"Basao",
    "gn:population":0,
    "gn:timezone":"Asia/Manila",
    "iso:country":"PH",
    "name:und_x_variant":[
        "Bassao",
        "Basao"
    ],
    "wof:name":"Basao",
    "wof:placetype":"locality"
},
  "geometry": {"coordinates":[125.69806,7.16833],"type":"Point"}
}