{
  "type": "Feature",
  "properties": {
    "gn:admin1_code":"01",
    "gn:admin2_code":"51",
    "gn:admin3_code":"15507000.0",
    "gn:asciiname":"Kita Kita",
    "gn:country_code":"PH",
    "gn:dem":44,
    "gn:feature_class":"P",
    "gn:feature_code":"PPL",
    "gn:name":"Kita Kita",
    "gn:population":0,
    "gn:timezone":"Asia/Manila",
    "iso:country":"PH",
    "name:fil_x_preferred":[
        "Kitakita"
    ],
    "name:fin_x_preferred":[
        "Kita Kita"
    ],
    "wof:name":"Kita Kita",
    "wof:placetype":"locality"
},
  "geometry": {"coordinates":[120.66349,15.89269],"type":"Point"}
}