{
  "type": "Feature",
  "properties": {
    "gn:admin1_code":"05",
    "gn:admin2_code":"05",
    "gn:admin3_code":"50511000.0",
    "gn:asciiname":"Tinapian",
    "gn:country_code":"PH",
    "gn:dem":15,
    "gn:feature_class":"P",
    "gn:feature_code":"PPL",
    "gn:name":"Tinapian",
    "gn:population":0,
    "gn:timezone":"Asia/Manila",
    "iso:country":"PH",
    "name:fil_x_preferred":[
        "Tinapian"
    ],
    "wof:name":"Tinapian",
    "wof:placetype":"locality"
},
  "geometry": {"coordinates":[123.8387,13.1016],"type":"Point"}
}