{
  "type": "Feature",
  "properties": {
    "gn:admin1_code":"08",
    "gn:admin2_code":"59",
    "gn:admin3_code":"86408000.0",
    "gn:asciiname":"Buscayan",
    "gn:country_code":"PH",
    "gn:dem":45,
    "gn:feature_class":"P",
    "gn:feature_code":"PPL",
    "gn:name":"Buscayan",
    "gn:population":0,
    "gn:timezone":"Asia/Manila",
    "iso:country":"PH",
    "name:und_x_variant":[
        "Biscayan",
        "Buscayan"
    ],
    "wof:name":"Buscayan",
    "wof:placetype":"locality"
},
  "geometry": {"coordinates":[124.96989000000001,10.05218],"type":"Point"}
}