{
  "type": "Feature",
  "properties": {
    "gn:admin1_code":"09",
    "gn:admin2_code":"ZSI",
    "gn:admin3_code":"98306000.0",
    "gn:asciiname":"Mangahas",
    "gn:country_code":"PH",
    "gn:dem":19,
    "gn:feature_class":"P",
    "gn:feature_code":"PPL",
    "gn:name":"Mangahas",
    "gn:population":0,
    "gn:timezone":"Asia/Manila",
    "iso:country":"PH",
    "name:fil_x_preferred":[
        "Mangahas"
    ],
    "wof:name":"Mangahas",
    "wof:placetype":"locality"
},
  "geometry": {"coordinates":[122.78556,7.79333],"type":"Point"}
}