{
  "type": "Feature",
  "properties": {
    "gn:admin1_code":"41",
    "gn:admin2_code":"49",
    "gn:admin3_code":"175305000.0",
    "gn:asciiname":"Sapa",
    "gn:country_code":"PH",
    "gn:dem":14,
    "gn:feature_class":"P",
    "gn:feature_code":"PPL",
    "gn:name":"Sapa",
    "gn:population":0,
    "gn:timezone":"Asia/Manila",
    "iso:country":"PH",
    "name:ceb_x_preferred":[
        "Sapa"
    ],
    "name:deu_x_preferred":[
        "Sapa"
    ],
    "name:eng_x_preferred":[
        "Sapa"
    ],
    "name:ita_x_preferred":[
        "Sapa"
    ],
    "name:nld_x_preferred":[
        "Sapa"
    ],
    "name:nor_x_preferred":[
        "Sapa"
    ],
    "name:pol_x_preferred":[
        "Sapa"
    ],
    "name:swe_x_preferred":[
        "Sapa"
    ],
    "name:und_x_variant":[
        "Coral"
    ],
    "wof:name":"Sapa",
    "wof:placetype":"locality"
},
  "geometry": {"coordinates":[117.28619,8.44353],"type":"Point"}
}