{
  "type": "Feature",
  "properties": {
    "gn:admin1_code":"40",
    "gn:admin2_code":"09",
    "gn:admin3_code":"41029000.0",
    "gn:asciiname":"Buli",
    "gn:country_code":"PH",
    "gn:dem":140,
    "gn:feature_class":"P",
    "gn:feature_code":"PPL",
    "gn:name":"Buli",
    "gn:population":0,
    "gn:timezone":"Asia/Manila",
    "iso:country":"PH",
    "name:fil_x_preferred":[
        "Buli"
    ],
    "wof:name":"Buli",
    "wof:placetype":"locality"
},
  "geometry": {"coordinates":[120.96016000000002,13.88196],"type":"Point"}
}