{
  "type": "Feature",
  "properties": {
    "gn:admin1_code":"14",
    "gn:admin2_code":"60",
    "gn:asciiname":"Kangkanga Kamawi",
    "gn:country_code":"PH",
    "gn:dem":3,
    "gn:feature_class":"P",
    "gn:feature_code":"PPL",
    "gn:name":"Kangkanga Kamawi",
    "gn:population":0,
    "gn:timezone":"Asia/Manila",
    "iso:country":"PH",
    "name:und_x_variant":[
        "Kangkanga Kamowi",
        "Kangkanga Kamawi"
    ],
    "wof:name":"Kangkanga Kamawi",
    "wof:placetype":"locality"
},
  "geometry": {"coordinates":[121.20197,5.81868],"type":"Point"}
}