{
  "type": "Feature",
  "properties": {
    "gn:admin1_code":"06",
    "gn:admin2_code":"06",
    "gn:admin3_code":"60609000.0",
    "gn:asciiname":"Lugta",
    "gn:country_code":"PH",
    "gn:dem":54,
    "gn:feature_class":"P",
    "gn:feature_code":"PPL",
    "gn:name":"Lugta",
    "gn:population":0,
    "gn:timezone":"Asia/Manila",
    "iso:country":"PH",
    "name:fil_x_preferred":[
        "Lugta"
    ],
    "wof:name":"Lugta",
    "wof:placetype":"locality"
},
  "geometry": {"coordinates":[122.05,11.15],"type":"Point"}
}