{
  "type": "Feature",
  "properties": {
    "gn:admin1_code":"03",
    "gn:admin2_code":"63",
    "gn:admin3_code":"36914000.0",
    "gn:asciiname":"Mangandingay",
    "gn:country_code":"PH",
    "gn:dem":22,
    "gn:feature_class":"P",
    "gn:feature_code":"PPL",
    "gn:name":"Mangandingay",
    "gn:population":0,
    "gn:timezone":"Asia/Manila",
    "iso:country":"PH",
    "name:fil_x_preferred":[
        "Mangandingay"
    ],
    "wof:name":"Mangandingay",
    "wof:placetype":"locality"
},
  "geometry": {"coordinates":[120.58069,15.81452],"type":"Point"}
}