{
  "type": "Feature",
  "properties": {
    "gn:admin1_code":"40",
    "gn:admin2_code":"20",
    "gn:admin3_code":"42110000.0",
    "gn:asciiname":"Agus-us",
    "gn:country_code":"PH",
    "gn:dem":219,
    "gn:feature_class":"P",
    "gn:feature_code":"PPL",
    "gn:name":"Agus-us",
    "gn:population":0,
    "gn:timezone":"Asia/Manila",
    "iso:country":"PH",
    "wof:name":"Agus-us",
    "wof:placetype":"locality"
},
  "geometry": {"coordinates":[120.85930999999999,14.22467],"type":"Point"}
}