{
  "type": "Feature",
  "properties": {
    "gn:admin1_code":"07",
    "gn:admin2_code":"21",
    "gn:admin3_code":"72205000.0",
    "gn:asciiname":"Canbanua",
    "gn:country_code":"PH",
    "gn:dem":20,
    "gn:feature_class":"P",
    "gn:feature_code":"PPL",
    "gn:name":"Canbanua",
    "gn:population":0,
    "gn:timezone":"Asia/Manila",
    "iso:country":"PH",
    "wof:name":"Canbanua",
    "wof:placetype":"locality"
},
  "geometry": {"coordinates":[123.58920000000001,9.88832],"type":"Point"}
}