{
  "type": "Feature",
  "properties": {
    "gn:admin1_code":"01",
    "gn:admin2_code":"36",
    "gn:admin3_code":"13318000.0",
    "gn:asciiname":"Boncayo",
    "gn:country_code":"PH",
    "gn:dem":36,
    "gn:feature_class":"P",
    "gn:feature_code":"PPL",
    "gn:name":"Boncayo",
    "gn:population":0,
    "gn:timezone":"Asia/Manila",
    "iso:country":"PH",
    "name:fil_x_preferred":[
        "Boncayo"
    ],
    "name:fil_x_variant":[
        "Bungcayo"
    ],
    "wof:name":"Boncayo",
    "wof:placetype":"locality"
},
  "geometry": {"coordinates":[120.44410000000001,16.7947],"type":"Point"}
}