{
  "type": "Feature",
  "properties": {
    "gn:country":"PH",
    "gn:fcode":"PPL",
    "gn:pop":2120,
    "iso:country":"PH",
    "name:fil_x_preferred":[
        "Bagu"
    ],
    "qs:name":"Bagu",
    "qs:photos_9r":0,
    "qs:photos_sr":0,
    "qs:pop_sr":"4",
    "wof:name":"Bagu",
    "wof:placetype":"locality",
    "wof:population":2120
},
  "geometry": {"coordinates":[121.35572999999999,18.42441],"type":"Point"}
}