{
  "type": "Feature",
  "properties": {
    "gn:admin1_code":"12",
    "gn:admin2_code":"57",
    "gn:admin3_code":"124703000.0",
    "gn:asciiname":"Buluan",
    "gn:country_code":"PH",
    "gn:dem":24,
    "gn:feature_class":"P",
    "gn:feature_code":"PPL",
    "gn:name":"Buluan",
    "gn:population":0,
    "gn:timezone":"Asia/Manila",
    "iso:country":"PH",
    "name:fil_x_preferred":[
        "Buluan"
    ],
    "wof:name":"Buluan",
    "wof:placetype":"locality"
},
  "geometry": {"coordinates":[124.81278,7.20194],"type":"Point"}
}