{
  "type": "Feature",
  "properties": {
    "gn:admin1_code":"06",
    "gn:admin2_code":"H3",
    "gn:admin3_code":"64503000.0",
    "gn:asciiname":"Visita Alegre",
    "gn:country_code":"PH",
    "gn:dem":12,
    "gn:feature_class":"P",
    "gn:feature_code":"PPL",
    "gn:name":"Visita Alegre",
    "gn:population":0,
    "gn:timezone":"Asia/Manila",
    "iso:country":"PH",
    "name:fil_x_preferred":[
        "Visita Alegre"
    ],
    "name:und_x_variant":[
        "Vista Alegre"
    ],
    "wof:name":"Visita Alegre",
    "wof:placetype":"locality"
},
  "geometry": {"coordinates":[122.8449,10.2051],"type":"Point"}
}