{
  "type": "Feature",
  "properties": {
    "gn:admin1_code":"40",
    "gn:admin2_code":"H2",
    "gn:admin3_code":"45646000.0",
    "gn:asciiname":"Kabugwang",
    "gn:country_code":"PH",
    "gn:dem":6,
    "gn:feature_class":"P",
    "gn:feature_code":"PPL",
    "gn:name":"Kabugwang",
    "gn:population":0,
    "gn:timezone":"Asia/Manila",
    "iso:country":"PH",
    "name:fil_x_preferred":[
        "Kabugwang"
    ],
    "wof:name":"Kabugwang",
    "wof:placetype":"locality"
},
  "geometry": {"coordinates":[122.3819,13.9943],"type":"Point"}
}