{
  "type": "Feature",
  "properties": {
    "gn:admin1_code":"14",
    "gn:admin2_code":"35",
    "gn:admin3_code":"153617000.0",
    "gn:asciiname":"Marinaut",
    "gn:country_code":"PH",
    "gn:dem":710,
    "gn:feature_class":"P",
    "gn:feature_code":"PPL",
    "gn:name":"Marinaut",
    "gn:population":0,
    "gn:timezone":"Asia/Manila",
    "iso:country":"PH",
    "name:fil_x_preferred":[
        "Marinaut"
    ],
    "name:fil_x_variant":[
        "Marinaot"
    ],
    "wof:name":"Marinaut",
    "wof:placetype":"locality"
},
  "geometry": {"coordinates":[124.29583,7.99278],"type":"Point"}
}