{
  "type": "Feature",
  "properties": {
    "gn:admin1_code":"15",
    "gn:admin2_code":"01",
    "gn:admin3_code":"140127000.0",
    "gn:asciiname":"Lang-Ayan",
    "gn:country_code":"PH",
    "gn:dem":597,
    "gn:feature_class":"P",
    "gn:feature_code":"PPL",
    "gn:name":"Lang-Ayan",
    "gn:population":0,
    "gn:timezone":"Asia/Manila",
    "iso:country":"PH",
    "name:fil_x_preferred":[
        "Lang-Ayan"
    ],
    "name:fil_x_variant":[
        "Langoyan"
    ],
    "wof:name":"Lang-Ayan",
    "wof:placetype":"locality"
},
  "geometry": {"coordinates":[120.6065,17.3074],"type":"Point"}
}