{
  "type": "Feature",
  "properties": {
    "gn:admin1_code":"41",
    "gn:admin2_code":"41",
    "gn:admin3_code":"175205000.0",
    "gn:asciiname":"Bucayao",
    "gn:country_code":"PH",
    "gn:dem":7,
    "gn:feature_class":"P",
    "gn:feature_code":"PPL",
    "gn:name":"Bucayao",
    "gn:population":0,
    "gn:timezone":"Asia/Manila",
    "iso:country":"PH",
    "name:fil_x_preferred":[
        "Bucayao"
    ],
    "wof:name":"Bucayao",
    "wof:placetype":"locality"
},
  "geometry": {"coordinates":[121.18333,13.41667],"type":"Point"}
}