{
  "type": "Feature",
  "properties": {
    "iso:country":"PH",
    "name:bcl_x_preferred":[
        "Dauis"
    ],
    "name:ceb_x_preferred":[
        "Dauis"
    ],
    "name:deu_x_preferred":[
        "Dauis"
    ],
    "name:eng_x_preferred":[
        "Dauis"
    ],
    "name:fra_x_preferred":[
        "Dauis"
    ],
    "name:ilo_x_preferred":[
        "Dauis"
    ],
    "name:ind_x_preferred":[
        "Dauis"
    ],
    "name:ita_x_preferred":[
        "Dauis"
    ],
    "name:jpn_x_preferred":[
        "\u30c0\u30a6\u30a4\u30b9"
    ],
    "name:nld_x_preferred":[
        "Dauis"
    ],
    "name:nob_x_preferred":[
        "Dauis"
    ],
    "name:pag_x_preferred":[
        "Dauis"
    ],
    "name:pam_x_preferred":[
        "Dauis"
    ],
    "name:swe_x_preferred":[
        "Dauis"
    ],
    "name:tgl_x_preferred":[
        "Dauis"
    ],
    "name:und_x_variant":[
        "Davis Union"
    ],
    "name:urd_x_preferred":[
        "\u062f\u0627\u0648\u06cc\u0633"
    ],
    "name:vie_x_preferred":[
        "Dauis"
    ],
    "name:war_x_preferred":[
        "Dauis"
    ],
    "name:zho_x_preferred":[
        "\u9053\u4f0a\u65af"
    ],
    "qs:gn_country":"PH",
    "qs:gn_fcode":"PPLA3",
    "qs:gn_pop":2553,
    "qs:name":"Dauis",
    "qs:name_adm0":"Philippines",
    "qs:name_adm1":"Central Visayas",
    "qs:photos":970,
    "qs:photos_1k":197,
    "qs:photos_9k":4,
    "qs:photos_9r":6,
    "qs:photos_all":970,
    "qs:photos_sr":10,
    "qs:placetype":"Town",
    "qs:pop_sr":"4",
    "qs:woe_adm0":23424934,
    "wof:name":"Dauis",
    "wof:placetype":"locality",
    "wof:population":2553
},
  "geometry": {"coordinates":[123.86583,9.62528],"type":"Point"}
}