{
  "type": "Feature",
  "properties": {
    "gn:admin1_code":"41",
    "gn:admin2_code":"38",
    "gn:admin3_code":"174003000.0",
    "gn:asciiname":"Dawis",
    "gn:country_code":"PH",
    "gn:dem":20,
    "gn:feature_class":"P",
    "gn:feature_code":"PPL",
    "gn:name":"Dawis",
    "gn:population":0,
    "gn:timezone":"Asia/Manila",
    "iso:country":"PH",
    "name:fil_x_preferred":[
        "Dawis"
    ],
    "name:fil_x_variant":[
        "Dauis"
    ],
    "name:und_x_variant":[
        "Dauis"
    ],
    "wof:name":"Dawis",
    "wof:placetype":"locality"
},
  "geometry": {"coordinates":[121.88928,13.28486],"type":"Point"}
}