{
  "type": "Feature",
  "properties": {
    "gn:admin1_code":"06",
    "gn:admin2_code":"H3",
    "gn:admin3_code":"64513000.0",
    "gn:asciiname":"Bogotban",
    "gn:country_code":"PH",
    "gn:dem":325,
    "gn:feature_class":"P",
    "gn:feature_code":"PPL",
    "gn:name":"Bogotban",
    "gn:population":0,
    "gn:timezone":"Asia/Manila",
    "iso:country":"PH",
    "name:fil_x_preferred":[
        "Bogotban"
    ],
    "wof:name":"Bogotban",
    "wof:placetype":"locality"
},
  "geometry": {"coordinates":[122.6983,9.6516],"type":"Point"}
}