{
  "type": "Feature",
  "properties": {
    "gn:admin1_code":"40",
    "gn:admin2_code":"09",
    "gn:admin3_code":"41022000.0",
    "gn:asciiname":"Lalayat",
    "gn:country_code":"PH",
    "gn:dem":202,
    "gn:feature_class":"P",
    "gn:feature_code":"PPL",
    "gn:name":"Lalayat",
    "gn:population":0,
    "gn:timezone":"Asia/Manila",
    "iso:country":"PH",
    "name:fil_x_preferred":[
        "Lalayat"
    ],
    "wof:name":"Lalayat",
    "wof:placetype":"locality"
},
  "geometry": {"coordinates":[121.0801,13.8634],"type":"Point"}
}