{
  "type": "Feature",
  "properties": {
    "gn:admin1_code":"15",
    "gn:admin2_code":"32",
    "gn:admin3_code":"143209000.0",
    "gn:asciiname":"Asa",
    "gn:country_code":"PH",
    "gn:dem":266,
    "gn:feature_class":"P",
    "gn:feature_code":"PPL",
    "gn:name":"Asa",
    "gn:population":0,
    "gn:timezone":"Asia/Manila",
    "iso:country":"PH",
    "name:cat_x_preferred":[
        "Asa"
    ],
    "name:ceb_x_preferred":[
        "Asa"
    ],
    "name:fil_x_preferred":[
        "Asa"
    ],
    "name:fin_x_preferred":[
        "Asa"
    ],
    "name:heb_x_preferred":[
        "\u05d0\u05e1\u05d0"
    ],
    "name:jpn_x_preferred":[
        "\u30a2\u30b5"
    ],
    "name:lmo_x_preferred":[
        "As\u00e0"
    ],
    "name:nld_x_preferred":[
        "Asa"
    ],
    "name:pol_x_preferred":[
        "Asa"
    ],
    "name:por_x_preferred":[
        "Asa"
    ],
    "name:spa_x_preferred":[
        "Asa"
    ],
    "name:swe_x_preferred":[
        "Asa"
    ],
    "wof:name":"Asa",
    "wof:placetype":"locality"
},
  "geometry": {"coordinates":[121.31455,17.51982000000001],"type":"Point"}
}