{
  "type": "Feature",
  "properties": {
    "gn:admin1_code":"14",
    "gn:admin2_code":"35",
    "gn:admin3_code":"153617000.0",
    "gn:asciiname":"Buyanga",
    "gn:country_code":"PH",
    "gn:dem":708,
    "gn:feature_class":"P",
    "gn:feature_code":"PPL",
    "gn:name":"Buyanga",
    "gn:population":0,
    "gn:timezone":"Asia/Manila",
    "iso:country":"PH",
    "name:fil_x_preferred":[
        "Buyanga"
    ],
    "wof:name":"Buyanga",
    "wof:placetype":"locality"
},
  "geometry": {"coordinates":[124.31444,7.99778],"type":"Point"}
}