{
  "type": "Feature",
  "properties": {
    "gn:admin1_code":"15",
    "gn:admin2_code":"01",
    "gn:admin3_code":"140119000.0",
    "gn:asciiname":"Narnara",
    "gn:country_code":"PH",
    "gn:dem":300,
    "gn:feature_class":"P",
    "gn:feature_code":"PPL",
    "gn:name":"Narnara",
    "gn:population":0,
    "gn:timezone":"Asia/Manila",
    "iso:country":"PH",
    "name:fil_x_preferred":[
        "Narnara"
    ],
    "wof:name":"Narnara",
    "wof:placetype":"locality"
},
  "geometry": {"coordinates":[120.6082,17.4026],"type":"Point"}
}