{
  "type": "Feature",
  "properties": {
    "gn:admin1_code":"08",
    "gn:admin2_code":"67",
    "gn:admin3_code":"84802000.0",
    "gn:asciiname":"Kauswagan",
    "gn:country_code":"PH",
    "gn:dem":5,
    "gn:feature_class":"P",
    "gn:feature_code":"PPL",
    "gn:name":"Kauswagan",
    "gn:population":0,
    "gn:timezone":"Asia/Manila",
    "iso:country":"PH",
    "name:fil_x_preferred":[
        "Kauswagan"
    ],
    "wof:name":"Kauswagan",
    "wof:placetype":"locality"
},
  "geometry": {"coordinates":[124.38916999999999,12.66111],"type":"Point"}
}