{
  "type": "Feature",
  "properties": {
    "gn:admin1_code":"06",
    "gn:admin2_code":"06",
    "gn:admin3_code":"60607000.0",
    "gn:asciiname":"Nasuli",
    "gn:country_code":"PH",
    "gn:dem":82,
    "gn:feature_class":"P",
    "gn:feature_code":"PPL",
    "gn:name":"Nasuli",
    "gn:population":0,
    "gn:timezone":"Asia/Manila",
    "iso:country":"PH",
    "name:fil_x_preferred":[
        "Nasuli"
    ],
    "name:und_x_variant":[
        "Nasuli-a"
    ],
    "wof:name":"Nasuli",
    "wof:placetype":"locality"
},
  "geometry": {"coordinates":[121.98950000000001,10.4746],"type":"Point"}
}