{
  "type": "Feature",
  "properties": {
    "gn:admin1_code":"02",
    "gn:admin2_code":"31",
    "gn:admin3_code":"23121000.0",
    "gn:asciiname":"Diarasac",
    "gn:country_code":"PH",
    "gn:dem":35,
    "gn:feature_class":"P",
    "gn:feature_code":"PPL",
    "gn:name":"Diarasac",
    "gn:population":0,
    "gn:timezone":"Asia/Manila",
    "iso:country":"PH",
    "name:fil_x_preferred":[
        "Diarasac"
    ],
    "wof:name":"Diarasac",
    "wof:placetype":"locality"
},
  "geometry": {"coordinates":[122.39484,16.95785],"type":"Point"}
}