{
  "type": "Feature",
  "properties": {
    "gn:admin1_code":"40",
    "gn:admin2_code":"20",
    "gn:asciiname":"Tictic",
    "gn:country_code":"PH",
    "gn:dem":12,
    "gn:feature_class":"P",
    "gn:feature_code":"PPL",
    "gn:name":"Tictic",
    "gn:population":0,
    "gn:timezone":"Asia/Manila",
    "iso:country":"PH",
    "name:fil_x_preferred":[
        "Tictic"
    ],
    "wof:name":"Tictic",
    "wof:placetype":"locality"
},
  "geometry": {"coordinates":[120.50417,14.44167],"type":"Point"}
}