{
  "type": "Feature",
  "properties": {
    "gn:admin1_code":"07",
    "gn:admin2_code":"21",
    "gn:admin3_code":"72239000.0",
    "gn:asciiname":"Tupas",
    "gn:country_code":"PH",
    "gn:dem":148,
    "gn:feature_class":"P",
    "gn:feature_code":"PPL",
    "gn:name":"Tupas",
    "gn:population":0,
    "gn:timezone":"Asia/Manila",
    "iso:country":"PH",
    "name:fil_x_preferred":[
        "Tupas"
    ],
    "wof:name":"Tupas",
    "wof:placetype":"locality"
},
  "geometry": {"coordinates":[123.44661000000001,9.98421],"type":"Point"}
}