{
  "type": "Feature",
  "properties": {
    "gn:admin1_code":"02",
    "gn:admin2_code":"14",
    "gn:admin3_code":"21512000.0",
    "gn:asciiname":"Lollin",
    "gn:country_code":"PH",
    "gn:dem":22,
    "gn:feature_class":"P",
    "gn:feature_code":"PPL",
    "gn:name":"Lollin",
    "gn:population":0,
    "gn:timezone":"Asia/Manila",
    "iso:country":"PH",
    "name:fil_x_preferred":[
        "Lollin"
    ],
    "wof:name":"Lollin",
    "wof:placetype":"locality"
},
  "geometry": {"coordinates":[121.7033,17.5762],"type":"Point"}
}