{
  "type": "Feature",
  "properties": {
    "gn:admin1_code":"08",
    "gn:admin2_code":"55",
    "gn:admin3_code":"86006000.0",
    "gn:asciiname":"Mabini",
    "gn:country_code":"PH",
    "gn:dem":17,
    "gn:feature_class":"P",
    "gn:feature_code":"PPL",
    "gn:name":"Mabini",
    "gn:population":0,
    "gn:timezone":"Asia/Manila",
    "iso:country":"PH",
    "name:fil_x_preferred":[
        "Mabini"
    ],
    "wof:name":"Mabini",
    "wof:placetype":"locality"
},
  "geometry": {"coordinates":[124.79940000000001,11.5565],"type":"Point"}
}