{
  "type": "Feature",
  "properties": {
    "gn:admin1_code":"08",
    "gn:admin2_code":"37",
    "gn:admin3_code":"83747000.0",
    "gn:asciiname":"Marasbaras",
    "gn:country_code":"PH",
    "gn:dem":4,
    "gn:feature_class":"P",
    "gn:feature_code":"PPL",
    "gn:name":"Marasbaras",
    "gn:population":0,
    "gn:timezone":"Asia/Manila",
    "iso:country":"PH",
    "wof:name":"Marasbaras",
    "wof:placetype":"locality"
},
  "geometry": {"coordinates":[125.00194,11.19472],"type":"Point"}
}