{
  "type": "Feature",
  "properties": {
    "gn:admin1_code":"01",
    "gn:admin2_code":"51",
    "gn:admin3_code":"15532000.0",
    "gn:asciiname":"Capataan",
    "gn:country_code":"PH",
    "gn:dem":8,
    "gn:feature_class":"P",
    "gn:feature_code":"PPL",
    "gn:name":"Capataan",
    "gn:population":0,
    "gn:timezone":"Asia/Manila",
    "iso:country":"PH",
    "name:und_x_variant":[
        "Capatgan"
    ],
    "wof:name":"Capataan",
    "wof:placetype":"locality"
},
  "geometry": {"coordinates":[120.31845,15.95252],"type":"Point"}
}