{
  "type": "Feature",
  "properties": {
    "gn:gn_country":"PH",
    "gn:gn_fcode":"PPL",
    "gn:gn_pop":3174,
    "gn:population":3174,
    "iso:country":"PH",
    "name:fil_x_preferred":[
        "Caraycaray"
    ],
    "name:unk_x_variant":[
        "Caraycary"
    ],
    "qs_pg:aaroncc":"PH",
    "qs_pg:gn_country":"PH",
    "qs_pg:gn_fcode":"PPL",
    "qs_pg:gn_pop":3174,
    "qs_pg:name":"Caraycaray",
    "qs_pg:photos_9r":0,
    "qs_pg:photos_sr":0,
    "qs_pg:pop_sr":4,
    "qs_pg:qs_pg_placetype":"locality",
    "wof:name":"Caraycaray",
    "wof:placetype":"locality",
    "wof:population":3174
},
  "geometry": {"coordinates":[124.41500000000001,11.5551],"type":"Point"}
}