{
  "type": "Feature",
  "properties": {
    "gn:country":"PH",
    "gn:fcode":"PPLA3",
    "gn:pop":34927,
    "iso:country":"PH",
    "name:bcl_x_preferred":[
        "Pandi"
    ],
    "name:cat_x_preferred":[
        "Pandi"
    ],
    "name:dut_x_preferred":[
        "Pandi"
    ],
    "name:eng_x_preferred":[
        "Pandi"
    ],
    "name:fre_x_preferred":[
        "Pandi"
    ],
    "name:ger_x_preferred":[
        "Pandi"
    ],
    "name:ilo_x_preferred":[
        "Pandi"
    ],
    "name:ind_x_preferred":[
        "Pandi"
    ],
    "name:ita_x_preferred":[
        "Pandi"
    ],
    "name:oci_x_preferred":[
        "Pandi"
    ],
    "name:pag_x_preferred":[
        "Pandi"
    ],
    "name:pam_x_preferred":[
        "Pandi"
    ],
    "name:per_x_preferred":[
        "\u067e\u0646\u062f\u06cc\u060c \u0628\u0648\u0644\u0627\u06a9\u0627\u0646"
    ],
    "name:rus_x_preferred":[
        "\u041f\u0430\u043d\u0434\u0430"
    ],
    "name:spa_x_preferred":[
        "Pandi"
    ],
    "name:swe_x_preferred":[
        "Pandi"
    ],
    "name:tgl_x_preferred":[
        "Pandi"
    ],
    "name:war_x_preferred":[
        "Pandi"
    ],
    "qs:name":"Pandi",
    "qs:photos_9r":0,
    "qs:photos_sr":0,
    "qs:pop_sr":"7",
    "wd:wordcount":44,
    "wof:name":"Pandi",
    "wof:placetype":"locality",
    "wof:population":34927
},
  "geometry": {"coordinates":[120.95722000000001,14.865],"type":"Point"}
}