{
  "type": "Feature",
  "properties": {
    "gn:country":"PH",
    "gn:fcode":"PPL",
    "gn:pop":2250,
    "iso:country":"PH",
    "name:fil_x_preferred":[
        "San Andres"
    ],
    "qs:name":"San Andres",
    "qs:photos_9r":0,
    "qs:photos_sr":0,
    "qs:pop_sr":"4",
    "wd:wordcount":293,
    "wof:name":"San Andres",
    "wof:placetype":"locality",
    "wof:population":2250
},
  "geometry": {"coordinates":[123.7795,13.2614],"type":"Point"}
}