{
  "type": "Feature",
  "properties": {
    "gn:admin1_code":"03",
    "gn:admin2_code":"13",
    "gn:admin3_code":"31413000.0",
    "gn:asciiname":"Paila",
    "gn:country_code":"PH",
    "gn:dem":178,
    "gn:feature_class":"P",
    "gn:feature_code":"PPL",
    "gn:name":"Paila",
    "gn:population":0,
    "gn:timezone":"Asia/Manila",
    "iso:country":"PH",
    "name:ara_x_preferred":[
        "\u0628\u0627\u064a\u0644\u0627"
    ],
    "name:fil_x_preferred":[
        "Paila"
    ],
    "name:jpn_x_preferred":[
        "\u30d1\u30a4\u30e9"
    ],
    "name:spa_x_preferred":[
        "Paila"
    ],
    "wof:name":"Paila",
    "wof:placetype":"locality"
},
  "geometry": {"coordinates":[121.11667,14.91667],"type":"Point"}
}