{
  "type": "Feature",
  "properties": {
    "gn:admin1_code":"14",
    "gn:admin2_code":"60",
    "gn:admin3_code":"156608000.0",
    "gn:asciiname":"Pandugo",
    "gn:country_code":"PH",
    "gn:dem":11,
    "gn:feature_class":"P",
    "gn:feature_code":"PPL",
    "gn:name":"Pandugo",
    "gn:population":0,
    "gn:timezone":"Asia/Manila",
    "iso:country":"PH",
    "name:fil_x_preferred":[
        "Pandugo"
    ],
    "wof:name":"Pandugo",
    "wof:placetype":"locality"
},
  "geometry": {"coordinates":[120.49666999999999,6.26722],"type":"Point"}
}