{
  "type": "Feature",
  "properties": {
    "gn:country":"PH",
    "gn:fcode":"ADM3",
    "gn:pop":58258,
    "iso:country":"PH",
    "name:fil_x_preferred":[
        "Cuyapo"
    ],
    "qs:name":"Cuyapo",
    "qs:photos_9r":0,
    "qs:photos_sr":0,
    "qs:pop_sr":"8",
    "wof:name":"Cuyapo",
    "wof:placetype":"localadmin",
    "wof:population":58258
},
  "geometry": {"coordinates":[120.71666999999999,15.76667],"type":"Point"}
}