{
  "type": "Feature",
  "properties": {
    "gn:admin1_code":"40",
    "gn:admin2_code":"33",
    "gn:admin3_code":"43421000.0",
    "gn:asciiname":"Tanawan Munti",
    "gn:country_code":"PH",
    "gn:dem":261,
    "gn:feature_class":"P",
    "gn:feature_code":"PPL",
    "gn:name":"Tanawan Munti",
    "gn:population":0,
    "gn:timezone":"Asia/Manila",
    "iso:country":"PH",
    "name:fil_x_preferred":[
        "Tanawan Munti"
    ],
    "wof:name":"Tanawan Munti",
    "wof:placetype":"locality"
},
  "geometry": {"coordinates":[121.48333,14.43333],"type":"Point"}
}