{
  "type": "Feature",
  "properties": {
    "iso:country":"PH",
    "name:fil_x_preferred":[
        "Katipunan"
    ],
    "qs:gn_country":"PH",
    "qs:gn_fcode":"PPL",
    "qs:gn_pop":2468,
    "qs:name":"Katipunan",
    "qs:name_adm0":"Philippines",
    "qs:name_adm1":"Davao Region",
    "qs:photos":0,
    "qs:photos_1k":0,
    "qs:photos_9k":0,
    "qs:photos_9r":0,
    "qs:photos_all":0,
    "qs:photos_sr":0,
    "qs:placetype":"Town",
    "qs:pop_sr":"4",
    "qs:woe_adm0":23424934,
    "wd:wordcount":10246,
    "wof:name":"Katipunan",
    "wof:placetype":"locality",
    "wof:population":2468
},
  "geometry": {"coordinates":[125.62027999999999,7.32028],"type":"Point"}
}