{
  "type": "Feature",
  "properties": {
    "iso:country":"PH",
    "name:afr_x_preferred":[
        "Katipunan"
    ],
    "name:ast_x_preferred":[
        "Katipunan"
    ],
    "name:bcl_x_preferred":[
        "Katipunan"
    ],
    "name:cat_x_preferred":[
        "Katipunan"
    ],
    "name:ceb_x_preferred":[
        "Katipunan"
    ],
    "name:ces_x_preferred":[
        "Katipunan"
    ],
    "name:deu_x_preferred":[
        "Katipunan"
    ],
    "name:eng_x_preferred":[
        "Katipunan"
    ],
    "name:fas_x_preferred":[
        "\u06a9\u0627\u062a\u06cc\u067e\u0648\u0646\u0627\u0646"
    ],
    "name:fil_x_preferred":[
        "Katipunan"
    ],
    "name:fin_x_preferred":[
        "Katipunan"
    ],
    "name:fra_x_preferred":[
        "Katipunan"
    ],
    "name:heb_x_preferred":[
        "\u05e7\u05d0\u05d8\u05d9\u05e4\u05d5\u05e0\u05d0\u05df"
    ],
    "name:ilo_x_preferred":[
        "Katipunan"
    ],
    "name:ina_x_preferred":[
        "Katipunan"
    ],
    "name:ind_x_preferred":[
        "Katipunan"
    ],
    "name:ita_x_preferred":[
        "Katipunan"
    ],
    "name:jpn_x_preferred":[
        "\u30ab\u30c6\u30a3\u30d7\u30ca\u30f3"
    ],
    "name:kor_x_preferred":[
        "\uce74\ud2f0\ud478\ub09c"
    ],
    "name:lat_x_preferred":[
        "Katipunan"
    ],
    "name:msa_x_preferred":[
        "Katipunan"
    ],
    "name:nld_x_preferred":[
        "Katipunan"
    ],
    "name:nob_x_preferred":[
        "Katipunan"
    ],
    "name:pol_x_preferred":[
        "Katipunan"
    ],
    "name:rus_x_preferred":[
        "\u041a\u0430\u0442\u0438\u043f\u0443\u043d\u0430\u043d"
    ],
    "name:spa_x_preferred":[
        "Katipunan"
    ],
    "name:tgl_x_preferred":[
        "Katipunan"
    ],
    "name:vie_x_preferred":[
        "Katipunan"
    ],
    "name:zho_x_preferred":[
        "\u5361\u8482\u666e\u5357"
    ],
    "qs:gn_country":"PH",
    "qs:gn_fcode":"PPL",
    "qs:gn_pop":2468,
    "qs:name":"Katipunan",
    "qs:name_adm0":"Philippines",
    "qs:name_adm1":"Davao Region",
    "qs:photos":0,
    "qs:photos_1k":0,
    "qs:photos_9k":0,
    "qs:photos_9r":0,
    "qs:photos_all":0,
    "qs:photos_sr":0,
    "qs:placetype":"Town",
    "qs:pop_sr":"4",
    "qs:woe_adm0":23424934,
    "wd:wordcount":10246,
    "wof:name":"Katipunan",
    "wof:placetype":"locality",
    "wof:population":2468
},
  "geometry": {"coordinates":[125.62027999999999,7.32028],"type":"Point"}
}