{
  "type": "Feature",
  "properties": {
    "gn:admin1_code":"01",
    "gn:admin2_code":"51",
    "gn:admin3_code":"15501000.0",
    "gn:asciiname":"Andoloy",
    "gn:country_code":"PH",
    "gn:dem":21,
    "gn:feature_class":"P",
    "gn:feature_code":"PPL",
    "gn:name":"Andoloy",
    "gn:population":0,
    "gn:timezone":"Asia/Manila",
    "iso:country":"PH",
    "name:fil_x_preferred":[
        "Andoloy"
    ],
    "wof:name":"Andoloy",
    "wof:placetype":"locality"
},
  "geometry": {"coordinates":[119.80629999999999,16.1098],"type":"Point"}
}