{
  "type": "Feature",
  "properties": {
    "gn:admin1_code":"41",
    "gn:admin2_code":"38",
    "gn:admin3_code":"174001000.0",
    "gn:asciiname":"Canaraw",
    "gn:country_code":"PH",
    "gn:dem":99,
    "gn:feature_class":"P",
    "gn:feature_code":"PPL",
    "gn:name":"Canaraw",
    "gn:population":0,
    "gn:timezone":"Asia/Manila",
    "iso:country":"PH",
    "name:fil_x_preferred":[
        "Canaraw"
    ],
    "wof:name":"Canaraw",
    "wof:placetype":"locality"
},
  "geometry": {"coordinates":[121.93333,13.36667],"type":"Point"}
}