{
  "type": "Feature",
  "properties": {
    "iso:country":"PH",
    "name:fil_x_preferred":[
        "Manarog"
    ],
    "qs:gn_country":"PH",
    "qs:gn_fcode":"PPL",
    "qs:gn_pop":0,
    "qs:name":"Manaoag",
    "qs:name_adm0":"Philippines",
    "qs:name_adm1":"Ilocos Region",
    "qs:photos":324,
    "qs:photos_1k":66,
    "qs:photos_9k":1,
    "qs:photos_9r":5,
    "qs:photos_all":324,
    "qs:photos_sr":5,
    "qs:placetype":"Town",
    "qs:pop_sr":"0",
    "qs:woe_adm0":23424934,
    "wof:name":"Manaoag",
    "wof:placetype":"locality"
},
  "geometry": {"coordinates":[121.0253,15.6179],"type":"Point"}
}