{
  "type": "Feature",
  "properties": {
    "gn:admin1_code":"09",
    "gn:admin2_code":"66",
    "gn:admin3_code":"97302000.0",
    "gn:asciiname":"Campo Numero Uno",
    "gn:country_code":"PH",
    "gn:dem":192,
    "gn:feature_class":"P",
    "gn:feature_code":"PPL",
    "gn:name":"Campo Numero Uno",
    "gn:population":0,
    "gn:timezone":"Asia/Manila",
    "iso:country":"PH",
    "name:eng_x_preferred":[
        "Campo Numero Uno"
    ],
    "name:und_x_variant":[
        "Campo No. 1",
        "Campo I"
    ],
    "wof:name":"Campo Numero Uno",
    "wof:placetype":"locality"
},
  "geometry": {"coordinates":[123.54900000000001,7.9851],"type":"Point"}
}