{
  "type": "Feature",
  "properties": {
    "gn:country":"PH",
    "gn:fcode":"PPL",
    "gn:pop":2427,
    "iso:country":"PH",
    "name:bcl_x_preferred":[
        "Kolambugan"
    ],
    "name:deu_x_preferred":[
        "Kolambugan"
    ],
    "name:eng_x_preferred":[
        "Kolambugan"
    ],
    "name:fra_x_preferred":[
        "Kolambugan"
    ],
    "name:ilo_x_preferred":[
        "Kolambugan"
    ],
    "name:ind_x_preferred":[
        "Kolambugan"
    ],
    "name:ita_x_preferred":[
        "Kolambugan"
    ],
    "name:jpn_x_preferred":[
        "\u30b3\u30e9\u30f3\u30d6\u30ab\u30f3"
    ],
    "name:nld_x_preferred":[
        "Kolambugan"
    ],
    "name:pag_x_preferred":[
        "Kolambugan"
    ],
    "name:pam_x_preferred":[
        "Kolambugan"
    ],
    "name:spa_x_preferred":[
        "Colambug\u00e1n"
    ],
    "name:swe_x_preferred":[
        "Kolambugan"
    ],
    "name:tgl_x_preferred":[
        "Kolambugan"
    ],
    "name:unk_x_variant":[
        "Migcamiguing"
    ],
    "name:vie_x_preferred":[
        "Kolambugan"
    ],
    "name:war_x_preferred":[
        "Kolambugan"
    ],
    "qs:name":"Kolambugan",
    "qs:photos_9r":0,
    "qs:photos_sr":0,
    "qs:pop_sr":"4",
    "wof:name":"Kolambugan",
    "wof:placetype":"locality",
    "wof:population":2427
},
  "geometry": {"coordinates":[123.89709999999999,8.1144],"type":"Point"}
}