{
  "type": "Feature",
  "properties": {
    "gn:country":"PH",
    "gn:fcode":"PPL",
    "gn:pop":3159,
    "iso:country":"PH",
    "name:fil_x_preferred":[
        "Binuang"
    ],
    "qs:name":"Binuang",
    "qs:photos_9r":0,
    "qs:photos_sr":0,
    "qs:pop_sr":"4",
    "wof:name":"Binuang",
    "wof:placetype":"locality",
    "wof:population":3159
},
  "geometry": {"coordinates":[121.06,5.95694],"type":"Point"}
}