{
  "type": "Feature",
  "properties": {
    "gn:country":"PH",
    "gn:fcode":"PPL",
    "gn:population":2402,
    "iso:country":"PH",
    "name:fil_x_preferred":[
        "Buang"
    ],
    "qs:name":"Buang",
    "qs:photos_9r":0,
    "qs:photos_sr":0,
    "qs:pop_sr":"4",
    "wd:wordcount":82,
    "wof:name":"Buang",
    "wof:placetype":"locality",
    "wof:population":2402
},
  "geometry": {"coordinates":[123.6421,13.3115],"type":"Point"}
}