{
  "type": "Feature",
  "properties": {
    "gn:admin1_code":"11",
    "gn:admin2_code":"25",
    "gn:admin3_code":"112402000.0",
    "gn:asciiname":"Malapigok",
    "gn:cc2":"PH",
    "gn:country_code":"PH",
    "gn:dem":328,
    "gn:feature_class":"P",
    "gn:feature_code":"PPL",
    "gn:name":"Malapigok",
    "gn:population":0,
    "gn:timezone":"Asia/Manila",
    "iso:country":"PH",
    "name:und_x_variant":[
        "Melapigok",
        "Malapigok"
    ],
    "wof:name":"Malapigok",
    "wof:placetype":"locality"
},
  "geometry": {"coordinates":[125.34583000000001,7.41528],"type":"Point"}
}