{
  "type": "Feature",
  "properties": {
    "gn:admin1_code":"10",
    "gn:admin2_code":"42",
    "gn:admin3_code":"104210000.0",
    "gn:asciiname":"Gala",
    "gn:country_code":"PH",
    "gn:dem":620,
    "gn:feature_class":"P",
    "gn:feature_code":"PPL",
    "gn:name":"Gala",
    "gn:population":0,
    "gn:timezone":"Asia/Manila",
    "iso:country":"PH",
    "name:eng_x_preferred":[
        "Gala"
    ],
    "wof:name":"Gala",
    "wof:placetype":"locality"
},
  "geometry": {"coordinates":[123.711,8.1732],"type":"Point"}
}