{
  "type": "Feature",
  "properties": {
    "gn:admin1_code":"01",
    "gn:admin2_code":"51",
    "gn:admin3_code":"15514000.0",
    "gn:asciiname":"Lasip",
    "gn:country_code":"PH",
    "gn:dem":14,
    "gn:feature_class":"P",
    "gn:feature_code":"PPL",
    "gn:name":"Lasip",
    "gn:population":0,
    "gn:timezone":"Asia/Manila",
    "iso:country":"PH",
    "name:fil_x_preferred":[
        "Lasip"
    ],
    "name:und_x_variant":[
        "Lasir"
    ],
    "wof:name":"Lasip",
    "wof:placetype":"locality"
},
  "geometry": {"coordinates":[119.9164,16.2897],"type":"Point"}
}