{
  "type": "Feature",
  "properties": {
    "gn:admin1_code":"01",
    "gn:admin2_code":"29",
    "gn:admin3_code":"12933000.0",
    "gn:asciiname":"Godel",
    "gn:country_code":"PH",
    "gn:dem":41,
    "gn:feature_class":"P",
    "gn:feature_code":"PPL",
    "gn:name":"Godel",
    "gn:population":0,
    "gn:timezone":"Asia/Manila",
    "iso:country":"PH",
    "name:fil_x_preferred":[
        "Godel"
    ],
    "wof:name":"Godel",
    "wof:placetype":"locality"
},
  "geometry": {"coordinates":[120.51260000000001,16.9189],"type":"Point"}
}