{
  "type": "Feature",
  "properties": {
    "gn:admin1_code":"01",
    "gn:admin2_code":"36",
    "gn:admin3_code":"13306000.0",
    "gn:asciiname":"Butac",
    "gn:country_code":"PH",
    "gn:dem":26,
    "gn:feature_class":"P",
    "gn:feature_code":"PPL",
    "gn:name":"Butac",
    "gn:population":0,
    "gn:timezone":"Asia/Manila",
    "iso:country":"PH",
    "name:fil_x_preferred":[
        "Butac"
    ],
    "wof:name":"Butac",
    "wof:placetype":"locality"
},
  "geometry": {"coordinates":[120.4533,16.8802],"type":"Point"}
}