{
  "type": "Feature",
  "properties": {
    "gn:admin1_code":"05",
    "gn:admin2_code":"58",
    "gn:admin3_code":"56213000.0",
    "gn:asciiname":"Poctol",
    "gn:country_code":"PH",
    "gn:dem":58,
    "gn:feature_class":"P",
    "gn:feature_code":"PPL",
    "gn:name":"Poctol",
    "gn:population":0,
    "gn:timezone":"Asia/Manila",
    "iso:country":"PH",
    "name:fil_x_preferred":[
        "Poctol"
    ],
    "wof:name":"Poctol",
    "wof:placetype":"locality"
},
  "geometry": {"coordinates":[123.68980000000001,13.0082],"type":"Point"}
}