{
  "type": "Feature",
  "properties": {
    "gn:country":"PH",
    "gn:fcode":"PPL",
    "gn:population":2501,
    "iso:country":"PH",
    "name:eng_x_preferred":[
        "Tagbita"
    ],
    "name:und_x_variant":[
        "Taburi"
    ],
    "qs:name":"Tagbita",
    "qs:photos_9r":0,
    "qs:photos_sr":0,
    "qs:pop_sr":"4",
    "wof:name":"Tagbita",
    "wof:placetype":"locality",
    "wof:population":2501
},
  "geometry": {"coordinates":[117.3399,8.67532],"type":"Point"}
}