{
  "type": "Feature",
  "properties": {
    "gn:admin1_code":"41",
    "gn:admin2_code":"54",
    "gn:admin3_code":"175908000.0",
    "gn:asciiname":"Cangouac",
    "gn:country_code":"PH",
    "gn:dem":10,
    "gn:feature_class":"P",
    "gn:feature_code":"PPL",
    "gn:name":"Cangouac",
    "gn:population":0,
    "gn:timezone":"Asia/Manila",
    "iso:country":"PH",
    "name:fil_x_preferred":[
        "Cangouac"
    ],
    "name:und_x_variant":[
        "Canguac",
        "Canouac"
    ],
    "wof:name":"Cangouac",
    "wof:placetype":"locality"
},
  "geometry": {"coordinates":[122.50491,12.49473],"type":"Point"}
}