{
  "type": "Feature",
  "properties": {
    "gn:admin1_code":"15",
    "gn:admin2_code":"01",
    "gn:admin3_code":"140103000.0",
    "gn:asciiname":"Dalaguisen",
    "gn:country_code":"PH",
    "gn:dem":71,
    "gn:feature_class":"P",
    "gn:feature_code":"PPL",
    "gn:name":"Dalaguisen",
    "gn:population":0,
    "gn:timezone":"Asia/Manila",
    "iso:country":"PH",
    "name:fil_x_preferred":[
        "Dalaguisen"
    ],
    "wof:name":"Dalaguisen",
    "wof:placetype":"locality"
},
  "geometry": {"coordinates":[120.73990000000001,17.5794],"type":"Point"}
}