{
  "type": "Feature",
  "properties": {
    "gn:admin1_code":"09",
    "gn:admin2_code":"66",
    "gn:admin3_code":"97322000.0",
    "gn:asciiname":"Balangasan",
    "gn:country_code":"PH",
    "gn:dem":69,
    "gn:feature_class":"P",
    "gn:feature_code":"PPL",
    "gn:name":"Balangasan",
    "gn:population":0,
    "gn:timezone":"Asia/Manila",
    "iso:country":"PH",
    "name:eng_x_preferred":[
        "Balangasan"
    ],
    "wof:name":"Balangasan",
    "wof:placetype":"locality"
},
  "geometry": {"coordinates":[123.4198,7.8265],"type":"Point"}
}