{
  "type": "Feature",
  "properties": {
    "iso:country":"PH",
    "name:bcl_x_preferred":[
        "Tibiao"
    ],
    "name:ceb_x_preferred":[
        "Tibiao"
    ],
    "name:deu_x_preferred":[
        "Tibiao"
    ],
    "name:fil_x_preferred":[
        "Tibiao"
    ],
    "name:fra_x_preferred":[
        "Tibiao"
    ],
    "name:ilo_x_preferred":[
        "Tibiao"
    ],
    "name:ind_x_preferred":[
        "Tibiao"
    ],
    "name:ita_x_preferred":[
        "Tibiao"
    ],
    "name:nld_x_preferred":[
        "Tibiao"
    ],
    "name:pag_x_preferred":[
        "Tibiao"
    ],
    "name:pam_x_preferred":[
        "Tibiao"
    ],
    "name:swe_x_preferred":[
        "Tibiao"
    ],
    "name:tgl_x_preferred":[
        "Tibiao"
    ],
    "name:urd_x_preferred":[
        "\u062a\u06cc\u0628\u06cc\u0627\u0648"
    ],
    "name:vie_x_preferred":[
        "Tibiao"
    ],
    "name:war_x_preferred":[
        "Tibiao"
    ],
    "qs:gn_country":"PH",
    "qs:gn_fcode":"PPL",
    "qs:gn_pop":0,
    "qs:name":"Tibiao",
    "qs:name_adm0":"Philippines",
    "qs:name_adm1":"Western Visayas",
    "qs:photos":7,
    "qs:photos_1k":1,
    "qs:photos_9k":1,
    "qs:photos_9r":1,
    "qs:photos_all":7,
    "qs:photos_sr":1,
    "qs:placetype":"Town",
    "qs:pop_sr":"0",
    "qs:woe_adm0":23424934,
    "wof:name":"Tibiao",
    "wof:placetype":"locality"
},
  "geometry": {"coordinates":[122.5027,11.4933],"type":"Point"}
}