{
  "type": "Feature",
  "properties": {
    "gn:admin1_code":"05",
    "gn:admin2_code":"58",
    "gn:admin3_code":"56203000.0",
    "gn:asciiname":"Pawic",
    "gn:country_code":"PH",
    "gn:dem":32,
    "gn:feature_class":"P",
    "gn:feature_code":"PPL",
    "gn:name":"Pawic",
    "gn:population":0,
    "gn:timezone":"Asia/Manila",
    "iso:country":"PH",
    "name:eng_x_preferred":[
        "Pawic"
    ],
    "name:und_x_variant":[
        "Pawio"
    ],
    "wof:name":"Pawic",
    "wof:placetype":"locality"
},
  "geometry": {"coordinates":[123.9588,12.6619],"type":"Point"}
}