{
  "type": "Feature",
  "properties": {
    "gn:admin1_code":"15",
    "gn:admin2_code":"01",
    "gn:admin3_code":"140104000.0",
    "gn:asciiname":"Daldalao",
    "gn:country_code":"PH",
    "gn:dem":350,
    "gn:feature_class":"P",
    "gn:feature_code":"PPL",
    "gn:name":"Daldalao",
    "gn:population":0,
    "gn:timezone":"Asia/Manila",
    "iso:country":"PH",
    "name:fil_x_preferred":[
        "Daldalao"
    ],
    "wof:name":"Daldalao",
    "wof:placetype":"locality"
},
  "geometry": {"coordinates":[120.83215,17.44203],"type":"Point"}
}