{
  "type": "Feature",
  "properties": {
    "gn:admin1_code":"40",
    "gn:admin2_code":"H2",
    "gn:admin3_code":"45624000.0",
    "gn:asciiname":"Gulang-gulang",
    "gn:cc2":"PH",
    "gn:country_code":"PH",
    "gn:dem":51,
    "gn:feature_class":"P",
    "gn:feature_code":"PPL",
    "gn:name":"Gulang-gulang",
    "gn:population":0,
    "gn:timezone":"Asia/Manila",
    "iso:country":"PH",
    "name:und_x_variant":[
        "Culanggulang",
        "Gulangulang"
    ],
    "wof:name":"Gulang-gulang",
    "wof:placetype":"locality"
},
  "geometry": {"coordinates":[121.60917000000001,13.96528],"type":"Point"}
}