{
  "type": "Feature",
  "properties": {
    "gn:admin1_code":"01",
    "gn:admin2_code":"36",
    "gn:admin3_code":"13302000.0",
    "gn:asciiname":"Santa Cecilia",
    "gn:country_code":"PH",
    "gn:dem":19,
    "gn:feature_class":"P",
    "gn:feature_code":"PPL",
    "gn:name":"Santa Cecilia",
    "gn:population":0,
    "gn:timezone":"Asia/Manila",
    "iso:country":"PH",
    "name:fil_x_preferred":[
        "Santa Cecilia"
    ],
    "wof:name":"Santa Cecilia",
    "wof:placetype":"locality"
},
  "geometry": {"coordinates":[120.4002,16.3877],"type":"Point"}
}