{
  "type": "Feature",
  "properties": {
    "gn:country":"PH",
    "gn:fcode":"PPL",
    "gn:population":6848,
    "iso:country":"PH",
    "name:fil_x_preferred":[
        "Tiglawigan"
    ],
    "qs:name":"Tiglauigan",
    "qs:photos_9r":0,
    "qs:photos_sr":0,
    "qs:pop_sr":"5",
    "wof:name":"Tiglauigan",
    "wof:placetype":"locality",
    "wof:population":6848
},
  "geometry": {"coordinates":[123.3575,10.9527],"type":"Point"}
}