{
  "type": "Feature",
  "properties": {
    "gn:admin1_code":"02",
    "gn:admin2_code":"31",
    "gn:admin3_code":"23103000.0",
    "gn:asciiname":"Gunitao",
    "gn:country_code":"PH",
    "gn:dem":51,
    "gn:feature_class":"P",
    "gn:feature_code":"PPL",
    "gn:name":"Gunitao",
    "gn:population":0,
    "gn:timezone":"Asia/Manila",
    "iso:country":"PH",
    "name:fil_x_preferred":[
        "Gunitao"
    ],
    "wof:name":"Gunitao",
    "wof:placetype":"locality"
},
  "geometry": {"coordinates":[121.69974000000001,17.00555],"type":"Point"}
}