{
  "type": "Feature",
  "properties": {
    "gn:admin1_code":"01",
    "gn:admin2_code":"51",
    "gn:admin3_code":"15545000.0",
    "gn:asciiname":"Gueteb",
    "gn:country_code":"PH",
    "gn:dem":10,
    "gn:feature_class":"P",
    "gn:feature_code":"PPL",
    "gn:name":"Gueteb",
    "gn:population":0,
    "gn:timezone":"Asia/Manila",
    "iso:country":"PH",
    "name:fil_x_preferred":[
        "Gueteb"
    ],
    "wof:name":"Gueteb",
    "wof:placetype":"locality"
},
  "geometry": {"coordinates":[120.35354,15.84669],"type":"Point"}
}