{
  "type": "Feature",
  "properties": {
    "gn:admin1_code":"01",
    "gn:admin2_code":"36",
    "gn:admin3_code":"13311000.0",
    "gn:asciiname":"Banoagan",
    "gn:country_code":"PH",
    "gn:dem":126,
    "gn:feature_class":"P",
    "gn:feature_code":"PPL",
    "gn:name":"Banoagan",
    "gn:population":0,
    "gn:timezone":"Asia/Manila",
    "iso:country":"PH",
    "name:fil_x_preferred":[
        "Banoagan"
    ],
    "wof:name":"Banoagan",
    "wof:placetype":"locality"
},
  "geometry": {"coordinates":[120.38333,16.55],"type":"Point"}
}