{
  "type": "Feature",
  "properties": {
    "gn:admin1_code":"40",
    "gn:admin2_code":"20",
    "gn:admin3_code":"42103000.0",
    "gn:asciiname":"South Susana",
    "gn:country_code":"PH",
    "gn:dem":31,
    "gn:feature_class":"P",
    "gn:feature_code":"PPL",
    "gn:name":"South Susana",
    "gn:population":0,
    "gn:timezone":"Asia/Manila",
    "iso:country":"PH",
    "wof:name":"South Susana",
    "wof:placetype":"locality"
},
  "geometry": {"coordinates":[120.98093,14.41244],"type":"Point"}
}