{
  "type": "Feature",
  "properties": {
    "gn:country":"PH",
    "gn:fcode":"PPL",
    "gn:population":2404,
    "iso:country":"PH",
    "name:fil_x_preferred":[
        "Usab"
    ],
    "qs:name":"Usab",
    "qs:photos_9r":0,
    "qs:photos_sr":0,
    "qs:pop_sr":"4",
    "wof:name":"Usab",
    "wof:placetype":"locality",
    "wof:population":2404
},
  "geometry": {"coordinates":[123.58091,12.32974],"type":"Point"}
}