{
  "type": "Feature",
  "properties": {
    "gn:admin1_code":"01",
    "gn:admin2_code":"51",
    "gn:admin3_code":"15505000.0",
    "gn:asciiname":"Batiarao",
    "gn:country_code":"PH",
    "gn:dem":9,
    "gn:feature_class":"P",
    "gn:feature_code":"PPL",
    "gn:name":"Batiarao",
    "gn:population":0,
    "gn:timezone":"Asia/Manila",
    "iso:country":"PH",
    "name:fil_x_preferred":[
        "Bati-arao"
    ],
    "wof:name":"Batiarao",
    "wof:placetype":"locality"
},
  "geometry": {"coordinates":[120.01233999999999,16.23841],"type":"Point"}
}