{
  "type": "Feature",
  "properties": {
    "gn:admin1_code":"01",
    "gn:admin2_code":"51",
    "gn:admin3_code":"15532000.0",
    "gn:asciiname":"Talang",
    "gn:country_code":"PH",
    "gn:dem":12,
    "gn:feature_class":"P",
    "gn:feature_code":"PPL",
    "gn:name":"Talang",
    "gn:population":0,
    "gn:timezone":"Asia/Manila",
    "iso:country":"PH",
    "name:ceb_x_preferred":[
        "Talang"
    ],
    "name:fra_x_preferred":[
        "Talang"
    ],
    "name:ind_x_preferred":[
        "Talang"
    ],
    "name:nld_x_preferred":[
        "Talang"
    ],
    "name:pol_x_preferred":[
        "Talang"
    ],
    "name:swe_x_preferred":[
        "Talang"
    ],
    "name:und_x_variant":[
        "Talano",
        "Talang"
    ],
    "wof:name":"Talang",
    "wof:placetype":"locality"
},
  "geometry": {"coordinates":[120.30450999999999,15.90541],"type":"Point"}
}