{
  "type": "Feature",
  "properties": {
    "gn:admin1_code":"13",
    "gn:admin2_code":"02",
    "gn:admin3_code":"160205000.0",
    "gn:asciiname":"Magdaguup",
    "gn:cc2":"PH",
    "gn:country_code":"PH",
    "gn:dem":62,
    "gn:feature_class":"P",
    "gn:feature_code":"PPL",
    "gn:name":"Magdaguup",
    "gn:population":0,
    "gn:timezone":"Asia/Manila",
    "iso:country":"PH",
    "name:und_x_variant":[
        "Magdago-oc",
        "Magdaguup"
    ],
    "wof:name":"Magdaguup",
    "wof:placetype":"locality"
},
  "geometry": {"coordinates":[125.48333,9.35611],"type":"Point"}
}