{
  "type": "Feature",
  "properties": {
    "gn:admin1_code":"09",
    "gn:admin2_code":"66",
    "gn:admin3_code":"97313000.0",
    "gn:asciiname":"Pingalay",
    "gn:country_code":"PH",
    "gn:dem":71,
    "gn:feature_class":"P",
    "gn:feature_code":"PPL",
    "gn:name":"Pingalay",
    "gn:population":0,
    "gn:timezone":"Asia/Manila",
    "iso:country":"PH",
    "wof:name":"Pingalay",
    "wof:placetype":"locality"
},
  "geometry": {"coordinates":[123.15222,7.69639],"type":"Point"}
}