{
  "type": "Feature",
  "properties": {
    "gn:admin1_code":"41",
    "gn:admin2_code":"38",
    "gn:admin3_code":"174005000.0",
    "gn:asciiname":"Pinagkalerohan",
    "gn:country_code":"PH",
    "gn:dem":8,
    "gn:feature_class":"P",
    "gn:feature_code":"PPL",
    "gn:name":"Pinagkalerohan",
    "gn:population":0,
    "gn:timezone":"Asia/Manila",
    "iso:country":"PH",
    "name:fil_x_preferred":[
        "Pinagkalerohan"
    ],
    "wof:name":"Pinagkalerohan",
    "wof:placetype":"locality"
},
  "geometry": {"coordinates":[122.07769999999999,13.5065],"type":"Point"}
}