{
  "type": "Feature",
  "properties": {
    "gn:country":"PH",
    "gn:fcode":"PPLA3",
    "gn:pop":2018,
    "iso:country":"PH",
    "name:bcl_x_preferred":[
        "San Sebastian"
    ],
    "name:ceb_x_preferred":[
        "San Sebastian"
    ],
    "name:deu_x_preferred":[
        "San Sebastian"
    ],
    "name:eng_x_preferred":[
        "San Sebastian"
    ],
    "name:fra_x_preferred":[
        "San Sebastian"
    ],
    "name:ilo_x_preferred":[
        "San Sebastian"
    ],
    "name:ind_x_preferred":[
        "San Sebastian"
    ],
    "name:ita_x_preferred":[
        "San Sebastian"
    ],
    "name:nld_x_preferred":[
        "San Sebastian"
    ],
    "name:pag_x_preferred":[
        "San Sebastian"
    ],
    "name:pam_x_preferred":[
        "San Sebastian"
    ],
    "name:spa_x_preferred":[
        "San Sebasti\u00e1n"
    ],
    "name:swe_x_preferred":[
        "San Sebastian"
    ],
    "name:tgl_x_preferred":[
        "San Sebastian"
    ],
    "name:war_x_preferred":[
        "San Sebastian"
    ],
    "qs:name":"San Sebastian",
    "qs:photos_9r":0,
    "qs:photos_sr":0,
    "qs:pop_sr":"4",
    "wd:wordcount":414,
    "wof:name":"San Sebastian",
    "wof:placetype":"locality",
    "wof:population":2018
},
  "geometry": {"coordinates":[125.01806000000001,11.71],"type":"Point"}
}