{
  "type": "Feature",
  "properties": {
    "gn:admin1_code":"07",
    "gn:admin2_code":"11",
    "gn:admin3_code":"71217000.0",
    "gn:asciiname":"Cagawitan",
    "gn:country_code":"PH",
    "gn:dem":105,
    "gn:feature_class":"P",
    "gn:feature_code":"PPL",
    "gn:name":"Cagawitan",
    "gn:population":0,
    "gn:timezone":"Asia/Manila",
    "iso:country":"PH",
    "name:fil_x_preferred":[
        "Cagawitan"
    ],
    "wof:name":"Cagawitan",
    "wof:placetype":"locality"
},
  "geometry": {"coordinates":[124.2885,9.912],"type":"Point"}
}