{
  "type": "Feature",
  "properties": {
    "gn:admin1_code":"03",
    "gn:admin2_code":"50",
    "gn:admin3_code":"35411000.0",
    "gn:asciiname":"Balitucan",
    "gn:country_code":"PH",
    "gn:dem":24,
    "gn:feature_class":"P",
    "gn:feature_code":"PPL",
    "gn:name":"Balitucan",
    "gn:population":0,
    "gn:timezone":"Asia/Manila",
    "iso:country":"PH",
    "name:fil_x_preferred":[
        "Balitucan"
    ],
    "wof:name":"Balitucan",
    "wof:placetype":"locality"
},
  "geometry": {"coordinates":[120.71313000000001,15.25646],"type":"Point"}
}