{
  "type": "Feature",
  "properties": {
    "gn:admin1_code":"14",
    "gn:admin2_code":"60",
    "gn:admin3_code":"156611000.0",
    "gn:asciiname":"Maligay",
    "gn:country_code":"PH",
    "gn:dem":206,
    "gn:feature_class":"P",
    "gn:feature_code":"PPL",
    "gn:name":"Maligay",
    "gn:population":0,
    "gn:timezone":"Asia/Manila",
    "iso:country":"PH",
    "name:fil_x_preferred":[
        "Maligay"
    ],
    "wof:name":"Maligay",
    "wof:placetype":"locality"
},
  "geometry": {"coordinates":[121.06222,6.04639],"type":"Point"}
}