{
  "type": "Feature",
  "properties": {
    "gn:admin1_code":"09",
    "gn:admin2_code":"65",
    "gn:admin3_code":"97210000.0",
    "gn:asciiname":"Dansullan",
    "gn:country_code":"PH",
    "gn:dem":23,
    "gn:feature_class":"P",
    "gn:feature_code":"PPL",
    "gn:name":"Dansullan",
    "gn:population":0,
    "gn:timezone":"Asia/Manila",
    "iso:country":"PH",
    "name:fil_x_preferred":[
        "Dansullan"
    ],
    "wof:name":"Dansullan",
    "wof:placetype":"locality"
},
  "geometry": {"coordinates":[123.40000000000001,8.51667],"type":"Point"}
}