{
  "type": "Feature",
  "properties": {
    "gn:admin1_code":"14",
    "gn:admin2_code":"60",
    "gn:admin3_code":"156608000.0",
    "gn:asciiname":"Luuk Pataw",
    "gn:country_code":"PH",
    "gn:dem":5,
    "gn:feature_class":"P",
    "gn:feature_code":"PPL",
    "gn:name":"Luuk Pataw",
    "gn:population":0,
    "gn:timezone":"Asia/Manila",
    "iso:country":"PH",
    "name:fil_x_preferred":[
        "Luuk Pataw"
    ],
    "wof:name":"Luuk Pataw",
    "wof:placetype":"locality"
},
  "geometry": {"coordinates":[120.55528,6.35917],"type":"Point"}
}