{
  "type": "Feature",
  "properties": {
    "gn:admin1_code":"40",
    "gn:admin2_code":"20",
    "gn:admin3_code":"42117000.0",
    "gn:asciiname":"Ligtong",
    "gn:country_code":"PH",
    "gn:dem":6,
    "gn:feature_class":"P",
    "gn:feature_code":"PPL",
    "gn:name":"Ligtong",
    "gn:population":0,
    "gn:timezone":"Asia/Manila",
    "iso:country":"PH",
    "name:fil_x_preferred":[
        "Ligtong"
    ],
    "wof:name":"Ligtong",
    "wof:placetype":"locality"
},
  "geometry": {"coordinates":[120.86775,14.425],"type":"Point"}
}