{
  "type": "Feature",
  "properties": {
    "gn:admin1_code":"05",
    "gn:admin2_code":"05",
    "gn:admin3_code":"50502000.0",
    "gn:asciiname":"Kinawitan",
    "gn:country_code":"PH",
    "gn:dem":78,
    "gn:feature_class":"P",
    "gn:feature_code":"PPL",
    "gn:name":"Kinawitan",
    "gn:population":0,
    "gn:timezone":"Asia/Manila",
    "iso:country":"PH",
    "name:fil_x_preferred":[
        "Kinawitan"
    ],
    "wof:name":"Kinawitan",
    "wof:placetype":"locality"
},
  "geometry": {"coordinates":[123.66667,13.08333],"type":"Point"}
}