{
  "type": "Feature",
  "properties": {
    "gn:country":"PH",
    "gn:fcode":"PPL",
    "gn:pop":2366,
    "iso:country":"PH",
    "name:fil_x_preferred":[
        "San Bernardo"
    ],
    "name:fil_x_variant":[
        "San Bernardino"
    ],
    "qs:name":"San Bernardino",
    "qs:photos_9r":0,
    "qs:photos_sr":0,
    "qs:pop_sr":"4",
    "wd:wordcount":8303,
    "wof:name":"San Bernardino",
    "wof:placetype":"locality",
    "wof:population":2366
},
  "geometry": {"coordinates":[121.75385,17.40382],"type":"Point"}
}