{
  "type": "Feature",
  "properties": {
    "gn:country":"PH",
    "gn:fcode":"PPL",
    "gn:pop":13979,
    "iso:country":"PH",
    "name:fil_x_preferred":[
        "Bulihan"
    ],
    "qs:name":"Bulihan",
    "qs:photos_9r":0,
    "qs:photos_sr":0,
    "qs:pop_sr":"6",
    "wof:name":"Bulihan",
    "wof:placetype":"locality",
    "wof:population":13979
},
  "geometry": {"coordinates":[120.99545999999999,14.26974],"type":"Point"}
}