{
  "type": "Feature",
  "properties": {
    "gn:admin1_code":"01",
    "gn:admin2_code":"36",
    "gn:admin3_code":"13311000.0",
    "gn:asciiname":"Angin",
    "gn:country_code":"PH",
    "gn:dem":20,
    "gn:feature_class":"P",
    "gn:feature_code":"PPL",
    "gn:name":"Angin",
    "gn:population":0,
    "gn:timezone":"Asia/Manila",
    "iso:country":"PH",
    "name:fil_x_preferred":[
        "Angin"
    ],
    "wof:name":"Angin",
    "wof:placetype":"locality"
},
  "geometry": {"coordinates":[120.40028,16.51139],"type":"Point"}
}