{
  "type": "Feature",
  "properties": {
    "gn:country":"PH",
    "gn:fcode":"ADM3",
    "gn:pop":107995,
    "iso:country":"PH",
    "name:fil_x_preferred":[
        "Capas"
    ],
    "qs:name":"Capas",
    "qs:photos_9r":0,
    "qs:photos_sr":0,
    "qs:pop_sr":"9",
    "wd:wordcount":31,
    "wof:name":"Capas",
    "wof:placetype":"localadmin",
    "wof:population":107995
},
  "geometry": {"coordinates":[120.46666999999999,15.35],"type":"Point"}
}