{
  "type": "Feature",
  "properties": {
    "gn:admin1_code":"05",
    "gn:admin2_code":"16",
    "gn:admin3_code":"51714000.0",
    "gn:asciiname":"Bahi",
    "gn:country_code":"PH",
    "gn:dem":13,
    "gn:feature_class":"P",
    "gn:feature_code":"PPL",
    "gn:name":"Bahi",
    "gn:population":0,
    "gn:timezone":"Asia/Manila",
    "iso:country":"PH",
    "name:fil_x_preferred":[
        "Bahi"
    ],
    "wof:name":"Bahi",
    "wof:placetype":"locality"
},
  "geometry": {"coordinates":[123.6292,13.8871],"type":"Point"}
}