{
  "type": "Feature",
  "properties": {
    "gn:admin1_code":"02",
    "gn:admin2_code":"14",
    "gn:admin3_code":"21516000.0",
    "gn:asciiname":"San Lorenzo",
    "gn:country_code":"PH",
    "gn:dem":14,
    "gn:feature_class":"P",
    "gn:feature_code":"PPL",
    "gn:name":"San Lorenzo",
    "gn:population":0,
    "gn:timezone":"Asia/Manila",
    "iso:country":"PH",
    "name:ara_x_preferred":[
        "\u0633\u0627\u0646 \u0644\u0648\u0631\u064a\u0646\u0632\u0648"
    ],
    "name:arg_x_preferred":[
        "Sant Lorient"
    ],
    "name:cat_x_preferred":[
        "San Lorenzo"
    ],
    "name:ceb_x_preferred":[
        "San Lorenzo"
    ],
    "name:ces_x_preferred":[
        "San Lorenzo"
    ],
    "name:deu_x_preferred":[
        "San Lorenzo"
    ],
    "name:epo_x_preferred":[
        "San Lorenzo"
    ],
    "name:eus_x_preferred":[
        "San Lorenzo"
    ],
    "name:fas_x_preferred":[
        "\u0633\u0646 \u0644\u0648\u0631\u0646\u0632\u0648"
    ],
    "name:fil_x_preferred":[
        "San Lorenzo"
    ],
    "name:fin_x_preferred":[
        "San Lorenzo"
    ],
    "name:fra_x_preferred":[
        "San Lorenzo"
    ],
    "name:heb_x_preferred":[
        "\u05e1\u05df \u05dc\u05d5\u05e8\u05e0\u05e6\u05d5"
    ],
    "name:hun_x_preferred":[
        "San Lorenzo"
    ],
    "name:ita_x_preferred":[
        "San Lorenzo"
    ],
    "name:jpn_x_preferred":[
        "\u30b5\u30f3\u30ed\u30ec\u30f3\u30bd"
    ],
    "name:kor_x_preferred":[
        "\uc0b0 \ub85c\ub80c\uc870"
    ],
    "name:kor_x_variant":[
        "\uc0b0\ub85c\ub80c\uc18c"
    ],
    "name:lit_x_preferred":[
        "San Lorensas"
    ],
    "name:mlg_x_preferred":[
        "San Lorenzo"
    ],
    "name:nds_x_preferred":[
        "San Lorenzo"
    ],
    "name:nld_x_preferred":[
        "San Lorenzo"
    ],
    "name:nor_x_preferred":[
        "San Lorenzo"
    ],
    "name:pol_x_preferred":[
        "San Lorenzo"
    ],
    "name:por_x_preferred":[
        "San Lorenzo"
    ],
    "name:ron_x_preferred":[
        "San Lorenzo"
    ],
    "name:rus_x_preferred":[
        "\u0421\u0430\u043d-\u041b\u043e\u0440\u0435\u043d\u0441\u043e"
    ],
    "name:sco_x_preferred":[
        "San Lorenzo"
    ],
    "name:slk_x_preferred":[
        "San Lorenzo"
    ],
    "name:spa_x_preferred":[
        "San Lorenzo"
    ],
    "name:srp_x_preferred":[
        "\u0421\u0430\u043d \u041b\u043e\u0440\u0435\u043d\u0446\u043e"
    ],
    "name:swe_x_preferred":[
        "San Lorenzo"
    ],
    "name:tur_x_preferred":[
        "San Lorenzo"
    ],
    "name:ukr_x_preferred":[
        "\u0421\u0430\u043d-\u041b\u043e\u0440\u0435\u043d\u0441\u043e"
    ],
    "name:urd_x_preferred":[
        "\u0633\u0627\u0646 \u0644\u0648\u0631\u06cc\u0646\u0632\u0648"
    ],
    "name:vep_x_preferred":[
        "San Lorenso"
    ],
    "name:vie_x_preferred":[
        "San Lorenzo"
    ],
    "name:vol_x_preferred":[
        "San Lorenzo"
    ],
    "name:war_x_preferred":[
        "San Lorenzo"
    ],
    "name:zho_cn_x_preferred":[
        "\u5723\u6d1b\u4f26\u7d22"
    ],
    "name:zho_tw_x_preferred":[
        "\u8056\u6d1b\u502b\u7d22"
    ],
    "wof:name":"San Lorenzo",
    "wof:placetype":"locality"
},
  "geometry": {"coordinates":[121.64569,18.14921],"type":"Point"}
}