{
  "type": "Feature",
  "properties": {
    "gn:admin1_code":"02",
    "gn:admin2_code":"14",
    "gn:admin3_code":"21516000.0",
    "gn:asciiname":"San Lorenzo",
    "gn:country_code":"PH",
    "gn:dem":14,
    "gn:feature_class":"P",
    "gn:feature_code":"PPL",
    "gn:name":"San Lorenzo",
    "gn:population":0,
    "gn:timezone":"Asia/Manila",
    "iso:country":"PH",
    "name:fil_x_preferred":[
        "San Lorenzo"
    ],
    "wof:name":"San Lorenzo",
    "wof:placetype":"locality"
},
  "geometry": {"coordinates":[121.64569,18.14921],"type":"Point"}
}