{
  "type": "Feature",
  "properties": {
    "gn:country":"PH",
    "gn:fcode":"PPL",
    "gn:pop":6003,
    "iso:country":"PH",
    "name:fil_x_preferred":[
        "Talaban"
    ],
    "qs:name":"Talaban",
    "qs:photos_9r":0,
    "qs:photos_sr":0,
    "qs:pop_sr":"5",
    "wof:name":"Talaban",
    "wof:placetype":"locality",
    "wof:population":6003
},
  "geometry": {"coordinates":[122.86709999999999,10.1254],"type":"Point"}
}