{
  "type": "Feature",
  "properties": {
    "gn:admin1_code":"40",
    "gn:admin2_code":"H2",
    "gn:admin3_code":"45617000.0",
    "gn:asciiname":"May Neu",
    "gn:country_code":"PH",
    "gn:dem":227,
    "gn:feature_class":"P",
    "gn:feature_code":"PPL",
    "gn:name":"May Neu",
    "gn:population":0,
    "gn:timezone":"Asia/Manila",
    "iso:country":"PH",
    "name:fil_x_preferred":[
        "May Neu"
    ],
    "wof:name":"May Neu",
    "wof:placetype":"locality"
},
  "geometry": {"coordinates":[121.51667,14.68333],"type":"Point"}
}