{
  "type": "Feature",
  "properties": {
    "gn:country":"PH",
    "gn:fcode":"PPL",
    "gn:pop":4796,
    "iso:country":"PH",
    "name:bcl_x_preferred":[
        "Libacao"
    ],
    "name:ceb_x_preferred":[
        "Libacao"
    ],
    "name:deu_x_preferred":[
        "Libacao"
    ],
    "name:fil_x_preferred":[
        "Libacao"
    ],
    "name:fra_x_preferred":[
        "Libacao"
    ],
    "name:ilo_x_preferred":[
        "Libacao"
    ],
    "name:ind_x_preferred":[
        "Libacao"
    ],
    "name:ita_x_preferred":[
        "Libacao"
    ],
    "name:msa_x_preferred":[
        "Libacao"
    ],
    "name:nld_x_preferred":[
        "Libacao"
    ],
    "name:pag_x_preferred":[
        "Libacao"
    ],
    "name:pam_x_preferred":[
        "Libacao"
    ],
    "name:por_x_preferred":[
        "Libacao"
    ],
    "name:swe_x_preferred":[
        "Libacao"
    ],
    "name:tgl_x_preferred":[
        "Libacao"
    ],
    "name:urd_x_preferred":[
        "\u0644\u06cc\u0628\u0627\u0633\u0627\u0648"
    ],
    "name:vie_x_preferred":[
        "Libacao"
    ],
    "name:war_x_preferred":[
        "Libacao"
    ],
    "qs:name":"Libacao",
    "qs:photos_9r":0,
    "qs:photos_sr":0,
    "qs:pop_sr":"4",
    "wof:name":"Libacao",
    "wof:placetype":"locality",
    "wof:population":4796
},
  "geometry": {"coordinates":[122.91370000000001,10.18],"type":"Point"}
}