{
  "type": "Feature",
  "properties": {
    "gn:country":"PH",
    "gn:fcode":"PPL",
    "gn:pop":4796,
    "iso:country":"PH",
    "name:fil_x_preferred":[
        "Libacao"
    ],
    "qs:name":"Libacao",
    "qs:photos_9r":0,
    "qs:photos_sr":0,
    "qs:pop_sr":"4",
    "wof:name":"Libacao",
    "wof:placetype":"locality",
    "wof:population":4796
},
  "geometry": {"coordinates":[122.91370000000001,10.18],"type":"Point"}
}