{
  "type": "Feature",
  "properties": {
    "gn:country":"PH",
    "gn:fcode":"PPL",
    "gn:population":2554,
    "iso:country":"PH",
    "name:deu_x_preferred":[
        "Doong-Insel"
    ],
    "name:eng_x_preferred":[
        "Doong"
    ],
    "name:eng_x_variant":[
        "Doong Island"
    ],
    "name:fil_x_preferred":[
        "Doong"
    ],
    "name:ind_x_preferred":[
        "Pulau Doong"
    ],
    "name:jpn_x_preferred":[
        "\u30c9\u30aa\u30f3\u5cf6"
    ],
    "qs:name":"Doong",
    "qs:photos_9r":0,
    "qs:photos_sr":0,
    "qs:pop_sr":"4",
    "wd:wordcount":41,
    "wof:name":"Doong",
    "wof:placetype":"locality",
    "wof:population":2554
},
  "geometry": {"coordinates":[123.6395,11.0786],"type":"Point"}
}