{
  "type": "Feature",
  "properties": {
    "gn:country":"PH",
    "gn:fcode":"PPL",
    "gn:pop":2554,
    "iso:country":"PH",
    "name:eng_x_preferred":[
        "Doong"
    ],
    "name:fil_x_preferred":[
        "Doong"
    ],
    "qs:name":"Doong",
    "qs:photos_9r":0,
    "qs:photos_sr":0,
    "qs:pop_sr":"4",
    "wd:wordcount":41,
    "wof:name":"Doong",
    "wof:placetype":"locality",
    "wof:population":2554
},
  "geometry": {"coordinates":[123.6395,11.0786],"type":"Point"}
}