{
  "type": "Feature",
  "properties": {
    "gn:admin1_code":"07",
    "gn:admin2_code":"11",
    "gn:admin3_code":"71208000.0",
    "gn:asciiname":"Canbigsi",
    "gn:cc2":"PH",
    "gn:country_code":"PH",
    "gn:dem":473,
    "gn:feature_class":"P",
    "gn:feature_code":"PPL",
    "gn:name":"Canbigsi",
    "gn:population":0,
    "gn:timezone":"Asia/Manila",
    "iso:country":"PH",
    "name:und_x_variant":[
        "Cambigsi",
        "Canbigsi"
    ],
    "wof:name":"Canbigsi",
    "wof:placetype":"locality"
},
  "geometry": {"coordinates":[124.16694,9.74361],"type":"Point"}
}