{
  "type": "Feature",
  "properties": {
    "gn:admin1_code":"03",
    "gn:admin2_code":"64",
    "gn:admin3_code":"37108000.0",
    "gn:asciiname":"Macarang",
    "gn:country_code":"PH",
    "gn:dem":15,
    "gn:feature_class":"P",
    "gn:feature_code":"PPL",
    "gn:name":"Macarang",
    "gn:population":0,
    "gn:timezone":"Asia/Manila",
    "iso:country":"PH",
    "name:fil_x_preferred":[
        "Macarang"
    ],
    "wof:name":"Macarang",
    "wof:placetype":"locality"
},
  "geometry": {"coordinates":[119.9345,15.4052],"type":"Point"}
}