{
  "type": "Feature",
  "properties": {
    "gn:admin1_code":"07",
    "gn:admin2_code":"11",
    "gn:admin3_code":"71213000.0",
    "gn:asciiname":"Cambailan",
    "gn:country_code":"PH",
    "gn:dem":250,
    "gn:feature_class":"P",
    "gn:feature_code":"PPL",
    "gn:name":"Cambailan",
    "gn:population":0,
    "gn:timezone":"Asia/Manila",
    "iso:country":"PH",
    "name:fil_x_preferred":[
        "Cambailan"
    ],
    "wof:name":"Cambailan",
    "wof:placetype":"locality"
},
  "geometry": {"coordinates":[124.0461,9.8297],"type":"Point"}
}