{
  "type": "Feature",
  "properties": {
    "gn:gn_country":"PH",
    "gn:gn_fcode":"PPL",
    "gn:gn_pop":2234,
    "gn:population":2234,
    "iso:country":"PH",
    "name:fil_x_preferred":[
        "Capuluan"
    ],
    "name:unk_x_variant":[
        "Capuluan Central"
    ],
    "qs_pg:aaroncc":"PH",
    "qs_pg:gn_country":"PH",
    "qs_pg:gn_fcode":"PPL",
    "qs_pg:gn_pop":2234,
    "qs_pg:name":"Capuluan",
    "qs_pg:photos_9r":0,
    "qs_pg:photos_sr":0,
    "qs_pg:pop_sr":4,
    "qs_pg:qs_pg_placetype":"locality",
    "wof:name":"Capuluan",
    "wof:placetype":"locality",
    "wof:population":2234
},
  "geometry": {"coordinates":[122.5158,13.8162],"type":"Point"}
}