{
  "type": "Feature",
  "properties": {
    "gn:admin1_code":"08",
    "gn:admin2_code":"H9",
    "gn:admin3_code":"87807000.0",
    "gn:asciiname":"Casibong",
    "gn:country_code":"PH",
    "gn:dem":72,
    "gn:feature_class":"P",
    "gn:feature_code":"PPL",
    "gn:name":"Casibong",
    "gn:population":0,
    "gn:timezone":"Asia/Manila",
    "iso:country":"PH",
    "name:fil_x_preferred":[
        "Casibong"
    ],
    "wof:name":"Casibong",
    "wof:placetype":"locality"
},
  "geometry": {"coordinates":[124.31111,11.76972],"type":"Point"}
}