{
  "type": "Feature",
  "properties": {
    "gn:admin1_code":"02",
    "gn:admin2_code":"31",
    "gn:admin3_code":"23131000.0",
    "gn:asciiname":"Pili",
    "gn:country_code":"PH",
    "gn:dem":229,
    "gn:feature_class":"P",
    "gn:feature_code":"PPL",
    "gn:name":"Pili",
    "gn:population":0,
    "gn:timezone":"Asia/Manila",
    "iso:country":"PH",
    "name:cat_x_preferred":[
        "Pili"
    ],
    "name:ceb_x_preferred":[
        "Pili"
    ],
    "name:deu_x_preferred":[
        "Pili"
    ],
    "name:fil_x_preferred":[
        "Pili"
    ],
    "name:fin_x_preferred":[
        "Pili"
    ],
    "name:fra_x_preferred":[
        "Pili"
    ],
    "name:ita_x_preferred":[
        "Pili"
    ],
    "name:swe_x_preferred":[
        "Pili"
    ],
    "name:tgl_x_preferred":[
        "Pili"
    ],
    "name:tur_x_preferred":[
        "Pili"
    ],
    "wof:name":"Pili",
    "wof:placetype":"locality"
},
  "geometry": {"coordinates":[122.03564,16.75116],"type":"Point"}
}