{
  "type": "Feature",
  "properties": {
    "gn:admin1_code":"12",
    "gn:admin2_code":"57",
    "gn:admin3_code":"124712000.0",
    "gn:asciiname":"Gapon",
    "gn:country_code":"PH",
    "gn:dem":7,
    "gn:feature_class":"P",
    "gn:feature_code":"PPL",
    "gn:name":"Gapon",
    "gn:population":0,
    "gn:timezone":"Asia/Manila",
    "iso:country":"PH",
    "name:fil_x_preferred":[
        "Gapon"
    ],
    "wof:name":"Gapon",
    "wof:placetype":"locality"
},
  "geometry": {"coordinates":[124.53333000000001,7.03333],"type":"Point"}
}