{
  "type": "Feature",
  "properties": {
    "gn:admin1_code":"03",
    "gn:admin2_code":"50",
    "gn:admin3_code":"35412000.0",
    "gn:asciiname":"Caingin",
    "gn:country_code":"PH",
    "gn:dem":5,
    "gn:feature_class":"P",
    "gn:feature_code":"PPL",
    "gn:name":"Caingin",
    "gn:population":0,
    "gn:timezone":"Asia/Manila",
    "iso:country":"PH",
    "name:fil_x_preferred":[
        "Caingin"
    ],
    "name:fil_x_variant":[
        "Gaingin"
    ],
    "wof:name":"Caingin",
    "wof:placetype":"locality"
},
  "geometry": {"coordinates":[120.6979,14.8624],"type":"Point"}
}