{
  "type": "Feature",
  "properties": {
    "gn:admin1_code":"05",
    "gn:admin2_code":"19",
    "gn:admin3_code":"52011000.0",
    "gn:asciiname":"Francia",
    "gn:country_code":"PH",
    "gn:dem":5,
    "gn:feature_class":"P",
    "gn:feature_code":"PPL",
    "gn:name":"Francia",
    "gn:population":0,
    "gn:timezone":"Asia/Manila",
    "iso:country":"PH",
    "name:fil_x_preferred":[
        "Francia"
    ],
    "wof:name":"Francia",
    "wof:placetype":"locality"
},
  "geometry": {"coordinates":[124.24160000000001,13.5899],"type":"Point"}
}