{
  "type": "Feature",
  "properties": {
    "gn:admin1_code":"02",
    "gn:admin2_code":"14",
    "gn:admin3_code":"21508000.0",
    "gn:asciiname":"Fula",
    "gn:country_code":"PH",
    "gn:dem":12,
    "gn:feature_class":"P",
    "gn:feature_code":"PPL",
    "gn:name":"Fula",
    "gn:population":0,
    "gn:timezone":"Asia/Manila",
    "iso:country":"PH",
    "name:ceb_x_preferred":[
        "Fula"
    ],
    "name:fil_x_preferred":[
        "Fula"
    ],
    "name:ita_x_preferred":[
        "Fula"
    ],
    "name:nld_x_preferred":[
        "Fula"
    ],
    "name:pol_x_preferred":[
        "Fula"
    ],
    "name:por_x_preferred":[
        "Fula"
    ],
    "name:spa_x_preferred":[
        "Fula"
    ],
    "name:swe_x_preferred":[
        "Fula"
    ],
    "name:und_x_variant":[
        "Fulla"
    ],
    "wof:name":"Fula",
    "wof:placetype":"locality"
},
  "geometry": {"coordinates":[121.78385,18.24907],"type":"Point"}
}