{
  "type": "Feature",
  "properties": {
    "gn:admin1_code":"40",
    "gn:admin2_code":"33",
    "gn:admin3_code":"43414000.0",
    "gn:asciiname":"Dakila",
    "gn:country_code":"PH",
    "gn:dem":4,
    "gn:feature_class":"P",
    "gn:feature_code":"PPL",
    "gn:name":"Dakila",
    "gn:population":0,
    "gn:timezone":"Asia/Manila",
    "iso:country":"PH",
    "name:fil_x_preferred":[
        "Dakila"
    ],
    "wof:name":"Dakila",
    "wof:placetype":"locality"
},
  "geometry": {"coordinates":[121.4224,14.4116],"type":"Point"}
}