{
  "type": "Feature",
  "properties": {
    "gn:admin1_code":"40",
    "gn:admin2_code":"H2",
    "gn:admin3_code":"45619000.0",
    "gn:asciiname":"Anos",
    "gn:country_code":"PH",
    "gn:dem":249,
    "gn:feature_class":"P",
    "gn:feature_code":"PPL",
    "gn:name":"Anos",
    "gn:population":0,
    "gn:timezone":"Asia/Manila",
    "iso:country":"PH",
    "name:fil_x_preferred":[
        "Anos"
    ],
    "name:und_x_variant":[
        "Anus"
    ],
    "wof:name":"Anos",
    "wof:placetype":"locality"
},
  "geometry": {"coordinates":[122.18600000000001,13.8268],"type":"Point"}
}