{
  "type": "Feature",
  "properties": {
    "gn:admin1_code":"40",
    "gn:admin2_code":"H2",
    "gn:admin3_code":"45619000.0",
    "gn:asciiname":"Anos",
    "gn:country_code":"PH",
    "gn:dem":249,
    "gn:feature_class":"P",
    "gn:feature_code":"PPL",
    "gn:name":"Anos",
    "gn:population":0,
    "gn:timezone":"Asia/Manila",
    "iso:country":"PH",
    "name:arg_x_preferred":[
        "An\u00f2s"
    ],
    "name:cat_x_preferred":[
        "An\u00f2s"
    ],
    "name:ceb_x_preferred":[
        "Anos"
    ],
    "name:deu_x_preferred":[
        "Anos"
    ],
    "name:eus_x_preferred":[
        "Anos"
    ],
    "name:fil_x_preferred":[
        "Anos"
    ],
    "name:fra_x_preferred":[
        "Anos"
    ],
    "name:hun_x_preferred":[
        "Anos"
    ],
    "name:ita_x_preferred":[
        "Anos"
    ],
    "name:kaz_x_preferred":[
        "\u0410\u043d\u043e\u0441"
    ],
    "name:lat_x_preferred":[
        "Anos"
    ],
    "name:msa_x_preferred":[
        "Anos"
    ],
    "name:nld_x_preferred":[
        "Anos"
    ],
    "name:oci_x_preferred":[
        "An\u00f2s"
    ],
    "name:pms_x_preferred":[
        "Anos"
    ],
    "name:pol_x_preferred":[
        "Anos"
    ],
    "name:por_x_preferred":[
        "Anos"
    ],
    "name:ron_x_preferred":[
        "Anos"
    ],
    "name:rus_x_preferred":[
        "\u0410\u043d\u043e\u0441"
    ],
    "name:slk_x_preferred":[
        "Anos"
    ],
    "name:spa_x_preferred":[
        "Anos"
    ],
    "name:srp_x_preferred":[
        "\u0410\u043d\u043e"
    ],
    "name:swe_x_preferred":[
        "Anos"
    ],
    "name:ukr_x_preferred":[
        "\u0410\u043d\u043e\u0441"
    ],
    "name:und_x_variant":[
        "Anus"
    ],
    "name:uzb_x_preferred":[
        "Anos"
    ],
    "name:vie_x_preferred":[
        "Anos"
    ],
    "name:vol_x_preferred":[
        "Anos"
    ],
    "name:war_x_preferred":[
        "Anos"
    ],
    "name:zho_x_preferred":[
        "\u963f\u8bfa\u65af"
    ],
    "wof:name":"Anos",
    "wof:placetype":"locality"
},
  "geometry": {"coordinates":[122.18600000000001,13.8268],"type":"Point"}
}