{
  "type": "Feature",
  "properties": {
    "gn:admin1_code":"06",
    "gn:admin2_code":"J3",
    "gn:admin3_code":"67905000.0",
    "gn:asciiname":"Curipao",
    "gn:country_code":"PH",
    "gn:dem":165,
    "gn:feature_class":"P",
    "gn:feature_code":"PPL",
    "gn:name":"Curipao",
    "gn:population":0,
    "gn:timezone":"Asia/Manila",
    "iso:country":"PH",
    "name:fil_x_preferred":[
        "Curipao"
    ],
    "wof:name":"Curipao",
    "wof:placetype":"locality"
},
  "geometry": {"coordinates":[122.6096,10.57416],"type":"Point"}
}