{
  "type": "Feature",
  "properties": {
    "gn:admin1_code":"05",
    "gn:admin2_code":"05",
    "gn:admin3_code":"50512000.0",
    "gn:asciiname":"Tobgon",
    "gn:country_code":"PH",
    "gn:dem":150,
    "gn:feature_class":"P",
    "gn:feature_code":"PPL",
    "gn:name":"Tobgon",
    "gn:population":0,
    "gn:timezone":"Asia/Manila",
    "iso:country":"PH",
    "name:fil_x_preferred":[
        "Tobgon"
    ],
    "wof:name":"Tobgon",
    "wof:placetype":"locality"
},
  "geometry": {"coordinates":[123.43986,13.22397],"type":"Point"}
}