{
  "type": "Feature",
  "properties": {
    "gn:admin1_code":"03",
    "gn:admin2_code":"50",
    "gn:admin3_code":"35415000.0",
    "gn:asciiname":"Sepung Bulaun",
    "gn:country_code":"PH",
    "gn:dem":65,
    "gn:feature_class":"P",
    "gn:feature_code":"PPL",
    "gn:name":"Sepung Bulaun",
    "gn:population":0,
    "gn:timezone":"Asia/Manila",
    "iso:country":"PH",
    "name:fil_x_preferred":[
        "Sepung Bulaun"
    ],
    "name:fil_x_variant":[
        "Sepung Bulaon"
    ],
    "name:und_x_variant":[
        "Sepung Bulaon"
    ],
    "wof:name":"Sepung Bulaun",
    "wof:placetype":"locality"
},
  "geometry": {"coordinates":[120.54957,15.04352],"type":"Point"}
}