{
  "type": "Feature",
  "properties": {
    "gn:admin1_code":"06",
    "gn:admin2_code":"06",
    "gn:admin3_code":"60608000.0",
    "gn:asciiname":"Bia-an",
    "gn:country_code":"PH",
    "gn:dem":14,
    "gn:feature_class":"P",
    "gn:feature_code":"PPL",
    "gn:name":"Bia-an",
    "gn:population":0,
    "gn:timezone":"Asia/Manila",
    "iso:country":"PH",
    "name:fil_x_preferred":[
        "Bia-an"
    ],
    "wof:name":"Bia-an",
    "wof:placetype":"locality"
},
  "geometry": {"coordinates":[121.99379999999999,10.7193],"type":"Point"}
}