{
  "type": "Feature",
  "properties": {
    "gn:admin1_code":"13",
    "gn:admin2_code":"61",
    "gn:admin3_code":"166721000.0",
    "gn:asciiname":"Alegria",
    "gn:cc2":"PH",
    "gn:country_code":"PH",
    "gn:dem":11,
    "gn:feature_class":"P",
    "gn:feature_code":"PPL",
    "gn:name":"Alegria",
    "gn:population":0,
    "gn:timezone":"Asia/Manila",
    "iso:country":"PH",
    "name:und_x_variant":[
        "Algeria",
        "Alegria"
    ],
    "wof:name":"Alegria",
    "wof:placetype":"locality"
},
  "geometry": {"coordinates":[126.06889,10.05528],"type":"Point"}
}