{
  "type": "Feature",
  "properties": {
    "gn:admin1_code":"15",
    "gn:admin2_code":"32",
    "gn:admin3_code":"143201000.0",
    "gn:asciiname":"Gollod",
    "gn:country_code":"PH",
    "gn:dem":489,
    "gn:feature_class":"P",
    "gn:feature_code":"PPL",
    "gn:name":"Gollod",
    "gn:population":0,
    "gn:timezone":"Asia/Manila",
    "iso:country":"PH",
    "name:fil_x_preferred":[
        "Gollod"
    ],
    "wof:name":"Gollod",
    "wof:placetype":"locality"
},
  "geometry": {"coordinates":[121.30745,17.55002],"type":"Point"}
}