{
  "type": "Feature",
  "properties": {
    "gn:admin1_code":"06",
    "gn:admin2_code":"30",
    "gn:admin3_code":"63012000.0",
    "gn:asciiname":"Badon",
    "gn:country_code":"PH",
    "gn:dem":64,
    "gn:feature_class":"P",
    "gn:feature_code":"PPL",
    "gn:name":"Badon",
    "gn:population":0,
    "gn:timezone":"Asia/Manila",
    "iso:country":"PH",
    "name:ceb_x_preferred":[
        "Badon"
    ],
    "name:fil_x_preferred":[
        "Badon"
    ],
    "name:ita_x_preferred":[
        "Badon"
    ],
    "name:swe_x_preferred":[
        "Badon"
    ],
    "name:und_x_variant":[
        "Bacan"
    ],
    "wof:name":"Badon",
    "wof:placetype":"locality"
},
  "geometry": {"coordinates":[122.46120000000001,10.8852],"type":"Point"}
}