{
  "type": "Feature",
  "properties": {
    "gn:admin1_code":"14",
    "gn:admin2_code":"60",
    "gn:admin3_code":"156605000.0",
    "gn:asciiname":"Bualo Lahi",
    "gn:country_code":"PH",
    "gn:dem":22,
    "gn:feature_class":"P",
    "gn:feature_code":"PPL",
    "gn:name":"Bualo Lahi",
    "gn:population":0,
    "gn:timezone":"Asia/Manila",
    "iso:country":"PH",
    "name:fil_x_preferred":[
        "Bualo Lahi"
    ],
    "wof:name":"Bualo Lahi",
    "wof:placetype":"locality"
},
  "geometry": {"coordinates":[121.00472000000001,5.9275],"type":"Point"}
}