{
  "type": "Feature",
  "properties": {
    "gn:admin1_code":"02",
    "gn:admin2_code":"31",
    "gn:admin3_code":"23131000.0",
    "gn:asciiname":"Libati",
    "gn:country_code":"PH",
    "gn:dem":987,
    "gn:feature_class":"P",
    "gn:feature_code":"PPL",
    "gn:name":"Libati",
    "gn:population":0,
    "gn:timezone":"Asia/Manila",
    "iso:country":"PH",
    "name:fil_x_preferred":[
        "Libati"
    ],
    "wof:name":"Libati",
    "wof:placetype":"locality"
},
  "geometry": {"coordinates":[122.28333000000001,17.01667],"type":"Point"}
}