{
  "type": "Feature",
  "properties": {
    "gn:country":"PH",
    "gn:fcode":"PPL",
    "gn:pop":2704,
    "iso:country":"PH",
    "name:ara_x_preferred":[
        "\u0628\u064a\u0633\u0644\u064a\u062c"
    ],
    "name:bcl_x_preferred":[
        "Bislig"
    ],
    "name:ceb_x_preferred":[
        "Bislig"
    ],
    "name:deu_x_preferred":[
        "Bislig"
    ],
    "name:fra_x_preferred":[
        "Bislig"
    ],
    "name:ilo_x_preferred":[
        "Bislig"
    ],
    "name:ind_x_preferred":[
        "Bislig"
    ],
    "name:ita_x_preferred":[
        "Bislig"
    ],
    "name:nld_x_preferred":[
        "Bislig"
    ],
    "name:nor_x_preferred":[
        "Bislig"
    ],
    "name:pag_x_preferred":[
        "Bislig"
    ],
    "name:pam_x_preferred":[
        "Bislig"
    ],
    "name:spa_x_preferred":[
        "Bislig"
    ],
    "name:swe_x_preferred":[
        "Bislig"
    ],
    "name:tgl_x_preferred":[
        "Bislig"
    ],
    "name:unk_x_variant":[
        "Bitlig"
    ],
    "name:urd_x_preferred":[
        "\u0628\u0633\u0644\u06af"
    ],
    "name:war_x_preferred":[
        "Bislig"
    ],
    "name:zho_x_preferred":[
        "\u6bd4\u65af\u5229\u683c\u5e02"
    ],
    "qs:name":"Bislig",
    "qs:photos_9r":0,
    "qs:photos_sr":0,
    "qs:pop_sr":"4",
    "wd:wordcount":2668,
    "wof:name":"Bislig",
    "wof:placetype":"locality",
    "wof:population":2704
},
  "geometry": {"coordinates":[125.03361,11.0725],"type":"Point"}
}