{
  "type": "Feature",
  "properties": {
    "gn:country":"PH",
    "gn:fcode":"PPL",
    "gn:pop":5110,
    "iso:country":"PH",
    "name:ceb_x_preferred":[
        "Plaridel"
    ],
    "name:deu_x_preferred":[
        "Plaridel"
    ],
    "name:fil_x_preferred":[
        "Plaridel"
    ],
    "name:fra_x_preferred":[
        "Plaridel"
    ],
    "name:ita_x_preferred":[
        "Plaridel"
    ],
    "name:nld_x_preferred":[
        "Plaridel"
    ],
    "name:war_x_preferred":[
        "Plaridel"
    ],
    "qs:name":"Plaridel",
    "qs:photos_9r":0,
    "qs:photos_sr":0,
    "qs:pop_sr":"5",
    "wd:wordcount":50,
    "wof:name":"Plaridel",
    "wof:placetype":"locality",
    "wof:population":5110
},
  "geometry": {"coordinates":[123.4894,10.8974],"type":"Point"}
}