{
  "type": "Feature",
  "properties": {
    "gn:country":"PH",
    "gn:fcode":"PPL",
    "gn:pop":2769,
    "iso:country":"PH",
    "name:fil_x_preferred":[
        "San Miguel"
    ],
    "qs:name":"San Miguel",
    "qs:photos_9r":0,
    "qs:photos_sr":0,
    "qs:pop_sr":"4",
    "wd:wordcount":976,
    "wof:name":"San Miguel",
    "wof:placetype":"locality",
    "wof:population":2769
},
  "geometry": {"coordinates":[123.28530000000001,9.2239],"type":"Point"}
}