{
  "type": "Feature",
  "properties": {
    "gn:admin1_code":"06",
    "gn:admin2_code":"18",
    "gn:admin3_code":"61917000.0",
    "gn:asciiname":"McKinley",
    "gn:country_code":"PH",
    "gn:dem":59,
    "gn:feature_class":"P",
    "gn:feature_code":"PPL",
    "gn:name":"McKinley",
    "gn:population":0,
    "gn:timezone":"Asia/Manila",
    "iso:country":"PH",
    "name:bel_x_preferred":[
        "\u041c\u0430\u043a-\u041a\u0456\u043d\u043b\u0456"
    ],
    "name:ceb_x_preferred":[
        "McKinley"
    ],
    "name:deu_x_preferred":[
        "McKinley"
    ],
    "name:fil_x_preferred":[
        "McKinley"
    ],
    "name:fin_x_preferred":[
        "McKinley"
    ],
    "name:fra_x_preferred":[
        "McKinley"
    ],
    "name:heb_x_preferred":[
        "\u05de\u05e7\u05d9\u05e0\u05dc\u05d9"
    ],
    "name:ita_x_preferred":[
        "McKinley"
    ],
    "name:jpn_x_preferred":[
        "\u30de\u30c3\u30ad\u30f3\u30ea\u30fc"
    ],
    "name:kor_x_preferred":[
        "\ub9e4\ud0a8\ub9ac"
    ],
    "name:lav_x_preferred":[
        "Makinlijs"
    ],
    "name:lmo_x_preferred":[
        "McKinley"
    ],
    "name:nds_x_preferred":[
        "McKinley"
    ],
    "name:pol_x_preferred":[
        "McKinley"
    ],
    "name:por_x_preferred":[
        "McKinley"
    ],
    "name:rus_x_preferred":[
        "\u041c\u0430\u043a-\u041a\u0438\u043d\u043b\u0438"
    ],
    "name:slk_x_preferred":[
        "McKinley"
    ],
    "name:spa_x_preferred":[
        "McKinley"
    ],
    "name:srp_x_preferred":[
        "\u041c\u0430\u043a\u0438\u043d\u043b\u0438"
    ],
    "name:swe_x_preferred":[
        "McKinley"
    ],
    "name:ukr_x_preferred":[
        "\u041c\u0430\u043a-\u041a\u0456\u043d\u043b\u0456"
    ],
    "name:vol_x_preferred":[
        "McKinley"
    ],
    "name:zho_x_preferred":[
        "\u9ea6\u91d1\u83b1"
    ],
    "wof:name":"McKinley",
    "wof:placetype":"locality"
},
  "geometry": {"coordinates":[122.55,11.25],"type":"Point"}
}