{
  "type": "Feature",
  "properties": {
    "gn:admin1_code":"06",
    "gn:admin2_code":"18",
    "gn:admin3_code":"61917000.0",
    "gn:asciiname":"McKinley",
    "gn:country_code":"PH",
    "gn:dem":59,
    "gn:feature_class":"P",
    "gn:feature_code":"PPL",
    "gn:name":"McKinley",
    "gn:population":0,
    "gn:timezone":"Asia/Manila",
    "iso:country":"PH",
    "name:fil_x_preferred":[
        "McKinley"
    ],
    "wof:name":"McKinley",
    "wof:placetype":"locality"
},
  "geometry": {"coordinates":[122.55,11.25],"type":"Point"}
}