{
  "type": "Feature",
  "properties": {
    "gn:admin1_code":"41",
    "gn:admin2_code":"54",
    "gn:admin3_code":"175911000.0",
    "gn:asciiname":"Dumayay",
    "gn:country_code":"PH",
    "gn:dem":17,
    "gn:feature_class":"P",
    "gn:feature_code":"PPL",
    "gn:name":"Dumayay",
    "gn:population":0,
    "gn:timezone":"Asia/Manila",
    "iso:country":"PH",
    "name:fil_x_preferred":[
        "Dumayay"
    ],
    "wof:name":"Dumayay",
    "wof:placetype":"locality"
},
  "geometry": {"coordinates":[122.12860000000001,12.5987],"type":"Point"}
}