{
  "type": "Feature",
  "properties": {
    "gn:country":"PH",
    "gn:fcode":"PPL",
    "gn:population":3460,
    "iso:country":"PH",
    "name:fil_x_preferred":[
        "Managa"
    ],
    "qs:name":"Managa",
    "qs:photos_9r":0,
    "qs:photos_sr":0,
    "qs:pop_sr":"4",
    "wof:name":"Managa",
    "wof:placetype":"locality",
    "wof:population":3460
},
  "geometry": {"coordinates":[125.26806000000001,6.74611],"type":"Point"}
}