{
  "type": "Feature",
  "properties": {
    "gn:admin1_code":"41",
    "gn:admin2_code":"40",
    "gn:admin3_code":"175110000.0",
    "gn:asciiname":"Bunuaya",
    "gn:country_code":"PH",
    "gn:dem":35,
    "gn:feature_class":"P",
    "gn:feature_code":"PPL",
    "gn:name":"Bunuaya",
    "gn:population":0,
    "gn:timezone":"Asia/Manila",
    "iso:country":"PH",
    "name:fil_x_preferred":[
        "Bunuaya"
    ],
    "wof:name":"Bunuaya",
    "wof:placetype":"locality"
},
  "geometry": {"coordinates":[121.03991000000001,12.25676],"type":"Point"}
}