{
  "type": "Feature",
  "properties": {
    "gn:admin1_code":"14",
    "gn:admin2_code":"60",
    "gn:admin3_code":"156615000.0",
    "gn:asciiname":"Bukutua",
    "gn:cc2":"PH",
    "gn:country_code":"PH",
    "gn:dem":15,
    "gn:feature_class":"P",
    "gn:feature_code":"PPL",
    "gn:name":"Bukutua",
    "gn:population":0,
    "gn:timezone":"Asia/Manila",
    "iso:country":"PH",
    "name:und_x_variant":[
        "Bucutua",
        "Bukut Tua",
        "Bukutua"
    ],
    "wof:name":"Bukutua",
    "wof:placetype":"locality"
},
  "geometry": {"coordinates":[121.80278,6.16278],"type":"Point"}
}