{
  "type": "Feature",
  "properties": {
    "gn:admin1_code":"06",
    "gn:admin2_code":"18",
    "gn:admin3_code":"61908000.0",
    "gn:asciiname":"Pangpang",
    "gn:country_code":"PH",
    "gn:dem":17,
    "gn:feature_class":"P",
    "gn:feature_code":"PPL",
    "gn:name":"Pangpang",
    "gn:population":0,
    "gn:timezone":"Asia/Manila",
    "iso:country":"PH",
    "name:fil_x_preferred":[
        "Pangpang"
    ],
    "name:und_x_variant":[
        "Pangpang Sur"
    ],
    "wof:name":"Pangpang",
    "wof:placetype":"locality"
},
  "geometry": {"coordinates":[122.6254,11.4454],"type":"Point"}
}