{
  "type": "Feature",
  "properties": {
    "gn:admin1_code":"03",
    "gn:admin2_code":"50",
    "gn:admin3_code":"35405000.0",
    "gn:asciiname":"Tagulod",
    "gn:country_code":"PH",
    "gn:dem":11,
    "gn:feature_class":"P",
    "gn:feature_code":"PPL",
    "gn:name":"Tagulod",
    "gn:population":0,
    "gn:timezone":"Asia/Manila",
    "iso:country":"PH",
    "name:fil_x_preferred":[
        "Tagulis"
    ],
    "name:fil_x_variant":[
        "Tagulod"
    ],
    "name:und_x_variant":[
        "Tagulis",
        "Tagulod"
    ],
    "wof:name":"Tagulod",
    "wof:placetype":"locality"
},
  "geometry": {"coordinates":[120.92346000000001,15.1951],"type":"Point"}
}