{
  "type": "Feature",
  "properties": {
    "gn:admin1_code":"40",
    "gn:admin2_code":"53",
    "gn:admin3_code":"45814000.0",
    "gn:asciiname":"Dulumbayan",
    "gn:country_code":"PH",
    "gn:dem":175,
    "gn:feature_class":"P",
    "gn:feature_code":"PPL",
    "gn:name":"Dulumbayan",
    "gn:population":0,
    "gn:timezone":"Asia/Manila",
    "iso:country":"PH",
    "name:fil_x_preferred":[
        "Dulumbayan"
    ],
    "wof:name":"Dulumbayan",
    "wof:placetype":"locality"
},
  "geometry": {"coordinates":[121.1995,14.5525],"type":"Point"}
}