{
  "type": "Feature",
  "properties": {
    "gn:admin1_code":"08",
    "gn:admin2_code":"23",
    "gn:admin3_code":"82619000.0",
    "gn:asciiname":"Panaon",
    "gn:country_code":"PH",
    "gn:dem":50,
    "gn:feature_class":"P",
    "gn:feature_code":"PPL",
    "gn:name":"Panaon",
    "gn:population":0,
    "gn:timezone":"Asia/Manila",
    "iso:country":"PH",
    "name:fil_x_preferred":[
        "Panaon"
    ],
    "wof:name":"Panaon",
    "wof:placetype":"locality"
},
  "geometry": {"coordinates":[125.61667,11.16667],"type":"Point"}
}