{
  "type": "Feature",
  "properties": {
    "gn:admin1_code":"14",
    "gn:admin2_code":"60",
    "gn:admin3_code":"156608000.0",
    "gn:asciiname":"Tubig",
    "gn:country_code":"PH",
    "gn:dem":14,
    "gn:feature_class":"P",
    "gn:feature_code":"PPL",
    "gn:name":"Tubig",
    "gn:population":0,
    "gn:timezone":"Asia/Manila",
    "iso:country":"PH",
    "name:eng_x_preferred":[
        "Tubig"
    ],
    "wof:name":"Tubig",
    "wof:placetype":"locality"
},
  "geometry": {"coordinates":[120.5394,6.2815],"type":"Point"}
}