{
  "type": "Feature",
  "properties": {
    "gn:admin1_code":"40",
    "gn:admin2_code":"H2",
    "gn:admin3_code":"45620000.0",
    "gn:asciiname":"Dinahican",
    "gn:country_code":"PH",
    "gn:dem":5,
    "gn:feature_class":"P",
    "gn:feature_code":"PPL",
    "gn:name":"Dinahican",
    "gn:population":0,
    "gn:timezone":"Asia/Manila",
    "iso:country":"PH",
    "name:fil_x_preferred":[
        "Dinahican"
    ],
    "name:und_x_variant":[
        "Dinijican"
    ],
    "wof:name":"Dinahican",
    "wof:placetype":"locality"
},
  "geometry": {"coordinates":[121.71917000000001,14.69337],"type":"Point"}
}