{
  "type": "Feature",
  "properties": {
    "gn:admin1_code":"12",
    "gn:admin2_code":"57",
    "gn:asciiname":"Landong",
    "gn:country_code":"PH",
    "gn:dem":18,
    "gn:feature_class":"P",
    "gn:feature_code":"PPL",
    "gn:name":"Landong",
    "gn:population":0,
    "gn:timezone":"Asia/Manila",
    "iso:country":"PH",
    "name:fil_x_preferred":[
        "Landong"
    ],
    "wof:name":"Landong",
    "wof:placetype":"locality"
},
  "geometry": {"coordinates":[124.73193999999999,7.07333],"type":"Point"}
}