{
  "type": "Feature",
  "properties": {
    "gn:admin1_code":"11",
    "gn:admin2_code":"I6",
    "gn:admin3_code":"118206000.0",
    "gn:asciiname":"Cogon",
    "gn:country_code":"PH",
    "gn:dem":94,
    "gn:feature_class":"P",
    "gn:feature_code":"PPL",
    "gn:name":"Cogon",
    "gn:population":0,
    "gn:timezone":"Asia/Manila",
    "iso:country":"PH",
    "name:eng_x_preferred":[
        "Cogon"
    ],
    "wof:name":"Cogon",
    "wof:placetype":"locality"
},
  "geometry": {"coordinates":[125.95,7.4691],"type":"Point"}
}