{
  "type": "Feature",
  "properties": {
    "gn:admin1_code":"12",
    "gn:admin2_code":"57",
    "gn:admin3_code":"124712000.0",
    "gn:asciiname":"Balatican",
    "gn:country_code":"PH",
    "gn:dem":21,
    "gn:feature_class":"P",
    "gn:feature_code":"PPL",
    "gn:name":"Balatican",
    "gn:population":0,
    "gn:timezone":"Asia/Manila",
    "iso:country":"PH",
    "name:und_x_variant":[
        "Balatakan",
        "Balatikan"
    ],
    "wof:name":"Balatican",
    "wof:placetype":"locality"
},
  "geometry": {"coordinates":[124.68138999999999,7.08944],"type":"Point"}
}