{
  "type": "Feature",
  "properties": {
    "gn:admin1_code":"05",
    "gn:admin2_code":"39",
    "gn:admin3_code":"54110000.0",
    "gn:asciiname":"Buri",
    "gn:country_code":"PH",
    "gn:dem":9,
    "gn:feature_class":"P",
    "gn:feature_code":"PPL",
    "gn:name":"Buri",
    "gn:population":0,
    "gn:timezone":"Asia/Manila",
    "iso:country":"PH",
    "name:fil_x_preferred":[
        "Buri"
    ],
    "wof:name":"Buri",
    "wof:placetype":"locality"
},
  "geometry": {"coordinates":[123.24771,12.13765],"type":"Point"}
}