{
  "type": "Feature",
  "properties": {
    "gn:country":"PH",
    "gn:fcode":"PPL",
    "gn:population":3342,
    "iso:country":"PH",
    "name:fil_x_preferred":[
        "Catungawan Sur"
    ],
    "name:und_x_variant":[
        "Katungauan"
    ],
    "qs_pg:aaroncc":"PH",
    "qs_pg:gn_country":"PH",
    "qs_pg:gn_fcode":"PPL",
    "qs_pg:gn_pop":3342,
    "qs_pg:name":"Catungawan Sur",
    "qs_pg:photos_9r":0,
    "qs_pg:photos_sr":0,
    "qs_pg:pop_sr":4,
    "qs_pg:qs_pg_placetype":"locality",
    "wof:name":"Catungawan Sur",
    "wof:placetype":"locality",
    "wof:population":3342
},
  "geometry": {"coordinates":[124.4693,9.7817],"type":"Point"}
}