{
  "type": "Feature",
  "properties": {
    "gn:admin1_code":"08",
    "gn:admin2_code":"23",
    "gn:admin3_code":"82614000.0",
    "gn:asciiname":"Mojan od Tugas",
    "gn:country_code":"PH",
    "gn:dem":19,
    "gn:feature_class":"P",
    "gn:feature_code":"PPL",
    "gn:name":"Mojan od Tugas",
    "gn:population":0,
    "gn:timezone":"Asia/Manila",
    "iso:country":"PH",
    "name:eng_x_preferred":[
        "Mojan od Tugas"
    ],
    "wof:name":"Mojan od Tugas",
    "wof:placetype":"locality"
},
  "geometry": {"coordinates":[125.24760000000001,12.1584],"type":"Point"}
}