{
  "type": "Feature",
  "properties": {
    "gn:admin1_code":"14",
    "gn:admin2_code":"72",
    "gn:admin3_code":"157010000.0",
    "gn:asciiname":"Look Dato",
    "gn:country_code":"PH",
    "gn:dem":12,
    "gn:feature_class":"P",
    "gn:feature_code":"PPL",
    "gn:name":"Look Dato",
    "gn:population":0,
    "gn:timezone":"Asia/Manila",
    "iso:country":"PH",
    "name:eng_x_preferred":[
        "Look Dato"
    ],
    "name:und_x_variant":[
        "Locnato",
        "Look Nato"
    ],
    "wof:name":"Look Dato",
    "wof:placetype":"locality"
},
  "geometry": {"coordinates":[120.3165,5.1102],"type":"Point"}
}