{
  "type": "Feature",
  "properties": {
    "gn:admin1_code":"03",
    "gn:admin2_code":"63",
    "gn:admin3_code":"36902000.0",
    "gn:asciiname":"Cadmang",
    "gn:country_code":"PH",
    "gn:dem":654,
    "gn:feature_class":"P",
    "gn:feature_code":"PPL",
    "gn:name":"Cadmang",
    "gn:population":0,
    "gn:timezone":"Asia/Manila",
    "iso:country":"PH",
    "name:fil_x_preferred":[
        "Cadmang"
    ],
    "wof:name":"Cadmang",
    "wof:placetype":"locality"
},
  "geometry": {"coordinates":[120.40000000000001,15.21667],"type":"Point"}
}