{
  "type": "Feature",
  "properties": {
    "iso:country":"PH",
    "name:bcl_x_preferred":[
        "Sibulan"
    ],
    "name:cbk_zam_x_preferred":[
        "Sibulan"
    ],
    "name:ceb_x_preferred":[
        "Sibulan"
    ],
    "name:deu_x_preferred":[
        "Sibulan"
    ],
    "name:eng_x_preferred":[
        "Sibulan"
    ],
    "name:fil_x_preferred":[
        "Sibulan"
    ],
    "name:fra_x_preferred":[
        "Sibulan"
    ],
    "name:ilo_x_preferred":[
        "Sibulan"
    ],
    "name:ind_x_preferred":[
        "Sibulan"
    ],
    "name:ita_x_preferred":[
        "Sibulan"
    ],
    "name:jpn_x_preferred":[
        "\u30b7\u30d6\u30e9\u30f3"
    ],
    "name:nld_x_preferred":[
        "Sibulan"
    ],
    "name:pag_x_preferred":[
        "Sibulan"
    ],
    "name:pam_x_preferred":[
        "Sibulan"
    ],
    "name:spa_x_preferred":[
        "Sibul\u00e1n"
    ],
    "name:swe_x_preferred":[
        "Sibulan"
    ],
    "name:tgl_x_preferred":[
        "Sibulan"
    ],
    "name:vie_x_preferred":[
        "Sibulan"
    ],
    "name:war_x_preferred":[
        "Sibulan"
    ],
    "name:zho_x_preferred":[
        "\u932b\u5e03\u862d"
    ],
    "qs:gn_country":"PH",
    "qs:gn_fcode":"PPL",
    "qs:gn_pop":28079,
    "qs:name":"Sibulan",
    "qs:name_adm0":"Philippines",
    "qs:name_adm1":"Central Visayas",
    "qs:photos":237,
    "qs:photos_1k":48,
    "qs:photos_9k":1,
    "qs:photos_9r":4,
    "qs:photos_all":237,
    "qs:photos_sr":4,
    "qs:placetype":"Town",
    "qs:pop_sr":"7",
    "qs:woe_adm0":23424934,
    "wd:wordcount":526,
    "wof:name":"Sibulan",
    "wof:placetype":"locality",
    "wof:population":28079
},
  "geometry": {"coordinates":[123.285,9.3584],"type":"Point"}
}