{
  "type": "Feature",
  "properties": {
    "gn:admin1_code":"03",
    "gn:admin2_code":"63",
    "gn:admin3_code":"36917000.0",
    "gn:asciiname":"Canarem",
    "gn:country_code":"PH",
    "gn:dem":31,
    "gn:feature_class":"P",
    "gn:feature_code":"PPL",
    "gn:name":"Canarem",
    "gn:population":0,
    "gn:timezone":"Asia/Manila",
    "iso:country":"PH",
    "name:fil_x_preferred":[
        "Kanarem"
    ],
    "name:fil_x_variant":[
        "Canarem"
    ],
    "wof:name":"Canarem",
    "wof:placetype":"locality"
},
  "geometry": {"coordinates":[120.7145,15.5972],"type":"Point"}
}