{
  "type": "Feature",
  "properties": {
    "gn:admin1_code":"03",
    "gn:admin2_code":"13",
    "gn:admin3_code":"31419000.0",
    "gn:asciiname":"Santa Catalina Matanda",
    "gn:country_code":"PH",
    "gn:dem":40,
    "gn:feature_class":"P",
    "gn:feature_code":"PPL",
    "gn:name":"Santa Catalina Matanda",
    "gn:population":0,
    "gn:timezone":"Asia/Manila",
    "iso:country":"PH",
    "name:fil_x_preferred":[
        "Santa Catalina Matanda"
    ],
    "wof:name":"Santa Catalina Matanda",
    "wof:placetype":"locality"
},
  "geometry": {"coordinates":[120.98293,15.0903],"type":"Point"}
}