{
  "type": "Feature",
  "properties": {
    "gn:admin1_code":"06",
    "gn:admin2_code":"J3",
    "gn:admin3_code":"67903000.0",
    "gn:asciiname":"Guiuanon",
    "gn:country_code":"PH",
    "gn:dem":21,
    "gn:feature_class":"P",
    "gn:feature_code":"PPL",
    "gn:name":"Guiuanon",
    "gn:population":0,
    "gn:timezone":"Asia/Manila",
    "iso:country":"PH",
    "name:fil_x_preferred":[
        "Guiuanon"
    ],
    "name:und_x_variant":[
        "Guiwanon"
    ],
    "wof:name":"Guiuanon",
    "wof:placetype":"locality"
},
  "geometry": {"coordinates":[122.6006,10.3962],"type":"Point"}
}