{
  "type": "Feature",
  "properties": {
    "gn:admin1_code":"03",
    "gn:admin2_code":"47",
    "gn:admin3_code":"34921000.0",
    "gn:asciiname":"Barangay Uno",
    "gn:country_code":"PH",
    "gn:dem":38,
    "gn:feature_class":"P",
    "gn:feature_code":"PPL",
    "gn:name":"Barangay Uno",
    "gn:population":0,
    "gn:timezone":"Asia/Manila",
    "iso:country":"PH",
    "wof:name":"Barangay Uno",
    "wof:placetype":"locality"
},
  "geometry": {"coordinates":[121.00342000000001,15.35438],"type":"Point"}
}