{
  "type": "Feature",
  "properties": {
    "iso:country":"PH",
    "name:bcl_x_preferred":[
        "Pila"
    ],
    "name:cat_x_preferred":[
        "Pila"
    ],
    "name:cbk_zam_x_preferred":[
        "Pila"
    ],
    "name:ceb_x_preferred":[
        "Pila"
    ],
    "name:deu_x_preferred":[
        "Pila"
    ],
    "name:eng_x_preferred":[
        "Pila"
    ],
    "name:fas_x_preferred":[
        "\u067e\u06cc\u0644\u0627\u060c \u0644\u0627\u06af\u0648\u0646\u0627"
    ],
    "name:fil_x_preferred":[
        "Pila"
    ],
    "name:fra_x_preferred":[
        "Pila"
    ],
    "name:hbs_x_preferred":[
        "Pila"
    ],
    "name:ilo_x_preferred":[
        "Pila"
    ],
    "name:ind_x_preferred":[
        "Pila"
    ],
    "name:ita_x_preferred":[
        "Pila"
    ],
    "name:jpn_x_preferred":[
        "\u30d4\u30fc\u30e9"
    ],
    "name:nld_x_preferred":[
        "Pila"
    ],
    "name:oci_x_preferred":[
        "Pila"
    ],
    "name:pag_x_preferred":[
        "Pila"
    ],
    "name:pam_x_preferred":[
        "Pila"
    ],
    "name:rus_x_preferred":[
        "\u041f\u0438\u043b\u044b"
    ],
    "name:spa_x_preferred":[
        "Pila"
    ],
    "name:swe_x_preferred":[
        "Pila"
    ],
    "name:tgl_x_preferred":[
        "Pila"
    ],
    "name:vie_x_preferred":[
        "Pila"
    ],
    "name:war_x_preferred":[
        "Pila"
    ],
    "qs:gn_country":"PH",
    "qs:gn_fcode":"PPLA3",
    "qs:gn_pop":34383,
    "qs:name":"Pila",
    "qs:name_adm0":"Philippines",
    "qs:name_adm1":"Calabarzon",
    "qs:photos":0,
    "qs:photos_1k":0,
    "qs:photos_9k":1,
    "qs:photos_9r":1,
    "qs:photos_all":2,
    "qs:photos_sr":0,
    "qs:placetype":"Town",
    "qs:pop_sr":"7",
    "qs:woe_adm0":23424934,
    "wd:wordcount":2529,
    "wof:name":"Pila",
    "wof:placetype":"locality",
    "wof:population":34383
},
  "geometry": {"coordinates":[121.3648,14.2325],"type":"Point"}
}