{
  "type": "Feature",
  "properties": {
    "gn:admin1_code":"02",
    "gn:admin2_code":"14",
    "gn:admin3_code":"21519000.0",
    "gn:asciiname":"Callao Caves",
    "gn:country_code":"PH",
    "gn:dem":117,
    "gn:feature_class":"P",
    "gn:feature_code":"PPL",
    "gn:name":"Callao Caves",
    "gn:population":0,
    "gn:timezone":"Asia/Manila",
    "iso:country":"PH",
    "name:eng_x_preferred":[
        "Callao Caves"
    ],
    "wof:name":"Callao Caves",
    "wof:placetype":"locality"
},
  "geometry": {"coordinates":[121.81645,17.70821],"type":"Point"}
}