{
  "type": "Feature",
  "properties": {
    "iso:country":"PH",
    "name:ara_x_preferred":[
        "\u0625\u064a\u0644\u0627\u063a\u0627\u0646"
    ],
    "name:bcl_x_preferred":[
        "Ilagan"
    ],
    "name:ben_x_preferred":[
        "\u0987\u09b2\u09be\u0997\u09be\u09a8"
    ],
    "name:cbk_zam_x_preferred":[
        "Ilagan"
    ],
    "name:ceb_x_preferred":[
        "Ilagan"
    ],
    "name:dan_x_preferred":[
        "Ilagan"
    ],
    "name:deu_x_preferred":[
        "Ilagan"
    ],
    "name:ell_x_preferred":[
        "\u038a\u03bb\u03b1\u03b3\u03ba\u03b1\u03bd"
    ],
    "name:eng_x_preferred":[
        "Ilagan"
    ],
    "name:fil_x_preferred":[
        "Ilagan"
    ],
    "name:fin_x_preferred":[
        "Ilagan"
    ],
    "name:fra_x_preferred":[
        "Ilagan"
    ],
    "name:guj_x_preferred":[
        "\u0a88\u0ab2\u0a97\u0aa8"
    ],
    "name:hin_x_preferred":[
        "\u0907\u0932\u093e\u0917\u093e\u0928"
    ],
    "name:hun_x_preferred":[
        "Ilagan"
    ],
    "name:ilo_x_preferred":[
        "Ilagan"
    ],
    "name:ind_x_preferred":[
        "Ilagan"
    ],
    "name:ita_x_preferred":[
        "Ilagan"
    ],
    "name:jpn_x_preferred":[
        "\u30a4\u30e9\u30ac\u30f3"
    ],
    "name:kan_x_preferred":[
        "\u0c87\u0cb2\u0cbe\u0c97\u0ca8\u0ccd"
    ],
    "name:kor_x_preferred":[
        "\uc77c\ub77c\uac04"
    ],
    "name:lav_x_preferred":[
        "Ilagana"
    ],
    "name:lit_x_preferred":[
        "Ilaganas"
    ],
    "name:mar_x_preferred":[
        "\u0907\u0932\u0917\u0928"
    ],
    "name:msa_x_preferred":[
        "Ilagan"
    ],
    "name:nld_x_preferred":[
        "Ilagan"
    ],
    "name:nob_x_preferred":[
        "Ilagan"
    ],
    "name:nob_x_variant":[
        "Ilagan City"
    ],
    "name:pag_x_preferred":[
        "Ilagan"
    ],
    "name:pam_x_preferred":[
        "Ilagan"
    ],
    "name:pol_x_preferred":[
        "Ilagan"
    ],
    "name:rus_x_preferred":[
        "\u0418\u043b\u0430\u0433\u0430\u043d"
    ],
    "name:sin_x_preferred":[
        "\u0d89\u0dbd\u0d9c\u0db1\u0dca"
    ],
    "name:spa_x_preferred":[
        "Ilagan"
    ],
    "name:swe_x_preferred":[
        "Ilagan"
    ],
    "name:tam_x_preferred":[
        "\u0b87\u0bb3\u0b95\u0ba9\u0bcd"
    ],
    "name:tel_x_preferred":[
        "\u0c07\u0c32\u0c3e\u0c17\u0c3e\u0c28\u0c4d"
    ],
    "name:tgl_x_preferred":[
        "Ilagan"
    ],
    "name:tha_x_preferred":[
        "\u0e2d\u0e34\u0e25\u0e41\u0e01\u0e19"
    ],
    "name:tur_x_preferred":[
        "llagan"
    ],
    "name:ukr_x_preferred":[
        "\u0406\u043b\u0430\u0433\u0430\u043d"
    ],
    "name:urd_x_preferred":[
        "\u0627\u0644\u0627\u06af\u0627\u0646"
    ],
    "name:vie_x_preferred":[
        "Ilagan"
    ],
    "name:war_x_preferred":[
        "Ilagan"
    ],
    "name:zho_x_preferred":[
        "\u4f0a\u62c9\u7518"
    ],
    "qs:gn_country":"PH",
    "qs:gn_fcode":"PPL",
    "qs:gn_pop":72363,
    "qs:name":"Ilagan",
    "qs:name_adm0":"Philippines",
    "qs:name_adm1":"Cagayan Valley",
    "qs:photos":60,
    "qs:photos_1k":12,
    "qs:photos_9k":1,
    "qs:photos_9r":2,
    "qs:photos_all":60,
    "qs:photos_sr":2,
    "qs:placetype":"Town",
    "qs:pop_sr":"8",
    "qs:woe_adm0":23424934,
    "wd:wordcount":7959,
    "wof:name":"Ilagan",
    "wof:placetype":"locality",
    "wof:population":72363
},
  "geometry": {"coordinates":[121.88924,17.14854],"type":"Point"}
}