{
  "type": "Feature",
  "properties": {
    "gn:admin1_code":"14",
    "gn:admin2_code":"72",
    "gn:admin3_code":"157005000.0",
    "gn:asciiname":"Omapuy Asibi",
    "gn:country_code":"PH",
    "gn:dem":8,
    "gn:feature_class":"P",
    "gn:feature_code":"PPL",
    "gn:name":"Omapuy Asibi",
    "gn:population":0,
    "gn:timezone":"Asia/Manila",
    "iso:country":"PH",
    "name:fil_x_preferred":[
        "Omapuy Asibi"
    ],
    "wof:name":"Omapuy Asibi",
    "wof:placetype":"locality"
},
  "geometry": {"coordinates":[119.39806000000002,4.89056],"type":"Point"}
}