{
  "type": "Feature",
  "properties": {
    "gn:admin1_code":"03",
    "gn:admin2_code":"13",
    "gn:admin3_code":"31404000.0",
    "gn:asciiname":"Batia",
    "gn:country_code":"PH",
    "gn:dem":8,
    "gn:feature_class":"P",
    "gn:feature_code":"PPL",
    "gn:name":"Batia",
    "gn:population":0,
    "gn:timezone":"Asia/Manila",
    "iso:country":"PH",
    "name:ceb_x_preferred":[
        "Batia"
    ],
    "name:fil_x_preferred":[
        "Batia"
    ],
    "name:fra_x_preferred":[
        "Batia"
    ],
    "name:swe_x_preferred":[
        "Batia"
    ],
    "name:war_x_preferred":[
        "Batia"
    ],
    "wof:name":"Batia",
    "wof:placetype":"locality"
},
  "geometry": {"coordinates":[120.93852,14.82801],"type":"Point"}
}