{
  "type": "Feature",
  "properties": {
    "gn:admin1_code":"06",
    "gn:admin2_code":"30",
    "gn:admin3_code":"63019000.0",
    "gn:asciiname":"Botogon",
    "gn:country_code":"PH",
    "gn:dem":17,
    "gn:feature_class":"P",
    "gn:feature_code":"PPL",
    "gn:name":"Botogon",
    "gn:population":0,
    "gn:timezone":"Asia/Manila",
    "iso:country":"PH",
    "name:fil_x_preferred":[
        "Botogon"
    ],
    "wof:name":"Botogon",
    "wof:placetype":"locality"
},
  "geometry": {"coordinates":[123.15000000000001,11.45],"type":"Point"}
}