{
  "type": "Feature",
  "properties": {
    "gn:admin1_code":"05",
    "gn:admin2_code":"58",
    "gn:admin3_code":"56203000.0",
    "gn:asciiname":"Jamorawon",
    "gn:cc2":"PH",
    "gn:country_code":"PH",
    "gn:dem":36,
    "gn:feature_class":"P",
    "gn:feature_code":"PPL",
    "gn:name":"Jamorawon",
    "gn:population":0,
    "gn:timezone":"Asia/Manila",
    "iso:country":"PH",
    "name:und_x_variant":[
        "Hamurawon",
        "Jamarawon",
        "Jamorawon"
    ],
    "wof:name":"Jamorawon",
    "wof:placetype":"locality"
},
  "geometry": {"coordinates":[123.93361000000002,12.71278],"type":"Point"}
}