{
  "type": "Feature",
  "properties": {
    "gn:admin1_code":"05",
    "gn:admin2_code":"58",
    "gn:admin3_code":"56207000.0",
    "gn:asciiname":"Pawala",
    "gn:cc2":"PH",
    "gn:country_code":"PH",
    "gn:dem":56,
    "gn:feature_class":"P",
    "gn:feature_code":"PPL",
    "gn:name":"Pawala",
    "gn:population":0,
    "gn:timezone":"Asia/Manila",
    "iso:country":"PH",
    "name:und_x_variant":[
        "Pauala",
        "Pawala"
    ],
    "wof:name":"Pawala",
    "wof:placetype":"locality"
},
  "geometry": {"coordinates":[123.58333,13.01667],"type":"Point"}
}