{
  "type": "Feature",
  "properties": {
    "gn:admin1_code":"14",
    "gn:admin2_code":"72",
    "gn:admin3_code":"157007000.0",
    "gn:asciiname":"Tandu Batu",
    "gn:country_code":"PH",
    "gn:dem":0,
    "gn:feature_class":"P",
    "gn:feature_code":"PPL",
    "gn:name":"Tandu Batu",
    "gn:population":0,
    "gn:timezone":"Asia/Manila",
    "iso:country":"PH",
    "name:und_x_variant":[
        "Tandubato",
        "Tandu Batu"
    ],
    "wof:name":"Tandu Batu",
    "wof:placetype":"locality"
},
  "geometry": {"coordinates":[120.33333,5.13333],"type":"Point"}
}