{
  "type": "Feature",
  "properties": {
    "gn:admin1_code":"07",
    "gn:admin2_code":"21",
    "gn:admin3_code":"72223000.0",
    "gn:asciiname":"Kanlingo",
    "gn:country_code":"PH",
    "gn:dem":16,
    "gn:feature_class":"P",
    "gn:feature_code":"PPL",
    "gn:name":"Kanlingo",
    "gn:population":0,
    "gn:timezone":"Asia/Manila",
    "iso:country":"PH",
    "name:fil_x_preferred":[
        "Kanlingo"
    ],
    "wof:name":"Kanlingo",
    "wof:placetype":"locality"
},
  "geometry": {"coordinates":[124.02589999999999,10.4884],"type":"Point"}
}