{
  "type": "Feature",
  "properties": {
    "gn:admin1_code":"09",
    "gn:admin2_code":"ZSI",
    "gn:admin3_code":"98311000.0",
    "gn:asciiname":"Carilao",
    "gn:cc2":"PH",
    "gn:country_code":"PH",
    "gn:dem":19,
    "gn:feature_class":"P",
    "gn:feature_code":"PPL",
    "gn:name":"Carilao",
    "gn:population":0,
    "gn:timezone":"Asia/Manila",
    "iso:country":"PH",
    "name:und_x_variant":[
        "Kurilao",
        "Carilao"
    ],
    "wof:name":"Carilao",
    "wof:placetype":"locality"
},
  "geometry": {"coordinates":[122.85556,7.56472],"type":"Point"}
}