{
  "type": "Feature",
  "properties": {
    "gn:admin1_code":"11",
    "gn:admin2_code":"I7",
    "gn:admin3_code":"112319000.0",
    "gn:asciiname":"Bohol",
    "gn:country_code":"PH",
    "gn:dem":101,
    "gn:feature_class":"P",
    "gn:feature_code":"PPL",
    "gn:name":"Bohol",
    "gn:population":0,
    "gn:timezone":"Asia/Manila",
    "iso:country":"PH",
    "name:fil_x_preferred":[
        "Bohol"
    ],
    "wof:name":"Bohol",
    "wof:placetype":"locality"
},
  "geometry": {"coordinates":[125.843,7.4928],"type":"Point"}
}