{
  "type": "Feature",
  "properties": {
    "gn:admin1_code":"02",
    "gn:admin2_code":"14",
    "gn:admin3_code":"21514000.0",
    "gn:asciiname":"Magrafil",
    "gn:country_code":"PH",
    "gn:dem":116,
    "gn:feature_class":"P",
    "gn:feature_code":"PPL",
    "gn:name":"Magrafil",
    "gn:population":0,
    "gn:timezone":"Asia/Manila",
    "iso:country":"PH",
    "wof:name":"Magrafil",
    "wof:placetype":"locality"
},
  "geometry": {"coordinates":[122.06957,18.27961],"type":"Point"}
}