{
  "type": "Feature",
  "properties": {
    "gn:admin1_code":"01",
    "gn:admin2_code":"51",
    "gn:admin3_code":"15532000.0",
    "gn:asciiname":"Baliti Norte",
    "gn:country_code":"PH",
    "gn:dem":8,
    "gn:feature_class":"P",
    "gn:feature_code":"PPL",
    "gn:name":"Baliti Norte",
    "gn:population":0,
    "gn:timezone":"Asia/Manila",
    "iso:country":"PH",
    "name:fil_x_preferred":[
        "Baliti Norte"
    ],
    "name:fil_x_variant":[
        "Baliti"
    ],
    "wof:name":"Baliti Norte",
    "wof:placetype":"locality"
},
  "geometry": {"coordinates":[120.3296,15.9575],"type":"Point"}
}