{
  "type": "Feature",
  "properties": {
    "gn:admin1_code":"40",
    "gn:admin2_code":"33",
    "gn:admin3_code":"43419000.0",
    "gn:asciiname":"Moosegy",
    "gn:country_code":"PH",
    "gn:dem":16,
    "gn:feature_class":"P",
    "gn:feature_code":"PPL",
    "gn:name":"Moosegy",
    "gn:population":0,
    "gn:timezone":"Asia/Manila",
    "iso:country":"PH",
    "name:fil_x_preferred":[
        "Moosegy"
    ],
    "wof:name":"Moosegy",
    "wof:placetype":"locality"
},
  "geometry": {"coordinates":[121.43333,14.25],"type":"Point"}
}