{
  "type": "Feature",
  "properties": {
    "gn:admin1_code":"NCR",
    "gn:admin2_code":"137600000",
    "gn:admin3_code":"137602000.0",
    "gn:asciiname":"Pio Del Pilar",
    "gn:country_code":"PH",
    "gn:dem":9,
    "gn:feature_class":"P",
    "gn:feature_code":"PPL",
    "gn:name":"Pio Del Pilar",
    "gn:population":0,
    "gn:timezone":"Asia/Manila",
    "iso:country":"PH",
    "wof:name":"Pio Del Pilar",
    "wof:placetype":"locality"
},
  "geometry": {"coordinates":[121.0123,14.5479],"type":"Point"}
}