{
  "type": "Feature",
  "properties": {
    "gn:admin1_code":"15",
    "gn:admin2_code":"10",
    "gn:admin3_code":"141113000.0",
    "gn:asciiname":"Yagyagan",
    "gn:country_code":"PH",
    "gn:dem":1132,
    "gn:feature_class":"P",
    "gn:feature_code":"PPL",
    "gn:name":"Yagyagan",
    "gn:population":0,
    "gn:timezone":"Asia/Manila",
    "iso:country":"PH",
    "name:fil_x_preferred":[
        "Yagyagan"
    ],
    "name:fil_x_variant":[
        "Yayagan"
    ],
    "wof:name":"Yagyagan",
    "wof:placetype":"locality"
},
  "geometry": {"coordinates":[120.53476999999999,16.44328],"type":"Point"}
}