{
  "type": "Feature",
  "properties": {
    "gn:admin1_code":"02",
    "gn:admin2_code":"48",
    "gn:admin3_code":"25010000.0",
    "gn:asciiname":"Unib",
    "gn:country_code":"PH",
    "gn:dem":1008,
    "gn:feature_class":"P",
    "gn:feature_code":"PPL",
    "gn:name":"Unib",
    "gn:population":0,
    "gn:timezone":"Asia/Manila",
    "iso:country":"PH",
    "name:fil_x_preferred":[
        "Unib"
    ],
    "wof:name":"Unib",
    "wof:placetype":"locality"
},
  "geometry": {"coordinates":[120.88079999999999,16.2366],"type":"Point"}
}