{
  "type": "Feature",
  "properties": {
    "gn:admin1_code":"09",
    "gn:admin2_code":"65",
    "gn:admin3_code":"97215000.0",
    "gn:asciiname":"Sornob",
    "gn:country_code":"PH",
    "gn:dem":566,
    "gn:feature_class":"P",
    "gn:feature_code":"PPL",
    "gn:name":"Sornob",
    "gn:population":0,
    "gn:timezone":"Asia/Manila",
    "iso:country":"PH",
    "name:fil_x_preferred":[
        "Sornob"
    ],
    "wof:name":"Sornob",
    "wof:placetype":"locality"
},
  "geometry": {"coordinates":[123.17389,8.27806],"type":"Point"}
}