{
  "type": "Feature",
  "properties": {
    "gn:admin1_code":"06",
    "gn:admin2_code":"H3",
    "gn:admin3_code":"64526000.0",
    "gn:asciiname":"Hacienda Cubay",
    "gn:country_code":"PH",
    "gn:dem":170,
    "gn:feature_class":"P",
    "gn:feature_code":"PPL",
    "gn:name":"Hacienda Cubay",
    "gn:population":0,
    "gn:timezone":"Asia/Manila",
    "iso:country":"PH",
    "name:fil_x_preferred":[
        "Hacienda Cubay"
    ],
    "wof:name":"Hacienda Cubay",
    "wof:placetype":"locality"
},
  "geometry": {"coordinates":[123.1208,10.7885],"type":"Point"}
}