{
  "type": "Feature",
  "properties": {
    "gn:country":"PH",
    "gn:fcode":"PPL",
    "gn:pop":2690,
    "iso:country":"PH",
    "name:fil_x_preferred":[
        "Panique"
    ],
    "qs:name":"Panique",
    "qs:photos_9r":0,
    "qs:photos_sr":0,
    "qs:pop_sr":"4",
    "wd:wordcount":389,
    "wof:name":"Panique",
    "wof:placetype":"locality",
    "wof:population":2690
},
  "geometry": {"coordinates":[122.01461999999999,12.48025],"type":"Point"}
}