{
  "type": "Feature",
  "properties": {
    "gn:country":"PH",
    "gn:fcode":"PPL",
    "gn:population":2690,
    "iso:country":"PH",
    "name:cym_x_preferred":[
        "Panique"
    ],
    "name:dan_x_preferred":[
        "Panik"
    ],
    "name:deu_x_preferred":[
        "Panik"
    ],
    "name:ell_x_preferred":[
        "\u03a0\u03b1\u03bd\u03b9\u03ba\u03cc\u03c2"
    ],
    "name:eng_x_preferred":[
        "Panique"
    ],
    "name:fil_x_preferred":[
        "Panique"
    ],
    "name:fra_x_preferred":[
        "Panique"
    ],
    "name:ita_x_preferred":[
        "Panico"
    ],
    "name:jpn_x_preferred":[
        "\u30d1\u30cb\u30c3\u30af"
    ],
    "name:nld_x_preferred":[
        "Panique"
    ],
    "name:spa_x_preferred":[
        "P\u00e1nico"
    ],
    "name:swe_x_preferred":[
        "Panik"
    ],
    "name:ukr_x_preferred":[
        "\u041f\u0430\u043d\u0456\u043a\u0430"
    ],
    "qs:name":"Panique",
    "qs:photos_9r":0,
    "qs:photos_sr":0,
    "qs:pop_sr":"4",
    "wd:wordcount":389,
    "wof:name":"Panique",
    "wof:placetype":"locality",
    "wof:population":2690
},
  "geometry": {"coordinates":[122.01461999999999,12.48025],"type":"Point"}
}