{
  "type": "Feature",
  "properties": {
    "gn:admin1_code":"40",
    "gn:admin2_code":"F2",
    "gn:asciiname":"White Plains",
    "gn:country_code":"PH",
    "gn:dem":36,
    "gn:feature_class":"P",
    "gn:feature_code":"PPL",
    "gn:name":"White Plains",
    "gn:population":0,
    "gn:timezone":"Asia/Manila",
    "iso:country":"PH",
    "name:eng_x_preferred":[
        "White Plains"
    ],
    "wof:name":"White Plains",
    "wof:placetype":"locality"
},
  "geometry": {"coordinates":[121.0707,14.5965],"type":"Point"}
}