{
  "type": "Feature",
  "properties": {
    "gn:admin1_code":"03",
    "gn:admin2_code":"47",
    "gn:admin3_code":"34903000.0",
    "gn:asciiname":"Quezon District",
    "gn:country_code":"PH",
    "gn:dem":37,
    "gn:feature_class":"P",
    "gn:feature_code":"PPL",
    "gn:name":"Quezon District",
    "gn:population":0,
    "gn:timezone":"Asia/Manila",
    "iso:country":"PH",
    "wof:name":"Quezon District",
    "wof:placetype":"locality"
},
  "geometry": {"coordinates":[120.97414000000001,15.4882],"type":"Point"}
}