{
  "type": "Feature",
  "properties": {
    "gn:admin1_code":"40",
    "gn:admin2_code":"H2",
    "gn:admin3_code":"45618000.0",
    "gn:asciiname":"Kabagsangan",
    "gn:country_code":"PH",
    "gn:dem":39,
    "gn:feature_class":"P",
    "gn:feature_code":"PPL",
    "gn:name":"Kabagsangan",
    "gn:population":0,
    "gn:timezone":"Asia/Manila",
    "iso:country":"PH",
    "name:fil_x_preferred":[
        "Kabagsangan"
    ],
    "wof:name":"Kabagsangan",
    "wof:placetype":"locality"
},
  "geometry": {"coordinates":[122.3871,13.9599],"type":"Point"}
}