{
  "type": "Feature",
  "properties": {
    "gn:admin1_code":"01",
    "gn:admin2_code":"28",
    "gn:admin3_code":"12817000.0",
    "gn:asciiname":"Solongan",
    "gn:country_code":"PH",
    "gn:dem":23,
    "gn:feature_class":"P",
    "gn:feature_code":"PPL",
    "gn:name":"Solongan",
    "gn:population":0,
    "gn:timezone":"Asia/Manila",
    "iso:country":"PH",
    "name:fil_x_preferred":[
        "Solongan"
    ],
    "wof:name":"Solongan",
    "wof:placetype":"locality"
},
  "geometry": {"coordinates":[120.6054,18.3873],"type":"Point"}
}