{
  "type": "Feature",
  "properties": {
    "gn:admin1_code":"07",
    "gn:admin2_code":"11",
    "gn:admin3_code":"71206000.0",
    "gn:asciiname":"Magsija",
    "gn:country_code":"PH",
    "gn:dem":48,
    "gn:feature_class":"P",
    "gn:feature_code":"PPL",
    "gn:name":"Magsija",
    "gn:population":0,
    "gn:timezone":"Asia/Manila",
    "iso:country":"PH",
    "name:fil_x_preferred":[
        "Magsija"
    ],
    "wof:name":"Magsija",
    "wof:placetype":"locality"
},
  "geometry": {"coordinates":[123.9492,9.73071],"type":"Point"}
}