{
  "type": "Feature",
  "properties": {
    "gn:admin1_code":"08",
    "gn:admin2_code":"37",
    "gn:admin3_code":"83702000.0",
    "gn:asciiname":"Cabadsan",
    "gn:cc2":"PH",
    "gn:country_code":"PH",
    "gn:dem":31,
    "gn:feature_class":"P",
    "gn:feature_code":"PPL",
    "gn:name":"Cabadsan",
    "gn:population":0,
    "gn:timezone":"Asia/Manila",
    "iso:country":"PH",
    "name:und_x_variant":[
        "Kabadsan",
        "Cabadsan"
    ],
    "wof:name":"Cabadsan",
    "wof:placetype":"locality"
},
  "geometry": {"coordinates":[124.83333,11.25],"type":"Point"}
}