{
  "type": "Feature",
  "properties": {
    "gn:admin1_code":"41",
    "gn:admin2_code":"40",
    "gn:admin3_code":"175105000.0",
    "gn:asciiname":"Gapasan",
    "gn:country_code":"PH",
    "gn:dem":22,
    "gn:feature_class":"P",
    "gn:feature_code":"PPL",
    "gn:name":"Gapasan",
    "gn:population":0,
    "gn:timezone":"Asia/Manila",
    "iso:country":"PH",
    "name:fil_x_preferred":[
        "Gapasan"
    ],
    "wof:name":"Gapasan",
    "wof:placetype":"locality"
},
  "geometry": {"coordinates":[121.19280999999999,12.33685],"type":"Point"}
}