{
  "type": "Feature",
  "properties": {
    "gn:country":"PH",
    "gn:fcode":"PPL",
    "gn:pop":2700,
    "iso:country":"PH",
    "name:fil_x_preferred":[
        "Anopog"
    ],
    "qs:name":"Anopog",
    "qs:photos_9r":0,
    "qs:photos_sr":0,
    "qs:pop_sr":"4",
    "wof:name":"Anopog",
    "wof:placetype":"locality",
    "wof:population":2700
},
  "geometry": {"coordinates":[123.25,10.25],"type":"Point"}
}