{
  "type": "Feature",
  "properties": {
    "gn:admin1_code":"08",
    "gn:admin2_code":"37",
    "gn:admin3_code":"83714000.0",
    "gn:asciiname":"Minoro",
    "gn:country_code":"PH",
    "gn:dem":346,
    "gn:feature_class":"P",
    "gn:feature_code":"PPL",
    "gn:name":"Minoro",
    "gn:population":0,
    "gn:timezone":"Asia/Manila",
    "iso:country":"PH",
    "name:fil_x_preferred":[
        "Minoro"
    ],
    "wof:name":"Minoro",
    "wof:placetype":"locality"
},
  "geometry": {"coordinates":[124.63333,11.26667],"type":"Point"}
}