{
  "type": "Feature",
  "properties": {
    "gn:admin1_code":"01",
    "gn:admin2_code":"36",
    "gn:admin3_code":"13319000.0",
    "gn:asciiname":"Cobuar",
    "gn:country_code":"PH",
    "gn:dem":35,
    "gn:feature_class":"P",
    "gn:feature_code":"PPL",
    "gn:name":"Cobuar",
    "gn:population":0,
    "gn:timezone":"Asia/Manila",
    "iso:country":"PH",
    "name:fil_x_preferred":[
        "Cobuar"
    ],
    "wof:name":"Cobuar",
    "wof:placetype":"locality"
},
  "geometry": {"coordinates":[120.4551,16.8917],"type":"Point"}
}