{
  "type": "Feature",
  "properties": {
    "gn:admin1_code":"01",
    "gn:admin2_code":"36",
    "gn:admin3_code":"13313000.0",
    "gn:asciiname":"Vila",
    "gn:country_code":"PH",
    "gn:dem":157,
    "gn:feature_class":"P",
    "gn:feature_code":"PPL",
    "gn:name":"Vila",
    "gn:population":0,
    "gn:timezone":"Asia/Manila",
    "iso:country":"PH",
    "name:bre_x_preferred":[
        "Vila"
    ],
    "name:cat_x_preferred":[
        "Vila"
    ],
    "name:ceb_x_preferred":[
        "Vila"
    ],
    "name:ces_x_preferred":[
        "Villa"
    ],
    "name:deu_x_preferred":[
        "Vila"
    ],
    "name:est_x_preferred":[
        "Vila"
    ],
    "name:fil_x_preferred":[
        "Vila"
    ],
    "name:fin_x_preferred":[
        "Vila"
    ],
    "name:fra_x_preferred":[
        "Vila"
    ],
    "name:glg_x_preferred":[
        "Vila"
    ],
    "name:hun_x_preferred":[
        "Vila"
    ],
    "name:hye_x_preferred":[
        "\u054e\u056b\u056c\u0561"
    ],
    "name:ita_x_preferred":[
        "Vila"
    ],
    "name:nld_x_preferred":[
        "Vila"
    ],
    "name:por_x_preferred":[
        "Vila"
    ],
    "name:slk_x_preferred":[
        "Vila"
    ],
    "name:spa_x_preferred":[
        "Vila"
    ],
    "name:swe_x_preferred":[
        "Vila"
    ],
    "name:ukr_x_preferred":[
        "\u0412\u0456\u043b\u0430"
    ],
    "wof:name":"Vila",
    "wof:placetype":"locality"
},
  "geometry": {"coordinates":[120.46807,16.24096],"type":"Point"}
}