{
  "type": "Feature",
  "properties": {
    "gn:admin1_code":"01",
    "gn:admin2_code":"36",
    "gn:admin3_code":"13313000.0",
    "gn:asciiname":"Vila",
    "gn:country_code":"PH",
    "gn:dem":157,
    "gn:feature_class":"P",
    "gn:feature_code":"PPL",
    "gn:name":"Vila",
    "gn:population":0,
    "gn:timezone":"Asia/Manila",
    "iso:country":"PH",
    "name:fil_x_preferred":[
        "Vila"
    ],
    "wof:name":"Vila",
    "wof:placetype":"locality"
},
  "geometry": {"coordinates":[120.46807,16.24096],"type":"Point"}
}