{
  "type": "Feature",
  "properties": {
    "gn:admin1_code":"40",
    "gn:admin2_code":"09",
    "gn:admin3_code":"41021000.0",
    "gn:asciiname":"Itlogan",
    "gn:country_code":"PH",
    "gn:dem":132,
    "gn:feature_class":"P",
    "gn:feature_code":"PPL",
    "gn:name":"Itlogan",
    "gn:population":0,
    "gn:timezone":"Asia/Manila",
    "iso:country":"PH",
    "name:fil_x_preferred":[
        "Itlogan"
    ],
    "name:und_x_variant":[
        "Itlugan"
    ],
    "wof:name":"Itlogan",
    "wof:placetype":"locality"
},
  "geometry": {"coordinates":[121.20480000000001,13.8289],"type":"Point"}
}