{
  "type": "Feature",
  "properties": {
    "gn:admin1_code":"01",
    "gn:admin2_code":"29",
    "gn:admin3_code":"12906000.0",
    "gn:asciiname":"Oaig Daya",
    "gn:country_code":"PH",
    "gn:dem":10,
    "gn:feature_class":"P",
    "gn:feature_code":"PPL",
    "gn:name":"Oaig Daya",
    "gn:population":0,
    "gn:timezone":"Asia/Manila",
    "iso:country":"PH",
    "name:fil_x_preferred":[
        "Oaig Daya"
    ],
    "wof:name":"Oaig Daya",
    "wof:placetype":"locality"
},
  "geometry": {"coordinates":[120.45497,17.18202999999999],"type":"Point"}
}