{
  "type": "Feature",
  "properties": {
    "gn:admin1_code":"01",
    "gn:admin2_code":"29",
    "gn:admin3_code":"12930000.0",
    "gn:asciiname":"Nagbalioartian",
    "gn:country_code":"PH",
    "gn:dem":18,
    "gn:feature_class":"P",
    "gn:feature_code":"PPL",
    "gn:name":"Nagbalioartian",
    "gn:population":0,
    "gn:timezone":"Asia/Manila",
    "iso:country":"PH",
    "name:fil_x_preferred":[
        "Nagbalioartian"
    ],
    "wof:name":"Nagbalioartian",
    "wof:placetype":"locality"
},
  "geometry": {"coordinates":[120.4789,17.8654],"type":"Point"}
}