{
  "type": "Feature",
  "properties": {
    "gn:admin1_code":"08",
    "gn:admin2_code":"37",
    "gn:admin3_code":"83713000.0",
    "gn:asciiname":"Villahermosa",
    "gn:country_code":"PH",
    "gn:dem":15,
    "gn:feature_class":"P",
    "gn:feature_code":"PPL",
    "gn:name":"Villahermosa",
    "gn:population":0,
    "gn:timezone":"Asia/Manila",
    "iso:country":"PH",
    "name:fil_x_preferred":[
        "Villahermosa"
    ],
    "wof:name":"Villahermosa",
    "wof:placetype":"locality"
},
  "geometry": {"coordinates":[124.3862,11.4935],"type":"Point"}
}