{
  "type": "Feature",
  "properties": {
    "gn:admin1_code":"12",
    "gn:admin2_code":"57",
    "gn:admin3_code":"124706000.0",
    "gn:asciiname":"Marbel",
    "gn:country_code":"PH",
    "gn:dem":236,
    "gn:feature_class":"P",
    "gn:feature_code":"PPL",
    "gn:name":"Marbel",
    "gn:population":0,
    "gn:timezone":"Asia/Manila",
    "iso:country":"PH",
    "name:fil_x_preferred":[
        "Marbel"
    ],
    "wof:name":"Marbel",
    "wof:placetype":"locality"
},
  "geometry": {"coordinates":[125.09083,7.08639],"type":"Point"}
}