{
  "type": "Feature",
  "properties": {
    "gn:admin1_code":"12",
    "gn:admin2_code":"57",
    "gn:admin3_code":"124701000.0",
    "gn:asciiname":"Nicaan",
    "gn:country_code":"PH",
    "gn:dem":316,
    "gn:feature_class":"P",
    "gn:feature_code":"PPL",
    "gn:name":"Nicaan",
    "gn:population":0,
    "gn:timezone":"Asia/Manila",
    "iso:country":"PH",
    "name:fil_x_preferred":[
        "Nicaan"
    ],
    "wof:name":"Nicaan",
    "wof:placetype":"locality"
},
  "geometry": {"coordinates":[124.56694,7.38972],"type":"Point"}
}