{
  "type": "Feature",
  "properties": {
    "gn:country":"PH",
    "gn:fcode":"PPLA3",
    "gn:pop":19726,
    "iso:country":"PH",
    "name:bcl_x_preferred":[
        "Pangil"
    ],
    "name:cat_x_preferred":[
        "Pangil"
    ],
    "name:deu_x_preferred":[
        "Pangil"
    ],
    "name:eng_x_preferred":[
        "Pangil"
    ],
    "name:fil_x_preferred":[
        "Pangil"
    ],
    "name:fra_x_preferred":[
        "Pangil"
    ],
    "name:ilo_x_preferred":[
        "Pangil"
    ],
    "name:ind_x_preferred":[
        "Pangil"
    ],
    "name:ita_x_preferred":[
        "Pangil"
    ],
    "name:nld_x_preferred":[
        "Pangil"
    ],
    "name:oci_x_preferred":[
        "Pangil"
    ],
    "name:pag_x_preferred":[
        "Pangil"
    ],
    "name:pam_x_preferred":[
        "Pangil"
    ],
    "name:tgl_x_preferred":[
        "Pangil"
    ],
    "name:vie_x_preferred":[
        "Pangil"
    ],
    "name:war_x_preferred":[
        "Pangil"
    ],
    "qs:name":"Pangil",
    "qs:photos_9r":0,
    "qs:photos_sr":0,
    "qs:pop_sr":"6",
    "wd:wordcount":247,
    "wof:name":"Pangil",
    "wof:placetype":"locality",
    "wof:population":19726
},
  "geometry": {"coordinates":[121.46850000000001,14.4008],"type":"Point"}
}