{
  "type": "Feature",
  "properties": {
    "gn:admin1_code":"07",
    "gn:admin2_code":"21",
    "gn:admin3_code":"72222000.0",
    "gn:asciiname":"Sacsac",
    "gn:country_code":"PH",
    "gn:dem":249,
    "gn:feature_class":"P",
    "gn:feature_code":"PPL",
    "gn:name":"Sacsac",
    "gn:population":0,
    "gn:timezone":"Asia/Manila",
    "iso:country":"PH",
    "name:fil_x_preferred":[
        "Saksak"
    ],
    "wof:name":"Sacsac",
    "wof:placetype":"locality"
},
  "geometry": {"coordinates":[123.4988,9.78741],"type":"Point"}
}