{
  "type": "Feature",
  "properties": {
    "gn:admin1_code":"01",
    "gn:admin2_code":"28",
    "gn:admin3_code":"12812000.0",
    "gn:asciiname":"Tasod",
    "gn:country_code":"PH",
    "gn:dem":5,
    "gn:feature_class":"P",
    "gn:feature_code":"PPL",
    "gn:name":"Tasod",
    "gn:population":0,
    "gn:timezone":"Asia/Manila",
    "iso:country":"PH",
    "name:fil_x_preferred":[
        "Tasod"
    ],
    "wof:name":"Tasod",
    "wof:placetype":"locality"
},
  "geometry": {"coordinates":[120.53333000000001,18.18333],"type":"Point"}
}