{
  "type": "Feature",
  "properties": {
    "gn:admin1_code":"09",
    "gn:admin2_code":"ZSI",
    "gn:admin3_code":"98309000.0",
    "gn:asciiname":"Bacalan",
    "gn:cc2":"PH",
    "gn:country_code":"PH",
    "gn:dem":33,
    "gn:feature_class":"P",
    "gn:feature_code":"PPL",
    "gn:name":"Bacalan",
    "gn:population":0,
    "gn:timezone":"Asia/Manila",
    "iso:country":"PH",
    "name:und_x_variant":[
        "Bakalan",
        "Bacalan"
    ],
    "wof:name":"Bacalan",
    "wof:placetype":"locality"
},
  "geometry": {"coordinates":[122.65555999999999,7.80778],"type":"Point"}
}