{
  "type": "Feature",
  "properties": {
    "gn:country":"PH",
    "gn:fcode":"PPL",
    "gn:pop":4975,
    "iso:country":"PH",
    "qs:name":"Malagos",
    "qs:photos_9r":0,
    "qs:photos_sr":0,
    "qs:pop_sr":"4",
    "wof:name":"Malagos",
    "wof:placetype":"locality",
    "wof:population":4975
},
  "geometry": {"coordinates":[125.42222,7.185],"type":"Point"}
}