{
  "type": "Feature",
  "properties": {
    "gn:admin1_code":"40",
    "gn:admin2_code":"H2",
    "gn:admin3_code":"45641000.0",
    "gn:asciiname":"Sampaguita",
    "gn:country_code":"PH",
    "gn:dem":75,
    "gn:feature_class":"P",
    "gn:feature_code":"PPL",
    "gn:name":"Sampaguita",
    "gn:population":0,
    "gn:timezone":"Asia/Manila",
    "iso:country":"PH",
    "wof:name":"Sampaguita",
    "wof:placetype":"locality"
},
  "geometry": {"coordinates":[121.28628,13.88817],"type":"Point"}
}