{
  "type": "Feature",
  "properties": {
    "gn:admin1_code":"40",
    "gn:admin2_code":"20",
    "gn:admin3_code":"42102000.0",
    "gn:asciiname":"Talon",
    "gn:country_code":"PH",
    "gn:dem":549,
    "gn:feature_class":"P",
    "gn:feature_code":"PPL",
    "gn:name":"Talon",
    "gn:population":0,
    "gn:timezone":"Asia/Manila",
    "iso:country":"PH",
    "name:aze_x_preferred":[
        "Talon"
    ],
    "name:ceb_x_preferred":[
        "Talon"
    ],
    "name:ces_x_preferred":[
        "Talon"
    ],
    "name:dan_x_preferred":[
        "Talon"
    ],
    "name:deu_x_preferred":[
        "Talon"
    ],
    "name:fil_x_preferred":[
        "Talon"
    ],
    "name:fra_x_preferred":[
        "Talon"
    ],
    "name:ido_x_preferred":[
        "Talono"
    ],
    "name:ita_x_preferred":[
        "Talon"
    ],
    "name:nld_x_preferred":[
        "Talon"
    ],
    "name:oci_x_preferred":[
        "Talon"
    ],
    "name:pol_x_preferred":[
        "Talon"
    ],
    "name:rus_x_preferred":[
        "\u0422\u0430\u043b\u043e\u043d"
    ],
    "name:tgl_x_preferred":[
        "Talon"
    ],
    "name:ukr_x_preferred":[
        "\u0422\u0430\u043b\u043e\u043d"
    ],
    "wof:name":"Talon",
    "wof:placetype":"locality"
},
  "geometry": {"coordinates":[120.93772,14.13372],"type":"Point"}
}