{
  "type": "Feature",
  "properties": {
    "gn:admin1_code":"40",
    "gn:admin2_code":"H2",
    "gn:admin3_code":"45628000.0",
    "gn:asciiname":"Ajos Mulaney",
    "gn:country_code":"PH",
    "gn:dem":105,
    "gn:feature_class":"P",
    "gn:feature_code":"PPL",
    "gn:name":"Ajos Mulaney",
    "gn:population":0,
    "gn:timezone":"Asia/Manila",
    "iso:country":"PH",
    "name:fil_x_preferred":[
        "Ajos Mulaney"
    ],
    "wof:name":"Ajos Mulaney",
    "wof:placetype":"locality"
},
  "geometry": {"coordinates":[122.3789,13.5466],"type":"Point"}
}