{
  "type": "Feature",
  "properties": {
    "gn:admin1_code":"41",
    "gn:admin2_code":"38",
    "gn:admin3_code":"174006000.0",
    "gn:asciiname":"Macawayan",
    "gn:country_code":"PH",
    "gn:dem":14,
    "gn:feature_class":"P",
    "gn:feature_code":"PPL",
    "gn:name":"Macawayan",
    "gn:population":0,
    "gn:timezone":"Asia/Manila",
    "iso:country":"PH",
    "name:fil_x_preferred":[
        "Macawayan"
    ],
    "wof:name":"Macawayan",
    "wof:placetype":"locality"
},
  "geometry": {"coordinates":[122.0518,13.2537],"type":"Point"}
}