{
  "type": "Feature",
  "properties": {
    "gn:admin1_code":"41",
    "gn:admin2_code":"41",
    "gn:admin3_code":"175211000.0",
    "gn:asciiname":"Goob",
    "gn:country_code":"PH",
    "gn:dem":14,
    "gn:feature_class":"P",
    "gn:feature_code":"PPL",
    "gn:name":"Goob",
    "gn:population":0,
    "gn:timezone":"Asia/Manila",
    "iso:country":"PH",
    "name:eng_x_preferred":[
        "Goob"
    ],
    "wof:name":"Goob",
    "wof:placetype":"locality"
},
  "geometry": {"coordinates":[121.0003,13.4507],"type":"Point"}
}