{
  "type": "Feature",
  "properties": {
    "gn:admin1_code":"07",
    "gn:admin2_code":"11",
    "gn:admin3_code":"71234000.0",
    "gn:asciiname":"Dal Pilar",
    "gn:country_code":"PH",
    "gn:dem":137,
    "gn:feature_class":"P",
    "gn:feature_code":"PPL",
    "gn:name":"Dal Pilar",
    "gn:population":0,
    "gn:timezone":"Asia/Manila",
    "iso:country":"PH",
    "name:fil_x_preferred":[
        "Dal Pilar"
    ],
    "wof:name":"Dal Pilar",
    "wof:placetype":"locality"
},
  "geometry": {"coordinates":[124.31,9.84],"type":"Point"}
}