{
  "type": "Feature",
  "properties": {
    "gn:admin1_code":"40",
    "gn:admin2_code":"53",
    "gn:admin3_code":"45809000.0",
    "gn:asciiname":"Kulyat",
    "gn:country_code":"PH",
    "gn:dem":23,
    "gn:feature_class":"P",
    "gn:feature_code":"PPL",
    "gn:name":"Kulyat",
    "gn:population":0,
    "gn:timezone":"Asia/Manila",
    "iso:country":"PH",
    "name:fil_x_preferred":[
        "Kulyat"
    ],
    "wof:name":"Kulyat",
    "wof:placetype":"locality"
},
  "geometry": {"coordinates":[121.2574,14.5427],"type":"Point"}
}