{
  "type": "Feature",
  "properties": {
    "gn:admin1_code":"14",
    "gn:admin2_code":"60",
    "gn:admin3_code":"156617000.0",
    "gn:asciiname":"Bas",
    "gn:country_code":"PH",
    "gn:dem":12,
    "gn:feature_class":"P",
    "gn:feature_code":"PPL",
    "gn:name":"Bas",
    "gn:population":0,
    "gn:timezone":"Asia/Manila",
    "iso:country":"PH",
    "name:bel_x_preferred":[
        "\u0411\u0430\u0441"
    ],
    "name:bos_x_preferred":[
        "Bas"
    ],
    "name:bul_x_preferred":[
        "\u0411\u0430\u0441"
    ],
    "name:cat_x_preferred":[
        "Bas"
    ],
    "name:ceb_x_preferred":[
        "Bas"
    ],
    "name:dan_x_preferred":[
        "Bas"
    ],
    "name:deu_x_preferred":[
        "Bas"
    ],
    "name:eng_x_preferred":[
        "Bas"
    ],
    "name:hrv_x_preferred":[
        "Bas"
    ],
    "name:jpn_x_preferred":[
        "\u30d9\u30fc\u30b9"
    ],
    "name:nld_x_preferred":[
        "Bas"
    ],
    "name:pol_x_preferred":[
        "Bas"
    ],
    "name:por_x_preferred":[
        "Bas"
    ],
    "name:ron_x_preferred":[
        "Bas"
    ],
    "name:slk_x_preferred":[
        "Bas"
    ],
    "name:slv_x_preferred":[
        "Bas"
    ],
    "name:swe_x_preferred":[
        "Bas"
    ],
    "name:tur_x_preferred":[
        "Bas"
    ],
    "wof:name":"Bas",
    "wof:placetype":"locality"
},
  "geometry": {"coordinates":[120.84050000000001,5.7089],"type":"Point"}
}