{
  "type": "Feature",
  "properties": {
    "gn:admin1_code":"41",
    "gn:admin2_code":"41",
    "gn:admin3_code":"175204000.0",
    "gn:asciiname":"Canaya",
    "gn:country_code":"PH",
    "gn:dem":210,
    "gn:feature_class":"P",
    "gn:feature_code":"PPL",
    "gn:name":"Canaya",
    "gn:population":0,
    "gn:timezone":"Asia/Manila",
    "iso:country":"PH",
    "name:eng_x_preferred":[
        "Canaya"
    ],
    "wof:name":"Canaya",
    "wof:placetype":"locality"
},
  "geometry": {"coordinates":[121.27460000000001,12.333],"type":"Point"}
}