{
  "type": "Feature",
  "properties": {
    "gn:admin1_code":"07",
    "gn:admin2_code":"21",
    "gn:admin3_code":"72203000.0",
    "gn:asciiname":"Cancalanug",
    "gn:country_code":"PH",
    "gn:dem":523,
    "gn:feature_class":"P",
    "gn:feature_code":"PPL",
    "gn:name":"Cancalanug",
    "gn:population":0,
    "gn:timezone":"Asia/Manila",
    "iso:country":"PH",
    "name:fil_x_preferred":[
        "Cancalanug"
    ],
    "wof:name":"Cancalanug",
    "wof:placetype":"locality"
},
  "geometry": {"coordinates":[123.40219999999999,9.7817],"type":"Point"}
}