{
  "type": "Feature",
  "properties": {
    "gn:admin1_code":"05",
    "gn:admin2_code":"58",
    "gn:admin3_code":"56212000.0",
    "gn:asciiname":"Hidhid",
    "gn:country_code":"PH",
    "gn:dem":18,
    "gn:feature_class":"P",
    "gn:feature_code":"PPL",
    "gn:name":"Hidhid",
    "gn:population":0,
    "gn:timezone":"Asia/Manila",
    "iso:country":"PH",
    "name:fil_x_preferred":[
        "Hidhid"
    ],
    "wof:name":"Hidhid",
    "wof:placetype":"locality"
},
  "geometry": {"coordinates":[124.0489,12.6164],"type":"Point"}
}