{
  "type": "Feature",
  "properties": {
    "gn:admin1_code":"14",
    "gn:admin2_code":"60",
    "gn:admin3_code":"156604000.0",
    "gn:asciiname":"Bagsak",
    "gn:country_code":"PH",
    "gn:dem":127,
    "gn:feature_class":"P",
    "gn:feature_code":"PPL",
    "gn:name":"Bagsak",
    "gn:population":0,
    "gn:timezone":"Asia/Manila",
    "iso:country":"PH",
    "name:fil_x_preferred":[
        "Bagsak"
    ],
    "wof:name":"Bagsak",
    "wof:placetype":"locality"
},
  "geometry": {"coordinates":[121.34999999999999,5.93333],"type":"Point"}
}