{
  "type": "Feature",
  "properties": {
    "gn:country":"PH",
    "gn:fcode":"PPLA3",
    "gn:population":4585,
    "iso:country":"PH",
    "name:bcl_x_preferred":[
        "President Quirino"
    ],
    "name:ceb_x_preferred":[
        "President Quirino"
    ],
    "name:deu_x_preferred":[
        "President Quirino"
    ],
    "name:eng_x_preferred":[
        "President Quirino"
    ],
    "name:fra_x_preferred":[
        "President Quirino"
    ],
    "name:ilo_x_preferred":[
        "President Quirino"
    ],
    "name:ind_x_preferred":[
        "President Quirino"
    ],
    "name:ita_x_preferred":[
        "President Quirino"
    ],
    "name:nld_x_preferred":[
        "President Quirino"
    ],
    "name:pag_x_preferred":[
        "President Quirino"
    ],
    "name:pam_x_preferred":[
        "President Quirino"
    ],
    "name:spa_x_preferred":[
        "Sambulagu\u00e1n"
    ],
    "name:swe_x_preferred":[
        "President Quirino"
    ],
    "name:tgl_x_preferred":[
        "President Quirino"
    ],
    "name:und_x_variant":[
        "Simbulawan"
    ],
    "name:vie_x_preferred":[
        "President Quirino"
    ],
    "name:war_x_preferred":[
        "President Quirino"
    ],
    "qs:name":"President Quirino",
    "qs:photos_9r":0,
    "qs:photos_sr":0,
    "qs:pop_sr":"4",
    "wof:name":"President Quirino",
    "wof:placetype":"locality",
    "wof:population":4585
},
  "geometry": {"coordinates":[124.73721999999999,6.70389],"type":"Point"}
}