{
  "type": "Feature",
  "properties": {
    "gn:admin1_code":"08",
    "gn:admin2_code":"37",
    "gn:admin3_code":"83738000.0",
    "gn:asciiname":"Cabantog",
    "gn:country_code":"PH",
    "gn:dem":18,
    "gn:feature_class":"P",
    "gn:feature_code":"PPL",
    "gn:name":"Cabantog",
    "gn:population":0,
    "gn:timezone":"Asia/Manila",
    "iso:country":"PH",
    "wof:name":"Cabantog",
    "wof:placetype":"locality"
},
  "geometry": {"coordinates":[124.52222,11.05139],"type":"Point"}
}