{
  "type": "Feature",
  "properties": {
    "gn:admin1_code":"11",
    "gn:admin2_code":"25",
    "gn:admin3_code":"112412000.0",
    "gn:asciiname":"Sibulan",
    "gn:country_code":"PH",
    "gn:dem":506,
    "gn:feature_class":"P",
    "gn:feature_code":"PPL",
    "gn:name":"Sibulan",
    "gn:population":0,
    "gn:timezone":"Asia/Manila",
    "iso:country":"PH",
    "name:bcl_x_preferred":[
        "Sibulan"
    ],
    "name:ceb_x_preferred":[
        "Sibulan"
    ],
    "name:deu_x_preferred":[
        "Sibulan"
    ],
    "name:fil_x_preferred":[
        "Sibulan"
    ],
    "name:fra_x_preferred":[
        "Sibulan"
    ],
    "name:ilo_x_preferred":[
        "Sibulan"
    ],
    "name:ind_x_preferred":[
        "Sibulan"
    ],
    "name:ita_x_preferred":[
        "Sibulan"
    ],
    "name:nld_x_preferred":[
        "Sibulan"
    ],
    "name:pag_x_preferred":[
        "Sibulan"
    ],
    "name:pam_x_preferred":[
        "Sibulan"
    ],
    "name:spa_x_preferred":[
        "Sibul\u00e1n"
    ],
    "name:swe_x_preferred":[
        "Sibulan"
    ],
    "name:tgl_x_preferred":[
        "Sibulan"
    ],
    "name:vie_x_preferred":[
        "Sibulan"
    ],
    "name:war_x_preferred":[
        "Sibulan"
    ],
    "name:zho_x_preferred":[
        "\u9521\u5e03\u5170"
    ],
    "wof:name":"Sibulan",
    "wof:placetype":"locality"
},
  "geometry": {"coordinates":[125.40306,6.96389],"type":"Point"}
}