{
  "type": "Feature",
  "properties": {
    "gn:admin1_code":"06",
    "gn:admin2_code":"30",
    "gn:admin3_code":"63018000.0",
    "gn:asciiname":"Cayos",
    "gn:country_code":"PH",
    "gn:dem":6,
    "gn:feature_class":"P",
    "gn:feature_code":"PPL",
    "gn:name":"Cayos",
    "gn:population":0,
    "gn:timezone":"Asia/Manila",
    "iso:country":"PH",
    "name:fil_x_preferred":[
        "Cayos"
    ],
    "wof:name":"Cayos",
    "wof:placetype":"locality"
},
  "geometry": {"coordinates":[122.64667,10.81694],"type":"Point"}
}