{
  "type": "Feature",
  "properties": {
    "gn:admin1_code":"03",
    "gn:admin2_code":"47",
    "gn:admin3_code":"34903000.0",
    "gn:asciiname":"San Josef Sur",
    "gn:country_code":"PH",
    "gn:dem":35,
    "gn:feature_class":"P",
    "gn:feature_code":"PPL",
    "gn:name":"San Josef Sur",
    "gn:population":0,
    "gn:timezone":"Asia/Manila",
    "iso:country":"PH",
    "name:fil_x_preferred":[
        "San Josef"
    ],
    "name:und_x_variant":[
        "San Jose",
        "San Joseph",
        "San Josef Sur"
    ],
    "wof:name":"San Josef Sur",
    "wof:placetype":"locality"
},
  "geometry": {"coordinates":[120.94784,15.47588],"type":"Point"}
}