{
  "type": "Feature",
  "properties": {
    "gn:admin1_code":"08",
    "gn:admin2_code":"55",
    "gn:admin3_code":"86013000.0",
    "gn:asciiname":"Mambog",
    "gn:country_code":"PH",
    "gn:dem":130,
    "gn:feature_class":"P",
    "gn:feature_code":"PPL",
    "gn:name":"Mambog",
    "gn:population":0,
    "gn:timezone":"Asia/Manila",
    "iso:country":"PH",
    "name:fil_x_preferred":[
        "Mambog"
    ],
    "wof:name":"Mambog",
    "wof:placetype":"locality"
},
  "geometry": {"coordinates":[125.01667,11.55],"type":"Point"}
}