{
  "type": "Feature",
  "properties": {
    "gn:admin1_code":"10",
    "gn:admin2_code":"43",
    "gn:admin3_code":"104314000.0",
    "gn:asciiname":"Gassi",
    "gn:country_code":"PH",
    "gn:dem":74,
    "gn:feature_class":"P",
    "gn:feature_code":"PPL",
    "gn:name":"Gassi",
    "gn:population":0,
    "gn:timezone":"Asia/Manila",
    "iso:country":"PH",
    "name:fil_x_preferred":[
        "Gassi"
    ],
    "wof:name":"Gassi",
    "wof:placetype":"locality"
},
  "geometry": {"coordinates":[124.43778,8.5975],"type":"Point"}
}