{
  "type": "Feature",
  "properties": {
    "gn:admin1_code":"02",
    "gn:admin2_code":"14",
    "gn:admin3_code":"21509000.0",
    "gn:asciiname":"San Dionisio",
    "gn:country_code":"PH",
    "gn:dem":77,
    "gn:elevation":"0.0",
    "gn:feature_class":"P",
    "gn:feature_code":"PPL",
    "gn:name":"San Dionisio",
    "gn:population":0,
    "gn:timezone":"Asia/Manila",
    "iso:country":"PH",
    "name:fil_x_preferred":[
        "San Dionisio"
    ],
    "wof:name":"San Dionisio",
    "wof:placetype":"locality"
},
  "geometry": {"coordinates":[121.94246,19.492],"type":"Point"}
}