{
  "type": "Feature",
  "properties": {
    "gn:admin1_code":"11",
    "gn:admin2_code":"25",
    "gn:admin3_code":"112402000.0",
    "gn:asciiname":"Tigatto",
    "gn:cc2":"PH",
    "gn:country_code":"PH",
    "gn:dem":26,
    "gn:feature_class":"P",
    "gn:feature_code":"PPL",
    "gn:name":"Tigatto",
    "gn:population":0,
    "gn:timezone":"Asia/Manila",
    "iso:country":"PH",
    "name:und_x_variant":[
        "Tigatao",
        "Tigata",
        "Tiggatto"
    ],
    "wof:name":"Tigatto",
    "wof:placetype":"locality"
},
  "geometry": {"coordinates":[125.595,7.1275],"type":"Point"}
}