{
  "type": "Feature",
  "properties": {
    "gn:admin1_code":"05",
    "gn:admin2_code":"39",
    "gn:admin3_code":"54110000.0",
    "gn:asciiname":"Pandaigan",
    "gn:country_code":"PH",
    "gn:dem":10,
    "gn:feature_class":"P",
    "gn:feature_code":"PPL",
    "gn:name":"Pandaigan",
    "gn:population":0,
    "gn:timezone":"Asia/Manila",
    "iso:country":"PH",
    "name:fil_x_preferred":[
        "Pandaigan"
    ],
    "name:und_x_variant":[
        "Panobigan"
    ],
    "wof:name":"Pandaigan",
    "wof:placetype":"locality"
},
  "geometry": {"coordinates":[123.22451,12.22585],"type":"Point"}
}