{
  "type": "Feature",
  "properties": {
    "gn:admin1_code":"14",
    "gn:admin2_code":"60",
    "gn:admin3_code":"156603000.0",
    "gn:asciiname":"Mangal Mangal",
    "gn:country_code":"PH",
    "gn:dem":126,
    "gn:feature_class":"P",
    "gn:feature_code":"PPL",
    "gn:name":"Mangal Mangal",
    "gn:population":0,
    "gn:timezone":"Asia/Manila",
    "iso:country":"PH",
    "name:fil_x_preferred":[
        "Mangal Mangal"
    ],
    "wof:name":"Mangal Mangal",
    "wof:placetype":"locality"
},
  "geometry": {"coordinates":[121.29917,5.94194],"type":"Point"}
}