{
  "type": "Feature",
  "properties": {
    "gn:country":"PH",
    "gn:fcode":"PPL",
    "gn:population":4015,
    "iso:country":"PH",
    "name:fil_x_preferred":[
        "Basdiot"
    ],
    "qs_pg:aaroncc":"PH",
    "qs_pg:gn_country":"PH",
    "qs_pg:gn_fcode":"PPL",
    "qs_pg:gn_pop":4015,
    "qs_pg:name":"Basdiot",
    "qs_pg:photos_9r":0,
    "qs_pg:photos_sr":0,
    "qs_pg:pop_sr":4,
    "qs_pg:qs_pg_placetype":"locality",
    "wof:name":"Basdiot",
    "wof:placetype":"locality",
    "wof:population":4015
},
  "geometry": {"coordinates":[123.37515,9.94718],"type":"Point"}
}