{
  "type": "Feature",
  "properties": {
    "gn:country":"PH",
    "gn:fcode":"ADM3",
    "gn:pop":7761,
    "iso:country":"PH",
    "name:fil_x_preferred":[
        "San Esteban"
    ],
    "qs:name":"San Esteban",
    "qs:photos_9r":0,
    "qs:photos_sr":0,
    "qs:pop_sr":"5",
    "wd:wordcount":110,
    "wof:name":"San Esteban",
    "wof:placetype":"localadmin",
    "wof:population":7761
},
  "geometry": {"coordinates":[120.46666999999999,17.33333],"type":"Point"}
}