{
  "type": "Feature",
  "properties": {
    "gn:country":"PH",
    "gn:fcode":"ADM3",
    "gn:pop":7761,
    "iso:country":"PH",
    "name:ast_x_preferred":[
        "San Esteban"
    ],
    "name:ceb_x_preferred":[
        "San Esteban"
    ],
    "name:deu_x_preferred":[
        "San Esteban"
    ],
    "name:eus_x_preferred":[
        "San Esteban"
    ],
    "name:fil_x_preferred":[
        "San Esteban"
    ],
    "name:fra_x_preferred":[
        "San Esteban"
    ],
    "name:ita_x_preferred":[
        "San Esteban"
    ],
    "name:nld_x_preferred":[
        "San Esteban"
    ],
    "name:por_x_preferred":[
        "San Esteban"
    ],
    "name:spa_x_preferred":[
        "San Esteban"
    ],
    "name:srp_x_preferred":[
        "\u0421\u0430\u043d \u0415\u0441\u0442\u0435\u0431\u0430\u043d"
    ],
    "name:swe_x_preferred":[
        "San Esteban"
    ],
    "name:war_x_preferred":[
        "San Esteban"
    ],
    "qs:name":"San Esteban",
    "qs:photos_9r":0,
    "qs:photos_sr":0,
    "qs:pop_sr":"5",
    "wd:wordcount":110,
    "wof:name":"San Esteban",
    "wof:placetype":"localadmin",
    "wof:population":7761
},
  "geometry": {"coordinates":[120.46666999999999,17.33333],"type":"Point"}
}