{
  "type": "Feature",
  "properties": {
    "gn:admin1_code":"13",
    "gn:admin2_code":"61",
    "gn:admin3_code":"166721000.0",
    "gn:asciiname":"Solion",
    "gn:country_code":"PH",
    "gn:dem":43,
    "gn:feature_class":"P",
    "gn:feature_code":"PPL",
    "gn:name":"Solion",
    "gn:population":0,
    "gn:timezone":"Asia/Manila",
    "iso:country":"PH",
    "name:fil_x_preferred":[
        "Solion"
    ],
    "wof:name":"Solion",
    "wof:placetype":"locality"
},
  "geometry": {"coordinates":[126.04778,9.99611],"type":"Point"}
}