{
  "type": "Feature",
  "properties": {
    "gn:admin1_code":"05",
    "gn:admin2_code":"16",
    "gn:admin3_code":"51721000.0",
    "gn:asciiname":"Tahusanan",
    "gn:country_code":"PH",
    "gn:dem":5,
    "gn:feature_class":"P",
    "gn:feature_code":"PPL",
    "gn:name":"Tahusanan",
    "gn:population":0,
    "gn:timezone":"Asia/Manila",
    "iso:country":"PH",
    "name:fil_x_preferred":[
        "Tahusanan"
    ],
    "name:und_x_variant":[
        "Tarusanan"
    ],
    "wof:name":"Tahusanan",
    "wof:placetype":"locality"
},
  "geometry": {"coordinates":[123.17310000000001,13.6086],"type":"Point"}
}