{
  "type": "Feature",
  "properties": {
    "gn:admin1_code":"01",
    "gn:admin2_code":"51",
    "gn:admin3_code":"15516000.0",
    "gn:asciiname":"Culebra",
    "gn:country_code":"PH",
    "gn:dem":14,
    "gn:feature_class":"P",
    "gn:feature_code":"PPL",
    "gn:name":"Culebra",
    "gn:population":0,
    "gn:timezone":"Asia/Manila",
    "iso:country":"PH",
    "name:ceb_x_preferred":[
        "Culebra"
    ],
    "name:eng_x_preferred":[
        "Culebra"
    ],
    "name:fra_x_preferred":[
        "Culebra"
    ],
    "name:ita_x_preferred":[
        "Culebra"
    ],
    "name:pol_x_preferred":[
        "Culebra"
    ],
    "name:rus_x_preferred":[
        "\u041a\u0443\u043b\u0435\u0431\u0440\u0430"
    ],
    "name:spa_x_preferred":[
        "Culebra"
    ],
    "name:swe_x_preferred":[
        "Culebra"
    ],
    "wof:name":"Culebra",
    "wof:placetype":"locality"
},
  "geometry": {"coordinates":[119.89149999999999,16.0722],"type":"Point"}
}