{
  "type": "Feature",
  "properties": {
    "gn:admin1_code":"41",
    "gn:admin2_code":"54",
    "gn:admin3_code":"175912000.0",
    "gn:asciiname":"Dabdaban",
    "gn:country_code":"PH",
    "gn:dem":125,
    "gn:feature_class":"P",
    "gn:feature_code":"PPL",
    "gn:name":"Dabdaban",
    "gn:population":0,
    "gn:timezone":"Asia/Manila",
    "iso:country":"PH",
    "wof:name":"Dabdaban",
    "wof:placetype":"locality"
},
  "geometry": {"coordinates":[122.07639,12.56583],"type":"Point"}
}