{
  "type": "Feature",
  "properties": {
    "gn:admin1_code":"07",
    "gn:admin2_code":"11",
    "gn:admin3_code":"71235000.0",
    "gn:asciiname":"Bonbonon",
    "gn:country_code":"PH",
    "gn:dem":19,
    "gn:feature_class":"P",
    "gn:feature_code":"PPL",
    "gn:name":"Bonbonon",
    "gn:population":0,
    "gn:timezone":"Asia/Manila",
    "iso:country":"PH",
    "name:fil_x_preferred":[
        "Bonbonon"
    ],
    "wof:name":"Bonbonon",
    "wof:placetype":"locality"
},
  "geometry": {"coordinates":[124.5789,10.1253],"type":"Point"}
}