{
  "type": "Feature",
  "properties": {
    "gn:country":"PH",
    "gn:fcode":"PPL",
    "gn:pop":2698,
    "iso:country":"PH",
    "name:fil_x_preferred":[
        "Kablalan"
    ],
    "name:unk_x_variant":[
        "Cablallan"
    ],
    "qs:name":"Kablalan",
    "qs:photos_9r":0,
    "qs:photos_sr":0,
    "qs:pop_sr":"4",
    "wof:name":"Kablalan",
    "wof:placetype":"locality",
    "wof:population":2698
},
  "geometry": {"coordinates":[125.19777999999999,5.77972],"type":"Point"}
}