{
  "type": "Feature",
  "properties": {
    "gn:admin1_code":"03",
    "gn:admin2_code":"50",
    "gn:admin3_code":"35403000.0",
    "gn:asciiname":"Matamo",
    "gn:country_code":"PH",
    "gn:dem":11,
    "gn:feature_class":"P",
    "gn:feature_code":"PPL",
    "gn:name":"Matamo",
    "gn:population":0,
    "gn:timezone":"Asia/Manila",
    "iso:country":"PH",
    "name:fil_x_preferred":[
        "Matamo"
    ],
    "name:und_x_variant":[
        "Santa Lucia"
    ],
    "wof:name":"Matamo",
    "wof:placetype":"locality"
},
  "geometry": {"coordinates":[120.79904999999999,15.13657],"type":"Point"}
}