{
  "type": "Feature",
  "properties": {
    "gn:admin1_code":"06",
    "gn:admin2_code":"18",
    "gn:admin3_code":"61910000.0",
    "gn:asciiname":"Tinigban",
    "gn:country_code":"PH",
    "gn:dem":17,
    "gn:feature_class":"P",
    "gn:feature_code":"PPL",
    "gn:name":"Tinigban",
    "gn:population":0,
    "gn:timezone":"Asia/Manila",
    "iso:country":"PH",
    "name:fil_x_preferred":[
        "Tinigban"
    ],
    "wof:name":"Tinigban",
    "wof:placetype":"locality"
},
  "geometry": {"coordinates":[122.7907,11.4349],"type":"Point"}
}