{
  "type": "Feature",
  "properties": {
    "gn:country":"PH",
    "gn:fcode":"PPL",
    "gn:population":2318,
    "iso:country":"PH",
    "name:fil_x_preferred":[
        "Catungan"
    ],
    "qs_pg:aaroncc":"PH",
    "qs_pg:gn_country":"PH",
    "qs_pg:gn_fcode":"PPL",
    "qs_pg:gn_pop":2318,
    "qs_pg:name":"Catungan",
    "qs_pg:photos_9r":0,
    "qs_pg:photos_sr":0,
    "qs_pg:pop_sr":4,
    "qs_pg:qs_pg_placetype":"locality",
    "wof:name":"Catungan",
    "wof:placetype":"locality",
    "wof:population":2318
},
  "geometry": {"coordinates":[122.0149,10.7706],"type":"Point"}
}