{
  "type": "Feature",
  "properties": {
    "gn:admin1_code":"41",
    "gn:admin2_code":"54",
    "gn:admin3_code":"175903000.0",
    "gn:asciiname":"Magbagacay",
    "gn:country_code":"PH",
    "gn:dem":13,
    "gn:feature_class":"P",
    "gn:feature_code":"PPL",
    "gn:name":"Magbagacay",
    "gn:population":0,
    "gn:timezone":"Asia/Manila",
    "iso:country":"PH",
    "name:fil_x_preferred":[
        "Magbagacay"
    ],
    "wof:name":"Magbagacay",
    "wof:placetype":"locality"
},
  "geometry": {"coordinates":[122.66261000000002,12.45913],"type":"Point"}
}