{
  "type": "Feature",
  "properties": {
    "gn:admin1_code":"40",
    "gn:admin2_code":"20",
    "gn:admin3_code":"42118000.0",
    "gn:asciiname":"Iba",
    "gn:country_code":"PH",
    "gn:dem":324,
    "gn:feature_class":"P",
    "gn:feature_code":"PPL",
    "gn:name":"Iba",
    "gn:population":0,
    "gn:timezone":"Asia/Manila",
    "iso:country":"PH",
    "name:und_x_variant":[
        "Ida"
    ],
    "wof:name":"Iba",
    "wof:placetype":"locality"
},
  "geometry": {"coordinates":[120.9768,14.2204],"type":"Point"}
}