{
  "type": "Feature",
  "properties": {
    "gn:admin1_code":"06",
    "gn:admin2_code":"30",
    "gn:admin3_code":"63035000.0",
    "gn:asciiname":"Cairojan",
    "gn:country_code":"PH",
    "gn:dem":68,
    "gn:feature_class":"P",
    "gn:feature_code":"PPL",
    "gn:name":"Cairojan",
    "gn:population":0,
    "gn:timezone":"Asia/Manila",
    "iso:country":"PH",
    "name:fil_x_preferred":[
        "Cairojan"
    ],
    "name:und_x_variant":[
        "Cairohan"
    ],
    "wof:name":"Cairojan",
    "wof:placetype":"locality"
},
  "geometry": {"coordinates":[122.5861,11.1298],"type":"Point"}
}