{
  "type": "Feature",
  "properties": {
    "gn:admin1_code":"40",
    "gn:admin2_code":"H2",
    "gn:admin3_code":"45623000.0",
    "gn:asciiname":"Maramo",
    "gn:country_code":"PH",
    "gn:dem":424,
    "gn:feature_class":"P",
    "gn:feature_code":"PPL",
    "gn:name":"Maramo",
    "gn:population":0,
    "gn:timezone":"Asia/Manila",
    "iso:country":"PH",
    "name:fil_x_preferred":[
        "Maramo"
    ],
    "wof:name":"Maramo",
    "wof:placetype":"locality"
},
  "geometry": {"coordinates":[121.56667,14.11667],"type":"Point"}
}