{
  "type": "Feature",
  "properties": {
    "gn:country":"PH",
    "gn:fcode":"PPL",
    "gn:pop":9674,
    "iso:country":"PH",
    "name:fil_x_preferred":[
        "Nalundan"
    ],
    "qs:name":"Nalundan",
    "qs:photos_9r":0,
    "qs:photos_sr":0,
    "qs:pop_sr":"5",
    "wof:name":"Nalundan",
    "wof:placetype":"locality",
    "wof:population":9674
},
  "geometry": {"coordinates":[123.06667,9.75],"type":"Point"}
}