{
  "type": "Feature",
  "properties": {
    "gn:admin1_code":"05",
    "gn:admin2_code":"16",
    "gn:admin3_code":"51732000.0",
    "gn:asciiname":"Grijalvo",
    "gn:cc2":"PH",
    "gn:country_code":"PH",
    "gn:dem":21,
    "gn:feature_class":"P",
    "gn:feature_code":"PPL",
    "gn:name":"Grijalvo",
    "gn:population":0,
    "gn:timezone":"Asia/Manila",
    "iso:country":"PH",
    "name:und_x_variant":[
        "Grijalbo",
        "Grijalvo"
    ],
    "wof:name":"Grijalvo",
    "wof:placetype":"locality"
},
  "geometry": {"coordinates":[123.13333,13.55],"type":"Point"}
}