{
  "type": "Feature",
  "properties": {
    "gn:admin1_code":"08",
    "gn:admin2_code":"67",
    "gn:admin3_code":"84802000.0",
    "gn:asciiname":"Moalboal",
    "gn:country_code":"PH",
    "gn:dem":29,
    "gn:feature_class":"P",
    "gn:feature_code":"PPL",
    "gn:name":"Moalboal",
    "gn:population":0,
    "gn:timezone":"Asia/Manila",
    "iso:country":"PH",
    "name:fil_x_preferred":[
        "Moalboal"
    ],
    "wof:name":"Moalboal",
    "wof:placetype":"locality"
},
  "geometry": {"coordinates":[124.3913,12.6582],"type":"Point"}
}