{
  "type": "Feature",
  "properties": {
    "gn:admin1_code":"03",
    "gn:admin2_code":"64",
    "gn:admin3_code":"37102000.0",
    "gn:asciiname":"Laoag North",
    "gn:country_code":"PH",
    "gn:dem":13,
    "gn:feature_class":"P",
    "gn:feature_code":"PPL",
    "gn:name":"Laoag North",
    "gn:population":0,
    "gn:timezone":"Asia/Manila",
    "iso:country":"PH",
    "name:eng_x_preferred":[
        "Laoag North"
    ],
    "name:und_x_variant":[
        "Lawag",
        "Laog",
        "Labang",
        "Laoag"
    ],
    "wof:name":"Laoag North",
    "wof:placetype":"locality"
},
  "geometry": {"coordinates":[120.0528,15.128],"type":"Point"}
}