{
  "type": "Feature",
  "properties": {
    "gn:admin1_code":"14",
    "gn:admin2_code":"56",
    "gn:admin3_code":"153837000.0",
    "gn:asciiname":"Linantangon",
    "gn:country_code":"PH",
    "gn:dem":14,
    "gn:feature_class":"P",
    "gn:feature_code":"PPL",
    "gn:name":"Linantangon",
    "gn:population":0,
    "gn:timezone":"Asia/Manila",
    "iso:country":"PH",
    "name:fil_x_preferred":[
        "Linantangon"
    ],
    "wof:name":"Linantangon",
    "wof:placetype":"locality"
},
  "geometry": {"coordinates":[124.50360999999999,6.94194],"type":"Point"}
}