{
  "type": "Feature",
  "properties": {
    "iso:country":"PH",
    "name:bcl_x_preferred":[
        "Bayog"
    ],
    "name:cbk_zam_x_preferred":[
        "Bayog"
    ],
    "name:ceb_x_preferred":[
        "Bayog"
    ],
    "name:deu_x_preferred":[
        "Bayog"
    ],
    "name:dut_x_preferred":[
        "Bayog"
    ],
    "name:eng_x_preferred":[
        "Bayog"
    ],
    "name:fre_x_preferred":[
        "Bayog"
    ],
    "name:ger_x_preferred":[
        "Bayog"
    ],
    "name:ilo_x_preferred":[
        "Bayog"
    ],
    "name:ind_x_preferred":[
        "Bayog"
    ],
    "name:ita_x_preferred":[
        "Bayog"
    ],
    "name:nld_x_preferred":[
        "Bayog"
    ],
    "name:pag_x_preferred":[
        "Bayog"
    ],
    "name:pam_x_preferred":[
        "Bayog"
    ],
    "name:spa_x_preferred":[
        "Bayog"
    ],
    "name:swe_x_preferred":[
        "Bayog"
    ],
    "name:tgl_x_preferred":[
        "Bayog"
    ],
    "name:vie_x_preferred":[
        "Bayog"
    ],
    "name:war_x_preferred":[
        "Bayog"
    ],
    "qs:gn_country":"PH",
    "qs:gn_fcode":"PPL",
    "qs:gn_pop":4284,
    "qs:name":"Bayog",
    "qs:name_adm0":"Philippines",
    "qs:name_adm1":"Zamboanga Peninsula",
    "qs:photos":0,
    "qs:photos_1k":0,
    "qs:photos_9k":0,
    "qs:photos_9r":0,
    "qs:photos_all":0,
    "qs:photos_sr":0,
    "qs:placetype":"Town",
    "qs:pop_sr":"4",
    "qs:woe_adm0":23424934,
    "wd:wordcount":2549,
    "wof:name":"Bayog",
    "wof:placetype":"locality",
    "wof:population":4284
},
  "geometry": {"coordinates":[123.06667,7.86667],"type":"Point"}
}