{
  "type": "Feature",
  "properties": {
    "gn:admin1_code":"03",
    "gn:admin2_code":"50",
    "gn:admin3_code":"35407000.0",
    "gn:asciiname":"Santa Filomena",
    "gn:country_code":"PH",
    "gn:dem":6,
    "gn:feature_class":"P",
    "gn:feature_code":"PPL",
    "gn:name":"Santa Filomena",
    "gn:population":0,
    "gn:timezone":"Asia/Manila",
    "iso:country":"PH",
    "name:fil_x_preferred":[
        "Santa Filomena"
    ],
    "wof:name":"Santa Filomena",
    "wof:placetype":"locality"
},
  "geometry": {"coordinates":[120.63677,14.96681],"type":"Point"}
}