{
  "type": "Feature",
  "properties": {
    "gn:country":"PH",
    "gn:fcode":"PPL",
    "gn:population":4190,
    "iso:country":"PH",
    "name:fil_x_preferred":[
        "Santisimo Rosario"
    ],
    "name:und_x_variant":[
        "Santo Rosario"
    ],
    "qs_pg:aaroncc":"PH",
    "qs_pg:gn_country":"PH",
    "qs_pg:gn_fcode":"PPL",
    "qs_pg:gn_pop":4190,
    "qs_pg:name":"Santisimo Rosario",
    "qs_pg:photos_9r":0,
    "qs_pg:photos_sr":0,
    "qs_pg:pop_sr":4,
    "qs_pg:qs_pg_placetype":"locality",
    "wof:name":"Santisimo Rosario",
    "wof:placetype":"locality",
    "wof:population":4190
},
  "geometry": {"coordinates":[121.30918,13.99661],"type":"Point"}
}