{
  "type": "Feature",
  "properties": {
    "gn:country":"PH",
    "gn:fcode":"PPL",
    "gn:population":2085,
    "iso:country":"PH",
    "name:eng_x_preferred":[
        "Disod"
    ],
    "qs:name":"Disod",
    "qs:photos_9r":0,
    "qs:photos_sr":0,
    "qs:pop_sr":"4",
    "wof:name":"Disod",
    "wof:placetype":"locality",
    "wof:population":2085
},
  "geometry": {"coordinates":[123.01690000000001,8.2611],"type":"Point"}
}