{
  "type": "Feature",
  "properties": {
    "gn:admin1_code":"07",
    "gn:admin2_code":"11",
    "gn:admin3_code":"71204000.0",
    "gn:asciiname":"Cansubayon",
    "gn:country_code":"PH",
    "gn:dem":280,
    "gn:feature_class":"P",
    "gn:feature_code":"PPL",
    "gn:name":"Cansubayon",
    "gn:population":0,
    "gn:timezone":"Asia/Manila",
    "iso:country":"PH",
    "name:fil_x_preferred":[
        "Cansubayon"
    ],
    "name:und_x_variant":[
        "Consubayon"
    ],
    "wof:name":"Cansubayon",
    "wof:placetype":"locality"
},
  "geometry": {"coordinates":[123.9012,9.8281],"type":"Point"}
}