{
  "type": "Feature",
  "properties": {
    "gn:country":"PH",
    "gn:fcode":"PPL",
    "gn:pop":9095,
    "iso:country":"PH",
    "name:fil_x_preferred":[
        "Andop"
    ],
    "qs:name":"Andop",
    "qs:photos_9r":0,
    "qs:photos_sr":0,
    "qs:pop_sr":"5",
    "wof:name":"Andop",
    "wof:placetype":"locality",
    "wof:population":9095
},
  "geometry": {"coordinates":[125.75389,7.86111],"type":"Point"}
}