{
  "type": "Feature",
  "properties": {
    "gn:country":"PH",
    "gn:fcode":"ADM3",
    "gn:pop":24490,
    "iso:country":"PH",
    "name:fil_x_preferred":[
        "Macrohon"
    ],
    "qs:name":"Macrohon",
    "qs:photos_9r":0,
    "qs:photos_sr":0,
    "qs:pop_sr":"7",
    "wof:name":"Macrohon",
    "wof:placetype":"localadmin",
    "wof:population":24490
},
  "geometry": {"coordinates":[124.93333,10.11667],"type":"Point"}
}