{
  "type": "Feature",
  "properties": {
    "gn:admin1_code":"08",
    "gn:admin2_code":"55",
    "gn:admin3_code":"86025000.0",
    "gn:asciiname":"Naghituman",
    "gn:country_code":"PH",
    "gn:dem":13,
    "gn:feature_class":"P",
    "gn:feature_code":"PPL",
    "gn:name":"Naghituman",
    "gn:population":0,
    "gn:timezone":"Asia/Manila",
    "iso:country":"PH",
    "name:fil_x_preferred":[
        "Naghituman"
    ],
    "wof:name":"Naghituman",
    "wof:placetype":"locality"
},
  "geometry": {"coordinates":[124.86278,11.94889],"type":"Point"}
}