{
  "type": "Feature",
  "properties": {
    "gn:admin1_code":"03",
    "gn:admin2_code":"13",
    "gn:admin3_code":"31424000.0",
    "gn:asciiname":"Bagong",
    "gn:country_code":"PH",
    "gn:dem":67,
    "gn:feature_class":"P",
    "gn:feature_code":"PPL",
    "gn:name":"Bagong",
    "gn:population":0,
    "gn:timezone":"Asia/Manila",
    "iso:country":"PH",
    "name:fil_x_preferred":[
        "Bagong Barrio"
    ],
    "name:fil_x_variant":[
        "Bagong"
    ],
    "wof:name":"Bagong",
    "wof:placetype":"locality"
},
  "geometry": {"coordinates":[121.07089999999999,14.9565],"type":"Point"}
}