{
  "type": "Feature",
  "properties": {
    "gn:admin1_code":"05",
    "gn:admin2_code":"39",
    "gn:admin3_code":"54101000.0",
    "gn:asciiname":"Natimbunan",
    "gn:country_code":"PH",
    "gn:dem":11,
    "gn:feature_class":"P",
    "gn:feature_code":"PPL",
    "gn:name":"Natimbunan",
    "gn:population":0,
    "gn:timezone":"Asia/Manila",
    "iso:country":"PH",
    "name:fil_x_preferred":[
        "Natimbunan"
    ],
    "wof:name":"Natimbunan",
    "wof:placetype":"locality"
},
  "geometry": {"coordinates":[123.2878,12.4424],"type":"Point"}
}