{
  "type": "Feature",
  "properties": {
    "iso:country":"PH",
    "name:bcl_x_preferred":[
        "Kalilangan"
    ],
    "name:cbk_zam_x_preferred":[
        "Kalilangan"
    ],
    "name:ceb_x_preferred":[
        "Kalilangan"
    ],
    "name:deu_x_preferred":[
        "Kalilangan"
    ],
    "name:eng_x_preferred":[
        "Kalilangan"
    ],
    "name:fra_x_preferred":[
        "Kalilangan"
    ],
    "name:ilo_x_preferred":[
        "Kalilangan"
    ],
    "name:ind_x_preferred":[
        "Kalilangan"
    ],
    "name:ita_x_preferred":[
        "Kalilangan"
    ],
    "name:nld_x_preferred":[
        "Kalilangan"
    ],
    "name:pag_x_preferred":[
        "Kalilangan"
    ],
    "name:pam_x_preferred":[
        "Kalilangan"
    ],
    "name:spa_x_preferred":[
        "Kalilang\u00e1n"
    ],
    "name:swe_x_preferred":[
        "Kalilangan"
    ],
    "name:tgl_x_preferred":[
        "Kalilangan"
    ],
    "name:urd_x_preferred":[
        "\u06a9\u0627\u0644\u06cc\u0644\u0627\u0646\u06af\u0627\u0646"
    ],
    "name:vie_x_preferred":[
        "Kalilangan"
    ],
    "name:war_x_preferred":[
        "Kalilangan"
    ],
    "name:zho_x_preferred":[
        "\u5361\u5229\u5170\u6839"
    ],
    "qs:gn_country":"PH",
    "qs:gn_fcode":"PPL",
    "qs:gn_pop":14456,
    "qs:name":"Kalilangan",
    "qs:name_adm0":"Philippines",
    "qs:name_adm1":"Northern Mindanao",
    "qs:photos":0,
    "qs:photos_1k":0,
    "qs:photos_9k":0,
    "qs:photos_9r":0,
    "qs:photos_all":0,
    "qs:photos_sr":0,
    "qs:placetype":"Town",
    "qs:pop_sr":"6",
    "qs:woe_adm0":23424934,
    "wd:wordcount":963,
    "wof:name":"Kalilangan",
    "wof:placetype":"locality",
    "wof:population":14456
},
  "geometry": {"coordinates":[124.73139,7.82111],"type":"Point"}
}