{
  "type": "Feature",
  "properties": {
    "gn:admin1_code":"40",
    "gn:admin2_code":"H2",
    "gn:admin3_code":"45629000.0",
    "gn:asciiname":"Duhat",
    "gn:country_code":"PH",
    "gn:dem":70,
    "gn:feature_class":"P",
    "gn:feature_code":"PPL",
    "gn:name":"Duhat",
    "gn:population":0,
    "gn:timezone":"Asia/Manila",
    "iso:country":"PH",
    "name:fil_x_preferred":[
        "Duhat"
    ],
    "name:tgl_x_preferred":[
        "Duhat"
    ],
    "wof:name":"Duhat",
    "wof:placetype":"locality"
},
  "geometry": {"coordinates":[121.83029999999999,13.92699],"type":"Point"}
}