{
  "type": "Feature",
  "properties": {
    "gn:admin1_code":"09",
    "gn:admin2_code":"66",
    "gn:admin3_code":"97338000.0",
    "gn:asciiname":"Balabawan",
    "gn:country_code":"PH",
    "gn:dem":15,
    "gn:feature_class":"P",
    "gn:feature_code":"PPL",
    "gn:name":"Balabawan",
    "gn:population":0,
    "gn:timezone":"Asia/Manila",
    "iso:country":"PH",
    "name:eng_x_preferred":[
        "Balabawan"
    ],
    "name:und_x_variant":[
        "Balawan"
    ],
    "wof:name":"Balabawan",
    "wof:placetype":"locality"
},
  "geometry": {"coordinates":[123.3233,7.4385],"type":"Point"}
}