{
  "type": "Feature",
  "properties": {
    "gn:admin1_code":"05",
    "gn:admin2_code":"39",
    "gn:admin3_code":"54113000.0",
    "gn:asciiname":"Balatucan",
    "gn:country_code":"PH",
    "gn:dem":64,
    "gn:feature_class":"P",
    "gn:feature_code":"PPL",
    "gn:name":"Balatucan",
    "gn:population":0,
    "gn:timezone":"Asia/Manila",
    "iso:country":"PH",
    "name:fil_x_preferred":[
        "Balatucan"
    ],
    "wof:name":"Balatucan",
    "wof:placetype":"locality"
},
  "geometry": {"coordinates":[123.72371,12.27984],"type":"Point"}
}