{
  "type": "Feature",
  "properties": {
    "gn:gn_country":"PH",
    "gn:gn_fcode":"ADM3",
    "gn:gn_pop":25272,
    "gn:population":25272,
    "iso:country":"PH",
    "name:eng_x_preferred":[
        "Municipality of Ramon Magsaysay"
    ],
    "name:unk_x_variant":[
        "Liargo"
    ],
    "qs_pg:aaroncc":"PH",
    "qs_pg:gn_country":"PH",
    "qs_pg:gn_fcode":"ADM3",
    "qs_pg:gn_pop":25272,
    "qs_pg:name":"Municipality of Ramon Magsaysay",
    "qs_pg:photos_9r":0,
    "qs_pg:photos_sr":0,
    "qs_pg:pop_sr":7,
    "qs_pg:qs_pg_placetype":"localadmin",
    "wof:name":"Municipality of Ramon Magsaysay",
    "wof:placetype":"localadmin",
    "wof:population":25272
},
  "geometry": {"coordinates":[123.45829999999999,8.0172],"type":"Point"}
}