{
  "type": "Feature",
  "properties": {
    "gn:admin1_code":"01",
    "gn:admin2_code":"51",
    "gn:admin3_code":"15508000.0",
    "gn:asciiname":"Tipor",
    "gn:country_code":"PH",
    "gn:dem":45,
    "gn:feature_class":"P",
    "gn:feature_code":"PPL",
    "gn:name":"Tipor",
    "gn:population":0,
    "gn:timezone":"Asia/Manila",
    "iso:country":"PH",
    "name:fil_x_preferred":[
        "Tipor"
    ],
    "wof:name":"Tipor",
    "wof:placetype":"locality"
},
  "geometry": {"coordinates":[119.86839999999999,16.1484],"type":"Point"}
}