{
  "type": "Feature",
  "properties": {
    "gn:admin1_code":"05",
    "gn:admin2_code":"05",
    "gn:admin3_code":"50512000.0",
    "gn:asciiname":"Bangyawon",
    "gn:country_code":"PH",
    "gn:dem":112,
    "gn:feature_class":"P",
    "gn:feature_code":"PPL",
    "gn:name":"Bangyawon",
    "gn:population":0,
    "gn:timezone":"Asia/Manila",
    "iso:country":"PH",
    "name:fil_x_preferred":[
        "Bangyawon"
    ],
    "wof:name":"Bangyawon",
    "wof:placetype":"locality"
},
  "geometry": {"coordinates":[123.38688,13.18323],"type":"Point"}
}