{
  "type": "Feature",
  "properties": {
    "gn:admin1_code":"13",
    "gn:admin2_code":"03",
    "gn:admin3_code":"160306000.0",
    "gn:asciiname":"Las Navas",
    "gn:country_code":"PH",
    "gn:dem":32,
    "gn:feature_class":"P",
    "gn:feature_code":"PPL",
    "gn:name":"Las Navas",
    "gn:population":0,
    "gn:timezone":"Asia/Manila",
    "iso:country":"PH",
    "name:fil_x_preferred":[
        "Las Navas"
    ],
    "wof:name":"Las Navas",
    "wof:placetype":"locality"
},
  "geometry": {"coordinates":[125.90944,8.53333],"type":"Point"}
}