{
  "type": "Feature",
  "properties": {
    "gn:gn_country":"PH",
    "gn:gn_fcode":"PPL",
    "gn:gn_pop":3403,
    "gn:population":3403,
    "iso:country":"PH",
    "name:ceb_x_preferred":[
        "Calumpang"
    ],
    "name:fil_x_preferred":[
        "Calumpang"
    ],
    "qs_pg:aaroncc":"PH",
    "qs_pg:gn_country":"PH",
    "qs_pg:gn_fcode":"PPL",
    "qs_pg:gn_pop":3403,
    "qs_pg:name":"Calumpang",
    "qs_pg:photos_9r":0,
    "qs_pg:photos_sr":0,
    "qs_pg:pop_sr":4,
    "qs_pg:qs_pg_placetype":"locality",
    "wof:name":"Calumpang",
    "wof:placetype":"locality",
    "wof:population":3403
},
  "geometry": {"coordinates":[121.402,14.1966],"type":"Point"}
}