{
  "type": "Feature",
  "properties": {
    "gn:admin1_code":"07",
    "gn:admin2_code":"11",
    "gn:admin3_code":"71247000.0",
    "gn:asciiname":"Anonang",
    "gn:country_code":"PH",
    "gn:dem":416,
    "gn:feature_class":"P",
    "gn:feature_code":"PPL",
    "gn:name":"Anonang",
    "gn:population":0,
    "gn:timezone":"Asia/Manila",
    "iso:country":"PH",
    "name:fil_x_preferred":[
        "Anonang"
    ],
    "name:und_x_variant":[
        "Anunang"
    ],
    "wof:name":"Anonang",
    "wof:placetype":"locality"
},
  "geometry": {"coordinates":[124.20871,9.71067],"type":"Point"}
}