{
  "type": "Feature",
  "properties": {
    "gn:admin1_code":"05",
    "gn:admin2_code":"16",
    "gn:admin3_code":"51717000.0",
    "gn:asciiname":"Omalo",
    "gn:country_code":"PH",
    "gn:dem":8,
    "gn:feature_class":"P",
    "gn:feature_code":"PPL",
    "gn:name":"Omalo",
    "gn:population":0,
    "gn:timezone":"Asia/Manila",
    "iso:country":"PH",
    "name:fil_x_preferred":[
        "Omalo"
    ],
    "wof:name":"Omalo",
    "wof:placetype":"locality"
},
  "geometry": {"coordinates":[123.61790000000001,13.7244],"type":"Point"}
}