{
  "type": "Feature",
  "properties": {
    "gn:admin1_code":"05",
    "gn:admin2_code":"16",
    "gn:admin3_code":"51717000.0",
    "gn:asciiname":"Omalo",
    "gn:country_code":"PH",
    "gn:dem":8,
    "gn:feature_class":"P",
    "gn:feature_code":"PPL",
    "gn:name":"Omalo",
    "gn:population":0,
    "gn:timezone":"Asia/Manila",
    "iso:country":"PH",
    "name:bak_x_preferred":[
        "\u0418\u04ab\u043a\u0435 \u041e\u043c\u0430\u043b\u043e"
    ],
    "name:ben_x_preferred":[
        "\u0993\u09ae\u09be\u09b2\u09cb"
    ],
    "name:ces_x_preferred":[
        "Omalo"
    ],
    "name:che_x_preferred":[
        "\u041e\u043c\u0430\u043b\u043e"
    ],
    "name:ell_x_preferred":[
        "\u039f\u03bc\u03ac\u03bb\u03bf"
    ],
    "name:fas_x_preferred":[
        "\u0627\u0648\u0645\u0627\u0644\u0648"
    ],
    "name:fil_x_preferred":[
        "Omalo"
    ],
    "name:heb_x_preferred":[
        "\u05d0\u05d5\u05de\u05dc\u05d5"
    ],
    "name:hye_x_preferred":[
        "\u0555\u0574\u0561\u056c\u0578"
    ],
    "name:ita_x_preferred":[
        "Omalo"
    ],
    "name:kat_x_preferred":[
        "\u10dd\u10db\u10d0\u10da\u10dd"
    ],
    "name:nld_x_preferred":[
        "Omalo"
    ],
    "name:oss_x_preferred":[
        "\u041e\u043c\u0430\u043b\u043e"
    ],
    "name:rus_x_preferred":[
        "\u041e\u043c\u0430\u043b\u043e"
    ],
    "name:spa_x_preferred":[
        "Omalo"
    ],
    "name:tur_x_preferred":[
        "Omalo"
    ],
    "name:ukr_x_preferred":[
        "\u041e\u043c\u0430\u043b\u043e"
    ],
    "wof:name":"Omalo",
    "wof:placetype":"locality"
},
  "geometry": {"coordinates":[123.61790000000001,13.7244],"type":"Point"}
}