{
  "type": "Feature",
  "properties": {
    "gn:admin1_code":"07",
    "gn:admin2_code":"11",
    "gn:admin3_code":"71206000.0",
    "gn:asciiname":"Del Carmen Sur",
    "gn:country_code":"PH",
    "gn:dem":83,
    "gn:feature_class":"P",
    "gn:feature_code":"PPL",
    "gn:name":"Del Carmen Sur",
    "gn:population":0,
    "gn:timezone":"Asia/Manila",
    "iso:country":"PH",
    "wof:name":"Del Carmen Sur",
    "wof:placetype":"locality"
},
  "geometry": {"coordinates":[123.96619,9.74701],"type":"Point"}
}