{
  "type": "Feature",
  "properties": {
    "gn:admin1_code":"07",
    "gn:admin2_code":"69",
    "gn:admin3_code":"76104000.0",
    "gn:asciiname":"Lico-an",
    "gn:country_code":"PH",
    "gn:dem":89,
    "gn:feature_class":"P",
    "gn:feature_code":"PPL",
    "gn:name":"Lico-an",
    "gn:population":0,
    "gn:timezone":"Asia/Manila",
    "iso:country":"PH",
    "name:fil_x_preferred":[
        "Lico-an"
    ],
    "wof:name":"Lico-an",
    "wof:placetype":"locality"
},
  "geometry": {"coordinates":[123.6528,9.2209],"type":"Point"}
}