{
  "type": "Feature",
  "properties": {
    "gn:country":"PH",
    "gn:fcode":"PPL",
    "gn:population":2727,
    "iso:country":"PH",
    "name:eng_x_preferred":[
        "Timonan"
    ],
    "qs:name":"Timonan",
    "qs:photos_9r":0,
    "qs:photos_sr":0,
    "qs:pop_sr":"4",
    "wof:name":"Timonan",
    "wof:placetype":"locality",
    "wof:population":2727
},
  "geometry": {"coordinates":[123.0682,8.2117],"type":"Point"}
}