{
  "type": "Feature",
  "properties": {
    "gn:admin1_code":"03",
    "gn:admin2_code":"63",
    "gn:admin3_code":"36903000.0",
    "gn:asciiname":"Surgui First",
    "gn:country_code":"PH",
    "gn:dem":26,
    "gn:feature_class":"P",
    "gn:feature_code":"PPL",
    "gn:name":"Surgui First",
    "gn:population":0,
    "gn:timezone":"Asia/Manila",
    "iso:country":"PH",
    "name:fil_x_preferred":[
        "Surgui"
    ],
    "name:und_x_variant":[
        "Surgui Primero",
        "Surgui First"
    ],
    "wof:name":"Surgui First",
    "wof:placetype":"locality"
},
  "geometry": {"coordinates":[120.41495999999999,15.67163],"type":"Point"}
}