{
  "type": "Feature",
  "properties": {
    "gn:admin1_code":"07",
    "gn:admin2_code":"21",
    "gn:admin3_code":"72219000.0",
    "gn:asciiname":"Pit-os",
    "gn:country_code":"PH",
    "gn:dem":101,
    "gn:feature_class":"P",
    "gn:feature_code":"PPL",
    "gn:name":"Pit-os",
    "gn:population":0,
    "gn:timezone":"Asia/Manila",
    "iso:country":"PH",
    "wof:name":"Pit-os",
    "wof:placetype":"locality"
},
  "geometry": {"coordinates":[123.93333,10.38917],"type":"Point"}
}