{
  "type": "Feature",
  "properties": {
    "gn:country":"PH",
    "gn:fcode":"ADM3",
    "gn:pop":15118,
    "iso:country":"PH",
    "name:bcl_x_preferred":[
        "Kabugao"
    ],
    "name:ceb_x_preferred":[
        "Kabugao"
    ],
    "name:deu_x_preferred":[
        "Kabugao"
    ],
    "name:fra_x_preferred":[
        "Kabugao"
    ],
    "name:ilo_x_preferred":[
        "Kabugao"
    ],
    "name:ind_x_preferred":[
        "Kabugao"
    ],
    "name:ita_x_preferred":[
        "Kabugao"
    ],
    "name:msa_x_preferred":[
        "Kabugao"
    ],
    "name:nld_x_preferred":[
        "Kabugao"
    ],
    "name:nor_x_preferred":[
        "Kabugao"
    ],
    "name:pag_x_preferred":[
        "Kabugao"
    ],
    "name:pam_x_preferred":[
        "Kabugao"
    ],
    "name:spa_x_preferred":[
        "Kabugao"
    ],
    "name:swe_x_preferred":[
        "Kabugao"
    ],
    "name:tgl_x_preferred":[
        "Kabugao"
    ],
    "name:tha_x_preferred":[
        "\u0e04\u0e32\u0e1a\u0e39\u0e40\u0e01\u0e32"
    ],
    "name:urd_x_preferred":[
        "\u06a9\u0627\u0628\u0648\u06af\u0627\u0624"
    ],
    "name:vie_x_preferred":[
        "Kabugao"
    ],
    "name:war_x_preferred":[
        "Kabugao"
    ],
    "qs:name":"Kabugao",
    "qs:photos_9r":0,
    "qs:photos_sr":0,
    "qs:pop_sr":"6",
    "wof:name":"Kabugao",
    "wof:placetype":"localadmin",
    "wof:population":15118
},
  "geometry": {"coordinates":[121.18333,18.01667],"type":"Point"}
}