{
  "type": "Feature",
  "properties": {
    "gn:country":"PH",
    "gn:fcode":"ADM3",
    "gn:pop":15118,
    "iso:country":"PH",
    "qs:name":"Kabugao",
    "qs:photos_9r":0,
    "qs:photos_sr":0,
    "qs:pop_sr":"6",
    "wof:name":"Kabugao",
    "wof:placetype":"localadmin",
    "wof:population":15118
},
  "geometry": {"coordinates":[121.18333,18.01667],"type":"Point"}
}