{
  "type": "Feature",
  "properties": {
    "iso:country":"PH",
    "name:bcl_x_preferred":[
        "Quezon"
    ],
    "name:cat_x_preferred":[
        "Quezon"
    ],
    "name:ceb_x_preferred":[
        "Quezon"
    ],
    "name:deu_x_preferred":[
        "Quezon"
    ],
    "name:eng_x_preferred":[
        "Quezon"
    ],
    "name:fil_x_preferred":[
        "Quezon"
    ],
    "name:fra_x_preferred":[
        "Quezon"
    ],
    "name:ilo_x_preferred":[
        "Quezon"
    ],
    "name:ind_x_preferred":[
        "Quezon"
    ],
    "name:ita_x_preferred":[
        "Quezon"
    ],
    "name:jpn_x_preferred":[
        "\u30b1\u30bd\u30f3"
    ],
    "name:nld_x_preferred":[
        "Quezon"
    ],
    "name:oci_x_preferred":[
        "Quezon"
    ],
    "name:pag_x_preferred":[
        "Quezon"
    ],
    "name:pam_x_preferred":[
        "Quezon"
    ],
    "name:sco_x_preferred":[
        "Quezon"
    ],
    "name:swe_x_preferred":[
        "Quezon"
    ],
    "name:tgl_x_preferred":[
        "Quezon"
    ],
    "name:vie_x_preferred":[
        "Quezon"
    ],
    "name:war_x_preferred":[
        "Quezon"
    ],
    "qs:gn_country":"PH",
    "qs:gn_fcode":"PPL",
    "qs:gn_pop":6804,
    "qs:name":"Quezon",
    "qs:name_adm0":"Philippines",
    "qs:name_adm1":"Calabarzon",
    "qs:photos":0,
    "qs:photos_1k":0,
    "qs:photos_9k":0,
    "qs:photos_9r":0,
    "qs:photos_all":0,
    "qs:photos_sr":0,
    "qs:placetype":"Town",
    "qs:pop_sr":"5",
    "qs:woe_adm0":23424934,
    "wof:name":"Quezon",
    "wof:placetype":"locality",
    "wof:population":6804
},
  "geometry": {"coordinates":[122.18380000000001,14.0057],"type":"Point"}
}