{
  "type": "Feature",
  "properties": {
    "gn:admin1_code":"02",
    "gn:admin2_code":"31",
    "gn:admin3_code":"23105000.0",
    "gn:asciiname":"Raniag",
    "gn:country_code":"PH",
    "gn:dem":49,
    "gn:feature_class":"P",
    "gn:feature_code":"PPL",
    "gn:name":"Raniag",
    "gn:population":0,
    "gn:timezone":"Asia/Manila",
    "iso:country":"PH",
    "name:fil_x_preferred":[
        "Ranyag"
    ],
    "name:und_x_variant":[
        "Villa Raniag"
    ],
    "wof:name":"Raniag",
    "wof:placetype":"locality"
},
  "geometry": {"coordinates":[121.76458,17.06731],"type":"Point"}
}