{
  "type": "Feature",
  "properties": {
    "gn:admin1_code":"09",
    "gn:admin2_code":"65",
    "gn:admin3_code":"97222000.0",
    "gn:asciiname":"Maralac",
    "gn:country_code":"PH",
    "gn:dem":60,
    "gn:feature_class":"P",
    "gn:feature_code":"PPL",
    "gn:name":"Maralac",
    "gn:population":0,
    "gn:timezone":"Asia/Manila",
    "iso:country":"PH",
    "name:fil_x_preferred":[
        "Maralac"
    ],
    "wof:name":"Maralac",
    "wof:placetype":"locality"
},
  "geometry": {"coordinates":[122.9825,8.40056],"type":"Point"}
}