{
  "type": "Feature",
  "properties": {
    "iso:country":"PH",
    "name:bcl_x_preferred":[
        "Sibagat"
    ],
    "name:cbk_zam_x_preferred":[
        "Sibagat"
    ],
    "name:ceb_x_preferred":[
        "Sibagat"
    ],
    "name:deu_x_preferred":[
        "Sibagat"
    ],
    "name:eng_x_preferred":[
        "Sibagat"
    ],
    "name:fra_x_preferred":[
        "Sibagat"
    ],
    "name:ilo_x_preferred":[
        "Sibagat"
    ],
    "name:ind_x_preferred":[
        "Sibagat"
    ],
    "name:ita_x_preferred":[
        "Sibagat"
    ],
    "name:msa_x_preferred":[
        "Sibagat"
    ],
    "name:nld_x_preferred":[
        "Sibagat"
    ],
    "name:nob_x_preferred":[
        "Sibagat"
    ],
    "name:pag_x_preferred":[
        "Sibagat"
    ],
    "name:pam_x_preferred":[
        "Sibagat"
    ],
    "name:spa_x_preferred":[
        "Sibagat"
    ],
    "name:swe_x_preferred":[
        "Sibagat"
    ],
    "name:tgl_x_preferred":[
        "Sibagat"
    ],
    "name:und_x_variant":[
        "Sibagat Viejo"
    ],
    "name:urd_x_preferred":[
        "\u0633\u06cc\u0628\u0627\u06af\u0627\u062a"
    ],
    "name:vie_x_preferred":[
        "Sibagat"
    ],
    "name:war_x_preferred":[
        "Sibagat"
    ],
    "qs:gn_country":"PH",
    "qs:gn_fcode":"PPL",
    "qs:gn_pop":4865,
    "qs:name":"Sibagat",
    "qs:name_adm0":"Philippines",
    "qs:name_adm1":"Caraga",
    "qs:photos":0,
    "qs:photos_1k":0,
    "qs:photos_9k":1,
    "qs:photos_9r":1,
    "qs:photos_all":3,
    "qs:photos_sr":0,
    "qs:placetype":"Town",
    "qs:pop_sr":"4",
    "qs:woe_adm0":23424934,
    "wd:wordcount":227,
    "wof:name":"Sibagat",
    "wof:placetype":"locality",
    "wof:population":4865
},
  "geometry": {"coordinates":[125.69750000000001,8.8225],"type":"Point"}
}