{
  "type": "Feature",
  "properties": {
    "gn:admin1_code":"40",
    "gn:admin2_code":"20",
    "gn:admin3_code":"42115000.0",
    "gn:asciiname":"Ibayo Silangan",
    "gn:country_code":"PH",
    "gn:dem":15,
    "gn:feature_class":"P",
    "gn:feature_code":"PPL",
    "gn:name":"Ibayo Silangan",
    "gn:population":0,
    "gn:timezone":"Asia/Manila",
    "iso:country":"PH",
    "name:und_x_variant":[
        "Ibayo",
        "Ibayo Silangan"
    ],
    "wof:name":"Ibayo Silangan",
    "wof:placetype":"locality"
},
  "geometry": {"coordinates":[120.77482000000001,14.32452],"type":"Point"}
}