{
  "type": "Feature",
  "properties": {
    "gn:country":"PH",
    "gn:fcode":"PPL",
    "gn:pop":2164,
    "iso:country":"PH",
    "qs:name":"Baikingon",
    "qs:photos_9r":0,
    "qs:photos_sr":0,
    "qs:pop_sr":"4",
    "wd:wordcount":183,
    "wof:name":"Baikingon",
    "wof:placetype":"locality",
    "wof:population":2164
},
  "geometry": {"coordinates":[124.55361000000001,8.47222],"type":"Point"}
}