{
  "type": "Feature",
  "properties": {
    "gn:admin1_code":"10",
    "gn:admin2_code":"12",
    "gn:admin3_code":"101308000.0",
    "gn:asciiname":"Tumaras",
    "gn:country_code":"PH",
    "gn:dem":222,
    "gn:feature_class":"P",
    "gn:feature_code":"PPL",
    "gn:name":"Tumaras",
    "gn:population":0,
    "gn:timezone":"Asia/Manila",
    "iso:country":"PH",
    "name:fil_x_preferred":[
        "Tumaras"
    ],
    "wof:name":"Tumaras",
    "wof:placetype":"locality"
},
  "geometry": {"coordinates":[125.03082999999999,7.51806],"type":"Point"}
}