{
  "type": "Feature",
  "properties": {
    "gn:admin1_code":"03",
    "gn:admin2_code":"13",
    "gn:admin3_code":"31406000.0",
    "gn:asciiname":"Catacte",
    "gn:country_code":"PH",
    "gn:dem":34,
    "gn:feature_class":"P",
    "gn:feature_code":"PPL",
    "gn:name":"Catacte",
    "gn:population":0,
    "gn:timezone":"Asia/Manila",
    "iso:country":"PH",
    "name:und_x_variant":[
        "Catacta",
        "Katakte",
        "Catacte"
    ],
    "wof:name":"Catacte",
    "wof:placetype":"locality"
},
  "geometry": {"coordinates":[120.94341,14.92563],"type":"Point"}
}