{
  "type": "Feature",
  "properties": {
    "gn:admin1_code":"40",
    "gn:admin2_code":"09",
    "gn:admin3_code":"41022000.0",
    "gn:asciiname":"Palanka",
    "gn:country_code":"PH",
    "gn:dem":252,
    "gn:feature_class":"P",
    "gn:feature_code":"PPL",
    "gn:name":"Palanka",
    "gn:population":0,
    "gn:timezone":"Asia/Manila",
    "iso:country":"PH",
    "name:bos_x_preferred":[
        "Palanka"
    ],
    "name:ceb_x_preferred":[
        "Palanka"
    ],
    "name:deu_x_preferred":[
        "Palanka"
    ],
    "name:fil_x_preferred":[
        "Palanka"
    ],
    "name:fra_x_preferred":[
        "Palanka"
    ],
    "name:hrv_x_preferred":[
        "Palanka"
    ],
    "name:hun_x_preferred":[
        "Palanka"
    ],
    "name:slv_x_preferred":[
        "Palanka"
    ],
    "name:srp_x_preferred":[
        "\u041f\u0430\u043b\u0430\u043d\u043a\u0430"
    ],
    "name:swe_x_preferred":[
        "Palanka"
    ],
    "name:und_x_variant":[
        "Palanca"
    ],
    "wof:name":"Palanka",
    "wof:placetype":"locality"
},
  "geometry": {"coordinates":[121.0933,13.8815],"type":"Point"}
}