{
  "type": "Feature",
  "properties": {
    "gn:admin1_code":"15",
    "gn:admin2_code":"44",
    "gn:admin3_code":"144410000.0",
    "gn:asciiname":"Banaao",
    "gn:country_code":"PH",
    "gn:dem":1107,
    "gn:feature_class":"P",
    "gn:feature_code":"PPL",
    "gn:name":"Banaao",
    "gn:population":0,
    "gn:timezone":"Asia/Manila",
    "iso:country":"PH",
    "name:fil_x_preferred":[
        "Banaao"
    ],
    "wof:name":"Banaao",
    "wof:placetype":"locality"
},
  "geometry": {"coordinates":[120.8241,16.9288],"type":"Point"}
}