{
  "type": "Feature",
  "properties": {
    "gn:admin1_code":"41",
    "gn:admin2_code":"41",
    "gn:admin3_code":"175207000.0",
    "gn:asciiname":"Wawan",
    "gn:country_code":"PH",
    "gn:dem":371,
    "gn:feature_class":"P",
    "gn:feature_code":"PPL",
    "gn:name":"Wawan",
    "gn:population":0,
    "gn:timezone":"Asia/Manila",
    "iso:country":"PH",
    "name:fil_x_preferred":[
        "Wawan"
    ],
    "wof:name":"Wawan",
    "wof:placetype":"locality"
},
  "geometry": {"coordinates":[121.3869,12.4583],"type":"Point"}
}