{
  "type": "Feature",
  "properties": {
    "gn:admin1_code":"05",
    "gn:admin2_code":"19",
    "gn:admin3_code":"52011000.0",
    "gn:asciiname":"Hawan",
    "gn:country_code":"PH",
    "gn:dem":51,
    "gn:feature_class":"P",
    "gn:feature_code":"PPL",
    "gn:name":"Hawan",
    "gn:population":0,
    "gn:timezone":"Asia/Manila",
    "iso:country":"PH",
    "name:fil_x_preferred":[
        "Hawan"
    ],
    "wof:name":"Hawan",
    "wof:placetype":"locality"
},
  "geometry": {"coordinates":[124.1716,13.5572],"type":"Point"}
}