{
  "type": "Feature",
  "properties": {
    "gn:admin1_code":"01",
    "gn:admin2_code":"51",
    "gn:admin3_code":"15531000.0",
    "gn:asciiname":"Bakit Bakit",
    "gn:country_code":"PH",
    "gn:dem":35,
    "gn:feature_class":"P",
    "gn:feature_code":"PPL",
    "gn:name":"Bakit Bakit",
    "gn:population":0,
    "gn:timezone":"Asia/Manila",
    "iso:country":"PH",
    "name:fil_x_preferred":[
        "Batikbatik"
    ],
    "wof:name":"Bakit Bakit",
    "wof:placetype":"locality"
},
  "geometry": {"coordinates":[120.65056,15.89163],"type":"Point"}
}