{
  "type": "Feature",
  "properties": {
    "gn:admin1_code":"03",
    "gn:admin2_code":"07",
    "gn:admin3_code":"30805000.0",
    "gn:asciiname":"Pandatung",
    "gn:country_code":"PH",
    "gn:dem":30,
    "gn:feature_class":"P",
    "gn:feature_code":"PPL",
    "gn:name":"Pandatung",
    "gn:population":0,
    "gn:timezone":"Asia/Manila",
    "iso:country":"PH",
    "wof:name":"Pandatung",
    "wof:placetype":"locality"
},
  "geometry": {"coordinates":[120.46904000000001,14.82883],"type":"Point"}
}