{
  "type": "Feature",
  "properties": {
    "gn:admin1_code":"01",
    "gn:admin2_code":"51",
    "gn:admin3_code":"15542000.0",
    "gn:asciiname":"Baybay Norte",
    "gn:country_code":"PH",
    "gn:dem":15,
    "gn:feature_class":"P",
    "gn:feature_code":"PPL",
    "gn:name":"Baybay Norte",
    "gn:population":0,
    "gn:timezone":"Asia/Manila",
    "iso:country":"PH",
    "name:fil_x_preferred":[
        "Baybay Norte"
    ],
    "wof:name":"Baybay Norte",
    "wof:placetype":"locality"
},
  "geometry": {"coordinates":[120.07804,16.15315],"type":"Point"}
}