{
  "type": "Feature",
  "properties": {
    "iso:country":"PH",
    "name:bcl_x_preferred":[
        "Binidayan"
    ],
    "name:cbk_zam_x_preferred":[
        "Binidayan"
    ],
    "name:ceb_x_preferred":[
        "Binidayan"
    ],
    "name:deu_x_preferred":[
        "Binidayan"
    ],
    "name:dut_x_preferred":[
        "Binidayan"
    ],
    "name:eng_x_preferred":[
        "Binidayan"
    ],
    "name:fre_x_preferred":[
        "Binidayan"
    ],
    "name:ger_x_preferred":[
        "Binidayan"
    ],
    "name:ilo_x_preferred":[
        "Binidayan"
    ],
    "name:ind_x_preferred":[
        "Binidayan"
    ],
    "name:ita_x_preferred":[
        "Binidayan"
    ],
    "name:nld_x_preferred":[
        "Binidayan"
    ],
    "name:pag_x_preferred":[
        "Binidayan"
    ],
    "name:pam_x_preferred":[
        "Binidayan"
    ],
    "name:swe_x_preferred":[
        "Binidayan"
    ],
    "name:tgl_x_preferred":[
        "Binidayan"
    ],
    "name:urd_x_preferred":[
        "\u0628\u06cc\u0646\u06cc\u062f\u0627\u06cc\u0627\u0646\u060c \u0644\u0627\u0646\u0627\u0624 \u062c\u0646\u0648\u0628\u06cc"
    ],
    "name:vie_x_preferred":[
        "Binidayan"
    ],
    "name:war_x_preferred":[
        "Binidayan"
    ],
    "qs:gn_country":"PH",
    "qs:gn_fcode":"PPLA3",
    "qs:gn_pop":3848,
    "qs:name":"Binidayan",
    "qs:name_adm0":"Philippines",
    "qs:name_adm1":"Autonomous Region in Muslim Mindanao",
    "qs:photos":0,
    "qs:photos_1k":0,
    "qs:photos_9k":1,
    "qs:photos_9r":1,
    "qs:photos_all":3,
    "qs:photos_sr":0,
    "qs:placetype":"Town",
    "qs:pop_sr":"4",
    "qs:woe_adm0":23424934,
    "wd:wordcount":129,
    "wof:name":"Binidayan",
    "wof:placetype":"locality",
    "wof:population":3848
},
  "geometry": {"coordinates":[124.16846,7.80668],"type":"Point"}
}