{
  "type": "Feature",
  "properties": {
    "gn:admin1_code":"15",
    "gn:admin2_code":"27",
    "gn:admin3_code":"142705000.0",
    "gn:asciiname":"Malabago",
    "gn:country_code":"PH",
    "gn:dem":226,
    "gn:feature_class":"P",
    "gn:feature_code":"PPL",
    "gn:name":"Malabago",
    "gn:population":0,
    "gn:timezone":"Asia/Manila",
    "iso:country":"PH",
    "name:fil_x_preferred":[
        "Malabago"
    ],
    "wof:name":"Malabago",
    "wof:placetype":"locality"
},
  "geometry": {"coordinates":[121.20744000000001,16.65077],"type":"Point"}
}