{
  "type": "Feature",
  "properties": {
    "gn:admin1_code":"12",
    "gn:admin2_code":"70",
    "gn:admin3_code":"126303000.0",
    "gn:asciiname":"Buayan",
    "gn:country_code":"PH",
    "gn:dem":13,
    "gn:feature_class":"P",
    "gn:feature_code":"PPL",
    "gn:name":"Buayan",
    "gn:population":14607,
    "gn:timezone":"Asia/Manila",
    "iso:country":"PH",
    "name:deu_x_preferred":[
        "Buayan"
    ],
    "name:und_x_variant":[
        "Boayan"
    ],
    "wof:name":"Buayan",
    "wof:placetype":"locality",
    "wof:population":14607
},
  "geometry": {"coordinates":[125.23472,6.11639],"type":"Point"}
}