{
  "type": "Feature",
  "properties": {
    "gn:country":"PH",
    "gn:fcode":"PPL",
    "gn:population":2871,
    "iso:country":"PH",
    "name:fil_x_preferred":[
        "Bugsoc"
    ],
    "qs_pg:aaroncc":"PH",
    "qs_pg:gn_country":"PH",
    "qs_pg:gn_fcode":"PPL",
    "qs_pg:gn_pop":2871,
    "qs_pg:name":"Bugsoc",
    "qs_pg:photos_9r":0,
    "qs_pg:photos_sr":0,
    "qs_pg:pop_sr":4,
    "qs_pg:qs_pg_placetype":"locality",
    "wof:name":"Bugsoc",
    "wof:placetype":"locality",
    "wof:population":2871
},
  "geometry": {"coordinates":[124.27119999999999,9.7834],"type":"Point"}
}