{
  "type": "Feature",
  "properties": {
    "gn:admin1_code":"02",
    "gn:admin2_code":"31",
    "gn:admin3_code":"23127000.0",
    "gn:asciiname":"Dabubu Grande",
    "gn:country_code":"PH",
    "gn:dem":150,
    "gn:feature_class":"P",
    "gn:feature_code":"PPL",
    "gn:name":"Dabubu Grande",
    "gn:population":0,
    "gn:timezone":"Asia/Manila",
    "iso:country":"PH",
    "name:fil_x_preferred":[
        "Dabubu Grande"
    ],
    "wof:name":"Dabubu Grande",
    "wof:placetype":"locality"
},
  "geometry": {"coordinates":[121.78149999999999,16.4446],"type":"Point"}
}