{
  "type": "Feature",
  "properties": {
    "gn:admin1_code":"08",
    "gn:admin2_code":"37",
    "gn:asciiname":"Look",
    "gn:country_code":"PH",
    "gn:dem":1,
    "gn:feature_class":"P",
    "gn:feature_code":"PPL",
    "gn:name":"Look",
    "gn:population":0,
    "gn:timezone":"Asia/Manila",
    "iso:country":"PH",
    "name:deu_x_preferred":[
        "Look"
    ],
    "name:fil_x_preferred":[
        "Look"
    ],
    "name:fra_x_preferred":[
        "Look"
    ],
    "name:ita_x_preferred":[
        "Look"
    ],
    "name:jpn_x_preferred":[
        "\u30eb\u30c3\u30af"
    ],
    "name:nds_x_preferred":[
        "Look"
    ],
    "name:nld_x_preferred":[
        "Look"
    ],
    "name:spa_x_preferred":[
        "Look"
    ],
    "name:swe_x_preferred":[
        "Look"
    ],
    "name:ukr_x_preferred":[
        "Look"
    ],
    "wof:name":"Look",
    "wof:placetype":"locality"
},
  "geometry": {"coordinates":[124.60193999999998,11.55722],"type":"Point"}
}