{
  "type": "Feature",
  "properties": {
    "gn:admin1_code":"05",
    "gn:admin2_code":"15",
    "gn:admin3_code":"51605000.0",
    "gn:asciiname":"Manlutay",
    "gn:country_code":"PH",
    "gn:dem":39,
    "gn:feature_class":"P",
    "gn:feature_code":"PPL",
    "gn:name":"Manlutay",
    "gn:population":0,
    "gn:timezone":"Asia/Manila",
    "iso:country":"PH",
    "name:fil_x_preferred":[
        "Manlutay"
    ],
    "wof:name":"Manlutay",
    "wof:placetype":"locality"
},
  "geometry": {"coordinates":[122.6944,14.2623],"type":"Point"}
}