{
  "type": "Feature",
  "properties": {
    "gn:admin1_code":"05",
    "gn:admin2_code":"58",
    "gn:admin3_code":"56208000.0",
    "gn:asciiname":"Villareal",
    "gn:country_code":"PH",
    "gn:dem":7,
    "gn:feature_class":"P",
    "gn:feature_code":"PPL",
    "gn:name":"Villareal",
    "gn:population":0,
    "gn:timezone":"Asia/Manila",
    "iso:country":"PH",
    "name:fil_x_preferred":[
        "Villareal"
    ],
    "wof:name":"Villareal",
    "wof:placetype":"locality"
},
  "geometry": {"coordinates":[124.13,12.89],"type":"Point"}
}