{
  "type": "Feature",
  "properties": {
    "gn:admin1_code":"41",
    "gn:admin2_code":"49",
    "gn:admin3_code":"175320000.0",
    "gn:asciiname":"Silanga",
    "gn:country_code":"PH",
    "gn:dem":18,
    "gn:feature_class":"P",
    "gn:feature_code":"PPL",
    "gn:name":"Silanga",
    "gn:population":0,
    "gn:timezone":"Asia/Manila",
    "iso:country":"PH",
    "name:eng_x_preferred":[
        "Silanga"
    ],
    "wof:name":"Silanga",
    "wof:placetype":"locality"
},
  "geometry": {"coordinates":[119.5558,11.0378],"type":"Point"}
}