{
  "type": "Feature",
  "properties": {
    "gn:admin1_code":"05",
    "gn:admin2_code":"39",
    "gn:admin3_code":"54103000.0",
    "gn:asciiname":"Guinayangan Diutay",
    "gn:country_code":"PH",
    "gn:dem":15,
    "gn:feature_class":"P",
    "gn:feature_code":"PPL",
    "gn:name":"Guinayangan Diutay",
    "gn:population":0,
    "gn:timezone":"Asia/Manila",
    "iso:country":"PH",
    "name:und_x_variant":[
        "Quinayangan Diutay",
        "Guiniangan Diotay",
        "Quinangan Diotay"
    ],
    "wof:name":"Guinayangan Diutay",
    "wof:placetype":"locality"
},
  "geometry": {"coordinates":[123.23690999999999,11.96786],"type":"Point"}
}