{
  "type": "Feature",
  "properties": {
    "gn:admin1_code":"07",
    "gn:admin2_code":"11",
    "gn:admin3_code":"71205000.0",
    "gn:asciiname":"Payajan",
    "gn:country_code":"PH",
    "gn:dem":101,
    "gn:feature_class":"P",
    "gn:feature_code":"PPL",
    "gn:name":"Payajan",
    "gn:population":0,
    "gn:timezone":"Asia/Manila",
    "iso:country":"PH",
    "name:fil_x_preferred":[
        "Payajan"
    ],
    "wof:name":"Payajan",
    "wof:placetype":"locality"
},
  "geometry": {"coordinates":[123.91249999999999,9.63444],"type":"Point"}
}