{
  "type": "Feature",
  "properties": {
    "gn:admin1_code":"08",
    "gn:admin2_code":"23",
    "gn:admin3_code":"82613000.0",
    "gn:asciiname":"Canliuag",
    "gn:cc2":"PH",
    "gn:country_code":"PH",
    "gn:dem":11,
    "gn:feature_class":"P",
    "gn:feature_code":"PPL",
    "gn:name":"Canliuag",
    "gn:population":0,
    "gn:timezone":"Asia/Manila",
    "iso:country":"PH",
    "name:und_x_variant":[
        "Canlivag",
        "Canliwag",
        "Canliuag"
    ],
    "wof:name":"Canliuag",
    "wof:placetype":"locality"
},
  "geometry": {"coordinates":[125.58222000000001,11.38889],"type":"Point"}
}