{
  "type": "Feature",
  "properties": {
    "gn:country":"PH",
    "gn:fcode":"PPL",
    "gn:population":2323,
    "iso:country":"PH",
    "name:fil_x_preferred":[
        "Maxingul"
    ],
    "name:fil_x_variant":[
        "Maxingal"
    ],
    "qs_pg:aaroncc":"PH",
    "qs_pg:gn_country":"PH",
    "qs_pg:gn_fcode":"PPL",
    "qs_pg:gn_pop":2323,
    "qs_pg:name":"Maxingal",
    "qs_pg:photos_9r":0,
    "qs_pg:photos_sr":0,
    "qs_pg:pop_sr":4,
    "qs_pg:qs_pg_placetype":"locality",
    "wof:name":"Maxingal",
    "wof:placetype":"locality",
    "wof:population":2323
},
  "geometry": {"coordinates":[121.66815,18.21488],"type":"Point"}
}