{
  "type": "Feature",
  "properties": {
    "gn:admin1_code":"15",
    "gn:admin2_code":"01",
    "gn:admin3_code":"140115000.0",
    "gn:asciiname":"Bayabas",
    "gn:country_code":"PH",
    "gn:dem":650,
    "gn:feature_class":"P",
    "gn:feature_code":"PPL",
    "gn:name":"Bayabas",
    "gn:population":0,
    "gn:timezone":"Asia/Manila",
    "iso:country":"PH",
    "name:fil_x_preferred":[
        "Bayabas"
    ],
    "name:war_x_preferred":[
        "Bayabas"
    ],
    "wof:name":"Bayabas",
    "wof:placetype":"locality"
},
  "geometry": {"coordinates":[120.96666999999999,17.61667000000001],"type":"Point"}
}