{
  "type": "Feature",
  "properties": {
    "gn:admin1_code":"02",
    "gn:admin2_code":"31",
    "gn:admin3_code":"23112000.0",
    "gn:asciiname":"Reserva",
    "gn:country_code":"PH",
    "gn:dem":84,
    "gn:feature_class":"P",
    "gn:feature_code":"PPL",
    "gn:name":"Reserva",
    "gn:population":0,
    "gn:timezone":"Asia/Manila",
    "iso:country":"PH",
    "name:fil_x_preferred":[
        "Reserva"
    ],
    "wof:name":"Reserva",
    "wof:placetype":"locality"
},
  "geometry": {"coordinates":[121.67749999999999,16.6823],"type":"Point"}
}