{
  "type": "Feature",
  "properties": {
    "gn:admin1_code":"01",
    "gn:admin2_code":"28",
    "gn:admin3_code":"12816000.0",
    "gn:asciiname":"Masintoc",
    "gn:country_code":"PH",
    "gn:dem":9,
    "gn:feature_class":"P",
    "gn:feature_code":"PPL",
    "gn:name":"Masintoc",
    "gn:population":0,
    "gn:timezone":"Asia/Manila",
    "iso:country":"PH",
    "name:fil_x_preferred":[
        "Masintoc"
    ],
    "name:fil_x_variant":[
        "Nagcurata"
    ],
    "wof:name":"Masintoc",
    "wof:placetype":"locality"
},
  "geometry": {"coordinates":[120.48569999999999,18.0777],"type":"Point"}
}