{
  "type": "Feature",
  "properties": {
    "gn:admin1_code":"05",
    "gn:admin2_code":"39",
    "gn:admin3_code":"54108000.0",
    "gn:asciiname":"Calabad",
    "gn:country_code":"PH",
    "gn:dem":146,
    "gn:feature_class":"P",
    "gn:feature_code":"PPL",
    "gn:name":"Calabad",
    "gn:population":0,
    "gn:timezone":"Asia/Manila",
    "iso:country":"PH",
    "name:fil_x_preferred":[
        "Calabad"
    ],
    "wof:name":"Calabad",
    "wof:placetype":"locality"
},
  "geometry": {"coordinates":[123.8552,12.1752],"type":"Point"}
}