{
  "type": "Feature",
  "properties": {
    "gn:admin1_code":"08",
    "gn:admin2_code":"55",
    "gn:admin3_code":"86022000.0",
    "gn:asciiname":"Paranas",
    "gn:country_code":"PH",
    "gn:dem":152,
    "gn:feature_class":"P",
    "gn:feature_code":"PPLA3",
    "gn:name":"Paranas",
    "gn:population":0,
    "gn:timezone":"Asia/Manila",
    "iso:country":"PH",
    "wof:name":"Paranas",
    "wof:placetype":"locality"
},
  "geometry": {"coordinates":[125.11530999999999,11.85022],"type":"Point"}
}