{
  "type": "Feature",
  "properties": {
    "gn:admin1_code":"03",
    "gn:admin2_code":"63",
    "gn:admin3_code":"36903000.0",
    "gn:asciiname":"Caarosipan-Palimbo",
    "gn:country_code":"PH",
    "gn:dem":28,
    "gn:feature_class":"P",
    "gn:feature_code":"PPL",
    "gn:name":"Caarosipan-Palimbo",
    "gn:population":0,
    "gn:timezone":"Asia/Manila",
    "iso:country":"PH",
    "name:fil_x_preferred":[
        "Caarosipan-Palimbo"
    ],
    "wof:name":"Caarosipan-Palimbo",
    "wof:placetype":"locality"
},
  "geometry": {"coordinates":[120.41667,15.68333],"type":"Point"}
}