{
  "type": "Feature",
  "properties": {
    "gn:admin1_code":"05",
    "gn:admin2_code":"16",
    "gn:admin3_code":"51711000.0",
    "gn:asciiname":"Mapueda",
    "gn:country_code":"PH",
    "gn:dem":7,
    "gn:feature_class":"P",
    "gn:feature_code":"PPL",
    "gn:name":"Mapueda",
    "gn:population":0,
    "gn:timezone":"Asia/Manila",
    "iso:country":"PH",
    "name:fil_x_preferred":[
        "Mapueda"
    ],
    "name:und_x_variant":[
        "Maqueda"
    ],
    "wof:name":"Mapueda",
    "wof:placetype":"locality"
},
  "geometry": {"coordinates":[123.837,13.8206],"type":"Point"}
}