{
  "type": "Feature",
  "properties": {
    "gn:admin1_code":"01",
    "gn:admin2_code":"51",
    "gn:admin3_code":"15529000.0",
    "gn:asciiname":"Batchelor East",
    "gn:country_code":"PH",
    "gn:dem":122,
    "gn:feature_class":"P",
    "gn:feature_code":"PPL",
    "gn:name":"Batchelor East",
    "gn:population":0,
    "gn:timezone":"Asia/Manila",
    "iso:country":"PH",
    "name:eng_x_preferred":[
        "Batchelor East"
    ],
    "wof:name":"Batchelor East",
    "wof:placetype":"locality"
},
  "geometry": {"coordinates":[120.81489999999999,16.05],"type":"Point"}
}