{
  "type": "Feature",
  "properties": {
    "gn:admin1_code":"15",
    "gn:admin2_code":"10",
    "gn:admin3_code":"141110000.0",
    "gn:asciiname":"Tyan",
    "gn:country_code":"PH",
    "gn:dem":1252,
    "gn:feature_class":"P",
    "gn:feature_code":"PPL",
    "gn:name":"Tyan",
    "gn:population":0,
    "gn:timezone":"Asia/Manila",
    "iso:country":"PH",
    "name:ces_x_preferred":[
        "Tyan"
    ],
    "name:fil_x_preferred":[
        "Tyan"
    ],
    "name:fra_x_preferred":[
        "Tyan"
    ],
    "name:pol_x_preferred":[
        "Tyan"
    ],
    "name:por_x_preferred":[
        "Tyan"
    ],
    "name:rus_x_preferred":[
        "Tyan"
    ],
    "name:zho_x_preferred":[
        "\u6cf0\u5b89\u96fb\u8166"
    ],
    "wof:name":"Tyan",
    "wof:placetype":"locality"
},
  "geometry": {"coordinates":[120.63329,16.45907],"type":"Point"}
}