{
  "type": "Feature",
  "properties": {
    "iso:country":"PH",
    "name:eng_x_preferred":[
        "Araceli"
    ],
    "name:unk_x_variant":[
        "Dumaran"
    ],
    "qs:gn_country":"PH",
    "qs:gn_fcode":"PPL",
    "qs:gn_pop":3111,
    "qs:name":"Araceli",
    "qs:name_adm0":"Philippines",
    "qs:name_adm1":"Western Visayas",
    "qs:photos":0,
    "qs:photos_1k":0,
    "qs:photos_9k":0,
    "qs:photos_9r":0,
    "qs:photos_all":0,
    "qs:photos_sr":0,
    "qs:placetype":"Town",
    "qs:pop_sr":"4",
    "qs:woe_adm0":23424934,
    "wof:name":"Araceli",
    "wof:placetype":"locality",
    "wof:population":3111
},
  "geometry": {"coordinates":[119.9913,10.5529],"type":"Point"}
}