{
  "type": "Feature",
  "properties": {
    "gn:admin1_code":"01",
    "gn:admin2_code":"51",
    "gn:admin3_code":"15539000.0",
    "gn:asciiname":"Pilar",
    "gn:country_code":"PH",
    "gn:dem":39,
    "gn:feature_class":"P",
    "gn:feature_code":"PPL",
    "gn:name":"Pilar",
    "gn:population":0,
    "gn:timezone":"Asia/Manila",
    "iso:country":"PH",
    "name:fil_x_preferred":[
        "Pilar"
    ],
    "wof:name":"Pilar",
    "wof:placetype":"locality"
},
  "geometry": {"coordinates":[120.65712000000001,15.94552],"type":"Point"}
}