{
  "type": "Feature",
  "properties": {
    "gn:admin1_code":"05",
    "gn:admin2_code":"39",
    "gn:admin3_code":"54111000.0",
    "gn:asciiname":"Quinamaligan",
    "gn:country_code":"PH",
    "gn:dem":15,
    "gn:feature_class":"P",
    "gn:feature_code":"PPL",
    "gn:name":"Quinamaligan",
    "gn:population":0,
    "gn:timezone":"Asia/Manila",
    "iso:country":"PH",
    "name:fil_x_preferred":[
        "Quinamaligan"
    ],
    "name:und_x_variant":[
        "Kinamaligan"
    ],
    "wof:name":"Quinamaligan",
    "wof:placetype":"locality"
},
  "geometry": {"coordinates":[123.6263,12.3628],"type":"Point"}
}