{
  "type": "Feature",
  "properties": {
    "gn:admin1_code":"09",
    "gn:admin2_code":"65",
    "gn:admin3_code":"97220000.0",
    "gn:asciiname":"Macuyon",
    "gn:cc2":"PH",
    "gn:country_code":"PH",
    "gn:dem":24,
    "gn:feature_class":"P",
    "gn:feature_code":"PPL",
    "gn:name":"Macuyon",
    "gn:population":0,
    "gn:timezone":"Asia/Manila",
    "iso:country":"PH",
    "name:und_x_variant":[
        "Makuyana",
        "Macuyon"
    ],
    "wof:name":"Macuyon",
    "wof:placetype":"locality"
},
  "geometry": {"coordinates":[122.12194,7.58889],"type":"Point"}
}