{
  "type": "Feature",
  "properties": {
    "gn:admin1_code":"06",
    "gn:admin2_code":"06",
    "gn:admin3_code":"60607000.0",
    "gn:asciiname":"Igtugas",
    "gn:country_code":"PH",
    "gn:dem":143,
    "gn:feature_class":"P",
    "gn:feature_code":"PPL",
    "gn:name":"Igtugas",
    "gn:population":0,
    "gn:timezone":"Asia/Manila",
    "iso:country":"PH",
    "name:fil_x_preferred":[
        "Igtugas"
    ],
    "name:und_x_variant":[
        "Igtugas South"
    ],
    "wof:name":"Igtugas",
    "wof:placetype":"locality"
},
  "geometry": {"coordinates":[121.9943,10.5546],"type":"Point"}
}