{
  "type": "Feature",
  "properties": {
    "gn:admin1_code":"40",
    "gn:admin2_code":"20",
    "gn:admin3_code":"42121000.0",
    "gn:asciiname":"Zapang",
    "gn:country_code":"PH",
    "gn:dem":12,
    "gn:feature_class":"P",
    "gn:feature_code":"PPL",
    "gn:name":"Zapang",
    "gn:population":0,
    "gn:timezone":"Asia/Manila",
    "iso:country":"PH",
    "name:eng_x_preferred":[
        "Bucana Sapang"
    ],
    "name:fil_x_preferred":[
        "Zapang"
    ],
    "name:und_x_variant":[
        "Bucana Sapang",
        "Zapang"
    ],
    "wof:name":"Zapang",
    "wof:placetype":"locality"
},
  "geometry": {"coordinates":[120.7119,14.2841],"type":"Point"}
}