{
  "type": "Feature",
  "properties": {
    "gn:admin1_code":"14",
    "gn:admin2_code":"35",
    "gn:admin3_code":"153636000.0",
    "gn:asciiname":"Yalamay",
    "gn:country_code":"PH",
    "gn:dem":799,
    "gn:feature_class":"P",
    "gn:feature_code":"PPL",
    "gn:name":"Yalamay",
    "gn:population":0,
    "gn:timezone":"Asia/Manila",
    "iso:country":"PH",
    "name:fil_x_preferred":[
        "Yalamay"
    ],
    "wof:name":"Yalamay",
    "wof:placetype":"locality"
},
  "geometry": {"coordinates":[124.31667,7.78333],"type":"Point"}
}