{
  "type": "Feature",
  "properties": {
    "gn:admin1_code":"06",
    "gn:admin2_code":"06",
    "gn:admin3_code":"60612000.0",
    "gn:asciiname":"Macarena",
    "gn:country_code":"PH",
    "gn:dem":48,
    "gn:feature_class":"P",
    "gn:feature_code":"PPL",
    "gn:name":"Macarena",
    "gn:population":0,
    "gn:timezone":"Asia/Manila",
    "iso:country":"PH",
    "name:deu_x_preferred":[
        "Macarena"
    ],
    "name:fil_x_preferred":[
        "Macarena"
    ],
    "name:fra_x_preferred":[
        "La Macarena"
    ],
    "name:ita_x_preferred":[
        "Macarena"
    ],
    "name:jpn_x_preferred":[
        "\u30de\u30ab\u30ec\u30ca"
    ],
    "name:kor_x_preferred":[
        "\ub9c8\uce74\ub808\ub098"
    ],
    "name:nld_x_preferred":[
        "Macarena"
    ],
    "name:spa_x_preferred":[
        "Macarena"
    ],
    "name:swe_x_preferred":[
        "Macarena"
    ],
    "name:und_x_variant":[
        "Macarina"
    ],
    "name:zho_x_preferred":[
        "\u99ac\u5361\u96f7\u7d0d"
    ],
    "wof:name":"Macarena",
    "wof:placetype":"locality"
},
  "geometry": {"coordinates":[122.0278,10.9322],"type":"Point"}
}