{
  "type": "Feature",
  "properties": {
    "gn:admin1_code":"14",
    "gn:admin2_code":"35",
    "gn:admin3_code":"153635000.0",
    "gn:asciiname":"Subuan",
    "gn:country_code":"PH",
    "gn:dem":39,
    "gn:feature_class":"P",
    "gn:feature_code":"PPL",
    "gn:name":"Subuan",
    "gn:population":0,
    "gn:timezone":"Asia/Manila",
    "iso:country":"PH",
    "name:eng_x_preferred":[
        "Subuan"
    ],
    "wof:name":"Subuan",
    "wof:placetype":"locality"
},
  "geometry": {"coordinates":[123.931,7.7067],"type":"Point"}
}