{
  "type": "Feature",
  "properties": {
    "gn:admin1_code":"06",
    "gn:admin2_code":"04",
    "gn:admin3_code":"60404000.0",
    "gn:asciiname":"Tigbao",
    "gn:country_code":"PH",
    "gn:dem":16,
    "gn:feature_class":"P",
    "gn:feature_code":"PPL",
    "gn:name":"Tigbao",
    "gn:population":0,
    "gn:timezone":"Asia/Manila",
    "iso:country":"PH",
    "name:ceb_x_preferred":[
        "Tigbao"
    ],
    "name:fil_x_preferred":[
        "Tigbao"
    ],
    "wof:name":"Tigbao",
    "wof:placetype":"locality"
},
  "geometry": {"coordinates":[122.41719999999999,11.5697],"type":"Point"}
}