{
  "type": "Feature",
  "properties": {
    "gn:admin1_code":"08",
    "gn:admin2_code":"37",
    "gn:asciiname":"Maljo",
    "gn:country_code":"PH",
    "gn:dem":5,
    "gn:feature_class":"P",
    "gn:feature_code":"PPL",
    "gn:name":"Maljo",
    "gn:population":0,
    "gn:timezone":"Asia/Manila",
    "iso:country":"PH",
    "name:fil_x_preferred":[
        "Maljo"
    ],
    "wof:name":"Maljo",
    "wof:placetype":"locality"
},
  "geometry": {"coordinates":[124.75239999999999,10.5108],"type":"Point"}
}