{
  "type": "Feature",
  "properties": {
    "gn:admin1_code":"08",
    "gn:admin2_code":"55",
    "gn:admin3_code":"86007000.0",
    "gn:asciiname":"San Miguel",
    "gn:country_code":"PH",
    "gn:dem":9,
    "gn:feature_class":"P",
    "gn:feature_code":"PPL",
    "gn:name":"San Miguel",
    "gn:population":0,
    "gn:timezone":"Asia/Manila",
    "iso:country":"PH",
    "name:ara_x_preferred":[
        "\u0633\u0627\u0646 \u0645\u064a\u063a\u064a\u0644"
    ],
    "name:ben_x_preferred":[
        "\u09b8\u09be\u09a8 \u09ae\u09bf\u0997\u09c1\u09af\u09bc\u09c7\u09b2"
    ],
    "name:deu_x_preferred":[
        "San Miguel River"
    ],
    "name:ell_x_preferred":[
        "\u03a3\u03b1\u03bd \u039c\u03b9\u03b3\u03ba\u03ad\u03bb"
    ],
    "name:eng_x_preferred":[
        "San Miguel River"
    ],
    "name:fas_x_preferred":[
        "\u0633\u0627\u0646 \u0645\u06cc\u06af\u0648\u0626\u0644"
    ],
    "name:fil_x_preferred":[
        "San Miguel"
    ],
    "name:fra_x_preferred":[
        "San Miguel"
    ],
    "name:heb_x_preferred":[
        "\u05e1\u05df \u05de\u05d9\u05d2\u05dc"
    ],
    "name:hin_x_preferred":[
        "\u0938\u0948\u0928 \u092e\u093f\u0917\u0941\u090f\u0932"
    ],
    "name:hun_x_preferred":[
        "San Miguel"
    ],
    "name:ind_x_preferred":[
        "San Miguel"
    ],
    "name:ita_x_preferred":[
        "San Miguel"
    ],
    "name:jpn_x_preferred":[
        "\u30b5\u30f3\u30df\u30b2\u30eb\u5ddd"
    ],
    "name:kor_x_preferred":[
        "\uc0b0 \ubbf8\uad6c\uc5d8"
    ],
    "name:nld_x_preferred":[
        "San Miguel"
    ],
    "name:pol_x_preferred":[
        "San Miguel"
    ],
    "name:por_x_preferred":[
        "San Miguel"
    ],
    "name:rus_x_preferred":[
        "\u0440\u0435\u043a\u0430 \u0420\u0438\u043e-\u0421\u0430\u043d-\u041c\u0438\u0433\u0435\u043b\u044c"
    ],
    "name:spa_x_preferred":[
        "San Miguel"
    ],
    "name:swe_x_preferred":[
        "R\u00edo San Miguel"
    ],
    "name:tur_x_preferred":[
        "San Miguel"
    ],
    "name:ukr_x_preferred":[
        "\u0421\u0430\u043d-\u041c\u0456\u0433\u0435\u043b\u044c"
    ],
    "name:urd_x_preferred":[
        "\u0633\u0627\u0646 \u0645\u06cc\u06af\u0648\u0626\u0644"
    ],
    "name:vie_x_preferred":[
        "S\u00f4ng San Miguel"
    ],
    "name:zho_cn_x_preferred":[
        "\u5723\u7c73\u683c\u5c14\u6cb3"
    ],
    "name:zho_tw_x_preferred":[
        "\u8056\u7c73\u683c\u723e\u6cb3"
    ],
    "wof:name":"San Miguel",
    "wof:placetype":"locality"
},
  "geometry": {"coordinates":[124.8242,12.0042],"type":"Point"}
}