{
  "type": "Feature",
  "properties": {
    "gn:admin1_code":"06",
    "gn:admin2_code":"H3",
    "gn:admin3_code":"64531000.0",
    "gn:asciiname":"Ideal",
    "gn:country_code":"PH",
    "gn:dem":9,
    "gn:feature_class":"P",
    "gn:feature_code":"PPL",
    "gn:name":"Ideal",
    "gn:population":0,
    "gn:timezone":"Asia/Manila",
    "iso:country":"PH",
    "name:fil_x_preferred":[
        "Ideal"
    ],
    "wof:name":"Ideal",
    "wof:placetype":"locality"
},
  "geometry": {"coordinates":[123.045,10.89274],"type":"Point"}
}