{
  "type": "Feature",
  "properties": {
    "gn:admin1_code":"09",
    "gn:admin2_code":"66",
    "gn:admin3_code":"97306000.0",
    "gn:asciiname":"Legarda 2",
    "gn:country_code":"PH",
    "gn:dem":224,
    "gn:feature_class":"P",
    "gn:feature_code":"PPL",
    "gn:name":"Legarda 2",
    "gn:population":0,
    "gn:timezone":"Asia/Manila",
    "iso:country":"PH",
    "wof:name":"Legarda 2",
    "wof:placetype":"locality"
},
  "geometry": {"coordinates":[123.29611,7.63611],"type":"Point"}
}