{
  "type": "Feature",
  "properties": {
    "gn:country":"PH",
    "gn:fcode":"ADM3",
    "gn:pop":26402,
    "iso:country":"PH",
    "name:eng_x_preferred":[
        "Municipality of Lapuyan"
    ],
    "name:unk_x_variant":[
        "Lapuyan"
    ],
    "qs:name":"Municipality of Lapuyan",
    "qs:photos_9r":0,
    "qs:photos_sr":0,
    "qs:pop_sr":"7",
    "wd:wordcount":355,
    "wof:name":"Municipality of Lapuyan",
    "wof:placetype":"localadmin",
    "wof:population":26402
},
  "geometry": {"coordinates":[123.20059999999999,7.6862],"type":"Point"}
}