{
  "type": "Feature",
  "properties": {
    "gn:country":"PH",
    "gn:fcode":"ADM3",
    "gn:population":26402,
    "iso:country":"PH",
    "name:bcl_x_preferred":[
        "Lakewood"
    ],
    "name:ceb_x_preferred":[
        "Lakewood"
    ],
    "name:deu_x_preferred":[
        "Lakewood"
    ],
    "name:eng_x_preferred":[
        "Municipality of Lapuyan"
    ],
    "name:eng_x_variant":[
        "Lakewood"
    ],
    "name:fra_x_preferred":[
        "Lakewood"
    ],
    "name:ilo_x_preferred":[
        "Lakewood"
    ],
    "name:ind_x_preferred":[
        "Lakewood"
    ],
    "name:ita_x_preferred":[
        "Lakewood"
    ],
    "name:nld_x_preferred":[
        "Lakewood"
    ],
    "name:pag_x_preferred":[
        "Lakewood"
    ],
    "name:pam_x_preferred":[
        "Lakewood"
    ],
    "name:swe_x_preferred":[
        "Lakewood"
    ],
    "name:tgl_x_preferred":[
        "Lakewood"
    ],
    "name:und_x_variant":[
        "Lapuyan"
    ],
    "name:urd_x_preferred":[
        "\u0644\u06cc\u06a9 \u0648\u0648\u0688"
    ],
    "name:vie_x_preferred":[
        "Lakewood"
    ],
    "name:war_x_preferred":[
        "Lakewood"
    ],
    "qs:name":"Municipality of Lapuyan",
    "qs:photos_9r":0,
    "qs:photos_sr":0,
    "qs:pop_sr":"7",
    "wd:wordcount":355,
    "wof:name":"Municipality of Lapuyan",
    "wof:placetype":"localadmin",
    "wof:population":26402
},
  "geometry": {"coordinates":[123.20059999999999,7.6862],"type":"Point"}
}