{
  "type": "Feature",
  "properties": {
    "gn:admin1_code":"03",
    "gn:admin2_code":"50",
    "gn:admin3_code":"35403000.0",
    "gn:asciiname":"Cupang",
    "gn:country_code":"PH",
    "gn:dem":13,
    "gn:feature_class":"P",
    "gn:feature_code":"PPL",
    "gn:name":"Cupang",
    "gn:population":0,
    "gn:timezone":"Asia/Manila",
    "iso:country":"PH",
    "name:fil_x_preferred":[
        "Cupang"
    ],
    "wof:name":"Cupang",
    "wof:placetype":"locality"
},
  "geometry": {"coordinates":[120.7851,15.1361],"type":"Point"}
}