{
  "type": "Feature",
  "properties": {
    "gn:admin1_code":"03",
    "gn:admin2_code":"64",
    "gn:admin3_code":"37103000.0",
    "gn:asciiname":"Lauis",
    "gn:country_code":"PH",
    "gn:dem":18,
    "gn:feature_class":"P",
    "gn:feature_code":"PPL",
    "gn:name":"Lauis",
    "gn:population":0,
    "gn:timezone":"Asia/Manila",
    "iso:country":"PH",
    "name:fil_x_preferred":[
        "Lauis"
    ],
    "name:und_x_variant":[
        "Lawis"
    ],
    "wof:name":"Lauis",
    "wof:placetype":"locality"
},
  "geometry": {"coordinates":[119.9425,15.6003],"type":"Point"}
}