{
  "type": "Feature",
  "properties": {
    "gn:admin1_code":"41",
    "gn:admin2_code":"49",
    "gn:admin3_code":"175320000.0",
    "gn:asciiname":"Batas",
    "gn:country_code":"PH",
    "gn:dem":53,
    "gn:feature_class":"P",
    "gn:feature_code":"PPL",
    "gn:name":"Batas",
    "gn:population":0,
    "gn:timezone":"Asia/Manila",
    "iso:country":"PH",
    "name:eng_x_preferred":[
        "Bates"
    ],
    "name:und_x_variant":[
        "Estar",
        "Batas"
    ],
    "wof:name":"Batas",
    "wof:placetype":"locality"
},
  "geometry": {"coordinates":[119.60841000000001,11.16135],"type":"Point"}
}