{
  "type": "Feature",
  "properties": {
    "gn:admin1_code":"03",
    "gn:admin2_code":"64",
    "gn:admin3_code":"37111000.0",
    "gn:asciiname":"Nagbunga",
    "gn:country_code":"PH",
    "gn:dem":49,
    "gn:feature_class":"P",
    "gn:feature_code":"PPL",
    "gn:name":"Nagbunga",
    "gn:population":0,
    "gn:timezone":"Asia/Manila",
    "iso:country":"PH",
    "name:fil_x_preferred":[
        "Nagbunga"
    ],
    "name:und_x_variant":[
        "Nabunga"
    ],
    "wof:name":"Nagbunga",
    "wof:placetype":"locality"
},
  "geometry": {"coordinates":[120.17503000000001,14.95449],"type":"Point"}
}