{
  "type": "Feature",
  "properties": {
    "gn:admin1_code":"01",
    "gn:admin2_code":"28",
    "gn:admin3_code":"12805000.0",
    "gn:asciiname":"Babaculen",
    "gn:country_code":"PH",
    "gn:dem":54,
    "gn:feature_class":"P",
    "gn:feature_code":"PPL",
    "gn:name":"Babaculen",
    "gn:population":0,
    "gn:timezone":"Asia/Manila",
    "iso:country":"PH",
    "name:fil_x_preferred":[
        "Babaculen"
    ],
    "wof:name":"Babaculen",
    "wof:placetype":"locality"
},
  "geometry": {"coordinates":[120.6003,18.0783],"type":"Point"}
}