{
  "type": "Feature",
  "properties": {
    "gn:admin1_code":"05",
    "gn:admin2_code":"16",
    "gn:admin3_code":"51723000.0",
    "gn:asciiname":"Duran Nierva",
    "gn:country_code":"PH",
    "gn:dem":49,
    "gn:feature_class":"P",
    "gn:feature_code":"PPL",
    "gn:name":"Duran Nierva",
    "gn:population":0,
    "gn:timezone":"Asia/Manila",
    "iso:country":"PH",
    "name:fil_x_preferred":[
        "Duran Nierva"
    ],
    "wof:name":"Duran Nierva",
    "wof:placetype":"locality"
},
  "geometry": {"coordinates":[123.28870000000001,13.3872],"type":"Point"}
}