{
  "type": "Feature",
  "properties": {
    "gn:admin1_code":"01",
    "gn:admin2_code":"51",
    "gn:admin3_code":"15522000.0",
    "gn:asciiname":"Balococ",
    "gn:country_code":"PH",
    "gn:dem":8,
    "gn:feature_class":"P",
    "gn:feature_code":"PPL",
    "gn:name":"Balococ",
    "gn:population":0,
    "gn:timezone":"Asia/Manila",
    "iso:country":"PH",
    "name:fil_x_preferred":[
        "Balococ"
    ],
    "name:und_x_variant":[
        "Baloboc"
    ],
    "wof:name":"Balococ",
    "wof:placetype":"locality"
},
  "geometry": {"coordinates":[120.22539999999999,15.9971],"type":"Point"}
}