{
  "type": "Feature",
  "properties": {
    "gn:admin1_code":"03",
    "gn:admin2_code":"13",
    "gn:admin3_code":"31413000.0",
    "gn:asciiname":"Kay Luya",
    "gn:country_code":"PH",
    "gn:dem":163,
    "gn:feature_class":"P",
    "gn:feature_code":"PPL",
    "gn:name":"Kay Luya",
    "gn:population":0,
    "gn:timezone":"Asia/Manila",
    "iso:country":"PH",
    "name:fil_x_preferred":[
        "Kay Luya"
    ],
    "wof:name":"Kay Luya",
    "wof:placetype":"locality"
},
  "geometry": {"coordinates":[121.1341,14.8372],"type":"Point"}
}