{
  "type": "Feature",
  "properties": {
    "iso:country":"PH",
    "name:fil_x_preferred":[
        "Tigui"
    ],
    "name:fil_x_variant":[
        "Tigwi",
        "Tiguion",
        "Tigiui"
    ],
    "name:unk_x_variant":[
        "Tigiui"
    ],
    "qs:gn_country":"PH",
    "qs:gn_fcode":"PPL",
    "qs:gn_pop":2543,
    "qs:name":"Tigwi",
    "qs:name_adm0":"Philippines",
    "qs:name_adm1":"Mimaropa",
    "qs:photos":0,
    "qs:photos_1k":0,
    "qs:photos_9k":1,
    "qs:photos_9r":1,
    "qs:photos_all":3,
    "qs:photos_sr":0,
    "qs:placetype":"Town",
    "qs:pop_sr":"4",
    "qs:woe_adm0":23424934,
    "wof:name":"Tigwi",
    "wof:placetype":"locality",
    "wof:population":2543
},
  "geometry": {"coordinates":[122.0415,13.2681],"type":"Point"}
}