{
  "type": "Feature",
  "properties": {
    "gn:admin1_code":"05",
    "gn:admin2_code":"05",
    "gn:admin3_code":"50501000.0",
    "gn:asciiname":"Napao",
    "gn:country_code":"PH",
    "gn:dem":91,
    "gn:feature_class":"P",
    "gn:feature_code":"PPL",
    "gn:name":"Napao",
    "gn:population":0,
    "gn:timezone":"Asia/Manila",
    "iso:country":"PH",
    "name:fil_x_preferred":[
        "Napao"
    ],
    "wof:name":"Napao",
    "wof:placetype":"locality"
},
  "geometry": {"coordinates":[123.86320000000001,13.321],"type":"Point"}
}