{
  "type": "Feature",
  "properties": {
    "gn:admin1_code":"07",
    "gn:admin2_code":"69",
    "gn:admin3_code":"76101000.0",
    "gn:asciiname":"Bolot",
    "gn:country_code":"PH",
    "gn:dem":153,
    "gn:feature_class":"P",
    "gn:feature_code":"PPL",
    "gn:name":"Bolot",
    "gn:population":0,
    "gn:timezone":"Asia/Manila",
    "iso:country":"PH",
    "name:fil_x_preferred":[
        "Bolot"
    ],
    "wof:name":"Bolot",
    "wof:placetype":"locality"
},
  "geometry": {"coordinates":[123.63333,9.26667],"type":"Point"}
}