{
  "type": "Feature",
  "properties": {
    "gn:admin1_code":"10",
    "gn:admin2_code":"42",
    "gn:admin3_code":"104204000.0",
    "gn:asciiname":"Dupacan",
    "gn:country_code":"PH",
    "gn:dem":116,
    "gn:feature_class":"P",
    "gn:feature_code":"PPL",
    "gn:name":"Dupacan",
    "gn:population":0,
    "gn:timezone":"Asia/Manila",
    "iso:country":"PH",
    "name:eng_x_preferred":[
        "Dupacan"
    ],
    "wof:name":"Dupacan",
    "wof:placetype":"locality"
},
  "geometry": {"coordinates":[123.6266,8.5464],"type":"Point"}
}