{
  "type": "Feature",
  "properties": {
    "gn:admin1_code":"15",
    "gn:admin2_code":"01",
    "gn:admin3_code":"140111000.0",
    "gn:asciiname":"Kiwas",
    "gn:country_code":"PH",
    "gn:dem":138,
    "gn:feature_class":"P",
    "gn:feature_code":"PPL",
    "gn:name":"Kiwas",
    "gn:population":0,
    "gn:timezone":"Asia/Manila",
    "iso:country":"PH",
    "name:fil_x_preferred":[
        "Kiwas"
    ],
    "wof:name":"Kiwas",
    "wof:placetype":"locality"
},
  "geometry": {"coordinates":[120.7097,17.7383],"type":"Point"}
}