{
  "type": "Feature",
  "properties": {
    "gn:admin1_code":"03",
    "gn:admin2_code":"13",
    "gn:admin3_code":"31410000.0",
    "gn:asciiname":"Barihan",
    "gn:country_code":"PH",
    "gn:dem":12,
    "gn:feature_class":"P",
    "gn:feature_code":"PPL",
    "gn:name":"Barihan",
    "gn:population":0,
    "gn:timezone":"Asia/Manila",
    "iso:country":"PH",
    "name:fil_x_preferred":[
        "Barihan"
    ],
    "wof:name":"Barihan",
    "wof:placetype":"locality"
},
  "geometry": {"coordinates":[120.82914,14.87818],"type":"Point"}
}