{
  "type": "Feature",
  "properties": {
    "gn:admin1_code":"07",
    "gn:admin2_code":"46",
    "gn:admin3_code":"74606000.0",
    "gn:asciiname":"Canallum",
    "gn:country_code":"PH",
    "gn:dem":13,
    "gn:feature_class":"P",
    "gn:feature_code":"PPL",
    "gn:name":"Canallum",
    "gn:population":0,
    "gn:timezone":"Asia/Manila",
    "iso:country":"PH",
    "name:fil_x_preferred":[
        "Canallum"
    ],
    "wof:name":"Canallum",
    "wof:placetype":"locality"
},
  "geometry": {"coordinates":[122.81910000000001,9.3884],"type":"Point"}
}