{
  "type": "Feature",
  "properties": {
    "gn:admin1_code":"40",
    "gn:admin2_code":"09",
    "gn:admin3_code":"41012000.0",
    "gn:asciiname":"Tabla",
    "gn:country_code":"PH",
    "gn:dem":406,
    "gn:feature_class":"P",
    "gn:feature_code":"PPL",
    "gn:name":"Tabla",
    "gn:population":0,
    "gn:timezone":"Asia/Manila",
    "iso:country":"PH",
    "name:fil_x_preferred":[
        "Tabla"
    ],
    "wof:name":"Tabla",
    "wof:placetype":"locality"
},
  "geometry": {"coordinates":[120.87523,14.02545],"type":"Point"}
}