{
  "type": "Feature",
  "properties": {
    "gn:admin1_code":"09",
    "gn:admin2_code":"ZSI",
    "gn:admin3_code":"98304000.0",
    "gn:asciiname":"Canaan",
    "gn:country_code":"PH",
    "gn:dem":190,
    "gn:feature_class":"P",
    "gn:feature_code":"PPL",
    "gn:name":"Canaan",
    "gn:population":0,
    "gn:timezone":"Asia/Manila",
    "iso:country":"PH",
    "name:fil_x_preferred":[
        "Canaan"
    ],
    "wof:name":"Canaan",
    "wof:placetype":"locality"
},
  "geometry": {"coordinates":[122.95332999999999,7.61139],"type":"Point"}
}