{
  "type": "Feature",
  "properties": {
    "gn:admin1_code":"41",
    "gn:admin2_code":"41",
    "gn:admin3_code":"175208000.0",
    "gn:asciiname":"Casilihan",
    "gn:country_code":"PH",
    "gn:dem":14,
    "gn:feature_class":"P",
    "gn:feature_code":"PPL",
    "gn:name":"Casilihan",
    "gn:population":0,
    "gn:timezone":"Asia/Manila",
    "iso:country":"PH",
    "name:fil_x_preferred":[
        "Casilihan"
    ],
    "wof:name":"Casilihan",
    "wof:placetype":"locality"
},
  "geometry": {"coordinates":[121.30802,13.26069],"type":"Point"}
}