{
  "type": "Feature",
  "properties": {
    "gn:admin1_code":"12",
    "gn:admin2_code":"71",
    "gn:admin3_code":"126505000.0",
    "gn:asciiname":"Bosawan",
    "gn:country_code":"PH",
    "gn:dem":4,
    "gn:feature_class":"P",
    "gn:feature_code":"PPL",
    "gn:name":"Bosawan",
    "gn:population":0,
    "gn:timezone":"Asia/Manila",
    "iso:country":"PH",
    "name:fil_x_preferred":[
        "Bosawan"
    ],
    "wof:name":"Bosawan",
    "wof:placetype":"locality"
},
  "geometry": {"coordinates":[124.06426999999999,6.55002],"type":"Point"}
}