{
  "type": "Feature",
  "properties": {
    "gn:admin1_code":"40",
    "gn:admin2_code":"53",
    "gn:admin3_code":"45809000.0",
    "gn:asciiname":"Bombongan",
    "gn:country_code":"PH",
    "gn:dem":87,
    "gn:feature_class":"P",
    "gn:feature_code":"PPL",
    "gn:name":"Bombongan",
    "gn:population":0,
    "gn:timezone":"Asia/Manila",
    "iso:country":"PH",
    "name:fil_x_preferred":[
        "Bombongan"
    ],
    "wof:name":"Bombongan",
    "wof:placetype":"locality"
},
  "geometry": {"coordinates":[121.2192,14.507],"type":"Point"}
}