{
  "type": "Feature",
  "properties": {
    "gn:country":"PH",
    "gn:fcode":"PPL",
    "gn:pop":8648,
    "iso:country":"PH",
    "name:bcl_x_preferred":[
        "Sampan"
    ],
    "name:cat_x_preferred":[
        "sampan"
    ],
    "name:deu_x_preferred":[
        "Sampan"
    ],
    "name:eng_x_preferred":[
        "sampan"
    ],
    "name:fil_x_preferred":[
        "Sampao"
    ],
    "name:fra_x_preferred":[
        "sampan"
    ],
    "name:ind_x_preferred":[
        "Sampan"
    ],
    "name:ita_x_preferred":[
        "sampan"
    ],
    "name:jpn_x_preferred":[
        "\u30b5\u30f3\u30d1\u30f3"
    ],
    "name:kor_x_preferred":[
        "\uc0bc\ud310"
    ],
    "name:lit_x_preferred":[
        "Sampanas"
    ],
    "name:msa_x_preferred":[
        "Sampan"
    ],
    "name:nld_x_preferred":[
        "sampan"
    ],
    "name:nob_x_preferred":[
        "sampan"
    ],
    "name:oci_x_preferred":[
        "Sampan"
    ],
    "name:pol_x_preferred":[
        "Sampan"
    ],
    "name:por_x_preferred":[
        "Sampana"
    ],
    "name:rus_x_preferred":[
        "\u0421\u0430\u043c\u043f\u0430\u043d"
    ],
    "name:sin_x_preferred":[
        "\u0dc4\u0db8\u0dca\u0db6\u0db1\u0dca \u0dba\u0dcf\u0dad\u0dca\u200d\u0dbb\u0dcf\u0dc0"
    ],
    "name:slv_x_preferred":[
        "Sampan"
    ],
    "name:spa_x_preferred":[
        "junco"
    ],
    "name:swe_x_preferred":[
        "Sampan"
    ],
    "name:yue_x_preferred":[
        "\u4e09\u677f"
    ],
    "name:zho_x_preferred":[
        "\u8222\u8228"
    ],
    "qs:name":"Sampao",
    "qs:photos_9r":0,
    "qs:photos_sr":0,
    "qs:pop_sr":"5",
    "wd:wordcount":285,
    "wof:name":"Sampao",
    "wof:placetype":"locality",
    "wof:population":8648
},
  "geometry": {"coordinates":[125.66110999999999,7.59389],"type":"Point"}
}