{
  "type": "Feature",
  "properties": {
    "gn:country":"PH",
    "gn:fcode":"PPL",
    "gn:pop":8648,
    "iso:country":"PH",
    "name:fil_x_preferred":[
        "Sampao"
    ],
    "qs:name":"Sampao",
    "qs:photos_9r":0,
    "qs:photos_sr":0,
    "qs:pop_sr":"5",
    "wd:wordcount":285,
    "wof:name":"Sampao",
    "wof:placetype":"locality",
    "wof:population":8648
},
  "geometry": {"coordinates":[125.66110999999999,7.59389],"type":"Point"}
}