{
  "type": "Feature",
  "properties": {
    "gn:admin1_code":"41",
    "gn:admin2_code":"38",
    "gn:admin3_code":"174001000.0",
    "gn:asciiname":"Caganhao",
    "gn:country_code":"PH",
    "gn:dem":10,
    "gn:feature_class":"P",
    "gn:feature_code":"PPL",
    "gn:name":"Caganhao",
    "gn:population":0,
    "gn:timezone":"Asia/Manila",
    "iso:country":"PH",
    "name:fil_x_preferred":[
        "Caganhao"
    ],
    "wof:name":"Caganhao",
    "wof:placetype":"locality"
},
  "geometry": {"coordinates":[121.8223,13.4145],"type":"Point"}
}