{
  "type": "Feature",
  "properties": {
    "gn:admin1_code":"05",
    "gn:admin2_code":"58",
    "gn:admin3_code":"56213000.0",
    "gn:asciiname":"Ginablan",
    "gn:country_code":"PH",
    "gn:dem":13,
    "gn:feature_class":"P",
    "gn:feature_code":"PPL",
    "gn:name":"Ginablan",
    "gn:population":0,
    "gn:timezone":"Asia/Manila",
    "iso:country":"PH",
    "name:fil_x_preferred":[
        "Ginablan"
    ],
    "wof:name":"Ginablan",
    "wof:placetype":"locality"
},
  "geometry": {"coordinates":[123.7016,12.9567],"type":"Point"}
}