{
  "type": "Feature",
  "properties": {
    "gn:admin1_code":"41",
    "gn:admin2_code":"38",
    "gn:admin3_code":"174006000.0",
    "gn:asciiname":"Bahi",
    "gn:country_code":"PH",
    "gn:dem":364,
    "gn:feature_class":"P",
    "gn:feature_code":"PPL",
    "gn:name":"Bahi",
    "gn:population":0,
    "gn:timezone":"Asia/Manila",
    "iso:country":"PH",
    "name:fil_x_preferred":[
        "Bahi"
    ],
    "name:ita_x_preferred":[
        "Bahi"
    ],
    "name:swa_x_preferred":[
        "Bahi"
    ],
    "wof:name":"Bahi",
    "wof:placetype":"locality"
},
  "geometry": {"coordinates":[122.092,13.3603],"type":"Point"}
}