{
  "type": "Feature",
  "properties": {
    "gn:admin1_code":"08",
    "gn:admin2_code":"59",
    "gn:asciiname":"Kogon",
    "gn:country_code":"PH",
    "gn:dem":-9999,
    "gn:feature_class":"P",
    "gn:feature_code":"PPL",
    "gn:name":"Kogon",
    "gn:population":0,
    "gn:timezone":"Asia/Manila",
    "iso:country":"PH",
    "name:ceb_x_preferred":[
        "Kogon"
    ],
    "name:deu_x_preferred":[
        "Kogon"
    ],
    "name:fil_x_preferred":[
        "Kogon"
    ],
    "name:fra_x_preferred":[
        "Kogon"
    ],
    "name:nds_x_preferred":[
        "Kogon"
    ],
    "name:rus_x_preferred":[
        "\u041a\u043e\u0433\u043e\u043d"
    ],
    "name:swe_x_preferred":[
        "Kogon"
    ],
    "wof:name":"Kogon",
    "wof:placetype":"locality"
},
  "geometry": {"coordinates":[125.23333,10.25],"type":"Point"}
}