{
  "type": "Feature",
  "properties": {
    "gn:country":"PH",
    "gn:fcode":"PPL",
    "gn:population":2471,
    "iso:country":"PH",
    "name:fil_x_preferred":[
        "Bued"
    ],
    "qs:name":"Bued",
    "qs:photos_9r":0,
    "qs:photos_sr":0,
    "qs:pop_sr":"4",
    "wof:name":"Bued",
    "wof:placetype":"locality",
    "wof:population":2471
},
  "geometry": {"coordinates":[119.9973,16.1622],"type":"Point"}
}