{
  "type": "Feature",
  "properties": {
    "gn:admin1_code":"08",
    "gn:admin2_code":"55",
    "gn:admin3_code":"86002000.0",
    "gn:asciiname":"May-it",
    "gn:country_code":"PH",
    "gn:dem":10,
    "gn:feature_class":"P",
    "gn:feature_code":"PPL",
    "gn:name":"May-it",
    "gn:population":0,
    "gn:timezone":"Asia/Manila",
    "iso:country":"PH",
    "name:und_x_variant":[
        "Moit"
    ],
    "wof:name":"May-it",
    "wof:placetype":"locality"
},
  "geometry": {"coordinates":[125.01876,11.2958],"type":"Point"}
}