{
  "type": "Feature",
  "properties": {
    "gn:admin1_code":"14",
    "gn:admin2_code":"60",
    "gn:admin3_code":"156612000.0",
    "gn:asciiname":"Punyao",
    "gn:country_code":"PH",
    "gn:dem":182,
    "gn:feature_class":"P",
    "gn:feature_code":"PPL",
    "gn:name":"Punyao",
    "gn:population":0,
    "gn:timezone":"Asia/Manila",
    "iso:country":"PH",
    "name:fil_x_preferred":[
        "Punyao"
    ],
    "wof:name":"Punyao",
    "wof:placetype":"locality"
},
  "geometry": {"coordinates":[120.87278000000001,5.51444],"type":"Point"}
}