{
  "type": "Feature",
  "properties": {
    "gn:admin1_code":"01",
    "gn:admin2_code":"51",
    "gn:admin3_code":"15541000.0",
    "gn:asciiname":"Kabuanan",
    "gn:country_code":"PH",
    "gn:dem":79,
    "gn:feature_class":"P",
    "gn:feature_code":"PPL",
    "gn:name":"Kabuanan",
    "gn:population":0,
    "gn:timezone":"Asia/Manila",
    "iso:country":"PH",
    "name:fil_x_preferred":[
        "Kabuanan"
    ],
    "name:fil_x_variant":[
        "Cabuanan"
    ],
    "name:und_x_variant":[
        "Cabuanan"
    ],
    "wof:name":"Kabuanan",
    "wof:placetype":"locality"
},
  "geometry": {"coordinates":[120.47712,16.17237],"type":"Point"}
}