{
  "type": "Feature",
  "properties": {
    "gn:country":"PH",
    "gn:fcode":"ADM3",
    "gn:pop":134543,
    "iso:country":"PH",
    "name:fil_x_preferred":[
        "Montalban"
    ],
    "qs:name":"Montalban",
    "qs:photos_9r":0,
    "qs:photos_sr":0,
    "qs:pop_sr":"9",
    "wd:wordcount":85,
    "wof:name":"Montalban",
    "wof:placetype":"localadmin",
    "wof:population":134543
},
  "geometry": {"coordinates":[121.23333,14.78333],"type":"Point"}
}