{
  "type": "Feature",
  "properties": {
    "gn:country":"PH",
    "gn:fcode":"ADM3",
    "gn:pop":134543,
    "iso:country":"PH",
    "name:bre_x_preferred":[
        "Montalb\u00e1n"
    ],
    "name:cat_x_preferred":[
        "Montalb\u00e1n"
    ],
    "name:ceb_x_preferred":[
        "Montalb\u00e1n"
    ],
    "name:deu_x_preferred":[
        "Montalb\u00e1n"
    ],
    "name:fil_x_preferred":[
        "Montalban"
    ],
    "name:fra_x_preferred":[
        "Montalb\u00e1n"
    ],
    "name:glg_x_preferred":[
        "Montalb\u00e1n"
    ],
    "name:nds_x_preferred":[
        "Montalb\u00e1n"
    ],
    "name:nld_x_preferred":[
        "Montalb\u00e1n"
    ],
    "name:por_x_preferred":[
        "Montalb\u00e1n"
    ],
    "name:rus_x_preferred":[
        "\u041c\u043e\u043d\u0442\u0430\u043b\u044c\u0431\u0430\u043d"
    ],
    "name:scn_x_preferred":[
        "Montalb\u00e1n"
    ],
    "name:spa_x_preferred":[
        "Montalb\u00e1n"
    ],
    "name:swe_x_preferred":[
        "Montalb\u00e1n"
    ],
    "name:ukr_x_preferred":[
        "\u041c\u043e\u043d\u0442\u0430\u043b\u044c\u0431\u0430\u043d"
    ],
    "qs:name":"Montalban",
    "qs:photos_9r":0,
    "qs:photos_sr":0,
    "qs:pop_sr":"9",
    "wd:wordcount":85,
    "wof:name":"Montalban",
    "wof:placetype":"localadmin",
    "wof:population":134543
},
  "geometry": {"coordinates":[121.23333,14.78333],"type":"Point"}
}