{
  "type": "Feature",
  "properties": {
    "gn:admin1_code":"08",
    "gn:admin2_code":"67",
    "gn:admin3_code":"84811000.0",
    "gn:asciiname":"Villahermosa",
    "gn:country_code":"PH",
    "gn:dem":53,
    "gn:feature_class":"P",
    "gn:feature_code":"PPL",
    "gn:name":"Villahermosa",
    "gn:population":0,
    "gn:timezone":"Asia/Manila",
    "iso:country":"PH",
    "name:ara_x_preferred":[
        "\u0641\u064a\u0644\u0627\u0647\u064a\u0631\u0645\u0648\u0633\u0627"
    ],
    "name:bul_x_preferred":[
        "\u0412\u0438\u043b\u044f\u0435\u0440\u043c\u043e\u0441\u0430"
    ],
    "name:cat_x_preferred":[
        "Villahermosa"
    ],
    "name:ceb_x_preferred":[
        "Villahermosa"
    ],
    "name:deu_x_preferred":[
        "Villahermosa"
    ],
    "name:epo_x_preferred":[
        "Villahermosa"
    ],
    "name:eus_x_preferred":[
        "Villahermosa"
    ],
    "name:fas_x_preferred":[
        "\u0648\u06cc\u0644\u0627\u0647\u0631\u0645\u0633\u0627"
    ],
    "name:fil_x_preferred":[
        "Villahermosa"
    ],
    "name:fin_x_preferred":[
        "Villahermosa"
    ],
    "name:fra_x_preferred":[
        "Villahermosa"
    ],
    "name:heb_x_preferred":[
        "\u05d5\u05d9\u05d9\u05d0\u05e8\u05de\u05d5\u05e1\u05d4"
    ],
    "name:hun_x_preferred":[
        "Villahermosa"
    ],
    "name:ilo_x_preferred":[
        "Villahermosa"
    ],
    "name:ind_x_preferred":[
        "Villahermosa"
    ],
    "name:ita_x_preferred":[
        "Villahermosa"
    ],
    "name:jpn_x_preferred":[
        "\u30d3\u30e4\u30a8\u30eb\u30e2\u30b5"
    ],
    "name:kat_x_preferred":[
        "\u10d5\u10d8\u10da\u10d8\u10d0\u10d4\u10e0\u10db\u10dd\u10e1\u10d0"
    ],
    "name:kor_x_preferred":[
        "\ube44\uc57c\uc5d0\ub974\ubaa8\uc0ac"
    ],
    "name:lad_x_preferred":[
        "Villahermosa"
    ],
    "name:lit_x_preferred":[
        "Viljahermosa"
    ],
    "name:mar_x_preferred":[
        "\u0935\u094d\u0939\u093f\u092f\u093e\u090f\u0930\u094d\u092e\u094b\u0938\u093e"
    ],
    "name:mlg_x_preferred":[
        "Villahermosa"
    ],
    "name:msa_x_preferred":[
        "Villahermosa"
    ],
    "name:nld_x_preferred":[
        "Villahermosa"
    ],
    "name:nor_x_preferred":[
        "Villahermosa"
    ],
    "name:pol_x_preferred":[
        "Villahermosa"
    ],
    "name:por_x_preferred":[
        "Villahermosa"
    ],
    "name:que_x_preferred":[
        "Villahermosa"
    ],
    "name:rus_x_preferred":[
        "\u0412\u0438\u043b\u044c\u044f\u044d\u0440\u043c\u043e\u0441\u0430"
    ],
    "name:sco_x_preferred":[
        "Villahermosa"
    ],
    "name:spa_x_preferred":[
        "Villahermosa"
    ],
    "name:srp_x_preferred":[
        "\u0412\u0438\u0459\u0430\u0435\u0440\u043c\u043e\u0441\u0430"
    ],
    "name:swa_x_preferred":[
        "Villahermosa"
    ],
    "name:swe_x_preferred":[
        "Villahermosa"
    ],
    "name:tgl_x_preferred":[
        "Villahermosa"
    ],
    "name:tur_x_preferred":[
        "Villahermosa"
    ],
    "name:urd_x_preferred":[
        "\u0628\u06cc\u0627\u0626\u0631\u0645\u0648\u0633\u0627"
    ],
    "name:vie_x_preferred":[
        "Villahermosa"
    ],
    "name:war_x_preferred":[
        "Villahermosa"
    ],
    "name:xmf_x_preferred":[
        "\u10d5\u10d8\u10da\u10d8\u10d0\u10d4\u10e0\u10db\u10dd\u10e1\u10d0"
    ],
    "name:zho_x_preferred":[
        "\u6bd4\u4e9a\u57c3\u5c14\u83ab\u8428"
    ],
    "wof:name":"Villahermosa",
    "wof:placetype":"locality"
},
  "geometry": {"coordinates":[124.2991,12.5468],"type":"Point"}
}