{
  "type": "Feature",
  "properties": {
    "gn:admin1_code":"08",
    "gn:admin2_code":"67",
    "gn:admin3_code":"84811000.0",
    "gn:asciiname":"Villahermosa",
    "gn:country_code":"PH",
    "gn:dem":53,
    "gn:feature_class":"P",
    "gn:feature_code":"PPL",
    "gn:name":"Villahermosa",
    "gn:population":0,
    "gn:timezone":"Asia/Manila",
    "iso:country":"PH",
    "name:fil_x_preferred":[
        "Villahermosa"
    ],
    "wof:name":"Villahermosa",
    "wof:placetype":"locality"
},
  "geometry": {"coordinates":[124.2991,12.5468],"type":"Point"}
}