{
  "type": "Feature",
  "properties": {
    "gn:admin1_code":"09",
    "gn:admin2_code":"66",
    "gn:admin3_code":"97315000.0",
    "gn:asciiname":"Diwan",
    "gn:country_code":"PH",
    "gn:dem":37,
    "gn:feature_class":"P",
    "gn:feature_code":"PPL",
    "gn:name":"Diwan",
    "gn:population":0,
    "gn:timezone":"Asia/Manila",
    "iso:country":"PH",
    "name:ara_x_preferred":[
        "\u062f\u064a\u0648\u0627\u0646"
    ],
    "name:cat_x_preferred":[
        "Diwan"
    ],
    "name:ceb_x_preferred":[
        "Diwan"
    ],
    "name:ckb_x_preferred":[
        "\u062f\u06cc\u0648\u0627\u0646"
    ],
    "name:deu_x_preferred":[
        "Diwan"
    ],
    "name:eng_x_preferred":[
        "Diwan"
    ],
    "name:fas_x_preferred":[
        "\u062f\u06cc\u0648\u0627\u0646"
    ],
    "name:fra_x_preferred":[
        "Diwan"
    ],
    "name:ita_x_preferred":[
        "Diwan"
    ],
    "name:nld_x_preferred":[
        "Diwan"
    ],
    "name:pol_x_preferred":[
        "Dywan"
    ],
    "name:por_x_preferred":[
        "Div\u00e3"
    ],
    "name:swe_x_preferred":[
        "Diwan"
    ],
    "name:urd_x_preferred":[
        "\u062f\u06cc\u0648\u0627\u0646"
    ],
    "wof:name":"Diwan",
    "wof:placetype":"locality"
},
  "geometry": {"coordinates":[123.47239999999999,8.1262],"type":"Point"}
}