{
  "type": "Feature",
  "properties": {
    "gn:admin1_code":"08",
    "gn:admin2_code":"H9",
    "gn:admin3_code":"87802000.0",
    "gn:asciiname":"Pinangumhan",
    "gn:country_code":"PH",
    "gn:dem":75,
    "gn:feature_class":"P",
    "gn:feature_code":"PPL",
    "gn:name":"Pinangumhan",
    "gn:population":0,
    "gn:timezone":"Asia/Manila",
    "iso:country":"PH",
    "name:fil_x_preferred":[
        "Pinangumhan"
    ],
    "name:und_x_variant":[
        "Pinangomhan"
    ],
    "wof:name":"Pinangumhan",
    "wof:placetype":"locality"
},
  "geometry": {"coordinates":[124.46169999999999,11.4895],"type":"Point"}
}