{
  "type": "Feature",
  "properties": {
    "gn:admin1_code":"07",
    "gn:admin2_code":"69",
    "gn:admin3_code":"76102000.0",
    "gn:asciiname":"Poblacion",
    "gn:country_code":"PH",
    "gn:dem":11,
    "gn:feature_class":"P",
    "gn:feature_code":"PPL",
    "gn:name":"Poblacion",
    "gn:population":0,
    "gn:timezone":"Asia/Manila",
    "iso:country":"PH",
    "name:fil_x_preferred":[
        "Poblacion"
    ],
    "wof:name":"Poblacion",
    "wof:placetype":"locality"
},
  "geometry": {"coordinates":[123.5964,9.2482],"type":"Point"}
}