{
  "type": "Feature",
  "properties": {
    "gn:admin1_code":"08",
    "gn:admin2_code":"37",
    "gn:admin3_code":"83726000.0",
    "gn:asciiname":"Aguiting",
    "gn:cc2":"PH",
    "gn:country_code":"PH",
    "gn:dem":93,
    "gn:feature_class":"P",
    "gn:feature_code":"PPL",
    "gn:name":"Aguiting",
    "gn:population":0,
    "gn:timezone":"Asia/Manila",
    "iso:country":"PH",
    "name:und_x_variant":[
        "Aquiting"
    ],
    "wof:name":"Aguiting",
    "wof:placetype":"locality"
},
  "geometry": {"coordinates":[124.59806,11.13056],"type":"Point"}
}