{
  "type": "Feature",
  "properties": {
    "gn:admin1_code":"01",
    "gn:admin2_code":"51",
    "gn:admin3_code":"15515000.0",
    "gn:asciiname":"Cabayawasan",
    "gn:country_code":"PH",
    "gn:dem":10,
    "gn:feature_class":"P",
    "gn:feature_code":"PPL",
    "gn:name":"Cabayawasan",
    "gn:population":0,
    "gn:timezone":"Asia/Manila",
    "iso:country":"PH",
    "name:fil_x_preferred":[
        "Cabayawasan"
    ],
    "wof:name":"Cabayawasan",
    "wof:placetype":"locality"
},
  "geometry": {"coordinates":[120.22750000000001,15.9467],"type":"Point"}
}