{
  "type": "Feature",
  "properties": {
    "iso:country":"PH",
    "name:eng_x_preferred":[
        "Salunayan"
    ],
    "name:unk_x_variant":[
        "Serenaya"
    ],
    "qs:gn_country":"PH",
    "qs:gn_fcode":"PPL",
    "qs:gn_pop":2758,
    "qs:name":"Salunayan",
    "qs:name_adm0":"Philippines",
    "qs:name_adm1":"Soccsksargen",
    "qs:photos":0,
    "qs:photos_1k":0,
    "qs:photos_9k":0,
    "qs:photos_9r":0,
    "qs:photos_all":0,
    "qs:photos_sr":0,
    "qs:placetype":"Town",
    "qs:pop_sr":"4",
    "qs:woe_adm0":23424934,
    "wd:wordcount":224,
    "wof:name":"Salunayan",
    "wof:placetype":"locality",
    "wof:population":2758
},
  "geometry": {"coordinates":[124.4975,7.15444],"type":"Point"}
}