{
  "type": "Feature",
  "properties": {
    "gn:admin1_code":"08",
    "gn:admin2_code":"55",
    "gn:admin3_code":"86004000.0",
    "gn:asciiname":"Polangi",
    "gn:cc2":"PH",
    "gn:country_code":"PH",
    "gn:dem":29,
    "gn:feature_class":"P",
    "gn:feature_code":"PPL",
    "gn:name":"Pola\u00f1gi",
    "gn:population":0,
    "gn:timezone":"Asia/Manila",
    "iso:country":"PH",
    "name:und_x_variant":[
        "Polange",
        "Polangui",
        "Pola\u00f1gi"
    ],
    "wof:name":"Polangi",
    "wof:placetype":"locality"
},
  "geometry": {"coordinates":[125.03,11.63667],"type":"Point"}
}