{
  "type": "Feature",
  "properties": {
    "gn:admin1_code":"07",
    "gn:admin2_code":"21",
    "gn:admin3_code":"72216000.0",
    "gn:asciiname":"Mago",
    "gn:country_code":"PH",
    "gn:dem":507,
    "gn:feature_class":"P",
    "gn:feature_code":"PPL",
    "gn:name":"Mago",
    "gn:population":0,
    "gn:timezone":"Asia/Manila",
    "iso:country":"PH",
    "name:cat_x_preferred":[
        "Mag\u00f3"
    ],
    "name:ceb_x_preferred":[
        "Mago"
    ],
    "name:deu_x_preferred":[
        "Mago"
    ],
    "name:fil_x_preferred":[
        "Mago"
    ],
    "name:fra_x_preferred":[
        "Mago"
    ],
    "name:ita_x_preferred":[
        "Mago"
    ],
    "name:lat_x_preferred":[
        "Mago"
    ],
    "name:nld_x_preferred":[
        "Mago"
    ],
    "name:por_x_preferred":[
        "Mago"
    ],
    "name:spa_x_preferred":[
        "Mago"
    ],
    "name:sqi_x_preferred":[
        "Mago"
    ],
    "name:swe_x_preferred":[
        "Mago"
    ],
    "name:war_x_preferred":[
        "Mago"
    ],
    "wof:name":"Mago",
    "wof:placetype":"locality"
},
  "geometry": {"coordinates":[123.98333,10.63333],"type":"Point"}
}