{
  "type": "Feature",
  "properties": {
    "gn:admin1_code":"03",
    "gn:admin2_code":"63",
    "gn:admin3_code":"36917000.0",
    "gn:asciiname":"San Gavino",
    "gn:country_code":"PH",
    "gn:dem":29,
    "gn:feature_class":"P",
    "gn:feature_code":"PPL",
    "gn:name":"San Gavino",
    "gn:population":0,
    "gn:timezone":"Asia/Manila",
    "iso:country":"PH",
    "wof:name":"San Gavino",
    "wof:placetype":"locality"
},
  "geometry": {"coordinates":[120.69047,15.57631],"type":"Point"}
}