{
  "type": "Feature",
  "properties": {
    "gn:admin1_code":"03",
    "gn:admin2_code":"G8",
    "gn:admin3_code":"37701000.0",
    "gn:asciiname":"Gabgab",
    "gn:cc2":"PH",
    "gn:country_code":"PH",
    "gn:dem":11,
    "gn:feature_class":"P",
    "gn:feature_code":"PPL",
    "gn:name":"Gabgab",
    "gn:population":0,
    "gn:timezone":"Asia/Manila",
    "iso:country":"PH",
    "name:und_x_variant":[
        "Gapgap",
        "Gabgab"
    ],
    "wof:name":"Gabgab",
    "wof:placetype":"locality"
},
  "geometry": {"coordinates":[121.55,15.76667],"type":"Point"}
}