{
  "type": "Feature",
  "properties": {
    "gn:admin1_code":"06",
    "gn:admin2_code":"30",
    "gn:admin3_code":"63030000.0",
    "gn:asciiname":"San Roque",
    "gn:country_code":"PH",
    "gn:dem":8,
    "gn:feature_class":"P",
    "gn:feature_code":"PPL",
    "gn:name":"San Roque",
    "gn:population":0,
    "gn:timezone":"Asia/Manila",
    "iso:country":"PH",
    "name:ara_x_preferred":[
        "\u0633\u0627\u0646 \u0631\u0648\u062c"
    ],
    "name:ast_x_preferred":[
        "San Roque"
    ],
    "name:bre_x_preferred":[
        "San Roque"
    ],
    "name:ceb_x_preferred":[
        "San Roque"
    ],
    "name:deu_x_preferred":[
        "San Roque"
    ],
    "name:eus_x_preferred":[
        "San Roque"
    ],
    "name:fil_x_preferred":[
        "San Roque"
    ],
    "name:fra_x_preferred":[
        "San Roque"
    ],
    "name:glg_x_preferred":[
        "San Roque"
    ],
    "name:hun_x_preferred":[
        "San Roque"
    ],
    "name:ita_x_preferred":[
        "San Roque"
    ],
    "name:jpn_x_preferred":[
        "\u30b5\u30f3\u30fb\u30ed\u30b1"
    ],
    "name:mlg_x_preferred":[
        "San Roque"
    ],
    "name:msa_x_preferred":[
        "San Roque"
    ],
    "name:nld_x_preferred":[
        "San Roque"
    ],
    "name:por_x_preferred":[
        "San Roque"
    ],
    "name:rus_x_preferred":[
        "\u0421\u0430\u043d-\u0420\u043e\u043a\u0435"
    ],
    "name:slk_x_preferred":[
        "San Roque"
    ],
    "name:spa_x_preferred":[
        "San Roque"
    ],
    "name:swe_x_preferred":[
        "San Roque"
    ],
    "name:ukr_x_preferred":[
        "\u0421\u0430\u043d-\u0420\u043e\u043a\u0435"
    ],
    "name:vie_x_preferred":[
        "San Roque"
    ],
    "name:war_x_preferred":[
        "San Roque"
    ],
    "wof:name":"San Roque",
    "wof:placetype":"locality"
},
  "geometry": {"coordinates":[122.2123,10.6389],"type":"Point"}
}