{
  "type": "Feature",
  "properties": {
    "gn:country":"PH",
    "gn:fcode":"ADM3",
    "gn:population":18754,
    "iso:country":"PH",
    "name:fil_x_preferred":[
        "Cabucgayan"
    ],
    "qs:name":"Cabucgayan",
    "qs:photos_9r":0,
    "qs:photos_sr":0,
    "qs:pop_sr":"6",
    "wof:name":"Cabucgayan",
    "wof:placetype":"localadmin",
    "wof:population":18754
},
  "geometry": {"coordinates":[124.56667,11.51667],"type":"Point"}
}