{
  "type": "Feature",
  "properties": {
    "gn:country":"PH",
    "gn:fcode":"ADM3",
    "gn:population":21430,
    "iso:country":"PH",
    "name:fil_x_preferred":[
        "Salay"
    ],
    "qs_pg:aaroncc":"PH",
    "qs_pg:gn_country":"PH",
    "qs_pg:gn_fcode":"ADM3",
    "qs_pg:gn_pop":21430,
    "qs_pg:name":"Salay",
    "qs_pg:photos_9r":0,
    "qs_pg:photos_sr":0,
    "qs_pg:pop_sr":7,
    "qs_pg:qs_pg_placetype":"localadmin",
    "wof:name":"Salay",
    "wof:placetype":"localadmin",
    "wof:population":21430
},
  "geometry": {"coordinates":[124.81667,8.88333],"type":"Point"}
}