{
  "type": "Feature",
  "properties": {
    "gn:admin1_code":"01",
    "gn:admin2_code":"51",
    "gn:admin3_code":"15513000.0",
    "gn:asciiname":"Manat",
    "gn:country_code":"PH",
    "gn:dem":8,
    "gn:feature_class":"P",
    "gn:feature_code":"PPL",
    "gn:name":"Manat",
    "gn:population":0,
    "gn:timezone":"Asia/Manila",
    "iso:country":"PH",
    "name:aze_x_preferred":[
        "Manat"
    ],
    "name:bul_x_preferred":[
        "\u041c\u0430\u043d\u0430\u0442"
    ],
    "name:ceb_x_preferred":[
        "Manat"
    ],
    "name:ces_x_preferred":[
        "Manat"
    ],
    "name:deu_x_preferred":[
        "Manat"
    ],
    "name:est_x_preferred":[
        "Manat"
    ],
    "name:eus_x_preferred":[
        "Manat"
    ],
    "name:fas_x_preferred":[
        "\u0645\u0646\u0627\u062a"
    ],
    "name:fil_x_preferred":[
        "Manat"
    ],
    "name:fra_x_preferred":[
        "Manat"
    ],
    "name:hrv_x_preferred":[
        "Manat"
    ],
    "name:hun_x_preferred":[
        "Manat"
    ],
    "name:ita_x_preferred":[
        "Manat"
    ],
    "name:jpn_x_preferred":[
        "\u30de\u30ca\u30c8"
    ],
    "name:kor_x_preferred":[
        "\ub9c8\ub098\ud2b8"
    ],
    "name:msa_x_preferred":[
        "Manat"
    ],
    "name:nld_x_preferred":[
        "Manat"
    ],
    "name:pol_x_preferred":[
        "Manat"
    ],
    "name:por_x_preferred":[
        "Manat"
    ],
    "name:rus_x_preferred":[
        "\u041c\u0430\u043d\u0430\u0442"
    ],
    "name:sah_x_preferred":[
        "\u041c\u0430\u043d\u0430\u0442"
    ],
    "name:slk_x_preferred":[
        "Manat"
    ],
    "name:spa_x_preferred":[
        "Manat"
    ],
    "name:srp_x_preferred":[
        "\u041c\u0430\u043d\u0430\u0442"
    ],
    "name:swe_x_preferred":[
        "Manat"
    ],
    "name:tam_x_preferred":[
        "\u0bae\u0ba9\u0bbe\u0ba4\u0bcd"
    ],
    "name:tuk_x_preferred":[
        "Manat"
    ],
    "name:tur_x_preferred":[
        "Manat"
    ],
    "name:ukr_x_preferred":[
        "\u041c\u0430\u043d\u0430\u0442"
    ],
    "name:uzb_x_preferred":[
        "Manat"
    ],
    "name:zho_x_preferred":[
        "\u9a6c\u7eb3\u7279"
    ],
    "wof:name":"Manat",
    "wof:placetype":"locality"
},
  "geometry": {"coordinates":[120.27985,16.0173],"type":"Point"}
}