{
  "type": "Feature",
  "properties": {
    "gn:admin1_code":"01",
    "gn:admin2_code":"51",
    "gn:admin3_code":"15513000.0",
    "gn:asciiname":"Manat",
    "gn:country_code":"PH",
    "gn:dem":8,
    "gn:feature_class":"P",
    "gn:feature_code":"PPL",
    "gn:name":"Manat",
    "gn:population":0,
    "gn:timezone":"Asia/Manila",
    "iso:country":"PH",
    "name:fil_x_preferred":[
        "Manat"
    ],
    "wof:name":"Manat",
    "wof:placetype":"locality"
},
  "geometry": {"coordinates":[120.27985,16.0173],"type":"Point"}
}