{
  "type": "Feature",
  "properties": {
    "gn:admin1_code":"40",
    "gn:admin2_code":"H2",
    "gn:admin3_code":"45632000.0",
    "gn:asciiname":"Sangil",
    "gn:country_code":"PH",
    "gn:dem":7,
    "gn:feature_class":"P",
    "gn:feature_code":"PPL",
    "gn:name":"Sangil",
    "gn:population":0,
    "gn:timezone":"Asia/Manila",
    "iso:country":"PH",
    "name:fil_x_preferred":[
        "Sangil"
    ],
    "wof:name":"Sangil",
    "wof:placetype":"locality"
},
  "geometry": {"coordinates":[122.25230000000001,14.7703],"type":"Point"}
}