{
  "type": "Feature",
  "properties": {
    "gn:admin1_code":"15",
    "gn:admin2_code":"10",
    "gn:admin3_code":"141114000.0",
    "gn:asciiname":"Bahyan",
    "gn:country_code":"PH",
    "gn:dem":938,
    "gn:feature_class":"P",
    "gn:feature_code":"PPL",
    "gn:name":"Bahyan",
    "gn:population":0,
    "gn:timezone":"Asia/Manila",
    "iso:country":"PH",
    "name:fil_x_preferred":[
        "Bahyan"
    ],
    "wof:name":"Bahyan",
    "wof:placetype":"locality"
},
  "geometry": {"coordinates":[120.61667,16.51667],"type":"Point"}
}