{
  "type": "Feature",
  "properties": {
    "gn:admin1_code":"08",
    "gn:admin2_code":"67",
    "gn:admin3_code":"84813000.0",
    "gn:asciiname":"Banquerhan",
    "gn:country_code":"PH",
    "gn:dem":1,
    "gn:feature_class":"P",
    "gn:feature_code":"PPL",
    "gn:name":"Banquerhan",
    "gn:population":0,
    "gn:timezone":"Asia/Manila",
    "iso:country":"PH",
    "name:fil_x_preferred":[
        "Banquerhan"
    ],
    "wof:name":"Banquerhan",
    "wof:placetype":"locality"
},
  "geometry": {"coordinates":[124.7961,12.5384],"type":"Point"}
}