{
  "type": "Feature",
  "properties": {
    "gn:admin1_code":"07",
    "gn:admin2_code":"11",
    "gn:admin3_code":"71246000.0",
    "gn:asciiname":"Casate",
    "gn:country_code":"PH",
    "gn:dem":11,
    "gn:feature_class":"P",
    "gn:feature_code":"PPL",
    "gn:name":"Casate",
    "gn:population":0,
    "gn:timezone":"Asia/Manila",
    "iso:country":"PH",
    "name:fil_x_preferred":[
        "Casate"
    ],
    "wof:name":"Casate",
    "wof:placetype":"locality"
},
  "geometry": {"coordinates":[124.45747,10.04589],"type":"Point"}
}