{
  "type": "Feature",
  "properties": {
    "iso:country":"PH",
    "name:bcl_x_preferred":[
        "Dumanjug"
    ],
    "name:ceb_x_preferred":[
        "Dumanjug"
    ],
    "name:deu_x_preferred":[
        "Dumanjug"
    ],
    "name:eng_x_preferred":[
        "Dumanjug"
    ],
    "name:fil_x_preferred":[
        "Dumanjog"
    ],
    "name:fra_x_preferred":[
        "Dumanjug"
    ],
    "name:ilo_x_preferred":[
        "Dumanjug"
    ],
    "name:ind_x_preferred":[
        "Dumanjug"
    ],
    "name:ita_x_preferred":[
        "Dumanjug"
    ],
    "name:nld_x_preferred":[
        "Dumanjug"
    ],
    "name:pag_x_preferred":[
        "Dumanjug"
    ],
    "name:pam_x_preferred":[
        "Dumanjug"
    ],
    "name:swe_x_preferred":[
        "Dumanjug"
    ],
    "name:tgl_x_preferred":[
        "Dumanjug"
    ],
    "name:vie_x_preferred":[
        "Dumanjug"
    ],
    "name:war_x_preferred":[
        "Dumanjug"
    ],
    "qs:gn_country":"PH",
    "qs:gn_fcode":"PPL",
    "qs:gn_pop":3614,
    "qs:name":"Dumanjug",
    "qs:name_adm0":"Philippines",
    "qs:name_adm1":"Central Visayas",
    "qs:photos":19,
    "qs:photos_1k":4,
    "qs:photos_9k":1,
    "qs:photos_9r":1,
    "qs:photos_all":19,
    "qs:photos_sr":1,
    "qs:placetype":"Town",
    "qs:pop_sr":"4",
    "qs:woe_adm0":23424934,
    "wof:name":"Dumanjug",
    "wof:placetype":"locality",
    "wof:population":3614
},
  "geometry": {"coordinates":[123.4361,10.057],"type":"Point"}
}