{
  "type": "Feature",
  "properties": {
    "gn:admin1_code":"01",
    "gn:admin2_code":"29",
    "gn:admin3_code":"12901000.0",
    "gn:asciiname":"Apang",
    "gn:country_code":"PH",
    "gn:dem":246,
    "gn:feature_class":"P",
    "gn:feature_code":"PPL",
    "gn:name":"Apang",
    "gn:population":0,
    "gn:timezone":"Asia/Manila",
    "iso:country":"PH",
    "name:fil_x_preferred":[
        "Apang"
    ],
    "wof:name":"Apang",
    "wof:placetype":"locality"
},
  "geometry": {"coordinates":[120.58620000000001,16.8683],"type":"Point"}
}