{
  "type": "Feature",
  "properties": {
    "gn:admin1_code":"01",
    "gn:admin2_code":"51",
    "gn:admin3_code":"15505000.0",
    "gn:asciiname":"Rufina",
    "gn:country_code":"PH",
    "gn:dem":19,
    "gn:feature_class":"P",
    "gn:feature_code":"PPL",
    "gn:name":"Rufina",
    "gn:population":0,
    "gn:timezone":"Asia/Manila",
    "iso:country":"PH",
    "name:azb_x_preferred":[
        "\u0631\u0648\u0641\u06cc\u0646\u0627"
    ],
    "name:bcl_x_preferred":[
        "Rufina"
    ],
    "name:bel_x_preferred":[
        "\u0420\u0443\u0444\u0456\u043d\u0430"
    ],
    "name:bre_x_preferred":[
        "Rufina"
    ],
    "name:bul_x_preferred":[
        "\u0420\u0443\u0444\u0438\u043d\u0430"
    ],
    "name:cat_x_preferred":[
        "Rufina"
    ],
    "name:ceb_x_preferred":[
        "Rufina"
    ],
    "name:cos_x_preferred":[
        "Rufina"
    ],
    "name:deu_x_preferred":[
        "Rufina"
    ],
    "name:epo_x_preferred":[
        "Rufina"
    ],
    "name:eus_x_preferred":[
        "Rufina"
    ],
    "name:fas_x_preferred":[
        "\u0631\u0648\u0641\u06cc\u0646\u0627"
    ],
    "name:fil_x_preferred":[
        "Rufina"
    ],
    "name:fra_x_preferred":[
        "Rufina"
    ],
    "name:hun_x_preferred":[
        "Rufina"
    ],
    "name:hye_x_preferred":[
        "\u054c\u0578\u0582\u0586\u056b\u0576\u0561"
    ],
    "name:ita_x_preferred":[
        "Rufina"
    ],
    "name:jpn_x_preferred":[
        "\u30eb\u30fc\u30d5\u30a3\u30ca"
    ],
    "name:kaz_x_preferred":[
        "\u0420\u0443\u0444\u0438\u043d\u0430"
    ],
    "name:kor_x_preferred":[
        "\ub8e8\ud53c\ub098"
    ],
    "name:lat_x_preferred":[
        "Rufina"
    ],
    "name:lmo_x_preferred":[
        "Rufina"
    ],
    "name:msa_x_preferred":[
        "Rufina"
    ],
    "name:nap_x_preferred":[
        "Rufina"
    ],
    "name:nld_x_preferred":[
        "Rufina"
    ],
    "name:pms_x_preferred":[
        "Rufina"
    ],
    "name:pol_x_preferred":[
        "Rufina"
    ],
    "name:por_x_preferred":[
        "Rufina"
    ],
    "name:ron_x_preferred":[
        "Rufina"
    ],
    "name:rus_x_preferred":[
        "\u0420\u0443\u0444\u0438\u043d\u0430"
    ],
    "name:scn_x_preferred":[
        "Rufina"
    ],
    "name:spa_x_preferred":[
        "Rufina"
    ],
    "name:srp_x_preferred":[
        "\u0420\u0443\u0444\u0438\u043d\u0430"
    ],
    "name:tur_x_preferred":[
        "Rufina"
    ],
    "name:ukr_x_preferred":[
        "\u0420\u0443\u0444\u0456\u043d\u0430"
    ],
    "name:uzb_x_preferred":[
        "Rufina"
    ],
    "name:vec_x_preferred":[
        "Rufina"
    ],
    "name:vie_x_preferred":[
        "Rufina"
    ],
    "name:vol_x_preferred":[
        "Rufina"
    ],
    "name:war_x_preferred":[
        "Rufina"
    ],
    "name:zho_x_preferred":[
        "\u9c81\u83f2\u7eb3"
    ],
    "wof:name":"Rufina",
    "wof:placetype":"locality"
},
  "geometry": {"coordinates":[119.96819000000001,16.34061],"type":"Point"}
}