{
  "type": "Feature",
  "properties": {
    "gn:admin1_code":"01",
    "gn:admin2_code":"51",
    "gn:admin3_code":"15501000.0",
    "gn:asciiname":"Viga",
    "gn:country_code":"PH",
    "gn:dem":75,
    "gn:feature_class":"P",
    "gn:feature_code":"PPL",
    "gn:name":"Viga",
    "gn:population":0,
    "gn:timezone":"Asia/Manila",
    "iso:country":"PH",
    "name:fil_x_preferred":[
        "Viga"
    ],
    "wof:name":"Viga",
    "wof:placetype":"locality"
},
  "geometry": {"coordinates":[119.86969999999999,16.1236],"type":"Point"}
}