{
  "type": "Feature",
  "properties": {
    "gn:admin1_code":"08",
    "gn:admin2_code":"67",
    "gn:admin3_code":"84813000.0",
    "gn:asciiname":"Canbarcelo",
    "gn:country_code":"PH",
    "gn:dem":8,
    "gn:feature_class":"P",
    "gn:feature_code":"PPL",
    "gn:name":"Canbarcelo",
    "gn:population":0,
    "gn:timezone":"Asia/Manila",
    "iso:country":"PH",
    "name:fil_x_preferred":[
        "Canbarcelo"
    ],
    "name:und_x_variant":[
        "Cambarsilu"
    ],
    "wof:name":"Canbarcelo",
    "wof:placetype":"locality"
},
  "geometry": {"coordinates":[124.8019,12.5082],"type":"Point"}
}