{
  "type": "Feature",
  "properties": {
    "gn:admin1_code":"07",
    "gn:admin2_code":"21",
    "gn:admin3_code":"72234000.0",
    "gn:asciiname":"Jaguimit",
    "gn:country_code":"PH",
    "gn:dem":208,
    "gn:elevation":"0.0",
    "gn:feature_class":"P",
    "gn:feature_code":"PPL",
    "gn:name":"Jaguimit",
    "gn:population":0,
    "gn:timezone":"Asia/Manila",
    "iso:country":"PH",
    "name:fil_x_preferred":[
        "Jaguimit"
    ],
    "wof:name":"Jaguimit",
    "wof:placetype":"locality"
},
  "geometry": {"coordinates":[123.7157,10.22478],"type":"Point"}
}