{
  "type": "Feature",
  "properties": {
    "gn:admin1_code":"11",
    "gn:admin2_code":"I6",
    "gn:admin3_code":"118202000.0",
    "gn:asciiname":"San Vicente",
    "gn:cc2":"PH",
    "gn:country_code":"PH",
    "gn:dem":216,
    "gn:feature_class":"P",
    "gn:feature_code":"PPLA3",
    "gn:name":"San Vicente",
    "gn:population":0,
    "gn:timezone":"Asia/Manila",
    "iso:country":"PH",
    "name:und_x_variant":[
        "La-ac",
        "San Vicente"
    ],
    "wof:name":"San Vicente",
    "wof:placetype":"locality"
},
  "geometry": {"coordinates":[125.81667,7.83333],"type":"Point"}
}