{
  "type": "Feature",
  "properties": {
    "gn:admin1_code":"41",
    "gn:admin2_code":"49",
    "gn:admin3_code":"175318000.0",
    "gn:asciiname":"Jolo",
    "gn:country_code":"PH",
    "gn:dem":6,
    "gn:feature_class":"P",
    "gn:feature_code":"PPL",
    "gn:name":"Jolo",
    "gn:population":0,
    "gn:timezone":"Asia/Manila",
    "iso:country":"PH",
    "name:aze_x_preferred":[
        "Jolo adas\u0131"
    ],
    "name:ceb_x_preferred":[
        "Jolo Island"
    ],
    "name:ces_x_preferred":[
        "Jolo"
    ],
    "name:deu_x_preferred":[
        "Jolo"
    ],
    "name:eng_x_preferred":[
        "Jolo"
    ],
    "name:est_x_preferred":[
        "Jolo saar"
    ],
    "name:fas_x_preferred":[
        "\u062c\u0648\u0644\u0648"
    ],
    "name:fin_x_preferred":[
        "Jolo"
    ],
    "name:fra_x_preferred":[
        "Jolo"
    ],
    "name:glg_x_preferred":[
        "Jol\u00f3"
    ],
    "name:hrv_x_preferred":[
        "Jolo"
    ],
    "name:ilo_x_preferred":[
        "Jolo"
    ],
    "name:ind_x_preferred":[
        "Jolo"
    ],
    "name:ita_x_preferred":[
        "Jolo"
    ],
    "name:jpn_x_preferred":[
        "\u30db\u30ed\u5cf6"
    ],
    "name:kor_x_preferred":[
        "\ud640\ub85c\uc12c"
    ],
    "name:mrj_x_preferred":[
        "\u0425\u043e\u043b\u043e"
    ],
    "name:msa_x_preferred":[
        "Jolo"
    ],
    "name:nld_x_preferred":[
        "Jolo"
    ],
    "name:nor_x_preferred":[
        "Jolo"
    ],
    "name:pol_x_preferred":[
        "Jolo"
    ],
    "name:por_x_preferred":[
        "Jolo"
    ],
    "name:rus_x_preferred":[
        "\u0425\u043e\u043b\u043e"
    ],
    "name:sco_x_preferred":[
        "Jolo"
    ],
    "name:srp_x_preferred":[
        "\u040f\u043e\u043b\u043e"
    ],
    "name:ukr_x_preferred":[
        "\u0425\u043e\u043b\u043e"
    ],
    "name:war_x_preferred":[
        "Jolo"
    ],
    "name:zho_x_preferred":[
        "\u970d\u6d1b\u5cf6"
    ],
    "wof:name":"Jolo",
    "wof:placetype":"locality"
},
  "geometry": {"coordinates":[119.2141,10.08801],"type":"Point"}
}