{
  "type": "Feature",
  "properties": {
    "gn:admin1_code":"41",
    "gn:admin2_code":"49",
    "gn:admin3_code":"175318000.0",
    "gn:asciiname":"Jolo",
    "gn:country_code":"PH",
    "gn:dem":6,
    "gn:feature_class":"P",
    "gn:feature_code":"PPL",
    "gn:name":"Jolo",
    "gn:population":0,
    "gn:timezone":"Asia/Manila",
    "iso:country":"PH",
    "name:eng_x_preferred":[
        "Jolo"
    ],
    "wof:name":"Jolo",
    "wof:placetype":"locality"
},
  "geometry": {"coordinates":[119.2141,10.08801],"type":"Point"}
}