{
  "type": "Feature",
  "properties": {
    "gn:admin1_code":"01",
    "gn:admin2_code":"29",
    "gn:admin3_code":"12933000.0",
    "gn:asciiname":"Borono",
    "gn:country_code":"PH",
    "gn:dem":11,
    "gn:feature_class":"P",
    "gn:feature_code":"PPL",
    "gn:name":"Borono",
    "gn:population":0,
    "gn:timezone":"Asia/Manila",
    "iso:country":"PH",
    "name:fil_x_preferred":[
        "Borono"
    ],
    "wof:name":"Borono",
    "wof:placetype":"locality"
},
  "geometry": {"coordinates":[120.4513,16.9742],"type":"Point"}
}