{
  "type": "Feature",
  "properties": {
    "gn:admin1_code":"07",
    "gn:admin2_code":"46",
    "gn:admin3_code":"74621000.0",
    "gn:asciiname":"Palanas",
    "gn:country_code":"PH",
    "gn:dem":18,
    "gn:feature_class":"P",
    "gn:feature_code":"PPL",
    "gn:name":"Palanas",
    "gn:population":0,
    "gn:timezone":"Asia/Manila",
    "iso:country":"PH",
    "name:fil_x_preferred":[
        "Palanas"
    ],
    "wof:name":"Palanas",
    "wof:placetype":"locality"
},
  "geometry": {"coordinates":[123.10899999999999,9.5325],"type":"Point"}
}