{
  "type": "Feature",
  "properties": {
    "gn:admin1_code":"08",
    "gn:admin2_code":"37",
    "gn:admin3_code":"83708000.0",
    "gn:asciiname":"Magasu",
    "gn:country_code":"PH",
    "gn:dem":36,
    "gn:feature_class":"P",
    "gn:feature_code":"PPL",
    "gn:name":"Magasu",
    "gn:population":0,
    "gn:timezone":"Asia/Manila",
    "iso:country":"PH",
    "name:fas_x_preferred":[
        "\u0645\u06af\u0633\u0648"
    ],
    "name:fil_x_preferred":[
        "Magasu"
    ],
    "wof:name":"Magasu",
    "wof:placetype":"locality"
},
  "geometry": {"coordinates":[124.8202,10.7087],"type":"Point"}
}