{
  "type": "Feature",
  "properties": {
    "gn:gn_country":"PH",
    "gn:gn_fcode":"PPLA3",
    "gn:gn_pop":3015,
    "gn:population":3015,
    "iso:country":"PH",
    "name:bcl_x_preferred":[
        "Alcoy"
    ],
    "name:cat_x_preferred":[
        "Alcoy"
    ],
    "name:ceb_x_preferred":[
        "Alcoy"
    ],
    "name:deu_x_preferred":[
        "Alcoy"
    ],
    "name:eng_x_preferred":[
        "Alcoy"
    ],
    "name:fas_x_preferred":[
        "\u0627\u0644\u06a9\u0648\u06cc\u060c \u06a9\u0628\u0648"
    ],
    "name:fas_x_variant":[
        "\u0627\u0644\u06a9\u0648\u06cc"
    ],
    "name:fil_x_preferred":[
        "Alcoy"
    ],
    "name:fra_x_preferred":[
        "Alcoy"
    ],
    "name:ilo_x_preferred":[
        "Alcoy"
    ],
    "name:ind_x_preferred":[
        "Alcoy"
    ],
    "name:ita_x_preferred":[
        "Alcoy"
    ],
    "name:nld_x_preferred":[
        "Alcoy"
    ],
    "name:pag_x_preferred":[
        "Alcoy"
    ],
    "name:pam_x_preferred":[
        "Alcoy"
    ],
    "name:spa_x_preferred":[
        "Alcoy"
    ],
    "name:swe_x_preferred":[
        "Alcoy"
    ],
    "name:tgl_x_preferred":[
        "Alcoy"
    ],
    "name:vie_x_preferred":[
        "Alcoy"
    ],
    "name:war_x_preferred":[
        "Alcoy"
    ],
    "qs_pg:aaroncc":"PH",
    "qs_pg:gn_country":"PH",
    "qs_pg:gn_fcode":"PPLA3",
    "qs_pg:gn_pop":3015,
    "qs_pg:name":"Alcoy",
    "qs_pg:photos_9r":0,
    "qs_pg:photos_sr":0,
    "qs_pg:pop_sr":4,
    "qs_pg:qs_pg_placetype":"locality",
    "wof:name":"Alcoy",
    "wof:placetype":"locality",
    "wof:population":3015
},
  "geometry": {"coordinates":[123.5067,9.7102],"type":"Point"}
}