{
  "type": "Feature",
  "properties": {
    "gn:country":"PH",
    "gn:fcode":"PPLA3",
    "gn:pop":3471,
    "iso:country":"PH",
    "name:bcl_x_preferred":[
        "Caramoan"
    ],
    "name:ceb_x_preferred":[
        "Caramoan"
    ],
    "name:deu_x_preferred":[
        "Caramoan"
    ],
    "name:eng_x_preferred":[
        "Caramoan"
    ],
    "name:fil_x_preferred":[
        "Caramoan"
    ],
    "name:fra_x_preferred":[
        "Caramoan"
    ],
    "name:gor_x_preferred":[
        "Caramoan"
    ],
    "name:heb_x_preferred":[
        "\u05e7\u05e8\u05de\u05d5\u05d0\u05df"
    ],
    "name:ilo_x_preferred":[
        "Caramoan"
    ],
    "name:ind_x_preferred":[
        "Caramoan"
    ],
    "name:ita_x_preferred":[
        "Caramoan"
    ],
    "name:nld_x_preferred":[
        "Caramoan"
    ],
    "name:nob_x_preferred":[
        "Caramoan"
    ],
    "name:pag_x_preferred":[
        "Caramoan"
    ],
    "name:pam_x_preferred":[
        "Caramoan"
    ],
    "name:swe_x_preferred":[
        "Caramoan"
    ],
    "name:tgl_x_preferred":[
        "Caramoan"
    ],
    "name:war_x_preferred":[
        "Caramoan"
    ],
    "qs:name":"Caramoan",
    "qs:photos_9r":0,
    "qs:photos_sr":0,
    "qs:pop_sr":"4",
    "wd:wordcount":777,
    "wof:name":"Caramoan",
    "wof:placetype":"locality",
    "wof:population":3471
},
  "geometry": {"coordinates":[123.8631,13.7707],"type":"Point"}
}