{
  "type": "Feature",
  "properties": {
    "gn:admin1_code":"41",
    "gn:admin2_code":"49",
    "gn:admin3_code":"175306000.0",
    "gn:asciiname":"Pancovie",
    "gn:country_code":"PH",
    "gn:dem":37,
    "gn:feature_class":"P",
    "gn:feature_code":"PPL",
    "gn:name":"Pancovie",
    "gn:population":0,
    "gn:timezone":"Asia/Manila",
    "iso:country":"PH",
    "name:fil_x_preferred":[
        "Pancovie"
    ],
    "wof:name":"Pancovie",
    "wof:placetype":"locality"
},
  "geometry": {"coordinates":[117.80777999999999,8.80944],"type":"Point"}
}