{
  "type": "Feature",
  "properties": {
    "gn:admin1_code":"11",
    "gn:admin2_code":"70",
    "gn:asciiname":"Ladol",
    "gn:country_code":"PH",
    "gn:dem":15,
    "gn:feature_class":"P",
    "gn:feature_code":"PPL",
    "gn:name":"Ladol",
    "gn:population":0,
    "gn:timezone":"Asia/Manila",
    "iso:country":"PH",
    "wof:name":"Ladol",
    "wof:placetype":"locality"
},
  "geometry": {"coordinates":[125.24444,6.10639],"type":"Point"}
}