{
  "type": "Feature",
  "properties": {
    "gn:admin1_code":"10",
    "gn:admin2_code":"42",
    "gn:admin3_code":"104210000.0",
    "gn:asciiname":"Karongan",
    "gn:country_code":"PH",
    "gn:dem":38,
    "gn:feature_class":"P",
    "gn:feature_code":"PPL",
    "gn:name":"Karongan",
    "gn:population":0,
    "gn:timezone":"Asia/Manila",
    "iso:country":"PH",
    "name:fil_x_preferred":[
        "Karongan"
    ],
    "name:und_x_variant":[
        "Karangan"
    ],
    "wof:name":"Karongan",
    "wof:placetype":"locality"
},
  "geometry": {"coordinates":[123.8207,8.1612],"type":"Point"}
}