{
  "type": "Feature",
  "properties": {
    "gn:admin1_code":"03",
    "gn:admin2_code":"47",
    "gn:admin3_code":"34931000.0",
    "gn:asciiname":"Culiat",
    "gn:country_code":"PH",
    "gn:dem":55,
    "gn:feature_class":"P",
    "gn:feature_code":"PPL",
    "gn:name":"Culiat",
    "gn:population":0,
    "gn:timezone":"Asia/Manila",
    "iso:country":"PH",
    "wof:name":"Culiat",
    "wof:placetype":"locality"
},
  "geometry": {"coordinates":[120.83654,15.72132],"type":"Point"}
}