{
  "type": "Feature",
  "properties": {
    "gn:admin1_code":"06",
    "gn:admin2_code":"H3",
    "gn:admin3_code":"64515000.0",
    "gn:asciiname":"Linao",
    "gn:country_code":"PH",
    "gn:dem":13,
    "gn:feature_class":"P",
    "gn:feature_code":"PPL",
    "gn:name":"Linao",
    "gn:population":0,
    "gn:timezone":"Asia/Manila",
    "iso:country":"PH",
    "name:fil_x_preferred":[
        "Linao"
    ],
    "wof:name":"Linao",
    "wof:placetype":"locality"
},
  "geometry": {"coordinates":[122.7941,9.9829],"type":"Point"}
}