{
  "type": "Feature",
  "properties": {
    "gn:admin1_code":"07",
    "gn:admin2_code":"11",
    "gn:admin3_code":"71211000.0",
    "gn:asciiname":"Buyoan",
    "gn:cc2":"PH",
    "gn:country_code":"PH",
    "gn:dem":14,
    "gn:feature_class":"P",
    "gn:feature_code":"PPL",
    "gn:name":"Buyoan",
    "gn:population":0,
    "gn:timezone":"Asia/Manila",
    "iso:country":"PH",
    "name:und_x_variant":[
        "Buyuan",
        "Buyoan"
    ],
    "wof:name":"Buyoan",
    "wof:placetype":"locality"
},
  "geometry": {"coordinates":[124.48193999999999,9.83667],"type":"Point"}
}