{
  "type": "Feature",
  "properties": {
    "gn:admin1_code":"41",
    "gn:admin2_code":"54",
    "gn:admin3_code":"175908000.0",
    "gn:asciiname":"Ilaya",
    "gn:country_code":"PH",
    "gn:dem":175,
    "gn:feature_class":"P",
    "gn:feature_code":"PPL",
    "gn:name":"Ilaya",
    "gn:population":0,
    "gn:timezone":"Asia/Manila",
    "iso:country":"PH",
    "name:fil_x_preferred":[
        "Ilaya"
    ],
    "wof:name":"Ilaya",
    "wof:placetype":"locality"
},
  "geometry": {"coordinates":[122.47060999999999,12.46973],"type":"Point"}
}