{
  "type": "Feature",
  "properties": {
    "gn:country":"PH",
    "gn:fcode":"PPLA3",
    "gn:pop":9720,
    "iso:country":"PH",
    "name:bcl_x_preferred":[
        "Laurel"
    ],
    "name:cat_x_preferred":[
        "Laurel"
    ],
    "name:ceb_x_preferred":[
        "Laurel"
    ],
    "name:deu_x_preferred":[
        "Laurel"
    ],
    "name:eng_x_preferred":[
        "Laurel"
    ],
    "name:fra_x_preferred":[
        "Laurel"
    ],
    "name:ilo_x_preferred":[
        "Laurel"
    ],
    "name:ind_x_preferred":[
        "Laurel"
    ],
    "name:ita_x_preferred":[
        "Laurel"
    ],
    "name:nld_x_preferred":[
        "Laurel"
    ],
    "name:oci_x_preferred":[
        "Laurel"
    ],
    "name:pag_x_preferred":[
        "Laurel"
    ],
    "name:pam_x_preferred":[
        "Laurel"
    ],
    "name:spa_x_preferred":[
        "Laurel"
    ],
    "name:tgl_x_preferred":[
        "Laurel"
    ],
    "name:urd_x_preferred":[
        "\u0644\u0627\u0648\u0631\u06cc\u0644"
    ],
    "name:vie_x_preferred":[
        "Laurel"
    ],
    "name:war_x_preferred":[
        "Laurel"
    ],
    "qs:name":"Laurel",
    "qs:photos_9r":0,
    "qs:photos_sr":0,
    "qs:pop_sr":"5",
    "wd:wordcount":444,
    "wof:name":"Laurel",
    "wof:placetype":"locality",
    "wof:population":9720
},
  "geometry": {"coordinates":[120.91932,14.05542],"type":"Point"}
}