{
  "type": "Feature",
  "properties": {
    "gn:admin1_code":"03",
    "gn:admin2_code":"50",
    "gn:admin3_code":"35404000.0",
    "gn:asciiname":"Mesalipit",
    "gn:country_code":"PH",
    "gn:dem":8,
    "gn:feature_class":"P",
    "gn:feature_code":"PPL",
    "gn:name":"Mesalipit",
    "gn:population":0,
    "gn:timezone":"Asia/Manila",
    "iso:country":"PH",
    "name:fil_x_preferred":[
        "Mesalipit"
    ],
    "wof:name":"Mesalipit",
    "wof:placetype":"locality"
},
  "geometry": {"coordinates":[120.67289,14.98615],"type":"Point"}
}