{
  "type": "Feature",
  "properties": {
    "gn:admin1_code":"01",
    "gn:admin2_code":"29",
    "gn:admin3_code":"12902000.0",
    "gn:asciiname":"Bisangol",
    "gn:country_code":"PH",
    "gn:dem":27,
    "gn:feature_class":"P",
    "gn:feature_code":"PPL",
    "gn:name":"Bisangol",
    "gn:population":0,
    "gn:timezone":"Asia/Manila",
    "iso:country":"PH",
    "name:fil_x_preferred":[
        "Bisangol"
    ],
    "wof:name":"Bisangol",
    "wof:placetype":"locality"
},
  "geometry": {"coordinates":[120.47852,17.24261],"type":"Point"}
}