{
  "type": "Feature",
  "properties": {
    "gn:admin1_code":"40",
    "gn:admin2_code":"20",
    "gn:admin3_code":"42106000.0",
    "gn:asciiname":"Bukal",
    "gn:country_code":"PH",
    "gn:dem":179,
    "gn:feature_class":"P",
    "gn:feature_code":"PPL",
    "gn:name":"Bukal",
    "gn:population":0,
    "gn:timezone":"Asia/Manila",
    "iso:country":"PH",
    "name:ceb_x_preferred":[
        "Bukal"
    ],
    "name:fil_x_preferred":[
        "Bukal"
    ],
    "wof:name":"Bukal",
    "wof:placetype":"locality"
},
  "geometry": {"coordinates":[120.96062000000001,14.28402],"type":"Point"}
}