{
  "type": "Feature",
  "properties": {
    "gn:admin1_code":"01",
    "gn:admin2_code":"29",
    "gn:admin3_code":"12934000.0",
    "gn:asciiname":"Ayusan Norte",
    "gn:country_code":"PH",
    "gn:dem":4,
    "gn:feature_class":"P",
    "gn:feature_code":"PPL",
    "gn:name":"Ayusan Norte",
    "gn:population":0,
    "gn:timezone":"Asia/Manila",
    "iso:country":"PH",
    "name:fil_x_preferred":[
        "Ayusan Norte"
    ],
    "wof:name":"Ayusan Norte",
    "wof:placetype":"locality"
},
  "geometry": {"coordinates":[120.37512,17.57223],"type":"Point"}
}