{
  "type": "Feature",
  "properties": {
    "gn:admin1_code":"02",
    "gn:admin2_code":"14",
    "gn:admin3_code":"21516000.0",
    "gn:asciiname":"Fabrica",
    "gn:country_code":"PH",
    "gn:dem":7,
    "gn:feature_class":"P",
    "gn:feature_code":"PPL",
    "gn:name":"Fabrica",
    "gn:population":0,
    "gn:timezone":"Asia/Manila",
    "iso:country":"PH",
    "name:fil_x_preferred":[
        "Fabrica"
    ],
    "name:fil_x_variant":[
        "Malanao"
    ],
    "name:und_x_variant":[
        "Malanao"
    ],
    "wof:name":"Fabrica",
    "wof:placetype":"locality"
},
  "geometry": {"coordinates":[121.64675,18.20248],"type":"Point"}
}