{
  "type": "Feature",
  "properties": {
    "gn:country":"PH",
    "gn:fcode":"PPL",
    "gn:population":3641,
    "iso:country":"PH",
    "name:fil_x_preferred":[
        "Lobong"
    ],
    "qs:name":"Lobong",
    "qs:photos_9r":0,
    "qs:photos_sr":0,
    "qs:pop_sr":"4",
    "wof:name":"Lobong",
    "wof:placetype":"locality",
    "wof:population":3641
},
  "geometry": {"coordinates":[120.4704,16.0815],"type":"Point"}
}