{
  "type": "Feature",
  "properties": {
    "gn:admin1_code":"05",
    "gn:admin2_code":"39",
    "gn:admin3_code":"54104000.0",
    "gn:asciiname":"Panicijan",
    "gn:country_code":"PH",
    "gn:dem":5,
    "gn:feature_class":"P",
    "gn:feature_code":"PPL",
    "gn:name":"Panicijan",
    "gn:population":0,
    "gn:timezone":"Asia/Manila",
    "iso:country":"PH",
    "name:fil_x_preferred":[
        "Panicijan"
    ],
    "name:und_x_variant":[
        "Panisihan"
    ],
    "wof:name":"Panicijan",
    "wof:placetype":"locality"
},
  "geometry": {"coordinates":[123.77370000000001,12.4141],"type":"Point"}
}