{
  "type": "Feature",
  "properties": {
    "gn:admin1_code":"10",
    "gn:admin2_code":"34",
    "gn:admin3_code":"103504000.0",
    "gn:asciiname":"Saray",
    "gn:country_code":"PH",
    "gn:dem":6,
    "gn:feature_class":"P",
    "gn:feature_code":"PPL",
    "gn:name":"Saray",
    "gn:population":0,
    "gn:timezone":"Asia/Manila",
    "iso:country":"PH",
    "name:und_x_variant":[
        "Tibanga Saray"
    ],
    "wof:name":"Saray",
    "wof:placetype":"locality"
},
  "geometry": {"coordinates":[124.24332,8.24014],"type":"Point"}
}