{
  "type": "Feature",
  "properties": {
    "gn:admin1_code":"03",
    "gn:admin2_code":"47",
    "gn:admin3_code":"34908000.0",
    "gn:asciiname":"Malimba",
    "gn:country_code":"PH",
    "gn:dem":21,
    "gn:feature_class":"P",
    "gn:feature_code":"PPL",
    "gn:name":"Malimba",
    "gn:population":0,
    "gn:timezone":"Asia/Manila",
    "iso:country":"PH",
    "name:fil_x_preferred":[
        "Malimba"
    ],
    "wof:name":"Malimba",
    "wof:placetype":"locality"
},
  "geometry": {"coordinates":[120.95142,15.25477],"type":"Point"}
}