{
  "type": "Feature",
  "properties": {
    "iso:country":"PH",
    "name:bcl_x_preferred":[
        "Can-avid"
    ],
    "name:cbk_zam_x_preferred":[
        "Can-avid"
    ],
    "name:ceb_x_preferred":[
        "Can-avid"
    ],
    "name:deu_x_preferred":[
        "Can-avid"
    ],
    "name:eng_x_preferred":[
        "Can-avid"
    ],
    "name:fra_x_preferred":[
        "Can-avid"
    ],
    "name:ilo_x_preferred":[
        "Can-avid"
    ],
    "name:ind_x_preferred":[
        "Can-avid"
    ],
    "name:ita_x_preferred":[
        "Can-avid"
    ],
    "name:nld_x_preferred":[
        "Can-avid"
    ],
    "name:nob_x_preferred":[
        "Can-avid"
    ],
    "name:nor_x_preferred":[
        "Can-avid"
    ],
    "name:pag_x_preferred":[
        "Can-avid"
    ],
    "name:pag_x_variant":[
        "Can-Avid"
    ],
    "name:pam_x_preferred":[
        "Can-avid"
    ],
    "name:swe_x_preferred":[
        "Can-avid"
    ],
    "name:tgl_x_preferred":[
        "Can-avid"
    ],
    "name:unk_x_variant":[
        "Kanavid"
    ],
    "name:vie_x_preferred":[
        "Can-avid"
    ],
    "name:war_x_preferred":[
        "Can-avid"
    ],
    "qs:gn_country":"PH",
    "qs:gn_fcode":"PPLA3",
    "qs:gn_pop":5928,
    "qs:name":"Can-Avid",
    "qs:name_adm0":"Philippines",
    "qs:name_adm1":"Eastern Visayas",
    "qs:photos":0,
    "qs:photos_1k":0,
    "qs:photos_9k":1,
    "qs:photos_9r":1,
    "qs:photos_all":2,
    "qs:photos_sr":0,
    "qs:placetype":"Town",
    "qs:pop_sr":"5",
    "qs:woe_adm0":23424934,
    "wd:wordcount":221,
    "wof:name":"Can-Avid",
    "wof:placetype":"locality",
    "wof:population":5928
},
  "geometry": {"coordinates":[125.44722,11.99528],"type":"Point"}
}