{
  "type": "Feature",
  "properties": {
    "gn:admin1_code":"13",
    "gn:admin2_code":"I9",
    "gn:admin3_code":"168505000.0",
    "gn:asciiname":"Cambinlio",
    "gn:country_code":"PH",
    "gn:dem":0,
    "gn:feature_class":"P",
    "gn:feature_code":"PPL",
    "gn:name":"Cambinlio",
    "gn:population":0,
    "gn:timezone":"Asia/Manila",
    "iso:country":"PH",
    "name:fil_x_preferred":[
        "Cambinlio"
    ],
    "wof:name":"Cambinlio",
    "wof:placetype":"locality"
},
  "geometry": {"coordinates":[125.5986,10.3621],"type":"Point"}
}