{
  "type": "Feature",
  "properties": {
    "gn:admin1_code":"05",
    "gn:admin2_code":"16",
    "gn:admin3_code":"51728000.0",
    "gn:asciiname":"Ayan",
    "gn:country_code":"PH",
    "gn:dem":21,
    "gn:feature_class":"P",
    "gn:feature_code":"PPL",
    "gn:name":"Ayan",
    "gn:population":0,
    "gn:timezone":"Asia/Manila",
    "iso:country":"PH",
    "name:fil_x_preferred":[
        "Ayan"
    ],
    "wof:name":"Ayan",
    "wof:placetype":"locality"
},
  "geometry": {"coordinates":[123.28333000000001,13.53333],"type":"Point"}
}