{
  "type": "Feature",
  "properties": {
    "gn:admin1_code":"06",
    "gn:admin2_code":"H3",
    "gn:admin3_code":"64514000.0",
    "gn:asciiname":"Milagrosa",
    "gn:country_code":"PH",
    "gn:dem":20,
    "gn:feature_class":"P",
    "gn:feature_code":"PPL",
    "gn:name":"Milagrosa",
    "gn:population":0,
    "gn:timezone":"Asia/Manila",
    "iso:country":"PH",
    "name:fil_x_preferred":[
        "Milagrosa"
    ],
    "wof:name":"Milagrosa",
    "wof:placetype":"locality"
},
  "geometry": {"coordinates":[122.96980000000001,10.2385],"type":"Point"}
}