{
  "type": "Feature",
  "properties": {
    "gn:admin1_code":"09",
    "gn:admin2_code":"66",
    "gn:admin3_code":"97313000.0",
    "gn:asciiname":"Balubo",
    "gn:country_code":"PH",
    "gn:dem":261,
    "gn:feature_class":"P",
    "gn:feature_code":"PPL",
    "gn:name":"Balubo",
    "gn:population":0,
    "gn:timezone":"Asia/Manila",
    "iso:country":"PH",
    "wof:name":"Balubo",
    "wof:placetype":"locality"
},
  "geometry": {"coordinates":[123.20722000000001,7.69833],"type":"Point"}
}