{
  "type": "Feature",
  "properties": {
    "gn:admin1_code":"06",
    "gn:admin2_code":"04",
    "gn:admin3_code":"60405000.0",
    "gn:asciiname":"Tigum",
    "gn:country_code":"PH",
    "gn:dem":81,
    "gn:feature_class":"P",
    "gn:feature_code":"PPL",
    "gn:name":"Tigum",
    "gn:population":0,
    "gn:timezone":"Asia/Manila",
    "iso:country":"PH",
    "name:fil_x_preferred":[
        "Tigum"
    ],
    "wof:name":"Tigum",
    "wof:placetype":"locality"
},
  "geometry": {"coordinates":[121.88549999999999,11.8169],"type":"Point"}
}