{
  "type": "Feature",
  "properties": {
    "gn:admin1_code":"12",
    "gn:admin2_code":"70",
    "gn:admin3_code":"126319000.0",
    "gn:asciiname":"Siluton",
    "gn:country_code":"PH",
    "gn:dem":672,
    "gn:feature_class":"P",
    "gn:feature_code":"PPL",
    "gn:name":"Siluton",
    "gn:population":0,
    "gn:timezone":"Asia/Manila",
    "iso:country":"PH",
    "name:fil_x_preferred":[
        "Siluton"
    ],
    "wof:name":"Siluton",
    "wof:placetype":"locality"
},
  "geometry": {"coordinates":[124.72863,6.22999],"type":"Point"}
}