{
  "type": "Feature",
  "properties": {
    "gn:admin1_code":"15",
    "gn:admin2_code":"44",
    "gn:admin3_code":"144405000.0",
    "gn:asciiname":"Balangao",
    "gn:country_code":"PH",
    "gn:dem":938,
    "gn:feature_class":"P",
    "gn:feature_code":"PPL",
    "gn:name":"Balangao",
    "gn:population":0,
    "gn:timezone":"Asia/Manila",
    "iso:country":"PH",
    "name:fil_x_preferred":[
        "Balengao"
    ],
    "name:fil_x_variant":[
        "Balangao"
    ],
    "wof:name":"Balangao",
    "wof:placetype":"locality"
},
  "geometry": {"coordinates":[121.27464000000001,17.10694],"type":"Point"}
}