{
  "type": "Feature",
  "properties": {
    "gn:admin1_code":"40",
    "gn:admin2_code":"H2",
    "gn:admin3_code":"45618000.0",
    "gn:asciiname":"Dankalan-Caimawan",
    "gn:country_code":"PH",
    "gn:dem":12,
    "gn:feature_class":"P",
    "gn:feature_code":"PPL",
    "gn:name":"Dankalan-Caimawan",
    "gn:population":0,
    "gn:timezone":"Asia/Manila",
    "iso:country":"PH",
    "name:fil_x_preferred":[
        "Dankalan-Caimawan"
    ],
    "wof:name":"Dankalan-Caimawan",
    "wof:placetype":"locality"
},
  "geometry": {"coordinates":[122.48099999999999,13.8542],"type":"Point"}
}