{
  "type": "Feature",
  "properties": {
    "gn:admin1_code":"06",
    "gn:admin2_code":"06",
    "gn:admin3_code":"60606000.0",
    "gn:asciiname":"Jalandoni",
    "gn:country_code":"PH",
    "gn:dem":6,
    "gn:feature_class":"P",
    "gn:feature_code":"PPL",
    "gn:name":"Jalandoni",
    "gn:population":0,
    "gn:timezone":"Asia/Manila",
    "iso:country":"PH",
    "name:fil_x_preferred":[
        "Jalandoni"
    ],
    "wof:name":"Jalandoni",
    "wof:placetype":"locality"
},
  "geometry": {"coordinates":[122.05371,11.41391],"type":"Point"}
}