{
  "type": "Feature",
  "properties": {
    "gn:admin1_code":"01",
    "gn:admin2_code":"51",
    "gn:admin3_code":"15515000.0",
    "gn:asciiname":"Bolawen",
    "gn:country_code":"PH",
    "gn:dem":8,
    "gn:feature_class":"P",
    "gn:feature_code":"PPL",
    "gn:name":"Bolawen",
    "gn:population":0,
    "gn:timezone":"Asia/Manila",
    "iso:country":"PH",
    "name:fil_x_preferred":[
        "Bolawen"
    ],
    "wof:name":"Bolawen",
    "wof:placetype":"locality"
},
  "geometry": {"coordinates":[120.2287,15.932],"type":"Point"}
}