{
  "type": "Feature",
  "properties": {
    "gn:admin1_code":"01",
    "gn:admin2_code":"28",
    "gn:admin3_code":"12812000.0",
    "gn:asciiname":"Balacad",
    "gn:country_code":"PH",
    "gn:dem":20,
    "gn:feature_class":"P",
    "gn:feature_code":"PPL",
    "gn:name":"Balacad",
    "gn:population":0,
    "gn:timezone":"Asia/Manila",
    "iso:country":"PH",
    "name:fil_x_preferred":[
        "Balacad"
    ],
    "wof:name":"Balacad",
    "wof:placetype":"locality"
},
  "geometry": {"coordinates":[120.55370000000001,18.1553],"type":"Point"}
}