{
  "type": "Feature",
  "properties": {
    "gn:admin1_code":"01",
    "gn:admin2_code":"28",
    "gn:admin3_code":"12819000.0",
    "gn:asciiname":"Tapaa",
    "gn:country_code":"PH",
    "gn:dem":24,
    "gn:feature_class":"P",
    "gn:feature_code":"PPL",
    "gn:name":"Tapaa",
    "gn:population":0,
    "gn:timezone":"Asia/Manila",
    "iso:country":"PH",
    "name:fil_x_preferred":[
        "Tapaa"
    ],
    "wof:name":"Tapaa",
    "wof:placetype":"locality"
},
  "geometry": {"coordinates":[120.49250000000001,17.9679],"type":"Point"}
}