{
  "type": "Feature",
  "properties": {
    "gn:country":"PH",
    "gn:fcode":"PPL",
    "gn:pop":2298,
    "iso:country":"PH",
    "name:cat_x_preferred":[
        "Lais"
    ],
    "name:ceb_x_preferred":[
        "Lais"
    ],
    "name:ces_x_preferred":[
        "Lais"
    ],
    "name:deu_x_preferred":[
        "Lais"
    ],
    "name:fil_x_preferred":[
        "Lais"
    ],
    "name:fra_x_preferred":[
        "Lais"
    ],
    "name:ind_x_preferred":[
        "Lais"
    ],
    "name:ita_x_preferred":[
        "Lais"
    ],
    "name:nld_x_preferred":[
        "Lais"
    ],
    "name:pol_x_preferred":[
        "Lais"
    ],
    "name:por_x_preferred":[
        "La\u00eds"
    ],
    "name:spa_x_preferred":[
        "Lais"
    ],
    "name:swe_x_preferred":[
        "Lais"
    ],
    "name:unk_x_variant":[
        "Lias"
    ],
    "qs:name":"Lais",
    "qs:photos_9r":0,
    "qs:photos_sr":0,
    "qs:pop_sr":"4",
    "wof:name":"Lais",
    "wof:placetype":"locality",
    "wof:population":2298
},
  "geometry": {"coordinates":[125.64639,6.33278],"type":"Point"}
}