{
  "type": "Feature",
  "properties": {
    "gn:admin1_code":"07",
    "gn:admin2_code":"21",
    "gn:admin3_code":"72222000.0",
    "gn:asciiname":"Langkas",
    "gn:country_code":"PH",
    "gn:dem":647,
    "gn:feature_class":"P",
    "gn:feature_code":"PPL",
    "gn:name":"Langkas",
    "gn:population":0,
    "gn:timezone":"Asia/Manila",
    "iso:country":"PH",
    "name:fil_x_preferred":[
        "Langkas"
    ],
    "wof:name":"Langkas",
    "wof:placetype":"locality"
},
  "geometry": {"coordinates":[123.46575,9.79256],"type":"Point"}
}