{
  "type": "Feature",
  "properties": {
    "gn:admin1_code":"12",
    "gn:admin2_code":"57",
    "gn:admin3_code":"124704000.0",
    "gn:asciiname":"Singao",
    "gn:country_code":"PH",
    "gn:dem":205,
    "gn:feature_class":"P",
    "gn:feature_code":"PPL",
    "gn:name":"Singao",
    "gn:population":0,
    "gn:timezone":"Asia/Manila",
    "iso:country":"PH",
    "name:fil_x_preferred":[
        "Singao"
    ],
    "wof:name":"Singao",
    "wof:placetype":"locality"
},
  "geometry": {"coordinates":[125.06722000000001,6.99917],"type":"Point"}
}