{
  "type": "Feature",
  "properties": {
    "gn:admin1_code":"07",
    "gn:admin2_code":"21",
    "gn:admin3_code":"72241000.0",
    "gn:asciiname":"Banakay",
    "gn:country_code":"PH",
    "gn:dem":133,
    "gn:feature_class":"P",
    "gn:feature_code":"PPL",
    "gn:name":"Banakay",
    "gn:population":0,
    "gn:timezone":"Asia/Manila",
    "iso:country":"PH",
    "name:fil_x_preferred":[
        "Banakay"
    ],
    "name:und_x_variant":[
        "Bagakay"
    ],
    "wof:name":"Banakay",
    "wof:placetype":"locality"
},
  "geometry": {"coordinates":[123.6523,10.17118],"type":"Point"}
}