{
  "type": "Feature",
  "properties": {
    "gn:country":"PH",
    "gn:fcode":"PPL",
    "gn:pop":5031,
    "iso:country":"PH",
    "name:bcl_x_preferred":[
        "Sto. Domingo"
    ],
    "name:deu_x_preferred":[
        "Santo Domingo"
    ],
    "name:eng_x_preferred":[
        "Santo Domingo"
    ],
    "name:fil_x_preferred":[
        "Santo Domingo"
    ],
    "name:fra_x_preferred":[
        "Santo Domingo"
    ],
    "name:ilo_x_preferred":[
        "Santo Domingo"
    ],
    "name:ind_x_preferred":[
        "Santo Domingo"
    ],
    "name:ita_x_preferred":[
        "Santo Domingo"
    ],
    "name:nld_x_preferred":[
        "Santo Domingo"
    ],
    "name:nob_x_preferred":[
        "Santo Domingo"
    ],
    "name:pag_x_preferred":[
        "Santo Domingo"
    ],
    "name:pam_x_preferred":[
        "Santo Domingo"
    ],
    "name:spa_x_preferred":[
        "Santo Domingo"
    ],
    "name:swe_x_preferred":[
        "Santo Domingo"
    ],
    "name:tgl_x_preferred":[
        "Santo Domingo"
    ],
    "name:vie_x_preferred":[
        "Santo Domingo"
    ],
    "name:war_x_preferred":[
        "Santo Domingo"
    ],
    "qs:name":"Santo Domingo",
    "qs:photos_9r":0,
    "qs:photos_sr":0,
    "qs:pop_sr":"5",
    "wd:elevation":14.0,
    "wd:wordcount":5634,
    "wof:name":"Santo Domingo",
    "wof:placetype":"locality",
    "wof:population":5031
},
  "geometry": {"coordinates":[123.4486,13.42],"type":"Point"}
}