{
  "type": "Feature",
  "properties": {
    "gn:country":"PH",
    "gn:fcode":"PPL",
    "gn:population":5031,
    "iso:country":"PH",
    "name:bcl_x_preferred":[
        "Sto. Domingo"
    ],
    "name:bcl_x_variant":[
        "Santo Domingo"
    ],
    "name:ceb_x_preferred":[
        "Santo Domingo"
    ],
    "name:deu_x_preferred":[
        "Santo Domingo"
    ],
    "name:eng_x_preferred":[
        "Santo Domingo"
    ],
    "name:fil_x_preferred":[
        "Santo Domingo"
    ],
    "name:fra_x_preferred":[
        "Santo Domingo"
    ],
    "name:gor_x_preferred":[
        "Santo Domingo"
    ],
    "name:ilo_x_preferred":[
        "Santo Domingo"
    ],
    "name:ind_x_preferred":[
        "Santo Domingo"
    ],
    "name:ita_x_preferred":[
        "Santo Domingo"
    ],
    "name:jpn_x_preferred":[
        "\u30b5\u30f3\u30c8\u30fb\u30c9\u30df\u30f3\u30b4"
    ],
    "name:nld_x_preferred":[
        "Santo Domingo"
    ],
    "name:nob_x_preferred":[
        "Santo Domingo"
    ],
    "name:pag_x_preferred":[
        "Santo Domingo"
    ],
    "name:pam_x_preferred":[
        "Santo Domingo"
    ],
    "name:spa_x_preferred":[
        "Santo Domingo"
    ],
    "name:swe_x_preferred":[
        "Santo Domingo"
    ],
    "name:tgl_x_preferred":[
        "Santo Domingo"
    ],
    "name:urd_x_preferred":[
        "\u0633\u0627\u0646\u062a\u0648 \u062f\u0648\u0645\u06cc\u0646\u06af\u0648"
    ],
    "name:vie_x_preferred":[
        "Santo Domingo"
    ],
    "name:war_x_preferred":[
        "Santo Domingo"
    ],
    "qs:name":"Santo Domingo",
    "qs:photos_9r":0,
    "qs:photos_sr":0,
    "qs:pop_sr":"5",
    "wd:elevation":14.0,
    "wd:wordcount":5634,
    "wof:name":"Santo Domingo",
    "wof:placetype":"locality",
    "wof:population":5031
},
  "geometry": {"coordinates":[123.4486,13.42],"type":"Point"}
}