{
  "type": "Feature",
  "properties": {
    "gn:admin1_code":"10",
    "gn:admin2_code":"43",
    "gn:asciiname":"Kamatayan",
    "gn:cc2":"PH",
    "gn:country_code":"PH",
    "gn:dem":-9999,
    "gn:feature_class":"P",
    "gn:feature_code":"PPL",
    "gn:name":"Kamatayan",
    "gn:population":0,
    "gn:timezone":"Asia/Manila",
    "iso:country":"PH",
    "name:und_x_variant":[
        "Camatayan",
        "Kamatayan"
    ],
    "wof:name":"Kamatayan",
    "wof:placetype":"locality"
},
  "geometry": {"coordinates":[124.73333,8.68333],"type":"Point"}
}