{
  "type": "Feature",
  "properties": {
    "gn:admin1_code":"11",
    "gn:admin2_code":"I7",
    "gn:admin3_code":"112317000.0",
    "gn:asciiname":"Tagbaobo",
    "gn:country_code":"PH",
    "gn:dem":180,
    "gn:feature_class":"P",
    "gn:feature_code":"PPL",
    "gn:name":"Tagbaobo",
    "gn:population":0,
    "gn:timezone":"Asia/Manila",
    "iso:country":"PH",
    "name:fil_x_preferred":[
        "Tagbaobo"
    ],
    "wof:name":"Tagbaobo",
    "wof:placetype":"locality"
},
  "geometry": {"coordinates":[125.76611,7.02833],"type":"Point"}
}