{
  "type": "Feature",
  "properties": {
    "gn:admin1_code":"10",
    "gn:admin2_code":"34",
    "gn:admin3_code":"103504000.0",
    "gn:asciiname":"Tubaran",
    "gn:country_code":"PH",
    "gn:dem":28,
    "gn:feature_class":"P",
    "gn:feature_code":"PPL",
    "gn:name":"Tubaran",
    "gn:population":0,
    "gn:timezone":"Asia/Manila",
    "iso:country":"PH",
    "name:bcl_x_preferred":[
        "Tubaran"
    ],
    "name:ceb_x_preferred":[
        "Tubaran"
    ],
    "name:deu_x_preferred":[
        "Tubaran"
    ],
    "name:fas_x_preferred":[
        "\u062a\u0648\u0628\u0627\u0631\u0627\u0646"
    ],
    "name:fra_x_preferred":[
        "Tubaran"
    ],
    "name:ilo_x_preferred":[
        "Tubaran"
    ],
    "name:ind_x_preferred":[
        "Tubaran"
    ],
    "name:ita_x_preferred":[
        "Tubaran"
    ],
    "name:nld_x_preferred":[
        "Tubaran"
    ],
    "name:pag_x_preferred":[
        "Tubaran"
    ],
    "name:pam_x_preferred":[
        "Tubaran"
    ],
    "name:swe_x_preferred":[
        "Tubaran"
    ],
    "name:tgl_x_preferred":[
        "Tubaran"
    ],
    "name:urd_x_preferred":[
        "\u062a\u0648\u0628\u0627\u0631\u0627\u0646"
    ],
    "name:vie_x_preferred":[
        "Tubaran"
    ],
    "name:war_x_preferred":[
        "Tubaran"
    ],
    "wof:name":"Tubaran",
    "wof:placetype":"locality"
},
  "geometry": {"coordinates":[124.28917,8.25944],"type":"Point"}
}