{
  "type": "Feature",
  "properties": {
    "gn:admin1_code":"15",
    "gn:admin2_code":"H6",
    "gn:admin3_code":"148105000.0",
    "gn:asciiname":"Lappa",
    "gn:country_code":"PH",
    "gn:dem":66,
    "gn:feature_class":"P",
    "gn:feature_code":"PPL",
    "gn:name":"Lappa",
    "gn:population":0,
    "gn:timezone":"Asia/Manila",
    "iso:country":"PH",
    "name:ceb_x_preferred":[
        "Lappa"
    ],
    "name:fil_x_preferred":[
        "Lappa"
    ],
    "wof:name":"Lappa",
    "wof:placetype":"locality"
},
  "geometry": {"coordinates":[121.33784,18.33902],"type":"Point"}
}