{
  "type": "Feature",
  "properties": {
    "gn:gn_country":"PH",
    "gn:gn_fcode":"PPL",
    "gn:gn_pop":2504,
    "gn:population":2504,
    "iso:country":"PH",
    "name:fil_x_preferred":[
        "Anambongan"
    ],
    "qs_pg:aaroncc":"PH",
    "qs_pg:gn_country":"PH",
    "qs_pg:gn_fcode":"PPL",
    "qs_pg:gn_pop":2504,
    "qs_pg:name":"Anambongan",
    "qs_pg:photos_9r":0,
    "qs_pg:photos_sr":0,
    "qs_pg:pop_sr":4,
    "qs_pg:qs_pg_placetype":"locality",
    "wof:name":"Anambongan",
    "wof:placetype":"locality",
    "wof:population":2504
},
  "geometry": {"coordinates":[120.38858,15.86634],"type":"Point"}
}