{
  "type": "Feature",
  "properties": {
    "gn:admin1_code":"05",
    "gn:admin2_code":"39",
    "gn:admin3_code":"54118000.0",
    "gn:asciiname":"Guintadan",
    "gn:country_code":"PH",
    "gn:dem":38,
    "gn:feature_class":"P",
    "gn:feature_code":"PPL",
    "gn:name":"Guintadan",
    "gn:population":0,
    "gn:timezone":"Asia/Manila",
    "iso:country":"PH",
    "name:fil_x_preferred":[
        "Guintadan"
    ],
    "wof:name":"Guintadan",
    "wof:placetype":"locality"
},
  "geometry": {"coordinates":[123.767,12.4735],"type":"Point"}
}