{
  "type": "Feature",
  "properties": {
    "gn:admin1_code":"08",
    "gn:admin2_code":"55",
    "gn:admin3_code":"86003000.0",
    "gn:asciiname":"Enora",
    "gn:country_code":"PH",
    "gn:dem":20,
    "gn:feature_class":"P",
    "gn:feature_code":"PPL",
    "gn:name":"Enora",
    "gn:population":0,
    "gn:timezone":"Asia/Manila",
    "iso:country":"PH",
    "name:bre_x_preferred":[
        "Enora"
    ],
    "name:fil_x_preferred":[
        "Enora"
    ],
    "name:fra_x_preferred":[
        "Enora"
    ],
    "wof:name":"Enora",
    "wof:placetype":"locality"
},
  "geometry": {"coordinates":[124.5793,12.0731],"type":"Point"}
}