{
  "type": "Feature",
  "properties": {
    "gn:admin1_code":"05",
    "gn:admin2_code":"16",
    "gn:admin3_code":"51737000.0",
    "gn:asciiname":"Daigan",
    "gn:country_code":"PH",
    "gn:dem":6,
    "gn:feature_class":"P",
    "gn:feature_code":"PPL",
    "gn:name":"Daigan",
    "gn:population":0,
    "gn:timezone":"Asia/Manila",
    "iso:country":"PH",
    "name:fil_x_preferred":[
        "Daigan"
    ],
    "name:und_x_variant":[
        "Daligan"
    ],
    "wof:name":"Daigan",
    "wof:placetype":"locality"
},
  "geometry": {"coordinates":[123.31100000000001,13.9315],"type":"Point"}
}