{
  "type": "Feature",
  "properties": {
    "gn:admin1_code":"01",
    "gn:admin2_code":"29",
    "gn:admin3_code":"12912000.0",
    "gn:asciiname":"Miramar",
    "gn:country_code":"PH",
    "gn:dem":7,
    "gn:feature_class":"P",
    "gn:feature_code":"PPL",
    "gn:name":"Miramar",
    "gn:population":0,
    "gn:timezone":"Asia/Manila",
    "iso:country":"PH",
    "name:ara_x_preferred":[
        "\u0645\u064a\u0631\u0627\u0645\u0627\u0631"
    ],
    "name:cat_x_preferred":[
        "Miramar"
    ],
    "name:ceb_x_preferred":[
        "Miramar"
    ],
    "name:deu_x_preferred":[
        "Miramar"
    ],
    "name:fil_x_preferred":[
        "Miramar"
    ],
    "name:fra_x_preferred":[
        "Miramar"
    ],
    "name:glg_x_preferred":[
        "Miramar"
    ],
    "name:ita_x_preferred":[
        "Miramar"
    ],
    "name:jpn_x_preferred":[
        "\u30df\u30e9\u30de\u30fc"
    ],
    "name:lit_x_preferred":[
        "Miramaras"
    ],
    "name:nds_x_preferred":[
        "Miramar"
    ],
    "name:nld_x_preferred":[
        "Miramar"
    ],
    "name:pol_x_preferred":[
        "Miramar"
    ],
    "name:por_x_preferred":[
        "Miramar"
    ],
    "name:rus_x_preferred":[
        "\u041c\u0438\u0440\u0430\u043c\u0430\u0440"
    ],
    "name:spa_x_preferred":[
        "Miramar"
    ],
    "name:srp_x_preferred":[
        "\u041c\u0438\u0440\u0430\u043c\u0430\u0440"
    ],
    "name:swe_x_preferred":[
        "Miramar"
    ],
    "name:ukr_x_preferred":[
        "\u041c\u0456\u0440\u0430\u043c\u0430\u0440"
    ],
    "wof:name":"Miramar",
    "wof:placetype":"locality"
},
  "geometry": {"coordinates":[120.41367,17.70553],"type":"Point"}
}