{
  "type": "Feature",
  "properties": {
    "gn:admin1_code":"05",
    "gn:admin2_code":"16",
    "gn:admin3_code":"51718000.0",
    "gn:asciiname":"Ibit",
    "gn:country_code":"PH",
    "gn:dem":7,
    "gn:feature_class":"P",
    "gn:feature_code":"PPL",
    "gn:name":"Ibit",
    "gn:population":0,
    "gn:timezone":"Asia/Manila",
    "iso:country":"PH",
    "name:fil_x_preferred":[
        "Ibit"
    ],
    "name:und_x_variant":[
        "Ibig",
        "Ibid"
    ],
    "wof:name":"Ibit",
    "wof:placetype":"locality"
},
  "geometry": {"coordinates":[123.092,13.7031],"type":"Point"}
}