{
  "type": "Feature",
  "properties": {
    "gn:admin1_code":"11",
    "gn:admin2_code":"I6",
    "gn:admin3_code":"118203000.0",
    "gn:asciiname":"Lapinigan",
    "gn:country_code":"PH",
    "gn:dem":24,
    "gn:feature_class":"P",
    "gn:feature_code":"PPL",
    "gn:name":"Lapinigan",
    "gn:population":0,
    "gn:timezone":"Asia/Manila",
    "iso:country":"PH",
    "name:fil_x_preferred":[
        "Lapinigan"
    ],
    "name:und_x_variant":[
        "Lampinigan"
    ],
    "wof:name":"Lapinigan",
    "wof:placetype":"locality"
},
  "geometry": {"coordinates":[125.8545,7.3229],"type":"Point"}
}