{
  "type": "Feature",
  "properties": {
    "gn:admin1_code":"02",
    "gn:admin2_code":"14",
    "gn:admin3_code":"21519000.0",
    "gn:asciiname":"Bical",
    "gn:country_code":"PH",
    "gn:dem":55,
    "gn:feature_class":"P",
    "gn:feature_code":"PPL",
    "gn:name":"Bical",
    "gn:population":0,
    "gn:timezone":"Asia/Manila",
    "iso:country":"PH",
    "name:fil_x_preferred":[
        "Bical"
    ],
    "wof:name":"Bical",
    "wof:placetype":"locality"
},
  "geometry": {"coordinates":[121.82348,17.56705],"type":"Point"}
}