{
  "type": "Feature",
  "properties": {
    "gn:admin1_code":"14",
    "gn:admin2_code":"56",
    "gn:admin3_code":"153811000.0",
    "gn:asciiname":"Orandang",
    "gn:country_code":"PH",
    "gn:dem":96,
    "gn:feature_class":"P",
    "gn:feature_code":"PPL",
    "gn:name":"Orandang",
    "gn:population":0,
    "gn:timezone":"Asia/Manila",
    "iso:country":"PH",
    "name:fil_x_preferred":[
        "Orandang"
    ],
    "wof:name":"Orandang",
    "wof:placetype":"locality"
},
  "geometry": {"coordinates":[124.33750000000001,7.37917],"type":"Point"}
}