{
  "type": "Feature",
  "properties": {
    "gn:admin1_code":"07",
    "gn:admin2_code":"21",
    "gn:admin3_code":"72212000.0",
    "gn:asciiname":"Kansumap-ang",
    "gn:country_code":"PH",
    "gn:dem":393,
    "gn:feature_class":"P",
    "gn:feature_code":"PPL",
    "gn:name":"Kansumap-ang",
    "gn:population":0,
    "gn:timezone":"Asia/Manila",
    "iso:country":"PH",
    "name:fil_x_preferred":[
        "Kansumap-ang"
    ],
    "wof:name":"Kansumap-ang",
    "wof:placetype":"locality"
},
  "geometry": {"coordinates":[123.4063,9.6316],"type":"Point"}
}