{
  "type": "Feature",
  "properties": {
    "gn:admin1_code":"14",
    "gn:admin2_code":"35",
    "gn:admin3_code":"153611000.0",
    "gn:asciiname":"Rumayas",
    "gn:country_code":"PH",
    "gn:dem":711,
    "gn:feature_class":"P",
    "gn:feature_code":"PPL",
    "gn:name":"Rumayas",
    "gn:population":0,
    "gn:timezone":"Asia/Manila",
    "iso:country":"PH",
    "name:fil_x_preferred":[
        "Rumayas"
    ],
    "wof:name":"Rumayas",
    "wof:placetype":"locality"
},
  "geometry": {"coordinates":[124.36139,7.87472],"type":"Point"}
}