{
  "type": "Feature",
  "properties": {
    "gn:admin1_code":"14",
    "gn:admin2_code":"72",
    "gn:asciiname":"Ba'uwan",
    "gn:country_code":"PH",
    "gn:dem":-9999,
    "gn:feature_class":"P",
    "gn:feature_code":"PPL",
    "gn:name":"Ba\u2019uwan",
    "gn:population":0,
    "gn:timezone":"Asia/Manila",
    "iso:country":"PH",
    "name:fil_x_preferred":[
        "Ba\u2019uwan"
    ],
    "wof:name":"Ba'uwan",
    "wof:placetype":"locality"
},
  "geometry": {"coordinates":[120.28333000000001,5.15],"type":"Point"}
}