{
  "type": "Feature",
  "properties": {
    "iso:country":"PH",
    "name:bcl_x_preferred":[
        "San Jose"
    ],
    "name:cbk_zam_x_preferred":[
        "San Jose"
    ],
    "name:ceb_x_preferred":[
        "San Jose"
    ],
    "name:deu_x_preferred":[
        "San Jose City"
    ],
    "name:ilo_x_preferred":[
        "San Jose"
    ],
    "name:ind_x_preferred":[
        "Kota San Jose"
    ],
    "name:ita_x_preferred":[
        "San Jose"
    ],
    "name:nld_x_preferred":[
        "San Jose"
    ],
    "name:pag_x_preferred":[
        "San Jose"
    ],
    "name:pam_x_preferred":[
        "San Jose Lakanbalen"
    ],
    "name:pol_x_preferred":[
        "San Jose"
    ],
    "name:spa_x_preferred":[
        "San Jos\u00e9 de Casignan"
    ],
    "name:swe_x_preferred":[
        "San Jose City"
    ],
    "name:tgl_x_preferred":[
        "San Jose"
    ],
    "name:unk_x_variant":[
        "San Jose City"
    ],
    "name:war_x_preferred":[
        "San Jose"
    ],
    "qs:gn_country":"PH",
    "qs:gn_fcode":"PPL",
    "qs:gn_pop":0,
    "qs:name":"San Jose",
    "qs:name_adm0":"Philippines",
    "qs:name_adm1":"Central Luzon",
    "qs:photos":0,
    "qs:photos_1k":0,
    "qs:photos_9k":1,
    "qs:photos_9r":1,
    "qs:photos_all":4,
    "qs:photos_sr":0,
    "qs:placetype":"Town",
    "qs:pop_sr":"6",
    "qs:woe_adm0":23424934,
    "wd:wordcount":2911,
    "wof:name":"San Jose",
    "wof:placetype":"locality"
},
  "geometry": {"coordinates":[120.9894,15.7923],"type":"Point"}
}