{
  "type": "Feature",
  "properties": {
    "gn:gn_country":"PH",
    "gn:gn_fcode":"PPL",
    "gn:gn_pop":2684,
    "gn:population":2684,
    "iso:country":"PH",
    "name:fil_x_preferred":[
        "Bongued"
    ],
    "qs_pg:aaroncc":"PH",
    "qs_pg:gn_country":"PH",
    "qs_pg:gn_fcode":"PPL",
    "qs_pg:gn_pop":2684,
    "qs_pg:name":"Bongued",
    "qs_pg:photos_9r":0,
    "qs_pg:photos_sr":0,
    "qs_pg:pop_sr":4,
    "qs_pg:qs_pg_placetype":"locality",
    "wof:name":"Bongued",
    "wof:placetype":"locality",
    "wof:population":2684
},
  "geometry": {"coordinates":[124.40000000000001,7.11667],"type":"Point"}
}