{
  "type": "Feature",
  "properties": {
    "gn:admin1_code":"15",
    "gn:admin2_code":"32",
    "gn:admin3_code":"143214000.0",
    "gn:asciiname":"Magmet",
    "gn:country_code":"PH",
    "gn:dem":541,
    "gn:feature_class":"P",
    "gn:feature_code":"PPL",
    "gn:name":"Magmet",
    "gn:population":0,
    "gn:timezone":"Asia/Manila",
    "iso:country":"PH",
    "name:fil_x_preferred":[
        "Magmet"
    ],
    "wof:name":"Magmet",
    "wof:placetype":"locality"
},
  "geometry": {"coordinates":[121.2713,17.3431],"type":"Point"}
}