{
  "type": "Feature",
  "properties": {
    "gn:admin1_code":"15",
    "gn:admin2_code":"01",
    "gn:admin3_code":"140103000.0",
    "gn:asciiname":"Bana-ao",
    "gn:country_code":"PH",
    "gn:dem":191,
    "gn:feature_class":"P",
    "gn:feature_code":"PPL",
    "gn:name":"Bana-ao",
    "gn:population":0,
    "gn:timezone":"Asia/Manila",
    "iso:country":"PH",
    "name:fil_x_preferred":[
        "Bana-ao"
    ],
    "wof:name":"Bana-ao",
    "wof:placetype":"locality"
},
  "geometry": {"coordinates":[120.7089,17.5222],"type":"Point"}
}