{
  "type": "Feature",
  "properties": {
    "gn:admin1_code":"07",
    "gn:admin2_code":"11",
    "gn:admin3_code":"71205000.0",
    "gn:asciiname":"Campatok",
    "gn:country_code":"PH",
    "gn:dem":88,
    "gn:feature_class":"P",
    "gn:feature_code":"PPL",
    "gn:name":"Campatok",
    "gn:population":0,
    "gn:timezone":"Asia/Manila",
    "iso:country":"PH",
    "name:fil_x_preferred":[
        "Campatok"
    ],
    "wof:name":"Campatok",
    "wof:placetype":"locality"
},
  "geometry": {"coordinates":[123.90000000000001,9.65],"type":"Point"}
}