{
  "type": "Feature",
  "properties": {
    "gn:admin1_code":"40",
    "gn:admin2_code":"33",
    "gn:admin3_code":"43405000.0",
    "gn:asciiname":"Barangay Uno",
    "gn:country_code":"PH",
    "gn:dem":24,
    "gn:feature_class":"P",
    "gn:feature_code":"PPL",
    "gn:name":"Barangay Uno",
    "gn:population":0,
    "gn:timezone":"Asia/Manila",
    "iso:country":"PH",
    "name:und_x_variant":[
        "Barangay Primero"
    ],
    "wof:name":"Barangay Uno",
    "wof:placetype":"locality"
},
  "geometry": {"coordinates":[121.15669,14.20595],"type":"Point"}
}