{
  "type": "Feature",
  "properties": {
    "gn:admin1_code":"02",
    "gn:admin2_code":"14",
    "gn:admin3_code":"21520000.0",
    "gn:asciiname":"Aquib",
    "gn:country_code":"PH",
    "gn:dem":35,
    "gn:feature_class":"P",
    "gn:feature_code":"PPL",
    "gn:name":"Aquib",
    "gn:population":0,
    "gn:timezone":"Asia/Manila",
    "iso:country":"PH",
    "name:fil_x_preferred":[
        "Aquib Sur"
    ],
    "name:fil_x_variant":[
        "Aquib"
    ],
    "wof:name":"Aquib",
    "wof:placetype":"locality"
},
  "geometry": {"coordinates":[121.47487,17.79688999999999],"type":"Point"}
}