{
  "type": "Feature",
  "properties": {
    "gn:admin1_code":"01",
    "gn:admin2_code":"36",
    "gn:admin3_code":"13302000.0",
    "gn:asciiname":"San Simon West",
    "gn:country_code":"PH",
    "gn:dem":41,
    "gn:feature_class":"P",
    "gn:feature_code":"PPL",
    "gn:name":"San Simon West",
    "gn:population":0,
    "gn:timezone":"Asia/Manila",
    "iso:country":"PH",
    "name:eng_x_preferred":[
        "San Simon West"
    ],
    "wof:name":"San Simon West",
    "wof:placetype":"locality"
},
  "geometry": {"coordinates":[120.3861,16.3844],"type":"Point"}
}