{
  "type": "Feature",
  "properties": {
    "gn:admin1_code":"14",
    "gn:admin2_code":"56",
    "gn:admin3_code":"153815000.0",
    "gn:asciiname":"Nangi",
    "gn:country_code":"PH",
    "gn:dem":456,
    "gn:feature_class":"P",
    "gn:feature_code":"PPL",
    "gn:name":"Nangi",
    "gn:population":0,
    "gn:timezone":"Asia/Manila",
    "iso:country":"PH",
    "name:fil_x_preferred":[
        "Nangi"
    ],
    "wof:name":"Nangi",
    "wof:placetype":"locality"
},
  "geometry": {"coordinates":[124.16056,6.99389],"type":"Point"}
}