{
  "type": "Feature",
  "properties": {
    "gn:admin1_code":"12",
    "gn:admin2_code":"M9",
    "gn:admin3_code":"128006000.0",
    "gn:asciiname":"Tituan",
    "gn:country_code":"PH",
    "gn:dem":285,
    "gn:feature_class":"P",
    "gn:feature_code":"PPL",
    "gn:name":"Tituan",
    "gn:population":0,
    "gn:timezone":"Asia/Manila",
    "iso:country":"PH",
    "name:fil_x_preferred":[
        "Tituan"
    ],
    "wof:name":"Tituan",
    "wof:placetype":"locality"
},
  "geometry": {"coordinates":[125.39028,6.01722],"type":"Point"}
}