{
  "type": "Feature",
  "properties": {
    "gn:admin1_code":"05",
    "gn:admin2_code":"05",
    "gn:admin3_code":"50515000.0",
    "gn:asciiname":"Hamorauon",
    "gn:country_code":"PH",
    "gn:dem":153,
    "gn:feature_class":"P",
    "gn:feature_code":"PPL",
    "gn:name":"Hamorauon",
    "gn:population":0,
    "gn:timezone":"Asia/Manila",
    "iso:country":"PH",
    "name:fil_x_preferred":[
        "Hamorauon"
    ],
    "wof:name":"Hamorauon",
    "wof:placetype":"locality"
},
  "geometry": {"coordinates":[124.01667,13.25],"type":"Point"}
}