{
  "type": "Feature",
  "properties": {
    "gn:admin1_code":"40",
    "gn:admin2_code":"53",
    "gn:admin3_code":"45806000.0",
    "gn:asciiname":"Kasile",
    "gn:country_code":"PH",
    "gn:dem":69,
    "gn:feature_class":"P",
    "gn:feature_code":"PPL",
    "gn:name":"Kasile",
    "gn:population":0,
    "gn:timezone":"Asia/Manila",
    "iso:country":"PH",
    "name:fil_x_preferred":[
        "Kasile"
    ],
    "name:und_x_variant":[
        "Kasili",
        "Kasih"
    ],
    "wof:name":"Kasile",
    "wof:placetype":"locality"
},
  "geometry": {"coordinates":[121.227,14.3993],"type":"Point"}
}