{
  "type": "Feature",
  "properties": {
    "gn:country":"PH",
    "gn:fcode":"PPL",
    "gn:population":2221,
    "iso:country":"PH",
    "name:fil_x_preferred":[
        "Limot"
    ],
    "qs:name":"Limot",
    "qs:photos_9r":0,
    "qs:photos_sr":0,
    "qs:pop_sr":"4",
    "wof:name":"Limot",
    "wof:placetype":"locality",
    "wof:population":2221
},
  "geometry": {"coordinates":[126.27267999999999,7.0405],"type":"Point"}
}