{
  "type": "Feature",
  "properties": {
    "gn:admin1_code":"11",
    "gn:admin2_code":"25",
    "gn:admin3_code":"112402000.0",
    "gn:asciiname":"Luming",
    "gn:country_code":"PH",
    "gn:dem":779,
    "gn:feature_class":"P",
    "gn:feature_code":"PPL",
    "gn:name":"Luming",
    "gn:population":0,
    "gn:timezone":"Asia/Manila",
    "iso:country":"PH",
    "name:fil_x_preferred":[
        "Luming"
    ],
    "wof:name":"Luming",
    "wof:placetype":"locality"
},
  "geometry": {"coordinates":[125.40306,7.45444],"type":"Point"}
}