{
  "type": "Feature",
  "properties": {
    "gn:admin1_code":"05",
    "gn:admin2_code":"05",
    "gn:admin3_code":"50512000.0",
    "gn:asciiname":"Bongoran",
    "gn:country_code":"PH",
    "gn:dem":40,
    "gn:feature_class":"P",
    "gn:feature_code":"PPL",
    "gn:name":"Bongoran",
    "gn:population":0,
    "gn:timezone":"Asia/Manila",
    "iso:country":"PH",
    "name:fil_x_preferred":[
        "Bongoran"
    ],
    "wof:name":"Bongoran",
    "wof:placetype":"locality"
},
  "geometry": {"coordinates":[123.49405,13.23617],"type":"Point"}
}