{
  "type": "Feature",
  "properties": {
    "gn:admin1_code":"40",
    "gn:admin2_code":"H2",
    "gn:admin3_code":"45649000.0",
    "gn:asciiname":"Kalilayan Illaya",
    "gn:country_code":"PH",
    "gn:dem":24,
    "gn:feature_class":"P",
    "gn:feature_code":"PPL",
    "gn:name":"Kalilayan Illaya",
    "gn:population":0,
    "gn:timezone":"Asia/Manila",
    "iso:country":"PH",
    "name:fil_x_preferred":[
        "Kalilayan Illaya"
    ],
    "name:fil_x_variant":[
        "Ilayang Kalilyan"
    ],
    "wof:name":"Kalilayan Illaya",
    "wof:placetype":"locality"
},
  "geometry": {"coordinates":[121.95731000000001,13.8635],"type":"Point"}
}