{
  "type": "Feature",
  "properties": {
    "gn:admin1_code":"02",
    "gn:admin2_code":"31",
    "gn:admin3_code":"23120000.0",
    "gn:asciiname":"Palattao",
    "gn:country_code":"PH",
    "gn:dem":50,
    "gn:feature_class":"P",
    "gn:feature_code":"PPL",
    "gn:name":"Palattao",
    "gn:population":0,
    "gn:timezone":"Asia/Manila",
    "iso:country":"PH",
    "name:fil_x_preferred":[
        "Palattao"
    ],
    "name:fil_x_variant":[
        "Pallattao"
    ],
    "wof:name":"Palattao",
    "wof:placetype":"locality"
},
  "geometry": {"coordinates":[121.83024,17.00675],"type":"Point"}
}