{
  "type": "Feature",
  "properties": {
    "gn:admin1_code":"02",
    "gn:admin2_code":"14",
    "gn:admin3_code":"21514000.0",
    "gn:asciiname":"Casitan",
    "gn:country_code":"PH",
    "gn:dem":10,
    "gn:feature_class":"P",
    "gn:feature_code":"PPL",
    "gn:name":"Casitan",
    "gn:population":0,
    "gn:timezone":"Asia/Manila",
    "iso:country":"PH",
    "name:fil_x_preferred":[
        "Casiitan"
    ],
    "name:fil_x_variant":[
        "Casitan"
    ],
    "wof:name":"Casitan",
    "wof:placetype":"locality"
},
  "geometry": {"coordinates":[121.93267,18.26263],"type":"Point"}
}