{
  "type": "Feature",
  "properties": {
    "gn:admin1_code":"08",
    "gn:admin2_code":"59",
    "gn:admin3_code":"86406000.0",
    "gn:asciiname":"Guintoylan",
    "gn:country_code":"PH",
    "gn:dem":10,
    "gn:feature_class":"P",
    "gn:feature_code":"PPL",
    "gn:name":"Guintoylan",
    "gn:population":0,
    "gn:timezone":"Asia/Manila",
    "iso:country":"PH",
    "name:und_x_variant":[
        "Guintuylan",
        "Guintoylan"
    ],
    "wof:name":"Guintoylan",
    "wof:placetype":"locality"
},
  "geometry": {"coordinates":[125.16576999999999,10.13236],"type":"Point"}
}