{
  "type": "Feature",
  "properties": {
    "gn:admin1_code":"05",
    "gn:admin2_code":"19",
    "gn:admin3_code":"52008000.0",
    "gn:asciiname":"Lictin",
    "gn:country_code":"PH",
    "gn:dem":22,
    "gn:feature_class":"P",
    "gn:feature_code":"PPL",
    "gn:name":"Lictin",
    "gn:population":0,
    "gn:timezone":"Asia/Manila",
    "iso:country":"PH",
    "name:fil_x_preferred":[
        "Lictin"
    ],
    "name:und_x_variant":[
        "Liktin",
        "Lictin"
    ],
    "wof:name":"Lictin",
    "wof:placetype":"locality"
},
  "geometry": {"coordinates":[124.1289,13.6012],"type":"Point"}
}