{
  "type": "Feature",
  "properties": {
    "gn:admin1_code":"03",
    "gn:admin2_code":"63",
    "gn:admin3_code":"36912000.0",
    "gn:asciiname":"Coral-Iloco",
    "gn:country_code":"PH",
    "gn:dem":25,
    "gn:feature_class":"P",
    "gn:feature_code":"PPL",
    "gn:name":"Coral-Iloco",
    "gn:population":0,
    "gn:timezone":"Asia/Manila",
    "iso:country":"PH",
    "name:fil_x_preferred":[
        "Coral"
    ],
    "name:fil_x_variant":[
        "Corral Iloco"
    ],
    "wof:name":"Coral-Iloco",
    "wof:placetype":"locality"
},
  "geometry": {"coordinates":[120.637,15.6718],"type":"Point"}
}