{
  "type": "Feature",
  "properties": {
    "gn:admin1_code":"01",
    "gn:admin2_code":"29",
    "gn:admin3_code":"12922000.0",
    "gn:asciiname":"Sacuyya Sur",
    "gn:country_code":"PH",
    "gn:dem":32,
    "gn:feature_class":"P",
    "gn:feature_code":"PPL",
    "gn:name":"Sacuyya Sur",
    "gn:population":0,
    "gn:timezone":"Asia/Manila",
    "iso:country":"PH",
    "name:fil_x_preferred":[
        "Sacuyya Sur"
    ],
    "wof:name":"Sacuyya Sur",
    "wof:placetype":"locality"
},
  "geometry": {"coordinates":[120.44998,17.53769],"type":"Point"}
}