{
  "type": "Feature",
  "properties": {
    "gn:admin1_code":"14",
    "gn:admin2_code":"56",
    "gn:admin3_code":"153813000.0",
    "gn:asciiname":"Sadsalan",
    "gn:country_code":"PH",
    "gn:dem":14,
    "gn:feature_class":"P",
    "gn:feature_code":"PPL",
    "gn:name":"Sadsalan",
    "gn:population":0,
    "gn:timezone":"Asia/Manila",
    "iso:country":"PH",
    "name:fil_x_preferred":[
        "Sadsalan"
    ],
    "wof:name":"Sadsalan",
    "wof:placetype":"locality"
},
  "geometry": {"coordinates":[124.60722,6.90417],"type":"Point"}
}