{
  "type": "Feature",
  "properties": {
    "gn:admin1_code":"40",
    "gn:admin2_code":"H2",
    "gn:admin3_code":"45646000.0",
    "gn:asciiname":"Mampayunga",
    "gn:country_code":"PH",
    "gn:dem":16,
    "gn:feature_class":"P",
    "gn:feature_code":"PPL",
    "gn:name":"Mampayunga",
    "gn:population":0,
    "gn:timezone":"Asia/Manila",
    "iso:country":"PH",
    "name:fil_x_preferred":[
        "Mampayunga"
    ],
    "wof:name":"Mampayunga",
    "wof:placetype":"locality"
},
  "geometry": {"coordinates":[122.49209999999999,13.9403],"type":"Point"}
}