{
  "type": "Feature",
  "properties": {
    "gn:admin1_code":"07",
    "gn:admin2_code":"21",
    "gn:admin3_code":"72217000.0",
    "gn:asciiname":"Pangyao",
    "gn:country_code":"PH",
    "gn:dem":9,
    "gn:feature_class":"P",
    "gn:feature_code":"PPL",
    "gn:name":"Pangyao",
    "gn:population":0,
    "gn:timezone":"Asia/Manila",
    "iso:country":"PH",
    "wof:name":"Pangyao",
    "wof:placetype":"locality"
},
  "geometry": {"coordinates":[123.91527000000001,10.31602],"type":"Point"}
}