{
  "type": "Feature",
  "properties": {
    "gn:admin1_code":"07",
    "gn:admin2_code":"21",
    "gn:admin3_code":"72217000.0",
    "gn:asciiname":"Buhisan",
    "gn:country_code":"PH",
    "gn:dem":407,
    "gn:feature_class":"P",
    "gn:feature_code":"PPL",
    "gn:name":"Buhisan",
    "gn:population":0,
    "gn:timezone":"Asia/Manila",
    "iso:country":"PH",
    "wof:name":"Buhisan",
    "wof:placetype":"locality"
},
  "geometry": {"coordinates":[123.83833,10.32167],"type":"Point"}
}