{
  "type": "Feature",
  "properties": {
    "gn:admin1_code":"12",
    "gn:admin2_code":"M9",
    "gn:admin3_code":"128004000.0",
    "gn:asciiname":"Pananok",
    "gn:country_code":"PH",
    "gn:dem":8,
    "gn:feature_class":"P",
    "gn:feature_code":"PPL",
    "gn:name":"Pananok",
    "gn:population":0,
    "gn:timezone":"Asia/Manila",
    "iso:country":"PH",
    "name:und_x_variant":[
        "Ponanok",
        "Pananok"
    ],
    "wof:name":"Pananok",
    "wof:placetype":"locality"
},
  "geometry": {"coordinates":[124.9975,5.86028],"type":"Point"}
}