{
  "type": "Feature",
  "properties": {
    "gn:admin1_code":"40",
    "gn:admin2_code":"53",
    "gn:admin3_code":"45804000.0",
    "gn:asciiname":"Banaba",
    "gn:country_code":"PH",
    "gn:dem":7,
    "gn:feature_class":"P",
    "gn:feature_code":"PPL",
    "gn:name":"Banaba",
    "gn:population":0,
    "gn:timezone":"Asia/Manila",
    "iso:country":"PH",
    "name:fil_x_preferred":[
        "Banaba"
    ],
    "wof:name":"Banaba",
    "wof:placetype":"locality"
},
  "geometry": {"coordinates":[121.2414,14.3072],"type":"Point"}
}