{
  "type": "Feature",
  "properties": {
    "gn:country":"PH",
    "gn:fcode":"PPL",
    "gn:pop":9789,
    "iso:country":"PH",
    "name:fil_x_preferred":[
        "Sapu Padidu"
    ],
    "name:unk_x_variant":[
        "Sapu"
    ],
    "qs:name":"Sapu Padidu",
    "qs:photos_9r":0,
    "qs:photos_sr":0,
    "qs:pop_sr":"5",
    "wof:name":"Sapu Padidu",
    "wof:placetype":"locality",
    "wof:population":9789
},
  "geometry": {"coordinates":[125.26694000000001,5.91722],"type":"Point"}
}