{
  "type": "Feature",
  "properties": {
    "gn:admin1_code":"01",
    "gn:admin2_code":"28",
    "gn:admin3_code":"12821000.0",
    "gn:asciiname":"Sagaboan",
    "gn:country_code":"PH",
    "gn:dem":40,
    "gn:feature_class":"P",
    "gn:feature_code":"PPL",
    "gn:name":"Sagaboan",
    "gn:population":0,
    "gn:timezone":"Asia/Manila",
    "iso:country":"PH",
    "name:fil_x_preferred":[
        "Sagaboan"
    ],
    "wof:name":"Sagaboan",
    "wof:placetype":"locality"
},
  "geometry": {"coordinates":[120.6734,18.1535],"type":"Point"}
}