{
  "type": "Feature",
  "properties": {
    "gn:admin1_code":"41",
    "gn:admin2_code":"38",
    "gn:admin3_code":"174003000.0",
    "gn:asciiname":"Bognuyan",
    "gn:country_code":"PH",
    "gn:dem":13,
    "gn:feature_class":"P",
    "gn:feature_code":"PPL",
    "gn:name":"Bognuyan",
    "gn:population":0,
    "gn:timezone":"Asia/Manila",
    "iso:country":"PH",
    "name:fil_x_preferred":[
        "Bognuyan"
    ],
    "name:fil_x_variant":[
        "Bognoyan"
    ],
    "name:und_x_variant":[
        "Bognoyan"
    ],
    "wof:name":"Bognuyan",
    "wof:placetype":"locality"
},
  "geometry": {"coordinates":[121.86085,13.29577],"type":"Point"}
}