{
  "type": "Feature",
  "properties": {
    "gn:admin1_code":"40",
    "gn:admin2_code":"H2",
    "gn:admin3_code":"45606000.0",
    "gn:asciiname":"Aluyon",
    "gn:country_code":"PH",
    "gn:dem":6,
    "gn:feature_class":"P",
    "gn:feature_code":"PPL",
    "gn:name":"Aluyon",
    "gn:population":0,
    "gn:timezone":"Asia/Manila",
    "iso:country":"PH",
    "name:fil_x_preferred":[
        "Aluyon"
    ],
    "name:fil_x_variant":[
        "Aloyon"
    ],
    "name:und_x_variant":[
        "Aloyum",
        "Aloyun",
        "Aloyan",
        "Aluyun"
    ],
    "wof:name":"Aluyon",
    "wof:placetype":"locality"
},
  "geometry": {"coordinates":[121.96662999999999,14.8805],"type":"Point"}
}