{
  "type": "Feature",
  "properties": {
    "gn:admin1_code":"02",
    "gn:admin2_code":"31",
    "gn:admin3_code":"23103000.0",
    "gn:asciiname":"Rizaluna",
    "gn:country_code":"PH",
    "gn:dem":57,
    "gn:feature_class":"P",
    "gn:feature_code":"PPL",
    "gn:name":"Rizaluna",
    "gn:population":0,
    "gn:timezone":"Asia/Manila",
    "iso:country":"PH",
    "name:fil_x_preferred":[
        "La Paz"
    ],
    "name:fil_x_variant":[
        "Lapuz"
    ],
    "wof:name":"Rizaluna",
    "wof:placetype":"locality"
},
  "geometry": {"coordinates":[121.6643,17.0079],"type":"Point"}
}