{
  "type": "Feature",
  "properties": {
    "gn:admin1_code":"40",
    "gn:admin2_code":"H2",
    "gn:admin3_code":"45620000.0",
    "gn:asciiname":"Ilog",
    "gn:country_code":"PH",
    "gn:dem":9,
    "gn:feature_class":"P",
    "gn:feature_code":"PPL",
    "gn:name":"Ilog",
    "gn:population":0,
    "gn:timezone":"Asia/Manila",
    "iso:country":"PH",
    "name:ceb_x_preferred":[
        "Ilog"
    ],
    "name:fil_x_preferred":[
        "Ilog"
    ],
    "name:fra_x_preferred":[
        "Ilog"
    ],
    "wof:name":"Ilog",
    "wof:placetype":"locality"
},
  "geometry": {"coordinates":[121.63524,14.74742],"type":"Point"}
}