{
  "type": "Feature",
  "properties": {
    "gn:admin1_code":"12",
    "gn:admin2_code":"M9",
    "gn:admin3_code":"128004000.0",
    "gn:asciiname":"Dalao",
    "gn:country_code":"PH",
    "gn:dem":17,
    "gn:feature_class":"P",
    "gn:feature_code":"PPL",
    "gn:name":"Dalao",
    "gn:population":0,
    "gn:timezone":"Asia/Manila",
    "iso:country":"PH",
    "name:und_x_variant":[
        "Oalao",
        "Dalao"
    ],
    "wof:name":"Dalao",
    "wof:placetype":"locality"
},
  "geometry": {"coordinates":[124.89888999999999,5.87167],"type":"Point"}
}