{
  "type": "Feature",
  "properties": {
    "gn:admin1_code":"03",
    "gn:admin2_code":"63",
    "gn:admin3_code":"36907000.0",
    "gn:asciiname":"Balanoy",
    "gn:country_code":"PH",
    "gn:dem":21,
    "gn:feature_class":"P",
    "gn:feature_code":"PPL",
    "gn:name":"Balanoy",
    "gn:population":0,
    "gn:timezone":"Asia/Manila",
    "iso:country":"PH",
    "name:fil_x_preferred":[
        "Balanoy"
    ],
    "wof:name":"Balanoy",
    "wof:placetype":"locality"
},
  "geometry": {"coordinates":[120.72444,15.42472],"type":"Point"}
}