{
  "type": "Feature",
  "properties": {
    "gn:admin1_code":"03",
    "gn:admin2_code":"63",
    "gn:admin3_code":"36909000.0",
    "gn:asciiname":"Camposanto Primero",
    "gn:country_code":"PH",
    "gn:dem":17,
    "gn:feature_class":"P",
    "gn:feature_code":"PPL",
    "gn:name":"Camposanto Primero",
    "gn:population":0,
    "gn:timezone":"Asia/Manila",
    "iso:country":"PH",
    "name:fil_x_preferred":[
        "Camposanto Primero"
    ],
    "wof:name":"Camposanto Primero",
    "wof:placetype":"locality"
},
  "geometry": {"coordinates":[120.56541,15.75151],"type":"Point"}
}