{
  "type": "Feature",
  "properties": {
    "gn:admin1_code":"02",
    "gn:admin2_code":"48",
    "gn:admin3_code":"25003000.0",
    "gn:asciiname":"Manga",
    "gn:country_code":"PH",
    "gn:dem":342,
    "gn:feature_class":"P",
    "gn:feature_code":"PPL",
    "gn:name":"Manga",
    "gn:population":0,
    "gn:timezone":"Asia/Manila",
    "iso:country":"PH",
    "name:fil_x_preferred":[
        "Manga"
    ],
    "wof:name":"Manga",
    "wof:placetype":"locality"
},
  "geometry": {"coordinates":[121.3129,16.5616],"type":"Point"}
}