{
  "type": "Feature",
  "properties": {
    "gn:admin1_code":"01",
    "gn:admin2_code":"36",
    "gn:admin3_code":"13309000.0",
    "gn:asciiname":"San Cornelio",
    "gn:country_code":"PH",
    "gn:dem":52,
    "gn:feature_class":"P",
    "gn:feature_code":"PPL",
    "gn:name":"San Cornelio",
    "gn:population":0,
    "gn:timezone":"Asia/Manila",
    "iso:country":"PH",
    "name:fil_x_preferred":[
        "San Cornelio"
    ],
    "wof:name":"San Cornelio",
    "wof:placetype":"locality"
},
  "geometry": {"coordinates":[120.3578,16.4557],"type":"Point"}
}