{
  "type": "Feature",
  "properties": {
    "gn:admin1_code":"06",
    "gn:admin2_code":"04",
    "gn:admin3_code":"60409000.0",
    "gn:asciiname":"Ortega",
    "gn:country_code":"PH",
    "gn:dem":88,
    "gn:feature_class":"P",
    "gn:feature_code":"PPL",
    "gn:name":"Ortega",
    "gn:population":0,
    "gn:timezone":"Asia/Manila",
    "iso:country":"PH",
    "name:fil_x_preferred":[
        "Ortega"
    ],
    "wof:name":"Ortega",
    "wof:placetype":"locality"
},
  "geometry": {"coordinates":[122.32051,11.4362],"type":"Point"}
}