{
  "type": "Feature",
  "properties": {
    "gn:admin1_code":"15",
    "gn:admin2_code":"44",
    "gn:admin3_code":"144402000.0",
    "gn:asciiname":"Bagnen Proper",
    "gn:country_code":"PH",
    "gn:dem":1651,
    "gn:feature_class":"P",
    "gn:feature_code":"PPL",
    "gn:name":"Bagnen Proper",
    "gn:population":0,
    "gn:timezone":"Asia/Manila",
    "iso:country":"PH",
    "name:fil_x_preferred":[
        "Bagnen"
    ],
    "wof:name":"Bagnen Proper",
    "wof:placetype":"locality"
},
  "geometry": {"coordinates":[120.87985999999999,17.0359],"type":"Point"}
}