{
  "type": "Feature",
  "properties": {
    "gn:admin1_code":"41",
    "gn:admin2_code":"49",
    "gn:asciiname":"Lupa Pula",
    "gn:country_code":"PH",
    "gn:dem":8,
    "gn:feature_class":"P",
    "gn:feature_code":"PPL",
    "gn:name":"Lupa Pula",
    "gn:population":0,
    "gn:timezone":"Asia/Manila",
    "iso:country":"PH",
    "name:eng_x_preferred":[
        "Lupa Pula"
    ],
    "wof:name":"Lupa Pula",
    "wof:placetype":"locality"
},
  "geometry": {"coordinates":[118.5124,6.9782],"type":"Point"}
}