{
  "type": "Feature",
  "properties": {
    "gn:admin1_code":"06",
    "gn:admin2_code":"06",
    "gn:admin3_code":"60614000.0",
    "gn:asciiname":"Alegria",
    "gn:country_code":"PH",
    "gn:dem":422,
    "gn:feature_class":"P",
    "gn:feature_code":"PPL",
    "gn:name":"Alegria",
    "gn:population":0,
    "gn:timezone":"Asia/Manila",
    "iso:country":"PH",
    "name:fil_x_preferred":[
        "Alegria"
    ],
    "wof:name":"Alegria",
    "wof:placetype":"locality"
},
  "geometry": {"coordinates":[122.13333,10.85],"type":"Point"}
}