{
  "type": "Feature",
  "properties": {
    "gn:admin1_code":"03",
    "gn:admin2_code":"47",
    "gn:admin3_code":"34903000.0",
    "gn:asciiname":"Matanda",
    "gn:country_code":"PH",
    "gn:dem":35,
    "gn:feature_class":"P",
    "gn:feature_code":"PPL",
    "gn:name":"Matanda",
    "gn:population":0,
    "gn:timezone":"Asia/Manila",
    "iso:country":"PH",
    "name:fil_x_preferred":[
        "Matanda"
    ],
    "wof:name":"Matanda",
    "wof:placetype":"locality"
},
  "geometry": {"coordinates":[120.91719999999999,15.5004],"type":"Point"}
}