{
  "type": "Feature",
  "properties": {
    "gn:admin1_code":"40",
    "gn:admin2_code":"53",
    "gn:admin3_code":"45808000.0",
    "gn:asciiname":"Hantag",
    "gn:country_code":"PH",
    "gn:dem":169,
    "gn:feature_class":"P",
    "gn:feature_code":"PPL",
    "gn:name":"Hantag",
    "gn:population":0,
    "gn:timezone":"Asia/Manila",
    "iso:country":"PH",
    "name:fil_x_preferred":[
        "Hantag"
    ],
    "wof:name":"Hantag",
    "wof:placetype":"locality"
},
  "geometry": {"coordinates":[121.21576,14.78331],"type":"Point"}
}