{
  "type": "Feature",
  "properties": {
    "gn:admin1_code":"12",
    "gn:admin2_code":"57",
    "gn:admin3_code":"124712000.0",
    "gn:asciiname":"Calawag",
    "gn:cc2":"PH",
    "gn:country_code":"PH",
    "gn:dem":12,
    "gn:feature_class":"P",
    "gn:feature_code":"PPL",
    "gn:name":"Calawag",
    "gn:population":0,
    "gn:timezone":"Asia/Manila",
    "iso:country":"PH",
    "name:und_x_variant":[
        "Kalawag",
        "Calawag"
    ],
    "wof:name":"Calawag",
    "wof:placetype":"locality"
},
  "geometry": {"coordinates":[124.64749999999999,7.05278],"type":"Point"}
}