{
  "type": "Feature",
  "properties": {
    "gn:admin1_code":"03",
    "gn:admin2_code":"13",
    "gn:admin3_code":"31420000.0",
    "gn:asciiname":"Sapang Palay",
    "gn:country_code":"PH",
    "gn:dem":90,
    "gn:feature_class":"P",
    "gn:feature_code":"PPL",
    "gn:name":"Sapang Palay",
    "gn:population":0,
    "gn:timezone":"Asia/Manila",
    "iso:country":"PH",
    "name:fil_x_preferred":[
        "Sapangpalay"
    ],
    "wof:name":"Sapang Palay",
    "wof:placetype":"locality"
},
  "geometry": {"coordinates":[121.05278,14.84751],"type":"Point"}
}