{
  "type": "Feature",
  "properties": {
    "gn:admin1_code":"40",
    "gn:admin2_code":"33",
    "gn:admin3_code":"43414000.0",
    "gn:asciiname":"Maylatang",
    "gn:cc2":"PH",
    "gn:country_code":"PH",
    "gn:dem":7,
    "gn:feature_class":"P",
    "gn:feature_code":"PPL",
    "gn:name":"Maylatang",
    "gn:population":0,
    "gn:timezone":"Asia/Manila",
    "iso:country":"PH",
    "name:und_x_variant":[
        "Maytalang",
        "Maylatang"
    ],
    "wof:name":"Maylatang",
    "wof:placetype":"locality"
},
  "geometry": {"coordinates":[121.41667,14.45],"type":"Point"}
}