{
  "type": "Feature",
  "properties": {
    "gn:admin1_code":"15",
    "gn:admin2_code":"01",
    "gn:admin3_code":"140110000.0",
    "gn:asciiname":"Paganao",
    "gn:country_code":"PH",
    "gn:dem":129,
    "gn:feature_class":"P",
    "gn:feature_code":"PPL",
    "gn:name":"Paganao",
    "gn:population":0,
    "gn:timezone":"Asia/Manila",
    "iso:country":"PH",
    "name:fil_x_preferred":[
        "Paganao"
    ],
    "wof:name":"Paganao",
    "wof:placetype":"locality"
},
  "geometry": {"coordinates":[120.7889,17.6752],"type":"Point"}
}