{
  "type": "Feature",
  "properties": {
    "gn:admin1_code":"07",
    "gn:admin2_code":"11",
    "gn:admin3_code":"71204000.0",
    "gn:asciiname":"Danicop",
    "gn:country_code":"PH",
    "gn:dem":114,
    "gn:feature_class":"P",
    "gn:feature_code":"PPL",
    "gn:name":"Danicop",
    "gn:population":0,
    "gn:timezone":"Asia/Manila",
    "iso:country":"PH",
    "name:fil_x_preferred":[
        "Danicop"
    ],
    "wof:name":"Danicop",
    "wof:placetype":"locality"
},
  "geometry": {"coordinates":[123.9149,9.7909],"type":"Point"}
}