{
  "type": "Feature",
  "properties": {
    "iso:country":"PH",
    "name:fil_x_preferred":[
        "Paraiso"
    ],
    "qs:gn_country":"PH",
    "qs:gn_fcode":"PPL",
    "qs:gn_pop":30494,
    "qs:name":"Paraiso",
    "qs:name_adm0":"Philippines",
    "qs:name_adm1":"Western Visayas",
    "qs:photos":0,
    "qs:photos_1k":0,
    "qs:photos_9k":1,
    "qs:photos_9r":1,
    "qs:photos_all":1,
    "qs:photos_sr":0,
    "qs:placetype":"Town",
    "qs:pop_sr":"7",
    "qs:woe_adm0":23424934,
    "wof:name":"Paraiso",
    "wof:placetype":"locality",
    "wof:population":30494
},
  "geometry": {"coordinates":[123.3627,10.8849],"type":"Point"}
}