{
  "type": "Feature",
  "properties": {
    "gn:admin1_code":"08",
    "gn:admin2_code":"H9",
    "gn:admin3_code":"87803000.0",
    "gn:asciiname":"Ariquen",
    "gn:country_code":"PH",
    "gn:dem":17,
    "gn:feature_class":"P",
    "gn:feature_code":"PPL",
    "gn:name":"Ariquen",
    "gn:population":0,
    "gn:timezone":"Asia/Manila",
    "iso:country":"PH",
    "name:fil_x_preferred":[
        "Ariquen"
    ],
    "wof:name":"Ariquen",
    "wof:placetype":"locality"
},
  "geometry": {"coordinates":[124.54730000000001,11.4785],"type":"Point"}
}