{
  "type": "Feature",
  "properties": {
    "gn:admin1_code":"02",
    "gn:admin2_code":"31",
    "gn:admin3_code":"23116000.0",
    "gn:asciiname":"Dadap",
    "gn:country_code":"PH",
    "gn:dem":59,
    "gn:feature_class":"P",
    "gn:feature_code":"PPL",
    "gn:name":"Dadap",
    "gn:population":0,
    "gn:timezone":"Asia/Manila",
    "iso:country":"PH",
    "name:fil_x_preferred":[
        "Dapdap"
    ],
    "wof:name":"Dadap",
    "wof:placetype":"locality"
},
  "geometry": {"coordinates":[121.73414,16.95685],"type":"Point"}
}