{
  "type": "Feature",
  "properties": {
    "gn:admin1_code":"06",
    "gn:admin2_code":"04",
    "gn:admin3_code":"60412000.0",
    "gn:asciiname":"Habana",
    "gn:country_code":"PH",
    "gn:dem":55,
    "gn:feature_class":"P",
    "gn:feature_code":"PPL",
    "gn:name":"Habana",
    "gn:population":0,
    "gn:timezone":"Asia/Manila",
    "iso:country":"PH",
    "name:fil_x_preferred":[
        "Habana"
    ],
    "wof:name":"Habana",
    "wof:placetype":"locality"
},
  "geometry": {"coordinates":[121.91731,11.88058],"type":"Point"}
}