{
  "type": "Feature",
  "properties": {
    "gn:country":"PH",
    "gn:fcode":"PPL",
    "gn:population":4217,
    "iso:country":"PH",
    "name:fil_x_preferred":[
        "Tinang"
    ],
    "qs_pg:aaroncc":"PH",
    "qs_pg:gn_country":"PH",
    "qs_pg:gn_fcode":"PPL",
    "qs_pg:gn_pop":4217,
    "qs_pg:name":"Tinang",
    "qs_pg:photos_9r":0,
    "qs_pg:photos_sr":0,
    "qs_pg:pop_sr":4,
    "qs_pg:qs_pg_placetype":"locality",
    "wof:name":"Tinang",
    "wof:placetype":"locality",
    "wof:population":4217
},
  "geometry": {"coordinates":[120.65343,15.37626],"type":"Point"}
}