{
  "type": "Feature",
  "properties": {
    "gn:admin1_code":"09",
    "gn:admin2_code":"ZSI",
    "gn:admin3_code":"98313000.0",
    "gn:asciiname":"Lagting",
    "gn:country_code":"PH",
    "gn:dem":9,
    "gn:feature_class":"P",
    "gn:feature_code":"PPL",
    "gn:name":"Lagting",
    "gn:population":0,
    "gn:timezone":"Asia/Manila",
    "iso:country":"PH",
    "name:dan_x_preferred":[
        "Lagting"
    ],
    "name:deu_x_preferred":[
        "Lagting"
    ],
    "name:fil_x_preferred":[
        "Lagting"
    ],
    "name:pol_x_preferred":[
        "Lagting"
    ],
    "name:swe_x_preferred":[
        "Lagtinget"
    ],
    "wof:name":"Lagting",
    "wof:placetype":"locality"
},
  "geometry": {"coordinates":[122.86750000000001,7.65833],"type":"Point"}
}