{
  "type": "Feature",
  "properties": {
    "gn:admin1_code":"03",
    "gn:admin2_code":"13",
    "gn:asciiname":"Torres Buggallon",
    "gn:cc2":"PH",
    "gn:country_code":"PH",
    "gn:dem":21,
    "gn:feature_class":"P",
    "gn:feature_code":"PPL",
    "gn:name":"Torres Buggallon",
    "gn:population":0,
    "gn:timezone":"Asia/Manila",
    "iso:country":"PH",
    "name:und_x_variant":[
        "Torres Bugallon",
        "Torres Buggallon"
    ],
    "wof:name":"Torres Buggallon",
    "wof:placetype":"locality"
},
  "geometry": {"coordinates":[120.98139,14.69056],"type":"Point"}
}