{
  "type": "Feature",
  "properties": {
    "gn:admin1_code":"09",
    "gn:admin2_code":"ZSI",
    "gn:admin3_code":"98301000.0",
    "gn:asciiname":"Bomba",
    "gn:country_code":"PH",
    "gn:dem":38,
    "gn:feature_class":"P",
    "gn:feature_code":"PPL",
    "gn:name":"Bomba",
    "gn:population":0,
    "gn:timezone":"Asia/Manila",
    "iso:country":"PH",
    "name:cat_x_preferred":[
        "Bomba"
    ],
    "name:ceb_x_preferred":[
        "Bomba"
    ],
    "name:ces_x_preferred":[
        "Bomba"
    ],
    "name:deu_x_preferred":[
        "Bomba"
    ],
    "name:fil_x_preferred":[
        "Bomba"
    ],
    "name:fin_x_preferred":[
        "Bomba"
    ],
    "name:fra_x_preferred":[
        "Bomba"
    ],
    "name:glg_x_preferred":[
        "Bomba"
    ],
    "name:hrv_x_preferred":[
        "Bomba"
    ],
    "name:ind_x_preferred":[
        "Bomba"
    ],
    "name:ita_x_preferred":[
        "Bomba"
    ],
    "name:lit_x_preferred":[
        "Bomba"
    ],
    "name:nds_x_preferred":[
        "Bomba"
    ],
    "name:pol_x_preferred":[
        "Bomba"
    ],
    "name:por_x_preferred":[
        "Bomba"
    ],
    "name:rus_x_preferred":[
        "\u0411\u043e\u043c\u0431\u0430"
    ],
    "name:slk_x_preferred":[
        "Bomba"
    ],
    "name:spa_x_preferred":[
        "Bomba"
    ],
    "name:swe_x_preferred":[
        "Bomba"
    ],
    "name:tgl_x_preferred":[
        "Bomba"
    ],
    "name:tur_x_preferred":[
        "Bomba"
    ],
    "name:ukr_x_preferred":[
        "\u0411\u043e\u043c\u0431\u0430"
    ],
    "wof:name":"Bomba",
    "wof:placetype":"locality"
},
  "geometry": {"coordinates":[122.93333,7.51667],"type":"Point"}
}