{
  "type": "Feature",
  "properties": {
    "gn:admin1_code":"01",
    "gn:admin2_code":"28",
    "gn:admin3_code":"12805000.0",
    "gn:asciiname":"Veronica",
    "gn:country_code":"PH",
    "gn:dem":43,
    "gn:feature_class":"P",
    "gn:feature_code":"PPL",
    "gn:name":"Veronica",
    "gn:population":0,
    "gn:timezone":"Asia/Manila",
    "iso:country":"PH",
    "name:bul_x_preferred":[
        "\u0412\u0435\u0440\u043e\u043d\u0438\u043a\u0430"
    ],
    "name:ceb_x_preferred":[
        "Ver\u00f3nica"
    ],
    "name:ces_x_preferred":[
        "Veronica"
    ],
    "name:dan_x_preferred":[
        "Veronica"
    ],
    "name:deu_x_preferred":[
        "Veronica"
    ],
    "name:est_x_preferred":[
        "Veronica"
    ],
    "name:fas_x_preferred":[
        "\u0648\u0631\u0648\u0646\u06cc\u06a9\u0627"
    ],
    "name:fil_x_preferred":[
        "Veronica"
    ],
    "name:heb_x_preferred":[
        "\u05d5\u05e8\u05d5\u05e0\u05d9\u05e7\u05d4"
    ],
    "name:ita_x_preferred":[
        "Veronica"
    ],
    "name:jpn_x_preferred":[
        "\u30f4\u30a7\u30ed\u30cb\u30ab"
    ],
    "name:kor_x_preferred":[
        "\ubca0\ub85c\ub2c8\uce74"
    ],
    "name:lav_x_preferred":[
        "Veronika"
    ],
    "name:nld_x_preferred":[
        "Veronica"
    ],
    "name:nor_x_preferred":[
        "Veronica"
    ],
    "name:pol_x_preferred":[
        "Veronica"
    ],
    "name:que_x_preferred":[
        "Veronica"
    ],
    "name:ron_x_preferred":[
        "Veronica"
    ],
    "name:rus_x_preferred":[
        "\u0412\u0435\u0440\u043e\u043d\u0438\u043a\u0430"
    ],
    "name:spa_x_preferred":[
        "Ver\u00f3nica"
    ],
    "name:swe_x_preferred":[
        "Ver\u00f3nica"
    ],
    "name:ukr_x_preferred":[
        "\u0412\u0435\u0440\u043e\u043d\u0456\u043a\u0430"
    ],
    "name:zho_x_preferred":[
        "Veronica"
    ],
    "wof:name":"Veronica",
    "wof:placetype":"locality"
},
  "geometry": {"coordinates":[120.6027,18.0697],"type":"Point"}
}