{
  "type": "Feature",
  "properties": {
    "gn:admin1_code":"40",
    "gn:admin2_code":"H2",
    "gn:admin3_code":"45648000.0",
    "gn:asciiname":"Fernando",
    "gn:country_code":"PH",
    "gn:dem":73,
    "gn:feature_class":"P",
    "gn:feature_code":"PPL",
    "gn:name":"Fernando",
    "gn:population":0,
    "gn:timezone":"Asia/Manila",
    "iso:country":"PH",
    "name:aze_x_preferred":[
        "Fernando"
    ],
    "name:bre_x_preferred":[
        "Fernando"
    ],
    "name:ces_x_preferred":[
        "Ferdinand"
    ],
    "name:deu_x_preferred":[
        "Ferdinand"
    ],
    "name:epo_x_preferred":[
        "Ferdinando"
    ],
    "name:fil_x_preferred":[
        "Fernando"
    ],
    "name:fin_x_preferred":[
        "Ferdinand"
    ],
    "name:glg_x_preferred":[
        "Fernando"
    ],
    "name:hun_x_preferred":[
        "Ferdin\u00e1nd"
    ],
    "name:ita_x_preferred":[
        "Ferdinando"
    ],
    "name:lat_x_preferred":[
        "Ferdinandus"
    ],
    "name:nor_x_preferred":[
        "Ferdinand"
    ],
    "name:pol_x_preferred":[
        "Ferdynand"
    ],
    "name:por_x_preferred":[
        "Fernando"
    ],
    "name:rus_x_preferred":[
        "Fernando"
    ],
    "name:slk_x_preferred":[
        "Ferdinand"
    ],
    "name:slv_x_preferred":[
        "Ferdinand"
    ],
    "name:spa_x_preferred":[
        "Fernando"
    ],
    "name:ukr_x_preferred":[
        "\u0424\u0435\u0440\u043d\u0430\u043d\u0434\u0443"
    ],
    "wof:name":"Fernando",
    "wof:placetype":"locality"
},
  "geometry": {"coordinates":[121.38333,13.95],"type":"Point"}
}