{
  "type": "Feature",
  "properties": {
    "gn:admin1_code":"06",
    "gn:admin2_code":"06",
    "gn:admin3_code":"60616000.0",
    "gn:asciiname":"Bunga",
    "gn:country_code":"PH",
    "gn:dem":147,
    "gn:feature_class":"P",
    "gn:feature_code":"PPL",
    "gn:name":"Bunga",
    "gn:population":0,
    "gn:timezone":"Asia/Manila",
    "iso:country":"PH",
    "name:ara_x_preferred":[
        "\u0628\u0648\u0646\u062c\u0627"
    ],
    "name:ben_x_preferred":[
        "\u09ac\u09c1\u0982\u0997\u09be"
    ],
    "name:ceb_x_preferred":[
        "Bunga"
    ],
    "name:deu_x_preferred":[
        "Bunga "
    ],
    "name:ell_x_preferred":[
        "\u039c\u03c0\u03bf\u03cd\u03bd\u03b3\u03ba\u03b1"
    ],
    "name:fas_x_preferred":[
        "\u0628\u0648\u0646\u06af\u0627"
    ],
    "name:fil_x_preferred":[
        "Bunga"
    ],
    "name:fra_x_preferred":[
        "Bunga"
    ],
    "name:heb_x_preferred":[
        "\u05d1\u05d5\u05e0\u05d2\u05d4"
    ],
    "name:hin_x_preferred":[
        "\u092c\u0902\u0917\u093e"
    ],
    "name:hun_x_preferred":[
        "Bunga"
    ],
    "name:ind_x_preferred":[
        "Bunga"
    ],
    "name:ita_x_preferred":[
        "Bunga"
    ],
    "name:jpn_x_preferred":[
        "\u30d0\u30f3\u30ac\u5ddd"
    ],
    "name:kor_x_preferred":[
        "\ubd95\uac00"
    ],
    "name:nld_x_preferred":[
        "Bunga"
    ],
    "name:pol_x_preferred":[
        "Bunga"
    ],
    "name:por_x_preferred":[
        "Bunga"
    ],
    "name:rus_x_preferred":[
        "\u0411\u0443\u043d\u0433\u0430"
    ],
    "name:spa_x_preferred":[
        "Bunga"
    ],
    "name:swe_x_preferred":[
        "Bunga"
    ],
    "name:tgl_x_preferred":[
        "Bunga"
    ],
    "name:tur_x_preferred":[
        "Bunga"
    ],
    "name:ukr_x_preferred":[
        "\u0411\u0443\u043d\u0433\u0430"
    ],
    "name:urd_x_preferred":[
        "\u0628\u0648\u0646\u06af\u0627"
    ],
    "name:vie_x_preferred":[
        "S\u00f4ng Bunga"
    ],
    "name:zho_cn_x_preferred":[
        "\u90a6\u52a0\u6cb3"
    ],
    "name:zho_tw_x_preferred":[
        "\u73ed\u52a0"
    ],
    "wof:name":"Bunga",
    "wof:placetype":"locality"
},
  "geometry": {"coordinates":[122.08333,10.76667],"type":"Point"}
}