{
  "type": "Feature",
  "properties": {
    "gn:country":"PH",
    "gn:fcode":"PPL",
    "gn:pop":2639,
    "iso:country":"PH",
    "name:fil_x_preferred":[
        "Barcelona"
    ],
    "name:unk_x_variant":[
        "Barceloneta"
    ],
    "qs:name":"Barcelona",
    "qs:photos_9r":0,
    "qs:photos_sr":0,
    "qs:pop_sr":"4",
    "wof:name":"Barcelona",
    "wof:placetype":"locality",
    "wof:population":2639
},
  "geometry": {"coordinates":[123.0485,13.7715],"type":"Point"}
}