{
  "type": "Feature",
  "properties": {
    "gn:admin1_code":"14",
    "gn:admin2_code":"56",
    "gn:admin3_code":"153831000.0",
    "gn:asciiname":"Nunongan",
    "gn:country_code":"PH",
    "gn:dem":17,
    "gn:feature_class":"P",
    "gn:feature_code":"PPL",
    "gn:name":"Nunongan",
    "gn:population":0,
    "gn:timezone":"Asia/Manila",
    "iso:country":"PH",
    "name:fil_x_preferred":[
        "Nunongan"
    ],
    "wof:name":"Nunongan",
    "wof:placetype":"locality"
},
  "geometry": {"coordinates":[124.39055999999999,7.02056],"type":"Point"}
}