{
  "type": "Feature",
  "properties": {
    "gn:admin1_code":"41",
    "gn:admin2_code":"49",
    "gn:admin3_code":"175316000.0",
    "gn:asciiname":"Santa Teresa",
    "gn:country_code":"PH",
    "gn:dem":12,
    "gn:feature_class":"P",
    "gn:feature_code":"PPL",
    "gn:name":"Santa Teresa",
    "gn:population":0,
    "gn:timezone":"Asia/Manila",
    "iso:country":"PH",
    "name:fil_x_preferred":[
        "Santa Teresa"
    ],
    "wof:name":"Santa Teresa",
    "wof:placetype":"locality"
},
  "geometry": {"coordinates":[118.66667,9.73333],"type":"Point"}
}