{
  "type": "Feature",
  "properties": {
    "gn:country":"PH",
    "gn:fcode":"PPL",
    "gn:pop":2440,
    "iso:country":"PH",
    "name:aze_x_preferred":[
        "San-\u0130sidro"
    ],
    "name:cat_x_preferred":[
        "San Isidro"
    ],
    "name:ceb_x_preferred":[
        "San Isidro"
    ],
    "name:deu_x_preferred":[
        "San Isidro"
    ],
    "name:eus_x_preferred":[
        "San Isidro"
    ],
    "name:fil_x_preferred":[
        "San Isidro"
    ],
    "name:fra_x_preferred":[
        "San Isidro"
    ],
    "name:ilo_x_preferred":[
        "San Isidro"
    ],
    "name:ita_x_preferred":[
        "San Isidro"
    ],
    "name:lit_x_preferred":[
        "San Isidras"
    ],
    "name:mlg_x_preferred":[
        "San Isidro"
    ],
    "name:nds_x_preferred":[
        "San Isidro"
    ],
    "name:nld_x_preferred":[
        "San Isidro"
    ],
    "name:pol_x_preferred":[
        "San Isidro"
    ],
    "name:por_x_preferred":[
        "San Isidro"
    ],
    "name:rus_x_preferred":[
        "\u0421\u0430\u043d-\u0418\u0441\u0438\u0434\u0440\u043e"
    ],
    "name:sco_x_preferred":[
        "San Isidro"
    ],
    "name:spa_x_preferred":[
        "San Isidro"
    ],
    "name:srp_x_preferred":[
        "\u0421\u0430\u043d \u0418\u0441\u0438\u0434\u0440\u043e"
    ],
    "name:swe_x_preferred":[
        "San Isidro"
    ],
    "name:vie_x_preferred":[
        "San Isidro"
    ],
    "name:war_x_preferred":[
        "San Isidro"
    ],
    "qs:name":"San Isidro",
    "qs:photos_9r":0,
    "qs:photos_sr":0,
    "qs:pop_sr":"4",
    "wd:wordcount":1052,
    "wof:name":"San Isidro",
    "wof:placetype":"locality",
    "wof:population":2440
},
  "geometry": {"coordinates":[123.73350000000001,10.5508],"type":"Point"}
}