{
  "type": "Feature",
  "properties": {
    "gn:admin1_code":"03",
    "gn:admin2_code":"47",
    "gn:admin3_code":"34912000.0",
    "gn:asciiname":"Manaul",
    "gn:country_code":"PH",
    "gn:dem":22,
    "gn:feature_class":"P",
    "gn:feature_code":"PPL",
    "gn:name":"Manaul",
    "gn:population":0,
    "gn:timezone":"Asia/Manila",
    "iso:country":"PH",
    "name:fil_x_preferred":[
        "Manaul"
    ],
    "name:por_x_preferred":[
        "Manaul"
    ],
    "name:spa_x_preferred":[
        "Manaul"
    ],
    "name:tgl_x_preferred":[
        "Manaul"
    ],
    "wof:name":"Manaul",
    "wof:placetype":"locality"
},
  "geometry": {"coordinates":[120.81667,15.41667],"type":"Point"}
}