{
  "type": "Feature",
  "properties": {
    "gn:country":"PH",
    "gn:fcode":"PPL",
    "gn:population":2941,
    "iso:country":"PH",
    "name:fil_x_preferred":[
        "Lalagsan"
    ],
    "qs:name":"Lalagsan",
    "qs:photos_9r":0,
    "qs:photos_sr":0,
    "qs:pop_sr":"4",
    "wof:name":"Lalagsan",
    "wof:placetype":"locality",
    "wof:population":2941
},
  "geometry": {"coordinates":[123.01300000000001,10.2824],"type":"Point"}
}