{
  "type": "Feature",
  "properties": {
    "gn:admin1_code":"40",
    "gn:admin2_code":"20",
    "gn:admin3_code":"42112000.0",
    "gn:asciiname":"Tulay",
    "gn:country_code":"PH",
    "gn:dem":285,
    "gn:feature_class":"P",
    "gn:feature_code":"PPL",
    "gn:name":"Tulay",
    "gn:population":0,
    "gn:timezone":"Asia/Manila",
    "iso:country":"PH",
    "name:fil_x_preferred":[
        "Tulay"
    ],
    "wof:name":"Tulay",
    "wof:placetype":"locality"
},
  "geometry": {"coordinates":[120.78167000000001,14.13361],"type":"Point"}
}