{
  "type": "Feature",
  "properties": {
    "gn:admin1_code":"07",
    "gn:admin2_code":"11",
    "gn:admin3_code":"71242000.0",
    "gn:asciiname":"Mansasa",
    "gn:country_code":"PH",
    "gn:dem":25,
    "gn:feature_class":"P",
    "gn:feature_code":"PPL",
    "gn:name":"Mansasa",
    "gn:population":0,
    "gn:timezone":"Asia/Manila",
    "iso:country":"PH",
    "name:fil_x_preferred":[
        "Mansasa"
    ],
    "wof:name":"Mansasa",
    "wof:placetype":"locality"
},
  "geometry": {"coordinates":[123.869,9.63372],"type":"Point"}
}