{
  "type": "Feature",
  "properties": {
    "gn:admin1_code":"02",
    "gn:admin2_code":"14",
    "gn:admin3_code":"21522000.0",
    "gn:asciiname":"San Andreas",
    "gn:country_code":"PH",
    "gn:dem":12,
    "gn:feature_class":"P",
    "gn:feature_code":"PPL",
    "gn:name":"San Andreas",
    "gn:population":0,
    "gn:timezone":"Asia/Manila",
    "iso:country":"PH",
    "wof:name":"San Andreas",
    "wof:placetype":"locality"
},
  "geometry": {"coordinates":[121.17243000000001,18.60514],"type":"Point"}
}