{
  "type": "Feature",
  "properties": {
    "gn:admin1_code":"02",
    "gn:admin2_code":"14",
    "gn:admin3_code":"21522000.0",
    "gn:asciiname":"San Andreas",
    "gn:country_code":"PH",
    "gn:dem":12,
    "gn:feature_class":"P",
    "gn:feature_code":"PPL",
    "gn:name":"San Andreas",
    "gn:population":0,
    "gn:timezone":"Asia/Manila",
    "iso:country":"PH",
    "name:ara_x_preferred":[
        "\u0633\u0627\u0646 \u0623\u0646\u062f\u0631\u064a\u0627\u0633"
    ],
    "name:ceb_x_preferred":[
        "San Andreas"
    ],
    "name:ces_x_preferred":[
        "San Andreas"
    ],
    "name:deu_x_preferred":[
        "San Andreas"
    ],
    "name:fas_x_preferred":[
        "\u0633\u0646 \u0622\u0646\u062f\u0631\u06cc\u0627\u0633"
    ],
    "name:fin_x_preferred":[
        "San Andreas"
    ],
    "name:fra_x_preferred":[
        "San Andreas"
    ],
    "name:heb_x_preferred":[
        "\u05e1\u05df \u05d0\u05e0\u05d3\u05e8\u05d0\u05e1"
    ],
    "name:ita_x_preferred":[
        "San Andreas"
    ],
    "name:jpn_x_preferred":[
        "\u30b5\u30f3\u30a2\u30f3\u30c9\u30ec\u30a2\u30b9"
    ],
    "name:kor_x_preferred":[
        "\uc0cc\uc564\ub4dc\ub9ac\uc5b4\uc2a4"
    ],
    "name:lit_x_preferred":[
        "San Andreas"
    ],
    "name:nld_x_preferred":[
        "San Andreas"
    ],
    "name:nor_x_preferred":[
        "San Andreas"
    ],
    "name:pol_x_preferred":[
        "San Andreas"
    ],
    "name:por_x_preferred":[
        "San Andreas"
    ],
    "name:rus_x_preferred":[
        "\u0421\u0430\u043d-\u0410\u043d\u0434\u0440\u0435\u0430\u0441"
    ],
    "name:slk_x_preferred":[
        "San Andreas"
    ],
    "name:spa_x_preferred":[
        "San Andreas"
    ],
    "name:swe_x_preferred":[
        "San Andreas"
    ],
    "name:tha_x_preferred":[
        "\u0e41\u0e0b\u0e19\u0e41\u0e2d\u0e19\u0e40\u0e14\u0e23\u0e2d\u0e31\u0e2a"
    ],
    "name:tur_x_preferred":[
        "San Andreas"
    ],
    "name:ukr_x_preferred":[
        "\u0421\u0430\u043d-\u0410\u043d\u0434\u0440\u0435\u0430\u0441"
    ],
    "name:vie_x_preferred":[
        "San Andreas"
    ],
    "wof:name":"San Andreas",
    "wof:placetype":"locality"
},
  "geometry": {"coordinates":[121.17243000000001,18.60514],"type":"Point"}
}