{
  "type": "Feature",
  "properties": {
    "gn:admin1_code":"01",
    "gn:admin2_code":"29",
    "gn:admin3_code":"12903000.0",
    "gn:asciiname":"Ora",
    "gn:country_code":"PH",
    "gn:dem":15,
    "gn:feature_class":"P",
    "gn:feature_code":"PPL",
    "gn:name":"Ora",
    "gn:population":0,
    "gn:timezone":"Asia/Manila",
    "iso:country":"PH",
    "name:fil_x_preferred":[
        "Ora"
    ],
    "wof:name":"Ora",
    "wof:placetype":"locality"
},
  "geometry": {"coordinates":[120.41285000000001,17.6017],"type":"Point"}
}