{
  "type": "Feature",
  "properties": {
    "gn:admin1_code":"06",
    "gn:admin2_code":"H3",
    "gn:admin3_code":"64517000.0",
    "gn:asciiname":"Hacienda Velez Malaga",
    "gn:country_code":"PH",
    "gn:dem":54,
    "gn:feature_class":"P",
    "gn:feature_code":"PPL",
    "gn:name":"Hacienda Velez Malaga",
    "gn:population":0,
    "gn:timezone":"Asia/Manila",
    "iso:country":"PH",
    "name:fil_x_preferred":[
        "Hacienda Velez Malaga"
    ],
    "name:und_x_variant":[
        "Veles Malaga Hacienda"
    ],
    "wof:name":"Hacienda Velez Malaga",
    "wof:placetype":"locality"
},
  "geometry": {"coordinates":[123.0252,10.3125],"type":"Point"}
}