{
  "type": "Feature",
  "properties": {
    "gn:country":"PH",
    "gn:fcode":"PPL",
    "gn:pop":2214,
    "iso:country":"PH",
    "name:fil_x_preferred":[
        "Pagonisili"
    ],
    "qs:name":"Pogonsili",
    "qs:photos_9r":0,
    "qs:photos_sr":0,
    "qs:pop_sr":"4",
    "wof:name":"Pogonsili",
    "wof:placetype":"locality",
    "wof:population":2214
},
  "geometry": {"coordinates":[120.26017,15.82048],"type":"Point"}
}