{
  "type": "Feature",
  "properties": {
    "gn:country":"PH",
    "gn:fcode":"PPL",
    "gn:pop":5144,
    "iso:country":"PH",
    "name:ceb_x_preferred":[
        "Sabang"
    ],
    "name:fil_x_preferred":[
        "Sabang"
    ],
    "name:fra_x_preferred":[
        "Sabang"
    ],
    "name:swe_x_preferred":[
        "Sabang"
    ],
    "qs:name":"Sabang",
    "qs:photos_9r":0,
    "qs:photos_sr":0,
    "qs:pop_sr":"5",
    "wd:wordcount":86,
    "wof:name":"Sabang",
    "wof:placetype":"locality",
    "wof:population":5144
},
  "geometry": {"coordinates":[120.25069999999999,14.6951],"type":"Point"}
}