{
  "type": "Feature",
  "properties": {
    "gn:admin1_code":"11",
    "gn:admin2_code":"I6",
    "gn:admin3_code":"118201000.0",
    "gn:asciiname":"Lagab",
    "gn:country_code":"PH",
    "gn:dem":80,
    "gn:feature_class":"P",
    "gn:feature_code":"PPL",
    "gn:name":"Lagab",
    "gn:population":0,
    "gn:timezone":"Asia/Manila",
    "iso:country":"PH",
    "name:fil_x_preferred":[
        "Lagab"
    ],
    "wof:name":"Lagab",
    "wof:placetype":"locality"
},
  "geometry": {"coordinates":[126.0986,7.6522],"type":"Point"}
}