{
  "type": "Feature",
  "properties": {
    "gn:admin1_code":"06",
    "gn:admin2_code":"18",
    "gn:admin3_code":"61916000.0",
    "gn:asciiname":"Balsman",
    "gn:country_code":"PH",
    "gn:dem":23,
    "gn:feature_class":"P",
    "gn:feature_code":"PPL",
    "gn:name":"Balsman",
    "gn:population":0,
    "gn:timezone":"Asia/Manila",
    "iso:country":"PH",
    "name:fil_x_preferred":[
        "Balsman"
    ],
    "wof:name":"Balsman",
    "wof:placetype":"locality"
},
  "geometry": {"coordinates":[122.6375,11.4124],"type":"Point"}
}