{
  "type": "Feature",
  "properties": {
    "gn:country":"PH",
    "gn:fcode":"PPLA3",
    "gn:pop":0,
    "iso:country":"PH",
    "name:ceb_x_preferred":[
        "Danao"
    ],
    "name:ell_x_preferred":[
        "\u0394\u03b1\u03bd\u03b1\u03cc\u03c2"
    ],
    "name:eng_x_preferred":[
        "Danao"
    ],
    "name:fil_x_preferred":[
        "Danao"
    ],
    "name:fra_x_preferred":[
        "Danao"
    ],
    "name:ita_x_preferred":[
        "Danao"
    ],
    "name:msa_x_preferred":[
        "Danao"
    ],
    "name:nld_x_preferred":[
        "Danao"
    ],
    "name:spa_x_preferred":[
        "Danao"
    ],
    "name:war_x_preferred":[
        "Danao"
    ],
    "qs:name":"Danao",
    "qs:photos_9r":0,
    "qs:photos_sr":0,
    "qs:pop_sr":"0",
    "wd:wordcount":79,
    "wof:name":"Danao",
    "wof:placetype":"locality",
    "wof:population":0
},
  "geometry": {"coordinates":[124.22329999999999,9.945],"type":"Point"}
}