{
  "type": "Feature",
  "properties": {
    "gn:country":"PH",
    "gn:fcode":"PPL",
    "gn:pop":7418,
    "iso:country":"PH",
    "name:fil_x_preferred":[
        "Mamala"
    ],
    "name:unk_x_variant":[
        "Mamalo"
    ],
    "qs:name":"Mamala",
    "qs:photos_9r":0,
    "qs:photos_sr":0,
    "qs:pop_sr":"5",
    "wd:wordcount":350,
    "wof:name":"Mamala",
    "wof:placetype":"locality",
    "wof:population":7418
},
  "geometry": {"coordinates":[121.51667,14.01667],"type":"Point"}
}