{
  "type": "Feature",
  "properties": {
    "gn:admin1_code":"06",
    "gn:admin2_code":"30",
    "gn:admin3_code":"63021000.0",
    "gn:asciiname":"Tigbanaba",
    "gn:country_code":"PH",
    "gn:dem":193,
    "gn:feature_class":"P",
    "gn:feature_code":"PPL",
    "gn:name":"Tigbanaba",
    "gn:population":0,
    "gn:timezone":"Asia/Manila",
    "iso:country":"PH",
    "name:fil_x_preferred":[
        "Tigbanaba"
    ],
    "wof:name":"Tigbanaba",
    "wof:placetype":"locality"
},
  "geometry": {"coordinates":[122.22020000000001,10.75875],"type":"Point"}
}