{
  "type": "Feature",
  "properties": {
    "gn:admin1_code":"41",
    "gn:admin2_code":"49",
    "gn:admin3_code":"175309000.0",
    "gn:asciiname":"Wa",
    "gn:country_code":"PH",
    "gn:dem":40,
    "gn:feature_class":"P",
    "gn:feature_code":"PPL",
    "gn:name":"Wa",
    "gn:population":0,
    "gn:timezone":"Asia/Manila",
    "iso:country":"PH",
    "name:eng_x_preferred":[
        "Wa"
    ],
    "wof:name":"Wa",
    "wof:placetype":"locality"
},
  "geometry": {"coordinates":[120.20950000000001,12.08],"type":"Point"}
}