{
  "type": "Feature",
  "properties": {
    "gn:admin1_code":"01",
    "gn:admin2_code":"29",
    "gn:admin3_code":"12926000.0",
    "gn:asciiname":"Balangen",
    "gn:country_code":"PH",
    "gn:dem":9,
    "gn:feature_class":"P",
    "gn:feature_code":"PPL",
    "gn:name":"Balangen",
    "gn:population":0,
    "gn:timezone":"Asia/Manila",
    "iso:country":"PH",
    "name:fil_x_preferred":[
        "Balangen"
    ],
    "wof:name":"Balangen",
    "wof:placetype":"locality"
},
  "geometry": {"coordinates":[120.4462,17.3524],"type":"Point"}
}