{
  "type": "Feature",
  "properties": {
    "gn:admin1_code":"05",
    "gn:admin2_code":"16",
    "gn:admin3_code":"51723000.0",
    "gn:asciiname":"San Roque",
    "gn:country_code":"PH",
    "gn:dem":14,
    "gn:feature_class":"P",
    "gn:feature_code":"PPL",
    "gn:name":"San Roque",
    "gn:population":0,
    "gn:timezone":"Asia/Manila",
    "iso:country":"PH",
    "name:fil_x_preferred":[
        "San Roque"
    ],
    "wof:name":"San Roque",
    "wof:placetype":"locality"
},
  "geometry": {"coordinates":[123.37350000000001,13.3962],"type":"Point"}
}