{
  "type": "Feature",
  "properties": {
    "gn:country":"PH",
    "gn:fcode":"PPLA3",
    "gn:population":2340,
    "iso:country":"PH",
    "name:bcl_x_preferred":[
        "San Nicolas"
    ],
    "name:cat_x_preferred":[
        "San Nicolas"
    ],
    "name:ceb_x_preferred":[
        "San Nicolas"
    ],
    "name:deu_x_preferred":[
        "San Nicolas"
    ],
    "name:eng_x_preferred":[
        "San Nicolas"
    ],
    "name:fra_x_preferred":[
        "San Nicolas"
    ],
    "name:ilo_x_preferred":[
        "San Nicolas"
    ],
    "name:ind_x_preferred":[
        "San Nicolas"
    ],
    "name:ita_x_preferred":[
        "San Nicolas"
    ],
    "name:nld_x_preferred":[
        "San Nicolas"
    ],
    "name:oci_x_preferred":[
        "San Nicolas"
    ],
    "name:pag_x_preferred":[
        "San Nikolas"
    ],
    "name:pag_x_variant":[
        "San Nicolas"
    ],
    "name:pam_x_preferred":[
        "San Nicolas"
    ],
    "name:sco_x_preferred":[
        "San Nicolas"
    ],
    "name:spa_x_preferred":[
        "San Nicol\u00e1s"
    ],
    "name:swe_x_preferred":[
        "San Nicolas"
    ],
    "name:tgl_x_preferred":[
        "San Nicolas"
    ],
    "name:urd_x_preferred":[
        "\u0633\u0627\u0646 \u0646\u06cc\u06a9\u0648\u0644\u0627\u0633"
    ],
    "name:vie_x_preferred":[
        "San Nicolas"
    ],
    "name:war_x_preferred":[
        "San Nicolas"
    ],
    "qs:name":"San Nicolas",
    "qs:photos_9r":0,
    "qs:photos_sr":0,
    "qs:pop_sr":"4",
    "wd:wordcount":277,
    "wof:name":"San Nicolas",
    "wof:placetype":"locality",
    "wof:population":2340
},
  "geometry": {"coordinates":[120.95099999999999,13.92825],"type":"Point"}
}