{
  "type": "Feature",
  "properties": {
    "gn:country":"PH",
    "gn:fcode":"PPL",
    "gn:pop":2370,
    "iso:country":"PH",
    "name:eng_x_preferred":[
        "Nagiba"
    ],
    "name:unk_x_variant":[
        "Nag-iba II"
    ],
    "qs:name":"Nagiba",
    "qs:photos_9r":0,
    "qs:photos_sr":0,
    "qs:pop_sr":"4",
    "wof:name":"Nagiba",
    "wof:placetype":"locality",
    "wof:population":2370
},
  "geometry": {"coordinates":[121.27432,13.33018],"type":"Point"}
}