{
  "type": "Feature",
  "properties": {
    "gn:admin1_code":"06",
    "gn:admin2_code":"H3",
    "gn:admin3_code":"64521000.0",
    "gn:asciiname":"Natubungan",
    "gn:country_code":"PH",
    "gn:dem":18,
    "gn:feature_class":"P",
    "gn:feature_code":"PPL",
    "gn:name":"Natubungan",
    "gn:population":0,
    "gn:timezone":"Asia/Manila",
    "iso:country":"PH",
    "name:fil_x_preferred":[
        "Natubungan"
    ],
    "wof:name":"Natubungan",
    "wof:placetype":"locality"
},
  "geometry": {"coordinates":[122.9034,10.3289],"type":"Point"}
}