{
  "type": "Feature",
  "properties": {
    "gn:admin1_code":"40",
    "gn:admin2_code":"H2",
    "gn:admin3_code":"45608000.0",
    "gn:asciiname":"Masin Sur",
    "gn:country_code":"PH",
    "gn:dem":44,
    "gn:feature_class":"P",
    "gn:feature_code":"PPL",
    "gn:name":"Masin Sur",
    "gn:population":0,
    "gn:timezone":"Asia/Manila",
    "iso:country":"PH",
    "name:fil_x_preferred":[
        "Masin Sur"
    ],
    "name:und_x_variant":[
        "Masin"
    ],
    "wof:name":"Masin Sur",
    "wof:placetype":"locality"
},
  "geometry": {"coordinates":[121.39722,13.92028],"type":"Point"}
}