{
  "type": "Feature",
  "properties": {
    "gn:admin1_code":"09",
    "gn:admin2_code":"66",
    "gn:admin3_code":"97327000.0",
    "gn:asciiname":"Abongabong",
    "gn:country_code":"PH",
    "gn:dem":234,
    "gn:feature_class":"P",
    "gn:feature_code":"PPL",
    "gn:name":"Abongabong",
    "gn:population":0,
    "gn:timezone":"Asia/Manila",
    "iso:country":"PH",
    "name:ara_x_preferred":[
        "\u0623\u0628\u0648\u0646\u063a\u0627\u0628\u0648\u0646\u063a"
    ],
    "name:ben_x_preferred":[
        "\u0985\u09cd\u09af\u09be\u09ac\u09a8\u0997\u09cd\u09af\u09be\u09ac\u0982"
    ],
    "name:deu_x_preferred":[
        "Abongabong"
    ],
    "name:ell_x_preferred":[
        "\u0391\u03bc\u03c0\u03bf\u03bd\u03b3\u03ba\u03b1\u03bc\u03c0\u03cc\u03bd\u03b3\u03ba"
    ],
    "name:eng_x_preferred":[
        "Abongabong"
    ],
    "name:fas_x_preferred":[
        "\u0627\u0628\u0648\u0646\u06af\u0628\u0648\u0646\u06af"
    ],
    "name:fra_x_preferred":[
        "Montagne Abong-abong"
    ],
    "name:heb_x_preferred":[
        "\u05d0\u05d1\u05d5\u05e0\u05d2\u05d1\u05d5\u05e0\u05d2"
    ],
    "name:hin_x_preferred":[
        "\u0905\u092c\u094b\u0902\u0917\u093e\u092c\u094b\u0902\u0917"
    ],
    "name:hun_x_preferred":[
        "Abongabong"
    ],
    "name:ind_x_preferred":[
        "Abongabong"
    ],
    "name:ita_x_preferred":[
        "Abongabong"
    ],
    "name:jpn_x_preferred":[
        "\u30a2\u30dc\u30f3\u30ac\u30dc\u30f3\u30b0\u5c71\u8108"
    ],
    "name:kor_x_preferred":[
        "\uc544\ubd09\uac00\ubd09"
    ],
    "name:pol_x_preferred":[
        "Abong Abong"
    ],
    "name:por_x_preferred":[
        "Abong Abong"
    ],
    "name:rus_x_preferred":[
        "\u0410\u0431\u043e\u043d\u0433\u0430\u0431\u043e\u043d\u0433"
    ],
    "name:spa_x_preferred":[
        "Abongabong"
    ],
    "name:tur_x_preferred":[
        "Abongabong"
    ],
    "name:ukr_x_preferred":[
        "\u0410\u0431\u043e\u043d\u0433\u0430\u0431\u043e\u043d"
    ],
    "name:urd_x_preferred":[
        "\u0627\u06cc\u0628\u0648\u0646\u06af\u0627\u0628\u0648\u0646\u06af"
    ],
    "name:vie_x_preferred":[
        "N\u00fai Abongabong"
    ],
    "name:zho_cn_x_preferred":[
        "\u963f\u90a6\u963f\u90a6\u5c71"
    ],
    "name:zho_tw_x_preferred":[
        "\u963f\u90a6\u963f\u90a6"
    ],
    "wof:name":"Abongabong",
    "wof:placetype":"locality"
},
  "geometry": {"coordinates":[123.3965,7.4345],"type":"Point"}
}