{
  "type": "Feature",
  "properties": {
    "gn:admin1_code":"09",
    "gn:admin2_code":"66",
    "gn:admin3_code":"97327000.0",
    "gn:asciiname":"Abongabong",
    "gn:country_code":"PH",
    "gn:dem":234,
    "gn:feature_class":"P",
    "gn:feature_code":"PPL",
    "gn:name":"Abongabong",
    "gn:population":0,
    "gn:timezone":"Asia/Manila",
    "iso:country":"PH",
    "name:eng_x_preferred":[
        "Abongabong"
    ],
    "wof:name":"Abongabong",
    "wof:placetype":"locality"
},
  "geometry": {"coordinates":[123.3965,7.4345],"type":"Point"}
}