{
  "type": "Feature",
  "properties": {
    "gn:admin1_code":"15",
    "gn:admin2_code":"H6",
    "gn:admin3_code":"148104000.0",
    "gn:asciiname":"Magapta",
    "gn:country_code":"PH",
    "gn:dem":107,
    "gn:feature_class":"P",
    "gn:feature_code":"PPL",
    "gn:name":"Magapta",
    "gn:population":0,
    "gn:timezone":"Asia/Manila",
    "iso:country":"PH",
    "name:fil_x_preferred":[
        "Magapta"
    ],
    "wof:name":"Magapta",
    "wof:placetype":"locality"
},
  "geometry": {"coordinates":[121.19974999999999,18.02728],"type":"Point"}
}