{
  "type": "Feature",
  "properties": {
    "gn:admin1_code":"10",
    "gn:admin2_code":"34",
    "gn:admin3_code":"103504000.0",
    "gn:asciiname":"Datto Lantoy",
    "gn:cc2":"PH",
    "gn:country_code":"PH",
    "gn:dem":10,
    "gn:feature_class":"P",
    "gn:feature_code":"PPL",
    "gn:name":"Datto Lantoy",
    "gn:population":0,
    "gn:timezone":"Asia/Manila",
    "iso:country":"PH",
    "name:und_x_variant":[
        "Datto Lantay"
    ],
    "wof:name":"Datto Lantoy",
    "wof:placetype":"locality"
},
  "geometry": {"coordinates":[124.26667,8.25],"type":"Point"}
}