{
  "type": "Feature",
  "properties": {
    "gn:admin1_code":"06",
    "gn:admin2_code":"30",
    "gn:admin3_code":"63038000.0",
    "gn:asciiname":"Bondolan",
    "gn:country_code":"PH",
    "gn:dem":25,
    "gn:feature_class":"P",
    "gn:feature_code":"PPL",
    "gn:name":"Bondolan",
    "gn:population":0,
    "gn:timezone":"Asia/Manila",
    "iso:country":"PH",
    "name:eng_x_preferred":[
        "Bondolan"
    ],
    "name:und_x_variant":[
        "Bendulan"
    ],
    "wof:name":"Bondolan",
    "wof:placetype":"locality"
},
  "geometry": {"coordinates":[123.0783,11.2832],"type":"Point"}
}