{
  "type": "Feature",
  "properties": {
    "gn:admin1_code":"40",
    "gn:admin2_code":"09",
    "gn:admin3_code":"41006000.0",
    "gn:asciiname":"Batogo",
    "gn:country_code":"PH",
    "gn:dem":124,
    "gn:feature_class":"P",
    "gn:feature_code":"PPL",
    "gn:name":"Batogo",
    "gn:population":0,
    "gn:timezone":"Asia/Manila",
    "iso:country":"PH",
    "name:fil_x_preferred":[
        "Batogo"
    ],
    "wof:name":"Batogo",
    "wof:placetype":"locality"
},
  "geometry": {"coordinates":[120.95,13.78333],"type":"Point"}
}