{
  "type": "Feature",
  "properties": {
    "gn:admin1_code":"03",
    "gn:admin2_code":"13",
    "gn:admin3_code":"31424000.0",
    "gn:asciiname":"Camachile",
    "gn:country_code":"PH",
    "gn:dem":91,
    "gn:feature_class":"P",
    "gn:feature_code":"PPL",
    "gn:name":"Camachile",
    "gn:population":0,
    "gn:timezone":"Asia/Manila",
    "iso:country":"PH",
    "name:fil_x_preferred":[
        "Camachile"
    ],
    "wof:name":"Camachile",
    "wof:placetype":"locality"
},
  "geometry": {"coordinates":[121.07089999999999,14.9701],"type":"Point"}
}