{
  "type": "Feature",
  "properties": {
    "gn:country":"PH",
    "gn:fcode":"ADM3",
    "gn:population":6975,
    "iso:country":"PH",
    "name:fil_x_preferred":[
        "Talalora"
    ],
    "qs:name":"Talalora",
    "qs:photos_9r":0,
    "qs:photos_sr":0,
    "qs:pop_sr":"5",
    "wof:name":"Talalora",
    "wof:placetype":"localadmin",
    "wof:population":6975
},
  "geometry": {"coordinates":[124.86667,11.51667],"type":"Point"}
}