{
  "type": "Feature",
  "properties": {
    "gn:admin1_code":"40",
    "gn:admin2_code":"09",
    "gn:admin3_code":"41017000.0",
    "gn:asciiname":"Bulihan",
    "gn:country_code":"PH",
    "gn:dem":206,
    "gn:feature_class":"P",
    "gn:feature_code":"PPL",
    "gn:name":"Bulihan",
    "gn:population":0,
    "gn:timezone":"Asia/Manila",
    "iso:country":"PH",
    "name:fil_x_preferred":[
        "Bulihan"
    ],
    "wof:name":"Bulihan",
    "wof:placetype":"locality"
},
  "geometry": {"coordinates":[121.13764,14.03427],"type":"Point"}
}