{
  "type": "Feature",
  "properties": {
    "gn:admin1_code":"10",
    "gn:admin2_code":"34",
    "gn:admin3_code":"103513000.0",
    "gn:asciiname":"Balut",
    "gn:country_code":"PH",
    "gn:dem":553,
    "gn:feature_class":"P",
    "gn:feature_code":"PPL",
    "gn:name":"Balut",
    "gn:population":0,
    "gn:timezone":"Asia/Manila",
    "iso:country":"PH",
    "name:dan_x_preferred":[
        "Balut"
    ],
    "name:fil_x_preferred":[
        "Balut"
    ],
    "name:fra_x_preferred":[
        "Balut"
    ],
    "name:hun_x_preferred":[
        "Balut"
    ],
    "name:jav_x_preferred":[
        "Balut"
    ],
    "name:mar_x_preferred":[
        "\u092c\u0932\u0941\u0924\u0902"
    ],
    "name:nld_x_preferred":[
        "Balut"
    ],
    "wof:name":"Balut",
    "wof:placetype":"locality"
},
  "geometry": {"coordinates":[124.16139,8.08806],"type":"Point"}
}