{
  "type": "Feature",
  "properties": {
    "gn:admin1_code":"05",
    "gn:admin2_code":"15",
    "gn:admin3_code":"51610000.0",
    "gn:asciiname":"Palong Guitguit",
    "gn:country_code":"PH",
    "gn:dem":4,
    "gn:feature_class":"P",
    "gn:feature_code":"PPL",
    "gn:name":"Palong Guitguit",
    "gn:population":0,
    "gn:timezone":"Asia/Manila",
    "iso:country":"PH",
    "name:fil_x_preferred":[
        "Palong Guitguit"
    ],
    "name:und_x_variant":[
        "Polongguit-guit"
    ],
    "wof:name":"Palong Guitguit",
    "wof:placetype":"locality"
},
  "geometry": {"coordinates":[122.37627000000001,14.21295],"type":"Point"}
}