{
  "type": "Feature",
  "properties": {
    "gn:admin1_code":"08",
    "gn:admin2_code":"37",
    "gn:admin3_code":"83743000.0",
    "gn:asciiname":"Kinalumsan",
    "gn:country_code":"PH",
    "gn:dem":23,
    "gn:feature_class":"P",
    "gn:feature_code":"PPL",
    "gn:name":"Kinalumsan",
    "gn:population":0,
    "gn:timezone":"Asia/Manila",
    "iso:country":"PH",
    "name:eng_x_preferred":[
        "Kinalumsan"
    ],
    "name:und_x_variant":[
        "Kinalunsan"
    ],
    "wof:name":"Kinalumsan",
    "wof:placetype":"locality"
},
  "geometry": {"coordinates":[124.81529999999999,11.3444],"type":"Point"}
}