{
  "type": "Feature",
  "properties": {
    "gn:admin1_code":"06",
    "gn:admin2_code":"30",
    "gn:admin3_code":"63017000.0",
    "gn:asciiname":"Badiang",
    "gn:country_code":"PH",
    "gn:dem":57,
    "gn:feature_class":"P",
    "gn:feature_code":"PPL",
    "gn:name":"Badiang",
    "gn:population":0,
    "gn:timezone":"Asia/Manila",
    "iso:country":"PH",
    "name:fil_x_preferred":[
        "Badiang"
    ],
    "wof:name":"Badiang",
    "wof:placetype":"locality"
},
  "geometry": {"coordinates":[122.6138,11.089],"type":"Point"}
}