{
  "type": "Feature",
  "properties": {
    "gn:admin1_code":"41",
    "gn:admin2_code":"49",
    "gn:admin3_code":"175307000.0",
    "gn:asciiname":"Quezon",
    "gn:country_code":"PH",
    "gn:dem":12,
    "gn:feature_class":"P",
    "gn:feature_code":"PPL",
    "gn:name":"Quezon",
    "gn:population":0,
    "gn:timezone":"Asia/Manila",
    "iso:country":"PH",
    "name:ace_x_preferred":[
        "Propinsi Quezon"
    ],
    "name:ara_x_preferred":[
        "\u0643\u0632\u0648\u0646"
    ],
    "name:azb_x_preferred":[
        "\u06a9\u0632\u0648\u0646"
    ],
    "name:bcl_x_preferred":[
        "Quezon"
    ],
    "name:ceb_x_preferred":[
        "Quezon"
    ],
    "name:deu_x_preferred":[
        "Quezon"
    ],
    "name:eng_x_preferred":[
        "Quezon"
    ],
    "name:fas_x_preferred":[
        "\u06a9\u0632\u0648\u0646"
    ],
    "name:fin_x_preferred":[
        "Quezon"
    ],
    "name:fra_x_preferred":[
        "Quezon"
    ],
    "name:hin_x_preferred":[
        "\u0915\u0947\u091c\u093c\u094b\u0928 \u092a\u094d\u0930\u093e\u0928\u094d\u0924"
    ],
    "name:ilo_x_preferred":[
        "Quezon"
    ],
    "name:ind_x_preferred":[
        "Quezon"
    ],
    "name:jpn_x_preferred":[
        "\u30b1\u30bd\u30f3\u5dde"
    ],
    "name:kor_x_preferred":[
        "\ucf00\uc190\uc8fc"
    ],
    "name:lat_x_preferred":[
        "Quezon"
    ],
    "name:mkd_x_preferred":[
        "\u041a\u0435\u0437\u043e\u043d"
    ],
    "name:msa_x_preferred":[
        "Quezon"
    ],
    "name:nld_x_preferred":[
        "Quezon"
    ],
    "name:nor_x_preferred":[
        "Quezon"
    ],
    "name:pag_x_preferred":[
        "Quezon"
    ],
    "name:pam_x_preferred":[
        "Quezon"
    ],
    "name:pol_x_preferred":[
        "Quezon"
    ],
    "name:rus_x_preferred":[
        "\u041a\u0435\u0441\u043e\u043d"
    ],
    "name:sco_x_preferred":[
        "Quezon"
    ],
    "name:swe_x_preferred":[
        "Quezon"
    ],
    "name:tam_x_preferred":[
        "\u0b95\u0bc1\u0bb5\u0bbf\u0b9a\u0bcb\u0ba9\u0bcd"
    ],
    "name:tgl_x_preferred":[
        "Quezon"
    ],
    "name:tha_x_preferred":[
        "\u0e08\u0e31\u0e07\u0e2b\u0e27\u0e31\u0e14\u0e40\u0e04\u0e42\u0e0b\u0e19"
    ],
    "name:tur_x_preferred":[
        "Quezon"
    ],
    "name:ukr_x_preferred":[
        "\u041a\u0435\u0441\u043e\u043d"
    ],
    "name:urd_x_preferred":[
        "\u06a9\u0648\u06cc\u0632\u0648\u0646"
    ],
    "name:vie_x_preferred":[
        "Quezon"
    ],
    "name:war_x_preferred":[
        "Quezon"
    ],
    "name:zho_x_preferred":[
        "\u594e\u677e\u7701"
    ],
    "wof:name":"Quezon",
    "wof:placetype":"locality"
},
  "geometry": {"coordinates":[119.88061,12.27786],"type":"Point"}
}