{
  "type": "Feature",
  "properties": {
    "gn:country":"PH",
    "gn:fcode":"ADM3",
    "gn:pop":43417,
    "iso:country":"PH",
    "name:bcl_x_preferred":[
        "Guinayangan"
    ],
    "name:cat_x_preferred":[
        "Guinayangan"
    ],
    "name:ceb_x_preferred":[
        "Guinayangan"
    ],
    "name:deu_x_preferred":[
        "Guinayangan"
    ],
    "name:eng_x_preferred":[
        "Guinayangan"
    ],
    "name:fil_x_preferred":[
        "Guinayangan"
    ],
    "name:fra_x_preferred":[
        "Guinayangan"
    ],
    "name:ilo_x_preferred":[
        "Guinayangan"
    ],
    "name:ind_x_preferred":[
        "Guinayangan"
    ],
    "name:ita_x_preferred":[
        "Guinayangan"
    ],
    "name:jpn_x_preferred":[
        "\u30ae\u30ca\u30e4\u30f3\u30ac\u30f3"
    ],
    "name:nld_x_preferred":[
        "Guinayangan"
    ],
    "name:oci_x_preferred":[
        "Guinayangan"
    ],
    "name:pag_x_preferred":[
        "Guinayangan"
    ],
    "name:pam_x_preferred":[
        "Guinayangan"
    ],
    "name:spa_x_preferred":[
        "Guinayangan"
    ],
    "name:swe_x_preferred":[
        "Guinayangan"
    ],
    "name:tgl_x_preferred":[
        "Guinayangan"
    ],
    "name:vie_x_preferred":[
        "Guinayangan"
    ],
    "name:war_x_preferred":[
        "Guinayangan"
    ],
    "qs:name":"Guinayangan",
    "qs:photos_9r":0,
    "qs:photos_sr":0,
    "qs:pop_sr":"7",
    "wd:wordcount":379,
    "wof:name":"Guinayangan",
    "wof:placetype":"localadmin",
    "wof:population":43417
},
  "geometry": {"coordinates":[122.41667,13.93333],"type":"Point"}
}