{
  "type": "Feature",
  "properties": {
    "gn:admin1_code":"14",
    "gn:admin2_code":"35",
    "gn:admin3_code":"153618000.0",
    "gn:asciiname":"Senon",
    "gn:country_code":"PH",
    "gn:dem":702,
    "gn:feature_class":"P",
    "gn:feature_code":"PPL",
    "gn:name":"Senon",
    "gn:population":0,
    "gn:timezone":"Asia/Manila",
    "iso:country":"PH",
    "name:cat_x_preferred":[
        "Senon"
    ],
    "name:ceb_x_preferred":[
        "Senon"
    ],
    "name:deu_x_preferred":[
        "Senon"
    ],
    "name:eus_x_preferred":[
        "Senon"
    ],
    "name:fil_x_preferred":[
        "Senon"
    ],
    "name:fra_x_preferred":[
        "Senon"
    ],
    "name:hun_x_preferred":[
        "Senon"
    ],
    "name:ita_x_preferred":[
        "Senon"
    ],
    "name:kaz_x_preferred":[
        "\u0421\u0435\u043d\u043e\u043d"
    ],
    "name:lat_x_preferred":[
        "Senon"
    ],
    "name:ltz_x_preferred":[
        "Senon"
    ],
    "name:msa_x_preferred":[
        "Senon"
    ],
    "name:nld_x_preferred":[
        "Senon"
    ],
    "name:oci_x_preferred":[
        "Senon"
    ],
    "name:pms_x_preferred":[
        "Senon"
    ],
    "name:pol_x_preferred":[
        "Senon"
    ],
    "name:por_x_preferred":[
        "Senon"
    ],
    "name:ron_x_preferred":[
        "Senon"
    ],
    "name:slk_x_preferred":[
        "Senon"
    ],
    "name:spa_x_preferred":[
        "Senon"
    ],
    "name:swe_x_preferred":[
        "Senon"
    ],
    "name:ukr_x_preferred":[
        "\u0421\u0435\u043d\u043e\u043d"
    ],
    "name:uzb_x_preferred":[
        "Senon"
    ],
    "name:vie_x_preferred":[
        "Senon"
    ],
    "name:vol_x_preferred":[
        "Senon"
    ],
    "name:war_x_preferred":[
        "Senon"
    ],
    "name:zho_x_preferred":[
        "\u585e\u519c"
    ],
    "wof:name":"Senon",
    "wof:placetype":"locality"
},
  "geometry": {"coordinates":[124.31139,7.83056],"type":"Point"}
}