{
  "type": "Feature",
  "properties": {
    "gn:admin1_code":"07",
    "gn:admin2_code":"21",
    "gn:admin3_code":"72214000.0",
    "gn:asciiname":"Poblacion II",
    "gn:country_code":"PH",
    "gn:dem":16,
    "gn:feature_class":"P",
    "gn:feature_code":"PPL",
    "gn:name":"Poblacion II",
    "gn:population":0,
    "gn:timezone":"Asia/Manila",
    "iso:country":"PH",
    "name:eng_x_preferred":[
        "Poblacion II"
    ],
    "wof:name":"Poblacion II",
    "wof:placetype":"locality"
},
  "geometry": {"coordinates":[123.6414,10.0946],"type":"Point"}
}