{
  "type": "Feature",
  "properties": {
    "gn:admin1_code":"15",
    "gn:admin2_code":"01",
    "gn:admin3_code":"140108000.0",
    "gn:asciiname":"Padangitan",
    "gn:country_code":"PH",
    "gn:dem":65,
    "gn:feature_class":"P",
    "gn:feature_code":"PPL",
    "gn:name":"Padangitan",
    "gn:population":0,
    "gn:timezone":"Asia/Manila",
    "iso:country":"PH",
    "name:fil_x_preferred":[
        "Padangitan"
    ],
    "wof:name":"Padangitan",
    "wof:placetype":"locality"
},
  "geometry": {"coordinates":[120.6521,17.6458],"type":"Point"}
}