{
  "type": "Feature",
  "properties": {
    "gn:admin1_code":"40",
    "gn:admin2_code":"33",
    "gn:admin3_code":"43410000.0",
    "gn:asciiname":"Ilayang Bukal",
    "gn:country_code":"PH",
    "gn:dem":410,
    "gn:feature_class":"P",
    "gn:feature_code":"PPL",
    "gn:name":"Ilayang Bukal",
    "gn:population":0,
    "gn:timezone":"Asia/Manila",
    "iso:country":"PH",
    "name:fil_x_preferred":[
        "Ilayang Bukal"
    ],
    "wof:name":"Ilayang Bukal",
    "wof:placetype":"locality"
},
  "geometry": {"coordinates":[121.4529,14.1176],"type":"Point"}
}