{
  "type": "Feature",
  "properties": {
    "gn:admin1_code":"08",
    "gn:admin2_code":"67",
    "gn:admin3_code":"84808000.0",
    "gn:asciiname":"Pinatau",
    "gn:country_code":"PH",
    "gn:dem":8,
    "gn:feature_class":"P",
    "gn:feature_code":"PPL",
    "gn:name":"Pinatau",
    "gn:population":0,
    "gn:timezone":"Asia/Manila",
    "iso:country":"PH",
    "name:fil_x_preferred":[
        "Pinatau"
    ],
    "wof:name":"Pinatau",
    "wof:placetype":"locality"
},
  "geometry": {"coordinates":[125.065,12.67694],"type":"Point"}
}