{
  "type": "Feature",
  "properties": {
    "gn:admin1_code":"01",
    "gn:admin2_code":"51",
    "gn:admin3_code":"15511000.0",
    "gn:asciiname":"Sangcagulis",
    "gn:country_code":"PH",
    "gn:dem":30,
    "gn:feature_class":"P",
    "gn:feature_code":"PPL",
    "gn:name":"Sangcagulis",
    "gn:population":0,
    "gn:timezone":"Asia/Manila",
    "iso:country":"PH",
    "name:und_x_variant":[
        "Sancagulis"
    ],
    "wof:name":"Sangcagulis",
    "wof:placetype":"locality"
},
  "geometry": {"coordinates":[120.44324,15.78903],"type":"Point"}
}