{
  "type": "Feature",
  "properties": {
    "gn:admin1_code":"40",
    "gn:admin2_code":"09",
    "gn:admin3_code":"41015000.0",
    "gn:asciiname":"Soloc",
    "gn:country_code":"PH",
    "gn:dem":15,
    "gn:feature_class":"P",
    "gn:feature_code":"PPL",
    "gn:name":"Soloc",
    "gn:population":0,
    "gn:timezone":"Asia/Manila",
    "iso:country":"PH",
    "name:eng_x_preferred":[
        "Soloc"
    ],
    "name:und_x_variant":[
        "Solec"
    ],
    "wof:name":"Soloc",
    "wof:placetype":"locality"
},
  "geometry": {"coordinates":[121.246,13.6179],"type":"Point"}
}