{
  "type": "Feature",
  "properties": {
    "gn:country":"PH",
    "gn:fcode":"PPL",
    "gn:pop":5092,
    "iso:country":"PH",
    "name:fil_x_preferred":[
        "Dayap"
    ],
    "qs:name":"Dayap",
    "qs:photos_9r":0,
    "qs:photos_sr":0,
    "qs:pop_sr":"5",
    "wof:name":"Dayap",
    "wof:placetype":"locality",
    "wof:population":5092
},
  "geometry": {"coordinates":[121.3368,14.1793],"type":"Point"}
}