{
  "type": "Feature",
  "properties": {
    "gn:admin1_code":"41",
    "gn:admin2_code":"54",
    "gn:admin3_code":"175903000.0",
    "gn:asciiname":"Cambajao",
    "gn:country_code":"PH",
    "gn:dem":97,
    "gn:feature_class":"P",
    "gn:feature_code":"PPL",
    "gn:name":"Cambajao",
    "gn:population":0,
    "gn:timezone":"Asia/Manila",
    "iso:country":"PH",
    "name:fil_x_preferred":[
        "Cambajao"
    ],
    "wof:name":"Cambajao",
    "wof:placetype":"locality"
},
  "geometry": {"coordinates":[122.65467,12.3652],"type":"Point"}
}