{
  "type": "Feature",
  "properties": {
    "gn:admin1_code":"07",
    "gn:admin2_code":"69",
    "gn:admin3_code":"76102000.0",
    "gn:asciiname":"Canlambo",
    "gn:country_code":"PH",
    "gn:dem":23,
    "gn:feature_class":"P",
    "gn:feature_code":"PPL",
    "gn:name":"Canlambo",
    "gn:population":0,
    "gn:timezone":"Asia/Manila",
    "iso:country":"PH",
    "name:fil_x_preferred":[
        "Canlambo"
    ],
    "wof:name":"Canlambo",
    "wof:placetype":"locality"
},
  "geometry": {"coordinates":[123.59999999999999,9.26667],"type":"Point"}
}