{
  "type": "Feature",
  "properties": {
    "gn:admin1_code":"40",
    "gn:admin2_code":"09",
    "gn:admin3_code":"41013000.0",
    "gn:asciiname":"Puting Kahoy",
    "gn:country_code":"PH",
    "gn:dem":80,
    "gn:feature_class":"P",
    "gn:feature_code":"PPL",
    "gn:name":"Puting Kahoy",
    "gn:population":0,
    "gn:timezone":"Asia/Manila",
    "iso:country":"PH",
    "name:fil_x_preferred":[
        "Puting Kahoy"
    ],
    "name:fil_x_variant":[
        "Puntingkahoy"
    ],
    "wof:name":"Puting Kahoy",
    "wof:placetype":"locality"
},
  "geometry": {"coordinates":[120.6528,13.9803],"type":"Point"}
}