{
  "type": "Feature",
  "properties": {
    "gn:admin1_code":"14",
    "gn:admin2_code":"60",
    "gn:admin3_code":"156608000.0",
    "gn:asciiname":"Tubig Nanok",
    "gn:country_code":"PH",
    "gn:dem":7,
    "gn:feature_class":"P",
    "gn:feature_code":"PPL",
    "gn:name":"Tubig Nanok",
    "gn:population":0,
    "gn:timezone":"Asia/Manila",
    "iso:country":"PH",
    "name:eng_x_preferred":[
        "Tubig Nanok"
    ],
    "wof:name":"Tubig Nanok",
    "wof:placetype":"locality"
},
  "geometry": {"coordinates":[120.5538,6.3602],"type":"Point"}
}