{
  "type": "Feature",
  "properties": {
    "gn:admin1_code":"07",
    "gn:admin2_code":"21",
    "gn:admin3_code":"72205000.0",
    "gn:asciiname":"Anajao",
    "gn:country_code":"PH",
    "gn:dem":306,
    "gn:feature_class":"P",
    "gn:feature_code":"PPL",
    "gn:name":"Anajao",
    "gn:population":0,
    "gn:timezone":"Asia/Manila",
    "iso:country":"PH",
    "name:und_x_variant":[
        "Anahao",
        "Anajao"
    ],
    "wof:name":"Anajao",
    "wof:placetype":"locality"
},
  "geometry": {"coordinates":[123.51783,9.97664],"type":"Point"}
}