{
  "type": "Feature",
  "properties": {
    "gn:admin1_code":"40",
    "gn:admin2_code":"33",
    "gn:admin3_code":"43405000.0",
    "gn:asciiname":"Masili",
    "gn:country_code":"PH",
    "gn:dem":6,
    "gn:feature_class":"P",
    "gn:feature_code":"PPL",
    "gn:name":"Masili",
    "gn:population":0,
    "gn:timezone":"Asia/Manila",
    "iso:country":"PH",
    "name:fil_x_preferred":[
        "Masili"
    ],
    "wof:name":"Masili",
    "wof:placetype":"locality"
},
  "geometry": {"coordinates":[121.20099999999999,14.18193],"type":"Point"}
}