{
  "type": "Feature",
  "properties": {
    "gn:admin1_code":"08",
    "gn:admin2_code":"59",
    "gn:admin3_code":"86415000.0",
    "gn:asciiname":"Esperanza",
    "gn:country_code":"PH",
    "gn:dem":15,
    "gn:feature_class":"P",
    "gn:feature_code":"PPL",
    "gn:name":"Esperanza",
    "gn:population":0,
    "gn:timezone":"Asia/Manila",
    "iso:country":"PH",
    "name:fil_x_preferred":[
        "Esperanza"
    ],
    "wof:name":"Esperanza",
    "wof:placetype":"locality"
},
  "geometry": {"coordinates":[125.2744,9.9776],"type":"Point"}
}