{
  "type": "Feature",
  "properties": {
    "gn:admin1_code":"08",
    "gn:admin2_code":"59",
    "gn:admin3_code":"86408000.0",
    "gn:asciiname":"Aguinaldo",
    "gn:country_code":"PH",
    "gn:dem":11,
    "gn:feature_class":"P",
    "gn:feature_code":"PPL",
    "gn:name":"Aguinaldo",
    "gn:population":0,
    "gn:timezone":"Asia/Manila",
    "iso:country":"PH",
    "name:fil_x_preferred":[
        "Aguinaldo"
    ],
    "wof:name":"Aguinaldo",
    "wof:placetype":"locality"
},
  "geometry": {"coordinates":[124.95972,10.05611],"type":"Point"}
}