{
  "type": "Feature",
  "properties": {
    "gn:admin1_code":"13",
    "gn:admin2_code":"I9",
    "gn:admin3_code":"168502000.0",
    "gn:asciiname":"Cabonga-an",
    "gn:country_code":"PH",
    "gn:dem":32,
    "gn:feature_class":"P",
    "gn:feature_code":"PPL",
    "gn:name":"Cabonga-an",
    "gn:population":0,
    "gn:timezone":"Asia/Manila",
    "iso:country":"PH",
    "name:fil_x_preferred":[
        "Cabonga-an"
    ],
    "wof:name":"Cabonga-an",
    "wof:placetype":"locality"
},
  "geometry": {"coordinates":[125.6575,9.92278],"type":"Point"}
}