{
  "type": "Feature",
  "properties": {
    "gn:admin1_code":"03",
    "gn:admin2_code":"47",
    "gn:admin3_code":"34910000.0",
    "gn:asciiname":"Sumandig",
    "gn:country_code":"PH",
    "gn:dem":169,
    "gn:feature_class":"P",
    "gn:feature_code":"PPL",
    "gn:name":"Sumandig",
    "gn:population":0,
    "gn:timezone":"Asia/Manila",
    "iso:country":"PH",
    "name:fil_x_preferred":[
        "Sumandig"
    ],
    "wof:name":"Sumandig",
    "wof:placetype":"locality"
},
  "geometry": {"coordinates":[121.13333,15.33333],"type":"Point"}
}