{
  "type": "Feature",
  "properties": {
    "gn:admin1_code":"01",
    "gn:admin2_code":"51",
    "gn:admin3_code":"15509000.0",
    "gn:asciiname":"Bayoyong",
    "gn:country_code":"PH",
    "gn:dem":16,
    "gn:feature_class":"P",
    "gn:feature_code":"PPL",
    "gn:name":"Bayoyong",
    "gn:population":0,
    "gn:timezone":"Asia/Manila",
    "iso:country":"PH",
    "name:fil_x_preferred":[
        "Bayoyong"
    ],
    "wof:name":"Bayoyong",
    "wof:placetype":"locality"
},
  "geometry": {"coordinates":[120.37973,15.86194],"type":"Point"}
}