{
  "type": "Feature",
  "properties": {
    "gn:admin1_code":"09",
    "gn:admin2_code":"66",
    "gn:admin3_code":"97343000.0",
    "gn:asciiname":"Anti",
    "gn:country_code":"PH",
    "gn:dem":275,
    "gn:feature_class":"P",
    "gn:feature_code":"PPL",
    "gn:name":"Anti",
    "gn:population":0,
    "gn:timezone":"Asia/Manila",
    "iso:country":"PH",
    "name:dan_x_preferred":[
        "Anti"
    ],
    "name:deu_x_preferred":[
        "Anti"
    ],
    "name:est_x_preferred":[
        "Anti"
    ],
    "name:fin_x_preferred":[
        "Anti"
    ],
    "name:ita_x_preferred":[
        "Anti"
    ],
    "name:jpn_x_preferred":[
        "\u30a2\u30f3\u30c1"
    ],
    "name:kor_x_preferred":[
        "\uc548\ud2f0"
    ],
    "name:nld_x_preferred":[
        "Anti"
    ],
    "name:por_x_preferred":[
        "Anti"
    ],
    "name:spa_x_preferred":[
        "Anti"
    ],
    "name:sqi_x_preferred":[
        "Anti"
    ],
    "name:urd_x_preferred":[
        "\u0645\u062e\u0627\u0644\u0641"
    ],
    "wof:name":"Anti",
    "wof:placetype":"locality"
},
  "geometry": {"coordinates":[123.33333,7.71667],"type":"Point"}
}