{
  "type": "Feature",
  "properties": {
    "gn:country":"PH",
    "gn:fcode":"PPL",
    "gn:pop":2356,
    "iso:country":"PH",
    "name:fil_x_preferred":[
        "San Antonio"
    ],
    "qs:name":"San Antonio",
    "qs:photos_9r":0,
    "qs:photos_sr":0,
    "qs:pop_sr":"4",
    "wof:name":"San Antonio",
    "wof:placetype":"locality",
    "wof:population":2356
},
  "geometry": {"coordinates":[125.73972000000001,7.12],"type":"Point"}
}