{
  "type": "Feature",
  "properties": {
    "gn:admin1_code":"01",
    "gn:admin2_code":"36",
    "gn:admin3_code":"13314000.0",
    "gn:asciiname":"Cabarsican",
    "gn:country_code":"PH",
    "gn:dem":169,
    "gn:feature_class":"P",
    "gn:feature_code":"PPL",
    "gn:name":"Cabarsican",
    "gn:population":0,
    "gn:timezone":"Asia/Manila",
    "iso:country":"PH",
    "name:fil_x_preferred":[
        "Cabarsican"
    ],
    "wof:name":"Cabarsican",
    "wof:placetype":"locality"
},
  "geometry": {"coordinates":[120.40000000000001,16.58333],"type":"Point"}
}