{
  "type": "Feature",
  "properties": {
    "gn:admin1_code":"01",
    "gn:admin2_code":"51",
    "gn:admin3_code":"15505000.0",
    "gn:asciiname":"Bigat",
    "gn:country_code":"PH",
    "gn:dem":31,
    "gn:feature_class":"P",
    "gn:feature_code":"PPL",
    "gn:name":"Bigat",
    "gn:population":0,
    "gn:timezone":"Asia/Manila",
    "iso:country":"PH",
    "name:fil_x_preferred":[
        "Bigat"
    ],
    "wof:name":"Bigat",
    "wof:placetype":"locality"
},
  "geometry": {"coordinates":[119.97512,16.25675],"type":"Point"}
}