{
  "type": "Feature",
  "properties": {
    "gn:admin1_code":"13",
    "gn:admin2_code":"61",
    "gn:asciiname":"Bayogo",
    "gn:country_code":"PH",
    "gn:dem":38,
    "gn:feature_class":"P",
    "gn:feature_code":"PPL",
    "gn:name":"Bayogo",
    "gn:population":0,
    "gn:timezone":"Asia/Manila",
    "iso:country":"PH",
    "name:fil_x_preferred":[
        "Bayogo"
    ],
    "wof:name":"Bayogo",
    "wof:placetype":"locality"
},
  "geometry": {"coordinates":[125.48333,9.51667],"type":"Point"}
}