{
  "type": "Feature",
  "properties": {
    "gn:admin1_code":"15",
    "gn:admin2_code":"H6",
    "gn:admin3_code":"148107000.0",
    "gn:asciiname":"Sipa Proper",
    "gn:country_code":"PH",
    "gn:dem":20,
    "gn:feature_class":"P",
    "gn:feature_code":"PPL",
    "gn:name":"Sipa Proper",
    "gn:population":0,
    "gn:timezone":"Asia/Manila",
    "iso:country":"PH",
    "name:fil_x_preferred":[
        "Sipa"
    ],
    "wof:name":"Sipa Proper",
    "wof:placetype":"locality"
},
  "geometry": {"coordinates":[121.42292999999999,18.26144],"type":"Point"}
}