{
  "type": "Feature",
  "properties": {
    "gn:admin1_code":"40",
    "gn:admin2_code":"33",
    "gn:admin3_code":"43411000.0",
    "gn:asciiname":"Timugan",
    "gn:country_code":"PH",
    "gn:dem":44,
    "gn:feature_class":"P",
    "gn:feature_code":"PPL",
    "gn:name":"Timugan",
    "gn:population":0,
    "gn:timezone":"Asia/Manila",
    "iso:country":"PH",
    "wof:name":"Timugan",
    "wof:placetype":"locality"
},
  "geometry": {"coordinates":[121.22287,14.17276],"type":"Point"}
}