{
  "type": "Feature",
  "properties": {
    "gn:admin1_code":"07",
    "gn:admin2_code":"21",
    "gn:admin3_code":"72205000.0",
    "gn:asciiname":"Panadtaran",
    "gn:cc2":"PH",
    "gn:country_code":"PH",
    "gn:dem":104,
    "gn:feature_class":"P",
    "gn:feature_code":"PPL",
    "gn:name":"Panadtaran",
    "gn:population":0,
    "gn:timezone":"Asia/Manila",
    "iso:country":"PH",
    "name:und_x_variant":[
        "Pandtaran",
        "Panadtaran"
    ],
    "wof:name":"Panadtaran",
    "wof:placetype":"locality"
},
  "geometry": {"coordinates":[123.56028000000001,9.90194],"type":"Point"}
}