{
  "type": "Feature",
  "properties": {
    "gn:admin1_code":"02",
    "gn:admin2_code":"31",
    "gn:admin3_code":"23125000.0",
    "gn:asciiname":"Pequeno",
    "gn:country_code":"PH",
    "gn:dem":48,
    "gn:feature_class":"P",
    "gn:feature_code":"PPL",
    "gn:name":"Peque\u00f1o",
    "gn:population":0,
    "gn:timezone":"Asia/Manila",
    "iso:country":"PH",
    "name:fil_x_preferred":[
        "Peque\u00f1o"
    ],
    "wof:name":"Pequeno",
    "wof:placetype":"locality"
},
  "geometry": {"coordinates":[121.79028,16.97917],"type":"Point"}
}