{
  "type": "Feature",
  "properties": {
    "gn:admin1_code":"07",
    "gn:admin2_code":"69",
    "gn:admin3_code":"76103000.0",
    "gn:asciiname":"Campalanas",
    "gn:country_code":"PH",
    "gn:dem":189,
    "gn:feature_class":"P",
    "gn:feature_code":"PPL",
    "gn:name":"Campalanas",
    "gn:population":0,
    "gn:timezone":"Asia/Manila",
    "iso:country":"PH",
    "name:fil_x_preferred":[
        "Campalanas"
    ],
    "name:und_x_variant":[
        "Kampalanas"
    ],
    "wof:name":"Campalanas",
    "wof:placetype":"locality"
},
  "geometry": {"coordinates":[123.57859999999999,9.1207],"type":"Point"}
}