{
  "type": "Feature",
  "properties": {
    "iso:country":"PH",
    "name:bcl_x_preferred":[
        "Santa Cruz"
    ],
    "name:cat_x_preferred":[
        "Santa Cruz"
    ],
    "name:cbk_zam_x_preferred":[
        "Santa Cruz"
    ],
    "name:ceb_x_preferred":[
        "Santa Cruz"
    ],
    "name:deu_x_preferred":[
        "Santa Cruz"
    ],
    "name:eng_x_preferred":[
        "Santa Cruz"
    ],
    "name:fil_x_preferred":[
        "Santa Cruz"
    ],
    "name:fra_x_preferred":[
        "Santa Cruz"
    ],
    "name:ilo_x_preferred":[
        "Santa Cruz"
    ],
    "name:ind_x_preferred":[
        "Santa Cruz"
    ],
    "name:ita_x_preferred":[
        "Santa Cruz"
    ],
    "name:jpn_x_preferred":[
        "\u30b5\u30f3\u30bf\u30af\u30eb\u30b9"
    ],
    "name:nld_x_preferred":[
        "Santa Cruz"
    ],
    "name:oci_x_preferred":[
        "Santa Cruz"
    ],
    "name:pag_x_preferred":[
        "Santa Cruz"
    ],
    "name:pam_x_preferred":[
        "Santa Cruz"
    ],
    "name:pol_x_preferred":[
        "Santa Cruz"
    ],
    "name:swe_x_preferred":[
        "Santa Cruz"
    ],
    "name:tgl_x_preferred":[
        "Santa Cruz"
    ],
    "name:tha_x_preferred":[
        "\u0e0b\u0e31\u0e19\u0e15\u0e32\u0e04\u0e23\u0e38\u0e0b"
    ],
    "name:urd_x_preferred":[
        "\u0633\u0627\u0646\u062a\u0627 \u06a9\u0631\u0648\u0632"
    ],
    "name:urd_x_variant":[
        "\u0633\u0627\u0646\u062a\u0627 \u06a9\u0631\u0648\u0632\u060c \u0644\u0627\u06af\u0648\u0646\u0627"
    ],
    "name:vie_x_preferred":[
        "S\u00f4ng Santa Cruz"
    ],
    "name:vie_x_variant":[
        "Santa Cruz"
    ],
    "name:war_x_preferred":[
        "Santa Cruz"
    ],
    "name:zho_cn_x_preferred":[
        "\u5723\u514b\u9c81\u65af"
    ],
    "name:zho_tw_x_preferred":[
        "\u8056\u514b\u9b6f\u65af"
    ],
    "qs:gn_country":"PH",
    "qs:gn_fcode":"PPL",
    "qs:gn_pop":108145,
    "qs:name":"Santa Cruz",
    "qs:name_adm0":"Philippines",
    "qs:name_adm1":"Calabarzon",
    "qs:photos":704,
    "qs:photos_1k":143,
    "qs:photos_9k":3,
    "qs:photos_9r":5,
    "qs:photos_all":704,
    "qs:photos_sr":8,
    "qs:placetype":"Town",
    "qs:pop_sr":"9",
    "qs:woe_adm0":23424934,
    "wd:wordcount":1744,
    "wof:name":"Santa Cruz",
    "wof:placetype":"locality",
    "wof:population":108145
},
  "geometry": {"coordinates":[121.4161,14.2814],"type":"Point"}
}