{
  "type": "Feature",
  "properties": {
    "gn:admin1_code":"12",
    "gn:admin2_code":"70",
    "gn:admin3_code":"126311000.0",
    "gn:asciiname":"Ambuldan",
    "gn:country_code":"PH",
    "gn:dem":83,
    "gn:feature_class":"P",
    "gn:feature_code":"PPL",
    "gn:name":"Ambuldan",
    "gn:population":0,
    "gn:timezone":"Asia/Manila",
    "iso:country":"PH",
    "name:und_x_variant":[
        "Ambuludan"
    ],
    "wof:name":"Ambuldan",
    "wof:placetype":"locality"
},
  "geometry": {"coordinates":[124.65306,6.56806],"type":"Point"}
}