{
  "type": "Feature",
  "properties": {
    "gn:admin1_code":"06",
    "gn:admin2_code":"04",
    "gn:admin3_code":"60409000.0",
    "gn:asciiname":"Can-awan",
    "gn:country_code":"PH",
    "gn:dem":96,
    "gn:feature_class":"P",
    "gn:feature_code":"PPL",
    "gn:name":"Can-awan",
    "gn:population":0,
    "gn:timezone":"Asia/Manila",
    "iso:country":"PH",
    "name:fil_x_preferred":[
        "Can-awan"
    ],
    "wof:name":"Can-awan",
    "wof:placetype":"locality"
},
  "geometry": {"coordinates":[122.27631,11.4382],"type":"Point"}
}