{
  "type": "Feature",
  "properties": {
    "gn:admin1_code":"15",
    "gn:admin2_code":"27",
    "gn:admin3_code":"142710000.0",
    "gn:asciiname":"Ta-aw",
    "gn:country_code":"PH",
    "gn:dem":1684,
    "gn:feature_class":"P",
    "gn:feature_code":"PPL",
    "gn:name":"Ta-aw",
    "gn:population":0,
    "gn:timezone":"Asia/Manila",
    "iso:country":"PH",
    "name:fil_x_preferred":[
        "Ta-aw"
    ],
    "wof:name":"Ta-aw",
    "wof:placetype":"locality"
},
  "geometry": {"coordinates":[120.93164,16.64438],"type":"Point"}
}