{
  "type": "Feature",
  "properties": {
    "gn:admin1_code":"15",
    "gn:admin2_code":"H6",
    "gn:admin3_code":"148101000.0",
    "gn:asciiname":"Engango",
    "gn:country_code":"PH",
    "gn:dem":315,
    "gn:feature_class":"P",
    "gn:feature_code":"PPL",
    "gn:name":"Engango",
    "gn:population":0,
    "gn:timezone":"Asia/Manila",
    "iso:country":"PH",
    "name:fil_x_preferred":[
        "Engango"
    ],
    "name:und_x_variant":[
        "Enganga"
    ],
    "wof:name":"Engango",
    "wof:placetype":"locality"
},
  "geometry": {"coordinates":[121.0783,18.1966],"type":"Point"}
}