{
  "type": "Feature",
  "properties": {
    "gn:admin1_code":"13",
    "gn:admin2_code":"62",
    "gn:admin3_code":"166816000.0",
    "gn:asciiname":"Catihan",
    "gn:country_code":"PH",
    "gn:dem":63,
    "gn:feature_class":"P",
    "gn:feature_code":"PPL",
    "gn:name":"Catihan",
    "gn:population":0,
    "gn:timezone":"Asia/Manila",
    "iso:country":"PH",
    "name:fil_x_preferred":[
        "Catihan"
    ],
    "wof:name":"Catihan",
    "wof:placetype":"locality"
},
  "geometry": {"coordinates":[125.90260000000001,9.0438],"type":"Point"}
}