{
  "type": "Feature",
  "properties": {
    "gn:gn_country":"PH",
    "gn:gn_fcode":"PPLA3",
    "gn:gn_pop":5591,
    "gn:population":5591,
    "iso:country":"PH",
    "name:bcl_x_preferred":[
        "Ballesteros"
    ],
    "name:cat_x_preferred":[
        "Ballesteros"
    ],
    "name:dut_x_preferred":[
        "Ballesteros"
    ],
    "name:eng_x_preferred":[
        "Ballesteros"
    ],
    "name:fil_x_preferred":[
        "Ballesteros"
    ],
    "name:fre_x_preferred":[
        "Ballesteros"
    ],
    "name:ger_x_preferred":[
        "Ballesteros"
    ],
    "name:ilo_x_preferred":[
        "Ballesteros"
    ],
    "name:ind_x_preferred":[
        "Ballesteros"
    ],
    "name:ita_x_preferred":[
        "Ballesteros"
    ],
    "name:oci_x_preferred":[
        "Ballesteros"
    ],
    "name:pag_x_preferred":[
        "Ballesteros"
    ],
    "name:pam_x_preferred":[
        "Ballesteros"
    ],
    "name:per_x_preferred":[
        "\u0628\u0627\u0644\u0633\u062a\u0631\u0648\u0633\u060c \u06a9\u0627\u06af\u0627\u06cc\u0627\u0646"
    ],
    "name:spa_x_preferred":[
        "Ballesteros de Cagay\u00e1n"
    ],
    "name:swe_x_preferred":[
        "Ballesteros"
    ],
    "name:tgl_x_preferred":[
        "Ballesteros"
    ],
    "name:vie_x_preferred":[
        "Ballesteros"
    ],
    "name:war_x_preferred":[
        "Ballesteros"
    ],
    "qs_pg:aaroncc":"PH",
    "qs_pg:gn_country":"PH",
    "qs_pg:gn_fcode":"PPLA3",
    "qs_pg:gn_pop":5591,
    "qs_pg:name":"Ballesteros",
    "qs_pg:photos_9r":0,
    "qs_pg:photos_sr":0,
    "qs_pg:pop_sr":5,
    "qs_pg:qs_pg_placetype":"locality",
    "wof:name":"Ballesteros",
    "wof:placetype":"locality",
    "wof:population":5591
},
  "geometry": {"coordinates":[121.51519999999999,18.4126],"type":"Point"}
}