{
  "type": "Feature",
  "properties": {
    "gn:country":"PH",
    "gn:fcode":"PPL",
    "gn:pop":52248,
    "iso:country":"PH",
    "name:bcl_x_preferred":[
        "Malungon"
    ],
    "name:ceb_x_preferred":[
        "Malungon"
    ],
    "name:deu_x_preferred":[
        "Malungon"
    ],
    "name:eng_x_preferred":[
        "Malungon"
    ],
    "name:fil_x_preferred":[
        "Malu\u00f1gun"
    ],
    "name:fra_x_preferred":[
        "Malungon"
    ],
    "name:ilo_x_preferred":[
        "Malungon"
    ],
    "name:ind_x_preferred":[
        "Malungon"
    ],
    "name:ita_x_preferred":[
        "Malungon"
    ],
    "name:nld_x_preferred":[
        "Malungon"
    ],
    "name:pag_x_preferred":[
        "Malungon"
    ],
    "name:pam_x_preferred":[
        "Malungon"
    ],
    "name:spa_x_preferred":[
        "Malung\u00f3n"
    ],
    "name:swe_x_preferred":[
        "Malungon"
    ],
    "name:tgl_x_preferred":[
        "Malungon"
    ],
    "name:unk_x_variant":[
        "Malungon"
    ],
    "name:vie_x_preferred":[
        "Malungon"
    ],
    "name:war_x_preferred":[
        "Malungon"
    ],
    "qs:name":"Malu\u00f1gun",
    "qs:photos_9r":0,
    "qs:photos_sr":0,
    "qs:pop_sr":"8",
    "wof:name":"Malu\u00f1gun",
    "wof:placetype":"locality",
    "wof:population":52248
},
  "geometry": {"coordinates":[125.28167000000001,6.27917],"type":"Point"}
}