{
  "type": "Feature",
  "properties": {
    "gn:admin1_code":"12",
    "gn:admin2_code":"M9",
    "gn:admin3_code":"128002000.0",
    "gn:asciiname":"Dongon",
    "gn:country_code":"PH",
    "gn:dem":11,
    "gn:feature_class":"P",
    "gn:feature_code":"PPL",
    "gn:name":"Dongon",
    "gn:population":0,
    "gn:timezone":"Asia/Manila",
    "iso:country":"PH",
    "name:fil_x_preferred":[
        "Dongon"
    ],
    "wof:name":"Dongon",
    "wof:placetype":"locality"
},
  "geometry": {"coordinates":[125.2925,5.68083],"type":"Point"}
}