{
  "type": "Feature",
  "properties": {
    "gn:admin1_code":"03",
    "gn:admin2_code":"07",
    "gn:admin3_code":"30809000.0",
    "gn:asciiname":"Dona",
    "gn:country_code":"PH",
    "gn:dem":65,
    "gn:feature_class":"P",
    "gn:feature_code":"PPL",
    "gn:name":"Dona",
    "gn:population":0,
    "gn:timezone":"Asia/Manila",
    "iso:country":"PH",
    "name:cat_x_preferred":[
        "Dona"
    ],
    "name:ceb_x_preferred":[
        "Dona"
    ],
    "name:deu_x_preferred":[
        "Dona"
    ],
    "name:fra_x_preferred":[
        "Dona"
    ],
    "name:ita_x_preferred":[
        "Dona"
    ],
    "name:pol_x_preferred":[
        "Dona"
    ],
    "name:spa_x_preferred":[
        "Dona"
    ],
    "name:swe_x_preferred":[
        "Dona"
    ],
    "name:ukr_x_preferred":[
        "\u0414\u043e\u043d\u0430"
    ],
    "wof:name":"Dona",
    "wof:placetype":"locality"
},
  "geometry": {"coordinates":[120.48708999999999,14.79731],"type":"Point"}
}