{
  "type": "Feature",
  "properties": {
    "gn:admin1_code":"01",
    "gn:admin2_code":"51",
    "gn:admin3_code":"15546000.0",
    "gn:asciiname":"Bolaoen",
    "gn:country_code":"PH",
    "gn:dem":30,
    "gn:feature_class":"P",
    "gn:feature_code":"PPL",
    "gn:name":"Bolaoen",
    "gn:population":0,
    "gn:timezone":"Asia/Manila",
    "iso:country":"PH",
    "name:fil_x_preferred":[
        "Bulaoen"
    ],
    "wof:name":"Bolaoen",
    "wof:placetype":"locality"
},
  "geometry": {"coordinates":[120.60405,15.9947],"type":"Point"}
}