{
  "type": "Feature",
  "properties": {
    "gn:admin1_code":"06",
    "gn:admin2_code":"H3",
    "gn:admin3_code":"64514000.0",
    "gn:asciiname":"Alusiman",
    "gn:country_code":"PH",
    "gn:dem":19,
    "gn:feature_class":"P",
    "gn:feature_code":"PPL",
    "gn:name":"Alusiman",
    "gn:population":0,
    "gn:timezone":"Asia/Manila",
    "iso:country":"PH",
    "name:fil_x_preferred":[
        "Alusiman"
    ],
    "wof:name":"Alusiman",
    "wof:placetype":"locality"
},
  "geometry": {"coordinates":[122.9813,10.2244],"type":"Point"}
}