{
  "type": "Feature",
  "properties": {
    "gn:admin1_code":"02",
    "gn:admin2_code":"14",
    "gn:admin3_code":"21516000.0",
    "gn:asciiname":"Cullit",
    "gn:country_code":"PH",
    "gn:dem":11,
    "gn:feature_class":"P",
    "gn:feature_code":"PPL",
    "gn:name":"Cullit",
    "gn:population":0,
    "gn:timezone":"Asia/Manila",
    "iso:country":"PH",
    "name:fil_x_preferred":[
        "Cullit"
    ],
    "name:fil_x_variant":[
        "Cullit Norte"
    ],
    "wof:name":"Cullit",
    "wof:placetype":"locality"
},
  "geometry": {"coordinates":[121.75239000000001,18.24448],"type":"Point"}
}