{
  "type": "Feature",
  "properties": {
    "gn:admin1_code":"40",
    "gn:admin2_code":"H2",
    "gn:admin3_code":"45603000.0",
    "gn:asciiname":"Batong Dalig",
    "gn:country_code":"PH",
    "gn:dem":43,
    "gn:feature_class":"P",
    "gn:feature_code":"PPL",
    "gn:name":"Batong Dalig",
    "gn:population":0,
    "gn:timezone":"Asia/Manila",
    "iso:country":"PH",
    "name:fil_x_preferred":[
        "Batong Dalig"
    ],
    "name:und_x_variant":[
        "Baton Dalig"
    ],
    "wof:name":"Batong Dalig",
    "wof:placetype":"locality"
},
  "geometry": {"coordinates":[122.02979999999999,13.9024],"type":"Point"}
}