{
  "type": "Feature",
  "properties": {
    "gn:admin1_code":"40",
    "gn:admin2_code":"53",
    "gn:admin3_code":"45802000.0",
    "gn:asciiname":"Inarawan",
    "gn:country_code":"PH",
    "gn:dem":182,
    "gn:feature_class":"P",
    "gn:feature_code":"PPL",
    "gn:name":"Inarawan",
    "gn:population":0,
    "gn:timezone":"Asia/Manila",
    "iso:country":"PH",
    "name:fil_x_preferred":[
        "Inarawan"
    ],
    "wof:name":"Inarawan",
    "wof:placetype":"locality"
},
  "geometry": {"coordinates":[121.1835,14.6247],"type":"Point"}
}