{
  "type": "Feature",
  "properties": {
    "gn:admin1_code":"12",
    "gn:admin2_code":"57",
    "gn:admin3_code":"124701000.0",
    "gn:asciiname":"Kapad",
    "gn:country_code":"PH",
    "gn:dem":1089,
    "gn:feature_class":"P",
    "gn:feature_code":"PPL",
    "gn:name":"Kapad",
    "gn:population":0,
    "gn:timezone":"Asia/Manila",
    "iso:country":"PH",
    "name:fil_x_preferred":[
        "Kapad"
    ],
    "wof:name":"Kapad",
    "wof:placetype":"locality"
},
  "geometry": {"coordinates":[124.52200000000001,7.55995],"type":"Point"}
}