{
  "type": "Feature",
  "properties": {
    "gn:admin1_code":"05",
    "gn:admin2_code":"39",
    "gn:admin3_code":"54118000.0",
    "gn:asciiname":"Binancuan",
    "gn:country_code":"PH",
    "gn:dem":105,
    "gn:feature_class":"P",
    "gn:feature_code":"PPL",
    "gn:name":"Binancuan",
    "gn:population":0,
    "gn:timezone":"Asia/Manila",
    "iso:country":"PH",
    "name:fil_x_preferred":[
        "Binancuan"
    ],
    "wof:name":"Binancuan",
    "wof:placetype":"locality"
},
  "geometry": {"coordinates":[123.74420000000001,12.4759],"type":"Point"}
}