{
  "type": "Feature",
  "properties": {
    "gn:admin1_code":"41",
    "gn:admin2_code":"41",
    "gn:admin3_code":"175204000.0",
    "gn:asciiname":"Caway-an",
    "gn:country_code":"PH",
    "gn:dem":10,
    "gn:feature_class":"P",
    "gn:feature_code":"PPL",
    "gn:name":"Caway-an",
    "gn:population":0,
    "gn:timezone":"Asia/Manila",
    "iso:country":"PH",
    "name:fil_x_preferred":[
        "Caway-an"
    ],
    "name:und_x_variant":[
        "Gaway-an"
    ],
    "wof:name":"Caway-an",
    "wof:placetype":"locality"
},
  "geometry": {"coordinates":[121.33960999999999,12.31835],"type":"Point"}
}