{
  "type": "Feature",
  "properties": {
    "gn:admin1_code":"07",
    "gn:admin2_code":"46",
    "gn:admin3_code":"74607000.0",
    "gn:asciiname":"Talaptap",
    "gn:country_code":"PH",
    "gn:dem":7,
    "gn:feature_class":"P",
    "gn:feature_code":"PPL",
    "gn:name":"Talaptap",
    "gn:population":0,
    "gn:timezone":"Asia/Manila",
    "iso:country":"PH",
    "name:fil_x_preferred":[
        "Talaptap"
    ],
    "wof:name":"Talaptap",
    "wof:placetype":"locality"
},
  "geometry": {"coordinates":[123.14861000000001,9.75028],"type":"Point"}
}