{
  "type": "Feature",
  "properties": {
    "gn:country":"PH",
    "gn:fcode":"PPLA3",
    "gn:pop":10058,
    "iso:country":"PH",
    "name:bcl_x_preferred":[
        "Mambajao"
    ],
    "name:deu_x_preferred":[
        "Mambajao"
    ],
    "name:eng_x_preferred":[
        "Mambajao"
    ],
    "name:fil_x_preferred":[
        "Mambajao"
    ],
    "name:fra_x_preferred":[
        "Mambajao"
    ],
    "name:ilo_x_preferred":[
        "Mambajao"
    ],
    "name:ind_x_preferred":[
        "Mambajao"
    ],
    "name:ita_x_preferred":[
        "Mambajao"
    ],
    "name:jpn_x_preferred":[
        "\u30de\u30f3\u30d0\u30e4\u30aa"
    ],
    "name:nld_x_preferred":[
        "Mambajao"
    ],
    "name:nob_x_preferred":[
        "Mambajao"
    ],
    "name:pag_x_preferred":[
        "Mambajao"
    ],
    "name:pam_x_preferred":[
        "Mambajao"
    ],
    "name:spa_x_preferred":[
        "Mambajao"
    ],
    "name:swe_x_preferred":[
        "Mambajao"
    ],
    "name:tgl_x_preferred":[
        "Mambajao"
    ],
    "name:unk_x_variant":[
        "Mamajao"
    ],
    "name:urd_x_preferred":[
        "\u0645\u0627\u0645\u0628\u0627\u06c1\u0627\u0624"
    ],
    "name:war_x_preferred":[
        "Mambajao"
    ],
    "name:zho_x_preferred":[
        "\u66fc\u5df4\u8c6a"
    ],
    "qs:name":"Mambajao",
    "qs:photos_9r":0,
    "qs:photos_sr":0,
    "qs:pop_sr":"6",
    "wd:wordcount":208,
    "wof:name":"Mambajao",
    "wof:placetype":"locality",
    "wof:population":10058
},
  "geometry": {"coordinates":[124.71559999999999,9.2504],"type":"Point"}
}