{
  "type": "Feature",
  "properties": {
    "gn:admin1_code":"02",
    "gn:admin2_code":"14",
    "gn:admin3_code":"21506000.0",
    "gn:asciiname":"Alba",
    "gn:country_code":"PH",
    "gn:dem":37,
    "gn:feature_class":"P",
    "gn:feature_code":"PPL",
    "gn:name":"Alba",
    "gn:population":0,
    "gn:timezone":"Asia/Manila",
    "iso:country":"PH",
    "name:dan_x_preferred":[
        "Alba"
    ],
    "name:fil_x_preferred":[
        "Alba"
    ],
    "name:ita_x_preferred":[
        "Alba"
    ],
    "name:mkd_x_preferred":[
        "\u0410\u043b\u0431\u0430"
    ],
    "name:nor_x_preferred":[
        "Alba"
    ],
    "name:spa_x_preferred":[
        "Alba"
    ],
    "name:zho_x_preferred":[
        "\u963f\u5c14\u5df4"
    ],
    "wof:name":"Alba",
    "wof:placetype":"locality"
},
  "geometry": {"coordinates":[121.89125,17.97019],"type":"Point"}
}