{
  "type": "Feature",
  "properties": {
    "gn:admin1_code":"03",
    "gn:admin2_code":"47",
    "gn:admin3_code":"34905000.0",
    "gn:asciiname":"Awayan",
    "gn:country_code":"PH",
    "gn:dem":488,
    "gn:feature_class":"P",
    "gn:feature_code":"PPL",
    "gn:name":"Awayan",
    "gn:population":0,
    "gn:timezone":"Asia/Manila",
    "iso:country":"PH",
    "name:fil_x_preferred":[
        "Awayan"
    ],
    "wof:name":"Awayan",
    "wof:placetype":"locality"
},
  "geometry": {"coordinates":[121.04404,16.09171],"type":"Point"}
}