{
  "type": "Feature",
  "properties": {
    "gn:admin1_code":"07",
    "gn:admin2_code":"46",
    "gn:admin3_code":"74611000.0",
    "gn:asciiname":"Laguda",
    "gn:country_code":"PH",
    "gn:dem":93,
    "gn:feature_class":"P",
    "gn:feature_code":"PPL",
    "gn:name":"Laguda",
    "gn:population":0,
    "gn:timezone":"Asia/Manila",
    "iso:country":"PH",
    "name:fil_x_preferred":[
        "Laguda"
    ],
    "wof:name":"Laguda",
    "wof:placetype":"locality"
},
  "geometry": {"coordinates":[123.2993,10.2828],"type":"Point"}
}