{
  "type": "Feature",
  "properties": {
    "gn:country":"PH",
    "gn:fcode":"PPL",
    "gn:pop":2915,
    "iso:country":"PH",
    "name:fil_x_preferred":[
        "Osme\u00f1a"
    ],
    "qs:name":"Osme\u00f1a",
    "qs:photos_9r":0,
    "qs:photos_sr":0,
    "qs:pop_sr":"4",
    "wd:wordcount":73,
    "wof:name":"Osme\u00f1a",
    "wof:placetype":"locality",
    "wof:population":2915
},
  "geometry": {"coordinates":[123.3318,12.7315],"type":"Point"}
}