{
  "type": "Feature",
  "properties": {
    "gn:country":"PH",
    "gn:fcode":"PPL",
    "gn:population":2496,
    "iso:country":"PH",
    "name:fil_x_preferred":[
        "Susana"
    ],
    "name:fil_x_variant":[
        "Sagana"
    ],
    "name:nor_x_preferred":[
        "Sagana"
    ],
    "name:pol_x_preferred":[
        "Sagana"
    ],
    "name:swa_x_preferred":[
        "Sagana"
    ],
    "qs:name":"Sagana",
    "qs:photos_9r":0,
    "qs:photos_sr":0,
    "qs:pop_sr":"4",
    "wd:wordcount":294,
    "wof:name":"Sagana",
    "wof:placetype":"locality",
    "wof:population":2496
},
  "geometry": {"coordinates":[121.15219999999999,15.5689],"type":"Point"}
}