{
  "type": "Feature",
  "properties": {
    "gn:admin1_code":"06",
    "gn:admin2_code":"18",
    "gn:admin3_code":"61908000.0",
    "gn:asciiname":"Sinondojan",
    "gn:country_code":"PH",
    "gn:dem":19,
    "gn:feature_class":"P",
    "gn:feature_code":"PPL",
    "gn:name":"Sinondojan",
    "gn:population":0,
    "gn:timezone":"Asia/Manila",
    "iso:country":"PH",
    "name:fil_x_preferred":[
        "Sinondojan"
    ],
    "wof:name":"Sinondojan",
    "wof:placetype":"locality"
},
  "geometry": {"coordinates":[122.60429000000001,11.44364],"type":"Point"}
}