{
  "type": "Feature",
  "properties": {
    "gn:admin1_code":"15",
    "gn:admin2_code":"01",
    "gn:admin3_code":"140105000.0",
    "gn:asciiname":"Caberuyan",
    "gn:country_code":"PH",
    "gn:dem":413,
    "gn:feature_class":"P",
    "gn:feature_code":"PPL",
    "gn:name":"Caberuyan",
    "gn:population":0,
    "gn:timezone":"Asia/Manila",
    "iso:country":"PH",
    "name:fil_x_preferred":[
        "Caberuyan"
    ],
    "name:fil_x_variant":[
        "Cabaroyan",
        "Cabaruyan"
    ],
    "wof:name":"Caberuyan",
    "wof:placetype":"locality"
},
  "geometry": {"coordinates":[120.90225,17.45003],"type":"Point"}
}