{
  "type": "Feature",
  "properties": {
    "gn:admin1_code":"06",
    "gn:admin2_code":"30",
    "gn:admin3_code":"63028000.0",
    "gn:asciiname":"Pandan",
    "gn:country_code":"PH",
    "gn:dem":72,
    "gn:feature_class":"P",
    "gn:feature_code":"PPL",
    "gn:name":"Pandan",
    "gn:population":0,
    "gn:timezone":"Asia/Manila",
    "iso:country":"PH",
    "name:ceb_x_preferred":[
        "Pandan"
    ],
    "name:deu_x_preferred":[
        "Pandan"
    ],
    "name:fil_x_preferred":[
        "Pandan"
    ],
    "name:fra_x_preferred":[
        "Pandan"
    ],
    "name:ind_x_preferred":[
        "Pandan"
    ],
    "name:ita_x_preferred":[
        "Pandan"
    ],
    "name:msa_x_preferred":[
        "Pandan"
    ],
    "name:nld_x_preferred":[
        "Pandan"
    ],
    "name:swe_x_preferred":[
        "Pandan"
    ],
    "name:tgl_x_preferred":[
        "Pandan"
    ],
    "name:war_x_preferred":[
        "Pandan"
    ],
    "wof:name":"Pandan",
    "wof:placetype":"locality"
},
  "geometry": {"coordinates":[122.40639,10.7625],"type":"Point"}
}