{
  "type": "Feature",
  "properties": {
    "gn:admin1_code":"10",
    "gn:admin2_code":"42",
    "gn:admin3_code":"104205000.0",
    "gn:asciiname":"Lupagan",
    "gn:country_code":"PH",
    "gn:dem":10,
    "gn:feature_class":"P",
    "gn:feature_code":"PPL",
    "gn:name":"Lupagan",
    "gn:population":0,
    "gn:timezone":"Asia/Manila",
    "iso:country":"PH",
    "name:eng_x_preferred":[
        "Lupagan"
    ],
    "wof:name":"Lupagan",
    "wof:placetype":"locality"
},
  "geometry": {"coordinates":[123.85120000000001,8.2227],"type":"Point"}
}