{
  "type": "Feature",
  "properties": {
    "gn:admin1_code":"03",
    "gn:admin2_code":"47",
    "gn:admin3_code":"34913000.0",
    "gn:asciiname":"Betania",
    "gn:country_code":"PH",
    "gn:dem":65,
    "gn:feature_class":"P",
    "gn:feature_code":"PPL",
    "gn:name":"Betania",
    "gn:population":0,
    "gn:timezone":"Asia/Manila",
    "iso:country":"PH",
    "name:bre_x_preferred":[
        "Betania"
    ],
    "name:ceb_x_preferred":[
        "Betania"
    ],
    "name:deu_x_preferred":[
        "Betania"
    ],
    "name:fil_x_preferred":[
        "Betania"
    ],
    "name:fil_x_variant":[
        "Beta\u00f1a"
    ],
    "name:ita_x_preferred":[
        "Betania"
    ],
    "name:nld_x_preferred":[
        "Betania"
    ],
    "name:nor_x_preferred":[
        "Betania"
    ],
    "name:ron_x_preferred":[
        "Betania"
    ],
    "name:sco_x_preferred":[
        "Betania"
    ],
    "name:spa_x_preferred":[
        "Betania"
    ],
    "name:swe_x_preferred":[
        "Betania"
    ],
    "name:tgl_x_preferred":[
        "Betania"
    ],
    "name:war_x_preferred":[
        "Betania"
    ],
    "wof:name":"Betania",
    "wof:placetype":"locality"
},
  "geometry": {"coordinates":[121.16630000000001,15.6021],"type":"Point"}
}