{
  "type": "Feature",
  "properties": {
    "gn:admin1_code":"05",
    "gn:admin2_code":"58",
    "gn:admin3_code":"56204000.0",
    "gn:asciiname":"Tinampo",
    "gn:country_code":"PH",
    "gn:dem":54,
    "gn:feature_class":"P",
    "gn:feature_code":"PPL",
    "gn:name":"Tinampo",
    "gn:population":0,
    "gn:timezone":"Asia/Manila",
    "iso:country":"PH",
    "name:fil_x_preferred":[
        "Tinampo"
    ],
    "wof:name":"Tinampo",
    "wof:placetype":"locality"
},
  "geometry": {"coordinates":[124.1331,12.7239],"type":"Point"}
}