{
  "type": "Feature",
  "properties": {
    "gn:admin1_code":"07",
    "gn:admin2_code":"11",
    "gn:admin3_code":"71243000.0",
    "gn:asciiname":"Cadahon",
    "gn:country_code":"PH",
    "gn:dem":18,
    "gn:feature_class":"P",
    "gn:feature_code":"PPL",
    "gn:name":"Cadahon",
    "gn:population":0,
    "gn:timezone":"Asia/Manila",
    "iso:country":"PH",
    "name:fil_x_preferred":[
        "Cadahon"
    ],
    "wof:name":"Cadahon",
    "wof:placetype":"locality"
},
  "geometry": {"coordinates":[124.24889,10.15667],"type":"Point"}
}