{
  "type": "Feature",
  "properties": {
    "gn:admin1_code":"14",
    "gn:admin2_code":"35",
    "gn:admin3_code":"153627000.0",
    "gn:asciiname":"Sambulawan",
    "gn:country_code":"PH",
    "gn:dem":711,
    "gn:feature_class":"P",
    "gn:feature_code":"PPL",
    "gn:name":"Sambulawan",
    "gn:population":0,
    "gn:timezone":"Asia/Manila",
    "iso:country":"PH",
    "name:und_x_variant":[
        "Sambolawan"
    ],
    "wof:name":"Sambulawan",
    "wof:placetype":"locality"
},
  "geometry": {"coordinates":[124.34056,7.90278],"type":"Point"}
}