{
  "type": "Feature",
  "properties": {
    "gn:admin1_code":"07",
    "gn:admin2_code":"21",
    "gn:admin3_code":"72246000.0",
    "gn:asciiname":"Tuble",
    "gn:country_code":"PH",
    "gn:dem":135,
    "gn:feature_class":"P",
    "gn:feature_code":"PPL",
    "gn:name":"Tuble",
    "gn:population":0,
    "gn:timezone":"Asia/Manila",
    "iso:country":"PH",
    "name:fil_x_preferred":[
        "Tuble"
    ],
    "wof:name":"Tuble",
    "wof:placetype":"locality"
},
  "geometry": {"coordinates":[123.58167,10.01139],"type":"Point"}
}