{
  "type": "Feature",
  "properties": {
    "gn:admin1_code":"14",
    "gn:admin2_code":"60",
    "gn:admin3_code":"156603000.0",
    "gn:asciiname":"Limbuaya",
    "gn:country_code":"PH",
    "gn:dem":213,
    "gn:feature_class":"P",
    "gn:feature_code":"PPL",
    "gn:name":"Limbuaya",
    "gn:population":0,
    "gn:timezone":"Asia/Manila",
    "iso:country":"PH",
    "name:fil_x_preferred":[
        "Limbuaya"
    ],
    "wof:name":"Limbuaya",
    "wof:placetype":"locality"
},
  "geometry": {"coordinates":[121.29000000000001,5.90667],"type":"Point"}
}