{
  "type": "Feature",
  "properties": {
    "gn:admin1_code":"40",
    "gn:admin2_code":"09",
    "gn:admin3_code":"41019000.0",
    "gn:asciiname":"Bonducan",
    "gn:country_code":"PH",
    "gn:dem":11,
    "gn:feature_class":"P",
    "gn:feature_code":"PPL",
    "gn:name":"Bonducan",
    "gn:population":0,
    "gn:timezone":"Asia/Manila",
    "iso:country":"PH",
    "name:fil_x_preferred":[
        "Bonducan"
    ],
    "name:fil_x_variant":[
        "Bunducan"
    ],
    "wof:name":"Bonducan",
    "wof:placetype":"locality"
},
  "geometry": {"coordinates":[120.6288,14.0982],"type":"Point"}
}