{
  "type": "Feature",
  "properties": {
    "gn:admin1_code":"05",
    "gn:admin2_code":"39",
    "gn:admin3_code":"54114000.0",
    "gn:asciiname":"Bitong",
    "gn:country_code":"PH",
    "gn:dem":117,
    "gn:feature_class":"P",
    "gn:feature_code":"PPL",
    "gn:name":"Bitong",
    "gn:population":0,
    "gn:timezone":"Asia/Manila",
    "iso:country":"PH",
    "name:fil_x_preferred":[
        "Bitong"
    ],
    "wof:name":"Bitong",
    "wof:placetype":"locality"
},
  "geometry": {"coordinates":[123.6127,12.6578],"type":"Point"}
}