{
  "type": "Feature",
  "properties": {
    "gn:admin1_code":"40",
    "gn:admin2_code":"H2",
    "gn:admin3_code":"45620000.0",
    "gn:asciiname":"Boboin",
    "gn:country_code":"PH",
    "gn:dem":6,
    "gn:feature_class":"P",
    "gn:feature_code":"PPL",
    "gn:name":"Boboin",
    "gn:population":0,
    "gn:timezone":"Asia/Manila",
    "iso:country":"PH",
    "name:fil_x_preferred":[
        "Boboin"
    ],
    "name:fil_x_variant":[
        "Bobin"
    ],
    "wof:name":"Boboin",
    "wof:placetype":"locality"
},
  "geometry": {"coordinates":[121.65318000000001,14.76512],"type":"Point"}
}