{
  "type": "Feature",
  "properties": {
    "gn:admin1_code":"06",
    "gn:admin2_code":"H3",
    "gn:admin3_code":"64504000.0",
    "gn:asciiname":"Hacienda Biac",
    "gn:country_code":"PH",
    "gn:dem":41,
    "gn:feature_class":"P",
    "gn:feature_code":"PPL",
    "gn:name":"Hacienda Biac",
    "gn:population":0,
    "gn:timezone":"Asia/Manila",
    "iso:country":"PH",
    "name:fil_x_preferred":[
        "Hacienda Biac"
    ],
    "wof:name":"Hacienda Biac",
    "wof:placetype":"locality"
},
  "geometry": {"coordinates":[123.20650000000001,10.9208],"type":"Point"}
}