{
  "type": "Feature",
  "properties": {
    "gn:gn_country":"PH",
    "gn:gn_fcode":"PPL",
    "gn:gn_pop":5746,
    "gn:population":5746,
    "iso:country":"PH",
    "name:fil_x_preferred":[
        "Glad"
    ],
    "name:fra_x_preferred":[
        "Glad"
    ],
    "name:ita_x_preferred":[
        "Glad"
    ],
    "name:rus_x_preferred":[
        "\u0413\u043b\u044d\u0434"
    ],
    "qs_pg:aaroncc":"PH",
    "qs_pg:gn_country":"PH",
    "qs_pg:gn_fcode":"PPL",
    "qs_pg:gn_pop":5746,
    "qs_pg:name":"Glad",
    "qs_pg:photos_9r":0,
    "qs_pg:photos_sr":0,
    "qs_pg:pop_sr":5,
    "qs_pg:qs_pg_placetype":"locality",
    "wof:name":"Glad",
    "wof:placetype":"locality",
    "wof:population":5746
},
  "geometry": {"coordinates":[124.51806000000001,7.14833],"type":"Point"}
}