{
  "type": "Feature",
  "properties": {
    "gn:admin1_code":"03",
    "gn:admin2_code":"63",
    "gn:admin3_code":"36912000.0",
    "gn:asciiname":"Poblacion North",
    "gn:country_code":"PH",
    "gn:dem":24,
    "gn:feature_class":"P",
    "gn:feature_code":"PPL",
    "gn:name":"Poblacion North",
    "gn:population":0,
    "gn:timezone":"Asia/Manila",
    "iso:country":"PH",
    "wof:name":"Poblacion North",
    "wof:placetype":"locality"
},
  "geometry": {"coordinates":[120.63951000000002,15.67076],"type":"Point"}
}