{
  "type": "Feature",
  "properties": {
    "gn:admin1_code":"11",
    "gn:admin2_code":"P3",
    "gn:admin3_code":"118605000.0",
    "gn:asciiname":"Haway",
    "gn:country_code":"PH",
    "gn:dem":116,
    "gn:feature_class":"P",
    "gn:feature_code":"PPL",
    "gn:name":"Haway",
    "gn:population":0,
    "gn:timezone":"Asia/Manila",
    "iso:country":"PH",
    "name:fil_x_preferred":[
        "Haway"
    ],
    "wof:name":"Haway",
    "wof:placetype":"locality"
},
  "geometry": {"coordinates":[125.41943999999999,5.3725],"type":"Point"}
}