{
  "type": "Feature",
  "properties": {
    "gn:admin1_code":"10",
    "gn:admin2_code":"43",
    "gn:admin3_code":"104314000.0",
    "gn:asciiname":"Tagbabanga",
    "gn:country_code":"PH",
    "gn:dem":41,
    "gn:feature_class":"P",
    "gn:feature_code":"PPL",
    "gn:name":"Tagbabanga",
    "gn:population":0,
    "gn:timezone":"Asia/Manila",
    "iso:country":"PH",
    "name:fil_x_preferred":[
        "Tagbabanga"
    ],
    "wof:name":"Tagbabanga",
    "wof:placetype":"locality"
},
  "geometry": {"coordinates":[124.45,8.61667],"type":"Point"}
}