{
  "type": "Feature",
  "properties": {
    "gn:admin1_code":"08",
    "gn:admin2_code":"37",
    "gn:admin3_code":"83706000.0",
    "gn:asciiname":"Ballesteros",
    "gn:country_code":"PH",
    "gn:dem":8,
    "gn:feature_class":"P",
    "gn:feature_code":"PPL",
    "gn:name":"Ballesteros",
    "gn:population":0,
    "gn:timezone":"Asia/Manila",
    "iso:country":"PH",
    "name:cat_x_preferred":[
        "Ballesteros"
    ],
    "name:ceb_x_preferred":[
        "Ballesteros"
    ],
    "name:deu_x_preferred":[
        "Ballesteros"
    ],
    "name:fil_x_preferred":[
        "Ballesteros"
    ],
    "name:fra_x_preferred":[
        "Ballesteros"
    ],
    "name:ita_x_preferred":[
        "Ballesteros"
    ],
    "name:nld_x_preferred":[
        "Ballesteros"
    ],
    "name:rus_x_preferred":[
        "\u0411\u0430\u043b\u044c\u0435\u0441\u0442\u0435\u0440\u043e\u0441"
    ],
    "name:spa_x_preferred":[
        "Ballesteros"
    ],
    "name:swe_x_preferred":[
        "Ballesteros"
    ],
    "name:war_x_preferred":[
        "Ballesteros"
    ],
    "wof:name":"Ballesteros",
    "wof:placetype":"locality"
},
  "geometry": {"coordinates":[124.75639,11.33639],"type":"Point"}
}