{
  "type": "Feature",
  "properties": {
    "gn:admin1_code":"13",
    "gn:admin2_code":"03",
    "gn:admin3_code":"160312000.0",
    "gn:asciiname":"Tudela",
    "gn:country_code":"PH",
    "gn:dem":183,
    "gn:feature_class":"P",
    "gn:feature_code":"PPL",
    "gn:name":"Tudela",
    "gn:population":0,
    "gn:timezone":"Asia/Manila",
    "iso:country":"PH",
    "name:fil_x_preferred":[
        "Tudela"
    ],
    "wof:name":"Tudela",
    "wof:placetype":"locality"
},
  "geometry": {"coordinates":[126.21666999999999,8.13333],"type":"Point"}
}