{
  "type": "Feature",
  "properties": {
    "gn:admin1_code":"10",
    "gn:admin2_code":"12",
    "gn:admin3_code":"101320000.0",
    "gn:asciiname":"Binantalon",
    "gn:country_code":"PH",
    "gn:dem":1045,
    "gn:feature_class":"P",
    "gn:feature_code":"PPL",
    "gn:name":"Binantalon",
    "gn:population":0,
    "gn:timezone":"Asia/Manila",
    "iso:country":"PH",
    "name:fil_x_preferred":[
        "Binantalon"
    ],
    "name:und_x_variant":[
        "Benantalon"
    ],
    "wof:name":"Binantalon",
    "wof:placetype":"locality"
},
  "geometry": {"coordinates":[124.71472,8.07667],"type":"Point"}
}