{
  "type": "Feature",
  "properties": {
    "gn:admin1_code":"01",
    "gn:admin2_code":"28",
    "gn:admin3_code":"12805000.0",
    "gn:asciiname":"Bungon",
    "gn:country_code":"PH",
    "gn:dem":39,
    "gn:feature_class":"P",
    "gn:feature_code":"PPLL",
    "gn:name":"Bungon",
    "gn:population":0,
    "gn:timezone":"Asia/Manila",
    "iso:country":"PH",
    "name:fil_x_preferred":[
        "Bungon"
    ],
    "wof:name":"Bungon",
    "wof:placetype":"locality"
},
  "geometry": {"coordinates":[120.57941,18.10972000000001],"type":"Point"}
}