{
  "type": "Feature",
  "properties": {
    "gn:admin1_code":"10",
    "gn:admin2_code":"42",
    "gn:admin3_code":"104213000.0",
    "gn:asciiname":"Guinabot",
    "gn:country_code":"PH",
    "gn:dem":155,
    "gn:feature_class":"P",
    "gn:feature_code":"PPL",
    "gn:name":"Guinabot",
    "gn:population":0,
    "gn:timezone":"Asia/Manila",
    "iso:country":"PH",
    "name:eng_x_preferred":[
        "Guinabot"
    ],
    "wof:name":"Guinabot",
    "wof:placetype":"locality"
},
  "geometry": {"coordinates":[123.59059999999999,8.5395],"type":"Point"}
}