{
  "type": "Feature",
  "properties": {
    "gn:admin1_code":"01",
    "gn:admin2_code":"51",
    "gn:admin3_code":"15502000.0",
    "gn:asciiname":"Mangaralos",
    "gn:country_code":"PH",
    "gn:dem":19,
    "gn:feature_class":"P",
    "gn:feature_code":"PPL",
    "gn:name":"Mangaralos",
    "gn:population":0,
    "gn:timezone":"Asia/Manila",
    "iso:country":"PH",
    "name:fil_x_preferred":[
        "Mangaralos"
    ],
    "wof:name":"Mangaralos",
    "wof:placetype":"locality"
},
  "geometry": {"coordinates":[120.23333,15.88333],"type":"Point"}
}