{
  "type": "Feature",
  "properties": {
    "gn:admin1_code":"08",
    "gn:admin2_code":"37",
    "gn:admin3_code":"83715000.0",
    "gn:asciiname":"Gabas",
    "gn:country_code":"PH",
    "gn:dem":121,
    "gn:feature_class":"P",
    "gn:feature_code":"PPL",
    "gn:name":"Gabas",
    "gn:population":0,
    "gn:timezone":"Asia/Manila",
    "iso:country":"PH",
    "name:arg_x_preferred":[
        "Gab\u00e1s"
    ],
    "name:ceb_x_preferred":[
        "Gabas"
    ],
    "name:deu_x_preferred":[
        "Gabas"
    ],
    "name:fil_x_preferred":[
        "Gabas"
    ],
    "name:fra_x_preferred":[
        "Gabas"
    ],
    "name:swe_x_preferred":[
        "Gabas"
    ],
    "wof:name":"Gabas",
    "wof:placetype":"locality"
},
  "geometry": {"coordinates":[124.71666999999999,11.23333],"type":"Point"}
}