{
  "type": "Feature",
  "properties": {
    "gn:admin1_code":"41",
    "gn:admin2_code":"49",
    "gn:admin3_code":"175307000.0",
    "gn:asciiname":"Palua",
    "gn:country_code":"PH",
    "gn:dem":11,
    "gn:feature_class":"P",
    "gn:feature_code":"PPL",
    "gn:name":"Palua",
    "gn:population":0,
    "gn:timezone":"Asia/Manila",
    "iso:country":"PH",
    "name:fil_x_preferred":[
        "Palua"
    ],
    "wof:name":"Palua",
    "wof:placetype":"locality"
},
  "geometry": {"coordinates":[119.92901000000001,12.15317],"type":"Point"}
}