{
  "type": "Feature",
  "properties": {
    "gn:admin1_code":"40",
    "gn:admin2_code":"H2",
    "gn:admin3_code":"45636000.0",
    "gn:asciiname":"Quidadanom",
    "gn:country_code":"PH",
    "gn:dem":10,
    "gn:feature_class":"P",
    "gn:feature_code":"PPL",
    "gn:name":"Quidadanom",
    "gn:population":0,
    "gn:timezone":"Asia/Manila",
    "iso:country":"PH",
    "name:fil_x_preferred":[
        "Quidadanom"
    ],
    "wof:name":"Quidadanom",
    "wof:placetype":"locality"
},
  "geometry": {"coordinates":[121.88487000000001,14.84777],"type":"Point"}
}