{
  "type": "Feature",
  "properties": {
    "gn:admin1_code":"06",
    "gn:admin2_code":"30",
    "gn:admin3_code":"63038000.0",
    "gn:asciiname":"Cubay",
    "gn:country_code":"PH",
    "gn:dem":10,
    "gn:feature_class":"P",
    "gn:feature_code":"PPL",
    "gn:name":"Cubay",
    "gn:population":0,
    "gn:timezone":"Asia/Manila",
    "iso:country":"PH",
    "name:fil_x_preferred":[
        "Cubay"
    ],
    "name:und_x_variant":[
        "Cubacy"
    ],
    "wof:name":"Cubay",
    "wof:placetype":"locality"
},
  "geometry": {"coordinates":[123.095,11.3406],"type":"Point"}
}