{
  "type": "Feature",
  "properties": {
    "gn:admin1_code":"11",
    "gn:admin2_code":"25",
    "gn:admin3_code":"112414000.0",
    "gn:asciiname":"Balabag",
    "gn:cc2":"PH",
    "gn:country_code":"PH",
    "gn:dem":23,
    "gn:feature_class":"P",
    "gn:feature_code":"PPL",
    "gn:name":"Balabag",
    "gn:population":0,
    "gn:timezone":"Asia/Manila",
    "iso:country":"PH",
    "name:und_x_variant":[
        "Balabog",
        "Balabag"
    ],
    "wof:name":"Balabag",
    "wof:placetype":"locality"
},
  "geometry": {"coordinates":[125.3175,6.60639],"type":"Point"}
}