{
  "type": "Feature",
  "properties": {
    "gn:admin1_code":"07",
    "gn:admin2_code":"21",
    "gn:admin3_code":"72206000.0",
    "gn:asciiname":"Agtugop",
    "gn:country_code":"PH",
    "gn:dem":71,
    "gn:feature_class":"P",
    "gn:feature_code":"PPL",
    "gn:name":"Agtugop",
    "gn:population":0,
    "gn:timezone":"Asia/Manila",
    "iso:country":"PH",
    "name:fil_x_preferred":[
        "Agtugop"
    ],
    "wof:name":"Agtugop",
    "wof:placetype":"locality"
},
  "geometry": {"coordinates":[123.78583,10.59917],"type":"Point"}
}