{
  "type": "Feature",
  "properties": {
    "gn:admin1_code":"03",
    "gn:admin2_code":"47",
    "gn:admin3_code":"34910000.0",
    "gn:asciiname":"Pulong Matong",
    "gn:country_code":"PH",
    "gn:dem":49,
    "gn:feature_class":"P",
    "gn:feature_code":"PPL",
    "gn:name":"Pulong Matong",
    "gn:population":0,
    "gn:timezone":"Asia/Manila",
    "iso:country":"PH",
    "name:fil_x_preferred":[
        "Pulong Matong"
    ],
    "wof:name":"Pulong Matong",
    "wof:placetype":"locality"
},
  "geometry": {"coordinates":[121.03721000000002,15.34917],"type":"Point"}
}