{
  "type": "Feature",
  "properties": {
    "gn:admin1_code":"02",
    "gn:admin2_code":"31",
    "gn:admin3_code":"23108000.0",
    "gn:asciiname":"Casalatan",
    "gn:country_code":"PH",
    "gn:dem":85,
    "gn:feature_class":"P",
    "gn:feature_code":"PPL",
    "gn:name":"Casalatan",
    "gn:population":0,
    "gn:timezone":"Asia/Manila",
    "iso:country":"PH",
    "wof:name":"Casalatan",
    "wof:placetype":"locality"
},
  "geometry": {"coordinates":[121.86275000000001,16.89121],"type":"Point"}
}