{
  "type": "Feature",
  "properties": {
    "gn:admin1_code":"40",
    "gn:admin2_code":"33",
    "gn:admin3_code":"43423000.0",
    "gn:asciiname":"Antipolo",
    "gn:country_code":"PH",
    "gn:dem":253,
    "gn:feature_class":"P",
    "gn:feature_code":"PPL",
    "gn:name":"Antipolo",
    "gn:population":0,
    "gn:timezone":"Asia/Manila",
    "iso:country":"PH",
    "name:fil_x_preferred":[
        "Antipolo"
    ],
    "wof:name":"Antipolo",
    "wof:placetype":"locality"
},
  "geometry": {"coordinates":[121.3818,14.1104],"type":"Point"}
}