{
  "type": "Feature",
  "properties": {
    "gn:admin1_code":"05",
    "gn:admin2_code":"16",
    "gn:admin3_code":"51715000.0",
    "gn:asciiname":"Matacla",
    "gn:country_code":"PH",
    "gn:dem":73,
    "gn:feature_class":"P",
    "gn:feature_code":"PPL",
    "gn:name":"Matacla",
    "gn:population":0,
    "gn:timezone":"Asia/Manila",
    "iso:country":"PH",
    "name:fil_x_preferred":[
        "Matacla"
    ],
    "wof:name":"Matacla",
    "wof:placetype":"locality"
},
  "geometry": {"coordinates":[123.49509999999999,13.6839],"type":"Point"}
}