{
  "type": "Feature",
  "properties": {
    "gn:admin1_code":"01",
    "gn:admin2_code":"36",
    "gn:admin3_code":"13316000.0",
    "gn:asciiname":"Calincamasan",
    "gn:cc2":"PH",
    "gn:country_code":"PH",
    "gn:dem":10,
    "gn:feature_class":"P",
    "gn:feature_code":"PPL",
    "gn:name":"Calincamasan",
    "gn:population":0,
    "gn:timezone":"Asia/Manila",
    "iso:country":"PH",
    "name:und_x_variant":[
        "Calingcamasan",
        "Calincamasan"
    ],
    "wof:name":"Calincamasan",
    "wof:placetype":"locality"
},
  "geometry": {"coordinates":[120.34999999999999,16.68333],"type":"Point"}
}