{
  "type": "Feature",
  "properties": {
    "gn:country":"PH",
    "gn:fcode":"ADM3",
    "gn:population":16594,
    "iso:country":"PH",
    "name:ceb_x_preferred":[
        "Alabat"
    ],
    "name:fil_x_preferred":[
        "Alabat"
    ],
    "name:nld_x_preferred":[
        "Alabat"
    ],
    "qs:name":"Alabat",
    "qs:photos_9r":0,
    "qs:photos_sr":0,
    "qs:pop_sr":"6",
    "wof:name":"Alabat",
    "wof:placetype":"localadmin",
    "wof:population":16594
},
  "geometry": {"coordinates":[122.01667,14.11667],"type":"Point"}
}