{
  "type": "Feature",
  "properties": {
    "gn:admin1_code":"05",
    "gn:admin2_code":"05",
    "gn:admin3_code":"50505000.0",
    "gn:asciiname":"Bautista",
    "gn:country_code":"PH",
    "gn:dem":49,
    "gn:feature_class":"P",
    "gn:feature_code":"PPL",
    "gn:name":"Bautista",
    "gn:population":0,
    "gn:timezone":"Asia/Manila",
    "iso:country":"PH",
    "name:fil_x_preferred":[
        "Bautista"
    ],
    "wof:name":"Bautista",
    "wof:placetype":"locality"
},
  "geometry": {"coordinates":[123.5808,13.0453],"type":"Point"}
}