{
  "type": "Feature",
  "properties": {
    "gn:admin1_code":"40",
    "gn:admin2_code":"33",
    "gn:admin3_code":"43410000.0",
    "gn:asciiname":"Cabuyao",
    "gn:country_code":"PH",
    "gn:dem":107,
    "gn:feature_class":"P",
    "gn:feature_code":"PPL",
    "gn:name":"Cabuyao",
    "gn:population":0,
    "gn:timezone":"Asia/Manila",
    "iso:country":"PH",
    "name:ara_x_preferred":[
        "\u0643\u0627\u0628\u0648\u064a\u0627\u0648"
    ],
    "name:bcl_x_preferred":[
        "Cabuyao"
    ],
    "name:ceb_x_preferred":[
        "Cabuyao"
    ],
    "name:deu_x_preferred":[
        "Cabuyao"
    ],
    "name:fil_x_preferred":[
        "Cabuyao"
    ],
    "name:fra_x_preferred":[
        "Cabuyao"
    ],
    "name:ilo_x_preferred":[
        "Cabuyao"
    ],
    "name:ind_x_preferred":[
        "Cabuyao"
    ],
    "name:ita_x_preferred":[
        "Cabuyao"
    ],
    "name:jpn_x_preferred":[
        "\u30ab\u30d6\u30e4\u30aa"
    ],
    "name:nld_x_preferred":[
        "Cabuyao"
    ],
    "name:nor_x_preferred":[
        "Cabuyao"
    ],
    "name:pag_x_preferred":[
        "Cabuyao"
    ],
    "name:pam_x_preferred":[
        "Cabuyao"
    ],
    "name:pol_x_preferred":[
        "Cabuyao"
    ],
    "name:sco_x_preferred":[
        "Cabuyao"
    ],
    "name:spa_x_preferred":[
        "Cab\u00fayao"
    ],
    "name:swe_x_preferred":[
        "Cabuyao"
    ],
    "name:tgl_x_preferred":[
        "Cabuyao"
    ],
    "name:vie_x_preferred":[
        "Cabuyao"
    ],
    "name:war_x_preferred":[
        "Cabuyao"
    ],
    "name:zho_x_preferred":[
        "\u5361\u5e03\u582f"
    ],
    "wof:name":"Cabuyao",
    "wof:placetype":"locality"
},
  "geometry": {"coordinates":[121.41667,14.16667],"type":"Point"}
}