{
  "type": "Feature",
  "properties": {
    "gn:admin1_code":"40",
    "gn:admin2_code":"09",
    "gn:admin3_code":"41005000.0",
    "gn:asciiname":"Tinga Labac",
    "gn:country_code":"PH",
    "gn:dem":85,
    "gn:feature_class":"P",
    "gn:feature_code":"PPL",
    "gn:name":"Tinga Labac",
    "gn:population":0,
    "gn:timezone":"Asia/Manila",
    "iso:country":"PH",
    "name:fil_x_preferred":[
        "Tinga Labac"
    ],
    "name:fil_x_variant":[
        "Tinga Ibaba"
    ],
    "name:und_x_variant":[
        "Tinga Labak",
        "Tinga"
    ],
    "wof:name":"Tinga Labac",
    "wof:placetype":"locality"
},
  "geometry": {"coordinates":[121.08029999999999,13.7964],"type":"Point"}
}