{
  "type": "Feature",
  "properties": {
    "gn:admin1_code":"01",
    "gn:admin2_code":"51",
    "gn:admin3_code":"15501000.0",
    "gn:asciiname":"Alipanto",
    "gn:country_code":"PH",
    "gn:dem":66,
    "gn:feature_class":"P",
    "gn:feature_code":"PPL",
    "gn:name":"Alipanto",
    "gn:population":0,
    "gn:timezone":"Asia/Manila",
    "iso:country":"PH",
    "name:fil_x_preferred":[
        "Alipanto"
    ],
    "wof:name":"Alipanto",
    "wof:placetype":"locality"
},
  "geometry": {"coordinates":[119.7749,16.0837],"type":"Point"}
}