{
  "type": "Feature",
  "properties": {
    "gn:admin1_code":"02",
    "gn:admin2_code":"14",
    "gn:admin3_code":"21529000.0",
    "gn:asciiname":"Capatan",
    "gn:country_code":"PH",
    "gn:dem":28,
    "gn:feature_class":"P",
    "gn:feature_code":"PPL",
    "gn:name":"Capatan",
    "gn:population":0,
    "gn:timezone":"Asia/Manila",
    "iso:country":"PH",
    "name:fil_x_preferred":[
        "Capatan"
    ],
    "wof:name":"Capatan",
    "wof:placetype":"locality"
},
  "geometry": {"coordinates":[121.74509999999999,17.6165],"type":"Point"}
}