{
  "type": "Feature",
  "properties": {
    "gn:admin1_code":"41",
    "gn:admin2_code":"54",
    "gn:admin3_code":"175904000.0",
    "gn:asciiname":"Pagsangahan",
    "gn:country_code":"PH",
    "gn:dem":54,
    "gn:feature_class":"P",
    "gn:feature_code":"PPL",
    "gn:name":"Pagsangahan",
    "gn:population":0,
    "gn:timezone":"Asia/Manila",
    "iso:country":"PH",
    "name:fil_x_preferred":[
        "Pagsangahan"
    ],
    "wof:name":"Pagsangahan",
    "wof:placetype":"locality"
},
  "geometry": {"coordinates":[122.074,12.6016],"type":"Point"}
}