{
  "type": "Feature",
  "properties": {
    "gn:admin1_code":"08",
    "gn:admin2_code":"37",
    "gn:admin3_code":"83707000.0",
    "gn:asciiname":"Tagaytay",
    "gn:country_code":"PH",
    "gn:dem":11,
    "gn:feature_class":"P",
    "gn:feature_code":"PPL",
    "gn:name":"Tagaytay",
    "gn:population":0,
    "gn:timezone":"Asia/Manila",
    "iso:country":"PH",
    "name:fil_x_preferred":[
        "Tagaytay"
    ],
    "wof:name":"Tagaytay",
    "wof:placetype":"locality"
},
  "geometry": {"coordinates":[124.81667,10.35],"type":"Point"}
}