{
  "type": "Feature",
  "properties": {
    "gn:admin1_code":"08",
    "gn:admin2_code":"37",
    "gn:admin3_code":"83707000.0",
    "gn:asciiname":"Tagaytay",
    "gn:country_code":"PH",
    "gn:dem":11,
    "gn:feature_class":"P",
    "gn:feature_code":"PPL",
    "gn:name":"Tagaytay",
    "gn:population":0,
    "gn:timezone":"Asia/Manila",
    "iso:country":"PH",
    "name:ara_x_preferred":[
        "\u062a\u0627\u062c\u0627\u064a\u062a\u0627\u0649"
    ],
    "name:bcl_x_preferred":[
        "Tagaytay"
    ],
    "name:ceb_x_preferred":[
        "Tagaytay"
    ],
    "name:deu_x_preferred":[
        "Tagaytay"
    ],
    "name:fil_x_preferred":[
        "Tagaytay"
    ],
    "name:fra_x_preferred":[
        "Tagaytay"
    ],
    "name:ilo_x_preferred":[
        "Tagaytay"
    ],
    "name:ind_x_preferred":[
        "Tagaytay"
    ],
    "name:ita_x_preferred":[
        "Tagaytay"
    ],
    "name:jpn_x_preferred":[
        "\u30bf\u30ac\u30a4\u30bf\u30a4"
    ],
    "name:kor_x_preferred":[
        "\ud0c0\uac00\uc774\ud0c0\uc774"
    ],
    "name:msa_x_preferred":[
        "Tagaytay"
    ],
    "name:nld_x_preferred":[
        "Tagaytay"
    ],
    "name:nor_x_preferred":[
        "Tagaytay City"
    ],
    "name:pag_x_preferred":[
        "Tagaytay"
    ],
    "name:pam_x_preferred":[
        "Tagaytay"
    ],
    "name:pol_x_preferred":[
        "Tagaytay"
    ],
    "name:swe_x_preferred":[
        "Tagaytay"
    ],
    "name:tgl_x_preferred":[
        "Tagaytay"
    ],
    "name:vie_x_preferred":[
        "Tagaytay"
    ],
    "name:war_x_preferred":[
        "Tagaytay"
    ],
    "wof:name":"Tagaytay",
    "wof:placetype":"locality"
},
  "geometry": {"coordinates":[124.81667,10.35],"type":"Point"}
}