{
  "type": "Feature",
  "properties": {
    "gn:admin1_code":"15",
    "gn:admin2_code":"01",
    "gn:admin3_code":"140113000.0",
    "gn:asciiname":"Balaoang",
    "gn:country_code":"PH",
    "gn:dem":357,
    "gn:feature_class":"P",
    "gn:feature_code":"PPL",
    "gn:name":"Balaoang",
    "gn:population":0,
    "gn:timezone":"Asia/Manila",
    "iso:country":"PH",
    "name:fil_x_preferred":[
        "Balaoang"
    ],
    "wof:name":"Balaoang",
    "wof:placetype":"locality"
},
  "geometry": {"coordinates":[120.86667,17.65],"type":"Point"}
}