{
  "type": "Feature",
  "properties": {
    "gn:admin1_code":"06",
    "gn:admin2_code":"H3",
    "gn:admin3_code":"64502000.0",
    "gn:asciiname":"Hacienda Emma",
    "gn:country_code":"PH",
    "gn:dem":46,
    "gn:feature_class":"P",
    "gn:feature_code":"PPL",
    "gn:name":"Hacienda Emma",
    "gn:population":0,
    "gn:timezone":"Asia/Manila",
    "iso:country":"PH",
    "name:fil_x_preferred":[
        "Hacienda Emma"
    ],
    "wof:name":"Hacienda Emma",
    "wof:placetype":"locality"
},
  "geometry": {"coordinates":[122.97799999999999,10.4929],"type":"Point"}
}