{
  "type": "Feature",
  "properties": {
    "gn:admin1_code":"01",
    "gn:admin2_code":"51",
    "gn:admin3_code":"15534000.0",
    "gn:asciiname":"Bisal",
    "gn:country_code":"PH",
    "gn:dem":15,
    "gn:feature_class":"P",
    "gn:feature_code":"PPL",
    "gn:name":"Bisal",
    "gn:population":0,
    "gn:timezone":"Asia/Manila",
    "iso:country":"PH",
    "name:fil_x_preferred":[
        "Bisal"
    ],
    "wof:name":"Bisal",
    "wof:placetype":"locality"
},
  "geometry": {"coordinates":[120.45408999999999,16.04438],"type":"Point"}
}