{
  "type": "Feature",
  "properties": {
    "gn:admin1_code":"02",
    "gn:admin2_code":"14",
    "gn:admin3_code":"21513000.0",
    "gn:asciiname":"Langgan",
    "gn:country_code":"PH",
    "gn:dem":19,
    "gn:feature_class":"P",
    "gn:feature_code":"PPL",
    "gn:name":"Langgan",
    "gn:population":0,
    "gn:timezone":"Asia/Manila",
    "iso:country":"PH",
    "wof:name":"Langgan",
    "wof:placetype":"locality"
},
  "geometry": {"coordinates":[121.73484999999999,18.04351],"type":"Point"}
}