{
  "type": "Feature",
  "properties": {
    "iso:country":"PH",
    "name:bcl_x_preferred":[
        "Dilasag"
    ],
    "name:cat_x_preferred":[
        "Dilasag"
    ],
    "name:cbk_zam_x_preferred":[
        "Dilasag"
    ],
    "name:ceb_x_preferred":[
        "Dilasag"
    ],
    "name:deu_x_preferred":[
        "Dilasag"
    ],
    "name:eng_x_preferred":[
        "Dilasag"
    ],
    "name:fra_x_preferred":[
        "Dilasag"
    ],
    "name:ilo_x_preferred":[
        "Dilasag"
    ],
    "name:ind_x_preferred":[
        "Dilasag"
    ],
    "name:ita_x_preferred":[
        "Dilasag"
    ],
    "name:msa_x_preferred":[
        "Dilasag"
    ],
    "name:nld_x_preferred":[
        "Dilasag"
    ],
    "name:oci_x_preferred":[
        "Dilasag"
    ],
    "name:pag_x_preferred":[
        "Dilasag"
    ],
    "name:pam_x_preferred":[
        "Dilasag"
    ],
    "name:spa_x_preferred":[
        "Dilasag"
    ],
    "name:swe_x_preferred":[
        "Dilasag"
    ],
    "name:tgl_x_preferred":[
        "Dilasag"
    ],
    "name:unk_x_variant":[
        "Dislasag"
    ],
    "name:urd_x_preferred":[
        "\u062f\u06cc\u0644\u0627\u0633\u0627\u06af"
    ],
    "name:vie_x_preferred":[
        "Dilasag"
    ],
    "name:war_x_preferred":[
        "Dilasag"
    ],
    "qs:gn_country":"PH",
    "qs:gn_fcode":"PPL",
    "qs:gn_pop":0,
    "qs:name":"Dilasag",
    "qs:name_adm0":"Philippines",
    "qs:name_adm1":"Central Luzon",
    "qs:photos":0,
    "qs:photos_1k":0,
    "qs:photos_9k":0,
    "qs:photos_9r":0,
    "qs:photos_all":0,
    "qs:photos_sr":0,
    "qs:placetype":"Town",
    "qs:pop_sr":"0",
    "qs:woe_adm0":23424934,
    "wd:wordcount":414,
    "wof:name":"Dilasag",
    "wof:placetype":"locality"
},
  "geometry": {"coordinates":[122.21306,16.3975],"type":"Point"}
}