{
  "type": "Feature",
  "properties": {
    "gn:admin1_code":"10",
    "gn:admin2_code":"34",
    "gn:admin3_code":"103502000.0",
    "gn:asciiname":"Abaga",
    "gn:country_code":"PH",
    "gn:dem":356,
    "gn:feature_class":"P",
    "gn:feature_code":"PPL",
    "gn:name":"Abaga",
    "gn:population":0,
    "gn:timezone":"Asia/Manila",
    "iso:country":"PH",
    "wof:name":"Abaga",
    "wof:placetype":"locality"
},
  "geometry": {"coordinates":[124.22,8.14056],"type":"Point"}
}