{
  "type": "Feature",
  "properties": {
    "gn:admin1_code":"15",
    "gn:admin2_code":"10",
    "gn:admin3_code":"141101000.0",
    "gn:asciiname":"Bekes",
    "gn:country_code":"PH",
    "gn:dem":1623,
    "gn:feature_class":"P",
    "gn:feature_code":"PPL",
    "gn:name":"Bekes",
    "gn:population":0,
    "gn:timezone":"Asia/Manila",
    "iso:country":"PH",
    "name:fil_x_preferred":[
        "Bekes"
    ],
    "wof:name":"Bekes",
    "wof:placetype":"locality"
},
  "geometry": {"coordinates":[120.7239,16.6229],"type":"Point"}
}