{
  "type": "Feature",
  "properties": {
    "gn:admin1_code":"09",
    "gn:admin2_code":"66",
    "gn:admin3_code":"97306000.0",
    "gn:asciiname":"Calipapa",
    "gn:country_code":"PH",
    "gn:dem":34,
    "gn:feature_class":"P",
    "gn:feature_code":"PPL",
    "gn:name":"Calipapa",
    "gn:population":0,
    "gn:timezone":"Asia/Manila",
    "iso:country":"PH",
    "name:eng_x_preferred":[
        "Calipapa"
    ],
    "name:und_x_variant":[
        "Kalipapa"
    ],
    "wof:name":"Calipapa",
    "wof:placetype":"locality"
},
  "geometry": {"coordinates":[123.38249999999999,7.6279],"type":"Point"}
}