{
  "type": "Feature",
  "properties": {
    "gn:admin1_code":"40",
    "gn:admin2_code":"H2",
    "gn:admin3_code":"45603000.0",
    "gn:asciiname":"Kallagan",
    "gn:country_code":"PH",
    "gn:dem":182,
    "gn:feature_class":"P",
    "gn:feature_code":"PPL",
    "gn:name":"Kallagan",
    "gn:population":0,
    "gn:timezone":"Asia/Manila",
    "iso:country":"PH",
    "name:fil_x_preferred":[
        "Kallagan"
    ],
    "wof:name":"Kallagan",
    "wof:placetype":"locality"
},
  "geometry": {"coordinates":[121.88630000000001,13.9289],"type":"Point"}
}