{
  "type": "Feature",
  "properties": {
    "gn:admin1_code":"06",
    "gn:admin2_code":"30",
    "gn:admin3_code":"63038000.0",
    "gn:asciiname":"Cuconion",
    "gn:country_code":"PH",
    "gn:dem":73,
    "gn:feature_class":"P",
    "gn:feature_code":"PPL",
    "gn:name":"Cuconion",
    "gn:population":0,
    "gn:timezone":"Asia/Manila",
    "iso:country":"PH",
    "name:fil_x_preferred":[
        "Cuconion"
    ],
    "wof:name":"Cuconion",
    "wof:placetype":"locality"
},
  "geometry": {"coordinates":[123.0501,11.3168],"type":"Point"}
}