{
  "type": "Feature",
  "properties": {
    "gn:admin1_code":"40",
    "gn:admin2_code":"09",
    "gn:admin3_code":"41021000.0",
    "gn:asciiname":"Bayawang",
    "gn:country_code":"PH",
    "gn:dem":107,
    "gn:feature_class":"P",
    "gn:feature_code":"PPL",
    "gn:name":"Bayawang",
    "gn:population":0,
    "gn:timezone":"Asia/Manila",
    "iso:country":"PH",
    "wof:name":"Bayawang",
    "wof:placetype":"locality"
},
  "geometry": {"coordinates":[121.28400000000001,13.7969],"type":"Point"}
}