{
  "type": "Feature",
  "properties": {
    "gn:admin1_code":"41",
    "gn:admin2_code":"38",
    "gn:admin3_code":"174001000.0",
    "gn:asciiname":"Binunga",
    "gn:country_code":"PH",
    "gn:dem":105,
    "gn:feature_class":"P",
    "gn:feature_code":"PPL",
    "gn:name":"Binunga",
    "gn:population":0,
    "gn:timezone":"Asia/Manila",
    "iso:country":"PH",
    "name:fil_x_preferred":[
        "Binunga"
    ],
    "wof:name":"Binunga",
    "wof:placetype":"locality"
},
  "geometry": {"coordinates":[121.91764000000001,13.39371],"type":"Point"}
}