{
  "type": "Feature",
  "properties": {
    "gn:admin1_code":"07",
    "gn:admin2_code":"21",
    "gn:admin3_code":"72212000.0",
    "gn:asciiname":"Granada",
    "gn:country_code":"PH",
    "gn:dem":16,
    "gn:feature_class":"P",
    "gn:feature_code":"PPL",
    "gn:name":"Granada",
    "gn:population":0,
    "gn:timezone":"Asia/Manila",
    "iso:country":"PH",
    "name:fil_x_preferred":[
        "Granada"
    ],
    "wof:name":"Granada",
    "wof:placetype":"locality"
},
  "geometry": {"coordinates":[123.4727,9.6053],"type":"Point"}
}