{
  "type": "Feature",
  "properties": {
    "gn:admin1_code":"06",
    "gn:admin2_code":"30",
    "gn:admin3_code":"63025000.0",
    "gn:asciiname":"Pajo",
    "gn:country_code":"PH",
    "gn:dem":89,
    "gn:feature_class":"P",
    "gn:feature_code":"PPL",
    "gn:name":"Pajo",
    "gn:population":0,
    "gn:timezone":"Asia/Manila",
    "iso:country":"PH",
    "name:fil_x_preferred":[
        "Pajo"
    ],
    "name:und_x_variant":[
        "Pah"
    ],
    "wof:name":"Pajo",
    "wof:placetype":"locality"
},
  "geometry": {"coordinates":[122.4691,11.07133],"type":"Point"}
}