{
  "type": "Feature",
  "properties": {
    "gn:admin1_code":"06",
    "gn:admin2_code":"30",
    "gn:admin3_code":"63044000.0",
    "gn:asciiname":"Aglahog",
    "gn:country_code":"PH",
    "gn:dem":31,
    "gn:feature_class":"P",
    "gn:feature_code":"PPL",
    "gn:name":"Aglahog",
    "gn:population":0,
    "gn:timezone":"Asia/Manila",
    "iso:country":"PH",
    "name:fil_x_preferred":[
        "Aglahog"
    ],
    "name:und_x_variant":[
        "Alahog",
        "Aglahag"
    ],
    "wof:name":"Aglahog",
    "wof:placetype":"locality"
},
  "geometry": {"coordinates":[123.0543,11.229],"type":"Point"}
}