{
  "type": "Feature",
  "properties": {
    "gn:admin1_code":"14",
    "gn:admin2_code":"60",
    "gn:admin3_code":"156610000.0",
    "gn:asciiname":"Paandiung",
    "gn:country_code":"PH",
    "gn:dem":0,
    "gn:feature_class":"P",
    "gn:feature_code":"PPL",
    "gn:name":"Paandiung",
    "gn:population":0,
    "gn:timezone":"Asia/Manila",
    "iso:country":"PH",
    "name:fil_x_preferred":[
        "Paandiung"
    ],
    "wof:name":"Paandiung",
    "wof:placetype":"locality"
},
  "geometry": {"coordinates":[121.09146,5.84434],"type":"Point"}
}