{
  "type": "Feature",
  "properties": {
    "gn:admin1_code":"06",
    "gn:admin2_code":"H3",
    "gn:admin3_code":"64524000.0",
    "gn:asciiname":"Hacienda D Medina",
    "gn:country_code":"PH",
    "gn:dem":23,
    "gn:feature_class":"P",
    "gn:feature_code":"PPL",
    "gn:name":"Hacienda D Medina",
    "gn:population":0,
    "gn:timezone":"Asia/Manila",
    "iso:country":"PH",
    "name:fil_x_preferred":[
        "Hacienda D Medina"
    ],
    "wof:name":"Hacienda D Medina",
    "wof:placetype":"locality"
},
  "geometry": {"coordinates":[123.4104,10.50166],"type":"Point"}
}