{
  "type": "Feature",
  "properties": {
    "gn:admin1_code":"02",
    "gn:admin2_code":"14",
    "gn:admin3_code":"21506000.0",
    "gn:asciiname":"Badap",
    "gn:cc2":"PH",
    "gn:country_code":"PH",
    "gn:dem":34,
    "gn:feature_class":"P",
    "gn:feature_code":"PPL",
    "gn:name":"Badap",
    "gn:population":0,
    "gn:timezone":"Asia/Manila",
    "iso:country":"PH",
    "name:und_x_variant":[
        "Dadap",
        "Badap"
    ],
    "wof:name":"Badap",
    "wof:placetype":"locality"
},
  "geometry": {"coordinates":[121.91278,17.88332999999999],"type":"Point"}
}