{
  "type": "Feature",
  "properties": {
    "gn:admin1_code":"10",
    "gn:admin2_code":"43",
    "gn:admin3_code":"104306000.0",
    "gn:asciiname":"Solana",
    "gn:country_code":"PH",
    "gn:dem":531,
    "gn:feature_class":"P",
    "gn:feature_code":"PPL",
    "gn:name":"Solana",
    "gn:population":0,
    "gn:timezone":"Asia/Manila",
    "iso:country":"PH",
    "name:arg_x_preferred":[
        "Solana"
    ],
    "name:cat_x_preferred":[
        "Solana"
    ],
    "name:ceb_x_preferred":[
        "Solana"
    ],
    "name:deu_x_preferred":[
        "Solana"
    ],
    "name:fil_x_preferred":[
        "Solana"
    ],
    "name:fra_x_preferred":[
        "Solana"
    ],
    "name:ita_x_preferred":[
        "Solana"
    ],
    "name:nld_x_preferred":[
        "Solana"
    ],
    "name:por_x_preferred":[
        "Solana"
    ],
    "name:rus_x_preferred":[
        "\u0421\u043e\u043b\u0430\u043d\u0430"
    ],
    "name:slv_x_preferred":[
        "Solana"
    ],
    "name:spa_x_preferred":[
        "Solana"
    ],
    "name:ukr_x_preferred":[
        "\u0421\u043e\u043b\u0430\u043d\u0430"
    ],
    "name:war_x_preferred":[
        "Solana"
    ],
    "wof:name":"Solana",
    "wof:placetype":"locality"
},
  "geometry": {"coordinates":[124.83333,8.66667],"type":"Point"}
}