{
  "type": "Feature",
  "properties": {
    "gn:admin1_code":"07",
    "gn:admin2_code":"11",
    "gn:admin3_code":"71246000.0",
    "gn:asciiname":"Fatima",
    "gn:country_code":"PH",
    "gn:dem":8,
    "gn:feature_class":"P",
    "gn:feature_code":"PPL",
    "gn:name":"Fatima",
    "gn:population":0,
    "gn:timezone":"Asia/Manila",
    "iso:country":"PH",
    "name:fil_x_preferred":[
        "Fatima"
    ],
    "wof:name":"Fatima",
    "wof:placetype":"locality"
},
  "geometry": {"coordinates":[124.48333,10.05067],"type":"Point"}
}