{
  "type": "Feature",
  "properties": {
    "gn:admin1_code":"NCR",
    "gn:admin2_code":"137600000",
    "gn:admin3_code":"137607000.0",
    "gn:asciiname":"Western Bicutan",
    "gn:country_code":"PH",
    "gn:dem":29,
    "gn:feature_class":"P",
    "gn:feature_code":"PPL",
    "gn:name":"Western Bicutan",
    "gn:population":0,
    "gn:timezone":"Asia/Manila",
    "iso:country":"PH",
    "name:tgl_x_preferred":[
        "Kanlurang Bicutan"
    ],
    "wof:name":"Western Bicutan",
    "wof:placetype":"locality"
},
  "geometry": {"coordinates":[121.04000000000001,14.5097],"type":"Point"}
}