{
  "type": "Feature",
  "properties": {
    "gn:admin1_code":"05",
    "gn:admin2_code":"39",
    "gn:admin3_code":"54107000.0",
    "gn:asciiname":"Ilaya",
    "gn:country_code":"PH",
    "gn:dem":60,
    "gn:feature_class":"P",
    "gn:feature_code":"PPL",
    "gn:name":"Ilaya",
    "gn:population":0,
    "gn:timezone":"Asia/Manila",
    "iso:country":"PH",
    "name:eng_x_preferred":[
        "Ilaya"
    ],
    "wof:name":"Ilaya",
    "wof:placetype":"locality"
},
  "geometry": {"coordinates":[123.2445,12.8756],"type":"Point"}
}