{
  "type": "Feature",
  "properties": {
    "gn:country":"PH",
    "gn:fcode":"ADM3",
    "gn:pop":80919,
    "iso:country":"PH",
    "name:unk_x_variant":[
        "Tarikulan"
    ],
    "qs:name":"Manolo Fortich",
    "qs:photos_9r":0,
    "qs:photos_sr":0,
    "qs:pop_sr":"8",
    "wof:name":"Manolo Fortich",
    "wof:placetype":"localadmin",
    "wof:population":80919
},
  "geometry": {"coordinates":[124.86667,8.38333],"type":"Point"}
}