{
  "type": "Feature",
  "properties": {
    "gn:country":"PH",
    "gn:fcode":"PPL",
    "gn:pop":2885,
    "iso:country":"PH",
    "name:fil_x_preferred":[
        "Bailan"
    ],
    "qs:name":"Bailan",
    "qs:photos_9r":0,
    "qs:photos_sr":0,
    "qs:pop_sr":"4",
    "wof:name":"Bailan",
    "wof:placetype":"locality",
    "wof:population":2885
},
  "geometry": {"coordinates":[122.8301,11.4584],"type":"Point"}
}