{
  "type": "Feature",
  "properties": {
    "gn:admin1_code":"02",
    "gn:admin2_code":"68",
    "gn:admin3_code":"25704000.0",
    "gn:asciiname":"Sto Nino",
    "gn:country_code":"PH",
    "gn:dem":167,
    "gn:feature_class":"P",
    "gn:feature_code":"PPL",
    "gn:name":"Sto Ni\u00f1o",
    "gn:population":0,
    "gn:timezone":"Asia/Manila",
    "iso:country":"PH",
    "name:fil_x_preferred":[
        "Sto Ni\u00f1o"
    ],
    "wof:name":"Sto Nino",
    "wof:placetype":"locality"
},
  "geometry": {"coordinates":[121.6739,16.2994],"type":"Point"}
}