{
  "type": "Feature",
  "properties": {
    "gn:admin1_code":"07",
    "gn:admin2_code":"21",
    "gn:admin3_code":"72237000.0",
    "gn:asciiname":"Cueva",
    "gn:country_code":"PH",
    "gn:dem":71,
    "gn:elevation":"0.0",
    "gn:feature_class":"P",
    "gn:feature_code":"PPL",
    "gn:name":"Cueva",
    "gn:population":0,
    "gn:timezone":"Asia/Manila",
    "iso:country":"PH",
    "name:fil_x_preferred":[
        "Cueva"
    ],
    "wof:name":"Cueva",
    "wof:placetype":"locality"
},
  "geometry": {"coordinates":[123.6579,10.25828],"type":"Point"}
}