{
  "type": "Feature",
  "properties": {
    "gn:admin1_code":"08",
    "gn:admin2_code":"59",
    "gn:admin3_code":"86402000.0",
    "gn:asciiname":"Union",
    "gn:country_code":"PH",
    "gn:dem":6,
    "gn:feature_class":"P",
    "gn:feature_code":"PPL",
    "gn:name":"Union",
    "gn:population":0,
    "gn:timezone":"Asia/Manila",
    "iso:country":"PH",
    "name:fil_x_preferred":[
        "Union"
    ],
    "wof:name":"Union",
    "wof:placetype":"locality"
},
  "geometry": {"coordinates":[124.9712,10.3338],"type":"Point"}
}