{
  "type": "Feature",
  "properties": {
    "gn:admin1_code":"08",
    "gn:admin2_code":"23",
    "gn:admin3_code":"82609000.0",
    "gn:asciiname":"Timak",
    "gn:country_code":"PH",
    "gn:dem":34,
    "gn:feature_class":"P",
    "gn:feature_code":"PPL",
    "gn:name":"Timak",
    "gn:population":0,
    "gn:timezone":"Asia/Manila",
    "iso:country":"PH",
    "name:fil_x_preferred":[
        "Timak"
    ],
    "wof:name":"Timak",
    "wof:placetype":"locality"
},
  "geometry": {"coordinates":[125.73111000000002,11.06361],"type":"Point"}
}