{
  "type": "Feature",
  "properties": {
    "gn:admin1_code":"05",
    "gn:admin2_code":"58",
    "gn:admin3_code":"56215000.0",
    "gn:asciiname":"Calayogan",
    "gn:country_code":"PH",
    "gn:dem":17,
    "gn:feature_class":"P",
    "gn:feature_code":"PPL",
    "gn:name":"Calayogan",
    "gn:population":0,
    "gn:timezone":"Asia/Manila",
    "iso:country":"PH",
    "name:fil_x_preferred":[
        "Calayogan"
    ],
    "wof:name":"Calayogan",
    "wof:placetype":"locality"
},
  "geometry": {"coordinates":[124.08499999999999,12.6445],"type":"Point"}
}