{
  "type": "Feature",
  "properties": {
    "gn:admin1_code":"01",
    "gn:admin2_code":"36",
    "gn:admin3_code":"13306000.0",
    "gn:asciiname":"Paratong Norte",
    "gn:country_code":"PH",
    "gn:dem":9,
    "gn:feature_class":"P",
    "gn:feature_code":"PPL",
    "gn:name":"Paratong Norte",
    "gn:population":0,
    "gn:timezone":"Asia/Manila",
    "iso:country":"PH",
    "name:fil_x_preferred":[
        "Paratong Norte"
    ],
    "name:fil_x_variant":[
        "Paratong",
        "Paratang"
    ],
    "wof:name":"Paratong Norte",
    "wof:placetype":"locality"
},
  "geometry": {"coordinates":[120.4063,16.8956],"type":"Point"}
}