{
  "type": "Feature",
  "properties": {
    "gn:admin1_code":"03",
    "gn:admin2_code":"50",
    "gn:admin3_code":"35410000.0",
    "gn:asciiname":"Santo Rosario",
    "gn:country_code":"PH",
    "gn:dem":9,
    "gn:feature_class":"P",
    "gn:feature_code":"PPL",
    "gn:name":"Santo Rosario",
    "gn:population":0,
    "gn:timezone":"Asia/Manila",
    "iso:country":"PH",
    "name:fil_x_preferred":[
        "San Rosario"
    ],
    "name:fil_x_variant":[
        "Santo Rosario"
    ],
    "wof:name":"Santo Rosario",
    "wof:placetype":"locality"
},
  "geometry": {"coordinates":[120.71082,14.91042],"type":"Point"}
}