{
  "type": "Feature",
  "properties": {
    "gn:admin1_code":"40",
    "gn:admin2_code":"33",
    "gn:admin3_code":"43410000.0",
    "gn:asciiname":"Cabuyen",
    "gn:country_code":"PH",
    "gn:dem":192,
    "gn:feature_class":"P",
    "gn:feature_code":"PPL",
    "gn:name":"Cabuyen",
    "gn:population":0,
    "gn:timezone":"Asia/Manila",
    "iso:country":"PH",
    "name:fil_x_preferred":[
        "Cabuyen"
    ],
    "name:fil_x_variant":[
        "Cabuyew",
        "Cabuyeo"
    ],
    "wof:name":"Cabuyen",
    "wof:placetype":"locality"
},
  "geometry": {"coordinates":[121.42910000000001,14.146],"type":"Point"}
}