{
  "type": "Feature",
  "properties": {
    "iso:country":"PH",
    "name:bcl_x_preferred":[
        "Bulalacao"
    ],
    "name:cat_x_preferred":[
        "Bulalacao"
    ],
    "name:dut_x_preferred":[
        "Bulalacao"
    ],
    "name:eng_x_preferred":[
        "Bulalacao"
    ],
    "name:fil_x_preferred":[
        "Bulalacao"
    ],
    "name:fre_x_preferred":[
        "Bulalacao"
    ],
    "name:ger_x_preferred":[
        "Bulalacao"
    ],
    "name:ilo_x_preferred":[
        "Bulalacao"
    ],
    "name:ind_x_preferred":[
        "Bulalacao"
    ],
    "name:ita_x_preferred":[
        "Bulalacao"
    ],
    "name:oci_x_preferred":[
        "Bulalacao"
    ],
    "name:pag_x_preferred":[
        "San Pedro"
    ],
    "name:pam_x_preferred":[
        "Bulalacao"
    ],
    "name:spa_x_preferred":[
        "San Pedro de Bulalacao"
    ],
    "name:swe_x_preferred":[
        "Bulalacao"
    ],
    "name:tgl_x_preferred":[
        "Bulalacao"
    ],
    "name:unk_x_variant":[
        "Bulalakao"
    ],
    "name:vie_x_preferred":[
        "Bulalacao"
    ],
    "name:war_x_preferred":[
        "Bulalacao"
    ],
    "qs:gn_country":"PH",
    "qs:gn_fcode":"PPL",
    "qs:gn_pop":12027,
    "qs:name":"Bulalacao",
    "qs:name_adm0":"Philippines",
    "qs:name_adm1":"Mimaropa",
    "qs:photos":133,
    "qs:photos_1k":27,
    "qs:photos_9k":1,
    "qs:photos_9r":3,
    "qs:photos_all":133,
    "qs:photos_sr":3,
    "qs:placetype":"Town",
    "qs:pop_sr":"6",
    "qs:woe_adm0":23424934,
    "wof:name":"Bulalacao",
    "wof:placetype":"locality",
    "wof:population":12027
},
  "geometry": {"coordinates":[121.34350999999999,12.32535],"type":"Point"}
}