{
  "type": "Feature",
  "properties": {
    "gn:admin1_code":"02",
    "gn:admin2_code":"14",
    "gn:admin3_code":"21509000.0",
    "gn:asciiname":"Dadao",
    "gn:country_code":"PH",
    "gn:dem":14,
    "gn:feature_class":"P",
    "gn:feature_code":"PPL",
    "gn:name":"Dadao",
    "gn:population":0,
    "gn:timezone":"Asia/Manila",
    "iso:country":"PH",
    "name:fil_x_preferred":[
        "Dadao"
    ],
    "wof:name":"Dadao",
    "wof:placetype":"locality"
},
  "geometry": {"coordinates":[121.49460000000001,19.25605],"type":"Point"}
}