{
  "type": "Feature",
  "properties": {
    "gn:admin1_code":"03",
    "gn:admin2_code":"13",
    "gn:admin3_code":"31419000.0",
    "gn:asciiname":"Bubulong Malaki",
    "gn:country_code":"PH",
    "gn:dem":38,
    "gn:feature_class":"P",
    "gn:feature_code":"PPL",
    "gn:name":"Bubulong Malaki",
    "gn:population":0,
    "gn:timezone":"Asia/Manila",
    "iso:country":"PH",
    "name:fil_x_preferred":[
        "Bubulong Malaki"
    ],
    "wof:name":"Bubulong Malaki",
    "wof:placetype":"locality"
},
  "geometry": {"coordinates":[121.01220000000001,15.0848],"type":"Point"}
}