{
  "type": "Feature",
  "properties": {
    "gn:admin1_code":"03",
    "gn:admin2_code":"13",
    "gn:admin3_code":"31407000.0",
    "gn:asciiname":"San Marcos",
    "gn:country_code":"PH",
    "gn:dem":9,
    "gn:feature_class":"P",
    "gn:feature_code":"PPL",
    "gn:name":"San Marcos",
    "gn:population":0,
    "gn:timezone":"Asia/Manila",
    "iso:country":"PH",
    "name:bre_x_preferred":[
        "San Marcos"
    ],
    "name:bul_x_preferred":[
        "\u0421\u0430\u043d \u041c\u0430\u0440\u043a\u043e\u0441"
    ],
    "name:cat_x_preferred":[
        "San Marcos"
    ],
    "name:ceb_x_preferred":[
        "San Marcos"
    ],
    "name:deu_x_preferred":[
        "San Marcos"
    ],
    "name:est_x_preferred":[
        "San Marcos"
    ],
    "name:fil_x_preferred":[
        "San Marcos"
    ],
    "name:fin_x_preferred":[
        "San Marcos"
    ],
    "name:fra_x_preferred":[
        "San Marcos"
    ],
    "name:glg_x_preferred":[
        "San Marcos"
    ],
    "name:ita_x_preferred":[
        "San Marcos"
    ],
    "name:kor_x_preferred":[
        "\uc0b0\ub9c8\ub974\ucf54\uc2a4"
    ],
    "name:lit_x_preferred":[
        "San Markosas"
    ],
    "name:nds_x_preferred":[
        "San Marcos"
    ],
    "name:nld_x_preferred":[
        "San Marcos"
    ],
    "name:pol_x_preferred":[
        "San Marcos"
    ],
    "name:por_x_preferred":[
        "San Marcos"
    ],
    "name:rus_x_preferred":[
        "\u0421\u0430\u043d-\u041c\u0430\u0440\u043a\u043e\u0441"
    ],
    "name:sco_x_preferred":[
        "San Marcos"
    ],
    "name:spa_x_preferred":[
        "San Marcos"
    ],
    "name:srp_x_preferred":[
        "\u0421\u0430\u043d \u041c\u0430\u0440\u043a\u043e\u0441"
    ],
    "name:swa_x_preferred":[
        "San Marcos"
    ],
    "name:swe_x_preferred":[
        "San Marcos"
    ],
    "name:ukr_x_preferred":[
        "\u0421\u0430\u043d-\u041c\u0430\u0440\u043a\u043e\u0441"
    ],
    "name:vol_x_preferred":[
        "San Marcos"
    ],
    "name:war_x_preferred":[
        "San Marcos"
    ],
    "wof:name":"San Marcos",
    "wof:placetype":"locality"
},
  "geometry": {"coordinates":[120.78400999999999,14.8978],"type":"Point"}
}