{
  "type": "Feature",
  "properties": {
    "gn:admin1_code":"07",
    "gn:admin2_code":"21",
    "gn:admin3_code":"72234000.0",
    "gn:asciiname":"Tagjaguimit",
    "gn:country_code":"PH",
    "gn:dem":123,
    "gn:feature_class":"P",
    "gn:feature_code":"PPL",
    "gn:name":"Tagjaguimit",
    "gn:population":0,
    "gn:timezone":"Asia/Manila",
    "iso:country":"PH",
    "name:fil_x_preferred":[
        "Tagjaguimit"
    ],
    "wof:name":"Tagjaguimit",
    "wof:placetype":"locality"
},
  "geometry": {"coordinates":[123.75,10.21667],"type":"Point"}
}