{
  "type": "Feature",
  "properties": {
    "gn:admin1_code":"02",
    "gn:admin2_code":"48",
    "gn:admin3_code":"25012000.0",
    "gn:asciiname":"Malico",
    "gn:country_code":"PH",
    "gn:dem":1320,
    "gn:feature_class":"P",
    "gn:feature_code":"PPL",
    "gn:name":"Malico",
    "gn:population":0,
    "gn:timezone":"Asia/Manila",
    "iso:country":"PH",
    "name:fil_x_preferred":[
        "Malico"
    ],
    "wof:name":"Malico",
    "wof:placetype":"locality"
},
  "geometry": {"coordinates":[120.8708,16.1781],"type":"Point"}
}