{
  "type": "Feature",
  "properties": {
    "gn:admin1_code":"40",
    "gn:admin2_code":"33",
    "gn:admin3_code":"43405000.0",
    "gn:asciiname":"Maunong",
    "gn:country_code":"PH",
    "gn:dem":116,
    "gn:feature_class":"P",
    "gn:feature_code":"PPL",
    "gn:name":"Maunong",
    "gn:population":0,
    "gn:timezone":"Asia/Manila",
    "iso:country":"PH",
    "name:fil_x_preferred":[
        "Maunong"
    ],
    "wof:name":"Maunong",
    "wof:placetype":"locality"
},
  "geometry": {"coordinates":[121.15551000000001,14.17486],"type":"Point"}
}