{
  "type": "Feature",
  "properties": {
    "gn:admin1_code":"02",
    "gn:admin2_code":"48",
    "gn:admin3_code":"25007000.0",
    "gn:asciiname":"Tacbao",
    "gn:country_code":"PH",
    "gn:dem":434,
    "gn:feature_class":"P",
    "gn:feature_code":"PPL",
    "gn:name":"Tacbao",
    "gn:population":0,
    "gn:timezone":"Asia/Manila",
    "iso:country":"PH",
    "name:fil_x_preferred":[
        "Tacbao"
    ],
    "wof:name":"Tacbao",
    "wof:placetype":"locality"
},
  "geometry": {"coordinates":[121.1994,16.3039],"type":"Point"}
}