{
  "type": "Feature",
  "properties": {
    "gn:admin1_code":"07",
    "gn:admin2_code":"21",
    "gn:admin3_code":"72232000.0",
    "gn:asciiname":"Tawagan",
    "gn:country_code":"PH",
    "gn:dem":64,
    "gn:elevation":"0.0",
    "gn:feature_class":"P",
    "gn:feature_code":"PPL",
    "gn:name":"Tawagan",
    "gn:population":0,
    "gn:timezone":"Asia/Manila",
    "iso:country":"PH",
    "name:fil_x_preferred":[
        "Tawagan"
    ],
    "wof:name":"Tawagan",
    "wof:placetype":"locality"
},
  "geometry": {"coordinates":[123.7563,10.27378],"type":"Point"}
}