{
  "type": "Feature",
  "properties": {
    "gn:admin1_code":"05",
    "gn:admin2_code":"39",
    "gn:admin3_code":"54113000.0",
    "gn:asciiname":"Mabunga",
    "gn:country_code":"PH",
    "gn:dem":52,
    "gn:feature_class":"P",
    "gn:feature_code":"PPL",
    "gn:name":"Mabunga",
    "gn:population":0,
    "gn:timezone":"Asia/Manila",
    "iso:country":"PH",
    "name:fil_x_preferred":[
        "Mabunga"
    ],
    "wof:name":"Mabunga",
    "wof:placetype":"locality"
},
  "geometry": {"coordinates":[123.69110999999999,12.32556],"type":"Point"}
}