{
  "type": "Feature",
  "properties": {
    "gn:admin1_code":"01",
    "gn:admin2_code":"36",
    "gn:admin3_code":"13301000.0",
    "gn:asciiname":"Ambitacay",
    "gn:country_code":"PH",
    "gn:dem":49,
    "gn:feature_class":"P",
    "gn:feature_code":"PPL",
    "gn:name":"Ambitacay",
    "gn:population":0,
    "gn:timezone":"Asia/Manila",
    "iso:country":"PH",
    "name:fil_x_preferred":[
        "Ambitacay"
    ],
    "wof:name":"Ambitacay",
    "wof:placetype":"locality"
},
  "geometry": {"coordinates":[120.38030000000001,16.3178],"type":"Point"}
}