{
  "type": "Feature",
  "properties": {
    "gn:admin1_code":"10",
    "gn:admin2_code":"12",
    "gn:admin3_code":"101314000.0",
    "gn:asciiname":"Nunocan",
    "gn:country_code":"PH",
    "gn:dem":403,
    "gn:feature_class":"P",
    "gn:feature_code":"PPL",
    "gn:name":"Nunocan",
    "gn:population":0,
    "gn:timezone":"Asia/Manila",
    "iso:country":"PH",
    "name:fil_x_preferred":[
        "Nunocan"
    ],
    "wof:name":"Nunocan",
    "wof:placetype":"locality"
},
  "geometry": {"coordinates":[124.82583,8.42472],"type":"Point"}
}