{
  "type": "Feature",
  "properties": {
    "gn:admin1_code":"15",
    "gn:admin2_code":"32",
    "gn:admin3_code":"143215000.0",
    "gn:asciiname":"Buanao",
    "gn:country_code":"PH",
    "gn:dem":1109,
    "gn:feature_class":"P",
    "gn:feature_code":"PPL",
    "gn:name":"Buanao",
    "gn:population":0,
    "gn:timezone":"Asia/Manila",
    "iso:country":"PH",
    "name:fil_x_preferred":[
        "Buanao"
    ],
    "wof:name":"Buanao",
    "wof:placetype":"locality"
},
  "geometry": {"coordinates":[121.09610000000001,17.2628],"type":"Point"}
}