{
  "type": "Feature",
  "properties": {
    "gn:country":"PH",
    "gn:fcode":"ADM3",
    "gn:pop":60005,
    "iso:country":"PH",
    "name:ceb_x_preferred":[
        "Obando"
    ],
    "name:deu_x_preferred":[
        "Obando"
    ],
    "name:fil_x_preferred":[
        "Obando"
    ],
    "name:fra_x_preferred":[
        "Obando"
    ],
    "name:ita_x_preferred":[
        "Obando"
    ],
    "name:jpn_x_preferred":[
        "\u30aa\u30d0\u30f3\u30c9\u30fc"
    ],
    "name:nds_x_preferred":[
        "Obando"
    ],
    "name:nld_x_preferred":[
        "Obando"
    ],
    "name:sco_x_preferred":[
        "Obando"
    ],
    "name:spa_x_preferred":[
        "Obando"
    ],
    "name:swe_x_preferred":[
        "Obando"
    ],
    "name:tgl_x_preferred":[
        "Obando"
    ],
    "name:war_x_preferred":[
        "Obando"
    ],
    "qs:name":"Obando",
    "qs:photos_9r":0,
    "qs:photos_sr":0,
    "qs:pop_sr":"8",
    "wd:wordcount":153,
    "wof:name":"Obando",
    "wof:placetype":"localadmin",
    "wof:population":60005
},
  "geometry": {"coordinates":[120.9333,14.7167],"type":"Point"}
}