{
  "type": "Feature",
  "properties": {
    "gn:country":"PH",
    "gn:fcode":"PPL",
    "gn:population":2589,
    "iso:country":"PH",
    "name:fil_x_preferred":[
        "Del Rosario"
    ],
    "qs:name":"Del Rosario",
    "qs:photos_9r":0,
    "qs:photos_sr":0,
    "qs:pop_sr":"4",
    "wd:wordcount":953,
    "wof:name":"Del Rosario",
    "wof:placetype":"locality",
    "wof:population":2589
},
  "geometry": {"coordinates":[123.3133,13.3057],"type":"Point"}
}