{
  "type": "Feature",
  "properties": {
    "gn:admin1_code":"41",
    "gn:admin2_code":"54",
    "gn:admin3_code":"175913000.0",
    "gn:asciiname":"Sampiton",
    "gn:country_code":"PH",
    "gn:dem":20,
    "gn:feature_class":"P",
    "gn:feature_code":"PPL",
    "gn:name":"Sampiton",
    "gn:population":0,
    "gn:timezone":"Asia/Manila",
    "iso:country":"PH",
    "name:fil_x_preferred":[
        "Sampiton"
    ],
    "wof:name":"Sampiton",
    "wof:placetype":"locality"
},
  "geometry": {"coordinates":[122.42631000000002,12.43084],"type":"Point"}
}