{
  "type": "Feature",
  "properties": {
    "gn:country":"PH",
    "gn:fcode":"PPL",
    "gn:population":3552,
    "iso:country":"PH",
    "name:fil_x_preferred":[
        "Maticmatic"
    ],
    "qs:name":"Maticmatic",
    "qs:photos_9r":0,
    "qs:photos_sr":0,
    "qs:pop_sr":"4",
    "wof:name":"Maticmatic",
    "wof:placetype":"locality",
    "wof:population":3552
},
  "geometry": {"coordinates":[120.45192,15.9863],"type":"Point"}
}