{
  "type": "Feature",
  "properties": {
    "gn:admin1_code":"02",
    "gn:admin2_code":"14",
    "gn:admin3_code":"21512000.0",
    "gn:asciiname":"Maracuru",
    "gn:country_code":"PH",
    "gn:dem":31,
    "gn:feature_class":"P",
    "gn:feature_code":"PPL",
    "gn:name":"Maracuru",
    "gn:population":0,
    "gn:timezone":"Asia/Manila",
    "iso:country":"PH",
    "name:fil_x_preferred":[
        "Mara Cury"
    ],
    "name:fil_x_variant":[
        "Maracuru",
        "Marracuru"
    ],
    "wof:name":"Maracuru",
    "wof:placetype":"locality"
},
  "geometry": {"coordinates":[121.75834999999999,17.56103],"type":"Point"}
}