{
  "type": "Feature",
  "properties": {
    "gn:admin1_code":"07",
    "gn:admin2_code":"11",
    "gn:admin3_code":"71247000.0",
    "gn:asciiname":"Anas",
    "gn:country_code":"PH",
    "gn:dem":39,
    "gn:feature_class":"P",
    "gn:feature_code":"PPL",
    "gn:name":"Anas",
    "gn:population":0,
    "gn:timezone":"Asia/Manila",
    "iso:country":"PH",
    "name:fil_x_preferred":[
        "Anas"
    ],
    "wof:name":"Anas",
    "wof:placetype":"locality"
},
  "geometry": {"coordinates":[124.22793,9.60637],"type":"Point"}
}