{
  "type": "Feature",
  "properties": {
    "gn:admin1_code":"01",
    "gn:admin2_code":"29",
    "gn:admin3_code":"12928000.0",
    "gn:asciiname":"Sived",
    "gn:country_code":"PH",
    "gn:dem":10,
    "gn:feature_class":"P",
    "gn:feature_code":"PPL",
    "gn:name":"Sived",
    "gn:population":0,
    "gn:timezone":"Asia/Manila",
    "iso:country":"PH",
    "name:fil_x_preferred":[
        "Sived"
    ],
    "wof:name":"Sived",
    "wof:placetype":"locality"
},
  "geometry": {"coordinates":[120.37255999999999,17.65912],"type":"Point"}
}