{
  "type": "Feature",
  "properties": {
    "gn:admin1_code":"03",
    "gn:admin2_code":"63",
    "gn:admin3_code":"36903000.0",
    "gn:asciiname":"Bobon First",
    "gn:country_code":"PH",
    "gn:dem":29,
    "gn:feature_class":"P",
    "gn:feature_code":"PPL",
    "gn:name":"Bobon First",
    "gn:population":0,
    "gn:timezone":"Asia/Manila",
    "iso:country":"PH",
    "name:fil_x_preferred":[
        "Bobon"
    ],
    "name:und_x_variant":[
        "Bobon Primero",
        "Bobon First"
    ],
    "wof:name":"Bobon First",
    "wof:placetype":"locality"
},
  "geometry": {"coordinates":[120.38625999999999,15.66873],"type":"Point"}
}