{
  "type": "Feature",
  "properties": {
    "gn:admin1_code":"06",
    "gn:admin2_code":"18",
    "gn:admin3_code":"61904000.0",
    "gn:asciiname":"Danguid",
    "gn:country_code":"PH",
    "gn:dem":26,
    "gn:feature_class":"P",
    "gn:feature_code":"PPL",
    "gn:name":"Danguid",
    "gn:population":0,
    "gn:timezone":"Asia/Manila",
    "iso:country":"PH",
    "name:fil_x_preferred":[
        "Danguid"
    ],
    "name:und_x_variant":[
        "DaNgula"
    ],
    "wof:name":"Danguid",
    "wof:placetype":"locality"
},
  "geometry": {"coordinates":[122.666,11.3008],"type":"Point"}
}