{
  "type": "Feature",
  "properties": {
    "gn:admin1_code":"11",
    "gn:admin2_code":"I6",
    "gn:admin3_code":"118208000.0",
    "gn:asciiname":"Bankerohan",
    "gn:country_code":"PH",
    "gn:dem":75,
    "gn:feature_class":"P",
    "gn:feature_code":"PPL",
    "gn:name":"Bankerohan",
    "gn:population":0,
    "gn:timezone":"Asia/Manila",
    "iso:country":"PH",
    "name:fil_x_preferred":[
        "Bankerohan"
    ],
    "name:und_x_variant":[
        "Banquirohan",
        "Bangkerohan"
    ],
    "wof:name":"Bankerohan",
    "wof:placetype":"locality"
},
  "geometry": {"coordinates":[125.9919,7.7317],"type":"Point"}
}