{
  "type": "Feature",
  "properties": {
    "gn:admin1_code":"14",
    "gn:admin2_code":"56",
    "gn:admin3_code":"153818000.0",
    "gn:asciiname":"Tambac",
    "gn:country_code":"PH",
    "gn:dem":494,
    "gn:feature_class":"P",
    "gn:feature_code":"PPL",
    "gn:name":"Tambac",
    "gn:population":0,
    "gn:timezone":"Asia/Manila",
    "iso:country":"PH",
    "name:und_x_variant":[
        "Tombac",
        "Tambac",
        "Tambak"
    ],
    "wof:name":"Tambac",
    "wof:placetype":"locality"
},
  "geometry": {"coordinates":[124.34528,7.53833],"type":"Point"}
}