{
  "type": "Feature",
  "properties": {
    "gn:admin1_code":"03",
    "gn:admin2_code":"50",
    "gn:admin3_code":"35416000.0",
    "gn:asciiname":"San Isidro de Bacolor",
    "gn:country_code":"PH",
    "gn:dem":24,
    "gn:feature_class":"P",
    "gn:feature_code":"PPL",
    "gn:name":"San Isidro de Bacolor",
    "gn:population":0,
    "gn:timezone":"Asia/Manila",
    "iso:country":"PH",
    "name:fil_x_preferred":[
        "San Isidro de Bacolor"
    ],
    "name:fil_x_variant":[
        "San Isidro"
    ],
    "wof:name":"San Isidro de Bacolor",
    "wof:placetype":"locality"
},
  "geometry": {"coordinates":[120.65191000000002,15.0491],"type":"Point"}
}