{
  "type": "Feature",
  "properties": {
    "gn:admin1_code":"01",
    "gn:admin2_code":"29",
    "gn:admin3_code":"12903000.0",
    "gn:asciiname":"Taled",
    "gn:country_code":"PH",
    "gn:dem":17,
    "gn:feature_class":"P",
    "gn:feature_code":"PPL",
    "gn:name":"Taled",
    "gn:population":0,
    "gn:timezone":"Asia/Manila",
    "iso:country":"PH",
    "name:fil_x_preferred":[
        "Taleb"
    ],
    "name:fil_x_variant":[
        "Taled"
    ],
    "wof:name":"Taled",
    "wof:placetype":"locality"
},
  "geometry": {"coordinates":[120.44413,17.57997],"type":"Point"}
}