{
  "type": "Feature",
  "properties": {
    "gn:admin1_code":"05",
    "gn:admin2_code":"39",
    "gn:admin3_code":"54109000.0",
    "gn:asciiname":"Malobagonan",
    "gn:country_code":"PH",
    "gn:dem":13,
    "gn:feature_class":"P",
    "gn:feature_code":"PPL",
    "gn:name":"Malobagonan",
    "gn:population":0,
    "gn:timezone":"Asia/Manila",
    "iso:country":"PH",
    "name:fil_x_preferred":[
        "Malobagonan"
    ],
    "wof:name":"Malobagonan",
    "wof:placetype":"locality"
},
  "geometry": {"coordinates":[124.05759999999999,11.7232],"type":"Point"}
}