{
  "type": "Feature",
  "properties": {
    "gn:admin1_code":"03",
    "gn:admin2_code":"13",
    "gn:admin3_code":"31407000.0",
    "gn:asciiname":"Pungo",
    "gn:country_code":"PH",
    "gn:dem":6,
    "gn:feature_class":"P",
    "gn:feature_code":"PPL",
    "gn:name":"Pungo",
    "gn:population":0,
    "gn:timezone":"Asia/Manila",
    "iso:country":"PH",
    "name:fil_x_preferred":[
        "Pungo"
    ],
    "wof:name":"Pungo",
    "wof:placetype":"locality"
},
  "geometry": {"coordinates":[120.79456999999999,14.91781],"type":"Point"}
}