{
  "type": "Feature",
  "properties": {
    "gn:admin1_code":"01",
    "gn:admin2_code":"29",
    "gn:admin3_code":"12920000.0",
    "gn:asciiname":"Imayos Norte",
    "gn:country_code":"PH",
    "gn:dem":17,
    "gn:feature_class":"P",
    "gn:feature_code":"PPL",
    "gn:name":"Imayos Norte",
    "gn:population":0,
    "gn:timezone":"Asia/Manila",
    "iso:country":"PH",
    "name:fil_x_preferred":[
        "Imayos Norte"
    ],
    "name:und_x_variant":[
        "Immayos",
        "Immayus Norte"
    ],
    "wof:name":"Imayos Norte",
    "wof:placetype":"locality"
},
  "geometry": {"coordinates":[120.45517,17.7356],"type":"Point"}
}