{
  "type": "Feature",
  "properties": {
    "gn:admin1_code":"10",
    "gn:admin2_code":"12",
    "gn:admin3_code":"101322000.0",
    "gn:asciiname":"Lambagan",
    "gn:country_code":"PH",
    "gn:dem":477,
    "gn:feature_class":"P",
    "gn:feature_code":"PPL",
    "gn:name":"Lambagan",
    "gn:population":0,
    "gn:timezone":"Asia/Manila",
    "iso:country":"PH",
    "name:fil_x_preferred":[
        "Lambagan"
    ],
    "wof:name":"Lambagan",
    "wof:placetype":"locality"
},
  "geometry": {"coordinates":[125.25861,8.08278],"type":"Point"}
}