{
  "type": "Feature",
  "properties": {
    "gn:admin1_code":"06",
    "gn:admin2_code":"06",
    "gn:admin3_code":"60602000.0",
    "gn:asciiname":"Lan-as",
    "gn:country_code":"PH",
    "gn:dem":152,
    "gn:feature_class":"P",
    "gn:feature_code":"PPL",
    "gn:name":"Lan-as",
    "gn:population":0,
    "gn:timezone":"Asia/Manila",
    "iso:country":"PH",
    "name:fil_x_preferred":[
        "Lan-as"
    ],
    "wof:name":"Lan-as",
    "wof:placetype":"locality"
},
  "geometry": {"coordinates":[122.08381,11.19592],"type":"Point"}
}