{
  "type": "Feature",
  "properties": {
    "gn:admin1_code":"03",
    "gn:admin2_code":"07",
    "gn:admin3_code":"30805000.0",
    "gn:asciiname":"Culis",
    "gn:country_code":"PH",
    "gn:dem":15,
    "gn:feature_class":"P",
    "gn:feature_code":"PPL",
    "gn:name":"Culis",
    "gn:population":0,
    "gn:timezone":"Asia/Manila",
    "iso:country":"PH",
    "name:fil_x_preferred":[
        "Culis"
    ],
    "name:und_x_variant":[
        "Kulis",
        "Culis"
    ],
    "wof:name":"Culis",
    "wof:placetype":"locality"
},
  "geometry": {"coordinates":[120.48054,14.83831],"type":"Point"}
}