{
  "type": "Feature",
  "properties": {
    "iso:country":"PH",
    "qs:gn_pop":0,
    "qs:name":"Lagnay",
    "qs:name_adm0":"Philippines",
    "qs:name_adm1":"Bicol Region",
    "qs:photos":108,
    "qs:photos_1k":22,
    "qs:photos_9k":1,
    "qs:photos_9r":3,
    "qs:photos_all":108,
    "qs:photos_sr":3,
    "qs:placetype":"Town",
    "qs:pop_sr":"0",
    "qs:woe_adm0":23424934,
    "wof:name":"Lagnay",
    "wof:placetype":"locality"
},
  "geometry": {"coordinates":[123.670177,13.704729],"type":"Point"}
}