{
  "type": "Feature",
  "properties": {
    "gn:admin1_code":"02",
    "gn:admin2_code":"31",
    "gn:admin3_code":"23131000.0",
    "gn:asciiname":"Nasipa",
    "gn:cc2":"PH",
    "gn:country_code":"PH",
    "gn:dem":698,
    "gn:feature_class":"P",
    "gn:feature_code":"PPL",
    "gn:name":"Nasipa",
    "gn:population":0,
    "gn:timezone":"Asia/Manila",
    "iso:country":"PH",
    "name:und_x_variant":[
        "Nasupa",
        "Nasipa"
    ],
    "wof:name":"Nasipa",
    "wof:placetype":"locality"
},
  "geometry": {"coordinates":[122.25,16.98333],"type":"Point"}
}