{
  "type": "Feature",
  "properties": {
    "gn:admin1_code":"06",
    "gn:admin2_code":"H3",
    "gn:admin3_code":"64516000.0",
    "gn:asciiname":"Danao Veharri",
    "gn:country_code":"PH",
    "gn:dem":135,
    "gn:feature_class":"P",
    "gn:feature_code":"PPL",
    "gn:name":"Danao Veharri",
    "gn:population":0,
    "gn:timezone":"Asia/Manila",
    "iso:country":"PH",
    "name:fil_x_preferred":[
        "Danao Veharri"
    ],
    "name:fil_x_variant":[
        "Danao"
    ],
    "name:und_x_variant":[
        "Banao"
    ],
    "wof:name":"Danao Veharri",
    "wof:placetype":"locality"
},
  "geometry": {"coordinates":[123.01430000000001,10.3841],"type":"Point"}
}