{
  "type": "Feature",
  "properties": {
    "gn:admin1_code":"10",
    "gn:admin2_code":"43",
    "gn:admin3_code":"104302000.0",
    "gn:asciiname":"Binsir",
    "gn:country_code":"PH",
    "gn:dem":31,
    "gn:feature_class":"P",
    "gn:feature_code":"PPL",
    "gn:name":"Binsir",
    "gn:population":0,
    "gn:timezone":"Asia/Manila",
    "iso:country":"PH",
    "name:fil_x_preferred":[
        "Binsir"
    ],
    "wof:name":"Binsir",
    "wof:placetype":"locality"
},
  "geometry": {"coordinates":[124.79333,8.75722],"type":"Point"}
}