{
  "type": "Feature",
  "properties": {
    "gn:admin1_code":"11",
    "gn:admin2_code":"P3",
    "gn:admin3_code":"118603000.0",
    "gn:asciiname":"Balas",
    "gn:country_code":"PH",
    "gn:dem":19,
    "gn:feature_class":"P",
    "gn:feature_code":"PPL",
    "gn:name":"Balas",
    "gn:population":0,
    "gn:timezone":"Asia/Manila",
    "iso:country":"PH",
    "name:ceb_x_preferred":[
        "Bal\u016bs"
    ],
    "name:fas_x_preferred":[
        "\u0628\u0627\u0644\u0627\u0633"
    ],
    "name:fil_x_preferred":[
        "Balas"
    ],
    "name:swe_x_preferred":[
        "Bal\u016bs"
    ],
    "wof:name":"Balas",
    "wof:placetype":"locality"
},
  "geometry": {"coordinates":[125.64417,6.33917],"type":"Point"}
}