{
  "type": "Feature",
  "properties": {
    "gn:admin1_code":"01",
    "gn:admin2_code":"29",
    "gn:admin3_code":"12934000.0",
    "gn:asciiname":"Nagsangalan",
    "gn:country_code":"PH",
    "gn:dem":12,
    "gn:feature_class":"P",
    "gn:feature_code":"PPL",
    "gn:name":"Nagsangalan",
    "gn:population":0,
    "gn:timezone":"Asia/Manila",
    "iso:country":"PH",
    "name:und_x_variant":[
        "Nagsangalan Bisset"
    ],
    "wof:name":"Nagsangalan",
    "wof:placetype":"locality"
},
  "geometry": {"coordinates":[120.40864999999999,17.57005],"type":"Point"}
}