{
  "type": "Feature",
  "properties": {
    "gn:admin1_code":"06",
    "gn:admin2_code":"06",
    "gn:admin3_code":"60602000.0",
    "gn:asciiname":"Jinalinan",
    "gn:country_code":"PH",
    "gn:dem":7,
    "gn:feature_class":"P",
    "gn:feature_code":"PPL",
    "gn:name":"Jinalinan",
    "gn:population":0,
    "gn:timezone":"Asia/Manila",
    "iso:country":"PH",
    "name:fil_x_preferred":[
        "Jinalinan"
    ],
    "name:und_x_variant":[
        "Hinalinan"
    ],
    "wof:name":"Jinalinan",
    "wof:placetype":"locality"
},
  "geometry": {"coordinates":[122.05161,11.21932],"type":"Point"}
}