{
  "type": "Feature",
  "properties": {
    "gn:admin1_code":"02",
    "gn:admin2_code":"14",
    "gn:admin3_code":"21506000.0",
    "gn:asciiname":"Magaloyao",
    "gn:country_code":"PH",
    "gn:dem":43,
    "gn:feature_class":"P",
    "gn:feature_code":"PPL",
    "gn:name":"Magaloyao",
    "gn:population":0,
    "gn:timezone":"Asia/Manila",
    "iso:country":"PH",
    "name:fil_x_preferred":[
        "Magaloyao"
    ],
    "wof:name":"Magaloyao",
    "wof:placetype":"locality"
},
  "geometry": {"coordinates":[121.77845000000001,17.94079],"type":"Point"}
}