{
  "type": "Feature",
  "properties": {
    "gn:admin1_code":"02",
    "gn:admin2_code":"14",
    "gn:admin3_code":"21529000.0",
    "gn:asciiname":"Cataggaman Viejo",
    "gn:country_code":"PH",
    "gn:dem":28,
    "gn:feature_class":"P",
    "gn:feature_code":"PPL",
    "gn:name":"Cataggaman Viejo",
    "gn:population":0,
    "gn:timezone":"Asia/Manila",
    "iso:country":"PH",
    "name:fil_x_preferred":[
        "Cataggaman Viejo"
    ],
    "name:und_x_variant":[
        "Cataggamman Viejo"
    ],
    "wof:name":"Cataggaman Viejo",
    "wof:placetype":"locality"
},
  "geometry": {"coordinates":[121.70659999999999,17.59621],"type":"Point"}
}