{
  "type": "Feature",
  "properties": {
    "gn:admin1_code":"05",
    "gn:admin2_code":"16",
    "gn:admin3_code":"51713000.0",
    "gn:asciiname":"Sampaloc",
    "gn:country_code":"PH",
    "gn:dem":1,
    "gn:feature_class":"P",
    "gn:feature_code":"PPL",
    "gn:name":"Sampaloc",
    "gn:population":0,
    "gn:timezone":"Asia/Manila",
    "iso:country":"PH",
    "name:fil_x_preferred":[
        "Sampaloc"
    ],
    "wof:name":"Sampaloc",
    "wof:placetype":"locality"
},
  "geometry": {"coordinates":[123.13333,13.58333],"type":"Point"}
}