{
  "type": "Feature",
  "properties": {
    "gn:admin1_code":"14",
    "gn:admin2_code":"56",
    "gn:admin3_code":"153818000.0",
    "gn:asciiname":"Kalilangan",
    "gn:country_code":"PH",
    "gn:dem":257,
    "gn:feature_class":"P",
    "gn:feature_code":"PPL",
    "gn:name":"Kalilangan",
    "gn:population":0,
    "gn:timezone":"Asia/Manila",
    "iso:country":"PH",
    "name:fil_x_preferred":[
        "Kalilangan"
    ],
    "wof:name":"Kalilangan",
    "wof:placetype":"locality"
},
  "geometry": {"coordinates":[124.33693999999998,7.46111],"type":"Point"}
}