{
  "type": "Feature",
  "properties": {
    "gn:admin1_code":"06",
    "gn:admin2_code":"H3",
    "gn:admin3_code":"64511000.0",
    "gn:asciiname":"Feria",
    "gn:country_code":"PH",
    "gn:dem":16,
    "gn:feature_class":"P",
    "gn:feature_code":"PPL",
    "gn:name":"Feria",
    "gn:population":0,
    "gn:timezone":"Asia/Manila",
    "iso:country":"PH",
    "name:fil_x_preferred":[
        "Feria"
    ],
    "wof:name":"Feria",
    "wof:placetype":"locality"
},
  "geometry": {"coordinates":[122.94199999999999,10.2347],"type":"Point"}
}