{
  "type": "Feature",
  "properties": {
    "gn:gn_country":"PH",
    "gn:gn_fcode":"PPL",
    "gn:gn_pop":3508,
    "gn:population":3508,
    "iso:country":"PH",
    "name:eng_x_preferred":[
        "Taguitic"
    ],
    "name:unk_x_variant":[
        "Tagaitic"
    ],
    "qs_pg:aaroncc":"PH",
    "qs_pg:gn_country":"PH",
    "qs_pg:gn_fcode":"PPL",
    "qs_pg:gn_pop":3508,
    "qs_pg:name":"Taguitic",
    "qs_pg:photos_9r":0,
    "qs_pg:photos_sr":0,
    "qs_pg:pop_sr":4,
    "qs_pg:qs_pg_placetype":"locality",
    "wof:name":"Taguitic",
    "wof:placetype":"locality",
    "wof:population":3508
},
  "geometry": {"coordinates":[123.63120000000001,7.9387],"type":"Point"}
}