{
  "type": "Feature",
  "properties": {
    "gn:admin1_code":"06",
    "gn:admin2_code":"H3",
    "gn:admin3_code":"64522000.0",
    "gn:asciiname":"Patic",
    "gn:country_code":"PH",
    "gn:dem":6,
    "gn:feature_class":"P",
    "gn:feature_code":"PPL",
    "gn:name":"Patic",
    "gn:population":0,
    "gn:timezone":"Asia/Manila",
    "iso:country":"PH",
    "name:fil_x_preferred":[
        "Patic"
    ],
    "name:und_x_variant":[
        "Patio",
        "Patik"
    ],
    "wof:name":"Patic",
    "wof:placetype":"locality"
},
  "geometry": {"coordinates":[122.8116,10.5042],"type":"Point"}
}