{
  "type": "Feature",
  "properties": {
    "gn:admin1_code":"08",
    "gn:admin2_code":"59",
    "gn:asciiname":"Dagami",
    "gn:country_code":"PH",
    "gn:dem":633,
    "gn:feature_class":"P",
    "gn:feature_code":"PPL",
    "gn:name":"Dagami",
    "gn:population":0,
    "gn:timezone":"Asia/Manila",
    "iso:country":"PH",
    "name:fil_x_preferred":[
        "Dagami"
    ],
    "name:und_x_variant":[
        "Dagami-Tranka-Igtalongon"
    ],
    "wof:name":"Dagami",
    "wof:placetype":"locality"
},
  "geometry": {"coordinates":[122.3586,10.9483],"type":"Point"}
}