{
  "type": "Feature",
  "properties": {
    "gn:admin1_code":"01",
    "gn:admin2_code":"51",
    "gn:admin3_code":"15511000.0",
    "gn:asciiname":"Idong",
    "gn:country_code":"PH",
    "gn:dem":16,
    "gn:feature_class":"P",
    "gn:feature_code":"PPL",
    "gn:name":"Idong",
    "gn:population":0,
    "gn:timezone":"Asia/Manila",
    "iso:country":"PH",
    "wof:name":"Idong",
    "wof:placetype":"locality"
},
  "geometry": {"coordinates":[120.39700000000001,15.79514],"type":"Point"}
}