{
  "type": "Feature",
  "properties": {
    "gn:admin1_code":"05",
    "gn:admin2_code":"16",
    "gn:admin3_code":"51717000.0",
    "gn:asciiname":"Buludan",
    "gn:cc2":"PH",
    "gn:country_code":"PH",
    "gn:dem":72,
    "gn:feature_class":"P",
    "gn:feature_code":"PPL",
    "gn:name":"Buludan",
    "gn:population":0,
    "gn:timezone":"Asia/Manila",
    "iso:country":"PH",
    "name:und_x_variant":[
        "Bolodan",
        "Buludan"
    ],
    "wof:name":"Buludan",
    "wof:placetype":"locality"
},
  "geometry": {"coordinates":[123.43333,13.81667],"type":"Point"}
}