{
  "type": "Feature",
  "properties": {
    "gn:admin1_code":"10",
    "gn:admin2_code":"17",
    "gn:asciiname":"Tagtanawan",
    "gn:country_code":"PH",
    "gn:dem":204,
    "gn:feature_class":"P",
    "gn:feature_code":"PPL",
    "gn:name":"Tagtanawan",
    "gn:population":0,
    "gn:timezone":"Asia/Manila",
    "iso:country":"PH",
    "name:fil_x_preferred":[
        "Tagtanawan"
    ],
    "wof:name":"Tagtanawan",
    "wof:placetype":"locality"
},
  "geometry": {"coordinates":[125.7551,7.0572],"type":"Point"}
}