{
  "type": "Feature",
  "properties": {
    "gn:admin1_code":"15",
    "gn:admin2_code":"H6",
    "gn:admin3_code":"148104000.0",
    "gn:asciiname":"Agumingan",
    "gn:country_code":"PH",
    "gn:dem":461,
    "gn:feature_class":"P",
    "gn:feature_code":"PPL",
    "gn:name":"Agumingan",
    "gn:population":0,
    "gn:timezone":"Asia/Manila",
    "iso:country":"PH",
    "name:fil_x_preferred":[
        "Agumingan"
    ],
    "wof:name":"Agumingan",
    "wof:placetype":"locality"
},
  "geometry": {"coordinates":[121.1464,18.16744],"type":"Point"}
}