{
  "type": "Feature",
  "properties": {
    "gn:country":"PH",
    "gn:fcode":"ADM3",
    "gn:pop":36567,
    "iso:country":"PH",
    "name:eng_x_preferred":[
        "Municipality of Tukuran"
    ],
    "name:unk_x_variant":[
        "Tukuran"
    ],
    "qs:name":"Municipality of Tukuran",
    "qs:photos_9r":0,
    "qs:photos_sr":0,
    "qs:pop_sr":"7",
    "wd:wordcount":533,
    "wof:name":"Municipality of Tukuran",
    "wof:placetype":"localadmin",
    "wof:population":36567
},
  "geometry": {"coordinates":[123.5384,7.9065],"type":"Point"}
}