{
  "type": "Feature",
  "properties": {
    "gn:admin1_code":"05",
    "gn:admin2_code":"15",
    "gn:admin3_code":"51612000.0",
    "gn:asciiname":"Sugod",
    "gn:country_code":"PH",
    "gn:dem":4,
    "gn:feature_class":"P",
    "gn:feature_code":"PPL",
    "gn:name":"Sugod",
    "gn:population":0,
    "gn:timezone":"Asia/Manila",
    "iso:country":"PH",
    "name:fil_x_preferred":[
        "Sugod"
    ],
    "wof:name":"Sugod",
    "wof:placetype":"locality"
},
  "geometry": {"coordinates":[122.9389,14.4279],"type":"Point"}
}