{
  "type": "Feature",
  "properties": {
    "gn:admin1_code":"15",
    "gn:admin2_code":"10",
    "gn:admin3_code":"141104000.0",
    "gn:asciiname":"Peday",
    "gn:country_code":"PH",
    "gn:dem":1179,
    "gn:feature_class":"P",
    "gn:feature_code":"PPL",
    "gn:name":"Peday",
    "gn:population":0,
    "gn:timezone":"Asia/Manila",
    "iso:country":"PH",
    "name:fil_x_preferred":[
        "Peday"
    ],
    "name:fil_x_variant":[
        "Paday"
    ],
    "wof:name":"Peday",
    "wof:placetype":"locality"
},
  "geometry": {"coordinates":[120.85063999999998,16.52048],"type":"Point"}
}