{
  "type": "Feature",
  "properties": {
    "gn:admin1_code":"15",
    "gn:admin2_code":"32",
    "gn:admin3_code":"143208000.0",
    "gn:asciiname":"Ableg",
    "gn:country_code":"PH",
    "gn:dem":612,
    "gn:feature_class":"P",
    "gn:feature_code":"PPL",
    "gn:name":"Ableg",
    "gn:population":0,
    "gn:timezone":"Asia/Manila",
    "iso:country":"PH",
    "name:fil_x_preferred":[
        "Ableg"
    ],
    "wof:name":"Ableg",
    "wof:placetype":"locality"
},
  "geometry": {"coordinates":[121.17529999999999,17.3881],"type":"Point"}
}