{
  "type": "Feature",
  "properties": {
    "gn:admin1_code":"02",
    "gn:admin2_code":"14",
    "gn:admin3_code":"21503000.0",
    "gn:asciiname":"Labben",
    "gn:country_code":"PH",
    "gn:dem":21,
    "gn:feature_class":"P",
    "gn:feature_code":"PPL",
    "gn:name":"Labben",
    "gn:population":0,
    "gn:timezone":"Asia/Manila",
    "iso:country":"PH",
    "name:fil_x_preferred":[
        "Labben"
    ],
    "wof:name":"Labben",
    "wof:placetype":"locality"
},
  "geometry": {"coordinates":[121.55974999999999,18.19728],"type":"Point"}
}