{
  "type": "Feature",
  "properties": {
    "gn:gn_country":"PH",
    "gn:gn_fcode":"PPLA3",
    "gn:gn_pop":2354,
    "gn:population":2354,
    "iso:country":"PH",
    "name:bcl_x_preferred":[
        "Amulung"
    ],
    "name:cat_x_preferred":[
        "Amulung"
    ],
    "name:dut_x_preferred":[
        "Amulung"
    ],
    "name:eng_x_preferred":[
        "Amulung"
    ],
    "name:fil_x_preferred":[
        "Amulung"
    ],
    "name:fil_x_variant":[
        "Amulong"
    ],
    "name:fre_x_preferred":[
        "Amulung"
    ],
    "name:ger_x_preferred":[
        "Amulung"
    ],
    "name:ilo_x_preferred":[
        "Amulung"
    ],
    "name:ind_x_preferred":[
        "Amulung"
    ],
    "name:ita_x_preferred":[
        "Amulung"
    ],
    "name:oci_x_preferred":[
        "Amulung"
    ],
    "name:pag_x_preferred":[
        "Amulung"
    ],
    "name:pam_x_preferred":[
        "Amulung"
    ],
    "name:per_x_preferred":[
        "\u0627\u0645\u0648\u0644\u0627\u0646\u06af\u060c \u0633\u0627\u06af\u0627\u06cc\u0627\u0646"
    ],
    "name:spa_x_preferred":[
        "Amulung"
    ],
    "name:swe_x_preferred":[
        "Amulung"
    ],
    "name:tgl_x_preferred":[
        "Amulung"
    ],
    "name:unk_x_variant":[
        "Amulong"
    ],
    "name:vie_x_preferred":[
        "Amulung"
    ],
    "name:war_x_preferred":[
        "Amulung"
    ],
    "qs_pg:aaroncc":"PH",
    "qs_pg:gn_country":"PH",
    "qs_pg:gn_fcode":"PPLA3",
    "qs_pg:gn_pop":2354,
    "qs_pg:name":"Amulung",
    "qs_pg:photos_9r":0,
    "qs_pg:photos_sr":0,
    "qs_pg:pop_sr":4,
    "qs_pg:qs_pg_placetype":"locality",
    "wof:name":"Amulung",
    "wof:placetype":"locality",
    "wof:population":2354
},
  "geometry": {"coordinates":[121.72375,17.8357],"type":"Point"}
}