{
  "type": "Feature",
  "properties": {
    "gn:admin1_code":"06",
    "gn:admin2_code":"18",
    "gn:admin3_code":"61906000.0",
    "gn:asciiname":"Pangabutan",
    "gn:country_code":"PH",
    "gn:dem":49,
    "gn:feature_class":"P",
    "gn:feature_code":"PPL",
    "gn:name":"Pangabutan",
    "gn:population":0,
    "gn:timezone":"Asia/Manila",
    "iso:country":"PH",
    "name:fil_x_preferred":[
        "Pangabutan"
    ],
    "name:und_x_variant":[
        "Pangabuan"
    ],
    "wof:name":"Pangabutan",
    "wof:placetype":"locality"
},
  "geometry": {"coordinates":[122.5299,11.4189],"type":"Point"}
}