{
  "type": "Feature",
  "properties": {
    "gn:admin1_code":"40",
    "gn:admin2_code":"33",
    "gn:admin3_code":"43414000.0",
    "gn:asciiname":"Hanayan",
    "gn:country_code":"PH",
    "gn:dem":6,
    "gn:feature_class":"P",
    "gn:feature_code":"PPL",
    "gn:name":"Hanayan",
    "gn:population":0,
    "gn:timezone":"Asia/Manila",
    "iso:country":"PH",
    "name:fil_x_preferred":[
        "Hanayan"
    ],
    "wof:name":"Hanayan",
    "wof:placetype":"locality"
},
  "geometry": {"coordinates":[121.4115,14.4443],"type":"Point"}
}