{
  "type": "Feature",
  "properties": {
    "gn:admin1_code":"40",
    "gn:admin2_code":"09",
    "gn:admin3_code":"41001000.0",
    "gn:asciiname":"Pamiga",
    "gn:country_code":"PH",
    "gn:dem":77,
    "gn:feature_class":"P",
    "gn:feature_code":"PPL",
    "gn:name":"Pamiga",
    "gn:population":0,
    "gn:timezone":"Asia/Manila",
    "iso:country":"PH",
    "name:fil_x_preferred":[
        "Pamiga"
    ],
    "wof:name":"Pamiga",
    "wof:placetype":"locality"
},
  "geometry": {"coordinates":[120.92543000000001,13.93699],"type":"Point"}
}