{
  "type": "Feature",
  "properties": {
    "gn:country":"PH",
    "gn:fcode":"PPL",
    "gn:pop":2477,
    "iso:country":"PH",
    "name:fil_x_preferred":[
        "Bay-ang"
    ],
    "qs:name":"Bay-ang",
    "qs:photos_9r":0,
    "qs:photos_sr":0,
    "qs:pop_sr":"4",
    "wd:wordcount":337,
    "wof:name":"Bay-ang",
    "wof:placetype":"locality",
    "wof:population":2477
},
  "geometry": {"coordinates":[122.94167,11.03472],"type":"Point"}
}