{
  "type": "Feature",
  "properties": {
    "gn:admin1_code":"08",
    "gn:admin2_code":"55",
    "gn:admin3_code":"86006000.0",
    "gn:asciiname":"Molung",
    "gn:country_code":"PH",
    "gn:dem":16,
    "gn:feature_class":"P",
    "gn:feature_code":"PPL",
    "gn:name":"Molung",
    "gn:population":0,
    "gn:timezone":"Asia/Manila",
    "iso:country":"PH",
    "name:fil_x_preferred":[
        "Molung"
    ],
    "wof:name":"Molung",
    "wof:placetype":"locality"
},
  "geometry": {"coordinates":[124.72306,11.67333],"type":"Point"}
}