{
  "type": "Feature",
  "properties": {
    "gn:admin1_code":"05",
    "gn:admin2_code":"05",
    "gn:admin3_code":"50504000.0",
    "gn:asciiname":"Muladbucad Pequeno",
    "gn:country_code":"PH",
    "gn:dem":195,
    "gn:feature_class":"P",
    "gn:feature_code":"PPL",
    "gn:name":"Muladbucad Peque\u00f1o",
    "gn:population":0,
    "gn:timezone":"Asia/Manila",
    "iso:country":"PH",
    "name:fil_x_preferred":[
        "Muladbucad Peque\u00f1o"
    ],
    "wof:name":"Muladbucad Pequeno",
    "wof:placetype":"locality"
},
  "geometry": {"coordinates":[123.61028,13.23306],"type":"Point"}
}