{
  "type": "Feature",
  "properties": {
    "gn:admin1_code":"14",
    "gn:admin2_code":"35",
    "gn:admin3_code":"153639000.0",
    "gn:asciiname":"Matimus",
    "gn:country_code":"PH",
    "gn:dem":10,
    "gn:feature_class":"P",
    "gn:feature_code":"PPL",
    "gn:name":"Matimus",
    "gn:population":0,
    "gn:timezone":"Asia/Manila",
    "iso:country":"PH",
    "name:fil_x_preferred":[
        "Matimus"
    ],
    "wof:name":"Matimus",
    "wof:placetype":"locality"
},
  "geometry": {"coordinates":[124.15139000000001,7.44972],"type":"Point"}
}