{
  "type": "Feature",
  "properties": {
    "gn:admin1_code":"15",
    "gn:admin2_code":"01",
    "gn:admin3_code":"140118000.0",
    "gn:asciiname":"Naguirayan",
    "gn:country_code":"PH",
    "gn:dem":38,
    "gn:feature_class":"P",
    "gn:feature_code":"PPL",
    "gn:name":"Naguirayan",
    "gn:population":0,
    "gn:timezone":"Asia/Manila",
    "iso:country":"PH",
    "name:fil_x_preferred":[
        "Naguirayan"
    ],
    "wof:name":"Naguirayan",
    "wof:placetype":"locality"
},
  "geometry": {"coordinates":[120.57470000000001,17.5651],"type":"Point"}
}