{
  "type": "Feature",
  "properties": {
    "gn:admin1_code":"08",
    "gn:admin2_code":"55",
    "gn:admin3_code":"86018000.0",
    "gn:asciiname":"Narotanglad",
    "gn:country_code":"PH",
    "gn:dem":97,
    "gn:feature_class":"P",
    "gn:feature_code":"PPL",
    "gn:name":"Narotanglad",
    "gn:population":0,
    "gn:timezone":"Asia/Manila",
    "iso:country":"PH",
    "name:fil_x_preferred":[
        "Narotanglad"
    ],
    "wof:name":"Narotanglad",
    "wof:placetype":"locality"
},
  "geometry": {"coordinates":[124.45099999999999,11.9028],"type":"Point"}
}