{
  "type": "Feature",
  "properties": {
    "gn:admin1_code":"40",
    "gn:admin2_code":"H2",
    "gn:asciiname":"Cabulihan",
    "gn:country_code":"PH",
    "gn:dem":1,
    "gn:feature_class":"P",
    "gn:feature_code":"PPL",
    "gn:name":"Cabulihan",
    "gn:population":0,
    "gn:timezone":"Asia/Manila",
    "iso:country":"PH",
    "name:fil_x_preferred":[
        "Cabulihan"
    ],
    "name:und_x_variant":[
        "Ilayang Cabulihan",
        "Ilaya"
    ],
    "wof:name":"Cabulihan",
    "wof:placetype":"locality"
},
  "geometry": {"coordinates":[121.96666999999999,13.83333],"type":"Point"}
}