{
  "type": "Feature",
  "properties": {
    "gn:country":"PH",
    "gn:fcode":"PPLA3",
    "gn:pop":4724,
    "iso:country":"PH",
    "name:bcl_x_preferred":[
        "Minalabac"
    ],
    "name:ceb_x_preferred":[
        "Minalabac"
    ],
    "name:deu_x_preferred":[
        "Minalabac"
    ],
    "name:eng_x_preferred":[
        "Minalabac"
    ],
    "name:fil_x_preferred":[
        "Minalabac"
    ],
    "name:fra_x_preferred":[
        "Minalabac"
    ],
    "name:gor_x_preferred":[
        "Minalabac"
    ],
    "name:ilo_x_preferred":[
        "Minalabac"
    ],
    "name:ind_x_preferred":[
        "Minalabac"
    ],
    "name:ita_x_preferred":[
        "Minalabac"
    ],
    "name:nld_x_preferred":[
        "Minalabac"
    ],
    "name:nob_x_preferred":[
        "Minalabac"
    ],
    "name:pag_x_preferred":[
        "Minalabac"
    ],
    "name:pam_x_preferred":[
        "Minalabac"
    ],
    "name:swe_x_preferred":[
        "Minalabac"
    ],
    "name:tgl_x_preferred":[
        "Minalabac"
    ],
    "name:war_x_preferred":[
        "Minalabac"
    ],
    "qs:name":"Minalabac",
    "qs:photos_9r":0,
    "qs:photos_sr":0,
    "qs:pop_sr":"4",
    "wof:name":"Minalabac",
    "wof:placetype":"locality",
    "wof:population":4724
},
  "geometry": {"coordinates":[123.18380000000001,13.5687],"type":"Point"}
}