{
  "type": "Feature",
  "properties": {
    "gn:admin1_code":"02",
    "gn:admin2_code":"14",
    "gn:admin3_code":"21516000.0",
    "gn:asciiname":"Dalaya",
    "gn:country_code":"PH",
    "gn:dem":64,
    "gn:feature_class":"P",
    "gn:feature_code":"PPL",
    "gn:name":"Dalaya",
    "gn:population":0,
    "gn:timezone":"Asia/Manila",
    "iso:country":"PH",
    "name:fil_x_preferred":[
        "Dalaya"
    ],
    "wof:name":"Dalaya",
    "wof:placetype":"locality"
},
  "geometry": {"coordinates":[121.76667,18.15],"type":"Point"}
}