{
  "type": "Feature",
  "properties": {
    "gn:admin1_code":"03",
    "gn:admin2_code":"63",
    "gn:admin3_code":"36907000.0",
    "gn:asciiname":"Bantog-Caricutan",
    "gn:country_code":"PH",
    "gn:dem":21,
    "gn:feature_class":"P",
    "gn:feature_code":"PPL",
    "gn:name":"Bantog-Caricutan",
    "gn:population":0,
    "gn:timezone":"Asia/Manila",
    "iso:country":"PH",
    "name:fil_x_preferred":[
        "Bantog-Caricutan"
    ],
    "name:fil_x_variant":[
        "Bantug",
        "Bantog"
    ],
    "wof:name":"Bantog-Caricutan",
    "wof:placetype":"locality"
},
  "geometry": {"coordinates":[120.71281999999999,15.38735],"type":"Point"}
}