{
  "type": "Feature",
  "properties": {
    "gn:admin1_code":"14",
    "gn:admin2_code":"60",
    "gn:asciiname":"Tabu' Manuk",
    "gn:country_code":"PH",
    "gn:dem":1,
    "gn:feature_class":"P",
    "gn:feature_code":"PPL",
    "gn:name":"Tabu\u2019 Manuk",
    "gn:population":0,
    "gn:timezone":"Asia/Manila",
    "iso:country":"PH",
    "name:fil_x_preferred":[
        "Tabu\u2019 Manuk"
    ],
    "name:und_x_variant":[
        "Tabo Manok",
        "Tandumanuk"
    ],
    "wof:name":"Tabu' Manuk",
    "wof:placetype":"locality"
},
  "geometry": {"coordinates":[121.23333,5.93333],"type":"Point"}
}