{
  "type": "Feature",
  "properties": {
    "gn:admin1_code":"01",
    "gn:admin2_code":"29",
    "gn:admin3_code":"12931000.0",
    "gn:asciiname":"Pagogo",
    "gn:country_code":"PH",
    "gn:dem":173,
    "gn:feature_class":"P",
    "gn:feature_code":"PPL",
    "gn:name":"Pagogo",
    "gn:population":0,
    "gn:timezone":"Asia/Manila",
    "iso:country":"PH",
    "name:fil_x_preferred":[
        "Pagogo"
    ],
    "name:fil_x_variant":[
        "Pagago"
    ],
    "wof:name":"Pagogo",
    "wof:placetype":"locality"
},
  "geometry": {"coordinates":[120.5209,16.8592],"type":"Point"}
}