{
  "type": "Feature",
  "properties": {
    "gn:admin1_code":"40",
    "gn:admin2_code":"33",
    "gn:admin3_code":"43423000.0",
    "gn:asciiname":"Paule 1",
    "gn:country_code":"PH",
    "gn:dem":285,
    "gn:feature_class":"P",
    "gn:feature_code":"PPL",
    "gn:name":"Paule 1",
    "gn:population":0,
    "gn:timezone":"Asia/Manila",
    "iso:country":"PH",
    "name:fil_x_preferred":[
        "Paule I"
    ],
    "wof:name":"Paule 1",
    "wof:placetype":"locality"
},
  "geometry": {"coordinates":[121.4003,14.10769],"type":"Point"}
}