{
  "type": "Feature",
  "properties": {
    "gn:admin1_code":"05",
    "gn:admin2_code":"39",
    "gn:admin3_code":"54118000.0",
    "gn:asciiname":"Mabical",
    "gn:country_code":"PH",
    "gn:dem":98,
    "gn:feature_class":"P",
    "gn:feature_code":"PPL",
    "gn:name":"Mabical",
    "gn:population":0,
    "gn:timezone":"Asia/Manila",
    "iso:country":"PH",
    "name:fil_x_preferred":[
        "Mabical"
    ],
    "wof:name":"Mabical",
    "wof:placetype":"locality"
},
  "geometry": {"coordinates":[123.7526,12.4492],"type":"Point"}
}