{
  "type": "Feature",
  "properties": {
    "gn:gn_country":"PH",
    "gn:gn_fcode":"PPL",
    "gn:gn_pop":2613,
    "gn:population":2613,
    "iso:country":"PH",
    "name:fil_x_preferred":[
        "Maugat"
    ],
    "qs_pg:aaroncc":"PH",
    "qs_pg:gn_country":"PH",
    "qs_pg:gn_fcode":"PPL",
    "qs_pg:gn_pop":2613,
    "qs_pg:name":"Maugat West",
    "qs_pg:photos_9r":0,
    "qs_pg:photos_sr":0,
    "qs_pg:pop_sr":4,
    "qs_pg:qs_pg_placetype":"locality",
    "wof:name":"Maugat West",
    "wof:placetype":"locality",
    "wof:population":2613
},
  "geometry": {"coordinates":[121.28276,13.8613],"type":"Point"}
}