{
  "type": "Feature",
  "properties": {
    "gn:admin1_code":"03",
    "gn:admin2_code":"63",
    "gn:admin3_code":"36915000.0",
    "gn:asciiname":"Calipayan",
    "gn:country_code":"PH",
    "gn:dem":86,
    "gn:feature_class":"P",
    "gn:feature_code":"PPL",
    "gn:name":"Calipayan",
    "gn:population":0,
    "gn:timezone":"Asia/Manila",
    "iso:country":"PH",
    "name:fil_x_preferred":[
        "Calipayan"
    ],
    "name:und_x_variant":[
        "San Pedro-Calipayan"
    ],
    "wof:name":"Calipayan",
    "wof:placetype":"locality"
},
  "geometry": {"coordinates":[120.42449999999999,15.54408],"type":"Point"}
}