{
  "type": "Feature",
  "properties": {
    "gn:admin1_code":"02",
    "gn:admin2_code":"31",
    "gn:admin3_code":"23110000.0",
    "gn:asciiname":"Digollorin",
    "gn:country_code":"PH",
    "gn:dem":11,
    "gn:feature_class":"P",
    "gn:feature_code":"PPL",
    "gn:name":"Digollorin",
    "gn:population":0,
    "gn:timezone":"Asia/Manila",
    "iso:country":"PH",
    "name:fil_x_preferred":[
        "Digollorin"
    ],
    "wof:name":"Digollorin",
    "wof:placetype":"locality"
},
  "geometry": {"coordinates":[122.43074,16.83335],"type":"Point"}
}