{
  "type": "Feature",
  "properties": {
    "gn:admin1_code":"06",
    "gn:admin2_code":"H3",
    "gn:admin3_code":"64516000.0",
    "gn:asciiname":"Hacienda Palhi",
    "gn:country_code":"PH",
    "gn:dem":42,
    "gn:feature_class":"P",
    "gn:feature_code":"PPL",
    "gn:name":"Hacienda Palhi",
    "gn:population":0,
    "gn:timezone":"Asia/Manila",
    "iso:country":"PH",
    "name:fil_x_preferred":[
        "Hacienda Palhi"
    ],
    "wof:name":"Hacienda Palhi",
    "wof:placetype":"locality"
},
  "geometry": {"coordinates":[122.94240000000001,10.4197],"type":"Point"}
}