{
  "type": "Feature",
  "properties": {
    "gn:admin1_code":"02",
    "gn:admin2_code":"48",
    "gn:admin3_code":"25013000.0",
    "gn:asciiname":"Quezon",
    "gn:country_code":"PH",
    "gn:dem":262,
    "gn:feature_class":"P",
    "gn:feature_code":"PPL",
    "gn:name":"Quezon",
    "gn:population":0,
    "gn:timezone":"Asia/Manila",
    "iso:country":"PH",
    "name:fil_x_preferred":[
        "Quezon"
    ],
    "wof:name":"Quezon",
    "wof:placetype":"locality"
},
  "geometry": {"coordinates":[121.17494000000001,16.51488],"type":"Point"}
}