{
  "type": "Feature",
  "properties": {
    "gn:admin1_code":"40",
    "gn:admin2_code":"09",
    "gn:admin3_code":"41032000.0",
    "gn:asciiname":"San Marcelino",
    "gn:country_code":"PH",
    "gn:dem":179,
    "gn:feature_class":"P",
    "gn:feature_code":"PPL",
    "gn:name":"San Marcelino",
    "gn:population":0,
    "gn:timezone":"Asia/Manila",
    "iso:country":"PH",
    "name:bcl_x_preferred":[
        "San Marcelino"
    ],
    "name:ceb_x_preferred":[
        "San Marcelino"
    ],
    "name:deu_x_preferred":[
        "San Marcelino"
    ],
    "name:fil_x_preferred":[
        "San Marcelino"
    ],
    "name:fra_x_preferred":[
        "San Marcelino"
    ],
    "name:ilo_x_preferred":[
        "San Marcelino"
    ],
    "name:ind_x_preferred":[
        "San Marcelino"
    ],
    "name:ita_x_preferred":[
        "San Marcelino"
    ],
    "name:msa_x_preferred":[
        "San Marcelino"
    ],
    "name:nld_x_preferred":[
        "San Marcelino"
    ],
    "name:pag_x_preferred":[
        "San Marcelino"
    ],
    "name:pam_x_preferred":[
        "San Marcelino"
    ],
    "name:spa_x_preferred":[
        "San Marcelino"
    ],
    "name:swe_x_preferred":[
        "San Marcelino"
    ],
    "name:tgl_x_preferred":[
        "San Marcelino"
    ],
    "name:vie_x_preferred":[
        "San Marcelino"
    ],
    "name:war_x_preferred":[
        "San Marcelino"
    ],
    "wof:name":"San Marcelino",
    "wof:placetype":"locality"
},
  "geometry": {"coordinates":[121.2294,13.7531],"type":"Point"}
}