{
  "type": "Feature",
  "properties": {
    "gn:admin1_code":"40",
    "gn:admin2_code":"53",
    "gn:admin3_code":"45806000.0",
    "gn:asciiname":"Calubacan",
    "gn:country_code":"PH",
    "gn:dem":25,
    "gn:feature_class":"P",
    "gn:feature_code":"PPL",
    "gn:name":"Calubacan",
    "gn:population":0,
    "gn:timezone":"Asia/Manila",
    "iso:country":"PH",
    "name:fil_x_preferred":[
        "Calubacan"
    ],
    "wof:name":"Calubacan",
    "wof:placetype":"locality"
},
  "geometry": {"coordinates":[121.2349,14.3955],"type":"Point"}
}