{
  "type": "Feature",
  "properties": {
    "gn:admin1_code":"05",
    "gn:admin2_code":"58",
    "gn:asciiname":"Sipak",
    "gn:country_code":"PH",
    "gn:dem":1,
    "gn:feature_class":"P",
    "gn:feature_code":"PPL",
    "gn:name":"Sipak",
    "gn:population":0,
    "gn:timezone":"Asia/Manila",
    "iso:country":"PH",
    "name:fil_x_preferred":[
        "Sipak"
    ],
    "wof:name":"Sipak",
    "wof:placetype":"locality"
},
  "geometry": {"coordinates":[124.01667,12.96667],"type":"Point"}
}