{
  "type": "Feature",
  "properties": {
    "gn:admin1_code":"14",
    "gn:admin2_code":"56",
    "gn:admin3_code":"153822000.0",
    "gn:asciiname":"Butabuaya",
    "gn:country_code":"PH",
    "gn:dem":12,
    "gn:feature_class":"P",
    "gn:feature_code":"PPL",
    "gn:name":"Butabuaya",
    "gn:population":0,
    "gn:timezone":"Asia/Manila",
    "iso:country":"PH",
    "name:fil_x_preferred":[
        "Butabuaya"
    ],
    "wof:name":"Butabuaya",
    "wof:placetype":"locality"
},
  "geometry": {"coordinates":[124.75694,7.05083],"type":"Point"}
}