{
  "type": "Feature",
  "properties": {
    "gn:admin1_code":"07",
    "gn:admin2_code":"46",
    "gn:admin3_code":"74602000.0",
    "gn:asciiname":"Pardo de Tavera",
    "gn:country_code":"PH",
    "gn:dem":189,
    "gn:feature_class":"P",
    "gn:feature_code":"PPL",
    "gn:name":"Pardo de Tavera",
    "gn:population":0,
    "gn:timezone":"Asia/Manila",
    "iso:country":"PH",
    "name:fil_x_preferred":[
        "Pardo de Tavera"
    ],
    "wof:name":"Pardo de Tavera",
    "wof:placetype":"locality"
},
  "geometry": {"coordinates":[123.1168,9.8342],"type":"Point"}
}