{
  "type": "Feature",
  "properties": {
    "gn:admin1_code":"40",
    "gn:admin2_code":"09",
    "gn:admin3_code":"41012000.0",
    "gn:asciiname":"Talaga",
    "gn:country_code":"PH",
    "gn:dem":311,
    "gn:feature_class":"P",
    "gn:feature_code":"PPL",
    "gn:name":"Talaga",
    "gn:population":0,
    "gn:timezone":"Asia/Manila",
    "iso:country":"PH",
    "name:fil_x_preferred":[
        "Talaga"
    ],
    "wof:name":"Talaga",
    "wof:placetype":"locality"
},
  "geometry": {"coordinates":[120.87098,13.99184],"type":"Point"}
}