{
  "type": "Feature",
  "properties": {
    "gn:admin1_code":"14",
    "gn:admin2_code":"60",
    "gn:admin3_code":"156604000.0",
    "gn:asciiname":"Gantang",
    "gn:country_code":"PH",
    "gn:dem":59,
    "gn:feature_class":"P",
    "gn:feature_code":"PPL",
    "gn:name":"Gantang",
    "gn:population":0,
    "gn:timezone":"Asia/Manila",
    "iso:country":"PH",
    "name:eng_x_preferred":[
        "Gantang"
    ],
    "wof:name":"Gantang",
    "wof:placetype":"locality"
},
  "geometry": {"coordinates":[121.33428000000001,5.94628],"type":"Point"}
}