{
  "type": "Feature",
  "properties": {
    "gn:admin1_code":"01",
    "gn:admin2_code":"29",
    "gn:admin3_code":"12913000.0",
    "gn:asciiname":"Malamsit",
    "gn:country_code":"PH",
    "gn:dem":24,
    "gn:feature_class":"P",
    "gn:feature_code":"PPL",
    "gn:name":"Malamsit",
    "gn:population":0,
    "gn:timezone":"Asia/Manila",
    "iso:country":"PH",
    "name:fil_x_preferred":[
        "Malamsit"
    ],
    "wof:name":"Malamsit",
    "wof:placetype":"locality"
},
  "geometry": {"coordinates":[120.5254,17.4369],"type":"Point"}
}