{
  "type": "Feature",
  "properties": {
    "gn:admin1_code":"07",
    "gn:admin2_code":"21",
    "gn:admin3_code":"72252000.0",
    "gn:asciiname":"Katongkolan",
    "gn:country_code":"PH",
    "gn:dem":13,
    "gn:feature_class":"P",
    "gn:feature_code":"PPL",
    "gn:name":"Katongkolan",
    "gn:population":0,
    "gn:timezone":"Asia/Manila",
    "iso:country":"PH",
    "name:fil_x_preferred":[
        "Katongkolan"
    ],
    "wof:name":"Katongkolan",
    "wof:placetype":"locality"
},
  "geometry": {"coordinates":[123.8079,10.7035],"type":"Point"}
}