{
  "type": "Feature",
  "properties": {
    "gn:admin1_code":"03",
    "gn:admin2_code":"G8",
    "gn:asciiname":"Dauilican",
    "gn:country_code":"PH",
    "gn:dem":9,
    "gn:feature_class":"P",
    "gn:feature_code":"PPL",
    "gn:name":"Dauilican",
    "gn:population":0,
    "gn:timezone":"Asia/Manila",
    "iso:country":"PH",
    "name:fil_x_preferred":[
        "Dauilican"
    ],
    "wof:name":"Dauilican",
    "wof:placetype":"locality"
},
  "geometry": {"coordinates":[122.23333,16.48333],"type":"Point"}
}