{
  "type": "Feature",
  "properties": {
    "gn:admin1_code":"06",
    "gn:admin2_code":"06",
    "gn:admin3_code":"60612000.0",
    "gn:asciiname":"Caritan",
    "gn:country_code":"PH",
    "gn:dem":9,
    "gn:feature_class":"P",
    "gn:feature_code":"PPL",
    "gn:name":"Caritan",
    "gn:population":0,
    "gn:timezone":"Asia/Manila",
    "iso:country":"PH",
    "name:fil_x_preferred":[
        "Carit-an"
    ],
    "wof:name":"Caritan",
    "wof:placetype":"locality"
},
  "geometry": {"coordinates":[122.0095,10.9588],"type":"Point"}
}