{
  "type": "Feature",
  "properties": {
    "gn:admin1_code":"15",
    "gn:admin2_code":"32",
    "gn:admin3_code":"143209000.0",
    "gn:asciiname":"Limos",
    "gn:country_code":"PH",
    "gn:dem":308,
    "gn:feature_class":"P",
    "gn:feature_code":"PPL",
    "gn:name":"Limos",
    "gn:population":0,
    "gn:timezone":"Asia/Manila",
    "iso:country":"PH",
    "name:bre_x_preferred":[
        "Limos"
    ],
    "name:cat_x_preferred":[
        "Limos"
    ],
    "name:deu_x_preferred":[
        "Limos"
    ],
    "name:fil_x_preferred":[
        "Limos"
    ],
    "name:fra_x_preferred":[
        "Limos"
    ],
    "name:ita_x_preferred":[
        "Lim\u00f3s"
    ],
    "name:lit_x_preferred":[
        "Aetonas"
    ],
    "name:pol_x_preferred":[
        "Limos"
    ],
    "name:por_x_preferred":[
        "Limos"
    ],
    "name:spa_x_preferred":[
        "Limos"
    ],
    "wof:name":"Limos",
    "wof:placetype":"locality"
},
  "geometry": {"coordinates":[121.29225,17.50042],"type":"Point"}
}