{
  "type": "Feature",
  "properties": {
    "gn:country":"PH",
    "gn:fcode":"ADM3",
    "gn:pop":33197,
    "iso:country":"PH",
    "name:ceb_x_preferred":[
        "Oras"
    ],
    "name:deu_x_preferred":[
        "Oras"
    ],
    "name:fil_x_preferred":[
        "Oras"
    ],
    "name:fin_x_preferred":[
        "Oras"
    ],
    "name:swe_x_preferred":[
        "Oras"
    ],
    "name:tgl_x_preferred":[
        "Oras"
    ],
    "name:war_x_preferred":[
        "Oras"
    ],
    "qs:name":"Oras",
    "qs:photos_9r":0,
    "qs:photos_sr":0,
    "qs:pop_sr":"7",
    "wd:wordcount":65,
    "wof:name":"Oras",
    "wof:placetype":"localadmin",
    "wof:population":33197
},
  "geometry": {"coordinates":[125.40000000000001,12.15],"type":"Point"}
}