{
  "type": "Feature",
  "properties": {
    "gn:admin1_code":"03",
    "gn:admin2_code":"47",
    "gn:admin3_code":"34925000.0",
    "gn:asciiname":"Calaba",
    "gn:country_code":"PH",
    "gn:dem":23,
    "gn:feature_class":"P",
    "gn:feature_code":"PPL",
    "gn:name":"Calaba",
    "gn:population":4229,
    "gn:timezone":"Asia/Manila",
    "iso:country":"PH",
    "name:fil_x_preferred":[
        "Calaba"
    ],
    "wof:name":"Calaba",
    "wof:placetype":"locality",
    "wof:population":4229
},
  "geometry": {"coordinates":[120.87423,15.3005],"type":"Point"}
}