{
  "type": "Feature",
  "properties": {
    "gn:admin1_code":"06",
    "gn:admin2_code":"H3",
    "gn:admin3_code":"64510000.0",
    "gn:asciiname":"Unce",
    "gn:country_code":"PH",
    "gn:dem":21,
    "gn:feature_class":"P",
    "gn:feature_code":"PPL",
    "gn:name":"Unce",
    "gn:population":0,
    "gn:timezone":"Asia/Manila",
    "iso:country":"PH",
    "name:fil_x_preferred":[
        "Unce"
    ],
    "wof:name":"Unce",
    "wof:placetype":"locality"
},
  "geometry": {"coordinates":[122.8593,10.0405],"type":"Point"}
}