{
  "type": "Feature",
  "properties": {
    "gn:gn_country":"PH",
    "gn:gn_fcode":"PPL",
    "gn:gn_pop":2713,
    "gn:population":2713,
    "iso:country":"PH",
    "name:fil_x_preferred":[
        "Calaya"
    ],
    "qs_pg:aaroncc":"PH",
    "qs_pg:gn_country":"PH",
    "qs_pg:gn_fcode":"PPL",
    "qs_pg:gn_pop":2713,
    "qs_pg:name":"Calaya",
    "qs_pg:photos_9r":0,
    "qs_pg:photos_sr":0,
    "qs_pg:pop_sr":4,
    "qs_pg:qs_pg_placetype":"locality",
    "wof:name":"Calaya",
    "wof:placetype":"locality",
    "wof:population":2713
},
  "geometry": {"coordinates":[122.6255,10.4916],"type":"Point"}
}