{
  "type": "Feature",
  "properties": {
    "gn:admin1_code":"41",
    "gn:admin2_code":"38",
    "gn:admin3_code":"174006000.0",
    "gn:asciiname":"Danao",
    "gn:country_code":"PH",
    "gn:dem":326,
    "gn:feature_class":"P",
    "gn:feature_code":"PPL",
    "gn:name":"Danao",
    "gn:population":0,
    "gn:timezone":"Asia/Manila",
    "iso:country":"PH",
    "name:ceb_x_preferred":[
        "Danao"
    ],
    "name:ell_x_preferred":[
        "\u0394\u03b1\u03bd\u03b1\u03cc\u03c2"
    ],
    "name:fil_x_preferred":[
        "Danao"
    ],
    "name:fra_x_preferred":[
        "Danao"
    ],
    "name:ita_x_preferred":[
        "Danao"
    ],
    "name:msa_x_preferred":[
        "Danao"
    ],
    "name:nld_x_preferred":[
        "Danao"
    ],
    "name:spa_x_preferred":[
        "Danao"
    ],
    "name:war_x_preferred":[
        "Danao"
    ],
    "wof:name":"Danao",
    "wof:placetype":"locality"
},
  "geometry": {"coordinates":[122.0098,13.286],"type":"Point"}
}