{
  "type": "Feature",
  "properties": {
    "gn:admin1_code":"10",
    "gn:admin2_code":"12",
    "gn:admin3_code":"101312000.0",
    "gn:asciiname":"Langasihan",
    "gn:country_code":"PH",
    "gn:dem":441,
    "gn:feature_class":"P",
    "gn:feature_code":"PPL",
    "gn:name":"Langasihan",
    "gn:population":0,
    "gn:timezone":"Asia/Manila",
    "iso:country":"PH",
    "name:fil_x_preferred":[
        "Langasihan"
    ],
    "wof:name":"Langasihan",
    "wof:placetype":"locality"
},
  "geometry": {"coordinates":[125.21361,8.03417],"type":"Point"}
}