{
  "type": "Feature",
  "properties": {
    "gn:admin1_code":"08",
    "gn:admin2_code":"37",
    "gn:admin3_code":"83701000.0",
    "gn:asciiname":"Odiongan",
    "gn:country_code":"PH",
    "gn:dem":10,
    "gn:feature_class":"P",
    "gn:feature_code":"PPL",
    "gn:name":"Odiongan",
    "gn:population":0,
    "gn:timezone":"Asia/Manila",
    "iso:country":"PH",
    "name:bcl_x_preferred":[
        "Odiongan"
    ],
    "name:ceb_x_preferred":[
        "Odiongan"
    ],
    "name:deu_x_preferred":[
        "Odiongan"
    ],
    "name:fil_x_preferred":[
        "Odiongan"
    ],
    "name:fra_x_preferred":[
        "Odiongan"
    ],
    "name:ilo_x_preferred":[
        "Odiongan"
    ],
    "name:ind_x_preferred":[
        "Odiongan"
    ],
    "name:ita_x_preferred":[
        "Odiongan"
    ],
    "name:nld_x_preferred":[
        "Odiongan"
    ],
    "name:pag_x_preferred":[
        "Odiongan"
    ],
    "name:pam_x_preferred":[
        "Odiongan"
    ],
    "name:swe_x_preferred":[
        "Odiongan"
    ],
    "name:tgl_x_preferred":[
        "Odiongan"
    ],
    "name:vie_x_preferred":[
        "Odiongan"
    ],
    "name:war_x_preferred":[
        "Odiongan"
    ],
    "wof:name":"Odiongan",
    "wof:placetype":"locality"
},
  "geometry": {"coordinates":[124.985,10.6935],"type":"Point"}
}