{
  "type": "Feature",
  "properties": {
    "gn:admin1_code":"40",
    "gn:admin2_code":"20",
    "gn:admin3_code":"42123000.0",
    "gn:asciiname":"A. Olaes",
    "gn:country_code":"PH",
    "gn:dem":96,
    "gn:feature_class":"P",
    "gn:feature_code":"PPL",
    "gn:name":"A. Olaes",
    "gn:population":0,
    "gn:timezone":"Asia/Manila",
    "iso:country":"PH",
    "name:fil_x_preferred":[
        "A. Olaes"
    ],
    "wof:name":"A. Olaes",
    "wof:placetype":"locality"
},
  "geometry": {"coordinates":[121.01879,14.32166],"type":"Point"}
}