{
  "type": "Feature",
  "properties": {
    "gn:country":"PH",
    "gn:fcode":"PPL",
    "gn:population":2297,
    "iso:country":"PH",
    "name:fil_x_preferred":[
        "Camaley"
    ],
    "qs:name":"Camaley",
    "qs:photos_9r":0,
    "qs:photos_sr":0,
    "qs:pop_sr":"4",
    "wof:name":"Camaley",
    "wof:placetype":"locality",
    "wof:population":2297
},
  "geometry": {"coordinates":[120.30107,15.99724],"type":"Point"}
}