{
  "type": "Feature",
  "properties": {
    "gn:admin1_code":"03",
    "gn:admin2_code":"13",
    "gn:admin3_code":"31415000.0",
    "gn:asciiname":"Masagana",
    "gn:country_code":"PH",
    "gn:dem":18,
    "gn:feature_class":"P",
    "gn:feature_code":"PPL",
    "gn:name":"Masagana",
    "gn:population":0,
    "gn:timezone":"Asia/Manila",
    "iso:country":"PH",
    "wof:name":"Masagana",
    "wof:placetype":"locality"
},
  "geometry": {"coordinates":[120.92938999999998,14.88488],"type":"Point"}
}