{
  "type": "Feature",
  "properties": {
    "gn:admin1_code":"02",
    "gn:admin2_code":"48",
    "gn:admin3_code":"25010000.0",
    "gn:asciiname":"Banet",
    "gn:country_code":"PH",
    "gn:dem":758,
    "gn:feature_class":"P",
    "gn:feature_code":"PPL",
    "gn:name":"Banet",
    "gn:population":0,
    "gn:timezone":"Asia/Manila",
    "iso:country":"PH",
    "name:fil_x_preferred":[
        "Banet"
    ],
    "wof:name":"Banet",
    "wof:placetype":"locality"
},
  "geometry": {"coordinates":[120.86667,16.26667],"type":"Point"}
}