{
  "type": "Feature",
  "properties": {
    "gn:admin1_code":"01",
    "gn:admin2_code":"28",
    "gn:admin3_code":"12823000.0",
    "gn:asciiname":"Cabayo",
    "gn:country_code":"PH",
    "gn:dem":102,
    "gn:feature_class":"P",
    "gn:feature_code":"PPL",
    "gn:name":"Cabayo",
    "gn:population":0,
    "gn:timezone":"Asia/Manila",
    "iso:country":"PH",
    "name:fil_x_preferred":[
        "Cabayo"
    ],
    "wof:name":"Cabayo",
    "wof:placetype":"locality"
},
  "geometry": {"coordinates":[120.75257000000001,18.39474],"type":"Point"}
}