{
  "type": "Feature",
  "properties": {
    "gn:admin1_code":"06",
    "gn:admin2_code":"30",
    "gn:admin3_code":"63028000.0",
    "gn:asciiname":"Lonoc-Binolbog",
    "gn:country_code":"PH",
    "gn:dem":93,
    "gn:feature_class":"P",
    "gn:feature_code":"PPL",
    "gn:name":"Lonoc-Binolbog",
    "gn:population":0,
    "gn:timezone":"Asia/Manila",
    "iso:country":"PH",
    "name:fil_x_preferred":[
        "Lonoc-Binolbog"
    ],
    "name:und_x_variant":[
        "Binolbog",
        "Lonoc"
    ],
    "wof:name":"Lonoc-Binolbog",
    "wof:placetype":"locality"
},
  "geometry": {"coordinates":[122.34999999999999,10.76945],"type":"Point"}
}