{
  "type": "Feature",
  "properties": {
    "gn:admin1_code":"08",
    "gn:admin2_code":"55",
    "gn:admin3_code":"86003000.0",
    "gn:asciiname":"Pagsannag",
    "gn:country_code":"PH",
    "gn:dem":8,
    "gn:feature_class":"P",
    "gn:feature_code":"PPL",
    "gn:name":"Pagsannag",
    "gn:population":0,
    "gn:timezone":"Asia/Manila",
    "iso:country":"PH",
    "name:fil_x_preferred":[
        "Pagsannag"
    ],
    "name:fil_x_variant":[
        "Pagsangan"
    ],
    "wof:name":"Pagsannag",
    "wof:placetype":"locality"
},
  "geometry": {"coordinates":[124.53279999999999,12.1429],"type":"Point"}
}