{
  "type": "Feature",
  "properties": {
    "gn:admin1_code":"06",
    "gn:admin2_code":"J3",
    "gn:admin3_code":"67902000.0",
    "gn:asciiname":"Barospos",
    "gn:country_code":"PH",
    "gn:dem":89,
    "gn:feature_class":"P",
    "gn:feature_code":"PPL",
    "gn:name":"Barospos",
    "gn:population":0,
    "gn:timezone":"Asia/Manila",
    "iso:country":"PH",
    "name:fil_x_preferred":[
        "Barospos"
    ],
    "wof:name":"Barospos",
    "wof:placetype":"locality"
},
  "geometry": {"coordinates":[122.5774,10.61956],"type":"Point"}
}