{
  "type": "Feature",
  "properties": {
    "gn:admin1_code":"15",
    "gn:admin2_code":"27",
    "gn:admin3_code":"142701000.0",
    "gn:asciiname":"Hucbong",
    "gn:country_code":"PH",
    "gn:dem":664,
    "gn:feature_class":"P",
    "gn:feature_code":"PPL",
    "gn:name":"Hucbong",
    "gn:population":0,
    "gn:timezone":"Asia/Manila",
    "iso:country":"PH",
    "name:fil_x_preferred":[
        "Hucbong"
    ],
    "wof:name":"Hucbong",
    "wof:placetype":"locality"
},
  "geometry": {"coordinates":[121.18384,16.87236],"type":"Point"}
}