{
  "type": "Feature",
  "properties": {
    "gn:admin1_code":"40",
    "gn:admin2_code":"H2",
    "gn:admin3_code":"45632000.0",
    "gn:asciiname":"Casuguran",
    "gn:country_code":"PH",
    "gn:dem":9,
    "gn:feature_class":"P",
    "gn:feature_code":"PPL",
    "gn:name":"Casuguran",
    "gn:population":0,
    "gn:timezone":"Asia/Manila",
    "iso:country":"PH",
    "name:fil_x_preferred":[
        "Casuguran"
    ],
    "wof:name":"Casuguran",
    "wof:placetype":"locality"
},
  "geometry": {"coordinates":[122.20269999999999,14.8002],"type":"Point"}
}