{
  "type": "Feature",
  "properties": {
    "gn:admin1_code":"40",
    "gn:admin2_code":"H2",
    "gn:admin3_code":"45648000.0",
    "gn:asciiname":"Bukal",
    "gn:country_code":"PH",
    "gn:dem":86,
    "gn:feature_class":"P",
    "gn:feature_code":"PPL",
    "gn:name":"Bukal",
    "gn:population":0,
    "gn:timezone":"Asia/Manila",
    "iso:country":"PH",
    "name:ceb_x_preferred":[
        "Bukal"
    ],
    "name:fil_x_preferred":[
        "Bukal"
    ],
    "wof:name":"Bukal",
    "wof:placetype":"locality"
},
  "geometry": {"coordinates":[121.28198999999999,13.92906],"type":"Point"}
}