{
  "type": "Feature",
  "properties": {
    "gn:country":"PH",
    "gn:fcode":"PPLA3",
    "gn:pop":24276,
    "iso:country":"PH",
    "name:bcl_x_preferred":[
        "Calasiao"
    ],
    "name:cat_x_preferred":[
        "Calasiao"
    ],
    "name:ceb_x_preferred":[
        "Calasiao"
    ],
    "name:deu_x_preferred":[
        "Calasiao"
    ],
    "name:eng_x_preferred":[
        "Calasiao"
    ],
    "name:fil_x_preferred":[
        "Calasiao"
    ],
    "name:fil_x_variant":[
        "Colasiao"
    ],
    "name:fra_x_preferred":[
        "Calasiao"
    ],
    "name:ilo_x_preferred":[
        "Calasiao"
    ],
    "name:ind_x_preferred":[
        "Calasiao"
    ],
    "name:ita_x_preferred":[
        "Calasiao"
    ],
    "name:msa_x_preferred":[
        "Calasiao"
    ],
    "name:nld_x_preferred":[
        "Calasiao"
    ],
    "name:oci_x_preferred":[
        "Calasiao"
    ],
    "name:pag_x_preferred":[
        "Calasiao"
    ],
    "name:pam_x_preferred":[
        "Calasiao"
    ],
    "name:spa_x_preferred":[
        "Calasiao"
    ],
    "name:swe_x_preferred":[
        "Calasiao"
    ],
    "name:tgl_x_preferred":[
        "Calasiao"
    ],
    "name:unk_x_variant":[
        "Colasiao"
    ],
    "name:vie_x_preferred":[
        "Calasiao"
    ],
    "name:war_x_preferred":[
        "Calasiao"
    ],
    "qs:gn_pop":0,
    "qs:name":"Calasiao",
    "qs:name_adm0":"Philippines",
    "qs:name_adm1":"Ilocos Region",
    "qs:photos":326,
    "qs:photos_1k":66,
    "qs:photos_9k":1,
    "qs:photos_9r":5,
    "qs:photos_all":326,
    "qs:photos_sr":5,
    "qs:placetype":"Town",
    "qs:pop_sr":"0",
    "qs:woe_adm0":23424934,
    "wof:name":"Calasiao",
    "wof:placetype":"locality",
    "wof:population":24276
},
  "geometry": {"coordinates":[120.36106100000001,16.010505],"type":"Point"}
}