{
  "type": "Feature",
  "properties": {
    "gn:admin1_code":"01",
    "gn:admin2_code":"28",
    "gn:admin3_code":"12820000.0",
    "gn:asciiname":"Bolo",
    "gn:country_code":"PH",
    "gn:dem":18,
    "gn:feature_class":"P",
    "gn:feature_code":"PPL",
    "gn:name":"Bolo",
    "gn:population":0,
    "gn:timezone":"Asia/Manila",
    "iso:country":"PH",
    "name:ceb_x_preferred":[
        "Bolo"
    ],
    "name:deu_x_preferred":[
        "Bolo"
    ],
    "name:fil_x_preferred":[
        "Bolo"
    ],
    "name:fra_x_preferred":[
        "Bolo"
    ],
    "name:glg_x_preferred":[
        "Bolo"
    ],
    "name:nld_x_preferred":[
        "Bolo"
    ],
    "name:pol_x_preferred":[
        "Bolo"
    ],
    "name:por_x_preferred":[
        "Bolo"
    ],
    "name:spa_x_preferred":[
        "Bolo"
    ],
    "name:swe_x_preferred":[
        "Bolo"
    ],
    "name:tgl_x_preferred":[
        "Bolo"
    ],
    "wof:name":"Bolo",
    "wof:placetype":"locality"
},
  "geometry": {"coordinates":[120.6207,18.1561],"type":"Point"}
}