{
  "type": "Feature",
  "properties": {
    "gn:admin1_code":"12",
    "gn:admin2_code":"M9",
    "gn:admin3_code":"128005000.0",
    "gn:asciiname":"Talukao",
    "gn:country_code":"PH",
    "gn:dem":7,
    "gn:feature_class":"P",
    "gn:feature_code":"PPL",
    "gn:name":"Talukao",
    "gn:population":0,
    "gn:timezone":"Asia/Manila",
    "iso:country":"PH",
    "name:fil_x_preferred":[
        "Talukao"
    ],
    "wof:name":"Talukao",
    "wof:placetype":"locality"
},
  "geometry": {"coordinates":[124.43944,6.07889],"type":"Point"}
}