{
  "type": "Feature",
  "properties": {
    "gn:admin1_code":"41",
    "gn:admin2_code":"49",
    "gn:admin3_code":"175317000.0",
    "gn:asciiname":"Panitian",
    "gn:country_code":"PH",
    "gn:dem":5,
    "gn:feature_class":"P",
    "gn:feature_code":"PPL",
    "gn:name":"Panitian",
    "gn:population":0,
    "gn:timezone":"Asia/Manila",
    "iso:country":"PH",
    "name:fil_x_preferred":[
        "Panitian"
    ],
    "wof:name":"Panitian",
    "wof:placetype":"locality"
},
  "geometry": {"coordinates":[117.92471999999999,9.2175],"type":"Point"}
}