{
  "type": "Feature",
  "properties": {
    "gn:admin1_code":"05",
    "gn:admin2_code":"39",
    "gn:admin3_code":"54116000.0",
    "gn:asciiname":"Manaay",
    "gn:country_code":"PH",
    "gn:dem":11,
    "gn:feature_class":"P",
    "gn:feature_code":"PPL",
    "gn:name":"Manaay",
    "gn:population":0,
    "gn:timezone":"Asia/Manila",
    "iso:country":"PH",
    "name:fil_x_preferred":[
        "Manaay"
    ],
    "wof:name":"Manaay",
    "wof:placetype":"locality"
},
  "geometry": {"coordinates":[124.05821,11.86787],"type":"Point"}
}