{
  "type": "Feature",
  "properties": {
    "gn:gn_country":"PH",
    "gn:gn_fcode":"PPL",
    "gn:gn_pop":3857,
    "gn:population":3857,
    "iso:country":"PH",
    "name:fil_x_preferred":[
        "Talomo"
    ],
    "qs_pg:aaroncc":"PH",
    "qs_pg:gn_country":"PH",
    "qs_pg:gn_fcode":"PPL",
    "qs_pg:gn_pop":3857,
    "qs_pg:name":"Talomo",
    "qs_pg:photos_9r":0,
    "qs_pg:photos_sr":0,
    "qs_pg:pop_sr":4,
    "qs_pg:qs_pg_placetype":"locality",
    "wof:name":"Talomo",
    "wof:placetype":"locality",
    "wof:population":3857
},
  "geometry": {"coordinates":[125.72278,7.52861],"type":"Point"}
}