{
  "type": "Feature",
  "properties": {
    "gn:admin1_code":"09",
    "gn:admin2_code":"66",
    "gn:admin3_code":"97328000.0",
    "gn:asciiname":"Bolinsong",
    "gn:cc2":"PH",
    "gn:country_code":"PH",
    "gn:dem":0,
    "gn:feature_class":"P",
    "gn:feature_code":"PPL",
    "gn:name":"Bolinsong",
    "gn:population":0,
    "gn:timezone":"Asia/Manila",
    "iso:country":"PH",
    "name:und_x_variant":[
        "Bolingsong",
        "Bolinsong"
    ],
    "wof:name":"Bolinsong",
    "wof:placetype":"locality"
},
  "geometry": {"coordinates":[123.63333,8.01667],"type":"Point"}
}