{
  "type": "Feature",
  "properties": {
    "gn:admin1_code":"03",
    "gn:admin2_code":"13",
    "gn:admin3_code":"31414000.0",
    "gn:asciiname":"Quibadia",
    "gn:country_code":"PH",
    "gn:dem":6,
    "gn:feature_class":"P",
    "gn:feature_code":"PPL",
    "gn:name":"Quibadia",
    "gn:population":0,
    "gn:timezone":"Asia/Manila",
    "iso:country":"PH",
    "name:fil_x_preferred":[
        "Quibadia"
    ],
    "name:fil_x_variant":[
        "Quibalita",
        "Quibadra"
    ],
    "name:und_x_variant":[
        "Quibadra",
        "Quibalita",
        "Quibadia"
    ],
    "wof:name":"Quibadia",
    "wof:placetype":"locality"
},
  "geometry": {"coordinates":[120.929,14.7204],"type":"Point"}
}