{
  "type": "Feature",
  "properties": {
    "iso:country":"PH",
    "name:ceb_x_preferred":[
        "Silanga"
    ],
    "name:fil_x_preferred":[
        "Silanga"
    ],
    "name:msa_x_preferred":[
        "Silanga"
    ],
    "name:nep_x_preferred":[
        "\u0938\u093f\u0932\u0902\u0917\u093e"
    ],
    "name:new_x_preferred":[
        "\u0938\u093f\u0932\u0919\u094d\u0917\u093e"
    ],
    "name:pol_x_preferred":[
        "Silanga"
    ],
    "qs:gn_country":"PH",
    "qs:gn_fcode":"PPL",
    "qs:gn_pop":2350,
    "qs:name":"Silanga",
    "qs:name_adm0":"Philippines",
    "qs:name_adm1":"Eastern Visayas",
    "qs:photos":0,
    "qs:photos_1k":0,
    "qs:photos_9k":0,
    "qs:photos_9r":0,
    "qs:photos_all":0,
    "qs:photos_sr":0,
    "qs:placetype":"Town",
    "qs:pop_sr":"4",
    "qs:woe_adm0":23424934,
    "wd:wordcount":50,
    "wof:name":"Silanga",
    "wof:placetype":"locality",
    "wof:population":2350
},
  "geometry": {"coordinates":[124.84305999999999,11.81806],"type":"Point"}
}