{
  "type": "Feature",
  "properties": {
    "gn:admin1_code":"06",
    "gn:admin2_code":"04",
    "gn:admin3_code":"60410000.0",
    "gn:asciiname":"Tigbawan",
    "gn:country_code":"PH",
    "gn:dem":52,
    "gn:feature_class":"P",
    "gn:feature_code":"PPL",
    "gn:name":"Tigbawan",
    "gn:population":0,
    "gn:timezone":"Asia/Manila",
    "iso:country":"PH",
    "name:fil_x_preferred":[
        "Tigbawan"
    ],
    "wof:name":"Tigbawan",
    "wof:placetype":"locality"
},
  "geometry": {"coordinates":[122.3019,11.5068],"type":"Point"}
}