{
  "type": "Feature",
  "properties": {
    "gn:country":"PH",
    "gn:fcode":"ADM3",
    "gn:population":24514,
    "iso:country":"PH",
    "name:ceb_x_preferred":[
        "Olutanga Island"
    ],
    "name:eng_x_preferred":[
        "Olutanga"
    ],
    "name:fil_x_preferred":[
        "Olutanga"
    ],
    "name:ilo_x_preferred":[
        "Olutanga"
    ],
    "name:mrj_x_preferred":[
        "\u041e\u043b\u0443\u0442\u0430\u043d\u0433\u0430"
    ],
    "name:nld_x_preferred":[
        "Olutanga Island"
    ],
    "name:spa_x_preferred":[
        "Olutanga"
    ],
    "qs:name":"Olutanga",
    "qs:photos_9r":0,
    "qs:photos_sr":0,
    "qs:pop_sr":"7",
    "wd:wordcount":137,
    "wof:name":"Olutanga",
    "wof:placetype":"localadmin",
    "wof:population":24514
},
  "geometry": {"coordinates":[122.84999999999999,7.33333],"type":"Point"}
}