{
  "type": "Feature",
  "properties": {
    "gn:admin1_code":"40",
    "gn:admin2_code":"H2",
    "gn:admin3_code":"45606000.0",
    "gn:asciiname":"Kabalanaunan",
    "gn:country_code":"PH",
    "gn:dem":1,
    "gn:feature_class":"P",
    "gn:feature_code":"PPL",
    "gn:name":"Kabalanaunan",
    "gn:population":0,
    "gn:timezone":"Asia/Manila",
    "iso:country":"PH",
    "name:fil_x_preferred":[
        "Cabungalunan"
    ],
    "wof:name":"Kabalanaunan",
    "wof:placetype":"locality"
},
  "geometry": {"coordinates":[121.99651,14.95226],"type":"Point"}
}