{
  "type": "Feature",
  "properties": {
    "gn:admin1_code":"01",
    "gn:admin2_code":"29",
    "gn:admin3_code":"12904000.0",
    "gn:asciiname":"Dirdirig",
    "gn:country_code":"PH",
    "gn:dem":26,
    "gn:feature_class":"P",
    "gn:feature_code":"PPL",
    "gn:name":"Dirdirig",
    "gn:population":0,
    "gn:timezone":"Asia/Manila",
    "iso:country":"PH",
    "name:fil_x_preferred":[
        "Dirdirig"
    ],
    "wof:name":"Dirdirig",
    "wof:placetype":"locality"
},
  "geometry": {"coordinates":[120.4967,17.3055],"type":"Point"}
}