{
  "type": "Feature",
  "properties": {
    "gn:admin1_code":"15",
    "gn:admin2_code":"32",
    "gn:admin3_code":"143209000.0",
    "gn:asciiname":"Agantan",
    "gn:country_code":"PH",
    "gn:dem":247,
    "gn:feature_class":"P",
    "gn:feature_code":"PPL",
    "gn:name":"Agantan",
    "gn:population":0,
    "gn:timezone":"Asia/Manila",
    "iso:country":"PH",
    "name:fil_x_preferred":[
        "Agantan"
    ],
    "name:fil_x_variant":[
        "Aganlan"
    ],
    "name:und_x_variant":[
        "Aganlan"
    ],
    "wof:name":"Agantan",
    "wof:placetype":"locality"
},
  "geometry": {"coordinates":[121.30934999999999,17.56442],"type":"Point"}
}