{
  "type": "Feature",
  "properties": {
    "gn:admin1_code":"15",
    "gn:admin2_code":"01",
    "gn:admin3_code":"140124000.0",
    "gn:asciiname":"Velasco",
    "gn:country_code":"PH",
    "gn:dem":85,
    "gn:feature_class":"P",
    "gn:feature_code":"PPL",
    "gn:name":"Velasco",
    "gn:population":0,
    "gn:timezone":"Asia/Manila",
    "iso:country":"PH",
    "name:fil_x_preferred":[
        "Velasco"
    ],
    "name:fra_x_preferred":[
        "Velasco"
    ],
    "name:rus_x_preferred":[
        "\u0412\u0435\u043b\u0430\u0441\u043a\u043e"
    ],
    "name:spa_x_preferred":[
        "Velasco"
    ],
    "wof:name":"Velasco",
    "wof:placetype":"locality"
},
  "geometry": {"coordinates":[120.67100000000001,17.5892],"type":"Point"}
}