{
  "type": "Feature",
  "properties": {
    "gn:admin1_code":"11",
    "gn:admin2_code":"P3",
    "gn:admin3_code":"118605000.0",
    "gn:asciiname":"Tukal",
    "gn:country_code":"PH",
    "gn:dem":43,
    "gn:feature_class":"P",
    "gn:feature_code":"PPL",
    "gn:name":"Tukal",
    "gn:population":0,
    "gn:timezone":"Asia/Manila",
    "iso:country":"PH",
    "name:fil_x_preferred":[
        "Tukal"
    ],
    "wof:name":"Tukal",
    "wof:placetype":"locality"
},
  "geometry": {"coordinates":[125.40639,5.42694],"type":"Point"}
}