{
  "type": "Feature",
  "properties": {
    "gn:admin1_code":"06",
    "gn:admin2_code":"30",
    "gn:admin3_code":"63025000.0",
    "gn:asciiname":"Caloyahan",
    "gn:country_code":"PH",
    "gn:dem":88,
    "gn:feature_class":"P",
    "gn:feature_code":"PPL",
    "gn:name":"Caloyahan",
    "gn:population":0,
    "gn:timezone":"Asia/Manila",
    "iso:country":"PH",
    "name:fil_x_preferred":[
        "Caloyahan"
    ],
    "wof:name":"Caloyahan",
    "wof:placetype":"locality"
},
  "geometry": {"coordinates":[122.48333,11.03333],"type":"Point"}
}