{
  "type": "Feature",
  "properties": {
    "gn:admin1_code":"06",
    "gn:admin2_code":"H3",
    "gn:admin3_code":"64511000.0",
    "gn:asciiname":"Santo Cawacawa",
    "gn:country_code":"PH",
    "gn:dem":90,
    "gn:feature_class":"P",
    "gn:feature_code":"PPL",
    "gn:name":"Santo Cawacawa",
    "gn:population":0,
    "gn:timezone":"Asia/Manila",
    "iso:country":"PH",
    "name:fil_x_preferred":[
        "Santo Cawacawa"
    ],
    "wof:name":"Santo Cawacawa",
    "wof:placetype":"locality"
},
  "geometry": {"coordinates":[122.94280000000001,10.2851],"type":"Point"}
}