{
  "type": "Feature",
  "properties": {
    "gn:admin1_code":"01",
    "gn:admin2_code":"29",
    "gn:admin3_code":"12930000.0",
    "gn:asciiname":"Supit",
    "gn:country_code":"PH",
    "gn:dem":21,
    "gn:feature_class":"P",
    "gn:feature_code":"PPL",
    "gn:name":"Supit",
    "gn:population":0,
    "gn:timezone":"Asia/Manila",
    "iso:country":"PH",
    "name:fil_x_preferred":[
        "Supit"
    ],
    "wof:name":"Supit",
    "wof:placetype":"locality"
},
  "geometry": {"coordinates":[120.48333,17.83333],"type":"Point"}
}