{
  "type": "Feature",
  "properties": {
    "gn:admin1_code":"NCR",
    "gn:admin2_code":"137400000",
    "gn:admin3_code":"137402000.0",
    "gn:asciiname":"Parang",
    "gn:country_code":"PH",
    "gn:dem":32,
    "gn:feature_class":"P",
    "gn:feature_code":"PPL",
    "gn:name":"Parang",
    "gn:population":0,
    "gn:timezone":"Asia/Manila",
    "iso:country":"PH",
    "name:deu_x_preferred":[
        "Parang"
    ],
    "name:nno_x_preferred":[
        "Parang"
    ],
    "name:por_x_preferred":[
        "Parang"
    ],
    "wof:name":"Parang",
    "wof:placetype":"locality"
},
  "geometry": {"coordinates":[121.12269999999999,14.6617],"type":"Point"}
}