{
  "type": "Feature",
  "properties": {
    "gn:admin1_code":"15",
    "gn:admin2_code":"10",
    "gn:admin3_code":"141104000.0",
    "gn:asciiname":"Bobok",
    "gn:country_code":"PH",
    "gn:dem":1372,
    "gn:feature_class":"P",
    "gn:feature_code":"PPL",
    "gn:name":"Bobok",
    "gn:population":0,
    "gn:timezone":"Asia/Manila",
    "iso:country":"PH",
    "name:ara_x_preferred":[
        "\u0628\u0648\u0628\u0648\u0643"
    ],
    "name:cat_x_preferred":[
        "Bobok"
    ],
    "name:cor_x_preferred":[
        "Bobok"
    ],
    "name:deu_x_preferred":[
        "Bobok"
    ],
    "name:eng_x_preferred":[
        "Bobok"
    ],
    "name:fra_x_preferred":[
        "Bobok"
    ],
    "name:ita_x_preferred":[
        "Bobok"
    ],
    "name:por_x_preferred":[
        "Bobok"
    ],
    "name:rus_x_preferred":[
        "\u0411\u043e\u0431\u043e\u043a"
    ],
    "name:spa_x_preferred":[
        "Bobok"
    ],
    "name:srp_x_preferred":[
        "\u0411\u043e\u0431\u0430\u0446"
    ],
    "name:tur_x_preferred":[
        "Bobok"
    ],
    "name:und_x_variant":[
        "Bubok"
    ],
    "wof:name":"Bobok",
    "wof:placetype":"locality"
},
  "geometry": {"coordinates":[120.83069999999999,16.4405],"type":"Point"}
}