{
  "type": "Feature",
  "properties": {
    "gn:admin1_code":"08",
    "gn:admin2_code":"67",
    "gn:admin3_code":"84821000.0",
    "gn:asciiname":"Sangputan",
    "gn:country_code":"PH",
    "gn:dem":42,
    "gn:feature_class":"P",
    "gn:feature_code":"PPL",
    "gn:name":"Sangputan",
    "gn:population":0,
    "gn:timezone":"Asia/Manila",
    "iso:country":"PH",
    "name:fil_x_preferred":[
        "Sangputan"
    ],
    "wof:name":"Sangputan",
    "wof:placetype":"locality"
},
  "geometry": {"coordinates":[124.07444,12.36611],"type":"Point"}
}