{
  "type": "Feature",
  "properties": {
    "gn:admin1_code":"03",
    "gn:admin2_code":"07",
    "gn:admin3_code":"30805000.0",
    "gn:asciiname":"Saba",
    "gn:country_code":"PH",
    "gn:dem":13,
    "gn:feature_class":"P",
    "gn:feature_code":"PPL",
    "gn:name":"Saba",
    "gn:population":0,
    "gn:timezone":"Asia/Manila",
    "iso:country":"PH",
    "name:eng_x_preferred":[
        "Saba"
    ],
    "wof:name":"Saba",
    "wof:placetype":"locality"
},
  "geometry": {"coordinates":[120.49797,14.86879],"type":"Point"}
}