{
  "type": "Feature",
  "properties": {
    "gn:admin1_code":"02",
    "gn:admin2_code":"31",
    "gn:admin3_code":"23112000.0",
    "gn:asciiname":"Caniging",
    "gn:country_code":"PH",
    "gn:dem":81,
    "gn:feature_class":"P",
    "gn:feature_code":"PPL",
    "gn:name":"Caniging",
    "gn:population":0,
    "gn:timezone":"Asia/Manila",
    "iso:country":"PH",
    "name:fil_x_preferred":[
        "Caniging"
    ],
    "wof:name":"Caniging",
    "wof:placetype":"locality"
},
  "geometry": {"coordinates":[121.70610000000001,16.6884],"type":"Point"}
}