{
  "type": "Feature",
  "properties": {
    "gn:admin1_code":"10",
    "gn:admin2_code":"34",
    "gn:admin3_code":"103516000.0",
    "gn:asciiname":"Linabu",
    "gn:country_code":"PH",
    "gn:dem":659,
    "gn:feature_class":"P",
    "gn:feature_code":"PPL",
    "gn:name":"Linabu",
    "gn:population":0,
    "gn:timezone":"Asia/Manila",
    "iso:country":"PH",
    "name:fil_x_preferred":[
        "Linabu"
    ],
    "wof:name":"Linabu",
    "wof:placetype":"locality"
},
  "geometry": {"coordinates":[124.18333,8.03333],"type":"Point"}
}