{
  "type": "Feature",
  "properties": {
    "gn:country":"PH",
    "gn:fcode":"PPLA3",
    "gn:population":3401,
    "iso:country":"PH",
    "name:bcl_x_preferred":[
        "San Miguel"
    ],
    "name:ceb_x_preferred":[
        "San Miguel"
    ],
    "name:deu_x_preferred":[
        "San Miguel"
    ],
    "name:eng_x_preferred":[
        "San Miguel"
    ],
    "name:fra_x_preferred":[
        "San Miguel"
    ],
    "name:ilo_x_preferred":[
        "San Miguel"
    ],
    "name:ind_x_preferred":[
        "San Miguel"
    ],
    "name:ita_x_preferred":[
        "San Miguel"
    ],
    "name:jpn_x_preferred":[
        "\u30b5\u30f3\u30fb\u30df\u30b2\u30eb"
    ],
    "name:nld_x_preferred":[
        "San Miguel"
    ],
    "name:pag_x_preferred":[
        "San Miguel"
    ],
    "name:pam_x_preferred":[
        "San Miguel"
    ],
    "name:swe_x_preferred":[
        "San Miguel"
    ],
    "name:tgl_x_preferred":[
        "San Miguel"
    ],
    "name:vie_x_preferred":[
        "San Miguel"
    ],
    "name:war_x_preferred":[
        "San Miguel"
    ],
    "qs:name":"San Miguel",
    "qs:photos_9r":0,
    "qs:photos_sr":0,
    "qs:pop_sr":"4",
    "wd:wordcount":976,
    "wof:name":"San Miguel",
    "wof:placetype":"locality",
    "wof:population":3401
},
  "geometry": {"coordinates":[124.8325,11.26722],"type":"Point"}
}