{
  "type": "Feature",
  "properties": {
    "gn:country":"PH",
    "gn:fcode":"PPLA3",
    "gn:population":3401,
    "iso:country":"PH",
    "name:bcl_x_preferred":[
        "San Miguel"
    ],
    "name:ceb_x_preferred":[
        "San Miguel"
    ],
    "name:deu_x_preferred":[
        "San Miguel"
    ],
    "name:eng_x_preferred":[
        "San Miguel"
    ],
    "name:fra_x_preferred":[
        "San Miguel"
    ],
    "name:ilo_x_preferred":[
        "San Miguel"
    ],
    "name:ind_x_preferred":[
        "San Miguel"
    ],
    "name:ita_x_preferred":[
        "San Miguel"
    ],
    "name:jpn_x_preferred":[
        "\u30b5\u30f3\u30df\u30b2\u30eb\u5ddd"
    ],
    "name:jpn_x_variant":[
        "\u30b5\u30f3\u30fb\u30df\u30b2\u30eb"
    ],
    "name:kor_x_preferred":[
        "\uc0b0 \ubbf8\uad6c\uc5d8"
    ],
    "name:nld_x_preferred":[
        "San Miguel"
    ],
    "name:pag_x_preferred":[
        "San Miguel"
    ],
    "name:pam_x_preferred":[
        "San Miguel"
    ],
    "name:pol_x_preferred":[
        "San Miguel"
    ],
    "name:por_x_preferred":[
        "San Miguel"
    ],
    "name:rus_x_preferred":[
        "\u0440\u0435\u043a\u0430 \u0420\u0438\u043e-\u0421\u0430\u043d-\u041c\u0438\u0433\u0435\u043b\u044c"
    ],
    "name:swe_x_preferred":[
        "R\u00edo San Miguel"
    ],
    "name:swe_x_variant":[
        "San Miguel"
    ],
    "name:tgl_x_preferred":[
        "San Miguel"
    ],
    "name:tur_x_preferred":[
        "San Miguel"
    ],
    "name:ukr_x_preferred":[
        "\u0421\u0430\u043d-\u041c\u0456\u0433\u0435\u043b\u044c"
    ],
    "name:urd_x_preferred":[
        "\u0633\u0627\u0646 \u0645\u06cc\u06af\u0648\u0626\u0644"
    ],
    "name:vie_x_preferred":[
        "S\u00f4ng San Miguel"
    ],
    "name:vie_x_variant":[
        "San Miguel"
    ],
    "name:war_x_preferred":[
        "San Miguel"
    ],
    "name:zho_cn_x_preferred":[
        "\u5723\u7c73\u683c\u5c14\u6cb3"
    ],
    "name:zho_tw_x_preferred":[
        "\u8056\u7c73\u683c\u723e\u6cb3"
    ],
    "qs:name":"San Miguel",
    "qs:photos_9r":0,
    "qs:photos_sr":0,
    "qs:pop_sr":"4",
    "wd:wordcount":976,
    "wof:name":"San Miguel",
    "wof:placetype":"locality",
    "wof:population":3401
},
  "geometry": {"coordinates":[124.8325,11.26722],"type":"Point"}
}