{
  "type": "Feature",
  "properties": {
    "gn:admin1_code":"03",
    "gn:admin2_code":"63",
    "gn:admin3_code":"36908000.0",
    "gn:asciiname":"Ambalingit",
    "gn:country_code":"PH",
    "gn:dem":42,
    "gn:feature_class":"P",
    "gn:feature_code":"PPL",
    "gn:name":"Ambalingit",
    "gn:population":0,
    "gn:timezone":"Asia/Manila",
    "iso:country":"PH",
    "name:fil_x_preferred":[
        "Ambalingit"
    ],
    "wof:name":"Ambalingit",
    "wof:placetype":"locality"
},
  "geometry": {"coordinates":[120.37287999999999,15.62672],"type":"Point"}
}