{
  "type": "Feature",
  "properties": {
    "iso:country":"PH",
    "name:bcl_x_preferred":[
        "Roxas"
    ],
    "name:cat_x_preferred":[
        "Roxas"
    ],
    "name:deu_x_preferred":[
        "Roxas"
    ],
    "name:eng_x_preferred":[
        "Roxas"
    ],
    "name:fas_x_preferred":[
        "\u0631\u0648\u06a9\u0633\u0627\u0633"
    ],
    "name:fin_x_preferred":[
        "Roxas"
    ],
    "name:fra_x_preferred":[
        "Roxas"
    ],
    "name:ilo_x_preferred":[
        "Roxas"
    ],
    "name:ind_x_preferred":[
        "Roxas"
    ],
    "name:ita_x_preferred":[
        "Roxas"
    ],
    "name:nld_x_preferred":[
        "Roxas"
    ],
    "name:oci_x_preferred":[
        "Roxas"
    ],
    "name:pag_x_preferred":[
        "Roxas"
    ],
    "name:pam_x_preferred":[
        "Roxas"
    ],
    "name:spa_x_preferred":[
        "Roxas"
    ],
    "name:swe_x_preferred":[
        "Roxas"
    ],
    "name:tgl_x_preferred":[
        "Roxas"
    ],
    "name:vie_x_preferred":[
        "Roxas"
    ],
    "name:war_x_preferred":[
        "Roxas"
    ],
    "name:zho_x_preferred":[
        "\u6d1b\u514b\u85a9\u65af"
    ],
    "qs:gn_pop":0,
    "qs:name":"Roxas",
    "qs:name_adm0":"Philippines",
    "qs:name_adm1":"Western Visayas",
    "qs:photos":138,
    "qs:photos_1k":28,
    "qs:photos_9k":1,
    "qs:photos_9r":3,
    "qs:photos_all":138,
    "qs:photos_sr":3,
    "qs:placetype":"Town",
    "qs:pop_sr":"0",
    "qs:woe_adm0":23424934,
    "wd:wordcount":195,
    "wof:name":"Roxas",
    "wof:placetype":"locality"
},
  "geometry": {"coordinates":[119.373321,10.364905],"type":"Point"}
}