{
  "type": "Feature",
  "properties": {
    "gn:admin1_code":"07",
    "gn:admin2_code":"21",
    "gn:admin3_code":"72208000.0",
    "gn:asciiname":"Mambocayan",
    "gn:country_code":"PH",
    "gn:dem":18,
    "gn:feature_class":"P",
    "gn:feature_code":"PPL",
    "gn:name":"Mambocayan",
    "gn:population":0,
    "gn:timezone":"Asia/Manila",
    "iso:country":"PH",
    "name:fil_x_preferred":[
        "Mambocayan"
    ],
    "wof:name":"Mambocayan",
    "wof:placetype":"locality"
},
  "geometry": {"coordinates":[123.71639999999999,10.48846],"type":"Point"}
}