{
  "type": "Feature",
  "properties": {
    "gn:admin1_code":"09",
    "gn:admin2_code":"G7",
    "gn:asciiname":"Cocob",
    "gn:country_code":"PH",
    "gn:dem":-9999,
    "gn:feature_class":"P",
    "gn:feature_code":"PPL",
    "gn:name":"Cocob",
    "gn:population":0,
    "gn:timezone":"Asia/Manila",
    "iso:country":"PH",
    "wof:name":"Cocob",
    "wof:placetype":"locality"
},
  "geometry": {"coordinates":[122.29167,6.88972],"type":"Point"}
}