{
  "type": "Feature",
  "properties": {
    "gn:admin1_code":"06",
    "gn:admin2_code":"06",
    "gn:admin3_code":"60617000.0",
    "gn:asciiname":"Mamara",
    "gn:country_code":"PH",
    "gn:dem":253,
    "gn:feature_class":"P",
    "gn:feature_code":"PPL",
    "gn:name":"Mamara",
    "gn:population":0,
    "gn:timezone":"Asia/Manila",
    "iso:country":"PH",
    "name:ceb_x_preferred":[
        "Mamara"
    ],
    "name:eng_x_preferred":[
        "Mamara"
    ],
    "name:swe_x_preferred":[
        "Mamara"
    ],
    "wof:name":"Mamara",
    "wof:placetype":"locality"
},
  "geometry": {"coordinates":[122.09311,11.27782],"type":"Point"}
}