{
  "type": "Feature",
  "properties": {
    "gn:admin1_code":"14",
    "gn:admin2_code":"35",
    "gn:admin3_code":"153640000.0",
    "gn:asciiname":"Dicaporoan",
    "gn:country_code":"PH",
    "gn:dem":737,
    "gn:feature_class":"P",
    "gn:feature_code":"PPL",
    "gn:name":"Dicaporoan",
    "gn:population":0,
    "gn:timezone":"Asia/Manila",
    "iso:country":"PH",
    "name:fil_x_preferred":[
        "Dicaporoan"
    ],
    "wof:name":"Dicaporoan",
    "wof:placetype":"locality"
},
  "geometry": {"coordinates":[124.25722,7.71556],"type":"Point"}
}