{
  "type": "Feature",
  "properties": {
    "gn:admin1_code":"02",
    "gn:admin2_code":"31",
    "gn:admin3_code":"23112000.0",
    "gn:asciiname":"Pangal Norte",
    "gn:country_code":"PH",
    "gn:dem":93,
    "gn:feature_class":"P",
    "gn:feature_code":"PPL",
    "gn:name":"Pangal Norte",
    "gn:population":0,
    "gn:timezone":"Asia/Manila",
    "iso:country":"PH",
    "name:eng_x_preferred":[
        "Pangal North"
    ],
    "name:fil_x_preferred":[
        "Pengan"
    ],
    "wof:name":"Pangal Norte",
    "wof:placetype":"locality"
},
  "geometry": {"coordinates":[121.6776,16.60726],"type":"Point"}
}