{
  "type": "Feature",
  "properties": {
    "gn:admin1_code":"12",
    "gn:admin2_code":"71",
    "gn:admin3_code":"126508000.0",
    "gn:asciiname":"Torte",
    "gn:country_code":"PH",
    "gn:dem":17,
    "gn:feature_class":"P",
    "gn:feature_code":"PPL",
    "gn:name":"Torte",
    "gn:population":0,
    "gn:timezone":"Asia/Manila",
    "iso:country":"PH",
    "name:aze_x_preferred":[
        "Tort"
    ],
    "name:bak_x_preferred":[
        "\u0422\u043e\u0440\u0442"
    ],
    "name:bel_x_preferred":[
        "\u0422\u043e\u0440\u0442"
    ],
    "name:bos_x_preferred":[
        "Torta"
    ],
    "name:bul_x_preferred":[
        "\u0422\u043e\u0440\u0442\u0430"
    ],
    "name:ces_x_preferred":[
        "Dort"
    ],
    "name:cym_x_preferred":[
        "Torte"
    ],
    "name:dan_x_preferred":[
        "Lagkage"
    ],
    "name:deu_x_preferred":[
        "Torte"
    ],
    "name:epo_x_preferred":[
        "Torto"
    ],
    "name:fil_x_preferred":[
        "Torte"
    ],
    "name:heb_x_preferred":[
        "\u05d8\u05d5\u05e8\u05d8"
    ],
    "name:hrv_x_preferred":[
        "Torta"
    ],
    "name:hye_x_preferred":[
        "\u054f\u0578\u0580\u0569"
    ],
    "name:isl_x_preferred":[
        "Lagkaka"
    ],
    "name:ita_x_preferred":[
        "Torta"
    ],
    "name:jpn_x_preferred":[
        "\u30c8\u30eb\u30c6"
    ],
    "name:kaz_x_preferred":[
        "\u0422\u043e\u0440\u0442\u0442\u0430\u0440"
    ],
    "name:kor_x_preferred":[
        "\ud1a0\ub974\ud14c"
    ],
    "name:lav_x_preferred":[
        "Torte"
    ],
    "name:lit_x_preferred":[
        "Tortas"
    ],
    "name:mkd_x_preferred":[
        "\u0422\u043e\u0440\u0442\u0430"
    ],
    "name:mon_x_preferred":[
        "\u0425\u043e\u0442\u043e\u043b \u0431\u044f\u043b\u0443\u0443"
    ],
    "name:pol_x_preferred":[
        "Tort"
    ],
    "name:ron_x_preferred":[
        "Tort"
    ],
    "name:rus_x_preferred":[
        "\u0422\u043e\u0440\u0442"
    ],
    "name:slk_x_preferred":[
        "Torta"
    ],
    "name:srp_x_preferred":[
        "\u0422\u043e\u0440\u0442\u0430"
    ],
    "name:swe_x_preferred":[
        "T\u00e5rta"
    ],
    "name:ukr_x_preferred":[
        "\u0422\u043e\u0440\u0442"
    ],
    "wof:name":"Torte",
    "wof:placetype":"locality"
},
  "geometry": {"coordinates":[124.64917,6.84861],"type":"Point"}
}