{
  "type": "Feature",
  "properties": {
    "gn:admin1_code":"12",
    "gn:admin2_code":"71",
    "gn:admin3_code":"126508000.0",
    "gn:asciiname":"Torte",
    "gn:country_code":"PH",
    "gn:dem":17,
    "gn:feature_class":"P",
    "gn:feature_code":"PPL",
    "gn:name":"Torte",
    "gn:population":0,
    "gn:timezone":"Asia/Manila",
    "iso:country":"PH",
    "name:fil_x_preferred":[
        "Torte"
    ],
    "wof:name":"Torte",
    "wof:placetype":"locality"
},
  "geometry": {"coordinates":[124.64917,6.84861],"type":"Point"}
}