{
  "type": "Feature",
  "properties": {
    "gn:admin1_code":"03",
    "gn:admin2_code":"47",
    "gn:admin3_code":"34911000.0",
    "gn:asciiname":"San Casimiro",
    "gn:country_code":"PH",
    "gn:dem":37,
    "gn:feature_class":"P",
    "gn:feature_code":"PPL",
    "gn:name":"San Casimiro",
    "gn:population":0,
    "gn:timezone":"Asia/Manila",
    "iso:country":"PH",
    "name:lit_x_preferred":[
        "San Kasimiras"
    ],
    "name:por_x_preferred":[
        "San Casimiro"
    ],
    "name:zho_x_preferred":[
        "\u8056\u5361\u897f\u7c73\u7f85"
    ],
    "wof:name":"San Casimiro",
    "wof:placetype":"locality"
},
  "geometry": {"coordinates":[120.76667,15.65],"type":"Point"}
}