{
  "type": "Feature",
  "properties": {
    "gn:admin1_code":"08",
    "gn:admin2_code":"37",
    "gn:admin3_code":"83706000.0",
    "gn:asciiname":"Picas",
    "gn:cc2":"PH",
    "gn:country_code":"PH",
    "gn:dem":26,
    "gn:feature_class":"P",
    "gn:feature_code":"PPL",
    "gn:name":"Picas",
    "gn:population":0,
    "gn:timezone":"Asia/Manila",
    "iso:country":"PH",
    "name:und_x_variant":[
        "Pikas",
        "Picas"
    ],
    "wof:name":"Picas",
    "wof:placetype":"locality"
},
  "geometry": {"coordinates":[124.76416999999999,11.28694],"type":"Point"}
}