{
  "type": "Feature",
  "properties": {
    "gn:admin1_code":"40",
    "gn:admin2_code":"H2",
    "gn:admin3_code":"45606000.0",
    "gn:asciiname":"Tingtengon",
    "gn:country_code":"PH",
    "gn:dem":-9999,
    "gn:feature_class":"P",
    "gn:feature_code":"PPL",
    "gn:name":"Tingtengon",
    "gn:population":0,
    "gn:timezone":"Asia/Manila",
    "iso:country":"PH",
    "name:fil_x_preferred":[
        "Tingtengon"
    ],
    "wof:name":"Tingtengon",
    "wof:placetype":"locality"
},
  "geometry": {"coordinates":[122.01676999999999,14.92841],"type":"Point"}
}