{
  "type": "Feature",
  "properties": {
    "gn:country":"PH",
    "gn:fcode":"PPL",
    "gn:population":2116,
    "iso:country":"PH",
    "name:ceb_x_preferred":[
        "Valle Hermoso"
    ],
    "name:deu_x_preferred":[
        "Valle Hermoso"
    ],
    "name:fil_x_preferred":[
        "Valle Hermoso"
    ],
    "name:fra_x_preferred":[
        "Valle Hermoso"
    ],
    "name:ita_x_preferred":[
        "Valle Hermoso"
    ],
    "name:rus_x_preferred":[
        "\u0412\u0430\u043b\u044c\u0435-\u042d\u0440\u043c\u043e\u0441\u043e"
    ],
    "name:spa_x_preferred":[
        "Valle Hermoso"
    ],
    "name:swe_x_preferred":[
        "Valle Hermoso"
    ],
    "qs:name":"Valle Hermoso",
    "qs:photos_9r":0,
    "qs:photos_sr":0,
    "qs:pop_sr":"4",
    "wd:wordcount":24,
    "wof:name":"Valle Hermoso",
    "wof:placetype":"locality",
    "wof:population":2116
},
  "geometry": {"coordinates":[124.23650000000001,9.7939],"type":"Point"}
}