{
  "type": "Feature",
  "properties": {
    "gn:country":"PH",
    "gn:fcode":"PPL",
    "gn:pop":2116,
    "iso:country":"PH",
    "name:fil_x_preferred":[
        "Valle Hermoso"
    ],
    "qs:name":"Valle Hermoso",
    "qs:photos_9r":0,
    "qs:photos_sr":0,
    "qs:pop_sr":"4",
    "wd:wordcount":24,
    "wof:name":"Valle Hermoso",
    "wof:placetype":"locality",
    "wof:population":2116
},
  "geometry": {"coordinates":[124.23650000000001,9.7939],"type":"Point"}
}