{
  "type": "Feature",
  "properties": {
    "gn:admin1_code":"03",
    "gn:admin2_code":"07",
    "gn:admin3_code":"30804000.0",
    "gn:asciiname":"Tucop",
    "gn:country_code":"PH",
    "gn:dem":19,
    "gn:feature_class":"P",
    "gn:feature_code":"PPL",
    "gn:name":"Tucop",
    "gn:population":0,
    "gn:timezone":"Asia/Manila",
    "iso:country":"PH",
    "name:fil_x_preferred":[
        "Tucop"
    ],
    "wof:name":"Tucop",
    "wof:placetype":"locality"
},
  "geometry": {"coordinates":[120.47398,14.89925],"type":"Point"}
}