{
  "type": "Feature",
  "properties": {
    "gn:admin1_code":"NCR",
    "gn:admin2_code":"137600000",
    "gn:admin3_code":"137604000.0",
    "gn:asciiname":"Kalayaan Ville",
    "gn:country_code":"PH",
    "gn:dem":19,
    "gn:feature_class":"P",
    "gn:feature_code":"PPL",
    "gn:name":"Kalayaan Ville",
    "gn:population":0,
    "gn:timezone":"Asia/Manila",
    "iso:country":"PH",
    "name:eng_x_preferred":[
        "Kalayaan Ville"
    ],
    "wof:name":"Kalayaan Ville",
    "wof:placetype":"locality"
},
  "geometry": {"coordinates":[121.0311,14.5053],"type":"Point"}
}