{
  "type": "Feature",
  "properties": {
    "gn:admin1_code":"01",
    "gn:admin2_code":"29",
    "gn:admin3_code":"12912000.0",
    "gn:asciiname":"Latao",
    "gn:country_code":"PH",
    "gn:dem":49,
    "gn:feature_class":"P",
    "gn:feature_code":"PPL",
    "gn:name":"Latao",
    "gn:population":0,
    "gn:timezone":"Asia/Manila",
    "iso:country":"PH",
    "name:fil_x_preferred":[
        "Latao"
    ],
    "name:und_x_variant":[
        "Latoo",
        "Latad"
    ],
    "wof:name":"Latao",
    "wof:placetype":"locality"
},
  "geometry": {"coordinates":[120.46343,17.67987999999999],"type":"Point"}
}