{
  "type": "Feature",
  "properties": {
    "gn:admin1_code":"12",
    "gn:admin2_code":"71",
    "gn:admin3_code":"126509000.0",
    "gn:asciiname":"Balwan",
    "gn:country_code":"PH",
    "gn:dem":77,
    "gn:feature_class":"P",
    "gn:feature_code":"PPL",
    "gn:name":"Balwan",
    "gn:population":0,
    "gn:timezone":"Asia/Manila",
    "iso:country":"PH",
    "name:fil_x_preferred":[
        "Balwan"
    ],
    "name:fil_x_variant":[
        "Bulan"
    ],
    "name:und_x_variant":[
        "Balluan",
        "Blaun",
        "Buloan",
        "Bluan"
    ],
    "wof:name":"Balwan",
    "wof:placetype":"locality"
},
  "geometry": {"coordinates":[124.25669000000001,6.20841],"type":"Point"}
}