{
  "type": "Feature",
  "properties": {
    "gn:admin1_code":"01",
    "gn:admin2_code":"51",
    "gn:admin3_code":"15523000.0",
    "gn:asciiname":"Mambao",
    "gn:country_code":"PH",
    "gn:dem":132,
    "gn:feature_class":"P",
    "gn:feature_code":"PPL",
    "gn:name":"Mambao",
    "gn:population":0,
    "gn:timezone":"Asia/Manila",
    "iso:country":"PH",
    "name:fil_x_preferred":[
        "Mambao"
    ],
    "wof:name":"Mambao",
    "wof:placetype":"locality"
},
  "geometry": {"coordinates":[119.96666999999999,15.95361],"type":"Point"}
}