{
  "type": "Feature",
  "properties": {
    "gn:admin1_code":"02",
    "gn:admin2_code":"31",
    "gn:admin3_code":"23115000.0",
    "gn:asciiname":"Malannit",
    "gn:country_code":"PH",
    "gn:dem":117,
    "gn:feature_class":"P",
    "gn:feature_code":"PPL",
    "gn:name":"Malannit",
    "gn:population":0,
    "gn:timezone":"Asia/Manila",
    "iso:country":"PH",
    "name:fil_x_preferred":[
        "Malannit"
    ],
    "wof:name":"Malannit",
    "wof:placetype":"locality"
},
  "geometry": {"coordinates":[121.65505,16.56983],"type":"Point"}
}