{
  "type": "Feature",
  "properties": {
    "gn:admin1_code":"05",
    "gn:admin2_code":"39",
    "gn:admin3_code":"54115000.0",
    "gn:asciiname":"Malibas",
    "gn:country_code":"PH",
    "gn:dem":43,
    "gn:feature_class":"P",
    "gn:feature_code":"PPL",
    "gn:name":"Malibas",
    "gn:population":0,
    "gn:timezone":"Asia/Manila",
    "iso:country":"PH",
    "name:fil_x_preferred":[
        "Malibas"
    ],
    "wof:name":"Malibas",
    "wof:placetype":"locality"
},
  "geometry": {"coordinates":[123.8879,12.1499],"type":"Point"}
}