{
  "type": "Feature",
  "properties": {
    "gn:admin1_code":"01",
    "gn:admin2_code":"51",
    "gn:admin3_code":"15514000.0",
    "gn:asciiname":"Buyog",
    "gn:country_code":"PH",
    "gn:dem":112,
    "gn:feature_class":"P",
    "gn:feature_code":"PPL",
    "gn:name":"Buyog",
    "gn:population":0,
    "gn:timezone":"Asia/Manila",
    "iso:country":"PH",
    "name:fil_x_preferred":[
        "Buyog"
    ],
    "wof:name":"Buyog",
    "wof:placetype":"locality"
},
  "geometry": {"coordinates":[119.8669,16.2672],"type":"Point"}
}