{
  "type": "Feature",
  "properties": {
    "gn:admin1_code":"15",
    "gn:admin2_code":"H6",
    "gn:admin3_code":"148104000.0",
    "gn:asciiname":"Nosugsuan",
    "gn:country_code":"PH",
    "gn:dem":586,
    "gn:feature_class":"P",
    "gn:feature_code":"PPL",
    "gn:name":"Nosugsuan",
    "gn:population":0,
    "gn:timezone":"Asia/Manila",
    "iso:country":"PH",
    "name:fil_x_preferred":[
        "Nosugsuan"
    ],
    "wof:name":"Nosugsuan",
    "wof:placetype":"locality"
},
  "geometry": {"coordinates":[121.12526,18.14219],"type":"Point"}
}