{
  "type": "Feature",
  "properties": {
    "gn:admin1_code":"02",
    "gn:admin2_code":"14",
    "gn:admin3_code":"21502000.0",
    "gn:asciiname":"Afusing Bato",
    "gn:country_code":"PH",
    "gn:dem":6,
    "gn:feature_class":"P",
    "gn:feature_code":"PPL",
    "gn:name":"Afusing Bato",
    "gn:population":0,
    "gn:timezone":"Asia/Manila",
    "iso:country":"PH",
    "name:fil_x_preferred":[
        "Afusing Batu"
    ],
    "name:fil_x_variant":[
        "Afusing Bato"
    ],
    "wof:name":"Afusing Bato",
    "wof:placetype":"locality"
},
  "geometry": {"coordinates":[121.64252999999999,17.84807],"type":"Point"}
}