{
  "type": "Feature",
  "properties": {
    "gn:country":"PH",
    "gn:fcode":"PPL",
    "gn:pop":37329,
    "iso:country":"PH",
    "name:fil_x_preferred":[
        "Del Pilar"
    ],
    "qs:name":"Del Pilar",
    "qs:photos_9r":0,
    "qs:photos_sr":0,
    "qs:pop_sr":"7",
    "wof:name":"Del Pilar",
    "wof:placetype":"locality",
    "wof:population":37329
},
  "geometry": {"coordinates":[120.69935,15.03601],"type":"Point"}
}