{
  "type": "Feature",
  "properties": {
    "gn:admin1_code":"10",
    "gn:admin2_code":"34",
    "gn:admin3_code":"103519000.0",
    "gn:asciiname":"Masibay",
    "gn:country_code":"PH",
    "gn:dem":193,
    "gn:feature_class":"P",
    "gn:feature_code":"PPL",
    "gn:name":"Masibay",
    "gn:population":0,
    "gn:timezone":"Asia/Manila",
    "iso:country":"PH",
    "name:fil_x_preferred":[
        "Masibay"
    ],
    "wof:name":"Masibay",
    "wof:placetype":"locality"
},
  "geometry": {"coordinates":[123.84999999999999,7.81667],"type":"Point"}
}