{
  "type": "Feature",
  "properties": {
    "gn:admin1_code":"40",
    "gn:admin2_code":"20",
    "gn:admin3_code":"42108000.0",
    "gn:asciiname":"Monterey",
    "gn:country_code":"PH",
    "gn:dem":155,
    "gn:feature_class":"P",
    "gn:feature_code":"PPL",
    "gn:name":"Monterey",
    "gn:population":0,
    "gn:timezone":"Asia/Manila",
    "iso:country":"PH",
    "wof:name":"Monterey",
    "wof:placetype":"locality"
},
  "geometry": {"coordinates":[120.92915000000001,14.28453],"type":"Point"}
}