{
  "type": "Feature",
  "properties": {
    "gn:admin1_code":"14",
    "gn:admin2_code":"56",
    "gn:admin3_code":"153829000.0",
    "gn:asciiname":"Lasay",
    "gn:country_code":"PH",
    "gn:dem":7,
    "gn:feature_class":"P",
    "gn:feature_code":"PPL",
    "gn:name":"Lasay",
    "gn:population":0,
    "gn:timezone":"Asia/Manila",
    "iso:country":"PH",
    "name:fil_x_preferred":[
        "Lasay"
    ],
    "wof:name":"Lasay",
    "wof:placetype":"locality"
},
  "geometry": {"coordinates":[124.5475,6.95778],"type":"Point"}
}