{
  "type": "Feature",
  "properties": {
    "gn:gn_country":"PH",
    "gn:gn_fcode":"PPL",
    "gn:gn_pop":2607,
    "gn:population":2607,
    "iso:country":"PH",
    "name:bul_x_preferred":[
        "\u0410\u043a\u0438\u043d\u043e"
    ],
    "name:ceb_x_preferred":[
        "Aquino"
    ],
    "name:deu_x_preferred":[
        "Aquino"
    ],
    "name:epo_x_preferred":[
        "Aquino"
    ],
    "name:fil_x_preferred":[
        "Aquino"
    ],
    "name:fra_x_preferred":[
        "Aquino"
    ],
    "name:ilo_x_preferred":[
        "Aquino"
    ],
    "name:ita_x_preferred":[
        "Aquino"
    ],
    "name:jpn_x_preferred":[
        "\u30a2\u30ad\u30ce"
    ],
    "name:kor_x_preferred":[
        "\uc544\ud0a4\ub178"
    ],
    "name:nld_x_preferred":[
        "Aquino"
    ],
    "name:pol_x_preferred":[
        "Aquino"
    ],
    "name:rus_x_preferred":[
        "\u0410\u043a\u0438\u043d\u043e"
    ],
    "name:slv_x_preferred":[
        "Aquino"
    ],
    "name:spa_x_preferred":[
        "Aquino"
    ],
    "name:tgl_x_preferred":[
        "Aquino"
    ],
    "name:tur_x_preferred":[
        "Aquino"
    ],
    "name:unk_x_variant":[
        "Aguino"
    ],
    "qs_pg:aaroncc":"PH",
    "qs_pg:gn_country":"PH",
    "qs_pg:gn_fcode":"PPL",
    "qs_pg:gn_pop":2607,
    "qs_pg:name":"Aquino",
    "qs_pg:photos_9r":0,
    "qs_pg:photos_sr":0,
    "qs_pg:pop_sr":4,
    "qs_pg:qs_pg_placetype":"locality",
    "wof:name":"Aquino",
    "wof:placetype":"locality",
    "wof:population":2607
},
  "geometry": {"coordinates":[122.1088,11.8221],"type":"Point"}
}