{
  "type": "Feature",
  "properties": {
    "gn:admin1_code":"14",
    "gn:admin2_code":"22",
    "gn:admin3_code":"99701000.0",
    "gn:asciiname":"Lapinigan",
    "gn:country_code":"PH",
    "gn:dem":13,
    "gn:feature_class":"P",
    "gn:feature_code":"PPL",
    "gn:name":"Lapinigan",
    "gn:population":0,
    "gn:timezone":"Asia/Manila",
    "iso:country":"PH",
    "name:eng_x_preferred":[
        "Lapinigan"
    ],
    "name:und_x_variant":[
        "Lampinigan"
    ],
    "wof:name":"Lapinigan",
    "wof:placetype":"locality"
},
  "geometry": {"coordinates":[121.8772,6.6886],"type":"Point"}
}