{
  "type": "Feature",
  "properties": {
    "gn:admin1_code":"14",
    "gn:admin2_code":"56",
    "gn:admin3_code":"153826000.0",
    "gn:asciiname":"Salbu",
    "gn:country_code":"PH",
    "gn:dem":15,
    "gn:feature_class":"P",
    "gn:feature_code":"PPL",
    "gn:name":"Salbu",
    "gn:population":0,
    "gn:timezone":"Asia/Manila",
    "iso:country":"PH",
    "name:und_x_variant":[
        "Salbo",
        "Salbu"
    ],
    "wof:name":"Salbu",
    "wof:placetype":"locality"
},
  "geometry": {"coordinates":[124.42801,6.93485],"type":"Point"}
}