{
  "type": "Feature",
  "properties": {
    "gn:country":"PH",
    "gn:fcode":"PPLA3",
    "gn:population":24732,
    "iso:country":"PH",
    "name:bcl_x_preferred":[
        "Alicia"
    ],
    "name:ceb_x_preferred":[
        "Alicia"
    ],
    "name:deu_x_preferred":[
        "Alicia"
    ],
    "name:eng_x_preferred":[
        "Alicia"
    ],
    "name:fas_x_preferred":[
        "\u0627\u0644\u06cc\u0633\u06cc\u0627\u060c \u0627\u06cc\u0632\u0627\u0628\u0644\u0627"
    ],
    "name:fas_x_variant":[
        "\u0627\u0644\u06cc\u0633\u06cc\u0627"
    ],
    "name:fil_x_preferred":[
        "Alicia"
    ],
    "name:fra_x_preferred":[
        "Alicia"
    ],
    "name:ilo_x_preferred":[
        "Alicia"
    ],
    "name:ind_x_preferred":[
        "Alicia"
    ],
    "name:ita_x_preferred":[
        "Alicia"
    ],
    "name:nld_x_preferred":[
        "Alicia"
    ],
    "name:nob_x_preferred":[
        "Alicia"
    ],
    "name:oci_x_preferred":[
        "Alicia"
    ],
    "name:pag_x_preferred":[
        "Alicia"
    ],
    "name:pam_x_preferred":[
        "Alicia"
    ],
    "name:spa_x_preferred":[
        "Alicia de Isabela"
    ],
    "name:swe_x_preferred":[
        "Alicia"
    ],
    "name:tgl_x_preferred":[
        "Alicia"
    ],
    "name:vie_x_preferred":[
        "Alicia"
    ],
    "name:war_x_preferred":[
        "Alicia"
    ],
    "qs:name":"Alicia",
    "qs:photos_9r":0,
    "qs:photos_sr":0,
    "qs:pop_sr":"7",
    "wd:wordcount":145,
    "wof:name":"Alicia",
    "wof:placetype":"locality",
    "wof:population":24732
},
  "geometry": {"coordinates":[121.69734,16.77936],"type":"Point"}
}