{
  "type": "Feature",
  "properties": {
    "gn:admin1_code":"01",
    "gn:admin2_code":"29",
    "gn:admin3_code":"12905000.0",
    "gn:asciiname":"Apaya",
    "gn:country_code":"PH",
    "gn:dem":52,
    "gn:feature_class":"P",
    "gn:feature_code":"PPL",
    "gn:name":"Apaya",
    "gn:population":0,
    "gn:timezone":"Asia/Manila",
    "iso:country":"PH",
    "name:fil_x_preferred":[
        "Apaya"
    ],
    "wof:name":"Apaya",
    "wof:placetype":"locality"
},
  "geometry": {"coordinates":[120.45,17.76667],"type":"Point"}
}