{
  "type": "Feature",
  "properties": {
    "gn:country":"PH",
    "gn:fcode":"PPL",
    "gn:population":4880,
    "iso:country":"PH",
    "name:fil_x_preferred":[
        "Babug"
    ],
    "name:und_x_variant":[
        "Bubog"
    ],
    "qs:name":"Babug",
    "qs:photos_9r":0,
    "qs:photos_sr":0,
    "qs:pop_sr":"4",
    "wof:name":"Babug",
    "wof:placetype":"locality",
    "wof:population":4880
},
  "geometry": {"coordinates":[121.04170999999999,12.37325],"type":"Point"}
}