{
  "type": "Feature",
  "properties": {
    "iso:country":"PH",
    "name:bcl_x_preferred":[
        "Kalamansig"
    ],
    "name:ceb_x_preferred":[
        "Kalamansig"
    ],
    "name:deu_x_preferred":[
        "Kalamansig"
    ],
    "name:eng_x_preferred":[
        "Kalamansig"
    ],
    "name:fil_x_preferred":[
        "Kalamansig"
    ],
    "name:fra_x_preferred":[
        "Kalamansig"
    ],
    "name:ilo_x_preferred":[
        "Kalamansig"
    ],
    "name:ind_x_preferred":[
        "Kalamansig"
    ],
    "name:ita_x_preferred":[
        "Kalamansig"
    ],
    "name:nld_x_preferred":[
        "Kalamansig"
    ],
    "name:pag_x_preferred":[
        "Kalamansig"
    ],
    "name:pam_x_preferred":[
        "Kalamansig"
    ],
    "name:spa_x_preferred":[
        "Calamasing"
    ],
    "name:swe_x_preferred":[
        "Kalamansig"
    ],
    "name:tgl_x_preferred":[
        "Kalamansig"
    ],
    "name:unk_x_variant":[
        "Calamansig"
    ],
    "name:vie_x_preferred":[
        "Kalamansig"
    ],
    "name:war_x_preferred":[
        "Kalamansig"
    ],
    "qs:gn_country":"PH",
    "qs:gn_fcode":"PPL",
    "qs:gn_pop":12821,
    "qs:name":"Kalamansig",
    "qs:name_adm0":"Philippines",
    "qs:name_adm1":"Soccsksargen",
    "qs:photos":0,
    "qs:photos_1k":0,
    "qs:photos_9k":0,
    "qs:photos_9r":0,
    "qs:photos_all":0,
    "qs:photos_sr":0,
    "qs:placetype":"Town",
    "qs:pop_sr":"6",
    "qs:woe_adm0":23424934,
    "wof:name":"Kalamansig",
    "wof:placetype":"locality",
    "wof:population":12821
},
  "geometry": {"coordinates":[124.05110999999999,6.55187],"type":"Point"}
}