{
  "type": "Feature",
  "properties": {
    "gn:country":"PH",
    "gn:fcode":"ADM3",
    "gn:population":33339,
    "iso:country":"PH",
    "name:fil_x_preferred":[
        "Kalilangan"
    ],
    "qs:name":"Kalilangan",
    "qs:photos_9r":0,
    "qs:photos_sr":0,
    "qs:pop_sr":"7",
    "wof:name":"Kalilangan",
    "wof:placetype":"localadmin",
    "wof:population":33339
},
  "geometry": {"coordinates":[124.71666999999999,7.91667],"type":"Point"}
}