{
  "type": "Feature",
  "properties": {
    "gn:admin1_code":"11",
    "gn:admin2_code":"25",
    "gn:asciiname":"Padada",
    "gn:country_code":"PH",
    "gn:dem":665,
    "gn:feature_class":"P",
    "gn:feature_code":"PPL",
    "gn:name":"Padada",
    "gn:population":0,
    "gn:timezone":"Asia/Manila",
    "iso:country":"PH",
    "name:fil_x_preferred":[
        "Padada"
    ],
    "wof:name":"Padada",
    "wof:placetype":"locality"
},
  "geometry": {"coordinates":[125.45,5.88333],"type":"Point"}
}