{
  "type": "Feature",
  "properties": {
    "gn:admin1_code":"08",
    "gn:admin2_code":"37",
    "gn:admin3_code":"83742000.0",
    "gn:asciiname":"Hubay",
    "gn:country_code":"PH",
    "gn:dem":13,
    "gn:feature_class":"P",
    "gn:feature_code":"PPL",
    "gn:name":"Hubay",
    "gn:population":0,
    "gn:timezone":"Asia/Manila",
    "iso:country":"PH",
    "name:fil_x_preferred":[
        "Hubay"
    ],
    "name:und_x_variant":[
        "Jubay",
        "Hubay"
    ],
    "wof:name":"Hubay",
    "wof:placetype":"locality"
},
  "geometry": {"coordinates":[124.35120000000001,11.398],"type":"Point"}
}