{
  "type": "Feature",
  "properties": {
    "gn:admin1_code":"40",
    "gn:admin2_code":"33",
    "gn:admin3_code":"43403000.0",
    "gn:asciiname":"Timbao",
    "gn:country_code":"PH",
    "gn:dem":41,
    "gn:feature_class":"P",
    "gn:feature_code":"PPL",
    "gn:name":"Timbao",
    "gn:population":0,
    "gn:timezone":"Asia/Manila",
    "iso:country":"PH",
    "name:fil_x_preferred":[
        "Timbao"
    ],
    "wof:name":"Timbao",
    "wof:placetype":"locality"
},
  "geometry": {"coordinates":[121.06437,14.28571],"type":"Point"}
}