{
  "type": "Feature",
  "properties": {
    "gn:admin1_code":"15",
    "gn:admin2_code":"10",
    "gn:asciiname":"Bimalabag",
    "gn:country_code":"PH",
    "gn:dem":1981,
    "gn:feature_class":"P",
    "gn:feature_code":"PPL",
    "gn:name":"Bimalabag",
    "gn:population":0,
    "gn:timezone":"Asia/Manila",
    "iso:country":"PH",
    "name:fil_x_preferred":[
        "Bimalabag"
    ],
    "wof:name":"Bimalabag",
    "wof:placetype":"locality"
},
  "geometry": {"coordinates":[120.92834000000001,16.59388],"type":"Point"}
}