{
  "type": "Feature",
  "properties": {
    "gn:country":"PH",
    "gn:fcode":"PPLA3",
    "gn:pop":55195,
    "iso:country":"PH",
    "name:bcl_x_preferred":[
        "Naic"
    ],
    "name:cat_x_preferred":[
        "Naic"
    ],
    "name:chi_x_preferred":[
        "\u5948\u514b"
    ],
    "name:dut_x_preferred":[
        "Naic"
    ],
    "name:eng_x_preferred":[
        "Naic"
    ],
    "name:fre_x_preferred":[
        "Naic"
    ],
    "name:ger_x_preferred":[
        "Naic"
    ],
    "name:ilo_x_preferred":[
        "Naic"
    ],
    "name:ind_x_preferred":[
        "Naic"
    ],
    "name:ita_x_preferred":[
        "Naic"
    ],
    "name:jpn_x_preferred":[
        "\u30ca\u30a4\u30af"
    ],
    "name:may_x_preferred":[
        "Naic"
    ],
    "name:oci_x_preferred":[
        "Naic"
    ],
    "name:pag_x_preferred":[
        "Naic"
    ],
    "name:pam_x_preferred":[
        "Naic"
    ],
    "name:por_x_preferred":[
        "Naic"
    ],
    "name:spa_x_preferred":[
        "Naic"
    ],
    "name:swe_x_preferred":[
        "Naic"
    ],
    "name:tgl_x_preferred":[
        "Naic"
    ],
    "name:vie_x_preferred":[
        "Naic"
    ],
    "name:war_x_preferred":[
        "Naic"
    ],
    "qs:name":"Naic",
    "qs:photos_9r":0,
    "qs:photos_sr":0,
    "qs:pop_sr":"8",
    "wd:wordcount":628,
    "wof:name":"Naic",
    "wof:placetype":"locality",
    "wof:population":55195
},
  "geometry": {"coordinates":[120.76609000000001,14.31812],"type":"Point"}
}