{
  "type": "Feature",
  "properties": {
    "gn:country":"PH",
    "gn:fcode":"PPL",
    "gn:population":3294,
    "iso:country":"PH",
    "name:ceb_x_preferred":[
        "Tulay"
    ],
    "name:fil_x_preferred":[
        "Tulay"
    ],
    "qs:name":"Tulay",
    "qs:photos_9r":0,
    "qs:photos_sr":0,
    "qs:pop_sr":"4",
    "wd:wordcount":17,
    "wof:name":"Tulay",
    "wof:placetype":"locality",
    "wof:population":3294
},
  "geometry": {"coordinates":[120.76925,14.26969],"type":"Point"}
}