{
  "type": "Feature",
  "properties": {
    "gn:admin1_code":"13",
    "gn:admin2_code":"61",
    "gn:asciiname":"Osmena",
    "gn:country_code":"PH",
    "gn:dem":-9999,
    "gn:feature_class":"P",
    "gn:feature_code":"PPL",
    "gn:name":"Osme\u00f1a",
    "gn:population":0,
    "gn:timezone":"Asia/Manila",
    "iso:country":"PH",
    "name:fil_x_preferred":[
        "Osme\u00f1a"
    ],
    "wof:name":"Osmena",
    "wof:placetype":"locality"
},
  "geometry": {"coordinates":[125.51167,10.18694],"type":"Point"}
}