{
  "type": "Feature",
  "properties": {
    "gn:admin1_code":"06",
    "gn:admin2_code":"18",
    "gn:admin3_code":"61906000.0",
    "gn:asciiname":"Jaena Norte",
    "gn:country_code":"PH",
    "gn:dem":47,
    "gn:feature_class":"P",
    "gn:feature_code":"PPL",
    "gn:name":"Jaena Norte",
    "gn:population":0,
    "gn:timezone":"Asia/Manila",
    "iso:country":"PH",
    "name:fil_x_preferred":[
        "Jaena Norte"
    ],
    "name:und_x_variant":[
        "Jacna Norte"
    ],
    "wof:name":"Jaena Norte",
    "wof:placetype":"locality"
},
  "geometry": {"coordinates":[122.46451,11.4049],"type":"Point"}
}