{
  "type": "Feature",
  "properties": {
    "gn:admin1_code":"07",
    "gn:admin2_code":"21",
    "gn:admin3_code":"72226000.0",
    "gn:asciiname":"Pajo",
    "gn:country_code":"PH",
    "gn:dem":5,
    "gn:feature_class":"P",
    "gn:feature_code":"PPL",
    "gn:name":"Pajo",
    "gn:population":0,
    "gn:timezone":"Asia/Manila",
    "iso:country":"PH",
    "name:ceb_x_preferred":[
        "Pajo"
    ],
    "name:ido_x_preferred":[
        "Pajo"
    ],
    "name:swe_x_preferred":[
        "Pajo"
    ],
    "wof:name":"Pajo",
    "wof:placetype":"locality"
},
  "geometry": {"coordinates":[123.98797,10.29875],"type":"Point"}
}