{
  "type": "Feature",
  "properties": {
    "gn:admin1_code":"15",
    "gn:admin2_code":"10",
    "gn:admin3_code":"141108000.0",
    "gn:asciiname":"Salat",
    "gn:country_code":"PH",
    "gn:dem":1002,
    "gn:feature_class":"P",
    "gn:feature_code":"PPL",
    "gn:name":"Salat",
    "gn:population":0,
    "gn:timezone":"Asia/Manila",
    "iso:country":"PH",
    "name:fil_x_preferred":[
        "Salat"
    ],
    "wof:name":"Salat",
    "wof:placetype":"locality"
},
  "geometry": {"coordinates":[120.59,16.574],"type":"Point"}
}