{
  "type": "Feature",
  "properties": {
    "gn:admin1_code":"40",
    "gn:admin2_code":"33",
    "gn:admin3_code":"43403000.0",
    "gn:asciiname":"Calabuso",
    "gn:country_code":"PH",
    "gn:dem":24,
    "gn:feature_class":"P",
    "gn:feature_code":"PPL",
    "gn:name":"Calabuso",
    "gn:population":0,
    "gn:timezone":"Asia/Manila",
    "iso:country":"PH",
    "name:fil_x_preferred":[
        "Calabuso"
    ],
    "wof:name":"Calabuso",
    "wof:placetype":"locality"
},
  "geometry": {"coordinates":[121.0672,14.3136],"type":"Point"}
}