{
  "type": "Feature",
  "properties": {
    "gn:admin1_code":"05",
    "gn:admin2_code":"16",
    "gn:admin3_code":"51737000.0",
    "gn:asciiname":"Busaing",
    "gn:country_code":"PH",
    "gn:dem":18,
    "gn:feature_class":"P",
    "gn:feature_code":"PPL",
    "gn:name":"Busaing",
    "gn:population":0,
    "gn:timezone":"Asia/Manila",
    "iso:country":"PH",
    "name:fil_x_preferred":[
        "Busaing"
    ],
    "wof:name":"Busaing",
    "wof:placetype":"locality"
},
  "geometry": {"coordinates":[123.4152,13.8955],"type":"Point"}
}