{
  "type": "Feature",
  "properties": {
    "gn:admin1_code":"05",
    "gn:admin2_code":"58",
    "gn:admin3_code":"56214000.0",
    "gn:asciiname":"Binontolan",
    "gn:country_code":"PH",
    "gn:dem":3,
    "gn:feature_class":"P",
    "gn:feature_code":"PPL",
    "gn:name":"Binontolan",
    "gn:population":0,
    "gn:timezone":"Asia/Manila",
    "iso:country":"PH",
    "name:fil_x_preferred":[
        "Binontolan"
    ],
    "wof:name":"Binontolan",
    "wof:placetype":"locality"
},
  "geometry": {"coordinates":[124.18333,13.03333],"type":"Point"}
}