{
  "type": "Feature",
  "properties": {
    "gn:admin1_code":"09",
    "gn:admin2_code":"E7",
    "gn:asciiname":"Balaniug",
    "gn:country_code":"PH",
    "gn:dem":1,
    "gn:feature_class":"P",
    "gn:feature_code":"PPL",
    "gn:name":"Balaniug",
    "gn:population":0,
    "gn:timezone":"Asia/Manila",
    "iso:country":"PH",
    "wof:name":"Balaniug",
    "wof:placetype":"locality"
},
  "geometry": {"coordinates":[123.48333,7.81667],"type":"Point"}
}