{
  "type": "Feature",
  "properties": {
    "gn:country":"PH",
    "gn:fcode":"PPL",
    "gn:population":5074,
    "iso:country":"PH",
    "name:bcl_x_preferred":[
        "Tabina"
    ],
    "name:ceb_x_preferred":[
        "Tabina"
    ],
    "name:deu_x_preferred":[
        "Tabina"
    ],
    "name:eng_x_preferred":[
        "Tabina"
    ],
    "name:fra_x_preferred":[
        "Tabina"
    ],
    "name:ilo_x_preferred":[
        "Tabina"
    ],
    "name:ind_x_preferred":[
        "Tabina"
    ],
    "name:ita_x_preferred":[
        "Tabina"
    ],
    "name:nld_x_preferred":[
        "Tabina"
    ],
    "name:pag_x_preferred":[
        "Tabina"
    ],
    "name:pam_x_preferred":[
        "Tabina"
    ],
    "name:swe_x_preferred":[
        "Tabina"
    ],
    "name:tgl_x_preferred":[
        "Tabina"
    ],
    "name:vie_x_preferred":[
        "Tabina"
    ],
    "name:war_x_preferred":[
        "Tabina"
    ],
    "qs:name":"Tabina",
    "qs:photos_9r":0,
    "qs:photos_sr":0,
    "qs:pop_sr":"5",
    "wof:name":"Tabina",
    "wof:placetype":"locality",
    "wof:population":5074
},
  "geometry": {"coordinates":[123.4081,7.4669],"type":"Point"}
}