{
  "type": "Feature",
  "properties": {
    "gn:country":"PH",
    "gn:fcode":"PPL",
    "gn:population":5074,
    "iso:country":"PH",
    "name:ami_x_preferred":[
        "Tabina"
    ],
    "name:ang_x_preferred":[
        "Tabina"
    ],
    "name:ast_x_preferred":[
        "Tabina"
    ],
    "name:ban_x_preferred":[
        "Tabina"
    ],
    "name:bbc_x_preferred":[
        "Tabina"
    ],
    "name:bcl_x_preferred":[
        "Tabina"
    ],
    "name:bjn_x_preferred":[
        "Tabina"
    ],
    "name:bto_x_preferred":[
        "Tabina"
    ],
    "name:bug_x_preferred":[
        "Tabina"
    ],
    "name:cat_x_preferred":[
        "Tabina"
    ],
    "name:ceb_x_preferred":[
        "Tabina"
    ],
    "name:cps_x_preferred":[
        "Tabina"
    ],
    "name:cym_x_preferred":[
        "Tabina"
    ],
    "name:dag_x_preferred":[
        "Tabina"
    ],
    "name:dan_x_preferred":[
        "Tabina"
    ],
    "name:deu_x_preferred":[
        "Tabina"
    ],
    "name:eng_x_preferred":[
        "Tabina"
    ],
    "name:epo_x_preferred":[
        "Tabina"
    ],
    "name:eus_x_preferred":[
        "Tabina"
    ],
    "name:fij_x_preferred":[
        "Tabina"
    ],
    "name:fra_x_preferred":[
        "Tabina"
    ],
    "name:gle_x_preferred":[
        "Tabina"
    ],
    "name:gor_x_preferred":[
        "Tabina"
    ],
    "name:hau_x_preferred":[
        "Tabina"
    ],
    "name:hil_x_preferred":[
        "Tabina"
    ],
    "name:hmo_x_preferred":[
        "Tabina"
    ],
    "name:ibo_x_preferred":[
        "Tabina"
    ],
    "name:ilo_x_preferred":[
        "Tabina"
    ],
    "name:ind_x_preferred":[
        "Tabina"
    ],
    "name:ita_x_preferred":[
        "Tabina"
    ],
    "name:jam_x_preferred":[
        "Tabina"
    ],
    "name:jav_x_preferred":[
        "Tabina"
    ],
    "name:kat_x_preferred":[
        "\u10e2\u10d0\u10d1\u10d8\u10dc\u10d0"
    ],
    "name:kon_x_preferred":[
        "Tabina"
    ],
    "name:krj_x_preferred":[
        "Tabina"
    ],
    "name:min_x_preferred":[
        "Tabina"
    ],
    "name:mlg_x_preferred":[
        "Tabina"
    ],
    "name:mri_x_preferred":[
        "Tabina"
    ],
    "name:msa_x_preferred":[
        "Tabina"
    ],
    "name:nah_x_preferred":[
        "Tabina"
    ],
    "name:nau_x_preferred":[
        "Tabina"
    ],
    "name:nld_x_preferred":[
        "Tabina"
    ],
    "name:orm_x_preferred":[
        "Tabina"
    ],
    "name:pag_x_preferred":[
        "Tabina"
    ],
    "name:pam_x_preferred":[
        "Tabina"
    ],
    "name:por_x_preferred":[
        "Tabina"
    ],
    "name:pwn_x_preferred":[
        "Tabina"
    ],
    "name:sco_x_preferred":[
        "Tabina"
    ],
    "name:smo_x_preferred":[
        "Tabina"
    ],
    "name:sun_x_preferred":[
        "Tabina"
    ],
    "name:swa_x_preferred":[
        "Tabina"
    ],
    "name:swe_x_preferred":[
        "Tabina"
    ],
    "name:szy_x_preferred":[
        "Tabina"
    ],
    "name:tah_x_preferred":[
        "Tabina"
    ],
    "name:tet_x_preferred":[
        "Tabina"
    ],
    "name:tgl_x_preferred":[
        "Tabina"
    ],
    "name:tpi_x_preferred":[
        "Tabina"
    ],
    "name:vie_x_preferred":[
        "Tabina"
    ],
    "name:war_x_preferred":[
        "Tabina"
    ],
    "name:xho_x_preferred":[
        "Tabina"
    ],
    "name:yor_x_preferred":[
        "Tabina"
    ],
    "name:zul_x_preferred":[
        "Tabina"
    ],
    "qs:name":"Tabina",
    "qs:photos_9r":0,
    "qs:photos_sr":0,
    "qs:pop_sr":"5",
    "wof:name":"Tabina",
    "wof:placetype":"locality",
    "wof:population":5074
},
  "geometry": {"coordinates":[123.4081,7.4669],"type":"Point"}
}