{
  "type": "Feature",
  "properties": {
    "gn:admin1_code":"07",
    "gn:admin2_code":"46",
    "gn:admin3_code":"74615000.0",
    "gn:asciiname":"Mandalupang",
    "gn:country_code":"PH",
    "gn:dem":411,
    "gn:feature_class":"P",
    "gn:feature_code":"PPL",
    "gn:name":"Mandalupang",
    "gn:population":0,
    "gn:timezone":"Asia/Manila",
    "iso:country":"PH",
    "name:fil_x_preferred":[
        "Mandalupang"
    ],
    "wof:name":"Mandalupang",
    "wof:placetype":"locality"
},
  "geometry": {"coordinates":[123.0659,9.6624],"type":"Point"}
}