{
  "type": "Feature",
  "properties": {
    "gn:admin1_code":"14",
    "gn:admin2_code":"56",
    "gn:admin3_code":"153822000.0",
    "gn:asciiname":"Nabundas",
    "gn:country_code":"PH",
    "gn:dem":17,
    "gn:feature_class":"P",
    "gn:feature_code":"PPL",
    "gn:name":"Nabundas",
    "gn:population":0,
    "gn:timezone":"Asia/Manila",
    "iso:country":"PH",
    "name:fil_x_preferred":[
        "Nabundas"
    ],
    "wof:name":"Nabundas",
    "wof:placetype":"locality"
},
  "geometry": {"coordinates":[124.74267999999999,7.12122],"type":"Point"}
}