{
  "type": "Feature",
  "properties": {
    "gn:admin1_code":"06",
    "gn:admin2_code":"H3",
    "gn:admin3_code":"64520000.0",
    "gn:asciiname":"Enangua",
    "gn:country_code":"PH",
    "gn:dem":484,
    "gn:feature_class":"P",
    "gn:feature_code":"PPL",
    "gn:name":"Enangua",
    "gn:population":0,
    "gn:timezone":"Asia/Manila",
    "iso:country":"PH",
    "name:fil_x_preferred":[
        "Enangua"
    ],
    "name:und_x_variant":[
        "Enangue"
    ],
    "wof:name":"Enangua",
    "wof:placetype":"locality"
},
  "geometry": {"coordinates":[123.11969999999999,10.64645],"type":"Point"}
}