{
  "type": "Feature",
  "properties": {
    "gn:admin1_code":"09",
    "gn:admin2_code":"66",
    "gn:admin3_code":"97302000.0",
    "gn:asciiname":"Lintogop",
    "gn:country_code":"PH",
    "gn:dem":4,
    "gn:feature_class":"P",
    "gn:feature_code":"PPL",
    "gn:name":"Lintogop",
    "gn:population":0,
    "gn:timezone":"Asia/Manila",
    "iso:country":"PH",
    "name:eng_x_preferred":[
        "Lintogop"
    ],
    "name:und_x_variant":[
        "Lintogap"
    ],
    "wof:name":"Lintogop",
    "wof:placetype":"locality"
},
  "geometry": {"coordinates":[123.60469999999999,7.9676],"type":"Point"}
}