{
  "type": "Feature",
  "properties": {
    "gn:admin1_code":"06",
    "gn:admin2_code":"18",
    "gn:admin3_code":"61909000.0",
    "gn:asciiname":"Anhawon",
    "gn:cc2":"PH",
    "gn:country_code":"PH",
    "gn:dem":3,
    "gn:feature_class":"P",
    "gn:feature_code":"PPL",
    "gn:name":"Anhawon",
    "gn:population":0,
    "gn:timezone":"Asia/Manila",
    "iso:country":"PH",
    "name:und_x_variant":[
        "Anhauan",
        "Anhauon",
        "Anhawon"
    ],
    "wof:name":"Anhawon",
    "wof:placetype":"locality"
},
  "geometry": {"coordinates":[122.79222,11.53639],"type":"Point"}
}