{
  "type": "Feature",
  "properties": {
    "iso:country":"PH",
    "name:bcl_x_preferred":[
        "Margosatubig"
    ],
    "name:cbk_zam_x_preferred":[
        "Margosatubig"
    ],
    "name:ceb_x_preferred":[
        "Margosatubig"
    ],
    "name:deu_x_preferred":[
        "Margosatubig"
    ],
    "name:eng_x_preferred":[
        "Margosatubig"
    ],
    "name:fra_x_preferred":[
        "Margosatubig"
    ],
    "name:ilo_x_preferred":[
        "Margosatubig"
    ],
    "name:ind_x_preferred":[
        "Margosatubig"
    ],
    "name:ita_x_preferred":[
        "Margosatubig"
    ],
    "name:nld_x_preferred":[
        "Margosatubig"
    ],
    "name:pag_x_preferred":[
        "Margosatubig"
    ],
    "name:pam_x_preferred":[
        "Margosatubig"
    ],
    "name:spa_x_preferred":[
        "Margosatubig"
    ],
    "name:swe_x_preferred":[
        "Margosatubig"
    ],
    "name:tgl_x_preferred":[
        "Margosatubig"
    ],
    "name:und_x_variant":[
        "Fort Margosatubig"
    ],
    "name:vie_x_preferred":[
        "Margosatubig"
    ],
    "name:war_x_preferred":[
        "Margosatubig"
    ],
    "qs:gn_country":"PH",
    "qs:gn_fcode":"PPLA3",
    "qs:gn_pop":14605,
    "qs:name":"Margosatubig",
    "qs:name_adm0":"Philippines",
    "qs:name_adm1":"Zamboanga Peninsula",
    "qs:photos":0,
    "qs:photos_1k":0,
    "qs:photos_9k":1,
    "qs:photos_9r":1,
    "qs:photos_all":4,
    "qs:photos_sr":0,
    "qs:placetype":"Town",
    "qs:pop_sr":"6",
    "qs:woe_adm0":23424934,
    "wd:wordcount":589,
    "wof:name":"Margosatubig",
    "wof:placetype":"locality",
    "wof:population":14605
},
  "geometry": {"coordinates":[123.1658,7.5777],"type":"Point"}
}