{
  "type": "Feature",
  "properties": {
    "gn:admin1_code":"14",
    "gn:admin2_code":"72",
    "gn:asciiname":"Pamasan",
    "gn:country_code":"PH",
    "gn:dem":1,
    "gn:feature_class":"P",
    "gn:feature_code":"PPL",
    "gn:name":"Pamasan",
    "gn:population":0,
    "gn:timezone":"Asia/Manila",
    "iso:country":"PH",
    "name:eng_x_preferred":[
        "Pamasan"
    ],
    "wof:name":"Pamasan",
    "wof:placetype":"locality"
},
  "geometry": {"coordinates":[120.2752,5.1056],"type":"Point"}
}