{
  "type": "Feature",
  "properties": {
    "gn:admin1_code":"12",
    "gn:admin2_code":"70",
    "gn:admin3_code":"126303000.0",
    "gn:asciiname":"Dulongabong",
    "gn:cc2":"PH",
    "gn:country_code":"PH",
    "gn:dem":36,
    "gn:feature_class":"P",
    "gn:feature_code":"PPL",
    "gn:name":"Dulongabong",
    "gn:population":0,
    "gn:timezone":"Asia/Manila",
    "iso:country":"PH",
    "name:und_x_variant":[
        "Dulangabong"
    ],
    "wof:name":"Dulongabong",
    "wof:placetype":"locality"
},
  "geometry": {"coordinates":[125.14861000000001,6.11889],"type":"Point"}
}