{
  "type": "Feature",
  "properties": {
    "gn:admin1_code":"09",
    "gn:admin2_code":"ZSI",
    "gn:admin3_code":"98311000.0",
    "gn:asciiname":"Tamban",
    "gn:cc2":"PH",
    "gn:country_code":"PH",
    "gn:dem":10,
    "gn:feature_class":"P",
    "gn:feature_code":"PPL",
    "gn:name":"Tamban",
    "gn:population":0,
    "gn:timezone":"Asia/Manila",
    "iso:country":"PH",
    "name:und_x_variant":[
        "Tanban",
        "Tamban"
    ],
    "wof:name":"Tamban",
    "wof:placetype":"locality"
},
  "geometry": {"coordinates":[122.7825,7.47694],"type":"Point"}
}