{
  "type": "Feature",
  "properties": {
    "gn:admin1_code":"07",
    "gn:admin2_code":"11",
    "gn:admin3_code":"71243000.0",
    "gn:asciiname":"Butoyon",
    "gn:country_code":"PH",
    "gn:dem":40,
    "gn:feature_class":"P",
    "gn:feature_code":"PPL",
    "gn:name":"Butoyon",
    "gn:population":0,
    "gn:timezone":"Asia/Manila",
    "iso:country":"PH",
    "name:fil_x_preferred":[
        "Butoyon"
    ],
    "wof:name":"Butoyon",
    "wof:placetype":"locality"
},
  "geometry": {"coordinates":[124.26443999999999,10.10139],"type":"Point"}
}