{
  "type": "Feature",
  "properties": {
    "gn:admin1_code":"40",
    "gn:admin2_code":"H2",
    "gn:admin3_code":"45636000.0",
    "gn:asciiname":"Banadero",
    "gn:country_code":"PH",
    "gn:dem":106,
    "gn:feature_class":"P",
    "gn:feature_code":"PPL",
    "gn:name":"Ba\u00f1adero",
    "gn:population":0,
    "gn:timezone":"Asia/Manila",
    "iso:country":"PH",
    "name:fil_x_preferred":[
        "Ba\u00f1adero"
    ],
    "wof:name":"Banadero",
    "wof:placetype":"locality"
},
  "geometry": {"coordinates":[121.96666999999999,14.71667],"type":"Point"}
}