{
  "type": "Feature",
  "properties": {
    "gn:admin1_code":"41",
    "gn:admin2_code":"49",
    "gn:admin3_code":"175312000.0",
    "gn:asciiname":"Langi-langiban",
    "gn:country_code":"PH",
    "gn:dem":22,
    "gn:feature_class":"P",
    "gn:feature_code":"PPL",
    "gn:name":"Langi-langiban",
    "gn:population":0,
    "gn:timezone":"Asia/Manila",
    "iso:country":"PH",
    "name:fil_x_preferred":[
        "Langi-langiban"
    ],
    "wof:name":"Langi-langiban",
    "wof:placetype":"locality"
},
  "geometry": {"coordinates":[119.43333,11.18333],"type":"Point"}
}