{
  "type": "Feature",
  "properties": {
    "gn:country":"PH",
    "gn:fcode":"PPL",
    "gn:pop":4651,
    "iso:country":"PH",
    "name:fil_x_preferred":[
        "Colongolo"
    ],
    "qs:name":"Colongolo",
    "qs:photos_9r":0,
    "qs:photos_sr":0,
    "qs:pop_sr":"4",
    "wof:name":"Colongolo",
    "wof:placetype":"locality",
    "wof:population":4651
},
  "geometry": {"coordinates":[124.72167,6.33861],"type":"Point"}
}