{
  "type": "Feature",
  "properties": {
    "gn:admin1_code":"06",
    "gn:admin2_code":"06",
    "gn:admin3_code":"60601000.0",
    "gn:asciiname":"Igbarabatuan",
    "gn:country_code":"PH",
    "gn:dem":45,
    "gn:feature_class":"P",
    "gn:feature_code":"PPL",
    "gn:name":"Igbarabatuan",
    "gn:population":0,
    "gn:timezone":"Asia/Manila",
    "iso:country":"PH",
    "name:fil_x_preferred":[
        "Igbarabatuan"
    ],
    "wof:name":"Igbarabatuan",
    "wof:placetype":"locality"
},
  "geometry": {"coordinates":[121.9773,10.4529],"type":"Point"}
}