{
  "type": "Feature",
  "properties": {
    "gn:admin1_code":"14",
    "gn:admin2_code":"60",
    "gn:admin3_code":"156616000.0",
    "gn:asciiname":"Lubok-Lubok",
    "gn:country_code":"PH",
    "gn:dem":18,
    "gn:feature_class":"P",
    "gn:feature_code":"PPL",
    "gn:name":"Lubok-Lubok",
    "gn:population":0,
    "gn:timezone":"Asia/Manila",
    "iso:country":"PH",
    "name:fil_x_preferred":[
        "Lubok-Lubok"
    ],
    "wof:name":"Lubok-Lubok",
    "wof:placetype":"locality"
},
  "geometry": {"coordinates":[121.16528,5.94583],"type":"Point"}
}