{
  "type": "Feature",
  "properties": {
    "gn:admin1_code":"02",
    "gn:admin2_code":"31",
    "gn:admin3_code":"23127000.0",
    "gn:asciiname":"Sinaoangan Norte",
    "gn:country_code":"PH",
    "gn:dem":119,
    "gn:feature_class":"P",
    "gn:feature_code":"PPL",
    "gn:name":"Sinaoangan Norte",
    "gn:population":0,
    "gn:timezone":"Asia/Manila",
    "iso:country":"PH",
    "name:fil_x_preferred":[
        "Sinaoangan Norte"
    ],
    "name:und_x_variant":[
        "Sinao\u00f1gan Norte",
        "Sinauangan"
    ],
    "wof:name":"Sinaoangan Norte",
    "wof:placetype":"locality"
},
  "geometry": {"coordinates":[121.75451,16.44778],"type":"Point"}
}