{
  "type": "Feature",
  "properties": {
    "gn:admin1_code":"01",
    "gn:admin2_code":"29",
    "gn:admin3_code":"12934000.0",
    "gn:asciiname":"Cabalangegan",
    "gn:country_code":"PH",
    "gn:dem":10,
    "gn:feature_class":"P",
    "gn:feature_code":"PPL",
    "gn:name":"Cabalangegan",
    "gn:population":0,
    "gn:timezone":"Asia/Manila",
    "iso:country":"PH",
    "name:fil_x_preferred":[
        "Cabalangegan"
    ],
    "wof:name":"Cabalangegan",
    "wof:placetype":"locality"
},
  "geometry": {"coordinates":[120.39577,17.56247],"type":"Point"}
}