{
  "type": "Feature",
  "properties": {
    "gn:admin1_code":"15",
    "gn:admin2_code":"32",
    "gn:admin3_code":"143215000.0",
    "gn:asciiname":"Ngibat",
    "gn:country_code":"PH",
    "gn:dem":1136,
    "gn:feature_class":"P",
    "gn:feature_code":"PPL",
    "gn:name":"Ngibat",
    "gn:population":0,
    "gn:timezone":"Asia/Manila",
    "iso:country":"PH",
    "name:fil_x_preferred":[
        "Ngibat"
    ],
    "wof:name":"Ngibat",
    "wof:placetype":"locality"
},
  "geometry": {"coordinates":[121.10093999999999,17.24084],"type":"Point"}
}