{
  "type": "Feature",
  "properties": {
    "gn:admin1_code":"07",
    "gn:admin2_code":"11",
    "gn:admin3_code":"71218000.0",
    "gn:asciiname":"Kanoling",
    "gn:cc2":"PH",
    "gn:country_code":"PH",
    "gn:dem":51,
    "gn:feature_class":"P",
    "gn:feature_code":"PPL",
    "gn:name":"Kanoling",
    "gn:population":0,
    "gn:timezone":"Asia/Manila",
    "iso:country":"PH",
    "name:und_x_variant":[
        "Canoling",
        "Kanoling"
    ],
    "wof:name":"Kanoling",
    "wof:placetype":"locality"
},
  "geometry": {"coordinates":[124.16667,9.95],"type":"Point"}
}