{
  "type": "Feature",
  "properties": {
    "gn:admin1_code":"03",
    "gn:admin2_code":"47",
    "gn:admin3_code":"34901000.0",
    "gn:asciiname":"Poblacion East Primero",
    "gn:country_code":"PH",
    "gn:dem":29,
    "gn:feature_class":"P",
    "gn:feature_code":"PPL",
    "gn:name":"Poblacion East Primero",
    "gn:population":0,
    "gn:timezone":"Asia/Manila",
    "iso:country":"PH",
    "wof:name":"Poblacion East Primero",
    "wof:placetype":"locality"
},
  "geometry": {"coordinates":[120.84854,15.50479],"type":"Point"}
}