{
  "type": "Feature",
  "properties": {
    "gn:admin1_code":"01",
    "gn:admin2_code":"28",
    "gn:admin3_code":"12816000.0",
    "gn:asciiname":"Cabaruan",
    "gn:country_code":"PH",
    "gn:dem":15,
    "gn:feature_class":"P",
    "gn:feature_code":"PPL",
    "gn:name":"Cabaruan",
    "gn:population":0,
    "gn:timezone":"Asia/Manila",
    "iso:country":"PH",
    "name:fil_x_preferred":[
        "Cabaruan"
    ],
    "wof:name":"Cabaruan",
    "wof:placetype":"locality"
},
  "geometry": {"coordinates":[120.54040000000001,18.0753],"type":"Point"}
}