{
  "type": "Feature",
  "properties": {
    "gn:admin1_code":"03",
    "gn:admin2_code":"13",
    "gn:admin3_code":"31422000.0",
    "gn:asciiname":"Pinacpinacan",
    "gn:country_code":"PH",
    "gn:dem":28,
    "gn:feature_class":"P",
    "gn:feature_code":"PPL",
    "gn:name":"Pinacpinacan",
    "gn:population":0,
    "gn:timezone":"Asia/Manila",
    "iso:country":"PH",
    "name:fil_x_preferred":[
        "Pinakpinakan"
    ],
    "name:und_x_variant":[
        "Pinac Pinacan"
    ],
    "wof:name":"Pinacpinacan",
    "wof:placetype":"locality"
},
  "geometry": {"coordinates":[120.92778,15.0016],"type":"Point"}
}