{
  "type": "Feature",
  "properties": {
    "gn:admin1_code":"01",
    "gn:admin2_code":"51",
    "gn:admin3_code":"15546000.0",
    "gn:asciiname":"Labit Proper",
    "gn:country_code":"PH",
    "gn:dem":24,
    "gn:feature_class":"P",
    "gn:feature_code":"PPL",
    "gn:name":"Labit Proper",
    "gn:population":0,
    "gn:timezone":"Asia/Manila",
    "iso:country":"PH",
    "name:fil_x_preferred":[
        "Labit"
    ],
    "wof:name":"Labit Proper",
    "wof:placetype":"locality"
},
  "geometry": {"coordinates":[120.52873999999998,15.95616],"type":"Point"}
}