{
  "type": "Feature",
  "properties": {
    "gn:admin1_code":"08",
    "gn:admin2_code":"59",
    "gn:asciiname":"Inauangan",
    "gn:country_code":"PH",
    "gn:dem":223,
    "gn:feature_class":"P",
    "gn:feature_code":"PPL",
    "gn:name":"Inauangan",
    "gn:population":0,
    "gn:timezone":"Asia/Manila",
    "iso:country":"PH",
    "name:fil_x_preferred":[
        "Inauangan"
    ],
    "wof:name":"Inauangan",
    "wof:placetype":"locality"
},
  "geometry": {"coordinates":[122.3998,10.9617],"type":"Point"}
}