{
  "type": "Feature",
  "properties": {
    "gn:country":"PH",
    "gn:fcode":"PPL",
    "gn:population":4742,
    "iso:country":"PH",
    "name:und_x_variant":[
        "Bialong"
    ],
    "qs:name":"Bual",
    "qs:photos_9r":0,
    "qs:photos_sr":0,
    "qs:pop_sr":"4",
    "wof:name":"Bual",
    "wof:placetype":"locality",
    "wof:population":4742
},
  "geometry": {"coordinates":[124.91083,6.79583],"type":"Point"}
}