{
  "type": "Feature",
  "properties": {
    "gn:admin1_code":"02",
    "gn:admin2_code":"31",
    "gn:admin3_code":"23106000.0",
    "gn:asciiname":"Casibarag Norte",
    "gn:country_code":"PH",
    "gn:dem":35,
    "gn:feature_class":"P",
    "gn:feature_code":"PPL",
    "gn:name":"Casibarag Norte",
    "gn:population":0,
    "gn:timezone":"Asia/Manila",
    "iso:country":"PH",
    "name:fil_x_preferred":[
        "Casibarag Norte"
    ],
    "wof:name":"Casibarag Norte",
    "wof:placetype":"locality"
},
  "geometry": {"coordinates":[121.75407,17.43712],"type":"Point"}
}