{
  "type": "Feature",
  "properties": {
    "gn:admin1_code":"01",
    "gn:admin2_code":"29",
    "gn:admin3_code":"12921000.0",
    "gn:asciiname":"Suksuquit",
    "gn:country_code":"PH",
    "gn:dem":9,
    "gn:feature_class":"P",
    "gn:feature_code":"PPL",
    "gn:name":"Suksuquit",
    "gn:population":0,
    "gn:timezone":"Asia/Manila",
    "iso:country":"PH",
    "name:fil_x_preferred":[
        "Sucsucquit"
    ],
    "name:fil_x_variant":[
        "Suksuquit"
    ],
    "wof:name":"Suksuquit",
    "wof:placetype":"locality"
},
  "geometry": {"coordinates":[120.36323,17.63118],"type":"Point"}
}