{
  "type": "Feature",
  "properties": {
    "gn:gn_country":"PH",
    "gn:gn_fcode":"PPL",
    "gn:gn_pop":3140,
    "gn:population":3140,
    "iso:country":"PH",
    "name:fil_x_preferred":[
        "Polloc"
    ],
    "qs_pg:aaroncc":"PH",
    "qs_pg:gn_country":"PH",
    "qs_pg:gn_fcode":"PPL",
    "qs_pg:gn_pop":3140,
    "qs_pg:name":"Polloc",
    "qs_pg:photos_9r":0,
    "qs_pg:photos_sr":0,
    "qs_pg:pop_sr":4,
    "qs_pg:qs_pg_placetype":"locality",
    "wof:name":"Polloc",
    "wof:placetype":"locality",
    "wof:population":3140
},
  "geometry": {"coordinates":[124.22083000000001,7.35528],"type":"Point"}
}