{
  "type": "Feature",
  "properties": {
    "gn:admin1_code":"01",
    "gn:admin2_code":"51",
    "gn:admin3_code":"15507000.0",
    "gn:asciiname":"San Raymundo",
    "gn:country_code":"PH",
    "gn:dem":36,
    "gn:feature_class":"P",
    "gn:feature_code":"PPL",
    "gn:name":"San Raymundo",
    "gn:population":0,
    "gn:timezone":"Asia/Manila",
    "iso:country":"PH",
    "name:fil_x_preferred":[
        "San Raymundo"
    ],
    "wof:name":"San Raymundo",
    "wof:placetype":"locality"
},
  "geometry": {"coordinates":[120.66663,15.91666],"type":"Point"}
}