{
  "type": "Feature",
  "properties": {
    "gn:country":"PH",
    "gn:fcode":"PPL",
    "gn:pop":8306,
    "iso:country":"PH",
    "name:unk_x_variant":[
        "Tampacan"
    ],
    "qs:name":"Tampakan",
    "qs:photos_9r":0,
    "qs:photos_sr":0,
    "qs:pop_sr":"5",
    "wof:name":"Tampakan",
    "wof:placetype":"locality",
    "wof:population":8306
},
  "geometry": {"coordinates":[119.79389,4.92278],"type":"Point"}
}