{
  "type": "Feature",
  "properties": {
    "gn:admin1_code":"12",
    "gn:admin2_code":"57",
    "gn:admin3_code":"124716000.0",
    "gn:asciiname":"Pinamulaan",
    "gn:country_code":"PH",
    "gn:dem":443,
    "gn:feature_class":"P",
    "gn:feature_code":"PPL",
    "gn:name":"Pinamulaan",
    "gn:population":0,
    "gn:timezone":"Asia/Manila",
    "iso:country":"PH",
    "name:fil_x_preferred":[
        "Pinamulaan"
    ],
    "wof:name":"Pinamulaan",
    "wof:placetype":"locality"
},
  "geometry": {"coordinates":[124.75653,7.50169],"type":"Point"}
}