{
  "type": "Feature",
  "properties": {
    "gn:admin1_code":"40",
    "gn:admin2_code":"33",
    "gn:admin3_code":"43405000.0",
    "gn:asciiname":"Banlik Calamba",
    "gn:country_code":"PH",
    "gn:dem":17,
    "gn:feature_class":"P",
    "gn:feature_code":"PPL",
    "gn:name":"Banlik Calamba",
    "gn:population":0,
    "gn:timezone":"Asia/Manila",
    "iso:country":"PH",
    "name:fil_x_preferred":[
        "Banlik Calamba"
    ],
    "wof:name":"Banlik Calamba",
    "wof:placetype":"locality"
},
  "geometry": {"coordinates":[121.1544,14.2295],"type":"Point"}
}