{
  "type": "Feature",
  "properties": {
    "gn:admin1_code":"01",
    "gn:admin2_code":"29",
    "gn:admin3_code":"12920000.0",
    "gn:asciiname":"Malammin",
    "gn:cc2":"PH",
    "gn:country_code":"PH",
    "gn:dem":29,
    "gn:feature_class":"P",
    "gn:feature_code":"PPL",
    "gn:name":"Malammin",
    "gn:population":0,
    "gn:timezone":"Asia/Manila",
    "iso:country":"PH",
    "name:und_x_variant":[
        "Malammin Sur",
        "Malammin"
    ],
    "wof:name":"Malammin",
    "wof:placetype":"locality"
},
  "geometry": {"coordinates":[120.46666999999999,17.75],"type":"Point"}
}