{
  "type": "Feature",
  "properties": {
    "gn:admin1_code":"15",
    "gn:admin2_code":"10",
    "gn:admin3_code":"141103000.0",
    "gn:asciiname":"Toplao",
    "gn:country_code":"PH",
    "gn:dem":1770,
    "gn:feature_class":"P",
    "gn:feature_code":"PPL",
    "gn:name":"Toplao",
    "gn:population":0,
    "gn:timezone":"Asia/Manila",
    "iso:country":"PH",
    "name:fil_x_preferred":[
        "Toplao"
    ],
    "wof:name":"Toplao",
    "wof:placetype":"locality"
},
  "geometry": {"coordinates":[120.75,16.78333],"type":"Point"}
}