{
  "type": "Feature",
  "properties": {
    "gn:admin1_code":"05",
    "gn:admin2_code":"58",
    "gn:admin3_code":"56207000.0",
    "gn:asciiname":"Maguisa",
    "gn:country_code":"PH",
    "gn:dem":57,
    "gn:feature_class":"P",
    "gn:feature_code":"PPL",
    "gn:name":"Maguisa",
    "gn:population":0,
    "gn:timezone":"Asia/Manila",
    "iso:country":"PH",
    "name:fil_x_preferred":[
        "Maguisa"
    ],
    "wof:name":"Maguisa",
    "wof:placetype":"locality"
},
  "geometry": {"coordinates":[123.61667,12.95],"type":"Point"}
}