{
  "type": "Feature",
  "properties": {
    "gn:admin1_code":"09",
    "gn:admin2_code":"65",
    "gn:admin3_code":"97220000.0",
    "gn:asciiname":"Lagudi",
    "gn:country_code":"PH",
    "gn:dem":19,
    "gn:feature_class":"P",
    "gn:feature_code":"PPL",
    "gn:name":"Lagudi",
    "gn:population":0,
    "gn:timezone":"Asia/Manila",
    "iso:country":"PH",
    "name:fil_x_preferred":[
        "Lagudi"
    ],
    "wof:name":"Lagudi",
    "wof:placetype":"locality"
},
  "geometry": {"coordinates":[122.12222,7.60111],"type":"Point"}
}