{
  "type": "Feature",
  "properties": {
    "gn:admin1_code":"01",
    "gn:admin2_code":"51",
    "gn:admin3_code":"15542000.0",
    "gn:asciiname":"Sioasio Este",
    "gn:country_code":"PH",
    "gn:dem":114,
    "gn:feature_class":"P",
    "gn:feature_code":"PPL",
    "gn:name":"Sioasio Este",
    "gn:population":0,
    "gn:timezone":"Asia/Manila",
    "iso:country":"PH",
    "name:fil_x_preferred":[
        "Sioasio Este"
    ],
    "name:und_x_variant":[
        "Sioasio East"
    ],
    "wof:name":"Sioasio Este",
    "wof:placetype":"locality"
},
  "geometry": {"coordinates":[120.06294,16.02412],"type":"Point"}
}