{
  "type": "Feature",
  "properties": {
    "gn:admin1_code":"15",
    "gn:admin2_code":"01",
    "gn:admin3_code":"140123000.0",
    "gn:asciiname":"Baribarit",
    "gn:country_code":"PH",
    "gn:dem":79,
    "gn:feature_class":"P",
    "gn:feature_code":"PPL",
    "gn:name":"Baribarit",
    "gn:population":0,
    "gn:timezone":"Asia/Manila",
    "iso:country":"PH",
    "name:fil_x_preferred":[
        "Baribarit"
    ],
    "wof:name":"Baribarit",
    "wof:placetype":"locality"
},
  "geometry": {"coordinates":[120.53028,17.5175],"type":"Point"}
}