{
  "type": "Feature",
  "properties": {
    "gn:admin1_code":"06",
    "gn:admin2_code":"H3",
    "gn:admin3_code":"64507000.0",
    "gn:asciiname":"Baclan",
    "gn:country_code":"PH",
    "gn:dem":115,
    "gn:feature_class":"P",
    "gn:feature_code":"PPL",
    "gn:name":"Baclan",
    "gn:population":0,
    "gn:timezone":"Asia/Manila",
    "iso:country":"PH",
    "name:fil_x_preferred":[
        "Baclan"
    ],
    "wof:name":"Baclan",
    "wof:placetype":"locality"
},
  "geometry": {"coordinates":[122.53830000000001,9.9291],"type":"Point"}
}