{
  "type": "Feature",
  "properties": {
    "gn:admin1_code":"07",
    "gn:admin2_code":"21",
    "gn:admin3_code":"72225000.0",
    "gn:asciiname":"Mangako",
    "gn:country_code":"PH",
    "gn:dem":169,
    "gn:feature_class":"P",
    "gn:feature_code":"PPL",
    "gn:name":"Mangako",
    "gn:population":0,
    "gn:timezone":"Asia/Manila",
    "iso:country":"PH",
    "name:fil_x_preferred":[
        "Mangako"
    ],
    "name:und_x_variant":[
        "Mangaco"
    ],
    "wof:name":"Mangako",
    "wof:placetype":"locality"
},
  "geometry": {"coordinates":[123.3329,9.5677],"type":"Point"}
}