{
  "type": "Feature",
  "properties": {
    "gn:admin1_code":"11",
    "gn:admin2_code":"I7",
    "gn:admin3_code":"112317000.0",
    "gn:asciiname":"Dasag",
    "gn:country_code":"PH",
    "gn:dem":49,
    "gn:feature_class":"P",
    "gn:feature_code":"PPL",
    "gn:name":"Dasag",
    "gn:population":0,
    "gn:timezone":"Asia/Manila",
    "iso:country":"PH",
    "name:fil_x_preferred":[
        "Dasag"
    ],
    "wof:name":"Dasag",
    "wof:placetype":"locality"
},
  "geometry": {"coordinates":[125.71222,7.17278],"type":"Point"}
}