{
  "type": "Feature",
  "properties": {
    "gn:admin1_code":"13",
    "gn:admin2_code":"03",
    "gn:admin3_code":"160304000.0",
    "gn:asciiname":"Bataan",
    "gn:country_code":"PH",
    "gn:dem":37,
    "gn:feature_class":"P",
    "gn:feature_code":"PPL",
    "gn:name":"Bataan",
    "gn:population":0,
    "gn:timezone":"Asia/Manila",
    "iso:country":"PH",
    "name:fil_x_preferred":[
        "Bataan"
    ],
    "wof:name":"Bataan",
    "wof:placetype":"locality"
},
  "geometry": {"coordinates":[125.73944,8.23],"type":"Point"}
}