{
  "type": "Feature",
  "properties": {
    "gn:admin1_code":"02",
    "gn:admin2_code":"14",
    "gn:admin3_code":"21528000.0",
    "gn:asciiname":"Lakambini",
    "gn:country_code":"PH",
    "gn:dem":70,
    "gn:feature_class":"P",
    "gn:feature_code":"PPL",
    "gn:name":"Lakambini",
    "gn:population":0,
    "gn:timezone":"Asia/Manila",
    "iso:country":"PH",
    "wof:name":"Lakambini",
    "wof:placetype":"locality"
},
  "geometry": {"coordinates":[121.53667,17.71099],"type":"Point"}
}