{
  "type": "Feature",
  "properties": {
    "gn:admin1_code":"15",
    "gn:admin2_code":"27",
    "gn:admin3_code":"142704000.0",
    "gn:asciiname":"Nayon",
    "gn:country_code":"PH",
    "gn:dem":266,
    "gn:feature_class":"P",
    "gn:feature_code":"PPL",
    "gn:name":"Nayon",
    "gn:population":0,
    "gn:timezone":"Asia/Manila",
    "iso:country":"PH",
    "name:fil_x_preferred":[
        "Nayon"
    ],
    "name:mya_x_preferred":[
        "\u1014\u101a\u102f\u1014\u103a\u101c"
    ],
    "wof:name":"Nayon",
    "wof:placetype":"locality"
},
  "geometry": {"coordinates":[121.25360999999999,16.71694],"type":"Point"}
}