{
  "type": "Feature",
  "properties": {
    "gn:admin1_code":"15",
    "gn:admin2_code":"32",
    "gn:admin3_code":"143213000.0",
    "gn:asciiname":"Banat",
    "gn:country_code":"PH",
    "gn:dem":369,
    "gn:feature_class":"P",
    "gn:feature_code":"PPL",
    "gn:name":"Banat",
    "gn:population":0,
    "gn:timezone":"Asia/Manila",
    "iso:country":"PH",
    "name:fil_x_preferred":[
        "Banat"
    ],
    "wof:name":"Banat",
    "wof:placetype":"locality"
},
  "geometry": {"coordinates":[121.28830000000001,17.4072],"type":"Point"}
}