{
  "type": "Feature",
  "properties": {
    "gn:admin1_code":"40",
    "gn:admin2_code":"H2",
    "gn:admin3_code":"45619000.0",
    "gn:asciiname":"Villa Fuerte",
    "gn:country_code":"PH",
    "gn:dem":120,
    "gn:feature_class":"P",
    "gn:feature_code":"PPL",
    "gn:name":"Villa Fuerte",
    "gn:population":0,
    "gn:timezone":"Asia/Manila",
    "iso:country":"PH",
    "name:fil_x_preferred":[
        "Villa Fuerte"
    ],
    "wof:name":"Villa Fuerte",
    "wof:placetype":"locality"
},
  "geometry": {"coordinates":[122.1504,13.855],"type":"Point"}
}