{
  "type": "Feature",
  "properties": {
    "gn:admin1_code":"05",
    "gn:admin2_code":"16",
    "gn:admin3_code":"51712000.0",
    "gn:asciiname":"Kilbay",
    "gn:country_code":"PH",
    "gn:dem":7,
    "gn:feature_class":"P",
    "gn:feature_code":"PPL",
    "gn:name":"Kilbay",
    "gn:population":0,
    "gn:timezone":"Asia/Manila",
    "iso:country":"PH",
    "name:fil_x_preferred":[
        "Kilbay"
    ],
    "wof:name":"Kilbay",
    "wof:placetype":"locality"
},
  "geometry": {"coordinates":[122.5894,13.8969],"type":"Point"}
}