{
  "type": "Feature",
  "properties": {
    "gn:admin1_code":"02",
    "gn:admin2_code":"14",
    "gn:admin3_code":"21503000.0",
    "gn:asciiname":"Mapurao",
    "gn:country_code":"PH",
    "gn:dem":29,
    "gn:feature_class":"P",
    "gn:feature_code":"PPL",
    "gn:name":"Mapurao",
    "gn:population":0,
    "gn:timezone":"Asia/Manila",
    "iso:country":"PH",
    "name:fil_x_preferred":[
        "Maburao"
    ],
    "wof:name":"Mapurao",
    "wof:placetype":"locality"
},
  "geometry": {"coordinates":[121.50548000000001,18.16662],"type":"Point"}
}