{
  "type": "Feature",
  "properties": {
    "gn:admin1_code":"15",
    "gn:admin2_code":"10",
    "gn:admin3_code":"141107000.0",
    "gn:asciiname":"Maganig",
    "gn:country_code":"PH",
    "gn:dem":2352,
    "gn:feature_class":"P",
    "gn:feature_code":"PPL",
    "gn:name":"Maganig",
    "gn:population":0,
    "gn:timezone":"Asia/Manila",
    "iso:country":"PH",
    "name:fil_x_preferred":[
        "Maganig"
    ],
    "wof:name":"Maganig",
    "wof:placetype":"locality"
},
  "geometry": {"coordinates":[120.88674,16.66007],"type":"Point"}
}