{
  "type": "Feature",
  "properties": {
    "gn:admin1_code":"03",
    "gn:admin2_code":"47",
    "gn:admin3_code":"34906000.0",
    "gn:asciiname":"Balbinit",
    "gn:country_code":"PH",
    "gn:dem":32,
    "gn:feature_class":"P",
    "gn:feature_code":"PPL",
    "gn:name":"Balbinit",
    "gn:population":0,
    "gn:timezone":"Asia/Manila",
    "iso:country":"PH",
    "name:fil_x_preferred":[
        "Balbinit"
    ],
    "wof:name":"Balbinit",
    "wof:placetype":"locality"
},
  "geometry": {"coordinates":[120.715,15.7098],"type":"Point"}
}