{
  "type": "Feature",
  "properties": {
    "gn:admin1_code":"08",
    "gn:admin2_code":"37",
    "gn:admin3_code":"83742000.0",
    "gn:asciiname":"Bagulangsang",
    "gn:country_code":"PH",
    "gn:dem":59,
    "gn:feature_class":"P",
    "gn:feature_code":"PPL",
    "gn:name":"Bagulangsang",
    "gn:population":0,
    "gn:timezone":"Asia/Manila",
    "iso:country":"PH",
    "name:fil_x_preferred":[
        "Bagulangsang"
    ],
    "name:und_x_variant":[
        "Bagulansang",
        "Bagulangsang"
    ],
    "wof:name":"Bagulangsang",
    "wof:placetype":"locality"
},
  "geometry": {"coordinates":[124.2979,11.4944],"type":"Point"}
}