{
  "type": "Feature",
  "properties": {
    "gn:admin1_code":"05",
    "gn:admin2_code":"16",
    "gn:admin3_code":"51706000.0",
    "gn:asciiname":"Gnaragnara",
    "gn:country_code":"PH",
    "gn:dem":21,
    "gn:feature_class":"P",
    "gn:feature_code":"PPL",
    "gn:name":"Gnaragnara",
    "gn:population":0,
    "gn:timezone":"Asia/Manila",
    "iso:country":"PH",
    "name:fil_x_preferred":[
        "Gnaragnara"
    ],
    "wof:name":"Gnaragnara",
    "wof:placetype":"locality"
},
  "geometry": {"coordinates":[123.2043,13.3839],"type":"Point"}
}