{
  "type": "Feature",
  "properties": {
    "gn:admin1_code":"01",
    "gn:admin2_code":"51",
    "gn:admin3_code":"15516000.0",
    "gn:asciiname":"Anapao",
    "gn:country_code":"PH",
    "gn:dem":10,
    "gn:feature_class":"P",
    "gn:feature_code":"PPL",
    "gn:name":"Anapao",
    "gn:population":0,
    "gn:timezone":"Asia/Manila",
    "iso:country":"PH",
    "name:fil_x_preferred":[
        "Anapao"
    ],
    "wof:name":"Anapao",
    "wof:placetype":"locality"
},
  "geometry": {"coordinates":[119.8563,16.0947],"type":"Point"}
}