{
  "type": "Feature",
  "properties": {
    "gn:admin1_code":"15",
    "gn:admin2_code":"32",
    "gn:admin3_code":"143206000.0",
    "gn:asciiname":"Colong",
    "gn:country_code":"PH",
    "gn:dem":776,
    "gn:feature_class":"P",
    "gn:feature_code":"PPL",
    "gn:name":"Colong",
    "gn:population":0,
    "gn:timezone":"Asia/Manila",
    "iso:country":"PH",
    "name:fil_x_preferred":[
        "Colong"
    ],
    "wof:name":"Colong",
    "wof:placetype":"locality"
},
  "geometry": {"coordinates":[121.143,17.3682],"type":"Point"}
}