{
  "type": "Feature",
  "properties": {
    "gn:admin1_code":"40",
    "gn:admin2_code":"09",
    "gn:admin3_code":"41005000.0",
    "gn:asciiname":"Tabangao Aplaya",
    "gn:country_code":"PH",
    "gn:dem":12,
    "gn:feature_class":"P",
    "gn:feature_code":"PPL",
    "gn:name":"Tabangao Aplaya",
    "gn:population":0,
    "gn:timezone":"Asia/Manila",
    "iso:country":"PH",
    "name:fil_x_preferred":[
        "Tabangao Aplaya"
    ],
    "wof:name":"Tabangao Aplaya",
    "wof:placetype":"locality"
},
  "geometry": {"coordinates":[121.0634,13.7137],"type":"Point"}
}