{
  "type": "Feature",
  "properties": {
    "gn:admin1_code":"14",
    "gn:admin2_code":"60",
    "gn:asciiname":"Luuk",
    "gn:country_code":"PH",
    "gn:dem":0,
    "gn:feature_class":"P",
    "gn:feature_code":"PPL",
    "gn:name":"Luuk",
    "gn:population":0,
    "gn:timezone":"Asia/Manila",
    "iso:country":"PH",
    "name:bcl_x_preferred":[
        "Banguingui"
    ],
    "name:ceb_x_preferred":[
        "Banguingui"
    ],
    "name:deu_x_preferred":[
        "Banguingui"
    ],
    "name:eng_x_preferred":[
        "Luuk"
    ],
    "name:fra_x_preferred":[
        "Banguingui"
    ],
    "name:ilo_x_preferred":[
        "Banguingui"
    ],
    "name:ind_x_preferred":[
        "Banguingui"
    ],
    "name:ita_x_preferred":[
        "Tongkil"
    ],
    "name:nld_x_preferred":[
        "Banguingui"
    ],
    "name:pag_x_preferred":[
        "Banguingui"
    ],
    "name:pam_x_preferred":[
        "Banguingui"
    ],
    "name:sco_x_preferred":[
        "Banguingui"
    ],
    "name:swe_x_preferred":[
        "Banguingui"
    ],
    "name:tgl_x_preferred":[
        "Banguingui"
    ],
    "name:und_x_variant":[
        "Tungkil",
        "Loog"
    ],
    "name:urd_x_preferred":[
        "\u0628\u0627\u0646\u06af\u0648\u06cc\u0646\u06af\u0648\u06cc"
    ],
    "name:vie_x_preferred":[
        "Banguingui"
    ],
    "name:war_x_preferred":[
        "Banguingui"
    ],
    "wof:name":"Luuk",
    "wof:placetype":"locality"
},
  "geometry": {"coordinates":[121.78579000000001,6.0714],"type":"Point"}
}