{
  "type": "Feature",
  "properties": {
    "gn:admin1_code":"14",
    "gn:admin2_code":"60",
    "gn:asciiname":"Luuk",
    "gn:country_code":"PH",
    "gn:dem":0,
    "gn:feature_class":"P",
    "gn:feature_code":"PPL",
    "gn:name":"Luuk",
    "gn:population":0,
    "gn:timezone":"Asia/Manila",
    "iso:country":"PH",
    "name:eng_x_preferred":[
        "Luuk"
    ],
    "name:und_x_variant":[
        "Tungkil",
        "Loog",
        "Tongkil"
    ],
    "wof:name":"Luuk",
    "wof:placetype":"locality"
},
  "geometry": {"coordinates":[121.78579000000001,6.0714],"type":"Point"}
}