{
  "type": "Feature",
  "properties": {
    "gn:admin1_code":"02",
    "gn:admin2_code":"31",
    "gn:admin3_code":"23134000.0",
    "gn:asciiname":"Furao Dalag",
    "gn:country_code":"PH",
    "gn:dem":40,
    "gn:feature_class":"P",
    "gn:feature_code":"PPL",
    "gn:name":"Furao Dalag",
    "gn:population":0,
    "gn:timezone":"Asia/Manila",
    "iso:country":"PH",
    "name:fil_x_preferred":[
        "Furao Dalag"
    ],
    "wof:name":"Furao Dalag",
    "wof:placetype":"locality"
},
  "geometry": {"coordinates":[121.71115,17.46042000000001],"type":"Point"}
}