{
  "type": "Feature",
  "properties": {
    "gn:admin1_code":"15",
    "gn:admin2_code":"01",
    "gn:admin3_code":"140127000.0",
    "gn:asciiname":"Apa-apaya",
    "gn:country_code":"PH",
    "gn:dem":153,
    "gn:feature_class":"P",
    "gn:feature_code":"PPL",
    "gn:name":"Apa-apaya",
    "gn:population":0,
    "gn:timezone":"Asia/Manila",
    "iso:country":"PH",
    "name:fil_x_preferred":[
        "Apa-apaya"
    ],
    "wof:name":"Apa-apaya",
    "wof:placetype":"locality"
},
  "geometry": {"coordinates":[120.61667,17.45],"type":"Point"}
}