{
  "type": "Feature",
  "properties": {
    "gn:admin1_code":"40",
    "gn:admin2_code":"53",
    "gn:admin3_code":"45802000.0",
    "gn:asciiname":"Maagay",
    "gn:country_code":"PH",
    "gn:dem":150,
    "gn:feature_class":"P",
    "gn:feature_code":"PPL",
    "gn:name":"Maagay",
    "gn:population":0,
    "gn:timezone":"Asia/Manila",
    "iso:country":"PH",
    "name:fil_x_preferred":[
        "Maagay"
    ],
    "wof:name":"Maagay",
    "wof:placetype":"locality"
},
  "geometry": {"coordinates":[121.18528000000001,14.61944],"type":"Point"}
}