{
  "type": "Feature",
  "properties": {
    "gn:country":"PH",
    "gn:fcode":"ADM3",
    "gn:pop":23548,
    "iso:country":"PH",
    "name:bcl_x_preferred":[
        "Dingalan"
    ],
    "name:cat_x_preferred":[
        "Dingalan"
    ],
    "name:ceb_x_preferred":[
        "Dingalan"
    ],
    "name:deu_x_preferred":[
        "Dingalan"
    ],
    "name:eng_x_preferred":[
        "Dingalan"
    ],
    "name:fil_x_preferred":[
        "Dingalan"
    ],
    "name:fra_x_preferred":[
        "Dingalan"
    ],
    "name:ilo_x_preferred":[
        "Dingalan"
    ],
    "name:ind_x_preferred":[
        "Dingalan"
    ],
    "name:ita_x_preferred":[
        "Dingalan"
    ],
    "name:msa_x_preferred":[
        "Dingalan"
    ],
    "name:nld_x_preferred":[
        "Dingalan"
    ],
    "name:oci_x_preferred":[
        "Dingalan"
    ],
    "name:pag_x_preferred":[
        "Dingalan"
    ],
    "name:pam_x_preferred":[
        "Dingalan"
    ],
    "name:spa_x_preferred":[
        "Dingal\u00e1n"
    ],
    "name:swe_x_preferred":[
        "Dingalan"
    ],
    "name:tgl_x_preferred":[
        "Dingalan"
    ],
    "name:urd_x_preferred":[
        "\u062f\u06cc\u0646\u06af\u0627\u0644\u0627\u0646"
    ],
    "name:vie_x_preferred":[
        "Dingalan"
    ],
    "name:war_x_preferred":[
        "Dingalan"
    ],
    "name:zho_x_preferred":[
        "\u4e01\u963f\u862d"
    ],
    "qs:name":"Dingalan",
    "qs:photos_9r":0,
    "qs:photos_sr":0,
    "qs:pop_sr":"7",
    "wd:wordcount":389,
    "wof:name":"Dingalan",
    "wof:placetype":"localadmin",
    "wof:population":23548
},
  "geometry": {"coordinates":[121.34999999999999,15.26667],"type":"Point"}
}