{
  "type": "Feature",
  "properties": {
    "gn:country":"PH",
    "gn:fcode":"ADM3",
    "gn:pop":23548,
    "iso:country":"PH",
    "name:fil_x_preferred":[
        "Dingalan"
    ],
    "qs:name":"Dingalan",
    "qs:photos_9r":0,
    "qs:photos_sr":0,
    "qs:pop_sr":"7",
    "wd:wordcount":389,
    "wof:name":"Dingalan",
    "wof:placetype":"localadmin",
    "wof:population":23548
},
  "geometry": {"coordinates":[121.34999999999999,15.26667],"type":"Point"}
}