{
  "type": "Feature",
  "properties": {
    "gn:admin1_code":"01",
    "gn:admin2_code":"51",
    "gn:admin3_code":"15521000.0",
    "gn:asciiname":"Lawis",
    "gn:country_code":"PH",
    "gn:dem":10,
    "gn:feature_class":"P",
    "gn:feature_code":"PPL",
    "gn:name":"Lawis",
    "gn:population":0,
    "gn:timezone":"Asia/Manila",
    "iso:country":"PH",
    "name:fil_x_preferred":[
        "Lawis"
    ],
    "name:und_x_variant":[
        "Laois I",
        "Laois"
    ],
    "wof:name":"Lawis",
    "wof:placetype":"locality"
},
  "geometry": {"coordinates":[120.13954,16.03912],"type":"Point"}
}