{
  "type": "Feature",
  "properties": {
    "gn:admin1_code":"07",
    "gn:admin2_code":"11",
    "gn:admin3_code":"71224000.0",
    "gn:asciiname":"Cawayan",
    "gn:country_code":"PH",
    "gn:dem":7,
    "gn:feature_class":"P",
    "gn:feature_code":"PPL",
    "gn:name":"Cawayan",
    "gn:population":0,
    "gn:timezone":"Asia/Manila",
    "iso:country":"PH",
    "name:fil_x_preferred":[
        "Cawayan"
    ],
    "wof:name":"Cawayan",
    "wof:placetype":"locality"
},
  "geometry": {"coordinates":[124.06667,10.03333],"type":"Point"}
}