{
  "type": "Feature",
  "properties": {
    "gn:admin1_code":"02",
    "gn:admin2_code":"14",
    "gn:admin3_code":"21522000.0",
    "gn:asciiname":"Santiago",
    "gn:country_code":"PH",
    "gn:dem":17,
    "gn:feature_class":"P",
    "gn:feature_code":"PPL",
    "gn:name":"Santiago",
    "gn:population":0,
    "gn:timezone":"Asia/Manila",
    "iso:country":"PH",
    "name:fil_x_preferred":[
        "Santiago"
    ],
    "wof:name":"Santiago",
    "wof:placetype":"locality"
},
  "geometry": {"coordinates":[121.23593,18.52283],"type":"Point"}
}