{
  "type": "Feature",
  "properties": {
    "gn:admin1_code":"14",
    "gn:admin2_code":"22",
    "gn:admin3_code":"150711000.0",
    "gn:asciiname":"Matata",
    "gn:country_code":"PH",
    "gn:dem":13,
    "gn:feature_class":"P",
    "gn:feature_code":"PPL",
    "gn:name":"Matata",
    "gn:population":0,
    "gn:timezone":"Asia/Manila",
    "iso:country":"PH",
    "name:ceb_x_preferred":[
        "Matata"
    ],
    "name:fil_x_preferred":[
        "Matata"
    ],
    "name:msa_x_preferred":[
        "Matata"
    ],
    "wof:name":"Matata",
    "wof:placetype":"locality"
},
  "geometry": {"coordinates":[122.13806,6.4475],"type":"Point"}
}