{
  "type": "Feature",
  "properties": {
    "gn:admin1_code":"01",
    "gn:admin2_code":"36",
    "gn:admin3_code":"13313000.0",
    "gn:asciiname":"Nagtagaan",
    "gn:country_code":"PH",
    "gn:dem":28,
    "gn:feature_class":"P",
    "gn:feature_code":"PPL",
    "gn:name":"Nagtagaan",
    "gn:population":0,
    "gn:timezone":"Asia/Manila",
    "iso:country":"PH",
    "name:fil_x_preferred":[
        "Nagtagaan"
    ],
    "wof:name":"Nagtagaan",
    "wof:placetype":"locality"
},
  "geometry": {"coordinates":[120.42213,16.22808],"type":"Point"}
}