{
  "type": "Feature",
  "properties": {
    "gn:admin1_code":"01",
    "gn:admin2_code":"29",
    "gn:admin3_code":"12901000.0",
    "gn:asciiname":"Dagdad",
    "gn:country_code":"PH",
    "gn:dem":716,
    "gn:feature_class":"P",
    "gn:feature_code":"PPL",
    "gn:name":"Dagdad",
    "gn:population":0,
    "gn:timezone":"Asia/Manila",
    "iso:country":"PH",
    "name:fil_x_preferred":[
        "Dagdad"
    ],
    "wof:name":"Dagdad",
    "wof:placetype":"locality"
},
  "geometry": {"coordinates":[120.63379999999999,16.9288],"type":"Point"}
}