{
  "type": "Feature",
  "properties": {
    "gn:admin1_code":"40",
    "gn:admin2_code":"09",
    "gn:admin3_code":"41020000.0",
    "gn:asciiname":"Bungahan",
    "gn:country_code":"PH",
    "gn:dem":132,
    "gn:feature_class":"P",
    "gn:feature_code":"PPL",
    "gn:name":"Bungahan",
    "gn:population":0,
    "gn:timezone":"Asia/Manila",
    "iso:country":"PH",
    "wof:name":"Bungahan",
    "wof:placetype":"locality"
},
  "geometry": {"coordinates":[121.25,13.86667],"type":"Point"}
}