{
  "type": "Feature",
  "properties": {
    "gn:admin1_code":"03",
    "gn:admin2_code":"63",
    "gn:admin3_code":"36916000.0",
    "gn:asciiname":"Dela Paz",
    "gn:country_code":"PH",
    "gn:dem":66,
    "gn:feature_class":"P",
    "gn:feature_code":"PPL",
    "gn:name":"Dela Paz",
    "gn:population":0,
    "gn:timezone":"Asia/Manila",
    "iso:country":"PH",
    "name:fil_x_preferred":[
        "De la Paz"
    ],
    "wof:name":"Dela Paz",
    "wof:placetype":"locality"
},
  "geometry": {"coordinates":[120.58037,15.42439],"type":"Point"}
}