{
  "type": "Feature",
  "properties": {
    "gn:country":"PH",
    "gn:fcode":"PPL",
    "gn:population":5761,
    "iso:country":"PH",
    "name:fil_x_preferred":[
        "Aglayan"
    ],
    "qs_pg:aaroncc":"PH",
    "qs_pg:gn_country":"PH",
    "qs_pg:gn_fcode":"PPL",
    "qs_pg:gn_pop":5761,
    "qs_pg:name":"Aglayan",
    "qs_pg:photos_9r":0,
    "qs_pg:photos_sr":0,
    "qs_pg:pop_sr":5,
    "qs_pg:qs_pg_placetype":"locality",
    "wof:name":"Aglayan",
    "wof:placetype":"locality",
    "wof:population":5761
},
  "geometry": {"coordinates":[125.13417,8.055],"type":"Point"}
}