{
  "type": "Feature",
  "properties": {
    "gn:admin1_code":"06",
    "gn:admin2_code":"30",
    "gn:admin3_code":"63030000.0",
    "gn:asciiname":"Tiglaua",
    "gn:country_code":"PH",
    "gn:dem":37,
    "gn:feature_class":"P",
    "gn:feature_code":"PPL",
    "gn:name":"Tiglaua",
    "gn:population":0,
    "gn:timezone":"Asia/Manila",
    "iso:country":"PH",
    "name:fil_x_preferred":[
        "Tiglaua"
    ],
    "name:und_x_variant":[
        "Tiglawa"
    ],
    "wof:name":"Tiglaua",
    "wof:placetype":"locality"
},
  "geometry": {"coordinates":[122.24639999999999,10.67836],"type":"Point"}
}