{
  "type": "Feature",
  "properties": {
    "gn:admin1_code":"03",
    "gn:admin2_code":"50",
    "gn:admin3_code":"35402000.0",
    "gn:asciiname":"Sanpaga",
    "gn:country_code":"PH",
    "gn:dem":8,
    "gn:feature_class":"P",
    "gn:feature_code":"PPL",
    "gn:name":"Sanpaga",
    "gn:population":0,
    "gn:timezone":"Asia/Manila",
    "iso:country":"PH",
    "name:fil_x_preferred":[
        "Sanpaga"
    ],
    "wof:name":"Sanpaga",
    "wof:placetype":"locality"
},
  "geometry": {"coordinates":[120.7475,14.9458],"type":"Point"}
}