{
  "type": "Feature",
  "properties": {
    "gn:admin1_code":"03",
    "gn:admin2_code":"G8",
    "gn:admin3_code":"37703000.0",
    "gn:asciiname":"Decabasan South",
    "gn:country_code":"PH",
    "gn:dem":12,
    "gn:feature_class":"P",
    "gn:feature_code":"PPL",
    "gn:name":"Decabasan South",
    "gn:population":0,
    "gn:timezone":"Asia/Manila",
    "iso:country":"PH",
    "name:fil_x_preferred":[
        "Decabasan South"
    ],
    "wof:name":"Decabasan South",
    "wof:placetype":"locality"
},
  "geometry": {"coordinates":[122.19777999999999,16.415],"type":"Point"}
}