{
  "type": "Feature",
  "properties": {
    "gn:admin1_code":"03",
    "gn:admin2_code":"13",
    "gn:admin3_code":"31403000.0",
    "gn:asciiname":"Tangos",
    "gn:country_code":"PH",
    "gn:dem":15,
    "gn:feature_class":"P",
    "gn:feature_code":"PPL",
    "gn:name":"Tangos",
    "gn:population":0,
    "gn:timezone":"Asia/Manila",
    "iso:country":"PH",
    "name:fil_x_preferred":[
        "Tangos"
    ],
    "wof:name":"Tangos",
    "wof:placetype":"locality"
},
  "geometry": {"coordinates":[120.89781000000001,14.97684],"type":"Point"}
}