{
  "type": "Feature",
  "properties": {
    "gn:admin1_code":"40",
    "gn:admin2_code":"09",
    "gn:admin3_code":"41033000.0",
    "gn:asciiname":"Recodo",
    "gn:country_code":"PH",
    "gn:dem":27,
    "gn:feature_class":"P",
    "gn:feature_code":"PPL",
    "gn:name":"Recodo",
    "gn:population":0,
    "gn:timezone":"Asia/Manila",
    "iso:country":"PH",
    "name:fil_x_preferred":[
        "Recodo"
    ],
    "name:und_x_variant":[
        "Ricodo"
    ],
    "wof:name":"Recodo",
    "wof:placetype":"locality"
},
  "geometry": {"coordinates":[120.8891,13.655],"type":"Point"}
}