{
  "type": "Feature",
  "properties": {
    "gn:admin1_code":"41",
    "gn:admin2_code":"40",
    "gn:admin3_code":"175104000.0",
    "gn:asciiname":"Calamias",
    "gn:country_code":"PH",
    "gn:dem":20,
    "gn:feature_class":"P",
    "gn:feature_code":"PPL",
    "gn:name":"Calamias",
    "gn:population":0,
    "gn:timezone":"Asia/Manila",
    "iso:country":"PH",
    "name:fil_x_preferred":[
        "Calamias"
    ],
    "wof:name":"Calamias",
    "wof:placetype":"locality"
},
  "geometry": {"coordinates":[120.11702,13.78086],"type":"Point"}
}