{
  "type": "Feature",
  "properties": {
    "gn:admin1_code":"13",
    "gn:admin2_code":"62",
    "gn:admin3_code":"166813000.0",
    "gn:asciiname":"Pangdanan",
    "gn:country_code":"PH",
    "gn:dem":19,
    "gn:feature_class":"P",
    "gn:feature_code":"PPL",
    "gn:name":"Pangdanan",
    "gn:population":0,
    "gn:timezone":"Asia/Manila",
    "iso:country":"PH",
    "name:fil_x_preferred":[
        "Pangdanan"
    ],
    "wof:name":"Pangdanan",
    "wof:placetype":"locality"
},
  "geometry": {"coordinates":[125.95478,9.27265],"type":"Point"}
}