{
  "type": "Feature",
  "properties": {
    "gn:admin1_code":"15",
    "gn:admin2_code":"H6",
    "gn:admin3_code":"148101000.0",
    "gn:asciiname":"Tabangan",
    "gn:country_code":"PH",
    "gn:dem":294,
    "gn:feature_class":"P",
    "gn:feature_code":"PPL",
    "gn:name":"Tabangan",
    "gn:population":0,
    "gn:timezone":"Asia/Manila",
    "iso:country":"PH",
    "name:fil_x_preferred":[
        "Tabangan"
    ],
    "wof:name":"Tabangan",
    "wof:placetype":"locality"
},
  "geometry": {"coordinates":[121.03333000000001,18.25],"type":"Point"}
}