{
  "type": "Feature",
  "properties": {
    "gn:admin1_code":"02",
    "gn:admin2_code":"31",
    "gn:admin3_code":"23108000.0",
    "gn:asciiname":"Minante Primero",
    "gn:country_code":"PH",
    "gn:dem":62,
    "gn:feature_class":"P",
    "gn:feature_code":"PPL",
    "gn:name":"Minante Primero",
    "gn:population":0,
    "gn:timezone":"Asia/Manila",
    "iso:country":"PH",
    "name:fil_x_preferred":[
        "Minante I"
    ],
    "wof:name":"Minante Primero",
    "wof:placetype":"locality"
},
  "geometry": {"coordinates":[121.76084,16.91015],"type":"Point"}
}