{
  "type": "Feature",
  "properties": {
    "gn:admin1_code":"14",
    "gn:admin2_code":"60",
    "gn:admin3_code":"156612000.0",
    "gn:asciiname":"Buan",
    "gn:country_code":"PH",
    "gn:dem":18,
    "gn:feature_class":"P",
    "gn:feature_code":"PPL",
    "gn:name":"Buan",
    "gn:population":2646,
    "gn:timezone":"Asia/Manila",
    "iso:country":"PH",
    "name:eng_x_preferred":[
        "Buan"
    ],
    "wof:name":"Buan",
    "wof:placetype":"locality",
    "wof:population":2646
},
  "geometry": {"coordinates":[120.8815,5.5508],"type":"Point"}
}