{
  "type": "Feature",
  "properties": {
    "gn:admin1_code":"01",
    "gn:admin2_code":"29",
    "gn:admin3_code":"12932000.0",
    "gn:asciiname":"Quinvuctut",
    "gn:cc2":"PH",
    "gn:country_code":"PH",
    "gn:dem":697,
    "gn:feature_class":"P",
    "gn:feature_code":"PPL",
    "gn:name":"Quinvuctut",
    "gn:population":0,
    "gn:timezone":"Asia/Manila",
    "iso:country":"PH",
    "name:und_x_variant":[
        "Quinyuctut",
        "Quinvuctut"
    ],
    "wof:name":"Quinvuctut",
    "wof:placetype":"locality"
},
  "geometry": {"coordinates":[120.55028,17.03083],"type":"Point"}
}