{
  "type": "Feature",
  "properties": {
    "gn:admin1_code":"06",
    "gn:admin2_code":"30",
    "gn:admin3_code":"63044000.0",
    "gn:asciiname":"Alibayog",
    "gn:country_code":"PH",
    "gn:dem":29,
    "gn:feature_class":"P",
    "gn:feature_code":"PPL",
    "gn:name":"Alibayog",
    "gn:population":0,
    "gn:timezone":"Asia/Manila",
    "iso:country":"PH",
    "name:fil_x_preferred":[
        "Alibayog"
    ],
    "wof:name":"Alibayog",
    "wof:placetype":"locality"
},
  "geometry": {"coordinates":[122.9971,11.256],"type":"Point"}
}