{
  "type": "Feature",
  "properties": {
    "gn:country":"PH",
    "gn:fcode":"PPL",
    "gn:population":3664,
    "iso:country":"PH",
    "qs:name":"Paldit",
    "qs:photos_9r":0,
    "qs:photos_sr":0,
    "qs:pop_sr":"4",
    "wof:name":"Paldit",
    "wof:placetype":"locality",
    "wof:population":3664
},
  "geometry": {"coordinates":[120.53333000000001,16.16667],"type":"Point"}
}