{
  "type": "Feature",
  "properties": {
    "gn:country":"PH",
    "gn:fcode":"ADM3",
    "gn:pop":46188,
    "iso:country":"PH",
    "qs:name":"Lantapan",
    "qs:photos_9r":0,
    "qs:photos_sr":0,
    "qs:pop_sr":"7",
    "wof:name":"Lantapan",
    "wof:placetype":"localadmin",
    "wof:population":46188
},
  "geometry": {"coordinates":[125.05,8.01667],"type":"Point"}
}