{
  "type": "Feature",
  "properties": {
    "gn:admin1_code":"08",
    "gn:admin2_code":"55",
    "gn:admin3_code":"86005000.0",
    "gn:asciiname":"Mercedes",
    "gn:country_code":"PH",
    "gn:dem":31,
    "gn:feature_class":"P",
    "gn:feature_code":"PPL",
    "gn:name":"Mercedes",
    "gn:population":0,
    "gn:timezone":"Asia/Manila",
    "iso:country":"PH",
    "name:ben_x_preferred":[
        "\u09ae\u09be\u09b0\u09cd\u09b8\u09bf\u09a6\u09bf\u099c"
    ],
    "name:ell_x_preferred":[
        "\u039c\u03b5\u03c1\u03c3\u03ad\u03b4\u03b5\u03c2"
    ],
    "name:fil_x_preferred":[
        "Mercedes"
    ],
    "name:heb_x_preferred":[
        "\u05de\u05e8\u05e6\u05d3\u05e1"
    ],
    "name:hin_x_preferred":[
        "\u092e\u0930\u094d\u0938\u0940\u0921\u0940\u091c\u093c"
    ],
    "name:hun_x_preferred":[
        "Mercedes"
    ],
    "name:ind_x_preferred":[
        "Mercedes"
    ],
    "name:kor_x_preferred":[
        "\uba54\ub974\uc138\ub370\uc2a4"
    ],
    "name:urd_x_preferred":[
        "\u0645\u0631\u0633\u06cc\u0688\u06cc\u0632"
    ],
    "name:vie_x_preferred":[
        "Mercedes"
    ],
    "wof:name":"Mercedes",
    "wof:placetype":"locality"
},
  "geometry": {"coordinates":[124.87806,11.78417],"type":"Point"}
}