{
  "type": "Feature",
  "properties": {
    "gn:admin1_code":"02",
    "gn:admin2_code":"14",
    "gn:admin3_code":"21519000.0",
    "gn:asciiname":"Bugatay",
    "gn:country_code":"PH",
    "gn:dem":48,
    "gn:feature_class":"P",
    "gn:feature_code":"PPL",
    "gn:name":"Bugatay",
    "gn:population":0,
    "gn:timezone":"Asia/Manila",
    "iso:country":"PH",
    "name:fil_x_preferred":[
        "Bugatay"
    ],
    "wof:name":"Bugatay",
    "wof:placetype":"locality"
},
  "geometry": {"coordinates":[121.8133,17.61623999999999],"type":"Point"}
}