{
  "type": "Feature",
  "properties": {
    "gn:admin1_code":"13",
    "gn:admin2_code":"61",
    "gn:asciiname":"Tagbayakao",
    "gn:country_code":"PH",
    "gn:dem":-9999,
    "gn:feature_class":"P",
    "gn:feature_code":"PPL",
    "gn:name":"Tagbayakao",
    "gn:population":0,
    "gn:timezone":"Asia/Manila",
    "iso:country":"PH",
    "name:fil_x_preferred":[
        "Tagbayakao"
    ],
    "wof:name":"Tagbayakao",
    "wof:placetype":"locality"
},
  "geometry": {"coordinates":[125.56667,9.98333],"type":"Point"}
}