{
  "type": "Feature",
  "properties": {
    "gn:country":"PH",
    "gn:fcode":"PPL",
    "gn:population":2085,
    "iso:country":"PH",
    "name:und_x_variant":[
        "Masarayas"
    ],
    "qs:name":"Masarayao",
    "qs:photos_9r":0,
    "qs:photos_sr":0,
    "qs:pop_sr":"4",
    "wof:name":"Masarayao",
    "wof:placetype":"locality",
    "wof:population":2085
},
  "geometry": {"coordinates":[124.61750000000001,11.08972],"type":"Point"}
}