{
  "type": "Feature",
  "properties": {
    "gn:admin1_code":"05",
    "gn:admin2_code":"05",
    "gn:admin3_code":"50514000.0",
    "gn:asciiname":"Busac",
    "gn:country_code":"PH",
    "gn:dem":24,
    "gn:feature_class":"P",
    "gn:feature_code":"PPL",
    "gn:name":"Busac",
    "gn:population":0,
    "gn:timezone":"Asia/Manila",
    "iso:country":"PH",
    "name:fil_x_preferred":[
        "Busac"
    ],
    "wof:name":"Busac",
    "wof:placetype":"locality"
},
  "geometry": {"coordinates":[123.4729,13.2818],"type":"Point"}
}