{
  "type": "Feature",
  "properties": {
    "gn:admin1_code":"05",
    "gn:admin2_code":"58",
    "gn:admin3_code":"56216000.0",
    "gn:asciiname":"Capuy",
    "gn:cc2":"PH",
    "gn:country_code":"PH",
    "gn:dem":51,
    "gn:feature_class":"P",
    "gn:feature_code":"PPL",
    "gn:name":"Capuy",
    "gn:population":0,
    "gn:timezone":"Asia/Manila",
    "iso:country":"PH",
    "name:und_x_variant":[
        "Capay",
        "Capuy"
    ],
    "wof:name":"Capuy",
    "wof:placetype":"locality"
},
  "geometry": {"coordinates":[123.93556,12.98083],"type":"Point"}
}