{
  "type": "Feature",
  "properties": {
    "gn:admin1_code":"05",
    "gn:admin2_code":"16",
    "gn:admin3_code":"51702000.0",
    "gn:asciiname":"Laganac",
    "gn:country_code":"PH",
    "gn:dem":352,
    "gn:feature_class":"P",
    "gn:feature_code":"PPL",
    "gn:name":"Laganac",
    "gn:population":0,
    "gn:timezone":"Asia/Manila",
    "iso:country":"PH",
    "name:fil_x_preferred":[
        "Laganac"
    ],
    "wof:name":"Laganac",
    "wof:placetype":"locality"
},
  "geometry": {"coordinates":[123.23333,13.35],"type":"Point"}
}