{
  "type": "Feature",
  "properties": {
    "gn:admin1_code":"15",
    "gn:admin2_code":"01",
    "gn:admin3_code":"140122000.0",
    "gn:asciiname":"Sabangan",
    "gn:country_code":"PH",
    "gn:dem":71,
    "gn:feature_class":"P",
    "gn:feature_code":"PPL",
    "gn:name":"Sabangan",
    "gn:population":0,
    "gn:timezone":"Asia/Manila",
    "iso:country":"PH",
    "name:bcl_x_preferred":[
        "Sabangan"
    ],
    "name:ceb_x_preferred":[
        "Sabangan"
    ],
    "name:deu_x_preferred":[
        "Sabangan"
    ],
    "name:fil_x_preferred":[
        "Sabangan"
    ],
    "name:fra_x_preferred":[
        "Sabangan"
    ],
    "name:ilo_x_preferred":[
        "Sabangan"
    ],
    "name:ind_x_preferred":[
        "Sabangan"
    ],
    "name:ita_x_preferred":[
        "Sabangan"
    ],
    "name:nld_x_preferred":[
        "Sabangan"
    ],
    "name:pag_x_preferred":[
        "Sabangan"
    ],
    "name:pam_x_preferred":[
        "Sabangan"
    ],
    "name:spa_x_preferred":[
        "Sabangan"
    ],
    "name:swe_x_preferred":[
        "Sabangan"
    ],
    "name:tgl_x_preferred":[
        "Sabangan"
    ],
    "name:urd_x_preferred":[
        "\u0633\u0628\u0646\u06af\u0646"
    ],
    "name:vie_x_preferred":[
        "Sabangan"
    ],
    "name:war_x_preferred":[
        "Sabangan"
    ],
    "wof:name":"Sabangan",
    "wof:placetype":"locality"
},
  "geometry": {"coordinates":[120.73390000000001,17.6762],"type":"Point"}
}