{
  "type": "Feature",
  "properties": {
    "gn:admin1_code":"41",
    "gn:admin2_code":"41",
    "gn:admin3_code":"175210000.0",
    "gn:asciiname":"Buhay Na Tubig",
    "gn:country_code":"PH",
    "gn:dem":18,
    "gn:feature_class":"P",
    "gn:feature_code":"PPL",
    "gn:name":"Buhay Na Tubig",
    "gn:population":0,
    "gn:timezone":"Asia/Manila",
    "iso:country":"PH",
    "name:fil_x_preferred":[
        "Buhay Na Tubig"
    ],
    "wof:name":"Buhay Na Tubig",
    "wof:placetype":"locality"
},
  "geometry": {"coordinates":[121.52042,13.14339],"type":"Point"}
}