{
  "type": "Feature",
  "properties": {
    "gn:admin1_code":"03",
    "gn:admin2_code":"50",
    "gn:admin3_code":"35416000.0",
    "gn:asciiname":"Juliana",
    "gn:country_code":"PH",
    "gn:dem":7,
    "gn:feature_class":"P",
    "gn:feature_code":"PPL",
    "gn:name":"Juliana",
    "gn:population":0,
    "gn:timezone":"Asia/Manila",
    "iso:country":"PH",
    "name:deu_x_preferred":[
        "Juliana"
    ],
    "name:epo_x_preferred":[
        "Juliana"
    ],
    "name:fin_x_preferred":[
        "Juliana"
    ],
    "name:lat_x_preferred":[
        "Juliana"
    ],
    "name:ltz_x_preferred":[
        "Juliana"
    ],
    "name:nld_x_preferred":[
        "Juliana"
    ],
    "name:pol_x_preferred":[
        "Juliana"
    ],
    "name:slk_x_preferred":[
        "Juliana"
    ],
    "name:slv_x_preferred":[
        "Juliana"
    ],
    "wof:name":"Juliana",
    "wof:placetype":"locality"
},
  "geometry": {"coordinates":[120.69061000000001,15.03433],"type":"Point"}
}