{
  "type": "Feature",
  "properties": {
    "gn:admin1_code":"01",
    "gn:admin2_code":"51",
    "gn:admin3_code":"15505000.0",
    "gn:asciiname":"Pingan",
    "gn:country_code":"PH",
    "gn:dem":15,
    "gn:feature_class":"P",
    "gn:feature_code":"PPL",
    "gn:name":"Pingan",
    "gn:population":0,
    "gn:timezone":"Asia/Manila",
    "iso:country":"PH",
    "name:fil_x_preferred":[
        "Pingan"
    ],
    "wof:name":"Pingan",
    "wof:placetype":"locality"
},
  "geometry": {"coordinates":[119.9816,16.2415],"type":"Point"}
}