{
  "type": "Feature",
  "properties": {
    "gn:country":"PH",
    "gn:fcode":"PPL",
    "gn:population":2778,
    "iso:country":"PH",
    "name:fil_x_preferred":[
        "Banaba"
    ],
    "qs:name":"Banaba",
    "qs:photos_9r":0,
    "qs:photos_sr":0,
    "qs:pop_sr":"4",
    "wof:name":"Banaba",
    "wof:placetype":"locality",
    "wof:population":2778
},
  "geometry": {"coordinates":[121.20999999999999,13.8966],"type":"Point"}
}