{
  "type": "Feature",
  "properties": {
    "gn:country":"PH",
    "gn:fcode":"PPLA3",
    "gn:population":3779,
    "iso:country":"PH",
    "name:bcl_x_preferred":[
        "Maimbung"
    ],
    "name:ceb_x_preferred":[
        "Maimbung"
    ],
    "name:deu_x_preferred":[
        "Maimbung"
    ],
    "name:eng_x_preferred":[
        "Maimbung"
    ],
    "name:fra_x_preferred":[
        "Maimbung"
    ],
    "name:ilo_x_preferred":[
        "Maimbung"
    ],
    "name:ind_x_preferred":[
        "Maimbung"
    ],
    "name:ita_x_preferred":[
        "Maimbung"
    ],
    "name:jpn_x_preferred":[
        "\u30de\u30a4\u30f3\u30d6\u30f3"
    ],
    "name:nld_x_preferred":[
        "Maimbung"
    ],
    "name:pag_x_preferred":[
        "Maimbung"
    ],
    "name:pam_x_preferred":[
        "Maimbung"
    ],
    "name:sco_x_preferred":[
        "Maimbung"
    ],
    "name:swe_x_preferred":[
        "Maimbung"
    ],
    "name:tgl_x_preferred":[
        "Maimbung"
    ],
    "name:und_x_variant":[
        "Maibun"
    ],
    "name:urd_x_preferred":[
        "\u0645\u0627\u06cc\u0645\u0628\u0648\u0646\u06af\u060c \u0633\u0648\u0644\u0648"
    ],
    "name:urd_x_variant":[
        "\u0645\u0627\u06cc\u0645\u0628\u0648\u0646\u06af"
    ],
    "name:vie_x_preferred":[
        "Maimbung"
    ],
    "name:war_x_preferred":[
        "Maimbung"
    ],
    "qs:name":"Maimbung",
    "qs:photos_9r":0,
    "qs:photos_sr":0,
    "qs:pop_sr":"4",
    "wof:name":"Maimbung",
    "wof:placetype":"locality",
    "wof:population":3779
},
  "geometry": {"coordinates":[121.02934999999999,5.9272],"type":"Point"}
}