{
  "type": "Feature",
  "properties": {
    "gn:admin1_code":"03",
    "gn:admin2_code":"63",
    "gn:admin3_code":"36904000.0",
    "gn:asciiname":"Maano",
    "gn:country_code":"PH",
    "gn:dem":188,
    "gn:feature_class":"P",
    "gn:feature_code":"PPL",
    "gn:name":"Maano",
    "gn:population":0,
    "gn:timezone":"Asia/Manila",
    "iso:country":"PH",
    "name:fil_x_preferred":[
        "Maano"
    ],
    "wof:name":"Maano",
    "wof:placetype":"locality"
},
  "geometry": {"coordinates":[120.40000000000001,15.31667],"type":"Point"}
}