{
  "type": "Feature",
  "properties": {
    "gn:admin1_code":"03",
    "gn:admin2_code":"13",
    "gn:admin3_code":"31423000.0",
    "gn:asciiname":"Camangyanan",
    "gn:country_code":"PH",
    "gn:dem":34,
    "gn:feature_class":"P",
    "gn:feature_code":"PPL",
    "gn:name":"Camangyanan",
    "gn:population":0,
    "gn:timezone":"Asia/Manila",
    "iso:country":"PH",
    "name:und_x_variant":[
        "Kamangyanan"
    ],
    "wof:name":"Camangyanan",
    "wof:placetype":"locality"
},
  "geometry": {"coordinates":[120.97307000000001,14.80389],"type":"Point"}
}