{
  "type": "Feature",
  "properties": {
    "gn:admin1_code":"01",
    "gn:admin2_code":"51",
    "gn:admin3_code":"15504000.0",
    "gn:asciiname":"Gugumbaen",
    "gn:country_code":"PH",
    "gn:dem":20,
    "gn:feature_class":"P",
    "gn:feature_code":"PPL",
    "gn:name":"Gugumbaen",
    "gn:population":0,
    "gn:timezone":"Asia/Manila",
    "iso:country":"PH",
    "name:fil_x_preferred":[
        "Gugumbaen"
    ],
    "wof:name":"Gugumbaen",
    "wof:placetype":"locality"
},
  "geometry": {"coordinates":[120.51833999999999,15.81902],"type":"Point"}
}