{
  "type": "Feature",
  "properties": {
    "gn:admin1_code":"08",
    "gn:admin2_code":"55",
    "gn:admin3_code":"86007000.0",
    "gn:asciiname":"Hampton",
    "gn:country_code":"PH",
    "gn:dem":30,
    "gn:feature_class":"P",
    "gn:feature_code":"PPL",
    "gn:name":"Hampton",
    "gn:population":0,
    "gn:timezone":"Asia/Manila",
    "iso:country":"PH",
    "name:bre_x_preferred":[
        "Hampton"
    ],
    "name:cat_x_preferred":[
        "Hampton"
    ],
    "name:ceb_x_preferred":[
        "Hampton"
    ],
    "name:ces_x_preferred":[
        "Hampton"
    ],
    "name:deu_x_preferred":[
        "Hampton"
    ],
    "name:fil_x_preferred":[
        "Hampton"
    ],
    "name:fin_x_preferred":[
        "Hampton"
    ],
    "name:fra_x_preferred":[
        "Hampton"
    ],
    "name:hin_x_preferred":[
        "\u0939\u0948\u0902\u092a\u091f\u0928"
    ],
    "name:hin_x_variant":[
        "\u0939\u0948\u092e\u094d\u092a\u091f\u0928"
    ],
    "name:hun_x_preferred":[
        "Hampton"
    ],
    "name:ind_x_preferred":[
        "Hampton"
    ],
    "name:ita_x_preferred":[
        "Hampton"
    ],
    "name:jpn_x_preferred":[
        "\u30cf\u30f3\u30d7\u30c8\u30f3"
    ],
    "name:kor_x_preferred":[
        "\ud584\ud504\ud134"
    ],
    "name:mlg_x_preferred":[
        "Hampton"
    ],
    "name:nld_x_preferred":[
        "Hampton"
    ],
    "name:pol_x_preferred":[
        "Hampton"
    ],
    "name:por_x_preferred":[
        "Hampton"
    ],
    "name:rus_x_preferred":[
        "\u0425\u0430\u043c\u043f\u0442\u043e\u043d"
    ],
    "name:spa_x_preferred":[
        "Hampton"
    ],
    "name:srp_x_preferred":[
        "\u0425\u0435\u043c\u043f\u0442\u043e\u043d"
    ],
    "name:swe_x_preferred":[
        "Hampton"
    ],
    "name:ukr_x_preferred":[
        "\u0413\u0435\u043c\u043f\u0442\u043e\u043d"
    ],
    "name:vol_x_preferred":[
        "Hampton"
    ],
    "name:zho_x_preferred":[
        "\u6c49\u666e\u987f"
    ],
    "wof:name":"Hampton",
    "wof:placetype":"locality"
},
  "geometry": {"coordinates":[124.8603,12.1069],"type":"Point"}
}