{
  "type": "Feature",
  "properties": {
    "gn:admin1_code":"08",
    "gn:admin2_code":"55",
    "gn:admin3_code":"86007000.0",
    "gn:asciiname":"Hampton",
    "gn:country_code":"PH",
    "gn:dem":30,
    "gn:feature_class":"P",
    "gn:feature_code":"PPL",
    "gn:name":"Hampton",
    "gn:population":0,
    "gn:timezone":"Asia/Manila",
    "iso:country":"PH",
    "name:fil_x_preferred":[
        "Hampton"
    ],
    "wof:name":"Hampton",
    "wof:placetype":"locality"
},
  "geometry": {"coordinates":[124.8603,12.1069],"type":"Point"}
}