{
  "type": "Feature",
  "properties": {
    "gn:admin1_code":"05",
    "gn:admin2_code":"39",
    "gn:admin3_code":"54102000.0",
    "gn:asciiname":"Malbug",
    "gn:country_code":"PH",
    "gn:dem":65,
    "gn:feature_class":"P",
    "gn:feature_code":"PPL",
    "gn:name":"Malbug",
    "gn:population":0,
    "gn:timezone":"Asia/Manila",
    "iso:country":"PH",
    "name:fil_x_preferred":[
        "Malbug"
    ],
    "wof:name":"Malbug",
    "wof:placetype":"locality"
},
  "geometry": {"coordinates":[123.50972,12.45833],"type":"Point"}
}