{
  "type": "Feature",
  "properties": {
    "gn:admin1_code":"01",
    "gn:admin2_code":"28",
    "gn:admin3_code":"12805000.0",
    "gn:asciiname":"Magnuang",
    "gn:country_code":"PH",
    "gn:dem":31,
    "gn:feature_class":"P",
    "gn:feature_code":"PPL",
    "gn:name":"Magnuang",
    "gn:population":0,
    "gn:timezone":"Asia/Manila",
    "iso:country":"PH",
    "name:fil_x_preferred":[
        "Magnuang"
    ],
    "name:fil_x_variant":[
        "Magnwang"
    ],
    "name:und_x_variant":[
        "Magnwang"
    ],
    "wof:name":"Magnuang",
    "wof:placetype":"locality"
},
  "geometry": {"coordinates":[120.536,18.0184],"type":"Point"}
}