{
  "type": "Feature",
  "properties": {
    "gn:admin1_code":"03",
    "gn:admin2_code":"07",
    "gn:admin3_code":"30805000.0",
    "gn:asciiname":"Tibuangan",
    "gn:country_code":"PH",
    "gn:dem":96,
    "gn:feature_class":"P",
    "gn:feature_code":"PPL",
    "gn:name":"Tibuangan",
    "gn:population":0,
    "gn:timezone":"Asia/Manila",
    "iso:country":"PH",
    "name:fil_x_preferred":[
        "Tibuangan"
    ],
    "wof:name":"Tibuangan",
    "wof:placetype":"locality"
},
  "geometry": {"coordinates":[120.45,14.81667],"type":"Point"}
}