{
  "type": "Feature",
  "properties": {
    "gn:admin1_code":"40",
    "gn:admin2_code":"H2",
    "gn:admin3_code":"45647000.0",
    "gn:asciiname":"Ayaas",
    "gn:country_code":"PH",
    "gn:dem":128,
    "gn:feature_class":"P",
    "gn:feature_code":"PPL",
    "gn:name":"Ayaas",
    "gn:population":0,
    "gn:timezone":"Asia/Manila",
    "iso:country":"PH",
    "name:fil_x_preferred":[
        "Ayaas"
    ],
    "wof:name":"Ayaas",
    "wof:placetype":"locality"
},
  "geometry": {"coordinates":[121.61920000000001,14.0223],"type":"Point"}
}