{
  "type": "Feature",
  "properties": {
    "gn:admin1_code":"01",
    "gn:admin2_code":"28",
    "gn:admin3_code":"12815000.0",
    "gn:asciiname":"Lusong",
    "gn:country_code":"PH",
    "gn:dem":6,
    "gn:feature_class":"P",
    "gn:feature_code":"PPL",
    "gn:name":"Lusong",
    "gn:population":0,
    "gn:timezone":"Asia/Manila",
    "iso:country":"PH",
    "name:fil_x_preferred":[
        "Lusong"
    ],
    "wof:name":"Lusong",
    "wof:placetype":"locality"
},
  "geometry": {"coordinates":[120.79470000000001,18.5708],"type":"Point"}
}