{
  "type": "Feature",
  "properties": {
    "gn:admin1_code":"01",
    "gn:admin2_code":"51",
    "gn:admin3_code":"15544000.0",
    "gn:asciiname":"Nancapian",
    "gn:country_code":"PH",
    "gn:dem":135,
    "gn:feature_class":"P",
    "gn:feature_code":"PPL",
    "gn:name":"Nancapian",
    "gn:population":0,
    "gn:timezone":"Asia/Manila",
    "iso:country":"PH",
    "name:fil_x_preferred":[
        "Nancapian"
    ],
    "wof:name":"Nancapian",
    "wof:placetype":"locality"
},
  "geometry": {"coordinates":[120.86667,15.93333],"type":"Point"}
}