{
  "type": "Feature",
  "properties": {
    "gn:admin1_code":"07",
    "gn:admin2_code":"21",
    "gn:admin3_code":"72222000.0",
    "gn:asciiname":"Kangwayan",
    "gn:country_code":"PH",
    "gn:dem":666,
    "gn:feature_class":"P",
    "gn:feature_code":"PPL",
    "gn:name":"Kangwayan",
    "gn:population":0,
    "gn:timezone":"Asia/Manila",
    "iso:country":"PH",
    "name:fil_x_preferred":[
        "Kangwayan"
    ],
    "wof:name":"Kangwayan",
    "wof:placetype":"locality"
},
  "geometry": {"coordinates":[123.46417,9.84361],"type":"Point"}
}