{
  "type": "Feature",
  "properties": {
    "gn:admin1_code":"08",
    "gn:admin2_code":"55",
    "gn:admin3_code":"86017000.0",
    "gn:asciiname":"Lomboy",
    "gn:country_code":"PH",
    "gn:dem":14,
    "gn:feature_class":"P",
    "gn:feature_code":"PPL",
    "gn:name":"Lomboy",
    "gn:population":0,
    "gn:timezone":"Asia/Manila",
    "iso:country":"PH",
    "name:fil_x_preferred":[
        "Lomboy"
    ],
    "wof:name":"Lomboy",
    "wof:placetype":"locality"
},
  "geometry": {"coordinates":[125.03082999999999,11.46222],"type":"Point"}
}