{
  "type": "Feature",
  "properties": {
    "gn:country":"PH",
    "gn:fcode":"PPL",
    "gn:pop":2082,
    "iso:country":"PH",
    "name:unk_x_variant":[
        "Binguan"
    ],
    "qs:name":"Binguang",
    "qs:photos_9r":0,
    "qs:photos_sr":0,
    "qs:pop_sr":"4",
    "wof:name":"Binguang",
    "wof:placetype":"locality",
    "wof:population":2082
},
  "geometry": {"coordinates":[121.78278,17.46194],"type":"Point"}
}