{
  "type": "Feature",
  "properties": {
    "gn:admin1_code":"15",
    "gn:admin2_code":"01",
    "gn:admin3_code":"140124000.0",
    "gn:asciiname":"Deet",
    "gn:country_code":"PH",
    "gn:dem":52,
    "gn:feature_class":"P",
    "gn:feature_code":"PPL",
    "gn:name":"Deet",
    "gn:population":0,
    "gn:timezone":"Asia/Manila",
    "iso:country":"PH",
    "name:fil_x_preferred":[
        "Deet"
    ],
    "wof:name":"Deet",
    "wof:placetype":"locality"
},
  "geometry": {"coordinates":[120.66030000000001,17.6176],"type":"Point"}
}