{
  "type": "Feature",
  "properties": {
    "gn:admin1_code":"03",
    "gn:admin2_code":"13",
    "gn:admin3_code":"31419000.0",
    "gn:asciiname":"Calawitan",
    "gn:country_code":"PH",
    "gn:dem":15,
    "gn:feature_class":"P",
    "gn:feature_code":"PPL",
    "gn:name":"Calawitan",
    "gn:population":0,
    "gn:timezone":"Asia/Manila",
    "iso:country":"PH",
    "name:fil_x_preferred":[
        "Calawitan-pulunggubat"
    ],
    "name:fil_x_variant":[
        "Calawitan Pulungqubat",
        "Calawitan",
        "Calauitan"
    ],
    "wof:name":"Calawitan",
    "wof:placetype":"locality"
},
  "geometry": {"coordinates":[120.91508,15.07668],"type":"Point"}
}