{
  "type": "Feature",
  "properties": {
    "gn:admin1_code":"10",
    "gn:admin2_code":"43",
    "gn:admin3_code":"104310000.0",
    "gn:asciiname":"Apas",
    "gn:country_code":"PH",
    "gn:dem":19,
    "gn:feature_class":"P",
    "gn:feature_code":"PPL",
    "gn:name":"Apas",
    "gn:population":0,
    "gn:timezone":"Asia/Manila",
    "iso:country":"PH",
    "name:ceb_x_preferred":[
        "Apas"
    ],
    "name:fil_x_preferred":[
        "Apas"
    ],
    "name:swe_x_preferred":[
        "Apas"
    ],
    "wof:name":"Apas",
    "wof:placetype":"locality"
},
  "geometry": {"coordinates":[124.32083,8.49278],"type":"Point"}
}