{
  "type": "Feature",
  "properties": {
    "gn:admin1_code":"41",
    "gn:admin2_code":"49",
    "gn:admin3_code":"175306000.0",
    "gn:asciiname":"Males",
    "gn:country_code":"PH",
    "gn:dem":19,
    "gn:elevation":"0.0",
    "gn:feature_class":"P",
    "gn:feature_code":"PPL",
    "gn:name":"Males",
    "gn:population":0,
    "gn:timezone":"Asia/Manila",
    "iso:country":"PH",
    "name:fil_x_preferred":[
        "Males"
    ],
    "name:und_x_variant":[
        "Malis"
    ],
    "wof:name":"Males",
    "wof:placetype":"locality"
},
  "geometry": {"coordinates":[117.69089,8.69291],"type":"Point"}
}