{
  "type": "Feature",
  "properties": {
    "gn:country":"PH",
    "gn:fcode":"PPL",
    "gn:pop":10955,
    "iso:country":"PH",
    "name:fil_x_preferred":[
        "Buanoy"
    ],
    "qs:name":"Buanoy",
    "qs:photos_9r":0,
    "qs:photos_sr":0,
    "qs:pop_sr":"6",
    "wof:name":"Buanoy",
    "wof:placetype":"locality",
    "wof:population":10955
},
  "geometry": {"coordinates":[123.6999,10.46746],"type":"Point"}
}