{
  "type": "Feature",
  "properties": {
    "gn:admin1_code":"06",
    "gn:admin2_code":"06",
    "gn:admin3_code":"60616000.0",
    "gn:asciiname":"Nazaret",
    "gn:country_code":"PH",
    "gn:dem":121,
    "gn:feature_class":"P",
    "gn:feature_code":"PPL",
    "gn:name":"Nazaret",
    "gn:population":0,
    "gn:timezone":"Asia/Manila",
    "iso:country":"PH",
    "name:fil_x_preferred":[
        "Nazaret"
    ],
    "wof:name":"Nazaret",
    "wof:placetype":"locality"
},
  "geometry": {"coordinates":[122.0386,10.7731],"type":"Point"}
}