{
  "type": "Feature",
  "properties": {
    "gn:country":"PH",
    "gn:fcode":"PPL",
    "gn:pop":2266,
    "iso:country":"PH",
    "name:unk_x_variant":[
        "Tococ"
    ],
    "qs:name":"Tococ East",
    "qs:photos_9r":0,
    "qs:photos_sr":0,
    "qs:pop_sr":"4",
    "wof:name":"Tococ East",
    "wof:placetype":"locality",
    "wof:population":2266
},
  "geometry": {"coordinates":[120.42605,15.82498],"type":"Point"}
}