{
  "type": "Feature",
  "properties": {
    "gn:admin1_code":"01",
    "gn:admin2_code":"28",
    "gn:admin3_code":"12815000.0",
    "gn:asciiname":"Balaorte",
    "gn:country_code":"PH",
    "gn:dem":33,
    "gn:feature_class":"P",
    "gn:feature_code":"PPL",
    "gn:name":"Balaorte",
    "gn:population":0,
    "gn:timezone":"Asia/Manila",
    "iso:country":"PH",
    "name:fil_x_preferred":[
        "Balaorte"
    ],
    "wof:name":"Balaorte",
    "wof:placetype":"locality"
},
  "geometry": {"coordinates":[120.8172,18.5589],"type":"Point"}
}