{
  "type": "Feature",
  "properties": {
    "gn:admin1_code":"07",
    "gn:admin2_code":"21",
    "gn:admin3_code":"72248000.0",
    "gn:asciiname":"Mabuli",
    "gn:country_code":"PH",
    "gn:dem":4,
    "gn:feature_class":"P",
    "gn:feature_code":"PPL",
    "gn:name":"Mabuli",
    "gn:population":0,
    "gn:timezone":"Asia/Manila",
    "iso:country":"PH",
    "name:fil_x_preferred":[
        "Mabuli"
    ],
    "wof:name":"Mabuli",
    "wof:placetype":"locality"
},
  "geometry": {"coordinates":[124.03333000000001,10.95],"type":"Point"}
}