{
  "type": "Feature",
  "properties": {
    "gn:admin1_code":"15",
    "gn:admin2_code":"10",
    "gn:admin3_code":"141101000.0",
    "gn:asciiname":"Segebe",
    "gn:country_code":"PH",
    "gn:dem":1725,
    "gn:feature_class":"P",
    "gn:feature_code":"PPL",
    "gn:name":"Segebe",
    "gn:population":0,
    "gn:timezone":"Asia/Manila",
    "iso:country":"PH",
    "name:fil_x_preferred":[
        "Segebe"
    ],
    "wof:name":"Segebe",
    "wof:placetype":"locality"
},
  "geometry": {"coordinates":[120.6953,16.5317],"type":"Point"}
}