{
  "type": "Feature",
  "properties": {
    "gn:admin1_code":"09",
    "gn:admin2_code":"ZSI",
    "gn:admin3_code":"98312000.0",
    "gn:asciiname":"Kulambugan",
    "gn:country_code":"PH",
    "gn:dem":12,
    "gn:feature_class":"P",
    "gn:feature_code":"PPL",
    "gn:name":"Kulambugan",
    "gn:population":0,
    "gn:timezone":"Asia/Manila",
    "iso:country":"PH",
    "name:fil_x_preferred":[
        "Kulambugan"
    ],
    "name:und_x_variant":[
        "Kolambogan",
        "Kulambogan"
    ],
    "wof:name":"Kulambugan",
    "wof:placetype":"locality"
},
  "geometry": {"coordinates":[122.46903,7.65262],"type":"Point"}
}