{
  "type": "Feature",
  "properties": {
    "gn:country":"PH",
    "gn:fcode":"PPL",
    "gn:pop":2564,
    "iso:country":"PH",
    "name:fil_x_preferred":[
        "Masonogan"
    ],
    "name:unk_x_variant":[
        "Nasonugan"
    ],
    "qs:name":"Masonogan",
    "qs:photos_9r":0,
    "qs:photos_sr":0,
    "qs:pop_sr":"4",
    "wof:name":"Masonogan",
    "wof:placetype":"locality",
    "wof:population":2564
},
  "geometry": {"coordinates":[122.67529999999999,11.3686],"type":"Point"}
}