{
  "type": "Feature",
  "properties": {
    "gn:admin1_code":"02",
    "gn:admin2_code":"31",
    "gn:admin3_code":"23108000.0",
    "gn:asciiname":"Carabatan Chica",
    "gn:country_code":"PH",
    "gn:dem":49,
    "gn:feature_class":"P",
    "gn:feature_code":"PPL",
    "gn:name":"Carabatan Chica",
    "gn:population":0,
    "gn:timezone":"Asia/Manila",
    "iso:country":"PH",
    "name:fil_x_preferred":[
        "Carabbatan Chica"
    ],
    "wof:name":"Carabatan Chica",
    "wof:placetype":"locality"
},
  "geometry": {"coordinates":[121.77421,16.95525],"type":"Point"}
}