{
  "type": "Feature",
  "properties": {
    "gn:admin1_code":"01",
    "gn:admin2_code":"29",
    "gn:admin3_code":"12927000.0",
    "gn:asciiname":"Ambucao",
    "gn:country_code":"PH",
    "gn:dem":5,
    "gn:feature_class":"P",
    "gn:feature_code":"PPL",
    "gn:name":"Ambucao",
    "gn:population":0,
    "gn:timezone":"Asia/Manila",
    "iso:country":"PH",
    "name:fil_x_preferred":[
        "Ambucao"
    ],
    "name:fil_x_variant":[
        "Ambocao"
    ],
    "name:und_x_variant":[
        "Ambocao"
    ],
    "wof:name":"Ambucao",
    "wof:placetype":"locality"
},
  "geometry": {"coordinates":[120.42440000000001,17.2968],"type":"Point"}
}