{
  "type": "Feature",
  "properties": {
    "gn:admin1_code":"41",
    "gn:admin2_code":"54",
    "gn:admin3_code":"175905000.0",
    "gn:asciiname":"Agbatong",
    "gn:country_code":"PH",
    "gn:dem":50,
    "gn:feature_class":"P",
    "gn:feature_code":"PPL",
    "gn:name":"Agbatong",
    "gn:population":0,
    "gn:timezone":"Asia/Manila",
    "iso:country":"PH",
    "name:fil_x_preferred":[
        "Agbatong"
    ],
    "wof:name":"Agbatong",
    "wof:placetype":"locality"
},
  "geometry": {"coordinates":[121.70752,12.91091],"type":"Point"}
}