{
  "type": "Feature",
  "properties": {
    "gn:admin1_code":"40",
    "gn:admin2_code":"H2",
    "gn:admin3_code":"45610000.0",
    "gn:asciiname":"Balangson",
    "gn:country_code":"PH",
    "gn:dem":73,
    "gn:feature_class":"P",
    "gn:feature_code":"PPL",
    "gn:name":"Balangson",
    "gn:population":0,
    "gn:timezone":"Asia/Manila",
    "iso:country":"PH",
    "name:fil_x_preferred":[
        "Balangson"
    ],
    "name:fil_x_variant":[
        "Bulagsong"
    ],
    "name:und_x_variant":[
        "Balangsong"
    ],
    "wof:name":"Balangson",
    "wof:placetype":"locality"
},
  "geometry": {"coordinates":[122.2775,13.6327],"type":"Point"}
}