{
  "type": "Feature",
  "properties": {
    "gn:admin1_code":"02",
    "gn:admin2_code":"14",
    "gn:admin3_code":"21519000.0",
    "gn:asciiname":"Sisim",
    "gn:country_code":"PH",
    "gn:dem":49,
    "gn:feature_class":"P",
    "gn:feature_code":"PPL",
    "gn:name":"Sisim",
    "gn:population":0,
    "gn:timezone":"Asia/Manila",
    "iso:country":"PH",
    "name:fil_x_preferred":[
        "Sisim"
    ],
    "wof:name":"Sisim",
    "wof:placetype":"locality"
},
  "geometry": {"coordinates":[121.81325,17.62712999999999],"type":"Point"}
}