{
  "type": "Feature",
  "properties": {
    "gn:admin1_code":"07",
    "gn:admin2_code":"11",
    "gn:admin3_code":"71240000.0",
    "gn:asciiname":"Dusita",
    "gn:country_code":"PH",
    "gn:dem":339,
    "gn:feature_class":"P",
    "gn:feature_code":"PPL",
    "gn:name":"Dusita",
    "gn:population":0,
    "gn:timezone":"Asia/Manila",
    "iso:country":"PH",
    "name:fil_x_preferred":[
        "Dusita"
    ],
    "wof:name":"Dusita",
    "wof:placetype":"locality"
},
  "geometry": {"coordinates":[124.33110000000001,9.7835],"type":"Point"}
}