{
  "type": "Feature",
  "properties": {
    "gn:admin1_code":"07",
    "gn:admin2_code":"46",
    "gn:admin3_code":"74622000.0",
    "gn:asciiname":"Legarda",
    "gn:country_code":"PH",
    "gn:dem":241,
    "gn:feature_class":"P",
    "gn:feature_code":"PPL",
    "gn:name":"Legarda",
    "gn:population":0,
    "gn:timezone":"Asia/Manila",
    "iso:country":"PH",
    "name:fil_x_preferred":[
        "Legarda"
    ],
    "wof:name":"Legarda",
    "wof:placetype":"locality"
},
  "geometry": {"coordinates":[123.13849999999999,9.904],"type":"Point"}
}