{
  "type": "Feature",
  "properties": {
    "gn:admin1_code":"07",
    "gn:admin2_code":"46",
    "gn:admin3_code":"74622000.0",
    "gn:asciiname":"Legarda",
    "gn:country_code":"PH",
    "gn:dem":241,
    "gn:feature_class":"P",
    "gn:feature_code":"PPL",
    "gn:name":"Legarda",
    "gn:population":0,
    "gn:timezone":"Asia/Manila",
    "iso:country":"PH",
    "name:arg_x_preferred":[
        "Legarda"
    ],
    "name:ast_x_preferred":[
        "Legarda"
    ],
    "name:bre_x_preferred":[
        "Legarda"
    ],
    "name:cat_x_preferred":[
        "Legarda"
    ],
    "name:ceb_x_preferred":[
        "Legarda"
    ],
    "name:eus_x_preferred":[
        "Legarda"
    ],
    "name:fil_x_preferred":[
        "Legarda"
    ],
    "name:fra_x_preferred":[
        "Legarda"
    ],
    "name:hun_x_preferred":[
        "Legarda"
    ],
    "name:ita_x_preferred":[
        "Legarda"
    ],
    "name:msa_x_preferred":[
        "Legarda"
    ],
    "name:nld_x_preferred":[
        "Legarda"
    ],
    "name:oci_x_preferred":[
        "Legarda"
    ],
    "name:pol_x_preferred":[
        "Legarda"
    ],
    "name:por_x_preferred":[
        "Legarda"
    ],
    "name:rus_x_preferred":[
        "\u041b\u0435\u0433\u0430\u0440\u0434\u0430"
    ],
    "name:spa_x_preferred":[
        "Legarda"
    ],
    "name:swe_x_preferred":[
        "Legarda"
    ],
    "name:ukr_x_preferred":[
        "\u041b\u0435\u0433\u0430\u0440\u0434\u0430"
    ],
    "name:uzb_x_preferred":[
        "Legarda"
    ],
    "name:vie_x_preferred":[
        "Legarda"
    ],
    "name:war_x_preferred":[
        "Legarda"
    ],
    "name:zho_x_preferred":[
        "\u83b1\u52a0\u5c14\u8fbe"
    ],
    "wof:name":"Legarda",
    "wof:placetype":"locality"
},
  "geometry": {"coordinates":[123.13849999999999,9.904],"type":"Point"}
}