{
  "type": "Feature",
  "properties": {
    "gn:admin1_code":"06",
    "gn:admin2_code":"H3",
    "gn:admin3_code":"64510000.0",
    "gn:asciiname":"Tayuman",
    "gn:country_code":"PH",
    "gn:dem":8,
    "gn:feature_class":"P",
    "gn:feature_code":"PPL",
    "gn:name":"Tayuman",
    "gn:population":0,
    "gn:timezone":"Asia/Manila",
    "iso:country":"PH",
    "name:fil_x_preferred":[
        "Tayuman"
    ],
    "name:fil_x_variant":[
        "Tuyuman"
    ],
    "wof:name":"Tayuman",
    "wof:placetype":"locality"
},
  "geometry": {"coordinates":[122.8596,10.0717],"type":"Point"}
}