{
  "type": "Feature",
  "properties": {
    "gn:admin1_code":"12",
    "gn:admin2_code":"57",
    "gn:admin3_code":"124701000.0",
    "gn:asciiname":"Marakabak",
    "gn:country_code":"PH",
    "gn:dem":1114,
    "gn:feature_class":"P",
    "gn:feature_code":"PPL",
    "gn:name":"Marakabak",
    "gn:population":0,
    "gn:timezone":"Asia/Manila",
    "iso:country":"PH",
    "name:und_x_variant":[
        "Marikabag",
        "Marakabak"
    ],
    "wof:name":"Marakabak",
    "wof:placetype":"locality"
},
  "geometry": {"coordinates":[124.59976,7.53017],"type":"Point"}
}