{
  "type": "Feature",
  "properties": {
    "gn:admin1_code":"01",
    "gn:admin2_code":"28",
    "gn:admin3_code":"12805000.0",
    "gn:asciiname":"Busel",
    "gn:country_code":"PH",
    "gn:dem":29,
    "gn:feature_class":"P",
    "gn:feature_code":"PPL",
    "gn:name":"Busel",
    "gn:population":0,
    "gn:timezone":"Asia/Manila",
    "iso:country":"PH",
    "name:fil_x_preferred":[
        "Busel"
    ],
    "wof:name":"Busel",
    "wof:placetype":"locality"
},
  "geometry": {"coordinates":[120.5916,18.0581],"type":"Point"}
}