{
  "type": "Feature",
  "properties": {
    "gn:admin1_code":"03",
    "gn:admin2_code":"13",
    "gn:asciiname":"Lalom",
    "gn:country_code":"PH",
    "gn:dem":9,
    "gn:feature_class":"P",
    "gn:feature_code":"PPL",
    "gn:name":"Lalom",
    "gn:population":0,
    "gn:timezone":"Asia/Manila",
    "iso:country":"PH",
    "name:ceb_x_preferred":[
        "L\u0101lom"
    ],
    "name:fas_x_preferred":[
        "\u0644\u0627\u0644\u0645"
    ],
    "name:fil_x_preferred":[
        "Lalom"
    ],
    "name:msa_x_preferred":[
        "Lalom"
    ],
    "name:swe_x_preferred":[
        "L\u0101lom"
    ],
    "name:ukr_x_preferred":[
        "\u041b\u0430\u043b\u043e\u043c"
    ],
    "name:urd_x_preferred":[
        "\u0644\u0627\u0644\u0648\u0645"
    ],
    "wof:name":"Lalom",
    "wof:placetype":"locality"
},
  "geometry": {"coordinates":[121.1643,13.378],"type":"Point"}
}