{
  "type": "Feature",
  "properties": {
    "gn:admin1_code":"07",
    "gn:admin2_code":"46",
    "gn:admin3_code":"74621000.0",
    "gn:asciiname":"Nuevo",
    "gn:country_code":"PH",
    "gn:dem":11,
    "gn:feature_class":"P",
    "gn:feature_code":"PPL",
    "gn:name":"Nuevo",
    "gn:population":0,
    "gn:timezone":"Asia/Manila",
    "iso:country":"PH",
    "name:fil_x_preferred":[
        "Nuevo"
    ],
    "wof:name":"Nuevo",
    "wof:placetype":"locality"
},
  "geometry": {"coordinates":[123.09999999999999,9.53333],"type":"Point"}
}