{
  "type": "Feature",
  "properties": {
    "gn:admin1_code":"14",
    "gn:admin2_code":"60",
    "gn:admin3_code":"156610000.0",
    "gn:asciiname":"Andaran",
    "gn:country_code":"PH",
    "gn:dem":280,
    "gn:feature_class":"P",
    "gn:feature_code":"PPL",
    "gn:name":"Andaran",
    "gn:population":0,
    "gn:timezone":"Asia/Manila",
    "iso:country":"PH",
    "name:und_x_variant":[
        "Andalan"
    ],
    "wof:name":"Andaran",
    "wof:placetype":"locality"
},
  "geometry": {"coordinates":[121.16257,5.80368],"type":"Point"}
}