{
  "type": "Feature",
  "properties": {
    "gn:country":"PH",
    "gn:fcode":"PPL",
    "gn:population":2772,
    "iso:country":"PH",
    "name:fil_x_preferred":[
        "Liboran"
    ],
    "name:und_x_variant":[
        "Liburan"
    ],
    "qs:name":"Liboran",
    "qs:photos_9r":0,
    "qs:photos_sr":0,
    "qs:pop_sr":"4",
    "wof:name":"Liboran",
    "wof:placetype":"locality",
    "wof:population":2772
},
  "geometry": {"coordinates":[124.64888999999999,8.35472],"type":"Point"}
}