{
  "type": "Feature",
  "properties": {
    "gn:admin1_code":"41",
    "gn:admin2_code":"41",
    "gn:admin3_code":"175210000.0",
    "gn:asciiname":"Magulon",
    "gn:country_code":"PH",
    "gn:dem":50,
    "gn:feature_class":"P",
    "gn:feature_code":"PPL",
    "gn:name":"Magulon",
    "gn:population":0,
    "gn:timezone":"Asia/Manila",
    "iso:country":"PH",
    "name:eng_x_preferred":[
        "Magulon"
    ],
    "name:und_x_variant":[
        "Magulong"
    ],
    "wof:name":"Magulon",
    "wof:placetype":"locality"
},
  "geometry": {"coordinates":[121.44302,13.19779],"type":"Point"}
}