{
  "type": "Feature",
  "properties": {
    "gn:country":"PH",
    "gn:fcode":"ADM3",
    "gn:population":26793,
    "iso:country":"PH",
    "name:bcl_x_preferred":[
        "Macalelon"
    ],
    "name:cat_x_preferred":[
        "Macalelon"
    ],
    "name:ceb_x_preferred":[
        "Macalelon"
    ],
    "name:deu_x_preferred":[
        "Macalelon"
    ],
    "name:eng_x_preferred":[
        "Macalelon"
    ],
    "name:fil_x_preferred":[
        "Macalelon"
    ],
    "name:fra_x_preferred":[
        "Macalelon"
    ],
    "name:ilo_x_preferred":[
        "Macalelon"
    ],
    "name:ind_x_preferred":[
        "Macalelon"
    ],
    "name:ita_x_preferred":[
        "Macalelon"
    ],
    "name:jpn_x_preferred":[
        "\u30de\u30ab\u30ec\u30ed\u30f3"
    ],
    "name:nld_x_preferred":[
        "Macalelon"
    ],
    "name:nob_x_preferred":[
        "Macalelon"
    ],
    "name:oci_x_preferred":[
        "Macalelon"
    ],
    "name:pag_x_preferred":[
        "Macalelon"
    ],
    "name:pam_x_preferred":[
        "Macalelon"
    ],
    "name:spa_x_preferred":[
        "Macalelon"
    ],
    "name:swe_x_preferred":[
        "Macalelon"
    ],
    "name:tgl_x_preferred":[
        "Macalelon"
    ],
    "name:vie_x_preferred":[
        "Macalelon"
    ],
    "name:war_x_preferred":[
        "Macalelon"
    ],
    "qs:name":"Macalelon",
    "qs:photos_9r":0,
    "qs:photos_sr":0,
    "qs:pop_sr":"7",
    "wd:wordcount":270,
    "wof:name":"Macalelon",
    "wof:placetype":"localadmin",
    "wof:population":26793
},
  "geometry": {"coordinates":[122.16667,13.78333],"type":"Point"}
}