{
  "type": "Feature",
  "properties": {
    "gn:admin1_code":"06",
    "gn:admin2_code":"18",
    "gn:admin3_code":"61912000.0",
    "gn:asciiname":"Pina",
    "gn:country_code":"PH",
    "gn:dem":4,
    "gn:feature_class":"P",
    "gn:feature_code":"PPL",
    "gn:name":"Pi\u00f1a",
    "gn:population":0,
    "gn:timezone":"Asia/Manila",
    "iso:country":"PH",
    "name:fil_x_preferred":[
        "Pi\u00f1a"
    ],
    "wof:name":"Pina",
    "wof:placetype":"locality"
},
  "geometry": {"coordinates":[122.81667,11.48333],"type":"Point"}
}