{
  "type": "Feature",
  "properties": {
    "gn:admin1_code":"01",
    "gn:admin2_code":"29",
    "gn:admin3_code":"12921000.0",
    "gn:asciiname":"Nagtupacan",
    "gn:country_code":"PH",
    "gn:dem":4,
    "gn:feature_class":"P",
    "gn:feature_code":"PPL",
    "gn:name":"Nagtupacan",
    "gn:population":0,
    "gn:timezone":"Asia/Manila",
    "iso:country":"PH",
    "name:fil_x_preferred":[
        "Nagtapacan"
    ],
    "name:fil_x_variant":[
        "Nagtupacan"
    ],
    "wof:name":"Nagtupacan",
    "wof:placetype":"locality"
},
  "geometry": {"coordinates":[120.352,17.60796000000001],"type":"Point"}
}