{
  "type": "Feature",
  "properties": {
    "gn:admin1_code":"14",
    "gn:admin2_code":"35",
    "gn:admin3_code":"153624000.0",
    "gn:asciiname":"Panalawan",
    "gn:country_code":"PH",
    "gn:dem":782,
    "gn:feature_class":"P",
    "gn:feature_code":"PPL",
    "gn:name":"Panalawan",
    "gn:population":0,
    "gn:timezone":"Asia/Manila",
    "iso:country":"PH",
    "name:fil_x_preferred":[
        "Panalawan"
    ],
    "wof:name":"Panalawan",
    "wof:placetype":"locality"
},
  "geometry": {"coordinates":[124.36667,8.01667],"type":"Point"}
}