{
  "type": "Feature",
  "properties": {
    "gn:admin1_code":"02",
    "gn:admin2_code":"14",
    "gn:admin3_code":"21514000.0",
    "gn:asciiname":"Magim",
    "gn:country_code":"PH",
    "gn:dem":242,
    "gn:feature_class":"P",
    "gn:feature_code":"PPL",
    "gn:name":"Magim",
    "gn:population":0,
    "gn:timezone":"Asia/Manila",
    "iso:country":"PH",
    "name:fil_x_preferred":[
        "Magim"
    ],
    "wof:name":"Magim",
    "wof:placetype":"locality"
},
  "geometry": {"coordinates":[122.13333,18.31667],"type":"Point"}
}