{
  "type": "Feature",
  "properties": {
    "gn:admin1_code":"09",
    "gn:admin2_code":"66",
    "gn:admin3_code":"97313000.0",
    "gn:asciiname":"Dansol",
    "gn:country_code":"PH",
    "gn:dem":266,
    "gn:feature_class":"P",
    "gn:feature_code":"PPL",
    "gn:name":"Dansol",
    "gn:population":0,
    "gn:timezone":"Asia/Manila",
    "iso:country":"PH",
    "name:eng_x_preferred":[
        "Dansol"
    ],
    "wof:name":"Dansol",
    "wof:placetype":"locality"
},
  "geometry": {"coordinates":[123.22199999999999,7.657],"type":"Point"}
}