{
  "type": "Feature",
  "properties": {
    "gn:admin1_code":"40",
    "gn:admin2_code":"09",
    "gn:admin3_code":"41005000.0",
    "gn:asciiname":"Kumintang Ilaya",
    "gn:country_code":"PH",
    "gn:dem":15,
    "gn:feature_class":"P",
    "gn:feature_code":"PPL",
    "gn:name":"Kumintang Ilaya",
    "gn:population":0,
    "gn:timezone":"Asia/Manila",
    "iso:country":"PH",
    "name:fil_x_preferred":[
        "Kumintang Ilaya"
    ],
    "wof:name":"Kumintang Ilaya",
    "wof:placetype":"locality"
},
  "geometry": {"coordinates":[121.0675,13.7626],"type":"Point"}
}