{
  "type": "Feature",
  "properties": {
    "gn:admin1_code":"15",
    "gn:admin2_code":"27",
    "gn:admin3_code":"142709000.0",
    "gn:asciiname":"Pagong",
    "gn:country_code":"PH",
    "gn:dem":736,
    "gn:feature_class":"P",
    "gn:feature_code":"PPL",
    "gn:name":"Pagong",
    "gn:population":0,
    "gn:timezone":"Asia/Manila",
    "iso:country":"PH",
    "name:fil_x_preferred":[
        "Pagong"
    ],
    "wof:name":"Pagong",
    "wof:placetype":"locality"
},
  "geometry": {"coordinates":[121.09264,16.82826],"type":"Point"}
}