{
  "type": "Feature",
  "properties": {
    "gn:admin1_code":"01",
    "gn:admin2_code":"29",
    "gn:admin3_code":"12904000.0",
    "gn:asciiname":"Manaboc",
    "gn:country_code":"PH",
    "gn:dem":32,
    "gn:feature_class":"P",
    "gn:feature_code":"PPL",
    "gn:name":"Manaboc",
    "gn:population":0,
    "gn:timezone":"Asia/Manila",
    "iso:country":"PH",
    "name:fil_x_preferred":[
        "Manaboc"
    ],
    "name:fil_x_variant":[
        "Manabuc",
        "Manabac"
    ],
    "name:und_x_variant":[
        "Manabuc",
        "Manabac"
    ],
    "wof:name":"Manaboc",
    "wof:placetype":"locality"
},
  "geometry": {"coordinates":[120.51730000000001,17.3348],"type":"Point"}
}