{
  "type": "Feature",
  "properties": {
    "gn:country":"PH",
    "gn:fcode":"PPL",
    "gn:pop":2205,
    "iso:country":"PH",
    "name:fil_x_preferred":[
        "Kuanos"
    ],
    "name:unk_x_variant":[
        "Cuanos"
    ],
    "qs:name":"Kuanos",
    "qs:photos_9r":0,
    "qs:photos_sr":0,
    "qs:pop_sr":"4",
    "wof:name":"Kuanos",
    "wof:placetype":"locality",
    "wof:population":2205
},
  "geometry": {"coordinates":[123.78,10.28298],"type":"Point"}
}