{
  "type": "Feature",
  "properties": {
    "gn:admin1_code":"15",
    "gn:admin2_code":"32",
    "gn:admin3_code":"143214000.0",
    "gn:asciiname":"Lubo",
    "gn:country_code":"PH",
    "gn:dem":589,
    "gn:feature_class":"P",
    "gn:feature_code":"PPL",
    "gn:name":"Lubo",
    "gn:population":0,
    "gn:timezone":"Asia/Manila",
    "iso:country":"PH",
    "name:fil_x_preferred":[
        "Lubo"
    ],
    "wof:name":"Lubo",
    "wof:placetype":"locality"
},
  "geometry": {"coordinates":[121.2299,17.266],"type":"Point"}
}