{
  "type": "Feature",
  "properties": {
    "gn:admin1_code":"41",
    "gn:admin2_code":"40",
    "gn:admin3_code":"175111000.0",
    "gn:asciiname":"Pogoso",
    "gn:country_code":"PH",
    "gn:dem":18,
    "gn:feature_class":"P",
    "gn:feature_code":"PPL",
    "gn:name":"Pogoso",
    "gn:population":0,
    "gn:timezone":"Asia/Manila",
    "iso:country":"PH",
    "name:fil_x_preferred":[
        "Pogoso"
    ],
    "name:und_x_variant":[
        "Pagasa"
    ],
    "wof:name":"Pogoso",
    "wof:placetype":"locality"
},
  "geometry": {"coordinates":[120.77500000000001,13.0868],"type":"Point"}
}