{
  "type": "Feature",
  "properties": {
    "gn:admin1_code":"05",
    "gn:admin2_code":"39",
    "gn:admin3_code":"54112000.0",
    "gn:asciiname":"Palanas",
    "gn:country_code":"PH",
    "gn:dem":96,
    "gn:feature_class":"P",
    "gn:feature_code":"PPL",
    "gn:name":"Palanas",
    "gn:population":0,
    "gn:timezone":"Asia/Manila",
    "iso:country":"PH",
    "name:fil_x_preferred":[
        "Palanas"
    ],
    "wof:name":"Palanas",
    "wof:placetype":"locality"
},
  "geometry": {"coordinates":[123.38191,12.23374],"type":"Point"}
}