{
  "type": "Feature",
  "properties": {
    "gn:admin1_code":"10",
    "gn:admin2_code":"43",
    "gn:admin3_code":"104323000.0",
    "gn:asciiname":"Alicomoban",
    "gn:country_code":"PH",
    "gn:dem":166,
    "gn:feature_class":"P",
    "gn:feature_code":"PPL",
    "gn:name":"Alicomoban",
    "gn:population":0,
    "gn:timezone":"Asia/Manila",
    "iso:country":"PH",
    "name:fil_x_preferred":[
        "Alicomoban"
    ],
    "wof:name":"Alicomoban",
    "wof:placetype":"locality"
},
  "geometry": {"coordinates":[124.78722,8.94139],"type":"Point"}
}