{
  "type": "Feature",
  "properties": {
    "gn:admin1_code":"02",
    "gn:admin2_code":"31",
    "gn:admin3_code":"23123000.0",
    "gn:asciiname":"Villa Bulusan",
    "gn:country_code":"PH",
    "gn:dem":59,
    "gn:feature_class":"P",
    "gn:feature_code":"PPL",
    "gn:name":"Villa Bulusan",
    "gn:population":0,
    "gn:timezone":"Asia/Manila",
    "iso:country":"PH",
    "name:fil_x_preferred":[
        "Villa Bulusan"
    ],
    "wof:name":"Villa Bulusan",
    "wof:placetype":"locality"
},
  "geometry": {"coordinates":[121.68214,17.14254],"type":"Point"}
}