{
  "type": "Feature",
  "properties": {
    "gn:admin1_code":"15",
    "gn:admin2_code":"H6",
    "gn:admin3_code":"148104000.0",
    "gn:asciiname":"Guinabon",
    "gn:country_code":"PH",
    "gn:dem":135,
    "gn:feature_class":"P",
    "gn:feature_code":"PPL",
    "gn:name":"Guinabon",
    "gn:population":0,
    "gn:timezone":"Asia/Manila",
    "iso:country":"PH",
    "name:fil_x_preferred":[
        "Guinabon"
    ],
    "name:fil_x_variant":[
        "Guinabong"
    ],
    "wof:name":"Guinabon",
    "wof:placetype":"locality"
},
  "geometry": {"coordinates":[121.2011,17.9639],"type":"Point"}
}