{
  "type": "Feature",
  "properties": {
    "gn:admin1_code":"07",
    "gn:admin2_code":"11",
    "gn:admin3_code":"71229000.0",
    "gn:asciiname":"Gotoson",
    "gn:country_code":"PH",
    "gn:dem":105,
    "gn:elevation":"0.0",
    "gn:feature_class":"P",
    "gn:feature_code":"PPL",
    "gn:name":"Gotoson",
    "gn:population":0,
    "gn:timezone":"Asia/Manila",
    "iso:country":"PH",
    "name:fil_x_preferred":[
        "Gotoson"
    ],
    "name:und_x_variant":[
        "Gotozon"
    ],
    "wof:name":"Gotoson",
    "wof:placetype":"locality"
},
  "geometry": {"coordinates":[124.03806000000002,9.6497],"type":"Point"}
}