{
  "type": "Feature",
  "properties": {
    "gn:admin1_code":"02",
    "gn:admin2_code":"14",
    "gn:admin3_code":"21509000.0",
    "gn:asciiname":"Dilam",
    "gn:country_code":"PH",
    "gn:dem":63,
    "gn:feature_class":"P",
    "gn:feature_code":"PPL",
    "gn:name":"Dilam",
    "gn:population":0,
    "gn:timezone":"Asia/Manila",
    "iso:country":"PH",
    "name:fil_x_preferred":[
        "Dilam"
    ],
    "wof:name":"Dilam",
    "wof:placetype":"locality"
},
  "geometry": {"coordinates":[121.45332000000001,19.3727],"type":"Point"}
}