{
  "type": "Feature",
  "properties": {
    "gn:admin1_code":"14",
    "gn:admin2_code":"35",
    "gn:admin3_code":"153622000.0",
    "gn:asciiname":"Bubong",
    "gn:country_code":"PH",
    "gn:dem":727,
    "gn:feature_class":"P",
    "gn:feature_code":"PPL",
    "gn:name":"Bubong",
    "gn:population":0,
    "gn:timezone":"Asia/Manila",
    "iso:country":"PH",
    "name:fil_x_preferred":[
        "Bubong"
    ],
    "wof:name":"Bubong",
    "wof:placetype":"locality"
},
  "geometry": {"coordinates":[124.34860999999999,7.83083],"type":"Point"}
}