{
  "type": "Feature",
  "properties": {
    "gn:admin1_code":"03",
    "gn:admin2_code":"64",
    "gn:admin3_code":"37112000.0",
    "gn:asciiname":"Mabanglit",
    "gn:country_code":"PH",
    "gn:dem":31,
    "gn:feature_class":"P",
    "gn:feature_code":"PPL",
    "gn:name":"Mabanglit",
    "gn:population":0,
    "gn:timezone":"Asia/Manila",
    "iso:country":"PH",
    "name:fil_x_preferred":[
        "Mabanglit"
    ],
    "wof:name":"Mabanglit",
    "wof:placetype":"locality"
},
  "geometry": {"coordinates":[120.13333,15.01667],"type":"Point"}
}