{
  "type": "Feature",
  "properties": {
    "gn:admin1_code":"40",
    "gn:admin2_code":"09",
    "gn:admin3_code":"41015000.0",
    "gn:asciiname":"Nagatlarin",
    "gn:country_code":"PH",
    "gn:dem":17,
    "gn:feature_class":"P",
    "gn:feature_code":"PPL",
    "gn:name":"Nagatlarin",
    "gn:population":0,
    "gn:timezone":"Asia/Manila",
    "iso:country":"PH",
    "name:fil_x_preferred":[
        "Nagatlarin"
    ],
    "wof:name":"Nagatlarin",
    "wof:placetype":"locality"
},
  "geometry": {"coordinates":[121.22629999999999,13.635],"type":"Point"}
}