{
  "type": "Feature",
  "properties": {
    "gn:country":"PH",
    "gn:fcode":"ADM3",
    "gn:population":44687,
    "iso:country":"PH",
    "name:aze_x_preferred":[
        "San-\u0130sidro"
    ],
    "name:cat_x_preferred":[
        "San Isidro"
    ],
    "name:ceb_x_preferred":[
        "San Isidro"
    ],
    "name:deu_x_preferred":[
        "San Isidro"
    ],
    "name:eus_x_preferred":[
        "San Isidro"
    ],
    "name:fil_x_preferred":[
        "San Isidro"
    ],
    "name:fra_x_preferred":[
        "San Isidro"
    ],
    "name:ilo_x_preferred":[
        "San Isidro"
    ],
    "name:ita_x_preferred":[
        "San Isidro"
    ],
    "name:lit_x_preferred":[
        "San Isidras"
    ],
    "name:mlg_x_preferred":[
        "San Isidro"
    ],
    "name:nds_x_preferred":[
        "San Isidro"
    ],
    "name:nld_x_preferred":[
        "San Isidro"
    ],
    "name:pol_x_preferred":[
        "San Isidro"
    ],
    "name:por_x_preferred":[
        "San Isidro"
    ],
    "name:rus_x_preferred":[
        "\u0421\u0430\u043d-\u0418\u0441\u0438\u0434\u0440\u043e"
    ],
    "name:sco_x_preferred":[
        "San Isidro"
    ],
    "name:spa_x_preferred":[
        "San Isidro"
    ],
    "name:srp_x_preferred":[
        "\u0421\u0430\u043d \u0418\u0441\u0438\u0434\u0440\u043e"
    ],
    "name:swe_x_preferred":[
        "San Isidro"
    ],
    "name:vie_x_preferred":[
        "San Isidro"
    ],
    "name:war_x_preferred":[
        "San Isidro"
    ],
    "qs_pg:aaroncc":"PH",
    "qs_pg:gn_country":"PH",
    "qs_pg:gn_fcode":"ADM3",
    "qs_pg:gn_pop":44687,
    "qs_pg:name":"San Isidro",
    "qs_pg:photos_9r":0,
    "qs_pg:photos_sr":0,
    "qs_pg:pop_sr":7,
    "qs_pg:qs_pg_placetype":"localadmin",
    "wof:name":"San Isidro",
    "wof:placetype":"localadmin",
    "wof:population":44687
},
  "geometry": {"coordinates":[120.90000000000001,15.28333],"type":"Point"}
}