{
  "type": "Feature",
  "properties": {
    "gn:gn_country":"PH",
    "gn:gn_fcode":"ADM3",
    "gn:gn_pop":44687,
    "gn:population":44687,
    "iso:country":"PH",
    "name:fil_x_preferred":[
        "San Isidro"
    ],
    "qs_pg:aaroncc":"PH",
    "qs_pg:gn_country":"PH",
    "qs_pg:gn_fcode":"ADM3",
    "qs_pg:gn_pop":44687,
    "qs_pg:name":"San Isidro",
    "qs_pg:photos_9r":0,
    "qs_pg:photos_sr":0,
    "qs_pg:pop_sr":7,
    "qs_pg:qs_pg_placetype":"localadmin",
    "wof:name":"San Isidro",
    "wof:placetype":"localadmin",
    "wof:population":44687
},
  "geometry": {"coordinates":[120.90000000000001,15.28333],"type":"Point"}
}