{
  "type": "Feature",
  "properties": {
    "gn:admin1_code":"01",
    "gn:admin2_code":"36",
    "gn:admin3_code":"13303000.0",
    "gn:asciiname":"Calaotit",
    "gn:country_code":"PH",
    "gn:dem":20,
    "gn:feature_class":"P",
    "gn:feature_code":"PPL",
    "gn:name":"Calaotit",
    "gn:population":0,
    "gn:timezone":"Asia/Manila",
    "iso:country":"PH",
    "name:fil_x_preferred":[
        "Calaotit"
    ],
    "name:fil_x_variant":[
        "Calautit"
    ],
    "wof:name":"Calaotit",
    "wof:placetype":"locality"
},
  "geometry": {"coordinates":[120.381,16.7492],"type":"Point"}
}