{
  "type": "Feature",
  "properties": {
    "gn:admin1_code":"06",
    "gn:admin2_code":"30",
    "gn:admin3_code":"63037000.0",
    "gn:asciiname":"Porag",
    "gn:country_code":"PH",
    "gn:dem":30,
    "gn:feature_class":"P",
    "gn:feature_code":"PPL",
    "gn:name":"Porag",
    "gn:population":0,
    "gn:timezone":"Asia/Manila",
    "iso:country":"PH",
    "name:asm_x_preferred":[
        "\u09aa\u09f0\u09be\u0997"
    ],
    "name:fil_x_preferred":[
        "Porag"
    ],
    "name:und_x_variant":[
        "Porog",
        "Porog-Sal\u00f1gan"
    ],
    "wof:name":"Porag",
    "wof:placetype":"locality"
},
  "geometry": {"coordinates":[122.6148,10.9317],"type":"Point"}
}