{
  "type": "Feature",
  "properties": {
    "gn:admin1_code":"09",
    "gn:admin2_code":"ZSI",
    "gn:admin3_code":"98303000.0",
    "gn:asciiname":"Manangon",
    "gn:country_code":"PH",
    "gn:dem":30,
    "gn:feature_class":"P",
    "gn:feature_code":"PPL",
    "gn:name":"Manangon",
    "gn:population":0,
    "gn:timezone":"Asia/Manila",
    "iso:country":"PH",
    "name:fil_x_preferred":[
        "Manangon"
    ],
    "wof:name":"Manangon",
    "wof:placetype":"locality"
},
  "geometry": {"coordinates":[122.97556000000002,7.73889],"type":"Point"}
}