{
  "type": "Feature",
  "properties": {
    "gn:admin1_code":"08",
    "gn:admin2_code":"55",
    "gn:admin3_code":"86017000.0",
    "gn:asciiname":"Mansulung",
    "gn:country_code":"PH",
    "gn:dem":28,
    "gn:feature_class":"P",
    "gn:feature_code":"PPL",
    "gn:name":"Mansulung",
    "gn:population":0,
    "gn:timezone":"Asia/Manila",
    "iso:country":"PH",
    "name:fil_x_preferred":[
        "Mansulung"
    ],
    "wof:name":"Mansulung",
    "wof:placetype":"locality"
},
  "geometry": {"coordinates":[124.90860000000001,11.4908],"type":"Point"}
}