{
  "type": "Feature",
  "properties": {
    "gn:admin1_code":"14",
    "gn:admin2_code":"22",
    "gn:admin3_code":"150702000.0",
    "gn:asciiname":"Buhesapa",
    "gn:country_code":"PH",
    "gn:dem":166,
    "gn:feature_class":"P",
    "gn:feature_code":"PPL",
    "gn:name":"Buhesapa",
    "gn:population":0,
    "gn:timezone":"Asia/Manila",
    "iso:country":"PH",
    "name:fil_x_preferred":[
        "Buhesapa"
    ],
    "wof:name":"Buhesapa",
    "wof:placetype":"locality"
},
  "geometry": {"coordinates":[122.10389000000001,6.58722],"type":"Point"}
}