{
  "type": "Feature",
  "properties": {
    "gn:admin1_code":"02",
    "gn:admin2_code":"31",
    "gn:admin3_code":"23120000.0",
    "gn:asciiname":"Villa Paz",
    "gn:country_code":"PH",
    "gn:dem":79,
    "gn:feature_class":"P",
    "gn:feature_code":"PPL",
    "gn:name":"Villa Paz",
    "gn:population":0,
    "gn:timezone":"Asia/Manila",
    "iso:country":"PH",
    "name:fil_x_preferred":[
        "Villa Paz"
    ],
    "name:und_x_variant":[
        "Villapas"
    ],
    "wof:name":"Villa Paz",
    "wof:placetype":"locality"
},
  "geometry": {"coordinates":[121.88097,17.02185],"type":"Point"}
}