{
  "type": "Feature",
  "properties": {
    "gn:country":"PH",
    "gn:fcode":"ADM3",
    "gn:population":21168,
    "iso:country":"PH",
    "name:bcl_x_preferred":[
        "Tampilisan"
    ],
    "name:ceb_x_preferred":[
        "Tampilisan"
    ],
    "name:deu_x_preferred":[
        "Tampilisan"
    ],
    "name:fra_x_preferred":[
        "Tampilisan"
    ],
    "name:ilo_x_preferred":[
        "Tampilisan"
    ],
    "name:ind_x_preferred":[
        "Tampilisan"
    ],
    "name:ita_x_preferred":[
        "Tampilisan"
    ],
    "name:nld_x_preferred":[
        "Tampilisan"
    ],
    "name:pag_x_preferred":[
        "Tampilisan"
    ],
    "name:pam_x_preferred":[
        "Tampilisan"
    ],
    "name:spa_x_preferred":[
        "Tampilisan"
    ],
    "name:swe_x_preferred":[
        "Tampilisan"
    ],
    "name:tgl_x_preferred":[
        "Tampilisan"
    ],
    "name:vie_x_preferred":[
        "Tampilisan"
    ],
    "name:war_x_preferred":[
        "Tampilisan"
    ],
    "qs_pg:aaroncc":"PH",
    "qs_pg:gn_country":"PH",
    "qs_pg:gn_fcode":"ADM3",
    "qs_pg:gn_pop":21168,
    "qs_pg:name":"Tampilisan",
    "qs_pg:photos_9r":0,
    "qs_pg:photos_sr":0,
    "qs_pg:pop_sr":7,
    "qs_pg:qs_pg_placetype":"localadmin",
    "wof:name":"Tampilisan",
    "wof:placetype":"localadmin",
    "wof:population":21168
},
  "geometry": {"coordinates":[122.68333,8.01667],"type":"Point"}
}