{
  "type": "Feature",
  "properties": {
    "gn:admin1_code":"01",
    "gn:admin2_code":"51",
    "gn:admin3_code":"15523000.0",
    "gn:asciiname":"Cabanaetan",
    "gn:country_code":"PH",
    "gn:dem":37,
    "gn:feature_class":"P",
    "gn:feature_code":"PPL",
    "gn:name":"Cabanaetan",
    "gn:population":0,
    "gn:timezone":"Asia/Manila",
    "iso:country":"PH",
    "name:fil_x_preferred":[
        "Cabanaetan"
    ],
    "name:und_x_variant":[
        "Cabanaitan",
        "Cabanaetan"
    ],
    "wof:name":"Cabanaetan",
    "wof:placetype":"locality"
},
  "geometry": {"coordinates":[119.8841,16.1263],"type":"Point"}
}