{
  "type": "Feature",
  "properties": {
    "gn:admin1_code":"03",
    "gn:admin2_code":"13",
    "gn:admin3_code":"31422000.0",
    "gn:asciiname":"Pulo",
    "gn:country_code":"PH",
    "gn:dem":39,
    "gn:feature_class":"P",
    "gn:feature_code":"PPL",
    "gn:name":"Pulo",
    "gn:population":0,
    "gn:timezone":"Asia/Manila",
    "iso:country":"PH",
    "name:und_x_variant":[
        "Dulo",
        "Pulo"
    ],
    "wof:name":"Pulo",
    "wof:placetype":"locality"
},
  "geometry": {"coordinates":[120.99427,14.96426],"type":"Point"}
}