{
  "type": "Feature",
  "properties": {
    "gn:admin1_code":"40",
    "gn:admin2_code":"09",
    "gn:admin3_code":"41005000.0",
    "gn:asciiname":"Catandala",
    "gn:country_code":"PH",
    "gn:dem":114,
    "gn:feature_class":"P",
    "gn:feature_code":"PPL",
    "gn:name":"Catandala",
    "gn:population":0,
    "gn:timezone":"Asia/Manila",
    "iso:country":"PH",
    "wof:name":"Catandala",
    "wof:placetype":"locality"
},
  "geometry": {"coordinates":[121.13333,13.76667],"type":"Point"}
}