{
  "type": "Feature",
  "properties": {
    "gn:admin1_code":"08",
    "gn:admin2_code":"67",
    "gn:admin3_code":"84820000.0",
    "gn:asciiname":"Coroconog",
    "gn:country_code":"PH",
    "gn:dem":16,
    "gn:feature_class":"P",
    "gn:feature_code":"PPL",
    "gn:name":"Coroconog",
    "gn:population":0,
    "gn:timezone":"Asia/Manila",
    "iso:country":"PH",
    "name:fil_x_preferred":[
        "Coroconog"
    ],
    "wof:name":"Coroconog",
    "wof:placetype":"locality"
},
  "geometry": {"coordinates":[124.9053,12.5102],"type":"Point"}
}