{
  "type": "Feature",
  "properties": {
    "gn:admin1_code":"01",
    "gn:admin2_code":"51",
    "gn:admin3_code":"15517000.0",
    "gn:asciiname":"Bued",
    "gn:country_code":"PH",
    "gn:dem":8,
    "gn:feature_class":"P",
    "gn:feature_code":"PPL",
    "gn:name":"Bued",
    "gn:population":0,
    "gn:timezone":"Asia/Manila",
    "iso:country":"PH",
    "name:fil_x_preferred":[
        "Bued"
    ],
    "wof:name":"Bued",
    "wof:placetype":"locality"
},
  "geometry": {"coordinates":[120.3715,16.01805],"type":"Point"}
}