{
  "type": "Feature",
  "properties": {
    "gn:admin1_code":"03",
    "gn:admin2_code":"63",
    "gn:admin3_code":"36904000.0",
    "gn:asciiname":"Calumpit",
    "gn:country_code":"PH",
    "gn:dem":60,
    "gn:feature_class":"P",
    "gn:feature_code":"PPL",
    "gn:name":"Calumpit",
    "gn:population":0,
    "gn:timezone":"Asia/Manila",
    "iso:country":"PH",
    "name:bcl_x_preferred":[
        "Calumpit"
    ],
    "name:ceb_x_preferred":[
        "Calumpit"
    ],
    "name:deu_x_preferred":[
        "Calumpit"
    ],
    "name:fil_x_preferred":[
        "Calumpit"
    ],
    "name:fra_x_preferred":[
        "Calumpit"
    ],
    "name:ilo_x_preferred":[
        "Calumpit"
    ],
    "name:ind_x_preferred":[
        "Calumpit"
    ],
    "name:ita_x_preferred":[
        "Calumpit"
    ],
    "name:nld_x_preferred":[
        "Calumpit"
    ],
    "name:nor_x_preferred":[
        "Calumpit"
    ],
    "name:pag_x_preferred":[
        "Calumpit"
    ],
    "name:pam_x_preferred":[
        "Calumpit"
    ],
    "name:pol_x_preferred":[
        "Calumpit"
    ],
    "name:spa_x_preferred":[
        "Calumpit"
    ],
    "name:tgl_x_preferred":[
        "Calumpit"
    ],
    "name:urd_x_preferred":[
        "\u06a9\u0627\u0644\u0648\u0645\u067e\u06cc\u062a"
    ],
    "name:vie_x_preferred":[
        "Calumpit"
    ],
    "name:war_x_preferred":[
        "Calumpit"
    ],
    "name:zho_x_preferred":[
        "\u52a0\u502b\u7b46"
    ],
    "wof:name":"Calumpit",
    "wof:placetype":"locality"
},
  "geometry": {"coordinates":[120.56373000000001,15.35036],"type":"Point"}
}