{
  "type": "Feature",
  "properties": {
    "gn:country":"PH",
    "gn:fcode":"ADM3",
    "gn:population":18733,
    "iso:country":"PH",
    "name:fil_x_preferred":[
        "Balilihan"
    ],
    "qs:name":"Balilihan",
    "qs:photos_9r":0,
    "qs:photos_sr":0,
    "qs:pop_sr":"6",
    "wof:name":"Balilihan",
    "wof:placetype":"localadmin",
    "wof:population":18733
},
  "geometry": {"coordinates":[123.98333,9.75],"type":"Point"}
}