{
  "type": "Feature",
  "properties": {
    "iso:country":"PH",
    "name:bcl_x_preferred":[
        "Luisiana"
    ],
    "name:cat_x_preferred":[
        "Luisiana"
    ],
    "name:cbk_zam_x_preferred":[
        "Luisiana"
    ],
    "name:ceb_x_preferred":[
        "Luisiana"
    ],
    "name:deu_x_preferred":[
        "Luisiana"
    ],
    "name:dut_x_preferred":[
        "Luisiana"
    ],
    "name:eng_x_preferred":[
        "Luisiana"
    ],
    "name:fil_x_preferred":[
        "Luisiana"
    ],
    "name:fre_x_preferred":[
        "Luisiana"
    ],
    "name:ger_x_preferred":[
        "Luisiana"
    ],
    "name:ilo_x_preferred":[
        "Luisiana"
    ],
    "name:ind_x_preferred":[
        "Luisiana"
    ],
    "name:ita_x_preferred":[
        "Luisiana"
    ],
    "name:nld_x_preferred":[
        "Luisiana"
    ],
    "name:oci_x_preferred":[
        "Luisiana"
    ],
    "name:pag_x_preferred":[
        "Luisiana"
    ],
    "name:pam_x_preferred":[
        "Luisiana"
    ],
    "name:swe_x_preferred":[
        "Luisiana"
    ],
    "name:tgl_x_preferred":[
        "Luisiana"
    ],
    "name:vie_x_preferred":[
        "Luisiana"
    ],
    "name:war_x_preferred":[
        "Luisiana"
    ],
    "qs:gn_country":"PH",
    "qs:gn_fcode":"PPLA3",
    "qs:gn_pop":4554,
    "qs:name":"Luisiana",
    "qs:name_adm0":"Philippines",
    "qs:name_adm1":"Calabarzon",
    "qs:photos":0,
    "qs:photos_1k":0,
    "qs:photos_9k":1,
    "qs:photos_9r":1,
    "qs:photos_all":3,
    "qs:photos_sr":0,
    "qs:placetype":"Town",
    "qs:pop_sr":"4",
    "qs:woe_adm0":23424934,
    "wd:wordcount":1131,
    "wof:name":"Luisiana",
    "wof:placetype":"locality",
    "wof:population":4554
},
  "geometry": {"coordinates":[121.51090000000001,14.185],"type":"Point"}
}