{
  "type": "Feature",
  "properties": {
    "gn:admin1_code":"03",
    "gn:admin2_code":"07",
    "gn:admin3_code":"30809000.0",
    "gn:asciiname":"Butarero",
    "gn:country_code":"PH",
    "gn:dem":204,
    "gn:feature_class":"P",
    "gn:feature_code":"PPL",
    "gn:name":"Butarero",
    "gn:population":0,
    "gn:timezone":"Asia/Manila",
    "iso:country":"PH",
    "name:fil_x_preferred":[
        "Butarero"
    ],
    "wof:name":"Butarero",
    "wof:placetype":"locality"
},
  "geometry": {"coordinates":[120.45,14.78333],"type":"Point"}
}