{
  "type": "Feature",
  "properties": {
    "gn:admin1_code":"15",
    "gn:admin2_code":"01",
    "gn:admin3_code":"140127000.0",
    "gn:asciiname":"Denden",
    "gn:country_code":"PH",
    "gn:dem":316,
    "gn:feature_class":"P",
    "gn:feature_code":"PPL",
    "gn:name":"Denden",
    "gn:population":0,
    "gn:timezone":"Asia/Manila",
    "iso:country":"PH",
    "name:ara_x_preferred":[
        "\u062f\u064a\u0646\u062f\u0646"
    ],
    "name:fas_x_preferred":[
        "\u062f\u0646\u062f\u0646"
    ],
    "name:fil_x_preferred":[
        "Denden"
    ],
    "name:fra_x_preferred":[
        "Denden"
    ],
    "name:ita_x_preferred":[
        "Denden"
    ],
    "name:jpn_x_preferred":[
        "\u3067\u3093\u3067\u3093"
    ],
    "name:rus_x_preferred":[
        "\u0414\u044d\u043d\u0434\u044d\u043d"
    ],
    "name:spa_x_preferred":[
        "Denden"
    ],
    "wof:name":"Denden",
    "wof:placetype":"locality"
},
  "geometry": {"coordinates":[120.63333,17.41667],"type":"Point"}
}