{
  "type": "Feature",
  "properties": {
    "gn:admin1_code":"08",
    "gn:admin2_code":"55",
    "gn:admin3_code":"86021000.0",
    "gn:asciiname":"Santo Nino",
    "gn:country_code":"PH",
    "gn:dem":4,
    "gn:feature_class":"P",
    "gn:feature_code":"PPL",
    "gn:name":"Santo Nino",
    "gn:population":0,
    "gn:timezone":"Asia/Manila",
    "iso:country":"PH",
    "name:fil_x_preferred":[
        "Santo Nino"
    ],
    "wof:name":"Santo Nino",
    "wof:placetype":"locality"
},
  "geometry": {"coordinates":[124.9622,11.5814],"type":"Point"}
}