{
  "type": "Feature",
  "properties": {
    "gn:admin1_code":"41",
    "gn:admin2_code":"49",
    "gn:asciiname":"Campang",
    "gn:country_code":"PH",
    "gn:dem":37,
    "gn:feature_class":"P",
    "gn:feature_code":"PPL",
    "gn:name":"Campang",
    "gn:population":0,
    "gn:timezone":"Asia/Manila",
    "iso:country":"PH",
    "name:eng_x_preferred":[
        "Campang"
    ],
    "name:und_x_variant":[
        "Kaumpang"
    ],
    "wof:name":"Campang",
    "wof:placetype":"locality"
},
  "geometry": {"coordinates":[118.44629999999999,7.028],"type":"Point"}
}