{
  "type": "Feature",
  "properties": {
    "gn:admin1_code":"01",
    "gn:admin2_code":"29",
    "gn:admin3_code":"12928000.0",
    "gn:asciiname":"Naglaoa-An",
    "gn:country_code":"PH",
    "gn:dem":10,
    "gn:feature_class":"P",
    "gn:feature_code":"PPL",
    "gn:name":"Naglaoa-An",
    "gn:population":0,
    "gn:timezone":"Asia/Manila",
    "iso:country":"PH",
    "name:fil_x_preferred":[
        "Naglaoaan"
    ],
    "name:fil_x_variant":[
        "Naglaoa-An"
    ],
    "wof:name":"Naglaoa-An",
    "wof:placetype":"locality"
},
  "geometry": {"coordinates":[120.37366000000002,17.63412000000001],"type":"Point"}
}