{
  "type": "Feature",
  "properties": {
    "gn:admin1_code":"03",
    "gn:admin2_code":"64",
    "gn:admin3_code":"37105000.0",
    "gn:asciiname":"San Augustin",
    "gn:country_code":"PH",
    "gn:dem":12,
    "gn:feature_class":"P",
    "gn:feature_code":"PPL",
    "gn:name":"San Augustin",
    "gn:population":0,
    "gn:timezone":"Asia/Manila",
    "iso:country":"PH",
    "name:fil_x_preferred":[
        "San Augustin"
    ],
    "name:und_x_variant":[
        "San Agustin"
    ],
    "wof:name":"San Augustin",
    "wof:placetype":"locality"
},
  "geometry": {"coordinates":[119.9486,15.3756],"type":"Point"}
}