{
  "type": "Feature",
  "properties": {
    "gn:admin1_code":"40",
    "gn:admin2_code":"H2",
    "gn:admin3_code":"45617000.0",
    "gn:asciiname":"Lupa",
    "gn:country_code":"PH",
    "gn:dem":24,
    "gn:feature_class":"P",
    "gn:feature_code":"PPL",
    "gn:name":"Lupa",
    "gn:population":0,
    "gn:timezone":"Asia/Manila",
    "iso:country":"PH",
    "name:bul_x_preferred":[
        "\u041b\u0443\u043f\u0430"
    ],
    "name:ceb_x_preferred":[
        "Lupa"
    ],
    "name:ces_x_preferred":[
        "Lupa"
    ],
    "name:deu_x_preferred":[
        "Lupa"
    ],
    "name:fil_x_preferred":[
        "Lupa"
    ],
    "name:ita_x_preferred":[
        "Lupa"
    ],
    "name:lit_x_preferred":[
        "L\u016bpa"
    ],
    "name:pol_x_preferred":[
        "Lupa"
    ],
    "name:rus_x_preferred":[
        "\u041b\u0443\u043f\u0430"
    ],
    "name:slk_x_preferred":[
        "Lupa"
    ],
    "name:srp_x_preferred":[
        "Lupa"
    ],
    "name:swe_x_preferred":[
        "Lupa"
    ],
    "name:tgl_x_preferred":[
        "Lupa"
    ],
    "name:tur_x_preferred":[
        "Lupa"
    ],
    "name:ukr_x_preferred":[
        "\u041b\u0443\u043f\u0430"
    ],
    "wof:name":"Lupa",
    "wof:placetype":"locality"
},
  "geometry": {"coordinates":[121.61686,14.80516],"type":"Point"}
}