{
  "type": "Feature",
  "properties": {
    "gn:admin1_code":"02",
    "gn:admin2_code":"31",
    "gn:admin3_code":"23104000.0",
    "gn:asciiname":"Capuseran",
    "gn:country_code":"PH",
    "gn:dem":102,
    "gn:feature_class":"P",
    "gn:feature_code":"PPL",
    "gn:name":"Capuseran",
    "gn:population":0,
    "gn:timezone":"Asia/Manila",
    "iso:country":"PH",
    "name:fil_x_preferred":[
        "Capuseran"
    ],
    "name:und_x_variant":[
        "Capurocan"
    ],
    "wof:name":"Capuseran",
    "wof:placetype":"locality"
},
  "geometry": {"coordinates":[121.9755,16.82325],"type":"Point"}
}