{
  "type": "Feature",
  "properties": {
    "gn:admin1_code":"05",
    "gn:admin2_code":"19",
    "gn:admin3_code":"52010000.0",
    "gn:asciiname":"Ananong",
    "gn:country_code":"PH",
    "gn:dem":280,
    "gn:feature_class":"P",
    "gn:feature_code":"PPL",
    "gn:name":"Ananong",
    "gn:population":0,
    "gn:timezone":"Asia/Manila",
    "iso:country":"PH",
    "name:fil_x_preferred":[
        "Ananong"
    ],
    "wof:name":"Ananong",
    "wof:placetype":"locality"
},
  "geometry": {"coordinates":[124.31667,13.85],"type":"Point"}
}