{
  "type": "Feature",
  "properties": {
    "gn:admin1_code":"06",
    "gn:admin2_code":"06",
    "gn:admin3_code":"60616000.0",
    "gn:asciiname":"Nasunugan",
    "gn:country_code":"PH",
    "gn:dem":70,
    "gn:feature_class":"P",
    "gn:feature_code":"PPL",
    "gn:name":"Nasunugan",
    "gn:population":0,
    "gn:timezone":"Asia/Manila",
    "iso:country":"PH",
    "name:fil_x_preferred":[
        "Nasunugan"
    ],
    "wof:name":"Nasunugan",
    "wof:placetype":"locality"
},
  "geometry": {"coordinates":[122.0519,10.8013],"type":"Point"}
}