{
  "type": "Feature",
  "properties": {
    "gn:admin1_code":"03",
    "gn:admin2_code":"13",
    "gn:admin3_code":"31421000.0",
    "gn:asciiname":"Sacdalan",
    "gn:country_code":"PH",
    "gn:dem":18,
    "gn:feature_class":"P",
    "gn:feature_code":"PPL",
    "gn:name":"Sacdalan",
    "gn:population":0,
    "gn:timezone":"Asia/Manila",
    "iso:country":"PH",
    "name:fil_x_preferred":[
        "Sacdalan"
    ],
    "wof:name":"Sacdalan",
    "wof:placetype":"locality"
},
  "geometry": {"coordinates":[120.95708999999999,15.20415],"type":"Point"}
}