{
  "type": "Feature",
  "properties": {
    "gn:admin1_code":"06",
    "gn:admin2_code":"30",
    "gn:admin3_code":"63023000.0",
    "gn:asciiname":"Balanao",
    "gn:country_code":"PH",
    "gn:dem":98,
    "gn:feature_class":"P",
    "gn:feature_code":"PPL",
    "gn:name":"Balanao",
    "gn:population":0,
    "gn:timezone":"Asia/Manila",
    "iso:country":"PH",
    "name:fil_x_preferred":[
        "Balanao"
    ],
    "wof:name":"Balanao",
    "wof:placetype":"locality"
},
  "geometry": {"coordinates":[122.4717,10.9586],"type":"Point"}
}