{
  "type": "Feature",
  "properties": {
    "gn:admin1_code":"40",
    "gn:admin2_code":"09",
    "gn:admin3_code":"41007000.0",
    "gn:asciiname":"Sugod",
    "gn:country_code":"PH",
    "gn:dem":127,
    "gn:feature_class":"P",
    "gn:feature_code":"PPL",
    "gn:name":"Sugod",
    "gn:population":0,
    "gn:timezone":"Asia/Manila",
    "iso:country":"PH",
    "name:und_x_variant":[
        "Sukol",
        "Sugod"
    ],
    "wof:name":"Sugod",
    "wof:placetype":"locality"
},
  "geometry": {"coordinates":[120.77821000000002,13.99052],"type":"Point"}
}