{
  "type": "Feature",
  "properties": {
    "gn:admin1_code":"12",
    "gn:admin2_code":"70",
    "gn:admin3_code":"126318000.0",
    "gn:asciiname":"Norala Barrio Doce",
    "gn:country_code":"PH",
    "gn:dem":136,
    "gn:feature_class":"P",
    "gn:feature_code":"PPL",
    "gn:name":"Norala Barrio Doce",
    "gn:population":0,
    "gn:timezone":"Asia/Manila",
    "iso:country":"PH",
    "name:fil_x_preferred":[
        "Norala Barrio Doce"
    ],
    "wof:name":"Norala Barrio Doce",
    "wof:placetype":"locality"
},
  "geometry": {"coordinates":[124.68167,6.4575],"type":"Point"}
}