{
  "type": "Feature",
  "properties": {
    "gn:admin1_code":"40",
    "gn:admin2_code":"09",
    "gn:admin3_code":"41011000.0",
    "gn:asciiname":"Balakit",
    "gn:country_code":"PH",
    "gn:dem":247,
    "gn:feature_class":"P",
    "gn:feature_code":"PPL",
    "gn:name":"Balakit",
    "gn:population":0,
    "gn:timezone":"Asia/Manila",
    "iso:country":"PH",
    "name:fil_x_preferred":[
        "Balakit"
    ],
    "wof:name":"Balakit",
    "wof:placetype":"locality"
},
  "geometry": {"coordinates":[120.89385,14.02148],"type":"Point"}
}