{
  "type": "Feature",
  "properties": {
    "gn:admin1_code":"03",
    "gn:admin2_code":"50",
    "gn:admin3_code":"35414000.0",
    "gn:asciiname":"Maniango",
    "gn:country_code":"PH",
    "gn:dem":5,
    "gn:feature_class":"P",
    "gn:feature_code":"PPL",
    "gn:name":"Maniango",
    "gn:population":0,
    "gn:timezone":"Asia/Manila",
    "iso:country":"PH",
    "wof:name":"Maniango",
    "wof:placetype":"locality"
},
  "geometry": {"coordinates":[120.65597,14.93893],"type":"Point"}
}