{
  "type": "Feature",
  "properties": {
    "gn:admin1_code":"12",
    "gn:admin2_code":"B8",
    "gn:asciiname":"Lidiobong",
    "gn:country_code":"PH",
    "gn:dem":5,
    "gn:feature_class":"P",
    "gn:feature_code":"PPL",
    "gn:name":"Lidiobong",
    "gn:population":0,
    "gn:timezone":"Asia/Manila",
    "iso:country":"PH",
    "wof:name":"Lidiobong",
    "wof:placetype":"locality"
},
  "geometry": {"coordinates":[124.30194,7.16806],"type":"Point"}
}