{
  "type": "Feature",
  "properties": {
    "gn:admin1_code":"06",
    "gn:admin2_code":"30",
    "gn:admin3_code":"63042000.0",
    "gn:asciiname":"General Luna",
    "gn:country_code":"PH",
    "gn:dem":143,
    "gn:feature_class":"P",
    "gn:feature_code":"PPL",
    "gn:name":"General Luna",
    "gn:population":0,
    "gn:timezone":"Asia/Manila",
    "iso:country":"PH",
    "name:eng_x_preferred":[
        "General Luna"
    ],
    "wof:name":"General Luna",
    "wof:placetype":"locality"
},
  "geometry": {"coordinates":[122.8788,11.1676],"type":"Point"}
}