{
  "type": "Feature",
  "properties": {
    "gn:admin1_code":"05",
    "gn:admin2_code":"39",
    "gn:admin3_code":"54113000.0",
    "gn:asciiname":"Mapalanas",
    "gn:country_code":"PH",
    "gn:dem":106,
    "gn:elevation":"0.0",
    "gn:feature_class":"P",
    "gn:feature_code":"PPL",
    "gn:name":"Mapalanas",
    "gn:population":0,
    "gn:timezone":"Asia/Manila",
    "iso:country":"PH",
    "name:fil_x_preferred":[
        "Mapalanas"
    ],
    "wof:name":"Mapalanas",
    "wof:placetype":"locality"
},
  "geometry": {"coordinates":[123.62681000000001,12.23504],"type":"Point"}
}