{
  "type": "Feature",
  "properties": {
    "gn:admin1_code":"06",
    "gn:admin2_code":"H3",
    "gn:admin3_code":"64505000.0",
    "gn:asciiname":"Hacienda Calatrava",
    "gn:country_code":"PH",
    "gn:dem":68,
    "gn:feature_class":"P",
    "gn:feature_code":"PPL",
    "gn:name":"Hacienda Calatrava",
    "gn:population":0,
    "gn:timezone":"Asia/Manila",
    "iso:country":"PH",
    "name:fil_x_preferred":[
        "Hacienda Calatrava"
    ],
    "name:und_x_variant":[
        "Calatrava Hacienda"
    ],
    "wof:name":"Hacienda Calatrava",
    "wof:placetype":"locality"
},
  "geometry": {"coordinates":[123.4689,10.60846],"type":"Point"}
}