{
  "type": "Feature",
  "properties": {
    "gn:country":"PH",
    "gn:fcode":"ADM3",
    "gn:pop":0,
    "iso:country":"PH",
    "name:eng_x_preferred":[
        "Bulakan"
    ],
    "name:fil_x_preferred":[
        "Bulacan"
    ],
    "name:pag_x_preferred":[
        "Bulakan"
    ],
    "name:spa_x_preferred":[
        "Bulac\u00e1n"
    ],
    "name:tgl_x_preferred":[
        "Bulakan"
    ],
    "qs:name":"Bulacan",
    "qs:photos_9r":0,
    "qs:photos_sr":0,
    "qs:pop_sr":"0",
    "wd:wordcount":3756,
    "wof:name":"Bulacan",
    "wof:placetype":"localadmin",
    "wof:population":0
},
  "geometry": {"coordinates":[120.87614000000001,14.76627],"type":"Point"}
}