{
  "type": "Feature",
  "properties": {
    "gn:admin1_code":"03",
    "gn:admin2_code":"13",
    "gn:asciiname":"Ilagan",
    "gn:country_code":"PH",
    "gn:dem":222,
    "gn:feature_class":"P",
    "gn:feature_code":"PPL",
    "gn:name":"Ilagan",
    "gn:population":0,
    "gn:timezone":"Asia/Manila",
    "iso:country":"PH",
    "name:ara_x_preferred":[
        "\u0625\u064a\u0644\u0627\u063a\u0627\u0646"
    ],
    "name:bcl_x_preferred":[
        "Ilagan"
    ],
    "name:ceb_x_preferred":[
        "Ilagan"
    ],
    "name:deu_x_preferred":[
        "Ilagan"
    ],
    "name:fil_x_preferred":[
        "Ilagan"
    ],
    "name:fra_x_preferred":[
        "Ilagan"
    ],
    "name:ilo_x_preferred":[
        "Ilagan"
    ],
    "name:ind_x_preferred":[
        "Ilagan"
    ],
    "name:ita_x_preferred":[
        "Ilagan"
    ],
    "name:nld_x_preferred":[
        "Ilagan"
    ],
    "name:nor_x_preferred":[
        "Ilagan City"
    ],
    "name:pag_x_preferred":[
        "Ilagan"
    ],
    "name:pam_x_preferred":[
        "Ilagan"
    ],
    "name:rus_x_preferred":[
        "\u0418\u043b\u0430\u0433\u0430\u043d"
    ],
    "name:spa_x_preferred":[
        "Ilagan"
    ],
    "name:swe_x_preferred":[
        "Ilagan"
    ],
    "name:tgl_x_preferred":[
        "Ilagan"
    ],
    "name:tha_x_preferred":[
        "\u0e2d\u0e35\u0e25\u0e32\u0e01\u0e31\u0e19"
    ],
    "name:urd_x_preferred":[
        "\u0627\u0644\u0627\u06af\u0627\u0646"
    ],
    "name:vie_x_preferred":[
        "Ilagan"
    ],
    "name:war_x_preferred":[
        "Ilagan"
    ],
    "wof:name":"Ilagan",
    "wof:placetype":"locality"
},
  "geometry": {"coordinates":[121.19395,14.91442],"type":"Point"}
}