{
  "type": "Feature",
  "properties": {
    "gn:admin1_code":"03",
    "gn:admin2_code":"13",
    "gn:asciiname":"Ilagan",
    "gn:country_code":"PH",
    "gn:dem":222,
    "gn:feature_class":"P",
    "gn:feature_code":"PPL",
    "gn:name":"Ilagan",
    "gn:population":0,
    "gn:timezone":"Asia/Manila",
    "iso:country":"PH",
    "name:fil_x_preferred":[
        "Ilagan"
    ],
    "wof:name":"Ilagan",
    "wof:placetype":"locality"
},
  "geometry": {"coordinates":[121.19395,14.91442],"type":"Point"}
}