{
  "type": "Feature",
  "properties": {
    "gn:admin1_code":"12",
    "gn:admin2_code":"M9",
    "gn:admin3_code":"128003000.0",
    "gn:asciiname":"Kandulay",
    "gn:country_code":"PH",
    "gn:dem":25,
    "gn:feature_class":"P",
    "gn:feature_code":"PPL",
    "gn:name":"Kandulay",
    "gn:population":0,
    "gn:timezone":"Asia/Manila",
    "iso:country":"PH",
    "name:und_x_variant":[
        "Candulay",
        "Kandulay"
    ],
    "wof:name":"Kandulay",
    "wof:placetype":"locality"
},
  "geometry": {"coordinates":[124.68083,5.96889],"type":"Point"}
}