{
  "type": "Feature",
  "properties": {
    "gn:country":"PH",
    "gn:fcode":"PPL",
    "gn:population":5050,
    "iso:country":"PH",
    "name:eng_x_preferred":[
        "Tayaman"
    ],
    "qs:name":"Tayaman",
    "qs:photos_9r":0,
    "qs:photos_sr":0,
    "qs:pop_sr":"5",
    "wof:name":"Tayaman",
    "wof:placetype":"locality",
    "wof:population":5050
},
  "geometry": {"coordinates":[120.57259999999999,13.2295],"type":"Point"}
}