{
  "type": "Feature",
  "properties": {
    "gn:admin1_code":"40",
    "gn:admin2_code":"H2",
    "gn:admin3_code":"45607000.0",
    "gn:asciiname":"Concepcion",
    "gn:country_code":"PH",
    "gn:dem":6,
    "gn:feature_class":"P",
    "gn:feature_code":"PPL",
    "gn:name":"Concepcion",
    "gn:population":0,
    "gn:timezone":"Asia/Manila",
    "iso:country":"PH",
    "name:fil_x_preferred":[
        "Concepcion"
    ],
    "wof:name":"Concepcion",
    "wof:placetype":"locality"
},
  "geometry": {"coordinates":[122.33333,13.95],"type":"Point"}
}