{
  "type": "Feature",
  "properties": {
    "gn:admin1_code":"13",
    "gn:admin2_code":"03",
    "gn:admin3_code":"160305000.0",
    "gn:asciiname":"Johnson",
    "gn:country_code":"PH",
    "gn:dem":113,
    "gn:feature_class":"P",
    "gn:feature_code":"PPL",
    "gn:name":"Johnson",
    "gn:population":0,
    "gn:timezone":"Asia/Manila",
    "iso:country":"PH",
    "name:ces_x_preferred":[
        "Johnson"
    ],
    "name:deu_x_preferred":[
        "Johnson"
    ],
    "name:fil_x_preferred":[
        "Johnson"
    ],
    "name:lav_x_preferred":[
        "D\u017eonsons"
    ],
    "name:pol_x_preferred":[
        "Johnson"
    ],
    "name:swe_x_preferred":[
        "Johnson"
    ],
    "name:ukr_x_preferred":[
        "\u0414\u0436\u043e\u043d\u0441\u043e\u043d"
    ],
    "name:zho_x_preferred":[
        "\u7ea6\u7ff0\u900a"
    ],
    "wof:name":"Johnson",
    "wof:placetype":"locality"
},
  "geometry": {"coordinates":[125.73333,8.16667],"type":"Point"}
}