{
  "type": "Feature",
  "properties": {
    "gn:admin1_code":"02",
    "gn:admin2_code":"31",
    "gn:admin3_code":"23137000.0",
    "gn:asciiname":"Paragu",
    "gn:country_code":"PH",
    "gn:dem":24,
    "gn:feature_class":"P",
    "gn:feature_code":"PPL",
    "gn:name":"Paragu",
    "gn:population":0,
    "gn:timezone":"Asia/Manila",
    "iso:country":"PH",
    "name:fil_x_preferred":[
        "Paragu"
    ],
    "wof:name":"Paragu",
    "wof:placetype":"locality"
},
  "geometry": {"coordinates":[121.81896999999999,17.25568],"type":"Point"}
}