{
  "type": "Feature",
  "properties": {
    "gn:admin1_code":"02",
    "gn:admin2_code":"31",
    "gn:admin3_code":"23137000.0",
    "gn:asciiname":"Paragu",
    "gn:country_code":"PH",
    "gn:dem":24,
    "gn:feature_class":"P",
    "gn:feature_code":"PPL",
    "gn:name":"Paragu",
    "gn:population":0,
    "gn:timezone":"Asia/Manila",
    "iso:country":"PH",
    "name:fil_x_preferred":[
        "Paragu"
    ],
    "name:mya_x_preferred":[
        "\u1015\u102b\u101b\u1002\u1030\u104a \u1005\u102c\u101b\u1031\u1038\u1006\u101b\u102c"
    ],
    "wof:name":"Paragu",
    "wof:placetype":"locality"
},
  "geometry": {"coordinates":[121.81896999999999,17.25568],"type":"Point"}
}