{
  "type": "Feature",
  "properties": {
    "gn:admin1_code":"03",
    "gn:admin2_code":"47",
    "gn:admin3_code":"34903000.0",
    "gn:asciiname":"Aduas Centro",
    "gn:country_code":"PH",
    "gn:dem":41,
    "gn:feature_class":"P",
    "gn:feature_code":"PPL",
    "gn:name":"Aduas Centro",
    "gn:population":0,
    "gn:timezone":"Asia/Manila",
    "iso:country":"PH",
    "name:und_x_variant":[
        "Adduas",
        "Aduas",
        "Aduas Centro"
    ],
    "wof:name":"Aduas Centro",
    "wof:placetype":"locality"
},
  "geometry": {"coordinates":[120.96172,15.49901],"type":"Point"}
}