{
  "type": "Feature",
  "properties": {
    "gn:admin1_code":"06",
    "gn:admin2_code":"04",
    "gn:admin3_code":"60413000.0",
    "gn:asciiname":"Liloan",
    "gn:country_code":"PH",
    "gn:dem":29,
    "gn:feature_class":"P",
    "gn:feature_code":"PPL",
    "gn:name":"Liloan",
    "gn:population":0,
    "gn:timezone":"Asia/Manila",
    "iso:country":"PH",
    "name:ceb_x_preferred":[
        "Liloan"
    ],
    "name:deu_x_preferred":[
        "Liloan"
    ],
    "name:fil_x_preferred":[
        "Liloan"
    ],
    "name:fra_x_preferred":[
        "Liloan"
    ],
    "name:ita_x_preferred":[
        "Liloan"
    ],
    "name:nld_x_preferred":[
        "Liloan"
    ],
    "name:war_x_preferred":[
        "Liloan"
    ],
    "wof:name":"Liloan",
    "wof:placetype":"locality"
},
  "geometry": {"coordinates":[122.28740000000001,11.6585],"type":"Point"}
}