{
  "type": "Feature",
  "properties": {
    "gn:admin1_code":"08",
    "gn:admin2_code":"59",
    "gn:asciiname":"Canauiti",
    "gn:country_code":"PH",
    "gn:dem":140,
    "gn:feature_class":"P",
    "gn:feature_code":"PPL",
    "gn:name":"Canauiti",
    "gn:population":0,
    "gn:timezone":"Asia/Manila",
    "iso:country":"PH",
    "name:fil_x_preferred":[
        "Canauiti"
    ],
    "wof:name":"Canauiti",
    "wof:placetype":"locality"
},
  "geometry": {"coordinates":[122.4579,10.9449],"type":"Point"}
}