{
  "type": "Feature",
  "properties": {
    "gn:admin1_code":"06",
    "gn:admin2_code":"04",
    "gn:admin3_code":"60409000.0",
    "gn:asciiname":"Pinaoy",
    "gn:country_code":"PH",
    "gn:dem":55,
    "gn:feature_class":"P",
    "gn:feature_code":"PPL",
    "gn:name":"Pinaoy",
    "gn:population":0,
    "gn:timezone":"Asia/Manila",
    "iso:country":"PH",
    "name:fil_x_preferred":[
        "Pinaoy"
    ],
    "name:und_x_variant":[
        "Pononoy"
    ],
    "wof:name":"Pinaoy",
    "wof:placetype":"locality"
},
  "geometry": {"coordinates":[122.30781,11.4763],"type":"Point"}
}