{
  "type": "Feature",
  "properties": {
    "gn:admin1_code":"01",
    "gn:admin2_code":"51",
    "gn:admin3_code":"15504000.0",
    "gn:asciiname":"Macayo",
    "gn:country_code":"PH",
    "gn:dem":23,
    "gn:feature_class":"P",
    "gn:feature_code":"PPL",
    "gn:name":"Macayo",
    "gn:population":0,
    "gn:timezone":"Asia/Manila",
    "iso:country":"PH",
    "wof:name":"Macayo",
    "wof:placetype":"locality"
},
  "geometry": {"coordinates":[120.51203,15.86182],"type":"Point"}
}