{
  "type": "Feature",
  "properties": {
    "gn:admin1_code":"06",
    "gn:admin2_code":"H3",
    "gn:admin3_code":"64515000.0",
    "gn:asciiname":"Tomumbo",
    "gn:country_code":"PH",
    "gn:dem":31,
    "gn:feature_class":"P",
    "gn:feature_code":"PPL",
    "gn:name":"Tomumbo",
    "gn:population":0,
    "gn:timezone":"Asia/Manila",
    "iso:country":"PH",
    "name:fil_x_preferred":[
        "Tomumbo"
    ],
    "wof:name":"Tomumbo",
    "wof:placetype":"locality"
},
  "geometry": {"coordinates":[122.86199999999999,9.9637],"type":"Point"}
}