{
  "type": "Feature",
  "properties": {
    "gn:admin1_code":"14",
    "gn:admin2_code":"60",
    "gn:admin3_code":"156619000.0",
    "gn:asciiname":"Tangluba",
    "gn:country_code":"PH",
    "gn:dem":35,
    "gn:feature_class":"P",
    "gn:feature_code":"PPL",
    "gn:name":"Tangluba",
    "gn:population":0,
    "gn:timezone":"Asia/Manila",
    "iso:country":"PH",
    "name:eng_x_preferred":[
        "Tangluba"
    ],
    "wof:name":"Tangluba",
    "wof:placetype":"locality"
},
  "geometry": {"coordinates":[121.36584000000001,5.94787],"type":"Point"}
}