{
  "type": "Feature",
  "properties": {
    "gn:admin1_code":"05",
    "gn:admin2_code":"05",
    "gn:admin3_code":"50513000.0",
    "gn:asciiname":"Olyaoyao",
    "gn:country_code":"PH",
    "gn:dem":136,
    "gn:feature_class":"P",
    "gn:feature_code":"PPL",
    "gn:name":"Olyaoyao",
    "gn:population":0,
    "gn:timezone":"Asia/Manila",
    "iso:country":"PH",
    "name:fil_x_preferred":[
        "Olyaoyao"
    ],
    "wof:name":"Olyaoyao",
    "wof:placetype":"locality"
},
  "geometry": {"coordinates":[123.46583,13.09694],"type":"Point"}
}