{
  "type": "Feature",
  "properties": {
    "gn:admin1_code":"10",
    "gn:admin2_code":"43",
    "gn:admin3_code":"104305000.0",
    "gn:asciiname":"Mahabowa",
    "gn:country_code":"PH",
    "gn:dem":304,
    "gn:feature_class":"P",
    "gn:feature_code":"PPL",
    "gn:name":"Mahabowa",
    "gn:population":0,
    "gn:timezone":"Asia/Manila",
    "iso:country":"PH",
    "wof:name":"Mahabowa",
    "wof:placetype":"locality"
},
  "geometry": {"coordinates":[124.57778,8.25611],"type":"Point"}
}