{
  "type": "Feature",
  "properties": {
    "gn:admin1_code":"06",
    "gn:admin2_code":"18",
    "gn:admin3_code":"61907000.0",
    "gn:asciiname":"Ngalan",
    "gn:country_code":"PH",
    "gn:dem":46,
    "gn:feature_class":"P",
    "gn:feature_code":"PPL",
    "gn:name":"Ngalan",
    "gn:population":0,
    "gn:timezone":"Asia/Manila",
    "iso:country":"PH",
    "name:fil_x_preferred":[
        "Ngalan"
    ],
    "wof:name":"Ngalan",
    "wof:placetype":"locality"
},
  "geometry": {"coordinates":[122.9006,11.3709],"type":"Point"}
}