{
  "type": "Feature",
  "properties": {
    "gn:admin1_code":"02",
    "gn:admin2_code":"31",
    "gn:admin3_code":"23131000.0",
    "gn:asciiname":"Melmel",
    "gn:country_code":"PH",
    "gn:dem":540,
    "gn:feature_class":"P",
    "gn:feature_code":"PPL",
    "gn:name":"Melmel",
    "gn:population":0,
    "gn:timezone":"Asia/Manila",
    "iso:country":"PH",
    "name:fil_x_preferred":[
        "Melmel"
    ],
    "wof:name":"Melmel",
    "wof:placetype":"locality"
},
  "geometry": {"coordinates":[122.34999999999999,17.06667],"type":"Point"}
}