{
  "type": "Feature",
  "properties": {
    "gn:admin1_code":"07",
    "gn:admin2_code":"46",
    "gn:admin3_code":"74603000.0",
    "gn:asciiname":"Malangwa",
    "gn:country_code":"PH",
    "gn:dem":14,
    "gn:feature_class":"P",
    "gn:feature_code":"PPL",
    "gn:name":"Malangwa",
    "gn:population":0,
    "gn:timezone":"Asia/Manila",
    "iso:country":"PH",
    "name:ara_x_preferred":[
        "\u0645\u0627\u0644\u0627\u0646\u063a\u0627\u0648\u0627"
    ],
    "name:bih_x_preferred":[
        "\u092e\u0932\u0902\u0917\u0935\u093e"
    ],
    "name:deu_x_preferred":[
        "Malangwa"
    ],
    "name:fil_x_preferred":[
        "Malangwa"
    ],
    "name:fra_x_preferred":[
        "Malangwa"
    ],
    "name:mai_x_preferred":[
        "\u092e\u0932\u0919\u094d\u0935\u093e \u0928\u0917\u0930\u092a\u093e\u0932\u093f\u0915\u093e"
    ],
    "name:nep_x_preferred":[
        "\u092e\u0932\u0919\u094d\u0935\u093e \u0928\u0917\u0930\u092a\u093e\u0932\u093f\u0915\u093e"
    ],
    "name:new_x_preferred":[
        "\u092e\u0932\u0919\u0935\u093e \u0928\u0917\u0930\u092a\u093e\u0932\u093f\u0915\u093e"
    ],
    "name:nld_x_preferred":[
        "Malangwa"
    ],
    "name:pol_x_preferred":[
        "Malangawa"
    ],
    "name:por_x_preferred":[
        "Malangwa"
    ],
    "name:rus_x_preferred":[
        "\u041c\u0430\u043b\u0430\u043d\u0433\u0432\u0430"
    ],
    "name:ukr_x_preferred":[
        "\u041c\u0430\u043b\u0430\u043d\u0433\u0432\u0430"
    ],
    "name:urd_x_preferred":[
        "\u0645\u0644\u0646\u06af\u0648\u0627"
    ],
    "name:zho_x_preferred":[
        "\u9ed8\u502b\u74dc"
    ],
    "wof:name":"Malangwa",
    "wof:placetype":"locality"
},
  "geometry": {"coordinates":[123.29859999999999,9.2648],"type":"Point"}
}