{
  "type": "Feature",
  "properties": {
    "gn:admin1_code":"05",
    "gn:admin2_code":"39",
    "gn:admin3_code":"54116000.0",
    "gn:asciiname":"Mintac",
    "gn:country_code":"PH",
    "gn:dem":33,
    "gn:feature_class":"P",
    "gn:feature_code":"PPL",
    "gn:name":"Mintac",
    "gn:population":0,
    "gn:timezone":"Asia/Manila",
    "iso:country":"PH",
    "name:fil_x_preferred":[
        "Mintac"
    ],
    "name:und_x_variant":[
        "Mintao",
        "Mintac"
    ],
    "wof:name":"Mintac",
    "wof:placetype":"locality"
},
  "geometry": {"coordinates":[124.02791000000001,11.92786],"type":"Point"}
}