{
  "type": "Feature",
  "properties": {
    "gn:admin1_code":"07",
    "gn:admin2_code":"46",
    "gn:admin3_code":"74625000.0",
    "gn:asciiname":"Cadoldolan",
    "gn:country_code":"PH",
    "gn:dem":79,
    "gn:feature_class":"P",
    "gn:feature_code":"PPL",
    "gn:name":"Cadoldolan",
    "gn:population":0,
    "gn:timezone":"Asia/Manila",
    "iso:country":"PH",
    "name:fil_x_preferred":[
        "Cadoldolan"
    ],
    "wof:name":"Cadoldolan",
    "wof:placetype":"locality"
},
  "geometry": {"coordinates":[123.1554,9.0992],"type":"Point"}
}