{
  "type": "Feature",
  "properties": {
    "gn:admin1_code":"02",
    "gn:admin2_code":"68",
    "gn:admin3_code":"25704000.0",
    "gn:asciiname":"Villahemosa Norte",
    "gn:country_code":"PH",
    "gn:dem":153,
    "gn:feature_class":"P",
    "gn:feature_code":"PPL",
    "gn:name":"Villahemosa Norte",
    "gn:population":0,
    "gn:timezone":"Asia/Manila",
    "iso:country":"PH",
    "name:fil_x_preferred":[
        "Villahemosa Norte"
    ],
    "name:fil_x_variant":[
        "Villa Hermosa Norte",
        "Villahermosa",
        "Villahemosa"
    ],
    "name:und_x_variant":[
        "Villahermosa",
        "Villahemosa"
    ],
    "wof:name":"Villahemosa Norte",
    "wof:placetype":"locality"
},
  "geometry": {"coordinates":[121.6842,16.3597],"type":"Point"}
}