{
  "type": "Feature",
  "properties": {
    "gn:admin1_code":"03",
    "gn:admin2_code":"13",
    "gn:admin3_code":"31410000.0",
    "gn:asciiname":"Canalate",
    "gn:country_code":"PH",
    "gn:dem":7,
    "gn:feature_class":"P",
    "gn:feature_code":"PPL",
    "gn:name":"Canalate",
    "gn:population":0,
    "gn:timezone":"Asia/Manila",
    "iso:country":"PH",
    "name:fil_x_preferred":[
        "Kanalate"
    ],
    "wof:name":"Canalate",
    "wof:placetype":"locality"
},
  "geometry": {"coordinates":[120.80316000000001,14.84121],"type":"Point"}
}