{
  "type": "Feature",
  "properties": {
    "gn:admin1_code":"07",
    "gn:admin2_code":"21",
    "gn:admin3_code":"72211000.0",
    "gn:asciiname":"Binabag",
    "gn:country_code":"PH",
    "gn:dem":30,
    "gn:feature_class":"P",
    "gn:feature_code":"PPL",
    "gn:name":"Binabag",
    "gn:population":0,
    "gn:timezone":"Asia/Manila",
    "iso:country":"PH",
    "name:fil_x_preferred":[
        "Binabag"
    ],
    "wof:name":"Binabag",
    "wof:placetype":"locality"
},
  "geometry": {"coordinates":[123.96666999999999,11.05],"type":"Point"}
}