{
  "type": "Feature",
  "properties": {
    "gn:country":"PH",
    "gn:fcode":"PPL",
    "gn:population":19672,
    "iso:country":"PH",
    "name:fil_x_preferred":[
        "Suay"
    ],
    "qs:name":"Suay",
    "qs:photos_9r":0,
    "qs:photos_sr":0,
    "qs:pop_sr":"6",
    "wof:name":"Suay",
    "wof:placetype":"locality",
    "wof:population":19672
},
  "geometry": {"coordinates":[122.84229999999999,10.0533],"type":"Point"}
}