{
  "type": "Feature",
  "properties": {
    "gn:admin1_code":"03",
    "gn:admin2_code":"50",
    "gn:admin3_code":"35411000.0",
    "gn:asciiname":"Camias",
    "gn:country_code":"PH",
    "gn:dem":56,
    "gn:feature_class":"P",
    "gn:feature_code":"PPL",
    "gn:name":"Camias",
    "gn:population":0,
    "gn:timezone":"Asia/Manila",
    "iso:country":"PH",
    "name:fil_x_preferred":[
        "Camias"
    ],
    "wof:name":"Camias",
    "wof:placetype":"locality"
},
  "geometry": {"coordinates":[120.64588999999999,15.19718],"type":"Point"}
}