{
  "type": "Feature",
  "properties": {
    "gn:admin1_code":"41",
    "gn:admin2_code":"49",
    "gn:admin3_code":"175311000.0",
    "gn:asciiname":"Capayas",
    "gn:country_code":"PH",
    "gn:dem":5,
    "gn:feature_class":"P",
    "gn:feature_code":"PPL",
    "gn:name":"Capayas",
    "gn:population":0,
    "gn:timezone":"Asia/Manila",
    "iso:country":"PH",
    "name:eng_x_preferred":[
        "Capayas"
    ],
    "name:und_x_variant":[
        "Gapayas"
    ],
    "wof:name":"Capayas",
    "wof:placetype":"locality"
},
  "geometry": {"coordinates":[119.6524,10.46358],"type":"Point"}
}