{
  "type": "Feature",
  "properties": {
    "gn:admin1_code":"10",
    "gn:admin2_code":"43",
    "gn:admin3_code":"104318000.0",
    "gn:asciiname":"Old Manticao",
    "gn:country_code":"PH",
    "gn:dem":16,
    "gn:feature_class":"P",
    "gn:feature_code":"PPL",
    "gn:name":"Old Manticao",
    "gn:population":0,
    "gn:timezone":"Asia/Manila",
    "iso:country":"PH",
    "name:fil_x_preferred":[
        "Old Manticao"
    ],
    "wof:name":"Old Manticao",
    "wof:placetype":"locality"
},
  "geometry": {"coordinates":[124.28417,8.39667],"type":"Point"}
}