{
  "type": "Feature",
  "properties": {
    "gn:admin1_code":"03",
    "gn:admin2_code":"63",
    "gn:admin3_code":"36904000.0",
    "gn:asciiname":"Camino",
    "gn:country_code":"PH",
    "gn:dem":49,
    "gn:feature_class":"P",
    "gn:feature_code":"PPL",
    "gn:name":"Camino",
    "gn:population":0,
    "gn:timezone":"Asia/Manila",
    "iso:country":"PH",
    "name:cat_x_preferred":[
        "Camino"
    ],
    "name:ceb_x_preferred":[
        "Camino"
    ],
    "name:deu_x_preferred":[
        "Camino"
    ],
    "name:eus_x_preferred":[
        "Bide"
    ],
    "name:fil_x_preferred":[
        "Camino"
    ],
    "name:fra_x_preferred":[
        "Camino"
    ],
    "name:glg_x_preferred":[
        "Camino"
    ],
    "name:ita_x_preferred":[
        "Camino"
    ],
    "name:kor_x_preferred":[
        "\uce74\ubbf8\ub178"
    ],
    "name:nah_x_preferred":[
        "Ohtli"
    ],
    "name:nld_x_preferred":[
        "Camino"
    ],
    "name:pol_x_preferred":[
        "Camino"
    ],
    "name:por_x_preferred":[
        "Camino"
    ],
    "name:spa_x_preferred":[
        "Camino"
    ],
    "name:srp_x_preferred":[
        "Kamino"
    ],
    "name:swe_x_preferred":[
        "Camino"
    ],
    "name:vie_x_preferred":[
        "Camino"
    ],
    "name:vol_x_preferred":[
        "Camino"
    ],
    "wof:name":"Camino",
    "wof:placetype":"locality"
},
  "geometry": {"coordinates":[120.60153,15.34526],"type":"Point"}
}