{
  "type": "Feature",
  "properties": {
    "gn:admin1_code":"02",
    "gn:admin2_code":"68",
    "gn:admin3_code":"25703000.0",
    "gn:asciiname":"Baguio Village",
    "gn:country_code":"PH",
    "gn:dem":239,
    "gn:feature_class":"P",
    "gn:feature_code":"PPL",
    "gn:name":"Baguio Village",
    "gn:population":0,
    "gn:timezone":"Asia/Manila",
    "iso:country":"PH",
    "name:fil_x_preferred":[
        "Baguio Village"
    ],
    "wof:name":"Baguio Village",
    "wof:placetype":"locality"
},
  "geometry": {"coordinates":[121.43219999999999,16.5279],"type":"Point"}
}