{
  "type": "Feature",
  "properties": {
    "gn:country":"PH",
    "gn:fcode":"PPL",
    "gn:population":4034,
    "iso:country":"PH",
    "name:und_x_variant":[
        "Puro"
    ],
    "qs:name":"Puro Pinget",
    "qs:photos_9r":0,
    "qs:photos_sr":0,
    "qs:pop_sr":"4",
    "wof:name":"Puro Pinget",
    "wof:placetype":"locality",
    "wof:population":4034
},
  "geometry": {"coordinates":[120.35883,17.67967],"type":"Point"}
}