{
  "type": "Feature",
  "properties": {
    "gn:country":"PH",
    "gn:fcode":"PPLA3",
    "gn:pop":41235,
    "iso:country":"PH",
    "name:fil_x_preferred":[
        "Angat"
    ],
    "name:fil_x_variant":[
        "Santa Cruz"
    ],
    "name:unk_x_variant":[
        "Santa Cruz"
    ],
    "qs:name":"Angat",
    "qs:photos_9r":0,
    "qs:photos_sr":0,
    "qs:pop_sr":"7",
    "wd:wordcount":38,
    "wof:name":"Angat",
    "wof:placetype":"locality",
    "wof:population":41235
},
  "geometry": {"coordinates":[121.03,14.9285],"type":"Point"}
}