{
  "type": "Feature",
  "properties": {
    "gn:admin1_code":"41",
    "gn:admin2_code":"41",
    "gn:admin3_code":"175201000.0",
    "gn:asciiname":"Chicago",
    "gn:country_code":"PH",
    "gn:dem":14,
    "gn:feature_class":"P",
    "gn:feature_code":"PPL",
    "gn:name":"Chicago",
    "gn:population":0,
    "gn:timezone":"Asia/Manila",
    "iso:country":"PH",
    "name:eng_x_preferred":[
        "Chicago"
    ],
    "wof:name":"Chicago",
    "wof:placetype":"locality"
},
  "geometry": {"coordinates":[121.0984,13.396],"type":"Point"}
}