{
  "type": "Feature",
  "properties": {
    "gn:admin1_code":"08",
    "gn:admin2_code":"67",
    "gn:admin3_code":"84814000.0",
    "gn:asciiname":"Dang-o",
    "gn:country_code":"PH",
    "gn:dem":-1,
    "gn:feature_class":"P",
    "gn:feature_code":"PPL",
    "gn:name":"Dang-o",
    "gn:population":0,
    "gn:timezone":"Asia/Manila",
    "iso:country":"PH",
    "name:fil_x_preferred":[
        "Dang-o"
    ],
    "wof:name":"Dang-o",
    "wof:placetype":"locality"
},
  "geometry": {"coordinates":[125.0313,12.4612],"type":"Point"}
}