{
  "type": "Feature",
  "properties": {
    "gn:admin1_code":"08",
    "gn:admin2_code":"67",
    "gn:admin3_code":"84824000.0",
    "gn:asciiname":"Matagobtob",
    "gn:country_code":"PH",
    "gn:dem":24,
    "gn:feature_class":"P",
    "gn:feature_code":"PPL",
    "gn:name":"Matagobtob",
    "gn:population":0,
    "gn:timezone":"Asia/Manila",
    "iso:country":"PH",
    "name:fil_x_preferred":[
        "Matagobtob"
    ],
    "wof:name":"Matagobtob",
    "wof:placetype":"locality"
},
  "geometry": {"coordinates":[124.6399,12.3102],"type":"Point"}
}