{
  "type": "Feature",
  "properties": {
    "gn:admin1_code":"14",
    "gn:admin2_code":"56",
    "gn:admin3_code":"153801000.0",
    "gn:asciiname":"Daguma",
    "gn:country_code":"PH",
    "gn:dem":507,
    "gn:feature_class":"P",
    "gn:feature_code":"PPL",
    "gn:name":"Daguma",
    "gn:population":0,
    "gn:timezone":"Asia/Manila",
    "iso:country":"PH",
    "name:fil_x_preferred":[
        "Daguma"
    ],
    "wof:name":"Daguma",
    "wof:placetype":"locality"
},
  "geometry": {"coordinates":[124.42409000000001,6.76395],"type":"Point"}
}