{
  "type": "Feature",
  "properties": {
    "gn:country":"PH",
    "gn:fcode":"PPL",
    "gn:population":3905,
    "iso:country":"PH",
    "name:fil_x_preferred":[
        "Tibagon"
    ],
    "qs:name":"Tibagon",
    "qs:photos_9r":0,
    "qs:photos_sr":0,
    "qs:pop_sr":"4",
    "wof:name":"Tibagon",
    "wof:placetype":"locality",
    "wof:population":3905
},
  "geometry": {"coordinates":[125.86279999999999,7.2327],"type":"Point"}
}