{
  "type": "Feature",
  "properties": {
    "gn:admin1_code":"14",
    "gn:admin2_code":"60",
    "gn:admin3_code":"156605000.0",
    "gn:asciiname":"Bato-Ugis",
    "gn:country_code":"PH",
    "gn:dem":5,
    "gn:feature_class":"P",
    "gn:feature_code":"PPL",
    "gn:name":"Bato-Ugis",
    "gn:population":0,
    "gn:timezone":"Asia/Manila",
    "iso:country":"PH",
    "name:eng_x_preferred":[
        "Bato-Ugis"
    ],
    "wof:name":"Bato-Ugis",
    "wof:placetype":"locality"
},
  "geometry": {"coordinates":[120.991,5.914],"type":"Point"}
}