{
  "type": "Feature",
  "properties": {
    "gn:country":"PH",
    "gn:fcode":"PPL",
    "gn:pop":7495,
    "iso:country":"PH",
    "name:unk_x_variant":[
        "Balete Segundo"
    ],
    "qs:name":"Balete No 2",
    "qs:photos_9r":0,
    "qs:photos_sr":0,
    "qs:pop_sr":"5",
    "wof:name":"Balete No 2",
    "wof:placetype":"locality",
    "wof:population":7495
},
  "geometry": {"coordinates":[120.97685,14.1669],"type":"Point"}
}