{
  "type": "Feature",
  "properties": {
    "gn:country":"PH",
    "gn:fcode":"ADM3",
    "gn:pop":37621,
    "iso:country":"PH",
    "qs:name":"Banaybanay",
    "qs:photos_9r":0,
    "qs:photos_sr":0,
    "qs:pop_sr":"7",
    "wof:name":"Banaybanay",
    "wof:placetype":"localadmin",
    "wof:population":37621
},
  "geometry": {"coordinates":[126.1417,7.14188],"type":"Point"}
}