{
  "type": "Feature",
  "properties": {
    "gn:admin1_code":"15",
    "gn:admin2_code":"32",
    "gn:admin3_code":"143213000.0",
    "gn:asciiname":"Pinangan",
    "gn:country_code":"PH",
    "gn:dem":254,
    "gn:feature_class":"P",
    "gn:feature_code":"PPL",
    "gn:name":"Pinangan",
    "gn:population":0,
    "gn:timezone":"Asia/Manila",
    "iso:country":"PH",
    "name:fil_x_preferred":[
        "Pinangan"
    ],
    "wof:name":"Pinangan",
    "wof:placetype":"locality"
},
  "geometry": {"coordinates":[121.33410000000001,17.4055],"type":"Point"}
}