{
  "type": "Feature",
  "properties": {
    "gn:admin1_code":"15",
    "gn:admin2_code":"01",
    "gn:admin3_code":"140116000.0",
    "gn:asciiname":"Dalimono",
    "gn:country_code":"PH",
    "gn:dem":132,
    "gn:feature_class":"P",
    "gn:feature_code":"PPL",
    "gn:name":"Dalimono",
    "gn:population":0,
    "gn:timezone":"Asia/Manila",
    "iso:country":"PH",
    "name:fil_x_preferred":[
        "Dalimono"
    ],
    "wof:name":"Dalimono",
    "wof:placetype":"locality"
},
  "geometry": {"coordinates":[120.7026,17.4231],"type":"Point"}
}