{
  "type": "Feature",
  "properties": {
    "gn:admin1_code":"01",
    "gn:admin2_code":"51",
    "gn:admin3_code":"15532000.0",
    "gn:asciiname":"Buenglat",
    "gn:country_code":"PH",
    "gn:dem":10,
    "gn:feature_class":"P",
    "gn:feature_code":"PPL",
    "gn:name":"Buenglat",
    "gn:population":0,
    "gn:timezone":"Asia/Manila",
    "iso:country":"PH",
    "name:fil_x_preferred":[
        "Buenalat"
    ],
    "name:fil_x_variant":[
        "Benglat"
    ],
    "wof:name":"Buenglat",
    "wof:placetype":"locality"
},
  "geometry": {"coordinates":[120.30855,15.91287],"type":"Point"}
}