{
  "type": "Feature",
  "properties": {
    "gn:admin1_code":"10",
    "gn:admin2_code":"34",
    "gn:admin3_code":"103504000.0",
    "gn:asciiname":"Camp Overton",
    "gn:country_code":"PH",
    "gn:dem":7,
    "gn:feature_class":"P",
    "gn:feature_code":"PPL",
    "gn:name":"Camp Overton",
    "gn:population":0,
    "gn:timezone":"Asia/Manila",
    "iso:country":"PH",
    "name:und_x_variant":[
        "Overton"
    ],
    "wof:name":"Camp Overton",
    "wof:placetype":"locality"
},
  "geometry": {"coordinates":[124.20583000000001,8.20694],"type":"Point"}
}