{
  "type": "Feature",
  "properties": {
    "gn:admin1_code":"08",
    "gn:admin2_code":"67",
    "gn:admin3_code":"84824000.0",
    "gn:asciiname":"General Luna",
    "gn:country_code":"PH",
    "gn:dem":163,
    "gn:feature_class":"P",
    "gn:feature_code":"PPL",
    "gn:name":"General Luna",
    "gn:population":0,
    "gn:timezone":"Asia/Manila",
    "iso:country":"PH",
    "name:ceb_x_preferred":[
        "General Luna"
    ],
    "name:deu_x_preferred":[
        "General Luna"
    ],
    "name:fil_x_preferred":[
        "General Luna"
    ],
    "name:ita_x_preferred":[
        "General Luna"
    ],
    "name:nld_x_preferred":[
        "General Luna"
    ],
    "name:spa_x_preferred":[
        "General Luna"
    ],
    "name:war_x_preferred":[
        "General Luna"
    ],
    "wof:name":"General Luna",
    "wof:placetype":"locality"
},
  "geometry": {"coordinates":[124.68640000000001,12.2984],"type":"Point"}
}