{
  "type": "Feature",
  "properties": {
    "gn:country":"PH",
    "gn:fcode":"PPL",
    "gn:pop":3016,
    "iso:country":"PH",
    "name:fil_x_preferred":[
        "Padapada"
    ],
    "qs:name":"Padapada",
    "qs:photos_9r":0,
    "qs:photos_sr":0,
    "qs:pop_sr":"4",
    "wof:name":"Padapada",
    "wof:placetype":"locality",
    "wof:population":3016
},
  "geometry": {"coordinates":[120.5163,15.5517],"type":"Point"}
}