{
  "type": "Feature",
  "properties": {
    "gn:country":"PH",
    "gn:fcode":"PPL",
    "gn:population":2477,
    "iso:country":"PH",
    "name:und_x_variant":[
        "Giong"
    ],
    "qs:name":"Guiong",
    "qs:photos_9r":0,
    "qs:photos_sr":0,
    "qs:pop_sr":"4",
    "wof:name":"Guiong",
    "wof:placetype":"locality",
    "wof:population":2477
},
  "geometry": {"coordinates":[122.02583,6.41861],"type":"Point"}
}