{
  "type": "Feature",
  "properties": {
    "gn:admin1_code":"07",
    "gn:admin2_code":"11",
    "gn:admin3_code":"71228000.0",
    "gn:asciiname":"Tambangan",
    "gn:country_code":"PH",
    "gn:dem":36,
    "gn:feature_class":"P",
    "gn:feature_code":"PPL",
    "gn:name":"Tambangan",
    "gn:population":0,
    "gn:timezone":"Asia/Manila",
    "iso:country":"PH",
    "name:fil_x_preferred":[
        "Tambangan"
    ],
    "wof:name":"Tambangan",
    "wof:placetype":"locality"
},
  "geometry": {"coordinates":[123.99806,9.61167],"type":"Point"}
}