{
  "type": "Feature",
  "properties": {
    "gn:admin1_code":"14",
    "gn:admin2_code":"35",
    "gn:admin3_code":"153622000.0",
    "gn:asciiname":"Lumbac",
    "gn:country_code":"PH",
    "gn:dem":811,
    "gn:feature_class":"P",
    "gn:feature_code":"PPL",
    "gn:name":"Lumbac",
    "gn:population":0,
    "gn:timezone":"Asia/Manila",
    "iso:country":"PH",
    "name:fil_x_preferred":[
        "Lumbac"
    ],
    "wof:name":"Lumbac",
    "wof:placetype":"locality"
},
  "geometry": {"coordinates":[124.36667,7.83333],"type":"Point"}
}