{
  "type": "Feature",
  "properties": {
    "gn:admin1_code":"01",
    "gn:admin2_code":"51",
    "gn:admin3_code":"15542000.0",
    "gn:asciiname":"Pao",
    "gn:country_code":"PH",
    "gn:dem":16,
    "gn:feature_class":"P",
    "gn:feature_code":"PPL",
    "gn:name":"Pao",
    "gn:population":0,
    "gn:timezone":"Asia/Manila",
    "iso:country":"PH",
    "name:ceb_x_preferred":[
        "Pao"
    ],
    "name:deu_x_preferred":[
        "Pao"
    ],
    "name:fil_x_preferred":[
        "Pao"
    ],
    "name:spa_x_preferred":[
        "Pao"
    ],
    "name:swe_x_preferred":[
        "Pao"
    ],
    "wof:name":"Pao",
    "wof:placetype":"locality"
},
  "geometry": {"coordinates":[120.09633999999998,16.13251],"type":"Point"}
}