{
  "type": "Feature",
  "properties": {
    "gn:admin1_code":"03",
    "gn:admin2_code":"13",
    "gn:admin3_code":"31402000.0",
    "gn:asciiname":"Dalig",
    "gn:country_code":"PH",
    "gn:dem":9,
    "gn:feature_class":"P",
    "gn:feature_code":"PPL",
    "gn:name":"Dalig",
    "gn:population":0,
    "gn:timezone":"Asia/Manila",
    "iso:country":"PH",
    "name:fil_x_preferred":[
        "Dalig"
    ],
    "wof:name":"Dalig",
    "wof:placetype":"locality"
},
  "geometry": {"coordinates":[120.92138,14.84081],"type":"Point"}
}