{
  "type": "Feature",
  "properties": {
    "gn:admin1_code":"41",
    "gn:admin2_code":"49",
    "gn:asciiname":"Mahalo",
    "gn:country_code":"PH",
    "gn:dem":28,
    "gn:feature_class":"P",
    "gn:feature_code":"PPL",
    "gn:name":"Mahalo",
    "gn:population":0,
    "gn:timezone":"Asia/Manila",
    "iso:country":"PH",
    "name:eng_x_preferred":[
        "Mahalo"
    ],
    "name:fra_x_preferred":[
        "Mahalo"
    ],
    "name:ita_x_preferred":[
        "Mahalo"
    ],
    "wof:name":"Mahalo",
    "wof:placetype":"locality"
},
  "geometry": {"coordinates":[118.5069,6.9763],"type":"Point"}
}