{
  "type": "Feature",
  "properties": {
    "gn:admin1_code":"03",
    "gn:admin2_code":"63",
    "gn:admin3_code":"36906000.0",
    "gn:asciiname":"Pinasling",
    "gn:country_code":"PH",
    "gn:dem":32,
    "gn:feature_class":"P",
    "gn:feature_code":"PPL",
    "gn:name":"Pinasling",
    "gn:population":0,
    "gn:timezone":"Asia/Manila",
    "iso:country":"PH",
    "name:fil_x_preferred":[
        "Pinasling"
    ],
    "name:und_x_variant":[
        "Pinasung"
    ],
    "wof:name":"Pinasling",
    "wof:placetype":"locality"
},
  "geometry": {"coordinates":[120.5913,15.602],"type":"Point"}
}