{
  "type": "Feature",
  "properties": {
    "gn:admin1_code":"06",
    "gn:admin2_code":"30",
    "gn:admin3_code":"63002000.0",
    "gn:asciiname":"Luan-luan Viejo",
    "gn:country_code":"PH",
    "gn:dem":174,
    "gn:feature_class":"P",
    "gn:feature_code":"PPL",
    "gn:name":"Luan-luan Viejo",
    "gn:population":0,
    "gn:timezone":"Asia/Manila",
    "iso:country":"PH",
    "name:fil_x_preferred":[
        "Luan-luan Viejo"
    ],
    "wof:name":"Luan-luan Viejo",
    "wof:placetype":"locality"
},
  "geometry": {"coordinates":[122.41542,10.8186],"type":"Point"}
}