{
  "type": "Feature",
  "properties": {
    "gn:admin1_code":"01",
    "gn:admin2_code":"36",
    "gn:admin3_code":"13301000.0",
    "gn:asciiname":"Nazareno",
    "gn:country_code":"PH",
    "gn:dem":22,
    "gn:feature_class":"P",
    "gn:feature_code":"PPL",
    "gn:name":"Nazareno",
    "gn:population":0,
    "gn:timezone":"Asia/Manila",
    "iso:country":"PH",
    "name:arc_x_preferred":[
        "\u0722\u0728\u072a\u071d\u0710"
    ],
    "name:bpy_x_preferred":[
        "\u09a8\u09be\u099c\u09be\u09b0\u09c7\u09a8\u09cb"
    ],
    "name:ceb_x_preferred":[
        "Nazareno"
    ],
    "name:epo_x_preferred":[
        "Nazareno"
    ],
    "name:eus_x_preferred":[
        "Nazareno"
    ],
    "name:fil_x_preferred":[
        "Nazareno"
    ],
    "name:fra_x_preferred":[
        "Nazareno"
    ],
    "name:ita_x_preferred":[
        "Nazareno"
    ],
    "name:kat_x_preferred":[
        "\u10dc\u10d0\u10d6\u10d0\u10e0\u10d4\u10dc\u10e3"
    ],
    "name:kaz_x_preferred":[
        "\u041d\u0430\u0437\u0430\u0440\u0435\u043d\u0443"
    ],
    "name:nld_x_preferred":[
        "Nazareno"
    ],
    "name:nor_x_preferred":[
        "Nazareno"
    ],
    "name:pol_x_preferred":[
        "Nazareno"
    ],
    "name:por_x_preferred":[
        "Nazareno"
    ],
    "name:ron_x_preferred":[
        "Nazareno"
    ],
    "name:rus_x_preferred":[
        "\u041d\u0430\u0437\u0430\u0440\u0435\u043d\u0443"
    ],
    "name:vie_x_preferred":[
        "Nazareno"
    ],
    "name:vol_x_preferred":[
        "Nazareno"
    ],
    "name:war_x_preferred":[
        "Nazareno"
    ],
    "name:zho_x_preferred":[
        "\u7eb3\u624e\u96f7\u52aa"
    ],
    "wof:name":"Nazareno",
    "wof:placetype":"locality"
},
  "geometry": {"coordinates":[120.36020000000001,16.3465],"type":"Point"}
}