{
  "type": "Feature",
  "properties": {
    "gn:admin1_code":"11",
    "gn:admin2_code":"I6",
    "gn:admin3_code":"118203000.0",
    "gn:asciiname":"Tangnanan",
    "gn:country_code":"PH",
    "gn:dem":26,
    "gn:feature_class":"P",
    "gn:feature_code":"PPL",
    "gn:name":"Tangnanan",
    "gn:population":0,
    "gn:timezone":"Asia/Manila",
    "iso:country":"PH",
    "name:fil_x_preferred":[
        "Tangnanan"
    ],
    "name:und_x_variant":[
        "Tagnanan",
        "Tanganan",
        "Tanguanan"
    ],
    "wof:name":"Tangnanan",
    "wof:placetype":"locality"
},
  "geometry": {"coordinates":[125.8584,7.2648],"type":"Point"}
}