{
  "type": "Feature",
  "properties": {
    "gn:admin1_code":"06",
    "gn:admin2_code":"30",
    "gn:admin3_code":"63026000.0",
    "gn:asciiname":"Guintas",
    "gn:country_code":"PH",
    "gn:dem":3,
    "gn:feature_class":"P",
    "gn:feature_code":"PPL",
    "gn:name":"Guintas",
    "gn:population":0,
    "gn:timezone":"Asia/Manila",
    "iso:country":"PH",
    "name:fil_x_preferred":[
        "Guintas"
    ],
    "wof:name":"Guintas",
    "wof:placetype":"locality"
},
  "geometry": {"coordinates":[122.59999999999999,10.76667],"type":"Point"}
}