{
  "type": "Feature",
  "properties": {
    "gn:admin1_code":"14",
    "gn:admin2_code":"60",
    "gn:admin3_code":"156604000.0",
    "gn:asciiname":"Kan Bulak",
    "gn:country_code":"PH",
    "gn:dem":70,
    "gn:feature_class":"P",
    "gn:feature_code":"PPL",
    "gn:name":"Kan Bulak",
    "gn:population":0,
    "gn:timezone":"Asia/Manila",
    "iso:country":"PH",
    "name:fil_x_preferred":[
        "Kan Bulak"
    ],
    "wof:name":"Kan Bulak",
    "wof:placetype":"locality"
},
  "geometry": {"coordinates":[121.30333,5.98],"type":"Point"}
}