{
  "type": "Feature",
  "properties": {
    "gn:country":"PH",
    "gn:fcode":"ADM3",
    "gn:population":7267,
    "iso:country":"PH",
    "name:bcl_x_preferred":[
        "San Emilio"
    ],
    "name:cat_x_preferred":[
        "San Emilio"
    ],
    "name:ceb_x_preferred":[
        "San Emilio"
    ],
    "name:deu_x_preferred":[
        "San Emilio"
    ],
    "name:eng_x_preferred":[
        "San Emilio"
    ],
    "name:fil_x_preferred":[
        "San Emilio"
    ],
    "name:fra_x_preferred":[
        "San Emilio"
    ],
    "name:ilo_x_preferred":[
        "San Emilio"
    ],
    "name:ind_x_preferred":[
        "San Emilio"
    ],
    "name:ita_x_preferred":[
        "San Emilio"
    ],
    "name:nld_x_preferred":[
        "San Emilio"
    ],
    "name:oci_x_preferred":[
        "San Emilio"
    ],
    "name:pag_x_preferred":[
        "San Emilio"
    ],
    "name:pam_x_preferred":[
        "San Emilio"
    ],
    "name:spa_x_preferred":[
        "San Emilio"
    ],
    "name:swe_x_preferred":[
        "San Emilio"
    ],
    "name:tgl_x_preferred":[
        "San Emilio"
    ],
    "name:vie_x_preferred":[
        "San Emilio"
    ],
    "name:war_x_preferred":[
        "San Emilio"
    ],
    "qs:name":"San Emilio",
    "qs:photos_9r":0,
    "qs:photos_sr":0,
    "qs:pop_sr":"5",
    "wd:wordcount":136,
    "wof:name":"San Emilio",
    "wof:placetype":"localadmin",
    "wof:population":7267
},
  "geometry": {"coordinates":[120.61667,17.23333],"type":"Point"}
}