{
  "type": "Feature",
  "properties": {
    "gn:admin1_code":"06",
    "gn:admin2_code":"30",
    "gn:admin3_code":"63028000.0",
    "gn:asciiname":"Marirang",
    "gn:country_code":"PH",
    "gn:dem":366,
    "gn:feature_class":"P",
    "gn:feature_code":"PPL",
    "gn:name":"Marirang",
    "gn:population":0,
    "gn:timezone":"Asia/Manila",
    "iso:country":"PH",
    "name:fil_x_preferred":[
        "Marirang"
    ],
    "name:und_x_variant":[
        "Marirong"
    ],
    "wof:name":"Marirang",
    "wof:placetype":"locality"
},
  "geometry": {"coordinates":[122.3109,10.8364],"type":"Point"}
}