{
  "type": "Feature",
  "properties": {
    "gn:admin1_code":"03",
    "gn:admin2_code":"47",
    "gn:admin3_code":"34923000.0",
    "gn:asciiname":"Kagasatan",
    "gn:country_code":"PH",
    "gn:dem":65,
    "gn:feature_class":"P",
    "gn:feature_code":"PPL",
    "gn:name":"Kagasatan",
    "gn:population":0,
    "gn:timezone":"Asia/Manila",
    "iso:country":"PH",
    "name:fil_x_preferred":[
        "Kagasatan"
    ],
    "wof:name":"Kagasatan",
    "wof:placetype":"locality"
},
  "geometry": {"coordinates":[121.0834,15.6297],"type":"Point"}
}