{
  "type": "Feature",
  "properties": {
    "gn:admin1_code":"08",
    "gn:admin2_code":"37",
    "gn:admin3_code":"83701000.0",
    "gn:asciiname":"Old Taligue",
    "gn:country_code":"PH",
    "gn:dem":95,
    "gn:feature_class":"P",
    "gn:feature_code":"PPL",
    "gn:name":"Old Taligue",
    "gn:population":0,
    "gn:timezone":"Asia/Manila",
    "iso:country":"PH",
    "wof:name":"Old Taligue",
    "wof:placetype":"locality"
},
  "geometry": {"coordinates":[125.05249999999999,10.56889],"type":"Point"}
}