{
  "type": "Feature",
  "properties": {
    "gn:admin1_code":"06",
    "gn:admin2_code":"H3",
    "gn:admin3_code":"64520000.0",
    "gn:asciiname":"Hacienda Gatuslao",
    "gn:country_code":"PH",
    "gn:dem":111,
    "gn:feature_class":"P",
    "gn:feature_code":"PPL",
    "gn:name":"Hacienda Gatuslao",
    "gn:population":0,
    "gn:timezone":"Asia/Manila",
    "iso:country":"PH",
    "name:fil_x_preferred":[
        "Hacienda Gatuslao"
    ],
    "wof:name":"Hacienda Gatuslao",
    "wof:placetype":"locality"
},
  "geometry": {"coordinates":[123.03530000000001,10.59216],"type":"Point"}
}