{
  "type": "Feature",
  "properties": {
    "gn:admin1_code":"40",
    "gn:admin2_code":"09",
    "gn:admin3_code":"41026000.0",
    "gn:asciiname":"Ilat",
    "gn:country_code":"PH",
    "gn:dem":132,
    "gn:feature_class":"P",
    "gn:feature_code":"PPL",
    "gn:name":"Ilat",
    "gn:population":0,
    "gn:timezone":"Asia/Manila",
    "iso:country":"PH",
    "name:fil_x_preferred":[
        "Ilat"
    ],
    "wof:name":"Ilat",
    "wof:placetype":"locality"
},
  "geometry": {"coordinates":[121.01609999999999,13.8274],"type":"Point"}
}