{
  "type": "Feature",
  "properties": {
    "gn:admin1_code":"08",
    "gn:admin2_code":"67",
    "gn:admin3_code":"84815000.0",
    "gn:asciiname":"Sinonogan",
    "gn:cc2":"PH",
    "gn:country_code":"PH",
    "gn:dem":17,
    "gn:feature_class":"P",
    "gn:feature_code":"PPL",
    "gn:name":"Sinonogan",
    "gn:population":0,
    "gn:timezone":"Asia/Manila",
    "iso:country":"PH",
    "name:und_x_variant":[
        "Senonogan",
        "Sinonogan"
    ],
    "wof:name":"Sinonogan",
    "wof:placetype":"locality"
},
  "geometry": {"coordinates":[124.94333,12.42167],"type":"Point"}
}