{
  "type": "Feature",
  "properties": {
    "gn:admin1_code":"08",
    "gn:admin2_code":"67",
    "gn:admin3_code":"84801000.0",
    "gn:asciiname":"Lipata",
    "gn:country_code":"PH",
    "gn:dem":3,
    "gn:feature_class":"P",
    "gn:feature_code":"PPL",
    "gn:name":"Lipata",
    "gn:population":0,
    "gn:timezone":"Asia/Manila",
    "iso:country":"PH",
    "name:fil_x_preferred":[
        "Lipata"
    ],
    "wof:name":"Lipata",
    "wof:placetype":"locality"
},
  "geometry": {"coordinates":[124.2701,12.5365],"type":"Point"}
}