{
  "type": "Feature",
  "properties": {
    "gn:admin1_code":"08",
    "gn:admin2_code":"55",
    "gn:admin3_code":"86003000.0",
    "gn:asciiname":"Jibatang",
    "gn:country_code":"PH",
    "gn:dem":81,
    "gn:feature_class":"P",
    "gn:feature_code":"PPL",
    "gn:name":"Jibatang",
    "gn:population":0,
    "gn:timezone":"Asia/Manila",
    "iso:country":"PH",
    "name:fil_x_preferred":[
        "Jibatang"
    ],
    "wof:name":"Jibatang",
    "wof:placetype":"locality"
},
  "geometry": {"coordinates":[124.6585,12.2309],"type":"Point"}
}