{
  "type": "Feature",
  "properties": {
    "gn:admin1_code":"41",
    "gn:admin2_code":"54",
    "gn:admin3_code":"175901000.0",
    "gn:asciiname":"Casanangan",
    "gn:country_code":"PH",
    "gn:dem":10,
    "gn:feature_class":"P",
    "gn:feature_code":"PPL",
    "gn:name":"Casanangan",
    "gn:population":0,
    "gn:timezone":"Asia/Manila",
    "iso:country":"PH",
    "name:fil_x_preferred":[
        "Casanangan"
    ],
    "wof:name":"Casanangan",
    "wof:placetype":"locality"
},
  "geometry": {"coordinates":[122.0583,12.2652],"type":"Point"}
}