{
  "type": "Feature",
  "properties": {
    "gn:admin1_code":"05",
    "gn:admin2_code":"19",
    "gn:admin3_code":"52001000.0",
    "gn:asciiname":"Sochan",
    "gn:country_code":"PH",
    "gn:dem":6,
    "gn:feature_class":"P",
    "gn:feature_code":"PPL",
    "gn:name":"Sochan",
    "gn:population":0,
    "gn:timezone":"Asia/Manila",
    "iso:country":"PH",
    "name:fil_x_preferred":[
        "Sochan"
    ],
    "name:und_x_variant":[
        "Suchan"
    ],
    "wof:name":"Sochan",
    "wof:placetype":"locality"
},
  "geometry": {"coordinates":[124.315,13.9611],"type":"Point"}
}