{
  "type": "Feature",
  "properties": {
    "gn:admin1_code":"07",
    "gn:admin2_code":"21",
    "gn:admin3_code":"72216000.0",
    "gn:asciiname":"Balila",
    "gn:country_code":"PH",
    "gn:dem":184,
    "gn:feature_class":"P",
    "gn:feature_code":"PPL",
    "gn:name":"Balila",
    "gn:population":0,
    "gn:timezone":"Asia/Manila",
    "iso:country":"PH",
    "name:ara_x_preferred":[
        "\u0628\u0644\u064a\u0644\u0627"
    ],
    "name:fas_x_preferred":[
        "\u0628\u0644\u06cc\u0644\u0627"
    ],
    "name:fil_x_preferred":[
        "Balila"
    ],
    "name:pol_x_preferred":[
        "Balila"
    ],
    "name:sqi_x_preferred":[
        "Balila"
    ],
    "wof:name":"Balila",
    "wof:placetype":"locality"
},
  "geometry": {"coordinates":[123.97515,10.71978],"type":"Point"}
}