{
  "type": "Feature",
  "properties": {
    "gn:admin1_code":"06",
    "gn:admin2_code":"30",
    "gn:admin3_code":"63003000.0",
    "gn:asciiname":"Camiros",
    "gn:cc2":"PH",
    "gn:country_code":"PH",
    "gn:dem":102,
    "gn:feature_class":"P",
    "gn:feature_code":"PPL",
    "gn:name":"Camiros",
    "gn:population":0,
    "gn:timezone":"Asia/Manila",
    "iso:country":"PH",
    "name:und_x_variant":[
        "Kamiros",
        "Camiros"
    ],
    "wof:name":"Camiros",
    "wof:placetype":"locality"
},
  "geometry": {"coordinates":[122.71666999999999,11.01667],"type":"Point"}
}