{
  "type": "Feature",
  "properties": {
    "gn:admin1_code":"15",
    "gn:admin2_code":"10",
    "gn:admin3_code":"141101000.0",
    "gn:asciiname":"Colbong",
    "gn:country_code":"PH",
    "gn:dem":2478,
    "gn:feature_class":"P",
    "gn:feature_code":"PPL",
    "gn:name":"Colbong",
    "gn:population":0,
    "gn:timezone":"Asia/Manila",
    "iso:country":"PH",
    "name:fil_x_preferred":[
        "Colbong"
    ],
    "wof:name":"Colbong",
    "wof:placetype":"locality"
},
  "geometry": {"coordinates":[120.76824000000001,16.64327999999999],"type":"Point"}
}