{
  "type": "Feature",
  "properties": {
    "gn:admin1_code":"40",
    "gn:admin2_code":"20",
    "gn:admin3_code":"42118000.0",
    "gn:asciiname":"Mataas na Burol",
    "gn:country_code":"PH",
    "gn:dem":451,
    "gn:feature_class":"P",
    "gn:feature_code":"PPL",
    "gn:name":"Mataas na Burol",
    "gn:population":0,
    "gn:timezone":"Asia/Manila",
    "iso:country":"PH",
    "wof:name":"Mataas na Burol",
    "wof:placetype":"locality"
},
  "geometry": {"coordinates":[120.97308,14.16806],"type":"Point"}
}