{
  "type": "Feature",
  "properties": {
    "gn:admin1_code":"07",
    "gn:admin2_code":"21",
    "gn:admin3_code":"72201000.0",
    "gn:asciiname":"Cabil-isan",
    "gn:country_code":"PH",
    "gn:dem":35,
    "gn:feature_class":"P",
    "gn:feature_code":"PPL",
    "gn:name":"Cabil-isan",
    "gn:population":0,
    "gn:timezone":"Asia/Manila",
    "iso:country":"PH",
    "name:fil_x_preferred":[
        "Cabil-isan"
    ],
    "wof:name":"Cabil-isan",
    "wof:placetype":"locality"
},
  "geometry": {"coordinates":[123.4122,9.98069],"type":"Point"}
}