{
  "type": "Feature",
  "properties": {
    "gn:admin1_code":"40",
    "gn:admin2_code":"20",
    "gn:admin3_code":"42119000.0",
    "gn:asciiname":"Patutong Malaki",
    "gn:country_code":"PH",
    "gn:dem":589,
    "gn:feature_class":"P",
    "gn:feature_code":"PPL",
    "gn:name":"Patutong Malaki",
    "gn:population":0,
    "gn:timezone":"Asia/Manila",
    "iso:country":"PH",
    "name:fil_x_preferred":[
        "Patutong Malaki"
    ],
    "wof:name":"Patutong Malaki",
    "wof:placetype":"locality"
},
  "geometry": {"coordinates":[120.91383999999999,14.11256],"type":"Point"}
}