{
  "type": "Feature",
  "properties": {
    "gn:admin1_code":"05",
    "gn:admin2_code":"15",
    "gn:admin3_code":"51608000.0",
    "gn:asciiname":"Mancasay",
    "gn:country_code":"PH",
    "gn:dem":17,
    "gn:feature_class":"P",
    "gn:feature_code":"PPL",
    "gn:name":"Mancasay",
    "gn:population":0,
    "gn:timezone":"Asia/Manila",
    "iso:country":"PH",
    "name:fil_x_preferred":[
        "Mancasay"
    ],
    "name:und_x_variant":[
        "Mankasay"
    ],
    "wof:name":"Mancasay",
    "wof:placetype":"locality"
},
  "geometry": {"coordinates":[122.8082,14.2452],"type":"Point"}
}