{
  "type": "Feature",
  "properties": {
    "gn:admin1_code":"11",
    "gn:admin2_code":"I7",
    "gn:admin3_code":"112317000.0",
    "gn:asciiname":"Tagnasancan",
    "gn:country_code":"PH",
    "gn:dem":142,
    "gn:feature_class":"P",
    "gn:feature_code":"PPL",
    "gn:name":"Tagnasancan",
    "gn:population":0,
    "gn:timezone":"Asia/Manila",
    "iso:country":"PH",
    "name:fil_x_preferred":[
        "Tagnasancan"
    ],
    "wof:name":"Tagnasancan",
    "wof:placetype":"locality"
},
  "geometry": {"coordinates":[125.78333000000001,7.13333],"type":"Point"}
}