{
  "type": "Feature",
  "properties": {
    "gn:admin1_code":"02",
    "gn:admin2_code":"14",
    "gn:admin3_code":"21507000.0",
    "gn:asciiname":"Centro West",
    "gn:country_code":"PH",
    "gn:dem":9,
    "gn:feature_class":"P",
    "gn:feature_code":"PPL",
    "gn:name":"Centro West",
    "gn:population":0,
    "gn:timezone":"Asia/Manila",
    "iso:country":"PH",
    "wof:name":"Centro West",
    "wof:placetype":"locality"
},
  "geometry": {"coordinates":[121.50541,18.41418],"type":"Point"}
}