{
  "type": "Feature",
  "properties": {
    "gn:admin1_code":"14",
    "gn:admin2_code":"60",
    "gn:admin3_code":"156612000.0",
    "gn:asciiname":"Manta",
    "gn:country_code":"PH",
    "gn:dem":16,
    "gn:feature_class":"P",
    "gn:feature_code":"PPL",
    "gn:name":"Manta",
    "gn:population":0,
    "gn:timezone":"Asia/Manila",
    "iso:country":"PH",
    "name:eng_x_preferred":[
        "Manta"
    ],
    "wof:name":"Manta",
    "wof:placetype":"locality"
},
  "geometry": {"coordinates":[120.8733,5.5773],"type":"Point"}
}