{
  "type": "Feature",
  "properties": {
    "gn:admin1_code":"14",
    "gn:admin2_code":"60",
    "gn:admin3_code":"156612000.0",
    "gn:asciiname":"Manta",
    "gn:country_code":"PH",
    "gn:dem":16,
    "gn:feature_class":"P",
    "gn:feature_code":"PPL",
    "gn:name":"Manta",
    "gn:population":0,
    "gn:timezone":"Asia/Manila",
    "iso:country":"PH",
    "name:ceb_x_preferred":[
        "Manta"
    ],
    "name:deu_x_preferred":[
        "Manta"
    ],
    "name:eng_x_preferred":[
        "Manta"
    ],
    "name:eus_x_preferred":[
        "Manta"
    ],
    "name:fin_x_preferred":[
        "Manta"
    ],
    "name:fra_x_preferred":[
        "Manta"
    ],
    "name:hun_x_preferred":[
        "Manta"
    ],
    "name:hye_x_preferred":[
        "\u0544\u0561\u0576\u057f\u0561"
    ],
    "name:ind_x_preferred":[
        "Manta"
    ],
    "name:ita_x_preferred":[
        "Manta"
    ],
    "name:jpn_x_preferred":[
        "\u30de\u30f3\u30bf"
    ],
    "name:lav_x_preferred":[
        "Manta"
    ],
    "name:lmo_x_preferred":[
        "Manta"
    ],
    "name:nds_x_preferred":[
        "Manta"
    ],
    "name:nld_x_preferred":[
        "Manta"
    ],
    "name:nor_x_preferred":[
        "Manta"
    ],
    "name:pol_x_preferred":[
        "Manta"
    ],
    "name:por_x_preferred":[
        "Manta"
    ],
    "name:ron_x_preferred":[
        "Manta"
    ],
    "name:rus_x_preferred":[
        "\u041c\u0430\u043d\u0442\u0430"
    ],
    "name:scn_x_preferred":[
        "Manta"
    ],
    "name:spa_x_preferred":[
        "Manta"
    ],
    "name:swe_x_preferred":[
        "Manta"
    ],
    "name:tur_x_preferred":[
        "Manta"
    ],
    "name:ukr_x_preferred":[
        "\u041c\u0430\u043d\u0442\u0430"
    ],
    "name:vie_x_preferred":[
        "Manta"
    ],
    "name:vol_x_preferred":[
        "Manta"
    ],
    "wof:name":"Manta",
    "wof:placetype":"locality"
},
  "geometry": {"coordinates":[120.8733,5.5773],"type":"Point"}
}