{
  "type": "Feature",
  "properties": {
    "gn:admin1_code":"03",
    "gn:admin2_code":"64",
    "gn:admin3_code":"37105000.0",
    "gn:asciiname":"Marangla",
    "gn:country_code":"PH",
    "gn:dem":12,
    "gn:feature_class":"P",
    "gn:feature_code":"PPL",
    "gn:name":"Marangla",
    "gn:population":0,
    "gn:timezone":"Asia/Manila",
    "iso:country":"PH",
    "name:fil_x_preferred":[
        "Marangla"
    ],
    "name:und_x_variant":[
        "Maranala"
    ],
    "wof:name":"Marangla",
    "wof:placetype":"locality"
},
  "geometry": {"coordinates":[119.9695,15.3957],"type":"Point"}
}