{
  "type": "Feature",
  "properties": {
    "gn:admin1_code":"11",
    "gn:admin2_code":"I7",
    "gn:admin3_code":"112314000.0",
    "gn:asciiname":"Misaoy",
    "gn:country_code":"PH",
    "gn:dem":17,
    "gn:feature_class":"P",
    "gn:feature_code":"PPL",
    "gn:name":"Misaoy",
    "gn:population":0,
    "gn:timezone":"Asia/Manila",
    "iso:country":"PH",
    "name:fil_x_preferred":[
        "Misaoy"
    ],
    "name:und_x_variant":[
        "Misaay"
    ],
    "wof:name":"Misaoy",
    "wof:placetype":"locality"
},
  "geometry": {"coordinates":[125.7929,7.5215],"type":"Point"}
}