{
  "type": "Feature",
  "properties": {
    "gn:admin1_code":"15",
    "gn:admin2_code":"32",
    "gn:admin3_code":"143208000.0",
    "gn:asciiname":"Bagtayan",
    "gn:country_code":"PH",
    "gn:dem":1026,
    "gn:feature_class":"P",
    "gn:feature_code":"PPL",
    "gn:name":"Bagtayan",
    "gn:population":0,
    "gn:timezone":"Asia/Manila",
    "iso:country":"PH",
    "name:fil_x_preferred":[
        "Bagtayan"
    ],
    "wof:name":"Bagtayan",
    "wof:placetype":"locality"
},
  "geometry": {"coordinates":[121.15000000000001,17.41667],"type":"Point"}
}