{
  "type": "Feature",
  "properties": {
    "gn:admin1_code":"03",
    "gn:admin2_code":"13",
    "gn:admin3_code":"31418000.0",
    "gn:asciiname":"Santo Cristo",
    "gn:country_code":"PH",
    "gn:dem":13,
    "gn:feature_class":"P",
    "gn:feature_code":"PPL",
    "gn:name":"Santo Cristo",
    "gn:population":0,
    "gn:timezone":"Asia/Manila",
    "iso:country":"PH",
    "name:fil_x_preferred":[
        "Santo Cristo"
    ],
    "wof:name":"Santo Cristo",
    "wof:placetype":"locality"
},
  "geometry": {"coordinates":[120.84999999999999,14.93333],"type":"Point"}
}