{
  "type": "Feature",
  "properties": {
    "gn:admin1_code":"41",
    "gn:admin2_code":"49",
    "gn:admin3_code":"175322000.0",
    "gn:asciiname":"Diborda",
    "gn:country_code":"PH",
    "gn:dem":12,
    "gn:feature_class":"P",
    "gn:feature_code":"PPL",
    "gn:name":"Diborda",
    "gn:population":0,
    "gn:timezone":"Asia/Manila",
    "iso:country":"PH",
    "name:eng_x_preferred":[
        "Diborda"
    ],
    "wof:name":"Diborda",
    "wof:placetype":"locality"
},
  "geometry": {"coordinates":[119.85509999999999,11.9487],"type":"Point"}
}