{
  "type": "Feature",
  "properties": {
    "gn:admin1_code":"05",
    "gn:admin2_code":"58",
    "gn:admin3_code":"56207000.0",
    "gn:asciiname":"Servilla",
    "gn:country_code":"PH",
    "gn:dem":61,
    "gn:feature_class":"P",
    "gn:feature_code":"PPL",
    "gn:name":"Servilla",
    "gn:population":0,
    "gn:timezone":"Asia/Manila",
    "iso:country":"PH",
    "name:fil_x_preferred":[
        "Servilla"
    ],
    "name:und_x_variant":[
        "Sevilla"
    ],
    "wof:name":"Servilla",
    "wof:placetype":"locality"
},
  "geometry": {"coordinates":[123.6301,12.9395],"type":"Point"}
}