{
  "type": "Feature",
  "properties": {
    "gn:country":"PH",
    "gn:fcode":"ADM3",
    "gn:pop":14056,
    "iso:country":"PH",
    "name:ceb_x_preferred":[
        "Magdiwang"
    ],
    "name:fil_x_preferred":[
        "Magdiwang"
    ],
    "name:tgl_x_preferred":[
        "Magdiwang"
    ],
    "qs:name":"Magdiwang",
    "qs:photos_9r":0,
    "qs:photos_sr":0,
    "qs:pop_sr":"6",
    "wd:wordcount":33,
    "wof:name":"Magdiwang",
    "wof:placetype":"localadmin",
    "wof:population":14056
},
  "geometry": {"coordinates":[122.53333000000001,12.46667],"type":"Point"}
}