{
  "type": "Feature",
  "properties": {
    "gn:admin1_code":"07",
    "gn:admin2_code":"46",
    "gn:admin3_code":"74616000.0",
    "gn:asciiname":"Basang",
    "gn:country_code":"PH",
    "gn:dem":25,
    "gn:feature_class":"P",
    "gn:feature_code":"PPL",
    "gn:name":"Basang",
    "gn:population":0,
    "gn:timezone":"Asia/Manila",
    "iso:country":"PH",
    "name:fil_x_preferred":[
        "Basang"
    ],
    "name:swe_x_preferred":[
        "Pasang"
    ],
    "name:zho_x_preferred":[
        "\u5df4\u6851"
    ],
    "wof:name":"Basang",
    "wof:placetype":"locality"
},
  "geometry": {"coordinates":[123.11109999999999,9.4861],"type":"Point"}
}