{
  "type": "Feature",
  "properties": {
    "gn:admin1_code":"08",
    "gn:admin2_code":"55",
    "gn:admin3_code":"86016000.0",
    "gn:asciiname":"Sorsogon",
    "gn:country_code":"PH",
    "gn:dem":7,
    "gn:feature_class":"P",
    "gn:feature_code":"PPL",
    "gn:name":"Sorsogon",
    "gn:population":0,
    "gn:timezone":"Asia/Manila",
    "iso:country":"PH",
    "name:ace_x_preferred":[
        "Propinsi Sorsogon"
    ],
    "name:ara_x_preferred":[
        "\u0633\u0648\u0631\u0648\u0633\u0648\u063a\u0648\u0646"
    ],
    "name:azb_x_preferred":[
        "\u0633\u0648\u0631\u0633\u0648\u0642\u0648\u0646"
    ],
    "name:bcl_x_preferred":[
        "Sorsogon"
    ],
    "name:ceb_x_preferred":[
        "Sorsogon"
    ],
    "name:deu_x_preferred":[
        "Sorsogon"
    ],
    "name:epo_x_preferred":[
        "Sorsogono"
    ],
    "name:fas_x_preferred":[
        "\u0633\u0648\u0631\u0633\u0648\u06af\u0648\u0646"
    ],
    "name:fil_x_preferred":[
        "Sorsogon"
    ],
    "name:fin_x_preferred":[
        "Sorsogon"
    ],
    "name:fra_x_preferred":[
        "Sorsogon"
    ],
    "name:hin_x_preferred":[
        "\u0938\u094b\u0930\u0938\u094b\u0917\u094b\u0928 \u092a\u094d\u0930\u093e\u0928\u094d\u0924"
    ],
    "name:ilo_x_preferred":[
        "Sorsogon"
    ],
    "name:ind_x_preferred":[
        "Sorsogon"
    ],
    "name:jpn_x_preferred":[
        "\u30bd\u30eb\u30bd\u30b4\u30f3\u5dde"
    ],
    "name:kor_x_preferred":[
        "\uc18c\ub974\uc18c\uace4\uc8fc"
    ],
    "name:lat_x_preferred":[
        "Sorsogon"
    ],
    "name:mkd_x_preferred":[
        "\u0421\u043e\u0440\u0441\u043e\u0433\u043e\u043d"
    ],
    "name:nld_x_preferred":[
        "Sorsogon"
    ],
    "name:nor_x_preferred":[
        "Sorsogon"
    ],
    "name:pag_x_preferred":[
        "Sorsogon"
    ],
    "name:pam_x_preferred":[
        "Sorsogon"
    ],
    "name:pol_x_preferred":[
        "Sorsogon"
    ],
    "name:rus_x_preferred":[
        "\u0421\u043e\u0440\u0441\u043e\u0433\u043e\u043d"
    ],
    "name:swe_x_preferred":[
        "Sorsogon"
    ],
    "name:tam_x_preferred":[
        "\u0b9a\u0bca\u0bb0\u0bcd\u0b9a\u0bcb\u0b95\u0bca\u0ba9\u0bcd"
    ],
    "name:tgl_x_preferred":[
        "Sorsogon"
    ],
    "name:tha_x_preferred":[
        "\u0e08\u0e31\u0e07\u0e2b\u0e27\u0e31\u0e14\u0e0b\u0e2d\u0e23\u0e4c\u0e42\u0e0b\u0e42\u0e01\u0e19"
    ],
    "name:tur_x_preferred":[
        "Sorsogon"
    ],
    "name:ukr_x_preferred":[
        "\u0421\u043e\u0440\u0441\u043e\u0433\u043e\u043d"
    ],
    "name:und_x_variant":[
        "Solsogon"
    ],
    "name:urd_x_preferred":[
        "\u0633\u0648\u0631\u0633\u0648\u06af\u0648\u0646"
    ],
    "name:vie_x_preferred":[
        "Sorsogon"
    ],
    "name:war_x_preferred":[
        "Sorsogon"
    ],
    "name:zho_x_preferred":[
        "\u7d22\u7d22\u8ca2\u7701"
    ],
    "wof:name":"Sorsogon",
    "wof:placetype":"locality"
},
  "geometry": {"coordinates":[124.6739,12.0339],"type":"Point"}
}