{
  "type": "Feature",
  "properties": {
    "gn:admin1_code":"08",
    "gn:admin2_code":"55",
    "gn:admin3_code":"86016000.0",
    "gn:asciiname":"Sorsogon",
    "gn:country_code":"PH",
    "gn:dem":7,
    "gn:feature_class":"P",
    "gn:feature_code":"PPL",
    "gn:name":"Sorsogon",
    "gn:population":0,
    "gn:timezone":"Asia/Manila",
    "iso:country":"PH",
    "name:fil_x_preferred":[
        "Sorsogon"
    ],
    "name:rus_x_preferred":[
        "\u0421\u043e\u0440\u0441\u043e\u0433\u043e\u043d"
    ],
    "name:und_x_variant":[
        "Solsogon",
        "Sorsogon"
    ],
    "wof:name":"Sorsogon",
    "wof:placetype":"locality"
},
  "geometry": {"coordinates":[124.6739,12.0339],"type":"Point"}
}