{
  "type": "Feature",
  "properties": {
    "gn:admin1_code":"01",
    "gn:admin2_code":"51",
    "gn:admin3_code":"15530000.0",
    "gn:asciiname":"Maanbal",
    "gn:country_code":"PH",
    "gn:dem":40,
    "gn:feature_class":"P",
    "gn:feature_code":"PPL",
    "gn:name":"Maanbal",
    "gn:population":0,
    "gn:timezone":"Asia/Manila",
    "iso:country":"PH",
    "name:fil_x_preferred":[
        "Maanbal"
    ],
    "name:fil_x_variant":[
        "Manaol"
    ],
    "wof:name":"Maanbal",
    "wof:placetype":"locality"
},
  "geometry": {"coordinates":[120.51130000000001,16.1138],"type":"Point"}
}