{
  "type": "Feature",
  "properties": {
    "gn:admin1_code":"41",
    "gn:admin2_code":"49",
    "gn:admin3_code":"175309000.0",
    "gn:asciiname":"Dicaltom",
    "gn:country_code":"PH",
    "gn:dem":3,
    "gn:feature_class":"P",
    "gn:feature_code":"PPL",
    "gn:name":"Dicaltom",
    "gn:population":0,
    "gn:timezone":"Asia/Manila",
    "iso:country":"PH",
    "name:fil_x_preferred":[
        "Dicaltom"
    ],
    "wof:name":"Dicaltom",
    "wof:placetype":"locality"
},
  "geometry": {"coordinates":[120.21411000000001,12.17257],"type":"Point"}
}