{
  "type": "Feature",
  "properties": {
    "gn:admin1_code":"05",
    "gn:admin2_code":"05",
    "gn:admin3_code":"50507000.0",
    "gn:asciiname":"Lalombon",
    "gn:country_code":"PH",
    "gn:dem":147,
    "gn:feature_class":"P",
    "gn:feature_code":"PPL",
    "gn:name":"Lalombon",
    "gn:population":0,
    "gn:timezone":"Asia/Manila",
    "iso:country":"PH",
    "name:fil_x_preferred":[
        "Lalombon"
    ],
    "wof:name":"Lalombon",
    "wof:placetype":"locality"
},
  "geometry": {"coordinates":[123.33410000000001,13.2653],"type":"Point"}
}