{
  "type": "Feature",
  "properties": {
    "gn:admin1_code":"03",
    "gn:admin2_code":"47",
    "gn:admin3_code":"34922000.0",
    "gn:asciiname":"San Andres Primero",
    "gn:country_code":"PH",
    "gn:dem":31,
    "gn:feature_class":"P",
    "gn:feature_code":"PPL",
    "gn:name":"San Andres Primero",
    "gn:population":0,
    "gn:timezone":"Asia/Manila",
    "iso:country":"PH",
    "name:fil_x_preferred":[
        "San Andres I"
    ],
    "wof:name":"San Andres Primero",
    "wof:placetype":"locality"
},
  "geometry": {"coordinates":[120.84480000000001,15.5309],"type":"Point"}
}