{
  "type": "Feature",
  "properties": {
    "gn:country":"PH",
    "gn:fcode":"PPLA3",
    "gn:pop":119475,
    "iso:country":"PH",
    "name:bcl_x_preferred":[
        "Silang"
    ],
    "name:cat_x_preferred":[
        "Silang"
    ],
    "name:deu_x_preferred":[
        "Silang"
    ],
    "name:eng_x_preferred":[
        "Silang"
    ],
    "name:fra_x_preferred":[
        "Silang"
    ],
    "name:ilo_x_preferred":[
        "Silang"
    ],
    "name:ind_x_preferred":[
        "Silang"
    ],
    "name:ita_x_preferred":[
        "Silang"
    ],
    "name:jpn_x_preferred":[
        "\u30b7\u30e9\u30f3\u5e02"
    ],
    "name:msa_x_preferred":[
        "Silang"
    ],
    "name:nld_x_preferred":[
        "Silang"
    ],
    "name:oci_x_preferred":[
        "Silang"
    ],
    "name:pag_x_preferred":[
        "Silang"
    ],
    "name:pam_x_preferred":[
        "Silang"
    ],
    "name:spa_x_preferred":[
        "Silang"
    ],
    "name:swe_x_preferred":[
        "Silang"
    ],
    "name:tgl_x_preferred":[
        "Silang"
    ],
    "name:vie_x_preferred":[
        "Silang"
    ],
    "name:war_x_preferred":[
        "Silang"
    ],
    "qs:name":"Silang",
    "qs:photos_9r":0,
    "qs:photos_sr":0,
    "qs:pop_sr":"9",
    "wd:wordcount":10,
    "wof:name":"Silang",
    "wof:placetype":"locality",
    "wof:population":119475
},
  "geometry": {"coordinates":[120.97136999999999,14.21567],"type":"Point"}
}