{
  "type": "Feature",
  "properties": {
    "gn:admin1_code":"02",
    "gn:admin2_code":"31",
    "gn:admin3_code":"23133000.0",
    "gn:asciiname":"Cabanguan",
    "gn:country_code":"PH",
    "gn:dem":70,
    "gn:feature_class":"P",
    "gn:feature_code":"PPL",
    "gn:name":"Cabanguan",
    "gn:population":0,
    "gn:timezone":"Asia/Manila",
    "iso:country":"PH",
    "name:fil_x_preferred":[
        "Cabanguan"
    ],
    "wof:name":"Cabanguan",
    "wof:placetype":"locality"
},
  "geometry": {"coordinates":[121.86778,17.41889],"type":"Point"}
}