{
  "type": "Feature",
  "properties": {
    "gn:admin1_code":"40",
    "gn:admin2_code":"53",
    "gn:admin3_code":"45814000.0",
    "gn:asciiname":"Buhangin",
    "gn:country_code":"PH",
    "gn:dem":71,
    "gn:feature_class":"P",
    "gn:feature_code":"PPL",
    "gn:name":"Buha\u00f1gin",
    "gn:population":0,
    "gn:timezone":"Asia/Manila",
    "iso:country":"PH",
    "name:fil_x_preferred":[
        "Buha\u00f1gin"
    ],
    "wof:name":"Buhangin",
    "wof:placetype":"locality"
},
  "geometry": {"coordinates":[121.23333,14.58333],"type":"Point"}
}