{
  "type": "Feature",
  "properties": {
    "gn:admin1_code":"05",
    "gn:admin2_code":"58",
    "gn:admin3_code":"56216000.0",
    "gn:asciiname":"Pangpang",
    "gn:country_code":"PH",
    "gn:dem":49,
    "gn:feature_class":"P",
    "gn:feature_code":"PPL",
    "gn:name":"Pangpang",
    "gn:population":0,
    "gn:timezone":"Asia/Manila",
    "iso:country":"PH",
    "name:fil_x_preferred":[
        "Pangpang"
    ],
    "wof:name":"Pangpang",
    "wof:placetype":"locality"
},
  "geometry": {"coordinates":[123.98333,12.98333],"type":"Point"}
}