{
  "type": "Feature",
  "properties": {
    "gn:admin1_code":"01",
    "gn:admin2_code":"51",
    "gn:admin3_code":"15527000.0",
    "gn:asciiname":"Capaoan",
    "gn:country_code":"PH",
    "gn:dem":25,
    "gn:feature_class":"P",
    "gn:feature_code":"PPL",
    "gn:name":"Capaoan",
    "gn:population":0,
    "gn:timezone":"Asia/Manila",
    "iso:country":"PH",
    "name:fil_x_preferred":[
        "Capaoan"
    ],
    "wof:name":"Capaoan",
    "wof:placetype":"locality"
},
  "geometry": {"coordinates":[120.3152,15.7568],"type":"Point"}
}