{
  "type": "Feature",
  "properties": {
    "gn:admin1_code":"13",
    "gn:admin2_code":"02",
    "gn:admin3_code":"160208000.0",
    "gn:asciiname":"Mambutua",
    "gn:country_code":"PH",
    "gn:dem":8,
    "gn:feature_class":"P",
    "gn:feature_code":"PPL",
    "gn:name":"Mambutua",
    "gn:population":0,
    "gn:timezone":"Asia/Manila",
    "iso:country":"PH",
    "name:fil_x_preferred":[
        "Mambutua"
    ],
    "wof:name":"Mambutua",
    "wof:placetype":"locality"
},
  "geometry": {"coordinates":[125.56667,9.01667],"type":"Point"}
}