{
  "type": "Feature",
  "properties": {
    "gn:admin1_code":"40",
    "gn:admin2_code":"20",
    "gn:admin3_code":"42109000.0",
    "gn:asciiname":"Medicion Primero",
    "gn:country_code":"PH",
    "gn:dem":9,
    "gn:feature_class":"P",
    "gn:feature_code":"PPL",
    "gn:name":"Medicion Primero",
    "gn:population":0,
    "gn:timezone":"Asia/Manila",
    "iso:country":"PH",
    "name:fil_x_preferred":[
        "Medicion Primero"
    ],
    "wof:name":"Medicion Primero",
    "wof:placetype":"locality"
},
  "geometry": {"coordinates":[120.93333,14.43333],"type":"Point"}
}