{
  "type": "Feature",
  "properties": {
    "gn:admin1_code":"06",
    "gn:admin2_code":"H3",
    "gn:admin3_code":"64514000.0",
    "gn:asciiname":"Himook",
    "gn:country_code":"PH",
    "gn:dem":53,
    "gn:feature_class":"P",
    "gn:feature_code":"PPL",
    "gn:name":"Himook",
    "gn:population":0,
    "gn:timezone":"Asia/Manila",
    "iso:country":"PH",
    "name:fil_x_preferred":[
        "Himook"
    ],
    "wof:name":"Himook",
    "wof:placetype":"locality"
},
  "geometry": {"coordinates":[123.0021,10.1644],"type":"Point"}
}