{
  "type": "Feature",
  "properties": {
    "gn:admin1_code":"40",
    "gn:admin2_code":"09",
    "gn:admin3_code":"41031000.0",
    "gn:asciiname":"Natatas",
    "gn:country_code":"PH",
    "gn:dem":161,
    "gn:feature_class":"P",
    "gn:feature_code":"PPL",
    "gn:name":"Natatas",
    "gn:population":0,
    "gn:timezone":"Asia/Manila",
    "iso:country":"PH",
    "name:fil_x_preferred":[
        "Natatas"
    ],
    "wof:name":"Natatas",
    "wof:placetype":"locality"
},
  "geometry": {"coordinates":[121.12223,14.08093],"type":"Point"}
}