{
  "type": "Feature",
  "properties": {
    "gn:admin1_code":"14",
    "gn:admin2_code":"35",
    "gn:admin3_code":"153615000.0",
    "gn:asciiname":"Osio",
    "gn:country_code":"PH",
    "gn:dem":64,
    "gn:feature_class":"P",
    "gn:feature_code":"PPL",
    "gn:name":"Osio",
    "gn:population":0,
    "gn:timezone":"Asia/Manila",
    "iso:country":"PH",
    "name:fil_x_preferred":[
        "Osio"
    ],
    "name:ita_x_preferred":[
        "Osio"
    ],
    "name:por_x_preferred":[
        "Osio"
    ],
    "wof:name":"Osio",
    "wof:placetype":"locality"
},
  "geometry": {"coordinates":[124.09999999999999,7.56667],"type":"Point"}
}