{
  "type": "Feature",
  "properties": {
    "gn:admin1_code":"15",
    "gn:admin2_code":"01",
    "gn:admin3_code":"140117000.0",
    "gn:asciiname":"Balawarte",
    "gn:country_code":"PH",
    "gn:dem":200,
    "gn:feature_class":"P",
    "gn:feature_code":"PPL",
    "gn:name":"Balawarte",
    "gn:population":0,
    "gn:timezone":"Asia/Manila",
    "iso:country":"PH",
    "name:fil_x_preferred":[
        "Balawarte"
    ],
    "wof:name":"Balawarte",
    "wof:placetype":"locality"
},
  "geometry": {"coordinates":[120.66670000000001,17.549],"type":"Point"}
}