{
  "type": "Feature",
  "properties": {
    "gn:admin1_code":"01",
    "gn:admin2_code":"29",
    "gn:admin3_code":"12927000.0",
    "gn:asciiname":"Nalasin",
    "gn:country_code":"PH",
    "gn:dem":13,
    "gn:feature_class":"P",
    "gn:feature_code":"PPL",
    "gn:name":"Nalasin",
    "gn:population":0,
    "gn:timezone":"Asia/Manila",
    "iso:country":"PH",
    "name:fil_x_preferred":[
        "Nalasin"
    ],
    "wof:name":"Nalasin",
    "wof:placetype":"locality"
},
  "geometry": {"coordinates":[120.4472,17.2905],"type":"Point"}
}