{
  "type": "Feature",
  "properties": {
    "gn:admin1_code":"06",
    "gn:admin2_code":"04",
    "gn:admin3_code":"60403000.0",
    "gn:asciiname":"Daguitan",
    "gn:country_code":"PH",
    "gn:dem":39,
    "gn:feature_class":"P",
    "gn:feature_code":"PPL",
    "gn:name":"Daguitan",
    "gn:population":0,
    "gn:timezone":"Asia/Manila",
    "iso:country":"PH",
    "name:fil_x_preferred":[
        "Daguitan"
    ],
    "wof:name":"Daguitan",
    "wof:placetype":"locality"
},
  "geometry": {"coordinates":[122.3237,11.5481],"type":"Point"}
}