{
  "type": "Feature",
  "properties": {
    "gn:admin1_code":"40",
    "gn:admin2_code":"H2",
    "gn:admin3_code":"45631000.0",
    "gn:asciiname":"Pinagagan",
    "gn:country_code":"PH",
    "gn:dem":-9999,
    "gn:feature_class":"P",
    "gn:feature_code":"PPL",
    "gn:name":"Pinagagan",
    "gn:population":0,
    "gn:timezone":"Asia/Manila",
    "iso:country":"PH",
    "name:fil_x_preferred":[
        "Pinagagan"
    ],
    "wof:name":"Pinagagan",
    "wof:placetype":"locality"
},
  "geometry": {"coordinates":[121.83114999999999,15.00329],"type":"Point"}
}