{
  "type": "Feature",
  "properties": {
    "gn:admin1_code":"06",
    "gn:admin2_code":"06",
    "gn:admin3_code":"60614000.0",
    "gn:asciiname":"Lumpatan",
    "gn:country_code":"PH",
    "gn:dem":104,
    "gn:feature_class":"P",
    "gn:feature_code":"PPL",
    "gn:name":"Lumpatan",
    "gn:population":0,
    "gn:timezone":"Asia/Manila",
    "iso:country":"PH",
    "name:fil_x_preferred":[
        "Lumpatan"
    ],
    "wof:name":"Lumpatan",
    "wof:placetype":"locality"
},
  "geometry": {"coordinates":[122.1452,10.9027],"type":"Point"}
}