{
  "type": "Feature",
  "properties": {
    "gn:admin1_code":"07",
    "gn:admin2_code":"21",
    "gn:admin3_code":"72219000.0",
    "gn:asciiname":"Panas",
    "gn:country_code":"PH",
    "gn:dem":244,
    "gn:feature_class":"P",
    "gn:feature_code":"PPL",
    "gn:name":"Panas",
    "gn:population":0,
    "gn:timezone":"Asia/Manila",
    "iso:country":"PH",
    "name:deu_x_preferred":[
        "Panas"
    ],
    "name:fil_x_preferred":[
        "Panas"
    ],
    "name:rus_x_preferred":[
        "\u041f\u0430\u043d\u0430\u0441"
    ],
    "name:ukr_x_preferred":[
        "\u041f\u0430\u043d\u0430\u0441"
    ],
    "wof:name":"Panas",
    "wof:placetype":"locality"
},
  "geometry": {"coordinates":[123.93266,10.42612],"type":"Point"}
}