{
  "type": "Feature",
  "properties": {
    "gn:country":"PH",
    "gn:fcode":"PPL",
    "gn:pop":6302,
    "iso:country":"PH",
    "name:fil_x_preferred":[
        "Tamnag"
    ],
    "qs:name":"Tamnag",
    "qs:photos_9r":0,
    "qs:photos_sr":0,
    "qs:pop_sr":"5",
    "wof:name":"Tamnag",
    "wof:placetype":"locality",
    "wof:population":6302
},
  "geometry": {"coordinates":[124.85056,6.56778],"type":"Point"}
}