{
  "type": "Feature",
  "properties": {
    "gn:admin1_code":"14",
    "gn:admin2_code":"35",
    "gn:admin3_code":"153617000.0",
    "gn:asciiname":"Sugud",
    "gn:country_code":"PH",
    "gn:dem":705,
    "gn:feature_class":"P",
    "gn:feature_code":"PPL",
    "gn:name":"Sugud",
    "gn:population":0,
    "gn:timezone":"Asia/Manila",
    "iso:country":"PH",
    "name:fil_x_preferred":[
        "Sugud"
    ],
    "name:und_x_variant":[
        "Sugod"
    ],
    "wof:name":"Sugud",
    "wof:placetype":"locality"
},
  "geometry": {"coordinates":[124.31833,8.00611],"type":"Point"}
}