{
  "type": "Feature",
  "properties": {
    "gn:admin1_code":"09",
    "gn:admin2_code":"66",
    "gn:admin3_code":"97341000.0",
    "gn:asciiname":"Kabalao",
    "gn:country_code":"PH",
    "gn:dem":11,
    "gn:feature_class":"P",
    "gn:feature_code":"PPL",
    "gn:name":"Kabalao",
    "gn:population":0,
    "gn:timezone":"Asia/Manila",
    "iso:country":"PH",
    "wof:name":"Kabalao",
    "wof:placetype":"locality"
},
  "geometry": {"coordinates":[123.17556,7.49694],"type":"Point"}
}