{
  "type": "Feature",
  "properties": {
    "gn:admin1_code":"03",
    "gn:admin2_code":"63",
    "gn:admin3_code":"36905000.0",
    "gn:asciiname":"Talimundoc San Miguel",
    "gn:country_code":"PH",
    "gn:dem":34,
    "gn:feature_class":"P",
    "gn:feature_code":"PPL",
    "gn:name":"Talimundoc San Miguel",
    "gn:population":0,
    "gn:timezone":"Asia/Manila",
    "iso:country":"PH",
    "name:fil_x_preferred":[
        "Talimundoc"
    ],
    "name:fil_x_variant":[
        "San Miguel"
    ],
    "wof:name":"Talimundoc San Miguel",
    "wof:placetype":"locality"
},
  "geometry": {"coordinates":[120.66265,15.3516],"type":"Point"}
}