{
  "type": "Feature",
  "properties": {
    "gn:admin1_code":"03",
    "gn:admin2_code":"50",
    "gn:admin3_code":"35414000.0",
    "gn:asciiname":"Picamalican",
    "gn:country_code":"PH",
    "gn:dem":7,
    "gn:feature_class":"P",
    "gn:feature_code":"PPL",
    "gn:name":"Picamalican",
    "gn:population":0,
    "gn:timezone":"Asia/Manila",
    "iso:country":"PH",
    "name:fil_x_preferred":[
        "Picamalican"
    ],
    "wof:name":"Picamalican",
    "wof:placetype":"locality"
},
  "geometry": {"coordinates":[120.6748,14.9533],"type":"Point"}
}