{
  "type": "Feature",
  "properties": {
    "gn:admin1_code":"13",
    "gn:admin2_code":"I9",
    "gn:admin3_code":"168502000.0",
    "gn:asciiname":"Del Pilar",
    "gn:country_code":"PH",
    "gn:dem":9,
    "gn:feature_class":"P",
    "gn:feature_code":"PPL",
    "gn:name":"Del Pilar",
    "gn:population":0,
    "gn:timezone":"Asia/Manila",
    "iso:country":"PH",
    "name:fil_x_preferred":[
        "Del Pilar"
    ],
    "wof:name":"Del Pilar",
    "wof:placetype":"locality"
},
  "geometry": {"coordinates":[125.675,9.99528],"type":"Point"}
}