{
  "type": "Feature",
  "properties": {
    "gn:admin1_code":"07",
    "gn:admin2_code":"11",
    "gn:admin3_code":"71240000.0",
    "gn:asciiname":"Canlangit",
    "gn:country_code":"PH",
    "gn:dem":188,
    "gn:feature_class":"P",
    "gn:feature_code":"PPL",
    "gn:name":"Canlangit",
    "gn:population":0,
    "gn:timezone":"Asia/Manila",
    "iso:country":"PH",
    "name:fil_x_preferred":[
        "Canlangit"
    ],
    "wof:name":"Canlangit",
    "wof:placetype":"locality"
},
  "geometry": {"coordinates":[124.29649999999999,9.798],"type":"Point"}
}