{
  "type": "Feature",
  "properties": {
    "gn:country":"PH",
    "gn:fcode":"PPL",
    "gn:population":3729,
    "iso:country":"PH",
    "name:fil_x_preferred":[
        "Buensuceso"
    ],
    "name:fil_x_variant":[
        "Buensuseso"
    ],
    "qs:name":"Buensuseso",
    "qs:photos_9r":0,
    "qs:photos_sr":0,
    "qs:pop_sr":"4",
    "wof:name":"Buensuseso",
    "wof:placetype":"locality",
    "wof:population":3729
},
  "geometry": {"coordinates":[120.67314,15.19334],"type":"Point"}
}