{
  "type": "Feature",
  "properties": {
    "gn:country":"PH",
    "gn:fcode":"PPL",
    "gn:pop":2230,
    "iso:country":"PH",
    "name:ceb_x_preferred":[
        "Amag\u00e1"
    ],
    "name:deu_x_preferred":[
        "Amag\u00e1"
    ],
    "name:fas_x_preferred":[
        "\u0627\u0645\u0627\u06af\u0627"
    ],
    "name:fil_x_preferred":[
        "Amaga"
    ],
    "name:fra_x_preferred":[
        "Amag\u00e1"
    ],
    "name:gla_x_preferred":[
        "Amag\u00e1"
    ],
    "name:ile_x_preferred":[
        "Amag\u00e1"
    ],
    "name:ilo_x_preferred":[
        "Amag\u00e1"
    ],
    "name:ita_x_preferred":[
        "Amag\u00e1"
    ],
    "name:kat_x_preferred":[
        "\u10d0\u10db\u10d0\u10d2\u10d0"
    ],
    "name:msa_x_preferred":[
        "Amag\u00e1"
    ],
    "name:nld_x_preferred":[
        "Amag\u00e1"
    ],
    "name:por_x_preferred":[
        "Amag\u00e1"
    ],
    "name:ron_x_preferred":[
        "Amag\u00e1"
    ],
    "name:rus_x_preferred":[
        "\u0410\u043c\u0430\u0433\u0430"
    ],
    "name:spa_x_preferred":[
        "Amag\u00e1"
    ],
    "name:swe_x_preferred":[
        "Amag\u00e1"
    ],
    "name:szl_x_preferred":[
        "Amag\u00e1"
    ],
    "name:tgl_x_preferred":[
        "Amag\u00e1"
    ],
    "name:vie_x_preferred":[
        "Amag\u00e1"
    ],
    "name:war_x_preferred":[
        "Amag\u00e1"
    ],
    "name:zho_x_preferred":[
        "\u963f\u99ac\u52a0"
    ],
    "qs:name":"Amaga",
    "qs:photos_9r":0,
    "qs:photos_sr":0,
    "qs:pop_sr":"4",
    "wd:wordcount":149,
    "wof:name":"Amaga",
    "wof:placetype":"locality",
    "wof:population":2230
},
  "geometry": {"coordinates":[126.07028,8.53083],"type":"Point"}
}