{
  "type": "Feature",
  "properties": {
    "gn:country":"PH",
    "gn:fcode":"PPL",
    "gn:pop":2230,
    "iso:country":"PH",
    "name:fil_x_preferred":[
        "Amaga"
    ],
    "qs:name":"Amaga",
    "qs:photos_9r":0,
    "qs:photos_sr":0,
    "qs:pop_sr":"4",
    "wd:wordcount":149,
    "wof:name":"Amaga",
    "wof:placetype":"locality",
    "wof:population":2230
},
  "geometry": {"coordinates":[126.07028,8.53083],"type":"Point"}
}