{
  "type": "Feature",
  "properties": {
    "gn:country":"PH",
    "gn:fcode":"ADM3",
    "gn:population":7345,
    "iso:country":"PH",
    "name:fil_x_preferred":[
        "Sikatuna"
    ],
    "qs:name":"Sikatuna",
    "qs:photos_9r":0,
    "qs:photos_sr":0,
    "qs:pop_sr":"5",
    "wd:wordcount":16,
    "wof:name":"Sikatuna",
    "wof:placetype":"localadmin",
    "wof:population":7345
},
  "geometry": {"coordinates":[123.98241,9.6853],"type":"Point"}
}