{
  "type": "Feature",
  "properties": {
    "gn:admin1_code":"40",
    "gn:admin2_code":"H2",
    "gn:admin3_code":"45642000.0",
    "gn:asciiname":"Yabaan",
    "gn:country_code":"PH",
    "gn:dem":12,
    "gn:feature_class":"P",
    "gn:feature_code":"PPL",
    "gn:name":"Yabaan",
    "gn:population":0,
    "gn:timezone":"Asia/Manila",
    "iso:country":"PH",
    "name:fil_x_preferred":[
        "Yabaan"
    ],
    "wof:name":"Yabaan",
    "wof:placetype":"locality"
},
  "geometry": {"coordinates":[122.5391,13.22073],"type":"Point"}
}