{
  "type": "Feature",
  "properties": {
    "gn:admin1_code":"08",
    "gn:admin2_code":"37",
    "gn:admin3_code":"83705000.0",
    "gn:asciiname":"Samputan",
    "gn:cc2":"PH",
    "gn:country_code":"PH",
    "gn:dem":40,
    "gn:feature_class":"P",
    "gn:feature_code":"PPL",
    "gn:name":"Samputan",
    "gn:population":0,
    "gn:timezone":"Asia/Manila",
    "iso:country":"PH",
    "name:und_x_variant":[
        "Sangputan",
        "Samputan"
    ],
    "wof:name":"Samputan",
    "wof:placetype":"locality"
},
  "geometry": {"coordinates":[124.90639,11.41972],"type":"Point"}
}