{
  "type": "Feature",
  "properties": {
    "gn:admin1_code":"40",
    "gn:admin2_code":"H2",
    "gn:asciiname":"Minaloco",
    "gn:country_code":"PH",
    "gn:dem":7,
    "gn:feature_class":"P",
    "gn:feature_code":"PPL",
    "gn:name":"Minaloco",
    "gn:population":0,
    "gn:timezone":"Asia/Manila",
    "iso:country":"PH",
    "name:fil_x_preferred":[
        "Minaloco"
    ],
    "wof:name":"Minaloco",
    "wof:placetype":"locality"
},
  "geometry": {"coordinates":[122.2055,14.865],"type":"Point"}
}