{
  "type": "Feature",
  "properties": {
    "gn:admin1_code":"15",
    "gn:admin2_code":"10",
    "gn:admin3_code":"141108000.0",
    "gn:asciiname":"Paykek",
    "gn:country_code":"PH",
    "gn:dem":881,
    "gn:feature_class":"P",
    "gn:feature_code":"PPL",
    "gn:name":"Paykek",
    "gn:population":0,
    "gn:timezone":"Asia/Manila",
    "iso:country":"PH",
    "name:fil_x_preferred":[
        "Paykek"
    ],
    "name:fil_x_variant":[
        "Payuek",
        "Payquek",
        "Payquec"
    ],
    "name:und_x_variant":[
        "Payquek",
        "Payquec"
    ],
    "wof:name":"Paykek",
    "wof:placetype":"locality"
},
  "geometry": {"coordinates":[120.6033,16.5856],"type":"Point"}
}