{
  "type": "Feature",
  "properties": {
    "gn:admin1_code":"03",
    "gn:admin2_code":"63",
    "gn:admin3_code":"36905000.0",
    "gn:asciiname":"Alfonso",
    "gn:country_code":"PH",
    "gn:dem":42,
    "gn:feature_class":"P",
    "gn:feature_code":"PPL",
    "gn:name":"Alfonso",
    "gn:population":0,
    "gn:timezone":"Asia/Manila",
    "iso:country":"PH",
    "name:fil_x_preferred":[
        "Alfonso"
    ],
    "wof:name":"Alfonso",
    "wof:placetype":"locality"
},
  "geometry": {"coordinates":[120.63773,15.33266],"type":"Point"}
}