{
  "type": "Feature",
  "properties": {
    "iso:country":"PH",
    "name:bcl_x_preferred":[
        "Kadingilan"
    ],
    "name:cbk_zam_x_preferred":[
        "Kadingilan"
    ],
    "name:ceb_x_preferred":[
        "Kadingilan"
    ],
    "name:deu_x_preferred":[
        "Kadingilan"
    ],
    "name:eng_x_preferred":[
        "Kadingilan"
    ],
    "name:fra_x_preferred":[
        "Kadingilan"
    ],
    "name:ilo_x_preferred":[
        "Kadingilan"
    ],
    "name:ind_x_preferred":[
        "Kadingilan"
    ],
    "name:ita_x_preferred":[
        "Kadingilan"
    ],
    "name:nld_x_preferred":[
        "Kadingilan"
    ],
    "name:pag_x_preferred":[
        "Kadingilan"
    ],
    "name:pam_x_preferred":[
        "Kadingilan"
    ],
    "name:spa_x_preferred":[
        "Kandingil\u00e1n"
    ],
    "name:spa_x_variant":[
        "Kadingil\u00e1n"
    ],
    "name:swe_x_preferred":[
        "Kadingilan"
    ],
    "name:tgl_x_preferred":[
        "Kadingilan"
    ],
    "name:und_x_variant":[
        "Kada\u00f1gilan"
    ],
    "name:urd_x_preferred":[
        "\u06a9\u0627\u062f\u06cc\u0644\u0646\u06af\u06cc\u0644\u0627\u0646"
    ],
    "name:vie_x_preferred":[
        "Kadingilan"
    ],
    "name:war_x_preferred":[
        "Kadingilan"
    ],
    "qs:gn_country":"PH",
    "qs:gn_fcode":"PPL",
    "qs:gn_pop":7020,
    "qs:name":"Kadingilan",
    "qs:name_adm0":"Philippines",
    "qs:name_adm1":"Northern Mindanao",
    "qs:photos":0,
    "qs:photos_1k":0,
    "qs:photos_9k":0,
    "qs:photos_9r":0,
    "qs:photos_all":0,
    "qs:photos_sr":0,
    "qs:placetype":"Town",
    "qs:pop_sr":"5",
    "qs:woe_adm0":23424934,
    "wd:wordcount":1591,
    "wof:name":"Kadingilan",
    "wof:placetype":"locality",
    "wof:population":7020
},
  "geometry": {"coordinates":[124.90861,7.60111],"type":"Point"}
}