{
  "type": "Feature",
  "properties": {
    "gn:admin1_code":"01",
    "gn:admin2_code":"51",
    "gn:admin3_code":"15531000.0",
    "gn:asciiname":"Acop",
    "gn:country_code":"PH",
    "gn:dem":51,
    "gn:feature_class":"P",
    "gn:feature_code":"PPL",
    "gn:name":"Acop",
    "gn:population":0,
    "gn:timezone":"Asia/Manila",
    "iso:country":"PH",
    "name:fil_x_preferred":[
        "Acop"
    ],
    "wof:name":"Acop",
    "wof:placetype":"locality"
},
  "geometry": {"coordinates":[120.65304999999999,15.87204],"type":"Point"}
}