{
  "type": "Feature",
  "properties": {
    "gn:admin1_code":"03",
    "gn:admin2_code":"63",
    "gn:admin3_code":"36915000.0",
    "gn:asciiname":"San Sotero",
    "gn:country_code":"PH",
    "gn:dem":102,
    "gn:feature_class":"P",
    "gn:feature_code":"PPL",
    "gn:name":"San Sotero",
    "gn:population":0,
    "gn:timezone":"Asia/Manila",
    "iso:country":"PH",
    "name:fil_x_preferred":[
        "San Sotero"
    ],
    "wof:name":"San Sotero",
    "wof:placetype":"locality"
},
  "geometry": {"coordinates":[120.40057,15.53403],"type":"Point"}
}