{
  "type": "Feature",
  "properties": {
    "gn:admin1_code":"07",
    "gn:admin2_code":"11",
    "gn:admin3_code":"71214000.0",
    "gn:asciiname":"Bugtongbood",
    "gn:country_code":"PH",
    "gn:dem":234,
    "gn:feature_class":"P",
    "gn:feature_code":"PPL",
    "gn:name":"Bugtongbood",
    "gn:population":0,
    "gn:timezone":"Asia/Manila",
    "iso:country":"PH",
    "name:fil_x_preferred":[
        "Bugtongbood"
    ],
    "wof:name":"Bugtongbood",
    "wof:placetype":"locality"
},
  "geometry": {"coordinates":[124.0544,9.9337],"type":"Point"}
}