{
  "type": "Feature",
  "properties": {
    "gn:admin1_code":"14",
    "gn:admin2_code":"60",
    "gn:admin3_code":"156612000.0",
    "gn:asciiname":"Tubig Pansol",
    "gn:country_code":"PH",
    "gn:dem":355,
    "gn:feature_class":"P",
    "gn:feature_code":"PPL",
    "gn:name":"Tubig Pansol",
    "gn:population":0,
    "gn:timezone":"Asia/Manila",
    "iso:country":"PH",
    "wof:name":"Tubig Pansol",
    "wof:placetype":"locality"
},
  "geometry": {"coordinates":[120.85611000000002,5.52056],"type":"Point"}
}