{
  "type": "Feature",
  "properties": {
    "gn:country":"PH",
    "gn:fcode":"ADM3",
    "gn:pop":30997,
    "iso:country":"PH",
    "name:fil_x_preferred":[
        "Dagami"
    ],
    "qs:name":"Dagami",
    "qs:photos_9r":0,
    "qs:photos_sr":0,
    "qs:pop_sr":"7",
    "wof:name":"Dagami",
    "wof:placetype":"localadmin",
    "wof:population":30997
},
  "geometry": {"coordinates":[124.84999999999999,11.06667],"type":"Point"}
}