{
  "type": "Feature",
  "properties": {
    "gn:country":"PH",
    "gn:fcode":"PPL",
    "gn:population":3330,
    "iso:country":"PH",
    "name:fil_x_preferred":[
        "Damatulan"
    ],
    "qs:name":"Damatulan",
    "qs:photos_9r":0,
    "qs:photos_sr":0,
    "qs:pop_sr":"4",
    "wof:name":"Damatulan",
    "wof:placetype":"locality",
    "wof:population":3330
},
  "geometry": {"coordinates":[124.48278000000001,7.03889],"type":"Point"}
}