{
  "type": "Feature",
  "properties": {
    "gn:admin1_code":"12",
    "gn:admin2_code":"57",
    "gn:admin3_code":"124713000.0",
    "gn:asciiname":"Datu Onot",
    "gn:cc2":"PH",
    "gn:country_code":"PH",
    "gn:dem":446,
    "gn:feature_class":"P",
    "gn:feature_code":"PPL",
    "gn:name":"Datu Onot",
    "gn:population":0,
    "gn:timezone":"Asia/Manila",
    "iso:country":"PH",
    "name:und_x_variant":[
        "Dato Unot",
        "Datu Onot"
    ],
    "wof:name":"Datu Onot",
    "wof:placetype":"locality"
},
  "geometry": {"coordinates":[125.08333,7.21667],"type":"Point"}
}