{
  "type": "Feature",
  "properties": {
    "gn:gn_country":"PH",
    "gn:gn_fcode":"PPLA3",
    "gn:gn_pop":3429,
    "gn:population":3429,
    "iso:country":"PH",
    "name:bcl_x_preferred":[
        "Lazi"
    ],
    "name:ceb_x_preferred":[
        "Lazi"
    ],
    "name:deu_x_preferred":[
        "Lazi"
    ],
    "name:eng_x_preferred":[
        "Lazi"
    ],
    "name:fil_x_preferred":[
        "Lazi"
    ],
    "name:fra_x_preferred":[
        "Lazi"
    ],
    "name:ilo_x_preferred":[
        "Lazi"
    ],
    "name:ind_x_preferred":[
        "Lazi"
    ],
    "name:ita_x_preferred":[
        "Lazi"
    ],
    "name:nld_x_preferred":[
        "Lazi"
    ],
    "name:pag_x_preferred":[
        "Lazi"
    ],
    "name:pam_x_preferred":[
        "Lazi"
    ],
    "name:sco_x_preferred":[
        "Lazi"
    ],
    "name:swe_x_preferred":[
        "Lazi"
    ],
    "name:tgl_x_preferred":[
        "Lazi"
    ],
    "name:vie_x_preferred":[
        "Lazi"
    ],
    "name:war_x_preferred":[
        "Lazi"
    ],
    "qs_pg:aaroncc":"PH",
    "qs_pg:gn_country":"PH",
    "qs_pg:gn_fcode":"PPLA3",
    "qs_pg:gn_pop":3429,
    "qs_pg:name":"Lazi",
    "qs_pg:photos_9r":0,
    "qs_pg:photos_sr":0,
    "qs_pg:pop_sr":4,
    "qs_pg:qs_pg_placetype":"locality",
    "wof:name":"Lazi",
    "wof:placetype":"locality",
    "wof:population":3429
},
  "geometry": {"coordinates":[123.6356,9.1287],"type":"Point"}
}