{
  "type": "Feature",
  "properties": {
    "gn:country":"PH",
    "gn:fcode":"ADM3",
    "gn:population":1607,
    "iso:country":"PH",
    "name:bcl_x_preferred":[
        "Dumalneg"
    ],
    "name:cat_x_preferred":[
        "Dumalneg"
    ],
    "name:ceb_x_preferred":[
        "Dumalneg"
    ],
    "name:deu_x_preferred":[
        "Dumalneg"
    ],
    "name:eng_x_preferred":[
        "Dumalneg"
    ],
    "name:fil_x_preferred":[
        "Dumalneg"
    ],
    "name:fil_x_variant":[
        "Bayan ng Dumalneg"
    ],
    "name:fra_x_preferred":[
        "Dumalneg"
    ],
    "name:ilo_x_preferred":[
        "Dumalneg"
    ],
    "name:ind_x_preferred":[
        "Dumalneg"
    ],
    "name:ita_x_preferred":[
        "Dumalneg"
    ],
    "name:nld_x_preferred":[
        "Dumalneg"
    ],
    "name:oci_x_preferred":[
        "Dumalneg"
    ],
    "name:pag_x_preferred":[
        "Dumalneg"
    ],
    "name:pam_x_preferred":[
        "Dumalneg"
    ],
    "name:spa_x_preferred":[
        "Dumalneg"
    ],
    "name:swe_x_preferred":[
        "Dumalneg"
    ],
    "name:tgl_x_preferred":[
        "Dumalneg"
    ],
    "name:vie_x_preferred":[
        "Dumalneg"
    ],
    "name:war_x_preferred":[
        "Dumalneg"
    ],
    "qs:name":"Dumalneg",
    "qs:photos_9r":0,
    "qs:photos_sr":0,
    "qs:pop_sr":"3",
    "wd:wordcount":492,
    "wof:name":"Dumalneg",
    "wof:placetype":"localadmin",
    "wof:population":1607
},
  "geometry": {"coordinates":[120.83016000000001,18.47495],"type":"Point"}
}