{
  "type": "Feature",
  "properties": {
    "gn:country":"PH",
    "gn:fcode":"PPL",
    "gn:pop":3404,
    "iso:country":"PH",
    "name:fil_x_preferred":[
        "Palahanan Primero"
    ],
    "name:fil_x_variant":[
        "Palahanan Uno",
        "Palahanan I"
    ],
    "qs:name":"Palahanan Uno",
    "qs:photos_9r":0,
    "qs:photos_sr":0,
    "qs:pop_sr":"4",
    "wof:name":"Palahanan Uno",
    "wof:placetype":"locality",
    "wof:population":3404
},
  "geometry": {"coordinates":[121.35639,13.83113],"type":"Point"}
}