{
  "type": "Feature",
  "properties": {
    "gn:admin1_code":"05",
    "gn:admin2_code":"39",
    "gn:admin3_code":"54112000.0",
    "gn:asciiname":"Pinarian",
    "gn:country_code":"PH",
    "gn:dem":11,
    "gn:feature_class":"P",
    "gn:feature_code":"PPL",
    "gn:name":"Pinarian",
    "gn:population":0,
    "gn:timezone":"Asia/Manila",
    "iso:country":"PH",
    "name:fil_x_preferred":[
        "Pinarian"
    ],
    "wof:name":"Pinarian",
    "wof:placetype":"locality"
},
  "geometry": {"coordinates":[123.6063,12.1089],"type":"Point"}
}