{
  "type": "Feature",
  "properties": {
    "gn:admin1_code":"03",
    "gn:admin2_code":"13",
    "gn:admin3_code":"31408000.0",
    "gn:asciiname":"Pritil",
    "gn:country_code":"PH",
    "gn:dem":11,
    "gn:feature_class":"P",
    "gn:feature_code":"PPL",
    "gn:name":"Pritil",
    "gn:population":0,
    "gn:timezone":"Asia/Manila",
    "iso:country":"PH",
    "name:fil_x_preferred":[
        "Pritil"
    ],
    "wof:name":"Pritil",
    "wof:placetype":"locality"
},
  "geometry": {"coordinates":[120.8669,14.85504],"type":"Point"}
}