{
  "type": "Feature",
  "properties": {
    "gn:gn_country":"PH",
    "gn:gn_fcode":"ADM3",
    "gn:gn_pop":79511,
    "gn:population":79511,
    "iso:country":"PH",
    "name:bcl_x_preferred":[
        "Hinigaran"
    ],
    "name:ceb_x_preferred":[
        "Hinigaran"
    ],
    "name:deu_x_preferred":[
        "Hinigaran"
    ],
    "name:fil_x_preferred":[
        "Hinigaran"
    ],
    "name:fra_x_preferred":[
        "Hinigaran"
    ],
    "name:ilo_x_preferred":[
        "Hinigaran"
    ],
    "name:ind_x_preferred":[
        "Hinigaran"
    ],
    "name:ita_x_preferred":[
        "Hinigaran"
    ],
    "name:nld_x_preferred":[
        "Hinigaran"
    ],
    "name:pag_x_preferred":[
        "Hinigaran"
    ],
    "name:pam_x_preferred":[
        "Hinigaran"
    ],
    "name:tgl_x_preferred":[
        "Hinigaran"
    ],
    "name:war_x_preferred":[
        "Hinigaran"
    ],
    "qs_pg:aaroncc":"PH",
    "qs_pg:gn_country":"PH",
    "qs_pg:gn_fcode":"ADM3",
    "qs_pg:gn_pop":79511,
    "qs_pg:name":"Hinigaran",
    "qs_pg:photos_9r":0,
    "qs_pg:photos_sr":0,
    "qs_pg:pop_sr":8,
    "qs_pg:qs_pg_placetype":"localadmin",
    "wof:name":"Hinigaran",
    "wof:placetype":"localadmin",
    "wof:population":79511
},
  "geometry": {"coordinates":[122.90000000000001,10.26667],"type":"Point"}
}