{
  "type": "Feature",
  "properties": {
    "gn:admin1_code":"02",
    "gn:admin2_code":"31",
    "gn:admin3_code":"23102000.0",
    "gn:asciiname":"Dalenat",
    "gn:country_code":"PH",
    "gn:dem":66,
    "gn:feature_class":"P",
    "gn:feature_code":"PPL",
    "gn:name":"Dalenat",
    "gn:population":0,
    "gn:timezone":"Asia/Manila",
    "iso:country":"PH",
    "name:fil_x_preferred":[
        "Dalenat"
    ],
    "wof:name":"Dalenat",
    "wof:placetype":"locality"
},
  "geometry": {"coordinates":[121.7165,16.734],"type":"Point"}
}