{
  "type": "Feature",
  "properties": {
    "gn:admin1_code":"09",
    "gn:admin2_code":"65",
    "gn:admin3_code":"97219000.0",
    "gn:asciiname":"Balili",
    "gn:country_code":"PH",
    "gn:dem":15,
    "gn:feature_class":"P",
    "gn:feature_code":"PPL",
    "gn:name":"Balili",
    "gn:population":0,
    "gn:timezone":"Asia/Manila",
    "iso:country":"PH",
    "name:fil_x_preferred":[
        "Balili"
    ],
    "wof:name":"Balili",
    "wof:placetype":"locality"
},
  "geometry": {"coordinates":[122.14139,7.66333],"type":"Point"}
}