{
  "type": "Feature",
  "properties": {
    "gn:admin1_code":"02",
    "gn:admin2_code":"48",
    "gn:asciiname":"Lawigan",
    "gn:country_code":"PH",
    "gn:dem":505,
    "gn:feature_class":"P",
    "gn:feature_code":"PPL",
    "gn:name":"Lawigan",
    "gn:population":0,
    "gn:timezone":"Asia/Manila",
    "iso:country":"PH",
    "name:fil_x_preferred":[
        "Lawigan"
    ],
    "name:und_x_variant":[
        "Lawican"
    ],
    "wof:name":"Lawigan",
    "wof:placetype":"locality"
},
  "geometry": {"coordinates":[120.7624,16.2414],"type":"Point"}
}