{
  "type": "Feature",
  "properties": {
    "gn:country":"PH",
    "gn:fcode":"PPLA3",
    "gn:population":2497,
    "iso:country":"PH",
    "name:ara_x_preferred":[
        "\u0628\u0627\u0646\u0627\u0648\u064a"
    ],
    "name:bcl_x_preferred":[
        "Banaue"
    ],
    "name:ceb_x_preferred":[
        "Banaue"
    ],
    "name:ces_x_preferred":[
        "Banaue"
    ],
    "name:deu_x_preferred":[
        "Banaue"
    ],
    "name:eng_x_preferred":[
        "Banaue"
    ],
    "name:epo_x_preferred":[
        "Banaue"
    ],
    "name:fil_x_preferred":[
        "Banawe"
    ],
    "name:fil_x_variant":[
        "Banaue"
    ],
    "name:fra_x_preferred":[
        "Banaue"
    ],
    "name:heb_x_preferred":[
        "\u05d1\u05e0\u05d0\u05d5\u05d5\u05d4"
    ],
    "name:hrv_x_preferred":[
        "Banaue"
    ],
    "name:ilo_x_preferred":[
        "Banaue"
    ],
    "name:ind_x_preferred":[
        "Banaue"
    ],
    "name:ita_x_preferred":[
        "Banaue"
    ],
    "name:jpn_x_preferred":[
        "\u30d0\u30ca\u30a6\u30a7"
    ],
    "name:msa_x_preferred":[
        "Banaue"
    ],
    "name:nld_x_preferred":[
        "Banaue"
    ],
    "name:pag_x_preferred":[
        "Banaue"
    ],
    "name:pam_x_preferred":[
        "Banaue"
    ],
    "name:spa_x_preferred":[
        "Banaue"
    ],
    "name:swe_x_preferred":[
        "Banaue"
    ],
    "name:tgl_x_preferred":[
        "Banaue"
    ],
    "name:vie_x_preferred":[
        "Banaue"
    ],
    "name:war_x_preferred":[
        "Banaue"
    ],
    "name:zho_x_preferred":[
        "\u5df4\u7d0d\u5a01\u93ae"
    ],
    "qs:name":"Banaue",
    "qs:photos_9r":0,
    "qs:photos_sr":0,
    "qs:pop_sr":"4",
    "wd:wordcount":882,
    "wof:name":"Banaue",
    "wof:placetype":"locality",
    "wof:population":2497
},
  "geometry": {"coordinates":[121.06184,16.91356],"type":"Point"}
}