{
  "type": "Feature",
  "properties": {
    "gn:admin1_code":"41",
    "gn:admin2_code":"49",
    "gn:asciiname":"Papagang",
    "gn:country_code":"PH",
    "gn:dem":80,
    "gn:feature_class":"P",
    "gn:feature_code":"PPL",
    "gn:name":"Papagang",
    "gn:population":0,
    "gn:timezone":"Asia/Manila",
    "iso:country":"PH",
    "name:eng_x_preferred":[
        "Papagang"
    ],
    "wof:name":"Papagang",
    "wof:placetype":"locality"
},
  "geometry": {"coordinates":[118.5157,7.04],"type":"Point"}
}