{
  "type": "Feature",
  "properties": {
    "gn:country":"PH",
    "gn:fcode":"PPL",
    "gn:population":3794,
    "iso:country":"PH",
    "name:fil_x_preferred":[
        "Hacienda Santa Rosa"
    ],
    "name:und_x_variant":[
        "Santa Rosa Hacienda"
    ],
    "qs:name":"Hacienda Santa Rosa",
    "qs:photos_9r":0,
    "qs:photos_sr":0,
    "qs:pop_sr":"4",
    "wd:wordcount":557,
    "wof:name":"Hacienda Santa Rosa",
    "wof:placetype":"locality",
    "wof:population":3794
},
  "geometry": {"coordinates":[123.10120000000001,10.57226],"type":"Point"}
}