{
  "type": "Feature",
  "properties": {
    "gn:admin1_code":"41",
    "gn:admin2_code":"40",
    "gn:asciiname":"Bilat",
    "gn:country_code":"PH",
    "gn:dem":27,
    "gn:feature_class":"P",
    "gn:feature_code":"PPL",
    "gn:name":"Bilat",
    "gn:population":0,
    "gn:timezone":"Asia/Manila",
    "iso:country":"PH",
    "name:eng_x_preferred":[
        "Bilat"
    ],
    "wof:name":"Bilat",
    "wof:placetype":"locality"
},
  "geometry": {"coordinates":[121.13281000000001,12.24206],"type":"Point"}
}