{
  "type": "Feature",
  "properties": {
    "gn:admin1_code":"06",
    "gn:admin2_code":"30",
    "gn:admin3_code":"63044000.0",
    "gn:asciiname":"Sinarta",
    "gn:country_code":"PH",
    "gn:dem":239,
    "gn:feature_class":"P",
    "gn:feature_code":"PPL",
    "gn:name":"Sinarta",
    "gn:population":0,
    "gn:timezone":"Asia/Manila",
    "iso:country":"PH",
    "name:fil_x_preferred":[
        "Sinarta"
    ],
    "name:und_x_variant":[
        "Quinasop-an",
        "Quinasup-an"
    ],
    "wof:name":"Sinarta",
    "wof:placetype":"locality"
},
  "geometry": {"coordinates":[122.9961,11.3133],"type":"Point"}
}