{
  "type": "Feature",
  "properties": {
    "gn:admin1_code":"05",
    "gn:admin2_code":"15",
    "gn:admin3_code":"51607000.0",
    "gn:asciiname":"Caringo",
    "gn:country_code":"PH",
    "gn:dem":3,
    "gn:feature_class":"P",
    "gn:feature_code":"PPL",
    "gn:name":"Caringo",
    "gn:population":0,
    "gn:timezone":"Asia/Manila",
    "iso:country":"PH",
    "name:fil_x_preferred":[
        "Caringo"
    ],
    "name:und_x_variant":[
        "Cari\u00f1go Island",
        "Caringao"
    ],
    "wof:name":"Caringo",
    "wof:placetype":"locality"
},
  "geometry": {"coordinates":[123.0962,14.0407],"type":"Point"}
}