{
  "type": "Feature",
  "properties": {
    "gn:admin1_code":"41",
    "gn:admin2_code":"49",
    "gn:admin3_code":"175305000.0",
    "gn:asciiname":"Pongo-Pongo",
    "gn:country_code":"PH",
    "gn:dem":17,
    "gn:feature_class":"P",
    "gn:feature_code":"PPL",
    "gn:name":"Pongo-Pongo",
    "gn:population":0,
    "gn:timezone":"Asia/Manila",
    "iso:country":"PH",
    "name:eng_x_preferred":[
        "Pongo-Pongo"
    ],
    "wof:name":"Pongo-Pongo",
    "wof:placetype":"locality"
},
  "geometry": {"coordinates":[117.20559,8.33504],"type":"Point"}
}