{
  "type": "Feature",
  "properties": {
    "gn:admin1_code":"06",
    "gn:admin2_code":"30",
    "gn:admin3_code":"63023000.0",
    "gn:asciiname":"Quiput",
    "gn:country_code":"PH",
    "gn:dem":199,
    "gn:feature_class":"P",
    "gn:feature_code":"PPL",
    "gn:name":"Quiput",
    "gn:population":0,
    "gn:timezone":"Asia/Manila",
    "iso:country":"PH",
    "name:eng_x_preferred":[
        "Quiput"
    ],
    "wof:name":"Quiput",
    "wof:placetype":"locality"
},
  "geometry": {"coordinates":[122.3879,10.9863],"type":"Point"}
}