{
  "type": "Feature",
  "properties": {
    "gn:admin1_code":"06",
    "gn:admin2_code":"30",
    "gn:admin3_code":"63035000.0",
    "gn:asciiname":"Ingobong",
    "gn:country_code":"PH",
    "gn:dem":102,
    "gn:feature_class":"P",
    "gn:feature_code":"PPL",
    "gn:name":"Ingobong",
    "gn:population":0,
    "gn:timezone":"Asia/Manila",
    "iso:country":"PH",
    "name:fil_x_preferred":[
        "Ingobong"
    ],
    "wof:name":"Ingobong",
    "wof:placetype":"locality"
},
  "geometry": {"coordinates":[122.7594,11.2089],"type":"Point"}
}