{
  "type": "Feature",
  "properties": {
    "gn:admin1_code":"01",
    "gn:admin2_code":"28",
    "gn:admin3_code":"12817000.0",
    "gn:asciiname":"Dilabu",
    "gn:country_code":"PH",
    "gn:dem":36,
    "gn:feature_class":"P",
    "gn:feature_code":"PPL",
    "gn:name":"Dilabu",
    "gn:population":0,
    "gn:timezone":"Asia/Manila",
    "iso:country":"PH",
    "name:fil_x_preferred":[
        "Dilabu"
    ],
    "name:fil_x_variant":[
        "Dilavo",
        "Dilayo"
    ],
    "wof:name":"Dilabu",
    "wof:placetype":"locality"
},
  "geometry": {"coordinates":[120.5932,18.43],"type":"Point"}
}