{
  "type": "Feature",
  "properties": {
    "gn:admin1_code":"10",
    "gn:admin2_code":"42",
    "gn:admin3_code":"104203000.0",
    "gn:asciiname":"Pisaan",
    "gn:country_code":"PH",
    "gn:dem":58,
    "gn:feature_class":"P",
    "gn:feature_code":"PPL",
    "gn:name":"Pisaan",
    "gn:population":0,
    "gn:timezone":"Asia/Manila",
    "iso:country":"PH",
    "name:eng_x_preferred":[
        "Pisaan"
    ],
    "wof:name":"Pisaan",
    "wof:placetype":"locality"
},
  "geometry": {"coordinates":[123.6193,8.0432],"type":"Point"}
}