{
  "type": "Feature",
  "properties": {
    "iso:country":"PH",
    "name:deu_x_preferred":[
        "Panglao"
    ],
    "name:nld_x_preferred":[
        "Panglao"
    ],
    "name:tgl_x_preferred":[
        "Panglao"
    ],
    "qs:gn_country":"PH",
    "qs:gn_fcode":"PPL",
    "qs:gn_pop":0,
    "qs:name":"Panglao",
    "qs:name_adm0":"Philippines",
    "qs:name_adm1":"Central Visayas",
    "qs:photos":4997,
    "qs:photos_1k":1000,
    "qs:photos_9k":22,
    "qs:photos_9r":14,
    "qs:photos_all":4997,
    "qs:photos_sr":24,
    "qs:placetype":"Town",
    "qs:pop_sr":"0",
    "qs:woe_adm0":23424934,
    "wd:wordcount":17,
    "wof:name":"Panglao",
    "wof:placetype":"locality"
},
  "geometry": {"coordinates":[123.91667,10.31667],"type":"Point"}
}