{
  "type": "Feature",
  "properties": {
    "gn:admin1_code":"13",
    "gn:admin2_code":"62",
    "gn:admin3_code":"166805000.0",
    "gn:asciiname":"Cabahang",
    "gn:country_code":"PH",
    "gn:dem":41,
    "gn:feature_class":"P",
    "gn:feature_code":"PPL",
    "gn:name":"Cabahang",
    "gn:population":0,
    "gn:timezone":"Asia/Manila",
    "iso:country":"PH",
    "name:fil_x_preferred":[
        "Cabahang"
    ],
    "wof:name":"Cabahang",
    "wof:placetype":"locality"
},
  "geometry": {"coordinates":[125.89178,9.27365],"type":"Point"}
}