{
  "type": "Feature",
  "properties": {
    "gn:admin1_code":"10",
    "gn:admin2_code":"42",
    "gn:admin3_code":"104209000.0",
    "gn:asciiname":"Villaflor",
    "gn:country_code":"PH",
    "gn:dem":47,
    "gn:feature_class":"P",
    "gn:feature_code":"PPL",
    "gn:name":"Villaflor",
    "gn:population":0,
    "gn:timezone":"Asia/Manila",
    "iso:country":"PH",
    "name:ceb_x_preferred":[
        "Villaflor"
    ],
    "name:deu_x_preferred":[
        "Villaflor"
    ],
    "name:fil_x_preferred":[
        "Villaflor"
    ],
    "name:spa_x_preferred":[
        "Villaflor"
    ],
    "name:swe_x_preferred":[
        "Villaflor"
    ],
    "wof:name":"Villaflor",
    "wof:placetype":"locality"
},
  "geometry": {"coordinates":[123.78919999999999,8.4755],"type":"Point"}
}