{
  "type": "Feature",
  "properties": {
    "gn:country":"PH",
    "gn:fcode":"PPL",
    "gn:pop":2919,
    "iso:country":"PH",
    "name:fil_x_preferred":[
        "Santa Cruz"
    ],
    "qs:name":"Santa Cruz",
    "qs:photos_9r":0,
    "qs:photos_sr":0,
    "qs:pop_sr":"4",
    "wd:wordcount":1120,
    "wof:name":"Santa Cruz",
    "wof:placetype":"locality",
    "wof:population":2919
},
  "geometry": {"coordinates":[123.0821,10.63376],"type":"Point"}
}