{
  "type": "Feature",
  "properties": {
    "gn:country":"PH",
    "gn:fcode":"PPL",
    "gn:pop":2176,
    "iso:country":"PH",
    "name:fil_x_preferred":[
        "San Luis"
    ],
    "qs:name":"San Luis",
    "qs:photos_9r":0,
    "qs:photos_sr":0,
    "qs:pop_sr":"4",
    "wd:wordcount":268,
    "wof:name":"San Luis",
    "wof:placetype":"locality",
    "wof:population":2176
},
  "geometry": {"coordinates":[121.82783999999999,16.96455],"type":"Point"}
}