{
  "type": "Feature",
  "properties": {
    "gn:country":"PH",
    "gn:fcode":"PPL",
    "gn:population":2603,
    "iso:country":"PH",
    "name:fil_x_preferred":[
        "Abis"
    ],
    "name:ita_x_preferred":[
        "Abis"
    ],
    "qs:name":"Abis",
    "qs:photos_9r":0,
    "qs:photos_sr":0,
    "qs:pop_sr":"4",
    "wd:wordcount":86,
    "wof:name":"Abis",
    "wof:placetype":"locality",
    "wof:population":2603
},
  "geometry": {"coordinates":[122.9438,9.7173],"type":"Point"}
}