{
  "type": "Feature",
  "properties": {
    "gn:admin1_code":"02",
    "gn:admin2_code":"31",
    "gn:admin3_code":"23132000.0",
    "gn:asciiname":"Old Centro Segundo",
    "gn:country_code":"PH",
    "gn:dem":87,
    "gn:feature_class":"P",
    "gn:feature_code":"PPL",
    "gn:name":"Old Centro Segundo",
    "gn:population":0,
    "gn:timezone":"Asia/Manila",
    "iso:country":"PH",
    "name:fil_x_preferred":[
        "Old Centro Dos"
    ],
    "wof:name":"Old Centro Segundo",
    "wof:placetype":"locality"
},
  "geometry": {"coordinates":[121.56659000000001,16.88992],"type":"Point"}
}