{
  "type": "Feature",
  "properties": {
    "gn:admin1_code":"02",
    "gn:admin2_code":"31",
    "gn:admin3_code":"23102000.0",
    "gn:asciiname":"Layus",
    "gn:country_code":"PH",
    "gn:dem":59,
    "gn:feature_class":"P",
    "gn:feature_code":"PPL",
    "gn:name":"Layus",
    "gn:population":0,
    "gn:timezone":"Asia/Manila",
    "iso:country":"PH",
    "name:fil_x_preferred":[
        "Layus"
    ],
    "wof:name":"Layus",
    "wof:placetype":"locality"
},
  "geometry": {"coordinates":[121.75,16.75],"type":"Point"}
}