{
  "type": "Feature",
  "properties": {
    "gn:admin1_code":"06",
    "gn:admin2_code":"06",
    "gn:admin3_code":"60617000.0",
    "gn:asciiname":"Santa Ana",
    "gn:country_code":"PH",
    "gn:dem":21,
    "gn:feature_class":"P",
    "gn:feature_code":"PPL",
    "gn:name":"Santa Ana",
    "gn:population":0,
    "gn:timezone":"Asia/Manila",
    "iso:country":"PH",
    "name:fil_x_preferred":[
        "Santa Ana"
    ],
    "wof:name":"Santa Ana",
    "wof:placetype":"locality"
},
  "geometry": {"coordinates":[122.06641,11.24932],"type":"Point"}
}