{
  "type": "Feature",
  "properties": {
    "gn:admin1_code":"07",
    "gn:admin2_code":"69",
    "gn:admin3_code":"76104000.0",
    "gn:asciiname":"Lotloton",
    "gn:country_code":"PH",
    "gn:dem":15,
    "gn:feature_class":"P",
    "gn:feature_code":"PPL",
    "gn:name":"Lotloton",
    "gn:population":0,
    "gn:timezone":"Asia/Manila",
    "iso:country":"PH",
    "name:fil_x_preferred":[
        "Lotloton"
    ],
    "name:und_x_variant":[
        "Lotlotan"
    ],
    "wof:name":"Lotloton",
    "wof:placetype":"locality"
},
  "geometry": {"coordinates":[123.66419999999999,9.2324],"type":"Point"}
}