{
  "type": "Feature",
  "properties": {
    "gn:admin1_code":"41",
    "gn:admin2_code":"38",
    "gn:admin3_code":"174003000.0",
    "gn:asciiname":"Bachao Ibaba",
    "gn:country_code":"PH",
    "gn:dem":11,
    "gn:feature_class":"P",
    "gn:feature_code":"PPL",
    "gn:name":"Bachao Ibaba",
    "gn:population":0,
    "gn:timezone":"Asia/Manila",
    "iso:country":"PH",
    "name:fil_x_preferred":[
        "Bachao Ibaba"
    ],
    "name:fil_x_variant":[
        "Bachao",
        "Bakhaw"
    ],
    "wof:name":"Bachao Ibaba",
    "wof:placetype":"locality"
},
  "geometry": {"coordinates":[121.85769999999999,13.3015],"type":"Point"}
}