{
  "type": "Feature",
  "properties": {
    "gn:admin1_code":"02",
    "gn:admin2_code":"31",
    "gn:admin3_code":"23134000.0",
    "gn:asciiname":"Calibabagan",
    "gn:country_code":"PH",
    "gn:dem":45,
    "gn:feature_class":"P",
    "gn:feature_code":"PPL",
    "gn:name":"Calibabagan",
    "gn:population":0,
    "gn:timezone":"Asia/Manila",
    "iso:country":"PH",
    "name:fil_x_preferred":[
        "Calibabagan"
    ],
    "wof:name":"Calibabagan",
    "wof:placetype":"locality"
},
  "geometry": {"coordinates":[121.69544999999999,17.43262],"type":"Point"}
}