{
  "type": "Feature",
  "properties": {
    "gn:admin1_code":"08",
    "gn:admin2_code":"H9",
    "gn:admin3_code":"87805000.0",
    "gn:asciiname":"Amambahag",
    "gn:country_code":"PH",
    "gn:dem":9,
    "gn:feature_class":"P",
    "gn:feature_code":"PPL",
    "gn:name":"Amambahag",
    "gn:population":0,
    "gn:timezone":"Asia/Manila",
    "iso:country":"PH",
    "name:fil_x_preferred":[
        "Amambahag"
    ],
    "wof:name":"Amambahag",
    "wof:placetype":"locality"
},
  "geometry": {"coordinates":[124.53610999999999,11.66972],"type":"Point"}
}