{
  "type": "Feature",
  "properties": {
    "gn:admin1_code":"06",
    "gn:admin2_code":"H3",
    "gn:admin3_code":"64522000.0",
    "gn:asciiname":"Palaka Pequena",
    "gn:country_code":"PH",
    "gn:dem":6,
    "gn:feature_class":"P",
    "gn:feature_code":"PPL",
    "gn:name":"Palaka Peque\u00f1a",
    "gn:population":0,
    "gn:timezone":"Asia/Manila",
    "iso:country":"PH",
    "name:fil_x_preferred":[
        "Palaka Peque\u00f1a"
    ],
    "name:und_x_variant":[
        "Palaka Peque\u00f1o"
    ],
    "wof:name":"Palaka Pequena",
    "wof:placetype":"locality"
},
  "geometry": {"coordinates":[122.8139,10.4997],"type":"Point"}
}