{
  "type": "Feature",
  "properties": {
    "gn:admin1_code":"13",
    "gn:admin2_code":"I9",
    "gn:admin3_code":"168507000.0",
    "gn:asciiname":"Roxas",
    "gn:country_code":"PH",
    "gn:dem":50,
    "gn:feature_class":"P",
    "gn:feature_code":"PPL",
    "gn:name":"Roxas",
    "gn:population":0,
    "gn:timezone":"Asia/Manila",
    "iso:country":"PH",
    "name:ara_x_preferred":[
        "\u0623\u0631\u062c\u0648\u0627\u0646\u064a"
    ],
    "name:ben_x_preferred":[
        "\u09b0\u09cb\u0995\u09cd\u09b8\u09be\u09b8"
    ],
    "name:ceb_x_preferred":[
        "Roxas"
    ],
    "name:deu_x_preferred":[
        "Roxas"
    ],
    "name:ell_x_preferred":[
        "\u03a1\u03cc\u03be\u03b1\u03c2"
    ],
    "name:fas_x_preferred":[
        "\u0631\u0648\u06a9\u0632\u0627\u0633"
    ],
    "name:fil_x_preferred":[
        "Roxas"
    ],
    "name:fin_x_preferred":[
        "Roxas"
    ],
    "name:fra_x_preferred":[
        "Roxas"
    ],
    "name:heb_x_preferred":[
        "\u05e8\u05d5\u05e7\u05e1\u05e1"
    ],
    "name:hin_x_preferred":[
        "\u0930\u094b\u0915\u094d\u0938\u093e\u0938"
    ],
    "name:ilo_x_preferred":[
        "Roxas"
    ],
    "name:ita_x_preferred":[
        "Roxas"
    ],
    "name:nds_x_preferred":[
        "Roxas"
    ],
    "name:nld_x_preferred":[
        "Roxas"
    ],
    "name:spa_x_preferred":[
        "Roxas"
    ],
    "name:tgl_x_preferred":[
        "Roxas"
    ],
    "name:vie_x_preferred":[
        "Roxas"
    ],
    "name:war_x_preferred":[
        "Roxas"
    ],
    "wof:name":"Roxas",
    "wof:placetype":"locality"
},
  "geometry": {"coordinates":[125.5553,10.3473],"type":"Point"}
}