{
  "type": "Feature",
  "properties": {
    "gn:admin1_code":"13",
    "gn:admin2_code":"I9",
    "gn:admin3_code":"168507000.0",
    "gn:asciiname":"Roxas",
    "gn:country_code":"PH",
    "gn:dem":50,
    "gn:feature_class":"P",
    "gn:feature_code":"PPL",
    "gn:name":"Roxas",
    "gn:population":0,
    "gn:timezone":"Asia/Manila",
    "iso:country":"PH",
    "name:fil_x_preferred":[
        "Roxas"
    ],
    "wof:name":"Roxas",
    "wof:placetype":"locality"
},
  "geometry": {"coordinates":[125.5553,10.3473],"type":"Point"}
}