{
  "type": "Feature",
  "properties": {
    "gn:admin1_code":"07",
    "gn:admin2_code":"11",
    "gn:admin3_code":"71242000.0",
    "gn:asciiname":"Booy",
    "gn:country_code":"PH",
    "gn:dem":13,
    "gn:feature_class":"P",
    "gn:feature_code":"PPL",
    "gn:name":"Booy",
    "gn:population":0,
    "gn:timezone":"Asia/Manila",
    "iso:country":"PH",
    "name:fil_x_preferred":[
        "Booy"
    ],
    "wof:name":"Booy",
    "wof:placetype":"locality"
},
  "geometry": {"coordinates":[123.84999999999999,9.66667],"type":"Point"}
}