{
  "type": "Feature",
  "properties": {
    "gn:admin1_code":"02",
    "gn:admin2_code":"68",
    "gn:admin3_code":"25703000.0",
    "gn:asciiname":"Amogawen",
    "gn:country_code":"PH",
    "gn:dem":206,
    "gn:feature_class":"P",
    "gn:feature_code":"PPL",
    "gn:name":"Amogawen",
    "gn:population":0,
    "gn:timezone":"Asia/Manila",
    "iso:country":"PH",
    "name:fil_x_preferred":[
        "Amogawen"
    ],
    "wof:name":"Amogawen",
    "wof:placetype":"locality"
},
  "geometry": {"coordinates":[121.45650000000001,16.5657],"type":"Point"}
}