{
  "type": "Feature",
  "properties": {
    "gn:admin1_code":"02",
    "gn:admin2_code":"14",
    "gn:admin3_code":"21513000.0",
    "gn:asciiname":"Aguiguican",
    "gn:country_code":"PH",
    "gn:dem":14,
    "gn:feature_class":"P",
    "gn:feature_code":"PPL",
    "gn:name":"Aguiguican",
    "gn:population":0,
    "gn:timezone":"Asia/Manila",
    "iso:country":"PH",
    "name:fil_x_preferred":[
        "Aguiguican"
    ],
    "wof:name":"Aguiguican",
    "wof:placetype":"locality"
},
  "geometry": {"coordinates":[121.67646999999999,18.10871],"type":"Point"}
}