{
  "type": "Feature",
  "properties": {
    "gn:admin1_code":"06",
    "gn:admin2_code":"H3",
    "gn:admin3_code":"64504000.0",
    "gn:asciiname":"Hacienda Daho",
    "gn:country_code":"PH",
    "gn:dem":22,
    "gn:feature_class":"P",
    "gn:feature_code":"PPL",
    "gn:name":"Hacienda Daho",
    "gn:population":0,
    "gn:timezone":"Asia/Manila",
    "iso:country":"PH",
    "name:fil_x_preferred":[
        "Hacienda Daho"
    ],
    "wof:name":"Hacienda Daho",
    "wof:placetype":"locality"
},
  "geometry": {"coordinates":[123.2062,10.9342],"type":"Point"}
}