{
  "type": "Feature",
  "properties": {
    "gn:admin1_code":"06",
    "gn:admin2_code":"18",
    "gn:admin3_code":"61909000.0",
    "gn:asciiname":"Pulutan",
    "gn:country_code":"PH",
    "gn:dem":-5,
    "gn:feature_class":"P",
    "gn:feature_code":"PPL",
    "gn:name":"Pulutan",
    "gn:population":0,
    "gn:timezone":"Asia/Manila",
    "iso:country":"PH",
    "name:fil_x_preferred":[
        "Pulutan"
    ],
    "wof:name":"Pulutan",
    "wof:placetype":"locality"
},
  "geometry": {"coordinates":[122.9075,11.50778],"type":"Point"}
}