{
  "type": "Feature",
  "properties": {
    "gn:admin1_code":"14",
    "gn:admin2_code":"35",
    "gn:admin3_code":"153635000.0",
    "gn:asciiname":"Liangan",
    "gn:country_code":"PH",
    "gn:dem":12,
    "gn:feature_class":"P",
    "gn:feature_code":"PPL",
    "gn:name":"Liangan",
    "gn:population":0,
    "gn:timezone":"Asia/Manila",
    "iso:country":"PH",
    "name:eng_x_preferred":[
        "Liangan"
    ],
    "name:und_x_variant":[
        "Libangan"
    ],
    "wof:name":"Liangan",
    "wof:placetype":"locality"
},
  "geometry": {"coordinates":[123.9375,7.6866],"type":"Point"}
}