{
  "type": "Feature",
  "properties": {
    "gn:admin1_code":"06",
    "gn:admin2_code":"H3",
    "gn:admin3_code":"64509000.0",
    "gn:asciiname":"Hacienda Moro",
    "gn:country_code":"PH",
    "gn:dem":20,
    "gn:feature_class":"P",
    "gn:feature_code":"PPL",
    "gn:name":"Hacienda Moro",
    "gn:population":0,
    "gn:timezone":"Asia/Manila",
    "iso:country":"PH",
    "name:fil_x_preferred":[
        "Hacienda Moro"
    ],
    "wof:name":"Hacienda Moro",
    "wof:placetype":"locality"
},
  "geometry": {"coordinates":[123.5188,10.78684],"type":"Point"}
}