{
  "type": "Feature",
  "properties": {
    "gn:admin1_code":"08",
    "gn:admin2_code":"55",
    "gn:admin3_code":"86024000.0",
    "gn:asciiname":"Manlangi",
    "gn:country_code":"PH",
    "gn:dem":12,
    "gn:feature_class":"P",
    "gn:feature_code":"PPL",
    "gn:name":"Manlangi",
    "gn:population":0,
    "gn:timezone":"Asia/Manila",
    "iso:country":"PH",
    "name:fil_x_preferred":[
        "Manlangi"
    ],
    "wof:name":"Manlangi",
    "wof:placetype":"locality"
},
  "geometry": {"coordinates":[124.23101,12.07825],"type":"Point"}
}