{
  "type": "Feature",
  "properties": {
    "gn:admin1_code":"10",
    "gn:admin2_code":"12",
    "gn:admin3_code":"101316000.0",
    "gn:asciiname":"Pangantocan",
    "gn:cc2":"PH",
    "gn:country_code":"PH",
    "gn:dem":853,
    "gn:feature_class":"P",
    "gn:feature_code":"PPLA3",
    "gn:name":"Pangantocan",
    "gn:population":0,
    "gn:timezone":"Asia/Manila",
    "iso:country":"PH",
    "name:und_x_variant":[
        "Panatukan",
        "Pangantukan",
        "Pangantoean",
        "Pangantocan"
    ],
    "wof:name":"Pangantocan",
    "wof:placetype":"locality"
},
  "geometry": {"coordinates":[124.8125,7.84722],"type":"Point"}
}