{
  "type": "Feature",
  "properties": {
    "gn:country":"PH",
    "gn:fcode":"PPL",
    "gn:population":2221,
    "iso:country":"PH",
    "name:ceb_x_preferred":[
        "Sogod"
    ],
    "name:deu_x_preferred":[
        "Sogod"
    ],
    "name:fil_x_preferred":[
        "Sogod"
    ],
    "name:fra_x_preferred":[
        "Sogod"
    ],
    "name:ita_x_preferred":[
        "Sogod"
    ],
    "name:nld_x_preferred":[
        "Sogod"
    ],
    "name:und_x_variant":[
        "Sugod"
    ],
    "name:war_x_preferred":[
        "Sogod"
    ],
    "qs:name":"Sogod",
    "qs:photos_9r":0,
    "qs:photos_sr":0,
    "qs:pop_sr":"4",
    "wd:wordcount":11,
    "wof:name":"Sogod",
    "wof:placetype":"locality",
    "wof:population":2221
},
  "geometry": {"coordinates":[122.68431,12.38044],"type":"Point"}
}