{
  "type": "Feature",
  "properties": {
    "gn:country":"PH",
    "gn:fcode":"ADM3",
    "gn:population":43725,
    "iso:country":"PH",
    "name:fil_x_preferred":[
        "Alangalang"
    ],
    "qs:name":"Alangalang",
    "qs:photos_9r":0,
    "qs:photos_sr":0,
    "qs:pop_sr":"7",
    "wof:name":"Alangalang",
    "wof:placetype":"localadmin",
    "wof:population":43725
},
  "geometry": {"coordinates":[124.86667,11.21667],"type":"Point"}
}