{
  "type": "Feature",
  "properties": {
    "gn:admin1_code":"03",
    "gn:admin2_code":"63",
    "gn:admin3_code":"36901000.0",
    "gn:asciiname":"Hernando",
    "gn:country_code":"PH",
    "gn:dem":24,
    "gn:feature_class":"P",
    "gn:feature_code":"PPL",
    "gn:name":"Hernando",
    "gn:population":0,
    "gn:timezone":"Asia/Manila",
    "iso:country":"PH",
    "name:ceb_x_preferred":[
        "Hernando"
    ],
    "name:deu_x_preferred":[
        "Hernando"
    ],
    "name:fra_x_preferred":[
        "Hernando"
    ],
    "name:ita_x_preferred":[
        "Hernando"
    ],
    "name:jpn_x_preferred":[
        "\u30a8\u30eb\u30ca\u30f3\u30c9"
    ],
    "name:nld_x_preferred":[
        "Hernando"
    ],
    "name:pol_x_preferred":[
        "Hernando"
    ],
    "name:por_x_preferred":[
        "Hernando"
    ],
    "name:rus_x_preferred":[
        "\u042d\u0440\u043d\u0430\u043d\u0434\u043e"
    ],
    "name:spa_x_preferred":[
        "Hernando"
    ],
    "name:srp_x_preferred":[
        "\u0425\u0435\u0440\u043d\u0430\u043d\u0434\u043e"
    ],
    "name:swe_x_preferred":[
        "Hernando"
    ],
    "name:ukr_x_preferred":[
        "\u0415\u0440\u043d\u0430\u043d\u0434\u043e"
    ],
    "name:vol_x_preferred":[
        "Hernando"
    ],
    "wof:name":"Hernando",
    "wof:placetype":"locality"
},
  "geometry": {"coordinates":[120.6204,15.72388],"type":"Point"}
}