{
  "type": "Feature",
  "properties": {
    "gn:admin1_code":"13",
    "gn:admin2_code":"62",
    "gn:admin3_code":"166807000.0",
    "gn:asciiname":"Manag-as",
    "gn:country_code":"PH",
    "gn:dem":5,
    "gn:feature_class":"P",
    "gn:feature_code":"PPL",
    "gn:name":"Manag-as",
    "gn:population":0,
    "gn:timezone":"Asia/Manila",
    "iso:country":"PH",
    "name:fil_x_preferred":[
        "Manag-as"
    ],
    "wof:name":"Manag-as",
    "wof:placetype":"locality"
},
  "geometry": {"coordinates":[125.92583,9.37806],"type":"Point"}
}