{
  "type": "Feature",
  "properties": {
    "gn:admin1_code":"07",
    "gn:admin2_code":"21",
    "gn:admin3_code":"72250000.0",
    "gn:asciiname":"Candulawan",
    "gn:country_code":"PH",
    "gn:dem":92,
    "gn:feature_class":"P",
    "gn:feature_code":"PPL",
    "gn:name":"Candulawan",
    "gn:population":0,
    "gn:timezone":"Asia/Manila",
    "iso:country":"PH",
    "name:und_x_variant":[
        "Canduawan",
        "Candulawan"
    ],
    "wof:name":"Candulawan",
    "wof:placetype":"locality"
},
  "geometry": {"coordinates":[123.83788,10.28063],"type":"Point"}
}