{
  "type": "Feature",
  "properties": {
    "gn:admin1_code":"15",
    "gn:admin2_code":"01",
    "gn:admin3_code":"140113000.0",
    "gn:asciiname":"Obig",
    "gn:country_code":"PH",
    "gn:dem":199,
    "gn:feature_class":"P",
    "gn:feature_code":"PPL",
    "gn:name":"Obig",
    "gn:population":0,
    "gn:timezone":"Asia/Manila",
    "iso:country":"PH",
    "name:fil_x_preferred":[
        "Obig"
    ],
    "wof:name":"Obig",
    "wof:placetype":"locality"
},
  "geometry": {"coordinates":[120.8168,17.5449],"type":"Point"}
}