{
  "type": "Feature",
  "properties": {
    "gn:admin1_code":"01",
    "gn:admin2_code":"36",
    "gn:admin3_code":"13314000.0",
    "gn:asciiname":"Bangcusay",
    "gn:country_code":"PH",
    "gn:dem":7,
    "gn:feature_class":"P",
    "gn:feature_code":"PPL",
    "gn:name":"Bangcusay",
    "gn:population":0,
    "gn:timezone":"Asia/Manila",
    "iso:country":"PH",
    "name:fil_x_preferred":[
        "Bangcusay"
    ],
    "wof:name":"Bangcusay",
    "wof:placetype":"locality"
},
  "geometry": {"coordinates":[120.31667,16.63332999999999],"type":"Point"}
}