{
  "type": "Feature",
  "properties": {
    "gn:admin1_code":"40",
    "gn:admin2_code":"09",
    "gn:admin3_code":"41007000.0",
    "gn:asciiname":"Mahing",
    "gn:country_code":"PH",
    "gn:dem":202,
    "gn:feature_class":"P",
    "gn:feature_code":"PPL",
    "gn:name":"Mahing",
    "gn:population":0,
    "gn:timezone":"Asia/Manila",
    "iso:country":"PH",
    "name:fil_x_preferred":[
        "Mahing"
    ],
    "wof:name":"Mahing",
    "wof:placetype":"locality"
},
  "geometry": {"coordinates":[120.81502999999999,13.98471],"type":"Point"}
}