{
  "type": "Feature",
  "properties": {
    "gn:admin1_code":"06",
    "gn:admin2_code":"06",
    "gn:admin3_code":"60611000.0",
    "gn:asciiname":"Tuboran",
    "gn:country_code":"PH",
    "gn:dem":13,
    "gn:feature_class":"P",
    "gn:feature_code":"PPL",
    "gn:name":"Tuboran",
    "gn:population":0,
    "gn:timezone":"Asia/Manila",
    "iso:country":"PH",
    "name:fas_x_preferred":[
        "\u062a\u0648\u0628\u0631\u0627\u0646"
    ],
    "name:fil_x_preferred":[
        "Tuboran"
    ],
    "name:urd_x_preferred":[
        "\u062a\u0648\u0628\u0648\u0631\u0627\u0646"
    ],
    "wof:name":"Tuboran",
    "wof:placetype":"locality"
},
  "geometry": {"coordinates":[122.06610000000001,11.7494],"type":"Point"}
}