{
  "type": "Feature",
  "properties": {
    "gn:country":"PH",
    "gn:fcode":"PPLA3",
    "gn:pop":2083,
    "iso:country":"PH",
    "name:bcl_x_preferred":[
        "Bagulin"
    ],
    "name:cat_x_preferred":[
        "Bagulin"
    ],
    "name:dut_x_preferred":[
        "Bagulin"
    ],
    "name:eng_x_preferred":[
        "Bagulin"
    ],
    "name:fre_x_preferred":[
        "Bagulin"
    ],
    "name:ger_x_preferred":[
        "Bagulin"
    ],
    "name:ilo_x_preferred":[
        "Bagulin"
    ],
    "name:ind_x_preferred":[
        "Bagulin"
    ],
    "name:ita_x_preferred":[
        "Bagulin"
    ],
    "name:oci_x_preferred":[
        "Bagulin"
    ],
    "name:pag_x_preferred":[
        "Bagulin"
    ],
    "name:pam_x_preferred":[
        "Bagulin"
    ],
    "name:spa_x_preferred":[
        "Bagulin"
    ],
    "name:swe_x_preferred":[
        "Bagulin"
    ],
    "name:tgl_x_preferred":[
        "Bagulin"
    ],
    "name:unk_x_variant":[
        "Cambaly"
    ],
    "name:vie_x_preferred":[
        "Bagulin"
    ],
    "name:war_x_preferred":[
        "Bagulin"
    ],
    "qs:name":"Bagulin",
    "qs:photos_9r":0,
    "qs:photos_sr":0,
    "qs:pop_sr":"4",
    "wd:wordcount":598,
    "wof:name":"Bagulin",
    "wof:placetype":"locality",
    "wof:population":2083
},
  "geometry": {"coordinates":[120.43944,16.60833],"type":"Point"}
}