{
  "type": "Feature",
  "properties": {
    "gn:admin1_code":"02",
    "gn:admin2_code":"14",
    "gn:admin3_code":"21522000.0",
    "gn:asciiname":"Marzan",
    "gn:country_code":"PH",
    "gn:dem":7,
    "gn:feature_class":"P",
    "gn:feature_code":"PPL",
    "gn:name":"Marzan",
    "gn:population":0,
    "gn:timezone":"Asia/Manila",
    "iso:country":"PH",
    "name:als_x_preferred":[
        "Marzan"
    ],
    "name:bre_x_preferred":[
        "Marzhan"
    ],
    "name:cat_x_preferred":[
        "Marzan"
    ],
    "name:ceb_x_preferred":[
        "Marzan"
    ],
    "name:cym_x_preferred":[
        "Marzhan"
    ],
    "name:deu_x_preferred":[
        "Marzan"
    ],
    "name:eus_x_preferred":[
        "Marzan"
    ],
    "name:fra_x_preferred":[
        "Marzan"
    ],
    "name:glv_x_preferred":[
        "Marzhan"
    ],
    "name:hun_x_preferred":[
        "Marzan"
    ],
    "name:ita_x_preferred":[
        "Marzan"
    ],
    "name:kaz_x_preferred":[
        "\u041c\u0430\u0440\u0437\u0430\u043d"
    ],
    "name:lat_x_preferred":[
        "Marzan"
    ],
    "name:msa_x_preferred":[
        "Marzan"
    ],
    "name:nld_x_preferred":[
        "Marzan"
    ],
    "name:oci_x_preferred":[
        "Marzan"
    ],
    "name:pms_x_preferred":[
        "Marzan"
    ],
    "name:pol_x_preferred":[
        "Marzan"
    ],
    "name:por_x_preferred":[
        "Marzan"
    ],
    "name:ron_x_preferred":[
        "Marzan"
    ],
    "name:slk_x_preferred":[
        "Marzan"
    ],
    "name:spa_x_preferred":[
        "Marzan"
    ],
    "name:swe_x_preferred":[
        "Marzan"
    ],
    "name:ukr_x_preferred":[
        "\u041c\u0430\u0440\u0437\u0430\u043d"
    ],
    "name:uzb_x_preferred":[
        "Marzan"
    ],
    "name:vie_x_preferred":[
        "Marzan"
    ],
    "name:vol_x_preferred":[
        "Marzan"
    ],
    "name:war_x_preferred":[
        "Marzan"
    ],
    "name:zho_x_preferred":[
        "\u9a6c\u5c14\u85cf"
    ],
    "wof:name":"Marzan",
    "wof:placetype":"locality"
},
  "geometry": {"coordinates":[121.24686,18.56034],"type":"Point"}
}