{
  "type": "Feature",
  "properties": {
    "gn:admin1_code":"09",
    "gn:admin2_code":"ZSI",
    "gn:admin3_code":"98309000.0",
    "gn:asciiname":"Sisikan",
    "gn:country_code":"PH",
    "gn:dem":20,
    "gn:feature_class":"P",
    "gn:feature_code":"PPL",
    "gn:name":"Sisikan",
    "gn:population":0,
    "gn:timezone":"Asia/Manila",
    "iso:country":"PH",
    "name:fil_x_preferred":[
        "Sisikan"
    ],
    "wof:name":"Sisikan",
    "wof:placetype":"locality"
},
  "geometry": {"coordinates":[122.71222,7.80917],"type":"Point"}
}