{
  "type": "Feature",
  "properties": {
    "gn:admin1_code":"06",
    "gn:admin2_code":"30",
    "gn:admin3_code":"63021000.0",
    "gn:asciiname":"Bagacayan",
    "gn:country_code":"PH",
    "gn:dem":43,
    "gn:feature_class":"P",
    "gn:feature_code":"PPL",
    "gn:name":"Bagacayan",
    "gn:population":0,
    "gn:timezone":"Asia/Manila",
    "iso:country":"PH",
    "name:fil_x_preferred":[
        "Bagacayan"
    ],
    "wof:name":"Bagacayan",
    "wof:placetype":"locality"
},
  "geometry": {"coordinates":[122.26667,10.71667],"type":"Point"}
}