{
  "type": "Feature",
  "properties": {
    "gn:admin1_code":"14",
    "gn:admin2_code":"60",
    "gn:admin3_code":"156613000.0",
    "gn:asciiname":"Lubuk",
    "gn:country_code":"PH",
    "gn:dem":9,
    "gn:feature_class":"P",
    "gn:feature_code":"PPL",
    "gn:name":"Lubuk",
    "gn:population":0,
    "gn:timezone":"Asia/Manila",
    "iso:country":"PH",
    "name:nld_x_preferred":[
        "Lubuk"
    ],
    "name:und_x_variant":[
        "Luboc"
    ],
    "wof:name":"Lubuk",
    "wof:placetype":"locality"
},
  "geometry": {"coordinates":[121.11387000000001,5.91065],"type":"Point"}
}