{
  "type": "Feature",
  "properties": {
    "gn:admin1_code":"01",
    "gn:admin2_code":"28",
    "gn:admin3_code":"12802000.0",
    "gn:asciiname":"Tepang",
    "gn:country_code":"PH",
    "gn:dem":19,
    "gn:feature_class":"P",
    "gn:feature_code":"PPL",
    "gn:name":"Tepang",
    "gn:population":0,
    "gn:timezone":"Asia/Manila",
    "iso:country":"PH",
    "name:fil_x_preferred":[
        "Tepang"
    ],
    "name:fil_x_variant":[
        "Tippang"
    ],
    "wof:name":"Tepang",
    "wof:placetype":"locality"
},
  "geometry": {"coordinates":[120.6177,18.274],"type":"Point"}
}