{
  "type": "Feature",
  "properties": {
    "gn:admin1_code":"01",
    "gn:admin2_code":"51",
    "gn:admin3_code":"15503000.0",
    "gn:asciiname":"Tawintawin",
    "gn:country_code":"PH",
    "gn:dem":15,
    "gn:feature_class":"P",
    "gn:feature_code":"PPL",
    "gn:name":"Tawintawin",
    "gn:population":0,
    "gn:timezone":"Asia/Manila",
    "iso:country":"PH",
    "name:fil_x_preferred":[
        "Tawin Tawin"
    ],
    "wof:name":"Tawintawin",
    "wof:placetype":"locality"
},
  "geometry": {"coordinates":[119.91638,16.17617000000001],"type":"Point"}
}