{
  "type": "Feature",
  "properties": {
    "gn:admin1_code":"03",
    "gn:admin2_code":"64",
    "gn:admin3_code":"37113000.0",
    "gn:asciiname":"Lucapon South",
    "gn:country_code":"PH",
    "gn:dem":29,
    "gn:feature_class":"P",
    "gn:feature_code":"PPL",
    "gn:name":"Lucapon South",
    "gn:population":0,
    "gn:timezone":"Asia/Manila",
    "iso:country":"PH",
    "name:fil_x_preferred":[
        "Lucapon South"
    ],
    "wof:name":"Lucapon South",
    "wof:placetype":"locality"
},
  "geometry": {"coordinates":[119.94450000000001,15.7273],"type":"Point"}
}