{
  "type": "Feature",
  "properties": {
    "gn:admin1_code":"08",
    "gn:admin2_code":"23",
    "gn:admin3_code":"82606000.0",
    "gn:asciiname":"Lonang",
    "gn:country_code":"PH",
    "gn:dem":9,
    "gn:feature_class":"P",
    "gn:feature_code":"PPL",
    "gn:name":"Lonang",
    "gn:population":0,
    "gn:timezone":"Asia/Manila",
    "iso:country":"PH",
    "name:fil_x_preferred":[
        "Lonang"
    ],
    "wof:name":"Lonang",
    "wof:placetype":"locality"
},
  "geometry": {"coordinates":[125.4928,12.0493],"type":"Point"}
}