{
  "type": "Feature",
  "properties": {
    "gn:admin1_code":"08",
    "gn:admin2_code":"23",
    "gn:admin3_code":"82609000.0",
    "gn:asciiname":"Campayong",
    "gn:cc2":"PH",
    "gn:country_code":"PH",
    "gn:dem":9,
    "gn:feature_class":"P",
    "gn:feature_code":"PPL",
    "gn:name":"Campayong",
    "gn:population":0,
    "gn:timezone":"Asia/Manila",
    "iso:country":"PH",
    "name:und_x_variant":[
        "Camparang",
        "Campayong"
    ],
    "wof:name":"Campayong",
    "wof:placetype":"locality"
},
  "geometry": {"coordinates":[125.73278000000001,11.02417],"type":"Point"}
}