{
  "type": "Feature",
  "properties": {
    "gn:admin1_code":"02",
    "gn:admin2_code":"14",
    "gn:admin3_code":"21507000.0",
    "gn:asciiname":"Fugu",
    "gn:country_code":"PH",
    "gn:dem":13,
    "gn:feature_class":"P",
    "gn:feature_code":"PPL",
    "gn:name":"Fugu",
    "gn:population":0,
    "gn:timezone":"Asia/Manila",
    "iso:country":"PH",
    "name:afr_x_preferred":[
        "Fugu"
    ],
    "name:ast_x_preferred":[
        "Fugu"
    ],
    "name:aze_x_preferred":[
        "Fuqu"
    ],
    "name:bul_x_preferred":[
        "\u0424\u0443\u0433\u0443"
    ],
    "name:cdo_x_preferred":[
        "G\u0103\u0324"
    ],
    "name:deu_x_preferred":[
        "Fugu"
    ],
    "name:fas_x_preferred":[
        "\u0641\u0648\u06af\u0648"
    ],
    "name:fil_x_preferred":[
        "Fugu"
    ],
    "name:fil_x_variant":[
        "Fugo"
    ],
    "name:fra_x_preferred":[
        "T\u00e9traodon"
    ],
    "name:hun_x_preferred":[
        "Fugu"
    ],
    "name:hye_x_preferred":[
        "\u0556\u0578\u0582\u0563\u0578\u0582"
    ],
    "name:ind_x_preferred":[
        "Fugu"
    ],
    "name:ita_x_preferred":[
        "Fugu"
    ],
    "name:jav_x_preferred":[
        "Fugu"
    ],
    "name:kin_x_preferred":[
        "Fugu"
    ],
    "name:lmo_x_preferred":[
        "Fugu"
    ],
    "name:nld_x_preferred":[
        "Fugu"
    ],
    "name:nor_x_preferred":[
        "Fugu"
    ],
    "name:por_x_preferred":[
        "Baiacu"
    ],
    "name:rus_x_preferred":[
        "\u0424\u0443\u0433\u0443"
    ],
    "name:spa_x_preferred":[
        "Fugu"
    ],
    "name:srp_x_preferred":[
        "\u0424\u0443\u0433\u0443"
    ],
    "name:swe_x_preferred":[
        "Fugu"
    ],
    "name:tha_x_preferred":[
        "\u0e1f\u0e39\u0e07\u0e38"
    ],
    "name:tur_x_preferred":[
        "Fugu"
    ],
    "name:ukr_x_preferred":[
        "\u0424\u0443\u0491\u0443"
    ],
    "name:und_x_variant":[
        "Fugo"
    ],
    "name:urd_x_preferred":[
        "\u0641\u0648\u06af\u0648"
    ],
    "name:vie_x_preferred":[
        "Fugu"
    ],
    "wof:name":"Fugu",
    "wof:placetype":"locality"
},
  "geometry": {"coordinates":[121.5277,18.3322],"type":"Point"}
}