{
  "type": "Feature",
  "properties": {
    "gn:admin1_code":"02",
    "gn:admin2_code":"14",
    "gn:admin3_code":"21507000.0",
    "gn:asciiname":"Fugu",
    "gn:country_code":"PH",
    "gn:dem":13,
    "gn:feature_class":"P",
    "gn:feature_code":"PPL",
    "gn:name":"Fugu",
    "gn:population":0,
    "gn:timezone":"Asia/Manila",
    "iso:country":"PH",
    "name:fil_x_preferred":[
        "Fugu"
    ],
    "name:fil_x_variant":[
        "Fugo"
    ],
    "name:und_x_variant":[
        "Fugo"
    ],
    "wof:name":"Fugu",
    "wof:placetype":"locality"
},
  "geometry": {"coordinates":[121.5277,18.3322],"type":"Point"}
}