{
  "type": "Feature",
  "properties": {
    "gn:admin1_code":"03",
    "gn:admin2_code":"64",
    "gn:admin3_code":"37101000.0",
    "gn:asciiname":"Batonlapoc",
    "gn:country_code":"PH",
    "gn:dem":16,
    "gn:feature_class":"P",
    "gn:feature_code":"PPL",
    "gn:name":"Batonlapoc",
    "gn:population":0,
    "gn:timezone":"Asia/Manila",
    "iso:country":"PH",
    "name:fil_x_preferred":[
        "Batonlapoc"
    ],
    "name:und_x_variant":[
        "Balingajili",
        "Batonlapoc"
    ],
    "wof:name":"Batonlapoc",
    "wof:placetype":"locality"
},
  "geometry": {"coordinates":[120.032,15.2906],"type":"Point"}
}