{
  "type": "Feature",
  "properties": {
    "gn:admin1_code":"06",
    "gn:admin2_code":"H3",
    "gn:admin3_code":"64511000.0",
    "gn:asciiname":"Santo Rosario",
    "gn:country_code":"PH",
    "gn:dem":9,
    "gn:feature_class":"P",
    "gn:feature_code":"PPL",
    "gn:name":"Santo Rosario",
    "gn:population":0,
    "gn:timezone":"Asia/Manila",
    "iso:country":"PH",
    "name:ceb_x_preferred":[
        "Santo Rosario"
    ],
    "name:fil_x_preferred":[
        "Santo Rosario"
    ],
    "name:und_x_variant":[
        "Santo Rosario Hacienda"
    ],
    "wof:name":"Santo Rosario",
    "wof:placetype":"locality"
},
  "geometry": {"coordinates":[122.85890000000001,10.2672],"type":"Point"}
}