{
  "type": "Feature",
  "properties": {
    "gn:admin1_code":"41",
    "gn:admin2_code":"41",
    "gn:admin3_code":"175204000.0",
    "gn:asciiname":"Dangkalan Munti",
    "gn:country_code":"PH",
    "gn:dem":20,
    "gn:feature_class":"P",
    "gn:feature_code":"PPL",
    "gn:name":"Dangkalan Munti",
    "gn:population":0,
    "gn:timezone":"Asia/Manila",
    "iso:country":"PH",
    "name:fil_x_preferred":[
        "Dangkalan Munti"
    ],
    "wof:name":"Dangkalan Munti",
    "wof:placetype":"locality"
},
  "geometry": {"coordinates":[121.37681000000001,12.27525],"type":"Point"}
}