{
  "type": "Feature",
  "properties": {
    "gn:admin1_code":"06",
    "gn:admin2_code":"04",
    "gn:admin3_code":"60409000.0",
    "gn:asciiname":"Dalagsa-an",
    "gn:country_code":"PH",
    "gn:dem":404,
    "gn:feature_class":"P",
    "gn:feature_code":"PPL",
    "gn:name":"Dalagsa-an",
    "gn:population":0,
    "gn:timezone":"Asia/Manila",
    "iso:country":"PH",
    "name:fil_x_preferred":[
        "Dalagsa-an"
    ],
    "wof:name":"Dalagsa-an",
    "wof:placetype":"locality"
},
  "geometry": {"coordinates":[122.26730999999999,11.36771],"type":"Point"}
}