{
  "type": "Feature",
  "properties": {
    "gn:admin1_code":"01",
    "gn:admin2_code":"51",
    "gn:admin3_code":"15526000.0",
    "gn:asciiname":"Maasin",
    "gn:country_code":"PH",
    "gn:dem":5,
    "gn:feature_class":"P",
    "gn:feature_code":"PPL",
    "gn:name":"Maasin",
    "gn:population":0,
    "gn:timezone":"Asia/Manila",
    "iso:country":"PH",
    "name:fil_x_preferred":[
        "Maasim"
    ],
    "name:fil_x_variant":[
        "Maasin"
    ],
    "wof:name":"Maasin",
    "wof:placetype":"locality"
},
  "geometry": {"coordinates":[120.37528,16.06413],"type":"Point"}
}