{
  "type": "Feature",
  "properties": {
    "gn:admin1_code":"02",
    "gn:admin2_code":"68",
    "gn:admin3_code":"25704000.0",
    "gn:asciiname":"San Bernabe",
    "gn:country_code":"PH",
    "gn:dem":162,
    "gn:feature_class":"P",
    "gn:feature_code":"PPL",
    "gn:name":"San Bernabe",
    "gn:population":0,
    "gn:timezone":"Asia/Manila",
    "iso:country":"PH",
    "name:fil_x_preferred":[
        "San Bernabe"
    ],
    "wof:name":"San Bernabe",
    "wof:placetype":"locality"
},
  "geometry": {"coordinates":[121.7252,16.3777],"type":"Point"}
}