{
  "type": "Feature",
  "properties": {
    "gn:country":"PH",
    "gn:fcode":"PPL",
    "gn:population":2377,
    "iso:country":"PH",
    "name:fil_x_preferred":[
        "Acustilan"
    ],
    "name:fil_x_variant":[
        "Accusilian",
        "Accusillian"
    ],
    "qs:name":"Accusilian",
    "qs:photos_9r":0,
    "qs:photos_sr":0,
    "qs:pop_sr":"4",
    "wof:name":"Accusilian",
    "wof:placetype":"locality",
    "wof:population":2377
},
  "geometry": {"coordinates":[121.46254,17.74792],"type":"Point"}
}