{
  "type": "Feature",
  "properties": {
    "gn:admin1_code":"07",
    "gn:admin2_code":"69",
    "gn:admin3_code":"76103000.0",
    "gn:asciiname":"Simacolong",
    "gn:country_code":"PH",
    "gn:dem":53,
    "gn:feature_class":"P",
    "gn:feature_code":"PPL",
    "gn:name":"Simacolong",
    "gn:population":0,
    "gn:timezone":"Asia/Manila",
    "iso:country":"PH",
    "name:fil_x_preferred":[
        "Simacolong"
    ],
    "name:und_x_variant":[
        "Simaculong"
    ],
    "wof:name":"Simacolong",
    "wof:placetype":"locality"
},
  "geometry": {"coordinates":[123.65170000000001,9.1306],"type":"Point"}
}