{
  "type": "Feature",
  "properties": {
    "gn:country":"PH",
    "gn:fcode":"PPL",
    "gn:pop":4117,
    "iso:country":"PH",
    "name:ceb_x_preferred":[
        "Talisay"
    ],
    "name:deu_x_preferred":[
        "Talisay"
    ],
    "name:fil_x_preferred":[
        "Talisay"
    ],
    "name:fra_x_preferred":[
        "Talisay"
    ],
    "name:ilo_x_preferred":[
        "Talisay"
    ],
    "name:ita_x_preferred":[
        "Talisay"
    ],
    "name:jpn_x_preferred":[
        "\u30bf\u30ea\u30b5\u30a4"
    ],
    "name:kor_x_preferred":[
        "\ud0c8\ub9ac\uc0ac\uc774"
    ],
    "name:nld_x_preferred":[
        "Talisay"
    ],
    "name:nor_x_preferred":[
        "Talisay"
    ],
    "name:pol_x_preferred":[
        "Talisay"
    ],
    "name:sco_x_preferred":[
        "Talisay"
    ],
    "name:spa_x_preferred":[
        "Tal\u00edsay"
    ],
    "name:swe_x_preferred":[
        "Talisay"
    ],
    "name:tgl_x_preferred":[
        "Talisay"
    ],
    "name:unk_x_variant":[
        "Tailsay"
    ],
    "name:war_x_preferred":[
        "Talisay"
    ],
    "qs:name":"Talisay",
    "qs:photos_9r":0,
    "qs:photos_sr":0,
    "qs:pop_sr":"4",
    "wd:wordcount":30,
    "wof:name":"Talisay",
    "wof:placetype":"locality",
    "wof:population":4117
},
  "geometry": {"coordinates":[124.06189999999999,11.2434],"type":"Point"}
}