{
  "type": "Feature",
  "properties": {
    "gn:country":"PH",
    "gn:fcode":"PPL",
    "gn:pop":4117,
    "iso:country":"PH",
    "name:fil_x_preferred":[
        "Talisay"
    ],
    "name:unk_x_variant":[
        "Tailsay"
    ],
    "qs:name":"Talisay",
    "qs:photos_9r":0,
    "qs:photos_sr":0,
    "qs:pop_sr":"4",
    "wd:wordcount":30,
    "wof:name":"Talisay",
    "wof:placetype":"locality",
    "wof:population":4117
},
  "geometry": {"coordinates":[124.06189999999999,11.2434],"type":"Point"}
}