{
  "type": "Feature",
  "properties": {
    "gn:admin1_code":"06",
    "gn:admin2_code":"04",
    "gn:admin3_code":"60404000.0",
    "gn:asciiname":"Camance",
    "gn:cc2":"PH",
    "gn:country_code":"PH",
    "gn:dem":11,
    "gn:feature_class":"P",
    "gn:feature_code":"PPL",
    "gn:name":"Camance",
    "gn:population":0,
    "gn:timezone":"Asia/Manila",
    "iso:country":"PH",
    "name:und_x_variant":[
        "Kamansi",
        "Camance"
    ],
    "wof:name":"Camance",
    "wof:placetype":"locality"
},
  "geometry": {"coordinates":[122.56167000000001,11.54972],"type":"Point"}
}