{
  "type": "Feature",
  "properties": {
    "gn:admin1_code":"02",
    "gn:admin2_code":"14",
    "gn:admin3_code":"21505000.0",
    "gn:asciiname":"Poso",
    "gn:country_code":"PH",
    "gn:dem":9,
    "gn:feature_class":"P",
    "gn:feature_code":"PPL",
    "gn:name":"Poso",
    "gn:population":0,
    "gn:timezone":"Asia/Manila",
    "iso:country":"PH",
    "name:ara_x_preferred":[
        "\u0628\u0648\u0633\u0648"
    ],
    "name:ben_x_preferred":[
        "\u09aa\u09cb\u09b8\u09cb"
    ],
    "name:ceb_x_preferred":[
        "Poso"
    ],
    "name:deu_x_preferred":[
        "Poso"
    ],
    "name:ell_x_preferred":[
        "\u03a0\u03cc\u03c3\u03bf"
    ],
    "name:fas_x_preferred":[
        "\u067e\u0648\u0632\u0648"
    ],
    "name:fil_x_preferred":[
        "Poso"
    ],
    "name:fra_x_preferred":[
        "Poso"
    ],
    "name:heb_x_preferred":[
        "\u05e4\u05d5\u05e1\u05d5"
    ],
    "name:hin_x_preferred":[
        "\u092a\u094b\u0938\u094b"
    ],
    "name:hun_x_preferred":[
        "Poso"
    ],
    "name:ind_x_preferred":[
        "Poso"
    ],
    "name:ita_x_preferred":[
        "Poso"
    ],
    "name:jpn_x_preferred":[
        "\u30dd\u30fc\u30bd"
    ],
    "name:kor_x_preferred":[
        "\ud3ec\uc18c"
    ],
    "name:mlg_x_preferred":[
        "Poso"
    ],
    "name:nld_x_preferred":[
        "Poso"
    ],
    "name:pol_x_preferred":[
        "Poso"
    ],
    "name:por_x_preferred":[
        "Poso"
    ],
    "name:ron_x_preferred":[
        "Poso"
    ],
    "name:rus_x_preferred":[
        "\u041f\u043e\u0441\u043e"
    ],
    "name:spa_x_preferred":[
        "Poso"
    ],
    "name:tur_x_preferred":[
        "Poso"
    ],
    "name:ukr_x_preferred":[
        "\u041f\u043e\u0441\u043e"
    ],
    "name:urd_x_preferred":[
        "\u067e\u0648\u0633\u0648"
    ],
    "name:vie_x_preferred":[
        "Poso"
    ],
    "name:zho_cn_x_preferred":[
        "\u6ce2\u7d22"
    ],
    "name:zho_tw_x_preferred":[
        "\u6ce2\u7d22"
    ],
    "wof:name":"Poso",
    "wof:placetype":"locality"
},
  "geometry": {"coordinates":[121.28333000000001,18.88333],"type":"Point"}
}