{
  "type": "Feature",
  "properties": {
    "gn:admin1_code":"02",
    "gn:admin2_code":"14",
    "gn:admin3_code":"21505000.0",
    "gn:asciiname":"Poso",
    "gn:country_code":"PH",
    "gn:dem":9,
    "gn:feature_class":"P",
    "gn:feature_code":"PPL",
    "gn:name":"Poso",
    "gn:population":0,
    "gn:timezone":"Asia/Manila",
    "iso:country":"PH",
    "name:fil_x_preferred":[
        "Poso"
    ],
    "wof:name":"Poso",
    "wof:placetype":"locality"
},
  "geometry": {"coordinates":[121.28333000000001,18.88333],"type":"Point"}
}