{
  "type": "Feature",
  "properties": {
    "gn:admin1_code":"05",
    "gn:admin2_code":"39",
    "gn:admin3_code":"54121000.0",
    "gn:asciiname":"Dungon",
    "gn:country_code":"PH",
    "gn:dem":63,
    "gn:feature_class":"P",
    "gn:feature_code":"PPL",
    "gn:name":"Dungon",
    "gn:population":0,
    "gn:timezone":"Asia/Manila",
    "iso:country":"PH",
    "name:fil_x_preferred":[
        "Dungon"
    ],
    "wof:name":"Dungon",
    "wof:placetype":"locality"
},
  "geometry": {"coordinates":[123.8125,12.1974],"type":"Point"}
}