{
  "type": "Feature",
  "properties": {
    "gn:admin1_code":"03",
    "gn:admin2_code":"13",
    "gn:admin3_code":"31410000.0",
    "gn:asciiname":"Atlag",
    "gn:country_code":"PH",
    "gn:dem":5,
    "gn:feature_class":"P",
    "gn:feature_code":"PPL",
    "gn:name":"Atlag",
    "gn:population":0,
    "gn:timezone":"Asia/Manila",
    "iso:country":"PH",
    "name:fil_x_preferred":[
        "Atlag"
    ],
    "wof:name":"Atlag",
    "wof:placetype":"locality"
},
  "geometry": {"coordinates":[120.81836,14.82984],"type":"Point"}
}