{
  "type": "Feature",
  "properties": {
    "gn:admin1_code":"41",
    "gn:admin2_code":"54",
    "gn:admin3_code":"175903000.0",
    "gn:asciiname":"Alibagon",
    "gn:country_code":"PH",
    "gn:dem":170,
    "gn:feature_class":"P",
    "gn:feature_code":"PPL",
    "gn:name":"Alibagon",
    "gn:population":0,
    "gn:timezone":"Asia/Manila",
    "iso:country":"PH",
    "name:fil_x_preferred":[
        "Alibagon"
    ],
    "name:und_x_variant":[
        "Alibangon"
    ],
    "wof:name":"Alibagon",
    "wof:placetype":"locality"
},
  "geometry": {"coordinates":[122.67591000000002,12.35363],"type":"Point"}
}