{
  "type": "Feature",
  "properties": {
    "gn:admin1_code":"14",
    "gn:admin2_code":"72",
    "gn:admin3_code":"157007000.0",
    "gn:asciiname":"Tandubas",
    "gn:country_code":"PH",
    "gn:dem":2,
    "gn:feature_class":"P",
    "gn:feature_code":"PPL",
    "gn:name":"Tandubas",
    "gn:population":0,
    "gn:timezone":"Asia/Manila",
    "iso:country":"PH",
    "name:eng_x_preferred":[
        "Tandubas"
    ],
    "wof:name":"Tandubas",
    "wof:placetype":"locality"
},
  "geometry": {"coordinates":[120.1396,5.1977],"type":"Point"}
}