{
  "type": "Feature",
  "properties": {
    "gn:admin1_code":"15",
    "gn:admin2_code":"27",
    "gn:admin3_code":"142703000.0",
    "gn:asciiname":"Longa",
    "gn:country_code":"PH",
    "gn:dem":811,
    "gn:feature_class":"P",
    "gn:feature_code":"PPL",
    "gn:name":"Longa",
    "gn:population":0,
    "gn:timezone":"Asia/Manila",
    "iso:country":"PH",
    "name:ceb_x_preferred":[
        "Longa"
    ],
    "name:deu_x_preferred":[
        "Longa"
    ],
    "name:ell_x_preferred":[
        "\u039b\u03bf\u03b3\u03b3\u03ac"
    ],
    "name:fil_x_preferred":[
        "Lonsa"
    ],
    "name:fil_x_variant":[
        "Longa"
    ],
    "name:fra_x_preferred":[
        "Longa"
    ],
    "name:ind_x_preferred":[
        "Longa"
    ],
    "name:ita_x_preferred":[
        "Longa"
    ],
    "name:nld_x_preferred":[
        "Longa"
    ],
    "name:nno_x_preferred":[
        "Longa"
    ],
    "name:por_x_preferred":[
        "Longa"
    ],
    "name:swe_x_preferred":[
        "Longa"
    ],
    "wof:name":"Longa",
    "wof:placetype":"locality"
},
  "geometry": {"coordinates":[121.08104,16.77957],"type":"Point"}
}