{
  "type": "Feature",
  "properties": {
    "gn:admin1_code":"06",
    "gn:admin2_code":"H3",
    "gn:admin3_code":"64525000.0",
    "gn:asciiname":"Bagunaua",
    "gn:country_code":"PH",
    "gn:dem":5,
    "gn:feature_class":"P",
    "gn:feature_code":"PPL",
    "gn:name":"Bagunaua",
    "gn:population":0,
    "gn:timezone":"Asia/Manila",
    "iso:country":"PH",
    "name:fil_x_preferred":[
        "Bagunaua"
    ],
    "name:und_x_variant":[
        "Bagunana"
    ],
    "wof:name":"Bagunaua",
    "wof:placetype":"locality"
},
  "geometry": {"coordinates":[122.8776,10.4169],"type":"Point"}
}