{
  "type": "Feature",
  "properties": {
    "gn:admin1_code":"08",
    "gn:admin2_code":"67",
    "gn:admin3_code":"84811000.0",
    "gn:asciiname":"Busay",
    "gn:country_code":"PH",
    "gn:dem":32,
    "gn:feature_class":"P",
    "gn:feature_code":"PPL",
    "gn:name":"Busay",
    "gn:population":0,
    "gn:timezone":"Asia/Manila",
    "iso:country":"PH",
    "name:fil_x_preferred":[
        "Busay"
    ],
    "wof:name":"Busay",
    "wof:placetype":"locality"
},
  "geometry": {"coordinates":[124.36667,12.51667],"type":"Point"}
}