{
  "type": "Feature",
  "properties": {
    "gn:admin1_code":"02",
    "gn:admin2_code":"14",
    "gn:admin3_code":"21501000.0",
    "gn:asciiname":"Gubu",
    "gn:country_code":"PH",
    "gn:dem":9,
    "gn:feature_class":"P",
    "gn:feature_code":"PPL",
    "gn:name":"Gubu",
    "gn:population":0,
    "gn:timezone":"Asia/Manila",
    "iso:country":"PH",
    "name:fil_x_preferred":[
        "Gubu"
    ],
    "wof:name":"Gubu",
    "wof:placetype":"locality"
},
  "geometry": {"coordinates":[121.44347999999999,18.35378],"type":"Point"}
}