{
  "type": "Feature",
  "properties": {
    "gn:admin1_code":"02",
    "gn:admin2_code":"31",
    "gn:admin3_code":"23127000.0",
    "gn:asciiname":"Rangay",
    "gn:country_code":"PH",
    "gn:dem":141,
    "gn:feature_class":"P",
    "gn:feature_code":"PPL",
    "gn:name":"Rangay",
    "gn:population":0,
    "gn:timezone":"Asia/Manila",
    "iso:country":"PH",
    "name:fil_x_preferred":[
        "Rangay"
    ],
    "wof:name":"Rangay",
    "wof:placetype":"locality"
},
  "geometry": {"coordinates":[121.7715,16.4555],"type":"Point"}
}