{
  "type": "Feature",
  "properties": {
    "gn:admin1_code":"07",
    "gn:admin2_code":"21",
    "gn:admin3_code":"72241000.0",
    "gn:asciiname":"Poblacion North",
    "gn:country_code":"PH",
    "gn:dem":73,
    "gn:feature_class":"P",
    "gn:feature_code":"PPL",
    "gn:name":"Poblacion North",
    "gn:population":0,
    "gn:timezone":"Asia/Manila",
    "iso:country":"PH",
    "name:eng_x_preferred":[
        "Poblacion North"
    ],
    "wof:name":"Poblacion North",
    "wof:placetype":"locality"
},
  "geometry": {"coordinates":[123.7043,10.16978],"type":"Point"}
}