{
  "type": "Feature",
  "properties": {
    "gn:admin1_code":"08",
    "gn:admin2_code":"67",
    "gn:admin3_code":"84824000.0",
    "gn:asciiname":"Tinitdan",
    "gn:country_code":"PH",
    "gn:dem":44,
    "gn:feature_class":"P",
    "gn:feature_code":"PPL",
    "gn:name":"Tinitdan",
    "gn:population":0,
    "gn:timezone":"Asia/Manila",
    "iso:country":"PH",
    "name:fil_x_preferred":[
        "Tinitdan"
    ],
    "wof:name":"Tinitdan",
    "wof:placetype":"locality"
},
  "geometry": {"coordinates":[124.66667,12.31667],"type":"Point"}
}