{
  "type": "Feature",
  "properties": {
    "gn:country":"PH",
    "gn:fcode":"PPL",
    "gn:population":3002,
    "iso:country":"PH",
    "name:fil_x_preferred":[
        "Cabodiongan"
    ],
    "name:und_x_variant":[
        "Cabadiangan"
    ],
    "qs_pg:aaroncc":"PH",
    "qs_pg:gn_country":"PH",
    "qs_pg:gn_fcode":"PPL",
    "qs_pg:gn_pop":3002,
    "qs_pg:name":"Cabodiongan",
    "qs_pg:photos_9r":0,
    "qs_pg:photos_sr":0,
    "qs_pg:pop_sr":4,
    "qs_pg:qs_pg_placetype":"locality",
    "wof:name":"Cabodiongan",
    "wof:placetype":"locality",
    "wof:population":3002
},
  "geometry": {"coordinates":[125.04559999999999,12.6643],"type":"Point"}
}