{
  "type": "Feature",
  "properties": {
    "gn:admin1_code":"15",
    "gn:admin2_code":"01",
    "gn:admin3_code":"140101000.0",
    "gn:asciiname":"Biog",
    "gn:country_code":"PH",
    "gn:dem":257,
    "gn:feature_class":"P",
    "gn:feature_code":"PPL",
    "gn:name":"Biog",
    "gn:population":0,
    "gn:timezone":"Asia/Manila",
    "iso:country":"PH",
    "name:fil_x_preferred":[
        "Biog"
    ],
    "wof:name":"Biog",
    "wof:placetype":"locality"
},
  "geometry": {"coordinates":[120.6422,17.4931],"type":"Point"}
}