{
  "type": "Feature",
  "properties": {
    "gn:admin1_code":"07",
    "gn:admin2_code":"21",
    "gn:admin3_code":"72240000.0",
    "gn:asciiname":"Culasi",
    "gn:country_code":"PH",
    "gn:dem":25,
    "gn:feature_class":"P",
    "gn:feature_code":"PPL",
    "gn:name":"Culasi",
    "gn:population":0,
    "gn:timezone":"Asia/Manila",
    "iso:country":"PH",
    "name:fil_x_preferred":[
        "Culasi"
    ],
    "name:und_x_variant":[
        "Culase"
    ],
    "wof:name":"Culasi",
    "wof:placetype":"locality"
},
  "geometry": {"coordinates":[123.2984,9.472],"type":"Point"}
}