{
  "type": "Feature",
  "properties": {
    "gn:admin1_code":"07",
    "gn:admin2_code":"21",
    "gn:admin3_code":"72240000.0",
    "gn:asciiname":"Culasi",
    "gn:country_code":"PH",
    "gn:dem":25,
    "gn:feature_class":"P",
    "gn:feature_code":"PPL",
    "gn:name":"Culasi",
    "gn:population":0,
    "gn:timezone":"Asia/Manila",
    "iso:country":"PH",
    "name:bcl_x_preferred":[
        "Culasi"
    ],
    "name:ceb_x_preferred":[
        "Culasi"
    ],
    "name:deu_x_preferred":[
        "Culasi"
    ],
    "name:fil_x_preferred":[
        "Culasi"
    ],
    "name:fra_x_preferred":[
        "Culasi"
    ],
    "name:ilo_x_preferred":[
        "Culasi"
    ],
    "name:ind_x_preferred":[
        "Culasi"
    ],
    "name:ita_x_preferred":[
        "Culasi"
    ],
    "name:nld_x_preferred":[
        "Culasi"
    ],
    "name:pag_x_preferred":[
        "Culasi"
    ],
    "name:pam_x_preferred":[
        "Culasi"
    ],
    "name:swe_x_preferred":[
        "Culasi"
    ],
    "name:tgl_x_preferred":[
        "Culasi"
    ],
    "name:und_x_variant":[
        "Culase"
    ],
    "name:urd_x_preferred":[
        "\u06a9\u0648\u0644\u0627\u0633\u06cc"
    ],
    "name:vie_x_preferred":[
        "Culasi"
    ],
    "name:war_x_preferred":[
        "Culasi"
    ],
    "wof:name":"Culasi",
    "wof:placetype":"locality"
},
  "geometry": {"coordinates":[123.2984,9.472],"type":"Point"}
}