{
  "type": "Feature",
  "properties": {
    "gn:admin1_code":"01",
    "gn:admin2_code":"36",
    "gn:admin3_code":"13311000.0",
    "gn:asciiname":"Nagsidurisan",
    "gn:country_code":"PH",
    "gn:dem":25,
    "gn:feature_class":"P",
    "gn:feature_code":"PPL",
    "gn:name":"Nagsidurisan",
    "gn:population":0,
    "gn:timezone":"Asia/Manila",
    "iso:country":"PH",
    "name:fil_x_preferred":[
        "Nagsidurisan"
    ],
    "wof:name":"Nagsidurisan",
    "wof:placetype":"locality"
},
  "geometry": {"coordinates":[120.40000000000001,16.53333],"type":"Point"}
}