{
  "type": "Feature",
  "properties": {
    "gn:admin1_code":"14",
    "gn:admin2_code":"56",
    "gn:admin3_code":"153825000.0",
    "gn:asciiname":"Balili",
    "gn:country_code":"PH",
    "gn:dem":36,
    "gn:feature_class":"P",
    "gn:feature_code":"PPL",
    "gn:name":"Balili",
    "gn:population":0,
    "gn:timezone":"Asia/Manila",
    "iso:country":"PH",
    "name:fil_x_preferred":[
        "Balili"
    ],
    "wof:name":"Balili",
    "wof:placetype":"locality"
},
  "geometry": {"coordinates":[124.33556000000002,6.94667],"type":"Point"}
}