{
  "type": "Feature",
  "properties": {
    "gn:country":"PH",
    "gn:fcode":"ADM3",
    "gn:pop":25204,
    "iso:country":"PH",
    "name:eng_x_preferred":[
        "Municipality of Aloran"
    ],
    "name:unk_x_variant":[
        "Aloran"
    ],
    "qs:name":"Municipality of Aloran",
    "qs:photos_9r":0,
    "qs:photos_sr":0,
    "qs:pop_sr":"7",
    "wd:wordcount":1680,
    "wof:name":"Municipality of Aloran",
    "wof:placetype":"localadmin",
    "wof:population":25204
},
  "geometry": {"coordinates":[123.7623,8.3931],"type":"Point"}
}