{
  "type": "Feature",
  "properties": {
    "gn:admin1_code":"07",
    "gn:admin2_code":"69",
    "gn:admin3_code":"76105000.0",
    "gn:asciiname":"Candura",
    "gn:country_code":"PH",
    "gn:dem":147,
    "gn:feature_class":"P",
    "gn:feature_code":"PPL",
    "gn:name":"Candura",
    "gn:population":0,
    "gn:timezone":"Asia/Manila",
    "iso:country":"PH",
    "name:fil_x_preferred":[
        "Candura"
    ],
    "wof:name":"Candura",
    "wof:placetype":"locality"
},
  "geometry": {"coordinates":[123.51416999999999,9.16722],"type":"Point"}
}