{
  "type": "Feature",
  "properties": {
    "gn:country":"PH",
    "gn:fcode":"PPL",
    "gn:pop":2610,
    "iso:country":"PH",
    "name:fil_x_preferred":[
        "Tomado"
    ],
    "qs:name":"Tomado",
    "qs:photos_9r":0,
    "qs:photos_sr":0,
    "qs:pop_sr":"4",
    "wof:name":"Tomado",
    "wof:placetype":"locality",
    "wof:population":2610
},
  "geometry": {"coordinates":[124.60805999999999,7.1925],"type":"Point"}
}