{
  "type": "Feature",
  "properties": {
    "gn:admin1_code":"09",
    "gn:admin2_code":"66",
    "gn:admin3_code":"97332000.0",
    "gn:asciiname":"Palupalo",
    "gn:country_code":"PH",
    "gn:dem":32,
    "gn:feature_class":"P",
    "gn:feature_code":"PPL",
    "gn:name":"Palupalo",
    "gn:population":0,
    "gn:timezone":"Asia/Manila",
    "iso:country":"PH",
    "wof:name":"Palupalo",
    "wof:placetype":"locality"
},
  "geometry": {"coordinates":[122.28556,7.28417],"type":"Point"}
}