{
  "type": "Feature",
  "properties": {
    "gn:admin1_code":"08",
    "gn:admin2_code":"37",
    "gn:admin3_code":"83729000.0",
    "gn:asciiname":"Wagui",
    "gn:country_code":"PH",
    "gn:dem":24,
    "gn:feature_class":"P",
    "gn:feature_code":"PPL",
    "gn:name":"Wagui",
    "gn:population":0,
    "gn:timezone":"Asia/Manila",
    "iso:country":"PH",
    "name:eng_x_preferred":[
        "Wagui"
    ],
    "name:und_x_variant":[
        "Wague"
    ],
    "wof:name":"Wagui",
    "wof:placetype":"locality"
},
  "geometry": {"coordinates":[124.48820000000001,11.2908],"type":"Point"}
}