{
  "type": "Feature",
  "properties": {
    "gn:admin1_code":"07",
    "gn:admin2_code":"46",
    "gn:admin3_code":"74625000.0",
    "gn:asciiname":"Jamaoas",
    "gn:country_code":"PH",
    "gn:dem":468,
    "gn:feature_class":"P",
    "gn:feature_code":"PPL",
    "gn:name":"Jamaoas",
    "gn:population":0,
    "gn:timezone":"Asia/Manila",
    "iso:country":"PH",
    "name:fil_x_preferred":[
        "Jamaoas"
    ],
    "wof:name":"Jamaoas",
    "wof:placetype":"locality"
},
  "geometry": {"coordinates":[123.1853,9.197],"type":"Point"}
}