{
  "type": "Feature",
  "properties": {
    "iso:country":"PH",
    "name:bcl_x_preferred":[
        "Mexico"
    ],
    "name:cat_x_preferred":[
        "Mexico"
    ],
    "name:cbk_zam_x_preferred":[
        "Mexico"
    ],
    "name:ceb_x_preferred":[
        "Mexico"
    ],
    "name:deu_x_preferred":[
        "Mexico"
    ],
    "name:eng_x_preferred":[
        "Mexico"
    ],
    "name:fil_x_preferred":[
        "Mexico"
    ],
    "name:fra_x_preferred":[
        "Mexico"
    ],
    "name:ilo_x_preferred":[
        "Mexico"
    ],
    "name:ind_x_preferred":[
        "Mexico"
    ],
    "name:ita_x_preferred":[
        "Mexico"
    ],
    "name:nld_x_preferred":[
        "Mexico"
    ],
    "name:nob_x_preferred":[
        "Mexico"
    ],
    "name:oci_x_preferred":[
        "Mexico"
    ],
    "name:pag_x_preferred":[
        "Mexico"
    ],
    "name:pam_x_preferred":[
        "Mexico"
    ],
    "name:spa_x_preferred":[
        "M\u00e9xico"
    ],
    "name:swe_x_preferred":[
        "Mexico"
    ],
    "name:tgl_x_preferred":[
        "Mexico"
    ],
    "name:vie_x_preferred":[
        "Mexico"
    ],
    "name:war_x_preferred":[
        "Mexico"
    ],
    "qs:gn_country":"PH",
    "qs:gn_fcode":"PPLA3",
    "qs:gn_pop":43694,
    "qs:name":"Mexico",
    "qs:name_adm0":"Philippines",
    "qs:name_adm1":"Central Luzon",
    "qs:photos":186,
    "qs:photos_1k":38,
    "qs:photos_9k":1,
    "qs:photos_9r":4,
    "qs:photos_all":186,
    "qs:photos_sr":4,
    "qs:placetype":"Town",
    "qs:pop_sr":"7",
    "qs:woe_adm0":23424934,
    "wd:wordcount":2172,
    "wof:name":"Mexico",
    "wof:placetype":"locality",
    "wof:population":43694
},
  "geometry": {"coordinates":[120.71980000000001,15.0646],"type":"Point"}
}