{
  "type": "Feature",
  "properties": {
    "gn:admin1_code":"15",
    "gn:admin2_code":"H6",
    "gn:admin3_code":"148106000.0",
    "gn:asciiname":"Aripip",
    "gn:country_code":"PH",
    "gn:dem":134,
    "gn:feature_class":"P",
    "gn:feature_code":"PPL",
    "gn:name":"Aripip",
    "gn:population":0,
    "gn:timezone":"Asia/Manila",
    "iso:country":"PH",
    "name:fil_x_preferred":[
        "Aripip"
    ],
    "wof:name":"Aripip",
    "wof:placetype":"locality"
},
  "geometry": {"coordinates":[121.3206,18.0894],"type":"Point"}
}