{
  "type": "Feature",
  "properties": {
    "gn:country":"PH",
    "gn:fcode":"PPL",
    "gn:pop":4473,
    "iso:country":"PH",
    "qs:name":"Talipan",
    "qs:photos_9r":0,
    "qs:photos_sr":0,
    "qs:pop_sr":"4",
    "wof:name":"Talipan",
    "wof:placetype":"locality",
    "wof:population":4473
},
  "geometry": {"coordinates":[121.68333,13.93333],"type":"Point"}
}