{
  "type": "Feature",
  "properties": {
    "gn:admin1_code":"41",
    "gn:admin2_code":"54",
    "gn:admin3_code":"175908000.0",
    "gn:asciiname":"Agnoknok",
    "gn:country_code":"PH",
    "gn:dem":11,
    "gn:feature_class":"P",
    "gn:feature_code":"PPL",
    "gn:name":"Agnoknok",
    "gn:population":0,
    "gn:timezone":"Asia/Manila",
    "iso:country":"PH",
    "name:fil_x_preferred":[
        "Agnoknok"
    ],
    "name:und_x_variant":[
        "Agnonoc"
    ],
    "wof:name":"Agnoknok",
    "wof:placetype":"locality"
},
  "geometry": {"coordinates":[122.55931,12.49493],"type":"Point"}
}