{
  "type": "Feature",
  "properties": {
    "gn:admin1_code":"40",
    "gn:admin2_code":"09",
    "gn:admin3_code":"41034000.0",
    "gn:asciiname":"Bayudbud",
    "gn:country_code":"PH",
    "gn:dem":115,
    "gn:feature_class":"P",
    "gn:feature_code":"PPL",
    "gn:name":"Bayudbud",
    "gn:population":0,
    "gn:timezone":"Asia/Manila",
    "iso:country":"PH",
    "name:fil_x_preferred":[
        "Bayudbud"
    ],
    "name:fil_x_variant":[
        "Bayubud",
        "Bayabud"
    ],
    "wof:name":"Bayudbud",
    "wof:placetype":"locality"
},
  "geometry": {"coordinates":[120.73690000000001,14.0554],"type":"Point"}
}