{
  "type": "Feature",
  "properties": {
    "gn:admin1_code":"03",
    "gn:admin2_code":"64",
    "gn:admin3_code":"37108000.0",
    "gn:asciiname":"Loclocbalete",
    "gn:country_code":"PH",
    "gn:dem":10,
    "gn:feature_class":"P",
    "gn:feature_code":"PPL",
    "gn:name":"Loclocbalete",
    "gn:population":0,
    "gn:timezone":"Asia/Manila",
    "iso:country":"PH",
    "name:fil_x_preferred":[
        "Loclocbalete"
    ],
    "wof:name":"Loclocbalete",
    "wof:placetype":"locality"
},
  "geometry": {"coordinates":[119.91667,15.39889],"type":"Point"}
}