{
  "type": "Feature",
  "properties": {
    "gn:admin1_code":"06",
    "gn:admin2_code":"30",
    "gn:admin3_code":"63046000.0",
    "gn:asciiname":"Ambarihon",
    "gn:country_code":"PH",
    "gn:dem":105,
    "gn:feature_class":"P",
    "gn:feature_code":"PPL",
    "gn:name":"Ambarihon",
    "gn:population":0,
    "gn:timezone":"Asia/Manila",
    "iso:country":"PH",
    "name:fil_x_preferred":[
        "Ambarihon"
    ],
    "wof:name":"Ambarihon",
    "wof:placetype":"locality"
},
  "geometry": {"coordinates":[122.31667,10.75],"type":"Point"}
}