{
  "type": "Feature",
  "properties": {
    "gn:admin1_code":"10",
    "gn:admin2_code":"42",
    "gn:admin3_code":"104202000.0",
    "gn:asciiname":"Del Pilar",
    "gn:country_code":"PH",
    "gn:dem":67,
    "gn:feature_class":"P",
    "gn:feature_code":"PPL",
    "gn:name":"Del Pilar",
    "gn:population":0,
    "gn:timezone":"Asia/Manila",
    "iso:country":"PH",
    "name:eng_x_preferred":[
        "Del Pilar"
    ],
    "wof:name":"Del Pilar",
    "wof:placetype":"locality"
},
  "geometry": {"coordinates":[123.60890000000001,8.5761],"type":"Point"}
}