{
  "type": "Feature",
  "properties": {
    "gn:admin1_code":"01",
    "gn:admin2_code":"51",
    "gn:admin3_code":"15504000.0",
    "gn:asciiname":"Baong",
    "gn:country_code":"PH",
    "gn:dem":20,
    "gn:feature_class":"P",
    "gn:feature_code":"PPL",
    "gn:name":"Baong",
    "gn:population":0,
    "gn:timezone":"Asia/Manila",
    "iso:country":"PH",
    "name:fil_x_preferred":[
        "Baong"
    ],
    "wof:name":"Baong",
    "wof:placetype":"locality"
},
  "geometry": {"coordinates":[120.53333000000001,15.83333],"type":"Point"}
}