{
  "type": "Feature",
  "properties": {
    "gn:country":"PH",
    "gn:fcode":"ADM3",
    "gn:pop":52974,
    "iso:country":"PH",
    "name:fil_x_preferred":[
        "Binalonan"
    ],
    "qs:name":"Binalonan",
    "qs:photos_9r":0,
    "qs:photos_sr":0,
    "qs:pop_sr":"8",
    "wof:name":"Binalonan",
    "wof:placetype":"localadmin",
    "wof:population":52974
},
  "geometry": {"coordinates":[120.58333,16.05],"type":"Point"}
}