{
  "type": "Feature",
  "properties": {
    "gn:admin1_code":"06",
    "gn:admin2_code":"18",
    "gn:admin3_code":"61911000.0",
    "gn:asciiname":"Manjogay",
    "gn:country_code":"PH",
    "gn:dem":10,
    "gn:feature_class":"P",
    "gn:feature_code":"PPL",
    "gn:name":"Manjogay",
    "gn:population":0,
    "gn:timezone":"Asia/Manila",
    "iso:country":"PH",
    "name:fil_x_preferred":[
        "Manjogay"
    ],
    "wof:name":"Manjogay",
    "wof:placetype":"locality"
},
  "geometry": {"coordinates":[123.0278,11.4927],"type":"Point"}
}