{
  "type": "Feature",
  "properties": {
    "gn:admin1_code":"06",
    "gn:admin2_code":"H3",
    "gn:admin3_code":"64532000.0",
    "gn:asciiname":"Sibalao",
    "gn:country_code":"PH",
    "gn:dem":393,
    "gn:feature_class":"P",
    "gn:feature_code":"PPL",
    "gn:name":"Sibalao",
    "gn:population":0,
    "gn:timezone":"Asia/Manila",
    "iso:country":"PH",
    "name:fil_x_preferred":[
        "Sibalao"
    ],
    "name:und_x_variant":[
        "Sibalo"
    ],
    "wof:name":"Sibalao",
    "wof:placetype":"locality"
},
  "geometry": {"coordinates":[123.235,10.53896],"type":"Point"}
}