{
  "type": "Feature",
  "properties": {
    "gn:admin1_code":"10",
    "gn:admin2_code":"43",
    "gn:admin3_code":"104316000.0",
    "gn:asciiname":"Linabo",
    "gn:country_code":"PH",
    "gn:dem":265,
    "gn:feature_class":"P",
    "gn:feature_code":"PPL",
    "gn:name":"Linabo",
    "gn:population":0,
    "gn:timezone":"Asia/Manila",
    "iso:country":"PH",
    "name:fil_x_preferred":[
        "Linabo"
    ],
    "wof:name":"Linabo",
    "wof:placetype":"locality"
},
  "geometry": {"coordinates":[124.31667,8.33333],"type":"Point"}
}