{
  "type": "Feature",
  "properties": {
    "gn:admin1_code":"14",
    "gn:admin2_code":"22",
    "gn:admin3_code":"150705000.0",
    "gn:asciiname":"Langaray",
    "gn:country_code":"PH",
    "gn:dem":18,
    "gn:feature_class":"P",
    "gn:feature_code":"PPL",
    "gn:name":"Langaray",
    "gn:population":0,
    "gn:timezone":"Asia/Manila",
    "iso:country":"PH",
    "name:fil_x_preferred":[
        "Langaray"
    ],
    "wof:name":"Langaray",
    "wof:placetype":"locality"
},
  "geometry": {"coordinates":[122.04222,6.41861],"type":"Point"}
}