{
  "type": "Feature",
  "properties": {
    "gn:admin1_code":"03",
    "gn:admin2_code":"13",
    "gn:admin3_code":"31406000.0",
    "gn:asciiname":"Bonga Mayor",
    "gn:country_code":"PH",
    "gn:dem":17,
    "gn:feature_class":"P",
    "gn:feature_code":"PPL",
    "gn:name":"Bonga Mayor",
    "gn:population":0,
    "gn:timezone":"Asia/Manila",
    "iso:country":"PH",
    "name:fil_x_preferred":[
        "Bonga Mayor"
    ],
    "wof:name":"Bonga Mayor",
    "wof:placetype":"locality"
},
  "geometry": {"coordinates":[120.94073,14.95883],"type":"Point"}
}