{
  "type": "Feature",
  "properties": {
    "gn:admin1_code":"03",
    "gn:admin2_code":"13",
    "gn:admin3_code":"31419000.0",
    "gn:asciiname":"Tangue",
    "gn:country_code":"PH",
    "gn:dem":80,
    "gn:feature_class":"P",
    "gn:feature_code":"PPL",
    "gn:name":"Tangue",
    "gn:population":0,
    "gn:timezone":"Asia/Manila",
    "iso:country":"PH",
    "name:fil_x_preferred":[
        "Tangue"
    ],
    "wof:name":"Tangue",
    "wof:placetype":"locality"
},
  "geometry": {"coordinates":[121.0668,15.078],"type":"Point"}
}