{
  "type": "Feature",
  "properties": {
    "gn:admin1_code":"14",
    "gn:admin2_code":"60",
    "gn:admin3_code":"156609000.0",
    "gn:asciiname":"Loas",
    "gn:country_code":"PH",
    "gn:dem":50,
    "gn:feature_class":"P",
    "gn:feature_code":"PPL",
    "gn:name":"Loas",
    "gn:population":0,
    "gn:timezone":"Asia/Manila",
    "iso:country":"PH",
    "name:eng_x_preferred":[
        "Loas"
    ],
    "wof:name":"Loas",
    "wof:placetype":"locality"
},
  "geometry": {"coordinates":[120.92400000000001,5.8975],"type":"Point"}
}