{
  "type": "Feature",
  "properties": {
    "gn:country":"PH",
    "gn:fcode":"ADM3",
    "gn:pop":32451,
    "iso:country":"PH",
    "name:bcl_x_preferred":[
        "Guindulman"
    ],
    "name:ceb_x_preferred":[
        "Guindulman"
    ],
    "name:deu_x_preferred":[
        "Guindulman"
    ],
    "name:fil_x_preferred":[
        "Guindulman"
    ],
    "name:fra_x_preferred":[
        "Guindulman"
    ],
    "name:ilo_x_preferred":[
        "Guindulman"
    ],
    "name:ind_x_preferred":[
        "Guindulman"
    ],
    "name:ita_x_preferred":[
        "Guindulman"
    ],
    "name:nld_x_preferred":[
        "Guindulman"
    ],
    "name:nor_x_preferred":[
        "Guindulman"
    ],
    "name:pag_x_preferred":[
        "Guindulman"
    ],
    "name:pam_x_preferred":[
        "Guindulman"
    ],
    "name:swe_x_preferred":[
        "Guindulman"
    ],
    "name:tgl_x_preferred":[
        "Guindulman"
    ],
    "name:urd_x_preferred":[
        "\u06af\u0648\u06cc\u0646\u062f\u0648\u0644\u0645\u0627\u0646"
    ],
    "name:vie_x_preferred":[
        "Guindulman"
    ],
    "name:war_x_preferred":[
        "Guindulman"
    ],
    "qs:name":"Guindulman",
    "qs:photos_9r":0,
    "qs:photos_sr":0,
    "qs:pop_sr":"7",
    "wof:name":"Guindulman",
    "wof:placetype":"localadmin",
    "wof:population":32451
},
  "geometry": {"coordinates":[124.46666999999999,9.78333],"type":"Point"}
}