{
  "type": "Feature",
  "properties": {
    "gn:country":"PH",
    "gn:fcode":"ADM3",
    "gn:pop":32451,
    "iso:country":"PH",
    "name:fil_x_preferred":[
        "Guindulman"
    ],
    "qs:name":"Guindulman",
    "qs:photos_9r":0,
    "qs:photos_sr":0,
    "qs:pop_sr":"7",
    "wof:name":"Guindulman",
    "wof:placetype":"localadmin",
    "wof:population":32451
},
  "geometry": {"coordinates":[124.46666999999999,9.78333],"type":"Point"}
}