{
  "type": "Feature",
  "properties": {
    "gn:admin1_code":"08",
    "gn:admin2_code":"37",
    "gn:admin3_code":"83728000.0",
    "gn:asciiname":"Pawa",
    "gn:country_code":"PH",
    "gn:dem":82,
    "gn:feature_class":"P",
    "gn:feature_code":"PPL",
    "gn:name":"Pawa",
    "gn:population":0,
    "gn:timezone":"Asia/Manila",
    "iso:country":"PH",
    "name:ceb_x_preferred":[
        "Pawa"
    ],
    "name:deu_x_preferred":[
        "Pawa"
    ],
    "name:fil_x_preferred":[
        "Pawa"
    ],
    "wof:name":"Pawa",
    "wof:placetype":"locality"
},
  "geometry": {"coordinates":[124.93333,10.88333],"type":"Point"}
}