{
  "type": "Feature",
  "properties": {
    "gn:admin1_code":"40",
    "gn:admin2_code":"H2",
    "gn:admin3_code":"45622000.0",
    "gn:asciiname":"Villa Nacaob",
    "gn:country_code":"PH",
    "gn:dem":201,
    "gn:feature_class":"P",
    "gn:feature_code":"PPL",
    "gn:name":"Villa Nacaob",
    "gn:population":0,
    "gn:timezone":"Asia/Manila",
    "iso:country":"PH",
    "name:fil_x_preferred":[
        "Villa Nacaob"
    ],
    "name:fil_x_variant":[
        "Villa Nacaub"
    ],
    "wof:name":"Villa Nacaob",
    "wof:placetype":"locality"
},
  "geometry": {"coordinates":[122.2482,13.8118],"type":"Point"}
}