{
  "type": "Feature",
  "properties": {
    "gn:admin1_code":"40",
    "gn:admin2_code":"20",
    "gn:admin3_code":"42108000.0",
    "gn:asciiname":"Tejero",
    "gn:country_code":"PH",
    "gn:dem":14,
    "gn:feature_class":"P",
    "gn:feature_code":"PPL",
    "gn:name":"Tejero",
    "gn:population":0,
    "gn:timezone":"Asia/Manila",
    "iso:country":"PH",
    "name:und_x_variant":[
        "Tejeros",
        "Tehero",
        "Tejero"
    ],
    "wof:name":"Tejero",
    "wof:placetype":"locality"
},
  "geometry": {"coordinates":[120.86168000000001,14.39862],"type":"Point"}
}