{
  "type": "Feature",
  "properties": {
    "gn:admin1_code":"40",
    "gn:admin2_code":"09",
    "gn:admin3_code":"41009000.0",
    "gn:asciiname":"Dita",
    "gn:country_code":"PH",
    "gn:dem":407,
    "gn:feature_class":"P",
    "gn:feature_code":"PPL",
    "gn:name":"Dita",
    "gn:population":0,
    "gn:timezone":"Asia/Manila",
    "iso:country":"PH",
    "name:ceb_x_preferred":[
        "Dita"
    ],
    "name:deu_x_preferred":[
        "Dita"
    ],
    "name:fil_x_preferred":[
        "Dita"
    ],
    "name:fra_x_preferred":[
        "Dita"
    ],
    "name:nld_x_preferred":[
        "Dita"
    ],
    "name:rus_x_preferred":[
        "\u0414\u0438\u0442\u0430"
    ],
    "name:swe_x_preferred":[
        "Dita"
    ],
    "name:ukr_x_preferred":[
        "\u0414\u0456\u0442\u0430"
    ],
    "wof:name":"Dita",
    "wof:placetype":"locality"
},
  "geometry": {"coordinates":[121.0728,13.9208],"type":"Point"}
}