{
  "type": "Feature",
  "properties": {
    "gn:admin1_code":"09",
    "gn:admin2_code":"65",
    "gn:admin3_code":"97220000.0",
    "gn:asciiname":"Batocan",
    "gn:cc2":"PH",
    "gn:country_code":"PH",
    "gn:dem":76,
    "gn:feature_class":"P",
    "gn:feature_code":"PPL",
    "gn:name":"Batocan",
    "gn:population":0,
    "gn:timezone":"Asia/Manila",
    "iso:country":"PH",
    "name:und_x_variant":[
        "Betongan",
        "Betongano",
        "Batocan"
    ],
    "wof:name":"Batocan",
    "wof:placetype":"locality"
},
  "geometry": {"coordinates":[122.12667,7.54833],"type":"Point"}
}