{
  "type": "Feature",
  "properties": {
    "gn:country":"PH",
    "gn:fcode":"PPLA3",
    "gn:pop":3200,
    "iso:country":"PH",
    "name:bcl_x_preferred":[
        "Clarin"
    ],
    "name:ceb_x_preferred":[
        "Clarin"
    ],
    "name:deu_x_preferred":[
        "Clarin"
    ],
    "name:eng_x_preferred":[
        "Clarin"
    ],
    "name:fil_x_preferred":[
        "Clarin"
    ],
    "name:fra_x_preferred":[
        "Clarin"
    ],
    "name:ilo_x_preferred":[
        "Clarin"
    ],
    "name:ind_x_preferred":[
        "Clarin"
    ],
    "name:ita_x_preferred":[
        "Clarin"
    ],
    "name:nld_x_preferred":[
        "Clarin"
    ],
    "name:nob_x_preferred":[
        "Clarin"
    ],
    "name:pag_x_preferred":[
        "Clarin"
    ],
    "name:pam_x_preferred":[
        "Clarin"
    ],
    "name:swe_x_preferred":[
        "Clarin"
    ],
    "name:tgl_x_preferred":[
        "Clarin"
    ],
    "name:unk_x_variant":[
        "Canogan"
    ],
    "name:urd_x_preferred":[
        "\u06a9\u0644\u0627\u0631\u06cc\u0646"
    ],
    "name:vie_x_preferred":[
        "Clarin"
    ],
    "name:war_x_preferred":[
        "Clarin"
    ],
    "qs:name":"Clarin",
    "qs:photos_9r":0,
    "qs:photos_sr":0,
    "qs:pop_sr":"4",
    "wd:wordcount":126,
    "wof:name":"Clarin",
    "wof:placetype":"locality",
    "wof:population":3200
},
  "geometry": {"coordinates":[124.0252,9.9616],"type":"Point"}
}