{
  "type": "Feature",
  "properties": {
    "gn:country":"PH",
    "gn:fcode":"ADM3",
    "gn:population":104515,
    "iso:country":"PH",
    "name:fil_x_preferred":[
        "Bayambang"
    ],
    "qs:name":"Bayambang",
    "qs:photos_9r":0,
    "qs:photos_sr":0,
    "qs:pop_sr":"9",
    "wof:name":"Bayambang",
    "wof:placetype":"localadmin",
    "wof:population":104515
},
  "geometry": {"coordinates":[120.43333,15.78333],"type":"Point"}
}