{
  "type": "Feature",
  "properties": {
    "gn:admin1_code":"07",
    "gn:admin2_code":"46",
    "gn:admin3_code":"74609000.0",
    "gn:asciiname":"Apo",
    "gn:country_code":"PH",
    "gn:dem":14,
    "gn:feature_class":"P",
    "gn:feature_code":"PPL",
    "gn:name":"Apo",
    "gn:population":0,
    "gn:timezone":"Asia/Manila",
    "iso:country":"PH",
    "name:ceb_x_preferred":[
        "Apo"
    ],
    "name:diq_x_preferred":[
        "Apo"
    ],
    "name:eng_x_preferred":[
        "Apo"
    ],
    "name:fin_x_preferred":[
        "Apo"
    ],
    "name:nld_x_preferred":[
        "Apo"
    ],
    "name:por_x_preferred":[
        "Apo"
    ],
    "name:swe_x_preferred":[
        "Apo"
    ],
    "name:tgl_x_preferred":[
        "Apo"
    ],
    "name:tur_x_preferred":[
        "Apo"
    ],
    "name:und_x_variant":[
        "Apo Island"
    ],
    "wof:name":"Apo",
    "wof:placetype":"locality"
},
  "geometry": {"coordinates":[123.27079999999999,9.0765],"type":"Point"}
}