{
  "type": "Feature",
  "properties": {
    "gn:admin1_code":"03",
    "gn:admin2_code":"07",
    "gn:admin3_code":"30803000.0",
    "gn:asciiname":"Tinajero",
    "gn:cc2":"PH",
    "gn:country_code":"PH",
    "gn:dem":9,
    "gn:feature_class":"P",
    "gn:feature_code":"PPL",
    "gn:name":"Tinajero",
    "gn:population":0,
    "gn:timezone":"Asia/Manila",
    "iso:country":"PH",
    "name:und_x_variant":[
        "Tinajeros",
        "Tinajero"
    ],
    "wof:name":"Tinajero",
    "wof:placetype":"locality"
},
  "geometry": {"coordinates":[120.53749999999999,14.68167],"type":"Point"}
}