{
  "type": "Feature",
  "properties": {
    "gn:admin1_code":"40",
    "gn:admin2_code":"09",
    "gn:asciiname":"Volcan",
    "gn:country_code":"PH",
    "gn:dem":5,
    "gn:feature_class":"P",
    "gn:feature_code":"PPL",
    "gn:name":"Volcan",
    "gn:population":0,
    "gn:timezone":"Asia/Manila",
    "iso:country":"PH",
    "name:ceb_x_preferred":[
        "Volcan"
    ],
    "name:deu_x_preferred":[
        "Volcan"
    ],
    "name:fil_x_preferred":[
        "Volcan"
    ],
    "name:spa_x_preferred":[
        "Volc\u00e1n"
    ],
    "name:swe_x_preferred":[
        "Volcan"
    ],
    "wof:name":"Volcan",
    "wof:placetype":"locality"
},
  "geometry": {"coordinates":[121.01667,14.08333],"type":"Point"}
}