{
  "type": "Feature",
  "properties": {
    "gn:admin1_code":"06",
    "gn:admin2_code":"18",
    "gn:admin3_code":"61914000.0",
    "gn:asciiname":"Lawa-an",
    "gn:country_code":"PH",
    "gn:dem":12,
    "gn:feature_class":"P",
    "gn:feature_code":"PPL",
    "gn:name":"Lawa-an",
    "gn:population":0,
    "gn:timezone":"Asia/Manila",
    "iso:country":"PH",
    "name:fil_x_preferred":[
        "Lawa-an"
    ],
    "name:und_x_variant":[
        "Lauaan"
    ],
    "wof:name":"Lawa-an",
    "wof:placetype":"locality"
},
  "geometry": {"coordinates":[122.75583,11.56611],"type":"Point"}
}