{
  "type": "Feature",
  "properties": {
    "gn:admin1_code":"08",
    "gn:admin2_code":"37",
    "gn:admin3_code":"83708000.0",
    "gn:asciiname":"Hubas",
    "gn:country_code":"PH",
    "gn:dem":440,
    "gn:feature_class":"P",
    "gn:feature_code":"PPL",
    "gn:name":"Hubas",
    "gn:population":0,
    "gn:timezone":"Asia/Manila",
    "iso:country":"PH",
    "name:fil_x_preferred":[
        "Hubas"
    ],
    "wof:name":"Hubas",
    "wof:placetype":"locality"
},
  "geometry": {"coordinates":[124.81667,10.58333],"type":"Point"}
}