{
  "type": "Feature",
  "properties": {
    "gn:country":"PH",
    "gn:fcode":"ADM3",
    "gn:pop":20895,
    "iso:country":"PH",
    "name:fil_x_preferred":[
        "Pagudpud"
    ],
    "qs:name":"Pagudpud",
    "qs:photos_9r":0,
    "qs:photos_sr":0,
    "qs:pop_sr":"7",
    "wd:wordcount":674,
    "wof:name":"Pagudpud",
    "wof:placetype":"localadmin",
    "wof:population":20895
},
  "geometry": {"coordinates":[120.86478,18.56327],"type":"Point"}
}