{
  "type": "Feature",
  "properties": {
    "gn:country":"PH",
    "gn:fcode":"ADM3",
    "gn:population":20895,
    "iso:country":"PH",
    "name:bcl_x_preferred":[
        "Pagudpud"
    ],
    "name:cat_x_preferred":[
        "Pagudpud"
    ],
    "name:ceb_x_preferred":[
        "Pagudpud"
    ],
    "name:deu_x_preferred":[
        "Pagudpud"
    ],
    "name:eng_x_preferred":[
        "Pagudpud"
    ],
    "name:fil_x_preferred":[
        "Pagudpud"
    ],
    "name:fra_x_preferred":[
        "Pagudpud"
    ],
    "name:ilo_x_preferred":[
        "Pagudpud"
    ],
    "name:ind_x_preferred":[
        "Pagudpud"
    ],
    "name:ita_x_preferred":[
        "Pagudpud"
    ],
    "name:nld_x_preferred":[
        "Pagudpud"
    ],
    "name:oci_x_preferred":[
        "Pagudpud"
    ],
    "name:pag_x_preferred":[
        "Pagudpud"
    ],
    "name:pam_x_preferred":[
        "Pagudpud"
    ],
    "name:spa_x_preferred":[
        "Pagudpud"
    ],
    "name:swe_x_preferred":[
        "Pagudpud"
    ],
    "name:tgl_x_preferred":[
        "Pagudpud"
    ],
    "name:vie_x_preferred":[
        "Pagudpud"
    ],
    "name:war_x_preferred":[
        "Pagudpud"
    ],
    "name:zho_x_preferred":[
        "\u5e15\u53e4\u8fea\u5339"
    ],
    "qs:name":"Pagudpud",
    "qs:photos_9r":0,
    "qs:photos_sr":0,
    "qs:pop_sr":"7",
    "wd:wordcount":674,
    "wof:name":"Pagudpud",
    "wof:placetype":"localadmin",
    "wof:population":20895
},
  "geometry": {"coordinates":[120.86478,18.56327],"type":"Point"}
}