{
  "type": "Feature",
  "properties": {
    "gn:admin1_code":"14",
    "gn:admin2_code":"35",
    "gn:admin3_code":"153602000.0",
    "gn:asciiname":"Ig-Abay",
    "gn:country_code":"PH",
    "gn:dem":296,
    "gn:feature_class":"P",
    "gn:feature_code":"PPL",
    "gn:name":"Ig-Abay",
    "gn:population":0,
    "gn:timezone":"Asia/Manila",
    "iso:country":"PH",
    "name:und_x_variant":[
        "Igabay"
    ],
    "wof:name":"Ig-Abay",
    "wof:placetype":"locality"
},
  "geometry": {"coordinates":[124.18472,7.54611],"type":"Point"}
}