{
  "type": "Feature",
  "properties": {
    "gn:admin1_code":"40",
    "gn:admin2_code":"H2",
    "gn:admin3_code":"45646000.0",
    "gn:asciiname":"Awasan",
    "gn:country_code":"PH",
    "gn:dem":10,
    "gn:feature_class":"P",
    "gn:feature_code":"PPL",
    "gn:name":"Awasan",
    "gn:population":0,
    "gn:timezone":"Asia/Manila",
    "iso:country":"PH",
    "name:fil_x_preferred":[
        "Awasan"
    ],
    "wof:name":"Awasan",
    "wof:placetype":"locality"
},
  "geometry": {"coordinates":[122.52290000000001,13.9406],"type":"Point"}
}