{
  "type": "Feature",
  "properties": {
    "gn:admin1_code":"03",
    "gn:admin2_code":"63",
    "gn:admin3_code":"36909000.0",
    "gn:asciiname":"Atencio",
    "gn:country_code":"PH",
    "gn:dem":20,
    "gn:feature_class":"P",
    "gn:feature_code":"PPL",
    "gn:name":"Atencio",
    "gn:population":0,
    "gn:timezone":"Asia/Manila",
    "iso:country":"PH",
    "name:fil_x_preferred":[
        "Atencio"
    ],
    "wof:name":"Atencio",
    "wof:placetype":"locality"
},
  "geometry": {"coordinates":[120.57408,15.74555],"type":"Point"}
}