{
  "type": "Feature",
  "properties": {
    "gn:country":"PH",
    "gn:fcode":"PPL",
    "gn:population":2385,
    "iso:country":"PH",
    "name:und_x_variant":[
        "Gatho"
    ],
    "qs:name":"Gatbo",
    "qs:photos_9r":0,
    "qs:photos_sr":0,
    "qs:pop_sr":"4",
    "wof:name":"Gatbo",
    "wof:placetype":"locality",
    "wof:population":2385
},
  "geometry": {"coordinates":[123.38333,13.58333],"type":"Point"}
}