{
  "type": "Feature",
  "properties": {
    "gn:admin1_code":"01",
    "gn:admin2_code":"51",
    "gn:admin3_code":"15542000.0",
    "gn:asciiname":"Seselangen",
    "gn:country_code":"PH",
    "gn:dem":27,
    "gn:feature_class":"P",
    "gn:feature_code":"PPL",
    "gn:name":"Seselangen",
    "gn:population":0,
    "gn:timezone":"Asia/Manila",
    "iso:country":"PH",
    "name:fil_x_preferred":[
        "Seselangen"
    ],
    "name:und_x_variant":[
        "Seselangan",
        "Seselanguen"
    ],
    "wof:name":"Seselangen",
    "wof:placetype":"locality"
},
  "geometry": {"coordinates":[120.01584,16.10112],"type":"Point"}
}