{
  "type": "Feature",
  "properties": {
    "gn:admin1_code":"01",
    "gn:admin2_code":"28",
    "gn:admin3_code":"12804000.0",
    "gn:asciiname":"Caramuangen",
    "gn:country_code":"PH",
    "gn:dem":22,
    "gn:feature_class":"P",
    "gn:feature_code":"PPL",
    "gn:name":"Caramuangen",
    "gn:population":0,
    "gn:timezone":"Asia/Manila",
    "iso:country":"PH",
    "name:fil_x_preferred":[
        "Caramuangen"
    ],
    "wof:name":"Caramuangen",
    "wof:placetype":"locality"
},
  "geometry": {"coordinates":[120.79640000000001,18.5305],"type":"Point"}
}