{
  "type": "Feature",
  "properties": {
    "gn:admin1_code":"08",
    "gn:admin2_code":"67",
    "gn:admin3_code":"84814000.0",
    "gn:asciiname":"Campidico",
    "gn:country_code":"PH",
    "gn:dem":51,
    "gn:feature_class":"P",
    "gn:feature_code":"PPL",
    "gn:name":"Campidico",
    "gn:population":0,
    "gn:timezone":"Asia/Manila",
    "iso:country":"PH",
    "name:fil_x_preferred":[
        "Campidico"
    ],
    "wof:name":"Campidico",
    "wof:placetype":"locality"
},
  "geometry": {"coordinates":[125.0919,12.5403],"type":"Point"}
}