{
  "type": "Feature",
  "properties": {
    "gn:admin1_code":"06",
    "gn:admin2_code":"H3",
    "gn:admin3_code":"64511000.0",
    "gn:asciiname":"Canonoy",
    "gn:country_code":"PH",
    "gn:dem":17,
    "gn:feature_class":"P",
    "gn:feature_code":"PPL",
    "gn:name":"Canonoy",
    "gn:population":0,
    "gn:timezone":"Asia/Manila",
    "iso:country":"PH",
    "name:fil_x_preferred":[
        "Canonoy"
    ],
    "wof:name":"Canonoy",
    "wof:placetype":"locality"
},
  "geometry": {"coordinates":[122.8592,10.3221],"type":"Point"}
}