{
  "type": "Feature",
  "properties": {
    "gn:admin1_code":"01",
    "gn:admin2_code":"51",
    "gn:admin3_code":"15518000.0",
    "gn:asciiname":"Bonuan Boquig",
    "gn:country_code":"PH",
    "gn:dem":7,
    "gn:feature_class":"P",
    "gn:feature_code":"PPL",
    "gn:name":"Bonuan Boquig",
    "gn:population":0,
    "gn:timezone":"Asia/Manila",
    "iso:country":"PH",
    "wof:name":"Bonuan Boquig",
    "wof:placetype":"locality"
},
  "geometry": {"coordinates":[120.36139,16.07917],"type":"Point"}
}