{
  "type": "Feature",
  "properties": {
    "gn:admin1_code":"06",
    "gn:admin2_code":"06",
    "gn:admin3_code":"60606000.0",
    "gn:asciiname":"Lipata",
    "gn:country_code":"PH",
    "gn:dem":8,
    "gn:feature_class":"P",
    "gn:feature_code":"PPL",
    "gn:name":"Lipata",
    "gn:population":0,
    "gn:timezone":"Asia/Manila",
    "iso:country":"PH",
    "name:fil_x_preferred":[
        "Lipata"
    ],
    "wof:name":"Lipata",
    "wof:placetype":"locality"
},
  "geometry": {"coordinates":[122.05511,11.4668],"type":"Point"}
}