{
  "type": "Feature",
  "properties": {
    "gn:admin1_code":"NCR",
    "gn:admin2_code":"137400000",
    "gn:admin3_code":"137404000.0",
    "gn:asciiname":"Tanque",
    "gn:country_code":"PH",
    "gn:dem":14,
    "gn:feature_class":"P",
    "gn:feature_code":"PPL",
    "gn:name":"Tanque",
    "gn:population":0,
    "gn:timezone":"Asia/Manila",
    "iso:country":"PH",
    "name:fil_x_preferred":[
        "Tanque"
    ],
    "name:ita_x_preferred":[
        "Tanque"
    ],
    "name:por_x_preferred":[
        "Tanque"
    ],
    "wof:name":"Tanque",
    "wof:placetype":"locality"
},
  "geometry": {"coordinates":[121.01667,14.63333],"type":"Point"}
}