{
  "type": "Feature",
  "properties": {
    "gn:admin1_code":"10",
    "gn:admin2_code":"42",
    "gn:admin3_code":"104211000.0",
    "gn:asciiname":"Mohon",
    "gn:country_code":"PH",
    "gn:dem":89,
    "gn:feature_class":"P",
    "gn:feature_code":"PPL",
    "gn:name":"Mohon",
    "gn:population":0,
    "gn:timezone":"Asia/Manila",
    "iso:country":"PH",
    "name:als_x_preferred":[
        "Mohon"
    ],
    "name:ara_x_preferred":[
        "\u0645\u0648\u0647\u0648\u0646"
    ],
    "name:bre_x_preferred":[
        "Mozhon"
    ],
    "name:cat_x_preferred":[
        "Mohon"
    ],
    "name:ceb_x_preferred":[
        "Mohon"
    ],
    "name:cym_x_preferred":[
        "Mozhon"
    ],
    "name:deu_x_preferred":[
        "Mohon"
    ],
    "name:eng_x_preferred":[
        "Mohon"
    ],
    "name:eus_x_preferred":[
        "Mohon"
    ],
    "name:fra_x_preferred":[
        "Mohon"
    ],
    "name:hun_x_preferred":[
        "Mohon"
    ],
    "name:ita_x_preferred":[
        "Mohon"
    ],
    "name:kaz_x_preferred":[
        "\u041c\u043e\u043e\u043d"
    ],
    "name:lat_x_preferred":[
        "Mohon"
    ],
    "name:msa_x_preferred":[
        "Mohon"
    ],
    "name:nld_x_preferred":[
        "Mohon"
    ],
    "name:oci_x_preferred":[
        "Mohon"
    ],
    "name:pms_x_preferred":[
        "Mohon"
    ],
    "name:pol_x_preferred":[
        "Mohon"
    ],
    "name:por_x_preferred":[
        "Mohon"
    ],
    "name:ron_x_preferred":[
        "Mohon"
    ],
    "name:slk_x_preferred":[
        "Mohon"
    ],
    "name:spa_x_preferred":[
        "Mohon"
    ],
    "name:sqi_x_preferred":[
        "Mohon"
    ],
    "name:swe_x_preferred":[
        "Mohon"
    ],
    "name:ukr_x_preferred":[
        "\u041c\u043e\u043e\u043d"
    ],
    "name:und_x_variant":[
        "Mojan",
        "Mojon"
    ],
    "name:uzb_x_preferred":[
        "Mohon"
    ],
    "name:vie_x_preferred":[
        "Mohon"
    ],
    "name:vol_x_preferred":[
        "Mohon"
    ],
    "name:war_x_preferred":[
        "Mohon"
    ],
    "wof:name":"Mohon",
    "wof:placetype":"locality"
},
  "geometry": {"coordinates":[123.81999999999999,8.3668],"type":"Point"}
}