{
  "type": "Feature",
  "properties": {
    "gn:admin1_code":"10",
    "gn:admin2_code":"42",
    "gn:admin3_code":"104211000.0",
    "gn:asciiname":"Mohon",
    "gn:country_code":"PH",
    "gn:dem":89,
    "gn:feature_class":"P",
    "gn:feature_code":"PPL",
    "gn:name":"Mohon",
    "gn:population":0,
    "gn:timezone":"Asia/Manila",
    "iso:country":"PH",
    "name:eng_x_preferred":[
        "Mohon"
    ],
    "name:und_x_variant":[
        "Mojan",
        "Mojon"
    ],
    "wof:name":"Mohon",
    "wof:placetype":"locality"
},
  "geometry": {"coordinates":[123.81999999999999,8.3668],"type":"Point"}
}