{
  "type": "Feature",
  "properties": {
    "gn:admin1_code":"06",
    "gn:admin2_code":"H3",
    "gn:admin3_code":"64530000.0",
    "gn:asciiname":"Ayungon",
    "gn:country_code":"PH",
    "gn:dem":5,
    "gn:feature_class":"P",
    "gn:feature_code":"PPL",
    "gn:name":"Ayu\u00f1gon",
    "gn:population":0,
    "gn:timezone":"Asia/Manila",
    "iso:country":"PH",
    "name:fil_x_preferred":[
        "Ayu\u00f1gon"
    ],
    "wof:name":"Ayungon",
    "wof:placetype":"locality"
},
  "geometry": {"coordinates":[122.83333,10.45],"type":"Point"}
}