{
  "type": "Feature",
  "properties": {
    "gn:admin1_code":"07",
    "gn:admin2_code":"21",
    "gn:admin3_code":"72238000.0",
    "gn:asciiname":"Western Poblacion",
    "gn:country_code":"PH",
    "gn:dem":31,
    "gn:feature_class":"P",
    "gn:feature_code":"PPL",
    "gn:name":"Western Poblacion",
    "gn:population":0,
    "gn:timezone":"Asia/Manila",
    "iso:country":"PH",
    "name:eng_x_preferred":[
        "Western Poblacion"
    ],
    "wof:name":"Western Poblacion",
    "wof:placetype":"locality"
},
  "geometry": {"coordinates":[124.40192999999999,10.64135],"type":"Point"}
}