{
  "type": "Feature",
  "properties": {
    "gn:admin1_code":"07",
    "gn:admin2_code":"11",
    "gn:admin3_code":"71229000.0",
    "gn:asciiname":"Lobgob",
    "gn:country_code":"PH",
    "gn:dem":87,
    "gn:feature_class":"P",
    "gn:feature_code":"PPL",
    "gn:name":"Lobgob",
    "gn:population":0,
    "gn:timezone":"Asia/Manila",
    "iso:country":"PH",
    "name:fil_x_preferred":[
        "Lobgob"
    ],
    "wof:name":"Lobgob",
    "wof:placetype":"locality"
},
  "geometry": {"coordinates":[124.03400000000001,9.6771],"type":"Point"}
}