{
  "type": "Feature",
  "properties": {
    "gn:admin1_code":"06",
    "gn:admin2_code":"06",
    "gn:admin3_code":"60607000.0",
    "gn:asciiname":"Tene",
    "gn:country_code":"PH",
    "gn:dem":139,
    "gn:feature_class":"P",
    "gn:feature_code":"PPL",
    "gn:name":"Tene",
    "gn:population":0,
    "gn:timezone":"Asia/Manila",
    "iso:country":"PH",
    "name:ceb_x_preferred":[
        "Tene"
    ],
    "name:deu_x_preferred":[
        "Tene"
    ],
    "name:fil_x_preferred":[
        "Tene"
    ],
    "name:ita_x_preferred":[
        "Tene"
    ],
    "name:nld_x_preferred":[
        "Tene"
    ],
    "name:swe_x_preferred":[
        "Tene"
    ],
    "wof:name":"Tene",
    "wof:placetype":"locality"
},
  "geometry": {"coordinates":[121.9982,10.5379],"type":"Point"}
}