{
  "type": "Feature",
  "properties": {
    "gn:admin1_code":"03",
    "gn:admin2_code":"50",
    "gn:admin3_code":"35406000.0",
    "gn:asciiname":"Santa Monica",
    "gn:country_code":"PH",
    "gn:dem":22,
    "gn:feature_class":"P",
    "gn:feature_code":"PPL",
    "gn:name":"Santa Monica",
    "gn:population":0,
    "gn:timezone":"Asia/Manila",
    "iso:country":"PH",
    "name:fil_x_preferred":[
        "Santa Monica"
    ],
    "wof:name":"Santa Monica",
    "wof:placetype":"locality"
},
  "geometry": {"coordinates":[120.50794999999999,14.9536],"type":"Point"}
}