{
  "type": "Feature",
  "properties": {
    "gn:admin1_code":"03",
    "gn:admin2_code":"07",
    "gn:admin3_code":"30803000.0",
    "gn:asciiname":"Puerto Rivas",
    "gn:cc2":"PH",
    "gn:country_code":"PH",
    "gn:dem":-9999,
    "gn:feature_class":"P",
    "gn:feature_code":"PPL",
    "gn:name":"Puerto Rivas",
    "gn:population":0,
    "gn:timezone":"Asia/Manila",
    "iso:country":"PH",
    "name:und_x_variant":[
        "Puerta Rivas",
        "Puerto Rivas"
    ],
    "wof:name":"Puerto Rivas",
    "wof:placetype":"locality"
},
  "geometry": {"coordinates":[120.56139,14.69361],"type":"Point"}
}