{
  "type": "Feature",
  "properties": {
    "gn:admin1_code":"09",
    "gn:admin2_code":"66",
    "gn:admin3_code":"97323000.0",
    "gn:asciiname":"Malating",
    "gn:country_code":"PH",
    "gn:dem":24,
    "gn:feature_class":"P",
    "gn:feature_code":"PPL",
    "gn:name":"Malating",
    "gn:population":0,
    "gn:timezone":"Asia/Manila",
    "iso:country":"PH",
    "name:eng_x_preferred":[
        "Malating"
    ],
    "wof:name":"Malating",
    "wof:placetype":"locality"
},
  "geometry": {"coordinates":[123.4295,8.0608],"type":"Point"}
}