{
  "type": "Feature",
  "properties": {
    "gn:admin1_code":"05",
    "gn:admin2_code":"39",
    "gn:admin3_code":"54101000.0",
    "gn:asciiname":"Cambungal",
    "gn:country_code":"PH",
    "gn:dem":64,
    "gn:feature_class":"P",
    "gn:feature_code":"PPL",
    "gn:name":"Cambungal",
    "gn:population":0,
    "gn:timezone":"Asia/Manila",
    "iso:country":"PH",
    "name:fil_x_preferred":[
        "Cambungal"
    ],
    "wof:name":"Cambungal",
    "wof:placetype":"locality"
},
  "geometry": {"coordinates":[123.4148,12.4003],"type":"Point"}
}