{
  "type": "Feature",
  "properties": {
    "gn:country":"PH",
    "gn:fcode":"PPL",
    "gn:pop":2844,
    "iso:country":"PH",
    "name:fil_x_preferred":[
        "Nugas"
    ],
    "qs:name":"Nugas",
    "qs:photos_9r":0,
    "qs:photos_sr":0,
    "qs:pop_sr":"4",
    "wof:name":"Nugas",
    "wof:placetype":"locality",
    "wof:population":2844
},
  "geometry": {"coordinates":[123.4415,9.6968],"type":"Point"}
}