{
  "type": "Feature",
  "properties": {
    "gn:admin1_code":"15",
    "gn:admin2_code":"01",
    "gn:admin3_code":"140103000.0",
    "gn:asciiname":"Tabiog",
    "gn:country_code":"PH",
    "gn:dem":104,
    "gn:feature_class":"P",
    "gn:feature_code":"PPL",
    "gn:name":"Tabiog",
    "gn:population":0,
    "gn:timezone":"Asia/Manila",
    "iso:country":"PH",
    "name:fil_x_preferred":[
        "Tabiog"
    ],
    "wof:name":"Tabiog",
    "wof:placetype":"locality"
},
  "geometry": {"coordinates":[120.7452,17.5637],"type":"Point"}
}