{
  "type": "Feature",
  "properties": {
    "gn:country":"PH",
    "gn:fcode":"PPL",
    "gn:pop":2511,
    "iso:country":"PH",
    "name:fil_x_preferred":[
        "Maloco"
    ],
    "qs:name":"Maloco",
    "qs:photos_9r":0,
    "qs:photos_sr":0,
    "qs:pop_sr":"4",
    "wof:name":"Maloco",
    "wof:placetype":"locality",
    "wof:population":2511
},
  "geometry": {"coordinates":[122.152,11.7832],"type":"Point"}
}