{
  "type": "Feature",
  "properties": {
    "gn:admin1_code":"05",
    "gn:admin2_code":"16",
    "gn:admin3_code":"51718000.0",
    "gn:asciiname":"Patag",
    "gn:country_code":"PH",
    "gn:dem":13,
    "gn:feature_class":"P",
    "gn:feature_code":"PPL",
    "gn:name":"Patag",
    "gn:population":0,
    "gn:timezone":"Asia/Manila",
    "iso:country":"PH",
    "name:fil_x_preferred":[
        "Patag"
    ],
    "wof:name":"Patag",
    "wof:placetype":"locality"
},
  "geometry": {"coordinates":[123.05,13.73333],"type":"Point"}
}