{
  "type": "Feature",
  "properties": {
    "gn:admin1_code":"08",
    "gn:admin2_code":"59",
    "gn:admin3_code":"86417000.0",
    "gn:asciiname":"Buluang Consolacion",
    "gn:country_code":"PH",
    "gn:dem":20,
    "gn:feature_class":"P",
    "gn:feature_code":"PPL",
    "gn:name":"Buluang Consolacion",
    "gn:population":0,
    "gn:timezone":"Asia/Manila",
    "iso:country":"PH",
    "name:fil_x_preferred":[
        "Buluang Consolacion"
    ],
    "name:und_x_variant":[
        "Buluang"
    ],
    "wof:name":"Buluang Consolacion",
    "wof:placetype":"locality"
},
  "geometry": {"coordinates":[125.0065,10.395],"type":"Point"}
}