{
  "type": "Feature",
  "properties": {
    "gn:admin1_code":"15",
    "gn:admin2_code":"H6",
    "gn:admin3_code":"148102000.0",
    "gn:asciiname":"Abbot",
    "gn:country_code":"PH",
    "gn:dem":221,
    "gn:feature_class":"P",
    "gn:feature_code":"PPL",
    "gn:name":"Abbot",
    "gn:population":0,
    "gn:timezone":"Asia/Manila",
    "iso:country":"PH",
    "name:fil_x_preferred":[
        "Abbot"
    ],
    "wof:name":"Abbot",
    "wof:placetype":"locality"
},
  "geometry": {"coordinates":[121.41667,17.68332999999999],"type":"Point"}
}