{
  "type": "Feature",
  "properties": {
    "gn:admin1_code":"09",
    "gn:admin2_code":"66",
    "gn:admin3_code":"97307000.0",
    "gn:asciiname":"Baka",
    "gn:country_code":"PH",
    "gn:dem":285,
    "gn:feature_class":"P",
    "gn:feature_code":"PPL",
    "gn:name":"Baka",
    "gn:population":0,
    "gn:timezone":"Asia/Manila",
    "iso:country":"PH",
    "name:bel_x_preferred":[
        "\u0411\u0430\u043a\u0430"
    ],
    "name:cat_x_preferred":[
        "Baka"
    ],
    "name:ceb_x_preferred":[
        "Baka"
    ],
    "name:deu_x_preferred":[
        "Baka"
    ],
    "name:eng_x_preferred":[
        "Baka"
    ],
    "name:fra_x_preferred":[
        "Baka"
    ],
    "name:hun_x_preferred":[
        "Baka"
    ],
    "name:ita_x_preferred":[
        "Baka"
    ],
    "name:lav_x_preferred":[
        "Baka"
    ],
    "name:nld_x_preferred":[
        "Baka"
    ],
    "name:pol_x_preferred":[
        "Baka"
    ],
    "name:rus_x_preferred":[
        "\u0411\u0430\u043a\u0430"
    ],
    "name:spa_x_preferred":[
        "Baka"
    ],
    "name:srp_x_preferred":[
        "\u0411\u0430\u043a\u0430"
    ],
    "name:swe_x_preferred":[
        "Baka"
    ],
    "name:tgl_x_preferred":[
        "Baka"
    ],
    "name:ukr_x_preferred":[
        "\u0411\u0430\u043a\u0430"
    ],
    "name:und_x_variant":[
        "Baga"
    ],
    "wof:name":"Baka",
    "wof:placetype":"locality"
},
  "geometry": {"coordinates":[123.39109999999999,7.7697],"type":"Point"}
}