{
  "type": "Feature",
  "properties": {
    "gn:admin1_code":"03",
    "gn:admin2_code":"47",
    "gn:admin3_code":"34926000.0",
    "gn:asciiname":"Binabuyan",
    "gn:country_code":"PH",
    "gn:dem":104,
    "gn:feature_class":"P",
    "gn:feature_code":"PPL",
    "gn:name":"Binabuyan",
    "gn:population":0,
    "gn:timezone":"Asia/Manila",
    "iso:country":"PH",
    "name:fil_x_preferred":[
        "Binabuyan"
    ],
    "wof:name":"Binabuyan",
    "wof:placetype":"locality"
},
  "geometry": {"coordinates":[121.02549999999999,15.7539],"type":"Point"}
}