{
  "type": "Feature",
  "properties": {
    "gn:country":"PH",
    "gn:fcode":"PPL",
    "gn:pop":6994,
    "iso:country":"PH",
    "name:eng_x_preferred":[
        "Can-asujan"
    ],
    "name:unk_x_variant":[
        "Kanasujan"
    ],
    "qs:name":"Can-asujan",
    "qs:photos_9r":0,
    "qs:photos_sr":0,
    "qs:pop_sr":"5",
    "wof:name":"Can-asujan",
    "wof:placetype":"locality",
    "wof:population":6994
},
  "geometry": {"coordinates":[123.6574,10.1299],"type":"Point"}
}