{
  "type": "Feature",
  "properties": {
    "gn:admin1_code":"40",
    "gn:admin2_code":"H2",
    "gn:admin3_code":"45606000.0",
    "gn:asciiname":"Panasakin",
    "gn:country_code":"PH",
    "gn:dem":15,
    "gn:feature_class":"P",
    "gn:feature_code":"PPL",
    "gn:name":"Panasakin",
    "gn:population":0,
    "gn:timezone":"Asia/Manila",
    "iso:country":"PH",
    "name:fil_x_preferred":[
        "Panasakin"
    ],
    "wof:name":"Panasakin",
    "wof:placetype":"locality"
},
  "geometry": {"coordinates":[121.96953999999999,15.04885],"type":"Point"}
}