{
  "type": "Feature",
  "properties": {
    "gn:admin1_code":"02",
    "gn:admin2_code":"14",
    "gn:admin3_code":"21517000.0",
    "gn:asciiname":"Barangay",
    "gn:country_code":"PH",
    "gn:dem":17,
    "gn:feature_class":"P",
    "gn:feature_code":"PPL",
    "gn:name":"Barangay",
    "gn:population":0,
    "gn:timezone":"Asia/Manila",
    "iso:country":"PH",
    "name:ara_x_preferred":[
        "\u0628\u0631\u0646\u062c\u064a\u0647"
    ],
    "name:bcl_x_preferred":[
        "Barangay"
    ],
    "name:cat_x_preferred":[
        "Barangay"
    ],
    "name:ceb_x_preferred":[
        "Baranggay"
    ],
    "name:dan_x_preferred":[
        "Barangay"
    ],
    "name:deu_x_preferred":[
        "Barangay"
    ],
    "name:fil_x_preferred":[
        "Barangay"
    ],
    "name:fin_x_preferred":[
        "Barangay"
    ],
    "name:fra_x_preferred":[
        "Barangay"
    ],
    "name:hin_x_preferred":[
        "\u092c\u0930\u093e\u0902\u0917\u093e\u092f"
    ],
    "name:hrv_x_preferred":[
        "Barangay"
    ],
    "name:ilo_x_preferred":[
        "Baranggay"
    ],
    "name:ina_x_preferred":[
        "Barangay"
    ],
    "name:ind_x_preferred":[
        "Barangay"
    ],
    "name:ita_x_preferred":[
        "Barangay"
    ],
    "name:jpn_x_preferred":[
        "\u30d0\u30e9\u30f3\u30ac\u30a4"
    ],
    "name:kor_x_preferred":[
        "\ubc14\ub791\uac00\uc774"
    ],
    "name:lat_x_preferred":[
        "Barangay"
    ],
    "name:mkd_x_preferred":[
        "\u0411\u0430\u0440\u0430\u043d\u0433\u0430\u0458"
    ],
    "name:msa_x_preferred":[
        "Barangay"
    ],
    "name:nld_x_preferred":[
        "Barangay"
    ],
    "name:nor_x_preferred":[
        "Barangay"
    ],
    "name:pag_x_preferred":[
        "Barangay"
    ],
    "name:pam_x_preferred":[
        "Barangay"
    ],
    "name:por_x_preferred":[
        "Barangay"
    ],
    "name:rus_x_preferred":[
        "\u0411\u0430\u0440\u0430\u043d\u0433\u0430\u0439"
    ],
    "name:spa_x_preferred":[
        "Barangay"
    ],
    "name:swe_x_preferred":[
        "Barangay"
    ],
    "name:tgl_x_preferred":[
        "Barangay"
    ],
    "name:tha_x_preferred":[
        "\u0e1a\u0e32\u0e23\u0e31\u0e07\u0e44\u0e01\u0e22\u0e4c"
    ],
    "name:tur_x_preferred":[
        "Barangay"
    ],
    "name:ukr_x_preferred":[
        "\u0411\u0430\u0440\u0430\u043d\u0491\u0430\u0439"
    ],
    "name:urd_x_preferred":[
        "\u0628\u0627\u0631\u0627\u0646\u06af\u0627\u0626\u06d2"
    ],
    "name:vie_x_preferred":[
        "Barangay"
    ],
    "name:war_x_preferred":[
        "Baranggay"
    ],
    "name:zho_x_preferred":[
        "\u63cf\u7c60\u6daf"
    ],
    "wof:name":"Barangay",
    "wof:placetype":"locality"
},
  "geometry": {"coordinates":[121.63395,18.09698],"type":"Point"}
}