{
  "type": "Feature",
  "properties": {
    "gn:gn_country":"PH",
    "gn:gn_fcode":"PPL",
    "gn:gn_pop":3136,
    "gn:population":3136,
    "iso:country":"PH",
    "name:fil_x_preferred":[
        "Mataya"
    ],
    "qs_pg:aaroncc":"PH",
    "qs_pg:gn_country":"PH",
    "qs_pg:gn_fcode":"PPL",
    "qs_pg:gn_pop":3136,
    "qs_pg:name":"Mataya",
    "qs_pg:photos_9r":0,
    "qs_pg:photos_sr":0,
    "qs_pg:pop_sr":4,
    "qs_pg:qs_pg_placetype":"locality",
    "wof:name":"Mataya",
    "wof:placetype":"locality",
    "wof:population":3136
},
  "geometry": {"coordinates":[124.37194,7.47111],"type":"Point"}
}