{
  "type": "Feature",
  "properties": {
    "gn:admin1_code":"40",
    "gn:admin2_code":"33",
    "gn:admin3_code":"43414000.0",
    "gn:asciiname":"Nanguma",
    "gn:country_code":"PH",
    "gn:dem":11,
    "gn:feature_class":"P",
    "gn:feature_code":"PPL",
    "gn:name":"Nanguma",
    "gn:population":0,
    "gn:timezone":"Asia/Manila",
    "iso:country":"PH",
    "name:fil_x_preferred":[
        "Nanguma"
    ],
    "wof:name":"Nanguma",
    "wof:placetype":"locality"
},
  "geometry": {"coordinates":[121.4208,14.4453],"type":"Point"}
}