{
  "type": "Feature",
  "properties": {
    "gn:admin1_code":"01",
    "gn:admin2_code":"29",
    "gn:admin3_code":"12920000.0",
    "gn:asciiname":"Guimod",
    "gn:country_code":"PH",
    "gn:dem":16,
    "gn:feature_class":"P",
    "gn:feature_code":"PPL",
    "gn:name":"Guimod",
    "gn:population":0,
    "gn:timezone":"Asia/Manila",
    "iso:country":"PH",
    "name:fil_x_preferred":[
        "Guimod"
    ],
    "wof:name":"Guimod",
    "wof:placetype":"locality"
},
  "geometry": {"coordinates":[120.44126,17.72063],"type":"Point"}
}