{
  "type": "Feature",
  "properties": {
    "gn:admin1_code":"12",
    "gn:admin2_code":"57",
    "gn:admin3_code":"124707000.0",
    "gn:asciiname":"Lamitan",
    "gn:country_code":"PH",
    "gn:dem":266,
    "gn:feature_class":"P",
    "gn:feature_code":"PPL",
    "gn:name":"Lamitan",
    "gn:population":0,
    "gn:timezone":"Asia/Manila",
    "iso:country":"PH",
    "name:bcl_x_preferred":[
        "Lamitan"
    ],
    "name:ceb_x_preferred":[
        "Lamitan"
    ],
    "name:deu_x_preferred":[
        "Lamitan City"
    ],
    "name:fil_x_preferred":[
        "Lamitan"
    ],
    "name:fra_x_preferred":[
        "Lamitan"
    ],
    "name:ilo_x_preferred":[
        "Lamitan"
    ],
    "name:ind_x_preferred":[
        "Kota Lamitan"
    ],
    "name:ita_x_preferred":[
        "Lamitan"
    ],
    "name:msa_x_preferred":[
        "Lamitan City"
    ],
    "name:nld_x_preferred":[
        "Lamitan"
    ],
    "name:nor_x_preferred":[
        "Lamitan City"
    ],
    "name:pag_x_preferred":[
        "Lamitan"
    ],
    "name:pam_x_preferred":[
        "Lamitan"
    ],
    "name:spa_x_preferred":[
        "Lamitan"
    ],
    "name:swe_x_preferred":[
        "Lamitan"
    ],
    "name:tgl_x_preferred":[
        "Lamitan"
    ],
    "name:tha_x_preferred":[
        "\u0e25\u0e32\u0e21\u0e35\u0e15\u0e31\u0e19"
    ],
    "name:urd_x_preferred":[
        "\u0644\u0627\u0645\u06cc\u062a\u0627\u0646"
    ],
    "name:vie_x_preferred":[
        "Lamitan"
    ],
    "name:war_x_preferred":[
        "Lamitan"
    ],
    "wof:name":"Lamitan",
    "wof:placetype":"locality"
},
  "geometry": {"coordinates":[125.09222,6.95694],"type":"Point"}
}