{
  "type": "Feature",
  "properties": {
    "gn:admin1_code":"12",
    "gn:admin2_code":"57",
    "gn:admin3_code":"124707000.0",
    "gn:asciiname":"Lamitan",
    "gn:country_code":"PH",
    "gn:dem":266,
    "gn:feature_class":"P",
    "gn:feature_code":"PPL",
    "gn:name":"Lamitan",
    "gn:population":0,
    "gn:timezone":"Asia/Manila",
    "iso:country":"PH",
    "name:fil_x_preferred":[
        "Lamitan"
    ],
    "wof:name":"Lamitan",
    "wof:placetype":"locality"
},
  "geometry": {"coordinates":[125.09222,6.95694],"type":"Point"}
}