{
  "type": "Feature",
  "properties": {
    "gn:admin1_code":"01",
    "gn:admin2_code":"51",
    "gn:admin3_code":"15531000.0",
    "gn:asciiname":"Tomana West",
    "gn:country_code":"PH",
    "gn:dem":32,
    "gn:feature_class":"P",
    "gn:feature_code":"PPL",
    "gn:name":"Tomana West",
    "gn:population":0,
    "gn:timezone":"Asia/Manila",
    "iso:country":"PH",
    "name:fil_x_preferred":[
        "Tumana"
    ],
    "wof:name":"Tomana West",
    "wof:placetype":"locality"
},
  "geometry": {"coordinates":[120.60589,15.88911],"type":"Point"}
}