{
  "type": "Feature",
  "properties": {
    "gn:admin1_code":"01",
    "gn:admin2_code":"36",
    "gn:admin3_code":"13309000.0",
    "gn:asciiname":"Santiago Norte",
    "gn:country_code":"PH",
    "gn:dem":11,
    "gn:feature_class":"P",
    "gn:feature_code":"PPL",
    "gn:name":"Santiago Norte",
    "gn:population":0,
    "gn:timezone":"Asia/Manila",
    "iso:country":"PH",
    "name:fil_x_preferred":[
        "Santiago Norte"
    ],
    "name:fil_x_variant":[
        "Santiago"
    ],
    "wof:name":"Santiago Norte",
    "wof:placetype":"locality"
},
  "geometry": {"coordinates":[120.3361,16.4309],"type":"Point"}
}