{
  "type": "Feature",
  "properties": {
    "gn:admin1_code":"14",
    "gn:admin2_code":"60",
    "gn:admin3_code":"156613000.0",
    "gn:asciiname":"Lung Kiaban",
    "gn:country_code":"PH",
    "gn:dem":31,
    "gn:feature_class":"P",
    "gn:feature_code":"PPL",
    "gn:name":"Lung Kiaban",
    "gn:population":0,
    "gn:timezone":"Asia/Manila",
    "iso:country":"PH",
    "name:fil_x_preferred":[
        "Lung Kiaban"
    ],
    "wof:name":"Lung Kiaban",
    "wof:placetype":"locality"
},
  "geometry": {"coordinates":[121.15083,5.955],"type":"Point"}
}