{
  "type": "Feature",
  "properties": {
    "gn:admin1_code":"05",
    "gn:admin2_code":"15",
    "gn:admin3_code":"51609000.0",
    "gn:asciiname":"Marabilla",
    "gn:country_code":"PH",
    "gn:dem":36,
    "gn:feature_class":"P",
    "gn:feature_code":"PPL",
    "gn:name":"Marabilla",
    "gn:population":0,
    "gn:timezone":"Asia/Manila",
    "iso:country":"PH",
    "name:fil_x_preferred":[
        "Marabilla"
    ],
    "wof:name":"Marabilla",
    "wof:placetype":"locality"
},
  "geometry": {"coordinates":[122.8849,14.1087],"type":"Point"}
}