{
  "type": "Feature",
  "properties": {
    "gn:country":"PH",
    "gn:fcode":"PPL",
    "gn:population":6099,
    "iso:country":"PH",
    "name:eng_x_preferred":[
        "Pu\u00f1ay"
    ],
    "name:jpn_x_preferred":[
        "\u30d7\u30cb\u30e3\u30a4\u5c71"
    ],
    "name:que_x_preferred":[
        "Pu\u00f1ay"
    ],
    "name:und_x_variant":[
        "Punai"
    ],
    "qs:name":"Punay",
    "qs:photos_9r":0,
    "qs:photos_sr":0,
    "qs:pop_sr":"5",
    "wd:wordcount":399,
    "wof:name":"Punay",
    "wof:placetype":"locality",
    "wof:population":6099
},
  "geometry": {"coordinates":[121.19806,5.96139],"type":"Point"}
}