{
  "type": "Feature",
  "properties": {
    "gn:country":"PH",
    "gn:fcode":"PPL",
    "gn:pop":6099,
    "iso:country":"PH",
    "name:unk_x_variant":[
        "Punai"
    ],
    "qs:name":"Punay",
    "qs:photos_9r":0,
    "qs:photos_sr":0,
    "qs:pop_sr":"5",
    "wd:wordcount":399,
    "wof:name":"Punay",
    "wof:placetype":"locality",
    "wof:population":6099
},
  "geometry": {"coordinates":[121.19806,5.96139],"type":"Point"}
}