{
  "type": "Feature",
  "properties": {
    "gn:admin1_code":"01",
    "gn:admin2_code":"28",
    "gn:admin3_code":"12815000.0",
    "gn:asciiname":"Pansian",
    "gn:country_code":"PH",
    "gn:dem":21,
    "gn:feature_class":"P",
    "gn:feature_code":"PPL",
    "gn:name":"Pansian",
    "gn:population":0,
    "gn:timezone":"Asia/Manila",
    "iso:country":"PH",
    "name:fil_x_preferred":[
        "Pansian"
    ],
    "wof:name":"Pansian",
    "wof:placetype":"locality"
},
  "geometry": {"coordinates":[120.91638,18.56039],"type":"Point"}
}