{
  "type": "Feature",
  "properties": {
    "gn:admin1_code":"06",
    "gn:admin2_code":"30",
    "gn:admin3_code":"63012000.0",
    "gn:asciiname":"Camulogan",
    "gn:country_code":"PH",
    "gn:dem":56,
    "gn:feature_class":"P",
    "gn:feature_code":"PPL",
    "gn:name":"Camulogan",
    "gn:population":0,
    "gn:timezone":"Asia/Manila",
    "iso:country":"PH",
    "name:fil_x_preferred":[
        "Camulogan"
    ],
    "wof:name":"Camulogan",
    "wof:placetype":"locality"
},
  "geometry": {"coordinates":[122.4902,10.873],"type":"Point"}
}