{
  "type": "Feature",
  "properties": {
    "gn:admin1_code":"14",
    "gn:admin2_code":"56",
    "gn:asciiname":"Gligli",
    "gn:country_code":"PH",
    "gn:dem":17,
    "gn:feature_class":"P",
    "gn:feature_code":"PPL",
    "gn:name":"Gligli",
    "gn:population":0,
    "gn:timezone":"Asia/Manila",
    "iso:country":"PH",
    "name:fil_x_preferred":[
        "Gligli"
    ],
    "name:fil_x_variant":[
        "Guiliguili"
    ],
    "wof:name":"Gligli",
    "wof:placetype":"locality"
},
  "geometry": {"coordinates":[124.66970000000001,7.02484],"type":"Point"}
}