{
  "type": "Feature",
  "properties": {
    "gn:admin1_code":"03",
    "gn:admin2_code":"50",
    "gn:admin3_code":"35412000.0",
    "gn:asciiname":"Palimpe",
    "gn:country_code":"PH",
    "gn:dem":7,
    "gn:feature_class":"P",
    "gn:feature_code":"PPL",
    "gn:name":"Palimpe",
    "gn:population":0,
    "gn:timezone":"Asia/Manila",
    "iso:country":"PH",
    "wof:name":"Palimpe",
    "wof:placetype":"locality"
},
  "geometry": {"coordinates":[120.67487,14.87436],"type":"Point"}
}