{
  "type": "Feature",
  "properties": {
    "gn:country":"PH",
    "gn:fcode":"ADM3",
    "gn:pop":27994,
    "iso:country":"PH",
    "name:bcl_x_preferred":[
        "Masiu"
    ],
    "name:ceb_x_preferred":[
        "Masiu"
    ],
    "name:deu_x_preferred":[
        "Masiu"
    ],
    "name:fil_x_preferred":[
        "Masiu"
    ],
    "name:fra_x_preferred":[
        "Masiu"
    ],
    "name:ilo_x_preferred":[
        "Masiu"
    ],
    "name:ind_x_preferred":[
        "Masiu"
    ],
    "name:ita_x_preferred":[
        "Masiu"
    ],
    "name:nld_x_preferred":[
        "Masiu"
    ],
    "name:pag_x_preferred":[
        "Masiu"
    ],
    "name:pam_x_preferred":[
        "Masiu"
    ],
    "name:swe_x_preferred":[
        "Masiu"
    ],
    "name:tgl_x_preferred":[
        "Masiu"
    ],
    "name:urd_x_preferred":[
        "\u0645\u0627\u0633\u06cc\u0648"
    ],
    "name:vie_x_preferred":[
        "Masiu"
    ],
    "name:war_x_preferred":[
        "Masiu"
    ],
    "qs:name":"Masiu",
    "qs:photos_9r":0,
    "qs:photos_sr":0,
    "qs:pop_sr":"7",
    "wof:name":"Masiu",
    "wof:placetype":"localadmin",
    "wof:population":27994
},
  "geometry": {"coordinates":[124.33333,7.81667],"type":"Point"}
}