{
  "type": "Feature",
  "properties": {
    "gn:admin1_code":"40",
    "gn:admin2_code":"H2",
    "gn:admin3_code":"45620000.0",
    "gn:asciiname":"Tongohin",
    "gn:country_code":"PH",
    "gn:dem":10,
    "gn:feature_class":"P",
    "gn:feature_code":"PPL",
    "gn:name":"Tongohin",
    "gn:population":0,
    "gn:timezone":"Asia/Manila",
    "iso:country":"PH",
    "name:fil_x_preferred":[
        "Tongohin"
    ],
    "wof:name":"Tongohin",
    "wof:placetype":"locality"
},
  "geometry": {"coordinates":[121.62987,14.72241],"type":"Point"}
}