{
  "type": "Feature",
  "properties": {
    "gn:admin1_code":"01",
    "gn:admin2_code":"51",
    "gn:admin3_code":"15511000.0",
    "gn:asciiname":"Amancosiling Sur",
    "gn:country_code":"PH",
    "gn:dem":24,
    "gn:feature_class":"P",
    "gn:feature_code":"PPL",
    "gn:name":"Amancosiling Sur",
    "gn:population":0,
    "gn:timezone":"Asia/Manila",
    "iso:country":"PH",
    "name:fil_x_preferred":[
        "Amancosiling"
    ],
    "name:und_x_variant":[
        "Amancosiling"
    ],
    "wof:name":"Amancosiling Sur",
    "wof:placetype":"locality"
},
  "geometry": {"coordinates":[120.45729,15.77326],"type":"Point"}
}