{
  "type": "Feature",
  "properties": {
    "gn:admin1_code":"03",
    "gn:admin2_code":"07",
    "gn:admin3_code":"30805000.0",
    "gn:asciiname":"Kulisig",
    "gn:country_code":"PH",
    "gn:dem":24,
    "gn:feature_class":"P",
    "gn:feature_code":"PPL",
    "gn:name":"Kulisig",
    "gn:population":0,
    "gn:timezone":"Asia/Manila",
    "iso:country":"PH",
    "name:fil_x_preferred":[
        "Kulisig"
    ],
    "wof:name":"Kulisig",
    "wof:placetype":"locality"
},
  "geometry": {"coordinates":[120.40000000000001,14.83333],"type":"Point"}
}