{
  "type": "Feature",
  "properties": {
    "gn:admin1_code":"40",
    "gn:admin2_code":"53",
    "gn:admin3_code":"45812000.0",
    "gn:asciiname":"Sandalan",
    "gn:country_code":"PH",
    "gn:dem":486,
    "gn:feature_class":"P",
    "gn:feature_code":"PPL",
    "gn:name":"Sandalan",
    "gn:population":0,
    "gn:timezone":"Asia/Manila",
    "iso:country":"PH",
    "name:fil_x_preferred":[
        "Sandalan"
    ],
    "wof:name":"Sandalan",
    "wof:placetype":"locality"
},
  "geometry": {"coordinates":[121.33278,14.63306],"type":"Point"}
}