{
  "type": "Feature",
  "properties": {
    "gn:admin1_code":"15",
    "gn:admin2_code":"H6",
    "gn:admin3_code":"148103000.0",
    "gn:asciiname":"Anninipan",
    "gn:country_code":"PH",
    "gn:dem":40,
    "gn:feature_class":"P",
    "gn:feature_code":"PPL",
    "gn:name":"Anninipan",
    "gn:population":0,
    "gn:timezone":"Asia/Manila",
    "iso:country":"PH",
    "name:und_x_variant":[
        "Aninipan"
    ],
    "wof:name":"Anninipan",
    "wof:placetype":"locality"
},
  "geometry": {"coordinates":[121.45381,18.15887],"type":"Point"}
}