{
  "type": "Feature",
  "properties": {
    "gn:admin1_code":"08",
    "gn:admin2_code":"37",
    "gn:admin3_code":"83703000.0",
    "gn:asciiname":"Palanas",
    "gn:country_code":"PH",
    "gn:dem":21,
    "gn:elevation":"0.0",
    "gn:feature_class":"P",
    "gn:feature_code":"PPL",
    "gn:name":"Palanas",
    "gn:population":0,
    "gn:timezone":"Asia/Manila",
    "iso:country":"PH",
    "name:fil_x_preferred":[
        "Palanas"
    ],
    "wof:name":"Palanas",
    "wof:placetype":"locality"
},
  "geometry": {"coordinates":[124.71559999999999,10.8827],"type":"Point"}
}