{
  "type": "Feature",
  "properties": {
    "iso:country":"PH",
    "name:bcl_x_preferred":[
        "Clarin"
    ],
    "name:cbk_zam_x_preferred":[
        "Clarin"
    ],
    "name:ceb_x_preferred":[
        "Clarin"
    ],
    "name:deu_x_preferred":[
        "Clarin"
    ],
    "name:eng_x_preferred":[
        "Clarin"
    ],
    "name:fra_x_preferred":[
        "Clarin"
    ],
    "name:ilo_x_preferred":[
        "Clarin"
    ],
    "name:ind_x_preferred":[
        "Clarin"
    ],
    "name:ita_x_preferred":[
        "Clarin"
    ],
    "name:nld_x_preferred":[
        "Clarin"
    ],
    "name:pag_x_preferred":[
        "Clarin"
    ],
    "name:pam_x_preferred":[
        "Clarin"
    ],
    "name:spa_x_preferred":[
        "Clar\u00edn de Misamis"
    ],
    "name:swe_x_preferred":[
        "Clarin"
    ],
    "name:tgl_x_preferred":[
        "Clarin"
    ],
    "name:unk_x_variant":[
        "Loculan"
    ],
    "name:vie_x_preferred":[
        "Clarin"
    ],
    "name:war_x_preferred":[
        "Clarin"
    ],
    "qs:gn_country":"PH",
    "qs:gn_fcode":"PPL",
    "qs:gn_pop":7125,
    "qs:name":"Clarin",
    "qs:name_adm0":"Philippines",
    "qs:name_adm1":"Northern Mindanao",
    "qs:photos":40,
    "qs:photos_1k":8,
    "qs:photos_9k":1,
    "qs:photos_9r":2,
    "qs:photos_all":40,
    "qs:photos_sr":2,
    "qs:placetype":"Town",
    "qs:pop_sr":"5",
    "qs:woe_adm0":23424934,
    "wd:wordcount":199,
    "wof:name":"Clarin",
    "wof:placetype":"locality",
    "wof:population":7125
},
  "geometry": {"coordinates":[123.8582,8.2023],"type":"Point"}
}