{
  "type": "Feature",
  "properties": {
    "gn:admin1_code":"05",
    "gn:admin2_code":"16",
    "gn:admin3_code":"51712000.0",
    "gn:asciiname":"Magalis",
    "gn:country_code":"PH",
    "gn:dem":18,
    "gn:feature_class":"P",
    "gn:feature_code":"PPL",
    "gn:name":"Magalis",
    "gn:population":0,
    "gn:timezone":"Asia/Manila",
    "iso:country":"PH",
    "name:fil_x_preferred":[
        "Magalis"
    ],
    "name:und_x_variant":[
        "Magais"
    ],
    "wof:name":"Magalis",
    "wof:placetype":"locality"
},
  "geometry": {"coordinates":[122.5848,13.9388],"type":"Point"}
}