{
  "type": "Feature",
  "properties": {
    "gn:gn_country":"PH",
    "gn:gn_fcode":"PPLA3",
    "gn:gn_pop":6874,
    "gn:population":6874,
    "iso:country":"PH",
    "name:fil_x_preferred":[
        "Cabugao"
    ],
    "name:fil_x_variant":[
        "Kabugao"
    ],
    "name:unk_x_variant":[
        "Kabugao"
    ],
    "qs_pg:aaroncc":"PH",
    "qs_pg:gn_country":"PH",
    "qs_pg:gn_fcode":"PPLA3",
    "qs_pg:gn_pop":6874,
    "qs_pg:name":"Cabugao",
    "qs_pg:photos_9r":0,
    "qs_pg:photos_sr":0,
    "qs_pg:pop_sr":5,
    "qs_pg:qs_pg_placetype":"locality",
    "wof:name":"Cabugao",
    "wof:placetype":"locality",
    "wof:population":6874
},
  "geometry": {"coordinates":[120.45780000000001,17.7931],"type":"Point"}
}