{
  "type": "Feature",
  "properties": {
    "gn:gn_country":"PH",
    "gn:gn_fcode":"PPLA3",
    "gn:gn_pop":6874,
    "gn:population":6874,
    "iso:country":"PH",
    "name:bcl_x_preferred":[
        "Cabugao"
    ],
    "name:ceb_x_preferred":[
        "Cabugao"
    ],
    "name:deu_x_preferred":[
        "Cabugao"
    ],
    "name:fil_x_preferred":[
        "Cabugao"
    ],
    "name:fil_x_variant":[
        "Kabugao"
    ],
    "name:fra_x_preferred":[
        "Cabugao"
    ],
    "name:ilo_x_preferred":[
        "Cabugao"
    ],
    "name:ind_x_preferred":[
        "Cabugao"
    ],
    "name:ita_x_preferred":[
        "Cabugao"
    ],
    "name:nld_x_preferred":[
        "Cabugao"
    ],
    "name:pag_x_preferred":[
        "Cabugao"
    ],
    "name:pam_x_preferred":[
        "Cabugao"
    ],
    "name:spa_x_preferred":[
        "Cabugao"
    ],
    "name:swe_x_preferred":[
        "Cabugao"
    ],
    "name:tgl_x_preferred":[
        "Cabugao"
    ],
    "name:unk_x_variant":[
        "Kabugao"
    ],
    "name:vie_x_preferred":[
        "Cabugao"
    ],
    "name:war_x_preferred":[
        "Cabugao"
    ],
    "qs_pg:aaroncc":"PH",
    "qs_pg:gn_country":"PH",
    "qs_pg:gn_fcode":"PPLA3",
    "qs_pg:gn_pop":6874,
    "qs_pg:name":"Cabugao",
    "qs_pg:photos_9r":0,
    "qs_pg:photos_sr":0,
    "qs_pg:pop_sr":5,
    "qs_pg:qs_pg_placetype":"locality",
    "wof:name":"Cabugao",
    "wof:placetype":"locality",
    "wof:population":6874
},
  "geometry": {"coordinates":[120.45780000000001,17.7931],"type":"Point"}
}