{
  "type": "Feature",
  "properties": {
    "gn:admin1_code":"03",
    "gn:admin2_code":"50",
    "gn:admin3_code":"35404000.0",
    "gn:asciiname":"Mitia Proper",
    "gn:country_code":"PH",
    "gn:dem":85,
    "gn:feature_class":"P",
    "gn:feature_code":"PPL",
    "gn:name":"Mitia Proper",
    "gn:population":0,
    "gn:timezone":"Asia/Manila",
    "iso:country":"PH",
    "name:eng_x_preferred":[
        "Mitia Proper"
    ],
    "name:fil_x_preferred":[
        "Mitla"
    ],
    "wof:name":"Mitia Proper",
    "wof:placetype":"locality"
},
  "geometry": {"coordinates":[120.57483000000001,15.08018],"type":"Point"}
}