{
  "type": "Feature",
  "properties": {
    "iso:country":"PH",
    "name:cat_x_preferred":[
        "Ala"
    ],
    "name:ceb_x_preferred":[
        "Ala"
    ],
    "name:ces_x_preferred":[
        "Ala"
    ],
    "name:deu_x_preferred":[
        "Ala"
    ],
    "name:epo_x_preferred":[
        "ALA"
    ],
    "name:est_x_preferred":[
        "Ala"
    ],
    "name:fas_x_preferred":[
        "\u0639\u0644\u0627\u0621"
    ],
    "name:fil_x_preferred":[
        "Alae"
    ],
    "name:fin_x_preferred":[
        "Ala"
    ],
    "name:fra_x_preferred":[
        "Ala"
    ],
    "name:hbs_x_preferred":[
        "ALA"
    ],
    "name:hun_x_preferred":[
        "Ala"
    ],
    "name:hye_x_preferred":[
        "\u0531\u056c\u0561"
    ],
    "name:ita_x_preferred":[
        "ALA"
    ],
    "name:jpn_x_preferred":[
        "ALA"
    ],
    "name:kor_x_preferred":[
        "ALA"
    ],
    "name:lat_x_preferred":[
        "Ala"
    ],
    "name:lav_x_preferred":[
        "ALA"
    ],
    "name:lit_x_preferred":[
        "ALA"
    ],
    "name:lmo_x_preferred":[
        "Ala"
    ],
    "name:nld_x_preferred":[
        "Ala"
    ],
    "name:pms_x_preferred":[
        "Ala"
    ],
    "name:pol_x_preferred":[
        "Ala"
    ],
    "name:por_x_preferred":[
        "Ala"
    ],
    "name:rus_x_preferred":[
        "\u0410\u043b\u0430"
    ],
    "name:scn_x_preferred":[
        "Ala"
    ],
    "name:slv_x_preferred":[
        "ALA"
    ],
    "name:spa_x_preferred":[
        "Ala"
    ],
    "name:srp_x_preferred":[
        "Ala"
    ],
    "name:swe_x_preferred":[
        "Ala"
    ],
    "name:ukr_x_preferred":[
        "\u0410\u043b\u0430"
    ],
    "name:und_x_variant":[
        "Alai"
    ],
    "name:vol_x_preferred":[
        "Ala"
    ],
    "name:zho_x_preferred":[
        "ALA"
    ],
    "qs:gn_country":"PH",
    "qs:gn_fcode":"PPL",
    "qs:gn_pop":5121,
    "qs:name":"Alae",
    "qs:name_adm0":"Philippines",
    "qs:name_adm1":"Northern Mindanao",
    "qs:photos":0,
    "qs:photos_1k":0,
    "qs:photos_9k":1,
    "qs:photos_9r":3,
    "qs:photos_all":92,
    "qs:photos_sr":0,
    "qs:placetype":"Town",
    "qs:pop_sr":"5",
    "qs:woe_adm0":23424934,
    "wd:wordcount":582,
    "wof:name":"Alae",
    "wof:placetype":"locality",
    "wof:population":5121
},
  "geometry": {"coordinates":[124.81278,8.42444],"type":"Point"}
}