{
  "type": "Feature",
  "properties": {
    "gn:admin1_code":"01",
    "gn:admin2_code":"28",
    "gn:admin3_code":"12813000.0",
    "gn:asciiname":"Escoda",
    "gn:country_code":"PH",
    "gn:dem":55,
    "gn:feature_class":"P",
    "gn:feature_code":"PPL",
    "gn:name":"Escoda",
    "gn:population":0,
    "gn:timezone":"Asia/Manila",
    "iso:country":"PH",
    "name:fil_x_preferred":[
        "Escoda"
    ],
    "wof:name":"Escoda",
    "wof:placetype":"locality"
},
  "geometry": {"coordinates":[120.7025,18.0167],"type":"Point"}
}