{
  "type": "Feature",
  "properties": {
    "gn:admin1_code":"15",
    "gn:admin2_code":"H6",
    "gn:admin3_code":"148105000.0",
    "gn:asciiname":"Manakota",
    "gn:cc2":"PH",
    "gn:country_code":"PH",
    "gn:dem":34,
    "gn:feature_class":"P",
    "gn:feature_code":"PPL",
    "gn:name":"Manakota",
    "gn:population":0,
    "gn:timezone":"Asia/Manila",
    "iso:country":"PH",
    "name:und_x_variant":[
        "Manacota",
        "Manakota"
    ],
    "wof:name":"Manakota",
    "wof:placetype":"locality"
},
  "geometry": {"coordinates":[121.26917,18.34],"type":"Point"}
}