{
  "type": "Feature",
  "properties": {
    "gn:admin1_code":"02",
    "gn:admin2_code":"31",
    "gn:admin3_code":"23109000.0",
    "gn:asciiname":"Dicawal",
    "gn:country_code":"PH",
    "gn:dem":167,
    "gn:feature_class":"P",
    "gn:feature_code":"PPL",
    "gn:name":"Dicawal",
    "gn:population":0,
    "gn:timezone":"Asia/Manila",
    "iso:country":"PH",
    "name:fil_x_preferred":[
        "Dicawal"
    ],
    "wof:name":"Dicawal",
    "wof:placetype":"locality"
},
  "geometry": {"coordinates":[121.4225,16.648],"type":"Point"}
}