{
  "type": "Feature",
  "properties": {
    "gn:admin1_code":"03",
    "gn:admin2_code":"63",
    "gn:admin3_code":"36909000.0",
    "gn:asciiname":"Malbug",
    "gn:country_code":"PH",
    "gn:dem":22,
    "gn:feature_class":"P",
    "gn:feature_code":"PPL",
    "gn:name":"Malbug",
    "gn:population":0,
    "gn:timezone":"Asia/Manila",
    "iso:country":"PH",
    "name:fil_x_preferred":[
        "Malbug"
    ],
    "wof:name":"Malbug",
    "wof:placetype":"locality"
},
  "geometry": {"coordinates":[120.59999999999999,15.75],"type":"Point"}
}