{
  "type": "Feature",
  "properties": {
    "gn:admin1_code":"40",
    "gn:admin2_code":"H2",
    "gn:admin3_code":"45636000.0",
    "gn:asciiname":"Masisi",
    "gn:country_code":"PH",
    "gn:dem":28,
    "gn:feature_class":"P",
    "gn:feature_code":"PPL",
    "gn:name":"Masisi",
    "gn:population":0,
    "gn:timezone":"Asia/Manila",
    "iso:country":"PH",
    "name:azb_x_preferred":[
        "\u0645\u0627\u0633\u06cc\u0633\u06cc"
    ],
    "name:fas_x_preferred":[
        "\u0645\u0627\u0633\u06cc\u0633\u06cc"
    ],
    "name:fil_x_preferred":[
        "Masisi"
    ],
    "name:pol_x_preferred":[
        "Masisi"
    ],
    "name:ron_x_preferred":[
        "Masisi"
    ],
    "wof:name":"Masisi",
    "wof:placetype":"locality"
},
  "geometry": {"coordinates":[121.91576999999999,14.70319],"type":"Point"}
}