{
  "type": "Feature",
  "properties": {
    "gn:admin1_code":"03",
    "gn:admin2_code":"63",
    "gn:admin3_code":"36908000.0",
    "gn:asciiname":"Calabtangan",
    "gn:country_code":"PH",
    "gn:dem":67,
    "gn:feature_class":"P",
    "gn:feature_code":"PPL",
    "gn:name":"Calabtangan",
    "gn:population":0,
    "gn:timezone":"Asia/Manila",
    "iso:country":"PH",
    "wof:name":"Calabtangan",
    "wof:placetype":"locality"
},
  "geometry": {"coordinates":[120.39266000000001,15.6105],"type":"Point"}
}