{
  "type": "Feature",
  "properties": {
    "gn:admin1_code":"06",
    "gn:admin2_code":"04",
    "gn:admin3_code":"60408000.0",
    "gn:asciiname":"Tayhawan",
    "gn:country_code":"PH",
    "gn:dem":9,
    "gn:feature_class":"P",
    "gn:feature_code":"PPL",
    "gn:name":"Tayhawan",
    "gn:population":0,
    "gn:timezone":"Asia/Manila",
    "iso:country":"PH",
    "name:fil_x_preferred":[
        "Tayhawan"
    ],
    "wof:name":"Tayhawan",
    "wof:placetype":"locality"
},
  "geometry": {"coordinates":[122.33333,11.68333],"type":"Point"}
}