{
  "type": "Feature",
  "properties": {
    "gn:admin1_code":"07",
    "gn:admin2_code":"46",
    "gn:admin3_code":"74617000.0",
    "gn:asciiname":"Siapo",
    "gn:country_code":"PH",
    "gn:dem":202,
    "gn:feature_class":"P",
    "gn:feature_code":"PPL",
    "gn:name":"Siapo",
    "gn:population":0,
    "gn:timezone":"Asia/Manila",
    "iso:country":"PH",
    "name:fil_x_preferred":[
        "Siapo"
    ],
    "wof:name":"Siapo",
    "wof:placetype":"locality"
},
  "geometry": {"coordinates":[123.2032,9.4285],"type":"Point"}
}