{
  "type": "Feature",
  "properties": {
    "gn:country":"PH",
    "gn:fcode":"PPL",
    "gn:population":4301,
    "iso:country":"PH",
    "name:und_x_variant":[
        "Muzon"
    ],
    "qs:name":"Mozon",
    "qs:photos_9r":0,
    "qs:photos_sr":0,
    "qs:pop_sr":"4",
    "wof:name":"Mozon",
    "wof:placetype":"locality",
    "wof:population":4301
},
  "geometry": {"coordinates":[120.98934,13.8526],"type":"Point"}
}