{
  "type": "Feature",
  "properties": {
    "gn:admin1_code":"12",
    "gn:admin2_code":"57",
    "gn:admin3_code":"124709000.0",
    "gn:asciiname":"Langitan",
    "gn:country_code":"PH",
    "gn:dem":20,
    "gn:feature_class":"P",
    "gn:feature_code":"PPL",
    "gn:name":"Langitan",
    "gn:population":0,
    "gn:timezone":"Asia/Manila",
    "iso:country":"PH",
    "name:fil_x_preferred":[
        "Langitan"
    ],
    "wof:name":"Langitan",
    "wof:placetype":"locality"
},
  "geometry": {"coordinates":[124.53943999999998,7.15556],"type":"Point"}
}