{
  "type": "Feature",
  "properties": {
    "gn:admin1_code":"41",
    "gn:admin2_code":"54",
    "gn:admin3_code":"175906000.0",
    "gn:asciiname":"Ambolong",
    "gn:country_code":"PH",
    "gn:dem":9,
    "gn:feature_class":"P",
    "gn:feature_code":"PPL",
    "gn:name":"Ambolong",
    "gn:population":0,
    "gn:timezone":"Asia/Manila",
    "iso:country":"PH",
    "name:fil_x_preferred":[
        "Ambolong"
    ],
    "name:und_x_variant":[
        "Ambulong"
    ],
    "wof:name":"Ambolong",
    "wof:placetype":"locality"
},
  "geometry": {"coordinates":[122.05571999999999,12.78281],"type":"Point"}
}