{
  "type": "Feature",
  "properties": {
    "gn:admin1_code":"41",
    "gn:admin2_code":"54",
    "gn:admin3_code":"175902000.0",
    "gn:asciiname":"Nabalay",
    "gn:country_code":"PH",
    "gn:dem":128,
    "gn:feature_class":"P",
    "gn:feature_code":"PPL",
    "gn:name":"Nabalay",
    "gn:population":0,
    "gn:timezone":"Asia/Manila",
    "iso:country":"PH",
    "name:fil_x_preferred":[
        "Nabalay"
    ],
    "wof:name":"Nabalay",
    "wof:placetype":"locality"
},
  "geometry": {"coordinates":[122.07742,12.9593],"type":"Point"}
}