{
  "type": "Feature",
  "properties": {
    "gn:country":"PH",
    "gn:fcode":"PPL",
    "gn:pop":2362,
    "iso:country":"PH",
    "name:fil_x_preferred":[
        "Atabayan"
    ],
    "qs:name":"Atabayan",
    "qs:photos_9r":0,
    "qs:photos_sr":0,
    "qs:pop_sr":"4",
    "wof:name":"Atabayan",
    "wof:placetype":"locality",
    "wof:population":2362
},
  "geometry": {"coordinates":[122.41667,10.68333],"type":"Point"}
}