{
  "type": "Feature",
  "properties": {
    "gn:admin1_code":"06",
    "gn:admin2_code":"H3",
    "gn:admin3_code":"64523000.0",
    "gn:asciiname":"Tadlong",
    "gn:country_code":"PH",
    "gn:dem":56,
    "gn:feature_class":"P",
    "gn:feature_code":"PPL",
    "gn:name":"Tadlong",
    "gn:population":0,
    "gn:timezone":"Asia/Manila",
    "iso:country":"PH",
    "name:fil_x_preferred":[
        "Tadlong"
    ],
    "wof:name":"Tadlong",
    "wof:placetype":"locality"
},
  "geometry": {"coordinates":[123.3622,10.8612],"type":"Point"}
}