{
  "type": "Feature",
  "properties": {
    "gn:admin1_code":"03",
    "gn:admin2_code":"13",
    "gn:admin3_code":"31404000.0",
    "gn:asciiname":"Daungangpare",
    "gn:cc2":"PH",
    "gn:country_code":"PH",
    "gn:dem":13,
    "gn:feature_class":"P",
    "gn:feature_code":"PPL",
    "gn:name":"Daungangpare",
    "gn:population":0,
    "gn:timezone":"Asia/Manila",
    "iso:country":"PH",
    "name:und_x_variant":[
        "Daunganpari",
        "Daungangpare"
    ],
    "wof:name":"Daungangpare",
    "wof:placetype":"locality"
},
  "geometry": {"coordinates":[120.95,14.78333],"type":"Point"}
}