{
  "type": "Feature",
  "properties": {
    "gn:admin1_code":"02",
    "gn:admin2_code":"48",
    "gn:admin3_code":"25010000.0",
    "gn:asciiname":"Amilong",
    "gn:country_code":"PH",
    "gn:dem":1241,
    "gn:feature_class":"P",
    "gn:feature_code":"PPL",
    "gn:name":"Amilong",
    "gn:population":0,
    "gn:timezone":"Asia/Manila",
    "iso:country":"PH",
    "name:fil_x_preferred":[
        "Amilong"
    ],
    "wof:name":"Amilong",
    "wof:placetype":"locality"
},
  "geometry": {"coordinates":[120.88333,16.33333],"type":"Point"}
}