{
  "type": "Feature",
  "properties": {
    "gn:admin1_code":"02",
    "gn:admin2_code":"31",
    "gn:admin3_code":"23127000.0",
    "gn:asciiname":"Quinalabaza",
    "gn:country_code":"PH",
    "gn:dem":124,
    "gn:feature_class":"P",
    "gn:feature_code":"PPL",
    "gn:name":"Quinalabaza",
    "gn:population":0,
    "gn:timezone":"Asia/Manila",
    "iso:country":"PH",
    "name:fil_x_preferred":[
        "Quinalabaza"
    ],
    "wof:name":"Quinalabaza",
    "wof:placetype":"locality"
},
  "geometry": {"coordinates":[121.76667,16.48333],"type":"Point"}
}