{
  "type": "Feature",
  "properties": {
    "gn:admin1_code":"06",
    "gn:admin2_code":"18",
    "gn:admin3_code":"61901000.0",
    "gn:asciiname":"Bitoon",
    "gn:country_code":"PH",
    "gn:dem":20,
    "gn:feature_class":"P",
    "gn:feature_code":"PPL",
    "gn:name":"Bitoon",
    "gn:population":0,
    "gn:timezone":"Asia/Manila",
    "iso:country":"PH",
    "name:fil_x_preferred":[
        "Bitoon"
    ],
    "wof:name":"Bitoon",
    "wof:placetype":"locality"
},
  "geometry": {"coordinates":[122.6681,11.3233],"type":"Point"}
}