{
  "type": "Feature",
  "properties": {
    "gn:admin1_code":"01",
    "gn:admin2_code":"36",
    "gn:admin3_code":"13318000.0",
    "gn:asciiname":"Guilong",
    "gn:country_code":"PH",
    "gn:dem":52,
    "gn:feature_class":"P",
    "gn:feature_code":"PPL",
    "gn:name":"Guilong",
    "gn:population":0,
    "gn:timezone":"Asia/Manila",
    "iso:country":"PH",
    "name:fil_x_preferred":[
        "Guilong"
    ],
    "wof:name":"Guilong",
    "wof:placetype":"locality"
},
  "geometry": {"coordinates":[120.45489999999999,16.7911],"type":"Point"}
}