{
  "type": "Feature",
  "properties": {
    "gn:admin1_code":"01",
    "gn:admin2_code":"29",
    "gn:admin3_code":"12924000.0",
    "gn:asciiname":"Turod",
    "gn:country_code":"PH",
    "gn:dem":11,
    "gn:feature_class":"P",
    "gn:feature_code":"PPL",
    "gn:name":"Turod",
    "gn:population":0,
    "gn:timezone":"Asia/Manila",
    "iso:country":"PH",
    "name:und_x_variant":[
        "Torod",
        "Turod"
    ],
    "wof:name":"Turod",
    "wof:placetype":"locality"
},
  "geometry": {"coordinates":[120.46043,17.06552000000001],"type":"Point"}
}