{
  "type": "Feature",
  "properties": {
    "gn:admin1_code":"40",
    "gn:admin2_code":"33",
    "gn:admin3_code":"43426000.0",
    "gn:asciiname":"Palasa",
    "gn:country_code":"PH",
    "gn:dem":16,
    "gn:feature_class":"P",
    "gn:feature_code":"PPL",
    "gn:name":"Palasa",
    "gn:population":0,
    "gn:timezone":"Asia/Manila",
    "iso:country":"PH",
    "name:bpy_x_preferred":[
        "\u09aa\u09be\u09b2\u09be\u09b8\u09be"
    ],
    "name:fil_x_preferred":[
        "Palasa"
    ],
    "name:ita_x_preferred":[
        "Palasa-Kasibugga"
    ],
    "name:mlg_x_preferred":[
        "Palasa"
    ],
    "name:msa_x_preferred":[
        "Palasa"
    ],
    "name:new_x_preferred":[
        "\u092a\u0932\u093e\u0938 \u092e\u0923\u094d\u0921\u0932"
    ],
    "name:nld_x_preferred":[
        "Palasa-Kasibugga"
    ],
    "name:por_x_preferred":[
        "Palasa-Kasibugga"
    ],
    "name:tel_x_preferred":[
        "\u0c2a\u0c32\u0c3e\u0c38"
    ],
    "name:urd_x_preferred":[
        "\u067e\u0627\u0644\u0627\u0633\u0627"
    ],
    "name:vie_x_preferred":[
        "Palasa"
    ],
    "wof:name":"Palasa",
    "wof:placetype":"locality"
},
  "geometry": {"coordinates":[121.408,14.2547],"type":"Point"}
}