{
  "type": "Feature",
  "properties": {
    "gn:country":"PH",
    "gn:fcode":"PPL",
    "gn:population":4267,
    "iso:country":"PH",
    "name:bcl_x_preferred":[
        "Cabugao"
    ],
    "name:ceb_x_preferred":[
        "Cabugao"
    ],
    "name:deu_x_preferred":[
        "Cabugao"
    ],
    "name:fra_x_preferred":[
        "Cabugao"
    ],
    "name:ilo_x_preferred":[
        "Cabugao"
    ],
    "name:ind_x_preferred":[
        "Cabugao"
    ],
    "name:ita_x_preferred":[
        "Cabugao"
    ],
    "name:nld_x_preferred":[
        "Cabugao"
    ],
    "name:pag_x_preferred":[
        "Cabugao"
    ],
    "name:pam_x_preferred":[
        "Cabugao"
    ],
    "name:spa_x_preferred":[
        "Cabugao"
    ],
    "name:swe_x_preferred":[
        "Cabugao"
    ],
    "name:tgl_x_preferred":[
        "Cabugao"
    ],
    "name:und_x_variant":[
        "Cabugao Lucena"
    ],
    "name:vie_x_preferred":[
        "Cabugao"
    ],
    "name:war_x_preferred":[
        "Cabugao"
    ],
    "qs_pg:aaroncc":"PH",
    "qs_pg:gn_country":"PH",
    "qs_pg:gn_fcode":"PPL",
    "qs_pg:gn_pop":4267,
    "qs_pg:name":"Cabugao",
    "qs_pg:photos_9r":0,
    "qs_pg:photos_sr":0,
    "qs_pg:pop_sr":4,
    "qs_pg:qs_pg_placetype":"locality",
    "wof:name":"Cabugao",
    "wof:placetype":"locality",
    "wof:population":4267
},
  "geometry": {"coordinates":[122.54472,10.81028],"type":"Point"}
}