{
  "type": "Feature",
  "properties": {
    "gn:gn_country":"PH",
    "gn:gn_fcode":"PPL",
    "gn:gn_pop":4267,
    "gn:population":4267,
    "iso:country":"PH",
    "name:unk_x_variant":[
        "Cabugao Lucena"
    ],
    "qs_pg:aaroncc":"PH",
    "qs_pg:gn_country":"PH",
    "qs_pg:gn_fcode":"PPL",
    "qs_pg:gn_pop":4267,
    "qs_pg:name":"Cabugao",
    "qs_pg:photos_9r":0,
    "qs_pg:photos_sr":0,
    "qs_pg:pop_sr":4,
    "qs_pg:qs_pg_placetype":"locality",
    "wof:name":"Cabugao",
    "wof:placetype":"locality",
    "wof:population":4267
},
  "geometry": {"coordinates":[122.54472,10.81028],"type":"Point"}
}