{
  "type": "Feature",
  "properties": {
    "gn:admin1_code":"15",
    "gn:admin2_code":"32",
    "gn:admin3_code":"143213000.0",
    "gn:asciiname":"Agulusuanan",
    "gn:country_code":"PH",
    "gn:dem":130,
    "gn:feature_class":"P",
    "gn:feature_code":"PPL",
    "gn:name":"Agulusuanan",
    "gn:population":0,
    "gn:timezone":"Asia/Manila",
    "iso:country":"PH",
    "name:fil_x_preferred":[
        "Agalusuanan"
    ],
    "name:fil_x_variant":[
        "Agalusanan",
        "Agulusuanan"
    ],
    "name:und_x_variant":[
        "Agalusanan",
        "Agalusuanan"
    ],
    "wof:name":"Agulusuanan",
    "wof:placetype":"locality"
},
  "geometry": {"coordinates":[121.47,17.4945],"type":"Point"}
}