{
  "type": "Feature",
  "properties": {
    "gn:admin1_code":"40",
    "gn:admin2_code":"09",
    "gn:admin3_code":"41017000.0",
    "gn:asciiname":"Bagong Pook",
    "gn:country_code":"PH",
    "gn:dem":217,
    "gn:feature_class":"P",
    "gn:feature_code":"PPL",
    "gn:name":"Bagong Pook",
    "gn:population":0,
    "gn:timezone":"Asia/Manila",
    "iso:country":"PH",
    "name:fil_x_preferred":[
        "Bagong Pook"
    ],
    "wof:name":"Bagong Pook",
    "wof:placetype":"locality"
},
  "geometry": {"coordinates":[121.17231,14.04438],"type":"Point"}
}