{
  "type": "Feature",
  "properties": {
    "gn:admin1_code":"06",
    "gn:admin2_code":"H3",
    "gn:admin3_code":"64515000.0",
    "gn:asciiname":"Calumpang",
    "gn:country_code":"PH",
    "gn:dem":172,
    "gn:feature_class":"P",
    "gn:feature_code":"PPL",
    "gn:name":"Calumpang",
    "gn:population":0,
    "gn:timezone":"Asia/Manila",
    "iso:country":"PH",
    "name:ceb_x_preferred":[
        "Calumpang"
    ],
    "name:fil_x_preferred":[
        "Calumpang"
    ],
    "wof:name":"Calumpang",
    "wof:placetype":"locality"
},
  "geometry": {"coordinates":[122.7769,9.9357],"type":"Point"}
}