{
  "type": "Feature",
  "properties": {
    "gn:admin1_code":"40",
    "gn:admin2_code":"53",
    "gn:admin3_code":"45809000.0",
    "gn:asciiname":"Neojon",
    "gn:country_code":"PH",
    "gn:dem":14,
    "gn:feature_class":"P",
    "gn:feature_code":"PPL",
    "gn:name":"Neojon",
    "gn:population":0,
    "gn:timezone":"Asia/Manila",
    "iso:country":"PH",
    "name:fil_x_preferred":[
        "Neojon"
    ],
    "wof:name":"Neojon",
    "wof:placetype":"locality"
},
  "geometry": {"coordinates":[121.24339999999999,14.52028],"type":"Point"}
}