{
  "type": "Feature",
  "properties": {
    "gn:country":"PH",
    "gn:fcode":"ADM3",
    "gn:pop":34480,
    "iso:country":"PH",
    "name:fil_x_preferred":[
        "Aritao"
    ],
    "qs:name":"Aritao",
    "qs:photos_9r":0,
    "qs:photos_sr":0,
    "qs:pop_sr":"7",
    "wd:wordcount":420,
    "wof:name":"Aritao",
    "wof:placetype":"localadmin",
    "wof:population":34480
},
  "geometry": {"coordinates":[121.01667,16.26667],"type":"Point"}
}