{
  "type": "Feature",
  "properties": {
    "gn:country":"PH",
    "gn:fcode":"ADM3",
    "gn:pop":34480,
    "iso:country":"PH",
    "name:bcl_x_preferred":[
        "Aritao"
    ],
    "name:cat_x_preferred":[
        "Aritao"
    ],
    "name:ceb_x_preferred":[
        "Aritao"
    ],
    "name:deu_x_preferred":[
        "Aritao"
    ],
    "name:eng_x_preferred":[
        "Aritao"
    ],
    "name:fil_x_preferred":[
        "Aritao"
    ],
    "name:fra_x_preferred":[
        "Aritao"
    ],
    "name:ilo_x_preferred":[
        "Aritao"
    ],
    "name:ind_x_preferred":[
        "Aritao"
    ],
    "name:ita_x_preferred":[
        "Aritao"
    ],
    "name:jpn_x_preferred":[
        "\u30a2\u30ea\u30bf\u30aa"
    ],
    "name:nld_x_preferred":[
        "Aritao"
    ],
    "name:oci_x_preferred":[
        "Aritao"
    ],
    "name:pag_x_preferred":[
        "Aritao"
    ],
    "name:pam_x_preferred":[
        "Aritao"
    ],
    "name:spa_x_preferred":[
        "Aritao"
    ],
    "name:swe_x_preferred":[
        "Aritao"
    ],
    "name:tgl_x_preferred":[
        "Aritao"
    ],
    "name:vie_x_preferred":[
        "Aritao"
    ],
    "name:war_x_preferred":[
        "Aritao"
    ],
    "qs:name":"Aritao",
    "qs:photos_9r":0,
    "qs:photos_sr":0,
    "qs:pop_sr":"7",
    "wd:wordcount":420,
    "wof:name":"Aritao",
    "wof:placetype":"localadmin",
    "wof:population":34480
},
  "geometry": {"coordinates":[121.01667,16.26667],"type":"Point"}
}