{
  "type": "Feature",
  "properties": {
    "gn:admin1_code":"07",
    "gn:admin2_code":"21",
    "gn:admin3_code":"72218000.0",
    "gn:asciiname":"Baliang",
    "gn:country_code":"PH",
    "gn:dem":318,
    "gn:feature_class":"P",
    "gn:feature_code":"PPL",
    "gn:name":"Baliang",
    "gn:population":0,
    "gn:timezone":"Asia/Manila",
    "iso:country":"PH",
    "name:fil_x_preferred":[
        "Baliang"
    ],
    "wof:name":"Baliang",
    "wof:placetype":"locality"
},
  "geometry": {"coordinates":[123.96083,10.495],"type":"Point"}
}