{
  "type": "Feature",
  "properties": {
    "gn:admin1_code":"10",
    "gn:admin2_code":"43",
    "gn:admin3_code":"104306000.0",
    "gn:asciiname":"Guma-od",
    "gn:country_code":"PH",
    "gn:dem":389,
    "gn:feature_class":"P",
    "gn:feature_code":"PPL",
    "gn:name":"Guma-od",
    "gn:population":0,
    "gn:timezone":"Asia/Manila",
    "iso:country":"PH",
    "name:fil_x_preferred":[
        "Guma-od"
    ],
    "wof:name":"Guma-od",
    "wof:placetype":"locality"
},
  "geometry": {"coordinates":[124.8175,8.64889],"type":"Point"}
}