{
  "type": "Feature",
  "properties": {
    "gn:admin1_code":"40",
    "gn:admin2_code":"H2",
    "gn:admin3_code":"45601000.0",
    "gn:asciiname":"Kinagunan Ilaya",
    "gn:country_code":"PH",
    "gn:dem":16,
    "gn:feature_class":"P",
    "gn:feature_code":"PPL",
    "gn:name":"Kinagunan Ilaya",
    "gn:population":0,
    "gn:timezone":"Asia/Manila",
    "iso:country":"PH",
    "name:fil_x_preferred":[
        "Kinagunan Ilaya"
    ],
    "name:fil_x_variant":[
        "Ilayang Kinagunan"
    ],
    "name:und_x_variant":[
        "Quinagunan",
        "Kinagunan"
    ],
    "wof:name":"Kinagunan Ilaya",
    "wof:placetype":"locality"
},
  "geometry": {"coordinates":[121.91056,13.89247],"type":"Point"}
}