{
  "type": "Feature",
  "properties": {
    "iso:country":"PH",
    "name:ceb_x_preferred":[
        "Bantayan"
    ],
    "name:deu_x_preferred":[
        "Bantayan"
    ],
    "name:fil_x_preferred":[
        "Bantayan"
    ],
    "name:ind_x_preferred":[
        "Bantayan"
    ],
    "name:nld_x_preferred":[
        "Bantayan"
    ],
    "name:tgl_x_preferred":[
        "Bantayan"
    ],
    "qs:gn_country":"PH",
    "qs:gn_fcode":"PPL",
    "qs:gn_pop":3976,
    "qs:name":"Bantayan",
    "qs:name_adm0":"Philippines",
    "qs:name_adm1":"Eastern Visayas",
    "qs:photos":0,
    "qs:photos_1k":0,
    "qs:photos_9k":1,
    "qs:photos_9r":1,
    "qs:photos_all":1,
    "qs:photos_sr":0,
    "qs:placetype":"Town",
    "qs:pop_sr":"4",
    "qs:woe_adm0":23424934,
    "wd:wordcount":66,
    "wof:name":"Bantayan",
    "wof:placetype":"locality",
    "wof:population":3976
},
  "geometry": {"coordinates":[124.8283,12.5237],"type":"Point"}
}