{
  "type": "Feature",
  "properties": {
    "gn:admin1_code":"14",
    "gn:admin2_code":"60",
    "gn:asciiname":"Mangas",
    "gn:country_code":"PH",
    "gn:dem":0,
    "gn:feature_class":"P",
    "gn:feature_code":"PPL",
    "gn:name":"Mangas",
    "gn:population":0,
    "gn:timezone":"Asia/Manila",
    "iso:country":"PH",
    "name:eng_x_preferred":[
        "Mangas"
    ],
    "wof:name":"Mangas",
    "wof:placetype":"locality"
},
  "geometry": {"coordinates":[120.9631,6.1043],"type":"Point"}
}