{
  "type": "Feature",
  "properties": {
    "gn:gn_country":"PH",
    "gn:gn_fcode":"ADM3",
    "gn:gn_pop":7652,
    "gn:population":7652,
    "iso:country":"PH",
    "name:fil_x_preferred":[
        "Bumbaran"
    ],
    "qs_pg:aaroncc":"PH",
    "qs_pg:gn_country":"PH",
    "qs_pg:gn_fcode":"ADM3",
    "qs_pg:gn_pop":7652,
    "qs_pg:name":"Bumbaran",
    "qs_pg:photos_9r":0,
    "qs_pg:photos_sr":0,
    "qs_pg:pop_sr":5,
    "qs_pg:qs_pg_placetype":"localadmin",
    "wof:name":"Bumbaran",
    "wof:placetype":"localadmin",
    "wof:population":7652
},
  "geometry": {"coordinates":[124.63333,7.75],"type":"Point"}
}