{
  "type": "Feature",
  "properties": {
    "gn:admin1_code":"08",
    "gn:admin2_code":"59",
    "gn:asciiname":"Naslo",
    "gn:country_code":"PH",
    "gn:dem":111,
    "gn:feature_class":"P",
    "gn:feature_code":"PPL",
    "gn:name":"Naslo",
    "gn:population":0,
    "gn:timezone":"Asia/Manila",
    "iso:country":"PH",
    "name:fil_x_preferred":[
        "Naslo"
    ],
    "wof:name":"Naslo",
    "wof:placetype":"locality"
},
  "geometry": {"coordinates":[122.4405,10.8745],"type":"Point"}
}