{
  "type": "Feature",
  "properties": {
    "gn:gn_country":"PH",
    "gn:gn_fcode":"PPL",
    "gn:gn_pop":2231,
    "gn:population":2231,
    "iso:country":"PH",
    "name:fil_x_preferred":[
        "Manaulanan"
    ],
    "qs_pg:aaroncc":"PH",
    "qs_pg:gn_country":"PH",
    "qs_pg:gn_fcode":"PPL",
    "qs_pg:gn_pop":2231,
    "qs_pg:name":"Manaulanan",
    "qs_pg:photos_9r":0,
    "qs_pg:photos_sr":0,
    "qs_pg:pop_sr":4,
    "qs_pg:qs_pg_placetype":"locality",
    "wof:name":"Manaulanan",
    "wof:placetype":"locality",
    "wof:population":2231
},
  "geometry": {"coordinates":[124.61944,7.04806],"type":"Point"}
}