{
  "type": "Feature",
  "properties": {
    "gn:admin1_code":"40",
    "gn:admin2_code":"H2",
    "gn:admin3_code":"45620000.0",
    "gn:asciiname":"Kawagin",
    "gn:country_code":"PH",
    "gn:dem":3,
    "gn:feature_class":"P",
    "gn:feature_code":"PPL",
    "gn:name":"Kawagin",
    "gn:population":0,
    "gn:timezone":"Asia/Manila",
    "iso:country":"PH",
    "name:fil_x_preferred":[
        "Kawagin"
    ],
    "wof:name":"Kawagin",
    "wof:placetype":"locality"
},
  "geometry": {"coordinates":[121.66667,14.71667],"type":"Point"}
}