{
  "type": "Feature",
  "properties": {
    "gn:admin1_code":"05",
    "gn:admin2_code":"16",
    "gn:admin3_code":"51713000.0",
    "gn:asciiname":"Cabunga",
    "gn:country_code":"PH",
    "gn:dem":6,
    "gn:feature_class":"P",
    "gn:feature_code":"PPL",
    "gn:name":"Cabunga",
    "gn:population":0,
    "gn:timezone":"Asia/Manila",
    "iso:country":"PH",
    "name:fil_x_preferred":[
        "Cabunga"
    ],
    "name:und_x_variant":[
        "Cabugao"
    ],
    "wof:name":"Cabunga",
    "wof:placetype":"locality"
},
  "geometry": {"coordinates":[123.1546,13.6166],"type":"Point"}
}