{
  "type": "Feature",
  "properties": {
    "gn:admin1_code":"12",
    "gn:admin2_code":"57",
    "gn:admin3_code":"124709000.0",
    "gn:asciiname":"Atin",
    "gn:cc2":"PH",
    "gn:country_code":"PH",
    "gn:dem":122,
    "gn:feature_class":"P",
    "gn:feature_code":"PPL",
    "gn:name":"Atin",
    "gn:population":0,
    "gn:timezone":"Asia/Manila",
    "iso:country":"PH",
    "name:und_x_variant":[
        "Atio",
        "Atin"
    ],
    "wof:name":"Atin",
    "wof:placetype":"locality"
},
  "geometry": {"coordinates":[124.59972,7.26028],"type":"Point"}
}