{
  "type": "Feature",
  "properties": {
    "gn:admin1_code":"07",
    "gn:admin2_code":"11",
    "gn:admin3_code":"71230000.0",
    "gn:asciiname":"Nagtuang",
    "gn:country_code":"PH",
    "gn:dem":179,
    "gn:feature_class":"P",
    "gn:feature_code":"PPL",
    "gn:name":"Nagtuang",
    "gn:population":0,
    "gn:timezone":"Asia/Manila",
    "iso:country":"PH",
    "name:fil_x_preferred":[
        "Nagtuang"
    ],
    "wof:name":"Nagtuang",
    "wof:placetype":"locality"
},
  "geometry": {"coordinates":[123.8552,9.7992],"type":"Point"}
}