{
  "type": "Feature",
  "properties": {
    "gn:admin1_code":"03",
    "gn:admin2_code":"50",
    "gn:admin3_code":"35401000.0",
    "gn:asciiname":"Mining",
    "gn:country_code":"PH",
    "gn:dem":88,
    "gn:feature_class":"P",
    "gn:feature_code":"PPL",
    "gn:name":"Mining",
    "gn:population":0,
    "gn:timezone":"Asia/Manila",
    "iso:country":"PH",
    "wof:name":"Mining",
    "wof:placetype":"locality"
},
  "geometry": {"coordinates":[120.59999999999999,15.15],"type":"Point"}
}