{
  "type": "Feature",
  "properties": {
    "gn:admin1_code":"06",
    "gn:admin2_code":"H3",
    "gn:admin3_code":"64520000.0",
    "gn:asciiname":"Pitogo",
    "gn:country_code":"PH",
    "gn:dem":183,
    "gn:feature_class":"P",
    "gn:feature_code":"PPL",
    "gn:name":"Pitogo",
    "gn:population":0,
    "gn:timezone":"Asia/Manila",
    "iso:country":"PH",
    "name:ceb_x_preferred":[
        "Pitogo"
    ],
    "name:deu_x_preferred":[
        "Pitogo"
    ],
    "name:fil_x_preferred":[
        "Pitogo"
    ],
    "name:ita_x_preferred":[
        "Pitogo"
    ],
    "name:nld_x_preferred":[
        "Pitogo"
    ],
    "name:und_x_variant":[
        "Pitogo Hacienda"
    ],
    "name:war_x_preferred":[
        "Pitogo"
    ],
    "wof:name":"Pitogo",
    "wof:placetype":"locality"
},
  "geometry": {"coordinates":[123.06059999999999,10.63126],"type":"Point"}
}