{
  "type": "Feature",
  "properties": {
    "gn:admin1_code":"08",
    "gn:admin2_code":"55",
    "gn:admin3_code":"86001000.0",
    "gn:asciiname":"Marasbaras",
    "gn:country_code":"PH",
    "gn:dem":25,
    "gn:feature_class":"P",
    "gn:feature_code":"PPL",
    "gn:name":"Marasbaras",
    "gn:population":0,
    "gn:timezone":"Asia/Manila",
    "iso:country":"PH",
    "name:fil_x_preferred":[
        "Marasbaras"
    ],
    "wof:name":"Marasbaras",
    "wof:placetype":"locality"
},
  "geometry": {"coordinates":[124.3325,11.9512],"type":"Point"}
}