{
  "type": "Feature",
  "properties": {
    "gn:country":"PH",
    "gn:fcode":"ADM3",
    "gn:pop":20845,
    "iso:country":"PH",
    "qs:name":"Dapa",
    "qs:photos_9r":0,
    "qs:photos_sr":0,
    "qs:pop_sr":"7",
    "wd:wordcount":53,
    "wof:name":"Dapa",
    "wof:placetype":"localadmin",
    "wof:population":20845
},
  "geometry": {"coordinates":[126.05,9.76667],"type":"Point"}
}