{
  "type": "Feature",
  "properties": {
    "gn:gn_country":"PH",
    "gn:gn_fcode":"PPLA3",
    "gn:gn_pop":4395,
    "gn:population":4395,
    "iso:country":"PH",
    "name:bcl_x_preferred":[
        "Uson"
    ],
    "name:ceb_x_preferred":[
        "Uson"
    ],
    "name:deu_x_preferred":[
        "Uson"
    ],
    "name:eng_x_preferred":[
        "Uson"
    ],
    "name:fas_x_preferred":[
        "\u0622\u0633\u0648\u0646\u060c \u0645\u0627\u0633\u0628\u0627\u062a\u0647"
    ],
    "name:fas_x_variant":[
        "\u0622\u0633\u0648\u0646"
    ],
    "name:fil_x_preferred":[
        "Uson"
    ],
    "name:fra_x_preferred":[
        "Uson"
    ],
    "name:ilo_x_preferred":[
        "Uson"
    ],
    "name:ind_x_preferred":[
        "Uson"
    ],
    "name:ita_x_preferred":[
        "Uson"
    ],
    "name:nld_x_preferred":[
        "Uson"
    ],
    "name:pag_x_preferred":[
        "Uson"
    ],
    "name:pam_x_preferred":[
        "Uson"
    ],
    "name:swe_x_preferred":[
        "Uson"
    ],
    "name:tgl_x_preferred":[
        "Uson"
    ],
    "name:vie_x_preferred":[
        "Uson"
    ],
    "name:war_x_preferred":[
        "Uson"
    ],
    "qs_pg:aaroncc":"PH",
    "qs_pg:gn_country":"PH",
    "qs_pg:gn_fcode":"PPLA3",
    "qs_pg:gn_pop":4395,
    "qs_pg:name":"Uson",
    "qs_pg:photos_9r":0,
    "qs_pg:photos_sr":0,
    "qs_pg:pop_sr":4,
    "qs_pg:qs_pg_placetype":"locality",
    "wof:name":"Uson",
    "wof:placetype":"locality",
    "wof:population":4395
},
  "geometry": {"coordinates":[123.7834,12.2253],"type":"Point"}
}