{
  "type": "Feature",
  "properties": {
    "gn:admin1_code":"NCR",
    "gn:admin2_code":"137400000",
    "gn:admin3_code":"137404000.0",
    "gn:asciiname":"Culiat",
    "gn:country_code":"PH",
    "gn:dem":52,
    "gn:feature_class":"P",
    "gn:feature_code":"PPL",
    "gn:name":"Culiat",
    "gn:population":0,
    "gn:timezone":"Asia/Manila",
    "iso:country":"PH",
    "name:fil_x_preferred":[
        "Culiat"
    ],
    "name:fil_x_variant":[
        "Kuliat"
    ],
    "wof:name":"Culiat",
    "wof:placetype":"locality"
},
  "geometry": {"coordinates":[121.05268,14.67012],"type":"Point"}
}