{
  "type": "Feature",
  "properties": {
    "gn:admin1_code":"01",
    "gn:admin2_code":"51",
    "gn:admin3_code":"15542000.0",
    "gn:asciiname":"Baybay Sur",
    "gn:country_code":"PH",
    "gn:dem":20,
    "gn:feature_class":"P",
    "gn:feature_code":"PPL",
    "gn:name":"Baybay Sur",
    "gn:population":0,
    "gn:timezone":"Asia/Manila",
    "iso:country":"PH",
    "name:fil_x_preferred":[
        "Baybay Sur"
    ],
    "wof:name":"Baybay Sur",
    "wof:placetype":"locality"
},
  "geometry": {"coordinates":[120.08091,16.14878],"type":"Point"}
}