{
  "type": "Feature",
  "properties": {
    "gn:admin1_code":"40",
    "gn:admin2_code":"53",
    "gn:admin3_code":"45804000.0",
    "gn:asciiname":"Mabato",
    "gn:country_code":"PH",
    "gn:dem":48,
    "gn:feature_class":"P",
    "gn:feature_code":"PPL",
    "gn:name":"Mabato",
    "gn:population":0,
    "gn:timezone":"Asia/Manila",
    "iso:country":"PH",
    "name:fil_x_preferred":[
        "Mabato"
    ],
    "wof:name":"Mabato",
    "wof:placetype":"locality"
},
  "geometry": {"coordinates":[121.18810000000001,14.5003],"type":"Point"}
}