{
  "type": "Feature",
  "properties": {
    "gn:admin1_code":"03",
    "gn:admin2_code":"13",
    "gn:admin3_code":"31405000.0",
    "gn:asciiname":"Bambang",
    "gn:country_code":"PH",
    "gn:dem":7,
    "gn:feature_class":"P",
    "gn:feature_code":"PPL",
    "gn:name":"Bambang",
    "gn:population":0,
    "gn:timezone":"Asia/Manila",
    "iso:country":"PH",
    "name:ceb_x_preferred":[
        "Bambang"
    ],
    "name:fil_x_preferred":[
        "Bambang"
    ],
    "name:ind_x_preferred":[
        "Bambang"
    ],
    "name:nld_x_preferred":[
        "Bambang"
    ],
    "name:rus_x_preferred":[
        "\u0411\u0430\u043c\u0431\u0430\u043d\u0433"
    ],
    "name:swe_x_preferred":[
        "Bambang"
    ],
    "wof:name":"Bambang",
    "wof:placetype":"locality"
},
  "geometry": {"coordinates":[120.87875,14.78008],"type":"Point"}
}