{
  "type": "Feature",
  "properties": {
    "gn:admin1_code":"08",
    "gn:admin2_code":"67",
    "gn:admin3_code":"84814000.0",
    "gn:asciiname":"Cubi",
    "gn:country_code":"PH",
    "gn:dem":10,
    "gn:feature_class":"P",
    "gn:feature_code":"PPL",
    "gn:name":"Cubi",
    "gn:population":0,
    "gn:timezone":"Asia/Manila",
    "iso:country":"PH",
    "name:fil_x_preferred":[
        "Cubi"
    ],
    "wof:name":"Cubi",
    "wof:placetype":"locality"
},
  "geometry": {"coordinates":[125.10550000000001,12.5292],"type":"Point"}
}