{
  "type": "Feature",
  "properties": {
    "gn:admin1_code":"05",
    "gn:admin2_code":"39",
    "gn:admin3_code":"54101000.0",
    "gn:asciiname":"Loca",
    "gn:country_code":"PH",
    "gn:dem":23,
    "gn:feature_class":"P",
    "gn:feature_code":"PPL",
    "gn:name":"Loca",
    "gn:population":0,
    "gn:timezone":"Asia/Manila",
    "iso:country":"PH",
    "name:fil_x_preferred":[
        "Loca"
    ],
    "wof:name":"Loca",
    "wof:placetype":"locality"
},
  "geometry": {"coordinates":[123.30589999999999,12.5756],"type":"Point"}
}