{
  "type": "Feature",
  "properties": {
    "gn:admin1_code":"40",
    "gn:admin2_code":"20",
    "gn:admin3_code":"42102000.0",
    "gn:asciiname":"Maitim",
    "gn:country_code":"PH",
    "gn:dem":530,
    "gn:feature_class":"P",
    "gn:feature_code":"PPL",
    "gn:name":"Maitim",
    "gn:population":0,
    "gn:timezone":"Asia/Manila",
    "iso:country":"PH",
    "name:und_x_variant":[
        "Maytim",
        "Maitim Primero",
        "Maitim"
    ],
    "wof:name":"Maitim",
    "wof:placetype":"locality"
},
  "geometry": {"coordinates":[120.95047,14.14457],"type":"Point"}
}