{
  "type": "Feature",
  "properties": {
    "gn:admin1_code":"08",
    "gn:admin2_code":"37",
    "gn:admin3_code":"83714000.0",
    "gn:asciiname":"Colasian",
    "gn:cc2":"PH",
    "gn:country_code":"PH",
    "gn:dem":58,
    "gn:feature_class":"P",
    "gn:feature_code":"PPL",
    "gn:name":"Colasian",
    "gn:population":0,
    "gn:timezone":"Asia/Manila",
    "iso:country":"PH",
    "name:und_x_variant":[
        "Cotasian",
        "Colasian"
    ],
    "wof:name":"Colasian",
    "wof:placetype":"locality"
},
  "geometry": {"coordinates":[124.63527999999999,11.28417],"type":"Point"}
}