{
  "type": "Feature",
  "properties": {
    "gn:admin1_code":"13",
    "gn:admin2_code":"I9",
    "gn:admin3_code":"168502000.0",
    "gn:asciiname":"Guadaloupe",
    "gn:country_code":"PH",
    "gn:dem":10,
    "gn:feature_class":"P",
    "gn:feature_code":"PPL",
    "gn:name":"Guadaloupe",
    "gn:population":0,
    "gn:timezone":"Asia/Manila",
    "iso:country":"PH",
    "name:fil_x_preferred":[
        "Guadaloupe"
    ],
    "wof:name":"Guadaloupe",
    "wof:placetype":"locality"
},
  "geometry": {"coordinates":[125.66079999999999,10.1191],"type":"Point"}
}