{
  "type": "Feature",
  "properties": {
    "gn:country":"PH",
    "gn:fcode":"PPL",
    "gn:population":3724,
    "iso:country":"PH",
    "name:fil_x_preferred":[
        "Tinoto"
    ],
    "name:und_x_variant":[
        "Tinto"
    ],
    "qs:name":"Tinoto",
    "qs:photos_9r":0,
    "qs:photos_sr":0,
    "qs:pop_sr":"4",
    "wof:name":"Tinoto",
    "wof:placetype":"locality",
    "wof:population":3724
},
  "geometry": {"coordinates":[125.07056,5.88667],"type":"Point"}
}