{
  "type": "Feature",
  "properties": {
    "gn:admin1_code":"41",
    "gn:admin2_code":"38",
    "gn:admin3_code":"174006000.0",
    "gn:asciiname":"Tawang",
    "gn:country_code":"PH",
    "gn:dem":184,
    "gn:feature_class":"P",
    "gn:feature_code":"PPL",
    "gn:name":"Tawang",
    "gn:population":0,
    "gn:timezone":"Asia/Manila",
    "iso:country":"PH",
    "name:ara_x_preferred":[
        "\u062a\u0627\u0648\u0627\u0646\u062c"
    ],
    "name:asm_x_preferred":[
        "\u099f\u09be\u09f1\u09be\u0982"
    ],
    "name:ben_x_preferred":[
        "\u09a4\u0993\u09af\u09bc\u09be\u0982"
    ],
    "name:bpy_x_preferred":[
        "\u09a4\u09be\u0993\u09af\u09bc\u09be\u0982"
    ],
    "name:ceb_x_preferred":[
        "Tawang"
    ],
    "name:deu_x_preferred":[
        "Tawang"
    ],
    "name:fas_x_preferred":[
        "\u062a\u0627\u0648\u0627\u0646\u06af"
    ],
    "name:fil_x_preferred":[
        "Tawang"
    ],
    "name:fra_x_preferred":[
        "Tawang"
    ],
    "name:guj_x_preferred":[
        "\u0aa4\u0ab5\u0abe\u0a82\u0a97"
    ],
    "name:hin_x_preferred":[
        "\u0924\u0935\u093e\u0902\u0917"
    ],
    "name:ind_x_preferred":[
        "Tawang"
    ],
    "name:ita_x_preferred":[
        "Tawang"
    ],
    "name:lit_x_preferred":[
        "Tavangas"
    ],
    "name:mar_x_preferred":[
        "\u0924\u0935\u093e\u0902\u0917"
    ],
    "name:msa_x_preferred":[
        "Tawang"
    ],
    "name:nld_x_preferred":[
        "Tawang"
    ],
    "name:ori_x_preferred":[
        "\u0b24\u0b71\u0b3e\u0b19\u0b4d\u0b17"
    ],
    "name:pol_x_preferred":[
        "Tawang"
    ],
    "name:rus_x_preferred":[
        "\u0422\u0430\u0432\u0430\u043d\u0433"
    ],
    "name:spa_x_preferred":[
        "Tawang"
    ],
    "name:swe_x_preferred":[
        "Tawang"
    ],
    "name:tam_x_preferred":[
        "\u0b9f\u0bb5\u0bbe\u0b99\u0bcd \u0ba8\u0b95\u0bb0\u0bae\u0bcd"
    ],
    "name:urd_x_preferred":[
        "\u0679\u0648\u0627\u0646\u06af"
    ],
    "name:vie_x_preferred":[
        "Tawang"
    ],
    "name:zho_x_preferred":[
        "\u8fbe\u65fa\u9547"
    ],
    "wof:name":"Tawang",
    "wof:placetype":"locality"
},
  "geometry": {"coordinates":[122.04649999999999,13.3752],"type":"Point"}
}