{
  "type": "Feature",
  "properties": {
    "gn:admin1_code":"41",
    "gn:admin2_code":"38",
    "gn:admin3_code":"174006000.0",
    "gn:asciiname":"Tawang",
    "gn:country_code":"PH",
    "gn:dem":184,
    "gn:feature_class":"P",
    "gn:feature_code":"PPL",
    "gn:name":"Tawang",
    "gn:population":0,
    "gn:timezone":"Asia/Manila",
    "iso:country":"PH",
    "name:fil_x_preferred":[
        "Tawang"
    ],
    "wof:name":"Tawang",
    "wof:placetype":"locality"
},
  "geometry": {"coordinates":[122.04649999999999,13.3752],"type":"Point"}
}