{
  "type": "Feature",
  "properties": {
    "gn:admin1_code":"06",
    "gn:admin2_code":"04",
    "gn:admin3_code":"60407000.0",
    "gn:asciiname":"Tigayon",
    "gn:country_code":"PH",
    "gn:dem":13,
    "gn:feature_class":"P",
    "gn:feature_code":"PPL",
    "gn:name":"Tigayon",
    "gn:population":0,
    "gn:timezone":"Asia/Manila",
    "iso:country":"PH",
    "name:fil_x_preferred":[
        "Tigayon"
    ],
    "wof:name":"Tigayon",
    "wof:placetype":"locality"
},
  "geometry": {"coordinates":[122.36190000000001,11.6732],"type":"Point"}
}