{
  "type": "Feature",
  "properties": {
    "gn:admin1_code":"40",
    "gn:admin2_code":"H2",
    "gn:admin3_code":"45645000.0",
    "gn:asciiname":"Guisguis-San Roque",
    "gn:country_code":"PH",
    "gn:dem":6,
    "gn:feature_class":"P",
    "gn:feature_code":"PPL",
    "gn:name":"Guisguis-San Roque",
    "gn:population":0,
    "gn:timezone":"Asia/Manila",
    "iso:country":"PH",
    "name:und_x_variant":[
        "Gisgis"
    ],
    "wof:name":"Guisguis-San Roque",
    "wof:placetype":"locality"
},
  "geometry": {"coordinates":[121.49995,13.85749],"type":"Point"}
}