{
  "type": "Feature",
  "properties": {
    "gn:admin1_code":"11",
    "gn:admin2_code":"I6",
    "gn:admin3_code":"118210000.0",
    "gn:asciiname":"Katalogan",
    "gn:cc2":"PH",
    "gn:country_code":"PH",
    "gn:dem":106,
    "gn:feature_class":"P",
    "gn:feature_code":"PPL",
    "gn:name":"Katalogan",
    "gn:population":0,
    "gn:timezone":"Asia/Manila",
    "iso:country":"PH",
    "name:und_x_variant":[
        "Ketalogan",
        "Katalogan"
    ],
    "wof:name":"Katalogan",
    "wof:placetype":"locality"
},
  "geometry": {"coordinates":[126.12194,7.60528],"type":"Point"}
}