{
  "type": "Feature",
  "properties": {
    "gn:admin1_code":"05",
    "gn:admin2_code":"05",
    "gn:admin3_code":"50503000.0",
    "gn:asciiname":"Gapo",
    "gn:country_code":"PH",
    "gn:dem":112,
    "gn:feature_class":"P",
    "gn:feature_code":"PPL",
    "gn:name":"Gapo",
    "gn:population":0,
    "gn:timezone":"Asia/Manila",
    "iso:country":"PH",
    "name:fil_x_preferred":[
        "Gapo"
    ],
    "wof:name":"Gapo",
    "wof:placetype":"locality"
},
  "geometry": {"coordinates":[123.6842,13.1378],"type":"Point"}
}