{
  "type": "Feature",
  "properties": {
    "gn:admin1_code":"06",
    "gn:admin2_code":"30",
    "gn:admin3_code":"63042000.0",
    "gn:asciiname":"Cabasan",
    "gn:country_code":"PH",
    "gn:dem":104,
    "gn:feature_class":"P",
    "gn:feature_code":"PPL",
    "gn:name":"Cabasan",
    "gn:population":0,
    "gn:timezone":"Asia/Manila",
    "iso:country":"PH",
    "name:fil_x_preferred":[
        "Cabasan"
    ],
    "wof:name":"Cabasan",
    "wof:placetype":"locality"
},
  "geometry": {"coordinates":[122.78278,11.15806],"type":"Point"}
}