{
  "type": "Feature",
  "properties": {
    "gn:admin1_code":"41",
    "gn:admin2_code":"49",
    "gn:admin3_code":"175313000.0",
    "gn:asciiname":"Dicabaito",
    "gn:country_code":"PH",
    "gn:dem":28,
    "gn:feature_class":"P",
    "gn:feature_code":"PPL",
    "gn:name":"Dicabaito",
    "gn:population":0,
    "gn:timezone":"Asia/Manila",
    "iso:country":"PH",
    "name:eng_x_preferred":[
        "Dicabaito"
    ],
    "name:und_x_variant":[
        "Decabaitot"
    ],
    "wof:name":"Dicabaito",
    "wof:placetype":"locality"
},
  "geometry": {"coordinates":[119.9619,11.6482],"type":"Point"}
}