{
  "type": "Feature",
  "properties": {
    "gn:admin1_code":"10",
    "gn:admin2_code":"42",
    "gn:admin3_code":"104208000.0",
    "gn:asciiname":"Mansabay",
    "gn:country_code":"PH",
    "gn:dem":6,
    "gn:feature_class":"P",
    "gn:feature_code":"PPL",
    "gn:name":"Mansabay",
    "gn:population":0,
    "gn:timezone":"Asia/Manila",
    "iso:country":"PH",
    "name:eng_x_preferred":[
        "Mansabay"
    ],
    "wof:name":"Mansabay",
    "wof:placetype":"locality"
},
  "geometry": {"coordinates":[123.7739,8.5258],"type":"Point"}
}