{
  "type": "Feature",
  "properties": {
    "gn:gn_country":"PH",
    "gn:gn_fcode":"ADM3",
    "gn:gn_pop":229064,
    "gn:population":229064,
    "iso:country":"PH",
    "name:unk_x_variant":[
        "Lucena"
    ],
    "qs_pg:aaroncc":"PH",
    "qs_pg:gn_country":"PH",
    "qs_pg:gn_fcode":"ADM3",
    "qs_pg:gn_pop":229064,
    "qs_pg:name":"Lucena City",
    "qs_pg:photos_9r":0,
    "qs_pg:photos_sr":0,
    "qs_pg:pop_sr":10,
    "qs_pg:qs_pg_placetype":"localadmin",
    "wof:name":"Lucena City",
    "wof:placetype":"localadmin",
    "wof:population":229064
},
  "geometry": {"coordinates":[121.61667,13.93333],"type":"Point"}
}