{
  "type": "Feature",
  "properties": {
    "gn:admin1_code":"14",
    "gn:admin2_code":"56",
    "gn:asciiname":"Matenguen",
    "gn:cc2":"PH",
    "gn:country_code":"PH",
    "gn:dem":77,
    "gn:feature_class":"P",
    "gn:feature_code":"PPL",
    "gn:name":"Mate\u00f1guen",
    "gn:population":0,
    "gn:timezone":"Asia/Manila",
    "iso:country":"PH",
    "name:und_x_variant":[
        "Matengen",
        "Matenquen",
        "Mate\u00f1guen"
    ],
    "wof:name":"Matenguen",
    "wof:placetype":"locality"
},
  "geometry": {"coordinates":[124.38139,7.29639],"type":"Point"}
}