{
  "type": "Feature",
  "properties": {
    "gn:admin1_code":"02",
    "gn:admin2_code":"14",
    "gn:admin3_code":"21506000.0",
    "gn:asciiname":"Bagunot",
    "gn:country_code":"PH",
    "gn:dem":25,
    "gn:feature_class":"P",
    "gn:feature_code":"PPL",
    "gn:name":"Bagunot",
    "gn:population":0,
    "gn:timezone":"Asia/Manila",
    "iso:country":"PH",
    "name:fil_x_preferred":[
        "Bagunut"
    ],
    "name:fil_x_variant":[
        "Bagunot"
    ],
    "wof:name":"Bagunot",
    "wof:placetype":"locality"
},
  "geometry": {"coordinates":[121.78107,17.93921],"type":"Point"}
}