{
  "type": "Feature",
  "properties": {
    "gn:admin1_code":"02",
    "gn:admin2_code":"14",
    "gn:admin3_code":"21503000.0",
    "gn:asciiname":"Dagupan",
    "gn:country_code":"PH",
    "gn:dem":15,
    "gn:feature_class":"P",
    "gn:feature_code":"PPL",
    "gn:name":"Dagupan",
    "gn:population":0,
    "gn:timezone":"Asia/Manila",
    "iso:country":"PH",
    "name:ara_x_preferred":[
        "\u062f\u0627\u063a\u0648\u0628\u0627\u0646"
    ],
    "name:bcl_x_preferred":[
        "Dagupan"
    ],
    "name:ceb_x_preferred":[
        "Dagupan"
    ],
    "name:deu_x_preferred":[
        "Dagupan"
    ],
    "name:fil_x_preferred":[
        "Dagupan"
    ],
    "name:fra_x_preferred":[
        "Dagupan"
    ],
    "name:ilo_x_preferred":[
        "Dagupan"
    ],
    "name:ind_x_preferred":[
        "Dagupan"
    ],
    "name:ita_x_preferred":[
        "Dagupan"
    ],
    "name:kor_x_preferred":[
        "\ub2e4\uad6c\ud310"
    ],
    "name:lit_x_preferred":[
        "Dagupanas"
    ],
    "name:msa_x_preferred":[
        "Dagupan"
    ],
    "name:nld_x_preferred":[
        "Dagupan"
    ],
    "name:nor_x_preferred":[
        "Dagupan City"
    ],
    "name:pam_x_preferred":[
        "Dagupan"
    ],
    "name:pol_x_preferred":[
        "Dagupan"
    ],
    "name:spa_x_preferred":[
        "Dagup\u00e1n"
    ],
    "name:swe_x_preferred":[
        "Dagupan City"
    ],
    "name:tgl_x_preferred":[
        "Dagupan"
    ],
    "name:urd_x_preferred":[
        "\u062f\u0627\u06af\u0648\u067e\u0627\u0646"
    ],
    "name:war_x_preferred":[
        "Dagupan"
    ],
    "wof:name":"Dagupan",
    "wof:placetype":"locality"
},
  "geometry": {"coordinates":[121.55455000000001,18.21098],"type":"Point"}
}