{
  "type": "Feature",
  "properties": {
    "gn:admin1_code":"11",
    "gn:admin2_code":"I7",
    "gn:admin3_code":"112315000.0",
    "gn:asciiname":"Pandaitan",
    "gn:country_code":"PH",
    "gn:dem":42,
    "gn:feature_class":"P",
    "gn:feature_code":"PPL",
    "gn:name":"Pandaitan",
    "gn:population":0,
    "gn:timezone":"Asia/Manila",
    "iso:country":"PH",
    "name:fil_x_preferred":[
        "Pandaitan"
    ],
    "wof:name":"Pandaitan",
    "wof:placetype":"locality"
},
  "geometry": {"coordinates":[125.56917,7.41444],"type":"Point"}
}