{
  "type": "Feature",
  "properties": {
    "iso:country":"PH",
    "name:bcl_x_preferred":[
        "Taal"
    ],
    "name:cat_x_preferred":[
        "Taal"
    ],
    "name:cbk_zam_x_preferred":[
        "Taal"
    ],
    "name:ceb_x_preferred":[
        "Taal"
    ],
    "name:deu_x_preferred":[
        "Taal"
    ],
    "name:eng_x_preferred":[
        "Taal"
    ],
    "name:fra_x_preferred":[
        "Taal"
    ],
    "name:ilo_x_preferred":[
        "Taal"
    ],
    "name:ind_x_preferred":[
        "Taal"
    ],
    "name:ita_x_preferred":[
        "Taal"
    ],
    "name:jpn_x_preferred":[
        "\u30bf\u30fc\u30eb"
    ],
    "name:nld_x_preferred":[
        "Taal"
    ],
    "name:oci_x_preferred":[
        "Taal"
    ],
    "name:pag_x_preferred":[
        "Taal"
    ],
    "name:pam_x_preferred":[
        "Taal"
    ],
    "name:pol_x_preferred":[
        "Taal"
    ],
    "name:rus_x_preferred":[
        "\u0422\u0430\u0430\u043b"
    ],
    "name:spa_x_preferred":[
        "Taal"
    ],
    "name:swe_x_preferred":[
        "Taal"
    ],
    "name:tgl_x_preferred":[
        "Taal"
    ],
    "name:vie_x_preferred":[
        "Taal"
    ],
    "name:war_x_preferred":[
        "Taal"
    ],
    "qs:gn_country":"PH",
    "qs:gn_fcode":"PPLA3",
    "qs:gn_pop":39745,
    "qs:name":"Taal",
    "qs:name_adm0":"Philippines",
    "qs:name_adm1":"Calabarzon",
    "qs:photos":641,
    "qs:photos_1k":130,
    "qs:photos_9k":3,
    "qs:photos_9r":5,
    "qs:photos_all":641,
    "qs:photos_sr":8,
    "qs:placetype":"Town",
    "qs:pop_sr":"7",
    "qs:woe_adm0":23424934,
    "wd:wordcount":1190,
    "wof:name":"Taal",
    "wof:placetype":"locality",
    "wof:population":39745
},
  "geometry": {"coordinates":[120.92310999999999,13.87992],"type":"Point"}
}