{
  "type": "Feature",
  "properties": {
    "gn:admin1_code":"40",
    "gn:admin2_code":"H2",
    "gn:admin3_code":"45619000.0",
    "gn:asciiname":"Mahabang Bundoc",
    "gn:country_code":"PH",
    "gn:dem":64,
    "gn:feature_class":"P",
    "gn:feature_code":"PPL",
    "gn:name":"Mahabang Bundoc",
    "gn:population":0,
    "gn:timezone":"Asia/Manila",
    "iso:country":"PH",
    "name:fil_x_preferred":[
        "Mahabang Bundoc"
    ],
    "wof:name":"Mahabang Bundoc",
    "wof:placetype":"locality"
},
  "geometry": {"coordinates":[122.06667,13.88333],"type":"Point"}
}