{
  "type": "Feature",
  "properties": {
    "gn:admin1_code":"10",
    "gn:admin2_code":"43",
    "gn:admin3_code":"104322000.0",
    "gn:asciiname":"Ampinikan",
    "gn:cc2":"PH",
    "gn:country_code":"PH",
    "gn:dem":33,
    "gn:feature_class":"P",
    "gn:feature_code":"PPL",
    "gn:name":"Ampinikan",
    "gn:population":0,
    "gn:timezone":"Asia/Manila",
    "iso:country":"PH",
    "name:und_x_variant":[
        "Ampenican",
        "Ampinikan"
    ],
    "wof:name":"Ampinikan",
    "wof:placetype":"locality"
},
  "geometry": {"coordinates":[124.78694,8.89861],"type":"Point"}
}