{
  "type": "Feature",
  "properties": {
    "gn:admin1_code":"07",
    "gn:admin2_code":"11",
    "gn:admin3_code":"71207000.0",
    "gn:asciiname":"Cantigdas",
    "gn:country_code":"PH",
    "gn:dem":316,
    "gn:feature_class":"P",
    "gn:feature_code":"PPL",
    "gn:name":"Cantigdas",
    "gn:population":0,
    "gn:timezone":"Asia/Manila",
    "iso:country":"PH",
    "name:fil_x_preferred":[
        "Cantigdas"
    ],
    "wof:name":"Cantigdas",
    "wof:placetype":"locality"
},
  "geometry": {"coordinates":[124.1323,9.7854],"type":"Point"}
}