{
  "type": "Feature",
  "properties": {
    "gn:admin1_code":"08",
    "gn:admin2_code":"37",
    "gn:admin3_code":"83740000.0",
    "gn:asciiname":"Santiago",
    "gn:country_code":"PH",
    "gn:dem":61,
    "gn:feature_class":"P",
    "gn:feature_code":"PPL",
    "gn:name":"Santiago",
    "gn:population":0,
    "gn:timezone":"Asia/Manila",
    "iso:country":"PH",
    "name:fil_x_preferred":[
        "Santiago"
    ],
    "wof:name":"Santiago",
    "wof:placetype":"locality"
},
  "geometry": {"coordinates":[124.44070000000001,11.0665],"type":"Point"}
}