{
  "type": "Feature",
  "properties": {
    "gn:admin1_code":"07",
    "gn:admin2_code":"11",
    "gn:admin3_code":"71220000.0",
    "gn:asciiname":"Tawid",
    "gn:country_code":"PH",
    "gn:dem":60,
    "gn:elevation":"0.0",
    "gn:feature_class":"P",
    "gn:feature_code":"PPL",
    "gn:name":"Tawid",
    "gn:population":0,
    "gn:timezone":"Asia/Manila",
    "iso:country":"PH",
    "name:fil_x_preferred":[
        "Tawid"
    ],
    "wof:name":"Tawid",
    "wof:placetype":"locality"
},
  "geometry": {"coordinates":[124.17435,9.6211],"type":"Point"}
}