{
  "type": "Feature",
  "properties": {
    "gn:country":"PH",
    "gn:fcode":"PPL",
    "gn:pop":2780,
    "iso:country":"PH",
    "name:fil_x_preferred":[
        "Canan"
    ],
    "name:unk_x_variant":[
        "Canan"
    ],
    "qs:name":"Canan Norte",
    "qs:photos_9r":0,
    "qs:photos_sr":0,
    "qs:pop_sr":"4",
    "wof:name":"Canan Norte",
    "wof:placetype":"locality",
    "wof:population":2780
},
  "geometry": {"coordinates":[120.47763,15.90986],"type":"Point"}
}