{
  "type": "Feature",
  "properties": {
    "gn:admin1_code":"12",
    "gn:admin2_code":"B8",
    "gn:asciiname":"Lugaylugay",
    "gn:cc2":"PH",
    "gn:country_code":"PH",
    "gn:dem":1,
    "gn:feature_class":"P",
    "gn:feature_code":"PPL",
    "gn:name":"Lugaylugay",
    "gn:population":0,
    "gn:timezone":"Asia/Manila",
    "iso:country":"PH",
    "name:und_x_variant":[
        "Lugaylugan"
    ],
    "wof:name":"Lugaylugay",
    "wof:placetype":"locality"
},
  "geometry": {"coordinates":[124.21666999999999,7.25],"type":"Point"}
}