{
  "type": "Feature",
  "properties": {
    "gn:admin1_code":"07",
    "gn:admin2_code":"21",
    "gn:admin3_code":"72205000.0",
    "gn:asciiname":"Ubaub",
    "gn:country_code":"PH",
    "gn:dem":533,
    "gn:feature_class":"P",
    "gn:feature_code":"PPL",
    "gn:name":"Ubaub",
    "gn:population":0,
    "gn:timezone":"Asia/Manila",
    "iso:country":"PH",
    "name:und_x_variant":[
        "Ubaob",
        "Ubaub",
        "Uba-ub"
    ],
    "wof:name":"Ubaub",
    "wof:placetype":"locality"
},
  "geometry": {"coordinates":[123.54828999999999,9.9425],"type":"Point"}
}