{
  "type": "Feature",
  "properties": {
    "gn:admin1_code":"03",
    "gn:admin2_code":"13",
    "gn:admin3_code":"31416000.0",
    "gn:asciiname":"San Isidro Dos",
    "gn:country_code":"PH",
    "gn:dem":7,
    "gn:feature_class":"P",
    "gn:feature_code":"PPL",
    "gn:name":"San Isidro Dos",
    "gn:population":0,
    "gn:timezone":"Asia/Manila",
    "iso:country":"PH",
    "name:und_x_variant":[
        "San Isidro II"
    ],
    "wof:name":"San Isidro Dos",
    "wof:placetype":"locality"
},
  "geometry": {"coordinates":[120.77157,14.83601],"type":"Point"}
}