{
  "type": "Feature",
  "properties": {
    "gn:admin1_code":"15",
    "gn:admin2_code":"10",
    "gn:admin3_code":"141101000.0",
    "gn:asciiname":"Namegpagan",
    "gn:country_code":"PH",
    "gn:dem":2058,
    "gn:feature_class":"P",
    "gn:feature_code":"PPL",
    "gn:name":"Namegpagan",
    "gn:population":0,
    "gn:timezone":"Asia/Manila",
    "iso:country":"PH",
    "name:fil_x_preferred":[
        "Namegpagan"
    ],
    "wof:name":"Namegpagan",
    "wof:placetype":"locality"
},
  "geometry": {"coordinates":[120.77234,16.61838],"type":"Point"}
}