{
  "type": "Feature",
  "properties": {
    "gn:admin1_code":"01",
    "gn:admin2_code":"36",
    "gn:admin3_code":"13319000.0",
    "gn:asciiname":"Namaltogan",
    "gn:country_code":"PH",
    "gn:dem":73,
    "gn:feature_class":"P",
    "gn:feature_code":"PPL",
    "gn:name":"Namaltogan",
    "gn:population":0,
    "gn:timezone":"Asia/Manila",
    "iso:country":"PH",
    "name:fil_x_preferred":[
        "Namaltogan"
    ],
    "wof:name":"Namaltogan",
    "wof:placetype":"locality"
},
  "geometry": {"coordinates":[120.5033,16.9024],"type":"Point"}
}