{
  "type": "Feature",
  "properties": {
    "gn:admin1_code":"11",
    "gn:admin2_code":"I7",
    "gn:admin3_code":"112315000.0",
    "gn:asciiname":"Kaganjuan",
    "gn:cc2":"PH",
    "gn:country_code":"PH",
    "gn:dem":6,
    "gn:feature_class":"P",
    "gn:feature_code":"PPL",
    "gn:name":"Kaganjuan",
    "gn:population":0,
    "gn:timezone":"Asia/Manila",
    "iso:country":"PH",
    "name:und_x_variant":[
        "Caga\u00f1gohan",
        "Kaganjuan"
    ],
    "wof:name":"Kaganjuan",
    "wof:placetype":"locality"
},
  "geometry": {"coordinates":[125.68361000000002,7.27833],"type":"Point"}
}