{
  "type": "Feature",
  "properties": {
    "gn:admin1_code":"03",
    "gn:admin2_code":"50",
    "gn:admin3_code":"35413000.0",
    "gn:asciiname":"Dalisdis",
    "gn:country_code":"PH",
    "gn:dem":37,
    "gn:feature_class":"P",
    "gn:feature_code":"PPL",
    "gn:name":"Dalisdis",
    "gn:population":0,
    "gn:timezone":"Asia/Manila",
    "iso:country":"PH",
    "name:fil_x_preferred":[
        "Dalisdis"
    ],
    "wof:name":"Dalisdis",
    "wof:placetype":"locality"
},
  "geometry": {"coordinates":[120.6675,15.1106],"type":"Point"}
}