{
  "type": "Feature",
  "properties": {
    "iso:country":"PH",
    "qs:gn_pop":0,
    "qs:name":"Dakak",
    "qs:name_adm0":"Philippines",
    "qs:name_adm1":"Zamboanga Peninsula",
    "qs:photos":132,
    "qs:photos_1k":27,
    "qs:photos_9k":1,
    "qs:photos_9r":3,
    "qs:photos_all":132,
    "qs:photos_sr":3,
    "qs:placetype":"Town",
    "qs:pop_sr":"0",
    "qs:woe_adm0":23424934,
    "wof:name":"Dakak",
    "wof:placetype":"locality"
},
  "geometry": {"coordinates":[123.397064,8.707286],"type":"Point"}
}