{
  "type": "Feature",
  "properties": {
    "gn:admin1_code":"40",
    "gn:admin2_code":"09",
    "gn:admin3_code":"41009000.0",
    "gn:asciiname":"Ibabao",
    "gn:country_code":"PH",
    "gn:dem":21,
    "gn:feature_class":"P",
    "gn:feature_code":"PPL",
    "gn:name":"Ibabao",
    "gn:population":0,
    "gn:timezone":"Asia/Manila",
    "iso:country":"PH",
    "name:fil_x_preferred":[
        "Ibabao"
    ],
    "wof:name":"Ibabao",
    "wof:placetype":"locality"
},
  "geometry": {"coordinates":[121.0338,13.9085],"type":"Point"}
}