{
  "type": "Feature",
  "properties": {
    "gn:admin1_code":"05",
    "gn:admin2_code":"39",
    "gn:admin3_code":"54117000.0",
    "gn:asciiname":"Matubinao",
    "gn:country_code":"PH",
    "gn:dem":20,
    "gn:feature_class":"P",
    "gn:feature_code":"PPL",
    "gn:name":"Matubinao",
    "gn:population":0,
    "gn:timezone":"Asia/Manila",
    "iso:country":"PH",
    "name:fil_x_preferred":[
        "Matubinao"
    ],
    "name:und_x_variant":[
        "Matubina"
    ],
    "wof:name":"Matubinao",
    "wof:placetype":"locality"
},
  "geometry": {"coordinates":[123.8749,11.9724],"type":"Point"}
}