{
  "type": "Feature",
  "properties": {
    "gn:admin1_code":"14",
    "gn:admin2_code":"72",
    "gn:admin3_code":"157006000.0",
    "gn:asciiname":"South Ubian",
    "gn:country_code":"PH",
    "gn:dem":7,
    "gn:feature_class":"P",
    "gn:feature_code":"PPL",
    "gn:name":"South Ubian",
    "gn:population":0,
    "gn:timezone":"Asia/Manila",
    "iso:country":"PH",
    "name:eng_x_preferred":[
        "South Ubian"
    ],
    "name:und_x_variant":[
        "Ubian Timbang"
    ],
    "wof:name":"South Ubian",
    "wof:placetype":"locality"
},
  "geometry": {"coordinates":[120.49809999999999,5.1861],"type":"Point"}
}