{
  "type": "Feature",
  "properties": {
    "gn:admin1_code":"14",
    "gn:admin2_code":"72",
    "gn:admin3_code":"157006000.0",
    "gn:asciiname":"South Ubian",
    "gn:country_code":"PH",
    "gn:dem":7,
    "gn:feature_class":"P",
    "gn:feature_code":"PPL",
    "gn:name":"South Ubian",
    "gn:population":0,
    "gn:timezone":"Asia/Manila",
    "iso:country":"PH",
    "name:bcl_x_preferred":[
        "South Ubian"
    ],
    "name:ceb_x_preferred":[
        "Habagatang Ubian"
    ],
    "name:deu_x_preferred":[
        "S\u00fcdubian"
    ],
    "name:eng_x_preferred":[
        "South Ubian"
    ],
    "name:fra_x_preferred":[
        "South Ubian"
    ],
    "name:ilo_x_preferred":[
        "Abagatan nga Ubian"
    ],
    "name:ind_x_preferred":[
        "Ubian Selatan"
    ],
    "name:ita_x_preferred":[
        "South Ubian"
    ],
    "name:nld_x_preferred":[
        "South Ubian"
    ],
    "name:pag_x_preferred":[
        "South Ubian"
    ],
    "name:pam_x_preferred":[
        "Mauling Ubian"
    ],
    "name:swe_x_preferred":[
        "South Ubian"
    ],
    "name:tgl_x_preferred":[
        "Timog Ubian"
    ],
    "name:und_x_variant":[
        "Ubian Timbang"
    ],
    "name:urd_x_preferred":[
        "\u062c\u0646\u0648\u0628\u06cc \u0627\u0648\u0628\u06cc\u0627\u0646"
    ],
    "name:vie_x_preferred":[
        "South Ubian"
    ],
    "name:war_x_preferred":[
        "South Ubian"
    ],
    "wof:name":"South Ubian",
    "wof:placetype":"locality"
},
  "geometry": {"coordinates":[120.49809999999999,5.1861],"type":"Point"}
}