{
  "type": "Feature",
  "properties": {
    "gn:admin1_code":"03",
    "gn:admin2_code":"47",
    "gn:admin3_code":"34901000.0",
    "gn:asciiname":"Poblacion Centro",
    "gn:country_code":"PH",
    "gn:dem":27,
    "gn:feature_class":"P",
    "gn:feature_code":"PPL",
    "gn:name":"Poblacion Centro",
    "gn:population":0,
    "gn:timezone":"Asia/Manila",
    "iso:country":"PH",
    "name:und_x_variant":[
        "Poblacion Central"
    ],
    "wof:name":"Poblacion Centro",
    "wof:placetype":"locality"
},
  "geometry": {"coordinates":[120.8524,15.50059],"type":"Point"}
}