{
  "type": "Feature",
  "properties": {
    "gn:admin1_code":"02",
    "gn:admin2_code":"31",
    "gn:admin3_code":"23112000.0",
    "gn:asciiname":"Babaran",
    "gn:country_code":"PH",
    "gn:dem":97,
    "gn:feature_class":"P",
    "gn:feature_code":"PPL",
    "gn:name":"Babaran",
    "gn:population":0,
    "gn:timezone":"Asia/Manila",
    "iso:country":"PH",
    "name:fil_x_preferred":[
        "Babaran"
    ],
    "wof:name":"Babaran",
    "wof:placetype":"locality"
},
  "geometry": {"coordinates":[121.7201,16.67743],"type":"Point"}
}