{
  "type": "Feature",
  "properties": {
    "gn:admin1_code":"06",
    "gn:admin2_code":"30",
    "gn:admin3_code":"63027000.0",
    "gn:asciiname":"Herongan",
    "gn:country_code":"PH",
    "gn:dem":86,
    "gn:feature_class":"P",
    "gn:feature_code":"PPL",
    "gn:name":"Herongan",
    "gn:population":0,
    "gn:timezone":"Asia/Manila",
    "iso:country":"PH",
    "name:fil_x_preferred":[
        "Herongan"
    ],
    "wof:name":"Herongan",
    "wof:placetype":"locality"
},
  "geometry": {"coordinates":[122.88420000000001,11.1967],"type":"Point"}
}