{
  "type": "Feature",
  "properties": {
    "gn:country":"PH",
    "gn:fcode":"PPL",
    "gn:population":3353,
    "iso:country":"PH",
    "name:fil_x_preferred":[
        "Mapalad"
    ],
    "qs:name":"Mapalad",
    "qs:photos_9r":0,
    "qs:photos_sr":0,
    "qs:pop_sr":"4",
    "wof:name":"Mapalad",
    "wof:placetype":"locality",
    "wof:population":3353
},
  "geometry": {"coordinates":[121.08384,15.45133],"type":"Point"}
}