{
  "type": "Feature",
  "properties": {
    "gn:admin1_code":"03",
    "gn:admin2_code":"47",
    "gn:admin3_code":"34905000.0",
    "gn:asciiname":"Anabat",
    "gn:country_code":"PH",
    "gn:dem":371,
    "gn:feature_class":"P",
    "gn:feature_code":"PPL",
    "gn:name":"Anabat",
    "gn:population":0,
    "gn:timezone":"Asia/Manila",
    "iso:country":"PH",
    "name:fil_x_preferred":[
        "Anabat"
    ],
    "wof:name":"Anabat",
    "wof:placetype":"locality"
},
  "geometry": {"coordinates":[120.96259999999999,16.007],"type":"Point"}
}