{
  "type": "Feature",
  "properties": {
    "gn:country":"PH",
    "gn:fcode":"PPL",
    "gn:pop":2895,
    "iso:country":"PH",
    "name:fil_x_preferred":[
        "New Cebu"
    ],
    "qs:name":"New Cebu",
    "qs:photos_9r":0,
    "qs:photos_sr":0,
    "qs:pop_sr":"4",
    "wof:name":"New Cebu",
    "wof:placetype":"locality",
    "wof:population":2895
},
  "geometry": {"coordinates":[125.03361,7.09528],"type":"Point"}
}