{
  "type": "Feature",
  "properties": {
    "gn:admin1_code":"02",
    "gn:admin2_code":"14",
    "gn:admin3_code":"21527000.0",
    "gn:asciiname":"Palao",
    "gn:country_code":"PH",
    "gn:dem":61,
    "gn:feature_class":"P",
    "gn:feature_code":"PPL",
    "gn:name":"Palao",
    "gn:population":0,
    "gn:timezone":"Asia/Manila",
    "iso:country":"PH",
    "name:fil_x_preferred":[
        "Palao"
    ],
    "wof:name":"Palao",
    "wof:placetype":"locality"
},
  "geometry": {"coordinates":[121.58308999999998,17.56392],"type":"Point"}
}