{
  "type": "Feature",
  "properties": {
    "gn:admin1_code":"13",
    "gn:admin2_code":"61",
    "gn:admin3_code":"166714000.0",
    "gn:asciiname":"Mayag",
    "gn:country_code":"PH",
    "gn:dem":57,
    "gn:feature_class":"P",
    "gn:feature_code":"PPL",
    "gn:name":"Mayag",
    "gn:population":0,
    "gn:timezone":"Asia/Manila",
    "iso:country":"PH",
    "name:fil_x_preferred":[
        "Mayag"
    ],
    "wof:name":"Mayag",
    "wof:placetype":"locality"
},
  "geometry": {"coordinates":[125.47944,9.55306],"type":"Point"}
}