{
  "type": "Feature",
  "properties": {
    "gn:country":"PH",
    "gn:fcode":"PPLA3",
    "gn:pop":3306,
    "iso:country":"PH",
    "name:bcl_x_preferred":[
        "Alicia"
    ],
    "name:deu_x_preferred":[
        "Alicia"
    ],
    "name:eng_x_preferred":[
        "Alicia"
    ],
    "name:fas_x_preferred":[
        "\u0627\u0644\u06cc\u0633\u06cc\u0627\u060c \u0632\u0627\u0645\u0628\u0648\u0645\u06af\u0627 \u0633\u06cc\u0628\u0648\u06af\u0627\u06cc"
    ],
    "name:fra_x_preferred":[
        "Alicia"
    ],
    "name:ilo_x_preferred":[
        "Alicia"
    ],
    "name:ita_x_preferred":[
        "Alicia"
    ],
    "name:nld_x_preferred":[
        "Alicia"
    ],
    "name:pag_x_preferred":[
        "Alicia"
    ],
    "name:pam_x_preferred":[
        "Alicia"
    ],
    "name:spa_x_preferred":[
        "Alicia"
    ],
    "name:swe_x_preferred":[
        "Alicia"
    ],
    "name:tgl_x_preferred":[
        "Alicia"
    ],
    "name:unk_x_variant":[
        "Chinkang"
    ],
    "name:vie_x_preferred":[
        "Alicia"
    ],
    "name:war_x_preferred":[
        "Alicia"
    ],
    "qs:name":"Alicia",
    "qs:photos_9r":0,
    "qs:photos_sr":0,
    "qs:pop_sr":"4",
    "wd:wordcount":145,
    "wof:name":"Alicia",
    "wof:placetype":"locality",
    "wof:population":3306
},
  "geometry": {"coordinates":[122.93000000000001,7.51389],"type":"Point"}
}