{
  "type": "Feature",
  "properties": {
    "gn:admin1_code":"05",
    "gn:admin2_code":"05",
    "gn:admin3_code":"50510000.0",
    "gn:asciiname":"Tulu",
    "gn:country_code":"PH",
    "gn:dem":12,
    "gn:feature_class":"P",
    "gn:feature_code":"PPL",
    "gn:name":"Tulu",
    "gn:population":0,
    "gn:timezone":"Asia/Manila",
    "iso:country":"PH",
    "name:fil_x_preferred":[
        "Tulu"
    ],
    "wof:name":"Tulu",
    "wof:placetype":"locality"
},
  "geometry": {"coordinates":[123.68333,13.38333],"type":"Point"}
}