{
  "type": "Feature",
  "properties": {
    "gn:admin1_code":"03",
    "gn:admin2_code":"G8",
    "gn:admin3_code":"37707000.0",
    "gn:asciiname":"Florida",
    "gn:country_code":"PH",
    "gn:dem":31,
    "gn:feature_class":"P",
    "gn:feature_code":"PPL",
    "gn:name":"Florida",
    "gn:population":0,
    "gn:timezone":"Asia/Manila",
    "iso:country":"PH",
    "name:fil_x_preferred":[
        "Florida"
    ],
    "wof:name":"Florida",
    "wof:placetype":"locality"
},
  "geometry": {"coordinates":[121.4847,15.8024],"type":"Point"}
}