{
  "type": "Feature",
  "properties": {
    "gn:admin1_code":"07",
    "gn:admin2_code":"21",
    "gn:admin3_code":"72241000.0",
    "gn:asciiname":"Bugho",
    "gn:country_code":"PH",
    "gn:dem":294,
    "gn:feature_class":"P",
    "gn:feature_code":"PPL",
    "gn:name":"Bugho",
    "gn:population":0,
    "gn:timezone":"Asia/Manila",
    "iso:country":"PH",
    "name:fil_x_preferred":[
        "Bugho"
    ],
    "wof:name":"Bugho",
    "wof:placetype":"locality"
},
  "geometry": {"coordinates":[123.6739,10.19958],"type":"Point"}
}