{
  "type": "Feature",
  "properties": {
    "gn:admin1_code":"06",
    "gn:admin2_code":"06",
    "gn:admin3_code":"60618000.0",
    "gn:asciiname":"Bugnag",
    "gn:country_code":"PH",
    "gn:dem":137,
    "gn:feature_class":"P",
    "gn:feature_code":"PPL",
    "gn:name":"Bugnag",
    "gn:population":0,
    "gn:timezone":"Asia/Manila",
    "iso:country":"PH",
    "name:fil_x_preferred":[
        "Bugnag"
    ],
    "name:und_x_variant":[
        "Bugnay"
    ],
    "wof:name":"Bugnag",
    "wof:placetype":"locality"
},
  "geometry": {"coordinates":[122.08750000000001,10.9703],"type":"Point"}
}