{
  "type": "Feature",
  "properties": {
    "gn:admin1_code":"06",
    "gn:admin2_code":"H3",
    "gn:admin3_code":"64509000.0",
    "gn:asciiname":"Sagahan",
    "gn:country_code":"PH",
    "gn:dem":85,
    "gn:feature_class":"P",
    "gn:feature_code":"PPL",
    "gn:name":"Sagahan",
    "gn:population":0,
    "gn:timezone":"Asia/Manila",
    "iso:country":"PH",
    "name:fil_x_preferred":[
        "Sagahan"
    ],
    "wof:name":"Sagahan",
    "wof:placetype":"locality"
},
  "geometry": {"coordinates":[123.4534,10.75934],"type":"Point"}
}