{
  "type": "Feature",
  "properties": {
    "gn:admin1_code":"06",
    "gn:admin2_code":"30",
    "gn:admin3_code":"63009000.0",
    "gn:asciiname":"Banban",
    "gn:country_code":"PH",
    "gn:dem":8,
    "gn:feature_class":"P",
    "gn:feature_code":"PPL",
    "gn:name":"Banban",
    "gn:population":0,
    "gn:timezone":"Asia/Manila",
    "iso:country":"PH",
    "name:fil_x_preferred":[
        "Banban"
    ],
    "wof:name":"Banban",
    "wof:placetype":"locality"
},
  "geometry": {"coordinates":[123.1378,11.4096],"type":"Point"}
}