{
  "type": "Feature",
  "properties": {
    "gn:admin1_code":"15",
    "gn:admin2_code":"27",
    "gn:admin3_code":"142711000.0",
    "gn:asciiname":"Cawayan",
    "gn:country_code":"PH",
    "gn:dem":885,
    "gn:feature_class":"P",
    "gn:feature_code":"PPL",
    "gn:name":"Cawayan",
    "gn:population":0,
    "gn:timezone":"Asia/Manila",
    "iso:country":"PH",
    "name:fil_x_preferred":[
        "Cawayan"
    ],
    "wof:name":"Cawayan",
    "wof:placetype":"locality"
},
  "geometry": {"coordinates":[121.08454,16.63468],"type":"Point"}
}