{
  "type": "Feature",
  "properties": {
    "gn:admin1_code":"09",
    "gn:admin2_code":"66",
    "gn:admin3_code":"97307000.0",
    "gn:asciiname":"Tina",
    "gn:country_code":"PH",
    "gn:dem":38,
    "gn:feature_class":"P",
    "gn:feature_code":"PPL",
    "gn:name":"Tina",
    "gn:population":0,
    "gn:timezone":"Asia/Manila",
    "iso:country":"PH",
    "name:eng_x_preferred":[
        "Tina"
    ],
    "wof:name":"Tina",
    "wof:placetype":"locality"
},
  "geometry": {"coordinates":[123.41840000000001,7.7362],"type":"Point"}
}