{
  "type": "Feature",
  "properties": {
    "gn:admin1_code":"02",
    "gn:admin2_code":"31",
    "gn:admin3_code":"23108000.0",
    "gn:asciiname":"Marung",
    "gn:country_code":"PH",
    "gn:dem":36,
    "gn:feature_class":"P",
    "gn:feature_code":"PPL",
    "gn:name":"Marung",
    "gn:population":0,
    "gn:timezone":"Asia/Manila",
    "iso:country":"PH",
    "name:fil_x_preferred":[
        "Marung"
    ],
    "name:ukr_x_preferred":[
        "\u041c\u0430\u0440\u0443\u043d\u0433"
    ],
    "wof:name":"Marung",
    "wof:placetype":"locality"
},
  "geometry": {"coordinates":[121.78333000000001,16.95],"type":"Point"}
}