{
  "type": "Feature",
  "properties": {
    "gn:admin1_code":"10",
    "gn:admin2_code":"12",
    "gn:admin3_code":"101305000.0",
    "gn:asciiname":"Bontogon",
    "gn:country_code":"PH",
    "gn:dem":732,
    "gn:feature_class":"P",
    "gn:feature_code":"PPL",
    "gn:name":"Bontogon",
    "gn:population":0,
    "gn:timezone":"Asia/Manila",
    "iso:country":"PH",
    "name:fil_x_preferred":[
        "Bontogon"
    ],
    "name:und_x_variant":[
        "Buntugan",
        "Bontongon"
    ],
    "wof:name":"Bontogon",
    "wof:placetype":"locality"
},
  "geometry": {"coordinates":[125.10833,8.29833],"type":"Point"}
}