{
  "type": "Feature",
  "properties": {
    "gn:admin1_code":"03",
    "gn:admin2_code":"64",
    "gn:admin3_code":"37113000.0",
    "gn:asciiname":"Banlag",
    "gn:country_code":"PH",
    "gn:dem":16,
    "gn:feature_class":"P",
    "gn:feature_code":"PPL",
    "gn:name":"Banlag",
    "gn:population":0,
    "gn:timezone":"Asia/Manila",
    "iso:country":"PH",
    "name:fil_x_preferred":[
        "Banlag"
    ],
    "wof:name":"Banlag",
    "wof:placetype":"locality"
},
  "geometry": {"coordinates":[119.95399999999999,15.6977],"type":"Point"}
}