{
  "type": "Feature",
  "properties": {
    "gn:admin1_code":"05",
    "gn:admin2_code":"05",
    "gn:admin3_code":"50504000.0",
    "gn:asciiname":"Bamban",
    "gn:country_code":"PH",
    "gn:dem":237,
    "gn:feature_class":"P",
    "gn:feature_code":"PPL",
    "gn:name":"Bamban",
    "gn:population":0,
    "gn:timezone":"Asia/Manila",
    "iso:country":"PH",
    "name:fil_x_preferred":[
        "Bamban"
    ],
    "wof:name":"Bamban",
    "wof:placetype":"locality"
},
  "geometry": {"coordinates":[123.58333,13.16667],"type":"Point"}
}