{
  "type": "Feature",
  "properties": {
    "gn:admin1_code":"07",
    "gn:admin2_code":"46",
    "gn:admin3_code":"74623000.0",
    "gn:asciiname":"Balantian",
    "gn:country_code":"PH",
    "gn:dem":807,
    "gn:feature_class":"P",
    "gn:feature_code":"PPL",
    "gn:name":"Balantian",
    "gn:population":0,
    "gn:timezone":"Asia/Manila",
    "iso:country":"PH",
    "name:fil_x_preferred":[
        "Balantian"
    ],
    "wof:name":"Balantian",
    "wof:placetype":"locality"
},
  "geometry": {"coordinates":[123.1553,9.3045],"type":"Point"}
}