{
  "type": "Feature",
  "properties": {
    "gn:admin1_code":"03",
    "gn:admin2_code":"47",
    "gn:admin3_code":"34930000.0",
    "gn:asciiname":"Bagong Sikat",
    "gn:country_code":"PH",
    "gn:dem":49,
    "gn:feature_class":"P",
    "gn:feature_code":"PPL",
    "gn:name":"Bagong Sikat",
    "gn:population":0,
    "gn:timezone":"Asia/Manila",
    "iso:country":"PH",
    "name:fil_x_preferred":[
        "Bagong Sikat"
    ],
    "wof:name":"Bagong Sikat",
    "wof:placetype":"locality"
},
  "geometry": {"coordinates":[120.97575000000001,15.58537],"type":"Point"}
}