{
  "type": "Feature",
  "properties": {
    "gn:admin1_code":"14",
    "gn:admin2_code":"60",
    "gn:admin3_code":"156609000.0",
    "gn:asciiname":"Biid",
    "gn:country_code":"PH",
    "gn:dem":127,
    "gn:feature_class":"P",
    "gn:feature_code":"PPL",
    "gn:name":"Biid",
    "gn:population":0,
    "gn:timezone":"Asia/Manila",
    "iso:country":"PH",
    "name:eng_x_preferred":[
        "Biid"
    ],
    "wof:name":"Biid",
    "wof:placetype":"locality"
},
  "geometry": {"coordinates":[120.92243000000001,5.94302],"type":"Point"}
}