{
  "type": "Feature",
  "properties": {
    "gn:admin1_code":"14",
    "gn:admin2_code":"56",
    "gn:admin3_code":"153814000.0",
    "gn:asciiname":"Dapilican",
    "gn:country_code":"PH",
    "gn:dem":5,
    "gn:feature_class":"P",
    "gn:feature_code":"PPL",
    "gn:name":"Dapilican",
    "gn:population":0,
    "gn:timezone":"Asia/Manila",
    "iso:country":"PH",
    "name:fil_x_preferred":[
        "Dapilican"
    ],
    "wof:name":"Dapilican",
    "wof:placetype":"locality"
},
  "geometry": {"coordinates":[124.38333,7.11667],"type":"Point"}
}