{
  "type": "Feature",
  "properties": {
    "gn:gn_country":"PH",
    "gn:gn_fcode":"PPL",
    "gn:gn_pop":7820,
    "gn:population":7820,
    "iso:country":"PH",
    "name:fil_x_preferred":[
        "Camingawan"
    ],
    "qs_pg:aaroncc":"PH",
    "qs_pg:gn_country":"PH",
    "qs_pg:gn_fcode":"PPL",
    "qs_pg:gn_pop":7820,
    "qs_pg:name":"Camingawan",
    "qs_pg:photos_9r":0,
    "qs_pg:photos_sr":0,
    "qs_pg:pop_sr":5,
    "qs_pg:qs_pg_placetype":"locality",
    "wof:name":"Camingawan",
    "wof:placetype":"locality",
    "wof:population":7820
},
  "geometry": {"coordinates":[122.8625,9.8958],"type":"Point"}
}