{
  "type": "Feature",
  "properties": {
    "iso:country":"PH",
    "name:bcl_x_preferred":[
        "Candoni"
    ],
    "name:cbk_zam_x_preferred":[
        "Candoni"
    ],
    "name:ceb_x_preferred":[
        "Candoni"
    ],
    "name:deu_x_preferred":[
        "Candoni"
    ],
    "name:dut_x_preferred":[
        "Candoni"
    ],
    "name:eng_x_preferred":[
        "Candoni"
    ],
    "name:fil_x_preferred":[
        "Candoni"
    ],
    "name:fre_x_preferred":[
        "Candoni"
    ],
    "name:ger_x_preferred":[
        "Candoni"
    ],
    "name:ilo_x_preferred":[
        "Candoni"
    ],
    "name:ind_x_preferred":[
        "Candoni"
    ],
    "name:ita_x_preferred":[
        "Candoni"
    ],
    "name:nld_x_preferred":[
        "Candoni"
    ],
    "name:pag_x_preferred":[
        "Candoni"
    ],
    "name:pam_x_preferred":[
        "Candoni"
    ],
    "name:spa_x_preferred":[
        "Candoni"
    ],
    "name:tgl_x_preferred":[
        "Candoni"
    ],
    "name:war_x_preferred":[
        "Candoni"
    ],
    "qs:gn_country":"PH",
    "qs:gn_fcode":"PPL",
    "qs:gn_pop":6191,
    "qs:name":"Candoni",
    "qs:name_adm0":"Philippines",
    "qs:name_adm1":"Western Visayas",
    "qs:photos":0,
    "qs:photos_1k":0,
    "qs:photos_9k":1,
    "qs:photos_9r":1,
    "qs:photos_all":2,
    "qs:photos_sr":0,
    "qs:placetype":"Town",
    "qs:pop_sr":"5",
    "qs:woe_adm0":23424934,
    "wd:wordcount":1520,
    "wof:name":"Candoni",
    "wof:placetype":"locality",
    "wof:population":6191
},
  "geometry": {"coordinates":[122.60429999999999,9.817],"type":"Point"}
}