{
  "type": "Feature",
  "properties": {
    "gn:admin1_code":"06",
    "gn:admin2_code":"06",
    "gn:admin3_code":"60612000.0",
    "gn:asciiname":"Villa-galed",
    "gn:country_code":"PH",
    "gn:dem":49,
    "gn:feature_class":"P",
    "gn:feature_code":"PPL",
    "gn:name":"Villa-galed",
    "gn:population":0,
    "gn:timezone":"Asia/Manila",
    "iso:country":"PH",
    "name:fil_x_preferred":[
        "Villa-galed"
    ],
    "wof:name":"Villa-galed",
    "wof:placetype":"locality"
},
  "geometry": {"coordinates":[122.0348,10.9027],"type":"Point"}
}