{
  "type": "Feature",
  "properties": {
    "gn:admin1_code":"07",
    "gn:admin2_code":"11",
    "gn:admin3_code":"71239000.0",
    "gn:asciiname":"Copa",
    "gn:country_code":"PH",
    "gn:dem":131,
    "gn:feature_class":"P",
    "gn:feature_code":"PPL",
    "gn:name":"Copa",
    "gn:population":0,
    "gn:timezone":"Asia/Manila",
    "iso:country":"PH",
    "name:fil_x_preferred":[
        "Copa"
    ],
    "wof:name":"Copa",
    "wof:placetype":"locality"
},
  "geometry": {"coordinates":[124.0641,9.7037],"type":"Point"}
}