{
  "type": "Feature",
  "properties": {
    "gn:admin1_code":"08",
    "gn:admin2_code":"37",
    "gn:admin3_code":"83738000.0",
    "gn:asciiname":"Mogasao",
    "gn:cc2":"PH",
    "gn:country_code":"PH",
    "gn:dem":230,
    "gn:feature_class":"P",
    "gn:feature_code":"PPL",
    "gn:name":"Mogasao",
    "gn:population":0,
    "gn:timezone":"Asia/Manila",
    "iso:country":"PH",
    "name:und_x_variant":[
        "Magasao",
        "Magasui"
    ],
    "wof:name":"Mogasao",
    "wof:placetype":"locality"
},
  "geometry": {"coordinates":[124.63472,11.04861],"type":"Point"}
}