{
  "type": "Feature",
  "properties": {
    "gn:country":"PH",
    "gn:fcode":"ADM3",
    "gn:pop":29295,
    "iso:country":"PH",
    "name:ceb_x_preferred":[
        "Payao"
    ],
    "name:fil_x_preferred":[
        "Payao"
    ],
    "name:swe_x_preferred":[
        "Payao"
    ],
    "qs:name":"Payao",
    "qs:photos_9r":0,
    "qs:photos_sr":0,
    "qs:pop_sr":"7",
    "wd:wordcount":26,
    "wof:name":"Payao",
    "wof:placetype":"localadmin",
    "wof:population":29295
},
  "geometry": {"coordinates":[122.83333,7.56667],"type":"Point"}
}