{
  "type": "Feature",
  "properties": {
    "gn:admin1_code":"08",
    "gn:admin2_code":"67",
    "gn:admin3_code":"84810000.0",
    "gn:asciiname":"Hibubuliao",
    "gn:country_code":"PH",
    "gn:dem":14,
    "gn:feature_class":"P",
    "gn:feature_code":"PPL",
    "gn:name":"Hibubuliao",
    "gn:population":0,
    "gn:timezone":"Asia/Manila",
    "iso:country":"PH",
    "name:fil_x_preferred":[
        "Hibubuliao"
    ],
    "wof:name":"Hibubuliao",
    "wof:placetype":"locality"
},
  "geometry": {"coordinates":[125.08333,12.35],"type":"Point"}
}