{
  "type": "Feature",
  "properties": {
    "gn:admin1_code":"07",
    "gn:admin2_code":"21",
    "gn:admin3_code":"72243000.0",
    "gn:asciiname":"To-ong",
    "gn:cc2":"PH",
    "gn:country_code":"PH",
    "gn:dem":27,
    "gn:feature_class":"P",
    "gn:feature_code":"PPL",
    "gn:name":"To-ong",
    "gn:population":0,
    "gn:timezone":"Asia/Manila",
    "iso:country":"PH",
    "name:und_x_variant":[
        "Doong",
        "To-ong"
    ],
    "wof:name":"To-ong",
    "wof:placetype":"locality"
},
  "geometry": {"coordinates":[123.9375,11.01972],"type":"Point"}
}