{
  "type": "Feature",
  "properties": {
    "gn:gn_country":"PH",
    "gn:gn_fcode":"PPL",
    "gn:gn_pop":2522,
    "gn:population":2522,
    "iso:country":"PH",
    "name:eng_x_preferred":[
        "Tabinay"
    ],
    "qs_pg:aaroncc":"PH",
    "qs_pg:gn_country":"PH",
    "qs_pg:gn_fcode":"PPL",
    "qs_pg:gn_pop":2522,
    "qs_pg:name":"Tabinay",
    "qs_pg:photos_9r":0,
    "qs_pg:photos_sr":0,
    "qs_pg:pop_sr":4,
    "qs_pg:qs_pg_placetype":"locality",
    "wof:name":"Tabinay",
    "wof:placetype":"locality",
    "wof:population":2522
},
  "geometry": {"coordinates":[120.95659999999999,13.4871],"type":"Point"}
}