{
  "type": "Feature",
  "properties": {
    "gn:admin1_code":"08",
    "gn:admin2_code":"55",
    "gn:admin3_code":"86020000.0",
    "gn:asciiname":"Mangcares",
    "gn:cc2":"PH",
    "gn:country_code":"PH",
    "gn:dem":57,
    "gn:feature_class":"P",
    "gn:feature_code":"PPL",
    "gn:name":"Mangcares",
    "gn:population":0,
    "gn:timezone":"Asia/Manila",
    "iso:country":"PH",
    "name:und_x_variant":[
        "Mancares",
        "Mangcares"
    ],
    "wof:name":"Mangcares",
    "wof:placetype":"locality"
},
  "geometry": {"coordinates":[124.79083,11.86139],"type":"Point"}
}