{
  "type": "Feature",
  "properties": {
    "gn:admin1_code":"03",
    "gn:admin2_code":"64",
    "gn:admin3_code":"37103000.0",
    "gn:asciiname":"Don Simon",
    "gn:country_code":"PH",
    "gn:dem":26,
    "gn:feature_class":"P",
    "gn:feature_code":"PPL",
    "gn:name":"Don Simon",
    "gn:population":0,
    "gn:timezone":"Asia/Manila",
    "iso:country":"PH",
    "name:ara_x_preferred":[
        "\u062f\u0648\u0646 \u0633\u064a\u0645\u0648\u0646"
    ],
    "name:fil_x_preferred":[
        "Don Simon"
    ],
    "wof:name":"Don Simon",
    "wof:placetype":"locality"
},
  "geometry": {"coordinates":[119.96040000000001,15.5934],"type":"Point"}
}