{
  "type": "Feature",
  "properties": {
    "gn:country":"PH",
    "gn:fcode":"PPL",
    "gn:population":2788,
    "iso:country":"PH",
    "name:und_x_variant":[
        "Hinlayagan"
    ],
    "qs_pg:aaroncc":"PH",
    "qs_pg:gn_country":"PH",
    "qs_pg:gn_fcode":"PPL",
    "qs_pg:gn_pop":2788,
    "qs_pg:name":"Hinlayagan Ilaud",
    "qs_pg:photos_9r":0,
    "qs_pg:photos_sr":0,
    "qs_pg:pop_sr":4,
    "qs_pg:qs_pg_placetype":"locality",
    "wof:name":"Hinlayagan Ilaud",
    "wof:placetype":"locality",
    "wof:population":2788
},
  "geometry": {"coordinates":[124.33457,10.03061],"type":"Point"}
}