{
  "type": "Feature",
  "properties": {
    "gn:country":"PH",
    "gn:fcode":"PPL",
    "gn:pop":2973,
    "iso:country":"PH",
    "name:fil_x_preferred":[
        "Panalingaan"
    ],
    "qs:name":"Panalingaan",
    "qs:photos_9r":0,
    "qs:photos_sr":0,
    "qs:pop_sr":"4",
    "wof:name":"Panalingaan",
    "wof:placetype":"locality",
    "wof:population":2973
},
  "geometry": {"coordinates":[117.42306000000001,8.78417],"type":"Point"}
}