{
  "type": "Feature",
  "properties": {
    "gn:admin1_code":"40",
    "gn:admin2_code":"33",
    "gn:admin3_code":"43408000.0",
    "gn:asciiname":"Batuhan",
    "gn:country_code":"PH",
    "gn:dem":9,
    "gn:feature_class":"P",
    "gn:feature_code":"PPL",
    "gn:name":"Batuhan",
    "gn:population":0,
    "gn:timezone":"Asia/Manila",
    "iso:country":"PH",
    "name:deu_x_preferred":[
        "Batuhan"
    ],
    "name:fil_x_preferred":[
        "Batuhan"
    ],
    "wof:name":"Batuhan",
    "wof:placetype":"locality"
},
  "geometry": {"coordinates":[121.4485,14.4342],"type":"Point"}
}