{
  "type": "Feature",
  "properties": {
    "gn:admin1_code":"09",
    "gn:admin2_code":"ZSI",
    "gn:admin3_code":"98316000.0",
    "gn:asciiname":"Danao",
    "gn:country_code":"PH",
    "gn:dem":35,
    "gn:feature_class":"P",
    "gn:feature_code":"PPL",
    "gn:name":"Danao",
    "gn:population":0,
    "gn:timezone":"Asia/Manila",
    "iso:country":"PH",
    "name:ceb_x_preferred":[
        "Danao"
    ],
    "name:ell_x_preferred":[
        "\u0394\u03b1\u03bd\u03b1\u03cc\u03c2"
    ],
    "name:fra_x_preferred":[
        "Danao"
    ],
    "name:ita_x_preferred":[
        "Danao"
    ],
    "name:msa_x_preferred":[
        "Danao"
    ],
    "name:nld_x_preferred":[
        "Danao"
    ],
    "name:spa_x_preferred":[
        "Danao"
    ],
    "name:und_x_variant":[
        "Danau",
        "Danao"
    ],
    "name:war_x_preferred":[
        "Danao"
    ],
    "wof:name":"Danao",
    "wof:placetype":"locality"
},
  "geometry": {"coordinates":[122.49594,7.56837],"type":"Point"}
}