{
  "type": "Feature",
  "properties": {
    "gn:admin1_code":"14",
    "gn:admin2_code":"60",
    "gn:admin3_code":"156608000.0",
    "gn:asciiname":"Tabukan",
    "gn:country_code":"PH",
    "gn:dem":11,
    "gn:feature_class":"P",
    "gn:feature_code":"PPL",
    "gn:name":"Tabukan",
    "gn:population":0,
    "gn:timezone":"Asia/Manila",
    "iso:country":"PH",
    "name:eng_x_preferred":[
        "Tabukan"
    ],
    "wof:name":"Tabukan",
    "wof:placetype":"locality"
},
  "geometry": {"coordinates":[120.56229999999999,6.2799],"type":"Point"}
}