{
  "type": "Feature",
  "properties": {
    "gn:country":"PH",
    "gn:fcode":"AREA",
    "gn:population":1500,
    "iso:country":"PH",
    "name:und_x_variant":[
        "Pooc"
    ],
    "qs:name":"Brgy. Pook, Kalibo",
    "qs:photos_9r":0,
    "qs:photos_sr":0,
    "qs:pop_sr":"3",
    "wof:name":"Brgy. Pook, Kalibo",
    "wof:placetype":"locality",
    "wof:population":1500
},
  "geometry": {"coordinates":[122.38083,11.68833],"type":"Point"}
}