{
  "type": "Feature",
  "properties": {
    "gn:admin1_code":"07",
    "gn:admin2_code":"46",
    "gn:admin3_code":"74612000.0",
    "gn:asciiname":"Tamao",
    "gn:country_code":"PH",
    "gn:dem":368,
    "gn:feature_class":"P",
    "gn:feature_code":"PPL",
    "gn:name":"Tamao",
    "gn:population":0,
    "gn:timezone":"Asia/Manila",
    "iso:country":"PH",
    "name:fil_x_preferred":[
        "Tamao"
    ],
    "wof:name":"Tamao",
    "wof:placetype":"locality"
},
  "geometry": {"coordinates":[123.1499,9.9827],"type":"Point"}
}