{
  "type": "Feature",
  "properties": {
    "gn:admin1_code":"08",
    "gn:admin2_code":"37",
    "gn:admin3_code":"83724000.0",
    "gn:asciiname":"Buntay",
    "gn:country_code":"PH",
    "gn:dem":172,
    "gn:feature_class":"P",
    "gn:feature_code":"PPL",
    "gn:name":"Buntay",
    "gn:population":0,
    "gn:timezone":"Asia/Manila",
    "iso:country":"PH",
    "name:fil_x_preferred":[
        "Buntay"
    ],
    "wof:name":"Buntay",
    "wof:placetype":"locality"
},
  "geometry": {"coordinates":[124.91200000000001,10.722],"type":"Point"}
}