{
  "type": "Feature",
  "properties": {
    "gn:admin1_code":"40",
    "gn:admin2_code":"09",
    "gn:admin3_code":"41030000.0",
    "gn:asciiname":"Bignay",
    "gn:country_code":"PH",
    "gn:dem":19,
    "gn:feature_class":"P",
    "gn:feature_code":"PPL",
    "gn:name":"Bignay",
    "gn:population":0,
    "gn:timezone":"Asia/Manila",
    "iso:country":"PH",
    "name:fil_x_preferred":[
        "Bignay"
    ],
    "wof:name":"Bignay",
    "wof:placetype":"locality"
},
  "geometry": {"coordinates":[121.01606,14.03207],"type":"Point"}
}