{
  "type": "Feature",
  "properties": {
    "gn:admin1_code":"01",
    "gn:admin2_code":"28",
    "gn:admin3_code":"12823000.0",
    "gn:asciiname":"Cabangaran",
    "gn:country_code":"PH",
    "gn:dem":202,
    "gn:feature_class":"P",
    "gn:feature_code":"PPL",
    "gn:name":"Cabangaran",
    "gn:population":0,
    "gn:timezone":"Asia/Manila",
    "iso:country":"PH",
    "name:fil_x_preferred":[
        "Cabangaran"
    ],
    "wof:name":"Cabangaran",
    "wof:placetype":"locality"
},
  "geometry": {"coordinates":[120.79156,18.32682],"type":"Point"}
}