{
  "type": "Feature",
  "properties": {
    "gn:country":"PH",
    "gn:fcode":"PPL",
    "gn:population":2123,
    "iso:country":"PH",
    "name:fil_x_preferred":[
        "Ilioilio"
    ],
    "name:und_x_variant":[
        "Ollio-ilio"
    ],
    "qs:name":"Ilioilio",
    "qs:photos_9r":0,
    "qs:photos_sr":0,
    "qs:pop_sr":"4",
    "wof:name":"Ilioilio",
    "wof:placetype":"locality",
    "wof:population":2123
},
  "geometry": {"coordinates":[119.7658,15.9616],"type":"Point"}
}