{
  "type": "Feature",
  "properties": {
    "gn:admin1_code":"13",
    "gn:admin2_code":"61",
    "gn:admin3_code":"166715000.0",
    "gn:asciiname":"Bunyasan",
    "gn:cc2":"PH",
    "gn:country_code":"PH",
    "gn:dem":16,
    "gn:feature_class":"P",
    "gn:feature_code":"PPL",
    "gn:name":"Bunyasan",
    "gn:population":0,
    "gn:timezone":"Asia/Manila",
    "iso:country":"PH",
    "name:und_x_variant":[
        "Bu\u00f1ason",
        "Bunyasan"
    ],
    "wof:name":"Bunyasan",
    "wof:placetype":"locality"
},
  "geometry": {"coordinates":[125.41194,9.58361],"type":"Point"}
}