{
  "type": "Feature",
  "properties": {
    "gn:admin1_code":"06",
    "gn:admin2_code":"06",
    "gn:admin3_code":"60603000.0",
    "gn:asciiname":"Borocboroc",
    "gn:country_code":"PH",
    "gn:dem":10,
    "gn:feature_class":"P",
    "gn:feature_code":"PPL",
    "gn:name":"Borocboroc",
    "gn:population":0,
    "gn:timezone":"Asia/Manila",
    "iso:country":"PH",
    "name:fil_x_preferred":[
        "Borocboroc"
    ],
    "wof:name":"Borocboroc",
    "wof:placetype":"locality"
},
  "geometry": {"coordinates":[121.96429999999999,10.8585],"type":"Point"}
}