{
  "type": "Feature",
  "properties": {
    "gn:country":"PH",
    "gn:fcode":"PPL",
    "gn:pop":6093,
    "iso:country":"PH",
    "name:bcl_x_preferred":[
        "San Isidro"
    ],
    "name:cat_x_preferred":[
        "San Isidro"
    ],
    "name:deu_x_preferred":[
        "San Isidro"
    ],
    "name:eng_x_preferred":[
        "San Isidro"
    ],
    "name:fil_x_preferred":[
        "San Isidro"
    ],
    "name:fra_x_preferred":[
        "San Isidro"
    ],
    "name:ilo_x_preferred":[
        "San Isidro"
    ],
    "name:ind_x_preferred":[
        "San Isidro"
    ],
    "name:ita_x_preferred":[
        "San Isidro"
    ],
    "name:nld_x_preferred":[
        "San Isidro"
    ],
    "name:oci_x_preferred":[
        "San Isidro"
    ],
    "name:pag_x_preferred":[
        "San Isidro Labrador"
    ],
    "name:pam_x_preferred":[
        "San Isidro"
    ],
    "name:spa_x_preferred":[
        "San Isidro de Nueva \u00c9cija"
    ],
    "name:swe_x_preferred":[
        "San Isidro"
    ],
    "name:tgl_x_preferred":[
        "San Isidro"
    ],
    "name:vie_x_preferred":[
        "San Isidro"
    ],
    "name:war_x_preferred":[
        "San Isidro"
    ],
    "name:zho_x_preferred":[
        "\u8056\u4f0a\u897f\u5fb7\u7f85"
    ],
    "qs:name":"San Isidro",
    "qs:photos_9r":0,
    "qs:photos_sr":0,
    "qs:pop_sr":"5",
    "wd:wordcount":1052,
    "wof:name":"San Isidro",
    "wof:placetype":"locality",
    "wof:population":6093
},
  "geometry": {"coordinates":[120.82019,15.02116],"type":"Point"}
}