{
  "type": "Feature",
  "properties": {
    "gn:country":"PH",
    "gn:fcode":"PPL",
    "gn:pop":3469,
    "iso:country":"PH",
    "name:fil_x_preferred":[
        "San Isidro"
    ],
    "qs:name":"San Isidro",
    "qs:photos_9r":0,
    "qs:photos_sr":0,
    "qs:pop_sr":"4",
    "wd:wordcount":1052,
    "wof:name":"San Isidro",
    "wof:placetype":"locality",
    "wof:population":3469
},
  "geometry": {"coordinates":[122.2428,13.6325],"type":"Point"}
}