{
  "type": "Feature",
  "properties": {
    "gn:admin1_code":"10",
    "gn:admin2_code":"43",
    "gn:admin3_code":"104310000.0",
    "gn:asciiname":"Camaca",
    "gn:country_code":"PH",
    "gn:dem":104,
    "gn:feature_class":"P",
    "gn:feature_code":"PPL",
    "gn:name":"Camaca",
    "gn:population":0,
    "gn:timezone":"Asia/Manila",
    "iso:country":"PH",
    "name:fil_x_preferred":[
        "Camaca"
    ],
    "wof:name":"Camaca",
    "wof:placetype":"locality"
},
  "geometry": {"coordinates":[124.33722,8.52472],"type":"Point"}
}