{
  "type": "Feature",
  "properties": {
    "gn:admin1_code":"40",
    "gn:admin2_code":"20",
    "gn:admin3_code":"42101000.0",
    "gn:asciiname":"Tawanak Ibaba",
    "gn:cc2":"PH",
    "gn:country_code":"PH",
    "gn:dem":311,
    "gn:feature_class":"P",
    "gn:feature_code":"PPL",
    "gn:name":"Tawanak Ibaba",
    "gn:population":0,
    "gn:timezone":"Asia/Manila",
    "iso:country":"PH",
    "name:und_x_variant":[
        "Taywana",
        "Tawanak Ibaba"
    ],
    "wof:name":"Tawanak Ibaba",
    "wof:placetype":"locality"
},
  "geometry": {"coordinates":[120.83861,14.16694],"type":"Point"}
}