{
  "type": "Feature",
  "properties": {
    "gn:country":"PH",
    "gn:fcode":"PPL",
    "gn:pop":2436,
    "iso:country":"PH",
    "name:fil_x_preferred":[
        "Cansuje"
    ],
    "qs:name":"Cansuje",
    "qs:photos_9r":0,
    "qs:photos_sr":0,
    "qs:pop_sr":"4",
    "wof:name":"Cansuje",
    "wof:placetype":"locality",
    "wof:population":2436
},
  "geometry": {"coordinates":[123.49629,9.92314],"type":"Point"}
}