{
  "type": "Feature",
  "properties": {
    "gn:gn_country":"PH",
    "gn:gn_fcode":"PPL",
    "gn:gn_pop":3017,
    "gn:population":3017,
    "iso:country":"PH",
    "name:fil_x_preferred":[
        "Batana"
    ],
    "name:fil_x_variant":[
        "Batang"
    ],
    "qs_pg:aaroncc":"PH",
    "qs_pg:gn_country":"PH",
    "qs_pg:gn_fcode":"PPL",
    "qs_pg:gn_pop":3017,
    "qs_pg:name":"Batana",
    "qs_pg:photos_9r":0,
    "qs_pg:photos_sr":0,
    "qs_pg:pop_sr":4,
    "qs_pg:qs_pg_placetype":"locality",
    "wof:name":"Batana",
    "wof:placetype":"locality",
    "wof:population":3017
},
  "geometry": {"coordinates":[123.5641,13.2498],"type":"Point"}
}