{
  "type": "Feature",
  "properties": {
    "gn:admin1_code":"05",
    "gn:admin2_code":"16",
    "gn:admin3_code":"51737000.0",
    "gn:asciiname":"Tierra Nevada",
    "gn:cc2":"PH",
    "gn:country_code":"PH",
    "gn:dem":21,
    "gn:feature_class":"P",
    "gn:feature_code":"PPL",
    "gn:name":"Tierra Nevada",
    "gn:population":0,
    "gn:timezone":"Asia/Manila",
    "iso:country":"PH",
    "name:und_x_variant":[
        "Sierra Nevada",
        "Tinorilan",
        "Tierra Nevada"
    ],
    "wof:name":"Tierra Nevada",
    "wof:placetype":"locality"
},
  "geometry": {"coordinates":[123.33333,13.81667],"type":"Point"}
}