{
  "type": "Feature",
  "properties": {
    "gn:admin1_code":"07",
    "gn:admin2_code":"21",
    "gn:admin3_code":"72251000.0",
    "gn:asciiname":"Malobog",
    "gn:country_code":"PH",
    "gn:dem":92,
    "gn:feature_class":"P",
    "gn:feature_code":"PPL",
    "gn:name":"Malobog",
    "gn:population":0,
    "gn:timezone":"Asia/Manila",
    "iso:country":"PH",
    "name:fil_x_preferred":[
        "Malobog"
    ],
    "name:fil_x_variant":[
        "Malabog"
    ],
    "wof:name":"Malobog",
    "wof:placetype":"locality"
},
  "geometry": {"coordinates":[123.6942,10.36367],"type":"Point"}
}