{
  "type": "Feature",
  "properties": {
    "gn:admin1_code":"03",
    "gn:admin2_code":"63",
    "gn:admin3_code":"36905000.0",
    "gn:asciiname":"Gugu",
    "gn:country_code":"PH",
    "gn:dem":50,
    "gn:feature_class":"P",
    "gn:feature_code":"PPL",
    "gn:name":"Gugu",
    "gn:population":0,
    "gn:timezone":"Asia/Manila",
    "iso:country":"PH",
    "name:ara_x_preferred":[
        "\u062c\u0648\u062c\u0648"
    ],
    "name:ben_x_preferred":[
        "\u0997\u09c1\u0997\u09c1"
    ],
    "name:ceb_x_preferred":[
        "Gugu"
    ],
    "name:deu_x_preferred":[
        "Berg Gugu"
    ],
    "name:deu_x_variant":[
        "Gugu"
    ],
    "name:ell_x_preferred":[
        "\u0393\u03ba\u03bf\u03cd\u03b3\u03ba\u03bf\u03c5"
    ],
    "name:eng_x_preferred":[
        "Gugu"
    ],
    "name:fas_x_preferred":[
        "\u06af\u0648\u06af\u0648"
    ],
    "name:fil_x_preferred":[
        "Gugu"
    ],
    "name:fra_x_preferred":[
        "Gugu"
    ],
    "name:heb_x_preferred":[
        "\u05d2\u05d5\u05d2\u05d5"
    ],
    "name:hin_x_preferred":[
        "\u0917\u0941\u0917\u0941"
    ],
    "name:hun_x_preferred":[
        "Gugu"
    ],
    "name:ind_x_preferred":[
        "Gugu"
    ],
    "name:ita_x_preferred":[
        "Gugu"
    ],
    "name:jpn_x_preferred":[
        "\u30b0\u30b0\u5c71"
    ],
    "name:kor_x_preferred":[
        "\uad6c\uad6c"
    ],
    "name:pol_x_preferred":[
        "Gugu"
    ],
    "name:por_x_preferred":[
        "Gugu"
    ],
    "name:rus_x_preferred":[
        "\u0433\u043e\u0440\u0430 \u0413\u0443\u0433\u0443"
    ],
    "name:spa_x_preferred":[
        "Gugu"
    ],
    "name:swe_x_preferred":[
        "Gugu"
    ],
    "name:tur_x_preferred":[
        "Gugu"
    ],
    "name:ukr_x_preferred":[
        "\u0413\u0443\u0433\u0443"
    ],
    "name:urd_x_preferred":[
        "\u06af\u0648\u06af\u0648"
    ],
    "name:vie_x_preferred":[
        "N\u00fai Gugu"
    ],
    "name:zho_cn_x_preferred":[
        "\u53e4\u53e4\u5c71"
    ],
    "name:zho_tw_x_preferred":[
        "\u53e4\u56fa\u5c71"
    ],
    "wof:name":"Gugu",
    "wof:placetype":"locality"
},
  "geometry": {"coordinates":[120.61313,15.37516],"type":"Point"}
}