{
  "type": "Feature",
  "properties": {
    "gn:admin1_code":"01",
    "gn:admin2_code":"28",
    "gn:admin3_code":"12814000.0",
    "gn:asciiname":"Bugayong",
    "gn:country_code":"PH",
    "gn:dem":101,
    "gn:feature_class":"P",
    "gn:feature_code":"PPL",
    "gn:name":"Bugayong",
    "gn:population":0,
    "gn:timezone":"Asia/Manila",
    "iso:country":"PH",
    "name:fil_x_preferred":[
        "Bugayong"
    ],
    "wof:name":"Bugayong",
    "wof:placetype":"locality"
},
  "geometry": {"coordinates":[120.60850000000001,17.9332],"type":"Point"}
}