{
  "type": "Feature",
  "properties": {
    "gn:admin1_code":"05",
    "gn:admin2_code":"58",
    "gn:admin3_code":"56211000.0",
    "gn:asciiname":"Biton",
    "gn:cc2":"PH",
    "gn:country_code":"PH",
    "gn:dem":18,
    "gn:feature_class":"P",
    "gn:feature_code":"PPL",
    "gn:name":"Biton",
    "gn:population":0,
    "gn:timezone":"Asia/Manila",
    "iso:country":"PH",
    "name:und_x_variant":[
        "Biten",
        "Biton"
    ],
    "wof:name":"Biton",
    "wof:placetype":"locality"
},
  "geometry": {"coordinates":[123.84778,12.75583],"type":"Point"}
}