{
  "type": "Feature",
  "properties": {
    "gn:admin1_code":"03",
    "gn:admin2_code":"50",
    "gn:admin3_code":"35413000.0",
    "gn:asciiname":"San Jose Matulio",
    "gn:country_code":"PH",
    "gn:dem":8,
    "gn:feature_class":"P",
    "gn:feature_code":"PPL",
    "gn:name":"San Jose Matulio",
    "gn:population":0,
    "gn:timezone":"Asia/Manila",
    "iso:country":"PH",
    "name:fil_x_preferred":[
        "San Jose Matulio"
    ],
    "name:fil_x_variant":[
        "San Jose Matulid"
    ],
    "name:und_x_variant":[
        "San Jose de Matulid"
    ],
    "wof:name":"San Jose Matulio",
    "wof:placetype":"locality"
},
  "geometry": {"coordinates":[120.72709999999999,15.0333],"type":"Point"}
}