{
  "type": "Feature",
  "properties": {
    "gn:admin1_code":"40",
    "gn:admin2_code":"09",
    "gn:admin3_code":"41019000.0",
    "gn:asciiname":"Catandaan",
    "gn:country_code":"PH",
    "gn:dem":19,
    "gn:feature_class":"P",
    "gn:feature_code":"PPL",
    "gn:name":"Catandaan",
    "gn:population":0,
    "gn:timezone":"Asia/Manila",
    "iso:country":"PH",
    "name:fil_x_preferred":[
        "Catandaan"
    ],
    "wof:name":"Catandaan",
    "wof:placetype":"locality"
},
  "geometry": {"coordinates":[120.672,14.0794],"type":"Point"}
}