{
  "type": "Feature",
  "properties": {
    "gn:admin1_code":"08",
    "gn:admin2_code":"37",
    "gn:admin3_code":"83730000.0",
    "gn:asciiname":"Ubun",
    "gn:cc2":"PH",
    "gn:country_code":"PH",
    "gn:dem":8,
    "gn:feature_class":"P",
    "gn:feature_code":"PPL",
    "gn:name":"Ubun",
    "gn:population":0,
    "gn:timezone":"Asia/Manila",
    "iso:country":"PH",
    "name:und_x_variant":[
        "Uban",
        "Ubun"
    ],
    "wof:name":"Ubun",
    "wof:placetype":"locality"
},
  "geometry": {"coordinates":[125.00082999999999,10.84639],"type":"Point"}
}