{
  "type": "Feature",
  "properties": {
    "gn:country":"PH",
    "gn:fcode":"PPL",
    "gn:population":2201,
    "iso:country":"PH",
    "name:fil_x_preferred":[
        "Udtongan"
    ],
    "qs:name":"Ogtongon",
    "qs:photos_9r":0,
    "qs:photos_sr":0,
    "qs:pop_sr":"4",
    "wof:name":"Ogtongon",
    "wof:placetype":"locality",
    "wof:population":2201
},
  "geometry": {"coordinates":[123.52,10.77334],"type":"Point"}
}