{
  "type": "Feature",
  "properties": {
    "gn:admin1_code":"01",
    "gn:admin2_code":"51",
    "gn:admin3_code":"15512000.0",
    "gn:asciiname":"Bubo",
    "gn:country_code":"PH",
    "gn:dem":43,
    "gn:feature_class":"P",
    "gn:feature_code":"PPL",
    "gn:name":"Bubo",
    "gn:population":0,
    "gn:timezone":"Asia/Manila",
    "iso:country":"PH",
    "name:bel_x_preferred":[
        "\u0411\u0443\u0431\u043e\u043d"
    ],
    "name:cat_x_preferred":[
        "Bub\u00f3"
    ],
    "name:fil_x_preferred":[
        "Bubo"
    ],
    "name:ido_x_preferred":[
        "Bubono"
    ],
    "name:ita_x_preferred":[
        "Bubbone"
    ],
    "name:lit_x_preferred":[
        "Bubonas"
    ],
    "name:pol_x_preferred":[
        "Dymienica"
    ],
    "name:rus_x_preferred":[
        "\u0411\u0443\u0431\u043e\u043d"
    ],
    "name:spa_x_preferred":[
        "Bub\u00f3n"
    ],
    "name:tur_x_preferred":[
        "Bubo"
    ],
    "name:ukr_x_preferred":[
        "\u0411\u0443\u0431\u043e\u043d"
    ],
    "name:uzb_x_preferred":[
        "Bubon"
    ],
    "wof:name":"Bubo",
    "wof:placetype":"locality"
},
  "geometry": {"coordinates":[120.5898,16.0376],"type":"Point"}
}