{
  "type": "Feature",
  "properties": {
    "gn:admin1_code":"07",
    "gn:admin2_code":"21",
    "gn:admin3_code":"72246000.0",
    "gn:asciiname":"Bagakay",
    "gn:country_code":"PH",
    "gn:dem":7,
    "gn:feature_class":"P",
    "gn:feature_code":"PPL",
    "gn:name":"Bagakay",
    "gn:population":0,
    "gn:timezone":"Asia/Manila",
    "iso:country":"PH",
    "name:fil_x_preferred":[
        "Bagakay"
    ],
    "wof:name":"Bagakay",
    "wof:placetype":"locality"
},
  "geometry": {"coordinates":[123.61463000000001,9.98679],"type":"Point"}
}