{
  "type": "Feature",
  "properties": {
    "gn:admin1_code":"08",
    "gn:admin2_code":"37",
    "gn:admin3_code":"83702000.0",
    "gn:asciiname":"Binungto-an",
    "gn:country_code":"PH",
    "gn:dem":44,
    "gn:feature_class":"P",
    "gn:feature_code":"PPL",
    "gn:name":"Binungto-an",
    "gn:population":0,
    "gn:timezone":"Asia/Manila",
    "iso:country":"PH",
    "name:und_x_variant":[
        "Binungtuan",
        "Binungto-an"
    ],
    "wof:name":"Binungto-an",
    "wof:placetype":"locality"
},
  "geometry": {"coordinates":[124.83654,11.2157],"type":"Point"}
}