{
  "type": "Feature",
  "properties": {
    "gn:admin1_code":"07",
    "gn:admin2_code":"11",
    "gn:admin3_code":"71245000.0",
    "gn:asciiname":"Ilihan Norte",
    "gn:country_code":"PH",
    "gn:dem":5,
    "gn:feature_class":"P",
    "gn:feature_code":"PPL",
    "gn:name":"Ilihan Norte",
    "gn:population":0,
    "gn:timezone":"Asia/Manila",
    "iso:country":"PH",
    "name:fil_x_preferred":[
        "Ilihan Norte"
    ],
    "wof:name":"Ilihan Norte",
    "wof:placetype":"locality"
},
  "geometry": {"coordinates":[123.93333,9.93333],"type":"Point"}
}