{
  "type": "Feature",
  "properties": {
    "gn:country":"PH",
    "gn:fcode":"PPL",
    "gn:pop":2815,
    "iso:country":"PH",
    "qs:name":"Rizal",
    "qs:photos_9r":0,
    "qs:photos_sr":0,
    "qs:pop_sr":"4",
    "wd:wordcount":2016,
    "wof:name":"Rizal",
    "wof:placetype":"locality",
    "wof:population":2815
},
  "geometry": {"coordinates":[121.55528,16.71861],"type":"Point"}
}