{
  "type": "Feature",
  "properties": {
    "gn:country":"PH",
    "gn:fcode":"PPL",
    "gn:population":2815,
    "iso:country":"PH",
    "name:ace_x_preferred":[
        "Propinsi Rizal"
    ],
    "name:ara_x_preferred":[
        "\u0631\u064a\u0632\u0627\u0644"
    ],
    "name:azb_x_preferred":[
        "\u0631\u06cc\u0632\u0627\u0644"
    ],
    "name:bcl_x_preferred":[
        "Rizal"
    ],
    "name:ben_x_preferred":[
        "\u09b0\u09bf\u099c\u09be\u09b2"
    ],
    "name:cat_x_preferred":[
        "Rizal"
    ],
    "name:ceb_x_preferred":[
        "Rizal"
    ],
    "name:dan_x_preferred":[
        "Rizal"
    ],
    "name:deu_x_preferred":[
        "Rizal"
    ],
    "name:ell_x_preferred":[
        "\u03a1\u03b9\u03b6\u03ac\u03bb"
    ],
    "name:eng_x_preferred":[
        "Rizal"
    ],
    "name:fas_x_preferred":[
        "\u0631\u06cc\u0632\u0627\u0644"
    ],
    "name:fin_x_preferred":[
        "Rizal"
    ],
    "name:fra_x_preferred":[
        "Rizal"
    ],
    "name:guj_x_preferred":[
        "\u0ab0\u0abf\u0a9d\u0abe\u0ab2"
    ],
    "name:hin_x_preferred":[
        "\u0930\u093f\u091c\u093c\u093e\u0932 \u092a\u094d\u0930\u093e\u0928\u094d\u0924"
    ],
    "name:ilo_x_preferred":[
        "Rizal"
    ],
    "name:ind_x_preferred":[
        "Rizal"
    ],
    "name:jpn_x_preferred":[
        "\u30ea\u30b5\u30fc\u30eb"
    ],
    "name:kan_x_preferred":[
        "\u0cb0\u0cbf\u0c9c\u0cbe\u0cb2\u0ccd"
    ],
    "name:kor_x_preferred":[
        "\ub9ac\uc0b4\uc8fc"
    ],
    "name:lav_x_preferred":[
        "Rizala"
    ],
    "name:lit_x_preferred":[
        "Rizalis"
    ],
    "name:mar_x_preferred":[
        "\u0930\u093f\u092f\u093e\u091d\u0932"
    ],
    "name:mkd_x_preferred":[
        "\u0420\u0438\u0437\u0430\u043b"
    ],
    "name:msa_x_preferred":[
        "Rizal"
    ],
    "name:nan_x_preferred":[
        "Rizal"
    ],
    "name:nld_x_preferred":[
        "Rizal"
    ],
    "name:nob_x_preferred":[
        "Rizal"
    ],
    "name:oci_x_preferred":[
        "Rizal"
    ],
    "name:pag_x_preferred":[
        "Rizal"
    ],
    "name:pam_x_preferred":[
        "Rizal"
    ],
    "name:pol_x_preferred":[
        "Rizal"
    ],
    "name:por_x_preferred":[
        "Rizal"
    ],
    "name:rus_x_preferred":[
        "\u0420\u0438\u0441\u0430\u043b\u044c"
    ],
    "name:sco_x_preferred":[
        "Rizal"
    ],
    "name:sin_x_preferred":[
        "\u0dbb\u0dd2\u0dc3\u0dcf\u0dbd\u0dca"
    ],
    "name:spa_x_preferred":[
        "Rizal"
    ],
    "name:swe_x_preferred":[
        "Rizal"
    ],
    "name:tam_x_preferred":[
        "\u0bb0\u0bbf\u0b9a\u0bbe\u0bb2\u0bcd"
    ],
    "name:tel_x_preferred":[
        "\u0c30\u0c3f\u0c1c\u0c3e\u0c32\u0c4d"
    ],
    "name:tgl_x_preferred":[
        "Rizal"
    ],
    "name:tha_x_preferred":[
        "\u0e23\u0e35\u0e0b\u0e31\u0e25"
    ],
    "name:tur_x_preferred":[
        "Rizal"
    ],
    "name:ukr_x_preferred":[
        "\u0420\u0456\u0441\u0430\u043b\u044c"
    ],
    "name:urd_x_preferred":[
        "\u0631\u06cc\u0632\u0627\u0644"
    ],
    "name:vie_x_preferred":[
        "Rizal"
    ],
    "name:war_x_preferred":[
        "Rizal"
    ],
    "name:zho_x_preferred":[
        "\u9ece\u524e\u7701"
    ],
    "qs:name":"Rizal",
    "qs:photos_9r":0,
    "qs:photos_sr":0,
    "qs:pop_sr":"4",
    "wd:wordcount":2016,
    "wof:name":"Rizal",
    "wof:placetype":"locality",
    "wof:population":2815
},
  "geometry": {"coordinates":[121.55528,16.71861],"type":"Point"}
}