{
  "type": "Feature",
  "properties": {
    "gn:admin1_code":"40",
    "gn:admin2_code":"09",
    "gn:admin3_code":"41017000.0",
    "gn:asciiname":"Luta Del Norte",
    "gn:country_code":"PH",
    "gn:dem":224,
    "gn:feature_class":"P",
    "gn:feature_code":"PPL",
    "gn:name":"Luta Del Norte",
    "gn:population":0,
    "gn:timezone":"Asia/Manila",
    "iso:country":"PH",
    "name:und_x_variant":[
        "Luta"
    ],
    "wof:name":"Luta Del Norte",
    "wof:placetype":"locality"
},
  "geometry": {"coordinates":[121.15993,14.03775],"type":"Point"}
}