{
  "type": "Feature",
  "properties": {
    "gn:country":"PH",
    "gn:fcode":"PPL",
    "gn:population":2759,
    "iso:country":"PH",
    "name:ara_x_preferred":[
        "\u0641\u064a\u0644\u0627\u0631\u0648\u0632\u0627"
    ],
    "name:azb_x_preferred":[
        "\u0648\u06cc\u0644\u0627\u0631\u0648\u0633\u0627"
    ],
    "name:bul_x_preferred":[
        "\u0412\u0438\u043b\u0430\u0440\u043e\u0437\u0430"
    ],
    "name:cat_x_preferred":[
        "Villarosa"
    ],
    "name:ceb_x_preferred":[
        "Villarosa"
    ],
    "name:deu_x_preferred":[
        "Villarosa"
    ],
    "name:epo_x_preferred":[
        "Villarosa"
    ],
    "name:eus_x_preferred":[
        "Villarosa"
    ],
    "name:fas_x_preferred":[
        "\u0648\u06cc\u0644\u0627\u0631\u0648\u0633\u0627"
    ],
    "name:fil_x_preferred":[
        "Villarosa"
    ],
    "name:fra_x_preferred":[
        "Villarosa"
    ],
    "name:hun_x_preferred":[
        "Villarosa"
    ],
    "name:hye_x_preferred":[
        "\u054e\u056b\u056c\u056c\u0561\u0580\u0578\u057d\u0561"
    ],
    "name:ita_x_preferred":[
        "Villarosa"
    ],
    "name:jpn_x_preferred":[
        "\u30f4\u30a3\u30c3\u30e9\u30ed\u30fc\u30b6"
    ],
    "name:kat_x_preferred":[
        "\u10d5\u10d8\u10da\u10d0\u10e0\u10dd\u10d6\u10d0"
    ],
    "name:kaz_x_preferred":[
        "\u0412\u0438\u043b\u043b\u0430\u0440\u043e\u0441\u0430"
    ],
    "name:lat_x_preferred":[
        "Villa Rosa"
    ],
    "name:lmo_x_preferred":[
        "Villarosa"
    ],
    "name:msa_x_preferred":[
        "Villarosa"
    ],
    "name:nap_x_preferred":[
        "Villarosa"
    ],
    "name:nld_x_preferred":[
        "Villarosa"
    ],
    "name:pms_x_preferred":[
        "Villarosa"
    ],
    "name:pol_x_preferred":[
        "Villarosa"
    ],
    "name:por_x_preferred":[
        "Villarosa"
    ],
    "name:ron_x_preferred":[
        "Villarosa"
    ],
    "name:rus_x_preferred":[
        "\u0412\u0438\u043b\u043b\u0430\u0440\u043e\u0437\u0430"
    ],
    "name:scn_x_preferred":[
        "Villarosa"
    ],
    "name:sco_x_preferred":[
        "Villarosa"
    ],
    "name:spa_x_preferred":[
        "Villarosa"
    ],
    "name:srd_x_preferred":[
        "Villarosa"
    ],
    "name:srp_x_preferred":[
        "\u0412\u0438\u043b\u0430\u0440\u043e\u0437\u0430"
    ],
    "name:swe_x_preferred":[
        "Villarosa"
    ],
    "name:tgl_x_preferred":[
        "Villarosa"
    ],
    "name:ukr_x_preferred":[
        "\u0412\u0456\u043b\u043b\u0430\u0440\u043e\u0437\u0430"
    ],
    "name:uzb_x_preferred":[
        "Villarosa"
    ],
    "name:vol_x_preferred":[
        "Villarosa"
    ],
    "name:war_x_preferred":[
        "Villarosa"
    ],
    "name:zho_x_preferred":[
        "\u7ef4\u62c9\u7f57\u8428"
    ],
    "qs:name":"Villarosa",
    "qs:photos_9r":0,
    "qs:photos_sr":0,
    "qs:pop_sr":"4",
    "wd:wordcount":39,
    "wof:name":"Villarosa",
    "wof:placetype":"locality",
    "wof:population":2759
},
  "geometry": {"coordinates":[120.75,15.55],"type":"Point"}
}