{
  "type": "Feature",
  "properties": {
    "gn:country":"PH",
    "gn:fcode":"PPL",
    "gn:pop":2759,
    "iso:country":"PH",
    "name:fil_x_preferred":[
        "Villarosa"
    ],
    "name:unk_x_variant":[
        "Villa Rosa"
    ],
    "qs:name":"Villarosa",
    "qs:photos_9r":0,
    "qs:photos_sr":0,
    "qs:pop_sr":"4",
    "wd:wordcount":39,
    "wof:name":"Villarosa",
    "wof:placetype":"locality",
    "wof:population":2759
},
  "geometry": {"coordinates":[120.75,15.55],"type":"Point"}
}