{
  "type": "Feature",
  "properties": {
    "gn:admin1_code":"41",
    "gn:admin2_code":"49",
    "gn:admin3_code":"175324000.0",
    "gn:asciiname":"Corumi",
    "gn:country_code":"PH",
    "gn:dem":11,
    "gn:feature_class":"P",
    "gn:feature_code":"PPL",
    "gn:name":"Corumi",
    "gn:population":0,
    "gn:timezone":"Asia/Manila",
    "iso:country":"PH",
    "name:fil_x_preferred":[
        "Corumi"
    ],
    "wof:name":"Corumi",
    "wof:placetype":"locality"
},
  "geometry": {"coordinates":[118.01111000000002,8.93167],"type":"Point"}
}