{
  "type": "Feature",
  "properties": {
    "gn:admin1_code":"NCR",
    "gn:admin2_code":"137600000",
    "gn:admin3_code":"137607000.0",
    "gn:asciiname":"Maharlika Village",
    "gn:country_code":"PH",
    "gn:dem":21,
    "gn:feature_class":"P",
    "gn:feature_code":"PPL",
    "gn:name":"Maharlika Village",
    "gn:population":0,
    "gn:timezone":"Asia/Manila",
    "iso:country":"PH",
    "name:tgl_x_preferred":[
        "Maharlika Village"
    ],
    "wof:name":"Maharlika Village",
    "wof:placetype":"locality"
},
  "geometry": {"coordinates":[121.05459999999999,14.5038],"type":"Point"}
}