{
  "type": "Feature",
  "properties": {
    "gn:admin1_code":"15",
    "gn:admin2_code":"01",
    "gn:admin3_code":"140126000.0",
    "gn:asciiname":"Mapga",
    "gn:country_code":"PH",
    "gn:dem":431,
    "gn:feature_class":"P",
    "gn:feature_code":"PPL",
    "gn:name":"Mapga",
    "gn:population":0,
    "gn:timezone":"Asia/Manila",
    "iso:country":"PH",
    "name:fil_x_preferred":[
        "Mapga"
    ],
    "wof:name":"Mapga",
    "wof:placetype":"locality"
},
  "geometry": {"coordinates":[120.73333,17.18333],"type":"Point"}
}