{
  "type": "Feature",
  "properties": {
    "gn:admin1_code":"01",
    "gn:admin2_code":"29",
    "gn:admin3_code":"12903000.0",
    "gn:asciiname":"Baoay",
    "gn:country_code":"PH",
    "gn:dem":37,
    "gn:feature_class":"P",
    "gn:feature_code":"PPL",
    "gn:name":"Baoay",
    "gn:population":0,
    "gn:timezone":"Asia/Manila",
    "iso:country":"PH",
    "name:fil_x_preferred":[
        "Baoay"
    ],
    "wof:name":"Baoay",
    "wof:placetype":"locality"
},
  "geometry": {"coordinates":[120.44844999999999,17.6009],"type":"Point"}
}