{
  "type": "Feature",
  "properties": {
    "gn:admin1_code":"09",
    "gn:admin2_code":"66",
    "gn:asciiname":"Tumitus",
    "gn:country_code":"PH",
    "gn:dem":-5,
    "gn:feature_class":"P",
    "gn:feature_code":"PPL",
    "gn:name":"Tumitus",
    "gn:population":0,
    "gn:timezone":"Asia/Manila",
    "iso:country":"PH",
    "wof:name":"Tumitus",
    "wof:placetype":"locality"
},
  "geometry": {"coordinates":[122.38583,7.39417],"type":"Point"}
}