{
  "type": "Feature",
  "properties": {
    "gn:admin1_code":"05",
    "gn:admin2_code":"16",
    "gn:admin3_code":"51737000.0",
    "gn:asciiname":"Cauayan",
    "gn:country_code":"PH",
    "gn:dem":18,
    "gn:feature_class":"P",
    "gn:feature_code":"PPL",
    "gn:name":"Cauayan",
    "gn:population":0,
    "gn:timezone":"Asia/Manila",
    "iso:country":"PH",
    "name:ceb_x_preferred":[
        "Cauayan"
    ],
    "name:fil_x_preferred":[
        "Cauayan"
    ],
    "name:fra_x_preferred":[
        "Cauayan"
    ],
    "name:ilo_x_preferred":[
        "Cauayan"
    ],
    "name:ita_x_preferred":[
        "Cauayan"
    ],
    "name:nld_x_preferred":[
        "Cauayan"
    ],
    "name:war_x_preferred":[
        "Cauayan"
    ],
    "wof:name":"Cauayan",
    "wof:placetype":"locality"
},
  "geometry": {"coordinates":[123.31667,13.96667],"type":"Point"}
}