{
  "type": "Feature",
  "properties": {
    "gn:admin1_code":"40",
    "gn:admin2_code":"20",
    "gn:admin3_code":"42122000.0",
    "gn:asciiname":"Conchu",
    "gn:country_code":"PH",
    "gn:dem":147,
    "gn:feature_class":"P",
    "gn:feature_code":"PPL",
    "gn:name":"Conchu",
    "gn:population":0,
    "gn:timezone":"Asia/Manila",
    "iso:country":"PH",
    "name:fil_x_preferred":[
        "Conchu"
    ],
    "name:und_x_variant":[
        "Lagundian"
    ],
    "wof:name":"Conchu",
    "wof:placetype":"locality"
},
  "geometry": {"coordinates":[120.8807,14.26999],"type":"Point"}
}