{
  "type": "Feature",
  "properties": {
    "gn:admin1_code":"03",
    "gn:admin2_code":"07",
    "gn:admin3_code":"30804000.0",
    "gn:asciiname":"Tukot",
    "gn:country_code":"PH",
    "gn:dem":18,
    "gn:feature_class":"P",
    "gn:feature_code":"PPL",
    "gn:name":"Tukot",
    "gn:population":0,
    "gn:timezone":"Asia/Manila",
    "iso:country":"PH",
    "name:fil_x_preferred":[
        "Tukot"
    ],
    "wof:name":"Tukot",
    "wof:placetype":"locality"
},
  "geometry": {"coordinates":[120.47320000000001,14.8977],"type":"Point"}
}