{
  "type": "Feature",
  "properties": {
    "gn:admin1_code":"12",
    "gn:admin2_code":"M9",
    "gn:admin3_code":"128005000.0",
    "gn:asciiname":"Manubo Clearings",
    "gn:country_code":"PH",
    "gn:dem":608,
    "gn:feature_class":"P",
    "gn:feature_code":"PPL",
    "gn:name":"Manubo Clearings",
    "gn:population":0,
    "gn:timezone":"Asia/Manila",
    "iso:country":"PH",
    "name:fil_x_preferred":[
        "Manubo Clearings"
    ],
    "wof:name":"Manubo Clearings",
    "wof:placetype":"locality"
},
  "geometry": {"coordinates":[124.44098,6.19132],"type":"Point"}
}