{
  "type": "Feature",
  "properties": {
    "gn:admin1_code":"02",
    "gn:admin2_code":"14",
    "gn:admin3_code":"21507000.0",
    "gn:asciiname":"Ammubuan",
    "gn:country_code":"PH",
    "gn:dem":9,
    "gn:feature_class":"P",
    "gn:feature_code":"PPL",
    "gn:name":"Ammubuan",
    "gn:population":0,
    "gn:timezone":"Asia/Manila",
    "iso:country":"PH",
    "name:fil_x_preferred":[
        "Ammubuan"
    ],
    "wof:name":"Ammubuan",
    "wof:placetype":"locality"
},
  "geometry": {"coordinates":[121.53516999999999,18.39626],"type":"Point"}
}