{
  "type": "Feature",
  "properties": {
    "gn:admin1_code":"41",
    "gn:admin2_code":"40",
    "gn:admin3_code":"175109000.0",
    "gn:asciiname":"Guitong",
    "gn:country_code":"PH",
    "gn:dem":14,
    "gn:feature_class":"P",
    "gn:feature_code":"PPL",
    "gn:name":"Guitong",
    "gn:population":0,
    "gn:timezone":"Asia/Manila",
    "iso:country":"PH",
    "name:fil_x_preferred":[
        "Guitong"
    ],
    "wof:name":"Guitong",
    "wof:placetype":"locality"
},
  "geometry": {"coordinates":[120.8259,12.9529],"type":"Point"}
}