{
  "type": "Feature",
  "properties": {
    "gn:admin1_code":"06",
    "gn:admin2_code":"06",
    "gn:admin3_code":"60604000.0",
    "gn:asciiname":"Villa Siga",
    "gn:country_code":"PH",
    "gn:dem":152,
    "gn:feature_class":"P",
    "gn:feature_code":"PPL",
    "gn:name":"Villa Siga",
    "gn:population":0,
    "gn:timezone":"Asia/Manila",
    "iso:country":"PH",
    "name:fil_x_preferred":[
        "Villa Siga"
    ],
    "wof:name":"Villa Siga",
    "wof:placetype":"locality"
},
  "geometry": {"coordinates":[122.15000000000001,11.1434],"type":"Point"}
}