{
  "type": "Feature",
  "properties": {
    "gn:admin1_code":"08",
    "gn:admin2_code":"23",
    "gn:admin3_code":"82623000.0",
    "gn:asciiname":"Bongdo",
    "gn:country_code":"PH",
    "gn:dem":34,
    "gn:feature_class":"P",
    "gn:feature_code":"PPL",
    "gn:name":"Bongdo",
    "gn:population":0,
    "gn:timezone":"Asia/Manila",
    "iso:country":"PH",
    "name:fil_x_preferred":[
        "Bongdo"
    ],
    "wof:name":"Bongdo",
    "wof:placetype":"locality"
},
  "geometry": {"coordinates":[125.40000000000001,11.935],"type":"Point"}
}