{
  "type": "Feature",
  "properties": {
    "gn:admin1_code":"03",
    "gn:admin2_code":"64",
    "gn:admin3_code":"37114000.0",
    "gn:asciiname":"Cabitaogan",
    "gn:country_code":"PH",
    "gn:dem":13,
    "gn:feature_class":"P",
    "gn:feature_code":"PPL",
    "gn:name":"Cabitaogan",
    "gn:population":0,
    "gn:timezone":"Asia/Manila",
    "iso:country":"PH",
    "name:fil_x_preferred":[
        "Cabitaogan"
    ],
    "name:und_x_variant":[
        "Cabitaugan"
    ],
    "wof:name":"Cabitaogan",
    "wof:placetype":"locality"
},
  "geometry": {"coordinates":[120.20583000000001,14.87309],"type":"Point"}
}