{
  "type": "Feature",
  "properties": {
    "gn:country":"PH",
    "gn:fcode":"PPLA3",
    "gn:population":101037,
    "iso:country":"PH",
    "name:ara_x_preferred":[
        "\u0627\u0648\u0631\u062f\u0627\u0646\u064a\u062a\u0627"
    ],
    "name:bcl_x_preferred":[
        "Urdaneta"
    ],
    "name:ben_x_preferred":[
        "\u0986\u09b0\u09a1\u09be\u09a8\u09c7\u099f\u09be"
    ],
    "name:ceb_x_preferred":[
        "Urdaneta"
    ],
    "name:dan_x_preferred":[
        "Urdaneta"
    ],
    "name:deu_x_preferred":[
        "Urdaneta"
    ],
    "name:diq_x_preferred":[
        "Urdaneta"
    ],
    "name:ell_x_preferred":[
        "\u039f\u03c5\u03c1\u03bd\u03c4\u03b1\u03bd\u03ad\u03c4\u03b1"
    ],
    "name:eng_x_preferred":[
        "Urdaneta"
    ],
    "name:fin_x_preferred":[
        "Urdaneta"
    ],
    "name:fra_x_preferred":[
        "Urdaneta"
    ],
    "name:guj_x_preferred":[
        "\u0a89\u0ab0\u0acd\u0aa6\u0aa8\u0abf\u0a9f\u0abe"
    ],
    "name:hin_x_preferred":[
        "\u0909\u0921\u094d\u0921\u093e\u0923\u0947\u0924\u093e"
    ],
    "name:hun_x_preferred":[
        "Urdaneta"
    ],
    "name:ilo_x_preferred":[
        "Urdaneta"
    ],
    "name:ind_x_preferred":[
        "Kota Urdaneta"
    ],
    "name:ind_x_variant":[
        "Urdaneta City"
    ],
    "name:ita_x_preferred":[
        "Urdaneta"
    ],
    "name:jpn_x_preferred":[
        "\u30a6\u30eb\u30c0\u30cd\u30fc\u30bf"
    ],
    "name:kan_x_preferred":[
        "\u0c89\u0cb0\u0ccd\u0ca1\u0ca8\u0cc6\u0c9f"
    ],
    "name:kor_x_preferred":[
        "\uc6b0\ub974\ub2e4\ub124\ud0c0"
    ],
    "name:lav_x_preferred":[
        "Urdaneta"
    ],
    "name:lit_x_preferred":[
        "Urdaneta"
    ],
    "name:mar_x_preferred":[
        "\u0909\u0930\u094d\u0921\u0928\u093f\u091f\u093e"
    ],
    "name:msa_x_preferred":[
        "Urdaneta"
    ],
    "name:nld_x_preferred":[
        "Urdaneta"
    ],
    "name:nob_x_preferred":[
        "Urdaneta"
    ],
    "name:pag_x_preferred":[
        "Urdaneta City"
    ],
    "name:pag_x_variant":[
        "Urdaneta"
    ],
    "name:pam_x_preferred":[
        "Urdaneta Lakanbalen"
    ],
    "name:pol_x_preferred":[
        "Urdaneta"
    ],
    "name:por_x_preferred":[
        "Urdaneta"
    ],
    "name:rus_x_preferred":[
        "\u0423\u0440\u0434\u0430\u043d\u0435\u0442\u0430"
    ],
    "name:sin_x_preferred":[
        "\u0d85\u0dbb\u0dca\u0da9\u0db1\u0dda\u0da7\u0dcf"
    ],
    "name:spa_x_preferred":[
        "Urdaneta de Pangasin\u00e1n"
    ],
    "name:spa_x_variant":[
        "Urdaneta"
    ],
    "name:swe_x_preferred":[
        "Urdaneta"
    ],
    "name:tam_x_preferred":[
        "\u0bb5\u0bc2\u0bb0\u0bcd\u0ba4\u0bbe\u0ba9\u0bc6\u0b9f\u0bcd"
    ],
    "name:tel_x_preferred":[
        "\u0c09\u0c30\u0c4d\u0c21\u0c28\u0c47\u0c24"
    ],
    "name:tgl_x_preferred":[
        "Urdaneta"
    ],
    "name:tha_x_preferred":[
        "\u0e2d\u0e39\u0e23\u0e4c\u0e14\u0e32\u0e40\u0e19\u0e15\u0e32"
    ],
    "name:tur_x_preferred":[
        "Urdaneta"
    ],
    "name:ukr_x_preferred":[
        "\u0423\u0440\u0434\u0430\u043d\u0435\u0442\u0430"
    ],
    "name:urd_x_preferred":[
        "\u0648\u0631\u062f\u0627\u0646\u06cc\u062a\u0627"
    ],
    "name:vie_x_preferred":[
        "Urdaneta"
    ],
    "name:war_x_preferred":[
        "Urdaneta"
    ],
    "qs:name":"Urdaneta",
    "qs:photos_9r":0,
    "qs:photos_sr":0,
    "qs:pop_sr":"9",
    "wd:wordcount":108,
    "wof:name":"Urdaneta",
    "wof:placetype":"locality",
    "wof:population":101037
},
  "geometry": {"coordinates":[120.57111,15.97611],"type":"Point"}
}