{
  "type": "Feature",
  "properties": {
    "gn:admin1_code":"01",
    "gn:admin2_code":"51",
    "gn:admin3_code":"15507000.0",
    "gn:asciiname":"Mabini",
    "gn:country_code":"PH",
    "gn:dem":102,
    "gn:feature_class":"P",
    "gn:feature_code":"PPL",
    "gn:name":"Mabini",
    "gn:population":0,
    "gn:timezone":"Asia/Manila",
    "iso:country":"PH",
    "name:ceb_x_preferred":[
        "Mabini"
    ],
    "name:deu_x_preferred":[
        "Mabini"
    ],
    "name:fil_x_preferred":[
        "Mabini"
    ],
    "name:fra_x_preferred":[
        "Mabini"
    ],
    "name:ilo_x_preferred":[
        "Mabini"
    ],
    "name:ita_x_preferred":[
        "Mabini"
    ],
    "name:nld_x_preferred":[
        "Mabini"
    ],
    "name:nor_x_preferred":[
        "Mabini"
    ],
    "name:spa_x_preferred":[
        "Mabini"
    ],
    "name:swe_x_preferred":[
        "Mabini"
    ],
    "name:war_x_preferred":[
        "Mabini"
    ],
    "wof:name":"Mabini",
    "wof:placetype":"locality"
},
  "geometry": {"coordinates":[120.70132,15.85681],"type":"Point"}
}