{
  "type": "Feature",
  "properties": {
    "gn:admin1_code":"07",
    "gn:admin2_code":"21",
    "gn:admin3_code":"72237000.0",
    "gn:asciiname":"Cabiangon",
    "gn:country_code":"PH",
    "gn:dem":4,
    "gn:feature_class":"P",
    "gn:feature_code":"PPL",
    "gn:name":"Cabiangon",
    "gn:population":0,
    "gn:timezone":"Asia/Manila",
    "iso:country":"PH",
    "wof:name":"Cabiangon",
    "wof:placetype":"locality"
},
  "geometry": {"coordinates":[123.58333,10.26667],"type":"Point"}
}