{
  "type": "Feature",
  "properties": {
    "gn:admin1_code":"41",
    "gn:admin2_code":"49",
    "gn:admin3_code":"175313000.0",
    "gn:asciiname":"Bina",
    "gn:country_code":"PH",
    "gn:dem":17,
    "gn:feature_class":"P",
    "gn:feature_code":"PPL",
    "gn:name":"Bina",
    "gn:population":0,
    "gn:timezone":"Asia/Manila",
    "iso:country":"PH",
    "name:ceb_x_preferred":[
        "Bina"
    ],
    "name:deu_x_preferred":[
        "Bina"
    ],
    "name:fil_x_preferred":[
        "Bina"
    ],
    "name:heb_x_preferred":[
        "\u05d1\u05d9\u05e0\u05d4"
    ],
    "name:hin_x_preferred":[
        "\u092c\u0940\u0928\u093e"
    ],
    "name:ita_x_preferred":[
        "Bina"
    ],
    "name:por_x_preferred":[
        "Bina"
    ],
    "name:srp_x_preferred":[
        "\u0411\u0438\u043d\u0430"
    ],
    "name:swe_x_preferred":[
        "Bina"
    ],
    "name:tur_x_preferred":[
        "Bina"
    ],
    "wof:name":"Bina",
    "wof:placetype":"locality"
},
  "geometry": {"coordinates":[119.7696,11.4197],"type":"Point"}
}