{
  "type": "Feature",
  "properties": {
    "gn:admin1_code":"41",
    "gn:admin2_code":"49",
    "gn:admin3_code":"175313000.0",
    "gn:asciiname":"Bina",
    "gn:country_code":"PH",
    "gn:dem":17,
    "gn:feature_class":"P",
    "gn:feature_code":"PPL",
    "gn:name":"Bina",
    "gn:population":0,
    "gn:timezone":"Asia/Manila",
    "iso:country":"PH",
    "name:fil_x_preferred":[
        "Bina"
    ],
    "wof:name":"Bina",
    "wof:placetype":"locality"
},
  "geometry": {"coordinates":[119.7696,11.4197],"type":"Point"}
}