{
  "type": "Feature",
  "properties": {
    "gn:country":"PH",
    "gn:fcode":"ADM3",
    "gn:population":66290,
    "iso:country":"PH",
    "name:fil_x_preferred":[
        "Oas"
    ],
    "qs:name":"Oas",
    "qs:photos_9r":0,
    "qs:photos_sr":0,
    "qs:pop_sr":"8",
    "wof:name":"Oas",
    "wof:placetype":"localadmin",
    "wof:population":66290
},
  "geometry": {"coordinates":[123.34999999999999,13.15],"type":"Point"}
}