{
  "type": "Feature",
  "properties": {
    "gn:admin1_code":"07",
    "gn:admin2_code":"21",
    "gn:admin3_code":"72220000.0",
    "gn:asciiname":"Hilotongan",
    "gn:country_code":"PH",
    "gn:dem":5,
    "gn:feature_class":"P",
    "gn:feature_code":"PPL",
    "gn:name":"Hilotongan",
    "gn:population":0,
    "gn:timezone":"Asia/Manila",
    "iso:country":"PH",
    "name:fil_x_preferred":[
        "Hilotongan"
    ],
    "wof:name":"Hilotongan",
    "wof:placetype":"locality"
},
  "geometry": {"coordinates":[123.95,10.25],"type":"Point"}
}