{
  "type": "Feature",
  "properties": {
    "iso:country":"PH",
    "name:bcl_x_preferred":[
        "Sinait"
    ],
    "name:cat_x_preferred":[
        "Sinait"
    ],
    "name:cbk_zam_x_preferred":[
        "Sinait"
    ],
    "name:ceb_x_preferred":[
        "Sinait"
    ],
    "name:deu_x_preferred":[
        "Sinait"
    ],
    "name:eng_x_preferred":[
        "Sinait"
    ],
    "name:fil_x_preferred":[
        "Sinuat"
    ],
    "name:fra_x_preferred":[
        "Sinait"
    ],
    "name:ilo_x_preferred":[
        "Sinait"
    ],
    "name:ind_x_preferred":[
        "Sinait"
    ],
    "name:ita_x_preferred":[
        "Sinait"
    ],
    "name:nld_x_preferred":[
        "Sinait"
    ],
    "name:oci_x_preferred":[
        "Sinait"
    ],
    "name:pag_x_preferred":[
        "Sinait"
    ],
    "name:pam_x_preferred":[
        "Sinait"
    ],
    "name:spa_x_preferred":[
        "Sinait"
    ],
    "name:swe_x_preferred":[
        "Sinait"
    ],
    "name:tgl_x_preferred":[
        "Sinait"
    ],
    "name:war_x_preferred":[
        "Sinait"
    ],
    "name:zho_x_preferred":[
        "\u935a\u5948\u7279"
    ],
    "qs:gn_country":"PH",
    "qs:gn_fcode":"PPL",
    "qs:gn_pop":0,
    "qs:name":"Sinait",
    "qs:name_adm0":"Philippines",
    "qs:name_adm1":"Ilocos Region",
    "qs:photos":197,
    "qs:photos_1k":40,
    "qs:photos_9k":1,
    "qs:photos_9r":4,
    "qs:photos_all":197,
    "qs:photos_sr":4,
    "qs:placetype":"Town",
    "qs:pop_sr":"0",
    "qs:woe_adm0":23424934,
    "wd:wordcount":1038,
    "wof:name":"Sinait",
    "wof:placetype":"locality"
},
  "geometry": {"coordinates":[120.61790000000001,17.9762],"type":"Point"}
}