{
  "type": "Feature",
  "properties": {
    "gn:admin1_code":"05",
    "gn:admin2_code":"16",
    "gn:asciiname":"Sibobo",
    "gn:country_code":"PH",
    "gn:dem":1,
    "gn:feature_class":"P",
    "gn:feature_code":"PPL",
    "gn:name":"Sibobo",
    "gn:population":0,
    "gn:timezone":"Asia/Manila",
    "iso:country":"PH",
    "name:fil_x_preferred":[
        "Sibobo"
    ],
    "wof:name":"Sibobo",
    "wof:placetype":"locality"
},
  "geometry": {"coordinates":[123.28333000000001,13.76667],"type":"Point"}
}