{
  "type": "Feature",
  "properties": {
    "gn:admin1_code":"07",
    "gn:admin2_code":"46",
    "gn:admin3_code":"74607000.0",
    "gn:asciiname":"Salong",
    "gn:country_code":"PH",
    "gn:dem":137,
    "gn:feature_class":"P",
    "gn:feature_code":"PPL",
    "gn:name":"Salong",
    "gn:population":0,
    "gn:timezone":"Asia/Manila",
    "iso:country":"PH",
    "name:ceb_x_preferred":[
        "Salong"
    ],
    "name:fil_x_preferred":[
        "Salong"
    ],
    "name:nor_x_preferred":[
        "Salong"
    ],
    "name:swe_x_preferred":[
        "Salong"
    ],
    "wof:name":"Salong",
    "wof:placetype":"locality"
},
  "geometry": {"coordinates":[123.1391,9.73],"type":"Point"}
}