{
  "type": "Feature",
  "properties": {
    "gn:admin1_code":"06",
    "gn:admin2_code":"06",
    "gn:admin3_code":"60614000.0",
    "gn:asciiname":"Bangcuan",
    "gn:country_code":"PH",
    "gn:dem":302,
    "gn:feature_class":"P",
    "gn:feature_code":"PPL",
    "gn:name":"Bangcuan",
    "gn:population":0,
    "gn:timezone":"Asia/Manila",
    "iso:country":"PH",
    "name:fil_x_preferred":[
        "Bangcuan"
    ],
    "wof:name":"Bangcuan",
    "wof:placetype":"locality"
},
  "geometry": {"coordinates":[122.08629999999999,10.8714],"type":"Point"}
}