{
  "type": "Feature",
  "properties": {
    "gn:admin1_code":"40",
    "gn:admin2_code":"09",
    "gn:admin3_code":"41032000.0",
    "gn:asciiname":"Bucal",
    "gn:country_code":"PH",
    "gn:dem":150,
    "gn:feature_class":"P",
    "gn:feature_code":"PPL",
    "gn:name":"Bucal",
    "gn:population":0,
    "gn:timezone":"Asia/Manila",
    "iso:country":"PH",
    "name:fil_x_preferred":[
        "Bucal"
    ],
    "name:und_x_variant":[
        "Bukal"
    ],
    "wof:name":"Bucal",
    "wof:placetype":"locality"
},
  "geometry": {"coordinates":[121.2225,13.7806],"type":"Point"}
}