{
  "type": "Feature",
  "properties": {
    "gn:admin1_code":"06",
    "gn:admin2_code":"J3",
    "gn:admin3_code":"67901000.0",
    "gn:asciiname":"Salvacion",
    "gn:country_code":"PH",
    "gn:dem":19,
    "gn:feature_class":"P",
    "gn:feature_code":"PPL",
    "gn:name":"Salvacion",
    "gn:population":5565,
    "gn:timezone":"Asia/Manila",
    "iso:country":"PH",
    "name:fil_x_preferred":[
        "Salvacion"
    ],
    "wof:name":"Salvacion",
    "wof:placetype":"locality",
    "wof:population":5565
},
  "geometry": {"coordinates":[122.61667,10.68333],"type":"Point"}
}