{
  "type": "Feature",
  "properties": {
    "gn:admin1_code":"14",
    "gn:admin2_code":"35",
    "gn:admin3_code":"153619000.0",
    "gn:asciiname":"Mulundo",
    "gn:country_code":"PH",
    "gn:dem":708,
    "gn:feature_class":"P",
    "gn:feature_code":"PPL",
    "gn:name":"Mulundo",
    "gn:population":0,
    "gn:timezone":"Asia/Manila",
    "iso:country":"PH",
    "name:und_x_variant":[
        "Mulundu",
        "Mulundo",
        "Molundu",
        "Molundo"
    ],
    "wof:name":"Mulundo",
    "wof:placetype":"locality"
},
  "geometry": {"coordinates":[124.35639,7.91917],"type":"Point"}
}