{
  "type": "Feature",
  "properties": {
    "gn:admin1_code":"06",
    "gn:admin2_code":"J3",
    "gn:admin3_code":"67902000.0",
    "gn:asciiname":"Pangasinan",
    "gn:country_code":"PH",
    "gn:dem":14,
    "gn:feature_class":"P",
    "gn:feature_code":"PPL",
    "gn:name":"Pangasinan",
    "gn:population":0,
    "gn:timezone":"Asia/Manila",
    "iso:country":"PH",
    "name:fil_x_preferred":[
        "Pangasinan"
    ],
    "wof:name":"Pangasinan",
    "wof:placetype":"locality"
},
  "geometry": {"coordinates":[122.51779999999999,10.58336],"type":"Point"}
}