{
  "type": "Feature",
  "properties": {
    "gn:admin1_code":"02",
    "gn:admin2_code":"14",
    "gn:admin3_code":"21501000.0",
    "gn:asciiname":"Filomena",
    "gn:country_code":"PH",
    "gn:dem":21,
    "gn:feature_class":"P",
    "gn:feature_code":"PPL",
    "gn:name":"Filomena",
    "gn:population":0,
    "gn:timezone":"Asia/Manila",
    "iso:country":"PH",
    "name:deu_x_preferred":[
        "Filomena"
    ],
    "name:fil_x_preferred":[
        "Filomena"
    ],
    "name:hun_x_preferred":[
        "Filom\u00e9na"
    ],
    "name:ita_x_preferred":[
        "Filomena"
    ],
    "name:nor_x_preferred":[
        "Filomena"
    ],
    "name:pol_x_preferred":[
        "Filomena"
    ],
    "name:slk_x_preferred":[
        "Filom\u00e9na"
    ],
    "wof:name":"Filomena",
    "wof:placetype":"locality"
},
  "geometry": {"coordinates":[121.45762999999999,18.40802],"type":"Point"}
}