{
  "type": "Feature",
  "properties": {
    "gn:admin1_code":"06",
    "gn:admin2_code":"30",
    "gn:admin3_code":"63030000.0",
    "gn:asciiname":"Paraon",
    "gn:country_code":"PH",
    "gn:dem":87,
    "gn:feature_class":"P",
    "gn:feature_code":"PPL",
    "gn:name":"Paraon",
    "gn:population":0,
    "gn:timezone":"Asia/Manila",
    "iso:country":"PH",
    "name:fil_x_preferred":[
        "Paraon"
    ],
    "wof:name":"Paraon",
    "wof:placetype":"locality"
},
  "geometry": {"coordinates":[122.1677,10.6561],"type":"Point"}
}