{
  "type": "Feature",
  "properties": {
    "gn:country":"PH",
    "gn:fcode":"PPL",
    "gn:population":4688,
    "iso:country":"PH",
    "name:arg_x_preferred":[
        "Azagra"
    ],
    "name:bre_x_preferred":[
        "Azagra"
    ],
    "name:cat_x_preferred":[
        "Azagra"
    ],
    "name:ceb_x_preferred":[
        "Azagra"
    ],
    "name:eus_x_preferred":[
        "Azagra"
    ],
    "name:fil_x_preferred":[
        "Azagra"
    ],
    "name:fra_x_preferred":[
        "Azagra"
    ],
    "name:hun_x_preferred":[
        "Azagra"
    ],
    "name:ita_x_preferred":[
        "Azagra"
    ],
    "name:lat_x_preferred":[
        "Azagra"
    ],
    "name:msa_x_preferred":[
        "Azagra"
    ],
    "name:nld_x_preferred":[
        "Azagra"
    ],
    "name:oci_x_preferred":[
        "Azagra"
    ],
    "name:pol_x_preferred":[
        "Azagra"
    ],
    "name:por_x_preferred":[
        "Azagra"
    ],
    "name:rus_x_preferred":[
        "\u0410\u0441\u0430\u0433\u0440\u0430"
    ],
    "name:spa_x_preferred":[
        "Azagra"
    ],
    "name:swe_x_preferred":[
        "Azagra"
    ],
    "name:ukr_x_preferred":[
        "\u0410\u0441\u0430\u0433\u0440\u0430"
    ],
    "name:vie_x_preferred":[
        "Azagra"
    ],
    "name:war_x_preferred":[
        "Azagra"
    ],
    "name:zho_x_preferred":[
        "\u963f\u8428\u683c\u62c9"
    ],
    "qs_pg:aaroncc":"PH",
    "qs_pg:gn_country":"PH",
    "qs_pg:gn_fcode":"PPL",
    "qs_pg:gn_pop":4688,
    "qs_pg:name":"Azagra",
    "qs_pg:photos_9r":0,
    "qs_pg:photos_sr":0,
    "qs_pg:pop_sr":4,
    "qs_pg:qs_pg_placetype":"locality",
    "wof:name":"Azagra",
    "wof:placetype":"locality",
    "wof:population":4688
},
  "geometry": {"coordinates":[123.1367,9.4779],"type":"Point"}
}