{
  "type": "Feature",
  "properties": {
    "gn:gn_country":"PH",
    "gn:gn_fcode":"PPL",
    "gn:gn_pop":4688,
    "gn:population":4688,
    "iso:country":"PH",
    "name:fil_x_preferred":[
        "Azagra"
    ],
    "qs_pg:aaroncc":"PH",
    "qs_pg:gn_country":"PH",
    "qs_pg:gn_fcode":"PPL",
    "qs_pg:gn_pop":4688,
    "qs_pg:name":"Azagra",
    "qs_pg:photos_9r":0,
    "qs_pg:photos_sr":0,
    "qs_pg:pop_sr":4,
    "qs_pg:qs_pg_placetype":"locality",
    "wof:name":"Azagra",
    "wof:placetype":"locality",
    "wof:population":4688
},
  "geometry": {"coordinates":[123.1367,9.4779],"type":"Point"}
}