{
  "type": "Feature",
  "properties": {
    "gn:admin1_code":"15",
    "gn:admin2_code":"10",
    "gn:admin3_code":"141106000.0",
    "gn:asciiname":"Cabaritan",
    "gn:country_code":"PH",
    "gn:dem":419,
    "gn:feature_class":"P",
    "gn:feature_code":"PPL",
    "gn:name":"Cabaritan",
    "gn:population":0,
    "gn:timezone":"Asia/Manila",
    "iso:country":"PH",
    "name:fil_x_preferred":[
        "Capolitan"
    ],
    "name:fil_x_variant":[
        "Cabaritan"
    ],
    "wof:name":"Cabaritan",
    "wof:placetype":"locality"
},
  "geometry": {"coordinates":[120.73011,16.3078],"type":"Point"}
}