{
  "type": "Feature",
  "properties": {
    "gn:admin1_code":"NCR",
    "gn:admin2_code":"137500000",
    "gn:admin3_code":"137504000.0",
    "gn:asciiname":"Mapulanglupa",
    "gn:country_code":"PH",
    "gn:dem":30,
    "gn:feature_class":"P",
    "gn:feature_code":"PPL",
    "gn:name":"Mapulanglupa",
    "gn:population":0,
    "gn:timezone":"Asia/Manila",
    "iso:country":"PH",
    "name:fil_x_preferred":[
        "Mapulang Lupa"
    ],
    "wof:name":"Mapulanglupa",
    "wof:placetype":"locality"
},
  "geometry": {"coordinates":[121.0055,14.7018],"type":"Point"}
}