{
  "type": "Feature",
  "properties": {
    "gn:admin1_code":"40",
    "gn:admin2_code":"09",
    "gn:admin3_code":"41025000.0",
    "gn:asciiname":"Sinturisan",
    "gn:country_code":"PH",
    "gn:dem":77,
    "gn:feature_class":"P",
    "gn:feature_code":"PPL",
    "gn:name":"Sinturisan",
    "gn:population":0,
    "gn:timezone":"Asia/Manila",
    "iso:country":"PH",
    "name:fil_x_preferred":[
        "Sinturisan"
    ],
    "wof:name":"Sinturisan",
    "wof:placetype":"locality"
},
  "geometry": {"coordinates":[120.9367,13.90902],"type":"Point"}
}