{
  "type": "Feature",
  "properties": {
    "gn:admin1_code":"02",
    "gn:admin2_code":"31",
    "gn:admin3_code":"23137000.0",
    "gn:asciiname":"Annafunan",
    "gn:country_code":"PH",
    "gn:dem":39,
    "gn:feature_class":"P",
    "gn:feature_code":"PPL",
    "gn:name":"Annafunan",
    "gn:population":0,
    "gn:timezone":"Asia/Manila",
    "iso:country":"PH",
    "name:fil_x_preferred":[
        "Annafunan"
    ],
    "wof:name":"Annafunan",
    "wof:placetype":"locality"
},
  "geometry": {"coordinates":[121.80522999999999,17.28477],"type":"Point"}
}