{
  "type": "Feature",
  "properties": {
    "gn:admin1_code":"08",
    "gn:admin2_code":"55",
    "gn:admin3_code":"86001000.0",
    "gn:asciiname":"Bagacay",
    "gn:country_code":"PH",
    "gn:dem":24,
    "gn:feature_class":"P",
    "gn:feature_code":"PPL",
    "gn:name":"Bagacay",
    "gn:population":0,
    "gn:timezone":"Asia/Manila",
    "iso:country":"PH",
    "name:fil_x_preferred":[
        "Bagacay"
    ],
    "wof:name":"Bagacay",
    "wof:placetype":"locality"
},
  "geometry": {"coordinates":[124.2958,11.9302],"type":"Point"}
}