{
  "type": "Feature",
  "properties": {
    "gn:admin1_code":"12",
    "gn:admin2_code":"57",
    "gn:admin3_code":"124714000.0",
    "gn:asciiname":"Dimagaling",
    "gn:country_code":"PH",
    "gn:dem":25,
    "gn:feature_class":"P",
    "gn:feature_code":"PPL",
    "gn:name":"Dimagaling",
    "gn:population":0,
    "gn:timezone":"Asia/Manila",
    "iso:country":"PH",
    "name:fil_x_preferred":[
        "Dimagaling"
    ],
    "wof:name":"Dimagaling",
    "wof:placetype":"locality"
},
  "geometry": {"coordinates":[124.87833000000001,6.79944],"type":"Point"}
}