{
  "type": "Feature",
  "properties": {
    "gn:country":"PH",
    "gn:fcode":"ADM3",
    "gn:pop":38690,
    "iso:country":"PH",
    "name:eng_x_preferred":[
        "Municipality of Panglima Sugala"
    ],
    "name:unk_x_variant":[
        "Balimbing"
    ],
    "qs:name":"Municipality of Panglima Sugala",
    "qs:photos_9r":0,
    "qs:photos_sr":0,
    "qs:pop_sr":"7",
    "wd:wordcount":201,
    "wof:name":"Municipality of Panglima Sugala",
    "wof:placetype":"localadmin",
    "wof:population":38690
},
  "geometry": {"coordinates":[120.06180000000001,5.1908],"type":"Point"}
}