{
  "type": "Feature",
  "properties": {
    "gn:country":"PH",
    "gn:fcode":"ADM3",
    "gn:population":38690,
    "iso:country":"PH",
    "name:bcl_x_preferred":[
        "Panglima Sugala"
    ],
    "name:ceb_x_preferred":[
        "Panglima Sugala"
    ],
    "name:deu_x_preferred":[
        "Panglima Sugala"
    ],
    "name:eng_x_preferred":[
        "Municipality of Panglima Sugala"
    ],
    "name:eng_x_variant":[
        "Panglima Sugala"
    ],
    "name:fra_x_preferred":[
        "Panglima Sugala"
    ],
    "name:ilo_x_preferred":[
        "Panglima Sugala"
    ],
    "name:ind_x_preferred":[
        "Panglima Sugala"
    ],
    "name:ita_x_preferred":[
        "Panglima Sugala"
    ],
    "name:nld_x_preferred":[
        "Panglima Sugala"
    ],
    "name:nob_x_preferred":[
        "Panglima Sugala"
    ],
    "name:pag_x_preferred":[
        "Panglima Sugala"
    ],
    "name:pam_x_preferred":[
        "Panglima Sugala"
    ],
    "name:spa_x_preferred":[
        "Panglima Sugala"
    ],
    "name:swe_x_preferred":[
        "Panglima Sugala"
    ],
    "name:tgl_x_preferred":[
        "Panglima Sugala"
    ],
    "name:und_x_variant":[
        "Balimbing"
    ],
    "name:urd_x_preferred":[
        "\u067e\u0627\u0646\u06af\u0644\u06cc\u0645\u0627 \u0633\u0648\u06af\u0627\u0644\u0627"
    ],
    "name:vie_x_preferred":[
        "Panglima Sugala"
    ],
    "name:war_x_preferred":[
        "Panglima Sugala"
    ],
    "qs:name":"Municipality of Panglima Sugala",
    "qs:photos_9r":0,
    "qs:photos_sr":0,
    "qs:pop_sr":"7",
    "wd:wordcount":201,
    "wof:name":"Municipality of Panglima Sugala",
    "wof:placetype":"localadmin",
    "wof:population":38690
},
  "geometry": {"coordinates":[120.06180000000001,5.1908],"type":"Point"}
}