{
  "type": "Feature",
  "properties": {
    "gn:admin1_code":"01",
    "gn:admin2_code":"51",
    "gn:admin3_code":"15545000.0",
    "gn:asciiname":"Galarin",
    "gn:country_code":"PH",
    "gn:dem":18,
    "gn:feature_class":"P",
    "gn:feature_code":"PPL",
    "gn:name":"Galarin",
    "gn:population":0,
    "gn:timezone":"Asia/Manila",
    "iso:country":"PH",
    "name:fil_x_preferred":[
        "Galarin"
    ],
    "name:und_x_variant":[
        "Galarim"
    ],
    "wof:name":"Galarin",
    "wof:placetype":"locality"
},
  "geometry": {"coordinates":[120.36503999999999,15.79772],"type":"Point"}
}