{
  "type": "Feature",
  "properties": {
    "gn:admin1_code":"02",
    "gn:admin2_code":"14",
    "gn:admin3_code":"21514000.0",
    "gn:asciiname":"Balabalat",
    "gn:country_code":"PH",
    "gn:dem":9,
    "gn:feature_class":"P",
    "gn:feature_code":"PPL",
    "gn:name":"Balabalat",
    "gn:population":0,
    "gn:timezone":"Asia/Manila",
    "iso:country":"PH",
    "name:fil_x_preferred":[
        "Balabalat"
    ],
    "wof:name":"Balabalat",
    "wof:placetype":"locality"
},
  "geometry": {"coordinates":[122.03695,18.30477],"type":"Point"}
}