{
  "type": "Feature",
  "properties": {
    "gn:admin1_code":"05",
    "gn:admin2_code":"16",
    "gn:admin3_code":"51712000.0",
    "gn:asciiname":"Cabangajan",
    "gn:country_code":"PH",
    "gn:dem":34,
    "gn:feature_class":"P",
    "gn:feature_code":"PPL",
    "gn:name":"Cabangajan",
    "gn:population":0,
    "gn:timezone":"Asia/Manila",
    "iso:country":"PH",
    "name:fil_x_preferred":[
        "Cabangajan"
    ],
    "name:und_x_variant":[
        "Cabagnajan"
    ],
    "wof:name":"Cabangajan",
    "wof:placetype":"locality"
},
  "geometry": {"coordinates":[122.5746,13.9312],"type":"Point"}
}