{
  "type": "Feature",
  "properties": {
    "gn:admin1_code":"15",
    "gn:admin2_code":"01",
    "gn:admin3_code":"140116000.0",
    "gn:asciiname":"Bantaoay",
    "gn:country_code":"PH",
    "gn:dem":113,
    "gn:feature_class":"P",
    "gn:feature_code":"PPL",
    "gn:name":"Bantaoay",
    "gn:population":0,
    "gn:timezone":"Asia/Manila",
    "iso:country":"PH",
    "name:fil_x_preferred":[
        "Bantaoay"
    ],
    "wof:name":"Bantaoay",
    "wof:placetype":"locality"
},
  "geometry": {"coordinates":[120.7034,17.4368],"type":"Point"}
}