{
  "type": "Feature",
  "properties": {
    "gn:admin1_code":"08",
    "gn:admin2_code":"59",
    "gn:admin3_code":"86414000.0",
    "gn:asciiname":"Basak",
    "gn:country_code":"PH",
    "gn:dem":64,
    "gn:feature_class":"P",
    "gn:feature_code":"PPL",
    "gn:name":"Basak",
    "gn:population":0,
    "gn:timezone":"Asia/Manila",
    "iso:country":"PH",
    "name:ceb_x_preferred":[
        "Basak"
    ],
    "name:fil_x_preferred":[
        "Basak"
    ],
    "name:ita_x_preferred":[
        "Basak"
    ],
    "name:swe_x_preferred":[
        "Basak"
    ],
    "wof:name":"Basak",
    "wof:placetype":"locality"
},
  "geometry": {"coordinates":[125.18333,10.26667],"type":"Point"}
}