{
  "type": "Feature",
  "properties": {
    "gn:admin1_code":"02",
    "gn:admin2_code":"31",
    "gn:admin3_code":"23108000.0",
    "gn:asciiname":"Villa Capuchino",
    "gn:country_code":"PH",
    "gn:dem":83,
    "gn:feature_class":"P",
    "gn:feature_code":"PPL",
    "gn:name":"Villa Capuchino",
    "gn:population":0,
    "gn:timezone":"Asia/Manila",
    "iso:country":"PH",
    "name:fil_x_preferred":[
        "Villa Capuchino"
    ],
    "wof:name":"Villa Capuchino",
    "wof:placetype":"locality"
},
  "geometry": {"coordinates":[121.86194,16.89155],"type":"Point"}
}