{
  "type": "Feature",
  "properties": {
    "gn:admin1_code":"15",
    "gn:admin2_code":"10",
    "gn:admin3_code":"141105000.0",
    "gn:asciiname":"Bisokol",
    "gn:country_code":"PH",
    "gn:dem":1835,
    "gn:feature_class":"P",
    "gn:feature_code":"PPL",
    "gn:name":"Bisokol",
    "gn:population":0,
    "gn:timezone":"Asia/Manila",
    "iso:country":"PH",
    "name:fil_x_preferred":[
        "Bisokol"
    ],
    "wof:name":"Bisokol",
    "wof:placetype":"locality"
},
  "geometry": {"coordinates":[120.84504,16.68437],"type":"Point"}
}