{
  "type": "Feature",
  "properties": {
    "gn:admin1_code":"40",
    "gn:admin2_code":"H2",
    "gn:admin3_code":"45627000.0",
    "gn:asciiname":"Tapiyan",
    "gn:country_code":"PH",
    "gn:dem":28,
    "gn:feature_class":"P",
    "gn:feature_code":"PPL",
    "gn:name":"Tapiyan",
    "gn:population":0,
    "gn:timezone":"Asia/Manila",
    "iso:country":"PH",
    "name:fil_x_preferred":[
        "Tapiyan"
    ],
    "name:und_x_variant":[
        "Tapucan"
    ],
    "wof:name":"Tapiyan",
    "wof:placetype":"locality"
},
  "geometry": {"coordinates":[121.71666999999999,14.15],"type":"Point"}
}