{
  "type": "Feature",
  "properties": {
    "gn:admin1_code":"40",
    "gn:admin2_code":"09",
    "gn:admin3_code":"41010000.0",
    "gn:asciiname":"Coliat",
    "gn:country_code":"PH",
    "gn:dem":114,
    "gn:feature_class":"P",
    "gn:feature_code":"PPL",
    "gn:name":"Coliat",
    "gn:population":0,
    "gn:timezone":"Asia/Manila",
    "iso:country":"PH",
    "name:fil_x_preferred":[
        "Coliat"
    ],
    "name:und_x_variant":[
        "Kuliat"
    ],
    "wof:name":"Coliat",
    "wof:placetype":"locality"
},
  "geometry": {"coordinates":[121.1232,13.8132],"type":"Point"}
}