{
  "type": "Feature",
  "properties": {
    "gn:admin1_code":"05",
    "gn:admin2_code":"05",
    "gn:admin3_code":"50513000.0",
    "gn:asciiname":"Boton",
    "gn:country_code":"PH",
    "gn:dem":18,
    "gn:feature_class":"P",
    "gn:feature_code":"PPL",
    "gn:name":"Boton",
    "gn:population":0,
    "gn:timezone":"Asia/Manila",
    "iso:country":"PH",
    "name:fil_x_preferred":[
        "Boton"
    ],
    "name:nld_x_preferred":[
        "Boton"
    ],
    "wof:name":"Boton",
    "wof:placetype":"locality"
},
  "geometry": {"coordinates":[123.4525,13.04361],"type":"Point"}
}