{
  "type": "Feature",
  "properties": {
    "gn:admin1_code":"07",
    "gn:admin2_code":"11",
    "gn:admin3_code":"71230000.0",
    "gn:asciiname":"Giwanon",
    "gn:country_code":"PH",
    "gn:dem":68,
    "gn:feature_class":"P",
    "gn:feature_code":"PPL",
    "gn:name":"Giwanon",
    "gn:population":0,
    "gn:timezone":"Asia/Manila",
    "iso:country":"PH",
    "name:fil_x_preferred":[
        "Giwanon"
    ],
    "name:und_x_variant":[
        "Guiwanon"
    ],
    "wof:name":"Giwanon",
    "wof:placetype":"locality"
},
  "geometry": {"coordinates":[123.7897,9.7491],"type":"Point"}
}