{
  "type": "Feature",
  "properties": {
    "gn:admin1_code":"01",
    "gn:admin2_code":"36",
    "gn:admin3_code":"13319000.0",
    "gn:asciiname":"Puguil",
    "gn:country_code":"PH",
    "gn:dem":477,
    "gn:feature_class":"P",
    "gn:feature_code":"PPL",
    "gn:name":"Puguil",
    "gn:population":0,
    "gn:timezone":"Asia/Manila",
    "iso:country":"PH",
    "name:fil_x_preferred":[
        "Puguil"
    ],
    "name:fil_x_variant":[
        "Puguit",
        "Pugil"
    ],
    "wof:name":"Puguil",
    "wof:placetype":"locality"
},
  "geometry": {"coordinates":[120.51309999999999,16.7885],"type":"Point"}
}