{
  "type": "Feature",
  "properties": {
    "gn:admin1_code":"07",
    "gn:admin2_code":"11",
    "gn:admin3_code":"71225000.0",
    "gn:asciiname":"Cambugason",
    "gn:country_code":"PH",
    "gn:dem":36,
    "gn:feature_class":"P",
    "gn:feature_code":"PPL",
    "gn:name":"Cambugason",
    "gn:population":0,
    "gn:timezone":"Asia/Manila",
    "iso:country":"PH",
    "name:fil_x_preferred":[
        "Cambugason"
    ],
    "name:und_x_variant":[
        "Kambugason"
    ],
    "wof:name":"Cambugason",
    "wof:placetype":"locality"
},
  "geometry": {"coordinates":[124.3831,9.681],"type":"Point"}
}