{
  "type": "Feature",
  "properties": {
    "gn:admin1_code":"40",
    "gn:admin2_code":"09",
    "gn:admin3_code":"41003000.0",
    "gn:asciiname":"Dao",
    "gn:country_code":"PH",
    "gn:dem":89,
    "gn:feature_class":"P",
    "gn:feature_code":"PPL",
    "gn:name":"Dao",
    "gn:population":0,
    "gn:timezone":"Asia/Manila",
    "iso:country":"PH",
    "name:und_x_variant":[
        "Dao Tuy",
        "Dao"
    ],
    "wof:name":"Dao",
    "wof:placetype":"locality"
},
  "geometry": {"coordinates":[120.75626,13.98957],"type":"Point"}
}