{
  "type": "Feature",
  "properties": {
    "gn:country":"PH",
    "gn:fcode":"PPL",
    "gn:pop":3251,
    "iso:country":"PH",
    "name:bre_x_preferred":[
        "Esperanza"
    ],
    "name:ceb_x_preferred":[
        "Esperanza"
    ],
    "name:deu_x_preferred":[
        "Esperanza"
    ],
    "name:epo_x_preferred":[
        "Esperanza"
    ],
    "name:fil_x_preferred":[
        "Esperanza"
    ],
    "name:fra_x_preferred":[
        "Esperanza"
    ],
    "name:glg_x_preferred":[
        "Esperanza"
    ],
    "name:hye_x_preferred":[
        "\u0537\u057d\u057a\u0565\u0580\u0561\u0576\u057d\u0561"
    ],
    "name:ita_x_preferred":[
        "Esperanza"
    ],
    "name:jpn_x_preferred":[
        "\u30a8\u30b9\u30da\u30e9\u30f3\u30b5"
    ],
    "name:kor_x_preferred":[
        "\uc5d0\uc2a4\ud398\ub780\uc0ac"
    ],
    "name:nds_x_preferred":[
        "Esperanza"
    ],
    "name:nld_x_preferred":[
        "Esperanza"
    ],
    "name:por_x_preferred":[
        "Esperanza"
    ],
    "name:rus_x_preferred":[
        "\u042d\u0441\u043f\u0435\u0440\u0430\u043d\u0441\u0430"
    ],
    "name:spa_x_preferred":[
        "Esperanza"
    ],
    "name:srp_x_preferred":[
        "\u0415\u0441\u043f\u0435\u0440\u0430\u043d\u0437\u0430"
    ],
    "name:swe_x_preferred":[
        "Esperanza"
    ],
    "name:tgl_x_preferred":[
        "Esperanza"
    ],
    "name:vie_x_preferred":[
        "Esperanza"
    ],
    "name:war_x_preferred":[
        "Esperanza"
    ],
    "qs:name":"Esperanza",
    "qs:photos_9r":0,
    "qs:photos_sr":0,
    "qs:pop_sr":"4",
    "wd:wordcount":349,
    "wof:name":"Esperanza",
    "wof:placetype":"locality",
    "wof:population":3251
},
  "geometry": {"coordinates":[124.4143,10.7027],"type":"Point"}
}