{
  "type": "Feature",
  "properties": {
    "gn:country":"PH",
    "gn:fcode":"PPL",
    "gn:pop":3251,
    "iso:country":"PH",
    "name:fil_x_preferred":[
        "Esperanza"
    ],
    "qs:name":"Esperanza",
    "qs:photos_9r":0,
    "qs:photos_sr":0,
    "qs:pop_sr":"4",
    "wd:wordcount":349,
    "wof:name":"Esperanza",
    "wof:placetype":"locality",
    "wof:population":3251
},
  "geometry": {"coordinates":[124.4143,10.7027],"type":"Point"}
}