{
  "type": "Feature",
  "properties": {
    "gn:admin1_code":"41",
    "gn:admin2_code":"41",
    "gn:admin3_code":"175207000.0",
    "gn:asciiname":"Cogolong",
    "gn:country_code":"PH",
    "gn:dem":12,
    "gn:feature_class":"P",
    "gn:feature_code":"PPL",
    "gn:name":"Cogolong",
    "gn:population":0,
    "gn:timezone":"Asia/Manila",
    "iso:country":"PH",
    "name:fil_x_preferred":[
        "Cogolong"
    ],
    "wof:name":"Cogolong",
    "wof:placetype":"locality"
},
  "geometry": {"coordinates":[121.4366,12.4913],"type":"Point"}
}