{
  "type": "Feature",
  "properties": {
    "gn:country":"PH",
    "gn:fcode":"PPL",
    "gn:pop":2201,
    "iso:country":"PH",
    "name:fil_x_preferred":[
        "Lamak"
    ],
    "qs:name":"Lamak",
    "qs:photos_9r":0,
    "qs:photos_sr":0,
    "qs:pop_sr":"4",
    "wd:wordcount":12,
    "wof:name":"Lamak",
    "wof:placetype":"locality",
    "wof:population":2201
},
  "geometry": {"coordinates":[124.73889,10.39972],"type":"Point"}
}