{
  "type": "Feature",
  "properties": {
    "gn:country":"PH",
    "gn:fcode":"PPL",
    "gn:population":2201,
    "iso:country":"PH",
    "name:deu_x_preferred":[
        "Lamech"
    ],
    "name:fil_x_preferred":[
        "Lamak"
    ],
    "name:fra_x_preferred":[
        "Lamech"
    ],
    "name:pol_x_preferred":[
        "Lamech"
    ],
    "name:rus_x_preferred":[
        "\u041b\u0430\u043c\u0435\u0445"
    ],
    "name:spa_x_preferred":[
        "Lamec"
    ],
    "qs:name":"Lamak",
    "qs:photos_9r":0,
    "qs:photos_sr":0,
    "qs:pop_sr":"4",
    "wd:wordcount":12,
    "wof:name":"Lamak",
    "wof:placetype":"locality",
    "wof:population":2201
},
  "geometry": {"coordinates":[124.73889,10.39972],"type":"Point"}
}