{
  "type": "Feature",
  "properties": {
    "gn:admin1_code":"02",
    "gn:admin2_code":"31",
    "gn:admin3_code":"23102000.0",
    "gn:asciiname":"Rang-ayan",
    "gn:country_code":"PH",
    "gn:dem":104,
    "gn:feature_class":"P",
    "gn:feature_code":"PPL",
    "gn:name":"Rang-ayan",
    "gn:population":0,
    "gn:timezone":"Asia/Manila",
    "iso:country":"PH",
    "name:fil_x_preferred":[
        "Rangayan"
    ],
    "wof:name":"Rang-ayan",
    "wof:placetype":"locality"
},
  "geometry": {"coordinates":[121.88441,16.77897],"type":"Point"}
}