{
  "type": "Feature",
  "properties": {
    "gn:admin1_code":"02",
    "gn:admin2_code":"14",
    "gn:admin3_code":"21525000.0",
    "gn:asciiname":"Banggalao",
    "gn:country_code":"PH",
    "gn:dem":12,
    "gn:feature_class":"P",
    "gn:feature_code":"PPL",
    "gn:name":"Banggalao",
    "gn:population":0,
    "gn:timezone":"Asia/Manila",
    "iso:country":"PH",
    "name:fil_x_preferred":[
        "Banggalao"
    ],
    "wof:name":"Banggalao",
    "wof:placetype":"locality"
},
  "geometry": {"coordinates":[121.8737,18.2245],"type":"Point"}
}