{
  "type": "Feature",
  "properties": {
    "gn:admin1_code":"03",
    "gn:admin2_code":"47",
    "gn:admin3_code":"34927000.0",
    "gn:asciiname":"Bonifacio District",
    "gn:country_code":"PH",
    "gn:dem":33,
    "gn:feature_class":"P",
    "gn:feature_code":"PPL",
    "gn:name":"Bonifacio District",
    "gn:population":0,
    "gn:timezone":"Asia/Manila",
    "iso:country":"PH",
    "name:und_x_variant":[
        "Bonifacio"
    ],
    "wof:name":"Bonifacio District",
    "wof:placetype":"locality"
},
  "geometry": {"coordinates":[120.96493999999998,15.36837],"type":"Point"}
}