{
  "type": "Feature",
  "properties": {
    "gn:admin1_code":"01",
    "gn:admin2_code":"29",
    "gn:admin3_code":"12906000.0",
    "gn:asciiname":"San Jose de Bugnay",
    "gn:country_code":"PH",
    "gn:dem":45,
    "gn:feature_class":"P",
    "gn:feature_code":"PPL",
    "gn:name":"San Jose de Bugnay",
    "gn:population":0,
    "gn:timezone":"Asia/Manila",
    "iso:country":"PH",
    "name:fil_x_preferred":[
        "San Jose de Bugnay"
    ],
    "wof:name":"San Jose de Bugnay",
    "wof:placetype":"locality"
},
  "geometry": {"coordinates":[120.50806,17.20861],"type":"Point"}
}