{
  "type": "Feature",
  "properties": {
    "gn:admin1_code":"40",
    "gn:admin2_code":"H2",
    "gn:admin3_code":"45642000.0",
    "gn:asciiname":"Pagsanjan",
    "gn:country_code":"PH",
    "gn:dem":17,
    "gn:feature_class":"P",
    "gn:feature_code":"PPL",
    "gn:name":"Pagsanjan",
    "gn:population":0,
    "gn:timezone":"Asia/Manila",
    "iso:country":"PH",
    "name:fil_x_preferred":[
        "Pagsanjan"
    ],
    "wof:name":"Pagsanjan",
    "wof:placetype":"locality"
},
  "geometry": {"coordinates":[122.63697999999999,13.19119],"type":"Point"}
}