{
  "type": "Feature",
  "properties": {
    "gn:admin1_code":"07",
    "gn:admin2_code":"11",
    "gn:admin3_code":"71243000.0",
    "gn:asciiname":"Tanghaligue",
    "gn:country_code":"PH",
    "gn:dem":19,
    "gn:feature_class":"P",
    "gn:feature_code":"PPL",
    "gn:name":"Tanghaligue",
    "gn:population":0,
    "gn:timezone":"Asia/Manila",
    "iso:country":"PH",
    "name:fil_x_preferred":[
        "Tanghaligue"
    ],
    "wof:name":"Tanghaligue",
    "wof:placetype":"locality"
},
  "geometry": {"coordinates":[124.25299,10.14811],"type":"Point"}
}