{
  "type": "Feature",
  "properties": {
    "gn:admin1_code":"05",
    "gn:admin2_code":"15",
    "gn:admin3_code":"51603000.0",
    "gn:asciiname":"Danao",
    "gn:country_code":"PH",
    "gn:dem":14,
    "gn:feature_class":"P",
    "gn:feature_code":"PPL",
    "gn:name":"Danao",
    "gn:population":0,
    "gn:timezone":"Asia/Manila",
    "iso:country":"PH",
    "name:fil_x_preferred":[
        "Danao"
    ],
    "wof:name":"Danao",
    "wof:placetype":"locality"
},
  "geometry": {"coordinates":[122.93680000000001,14.114],"type":"Point"}
}