{
  "type": "Feature",
  "properties": {
    "gn:admin1_code":"03",
    "gn:admin2_code":"47",
    "gn:admin3_code":"34912000.0",
    "gn:asciiname":"Marcos",
    "gn:country_code":"PH",
    "gn:dem":26,
    "gn:feature_class":"P",
    "gn:feature_code":"PPL",
    "gn:name":"Marcos",
    "gn:population":0,
    "gn:timezone":"Asia/Manila",
    "iso:country":"PH",
    "name:ceb_x_preferred":[
        "Marcos"
    ],
    "name:deu_x_preferred":[
        "Marcos"
    ],
    "name:fil_x_preferred":[
        "Marcos"
    ],
    "name:fin_x_preferred":[
        "Marcos"
    ],
    "name:fra_x_preferred":[
        "Marcos"
    ],
    "name:glg_x_preferred":[
        "Marcos"
    ],
    "name:ilo_x_preferred":[
        "Marcos"
    ],
    "name:ita_x_preferred":[
        "Marcos"
    ],
    "name:jpn_x_preferred":[
        "\u30de\u30eb\u30b3\u30b9"
    ],
    "name:kor_x_preferred":[
        "\ub9c8\ub974\ucf54\uc2a4"
    ],
    "name:nld_x_preferred":[
        "Marcos"
    ],
    "name:nor_x_preferred":[
        "Marcos"
    ],
    "name:pol_x_preferred":[
        "Marcos"
    ],
    "name:por_x_preferred":[
        "Marcos"
    ],
    "name:rus_x_preferred":[
        "\u041c\u0430\u0440\u043a\u043e\u0441"
    ],
    "name:spa_x_preferred":[
        "Marcos"
    ],
    "name:swe_x_preferred":[
        "Marcos"
    ],
    "name:zho_x_preferred":[
        "\u9a6c\u79d1\u65af"
    ],
    "wof:name":"Marcos",
    "wof:placetype":"locality"
},
  "geometry": {"coordinates":[120.9127,15.3395],"type":"Point"}
}