{
  "type": "Feature",
  "properties": {
    "gn:admin1_code":"03",
    "gn:admin2_code":"64",
    "gn:admin3_code":"37114000.0",
    "gn:asciiname":"Calapandayan",
    "gn:country_code":"PH",
    "gn:dem":10,
    "gn:feature_class":"P",
    "gn:feature_code":"PPL",
    "gn:name":"Calapandayan",
    "gn:population":0,
    "gn:timezone":"Asia/Manila",
    "iso:country":"PH",
    "name:fil_x_preferred":[
        "Calapandayan"
    ],
    "wof:name":"Calapandayan",
    "wof:placetype":"locality"
},
  "geometry": {"coordinates":[120.23583000000001,14.87379],"type":"Point"}
}