{
  "type": "Feature",
  "properties": {
    "gn:admin1_code":"02",
    "gn:admin2_code":"31",
    "gn:admin3_code":"23112000.0",
    "gn:asciiname":"Caniguing",
    "gn:country_code":"PH",
    "gn:dem":94,
    "gn:feature_class":"P",
    "gn:feature_code":"PPL",
    "gn:name":"Caniguing",
    "gn:population":0,
    "gn:timezone":"Asia/Manila",
    "iso:country":"PH",
    "wof:name":"Caniguing",
    "wof:placetype":"locality"
},
  "geometry": {"coordinates":[121.77009,16.63918],"type":"Point"}
}