{
  "type": "Feature",
  "properties": {
    "gn:admin1_code":"08",
    "gn:admin2_code":"67",
    "gn:admin3_code":"84815000.0",
    "gn:asciiname":"Naganaga",
    "gn:country_code":"PH",
    "gn:dem":8,
    "gn:feature_class":"P",
    "gn:feature_code":"PPL",
    "gn:name":"Naganaga",
    "gn:population":0,
    "gn:timezone":"Asia/Manila",
    "iso:country":"PH",
    "name:fil_x_preferred":[
        "Naganaga"
    ],
    "wof:name":"Naganaga",
    "wof:placetype":"locality"
},
  "geometry": {"coordinates":[124.9174,12.5504],"type":"Point"}
}