{
  "type": "Feature",
  "properties": {
    "gn:country":"PH",
    "gn:fcode":"PPL",
    "gn:population":2083,
    "iso:country":"PH",
    "name:fil_x_preferred":[
        "Colinauan"
    ],
    "name:fil_x_variant":[
        "Calinauan",
        "Calinaoan"
    ],
    "qs:name":"Calinauan",
    "qs:photos_9r":0,
    "qs:photos_sr":0,
    "qs:pop_sr":"4",
    "wof:name":"Calinauan",
    "wof:placetype":"locality",
    "wof:population":2083
},
  "geometry": {"coordinates":[121.74234,17.36143],"type":"Point"}
}