{
  "type": "Feature",
  "properties": {
    "gn:country":"PH",
    "gn:fcode":"PPL",
    "gn:pop":21767,
    "iso:country":"PH",
    "name:ace_x_preferred":[
        "Propinsi Cebu"
    ],
    "name:ara_x_preferred":[
        "\u0633\u064a\u0628\u0648"
    ],
    "name:azb_x_preferred":[
        "\u0633\u06cc\u0628\u0648"
    ],
    "name:bcl_x_preferred":[
        "Cebu"
    ],
    "name:bre_x_preferred":[
        "Cebu"
    ],
    "name:ceb_x_preferred":[
        "Sugbo"
    ],
    "name:ces_x_preferred":[
        "Cebu"
    ],
    "name:dan_x_preferred":[
        "Cebu"
    ],
    "name:deu_x_preferred":[
        "Provinz Cebu"
    ],
    "name:epo_x_preferred":[
        "Cebuo"
    ],
    "name:fas_x_preferred":[
        "\u0633\u06cc\u0628\u0648"
    ],
    "name:fil_x_preferred":[
        "Sebu"
    ],
    "name:fin_x_preferred":[
        "Cebun provinssi"
    ],
    "name:fra_x_preferred":[
        "Cebu"
    ],
    "name:glg_x_preferred":[
        "Ceb\u00fa"
    ],
    "name:heb_x_preferred":[
        "\u05e1\u05d1\u05d5"
    ],
    "name:hin_x_preferred":[
        "\u0938\u093f\u092c\u0941"
    ],
    "name:ilo_x_preferred":[
        "Cebu"
    ],
    "name:ina_x_preferred":[
        "Provincia Cebu"
    ],
    "name:ind_x_preferred":[
        "Cebu"
    ],
    "name:jpn_x_preferred":[
        "\u30bb\u30d6\u5dde"
    ],
    "name:kor_x_preferred":[
        "\uc138\ubd80\uc8fc"
    ],
    "name:lat_x_preferred":[
        "Caebua"
    ],
    "name:lit_x_preferred":[
        "Sebu"
    ],
    "name:mal_x_preferred":[
        "\u0d38\u0d46\u0d2c\u0d42"
    ],
    "name:mkd_x_preferred":[
        "\u0421\u0435\u0431\u0443"
    ],
    "name:msa_x_preferred":[
        "Cebu"
    ],
    "name:nld_x_preferred":[
        "Cebu"
    ],
    "name:nno_x_preferred":[
        "Cebu"
    ],
    "name:nor_x_preferred":[
        "Cebu"
    ],
    "name:pag_x_preferred":[
        "Cebu"
    ],
    "name:pam_x_preferred":[
        "Cebu"
    ],
    "name:pol_x_preferred":[
        "Cebu"
    ],
    "name:por_x_preferred":[
        "Cebu"
    ],
    "name:rus_x_preferred":[
        "\u0421\u0435\u0431\u0443"
    ],
    "name:sco_x_preferred":[
        "Cebu"
    ],
    "name:srp_x_preferred":[
        "\u0421\u0435\u0431\u0443"
    ],
    "name:swe_x_preferred":[
        "Cebu"
    ],
    "name:tgl_x_preferred":[
        "Cebu"
    ],
    "name:tha_x_preferred":[
        "\u0e08\u0e31\u0e07\u0e2b\u0e27\u0e31\u0e14\u0e40\u0e0b\u0e1a\u0e39"
    ],
    "name:ukr_x_preferred":[
        "\u0421\u0435\u0431\u0443"
    ],
    "name:urd_x_preferred":[
        "\u0633\u06cc\u0628\u0648"
    ],
    "name:vie_x_preferred":[
        "Cebu"
    ],
    "name:war_x_preferred":[
        "Sugbo"
    ],
    "name:wuu_x_preferred":[
        "\u5bbf\u52a1\u7701"
    ],
    "name:yid_x_preferred":[
        "\u05e1\u05e2\u05d1\u05d5"
    ],
    "name:zho_x_preferred":[
        "\u5bbf\u9727\u7701"
    ],
    "qs:name":"Sebu",
    "qs:photos_9r":0,
    "qs:photos_sr":0,
    "qs:pop_sr":"7",
    "wd:wordcount":6739,
    "wof:name":"Sebu",
    "wof:placetype":"locality",
    "wof:population":21767
},
  "geometry": {"coordinates":[124.69361000000001,6.22],"type":"Point"}
}