{
  "type": "Feature",
  "properties": {
    "gn:country":"PH",
    "gn:fcode":"PPL",
    "gn:pop":21767,
    "iso:country":"PH",
    "name:fil_x_preferred":[
        "Sebu"
    ],
    "qs:name":"Sebu",
    "qs:photos_9r":0,
    "qs:photos_sr":0,
    "qs:pop_sr":"7",
    "wd:wordcount":6739,
    "wof:name":"Sebu",
    "wof:placetype":"locality",
    "wof:population":21767
},
  "geometry": {"coordinates":[124.69361000000001,6.22],"type":"Point"}
}