{
  "type": "Feature",
  "properties": {
    "gn:admin1_code":"14",
    "gn:admin2_code":"22",
    "gn:admin3_code":"150703000.0",
    "gn:asciiname":"Matarling",
    "gn:country_code":"PH",
    "gn:dem":142,
    "gn:feature_class":"P",
    "gn:feature_code":"PPL",
    "gn:name":"Matarling",
    "gn:population":0,
    "gn:timezone":"Asia/Manila",
    "iso:country":"PH",
    "name:eng_x_preferred":[
        "Matarling"
    ],
    "wof:name":"Matarling",
    "wof:placetype":"locality"
},
  "geometry": {"coordinates":[121.8933,6.6079],"type":"Point"}
}