{
  "type": "Feature",
  "properties": {
    "gn:country":"PH",
    "gn:fcode":"PPL",
    "gn:pop":1121974,
    "iso:country":"PH",
    "name:fil_x_preferred":[
        "Malingao"
    ],
    "qs:name":"Malingao",
    "qs:photos_9r":0,
    "qs:photos_sr":0,
    "qs:pop_sr":"12",
    "wof:name":"Malingao",
    "wof:placetype":"locality",
    "wof:population":1121974
},
  "geometry": {"coordinates":[124.47499999999999,7.16083],"type":"Point"}
}