{
  "type": "Feature",
  "properties": {
    "gn:gn_country":"PH",
    "gn:gn_fcode":"ADM3",
    "gn:gn_pop":23772,
    "gn:population":23772,
    "iso:country":"PH",
    "name:fil_x_preferred":[
        "Iguig"
    ],
    "qs_pg:aaroncc":"PH",
    "qs_pg:gn_country":"PH",
    "qs_pg:gn_fcode":"ADM3",
    "qs_pg:gn_pop":23772,
    "qs_pg:name":"Iguig",
    "qs_pg:photos_9r":0,
    "qs_pg:photos_sr":0,
    "qs_pg:pop_sr":7,
    "qs_pg:qs_pg_placetype":"localadmin",
    "wof:name":"Iguig",
    "wof:placetype":"localadmin",
    "wof:population":23772
},
  "geometry": {"coordinates":[121.76667,17.75],"type":"Point"}
}