{
  "type": "Feature",
  "properties": {
    "gn:admin1_code":"41",
    "gn:admin2_code":"54",
    "gn:admin3_code":"175903000.0",
    "gn:asciiname":"Talirao",
    "gn:country_code":"PH",
    "gn:dem":17,
    "gn:feature_class":"P",
    "gn:feature_code":"PPL",
    "gn:name":"Talirao",
    "gn:population":0,
    "gn:timezone":"Asia/Manila",
    "iso:country":"PH",
    "name:fil_x_preferred":[
        "Talirao"
    ],
    "wof:name":"Talirao",
    "wof:placetype":"locality"
},
  "geometry": {"coordinates":[122.66921000000001,12.44603],"type":"Point"}
}