{
  "type": "Feature",
  "properties": {
    "gn:admin1_code":"10",
    "gn:admin2_code":"34",
    "gn:admin3_code":"103516000.0",
    "gn:asciiname":"Bunat",
    "gn:country_code":"PH",
    "gn:dem":790,
    "gn:feature_class":"P",
    "gn:feature_code":"PPL",
    "gn:name":"Bunat",
    "gn:population":0,
    "gn:timezone":"Asia/Manila",
    "iso:country":"PH",
    "name:fil_x_preferred":[
        "Bunat"
    ],
    "wof:name":"Bunat",
    "wof:placetype":"locality"
},
  "geometry": {"coordinates":[124.15000000000001,8.05],"type":"Point"}
}