{
  "type": "Feature",
  "properties": {
    "gn:country":"PH",
    "gn:fcode":"PPL",
    "gn:pop":3155,
    "iso:country":"PH",
    "name:unk_x_variant":[
        "Malauag"
    ],
    "qs:name":"Malawag",
    "qs:photos_9r":0,
    "qs:photos_sr":0,
    "qs:pop_sr":"4",
    "wof:name":"Malawag",
    "wof:placetype":"locality",
    "wof:population":3155
},
  "geometry": {"coordinates":[123.28333000000001,13.38333],"type":"Point"}
}