{
  "type": "Feature",
  "properties": {
    "gn:admin1_code":"08",
    "gn:admin2_code":"67",
    "gn:admin3_code":"84806000.0",
    "gn:asciiname":"Sagudsuran",
    "gn:country_code":"PH",
    "gn:dem":5,
    "gn:feature_class":"P",
    "gn:feature_code":"PPL",
    "gn:name":"Sagudsuran",
    "gn:population":0,
    "gn:timezone":"Asia/Manila",
    "iso:country":"PH",
    "name:fil_x_preferred":[
        "Sagudsuran"
    ],
    "name:und_x_variant":[
        "Sagodsoron",
        "Sagudsoron"
    ],
    "wof:name":"Sagudsuran",
    "wof:placetype":"locality"
},
  "geometry": {"coordinates":[125.0517,12.3759],"type":"Point"}
}