{
  "type": "Feature",
  "properties": {
    "gn:admin1_code":"05",
    "gn:admin2_code":"05",
    "gn:admin3_code":"50518000.0",
    "gn:asciiname":"Nipa",
    "gn:country_code":"PH",
    "gn:dem":7,
    "gn:feature_class":"P",
    "gn:feature_code":"PPL",
    "gn:name":"Nipa",
    "gn:population":0,
    "gn:timezone":"Asia/Manila",
    "iso:country":"PH",
    "name:ceb_x_preferred":[
        "Nipa"
    ],
    "name:fil_x_preferred":[
        "Nipa"
    ],
    "name:swe_x_preferred":[
        "Nipa"
    ],
    "wof:name":"Nipa",
    "wof:placetype":"locality"
},
  "geometry": {"coordinates":[123.68333,13.45],"type":"Point"}
}