{
  "type": "Feature",
  "properties": {
    "gn:admin1_code":"07",
    "gn:admin2_code":"46",
    "gn:admin3_code":"74624000.0",
    "gn:asciiname":"Kodkod",
    "gn:country_code":"PH",
    "gn:dem":163,
    "gn:feature_class":"P",
    "gn:feature_code":"PPL",
    "gn:name":"Kodkod",
    "gn:population":0,
    "gn:timezone":"Asia/Manila",
    "iso:country":"PH",
    "name:fil_x_preferred":[
        "Kodkod"
    ],
    "wof:name":"Kodkod",
    "wof:placetype":"locality"
},
  "geometry": {"coordinates":[123.31667,10.33333],"type":"Point"}
}