{
  "type": "Feature",
  "properties": {
    "gn:admin1_code":"07",
    "gn:admin2_code":"46",
    "gn:admin3_code":"74624000.0",
    "gn:asciiname":"Kodkod",
    "gn:country_code":"PH",
    "gn:dem":163,
    "gn:feature_class":"P",
    "gn:feature_code":"PPL",
    "gn:name":"Kodkod",
    "gn:population":0,
    "gn:timezone":"Asia/Manila",
    "iso:country":"PH",
    "name:ara_x_preferred":[
        "\u0633\u0646\u0648\u0631 \u0627\u0644\u0643\u0648\u062f\u0643\u0648\u062f"
    ],
    "name:ava_x_preferred":[
        "\u041a\u043e\u0434\u043a\u043e\u0434"
    ],
    "name:aze_x_preferred":[
        "Kodkod"
    ],
    "name:bre_x_preferred":[
        "Kodkod"
    ],
    "name:bul_x_preferred":[
        "\u041a\u043e\u0434\u043a\u043e\u0434"
    ],
    "name:cat_x_preferred":[
        "Gat kodkod"
    ],
    "name:ceb_x_preferred":[
        "Leopardus guigna"
    ],
    "name:ces_x_preferred":[
        "Ko\u010dka tmav\u00e1"
    ],
    "name:dan_x_preferred":[
        "Kodkod"
    ],
    "name:deu_x_preferred":[
        "Chilenische Waldkatze"
    ],
    "name:ell_x_preferred":[
        "\u039a\u03bf\u03bd\u03c4\u03ba\u03cc\u03bd\u03c4"
    ],
    "name:eus_x_preferred":[
        "Leopardus guigna"
    ],
    "name:fas_x_preferred":[
        "\u06a9\u0648\u062f\u06a9\u0648\u062f"
    ],
    "name:fil_x_preferred":[
        "Kodkod"
    ],
    "name:fin_x_preferred":[
        "Y\u00f6kissa"
    ],
    "name:fra_x_preferred":[
        "Guigna"
    ],
    "name:heb_x_preferred":[
        "\u05d7\u05ea\u05d5\u05dc \u05e7\u05d5\u05d3\u05e7\u05d5\u05d3"
    ],
    "name:hrv_x_preferred":[
        "Kodkod"
    ],
    "name:hun_x_preferred":[
        "Kodkod"
    ],
    "name:hye_x_preferred":[
        "\u0549\u056b\u056c\u056b\u0561\u056f\u0561\u0576 \u056f\u0561\u057f\u0578\u0582"
    ],
    "name:ina_x_preferred":[
        "Guigna"
    ],
    "name:ind_x_preferred":[
        "Kodkod"
    ],
    "name:ita_x_preferred":[
        "Leopardus guigna"
    ],
    "name:jpn_x_preferred":[
        "\u30b3\u30c9\u30b3\u30c9"
    ],
    "name:kor_x_preferred":[
        "\ucf54\ub4dc\ucf54\ub4dc"
    ],
    "name:lat_x_preferred":[
        "Guigna"
    ],
    "name:lit_x_preferred":[
        "\u010cilin\u0117 kat\u0117"
    ],
    "name:ltg_x_preferred":[
        "Leopardus guigna"
    ],
    "name:mhr_x_preferred":[
        "\u041a\u043e\u0434\u043a\u043e\u0434"
    ],
    "name:mya_x_preferred":[
        "\u1000\u1031\u102c\u1037\u1000\u1031\u102c\u1037\u1000\u103c\u1031\u102c\u1004\u103a"
    ],
    "name:nld_x_preferred":[
        "Nachtkat"
    ],
    "name:nor_x_preferred":[
        "Kodkodkatt"
    ],
    "name:pnb_x_preferred":[
        "\u06a9\u0648\u0688\u06a9\u0648\u0688"
    ],
    "name:pol_x_preferred":[
        "Ocelot chilijski"
    ],
    "name:por_x_preferred":[
        "Leopardus guigna"
    ],
    "name:rus_x_preferred":[
        "\u0427\u0438\u043b\u0438\u0439\u0441\u043a\u0430\u044f \u043a\u043e\u0448\u043a\u0430"
    ],
    "name:sco_x_preferred":[
        "Kodkod"
    ],
    "name:spa_x_preferred":[
        "Leopardus guigna"
    ],
    "name:srp_x_preferred":[
        "\u041a\u043e\u0434\u043a\u043e\u0434"
    ],
    "name:swe_x_preferred":[
        "Kodkod"
    ],
    "name:udm_x_preferred":[
        "\u041a\u043e\u0434\u043a\u043e\u0434"
    ],
    "name:ukr_x_preferred":[
        "\u041b\u0435\u043e\u043f\u0430\u0440\u0434 \u043a\u043e\u0434\u043a\u043e\u0434"
    ],
    "name:war_x_preferred":[
        "Leopardus guigna"
    ],
    "name:zho_x_preferred":[
        "\u5357\u7f8e\u6797\u8c93"
    ],
    "wof:name":"Kodkod",
    "wof:placetype":"locality"
},
  "geometry": {"coordinates":[123.31667,10.33333],"type":"Point"}
}