{
  "type": "Feature",
  "properties": {
    "gn:admin1_code":"14",
    "gn:admin2_code":"60",
    "gn:admin3_code":"156607000.0",
    "gn:asciiname":"Kamalig",
    "gn:country_code":"PH",
    "gn:dem":37,
    "gn:feature_class":"P",
    "gn:feature_code":"PPL",
    "gn:name":"Kamalig",
    "gn:population":0,
    "gn:timezone":"Asia/Manila",
    "iso:country":"PH",
    "name:fil_x_preferred":[
        "Kamalig"
    ],
    "wof:name":"Kamalig",
    "wof:placetype":"locality"
},
  "geometry": {"coordinates":[121.22806,5.97889],"type":"Point"}
}