{
  "type": "Feature",
  "properties": {
    "gn:country":"PH",
    "gn:fcode":"PPL",
    "gn:pop":11161,
    "iso:country":"PH",
    "name:fil_x_preferred":[
        "Caminauit"
    ],
    "name:unk_x_variant":[
        "Caminawit"
    ],
    "qs:name":"Caminauit",
    "qs:photos_9r":0,
    "qs:photos_sr":0,
    "qs:pop_sr":"6",
    "wof:name":"Caminauit",
    "wof:placetype":"locality",
    "wof:population":11161
},
  "geometry": {"coordinates":[121.08251,12.33135],"type":"Point"}
}