{
  "type": "Feature",
  "properties": {
    "gn:admin1_code":"40",
    "gn:admin2_code":"H2",
    "gn:admin3_code":"45622000.0",
    "gn:asciiname":"Vegaflor",
    "gn:country_code":"PH",
    "gn:dem":39,
    "gn:feature_class":"P",
    "gn:feature_code":"PPL",
    "gn:name":"Vegaflor",
    "gn:population":0,
    "gn:timezone":"Asia/Manila",
    "iso:country":"PH",
    "name:fil_x_preferred":[
        "Vegaflor"
    ],
    "wof:name":"Vegaflor",
    "wof:placetype":"locality"
},
  "geometry": {"coordinates":[122.37990000000001,13.8585],"type":"Point"}
}