{
  "type": "Feature",
  "properties": {
    "gn:admin1_code":"10",
    "gn:admin2_code":"17",
    "gn:admin3_code":"101802000.0",
    "gn:asciiname":"Liong",
    "gn:country_code":"PH",
    "gn:dem":-3,
    "gn:feature_class":"P",
    "gn:feature_code":"PPL",
    "gn:name":"Liong",
    "gn:population":0,
    "gn:timezone":"Asia/Manila",
    "iso:country":"PH",
    "name:fil_x_preferred":[
        "Liong"
    ],
    "wof:name":"Liong",
    "wof:placetype":"locality"
},
  "geometry": {"coordinates":[124.78082999999999,9.08528],"type":"Point"}
}