{
  "type": "Feature",
  "properties": {
    "gn:admin1_code":"14",
    "gn:admin2_code":"35",
    "gn:asciiname":"Balot-Masla",
    "gn:cc2":"PH",
    "gn:country_code":"PH",
    "gn:dem":696,
    "gn:feature_class":"P",
    "gn:feature_code":"PPL",
    "gn:name":"Balot-Masla",
    "gn:population":0,
    "gn:timezone":"Asia/Manila",
    "iso:country":"PH",
    "name:und_x_variant":[
        "Balot Mosia",
        "Balot-Masla"
    ],
    "wof:name":"Balot-Masla",
    "wof:placetype":"locality"
},
  "geometry": {"coordinates":[124.11667,7.85],"type":"Point"}
}