{
  "type": "Feature",
  "properties": {
    "gn:country":"PH",
    "gn:fcode":"ADM3",
    "gn:pop":21248,
    "iso:country":"PH",
    "name:fil_x_preferred":[
        "Barira"
    ],
    "qs:name":"Barira",
    "qs:photos_9r":0,
    "qs:photos_sr":0,
    "qs:pop_sr":"7",
    "wof:name":"Barira",
    "wof:placetype":"localadmin",
    "wof:population":21248
},
  "geometry": {"coordinates":[124.31667,7.51667],"type":"Point"}
}