{
  "type": "Feature",
  "properties": {
    "iso:country":"PH",
    "name:bcl_x_preferred":[
        "Tayasan"
    ],
    "name:cbk_zam_x_preferred":[
        "Tayasan"
    ],
    "name:ceb_x_preferred":[
        "Tayasan"
    ],
    "name:deu_x_preferred":[
        "Tayasan"
    ],
    "name:ilo_x_preferred":[
        "Tayasan"
    ],
    "name:ind_x_preferred":[
        "Tayasan"
    ],
    "name:ita_x_preferred":[
        "Tayasan"
    ],
    "name:nld_x_preferred":[
        "Tayasan"
    ],
    "name:pag_x_preferred":[
        "Tayasan"
    ],
    "name:pam_x_preferred":[
        "Tayasan"
    ],
    "name:sco_x_preferred":[
        "Tayasan"
    ],
    "name:spa_x_preferred":[
        "Tayasan"
    ],
    "name:swe_x_preferred":[
        "Tayasan"
    ],
    "name:tgl_x_preferred":[
        "Tayasan"
    ],
    "name:unk_x_variant":[
        "Tawasan"
    ],
    "name:vie_x_preferred":[
        "Tayasan"
    ],
    "name:war_x_preferred":[
        "Tayasan"
    ],
    "qs:gn_country":"PH",
    "qs:gn_fcode":"PPL",
    "qs:gn_pop":0,
    "qs:name":"Tayasan",
    "qs:name_adm0":"Philippines",
    "qs:name_adm1":"Central Visayas",
    "qs:photos":10,
    "qs:photos_1k":2,
    "qs:photos_9k":1,
    "qs:photos_9r":1,
    "qs:photos_all":10,
    "qs:photos_sr":1,
    "qs:placetype":"Town",
    "qs:pop_sr":"0",
    "qs:woe_adm0":23424934,
    "wd:wordcount":141,
    "wof:name":"Tayasan",
    "wof:placetype":"locality"
},
  "geometry": {"coordinates":[123.95,10.33333],"type":"Point"}
}