{
  "type": "Feature",
  "properties": {
    "gn:admin1_code":"07",
    "gn:admin2_code":"21",
    "gn:admin3_code":"72232000.0",
    "gn:asciiname":"Gindaruhan",
    "gn:country_code":"PH",
    "gn:dem":47,
    "gn:elevation":"0.0",
    "gn:feature_class":"P",
    "gn:feature_code":"PPL",
    "gn:name":"Gindaruhan",
    "gn:population":0,
    "gn:timezone":"Asia/Manila",
    "iso:country":"PH",
    "name:fil_x_preferred":[
        "Gindaruhan"
    ],
    "name:und_x_variant":[
        "Guindarohan"
    ],
    "wof:name":"Gindaruhan",
    "wof:placetype":"locality"
},
  "geometry": {"coordinates":[123.76309999999999,10.26158],"type":"Point"}
}