{
  "type": "Feature",
  "properties": {
    "gn:admin1_code":"11",
    "gn:admin2_code":"I7",
    "gn:admin3_code":"112314000.0",
    "gn:asciiname":"Macgum",
    "gn:cc2":"PH",
    "gn:country_code":"PH",
    "gn:dem":36,
    "gn:feature_class":"P",
    "gn:feature_code":"PPL",
    "gn:name":"Macgum",
    "gn:population":0,
    "gn:timezone":"Asia/Manila",
    "iso:country":"PH",
    "name:und_x_variant":[
        "Macgom",
        "Macgum"
    ],
    "wof:name":"Macgum",
    "wof:placetype":"locality"
},
  "geometry": {"coordinates":[125.80028,7.64528],"type":"Point"}
}