{
  "type": "Feature",
  "properties": {
    "gn:country":"PH",
    "gn:fcode":"PPL",
    "gn:population":2433,
    "iso:country":"PH",
    "name:fil_x_preferred":[
        "Manup"
    ],
    "qs:name":"Manup",
    "qs:photos_9r":0,
    "qs:photos_sr":0,
    "qs:pop_sr":"4",
    "wof:name":"Manup",
    "wof:placetype":"locality",
    "wof:population":2433
},
  "geometry": {"coordinates":[122.498,11.5315],"type":"Point"}
}