{
  "type": "Feature",
  "properties": {
    "gn:admin1_code":"40",
    "gn:admin2_code":"33",
    "gn:admin3_code":"43428000.0",
    "gn:asciiname":"Pulong",
    "gn:cc2":"PH",
    "gn:country_code":"PH",
    "gn:dem":51,
    "gn:feature_class":"P",
    "gn:feature_code":"PPL",
    "gn:name":"Pulong",
    "gn:population":0,
    "gn:timezone":"Asia/Manila",
    "iso:country":"PH",
    "name:und_x_variant":[
        "Pulo Santa Cruz",
        "Pulong"
    ],
    "wof:name":"Pulong",
    "wof:placetype":"locality"
},
  "geometry": {"coordinates":[121.08333,14.26667],"type":"Point"}
}