{
  "type": "Feature",
  "properties": {
    "gn:admin1_code":"12",
    "gn:admin2_code":"M9",
    "gn:admin3_code":"128003000.0",
    "gn:asciiname":"Kitegas",
    "gn:country_code":"PH",
    "gn:dem":9,
    "gn:feature_class":"P",
    "gn:feature_code":"PPL",
    "gn:name":"Kitegas",
    "gn:population":0,
    "gn:timezone":"Asia/Manila",
    "iso:country":"PH",
    "name:und_x_variant":[
        "Kitagas",
        "Kitegas"
    ],
    "wof:name":"Kitegas",
    "wof:placetype":"locality"
},
  "geometry": {"coordinates":[124.81944,5.89694],"type":"Point"}
}