{
  "type": "Feature",
  "properties": {
    "gn:admin1_code":"41",
    "gn:admin2_code":"41",
    "gn:admin3_code":"175204000.0",
    "gn:asciiname":"Caratao",
    "gn:country_code":"PH",
    "gn:dem":7,
    "gn:feature_class":"P",
    "gn:feature_code":"PPL",
    "gn:name":"Caratao",
    "gn:population":0,
    "gn:timezone":"Asia/Manila",
    "iso:country":"PH",
    "name:fil_x_preferred":[
        "Caratao"
    ],
    "wof:name":"Caratao",
    "wof:placetype":"locality"
},
  "geometry": {"coordinates":[121.35961,12.32815],"type":"Point"}
}