{
  "type": "Feature",
  "properties": {
    "gn:admin1_code":"40",
    "gn:admin2_code":"H2",
    "gn:admin3_code":"45627000.0",
    "gn:asciiname":"Polo",
    "gn:country_code":"PH",
    "gn:dem":2,
    "gn:feature_class":"P",
    "gn:feature_code":"PPL",
    "gn:name":"Polo",
    "gn:population":0,
    "gn:timezone":"Asia/Manila",
    "iso:country":"PH",
    "name:fil_x_preferred":[
        "Polo"
    ],
    "wof:name":"Polo",
    "wof:placetype":"locality"
},
  "geometry": {"coordinates":[121.7285,14.1782],"type":"Point"}
}