{
  "type": "Feature",
  "properties": {
    "gn:admin1_code":"40",
    "gn:admin2_code":"H2",
    "gn:admin3_code":"45618000.0",
    "gn:asciiname":"Dankalan Central",
    "gn:country_code":"PH",
    "gn:dem":29,
    "gn:feature_class":"P",
    "gn:feature_code":"PPL",
    "gn:name":"Dankalan Central",
    "gn:population":0,
    "gn:timezone":"Asia/Manila",
    "iso:country":"PH",
    "name:fil_x_preferred":[
        "Dankalan Central"
    ],
    "name:fil_x_variant":[
        "Dangkalan"
    ],
    "name:und_x_variant":[
        "Dancalan"
    ],
    "wof:name":"Dankalan Central",
    "wof:placetype":"locality"
},
  "geometry": {"coordinates":[122.4697,13.868],"type":"Point"}
}