{
  "type": "Feature",
  "properties": {
    "gn:country":"PH",
    "gn:fcode":"PPL",
    "gn:population":2524,
    "iso:country":"PH",
    "name:fil_x_preferred":[
        "Carriedo"
    ],
    "qs:name":"Carriedo",
    "qs:photos_9r":0,
    "qs:photos_sr":0,
    "qs:pop_sr":"4",
    "wof:name":"Carriedo",
    "wof:placetype":"locality",
    "wof:population":2524
},
  "geometry": {"coordinates":[120.75490000000001,16.031],"type":"Point"}
}