{
  "type": "Feature",
  "properties": {
    "gn:admin1_code":"05",
    "gn:admin2_code":"39",
    "gn:admin3_code":"54112000.0",
    "gn:asciiname":"Capaculan",
    "gn:country_code":"PH",
    "gn:dem":13,
    "gn:feature_class":"P",
    "gn:feature_code":"PPL",
    "gn:name":"Capaculan",
    "gn:population":0,
    "gn:timezone":"Asia/Manila",
    "iso:country":"PH",
    "name:fil_x_preferred":[
        "Capaculan"
    ],
    "name:und_x_variant":[
        "Kapakulan",
        "Capakuan",
        "Capaclan"
    ],
    "wof:name":"Capaculan",
    "wof:placetype":"locality"
},
  "geometry": {"coordinates":[123.46541000000001,12.21645],"type":"Point"}
}