{
  "type": "Feature",
  "properties": {
    "gn:admin1_code":"02",
    "gn:admin2_code":"14",
    "gn:admin3_code":"21512000.0",
    "gn:asciiname":"Roma",
    "gn:country_code":"PH",
    "gn:dem":34,
    "gn:feature_class":"P",
    "gn:feature_code":"PPL",
    "gn:name":"Roma",
    "gn:population":0,
    "gn:timezone":"Asia/Manila",
    "iso:country":"PH",
    "name:fil_x_preferred":[
        "Roma"
    ],
    "wof:name":"Roma",
    "wof:placetype":"locality"
},
  "geometry": {"coordinates":[121.68908999999999,17.52378],"type":"Point"}
}