{
  "type": "Feature",
  "properties": {
    "gn:gn_country":"PH",
    "gn:gn_fcode":"PPL",
    "gn:gn_pop":7567,
    "gn:population":7567,
    "iso:country":"PH",
    "name:fil_x_preferred":[
        "Dahay"
    ],
    "qs_pg:aaroncc":"PH",
    "qs_pg:gn_country":"PH",
    "qs_pg:gn_fcode":"PPL",
    "qs_pg:gn_pop":7567,
    "qs_pg:name":"Dahay",
    "qs_pg:photos_9r":0,
    "qs_pg:photos_sr":0,
    "qs_pg:pop_sr":5,
    "qs_pg:qs_pg_placetype":"locality",
    "wof:name":"Dahay",
    "wof:placetype":"locality",
    "wof:population":7567
},
  "geometry": {"coordinates":[124.7225,6.39694],"type":"Point"}
}