{
  "type": "Feature",
  "properties": {
    "gn:admin1_code":"02",
    "gn:admin2_code":"14",
    "gn:admin3_code":"21509000.0",
    "gn:asciiname":"Dibay",
    "gn:country_code":"PH",
    "gn:dem":38,
    "gn:feature_class":"P",
    "gn:feature_code":"PPL",
    "gn:name":"Dibay",
    "gn:population":0,
    "gn:timezone":"Asia/Manila",
    "iso:country":"PH",
    "name:fil_x_preferred":[
        "Dibay"
    ],
    "wof:name":"Dibay",
    "wof:placetype":"locality"
},
  "geometry": {"coordinates":[121.39851000000002,19.37657],"type":"Point"}
}