{
  "type": "Feature",
  "properties": {
    "iso:country":"PH",
    "name:bcl_x_preferred":[
        "Manjuyod"
    ],
    "name:cat_x_preferred":[
        "Manjuyod"
    ],
    "name:cbk_zam_x_preferred":[
        "Manjuyod"
    ],
    "name:ceb_x_preferred":[
        "Manjuyod"
    ],
    "name:deu_x_preferred":[
        "Manjuyod"
    ],
    "name:dut_x_preferred":[
        "Manjuyod"
    ],
    "name:eng_x_preferred":[
        "Manjuyod"
    ],
    "name:fil_x_preferred":[
        "Manjuyod"
    ],
    "name:fre_x_preferred":[
        "Manjuyod"
    ],
    "name:ger_x_preferred":[
        "Manjuyod"
    ],
    "name:ilo_x_preferred":[
        "Manjuyod"
    ],
    "name:ind_x_preferred":[
        "Manjuyod"
    ],
    "name:ita_x_preferred":[
        "Manjuyod"
    ],
    "name:nld_x_preferred":[
        "Manjuyod"
    ],
    "name:pag_x_preferred":[
        "Manjuyod"
    ],
    "name:pam_x_preferred":[
        "Manjuyod"
    ],
    "name:spa_x_preferred":[
        "Manjuyod"
    ],
    "name:swe_x_preferred":[
        "Manjuyod"
    ],
    "name:tgl_x_preferred":[
        "Manjuyod"
    ],
    "name:unk_x_variant":[
        "Manjuyop"
    ],
    "name:vie_x_preferred":[
        "Manjuyod"
    ],
    "name:war_x_preferred":[
        "Manjuyod"
    ],
    "qs:gn_country":"PH",
    "qs:gn_fcode":"PPL",
    "qs:gn_pop":0,
    "qs:name":"Manjuyod",
    "qs:name_adm0":"Philippines",
    "qs:name_adm1":"Central Visayas",
    "qs:photos":0,
    "qs:photos_1k":0,
    "qs:photos_9k":1,
    "qs:photos_9r":1,
    "qs:photos_all":2,
    "qs:photos_sr":0,
    "qs:placetype":"Town",
    "qs:pop_sr":"5",
    "qs:woe_adm0":23424934,
    "wd:wordcount":212,
    "wof:name":"Manjuyod",
    "wof:placetype":"locality"
},
  "geometry": {"coordinates":[123.1469,9.6794],"type":"Point"}
}