{
  "type": "Feature",
  "properties": {
    "gn:admin1_code":"40",
    "gn:admin2_code":"09",
    "gn:admin3_code":"41019000.0",
    "gn:asciiname":"Cutad",
    "gn:country_code":"PH",
    "gn:dem":8,
    "gn:feature_class":"P",
    "gn:feature_code":"PPL",
    "gn:name":"Cutad",
    "gn:population":0,
    "gn:timezone":"Asia/Manila",
    "iso:country":"PH",
    "name:fil_x_preferred":[
        "Cutad"
    ],
    "wof:name":"Cutad",
    "wof:placetype":"locality"
},
  "geometry": {"coordinates":[120.5977,14.1905],"type":"Point"}
}