{
  "type": "Feature",
  "properties": {
    "gn:admin1_code":"05",
    "gn:admin2_code":"16",
    "gn:admin3_code":"51710000.0",
    "gn:asciiname":"Bawa",
    "gn:country_code":"PH",
    "gn:dem":3,
    "gn:feature_class":"P",
    "gn:feature_code":"PPL",
    "gn:name":"Bawa",
    "gn:population":0,
    "gn:timezone":"Asia/Manila",
    "iso:country":"PH",
    "name:ceb_x_preferred":[
        "Bawa"
    ],
    "name:deu_x_preferred":[
        "Bawa"
    ],
    "name:fil_x_preferred":[
        "Bawa"
    ],
    "name:fra_x_preferred":[
        "Bawa"
    ],
    "name:swe_x_preferred":[
        "Bawa"
    ],
    "wof:name":"Bawa",
    "wof:placetype":"locality"
},
  "geometry": {"coordinates":[123.11450000000001,13.6482],"type":"Point"}
}