{
  "type": "Feature",
  "properties": {
    "gn:admin1_code":"40",
    "gn:admin2_code":"33",
    "gn:admin3_code":"43416000.0",
    "gn:asciiname":"Tanaual",
    "gn:country_code":"PH",
    "gn:dem":134,
    "gn:feature_class":"P",
    "gn:feature_code":"PPL",
    "gn:name":"Tanaual",
    "gn:population":0,
    "gn:timezone":"Asia/Manila",
    "iso:country":"PH",
    "name:fil_x_preferred":[
        "Tanaual"
    ],
    "wof:name":"Tanaual",
    "wof:placetype":"locality"
},
  "geometry": {"coordinates":[121.45999999999999,14.18306],"type":"Point"}
}