{
  "type": "Feature",
  "properties": {
    "gn:country":"PH",
    "gn:fcode":"PPL",
    "gn:population":3154,
    "iso:country":"PH",
    "qs:name":"Tidman",
    "qs:photos_9r":0,
    "qs:photos_sr":0,
    "qs:pop_sr":"4",
    "wof:name":"Tidman",
    "wof:placetype":"locality",
    "wof:population":3154
},
  "geometry": {"coordinates":[126.33889000000001,8.29861],"type":"Point"}
}