{
  "type": "Feature",
  "properties": {
    "gn:admin1_code":"10",
    "gn:admin2_code":"43",
    "gn:admin3_code":"104304000.0",
    "gn:asciiname":"Dampias",
    "gn:country_code":"PH",
    "gn:dem":24,
    "gn:feature_class":"P",
    "gn:feature_code":"PPL",
    "gn:name":"Dampias",
    "gn:population":0,
    "gn:timezone":"Asia/Manila",
    "iso:country":"PH",
    "name:fil_x_preferred":[
        "Dampias"
    ],
    "wof:name":"Dampias",
    "wof:placetype":"locality"
},
  "geometry": {"coordinates":[124.78583,8.90889],"type":"Point"}
}