{
  "type": "Feature",
  "properties": {
    "gn:admin1_code":"07",
    "gn:admin2_code":"11",
    "gn:admin3_code":"71222000.0",
    "gn:asciiname":"Tabuan",
    "gn:country_code":"PH",
    "gn:dem":176,
    "gn:feature_class":"P",
    "gn:feature_code":"PPL",
    "gn:name":"Tabuan",
    "gn:population":0,
    "gn:timezone":"Asia/Manila",
    "iso:country":"PH",
    "name:fil_x_preferred":[
        "Tabuan"
    ],
    "wof:name":"Tabuan",
    "wof:placetype":"locality"
},
  "geometry": {"coordinates":[124.2925,9.665],"type":"Point"}
}