{
  "type": "Feature",
  "properties": {
    "gn:admin1_code":"06",
    "gn:admin2_code":"18",
    "gn:admin3_code":"61909000.0",
    "gn:asciiname":"Bago Grande",
    "gn:country_code":"PH",
    "gn:dem":6,
    "gn:feature_class":"P",
    "gn:feature_code":"PPL",
    "gn:name":"Bago Grande",
    "gn:population":0,
    "gn:timezone":"Asia/Manila",
    "iso:country":"PH",
    "name:fil_x_preferred":[
        "Bago Grande"
    ],
    "name:und_x_variant":[
        "Bago"
    ],
    "wof:name":"Bago Grande",
    "wof:placetype":"locality"
},
  "geometry": {"coordinates":[122.77977,11.52086],"type":"Point"}
}