{
  "type": "Feature",
  "properties": {
    "gn:admin1_code":"13",
    "gn:admin2_code":"61",
    "gn:admin3_code":"166714000.0",
    "gn:asciiname":"Agong-ongan",
    "gn:country_code":"PH",
    "gn:dem":50,
    "gn:feature_class":"P",
    "gn:feature_code":"PPL",
    "gn:name":"Agong-ongan",
    "gn:population":0,
    "gn:timezone":"Asia/Manila",
    "iso:country":"PH",
    "name:fil_x_preferred":[
        "Agong-ongan"
    ],
    "wof:name":"Agong-ongan",
    "wof:placetype":"locality"
},
  "geometry": {"coordinates":[125.5428,9.5381],"type":"Point"}
}