{
  "type": "Feature",
  "properties": {
    "gn:admin1_code":"13",
    "gn:admin2_code":"03",
    "gn:admin3_code":"160305000.0",
    "gn:asciiname":"Antipolo",
    "gn:country_code":"PH",
    "gn:dem":66,
    "gn:feature_class":"P",
    "gn:feature_code":"PPL",
    "gn:name":"Antipolo",
    "gn:population":0,
    "gn:timezone":"Asia/Manila",
    "iso:country":"PH",
    "name:fil_x_preferred":[
        "Antipolo"
    ],
    "wof:name":"Antipolo",
    "wof:placetype":"locality"
},
  "geometry": {"coordinates":[125.81667,8.15],"type":"Point"}
}