{
  "type": "Feature",
  "properties": {
    "gn:admin1_code":"15",
    "gn:admin2_code":"10",
    "gn:admin3_code":"141104000.0",
    "gn:asciiname":"Chapus",
    "gn:country_code":"PH",
    "gn:dem":916,
    "gn:feature_class":"P",
    "gn:feature_code":"PPL",
    "gn:name":"Chapus",
    "gn:population":0,
    "gn:timezone":"Asia/Manila",
    "iso:country":"PH",
    "name:eng_x_preferred":[
        "Chapus"
    ],
    "wof:name":"Chapus",
    "wof:placetype":"locality"
},
  "geometry": {"coordinates":[120.8047,16.4715],"type":"Point"}
}