{
  "type": "Feature",
  "properties": {
    "gn:admin1_code":"07",
    "gn:admin2_code":"11",
    "gn:admin3_code":"71210000.0",
    "gn:asciiname":"Libjo",
    "gn:country_code":"PH",
    "gn:dem":13,
    "gn:feature_class":"P",
    "gn:feature_code":"PPL",
    "gn:name":"Libjo",
    "gn:population":0,
    "gn:timezone":"Asia/Manila",
    "iso:country":"PH",
    "name:fil_x_preferred":[
        "Libjo"
    ],
    "wof:name":"Libjo",
    "wof:placetype":"locality"
},
  "geometry": {"coordinates":[123.88333,9.88333],"type":"Point"}
}