{
  "type": "Feature",
  "properties": {
    "gn:admin1_code":"12",
    "gn:admin2_code":"M9",
    "gn:admin3_code":"128002000.0",
    "gn:asciiname":"Kiogam",
    "gn:country_code":"PH",
    "gn:dem":136,
    "gn:feature_class":"P",
    "gn:feature_code":"PPL",
    "gn:name":"Kiogam",
    "gn:population":0,
    "gn:timezone":"Asia/Manila",
    "iso:country":"PH",
    "name:fil_x_preferred":[
        "Kiogam"
    ],
    "name:und_x_variant":[
        "Kiogan"
    ],
    "wof:name":"Kiogam",
    "wof:placetype":"locality"
},
  "geometry": {"coordinates":[125.25749999999999,5.82889],"type":"Point"}
}