{
  "type": "Feature",
  "properties": {
    "gn:admin1_code":"07",
    "gn:admin2_code":"21",
    "gn:admin3_code":"72246000.0",
    "gn:asciiname":"Bae",
    "gn:country_code":"PH",
    "gn:dem":226,
    "gn:feature_class":"P",
    "gn:feature_code":"PPL",
    "gn:name":"Bae",
    "gn:population":0,
    "gn:timezone":"Asia/Manila",
    "iso:country":"PH",
    "name:ceb_x_preferred":[
        "Bae"
    ],
    "name:fil_x_preferred":[
        "Bae"
    ],
    "name:swe_x_preferred":[
        "Bae"
    ],
    "name:tur_x_preferred":[
        "BAE"
    ],
    "wof:name":"Bae",
    "wof:placetype":"locality"
},
  "geometry": {"coordinates":[123.53758999999999,9.99363],"type":"Point"}
}