{
  "type": "Feature",
  "properties": {
    "gn:admin1_code":"40",
    "gn:admin2_code":"09",
    "gn:admin3_code":"41005000.0",
    "gn:asciiname":"East Banaba Batangas",
    "gn:country_code":"PH",
    "gn:dem":125,
    "gn:feature_class":"P",
    "gn:feature_code":"PPL",
    "gn:name":"East Banaba Batangas",
    "gn:population":0,
    "gn:timezone":"Asia/Manila",
    "iso:country":"PH",
    "name:fil_x_preferred":[
        "East Banaba Batangas"
    ],
    "name:fil_x_variant":[
        "Banaba"
    ],
    "name:und_x_variant":[
        "Banaba Batangas",
        "Bianaba"
    ],
    "wof:name":"East Banaba Batangas",
    "wof:placetype":"locality"
},
  "geometry": {"coordinates":[121.05736,13.81743],"type":"Point"}
}