{
  "type": "Feature",
  "properties": {
    "gn:admin1_code":"03",
    "gn:admin2_code":"13",
    "gn:admin3_code":"31410000.0",
    "gn:asciiname":"Santo Cristo",
    "gn:country_code":"PH",
    "gn:dem":7,
    "gn:feature_class":"P",
    "gn:feature_code":"PPL",
    "gn:name":"Santo Cristo",
    "gn:population":0,
    "gn:timezone":"Asia/Manila",
    "iso:country":"PH",
    "name:bpy_x_preferred":[
        "\u09b8\u09be\u09a8\u09cd\u099f\u09cb \u0995\u09b0\u09bf\u09b8\u099f\u09cb"
    ],
    "name:ceb_x_preferred":[
        "Santo Cristo"
    ],
    "name:epo_x_preferred":[
        "Santo Cristo"
    ],
    "name:eus_x_preferred":[
        "Santo Cristo"
    ],
    "name:fil_x_preferred":[
        "Santo Cristo"
    ],
    "name:ita_x_preferred":[
        "Santo Cristo"
    ],
    "name:kaz_x_preferred":[
        "\u0421\u0430\u043d\u0442\u0443-\u041a\u0440\u0438\u0441\u0442\u0443"
    ],
    "name:mlg_x_preferred":[
        "Santo Cristo"
    ],
    "name:nld_x_preferred":[
        "Santo Cristo"
    ],
    "name:nor_x_preferred":[
        "Santo Cristo"
    ],
    "name:pol_x_preferred":[
        "Santo Cristo"
    ],
    "name:por_x_preferred":[
        "Santo Cristo"
    ],
    "name:ron_x_preferred":[
        "Santo Cristo"
    ],
    "name:rus_x_preferred":[
        "\u0421\u0430\u043d\u0442\u0443-\u041a\u0440\u0438\u0441\u0442\u0443"
    ],
    "name:spa_x_preferred":[
        "Santo Cristo"
    ],
    "name:swe_x_preferred":[
        "Santo Cristo"
    ],
    "name:vie_x_preferred":[
        "Santo Cristo"
    ],
    "name:vol_x_preferred":[
        "Santo Cristo"
    ],
    "name:zho_x_preferred":[
        "\u5723\u514b\u91cc\u65af\u56fe"
    ],
    "wof:name":"Santo Cristo",
    "wof:placetype":"locality"
},
  "geometry": {"coordinates":[120.81779,14.83301],"type":"Point"}
}