{
  "type": "Feature",
  "properties": {
    "gn:admin1_code":"11",
    "gn:admin2_code":"I7",
    "gn:admin3_code":"112305000.0",
    "gn:asciiname":"Magluga",
    "gn:country_code":"PH",
    "gn:dem":113,
    "gn:feature_class":"P",
    "gn:feature_code":"PPL",
    "gn:name":"Magluga",
    "gn:population":0,
    "gn:timezone":"Asia/Manila",
    "iso:country":"PH",
    "name:fil_x_preferred":[
        "Magluga"
    ],
    "wof:name":"Magluga",
    "wof:placetype":"locality"
},
  "geometry": {"coordinates":[125.54917,7.87944],"type":"Point"}
}