{
  "type": "Feature",
  "properties": {
    "gn:admin1_code":"08",
    "gn:admin2_code":"67",
    "gn:admin3_code":"84813000.0",
    "gn:asciiname":"Cabaturn",
    "gn:country_code":"PH",
    "gn:dem":19,
    "gn:feature_class":"P",
    "gn:feature_code":"PPL",
    "gn:name":"Cabaturn",
    "gn:population":0,
    "gn:timezone":"Asia/Manila",
    "iso:country":"PH",
    "name:fil_x_preferred":[
        "Cabaturn"
    ],
    "wof:name":"Cabaturn",
    "wof:placetype":"locality"
},
  "geometry": {"coordinates":[124.7448,12.5025],"type":"Point"}
}