{
  "type": "Feature",
  "properties": {
    "gn:country":"PH",
    "gn:fcode":"ADM3",
    "gn:population":16322,
    "iso:country":"PH",
    "name:fil_x_preferred":[
        "Jiabong"
    ],
    "qs:name":"Jiabong",
    "qs:photos_9r":0,
    "qs:photos_sr":0,
    "qs:pop_sr":"6",
    "wof:name":"Jiabong",
    "wof:placetype":"localadmin",
    "wof:population":16322
},
  "geometry": {"coordinates":[124.98333,11.85],"type":"Point"}
}