{
  "type": "Feature",
  "properties": {
    "gn:admin1_code":"40",
    "gn:admin2_code":"09",
    "gn:admin3_code":"41007000.0",
    "gn:asciiname":"Madalunot",
    "gn:country_code":"PH",
    "gn:dem":199,
    "gn:feature_class":"P",
    "gn:feature_code":"PPL",
    "gn:name":"Madalunot",
    "gn:population":0,
    "gn:timezone":"Asia/Manila",
    "iso:country":"PH",
    "name:und_x_variant":[
        "Madalumot",
        "Madalunot"
    ],
    "wof:name":"Madalunot",
    "wof:placetype":"locality"
},
  "geometry": {"coordinates":[120.82744,13.97391],"type":"Point"}
}