{
  "type": "Feature",
  "properties": {
    "gn:admin1_code":"40",
    "gn:admin2_code":"F2",
    "gn:asciiname":"Sienna",
    "gn:country_code":"PH",
    "gn:dem":9,
    "gn:feature_class":"P",
    "gn:feature_code":"PPL",
    "gn:name":"Sienna",
    "gn:population":0,
    "gn:timezone":"Asia/Manila",
    "iso:country":"PH",
    "name:afr_x_preferred":[
        "Sienna"
    ],
    "name:ces_x_preferred":[
        "Siena p\u00e1len\u00e1"
    ],
    "name:deu_x_preferred":[
        "Siena"
    ],
    "name:fil_x_preferred":[
        "Sienna"
    ],
    "name:fin_x_preferred":[
        "Siena"
    ],
    "name:jpn_x_preferred":[
        "\u30b7\u30a7\u30f3\u30ca"
    ],
    "name:lin_x_preferred":[
        "Maron"
    ],
    "name:lit_x_preferred":[
        "Siena"
    ],
    "name:nld_x_preferred":[
        "Rauwe sienna"
    ],
    "name:pol_x_preferred":[
        "Sjena palona"
    ],
    "name:rus_x_preferred":[
        "\u0421\u0438\u0435\u043d\u0430"
    ],
    "name:slk_x_preferred":[
        "Siena"
    ],
    "name:spa_x_preferred":[
        "Siena"
    ],
    "name:swe_x_preferred":[
        "Sienna"
    ],
    "name:ukr_x_preferred":[
        "\u0422\u0435\u0440\u0430-\u0421\u0456\u0454\u043d\u0430"
    ],
    "wof:name":"Sienna",
    "wof:placetype":"locality"
},
  "geometry": {"coordinates":[121.0055,14.6331],"type":"Point"}
}