{
  "type": "Feature",
  "properties": {
    "gn:admin1_code":"01",
    "gn:admin2_code":"29",
    "gn:admin3_code":"12909000.0",
    "gn:asciiname":"Calumbaya",
    "gn:country_code":"PH",
    "gn:dem":39,
    "gn:feature_class":"P",
    "gn:feature_code":"PPL",
    "gn:name":"Calumbaya",
    "gn:population":0,
    "gn:timezone":"Asia/Manila",
    "iso:country":"PH",
    "name:fil_x_preferred":[
        "Calumbaya"
    ],
    "wof:name":"Calumbaya",
    "wof:placetype":"locality"
},
  "geometry": {"coordinates":[120.48341000000001,17.19316],"type":"Point"}
}