{
  "type": "Feature",
  "properties": {
    "gn:admin1_code":"03",
    "gn:admin2_code":"47",
    "gn:admin3_code":"34912000.0",
    "gn:asciiname":"Niyugan",
    "gn:country_code":"PH",
    "gn:dem":18,
    "gn:feature_class":"P",
    "gn:feature_code":"PPL",
    "gn:name":"Niyugan",
    "gn:population":0,
    "gn:timezone":"Asia/Manila",
    "iso:country":"PH",
    "name:fil_x_preferred":[
        "Niyugan"
    ],
    "wof:name":"Niyugan",
    "wof:placetype":"locality"
},
  "geometry": {"coordinates":[120.88617000000001,15.3233],"type":"Point"}
}