{
  "type": "Feature",
  "properties": {
    "gn:admin1_code":"06",
    "gn:admin2_code":"H3",
    "gn:asciiname":"Nangka",
    "gn:country_code":"PH",
    "gn:dem":1,
    "gn:feature_class":"P",
    "gn:feature_code":"PPL",
    "gn:name":"Nangka",
    "gn:population":0,
    "gn:timezone":"Asia/Manila",
    "iso:country":"PH",
    "name:ceb_x_preferred":[
        "Nangka"
    ],
    "name:fil_x_preferred":[
        "Nangka"
    ],
    "name:msa_x_preferred":[
        "Nangka"
    ],
    "name:swe_x_preferred":[
        "Nangka"
    ],
    "name:und_x_variant":[
        "Nanka"
    ],
    "wof:name":"Nangka",
    "wof:placetype":"locality"
},
  "geometry": {"coordinates":[122.96420000000001,10.89754],"type":"Point"}
}