{
  "type": "Feature",
  "properties": {
    "gn:admin1_code":"09",
    "gn:admin2_code":"66",
    "gn:admin3_code":"97305000.0",
    "gn:asciiname":"Lalab",
    "gn:country_code":"PH",
    "gn:dem":227,
    "gn:feature_class":"P",
    "gn:feature_code":"PPL",
    "gn:name":"Lalab",
    "gn:population":0,
    "gn:timezone":"Asia/Manila",
    "iso:country":"PH",
    "name:ind_x_preferred":[
        "Lalap"
    ],
    "name:jav_x_preferred":[
        "Lalab"
    ],
    "name:sun_x_preferred":[
        "Lalab"
    ],
    "name:tha_x_preferred":[
        "\u0e25\u0e32\u0e25\u0e31\u0e1a"
    ],
    "wof:name":"Lalab",
    "wof:placetype":"locality"
},
  "geometry": {"coordinates":[123.27222,7.54722],"type":"Point"}
}