{
  "type": "Feature",
  "properties": {
    "gn:admin1_code":"03",
    "gn:admin2_code":"13",
    "gn:admin3_code":"31412000.0",
    "gn:asciiname":"Malhakan",
    "gn:country_code":"PH",
    "gn:dem":7,
    "gn:feature_class":"P",
    "gn:feature_code":"PPL",
    "gn:name":"Malhakan",
    "gn:population":0,
    "gn:timezone":"Asia/Manila",
    "iso:country":"PH",
    "name:und_x_variant":[
        "Matajacan",
        "Malahacan",
        "Malhakan",
        "Malahakan",
        "Malajacan"
    ],
    "wof:name":"Malhakan",
    "wof:placetype":"locality"
},
  "geometry": {"coordinates":[120.9665,14.7416],"type":"Point"}
}