{
  "type": "Feature",
  "properties": {
    "gn:admin1_code":"14",
    "gn:admin2_code":"22",
    "gn:admin3_code":"150702000.0",
    "gn:asciiname":"Bulingan",
    "gn:country_code":"PH",
    "gn:dem":162,
    "gn:feature_class":"P",
    "gn:feature_code":"PPL",
    "gn:name":"Bulingan",
    "gn:population":0,
    "gn:timezone":"Asia/Manila",
    "iso:country":"PH",
    "name:fil_x_preferred":[
        "Bulingan"
    ],
    "wof:name":"Bulingan",
    "wof:placetype":"locality"
},
  "geometry": {"coordinates":[122.11917,6.57444],"type":"Point"}
}