{
  "type": "Feature",
  "properties": {
    "gn:admin1_code":"03",
    "gn:admin2_code":"47",
    "gn:admin3_code":"34919000.0",
    "gn:asciiname":"Barrio Militar",
    "gn:country_code":"PH",
    "gn:dem":69,
    "gn:feature_class":"P",
    "gn:feature_code":"PPL",
    "gn:name":"Barrio Militar",
    "gn:population":0,
    "gn:timezone":"Asia/Manila",
    "iso:country":"PH",
    "name:fil_x_preferred":[
        "Barrio Militar"
    ],
    "name:und_x_variant":[
        "Fort Magsaysay"
    ],
    "wof:name":"Barrio Militar",
    "wof:placetype":"locality"
},
  "geometry": {"coordinates":[121.07633,15.43405],"type":"Point"}
}