{
  "type": "Feature",
  "properties": {
    "gn:admin1_code":"06",
    "gn:admin2_code":"06",
    "gn:admin3_code":"60601000.0",
    "gn:asciiname":"Ginarogan",
    "gn:country_code":"PH",
    "gn:dem":96,
    "gn:feature_class":"P",
    "gn:feature_code":"PPL",
    "gn:name":"Ginarogan",
    "gn:population":0,
    "gn:timezone":"Asia/Manila",
    "iso:country":"PH",
    "name:fil_x_preferred":[
        "Ginarogan"
    ],
    "wof:name":"Ginarogan",
    "wof:placetype":"locality"
},
  "geometry": {"coordinates":[121.96666999999999,10.46667],"type":"Point"}
}