{
  "type": "Feature",
  "properties": {
    "gn:admin1_code":"40",
    "gn:admin2_code":"09",
    "gn:admin3_code":"41033000.0",
    "gn:asciiname":"San Juan",
    "gn:country_code":"PH",
    "gn:dem":114,
    "gn:feature_class":"P",
    "gn:feature_code":"PPL",
    "gn:name":"San Juan",
    "gn:population":0,
    "gn:timezone":"Asia/Manila",
    "iso:country":"PH",
    "name:fil_x_preferred":[
        "San Juan"
    ],
    "wof:name":"San Juan",
    "wof:placetype":"locality"
},
  "geometry": {"coordinates":[120.87632000000001,13.63794],"type":"Point"}
}