{
  "type": "Feature",
  "properties": {
    "gn:admin1_code":"14",
    "gn:admin2_code":"56",
    "gn:asciiname":"Dinganen",
    "gn:country_code":"PH",
    "gn:dem":121,
    "gn:feature_class":"P",
    "gn:feature_code":"PPL",
    "gn:name":"Dinganen",
    "gn:population":0,
    "gn:timezone":"Asia/Manila",
    "iso:country":"PH",
    "name:fil_x_preferred":[
        "Dinganen"
    ],
    "wof:name":"Dinganen",
    "wof:placetype":"locality"
},
  "geometry": {"coordinates":[124.40861,7.36639],"type":"Point"}
}