{
  "type": "Feature",
  "properties": {
    "gn:admin1_code":"06",
    "gn:admin2_code":"30",
    "gn:asciiname":"San Juan Crisostomo",
    "gn:country_code":"PH",
    "gn:dem":-9999,
    "gn:feature_class":"P",
    "gn:feature_code":"PPL",
    "gn:name":"San Juan Crisostomo",
    "gn:population":0,
    "gn:timezone":"Asia/Manila",
    "iso:country":"PH",
    "name:fil_x_preferred":[
        "San Juan Crisostomo"
    ],
    "wof:name":"San Juan Crisostomo",
    "wof:placetype":"locality"
},
  "geometry": {"coordinates":[122.78333000000001,10.98333],"type":"Point"}
}