{
  "type": "Feature",
  "properties": {
    "gn:admin1_code":"07",
    "gn:admin2_code":"11",
    "gn:admin3_code":"71230000.0",
    "gn:asciiname":"Calmanoc",
    "gn:country_code":"PH",
    "gn:dem":360,
    "gn:feature_class":"P",
    "gn:feature_code":"PPL",
    "gn:name":"Calmanoc",
    "gn:population":0,
    "gn:timezone":"Asia/Manila",
    "iso:country":"PH",
    "name:fil_x_preferred":[
        "Calmanoc"
    ],
    "name:und_x_variant":[
        "Canmanok"
    ],
    "wof:name":"Calmanoc",
    "wof:placetype":"locality"
},
  "geometry": {"coordinates":[123.8145,9.7783],"type":"Point"}
}