{
  "type": "Feature",
  "properties": {
    "gn:admin1_code":"40",
    "gn:admin2_code":"H2",
    "gn:admin3_code":"45642000.0",
    "gn:asciiname":"Kunoy",
    "gn:country_code":"PH",
    "gn:dem":216,
    "gn:feature_class":"P",
    "gn:feature_code":"PPL",
    "gn:name":"Kunoy",
    "gn:population":0,
    "gn:timezone":"Asia/Manila",
    "iso:country":"PH",
    "name:aze_x_preferred":[
        "Kunoy adas\u0131"
    ],
    "name:bel_x_preferred":[
        "\u041a\u0443\u043d\u0430\u0439"
    ],
    "name:cat_x_preferred":[
        "Kunoy"
    ],
    "name:ces_x_preferred":[
        "Kunoy"
    ],
    "name:dan_x_preferred":[
        "Kunoy"
    ],
    "name:deu_x_preferred":[
        "Kunoy"
    ],
    "name:ell_x_preferred":[
        "\u039a\u03bf\u03cd\u03bd\u03bf\u03ca"
    ],
    "name:epo_x_preferred":[
        "Kunoy"
    ],
    "name:fao_x_preferred":[
        "Kunoy"
    ],
    "name:fil_x_preferred":[
        "Kunoy"
    ],
    "name:fin_x_preferred":[
        "Kunoy"
    ],
    "name:fra_x_preferred":[
        "Kunoy"
    ],
    "name:gla_x_preferred":[
        "Kunoy"
    ],
    "name:gle_x_preferred":[
        "Kunoy"
    ],
    "name:heb_x_preferred":[
        "\u05e7\u05d5\u05e0\u05d5\u05d9"
    ],
    "name:hun_x_preferred":[
        "Kunoy"
    ],
    "name:ind_x_preferred":[
        "Kunoy"
    ],
    "name:isl_x_preferred":[
        "Kunoy"
    ],
    "name:ita_x_preferred":[
        "Kunoy"
    ],
    "name:jpn_x_preferred":[
        "\u30af\u30ce\u30a4\u5cf6"
    ],
    "name:kor_x_preferred":[
        "\ucfe0\ub178\uc774\uc12c"
    ],
    "name:lit_x_preferred":[
        "Kunojus"
    ],
    "name:nld_x_preferred":[
        "Kunoy"
    ],
    "name:nno_x_preferred":[
        "Kunoy"
    ],
    "name:nor_x_preferred":[
        "Kunoy"
    ],
    "name:oss_x_preferred":[
        "\u041a\u0443\u043d\u043e\u0439"
    ],
    "name:pol_x_preferred":[
        "Kunoy"
    ],
    "name:por_x_preferred":[
        "Kunoy"
    ],
    "name:ron_x_preferred":[
        "Kunoy"
    ],
    "name:rus_x_preferred":[
        "\u041a\u0443\u043d\u0451"
    ],
    "name:slk_x_preferred":[
        "Kunoy"
    ],
    "name:spa_x_preferred":[
        "Kunoy"
    ],
    "name:swe_x_preferred":[
        "Kunoy"
    ],
    "name:ukr_x_preferred":[
        "\u041a\u0443\u043d\u043e\u0439"
    ],
    "name:vie_x_preferred":[
        "Kunoy"
    ],
    "wof:name":"Kunoy",
    "wof:placetype":"locality"
},
  "geometry": {"coordinates":[122.5483,13.269],"type":"Point"}
}