{
  "type": "Feature",
  "properties": {
    "gn:admin1_code":"01",
    "gn:admin2_code":"29",
    "gn:admin3_code":"12904000.0",
    "gn:asciiname":"Bartkir",
    "gn:country_code":"PH",
    "gn:dem":33,
    "gn:feature_class":"P",
    "gn:feature_code":"PPL",
    "gn:name":"Bartkir",
    "gn:population":0,
    "gn:timezone":"Asia/Manila",
    "iso:country":"PH",
    "name:fil_x_preferred":[
        "Bartkir"
    ],
    "name:fil_x_variant":[
        "Barikir"
    ],
    "wof:name":"Bartkir",
    "wof:placetype":"locality"
},
  "geometry": {"coordinates":[120.5128,17.3241],"type":"Point"}
}