{
  "type": "Feature",
  "properties": {
    "gn:admin1_code":"06",
    "gn:admin2_code":"30",
    "gn:admin3_code":"63037000.0",
    "gn:asciiname":"Bungco",
    "gn:country_code":"PH",
    "gn:dem":10,
    "gn:feature_class":"P",
    "gn:feature_code":"PPL",
    "gn:name":"Bungco",
    "gn:population":0,
    "gn:timezone":"Asia/Manila",
    "iso:country":"PH",
    "name:fil_x_preferred":[
        "Bungco"
    ],
    "wof:name":"Bungco",
    "wof:placetype":"locality"
},
  "geometry": {"coordinates":[122.65000000000001,10.85],"type":"Point"}
}