{
  "type": "Feature",
  "properties": {
    "gn:admin1_code":"40",
    "gn:admin2_code":"09",
    "gn:admin3_code":"41021000.0",
    "gn:asciiname":"Balukbuk",
    "gn:country_code":"PH",
    "gn:dem":120,
    "gn:feature_class":"P",
    "gn:feature_code":"PPL",
    "gn:name":"Balukbuk",
    "gn:population":0,
    "gn:timezone":"Asia/Manila",
    "iso:country":"PH",
    "name:fil_x_preferred":[
        "Balukbuk"
    ],
    "wof:name":"Balukbuk",
    "wof:placetype":"locality"
},
  "geometry": {"coordinates":[121.26667,13.83333],"type":"Point"}
}