{
  "type": "Feature",
  "properties": {
    "gn:admin1_code":"14",
    "gn:admin2_code":"56",
    "gn:admin3_code":"153828000.0",
    "gn:asciiname":"Kamasi",
    "gn:country_code":"PH",
    "gn:dem":83,
    "gn:feature_class":"P",
    "gn:feature_code":"PPL",
    "gn:name":"Kamasi",
    "gn:population":0,
    "gn:timezone":"Asia/Manila",
    "iso:country":"PH",
    "name:ara_x_preferred":[
        "\u0643\u0645\u0627\u0633\u064a"
    ],
    "name:fas_x_preferred":[
        "\u06a9\u0645\u0627\u0633\u06cc"
    ],
    "name:fil_x_preferred":[
        "Kamasi"
    ],
    "name:msa_x_preferred":[
        "Kamasi"
    ],
    "wof:name":"Kamasi",
    "wof:placetype":"locality"
},
  "geometry": {"coordinates":[124.4864,6.72568],"type":"Point"}
}