{
  "type": "Feature",
  "properties": {
    "gn:admin1_code":"15",
    "gn:admin2_code":"H6",
    "gn:admin3_code":"148105000.0",
    "gn:asciiname":"Santa Lina",
    "gn:country_code":"PH",
    "gn:dem":16,
    "gn:feature_class":"P",
    "gn:feature_code":"PPL",
    "gn:name":"Santa Lina",
    "gn:population":0,
    "gn:timezone":"Asia/Manila",
    "iso:country":"PH",
    "wof:name":"Santa Lina",
    "wof:placetype":"locality"
},
  "geometry": {"coordinates":[121.38446,18.30649],"type":"Point"}
}