{
  "type": "Feature",
  "properties": {
    "gn:admin1_code":"08",
    "gn:admin2_code":"55",
    "gn:asciiname":"Cinco",
    "gn:cc2":"PH",
    "gn:country_code":"PH",
    "gn:dem":94,
    "gn:feature_class":"P",
    "gn:feature_code":"PPL",
    "gn:name":"Cinco",
    "gn:population":0,
    "gn:timezone":"Asia/Manila",
    "iso:country":"PH",
    "name:deu_x_preferred":[
        "Cinco"
    ],
    "name:fra_x_preferred":[
        "Cinco"
    ],
    "name:nld_x_preferred":[
        "Cinco"
    ],
    "name:spa_x_preferred":[
        "Cinco"
    ],
    "name:und_x_variant":[
        "Rama"
    ],
    "wof:name":"Cinco",
    "wof:placetype":"locality"
},
  "geometry": {"coordinates":[124.69833,11.82222],"type":"Point"}
}