{
  "type": "Feature",
  "properties": {
    "gn:admin1_code":"07",
    "gn:admin2_code":"11",
    "gn:admin3_code":"71216000.0",
    "gn:asciiname":"De la Paz",
    "gn:country_code":"PH",
    "gn:dem":4,
    "gn:feature_class":"P",
    "gn:feature_code":"PPL",
    "gn:name":"De la Paz",
    "gn:population":3144,
    "gn:timezone":"Asia/Manila",
    "iso:country":"PH",
    "name:fil_x_preferred":[
        "La Paz"
    ],
    "name:und_x_variant":[
        "De la Paz"
    ],
    "wof:name":"De la Paz",
    "wof:placetype":"locality",
    "wof:population":3144
},
  "geometry": {"coordinates":[123.86433,9.70004],"type":"Point"}
}