{
  "type": "Feature",
  "properties": {
    "gn:admin1_code":"03",
    "gn:admin2_code":"47",
    "gn:admin3_code":"34907000.0",
    "gn:asciiname":"Irorolong",
    "gn:country_code":"PH",
    "gn:dem":163,
    "gn:feature_class":"P",
    "gn:feature_code":"PPL",
    "gn:name":"Irorolong",
    "gn:population":0,
    "gn:timezone":"Asia/Manila",
    "iso:country":"PH",
    "name:fil_x_preferred":[
        "Irorolong"
    ],
    "name:fil_x_variant":[
        "Ururulong"
    ],
    "wof:name":"Irorolong",
    "wof:placetype":"locality"
},
  "geometry": {"coordinates":[121.343,15.429],"type":"Point"}
}