{
  "type": "Feature",
  "properties": {
    "gn:admin1_code":"07",
    "gn:admin2_code":"46",
    "gn:admin3_code":"74623000.0",
    "gn:asciiname":"Bongbong",
    "gn:country_code":"PH",
    "gn:dem":286,
    "gn:feature_class":"P",
    "gn:feature_code":"PPL",
    "gn:name":"Bongbong",
    "gn:population":0,
    "gn:timezone":"Asia/Manila",
    "iso:country":"PH",
    "name:fil_x_preferred":[
        "Bongbong"
    ],
    "wof:name":"Bongbong",
    "wof:placetype":"locality"
},
  "geometry": {"coordinates":[123.23609999999999,9.279],"type":"Point"}
}