{
  "type": "Feature",
  "properties": {
    "gn:country":"PH",
    "gn:fcode":"PPL",
    "gn:population":4910,
    "iso:country":"PH",
    "name:fil_x_preferred":[
        "Sandiat"
    ],
    "name:und_x_variant":[
        "Sandiat Centro"
    ],
    "qs:name":"Sandiat",
    "qs:photos_9r":0,
    "qs:photos_sr":0,
    "qs:pop_sr":"4",
    "wof:name":"Sandiat",
    "wof:placetype":"locality",
    "wof:population":4910
},
  "geometry": {"coordinates":[121.66584,17.07404],"type":"Point"}
}