{
  "type": "Feature",
  "properties": {
    "gn:admin1_code":"06",
    "gn:admin2_code":"30",
    "gn:admin3_code":"63025000.0",
    "gn:asciiname":"Misi",
    "gn:country_code":"PH",
    "gn:dem":126,
    "gn:feature_class":"P",
    "gn:feature_code":"PPL",
    "gn:name":"Misi",
    "gn:population":0,
    "gn:timezone":"Asia/Manila",
    "iso:country":"PH",
    "name:fil_x_preferred":[
        "Misi"
    ],
    "wof:name":"Misi",
    "wof:placetype":"locality"
},
  "geometry": {"coordinates":[122.45171000000001,11.05113],"type":"Point"}
}