{
  "type": "Feature",
  "properties": {
    "gn:admin1_code":"09",
    "gn:admin2_code":"ZSI",
    "gn:admin3_code":"98301000.0",
    "gn:asciiname":"Letayan",
    "gn:cc2":"PH",
    "gn:country_code":"PH",
    "gn:dem":5,
    "gn:feature_class":"P",
    "gn:feature_code":"PPL",
    "gn:name":"Letayan",
    "gn:population":0,
    "gn:timezone":"Asia/Manila",
    "iso:country":"PH",
    "name:und_x_variant":[
        "Letayen",
        "Letayan"
    ],
    "wof:name":"Letayan",
    "wof:placetype":"locality"
},
  "geometry": {"coordinates":[122.96611,7.46083],"type":"Point"}
}