{
  "type": "Feature",
  "properties": {
    "gn:admin1_code":"03",
    "gn:admin2_code":"64",
    "gn:admin3_code":"37114000.0",
    "gn:asciiname":"Naugsol",
    "gn:country_code":"PH",
    "gn:dem":19,
    "gn:feature_class":"P",
    "gn:feature_code":"PPL",
    "gn:name":"Naugsol",
    "gn:population":0,
    "gn:timezone":"Asia/Manila",
    "iso:country":"PH",
    "name:eng_x_preferred":[
        "Naugsol"
    ],
    "name:und_x_variant":[
        "Naogsol",
        "Naugsol"
    ],
    "wof:name":"Naugsol",
    "wof:placetype":"locality"
},
  "geometry": {"coordinates":[120.26429,14.87995],"type":"Point"}
}