{
  "type": "Feature",
  "properties": {
    "gn:admin1_code":"40",
    "gn:admin2_code":"09",
    "gn:admin3_code":"41019000.0",
    "gn:asciiname":"Botocan",
    "gn:country_code":"PH",
    "gn:dem":47,
    "gn:feature_class":"P",
    "gn:feature_code":"PPL",
    "gn:name":"Botocan",
    "gn:population":0,
    "gn:timezone":"Asia/Manila",
    "iso:country":"PH",
    "name:fil_x_preferred":[
        "Botocan"
    ],
    "wof:name":"Botocan",
    "wof:placetype":"locality"
},
  "geometry": {"coordinates":[120.68899999999999,14.1195],"type":"Point"}
}