{
  "type": "Feature",
  "properties": {
    "gn:admin1_code":"01",
    "gn:admin2_code":"51",
    "gn:admin3_code":"15537000.0",
    "gn:asciiname":"Zamora",
    "gn:country_code":"PH",
    "gn:dem":80,
    "gn:feature_class":"P",
    "gn:feature_code":"PPL",
    "gn:name":"Zamora",
    "gn:population":0,
    "gn:timezone":"Asia/Manila",
    "iso:country":"PH",
    "name:fil_x_preferred":[
        "Zamora"
    ],
    "wof:name":"Zamora",
    "wof:placetype":"locality"
},
  "geometry": {"coordinates":[120.7855,16.0005],"type":"Point"}
}