{
  "type": "Feature",
  "properties": {
    "gn:admin1_code":"06",
    "gn:admin2_code":"30",
    "gn:admin3_code":"63031000.0",
    "gn:asciiname":"Malublub",
    "gn:country_code":"PH",
    "gn:dem":52,
    "gn:feature_class":"P",
    "gn:feature_code":"PPL",
    "gn:name":"Malublub",
    "gn:population":0,
    "gn:timezone":"Asia/Manila",
    "iso:country":"PH",
    "name:fil_x_preferred":[
        "Malublub"
    ],
    "wof:name":"Malublub",
    "wof:placetype":"locality"
},
  "geometry": {"coordinates":[122.5729,10.97],"type":"Point"}
}