{
  "type": "Feature",
  "properties": {
    "gn:country":"PH",
    "gn:fcode":"PPL",
    "gn:population":6610,
    "iso:country":"PH",
    "name:fil_x_preferred":[
        "Inayagan"
    ],
    "qs:name":"Inayagan",
    "qs:photos_9r":0,
    "qs:photos_sr":0,
    "qs:pop_sr":"5",
    "wof:name":"Inayagan",
    "wof:placetype":"locality",
    "wof:population":6610
},
  "geometry": {"coordinates":[123.76900000000001,10.23478],"type":"Point"}
}