{
  "type": "Feature",
  "properties": {
    "gn:admin1_code":"01",
    "gn:admin2_code":"28",
    "gn:admin3_code":"12822000.0",
    "gn:asciiname":"Santana",
    "gn:country_code":"PH",
    "gn:dem":66,
    "gn:feature_class":"P",
    "gn:feature_code":"PPL",
    "gn:name":"Santana",
    "gn:population":0,
    "gn:timezone":"Asia/Manila",
    "iso:country":"PH",
    "name:fil_x_preferred":[
        "Santa Ana"
    ],
    "name:fil_x_variant":[
        "Santana"
    ],
    "wof:name":"Santana",
    "wof:placetype":"locality"
},
  "geometry": {"coordinates":[120.78973000000001,18.07007],"type":"Point"}
}