{
  "type": "Feature",
  "properties": {
    "gn:admin1_code":"08",
    "gn:admin2_code":"59",
    "gn:admin3_code":"86407000.0",
    "gn:asciiname":"Asuncion",
    "gn:country_code":"PH",
    "gn:dem":32,
    "gn:feature_class":"P",
    "gn:feature_code":"PPL",
    "gn:name":"Asuncion",
    "gn:population":0,
    "gn:timezone":"Asia/Manila",
    "iso:country":"PH",
    "name:fil_x_preferred":[
        "Asuncion"
    ],
    "name:fil_x_variant":[
        "Pacu",
        "Paco"
    ],
    "wof:name":"Asuncion",
    "wof:placetype":"locality"
},
  "geometry": {"coordinates":[124.86139,10.13389],"type":"Point"}
}