{
  "type": "Feature",
  "properties": {
    "iso:country":"PH",
    "name:bcl_x_preferred":[
        "Carigara"
    ],
    "name:cbk_zam_x_preferred":[
        "Carigara"
    ],
    "name:ceb_x_preferred":[
        "Carigara"
    ],
    "name:deu_x_preferred":[
        "Carigara"
    ],
    "name:eng_x_preferred":[
        "Carigara"
    ],
    "name:fra_x_preferred":[
        "Carigara"
    ],
    "name:ilo_x_preferred":[
        "Carigara"
    ],
    "name:ind_x_preferred":[
        "Carigara"
    ],
    "name:ita_x_preferred":[
        "Carigara"
    ],
    "name:jpn_x_preferred":[
        "\u30ab\u30ea\u30ac\u30e9"
    ],
    "name:nld_x_preferred":[
        "Carigara"
    ],
    "name:pag_x_preferred":[
        "Carigara"
    ],
    "name:pam_x_preferred":[
        "Carigara"
    ],
    "name:por_x_preferred":[
        "Carigara"
    ],
    "name:swe_x_preferred":[
        "Carigara"
    ],
    "name:tgl_x_preferred":[
        "Carigara"
    ],
    "name:unk_x_variant":[
        "Garigara"
    ],
    "name:vie_x_preferred":[
        "Carigara"
    ],
    "name:war_x_preferred":[
        "Carigara"
    ],
    "qs:gn_country":"PH",
    "qs:gn_fcode":"PPLA3",
    "qs:gn_pop":17495,
    "qs:name":"Carigara",
    "qs:name_adm0":"Philippines",
    "qs:name_adm1":"Eastern Visayas",
    "qs:photos":0,
    "qs:photos_1k":0,
    "qs:photos_9k":1,
    "qs:photos_9r":1,
    "qs:photos_all":21,
    "qs:photos_sr":0,
    "qs:placetype":"Town",
    "qs:pop_sr":"6",
    "qs:woe_adm0":23424934,
    "wd:wordcount":347,
    "wof:name":"Carigara",
    "wof:placetype":"locality",
    "wof:population":17495
},
  "geometry": {"coordinates":[124.67556,11.29917],"type":"Point"}
}