{
  "type": "Feature",
  "properties": {
    "gn:admin1_code":"02",
    "gn:admin2_code":"31",
    "gn:admin3_code":"23114000.0",
    "gn:asciiname":"Maridi",
    "gn:country_code":"PH",
    "gn:dem":51,
    "gn:feature_class":"P",
    "gn:feature_code":"PPL",
    "gn:name":"Maridi",
    "gn:population":0,
    "gn:timezone":"Asia/Manila",
    "iso:country":"PH",
    "name:ara_x_preferred":[
        "\u0645\u0627\u0631\u064a\u062f\u064a"
    ],
    "name:ceb_x_preferred":[
        "Mar\u012bdi"
    ],
    "name:deu_x_preferred":[
        "Maridi"
    ],
    "name:fil_x_preferred":[
        "Maridi"
    ],
    "name:fra_x_preferred":[
        "Maridi"
    ],
    "name:ita_x_preferred":[
        "Maridi"
    ],
    "name:pol_x_preferred":[
        "Maridi"
    ],
    "name:rus_x_preferred":[
        "\u041c\u0430\u0440\u0438\u0434\u0438"
    ],
    "name:srp_x_preferred":[
        "\u041c\u0430\u0440\u0438\u0434\u0438"
    ],
    "name:swe_x_preferred":[
        "Mar\u012bdi"
    ],
    "name:ukr_x_preferred":[
        "\u041c\u0430\u0440\u0438\u0434\u0456"
    ],
    "name:zho_x_preferred":[
        "\u99ac\u91cc\u8fea"
    ],
    "wof:name":"Maridi",
    "wof:placetype":"locality"
},
  "geometry": {"coordinates":[121.97774,17.04584],"type":"Point"}
}