{
  "type": "Feature",
  "properties": {
    "gn:admin1_code":"02",
    "gn:admin2_code":"31",
    "gn:admin3_code":"23114000.0",
    "gn:asciiname":"Maridi",
    "gn:country_code":"PH",
    "gn:dem":51,
    "gn:feature_class":"P",
    "gn:feature_code":"PPL",
    "gn:name":"Maridi",
    "gn:population":0,
    "gn:timezone":"Asia/Manila",
    "iso:country":"PH",
    "name:ara_x_preferred":[
        "\u0645\u0627\u0631\u064a\u062f\u064a"
    ],
    "name:ben_x_preferred":[
        "\u09ae\u09be\u09b0\u09bf\u09a6\u09bf"
    ],
    "name:ceb_x_preferred":[
        "Mar\u012bdi"
    ],
    "name:deu_x_preferred":[
        "Maridi"
    ],
    "name:ell_x_preferred":[
        "\u039c\u03b1\u03c1\u03af\u03b4\u03b9"
    ],
    "name:fas_x_preferred":[
        "\u0645\u0627\u0631\u06cc\u062f\u06cc"
    ],
    "name:fil_x_preferred":[
        "Maridi"
    ],
    "name:fra_x_preferred":[
        "Maridi"
    ],
    "name:heb_x_preferred":[
        "\u05de\u05e8\u05d9\u05d3\u05d9"
    ],
    "name:hin_x_preferred":[
        "\u092e\u0930\u0940\u0926\u0940"
    ],
    "name:hun_x_preferred":[
        "Maridi"
    ],
    "name:ind_x_preferred":[
        "Maridi"
    ],
    "name:ita_x_preferred":[
        "Maridi"
    ],
    "name:kor_x_preferred":[
        "\ub9c8\ub9ac\ub514"
    ],
    "name:pol_x_preferred":[
        "Maridi"
    ],
    "name:rus_x_preferred":[
        "\u041c\u0430\u0440\u0438\u0434\u0438"
    ],
    "name:spa_x_preferred":[
        "Maridi"
    ],
    "name:srp_x_preferred":[
        "\u041c\u0430\u0440\u0438\u0434\u0438"
    ],
    "name:swe_x_preferred":[
        "Mar\u012bdi"
    ],
    "name:tur_x_preferred":[
        "Maridi"
    ],
    "name:ukr_x_preferred":[
        "\u041c\u0430\u0440\u0438\u0434\u0456"
    ],
    "name:urd_x_preferred":[
        "\u0645\u0627\u0631\u06cc\u0688\u06cc"
    ],
    "name:zho_x_preferred":[
        "\u99ac\u91cc\u8fea"
    ],
    "wof:name":"Maridi",
    "wof:placetype":"locality"
},
  "geometry": {"coordinates":[121.97774,17.04584],"type":"Point"}
}