{
  "type": "Feature",
  "properties": {
    "gn:admin1_code":"02",
    "gn:admin2_code":"31",
    "gn:admin3_code":"23114000.0",
    "gn:asciiname":"Maridi",
    "gn:country_code":"PH",
    "gn:dem":51,
    "gn:feature_class":"P",
    "gn:feature_code":"PPL",
    "gn:name":"Maridi",
    "gn:population":0,
    "gn:timezone":"Asia/Manila",
    "iso:country":"PH",
    "name:fil_x_preferred":[
        "Maridi"
    ],
    "wof:name":"Maridi",
    "wof:placetype":"locality"
},
  "geometry": {"coordinates":[121.97774,17.04584],"type":"Point"}
}