{
  "type": "Feature",
  "properties": {
    "gn:admin1_code":"08",
    "gn:admin2_code":"37",
    "gn:admin3_code":"83708000.0",
    "gn:asciiname":"Kabalasan",
    "gn:country_code":"PH",
    "gn:dem":26,
    "gn:feature_class":"P",
    "gn:feature_code":"PPL",
    "gn:name":"Kabalasan",
    "gn:population":0,
    "gn:timezone":"Asia/Manila",
    "iso:country":"PH",
    "name:fil_x_preferred":[
        "Kabalasan"
    ],
    "name:und_x_variant":[
        "Cabalasan",
        "Kabalasan"
    ],
    "wof:name":"Kabalasan",
    "wof:placetype":"locality"
},
  "geometry": {"coordinates":[124.8387,10.64],"type":"Point"}
}