{
  "type": "Feature",
  "properties": {
    "gn:admin1_code":"14",
    "gn:admin2_code":"56",
    "gn:admin3_code":"153813000.0",
    "gn:asciiname":"Sambuan",
    "gn:country_code":"PH",
    "gn:dem":10,
    "gn:feature_class":"P",
    "gn:feature_code":"PPL",
    "gn:name":"Sambuan",
    "gn:population":0,
    "gn:timezone":"Asia/Manila",
    "iso:country":"PH",
    "name:fil_x_preferred":[
        "Sambuan"
    ],
    "wof:name":"Sambuan",
    "wof:placetype":"locality"
},
  "geometry": {"coordinates":[124.68333,6.88333],"type":"Point"}
}