{
  "type": "Feature",
  "properties": {
    "gn:admin1_code":"02",
    "gn:admin2_code":"31",
    "gn:admin3_code":"23114000.0",
    "gn:asciiname":"Calamagui First",
    "gn:country_code":"PH",
    "gn:dem":44,
    "gn:feature_class":"P",
    "gn:feature_code":"PPL",
    "gn:name":"Calamagui First",
    "gn:population":0,
    "gn:timezone":"Asia/Manila",
    "iso:country":"PH",
    "name:fil_x_preferred":[
        "Calamagui-Primero"
    ],
    "name:fil_x_variant":[
        "Calamagui I",
        "Calamagui One"
    ],
    "name:und_x_variant":[
        "Calamagui First",
        "Calamagui Uno"
    ],
    "wof:name":"Calamagui First",
    "wof:placetype":"locality"
},
  "geometry": {"coordinates":[121.86671,17.13848],"type":"Point"}
}