{
  "type": "Feature",
  "properties": {
    "gn:admin1_code":"41",
    "gn:admin2_code":"49",
    "gn:admin3_code":"175322000.0",
    "gn:asciiname":"Balala",
    "gn:country_code":"PH",
    "gn:dem":9,
    "gn:feature_class":"P",
    "gn:feature_code":"PPL",
    "gn:name":"Balala",
    "gn:population":0,
    "gn:timezone":"Asia/Manila",
    "iso:country":"PH",
    "name:fil_x_preferred":[
        "Balala"
    ],
    "wof:name":"Balala",
    "wof:placetype":"locality"
},
  "geometry": {"coordinates":[120.021,11.893],"type":"Point"}
}