{
  "type": "Feature",
  "properties": {
    "gn:admin1_code":"10",
    "gn:admin2_code":"34",
    "gn:asciiname":"Tabique",
    "gn:country_code":"PH",
    "gn:dem":-9999,
    "gn:feature_class":"P",
    "gn:feature_code":"PPL",
    "gn:name":"Tabique",
    "gn:population":0,
    "gn:timezone":"Asia/Manila",
    "iso:country":"PH",
    "name:eng_x_preferred":[
        "Tabique"
    ],
    "name:und_x_variant":[
        "Tabigue"
    ],
    "wof:name":"Tabique",
    "wof:placetype":"locality"
},
  "geometry": {"coordinates":[123.839,8.0984],"type":"Point"}
}