{
  "type": "Feature",
  "properties": {
    "gn:admin1_code":"03",
    "gn:admin2_code":"63",
    "gn:admin3_code":"36908000.0",
    "gn:asciiname":"Bigbiga",
    "gn:country_code":"PH",
    "gn:dem":123,
    "gn:feature_class":"P",
    "gn:feature_code":"PPL",
    "gn:name":"Bigbiga",
    "gn:population":0,
    "gn:timezone":"Asia/Manila",
    "iso:country":"PH",
    "name:fil_x_preferred":[
        "Bigbiga"
    ],
    "wof:name":"Bigbiga",
    "wof:placetype":"locality"
},
  "geometry": {"coordinates":[120.37645999999999,15.52811],"type":"Point"}
}