{
  "type": "Feature",
  "properties": {
    "gn:admin1_code":"40",
    "gn:admin2_code":"H2",
    "gn:admin3_code":"45629000.0",
    "gn:asciiname":"Vargas",
    "gn:country_code":"PH",
    "gn:dem":114,
    "gn:feature_class":"P",
    "gn:feature_code":"PPL",
    "gn:name":"Vargas",
    "gn:population":0,
    "gn:timezone":"Asia/Manila",
    "iso:country":"PH",
    "name:bre_x_preferred":[
        "Vargas"
    ],
    "name:bul_x_preferred":[
        "\u0412\u0430\u0440\u0433\u0430\u0441"
    ],
    "name:cat_x_preferred":[
        "Vargas"
    ],
    "name:ceb_x_preferred":[
        "Vargas"
    ],
    "name:ces_x_preferred":[
        "Vargas"
    ],
    "name:deu_x_preferred":[
        "Vargas"
    ],
    "name:epo_x_preferred":[
        "Vargas"
    ],
    "name:fil_x_preferred":[
        "Vargas"
    ],
    "name:fin_x_preferred":[
        "Vargas"
    ],
    "name:fra_x_preferred":[
        "Vargas"
    ],
    "name:heb_x_preferred":[
        "\u05d5\u05e8\u05d2\u05d0\u05e1"
    ],
    "name:ita_x_preferred":[
        "Vargas"
    ],
    "name:jpn_x_preferred":[
        "\u30d0\u30eb\u30ac\u30b9"
    ],
    "name:kor_x_preferred":[
        "\ubc14\ub974\uac00\uc2a4"
    ],
    "name:nds_x_preferred":[
        "Vargas"
    ],
    "name:nld_x_preferred":[
        "Vargas"
    ],
    "name:pol_x_preferred":[
        "Vargas"
    ],
    "name:por_x_preferred":[
        "Vargas"
    ],
    "name:rus_x_preferred":[
        "\u0412\u0430\u0440\u0433\u0430\u0441"
    ],
    "name:sco_x_preferred":[
        "Vargas"
    ],
    "name:spa_x_preferred":[
        "Vargas"
    ],
    "name:srp_x_preferred":[
        "\u0412\u0430\u0440\u0433\u0430\u0441"
    ],
    "name:swe_x_preferred":[
        "Vargas"
    ],
    "name:ukr_x_preferred":[
        "\u0412\u0430\u0440\u0491\u0430\u0441"
    ],
    "wof:name":"Vargas",
    "wof:placetype":"locality"
},
  "geometry": {"coordinates":[121.83333,13.96667],"type":"Point"}
}