{
  "type": "Feature",
  "properties": {
    "gn:admin1_code":"40",
    "gn:admin2_code":"H2",
    "gn:admin3_code":"45629000.0",
    "gn:asciiname":"Vargas",
    "gn:country_code":"PH",
    "gn:dem":114,
    "gn:feature_class":"P",
    "gn:feature_code":"PPL",
    "gn:name":"Vargas",
    "gn:population":0,
    "gn:timezone":"Asia/Manila",
    "iso:country":"PH",
    "name:fil_x_preferred":[
        "Vargas"
    ],
    "wof:name":"Vargas",
    "wof:placetype":"locality"
},
  "geometry": {"coordinates":[121.83333,13.96667],"type":"Point"}
}