{
  "type": "Feature",
  "properties": {
    "gn:admin1_code":"40",
    "gn:admin2_code":"H2",
    "gn:admin3_code":"45642000.0",
    "gn:asciiname":"Malangog",
    "gn:country_code":"PH",
    "gn:dem":155,
    "gn:feature_class":"P",
    "gn:feature_code":"PPL",
    "gn:name":"Malangog",
    "gn:population":0,
    "gn:timezone":"Asia/Manila",
    "iso:country":"PH",
    "name:fil_x_preferred":[
        "Malangog"
    ],
    "wof:name":"Malangog",
    "wof:placetype":"locality"
},
  "geometry": {"coordinates":[122.58444,13.21472],"type":"Point"}
}