{
  "type": "Feature",
  "properties": {
    "gn:country":"PH",
    "gn:fcode":"PPLA3",
    "gn:pop":12538,
    "iso:country":"PH",
    "name:bcl_x_preferred":[
        "South Upi"
    ],
    "name:dut_x_preferred":[
        "South Upi"
    ],
    "name:eng_x_preferred":[
        "South Upi"
    ],
    "name:fre_x_preferred":[
        "South Upi"
    ],
    "name:ger_x_preferred":[
        "South Upi"
    ],
    "name:ilo_x_preferred":[
        "Abagatan nga Upi"
    ],
    "name:ind_x_preferred":[
        "Upi Selatan"
    ],
    "name:ita_x_preferred":[
        "South Upi"
    ],
    "name:pag_x_preferred":[
        "South Upi"
    ],
    "name:pam_x_preferred":[
        "Mauling Upi"
    ],
    "name:spa_x_preferred":[
        "Upi del Sur"
    ],
    "name:swe_x_preferred":[
        "South Upi"
    ],
    "name:tgl_x_preferred":[
        "South Upi"
    ],
    "name:unk_x_variant":[
        "Looy"
    ],
    "name:urd_x_preferred":[
        "\u062c\u0646\u0648\u0628\u06cc \u0627\u0648\u067e\u06cc\u060c \u0645\u0627\u06af\u0648\u0626\u0646\u062f\u0627\u0646\u0627\u0624"
    ],
    "name:vie_x_preferred":[
        "Nam Upi"
    ],
    "name:war_x_preferred":[
        "South Upi"
    ],
    "qs:name":"South Upi",
    "qs:photos_9r":0,
    "qs:photos_sr":0,
    "qs:pop_sr":"6",
    "wof:name":"South Upi",
    "wof:placetype":"locality",
    "wof:population":12538
},
  "geometry": {"coordinates":[124.15000000000001,6.83333],"type":"Point"}
}