{
  "type": "Feature",
  "properties": {
    "gn:admin1_code":"13",
    "gn:admin2_code":"62",
    "gn:admin3_code":"166808000.0",
    "gn:asciiname":"Nucia",
    "gn:cc2":"PH",
    "gn:country_code":"PH",
    "gn:dem":35,
    "gn:feature_class":"P",
    "gn:feature_code":"PPL",
    "gn:name":"Nucia",
    "gn:population":0,
    "gn:timezone":"Asia/Manila",
    "iso:country":"PH",
    "name:und_x_variant":[
        "Lucia",
        "Nusia",
        "Nucia"
    ],
    "wof:name":"Nucia",
    "wof:placetype":"locality"
},
  "geometry": {"coordinates":[126.16472,9.27778],"type":"Point"}
}