{
  "type": "Feature",
  "properties": {
    "gn:admin1_code":"10",
    "gn:admin2_code":"17",
    "gn:admin3_code":"101804000.0",
    "gn:asciiname":"Harasan",
    "gn:country_code":"PH",
    "gn:dem":162,
    "gn:feature_class":"P",
    "gn:feature_code":"PPL",
    "gn:name":"Harasan",
    "gn:population":0,
    "gn:timezone":"Asia/Manila",
    "iso:country":"PH",
    "name:fil_x_preferred":[
        "Harasan"
    ],
    "wof:name":"Harasan",
    "wof:placetype":"locality"
},
  "geometry": {"coordinates":[124.7242,9.2253],"type":"Point"}
}