{
  "type": "Feature",
  "properties": {
    "gn:admin1_code":"08",
    "gn:admin2_code":"55",
    "gn:admin3_code":"86020000.0",
    "gn:asciiname":"Libucan Gote",
    "gn:country_code":"PH",
    "gn:dem":3,
    "gn:feature_class":"P",
    "gn:feature_code":"PPL",
    "gn:name":"Libucan Gote",
    "gn:population":0,
    "gn:timezone":"Asia/Manila",
    "iso:country":"PH",
    "name:fil_x_preferred":[
        "Libucan West"
    ],
    "name:fil_x_variant":[
        "Libucan Gote"
    ],
    "wof:name":"Libucan Gote",
    "wof:placetype":"locality"
},
  "geometry": {"coordinates":[124.63081,11.9124],"type":"Point"}
}