{
  "type": "Feature",
  "properties": {
    "gn:admin1_code":"05",
    "gn:admin2_code":"58",
    "gn:admin3_code":"56205000.0",
    "gn:asciiname":"Tulay",
    "gn:country_code":"PH",
    "gn:dem":8,
    "gn:feature_class":"P",
    "gn:feature_code":"PPL",
    "gn:name":"Tulay",
    "gn:population":0,
    "gn:timezone":"Asia/Manila",
    "iso:country":"PH",
    "name:ceb_x_preferred":[
        "Tulay"
    ],
    "name:fil_x_preferred":[
        "Tulay"
    ],
    "wof:name":"Tulay",
    "wof:placetype":"locality"
},
  "geometry": {"coordinates":[124.00700000000001,12.8713],"type":"Point"}
}