{
  "type": "Feature",
  "properties": {
    "gn:admin1_code":"06",
    "gn:admin2_code":"30",
    "gn:admin3_code":"63025000.0",
    "gn:asciiname":"Supac",
    "gn:country_code":"PH",
    "gn:dem":374,
    "gn:feature_class":"P",
    "gn:feature_code":"PPL",
    "gn:name":"Supac",
    "gn:population":0,
    "gn:timezone":"Asia/Manila",
    "iso:country":"PH",
    "name:fil_x_preferred":[
        "Supac"
    ],
    "wof:name":"Supac",
    "wof:placetype":"locality"
},
  "geometry": {"coordinates":[122.38370999999999,11.11403],"type":"Point"}
}