{
  "type": "Feature",
  "properties": {
    "gn:admin1_code":"10",
    "gn:admin2_code":"12",
    "gn:admin3_code":"101311000.0",
    "gn:asciiname":"Capihan",
    "gn:country_code":"PH",
    "gn:dem":914,
    "gn:feature_class":"P",
    "gn:feature_code":"PPL",
    "gn:name":"Capihan",
    "gn:population":0,
    "gn:timezone":"Asia/Manila",
    "iso:country":"PH",
    "name:fil_x_preferred":[
        "Capihan"
    ],
    "wof:name":"Capihan",
    "wof:placetype":"locality"
},
  "geometry": {"coordinates":[124.80028,8.23528],"type":"Point"}
}