{
  "type": "Feature",
  "properties": {
    "gn:admin1_code":"03",
    "gn:admin2_code":"47",
    "gn:admin3_code":"34917000.0",
    "gn:asciiname":"Villa Nati",
    "gn:country_code":"PH",
    "gn:dem":73,
    "gn:feature_class":"P",
    "gn:feature_code":"PPL",
    "gn:name":"Villa Nati",
    "gn:population":0,
    "gn:timezone":"Asia/Manila",
    "iso:country":"PH",
    "name:fil_x_preferred":[
        "Villa Nati"
    ],
    "wof:name":"Villa Nati",
    "wof:placetype":"locality"
},
  "geometry": {"coordinates":[120.93731,15.69366],"type":"Point"}
}