{
  "type": "Feature",
  "properties": {
    "gn:admin1_code":"40",
    "gn:admin2_code":"H2",
    "gn:admin3_code":"45621000.0",
    "gn:asciiname":"Talisoy",
    "gn:country_code":"PH",
    "gn:dem":17,
    "gn:feature_class":"P",
    "gn:feature_code":"PPL",
    "gn:name":"Talisoy",
    "gn:population":0,
    "gn:timezone":"Asia/Manila",
    "iso:country":"PH",
    "wof:name":"Talisoy",
    "wof:placetype":"locality"
},
  "geometry": {"coordinates":[122.33787,14.69947],"type":"Point"}
}