{
  "type": "Feature",
  "properties": {
    "gn:admin1_code":"12",
    "gn:admin2_code":"57",
    "gn:admin3_code":"124702000.0",
    "gn:asciiname":"Kitubod",
    "gn:cc2":"PH",
    "gn:country_code":"PH",
    "gn:dem":41,
    "gn:feature_class":"P",
    "gn:feature_code":"PPL",
    "gn:name":"Kitubod",
    "gn:population":0,
    "gn:timezone":"Asia/Manila",
    "iso:country":"PH",
    "name:und_x_variant":[
        "Kitubud",
        "Kitubod"
    ],
    "wof:name":"Kitubod",
    "wof:placetype":"locality"
},
  "geometry": {"coordinates":[124.70917,7.2875],"type":"Point"}
}