{
  "type": "Feature",
  "properties": {
    "gn:admin1_code":"01",
    "gn:admin2_code":"29",
    "gn:admin3_code":"12910000.0",
    "gn:asciiname":"Mabatano",
    "gn:country_code":"PH",
    "gn:dem":505,
    "gn:feature_class":"P",
    "gn:feature_code":"PPL",
    "gn:name":"Mabatano",
    "gn:population":0,
    "gn:timezone":"Asia/Manila",
    "iso:country":"PH",
    "name:fil_x_preferred":[
        "Mabatano"
    ],
    "wof:name":"Mabatano",
    "wof:placetype":"locality"
},
  "geometry": {"coordinates":[120.61611000000001,17.13778],"type":"Point"}
}