{
  "type": "Feature",
  "properties": {
    "gn:country":"PH",
    "gn:fcode":"PPL",
    "gn:population":5164,
    "iso:country":"PH",
    "name:eng_x_preferred":[
        "Conduaga"
    ],
    "name:und_x_variant":[
        "Candawaga"
    ],
    "qs:name":"Conduaga",
    "qs:photos_9r":0,
    "qs:photos_sr":0,
    "qs:pop_sr":"5",
    "wof:name":"Conduaga",
    "wof:placetype":"locality",
    "wof:population":5164
},
  "geometry": {"coordinates":[117.4893,8.862],"type":"Point"}
}