{
  "type": "Feature",
  "properties": {
    "gn:admin1_code":"06",
    "gn:admin2_code":"H3",
    "gn:admin3_code":"64513000.0",
    "gn:asciiname":"Talubangi",
    "gn:country_code":"PH",
    "gn:dem":11,
    "gn:feature_class":"P",
    "gn:feature_code":"PPL",
    "gn:name":"Talubangi",
    "gn:population":0,
    "gn:timezone":"Asia/Manila",
    "iso:country":"PH",
    "name:fil_x_preferred":[
        "Talubangi"
    ],
    "name:und_x_variant":[
        "Talubang"
    ],
    "wof:name":"Talubangi",
    "wof:placetype":"locality"
},
  "geometry": {"coordinates":[122.80200000000001,10.0103],"type":"Point"}
}