{
  "type": "Feature",
  "properties": {
    "gn:admin1_code":"15",
    "gn:admin2_code":"01",
    "gn:admin3_code":"140114000.0",
    "gn:asciiname":"Agomanay",
    "gn:country_code":"PH",
    "gn:dem":435,
    "gn:feature_class":"P",
    "gn:feature_code":"PPL",
    "gn:name":"Agomanay",
    "gn:population":0,
    "gn:timezone":"Asia/Manila",
    "iso:country":"PH",
    "name:fil_x_preferred":[
        "Agomanay"
    ],
    "wof:name":"Agomanay",
    "wof:placetype":"locality"
},
  "geometry": {"coordinates":[120.64749999999999,17.2927],"type":"Point"}
}