{
  "type": "Feature",
  "properties": {
    "gn:country":"PH",
    "gn:fcode":"PPL",
    "gn:pop":11121,
    "iso:country":"PH",
    "name:ara_x_preferred":[
        "\u063a\u0648\u0627\u062f\u0627\u0644\u0648\u0628\u064a"
    ],
    "name:arg_x_preferred":[
        "Guadalupe"
    ],
    "name:bre_x_preferred":[
        "Guadalupe"
    ],
    "name:cat_x_preferred":[
        "Guadalupe"
    ],
    "name:ceb_x_preferred":[
        "Guadalupe"
    ],
    "name:ces_x_preferred":[
        "Guadalupe"
    ],
    "name:deu_x_preferred":[
        "Guadalupe"
    ],
    "name:epo_x_preferred":[
        "Guadalupe"
    ],
    "name:eus_x_preferred":[
        "Guadalupe"
    ],
    "name:fas_x_preferred":[
        "\u06af\u0648\u0627\u062f\u0644\u0648\u067e"
    ],
    "name:fil_x_preferred":[
        "Guadalupe"
    ],
    "name:fra_x_preferred":[
        "Guadalupe"
    ],
    "name:glg_x_preferred":[
        "Guadalupe"
    ],
    "name:ind_x_preferred":[
        "Guadalupe"
    ],
    "name:ita_x_preferred":[
        "Guadalupe"
    ],
    "name:jpn_x_preferred":[
        "\u30b0\u30a2\u30c0\u30eb\u30fc\u30da"
    ],
    "name:kat_x_preferred":[
        "\u10d2\u10d5\u10d0\u10d3\u10d0\u10da\u10e3\u10de\u10d4"
    ],
    "name:kor_x_preferred":[
        "\uacfc\ub2ec\ub8e8\ud398"
    ],
    "name:lad_x_preferred":[
        "Guadalupe"
    ],
    "name:lit_x_preferred":[
        "Gvadalup\u0117"
    ],
    "name:msa_x_preferred":[
        "Guadalupe"
    ],
    "name:nah_x_preferred":[
        "Guadalupe"
    ],
    "name:nld_x_preferred":[
        "Guadalupe"
    ],
    "name:nor_x_preferred":[
        "Guadalupe"
    ],
    "name:oci_x_preferred":[
        "Guadalupe"
    ],
    "name:pol_x_preferred":[
        "Guadalupe"
    ],
    "name:por_x_preferred":[
        "Guadalupe"
    ],
    "name:ron_x_preferred":[
        "Guadalupe"
    ],
    "name:rus_x_preferred":[
        "\u0413\u0443\u0430\u0434\u0430\u043b\u0443\u043f\u0435"
    ],
    "name:sco_x_preferred":[
        "Guadalupe"
    ],
    "name:spa_x_preferred":[
        "Guadalupe"
    ],
    "name:srp_x_preferred":[
        "\u0413\u0432\u0430\u0434\u0430\u043b\u0443\u043f"
    ],
    "name:swe_x_preferred":[
        "Guadalupe"
    ],
    "name:ukr_x_preferred":[
        "\u0413\u0432\u0430\u0434\u0430\u043b\u0443\u043f\u0435"
    ],
    "name:unk_x_variant":[
        "Guadelupe"
    ],
    "name:vie_x_preferred":[
        "Guadalupe"
    ],
    "name:vol_x_preferred":[
        "Guadalupe"
    ],
    "name:war_x_preferred":[
        "Guadalupe"
    ],
    "qs:name":"Guadalupe",
    "qs:photos_9r":0,
    "qs:photos_sr":0,
    "qs:pop_sr":"6",
    "wd:wordcount":339,
    "wof:name":"Guadalupe",
    "wof:placetype":"locality",
    "wof:population":11121
},
  "geometry": {"coordinates":[123.60720000000001,10.1165],"type":"Point"}
}