{
  "type": "Feature",
  "properties": {
    "gn:country":"PH",
    "gn:fcode":"PPL",
    "gn:pop":11121,
    "iso:country":"PH",
    "name:fil_x_preferred":[
        "Guadalupe"
    ],
    "name:unk_x_variant":[
        "Guadelupe"
    ],
    "qs:name":"Guadalupe",
    "qs:photos_9r":0,
    "qs:photos_sr":0,
    "qs:pop_sr":"6",
    "wd:wordcount":339,
    "wof:name":"Guadalupe",
    "wof:placetype":"locality",
    "wof:population":11121
},
  "geometry": {"coordinates":[123.60720000000001,10.1165],"type":"Point"}
}