{
  "type": "Feature",
  "properties": {
    "gn:admin1_code":"08",
    "gn:admin2_code":"55",
    "gn:admin3_code":"86008000.0",
    "gn:asciiname":"Cag-obaca",
    "gn:country_code":"PH",
    "gn:dem":45,
    "gn:feature_class":"P",
    "gn:feature_code":"PPL",
    "gn:name":"Cag-obaca",
    "gn:population":0,
    "gn:timezone":"Asia/Manila",
    "iso:country":"PH",
    "name:fil_x_preferred":[
        "Cag-obaca"
    ],
    "wof:name":"Cag-obaca",
    "wof:placetype":"locality"
},
  "geometry": {"coordinates":[125.07333,11.67528],"type":"Point"}
}