{
  "type": "Feature",
  "properties": {
    "gn:admin1_code":"01",
    "gn:admin2_code":"36",
    "gn:admin3_code":"13310000.0",
    "gn:asciiname":"Sucoc Sur",
    "gn:country_code":"PH",
    "gn:dem":12,
    "gn:feature_class":"P",
    "gn:feature_code":"PPL",
    "gn:name":"Sucoc Sur",
    "gn:population":0,
    "gn:timezone":"Asia/Manila",
    "iso:country":"PH",
    "name:fil_x_preferred":[
        "Sucoc Sur"
    ],
    "name:fil_x_variant":[
        "Sucoc"
    ],
    "name:und_x_variant":[
        "Sucoc",
        "Sucoc Sur"
    ],
    "wof:name":"Sucoc Sur",
    "wof:placetype":"locality"
},
  "geometry": {"coordinates":[120.36969999999999,16.8375],"type":"Point"}
}