{
  "type": "Feature",
  "properties": {
    "iso:country":"PH",
    "name:bcl_x_preferred":[
        "Uyugan"
    ],
    "name:cat_x_preferred":[
        "Uyugan"
    ],
    "name:cbk_zam_x_preferred":[
        "Uyugan"
    ],
    "name:ceb_x_preferred":[
        "Uyugan"
    ],
    "name:deu_x_preferred":[
        "Uyugan"
    ],
    "name:eng_x_preferred":[
        "Uyugan"
    ],
    "name:fil_x_preferred":[
        "Uyugan"
    ],
    "name:fra_x_preferred":[
        "Uyugan"
    ],
    "name:ilo_x_preferred":[
        "Uyugan"
    ],
    "name:ind_x_preferred":[
        "Uyugan"
    ],
    "name:ita_x_preferred":[
        "Uyugan"
    ],
    "name:jpn_x_preferred":[
        "\u30aa\u30e6\u30ac\u30f3"
    ],
    "name:nan_x_preferred":[
        "Uyugan"
    ],
    "name:nld_x_preferred":[
        "Uyugan"
    ],
    "name:oci_x_preferred":[
        "Uyugan"
    ],
    "name:pag_x_preferred":[
        "Uyugan"
    ],
    "name:pam_x_preferred":[
        "Uyugan"
    ],
    "name:spa_x_preferred":[
        "Uyugan"
    ],
    "name:swe_x_preferred":[
        "Uyugan"
    ],
    "name:tgl_x_preferred":[
        "Uyugan"
    ],
    "name:und_x_variant":[
        "San Antonio"
    ],
    "name:urd_x_preferred":[
        "\u0627\u0648\u06cc\u0648\u06af\u0627\u0646"
    ],
    "name:vie_x_preferred":[
        "Uyugan"
    ],
    "name:war_x_preferred":[
        "Uyugan"
    ],
    "qs:gn_country":"PH",
    "qs:gn_fcode":"PPLA3",
    "qs:gn_pop":0,
    "qs:name":"Uyugan",
    "qs:name_adm0":"Philippines",
    "qs:name_adm1":"Cagayan Valley",
    "qs:photos":36,
    "qs:photos_1k":7,
    "qs:photos_9k":1,
    "qs:photos_9r":2,
    "qs:photos_all":36,
    "qs:photos_sr":2,
    "qs:placetype":"Town",
    "qs:pop_sr":"0",
    "qs:woe_adm0":23424934,
    "wd:wordcount":1383,
    "wof:name":"Uyugan",
    "wof:placetype":"locality"
},
  "geometry": {"coordinates":[121.93777,20.35045],"type":"Point"}
}