{
  "type": "Feature",
  "properties": {
    "gn:admin1_code":"11",
    "gn:admin2_code":"P3",
    "gn:admin3_code":"118603000.0",
    "gn:asciiname":"Pangayon",
    "gn:country_code":"PH",
    "gn:dem":103,
    "gn:feature_class":"P",
    "gn:feature_code":"PPL",
    "gn:name":"Pangayon",
    "gn:population":0,
    "gn:timezone":"Asia/Manila",
    "iso:country":"PH",
    "name:fil_x_preferred":[
        "Pangayon"
    ],
    "name:und_x_variant":[
        "Pangayan"
    ],
    "wof:name":"Pangayon",
    "wof:placetype":"locality"
},
  "geometry": {"coordinates":[125.52639000000001,6.44722],"type":"Point"}
}