{
  "type": "Feature",
  "properties": {
    "gn:admin1_code":"05",
    "gn:admin2_code":"05",
    "gn:admin3_code":"50501000.0",
    "gn:asciiname":"Tanagan",
    "gn:country_code":"PH",
    "gn:dem":8,
    "gn:feature_class":"P",
    "gn:feature_code":"PPL",
    "gn:name":"Tanagan",
    "gn:population":0,
    "gn:timezone":"Asia/Manila",
    "iso:country":"PH",
    "name:fil_x_preferred":[
        "Tanagan"
    ],
    "wof:name":"Tanagan",
    "wof:placetype":"locality"
},
  "geometry": {"coordinates":[123.8646,13.3126],"type":"Point"}
}