{
  "type": "Feature",
  "properties": {
    "gn:admin1_code":"06",
    "gn:admin2_code":"06",
    "gn:admin3_code":"60606000.0",
    "gn:asciiname":"Panganta",
    "gn:country_code":"PH",
    "gn:dem":17,
    "gn:feature_class":"P",
    "gn:feature_code":"PPL",
    "gn:name":"Panganta",
    "gn:population":0,
    "gn:timezone":"Asia/Manila",
    "iso:country":"PH",
    "name:fil_x_preferred":[
        "Panganta"
    ],
    "wof:name":"Panganta",
    "wof:placetype":"locality"
},
  "geometry": {"coordinates":[122.06690999999999,11.4601],"type":"Point"}
}