{
  "type": "Feature",
  "properties": {
    "gn:admin1_code":"08",
    "gn:admin2_code":"37",
    "gn:admin3_code":"83724000.0",
    "gn:asciiname":"Pinocawan",
    "gn:country_code":"PH",
    "gn:dem":18,
    "gn:feature_class":"P",
    "gn:feature_code":"PPL",
    "gn:name":"Pinocawan",
    "gn:population":0,
    "gn:timezone":"Asia/Manila",
    "iso:country":"PH",
    "name:fil_x_preferred":[
        "Pinocawan"
    ],
    "wof:name":"Pinocawan",
    "wof:placetype":"locality"
},
  "geometry": {"coordinates":[124.95350000000001,10.8048],"type":"Point"}
}