{
  "type": "Feature",
  "properties": {
    "gn:country":"PH",
    "gn:fcode":"PPL",
    "gn:population":3699,
    "iso:country":"PH",
    "name:fil_x_preferred":[
        "Banog Sur"
    ],
    "name:und_x_variant":[
        "Banog"
    ],
    "qs_pg:aaroncc":"PH",
    "qs_pg:gn_country":"PH",
    "qs_pg:gn_fcode":"PPL",
    "qs_pg:gn_pop":3699,
    "qs_pg:name":"Banog Sur",
    "qs_pg:photos_9r":0,
    "qs_pg:photos_sr":0,
    "qs_pg:pop_sr":4,
    "qs_pg:qs_pg_placetype":"locality",
    "wof:name":"Banog Sur",
    "wof:placetype":"locality",
    "wof:population":3699
},
  "geometry": {"coordinates":[119.89409999999999,16.1672],"type":"Point"}
}