{
  "type": "Feature",
  "properties": {
    "gn:admin1_code":"12",
    "gn:admin2_code":"71",
    "gn:asciiname":"Akot",
    "gn:country_code":"PH",
    "gn:dem":4,
    "gn:feature_class":"P",
    "gn:feature_code":"PPL",
    "gn:name":"Akot",
    "gn:population":0,
    "gn:timezone":"Asia/Manila",
    "iso:country":"PH",
    "name:und_x_variant":[
        "Akol"
    ],
    "wof:name":"Akot",
    "wof:placetype":"locality"
},
  "geometry": {"coordinates":[124.16916999999999,6.265],"type":"Point"}
}