{
  "type": "Feature",
  "properties": {
    "gn:admin1_code":"12",
    "gn:admin2_code":"71",
    "gn:asciiname":"Akot",
    "gn:country_code":"PH",
    "gn:dem":4,
    "gn:feature_class":"P",
    "gn:feature_code":"PPL",
    "gn:name":"Akot",
    "gn:population":0,
    "gn:timezone":"Asia/Manila",
    "iso:country":"PH",
    "name:ben_x_preferred":[
        "\u0985\u0995\u09cb\u099f"
    ],
    "name:bpy_x_preferred":[
        "\u0985\u0995\u09cb\u099f"
    ],
    "name:cat_x_preferred":[
        "Akot"
    ],
    "name:ceb_x_preferred":[
        "Akot"
    ],
    "name:ces_x_preferred":[
        "Akot"
    ],
    "name:fas_x_preferred":[
        "\u0627\u06a9\u0627\u062a"
    ],
    "name:hif_x_preferred":[
        "Akot"
    ],
    "name:hin_x_preferred":[
        "\u0905\u0915\u094b\u091f"
    ],
    "name:ita_x_preferred":[
        "Akot"
    ],
    "name:mar_x_preferred":[
        "\u0905\u0915\u094b\u091f"
    ],
    "name:min_x_preferred":[
        "Akot"
    ],
    "name:msa_x_preferred":[
        "Akot"
    ],
    "name:new_x_preferred":[
        "\u0905\u0915\u094b\u0924"
    ],
    "name:nld_x_preferred":[
        "Akot"
    ],
    "name:ori_x_preferred":[
        "\u0b06\u0b15\u0b4b\u0b1f"
    ],
    "name:por_x_preferred":[
        "Akot"
    ],
    "name:swe_x_preferred":[
        "Akot"
    ],
    "name:und_x_variant":[
        "Akol"
    ],
    "name:urd_x_preferred":[
        "\u0622\u06a9\u0648\u0679"
    ],
    "name:vie_x_preferred":[
        "Akot"
    ],
    "name:zho_x_preferred":[
        "\u963f\u79d1\u7279"
    ],
    "wof:name":"Akot",
    "wof:placetype":"locality"
},
  "geometry": {"coordinates":[124.16916999999999,6.265],"type":"Point"}
}