{
  "type": "Feature",
  "properties": {
    "gn:admin1_code":"15",
    "gn:admin2_code":"44",
    "gn:admin3_code":"144406000.0",
    "gn:asciiname":"Walawal",
    "gn:country_code":"PH",
    "gn:dem":169,
    "gn:feature_class":"P",
    "gn:feature_code":"PPL",
    "gn:name":"Walawal",
    "gn:population":0,
    "gn:timezone":"Asia/Manila",
    "iso:country":"PH",
    "name:fil_x_preferred":[
        "Walawal"
    ],
    "wof:name":"Walawal",
    "wof:placetype":"locality"
},
  "geometry": {"coordinates":[121.4943,17.2513],"type":"Point"}
}