{
  "type": "Feature",
  "properties": {
    "gn:country":"PH",
    "gn:fcode":"ADM3",
    "gn:pop":23849,
    "iso:country":"PH",
    "name:fil_x_preferred":[
        "Altavas"
    ],
    "qs:name":"Altavas",
    "qs:photos_9r":0,
    "qs:photos_sr":0,
    "qs:pop_sr":"7",
    "wof:name":"Altavas",
    "wof:placetype":"localadmin",
    "wof:population":23849
},
  "geometry": {"coordinates":[122.46666999999999,11.51667],"type":"Point"}
}