{
  "type": "Feature",
  "properties": {
    "gn:admin1_code":"14",
    "gn:admin2_code":"56",
    "gn:admin3_code":"153812000.0",
    "gn:asciiname":"Darapanan",
    "gn:country_code":"PH",
    "gn:dem":29,
    "gn:feature_class":"P",
    "gn:feature_code":"PPL",
    "gn:name":"Darapanan",
    "gn:population":0,
    "gn:timezone":"Asia/Manila",
    "iso:country":"PH",
    "name:fil_x_preferred":[
        "Darapanan"
    ],
    "wof:name":"Darapanan",
    "wof:placetype":"locality"
},
  "geometry": {"coordinates":[124.30861000000002,7.2825],"type":"Point"}
}