{
  "type": "Feature",
  "properties": {
    "gn:admin1_code":"07",
    "gn:admin2_code":"11",
    "gn:admin3_code":"71239000.0",
    "gn:asciiname":"Cabangcalan",
    "gn:country_code":"PH",
    "gn:dem":130,
    "gn:feature_class":"P",
    "gn:feature_code":"PPL",
    "gn:name":"Cabangcalan",
    "gn:population":0,
    "gn:timezone":"Asia/Manila",
    "iso:country":"PH",
    "name:fil_x_preferred":[
        "Cabangcalan"
    ],
    "name:und_x_variant":[
        "Kabankalan",
        "Cabancalan"
    ],
    "wof:name":"Cabangcalan",
    "wof:placetype":"locality"
},
  "geometry": {"coordinates":[124.0578,9.7093],"type":"Point"}
}