{
  "type": "Feature",
  "properties": {
    "gn:admin1_code":"03",
    "gn:admin2_code":"63",
    "gn:admin3_code":"36905000.0",
    "gn:asciiname":"Minane",
    "gn:country_code":"PH",
    "gn:dem":40,
    "gn:feature_class":"P",
    "gn:feature_code":"PPL",
    "gn:name":"Minane",
    "gn:population":0,
    "gn:timezone":"Asia/Manila",
    "iso:country":"PH",
    "name:fil_x_preferred":[
        "Minane"
    ],
    "wof:name":"Minane",
    "wof:placetype":"locality"
},
  "geometry": {"coordinates":[120.64163000000001,15.31426],"type":"Point"}
}