{
  "type": "Feature",
  "properties": {
    "gn:admin1_code":"07",
    "gn:admin2_code":"11",
    "gn:admin3_code":"71223000.0",
    "gn:asciiname":"Cansiwang",
    "gn:country_code":"PH",
    "gn:dem":105,
    "gn:feature_class":"P",
    "gn:feature_code":"PPL",
    "gn:name":"Cansiwang",
    "gn:population":0,
    "gn:timezone":"Asia/Manila",
    "iso:country":"PH",
    "name:fil_x_preferred":[
        "Cansiwang"
    ],
    "name:und_x_variant":[
        "Kansiwang",
        "Cansimang"
    ],
    "wof:name":"Cansiwang",
    "wof:placetype":"locality"
},
  "geometry": {"coordinates":[124.43859999999999,9.7479],"type":"Point"}
}