{
  "type": "Feature",
  "properties": {
    "gn:admin1_code":"01",
    "gn:admin2_code":"36",
    "gn:admin3_code":"13318000.0",
    "gn:asciiname":"Pagleddegan",
    "gn:country_code":"PH",
    "gn:dem":54,
    "gn:feature_class":"P",
    "gn:feature_code":"PPL",
    "gn:name":"Pagleddegan",
    "gn:population":0,
    "gn:timezone":"Asia/Manila",
    "iso:country":"PH",
    "name:fil_x_preferred":[
        "Pagleddegan"
    ],
    "wof:name":"Pagleddegan",
    "wof:placetype":"locality"
},
  "geometry": {"coordinates":[120.4542,16.7998],"type":"Point"}
}