{
  "type": "Feature",
  "properties": {
    "gn:admin1_code":"07",
    "gn:admin2_code":"46",
    "gn:admin3_code":"74610000.0",
    "gn:asciiname":"Catil-i",
    "gn:country_code":"PH",
    "gn:dem":58,
    "gn:feature_class":"P",
    "gn:feature_code":"PPL",
    "gn:name":"Catil-i",
    "gn:population":0,
    "gn:timezone":"Asia/Manila",
    "iso:country":"PH",
    "name:fil_x_preferred":[
        "Catil-i"
    ],
    "name:fil_x_variant":[
        "Cantil-i"
    ],
    "wof:name":"Catil-i",
    "wof:placetype":"locality"
},
  "geometry": {"coordinates":[123.2775,9.2856],"type":"Point"}
}