{
  "type": "Feature",
  "properties": {
    "gn:admin1_code":"07",
    "gn:admin2_code":"11",
    "gn:admin3_code":"71221000.0",
    "gn:asciiname":"Alejawan",
    "gn:country_code":"PH",
    "gn:dem":6,
    "gn:feature_class":"P",
    "gn:feature_code":"PPL",
    "gn:name":"Alejawan",
    "gn:population":0,
    "gn:timezone":"Asia/Manila",
    "iso:country":"PH",
    "name:fil_x_preferred":[
        "Alejawan"
    ],
    "name:und_x_variant":[
        "Alijawan",
        "Alihawan",
        "Alijauan"
    ],
    "wof:name":"Alejawan",
    "wof:placetype":"locality"
},
  "geometry": {"coordinates":[124.40089999999999,9.6826],"type":"Point"}
}