{
  "type": "Feature",
  "properties": {
    "gn:country":"PH",
    "gn:fcode":"PPL",
    "gn:pop":4000,
    "iso:country":"PH",
    "name:fil_x_preferred":[
        "Santa Teresa"
    ],
    "qs:name":"Santa Teresa",
    "qs:photos_9r":0,
    "qs:photos_sr":0,
    "qs:pop_sr":"4",
    "wd:wordcount":166,
    "wof:name":"Santa Teresa",
    "wof:placetype":"locality",
    "wof:population":4000
},
  "geometry": {"coordinates":[122.5604,10.58546],"type":"Point"}
}