{
  "type": "Feature",
  "properties": {
    "gn:country":"PH",
    "gn:fcode":"PPL",
    "gn:population":4000,
    "iso:country":"PH",
    "name:bpy_x_preferred":[
        "\u09b8\u09be\u09a8\u09cd\u099f\u09be \u099f\u09c7\u09b0\u09c7\u09b8\u09be"
    ],
    "name:cat_x_preferred":[
        "Santa Teresa"
    ],
    "name:ceb_x_preferred":[
        "Santa Teresa"
    ],
    "name:deu_x_preferred":[
        "Santa Teresa"
    ],
    "name:eus_x_preferred":[
        "Santa Teresa"
    ],
    "name:fil_x_preferred":[
        "Santa Teresa"
    ],
    "name:fra_x_preferred":[
        "Santa Teresa"
    ],
    "name:ita_x_preferred":[
        "Santa Teresa"
    ],
    "name:nds_x_preferred":[
        "Santa Teresa"
    ],
    "name:nld_x_preferred":[
        "Santa Teresa"
    ],
    "name:nor_x_preferred":[
        "Santa Teresa"
    ],
    "name:pms_x_preferred":[
        "Santa Teresa"
    ],
    "name:pol_x_preferred":[
        "Santa Teresa"
    ],
    "name:por_x_preferred":[
        "Santa Teresa"
    ],
    "name:rus_x_preferred":[
        "\u0421\u0430\u043d\u0442\u0430-\u0422\u0435\u0440\u0435\u0437\u0430"
    ],
    "name:spa_x_preferred":[
        "Santa Teresa"
    ],
    "name:srp_x_preferred":[
        "Santa Teresa"
    ],
    "name:swe_x_preferred":[
        "Santa Teresa"
    ],
    "name:vie_x_preferred":[
        "Santa Teresa"
    ],
    "name:vol_x_preferred":[
        "Santa Teresa"
    ],
    "qs:name":"Santa Teresa",
    "qs:photos_9r":0,
    "qs:photos_sr":0,
    "qs:pop_sr":"4",
    "wd:wordcount":166,
    "wof:name":"Santa Teresa",
    "wof:placetype":"locality",
    "wof:population":4000
},
  "geometry": {"coordinates":[122.5604,10.58546],"type":"Point"}
}