{
  "type": "Feature",
  "properties": {
    "gn:admin1_code":"07",
    "gn:admin2_code":"21",
    "gn:admin3_code":"72203000.0",
    "gn:asciiname":"Tiguib",
    "gn:country_code":"PH",
    "gn:dem":593,
    "gn:feature_class":"P",
    "gn:feature_code":"PPL",
    "gn:name":"Tiguib",
    "gn:population":0,
    "gn:timezone":"Asia/Manila",
    "iso:country":"PH",
    "name:fil_x_preferred":[
        "Tiguib"
    ],
    "wof:name":"Tiguib",
    "wof:placetype":"locality"
},
  "geometry": {"coordinates":[123.3998,9.743],"type":"Point"}
}