{
  "type": "Feature",
  "properties": {
    "gn:country":"PH",
    "gn:fcode":"PPL",
    "gn:pop":2137,
    "iso:country":"PH",
    "name:fil_x_preferred":[
        "Kalandagan"
    ],
    "qs:name":"Kalandagan",
    "qs:photos_9r":0,
    "qs:photos_sr":0,
    "qs:pop_sr":"4",
    "wof:name":"Kalandagan",
    "wof:placetype":"locality",
    "wof:population":2137
},
  "geometry": {"coordinates":[124.72333,6.67861],"type":"Point"}
}