{
  "type": "Feature",
  "properties": {
    "gn:admin1_code":"02",
    "gn:admin2_code":"31",
    "gn:admin3_code":"23134000.0",
    "gn:asciiname":"Mozzozzin North",
    "gn:country_code":"PH",
    "gn:dem":40,
    "gn:feature_class":"P",
    "gn:feature_code":"PPL",
    "gn:name":"Mozzozzin North",
    "gn:population":0,
    "gn:timezone":"Asia/Manila",
    "iso:country":"PH",
    "name:und_x_variant":[
        "Mozzozzin Norte"
    ],
    "wof:name":"Mozzozzin North",
    "wof:placetype":"locality"
},
  "geometry": {"coordinates":[121.74612,17.45819],"type":"Point"}
}