{
  "type": "Feature",
  "properties": {
    "gn:admin1_code":"07",
    "gn:admin2_code":"11",
    "gn:admin3_code":"71209000.0",
    "gn:asciiname":"Sanga",
    "gn:country_code":"PH",
    "gn:dem":68,
    "gn:feature_class":"P",
    "gn:feature_code":"PPL",
    "gn:name":"Sanga",
    "gn:population":0,
    "gn:timezone":"Asia/Manila",
    "iso:country":"PH",
    "name:ceb_x_preferred":[
        "Sanga"
    ],
    "name:deu_x_preferred":[
        "Sanga"
    ],
    "name:fil_x_preferred":[
        "Sanga"
    ],
    "name:fra_x_preferred":[
        "Sanga"
    ],
    "name:ita_x_preferred":[
        "Sanga"
    ],
    "name:por_x_preferred":[
        "Sanga"
    ],
    "name:swe_x_preferred":[
        "Sanga"
    ],
    "wof:name":"Sanga",
    "wof:placetype":"locality"
},
  "geometry": {"coordinates":[124.15000000000001,10.03333],"type":"Point"}
}