{
  "type": "Feature",
  "properties": {
    "gn:admin1_code":"01",
    "gn:admin2_code":"51",
    "gn:admin3_code":"15501000.0",
    "gn:asciiname":"Cacayasen",
    "gn:country_code":"PH",
    "gn:dem":8,
    "gn:feature_class":"P",
    "gn:feature_code":"PPL",
    "gn:name":"Cacayasen",
    "gn:population":0,
    "gn:timezone":"Asia/Manila",
    "iso:country":"PH",
    "name:fil_x_preferred":[
        "Cacayasen"
    ],
    "wof:name":"Cacayasen",
    "wof:placetype":"locality"
},
  "geometry": {"coordinates":[119.84010000000001,16.0814],"type":"Point"}
}