{
  "type": "Feature",
  "properties": {
    "gn:admin1_code":"08",
    "gn:admin2_code":"67",
    "gn:admin3_code":"84801000.0",
    "gn:asciiname":"Lagund",
    "gn:country_code":"PH",
    "gn:dem":5,
    "gn:feature_class":"P",
    "gn:feature_code":"PPL",
    "gn:name":"Lagund",
    "gn:population":0,
    "gn:timezone":"Asia/Manila",
    "iso:country":"PH",
    "name:fil_x_preferred":[
        "Lagund"
    ],
    "name:und_x_variant":[
        "Lagundi",
        "Lagund"
    ],
    "wof:name":"Lagund",
    "wof:placetype":"locality"
},
  "geometry": {"coordinates":[124.2837,12.51],"type":"Point"}
}