{
  "type": "Feature",
  "properties": {
    "gn:admin1_code":"41",
    "gn:admin2_code":"54",
    "gn:admin3_code":"175915000.0",
    "gn:asciiname":"Tabugon",
    "gn:country_code":"PH",
    "gn:dem":24,
    "gn:feature_class":"P",
    "gn:feature_code":"PPL",
    "gn:name":"Tabugon",
    "gn:population":0,
    "gn:timezone":"Asia/Manila",
    "iso:country":"PH",
    "name:fil_x_preferred":[
        "Tabugon"
    ],
    "wof:name":"Tabugon",
    "wof:placetype":"locality"
},
  "geometry": {"coordinates":[122.01691,12.12916],"type":"Point"}
}