{
  "type": "Feature",
  "properties": {
    "gn:admin1_code":"01",
    "gn:admin2_code":"29",
    "gn:admin3_code":"12926000.0",
    "gn:asciiname":"Nueva Coveta",
    "gn:country_code":"PH",
    "gn:dem":77,
    "gn:feature_class":"P",
    "gn:feature_code":"PPL",
    "gn:name":"Nueva Coveta",
    "gn:population":0,
    "gn:timezone":"Asia/Manila",
    "iso:country":"PH",
    "name:fil_x_preferred":[
        "Nueva Coveta"
    ],
    "wof:name":"Nueva Coveta",
    "wof:placetype":"locality"
},
  "geometry": {"coordinates":[120.48333,17.33333],"type":"Point"}
}