{
  "type": "Feature",
  "properties": {
    "gn:admin1_code":"02",
    "gn:admin2_code":"14",
    "gn:admin3_code":"21504000.0",
    "gn:asciiname":"Annafatan",
    "gn:country_code":"PH",
    "gn:dem":18,
    "gn:feature_class":"P",
    "gn:feature_code":"PPL",
    "gn:name":"Annafatan",
    "gn:population":0,
    "gn:timezone":"Asia/Manila",
    "iso:country":"PH",
    "name:fil_x_preferred":[
        "Annafatan"
    ],
    "wof:name":"Annafatan",
    "wof:placetype":"locality"
},
  "geometry": {"coordinates":[121.66271999999999,17.8021],"type":"Point"}
}