{
  "type": "Feature",
  "properties": {
    "gn:admin1_code":"08",
    "gn:admin2_code":"67",
    "gn:admin3_code":"84822000.0",
    "gn:asciiname":"Camayaan",
    "gn:country_code":"PH",
    "gn:dem":40,
    "gn:feature_class":"P",
    "gn:feature_code":"PPL",
    "gn:name":"Camayaan",
    "gn:population":0,
    "gn:timezone":"Asia/Manila",
    "iso:country":"PH",
    "name:fil_x_preferred":[
        "Camayaan"
    ],
    "wof:name":"Camayaan",
    "wof:placetype":"locality"
},
  "geometry": {"coordinates":[124.83580000000001,12.2799],"type":"Point"}
}