{
  "type": "Feature",
  "properties": {
    "gn:admin1_code":"05",
    "gn:admin2_code":"39",
    "gn:admin3_code":"54107000.0",
    "gn:asciiname":"Macamote",
    "gn:country_code":"PH",
    "gn:dem":162,
    "gn:feature_class":"P",
    "gn:feature_code":"PPL",
    "gn:name":"Macamote",
    "gn:population":0,
    "gn:timezone":"Asia/Manila",
    "iso:country":"PH",
    "name:fil_x_preferred":[
        "Macamote"
    ],
    "wof:name":"Macamote",
    "wof:placetype":"locality"
},
  "geometry": {"coordinates":[123.3246,12.7612],"type":"Point"}
}