{
  "type": "Feature",
  "properties": {
    "gn:admin1_code":"41",
    "gn:admin2_code":"49",
    "gn:admin3_code":"175316000.0",
    "gn:asciiname":"Malamig",
    "gn:cc2":"PH",
    "gn:country_code":"PH",
    "gn:dem":14,
    "gn:feature_class":"P",
    "gn:feature_code":"PPL",
    "gn:name":"Malamig",
    "gn:population":0,
    "gn:timezone":"Asia/Manila",
    "iso:country":"PH",
    "name:und_x_variant":[
        "Sigota"
    ],
    "wof:name":"Malamig",
    "wof:placetype":"locality"
},
  "geometry": {"coordinates":[118.6725,9.76917],"type":"Point"}
}