{
  "type": "Feature",
  "properties": {
    "gn:country":"PH",
    "gn:fcode":"PPL",
    "gn:population":3920,
    "iso:country":"PH",
    "name:ara_x_preferred":[
        "\u0646\u0627\u0644\u0648\u0633"
    ],
    "name:aze_x_preferred":[
        "Nalus"
    ],
    "name:ceb_x_preferred":[
        "N\u0101l\u016bs"
    ],
    "name:ckb_x_preferred":[
        "\u0646\u06d5\u06b5\u06c6\u0633"
    ],
    "name:fas_x_preferred":[
        "\u0646\u0627\u0644\u0648\u0633"
    ],
    "name:fil_x_preferred":[
        "Nalus"
    ],
    "name:kur_x_preferred":[
        "Nellos"
    ],
    "name:mlg_x_preferred":[
        "Nalus"
    ],
    "name:msa_x_preferred":[
        "Nalus"
    ],
    "name:swe_x_preferred":[
        "N\u0101l\u016bs"
    ],
    "name:tur_x_preferred":[
        "Nalus"
    ],
    "name:urd_x_preferred":[
        "\u0646\u0627\u0644\u0648\u0633"
    ],
    "qs_pg:aaroncc":"PH",
    "qs_pg:gn_country":"PH",
    "qs_pg:gn_fcode":"PPL",
    "qs_pg:gn_pop":3920,
    "qs_pg:name":"Nalus",
    "qs_pg:photos_9r":0,
    "qs_pg:photos_sr":0,
    "qs_pg:pop_sr":4,
    "qs_pg:qs_pg_placetype":"locality",
    "wof:name":"Nalus",
    "wof:placetype":"locality",
    "wof:population":3920
},
  "geometry": {"coordinates":[124.58528,6.01222],"type":"Point"}
}