{
  "type": "Feature",
  "properties": {
    "gn:admin1_code":"07",
    "gn:admin2_code":"21",
    "gn:admin3_code":"72236000.0",
    "gn:asciiname":"Dapdap",
    "gn:country_code":"PH",
    "gn:dem":11,
    "gn:feature_class":"P",
    "gn:feature_code":"PPL",
    "gn:name":"Dapdap",
    "gn:population":0,
    "gn:timezone":"Asia/Manila",
    "iso:country":"PH",
    "name:fil_x_preferred":[
        "Dapdap"
    ],
    "name:und_x_variant":[
        "Dapdad"
    ],
    "wof:name":"Dapdap",
    "wof:placetype":"locality"
},
  "geometry": {"coordinates":[124.52419999999999,10.7851],"type":"Point"}
}