{
  "type": "Feature",
  "properties": {
    "gn:admin1_code":"15",
    "gn:admin2_code":"H6",
    "gn:admin3_code":"148106000.0",
    "gn:asciiname":"Pagatanan",
    "gn:country_code":"PH",
    "gn:dem":90,
    "gn:feature_class":"P",
    "gn:feature_code":"PPL",
    "gn:name":"Pagatanan",
    "gn:population":0,
    "gn:timezone":"Asia/Manila",
    "iso:country":"PH",
    "name:fil_x_preferred":[
        "Pagatanan"
    ],
    "wof:name":"Pagatanan",
    "wof:placetype":"locality"
},
  "geometry": {"coordinates":[121.3424,18.1835],"type":"Point"}
}