{
  "type": "Feature",
  "properties": {
    "gn:country":"PH",
    "gn:fcode":"PPL",
    "gn:population":4275,
    "iso:country":"PH",
    "name:fil_x_preferred":[
        "Maligaya"
    ],
    "qs:name":"Maligaya",
    "qs:photos_9r":0,
    "qs:photos_sr":0,
    "qs:pop_sr":"4",
    "wof:name":"Maligaya",
    "wof:placetype":"locality",
    "wof:population":4275
},
  "geometry": {"coordinates":[120.8887,15.6747],"type":"Point"}
}