{
  "type": "Feature",
  "properties": {
    "gn:admin1_code":"06",
    "gn:admin2_code":"30",
    "gn:admin3_code":"63013000.0",
    "gn:asciiname":"Bado",
    "gn:country_code":"PH",
    "gn:dem":111,
    "gn:feature_class":"P",
    "gn:feature_code":"PPL",
    "gn:name":"Bado",
    "gn:population":0,
    "gn:timezone":"Asia/Manila",
    "iso:country":"PH",
    "name:ceb_x_preferred":[
        "Bado"
    ],
    "name:deu_x_preferred":[
        "Bado"
    ],
    "name:fil_x_preferred":[
        "Bado"
    ],
    "name:swe_x_preferred":[
        "Bado"
    ],
    "wof:name":"Bado",
    "wof:placetype":"locality"
},
  "geometry": {"coordinates":[122.46890999999999,11.13512],"type":"Point"}
}