{
  "type": "Feature",
  "properties": {
    "gn:admin1_code":"02",
    "gn:admin2_code":"31",
    "gn:admin3_code":"23120000.0",
    "gn:asciiname":"Luna",
    "gn:country_code":"PH",
    "gn:dem":39,
    "gn:feature_class":"P",
    "gn:feature_code":"PPL",
    "gn:name":"Luna",
    "gn:population":0,
    "gn:timezone":"Asia/Manila",
    "iso:country":"PH",
    "name:fil_x_preferred":[
        "Luna"
    ],
    "wof:name":"Luna",
    "wof:placetype":"locality"
},
  "geometry": {"coordinates":[121.83333,17.03333],"type":"Point"}
}