{
  "type": "Feature",
  "properties": {
    "gn:admin1_code":"06",
    "gn:admin2_code":"18",
    "gn:admin3_code":"61906000.0",
    "gn:asciiname":"Catmon",
    "gn:country_code":"PH",
    "gn:dem":94,
    "gn:feature_class":"P",
    "gn:feature_code":"PPL",
    "gn:name":"Catmon",
    "gn:population":0,
    "gn:timezone":"Asia/Manila",
    "iso:country":"PH",
    "name:fil_x_preferred":[
        "Catmon"
    ],
    "wof:name":"Catmon",
    "wof:placetype":"locality"
},
  "geometry": {"coordinates":[122.5201,11.4809],"type":"Point"}
}