{
  "type": "Feature",
  "properties": {
    "gn:admin1_code":"07",
    "gn:admin2_code":"11",
    "gn:admin3_code":"71221000.0",
    "gn:asciiname":"Itum",
    "gn:country_code":"PH",
    "gn:dem":7,
    "gn:feature_class":"P",
    "gn:feature_code":"PPL",
    "gn:name":"Itum",
    "gn:population":0,
    "gn:timezone":"Asia/Manila",
    "iso:country":"PH",
    "name:fil_x_preferred":[
        "Itum"
    ],
    "name:und_x_variant":[
        "Ytum"
    ],
    "wof:name":"Itum",
    "wof:placetype":"locality"
},
  "geometry": {"coordinates":[124.4131,9.7145],"type":"Point"}
}