{
  "type": "Feature",
  "properties": {
    "gn:admin1_code":"12",
    "gn:admin2_code":"57",
    "gn:admin3_code":"124711000.0",
    "gn:asciiname":"Kimarayao",
    "gn:country_code":"PH",
    "gn:dem":56,
    "gn:feature_class":"P",
    "gn:feature_code":"PPL",
    "gn:name":"Kimarayao",
    "gn:population":0,
    "gn:timezone":"Asia/Manila",
    "iso:country":"PH",
    "name:fil_x_preferred":[
        "Kimarayao"
    ],
    "wof:name":"Kimarayao",
    "wof:placetype":"locality"
},
  "geometry": {"coordinates":[124.47360999999999,7.30667],"type":"Point"}
}