{
  "type": "Feature",
  "properties": {
    "gn:admin1_code":"15",
    "gn:admin2_code":"10",
    "gn:admin3_code":"141109000.0",
    "gn:asciiname":"Lobo",
    "gn:country_code":"PH",
    "gn:dem":1910,
    "gn:feature_class":"P",
    "gn:feature_code":"PPL",
    "gn:name":"Lobo",
    "gn:population":0,
    "gn:timezone":"Asia/Manila",
    "iso:country":"PH",
    "name:fil_x_preferred":[
        "Lobo"
    ],
    "wof:name":"Lobo",
    "wof:placetype":"locality"
},
  "geometry": {"coordinates":[120.6825,16.7814],"type":"Point"}
}