{
  "type": "Feature",
  "properties": {
    "gn:country":"PH",
    "gn:fcode":"PPL",
    "gn:population":3380,
    "iso:country":"PH",
    "name:und_x_variant":[
        "Adtuyon"
    ],
    "qs:name":"Adtugan",
    "qs:photos_9r":0,
    "qs:photos_sr":0,
    "qs:pop_sr":"4",
    "wof:name":"Adtugan",
    "wof:placetype":"locality",
    "wof:population":3380
},
  "geometry": {"coordinates":[124.85444,7.81194],"type":"Point"}
}