{
  "type": "Feature",
  "properties": {
    "gn:admin1_code":"08",
    "gn:admin2_code":"55",
    "gn:admin3_code":"86009000.0",
    "gn:asciiname":"Camoroboan",
    "gn:country_code":"PH",
    "gn:dem":13,
    "gn:feature_class":"P",
    "gn:feature_code":"PPL",
    "gn:name":"Camoroboan",
    "gn:population":0,
    "gn:timezone":"Asia/Manila",
    "iso:country":"PH",
    "name:fil_x_preferred":[
        "Camoroboan"
    ],
    "wof:name":"Camoroboan",
    "wof:placetype":"locality"
},
  "geometry": {"coordinates":[124.97389,11.81167],"type":"Point"}
}