{
  "type": "Feature",
  "properties": {
    "gn:admin1_code":"40",
    "gn:admin2_code":"33",
    "gn:admin3_code":"43415000.0",
    "gn:asciiname":"Burlungan",
    "gn:country_code":"PH",
    "gn:dem":120,
    "gn:feature_class":"P",
    "gn:feature_code":"PPL",
    "gn:name":"Burlungan",
    "gn:population":0,
    "gn:timezone":"Asia/Manila",
    "iso:country":"PH",
    "name:fil_x_preferred":[
        "Burlungan"
    ],
    "wof:name":"Burlungan",
    "wof:placetype":"locality"
},
  "geometry": {"coordinates":[121.4289,14.1844],"type":"Point"}
}