{
  "type": "Feature",
  "properties": {
    "gn:admin1_code":"07",
    "gn:admin2_code":"21",
    "gn:admin3_code":"72252000.0",
    "gn:asciiname":"Gimamaa",
    "gn:country_code":"PH",
    "gn:dem":277,
    "gn:feature_class":"P",
    "gn:feature_code":"PPL",
    "gn:name":"Gimamaa",
    "gn:population":0,
    "gn:timezone":"Asia/Manila",
    "iso:country":"PH",
    "name:fil_x_preferred":[
        "Gimamaa"
    ],
    "name:und_x_variant":[
        "Guimamaa"
    ],
    "wof:name":"Gimamaa",
    "wof:placetype":"locality"
},
  "geometry": {"coordinates":[123.8865,10.6985],"type":"Point"}
}