{
  "type": "Feature",
  "properties": {
    "gn:admin1_code":"40",
    "gn:admin2_code":"20",
    "gn:admin3_code":"42119000.0",
    "gn:asciiname":"Galicias",
    "gn:country_code":"PH",
    "gn:dem":337,
    "gn:feature_class":"P",
    "gn:feature_code":"PPL",
    "gn:name":"Galicias",
    "gn:population":0,
    "gn:timezone":"Asia/Manila",
    "iso:country":"PH",
    "name:fil_x_preferred":[
        "Galicias"
    ],
    "name:und_x_variant":[
        "Galicia"
    ],
    "wof:name":"Galicias",
    "wof:placetype":"locality"
},
  "geometry": {"coordinates":[120.90269000000001,14.08155],"type":"Point"}
}