{
  "type": "Feature",
  "properties": {
    "gn:admin1_code":"06",
    "gn:admin2_code":"04",
    "gn:admin3_code":"60402000.0",
    "gn:asciiname":"Aranas East",
    "gn:country_code":"PH",
    "gn:dem":14,
    "gn:feature_class":"P",
    "gn:feature_code":"PPL",
    "gn:name":"Aranas East",
    "gn:population":0,
    "gn:timezone":"Asia/Manila",
    "iso:country":"PH",
    "name:eng_x_preferred":[
        "Aranas East"
    ],
    "wof:name":"Aranas East",
    "wof:placetype":"locality"
},
  "geometry": {"coordinates":[122.4121,11.57],"type":"Point"}
}