{
  "type": "Feature",
  "properties": {
    "gn:admin1_code":"15",
    "gn:admin2_code":"10",
    "gn:admin3_code":"141102000.0",
    "gn:asciiname":"Camp John Hay",
    "gn:country_code":"PH",
    "gn:dem":1515,
    "gn:feature_class":"P",
    "gn:feature_code":"PPL",
    "gn:name":"Camp John Hay",
    "gn:population":0,
    "gn:timezone":"Asia/Manila",
    "iso:country":"PH",
    "name:fil_x_preferred":[
        "Camp John Hay"
    ],
    "wof:name":"Camp John Hay",
    "wof:placetype":"locality"
},
  "geometry": {"coordinates":[120.61626,16.3973],"type":"Point"}
}