{
  "type": "Feature",
  "properties": {
    "gn:admin1_code":"40",
    "gn:admin2_code":"H2",
    "gn:admin3_code":"45630000.0",
    "gn:asciiname":"Viena",
    "gn:country_code":"PH",
    "gn:dem":60,
    "gn:feature_class":"P",
    "gn:feature_code":"PPL",
    "gn:name":"Viena",
    "gn:population":0,
    "gn:timezone":"Asia/Manila",
    "iso:country":"PH",
    "name:fil_x_preferred":[
        "Viena"
    ],
    "wof:name":"Viena",
    "wof:placetype":"locality"
},
  "geometry": {"coordinates":[121.68333,13.98333],"type":"Point"}
}