{
  "type": "Feature",
  "properties": {
    "gn:admin1_code":"09",
    "gn:admin2_code":"66",
    "gn:admin3_code":"97322000.0",
    "gn:asciiname":"Marum",
    "gn:country_code":"PH",
    "gn:dem":5,
    "gn:feature_class":"P",
    "gn:feature_code":"PPL",
    "gn:name":"Marum",
    "gn:population":0,
    "gn:timezone":"Asia/Manila",
    "iso:country":"PH",
    "name:eng_x_preferred":[
        "Marum"
    ],
    "wof:name":"Marum",
    "wof:placetype":"locality"
},
  "geometry": {"coordinates":[123.46420000000001,7.8286],"type":"Point"}
}