{
  "type": "Feature",
  "properties": {
    "gn:admin1_code":"09",
    "gn:admin2_code":"66",
    "gn:admin3_code":"97322000.0",
    "gn:asciiname":"Marum",
    "gn:country_code":"PH",
    "gn:dem":5,
    "gn:feature_class":"P",
    "gn:feature_code":"PPL",
    "gn:name":"Marum",
    "gn:population":0,
    "gn:timezone":"Asia/Manila",
    "iso:country":"PH",
    "name:afr_x_preferred":[
        "Marum"
    ],
    "name:ara_x_preferred":[
        "\u0645\u0627\u0631\u0648\u0645"
    ],
    "name:bre_x_preferred":[
        "Marum"
    ],
    "name:cat_x_preferred":[
        "Marum"
    ],
    "name:ceb_x_preferred":[
        "Gemeente Marum"
    ],
    "name:deu_x_preferred":[
        "Marum"
    ],
    "name:eng_x_preferred":[
        "Marum"
    ],
    "name:epo_x_preferred":[
        "Marum"
    ],
    "name:eus_x_preferred":[
        "Marum"
    ],
    "name:fas_x_preferred":[
        "\u0645\u0627\u0631\u0648\u0645"
    ],
    "name:fra_x_preferred":[
        "Marum"
    ],
    "name:fry_x_preferred":[
        "Mearum"
    ],
    "name:gle_x_preferred":[
        "Marum"
    ],
    "name:hye_x_preferred":[
        "\u0544\u0561\u0580\u0578\u0582\u0574"
    ],
    "name:ind_x_preferred":[
        "Marum"
    ],
    "name:ita_x_preferred":[
        "Marum"
    ],
    "name:lim_x_preferred":[
        "Marum"
    ],
    "name:min_x_preferred":[
        "Marum"
    ],
    "name:msa_x_preferred":[
        "Marum"
    ],
    "name:nld_x_preferred":[
        "Marum"
    ],
    "name:nor_x_preferred":[
        "Marum"
    ],
    "name:pol_x_preferred":[
        "Marum"
    ],
    "name:ron_x_preferred":[
        "Marum"
    ],
    "name:rus_x_preferred":[
        "\u041c\u0430\u0440\u044e\u043c"
    ],
    "name:spa_x_preferred":[
        "Marum"
    ],
    "name:sqi_x_preferred":[
        "Marum"
    ],
    "name:stq_x_preferred":[
        "Marum"
    ],
    "name:swe_x_preferred":[
        "Marum"
    ],
    "name:tur_x_preferred":[
        "Marum"
    ],
    "name:vie_x_preferred":[
        "Marum"
    ],
    "name:vol_x_preferred":[
        "Marum"
    ],
    "name:war_x_preferred":[
        "Marum"
    ],
    "name:zho_x_preferred":[
        "\u9a6c\u52d2\u59c6"
    ],
    "wof:name":"Marum",
    "wof:placetype":"locality"
},
  "geometry": {"coordinates":[123.46420000000001,7.8286],"type":"Point"}
}