{
  "type": "Feature",
  "properties": {
    "gn:gn_country":"PH",
    "gn:gn_fcode":"PPL",
    "gn:gn_pop":3333,
    "gn:population":3333,
    "iso:country":"PH",
    "name:ceb_x_preferred":[
        "Ipil"
    ],
    "name:deu_x_preferred":[
        "Ipil"
    ],
    "name:fil_x_preferred":[
        "Ipil"
    ],
    "name:tgl_x_preferred":[
        "Ipil"
    ],
    "qs_pg:aaroncc":"PH",
    "qs_pg:gn_country":"PH",
    "qs_pg:gn_fcode":"PPL",
    "qs_pg:gn_pop":3333,
    "qs_pg:name":"Ipil",
    "qs_pg:photos_9r":0,
    "qs_pg:photos_sr":0,
    "qs_pg:pop_sr":4,
    "qs_pg:qs_pg_placetype":"locality",
    "wof:name":"Ipil",
    "wof:placetype":"locality",
    "wof:population":3333
},
  "geometry": {"coordinates":[125.44028,9.7875],"type":"Point"}
}