{
  "type": "Feature",
  "properties": {
    "iso:country":"PH",
    "name:eng_x_preferred":[
        "Maloma"
    ],
    "qs:gn_country":"PH",
    "qs:gn_fcode":"PPL",
    "qs:gn_pop":4430,
    "qs:name":"Maloma",
    "qs:name_adm0":"Philippines",
    "qs:name_adm1":"Central Luzon",
    "qs:photos":0,
    "qs:photos_1k":0,
    "qs:photos_9k":0,
    "qs:photos_9r":0,
    "qs:photos_all":0,
    "qs:photos_sr":0,
    "qs:placetype":"Town",
    "qs:pop_sr":"4",
    "qs:woe_adm0":23424934,
    "wd:wordcount":42,
    "wof:name":"Maloma",
    "wof:placetype":"locality",
    "wof:population":4430
},
  "geometry": {"coordinates":[120.0639,15.1135],"type":"Point"}
}