{
  "type": "Feature",
  "properties": {
    "gn:admin1_code":"14",
    "gn:admin2_code":"72",
    "gn:admin3_code":"157002000.0",
    "gn:asciiname":"Karungdung",
    "gn:cc2":"PH",
    "gn:country_code":"PH",
    "gn:dem":6,
    "gn:feature_class":"P",
    "gn:feature_code":"PPL",
    "gn:name":"Karungdung",
    "gn:population":0,
    "gn:timezone":"Asia/Manila",
    "iso:country":"PH",
    "name:und_x_variant":[
        "Karundung",
        "Karondon",
        "Karungdong",
        "Karungdung"
    ],
    "wof:name":"Karungdung",
    "wof:placetype":"locality"
},
  "geometry": {"coordinates":[119.77028,5.045],"type":"Point"}
}