{
  "type": "Feature",
  "properties": {
    "gn:admin1_code":"40",
    "gn:admin2_code":"09",
    "gn:admin3_code":"41029000.0",
    "gn:asciiname":"Balisong",
    "gn:country_code":"PH",
    "gn:dem":69,
    "gn:feature_class":"P",
    "gn:feature_code":"PPL",
    "gn:name":"Balisong",
    "gn:population":0,
    "gn:timezone":"Asia/Manila",
    "iso:country":"PH",
    "name:fil_x_preferred":[
        "Balisong"
    ],
    "wof:name":"Balisong",
    "wof:placetype":"locality"
},
  "geometry": {"coordinates":[120.93333,13.88333],"type":"Point"}
}