{
  "type": "Feature",
  "properties": {
    "gn:admin1_code":"05",
    "gn:admin2_code":"05",
    "gn:admin3_code":"50514000.0",
    "gn:asciiname":"Magurang",
    "gn:country_code":"PH",
    "gn:dem":32,
    "gn:feature_class":"P",
    "gn:feature_code":"PPL",
    "gn:name":"Magurang",
    "gn:population":0,
    "gn:timezone":"Asia/Manila",
    "iso:country":"PH",
    "name:fil_x_preferred":[
        "Magurang"
    ],
    "wof:name":"Magurang",
    "wof:placetype":"locality"
},
  "geometry": {"coordinates":[123.494,13.2906],"type":"Point"}
}