{
  "type": "Feature",
  "properties": {
    "gn:country":"PH",
    "gn:fcode":"PPL",
    "gn:population":2443,
    "iso:country":"PH",
    "name:und_x_variant":[
        "Palusapis"
    ],
    "qs_pg:aaroncc":"PH",
    "qs_pg:gn_country":"PH",
    "qs_pg:gn_fcode":"PPL",
    "qs_pg:gn_pop":2443,
    "qs_pg:name":"Palusapig",
    "qs_pg:photos_9r":0,
    "qs_pg:photos_sr":0,
    "qs_pg:pop_sr":4,
    "qs_pg:qs_pg_placetype":"locality",
    "wof:name":"Palusapig",
    "wof:placetype":"locality",
    "wof:population":2443
},
  "geometry": {"coordinates":[120.8614,15.6796],"type":"Point"}
}