{
  "type": "Feature",
  "properties": {
    "gn:admin1_code":"08",
    "gn:admin2_code":"37",
    "gn:admin3_code":"83729000.0",
    "gn:asciiname":"Bachao",
    "gn:country_code":"PH",
    "gn:dem":12,
    "gn:feature_class":"P",
    "gn:feature_code":"PPL",
    "gn:name":"Bachao",
    "gn:population":0,
    "gn:timezone":"Asia/Manila",
    "iso:country":"PH",
    "name:fil_x_preferred":[
        "Bachao"
    ],
    "wof:name":"Bachao",
    "wof:placetype":"locality"
},
  "geometry": {"coordinates":[124.4923,11.4459],"type":"Point"}
}