{
  "type": "Feature",
  "properties": {
    "gn:admin1_code":"40",
    "gn:admin2_code":"H2",
    "gn:admin3_code":"45649000.0",
    "gn:asciiname":"Balanakan",
    "gn:country_code":"PH",
    "gn:dem":14,
    "gn:feature_class":"P",
    "gn:feature_code":"PPL",
    "gn:name":"Balanakan",
    "gn:population":0,
    "gn:timezone":"Asia/Manila",
    "iso:country":"PH",
    "name:fil_x_preferred":[
        "Balanakan"
    ],
    "name:fil_x_variant":[
        "Balanacan"
    ],
    "wof:name":"Balanakan",
    "wof:placetype":"locality"
},
  "geometry": {"coordinates":[121.9516,13.8611],"type":"Point"}
}