{
  "type": "Feature",
  "properties": {
    "gn:admin1_code":"07",
    "gn:admin2_code":"11",
    "gn:admin3_code":"71202000.0",
    "gn:asciiname":"Mahayag",
    "gn:country_code":"PH",
    "gn:dem":84,
    "gn:feature_class":"P",
    "gn:feature_code":"PPL",
    "gn:name":"Mahayag",
    "gn:population":0,
    "gn:timezone":"Asia/Manila",
    "iso:country":"PH",
    "name:fil_x_preferred":[
        "Mahayag"
    ],
    "wof:name":"Mahayag",
    "wof:placetype":"locality"
},
  "geometry": {"coordinates":[124.4457,9.8629],"type":"Point"}
}