{
  "type": "Feature",
  "properties": {
    "gn:admin1_code":"15",
    "gn:admin2_code":"27",
    "gn:admin3_code":"142703000.0",
    "gn:asciiname":"Ibulao",
    "gn:country_code":"PH",
    "gn:dem":425,
    "gn:feature_class":"P",
    "gn:feature_code":"PPL",
    "gn:name":"Ibulao",
    "gn:population":0,
    "gn:timezone":"Asia/Manila",
    "iso:country":"PH",
    "name:fil_x_preferred":[
        "Ibulao"
    ],
    "wof:name":"Ibulao",
    "wof:placetype":"locality"
},
  "geometry": {"coordinates":[121.11774,16.78537],"type":"Point"}
}