{
  "type": "Feature",
  "properties": {
    "gn:admin1_code":"14",
    "gn:admin2_code":"56",
    "gn:admin3_code":"153835000.0",
    "gn:asciiname":"Meta",
    "gn:country_code":"PH",
    "gn:dem":110,
    "gn:feature_class":"P",
    "gn:feature_code":"PPL",
    "gn:name":"Meta",
    "gn:population":0,
    "gn:timezone":"Asia/Manila",
    "iso:country":"PH",
    "name:fil_x_preferred":[
        "Meta"
    ],
    "name:und_x_variant":[
        "Mala",
        "Mata"
    ],
    "wof:name":"Meta",
    "wof:placetype":"locality"
},
  "geometry": {"coordinates":[124.40806000000001,6.88361],"type":"Point"}
}