{
  "type": "Feature",
  "properties": {
    "gn:admin1_code":"14",
    "gn:admin2_code":"56",
    "gn:admin3_code":"153835000.0",
    "gn:asciiname":"Meta",
    "gn:country_code":"PH",
    "gn:dem":110,
    "gn:feature_class":"P",
    "gn:feature_code":"PPL",
    "gn:name":"Meta",
    "gn:population":0,
    "gn:timezone":"Asia/Manila",
    "iso:country":"PH",
    "name:ara_x_preferred":[
        "\u0645\u064a\u062a\u0627"
    ],
    "name:bel_x_preferred":[
        "\u041c\u0435\u0442\u0430-"
    ],
    "name:dan_x_preferred":[
        "Meta"
    ],
    "name:est_x_preferred":[
        "Meta-"
    ],
    "name:fas_x_preferred":[
        "\u0645\u062a\u0627"
    ],
    "name:fil_x_preferred":[
        "Meta"
    ],
    "name:fin_x_preferred":[
        "Meta"
    ],
    "name:fra_x_preferred":[
        "M\u00e9ta"
    ],
    "name:heb_x_preferred":[
        "\u05de\u05d8\u05d4 \u05d0\u05d9\u05e0\u05e7\u05d5\u05d2\u05e0\u05d9\u05d8\u05d4"
    ],
    "name:heb_x_variant":[
        "\u05de\u05d8\u05d0"
    ],
    "name:hun_x_preferred":[
        "Meta"
    ],
    "name:ind_x_preferred":[
        "Meta"
    ],
    "name:kat_x_preferred":[
        "\u10db\u10d4\u10e2\u10d0..."
    ],
    "name:kir_x_preferred":[
        "\u041c\u0435\u0442\u0430..."
    ],
    "name:nno_x_preferred":[
        "Meta"
    ],
    "name:nor_x_preferred":[
        "Meta"
    ],
    "name:rus_x_preferred":[
        "\u041c\u0435\u0442\u0430-"
    ],
    "name:spa_x_preferred":[
        "Meta"
    ],
    "name:swe_x_preferred":[
        "Meta-"
    ],
    "name:tha_x_preferred":[
        "\u0e40\u0e21\u0e17\u0e32"
    ],
    "name:und_x_variant":[
        "Mala",
        "Mata"
    ],
    "name:urd_x_preferred":[
        "\u0645\u06cc\u0679\u0627"
    ],
    "name:vie_x_preferred":[
        "S\u00f4ng Meta"
    ],
    "wof:name":"Meta",
    "wof:placetype":"locality"
},
  "geometry": {"coordinates":[124.40806000000001,6.88361],"type":"Point"}
}