{
  "type": "Feature",
  "properties": {
    "gn:admin1_code":"09",
    "gn:admin2_code":"66",
    "gn:admin3_code":"97302000.0",
    "gn:asciiname":"Lantongan",
    "gn:country_code":"PH",
    "gn:dem":182,
    "gn:feature_class":"P",
    "gn:feature_code":"PPL",
    "gn:name":"Lantongan",
    "gn:population":0,
    "gn:timezone":"Asia/Manila",
    "iso:country":"PH",
    "name:eng_x_preferred":[
        "Lantongan"
    ],
    "name:und_x_variant":[
        "Lantongar"
    ],
    "wof:name":"Lantongan",
    "wof:placetype":"locality"
},
  "geometry": {"coordinates":[123.6258,7.9001],"type":"Point"}
}