{
  "type": "Feature",
  "properties": {
    "gn:admin1_code":"40",
    "gn:admin2_code":"33",
    "gn:admin3_code":"43429000.0",
    "gn:asciiname":"Cevida",
    "gn:country_code":"PH",
    "gn:dem":8,
    "gn:feature_class":"P",
    "gn:feature_code":"PPL",
    "gn:name":"Cevida",
    "gn:population":0,
    "gn:timezone":"Asia/Manila",
    "iso:country":"PH",
    "name:fil_x_preferred":[
        "Cevida"
    ],
    "wof:name":"Cevida",
    "wof:placetype":"locality"
},
  "geometry": {"coordinates":[121.44589999999999,14.4175],"type":"Point"}
}