{
  "type": "Feature",
  "properties": {
    "gn:admin1_code":"03",
    "gn:admin2_code":"47",
    "gn:admin3_code":"34919000.0",
    "gn:asciiname":"Barrio Libis",
    "gn:country_code":"PH",
    "gn:dem":73,
    "gn:feature_class":"P",
    "gn:feature_code":"PPL",
    "gn:name":"Barrio Libis",
    "gn:population":0,
    "gn:timezone":"Asia/Manila",
    "iso:country":"PH",
    "name:fil_x_preferred":[
        "Barrio Libis"
    ],
    "wof:name":"Barrio Libis",
    "wof:placetype":"locality"
},
  "geometry": {"coordinates":[121.08838,15.4161],"type":"Point"}
}