{
  "type": "Feature",
  "properties": {
    "gn:admin1_code":"09",
    "gn:admin2_code":"66",
    "gn:admin3_code":"97306000.0",
    "gn:asciiname":"Upper Sibul",
    "gn:country_code":"PH",
    "gn:dem":388,
    "gn:feature_class":"P",
    "gn:feature_code":"PPL",
    "gn:name":"Upper Sibul",
    "gn:population":0,
    "gn:timezone":"Asia/Manila",
    "iso:country":"PH",
    "wof:name":"Upper Sibul",
    "wof:placetype":"locality"
},
  "geometry": {"coordinates":[123.26582999999999,7.60556],"type":"Point"}
}