{
  "type": "Feature",
  "properties": {
    "gn:admin1_code":"08",
    "gn:admin2_code":"37",
    "gn:admin3_code":"83751000.0",
    "gn:asciiname":"Jordan",
    "gn:country_code":"PH",
    "gn:dem":7,
    "gn:feature_class":"P",
    "gn:feature_code":"PPL",
    "gn:name":"Jordan",
    "gn:population":0,
    "gn:timezone":"Asia/Manila",
    "iso:country":"PH",
    "name:fil_x_preferred":[
        "Jordan"
    ],
    "wof:name":"Jordan",
    "wof:placetype":"locality"
},
  "geometry": {"coordinates":[124.3927,11.1637],"type":"Point"}
}