{
  "type": "Feature",
  "properties": {
    "gn:admin1_code":"01",
    "gn:admin2_code":"51",
    "gn:admin3_code":"15548000.0",
    "gn:asciiname":"Laoac East",
    "gn:country_code":"PH",
    "gn:dem":35,
    "gn:feature_class":"P",
    "gn:feature_code":"PPL",
    "gn:name":"Laoac East",
    "gn:population":0,
    "gn:timezone":"Asia/Manila",
    "iso:country":"PH",
    "name:eng_x_preferred":[
        "Laoac East"
    ],
    "name:fil_x_preferred":[
        "Laoac"
    ],
    "name:fil_x_variant":[
        "Laoak Este"
    ],
    "name:und_x_variant":[
        "Laoak Este"
    ],
    "wof:name":"Laoac East",
    "wof:placetype":"locality"
},
  "geometry": {"coordinates":[120.5565,16.0523],"type":"Point"}
}