{
  "type": "Feature",
  "properties": {
    "gn:gn_country":"PH",
    "gn:gn_fcode":"PPL",
    "gn:gn_pop":5502,
    "gn:population":5502,
    "iso:country":"PH",
    "name:bcl_x_preferred":[
        "Polillo"
    ],
    "name:cat_x_preferred":[
        "Polillo"
    ],
    "name:ceb_x_preferred":[
        "Polillo"
    ],
    "name:deu_x_preferred":[
        "Polillo"
    ],
    "name:eng_x_preferred":[
        "Polillo"
    ],
    "name:fil_x_preferred":[
        "Polillo"
    ],
    "name:fra_x_preferred":[
        "Polillo"
    ],
    "name:ilo_x_preferred":[
        "Polillo"
    ],
    "name:ind_x_preferred":[
        "Polillo"
    ],
    "name:ita_x_preferred":[
        "Polillo"
    ],
    "name:jpn_x_preferred":[
        "\u30dd\u30ea\u30ed"
    ],
    "name:nld_x_preferred":[
        "Polillo"
    ],
    "name:oci_x_preferred":[
        "Polillo"
    ],
    "name:pag_x_preferred":[
        "Polillo"
    ],
    "name:pam_x_preferred":[
        "Polillo"
    ],
    "name:swe_x_preferred":[
        "Polillo"
    ],
    "name:tgl_x_preferred":[
        "Polillo"
    ],
    "name:vie_x_preferred":[
        "Polillo"
    ],
    "name:war_x_preferred":[
        "Polillo"
    ],
    "qs_pg:aaroncc":"PH",
    "qs_pg:gn_country":"PH",
    "qs_pg:gn_fcode":"PPL",
    "qs_pg:gn_pop":5502,
    "qs_pg:name":"Polillo",
    "qs_pg:photos_9r":0,
    "qs_pg:photos_sr":0,
    "qs_pg:pop_sr":5,
    "qs_pg:qs_pg_placetype":"locality",
    "wof:name":"Polillo",
    "wof:placetype":"locality",
    "wof:population":5502
},
  "geometry": {"coordinates":[121.93810000000001,14.71642],"type":"Point"}
}