{
  "type": "Feature",
  "properties": {
    "gn:admin1_code":"06",
    "gn:admin2_code":"04",
    "gn:admin3_code":"60402000.0",
    "gn:asciiname":"Buta",
    "gn:country_code":"PH",
    "gn:dem":58,
    "gn:feature_class":"P",
    "gn:feature_code":"PPL",
    "gn:name":"Buta",
    "gn:population":0,
    "gn:timezone":"Asia/Manila",
    "iso:country":"PH",
    "name:ceb_x_preferred":[
        "Buta"
    ],
    "name:deu_x_preferred":[
        "Buta"
    ],
    "name:fil_x_preferred":[
        "Buta"
    ],
    "name:ita_x_preferred":[
        "Buta"
    ],
    "name:por_x_preferred":[
        "Buta"
    ],
    "name:ron_x_preferred":[
        "Buta"
    ],
    "name:rus_x_preferred":[
        "\u0411\u0443\u0442\u0430"
    ],
    "name:srp_x_preferred":[
        "\u0411\u0443\u0442\u0430"
    ],
    "name:swe_x_preferred":[
        "Buta"
    ],
    "name:ukr_x_preferred":[
        "\u0411\u0443\u0442\u0430"
    ],
    "wof:name":"Buta",
    "wof:placetype":"locality"
},
  "geometry": {"coordinates":[122.39660000000001,11.5081],"type":"Point"}
}