{
  "type": "Feature",
  "properties": {
    "gn:admin1_code":"08",
    "gn:admin2_code":"67",
    "gn:admin3_code":"84810000.0",
    "gn:asciiname":"Giracdo",
    "gn:country_code":"PH",
    "gn:dem":5,
    "gn:feature_class":"P",
    "gn:feature_code":"PPL",
    "gn:name":"Giracdo",
    "gn:population":0,
    "gn:timezone":"Asia/Manila",
    "iso:country":"PH",
    "name:fil_x_preferred":[
        "Giracdo"
    ],
    "name:und_x_variant":[
        "Geracdo",
        "Giracdo"
    ],
    "wof:name":"Giracdo",
    "wof:placetype":"locality"
},
  "geometry": {"coordinates":[125.0355,12.3543],"type":"Point"}
}