{
  "type": "Feature",
  "properties": {
    "gn:admin1_code":"40",
    "gn:admin2_code":"20",
    "gn:admin3_code":"42123000.0",
    "gn:asciiname":"B. Pulido",
    "gn:country_code":"PH",
    "gn:dem":116,
    "gn:feature_class":"P",
    "gn:feature_code":"PPL",
    "gn:name":"B. Pulido",
    "gn:population":0,
    "gn:timezone":"Asia/Manila",
    "iso:country":"PH",
    "name:fil_x_preferred":[
        "B. Pulido"
    ],
    "wof:name":"B. Pulido",
    "wof:placetype":"locality"
},
  "geometry": {"coordinates":[121.0183,14.3085],"type":"Point"}
}