{
  "type": "Feature",
  "properties": {
    "gn:admin1_code":"07",
    "gn:admin2_code":"11",
    "gn:admin3_code":"71218000.0",
    "gn:asciiname":"Cantobod",
    "gn:country_code":"PH",
    "gn:dem":157,
    "gn:feature_class":"P",
    "gn:feature_code":"PPL",
    "gn:name":"Cantobod",
    "gn:population":0,
    "gn:timezone":"Asia/Manila",
    "iso:country":"PH",
    "name:fil_x_preferred":[
        "Cantobod"
    ],
    "wof:name":"Cantobod",
    "wof:placetype":"locality"
},
  "geometry": {"coordinates":[124.17972,9.92833],"type":"Point"}
}