{
  "type": "Feature",
  "properties": {
    "gn:admin1_code":"06",
    "gn:admin2_code":"06",
    "gn:admin3_code":"60604000.0",
    "gn:asciiname":"Igtugas",
    "gn:country_code":"PH",
    "gn:dem":106,
    "gn:feature_class":"P",
    "gn:feature_code":"PPL",
    "gn:name":"Igtugas",
    "gn:population":0,
    "gn:timezone":"Asia/Manila",
    "iso:country":"PH",
    "name:fil_x_preferred":[
        "Igtugas"
    ],
    "wof:name":"Igtugas",
    "wof:placetype":"locality"
},
  "geometry": {"coordinates":[122.1491,11.0681],"type":"Point"}
}