{
  "type": "Feature",
  "properties": {
    "gn:admin1_code":"07",
    "gn:admin2_code":"46",
    "gn:admin3_code":"74620000.0",
    "gn:asciiname":"Bolocboloc",
    "gn:country_code":"PH",
    "gn:dem":16,
    "gn:feature_class":"P",
    "gn:feature_code":"PPL",
    "gn:name":"Bolocboloc",
    "gn:population":0,
    "gn:timezone":"Asia/Manila",
    "iso:country":"PH",
    "name:fil_x_preferred":[
        "Bolocboloc"
    ],
    "name:und_x_variant":[
        "Bolokbolok"
    ],
    "wof:name":"Bolocboloc",
    "wof:placetype":"locality"
},
  "geometry": {"coordinates":[123.2927,9.3373],"type":"Point"}
}