{
  "type": "Feature",
  "properties": {
    "gn:admin1_code":"08",
    "gn:admin2_code":"37",
    "gn:admin3_code":"83706000.0",
    "gn:asciiname":"Guinputngan",
    "gn:country_code":"PH",
    "gn:dem":32,
    "gn:feature_class":"P",
    "gn:feature_code":"PPL",
    "gn:name":"Guinputngan",
    "gn:population":0,
    "gn:timezone":"Asia/Manila",
    "iso:country":"PH",
    "name:fil_x_preferred":[
        "Guinputngan"
    ],
    "wof:name":"Guinputngan",
    "wof:placetype":"locality"
},
  "geometry": {"coordinates":[124.78333000000001,11.26667],"type":"Point"}
}