{
  "type": "Feature",
  "properties": {
    "gn:country":"PH",
    "gn:fcode":"ADM3",
    "gn:pop":39727,
    "iso:country":"PH",
    "name:fil_x_preferred":[
        "Lal-lo"
    ],
    "qs:name":"Lal-lo",
    "qs:photos_9r":0,
    "qs:photos_sr":0,
    "qs:pop_sr":"7",
    "wof:name":"Lal-lo",
    "wof:placetype":"localadmin",
    "wof:population":39727
},
  "geometry": {"coordinates":[121.88333,18.18333],"type":"Point"}
}