{
  "type": "Feature",
  "properties": {
    "gn:admin1_code":"07",
    "gn:admin2_code":"46",
    "gn:admin3_code":"74623000.0",
    "gn:asciiname":"Malabo",
    "gn:country_code":"PH",
    "gn:dem":540,
    "gn:feature_class":"P",
    "gn:feature_code":"PPL",
    "gn:name":"Malabo",
    "gn:population":0,
    "gn:timezone":"Asia/Manila",
    "iso:country":"PH",
    "name:fil_x_preferred":[
        "Malabo"
    ],
    "wof:name":"Malabo",
    "wof:placetype":"locality"
},
  "geometry": {"coordinates":[123.2007,9.3217],"type":"Point"}
}