{
  "type": "Feature",
  "properties": {
    "gn:admin1_code":"05",
    "gn:admin2_code":"15",
    "gn:admin3_code":"51601000.0",
    "gn:asciiname":"Salasa",
    "gn:country_code":"PH",
    "gn:dem":17,
    "gn:feature_class":"P",
    "gn:feature_code":"PPL",
    "gn:name":"Salasa",
    "gn:population":0,
    "gn:timezone":"Asia/Manila",
    "iso:country":"PH",
    "name:fil_x_preferred":[
        "Salasa"
    ],
    "wof:name":"Salasa",
    "wof:placetype":"locality"
},
  "geometry": {"coordinates":[122.94629999999999,14.077],"type":"Point"}
}