{
  "type": "Feature",
  "properties": {
    "gn:admin1_code":"40",
    "gn:admin2_code":"33",
    "gn:admin3_code":"43405000.0",
    "gn:asciiname":"Sampiruhan",
    "gn:country_code":"PH",
    "gn:dem":7,
    "gn:feature_class":"P",
    "gn:feature_code":"PPL",
    "gn:name":"Sampiruhan",
    "gn:population":0,
    "gn:timezone":"Asia/Manila",
    "iso:country":"PH",
    "name:fil_x_preferred":[
        "Sampiruhan"
    ],
    "wof:name":"Sampiruhan",
    "wof:placetype":"locality"
},
  "geometry": {"coordinates":[121.18438,14.21766],"type":"Point"}
}