{
  "type": "Feature",
  "properties": {
    "gn:admin1_code":"02",
    "gn:admin2_code":"31",
    "gn:admin3_code":"23103000.0",
    "gn:asciiname":"Bagnos",
    "gn:country_code":"PH",
    "gn:dem":58,
    "gn:feature_class":"P",
    "gn:feature_code":"PPL",
    "gn:name":"Bagnos",
    "gn:population":0,
    "gn:timezone":"Asia/Manila",
    "iso:country":"PH",
    "name:fil_x_preferred":[
        "Bagno"
    ],
    "name:fil_x_variant":[
        "Bagho"
    ],
    "wof:name":"Bagnos",
    "wof:placetype":"locality"
},
  "geometry": {"coordinates":[121.67446,17.00715],"type":"Point"}
}