{
  "type": "Feature",
  "properties": {
    "gn:country":"PH",
    "gn:fcode":"PPL",
    "gn:population":6224,
    "iso:country":"PH",
    "name:fil_x_preferred":[
        "Malicboy"
    ],
    "name:und_x_variant":[
        "Malicbuy"
    ],
    "qs_pg:aaroncc":"PH",
    "qs_pg:gn_country":"PH",
    "qs_pg:gn_fcode":"PPL",
    "qs_pg:gn_pop":6224,
    "qs_pg:name":"Malicboy",
    "qs_pg:photos_9r":0,
    "qs_pg:photos_sr":0,
    "qs_pg:pop_sr":5,
    "qs_pg:qs_pg_placetype":"locality",
    "wof:name":"Malicboy",
    "wof:placetype":"locality",
    "wof:population":6224
},
  "geometry": {"coordinates":[121.78888000000001,13.98155],"type":"Point"}
}