{
  "type": "Feature",
  "properties": {
    "gn:admin1_code":"07",
    "gn:admin2_code":"69",
    "gn:asciiname":"Taculing",
    "gn:cc2":"PH",
    "gn:country_code":"PH",
    "gn:dem":1,
    "gn:feature_class":"P",
    "gn:feature_code":"PPL",
    "gn:name":"Taculing",
    "gn:population":0,
    "gn:timezone":"Asia/Manila",
    "iso:country":"PH",
    "name:und_x_variant":[
        "Takaling",
        "Takoling",
        "Taculing"
    ],
    "wof:name":"Taculing",
    "wof:placetype":"locality"
},
  "geometry": {"coordinates":[123.59667,9.27194],"type":"Point"}
}