{
  "type": "Feature",
  "properties": {
    "gn:admin1_code":"01",
    "gn:admin2_code":"28",
    "gn:admin3_code":"12813000.0",
    "gn:asciiname":"Santa Regina",
    "gn:country_code":"PH",
    "gn:dem":58,
    "gn:feature_class":"P",
    "gn:feature_code":"PPL",
    "gn:name":"Santa Regina",
    "gn:population":0,
    "gn:timezone":"Asia/Manila",
    "iso:country":"PH",
    "name:fil_x_preferred":[
        "Santa Regina"
    ],
    "wof:name":"Santa Regina",
    "wof:placetype":"locality"
},
  "geometry": {"coordinates":[120.71169999999999,18.0175],"type":"Point"}
}