{
  "type": "Feature",
  "properties": {
    "gn:admin1_code":"05",
    "gn:admin2_code":"19",
    "gn:admin3_code":"52006000.0",
    "gn:asciiname":"Nagnonot",
    "gn:country_code":"PH",
    "gn:dem":11,
    "gn:feature_class":"P",
    "gn:feature_code":"PPL",
    "gn:name":"Nagnonot",
    "gn:population":0,
    "gn:timezone":"Asia/Manila",
    "iso:country":"PH",
    "name:fil_x_preferred":[
        "Nagnonot"
    ],
    "wof:name":"Nagnonot",
    "wof:placetype":"locality"
},
  "geometry": {"coordinates":[124.1532,14.0396],"type":"Point"}
}