{
  "type": "Feature",
  "properties": {
    "gn:country":"PH",
    "gn:fcode":"PPL",
    "gn:pop":3523,
    "iso:country":"PH",
    "name:fil_x_preferred":[
        "Culaman"
    ],
    "name:unk_x_variant":[
        "Kulaman"
    ],
    "qs:name":"Culaman",
    "qs:photos_9r":0,
    "qs:photos_sr":0,
    "qs:pop_sr":"4",
    "wof:name":"Culaman",
    "wof:placetype":"locality",
    "wof:population":3523
},
  "geometry": {"coordinates":[125.65861,5.96028],"type":"Point"}
}