{
  "type": "Feature",
  "properties": {
    "gn:admin1_code":"05",
    "gn:admin2_code":"58",
    "gn:asciiname":"Cobarawan",
    "gn:country_code":"PH",
    "gn:dem":69,
    "gn:feature_class":"P",
    "gn:feature_code":"PPL",
    "gn:name":"Cobarawan",
    "gn:population":0,
    "gn:timezone":"Asia/Manila",
    "iso:country":"PH",
    "name:fil_x_preferred":[
        "Cobarawan"
    ],
    "wof:name":"Cobarawan",
    "wof:placetype":"locality"
},
  "geometry": {"coordinates":[123.96666999999999,12.56667],"type":"Point"}
}