{
  "type": "Feature",
  "properties": {
    "gn:admin1_code":"40",
    "gn:admin2_code":"09",
    "gn:admin3_code":"41014000.0",
    "gn:asciiname":"Tangob",
    "gn:country_code":"PH",
    "gn:dem":298,
    "gn:feature_class":"P",
    "gn:feature_code":"PPL",
    "gn:name":"Tangob",
    "gn:population":0,
    "gn:timezone":"Asia/Manila",
    "iso:country":"PH",
    "name:fil_x_preferred":[
        "Tangob"
    ],
    "wof:name":"Tangob",
    "wof:placetype":"locality"
},
  "geometry": {"coordinates":[121.19629999999999,13.9474],"type":"Point"}
}