{
  "type": "Feature",
  "properties": {
    "iso:country":"PH",
    "name:bcl_x_preferred":[
        "Bulacan"
    ],
    "name:bcl_x_variant":[
        "Bulakan"
    ],
    "name:cat_x_preferred":[
        "Bulacan"
    ],
    "name:cbk_zam_x_preferred":[
        "Bulacan"
    ],
    "name:ceb_x_preferred":[
        "Bulacan"
    ],
    "name:ceb_x_variant":[
        "Bulakan"
    ],
    "name:deu_x_preferred":[
        "Bulacan"
    ],
    "name:eng_x_preferred":[
        "Bulakan"
    ],
    "name:fil_x_preferred":[
        "Bulacan"
    ],
    "name:fra_x_preferred":[
        "Bulacan"
    ],
    "name:ilo_x_preferred":[
        "Bulacan"
    ],
    "name:ilo_x_variant":[
        "Bulakan"
    ],
    "name:ind_x_preferred":[
        "Bulacan"
    ],
    "name:ind_x_variant":[
        "Bulakan"
    ],
    "name:ita_x_preferred":[
        "Bulacan"
    ],
    "name:nld_x_preferred":[
        "Bulacan"
    ],
    "name:nob_x_preferred":[
        "Bulacan"
    ],
    "name:oci_x_preferred":[
        "Bulacan"
    ],
    "name:pag_x_preferred":[
        "Bulakan"
    ],
    "name:pam_x_preferred":[
        "Bulacan"
    ],
    "name:pam_x_variant":[
        "Bulakan"
    ],
    "name:spa_x_preferred":[
        "Bulac\u00e1n"
    ],
    "name:swe_x_preferred":[
        "Bulacan"
    ],
    "name:tgl_x_preferred":[
        "Bulakan"
    ],
    "name:war_x_preferred":[
        "Bulakan"
    ],
    "qs:gn_country":"PH",
    "qs:gn_fcode":"PPLA3",
    "qs:gn_pop":71274,
    "qs:name":"Bulacan",
    "qs:name_adm0":"Philippines",
    "qs:name_adm1":"Central Luzon",
    "qs:photos":265,
    "qs:photos_1k":54,
    "qs:photos_9k":1,
    "qs:photos_9r":4,
    "qs:photos_all":265,
    "qs:photos_sr":5,
    "qs:placetype":"Town",
    "qs:pop_sr":"8",
    "qs:woe_adm0":23424934,
    "wd:wordcount":2109,
    "wof:name":"Bulacan",
    "wof:placetype":"locality",
    "wof:population":71274
},
  "geometry": {"coordinates":[120.87889,14.79278],"type":"Point"}
}