{
  "type": "Feature",
  "properties": {
    "gn:admin1_code":"03",
    "gn:admin2_code":"07",
    "gn:admin3_code":"30804000.0",
    "gn:asciiname":"Bangal",
    "gn:country_code":"PH",
    "gn:dem":158,
    "gn:feature_class":"P",
    "gn:feature_code":"PPL",
    "gn:name":"Bangal",
    "gn:population":0,
    "gn:timezone":"Asia/Manila",
    "iso:country":"PH",
    "wof:name":"Bangal",
    "wof:placetype":"locality"
},
  "geometry": {"coordinates":[120.34690000000001,14.84869],"type":"Point"}
}