{
  "type": "Feature",
  "properties": {
    "gn:admin1_code":"06",
    "gn:admin2_code":"30",
    "gn:admin3_code":"63008000.0",
    "gn:asciiname":"Nueva Sevilla",
    "gn:country_code":"PH",
    "gn:dem":4,
    "gn:feature_class":"P",
    "gn:feature_code":"PPL",
    "gn:name":"Nueva Sevilla",
    "gn:population":0,
    "gn:timezone":"Asia/Manila",
    "iso:country":"PH",
    "name:fil_x_preferred":[
        "Nueva Sevilla"
    ],
    "wof:name":"Nueva Sevilla",
    "wof:placetype":"locality"
},
  "geometry": {"coordinates":[122.85333,11.02278],"type":"Point"}
}