{
  "type": "Feature",
  "properties": {
    "gn:admin1_code":"06",
    "gn:admin2_code":"H3",
    "gn:admin3_code":"64524000.0",
    "gn:asciiname":"Galicia Hacienda",
    "gn:country_code":"PH",
    "gn:dem":4,
    "gn:feature_class":"P",
    "gn:feature_code":"PPL",
    "gn:name":"Galicia Hacienda",
    "gn:population":0,
    "gn:timezone":"Asia/Manila",
    "iso:country":"PH",
    "name:fil_x_preferred":[
        "Galicia Hacienda"
    ],
    "wof:name":"Galicia Hacienda",
    "wof:placetype":"locality"
},
  "geometry": {"coordinates":[123.4118,10.4776],"type":"Point"}
}