{
  "type": "Feature",
  "properties": {
    "gn:admin1_code":"14",
    "gn:admin2_code":"60",
    "gn:admin3_code":"156601000.0",
    "gn:asciiname":"Tagbak",
    "gn:country_code":"PH",
    "gn:dem":159,
    "gn:feature_class":"P",
    "gn:feature_code":"PPL",
    "gn:name":"Tagbak",
    "gn:population":0,
    "gn:timezone":"Asia/Manila",
    "iso:country":"PH",
    "name:eng_x_preferred":[
        "Tagbak"
    ],
    "wof:name":"Tagbak",
    "wof:placetype":"locality"
},
  "geometry": {"coordinates":[120.99290000000001,6.0165],"type":"Point"}
}