{
  "type": "Feature",
  "properties": {
    "gn:admin1_code":"02",
    "gn:admin2_code":"14",
    "gn:admin3_code":"21513000.0",
    "gn:asciiname":"Aggunetan",
    "gn:country_code":"PH",
    "gn:dem":16,
    "gn:feature_class":"P",
    "gn:feature_code":"PPL",
    "gn:name":"Aggunetan",
    "gn:population":0,
    "gn:timezone":"Asia/Manila",
    "iso:country":"PH",
    "name:fil_x_preferred":[
        "Aggunatan"
    ],
    "name:fil_x_variant":[
        "Aggunetan"
    ],
    "wof:name":"Aggunetan",
    "wof:placetype":"locality"
},
  "geometry": {"coordinates":[121.60554999999999,17.99599],"type":"Point"}
}