{
  "type": "Feature",
  "properties": {
    "gn:admin1_code":"13",
    "gn:admin2_code":"62",
    "gn:admin3_code":"166817000.0",
    "gn:asciiname":"Carpenito",
    "gn:country_code":"PH",
    "gn:dem":12,
    "gn:feature_class":"P",
    "gn:feature_code":"PPL",
    "gn:name":"Carpenito",
    "gn:population":0,
    "gn:timezone":"Asia/Manila",
    "iso:country":"PH",
    "name:fil_x_preferred":[
        "Carpenito"
    ],
    "wof:name":"Carpenito",
    "wof:placetype":"locality"
},
  "geometry": {"coordinates":[126.22556000000002,8.41944],"type":"Point"}
}