{
  "type": "Feature",
  "properties": {
    "gn:admin1_code":"13",
    "gn:admin2_code":"02",
    "gn:admin3_code":"160210000.0",
    "gn:asciiname":"Tagmamarcay",
    "gn:country_code":"PH",
    "gn:dem":43,
    "gn:feature_class":"P",
    "gn:feature_code":"PPL",
    "gn:name":"Tagmamarcay",
    "gn:population":0,
    "gn:timezone":"Asia/Manila",
    "iso:country":"PH",
    "name:fil_x_preferred":[
        "Tagmamarcay"
    ],
    "wof:name":"Tagmamarcay",
    "wof:placetype":"locality"
},
  "geometry": {"coordinates":[125.56556,9.22306],"type":"Point"}
}