{
  "type": "Feature",
  "properties": {
    "gn:admin1_code":"10",
    "gn:admin2_code":"42",
    "gn:admin3_code":"104216000.0",
    "gn:asciiname":"Loocson",
    "gn:country_code":"PH",
    "gn:dem":41,
    "gn:feature_class":"P",
    "gn:feature_code":"PPL",
    "gn:name":"Loocson",
    "gn:population":0,
    "gn:timezone":"Asia/Manila",
    "iso:country":"PH",
    "name:eng_x_preferred":[
        "Loocson"
    ],
    "name:und_x_variant":[
        "Locsoon"
    ],
    "wof:name":"Loocson",
    "wof:placetype":"locality"
},
  "geometry": {"coordinates":[123.834,8.2278],"type":"Point"}
}