{
  "type": "Feature",
  "properties": {
    "gn:admin1_code":"41",
    "gn:admin2_code":"54",
    "gn:admin3_code":"175913000.0",
    "gn:asciiname":"Azagra",
    "gn:country_code":"PH",
    "gn:dem":121,
    "gn:feature_class":"P",
    "gn:feature_code":"PPL",
    "gn:name":"Azagra",
    "gn:population":0,
    "gn:timezone":"Asia/Manila",
    "iso:country":"PH",
    "name:fil_x_preferred":[
        "Azagra"
    ],
    "name:und_x_variant":[
        "Azarga"
    ],
    "wof:name":"Azagra",
    "wof:placetype":"locality"
},
  "geometry": {"coordinates":[122.62961,12.29107],"type":"Point"}
}