{
  "type": "Feature",
  "properties": {
    "gn:admin1_code":"41",
    "gn:admin2_code":"54",
    "gn:admin3_code":"175913000.0",
    "gn:asciiname":"Azagra",
    "gn:country_code":"PH",
    "gn:dem":121,
    "gn:feature_class":"P",
    "gn:feature_code":"PPL",
    "gn:name":"Azagra",
    "gn:population":0,
    "gn:timezone":"Asia/Manila",
    "iso:country":"PH",
    "name:arg_x_preferred":[
        "Azagra"
    ],
    "name:bre_x_preferred":[
        "Azagra"
    ],
    "name:cat_x_preferred":[
        "Azagra"
    ],
    "name:ceb_x_preferred":[
        "Azagra"
    ],
    "name:eus_x_preferred":[
        "Azagra"
    ],
    "name:fil_x_preferred":[
        "Azagra"
    ],
    "name:fra_x_preferred":[
        "Azagra"
    ],
    "name:hun_x_preferred":[
        "Azagra"
    ],
    "name:ita_x_preferred":[
        "Azagra"
    ],
    "name:lat_x_preferred":[
        "Azagra"
    ],
    "name:msa_x_preferred":[
        "Azagra"
    ],
    "name:nld_x_preferred":[
        "Azagra"
    ],
    "name:oci_x_preferred":[
        "Azagra"
    ],
    "name:pol_x_preferred":[
        "Azagra"
    ],
    "name:por_x_preferred":[
        "Azagra"
    ],
    "name:rus_x_preferred":[
        "\u0410\u0441\u0430\u0433\u0440\u0430"
    ],
    "name:spa_x_preferred":[
        "Azagra"
    ],
    "name:swe_x_preferred":[
        "Azagra"
    ],
    "name:ukr_x_preferred":[
        "\u0410\u0441\u0430\u0433\u0440\u0430"
    ],
    "name:und_x_variant":[
        "Azarga"
    ],
    "name:vie_x_preferred":[
        "Azagra"
    ],
    "name:war_x_preferred":[
        "Azagra"
    ],
    "name:zho_x_preferred":[
        "\u963f\u8428\u683c\u62c9"
    ],
    "wof:name":"Azagra",
    "wof:placetype":"locality"
},
  "geometry": {"coordinates":[122.62961,12.29107],"type":"Point"}
}