{
  "type": "Feature",
  "properties": {
    "gn:admin1_code":"40",
    "gn:admin2_code":"53",
    "gn:admin3_code":"45803000.0",
    "gn:asciiname":"Dagat Dagatan",
    "gn:country_code":"PH",
    "gn:dem":200,
    "gn:feature_class":"P",
    "gn:feature_code":"PPL",
    "gn:name":"Dagat Dagatan",
    "gn:population":0,
    "gn:timezone":"Asia/Manila",
    "iso:country":"PH",
    "name:fil_x_preferred":[
        "Dagat Dagatan"
    ],
    "wof:name":"Dagat Dagatan",
    "wof:placetype":"locality"
},
  "geometry": {"coordinates":[121.2794,14.6113],"type":"Point"}
}