{
  "type": "Feature",
  "properties": {
    "gn:admin1_code":"05",
    "gn:admin2_code":"39",
    "gn:admin3_code":"54107000.0",
    "gn:asciiname":"Pasig",
    "gn:country_code":"PH",
    "gn:dem":9,
    "gn:feature_class":"P",
    "gn:feature_code":"PPL",
    "gn:name":"Pasig",
    "gn:population":0,
    "gn:timezone":"Asia/Manila",
    "iso:country":"PH",
    "name:ara_x_preferred":[
        "\u0628\u0627\u0633\u064a\u062c"
    ],
    "name:ceb_x_preferred":[
        "Pasig"
    ],
    "name:deu_x_preferred":[
        "Pasig City"
    ],
    "name:eng_x_preferred":[
        "Pasig"
    ],
    "name:epo_x_preferred":[
        "Pasigo"
    ],
    "name:fin_x_preferred":[
        "Pasig"
    ],
    "name:fra_x_preferred":[
        "Pasig"
    ],
    "name:hun_x_preferred":[
        "Pasig"
    ],
    "name:ilo_x_preferred":[
        "Pasig"
    ],
    "name:ind_x_preferred":[
        "Kota Pasig"
    ],
    "name:ita_x_preferred":[
        "Pasig"
    ],
    "name:jpn_x_preferred":[
        "\u30d1\u30b7\u30c3\u30b0"
    ],
    "name:kor_x_preferred":[
        "\ud30c\uc2dc\uadf8"
    ],
    "name:msa_x_preferred":[
        "Pasig"
    ],
    "name:nld_x_preferred":[
        "Pasig"
    ],
    "name:nor_x_preferred":[
        "Pasig"
    ],
    "name:pag_x_preferred":[
        "Pasig"
    ],
    "name:pam_x_preferred":[
        "Pasig"
    ],
    "name:pol_x_preferred":[
        "Pasig"
    ],
    "name:por_x_preferred":[
        "Pasig"
    ],
    "name:rus_x_preferred":[
        "\u041f\u0430\u0441\u0438\u0433"
    ],
    "name:sco_x_preferred":[
        "Pasig"
    ],
    "name:spa_x_preferred":[
        "P\u00e1sig"
    ],
    "name:swe_x_preferred":[
        "Pasig"
    ],
    "name:szl_x_preferred":[
        "Pasig"
    ],
    "name:tgl_x_preferred":[
        "Pasig"
    ],
    "name:tur_x_preferred":[
        "Pasig"
    ],
    "name:urd_x_preferred":[
        "\u067e\u0627\u0633\u06cc\u06af"
    ],
    "name:vie_x_preferred":[
        "Pasig"
    ],
    "name:war_x_preferred":[
        "Pasig"
    ],
    "name:zho_x_preferred":[
        "\u5e15\u897f\u683c"
    ],
    "wof:name":"Pasig",
    "wof:placetype":"locality"
},
  "geometry": {"coordinates":[123.1718,12.8853],"type":"Point"}
}