{
  "type": "Feature",
  "properties": {
    "gn:country":"PH",
    "gn:fcode":"PPL",
    "gn:pop":2545,
    "iso:country":"PH",
    "name:fil_x_preferred":[
        "Buenlag"
    ],
    "qs:name":"Buenlag",
    "qs:photos_9r":0,
    "qs:photos_sr":0,
    "qs:pop_sr":"4",
    "wof:name":"Buenlag",
    "wof:placetype":"locality",
    "wof:population":2545
},
  "geometry": {"coordinates":[120.5827,15.6304],"type":"Point"}
}