{
  "type": "Feature",
  "properties": {
    "gn:admin1_code":"01",
    "gn:admin2_code":"36",
    "gn:admin3_code":"13314000.0",
    "gn:asciiname":"Carlatan",
    "gn:country_code":"PH",
    "gn:dem":5,
    "gn:feature_class":"P",
    "gn:feature_code":"PPL",
    "gn:name":"Carlatan",
    "gn:population":0,
    "gn:timezone":"Asia/Manila",
    "iso:country":"PH",
    "name:fil_x_preferred":[
        "Carlatan"
    ],
    "wof:name":"Carlatan",
    "wof:placetype":"locality"
},
  "geometry": {"coordinates":[120.32333,16.63472],"type":"Point"}
}