{
  "type": "Feature",
  "properties": {
    "gn:gn_country":"PH",
    "gn:gn_fcode":"PPLA3",
    "gn:gn_pop":8789,
    "gn:population":8789,
    "iso:country":"PH",
    "name:bcl_x_preferred":[
        "Damulog"
    ],
    "name:ceb_x_preferred":[
        "Damulog"
    ],
    "name:deu_x_preferred":[
        "Damulog"
    ],
    "name:eng_x_preferred":[
        "Damulog"
    ],
    "name:fra_x_preferred":[
        "Damulog"
    ],
    "name:ilo_x_preferred":[
        "Damulog"
    ],
    "name:ind_x_preferred":[
        "Damulog"
    ],
    "name:ita_x_preferred":[
        "Damulog"
    ],
    "name:nld_x_preferred":[
        "Damulog"
    ],
    "name:pag_x_preferred":[
        "Damulog"
    ],
    "name:pam_x_preferred":[
        "Damulog"
    ],
    "name:spa_x_preferred":[
        "Damulog"
    ],
    "name:swe_x_preferred":[
        "Damulog"
    ],
    "name:tgl_x_preferred":[
        "Damulog"
    ],
    "name:unk_x_variant":[
        "Dumulug"
    ],
    "name:urd_x_preferred":[
        "\u062f\u0627\u0645\u0648\u0644\u0648\u06af"
    ],
    "name:vie_x_preferred":[
        "Damulog"
    ],
    "name:war_x_preferred":[
        "Damulog"
    ],
    "qs_pg:aaroncc":"PH",
    "qs_pg:gn_country":"PH",
    "qs_pg:gn_fcode":"PPLA3",
    "qs_pg:gn_pop":8789,
    "qs_pg:name":"Damulog",
    "qs_pg:photos_9r":0,
    "qs_pg:photos_sr":0,
    "qs_pg:pop_sr":5,
    "qs_pg:qs_pg_placetype":"locality",
    "wof:name":"Damulog",
    "wof:placetype":"locality",
    "wof:population":8789
},
  "geometry": {"coordinates":[124.94306,7.48361],"type":"Point"}
}