{
  "type": "Feature",
  "properties": {
    "gn:admin1_code":"41",
    "gn:admin2_code":"54",
    "gn:admin3_code":"175913000.0",
    "gn:asciiname":"Cantingas",
    "gn:country_code":"PH",
    "gn:dem":5,
    "gn:feature_class":"P",
    "gn:feature_code":"PPL",
    "gn:name":"Cantingas",
    "gn:population":0,
    "gn:timezone":"Asia/Manila",
    "iso:country":"PH",
    "name:fil_x_preferred":[
        "Cantingas"
    ],
    "wof:name":"Cantingas",
    "wof:placetype":"locality"
},
  "geometry": {"coordinates":[122.57571000000002,12.30684],"type":"Point"}
}