{
  "type": "Feature",
  "properties": {
    "gn:admin1_code":"01",
    "gn:admin2_code":"51",
    "gn:admin3_code":"15509000.0",
    "gn:asciiname":"Obong",
    "gn:country_code":"PH",
    "gn:dem":18,
    "gn:feature_class":"P",
    "gn:feature_code":"PPL",
    "gn:name":"Obong",
    "gn:population":0,
    "gn:timezone":"Asia/Manila",
    "iso:country":"PH",
    "name:fil_x_preferred":[
        "Obong"
    ],
    "wof:name":"Obong",
    "wof:placetype":"locality"
},
  "geometry": {"coordinates":[120.40988,15.85555],"type":"Point"}
}