{
  "type": "Feature",
  "properties": {
    "gn:country":"PH",
    "gn:fcode":"ADM3",
    "gn:pop":67928,
    "iso:country":"PH",
    "qs:name":"Kabacan",
    "qs:photos_9r":0,
    "qs:photos_sr":0,
    "qs:pop_sr":"8",
    "wof:name":"Kabacan",
    "wof:placetype":"localadmin",
    "wof:population":67928
},
  "geometry": {"coordinates":[124.81667,7.11667],"type":"Point"}
}