{
  "type": "Feature",
  "properties": {
    "gn:admin1_code":"15",
    "gn:admin2_code":"10",
    "gn:admin3_code":"141108000.0",
    "gn:asciiname":"Sagubo",
    "gn:country_code":"PH",
    "gn:dem":1228,
    "gn:feature_class":"P",
    "gn:feature_code":"PPL",
    "gn:name":"Sagubo",
    "gn:population":0,
    "gn:timezone":"Asia/Manila",
    "iso:country":"PH",
    "name:fil_x_preferred":[
        "Sagubo"
    ],
    "name:fil_x_variant":[
        "Saguba"
    ],
    "name:und_x_variant":[
        "Saguba"
    ],
    "wof:name":"Sagubo",
    "wof:placetype":"locality"
},
  "geometry": {"coordinates":[120.57769999999999,16.5808],"type":"Point"}
}