{
  "type": "Feature",
  "properties": {
    "gn:admin1_code":"08",
    "gn:admin2_code":"23",
    "gn:admin3_code":"82604000.0",
    "gn:asciiname":"Minale",
    "gn:country_code":"PH",
    "gn:dem":114,
    "gn:feature_class":"P",
    "gn:feature_code":"PPL",
    "gn:name":"Minale",
    "gn:population":0,
    "gn:timezone":"Asia/Manila",
    "iso:country":"PH",
    "name:fil_x_preferred":[
        "Minale"
    ],
    "wof:name":"Minale",
    "wof:placetype":"locality"
},
  "geometry": {"coordinates":[125.40000000000001,11.61667],"type":"Point"}
}