{
  "type": "Feature",
  "properties": {
    "gn:admin1_code":"03",
    "gn:admin2_code":"63",
    "gn:admin3_code":"36912000.0",
    "gn:asciiname":"Tumalat",
    "gn:country_code":"PH",
    "gn:dem":23,
    "gn:feature_class":"P",
    "gn:feature_code":"PPL",
    "gn:name":"Tumalat",
    "gn:population":0,
    "gn:timezone":"Asia/Manila",
    "iso:country":"PH",
    "name:fil_x_preferred":[
        "Tumalat"
    ],
    "wof:name":"Tumalat",
    "wof:placetype":"locality"
},
  "geometry": {"coordinates":[120.63679999999999,15.6825],"type":"Point"}
}