{
  "type": "Feature",
  "properties": {
    "gn:admin1_code":"14",
    "gn:admin2_code":"22",
    "gn:admin3_code":"150710000.0",
    "gn:asciiname":"Gitom",
    "gn:country_code":"PH",
    "gn:dem":14,
    "gn:feature_class":"P",
    "gn:feature_code":"PPL",
    "gn:name":"Gitom",
    "gn:population":0,
    "gn:timezone":"Asia/Manila",
    "iso:country":"PH",
    "name:fil_x_preferred":[
        "Gitom"
    ],
    "wof:name":"Gitom",
    "wof:placetype":"locality"
},
  "geometry": {"coordinates":[122.3725,6.77],"type":"Point"}
}