{
  "type": "Feature",
  "properties": {
    "gn:admin1_code":"01",
    "gn:admin2_code":"29",
    "gn:admin3_code":"12934000.0",
    "gn:asciiname":"Paratong",
    "gn:country_code":"PH",
    "gn:dem":7,
    "gn:feature_class":"P",
    "gn:feature_code":"PPL",
    "gn:name":"Paratong",
    "gn:population":0,
    "gn:timezone":"Asia/Manila",
    "iso:country":"PH",
    "name:fil_x_preferred":[
        "Paratong"
    ],
    "wof:name":"Paratong",
    "wof:placetype":"locality"
},
  "geometry": {"coordinates":[120.36530999999999,17.55506],"type":"Point"}
}