{
  "type": "Feature",
  "properties": {
    "gn:admin1_code":"05",
    "gn:admin2_code":"15",
    "gn:admin3_code":"51608000.0",
    "gn:asciiname":"Labnig",
    "gn:country_code":"PH",
    "gn:dem":8,
    "gn:feature_class":"P",
    "gn:feature_code":"PPL",
    "gn:name":"Labnig",
    "gn:population":0,
    "gn:timezone":"Asia/Manila",
    "iso:country":"PH",
    "name:fil_x_preferred":[
        "Labnig"
    ],
    "wof:name":"Labnig",
    "wof:placetype":"locality"
},
  "geometry": {"coordinates":[122.8151,14.2721],"type":"Point"}
}