{
  "type": "Feature",
  "properties": {
    "gn:admin1_code":"08",
    "gn:admin2_code":"37",
    "gn:admin3_code":"83726000.0",
    "gn:asciiname":"Maulayan",
    "gn:country_code":"PH",
    "gn:dem":78,
    "gn:feature_class":"P",
    "gn:feature_code":"PPL",
    "gn:name":"Maulayan",
    "gn:population":0,
    "gn:timezone":"Asia/Manila",
    "iso:country":"PH",
    "name:eng_x_preferred":[
        "Maulayan"
    ],
    "wof:name":"Maulayan",
    "wof:placetype":"locality"
},
  "geometry": {"coordinates":[124.51179999999999,11.208],"type":"Point"}
}