{
  "type": "Feature",
  "properties": {
    "gn:admin1_code":"12",
    "gn:admin2_code":"71",
    "gn:admin3_code":"126511000.0",
    "gn:asciiname":"San Emmanuel",
    "gn:country_code":"PH",
    "gn:dem":36,
    "gn:feature_class":"P",
    "gn:feature_code":"PPL",
    "gn:name":"San Emmanuel",
    "gn:population":0,
    "gn:timezone":"Asia/Manila",
    "iso:country":"PH",
    "name:fil_x_preferred":[
        "San Manuel"
    ],
    "name:fil_x_variant":[
        "San Emmanuel"
    ],
    "wof:name":"San Emmanuel",
    "wof:placetype":"locality"
},
  "geometry": {"coordinates":[124.70086000000001,6.69528],"type":"Point"}
}