{
  "type": "Feature",
  "properties": {
    "gn:admin1_code":"14",
    "gn:admin2_code":"60",
    "gn:admin3_code":"156603000.0",
    "gn:asciiname":"Kanpagaya",
    "gn:country_code":"PH",
    "gn:dem":145,
    "gn:feature_class":"P",
    "gn:feature_code":"PPL",
    "gn:name":"Kanpagaya",
    "gn:population":0,
    "gn:timezone":"Asia/Manila",
    "iso:country":"PH",
    "name:fil_x_preferred":[
        "Kanpagaya"
    ],
    "wof:name":"Kanpagaya",
    "wof:placetype":"locality"
},
  "geometry": {"coordinates":[121.29528000000001,5.93833],"type":"Point"}
}