{
  "type": "Feature",
  "properties": {
    "gn:country":"PH",
    "gn:fcode":"PPLA3",
    "gn:population":17448,
    "iso:country":"PH",
    "name:bcl_x_preferred":[
        "Murcia"
    ],
    "name:ceb_x_preferred":[
        "Murcia"
    ],
    "name:deu_x_preferred":[
        "Murcia"
    ],
    "name:eng_x_preferred":[
        "Murcia"
    ],
    "name:fil_x_preferred":[
        "Murcia"
    ],
    "name:fra_x_preferred":[
        "Murcia"
    ],
    "name:glg_x_preferred":[
        "Murcia"
    ],
    "name:ilo_x_preferred":[
        "Murcia"
    ],
    "name:ind_x_preferred":[
        "Murcia"
    ],
    "name:ita_x_preferred":[
        "Murcia"
    ],
    "name:lmo_x_preferred":[
        "Murcia"
    ],
    "name:nld_x_preferred":[
        "Murcia"
    ],
    "name:pag_x_preferred":[
        "Murcia"
    ],
    "name:pam_x_preferred":[
        "Murcia"
    ],
    "name:pms_x_preferred":[
        "Murcia"
    ],
    "name:pol_x_preferred":[
        "Murcia"
    ],
    "name:spa_x_preferred":[
        "Murcia"
    ],
    "name:tgl_x_preferred":[
        "Murcia"
    ],
    "name:war_x_preferred":[
        "Murcia"
    ],
    "qs:name":"Murcia",
    "qs:photos_9r":0,
    "qs:photos_sr":0,
    "qs:pop_sr":"6",
    "wof:name":"Murcia",
    "wof:placetype":"locality",
    "wof:population":17448
},
  "geometry": {"coordinates":[123.04170000000001,10.60516],"type":"Point"}
}