{
  "type": "Feature",
  "properties": {
    "gn:admin1_code":"41",
    "gn:admin2_code":"54",
    "gn:admin3_code":"175915000.0",
    "gn:asciiname":"Tabonac",
    "gn:country_code":"PH",
    "gn:dem":17,
    "gn:feature_class":"P",
    "gn:feature_code":"PPL",
    "gn:name":"Tabonac",
    "gn:population":0,
    "gn:timezone":"Asia/Manila",
    "iso:country":"PH",
    "name:fil_x_preferred":[
        "Tabonac"
    ],
    "wof:name":"Tabonac",
    "wof:placetype":"locality"
},
  "geometry": {"coordinates":[122.05710000000001,12.1884],"type":"Point"}
}