{
  "type": "Feature",
  "properties": {
    "gn:admin1_code":"15",
    "gn:admin2_code":"44",
    "gn:admin3_code":"144405000.0",
    "gn:asciiname":"Oboob",
    "gn:country_code":"PH",
    "gn:dem":778,
    "gn:feature_class":"P",
    "gn:feature_code":"PPL",
    "gn:name":"Oboob",
    "gn:population":0,
    "gn:timezone":"Asia/Manila",
    "iso:country":"PH",
    "name:fil_x_preferred":[
        "Oboob"
    ],
    "wof:name":"Oboob",
    "wof:placetype":"locality"
},
  "geometry": {"coordinates":[121.24754,17.07595],"type":"Point"}
}