{
  "type": "Feature",
  "properties": {
    "gn:admin1_code":"41",
    "gn:admin2_code":"49",
    "gn:admin3_code":"175322000.0",
    "gn:asciiname":"Danat",
    "gn:country_code":"PH",
    "gn:dem":19,
    "gn:feature_class":"P",
    "gn:feature_code":"PPL",
    "gn:name":"Danat",
    "gn:population":0,
    "gn:timezone":"Asia/Manila",
    "iso:country":"PH",
    "name:fil_x_preferred":[
        "Danat"
    ],
    "wof:name":"Danat",
    "wof:placetype":"locality"
},
  "geometry": {"coordinates":[119.93611,11.93444],"type":"Point"}
}