{
  "type": "Feature",
  "properties": {
    "gn:admin1_code":"02",
    "gn:admin2_code":"48",
    "gn:admin3_code":"25013000.0",
    "gn:asciiname":"Bangar",
    "gn:country_code":"PH",
    "gn:dem":237,
    "gn:feature_class":"P",
    "gn:feature_code":"PPL",
    "gn:name":"Bangar",
    "gn:population":0,
    "gn:timezone":"Asia/Manila",
    "iso:country":"PH",
    "name:fil_x_preferred":[
        "Bangar"
    ],
    "name:fil_x_variant":[
        "Bangan"
    ],
    "name:und_x_variant":[
        "Bangan"
    ],
    "wof:name":"Bangar",
    "wof:placetype":"locality"
},
  "geometry": {"coordinates":[121.24194,16.54298],"type":"Point"}
}