{
  "type": "Feature",
  "properties": {
    "gn:country":"PH",
    "gn:fcode":"PPL",
    "gn:population":4712,
    "iso:country":"PH",
    "name:bcl_x_preferred":[
        "Pangutaran"
    ],
    "name:ceb_x_preferred":[
        "Pangutaran"
    ],
    "name:deu_x_preferred":[
        "Pangutaran"
    ],
    "name:eng_x_preferred":[
        "Simbahan"
    ],
    "name:eng_x_variant":[
        "Pangutaran"
    ],
    "name:fra_x_preferred":[
        "Pangutaran"
    ],
    "name:ilo_x_preferred":[
        "Pangutaran"
    ],
    "name:ind_x_preferred":[
        "Pangutaran"
    ],
    "name:ita_x_preferred":[
        "Pangutaran"
    ],
    "name:jpn_x_preferred":[
        "\u30d1\u30f3\u30b0\u30bf\u30e9\u30f3"
    ],
    "name:nld_x_preferred":[
        "Pangutaran"
    ],
    "name:pag_x_preferred":[
        "Pangutaran"
    ],
    "name:pam_x_preferred":[
        "Pangutaran"
    ],
    "name:sco_x_preferred":[
        "Pangutaran"
    ],
    "name:swe_x_preferred":[
        "Pangutaran"
    ],
    "name:tgl_x_preferred":[
        "Pangutaran"
    ],
    "name:und_x_variant":[
        "Simbanan"
    ],
    "name:urd_x_preferred":[
        "\u067e\u0627\u0646\u06af\u0648\u062a\u0627\u0631\u0627\u0646\u060c \u0633\u0648\u0644\u0648"
    ],
    "name:urd_x_variant":[
        "\u067e\u0627\u0646\u06af\u0648\u062a\u0627\u0631\u0627\u0646"
    ],
    "name:vie_x_preferred":[
        "Pangutaran"
    ],
    "name:war_x_preferred":[
        "Pangutaran"
    ],
    "qs:name":"Simbahan",
    "qs:photos_9r":0,
    "qs:photos_sr":0,
    "qs:pop_sr":"4",
    "wof:name":"Simbahan",
    "wof:placetype":"locality",
    "wof:population":4712
},
  "geometry": {"coordinates":[120.5836,6.3032],"type":"Point"}
}