{
  "type": "Feature",
  "properties": {
    "gn:admin1_code":"15",
    "gn:admin2_code":"01",
    "gn:admin3_code":"140103000.0",
    "gn:asciiname":"Bugbog",
    "gn:country_code":"PH",
    "gn:dem":199,
    "gn:feature_class":"P",
    "gn:feature_code":"PPL",
    "gn:name":"Bugbog",
    "gn:population":0,
    "gn:timezone":"Asia/Manila",
    "iso:country":"PH",
    "name:fil_x_preferred":[
        "Bugbog"
    ],
    "name:fil_x_variant":[
        "Bugbug"
    ],
    "wof:name":"Bugbog",
    "wof:placetype":"locality"
},
  "geometry": {"coordinates":[120.69629999999999,17.5605],"type":"Point"}
}