{
  "type": "Feature",
  "properties": {
    "gn:admin1_code":"01",
    "gn:admin2_code":"29",
    "gn:admin3_code":"12925000.0",
    "gn:asciiname":"Palali Sur",
    "gn:country_code":"PH",
    "gn:dem":38,
    "gn:feature_class":"P",
    "gn:feature_code":"PPL",
    "gn:name":"Palali Sur",
    "gn:population":0,
    "gn:timezone":"Asia/Manila",
    "iso:country":"PH",
    "name:fil_x_preferred":[
        "Palali Sur"
    ],
    "wof:name":"Palali Sur",
    "wof:placetype":"locality"
},
  "geometry": {"coordinates":[120.48287000000001,17.12511],"type":"Point"}
}