{
  "type": "Feature",
  "properties": {
    "gn:admin1_code":"40",
    "gn:admin2_code":"H2",
    "gn:admin3_code":"45622000.0",
    "gn:asciiname":"Magallanes",
    "gn:country_code":"PH",
    "gn:dem":8,
    "gn:feature_class":"P",
    "gn:feature_code":"PPL",
    "gn:name":"Magallanes",
    "gn:population":0,
    "gn:timezone":"Asia/Manila",
    "iso:country":"PH",
    "name:ceb_x_preferred":[
        "Magallanes"
    ],
    "name:deu_x_preferred":[
        "Magallanes"
    ],
    "name:fil_x_preferred":[
        "Magallanes"
    ],
    "name:fra_x_preferred":[
        "Magallanes"
    ],
    "name:hrv_x_preferred":[
        "Magallanes"
    ],
    "name:ilo_x_preferred":[
        "Magallanes"
    ],
    "name:ita_x_preferred":[
        "Magallanes"
    ],
    "name:nld_x_preferred":[
        "Magallanes"
    ],
    "name:por_x_preferred":[
        "Magallanes"
    ],
    "name:rus_x_preferred":[
        "\u041c\u0430\u0433\u0430\u043b\u044c\u044f\u043d\u0435\u0441"
    ],
    "name:sco_x_preferred":[
        "Magallanes"
    ],
    "name:slk_x_preferred":[
        "Magallanes"
    ],
    "name:spa_x_preferred":[
        "Magallanes"
    ],
    "name:swe_x_preferred":[
        "Magallanes"
    ],
    "name:ukr_x_preferred":[
        "\u041c\u0430\u0433\u0430\u043b\u044c\u044f\u043d\u0435\u0441"
    ],
    "name:war_x_preferred":[
        "Magallanes"
    ],
    "wof:name":"Magallanes",
    "wof:placetype":"locality"
},
  "geometry": {"coordinates":[122.25,13.88333],"type":"Point"}
}