{
  "type": "Feature",
  "properties": {
    "gn:admin1_code":"13",
    "gn:admin2_code":"62",
    "gn:admin3_code":"166817000.0",
    "gn:asciiname":"Batunan",
    "gn:country_code":"PH",
    "gn:dem":26,
    "gn:feature_class":"P",
    "gn:feature_code":"PPL",
    "gn:name":"Batunan",
    "gn:population":0,
    "gn:timezone":"Asia/Manila",
    "iso:country":"PH",
    "name:fil_x_preferred":[
        "Batunan"
    ],
    "wof:name":"Batunan",
    "wof:placetype":"locality"
},
  "geometry": {"coordinates":[126.16388999999999,8.43806],"type":"Point"}
}