{
  "type": "Feature",
  "properties": {
    "gn:admin1_code":"01",
    "gn:admin2_code":"28",
    "gn:admin3_code":"12819000.0",
    "gn:asciiname":"Bulbulala",
    "gn:country_code":"PH",
    "gn:dem":20,
    "gn:feature_class":"P",
    "gn:feature_code":"PPL",
    "gn:name":"Bulbulala",
    "gn:population":0,
    "gn:timezone":"Asia/Manila",
    "iso:country":"PH",
    "name:fil_x_preferred":[
        "Bulbulala"
    ],
    "wof:name":"Bulbulala",
    "wof:placetype":"locality"
},
  "geometry": {"coordinates":[120.5147,17.9502],"type":"Point"}
}