{
  "type": "Feature",
  "properties": {
    "gn:admin1_code":"02",
    "gn:admin2_code":"48",
    "gn:admin3_code":"25013000.0",
    "gn:asciiname":"Curifang",
    "gn:country_code":"PH",
    "gn:dem":243,
    "gn:feature_class":"P",
    "gn:feature_code":"PPL",
    "gn:name":"Curifang",
    "gn:population":0,
    "gn:timezone":"Asia/Manila",
    "iso:country":"PH",
    "name:fil_x_preferred":[
        "Curifang"
    ],
    "name:fil_x_variant":[
        "Curipang"
    ],
    "wof:name":"Curifang",
    "wof:placetype":"locality"
},
  "geometry": {"coordinates":[121.22433999999998,16.51667999999999],"type":"Point"}
}