{
  "type": "Feature",
  "properties": {
    "gn:admin1_code":"07",
    "gn:admin2_code":"21",
    "gn:admin3_code":"72215000.0",
    "gn:asciiname":"Luyang",
    "gn:country_code":"PH",
    "gn:dem":4,
    "gn:feature_class":"P",
    "gn:feature_code":"PPL",
    "gn:name":"Luyang",
    "gn:population":0,
    "gn:timezone":"Asia/Manila",
    "iso:country":"PH",
    "name:fil_x_preferred":[
        "Luyang"
    ],
    "wof:name":"Luyang",
    "wof:placetype":"locality"
},
  "geometry": {"coordinates":[124.02584,10.60253],"type":"Point"}
}