{
  "type": "Feature",
  "properties": {
    "gn:admin1_code":"08",
    "gn:admin2_code":"37",
    "gn:admin3_code":"83740000.0",
    "gn:asciiname":"Sabang",
    "gn:country_code":"PH",
    "gn:dem":6,
    "gn:feature_class":"P",
    "gn:feature_code":"PPL",
    "gn:name":"Sabang",
    "gn:population":0,
    "gn:timezone":"Asia/Manila",
    "iso:country":"PH",
    "name:ceb_x_preferred":[
        "Sabang"
    ],
    "name:fil_x_preferred":[
        "Sabang"
    ],
    "name:fra_x_preferred":[
        "Sabang"
    ],
    "name:swe_x_preferred":[
        "Sabang"
    ],
    "wof:name":"Sabang",
    "wof:placetype":"locality"
},
  "geometry": {"coordinates":[124.38720000000001,11.0777],"type":"Point"}
}