{
  "type": "Feature",
  "properties": {
    "gn:admin1_code":"14",
    "gn:admin2_code":"60",
    "gn:admin3_code":"156611000.0",
    "gn:asciiname":"Lati",
    "gn:country_code":"PH",
    "gn:dem":198,
    "gn:feature_class":"P",
    "gn:feature_code":"PPL",
    "gn:name":"Lati",
    "gn:population":0,
    "gn:timezone":"Asia/Manila",
    "iso:country":"PH",
    "name:ceb_x_preferred":[
        "Lati"
    ],
    "name:fil_x_preferred":[
        "Lati"
    ],
    "name:sco_x_preferred":[
        "Lati"
    ],
    "name:swe_x_preferred":[
        "Lati"
    ],
    "wof:name":"Lati",
    "wof:placetype":"locality"
},
  "geometry": {"coordinates":[121.03361,6.03389],"type":"Point"}
}