{
  "type": "Feature",
  "properties": {
    "gn:admin1_code":"05",
    "gn:admin2_code":"39",
    "gn:admin3_code":"54119000.0",
    "gn:asciiname":"Baguiad",
    "gn:country_code":"PH",
    "gn:dem":23,
    "gn:feature_class":"P",
    "gn:feature_code":"PPL",
    "gn:name":"Baguiad",
    "gn:population":0,
    "gn:timezone":"Asia/Manila",
    "iso:country":"PH",
    "name:fil_x_preferred":[
        "Baguiad"
    ],
    "wof:name":"Baguiad",
    "wof:placetype":"locality"
},
  "geometry": {"coordinates":[123.65519999999999,12.5208],"type":"Point"}
}