{
  "type": "Feature",
  "properties": {
    "gn:admin1_code":"14",
    "gn:admin2_code":"35",
    "gn:admin3_code":"153638000.0",
    "gn:asciiname":"Tagoloan",
    "gn:country_code":"PH",
    "gn:dem":947,
    "gn:feature_class":"P",
    "gn:feature_code":"PPL",
    "gn:name":"Tagoloan",
    "gn:population":0,
    "gn:timezone":"Asia/Manila",
    "iso:country":"PH",
    "name:ceb_x_preferred":[
        "Tagoloan"
    ],
    "name:deu_x_preferred":[
        "Tagoloan"
    ],
    "name:fil_x_preferred":[
        "Tagoloan"
    ],
    "name:fra_x_preferred":[
        "Tagoloan"
    ],
    "name:ita_x_preferred":[
        "Tagoloan"
    ],
    "name:nld_x_preferred":[
        "Tagoloan"
    ],
    "name:war_x_preferred":[
        "Tagoloan"
    ],
    "wof:name":"Tagoloan",
    "wof:placetype":"locality"
},
  "geometry": {"coordinates":[124.45,8.08333],"type":"Point"}
}