{
  "type": "Feature",
  "properties": {
    "gn:country":"PH",
    "gn:fcode":"PPLA3",
    "gn:pop":9957,
    "iso:country":"PH",
    "name:bcl_x_preferred":[
        "Pilar"
    ],
    "name:ceb_x_preferred":[
        "Pilar"
    ],
    "name:deu_x_preferred":[
        "Pilar"
    ],
    "name:eng_x_preferred":[
        "Pilar"
    ],
    "name:fil_x_preferred":[
        "Pilar"
    ],
    "name:fra_x_preferred":[
        "Pilar"
    ],
    "name:ilo_x_preferred":[
        "Pilar"
    ],
    "name:ind_x_preferred":[
        "Pilar"
    ],
    "name:ita_x_preferred":[
        "Pilar"
    ],
    "name:nld_x_preferred":[
        "Pilar"
    ],
    "name:nob_x_preferred":[
        "Pilar"
    ],
    "name:pag_x_preferred":[
        "Pilar"
    ],
    "name:pam_x_preferred":[
        "Pilar"
    ],
    "name:spa_x_preferred":[
        "Pilar"
    ],
    "name:swe_x_preferred":[
        "Pilar"
    ],
    "name:tgl_x_preferred":[
        "Pilar"
    ],
    "name:unk_x_variant":[
        "Pilar Town"
    ],
    "name:vie_x_preferred":[
        "Pilar"
    ],
    "name:war_x_preferred":[
        "Pilar"
    ],
    "qs:name":"Pilar",
    "qs:photos_9r":0,
    "qs:photos_sr":0,
    "qs:pop_sr":"5",
    "wd:wordcount":372,
    "wof:name":"Pilar",
    "wof:placetype":"locality",
    "wof:population":9957
},
  "geometry": {"coordinates":[122.99630000000001,11.487],"type":"Point"}
}