{
  "type": "Feature",
  "properties": {
    "gn:admin1_code":"40",
    "gn:admin2_code":"09",
    "gn:admin3_code":"41034000.0",
    "gn:asciiname":"Tuyon-Tuyon",
    "gn:country_code":"PH",
    "gn:dem":81,
    "gn:feature_class":"P",
    "gn:feature_code":"PPL",
    "gn:name":"Tuyon-Tuyon",
    "gn:population":0,
    "gn:timezone":"Asia/Manila",
    "iso:country":"PH",
    "name:fil_x_preferred":[
        "Tuyon-Tuyon"
    ],
    "wof:name":"Tuyon-Tuyon",
    "wof:placetype":"locality"
},
  "geometry": {"coordinates":[120.7396,14.0118],"type":"Point"}
}