{
  "type": "Feature",
  "properties": {
    "gn:admin1_code":"13",
    "gn:admin2_code":"61",
    "gn:admin3_code":"166706000.0",
    "gn:asciiname":"Cabugo",
    "gn:country_code":"PH",
    "gn:dem":32,
    "gn:feature_class":"P",
    "gn:feature_code":"PPL",
    "gn:name":"Cabugo",
    "gn:population":0,
    "gn:timezone":"Asia/Manila",
    "iso:country":"PH",
    "name:fil_x_preferred":[
        "Cabugo"
    ],
    "wof:name":"Cabugo",
    "wof:placetype":"locality"
},
  "geometry": {"coordinates":[125.76582999999999,9.5475],"type":"Point"}
}