{
  "type": "Feature",
  "properties": {
    "gn:admin1_code":"14",
    "gn:admin2_code":"60",
    "gn:admin3_code":"156613000.0",
    "gn:asciiname":"Gamay",
    "gn:country_code":"PH",
    "gn:dem":84,
    "gn:feature_class":"P",
    "gn:feature_code":"PPL",
    "gn:name":"Gamay",
    "gn:population":0,
    "gn:timezone":"Asia/Manila",
    "iso:country":"PH",
    "name:bul_x_preferred":[
        "\u0413\u0430\u043c\u0435 \u043d\u043e\u0430\u0440"
    ],
    "name:cat_x_preferred":[
        "Gamay"
    ],
    "name:chv_x_preferred":[
        "\u0413\u0430\u043c\u044d"
    ],
    "name:deu_x_preferred":[
        "Gamay"
    ],
    "name:fil_x_preferred":[
        "Gamay"
    ],
    "name:fin_x_preferred":[
        "Gamay"
    ],
    "name:fra_x_preferred":[
        "Gamay"
    ],
    "name:hrv_x_preferred":[
        "Borgonja"
    ],
    "name:ita_x_preferred":[
        "Gamay"
    ],
    "name:ltz_x_preferred":[
        "Gamay"
    ],
    "name:nld_x_preferred":[
        "Gamay noir"
    ],
    "name:nor_x_preferred":[
        "Gamay"
    ],
    "name:pcd_x_preferred":[
        "Gamay"
    ],
    "name:pol_x_preferred":[
        "Gamay"
    ],
    "name:por_x_preferred":[
        "Gamay"
    ],
    "name:ron_x_preferred":[
        "Gamay"
    ],
    "name:rus_x_preferred":[
        "\u0413\u0430\u043c\u0435"
    ],
    "name:scn_x_preferred":[
        "Gamay"
    ],
    "name:spa_x_preferred":[
        "Gamay"
    ],
    "name:swe_x_preferred":[
        "Gamay"
    ],
    "wof:name":"Gamay",
    "wof:placetype":"locality"
},
  "geometry": {"coordinates":[121.14594,5.97482],"type":"Point"}
}