{
  "type": "Feature",
  "properties": {
    "gn:country":"PH",
    "gn:fcode":"ADM3",
    "gn:population":31244,
    "iso:country":"PH",
    "name:fil_x_preferred":[
        "Buldon"
    ],
    "qs:name":"Buldon",
    "qs:photos_9r":0,
    "qs:photos_sr":0,
    "qs:pop_sr":"7",
    "wof:name":"Buldon",
    "wof:placetype":"localadmin",
    "wof:population":31244
},
  "geometry": {"coordinates":[124.45,7.55],"type":"Point"}
}