{
  "type": "Feature",
  "properties": {
    "gn:admin1_code":"14",
    "gn:admin2_code":"22",
    "gn:admin3_code":"150706000.0",
    "gn:asciiname":"Dangkalan",
    "gn:country_code":"PH",
    "gn:dem":27,
    "gn:feature_class":"P",
    "gn:feature_code":"PPL",
    "gn:name":"Dangkalan",
    "gn:population":0,
    "gn:timezone":"Asia/Manila",
    "iso:country":"PH",
    "name:fil_x_preferred":[
        "Dangkalan"
    ],
    "wof:name":"Dangkalan",
    "wof:placetype":"locality"
},
  "geometry": {"coordinates":[122.20222,6.54611],"type":"Point"}
}