{
  "type": "Feature",
  "properties": {
    "gn:admin1_code":"03",
    "gn:admin2_code":"64",
    "gn:admin3_code":"37105000.0",
    "gn:asciiname":"Dampay",
    "gn:country_code":"PH",
    "gn:dem":13,
    "gn:feature_class":"P",
    "gn:feature_code":"PPL",
    "gn:name":"Dampay",
    "gn:population":0,
    "gn:timezone":"Asia/Manila",
    "iso:country":"PH",
    "name:fil_x_preferred":[
        "Dampay"
    ],
    "wof:name":"Dampay",
    "wof:placetype":"locality"
},
  "geometry": {"coordinates":[119.9602,15.3733],"type":"Point"}
}