{
  "type": "Feature",
  "properties": {
    "gn:admin1_code":"05",
    "gn:admin2_code":"16",
    "gn:admin3_code":"51718000.0",
    "gn:asciiname":"Jandig",
    "gn:country_code":"PH",
    "gn:dem":34,
    "gn:feature_class":"P",
    "gn:feature_code":"PPL",
    "gn:name":"Jandig",
    "gn:population":0,
    "gn:timezone":"Asia/Manila",
    "iso:country":"PH",
    "name:fil_x_preferred":[
        "Jandig"
    ],
    "wof:name":"Jandig",
    "wof:placetype":"locality"
},
  "geometry": {"coordinates":[123.01667,13.75],"type":"Point"}
}