{
  "type": "Feature",
  "properties": {
    "gn:admin1_code":"08",
    "gn:admin2_code":"37",
    "gn:admin3_code":"83740000.0",
    "gn:asciiname":"Saay",
    "gn:country_code":"PH",
    "gn:dem":212,
    "gn:feature_class":"P",
    "gn:feature_code":"PPL",
    "gn:name":"Saay",
    "gn:population":0,
    "gn:timezone":"Asia/Manila",
    "iso:country":"PH",
    "name:fil_x_preferred":[
        "Saay"
    ],
    "wof:name":"Saay",
    "wof:placetype":"locality"
},
  "geometry": {"coordinates":[124.43333,11.11667],"type":"Point"}
}