{
  "type": "Feature",
  "properties": {
    "gn:admin1_code":"05",
    "gn:admin2_code":"05",
    "gn:admin3_code":"50506000.0",
    "gn:asciiname":"Lamba",
    "gn:country_code":"PH",
    "gn:dem":21,
    "gn:feature_class":"P",
    "gn:feature_code":"PPL",
    "gn:name":"Lamba",
    "gn:population":0,
    "gn:timezone":"Asia/Manila",
    "iso:country":"PH",
    "name:ceb_x_preferred":[
        "Lamba"
    ],
    "name:deu_x_preferred":[
        "Lamba"
    ],
    "name:fil_x_preferred":[
        "Lamba"
    ],
    "name:fra_x_preferred":[
        "Lamba"
    ],
    "name:hye_x_preferred":[
        "\u053c\u0561\u0574\u0562\u0561"
    ],
    "name:nld_x_preferred":[
        "Lamba"
    ],
    "name:nor_x_preferred":[
        "Lamba"
    ],
    "name:rus_x_preferred":[
        "\u041b\u0430\u043c\u0431\u0430"
    ],
    "name:swe_x_preferred":[
        "Lamba"
    ],
    "name:tur_x_preferred":[
        "Lamba"
    ],
    "name:ukr_x_preferred":[
        "\u041b\u0430\u043c\u0431\u0430"
    ],
    "wof:name":"Lamba",
    "wof:placetype":"locality"
},
  "geometry": {"coordinates":[123.7664,13.1284],"type":"Point"}
}