{
  "type": "Feature",
  "properties": {
    "gn:admin1_code":"05",
    "gn:admin2_code":"05",
    "gn:admin3_code":"50506000.0",
    "gn:asciiname":"Lamba",
    "gn:country_code":"PH",
    "gn:dem":21,
    "gn:feature_class":"P",
    "gn:feature_code":"PPL",
    "gn:name":"Lamba",
    "gn:population":0,
    "gn:timezone":"Asia/Manila",
    "iso:country":"PH",
    "name:fil_x_preferred":[
        "Lamba"
    ],
    "wof:name":"Lamba",
    "wof:placetype":"locality"
},
  "geometry": {"coordinates":[123.7664,13.1284],"type":"Point"}
}