{
  "type": "Feature",
  "properties": {
    "gn:admin1_code":"08",
    "gn:admin2_code":"23",
    "gn:admin3_code":"82617000.0",
    "gn:asciiname":"Bato",
    "gn:country_code":"PH",
    "gn:dem":3,
    "gn:feature_class":"P",
    "gn:feature_code":"PPL",
    "gn:name":"Bato",
    "gn:population":0,
    "gn:timezone":"Asia/Manila",
    "iso:country":"PH",
    "name:fil_x_preferred":[
        "Bato"
    ],
    "wof:name":"Bato",
    "wof:placetype":"locality"
},
  "geometry": {"coordinates":[125.3254,12.2299],"type":"Point"}
}