{
  "type": "Feature",
  "properties": {
    "gn:admin1_code":"40",
    "gn:admin2_code":"H2",
    "gn:admin3_code":"45630000.0",
    "gn:asciiname":"Ikirin",
    "gn:country_code":"PH",
    "gn:dem":28,
    "gn:feature_class":"P",
    "gn:feature_code":"PPL",
    "gn:name":"Ikirin",
    "gn:population":0,
    "gn:timezone":"Asia/Manila",
    "iso:country":"PH",
    "name:fil_x_preferred":[
        "Ikirin"
    ],
    "wof:name":"Ikirin",
    "wof:placetype":"locality"
},
  "geometry": {"coordinates":[121.68333,13.96667],"type":"Point"}
}