{
  "type": "Feature",
  "properties": {
    "gn:admin1_code":"05",
    "gn:admin2_code":"16",
    "gn:admin3_code":"51727000.0",
    "gn:asciiname":"Bical",
    "gn:country_code":"PH",
    "gn:dem":16,
    "gn:feature_class":"P",
    "gn:feature_code":"PPL",
    "gn:name":"Bical",
    "gn:population":0,
    "gn:timezone":"Asia/Manila",
    "iso:country":"PH",
    "name:fil_x_preferred":[
        "Bical"
    ],
    "name:und_x_variant":[
        "Bikal",
        "Vical"
    ],
    "wof:name":"Bical",
    "wof:placetype":"locality"
},
  "geometry": {"coordinates":[122.9063,13.5972],"type":"Point"}
}