{
  "type": "Feature",
  "properties": {
    "gn:admin1_code":"01",
    "gn:admin2_code":"29",
    "gn:admin3_code":"12934000.0",
    "gn:asciiname":"Capangpangan",
    "gn:country_code":"PH",
    "gn:dem":11,
    "gn:feature_class":"P",
    "gn:feature_code":"PPL",
    "gn:name":"Capangpangan",
    "gn:population":0,
    "gn:timezone":"Asia/Manila",
    "iso:country":"PH",
    "name:fil_x_preferred":[
        "Capangpangan"
    ],
    "wof:name":"Capangpangan",
    "wof:placetype":"locality"
},
  "geometry": {"coordinates":[120.40028,17.57505],"type":"Point"}
}