{
  "type": "Feature",
  "properties": {
    "gn:admin1_code":"41",
    "gn:admin2_code":"49",
    "gn:admin3_code":"175309000.0",
    "gn:asciiname":"Ducol",
    "gn:country_code":"PH",
    "gn:dem":5,
    "gn:feature_class":"P",
    "gn:feature_code":"PPL",
    "gn:name":"Ducol",
    "gn:population":0,
    "gn:timezone":"Asia/Manila",
    "iso:country":"PH",
    "name:eng_x_preferred":[
        "Ducol"
    ],
    "wof:name":"Ducol",
    "wof:placetype":"locality"
},
  "geometry": {"coordinates":[120.2461,12.1296],"type":"Point"}
}