{
  "type": "Feature",
  "properties": {
    "gn:admin1_code":"03",
    "gn:admin2_code":"47",
    "gn:admin3_code":"34906000.0",
    "gn:asciiname":"Calancuasan Sur",
    "gn:country_code":"PH",
    "gn:dem":25,
    "gn:feature_class":"P",
    "gn:feature_code":"PPL",
    "gn:name":"Calancuasan Sur",
    "gn:population":0,
    "gn:timezone":"Asia/Manila",
    "iso:country":"PH",
    "name:und_x_variant":[
        "Calancuasan",
        "Calancuasan Sur"
    ],
    "wof:name":"Calancuasan Sur",
    "wof:placetype":"locality"
},
  "geometry": {"coordinates":[120.63482,15.79067],"type":"Point"}
}