{
  "type": "Feature",
  "properties": {
    "gn:admin1_code":"14",
    "gn:admin2_code":"22",
    "gn:admin3_code":"150707000.0",
    "gn:asciiname":"Luuk",
    "gn:country_code":"PH",
    "gn:dem":13,
    "gn:feature_class":"P",
    "gn:feature_code":"PPL",
    "gn:name":"Luuk",
    "gn:population":0,
    "gn:timezone":"Asia/Manila",
    "iso:country":"PH",
    "name:fil_x_preferred":[
        "Luuk"
    ],
    "wof:name":"Luuk",
    "wof:placetype":"locality"
},
  "geometry": {"coordinates":[122.24917000000001,6.59639],"type":"Point"}
}