{
  "type": "Feature",
  "properties": {
    "gn:admin1_code":"06",
    "gn:admin2_code":"06",
    "gn:admin3_code":"60607000.0",
    "gn:asciiname":"Opsan",
    "gn:country_code":"PH",
    "gn:dem":100,
    "gn:feature_class":"P",
    "gn:feature_code":"PPL",
    "gn:name":"Opsan",
    "gn:population":0,
    "gn:timezone":"Asia/Manila",
    "iso:country":"PH",
    "name:fil_x_preferred":[
        "Opsan"
    ],
    "name:und_x_variant":[
        "Ouanan"
    ],
    "wof:name":"Opsan",
    "wof:placetype":"locality"
},
  "geometry": {"coordinates":[121.9731,10.5012],"type":"Point"}
}