{
  "type": "Feature",
  "properties": {
    "gn:country":"PH",
    "gn:fcode":"ADM3",
    "gn:population":0,
    "iso:country":"PH",
    "name:fil_x_preferred":[
        "Sagay City"
    ],
    "name:fil_x_variant":[
        "Sagay"
    ],
    "qs:name":"Sagay City",
    "qs:photos_9r":0,
    "qs:photos_sr":0,
    "qs:pop_sr":"0",
    "wof:name":"Sagay City",
    "wof:placetype":"localadmin",
    "wof:population":0
},
  "geometry": {"coordinates":[123.38333,10.86667],"type":"Point"}
}