{
  "type": "Feature",
  "properties": {
    "gn:admin1_code":"11",
    "gn:admin2_code":"P3",
    "gn:admin3_code":"118604000.0",
    "gn:asciiname":"Basiawan",
    "gn:country_code":"PH",
    "gn:dem":31,
    "gn:feature_class":"P",
    "gn:feature_code":"PPL",
    "gn:name":"Basiawan",
    "gn:population":0,
    "gn:timezone":"Asia/Manila",
    "iso:country":"PH",
    "name:fil_x_preferred":[
        "Basiawan"
    ],
    "name:und_x_variant":[
        "Dool",
        "Basiauan",
        "Baslawan"
    ],
    "wof:name":"Basiawan",
    "wof:placetype":"locality"
},
  "geometry": {"coordinates":[125.50833,6.50944],"type":"Point"}
}