{
  "type": "Feature",
  "properties": {
    "gn:admin1_code":"40",
    "gn:admin2_code":"H2",
    "gn:admin3_code":"45646000.0",
    "gn:asciiname":"Katimo",
    "gn:country_code":"PH",
    "gn:dem":14,
    "gn:feature_class":"P",
    "gn:feature_code":"PPL",
    "gn:name":"Katimo",
    "gn:population":0,
    "gn:timezone":"Asia/Manila",
    "iso:country":"PH",
    "name:fil_x_preferred":[
        "Katimo"
    ],
    "wof:name":"Katimo",
    "wof:placetype":"locality"
},
  "geometry": {"coordinates":[122.44799999999999,13.9408],"type":"Point"}
}