{
  "type": "Feature",
  "properties": {
    "gn:gn_country":"PH",
    "gn:gn_fcode":"ADM3",
    "gn:gn_pop":34888,
    "gn:population":34888,
    "iso:country":"PH",
    "name:fil_x_preferred":[
        "Gonzaga"
    ],
    "qs_pg:aaroncc":"PH",
    "qs_pg:gn_country":"PH",
    "qs_pg:gn_fcode":"ADM3",
    "qs_pg:gn_pop":34888,
    "qs_pg:name":"Gonzaga",
    "qs_pg:photos_9r":0,
    "qs_pg:photos_sr":0,
    "qs_pg:pop_sr":7,
    "qs_pg:qs_pg_placetype":"localadmin",
    "wof:name":"Gonzaga",
    "wof:placetype":"localadmin",
    "wof:population":34888
},
  "geometry": {"coordinates":[122.11667,18.28333],"type":"Point"}
}