{
  "type": "Feature",
  "properties": {
    "gn:country":"PH",
    "gn:fcode":"ADM3",
    "gn:population":34888,
    "iso:country":"PH",
    "name:bel_x_preferred":[
        "\u0413\u0430\u043d\u0437\u0430\u0433\u0430"
    ],
    "name:bre_x_preferred":[
        "Gonzaga"
    ],
    "name:cat_x_preferred":[
        "Gonzaga"
    ],
    "name:ceb_x_preferred":[
        "Gonzaga"
    ],
    "name:ces_x_preferred":[
        "Gonzaga"
    ],
    "name:deu_x_preferred":[
        "Gonzaga"
    ],
    "name:epo_x_preferred":[
        "Gonzaga"
    ],
    "name:fil_x_preferred":[
        "Gonzaga"
    ],
    "name:fra_x_preferred":[
        "Gonzaga"
    ],
    "name:heb_x_preferred":[
        "\u05d2\u05d5\u05e0\u05d6\u05d2\u05d4"
    ],
    "name:ind_x_preferred":[
        "Gonzaga"
    ],
    "name:ita_x_preferred":[
        "Gonzaga"
    ],
    "name:kat_x_preferred":[
        "\u10d2\u10dd\u10dc\u10eb\u10d0\u10d2\u10d0"
    ],
    "name:lat_x_preferred":[
        "Gonzaga"
    ],
    "name:nld_x_preferred":[
        "Gonzaga"
    ],
    "name:por_x_preferred":[
        "Gonzaga"
    ],
    "name:ron_x_preferred":[
        "Gonzaga"
    ],
    "name:rus_x_preferred":[
        "\u0413\u043e\u043d\u0437\u0430\u0433\u0430"
    ],
    "name:spa_x_preferred":[
        "Gonzaga"
    ],
    "name:swe_x_preferred":[
        "Gonzaga"
    ],
    "name:ukr_x_preferred":[
        "\u0413\u043e\u043d\u0437\u0430\u0433\u0430"
    ],
    "name:vol_x_preferred":[
        "Gonzaga"
    ],
    "name:war_x_preferred":[
        "Gonzaga"
    ],
    "qs_pg:aaroncc":"PH",
    "qs_pg:gn_country":"PH",
    "qs_pg:gn_fcode":"ADM3",
    "qs_pg:gn_pop":34888,
    "qs_pg:name":"Gonzaga",
    "qs_pg:photos_9r":0,
    "qs_pg:photos_sr":0,
    "qs_pg:pop_sr":7,
    "qs_pg:qs_pg_placetype":"localadmin",
    "wof:name":"Gonzaga",
    "wof:placetype":"localadmin",
    "wof:population":34888
},
  "geometry": {"coordinates":[122.11667,18.28333],"type":"Point"}
}