{
  "type": "Feature",
  "properties": {
    "gn:admin1_code":"02",
    "gn:admin2_code":"48",
    "gn:admin3_code":"25005000.0",
    "gn:asciiname":"Magsayssay",
    "gn:country_code":"PH",
    "gn:dem":279,
    "gn:feature_class":"P",
    "gn:feature_code":"PPL",
    "gn:name":"Magsayssay",
    "gn:population":0,
    "gn:timezone":"Asia/Manila",
    "iso:country":"PH",
    "name:fil_x_preferred":[
        "Magsayssay"
    ],
    "wof:name":"Magsayssay",
    "wof:placetype":"locality"
},
  "geometry": {"coordinates":[121.1422,16.4887],"type":"Point"}
}