{
  "type": "Feature",
  "properties": {
    "gn:admin1_code":"12",
    "gn:admin2_code":"57",
    "gn:admin3_code":"124705000.0",
    "gn:asciiname":"Matama",
    "gn:cc2":"PH",
    "gn:country_code":"PH",
    "gn:dem":110,
    "gn:feature_class":"P",
    "gn:feature_code":"PPL",
    "gn:name":"Matama",
    "gn:population":0,
    "gn:timezone":"Asia/Manila",
    "iso:country":"PH",
    "name:und_x_variant":[
        "Matania",
        "Matama"
    ],
    "wof:name":"Matama",
    "wof:placetype":"locality"
},
  "geometry": {"coordinates":[124.54028,7.305],"type":"Point"}
}