{
  "type": "Feature",
  "properties": {
    "gn:admin1_code":"02",
    "gn:admin2_code":"68",
    "gn:admin3_code":"25706000.0",
    "gn:asciiname":"Cagadiagan",
    "gn:country_code":"PH",
    "gn:dem":187,
    "gn:feature_class":"P",
    "gn:feature_code":"PPL",
    "gn:name":"Cagadiagan",
    "gn:population":0,
    "gn:timezone":"Asia/Manila",
    "iso:country":"PH",
    "name:fil_x_preferred":[
        "Cagadiagan"
    ],
    "wof:name":"Cagadiagan",
    "wof:placetype":"locality"
},
  "geometry": {"coordinates":[121.65139000000001,16.23082999999999],"type":"Point"}
}