{
  "type": "Feature",
  "properties": {
    "gn:admin1_code":"02",
    "gn:admin2_code":"14",
    "gn:admin3_code":"21504000.0",
    "gn:asciiname":"Calintaan",
    "gn:country_code":"PH",
    "gn:dem":16,
    "gn:feature_class":"P",
    "gn:feature_code":"PPL",
    "gn:name":"Calintaan",
    "gn:population":0,
    "gn:timezone":"Asia/Manila",
    "iso:country":"PH",
    "name:fil_x_preferred":[
        "Calintaan"
    ],
    "wof:name":"Calintaan",
    "wof:placetype":"locality"
},
  "geometry": {"coordinates":[121.62860999999999,17.79298],"type":"Point"}
}