{
  "type": "Feature",
  "properties": {
    "gn:admin1_code":"02",
    "gn:admin2_code":"14",
    "gn:admin3_code":"21504000.0",
    "gn:asciiname":"Calintaan",
    "gn:country_code":"PH",
    "gn:dem":16,
    "gn:feature_class":"P",
    "gn:feature_code":"PPL",
    "gn:name":"Calintaan",
    "gn:population":0,
    "gn:timezone":"Asia/Manila",
    "iso:country":"PH",
    "name:bcl_x_preferred":[
        "Calintaan"
    ],
    "name:ceb_x_preferred":[
        "Calintaan"
    ],
    "name:deu_x_preferred":[
        "Calintaan"
    ],
    "name:fil_x_preferred":[
        "Calintaan"
    ],
    "name:ilo_x_preferred":[
        "Calintaan"
    ],
    "name:ind_x_preferred":[
        "Calintaan"
    ],
    "name:ita_x_preferred":[
        "Calintaan"
    ],
    "name:nld_x_preferred":[
        "Calintaan"
    ],
    "name:pag_x_preferred":[
        "Calintaan"
    ],
    "name:pam_x_preferred":[
        "Calintaan"
    ],
    "name:spa_x_preferred":[
        "Calinta\u00e1n"
    ],
    "name:swe_x_preferred":[
        "Calintaan"
    ],
    "name:tgl_x_preferred":[
        "Calintaan"
    ],
    "name:vie_x_preferred":[
        "Calintaan"
    ],
    "name:war_x_preferred":[
        "Calintaan"
    ],
    "wof:name":"Calintaan",
    "wof:placetype":"locality"
},
  "geometry": {"coordinates":[121.62860999999999,17.79298],"type":"Point"}
}