{
  "type": "Feature",
  "properties": {
    "gn:admin1_code":"01",
    "gn:admin2_code":"36",
    "gn:admin3_code":"13315000.0",
    "gn:asciiname":"Lon-oy",
    "gn:cc2":"PH",
    "gn:country_code":"PH",
    "gn:dem":278,
    "gn:feature_class":"P",
    "gn:feature_code":"PPL",
    "gn:name":"Lon-oy",
    "gn:population":0,
    "gn:timezone":"Asia/Manila",
    "iso:country":"PH",
    "name:und_x_variant":[
        "Lunoy",
        "Lon-oy"
    ],
    "wof:name":"Lon-oy",
    "wof:placetype":"locality"
},
  "geometry": {"coordinates":[120.49167,16.69639],"type":"Point"}
}