{
  "type": "Feature",
  "properties": {
    "gn:admin1_code":"05",
    "gn:admin2_code":"16",
    "gn:admin3_code":"51718000.0",
    "gn:asciiname":"Mambato",
    "gn:country_code":"PH",
    "gn:dem":171,
    "gn:feature_class":"P",
    "gn:feature_code":"PPL",
    "gn:name":"Mambato",
    "gn:population":0,
    "gn:timezone":"Asia/Manila",
    "iso:country":"PH",
    "name:fil_x_preferred":[
        "Mambato"
    ],
    "wof:name":"Mambato",
    "wof:placetype":"locality"
},
  "geometry": {"coordinates":[122.91079999999999,13.6811],"type":"Point"}
}