{
  "type": "Feature",
  "properties": {
    "gn:admin1_code":"01",
    "gn:admin2_code":"51",
    "gn:admin3_code":"15527000.0",
    "gn:asciiname":"Dorongan Valerio",
    "gn:country_code":"PH",
    "gn:dem":17,
    "gn:feature_class":"P",
    "gn:feature_code":"PPL",
    "gn:name":"Dorongan Valerio",
    "gn:population":0,
    "gn:timezone":"Asia/Manila",
    "iso:country":"PH",
    "wof:name":"Dorongan Valerio",
    "wof:placetype":"locality"
},
  "geometry": {"coordinates":[120.31185000000001,15.82254],"type":"Point"}
}