{
  "type": "Feature",
  "properties": {
    "gn:admin1_code":"07",
    "gn:admin2_code":"46",
    "gn:admin3_code":"74604000.0",
    "gn:asciiname":"Rotea",
    "gn:country_code":"PH",
    "gn:dem":2,
    "gn:feature_class":"P",
    "gn:feature_code":"PPL",
    "gn:name":"Rotea",
    "gn:population":0,
    "gn:timezone":"Asia/Manila",
    "iso:country":"PH",
    "name:fil_x_preferred":[
        "Rotea"
    ],
    "wof:name":"Rotea",
    "wof:placetype":"locality"
},
  "geometry": {"coordinates":[123.1198,9.603],"type":"Point"}
}