{
  "type": "Feature",
  "properties": {
    "gn:country":"PH",
    "gn:fcode":"PPL",
    "gn:population":2089,
    "iso:country":"PH",
    "name:fil_x_preferred":[
        "Pagsanahgn"
    ],
    "name:fil_x_variant":[
        "Pagsana-an"
    ],
    "qs:name":"Pagsanahan Norte",
    "qs:photos_9r":0,
    "qs:photos_sr":0,
    "qs:pop_sr":"4",
    "wof:name":"Pagsanahan Norte",
    "wof:placetype":"locality",
    "wof:population":2089
},
  "geometry": {"coordinates":[120.44580000000001,17.9193],"type":"Point"}
}