{
  "type": "Feature",
  "properties": {
    "gn:admin1_code":"15",
    "gn:admin2_code":"10",
    "gn:admin3_code":"141101000.0",
    "gn:asciiname":"Patapat",
    "gn:country_code":"PH",
    "gn:dem":1925,
    "gn:feature_class":"P",
    "gn:feature_code":"PPL",
    "gn:name":"Patapat",
    "gn:population":0,
    "gn:timezone":"Asia/Manila",
    "iso:country":"PH",
    "name:fil_x_preferred":[
        "Patapat"
    ],
    "wof:name":"Patapat",
    "wof:placetype":"locality"
},
  "geometry": {"coordinates":[120.7257,16.5508],"type":"Point"}
}