{
  "type": "Feature",
  "properties": {
    "gn:admin1_code":"06",
    "gn:admin2_code":"30",
    "gn:admin3_code":"63032000.0",
    "gn:asciiname":"Baulan",
    "gn:country_code":"PH",
    "gn:dem":30,
    "gn:feature_class":"P",
    "gn:feature_code":"PPL",
    "gn:name":"Baulan",
    "gn:population":0,
    "gn:timezone":"Asia/Manila",
    "iso:country":"PH",
    "name:fil_x_preferred":[
        "Baulan"
    ],
    "wof:name":"Baulan",
    "wof:placetype":"locality"
},
  "geometry": {"coordinates":[122.5804,10.8909],"type":"Point"}
}