{
  "type": "Feature",
  "properties": {
    "gn:admin1_code":"41",
    "gn:admin2_code":"49",
    "gn:asciiname":"Idoc-Idoc",
    "gn:country_code":"PH",
    "gn:dem":25,
    "gn:feature_class":"P",
    "gn:feature_code":"PPL",
    "gn:name":"Idoc-Idoc",
    "gn:population":0,
    "gn:timezone":"Asia/Manila",
    "iso:country":"PH",
    "name:eng_x_preferred":[
        "Idoc-Idoc"
    ],
    "wof:name":"Idoc-Idoc",
    "wof:placetype":"locality"
},
  "geometry": {"coordinates":[118.45010000000001,6.9861],"type":"Point"}
}