{
  "type": "Feature",
  "properties": {
    "gn:admin1_code":"09",
    "gn:admin2_code":"ZSI",
    "gn:admin3_code":"98313000.0",
    "gn:asciiname":"Laih",
    "gn:country_code":"PH",
    "gn:dem":36,
    "gn:feature_class":"P",
    "gn:feature_code":"PPL",
    "gn:name":"Laih",
    "gn:population":0,
    "gn:timezone":"Asia/Manila",
    "iso:country":"PH",
    "name:fil_x_preferred":[
        "Laih"
    ],
    "wof:name":"Laih",
    "wof:placetype":"locality"
},
  "geometry": {"coordinates":[122.82693999999999,7.73972],"type":"Point"}
}