{
  "type": "Feature",
  "properties": {
    "gn:admin1_code":"03",
    "gn:admin2_code":"47",
    "gn:admin3_code":"34918000.0",
    "gn:asciiname":"Edy",
    "gn:country_code":"PH",
    "gn:dem":23,
    "gn:feature_class":"P",
    "gn:feature_code":"PPL",
    "gn:name":"Edy",
    "gn:population":0,
    "gn:timezone":"Asia/Manila",
    "iso:country":"PH",
    "name:fil_x_preferred":[
        "Edy"
    ],
    "name:jpn_x_preferred":[
        "\u697d\u5929Edy"
    ],
    "name:kor_x_preferred":[
        "Edy"
    ],
    "name:por_x_preferred":[
        "Edy"
    ],
    "name:spa_x_preferred":[
        "Edy"
    ],
    "name:zho_x_preferred":[
        "Edy"
    ],
    "wof:name":"Edy",
    "wof:placetype":"locality"
},
  "geometry": {"coordinates":[120.65430000000001,15.7002],"type":"Point"}
}