{
  "type": "Feature",
  "properties": {
    "gn:admin1_code":"01",
    "gn:admin2_code":"51",
    "gn:admin3_code":"15527000.0",
    "gn:asciiname":"Bueno",
    "gn:country_code":"PH",
    "gn:dem":22,
    "gn:feature_class":"P",
    "gn:feature_code":"PPL",
    "gn:name":"Bueno",
    "gn:population":0,
    "gn:timezone":"Asia/Manila",
    "iso:country":"PH",
    "name:deu_x_preferred":[
        "Bueno"
    ],
    "name:fil_x_preferred":[
        "Bueno"
    ],
    "name:fra_x_preferred":[
        "Bueno"
    ],
    "name:heb_x_preferred":[
        "\u05d1\u05d5\u05d0\u05e0\u05d5"
    ],
    "name:ita_x_preferred":[
        "Bueno"
    ],
    "name:jpn_x_preferred":[
        "\u30d6\u30a8\u30ce"
    ],
    "name:por_x_preferred":[
        "Bueno"
    ],
    "name:spa_x_preferred":[
        "Bueno"
    ],
    "wof:name":"Bueno",
    "wof:placetype":"locality"
},
  "geometry": {"coordinates":[120.30646000000002,15.78029],"type":"Point"}
}