{
  "type": "Feature",
  "properties": {
    "gn:country":"PH",
    "gn:fcode":"PPL",
    "gn:population":2907,
    "iso:country":"PH",
    "name:fil_x_preferred":[
        "Tagcatong"
    ],
    "qs:name":"Tagcatong",
    "qs:photos_9r":0,
    "qs:photos_sr":0,
    "qs:pop_sr":"4",
    "wof:name":"Tagcatong",
    "wof:placetype":"locality",
    "wof:population":2907
},
  "geometry": {"coordinates":[125.25694,9.00222],"type":"Point"}
}