{
  "type": "Feature",
  "properties": {
    "gn:admin1_code":"40",
    "gn:admin2_code":"H2",
    "gn:asciiname":"Payasan",
    "gn:country_code":"PH",
    "gn:dem":213,
    "gn:feature_class":"P",
    "gn:feature_code":"PPL",
    "gn:name":"Payasan",
    "gn:population":0,
    "gn:timezone":"Asia/Manila",
    "iso:country":"PH",
    "name:fil_x_preferred":[
        "Payasan"
    ],
    "wof:name":"Payasan",
    "wof:placetype":"locality"
},
  "geometry": {"coordinates":[121.96666999999999,13.23333],"type":"Point"}
}