{
  "type": "Feature",
  "properties": {
    "gn:admin1_code":"02",
    "gn:admin2_code":"14",
    "gn:admin3_code":"21508000.0",
    "gn:asciiname":"Cabaritan",
    "gn:country_code":"PH",
    "gn:dem":8,
    "gn:feature_class":"P",
    "gn:feature_code":"PPL",
    "gn:name":"Cabaritan",
    "gn:population":0,
    "gn:timezone":"Asia/Manila",
    "iso:country":"PH",
    "name:fil_x_preferred":[
        "Cabaritan"
    ],
    "wof:name":"Cabaritan",
    "wof:placetype":"locality"
},
  "geometry": {"coordinates":[121.82741,18.28958],"type":"Point"}
}