{
  "type": "Feature",
  "properties": {
    "gn:admin1_code":"07",
    "gn:admin2_code":"46",
    "gn:admin3_code":"74612000.0",
    "gn:asciiname":"Apanangon",
    "gn:country_code":"PH",
    "gn:dem":634,
    "gn:feature_class":"P",
    "gn:feature_code":"PPL",
    "gn:name":"Apanangon",
    "gn:population":0,
    "gn:timezone":"Asia/Manila",
    "iso:country":"PH",
    "name:fil_x_preferred":[
        "Apanangon"
    ],
    "wof:name":"Apanangon",
    "wof:placetype":"locality"
},
  "geometry": {"coordinates":[123.11667,10.03333],"type":"Point"}
}