{
  "type": "Feature",
  "properties": {
    "gn:admin1_code":"06",
    "gn:admin2_code":"06",
    "gn:admin3_code":"60607000.0",
    "gn:asciiname":"Danawan",
    "gn:country_code":"PH",
    "gn:dem":320,
    "gn:feature_class":"P",
    "gn:feature_code":"PPL",
    "gn:name":"Danawan",
    "gn:population":0,
    "gn:timezone":"Asia/Manila",
    "iso:country":"PH",
    "name:fil_x_preferred":[
        "Danawan"
    ],
    "name:und_x_variant":[
        "Danauan"
    ],
    "wof:name":"Danawan",
    "wof:placetype":"locality"
},
  "geometry": {"coordinates":[121.9764,10.4834],"type":"Point"}
}