{
  "type": "Feature",
  "properties": {
    "gn:admin1_code":"40",
    "gn:admin2_code":"09",
    "gn:admin3_code":"41005000.0",
    "gn:asciiname":"Pajo",
    "gn:country_code":"PH",
    "gn:dem":139,
    "gn:feature_class":"P",
    "gn:feature_code":"PPL",
    "gn:name":"Pajo",
    "gn:population":0,
    "gn:timezone":"Asia/Manila",
    "iso:country":"PH",
    "name:ceb_x_preferred":[
        "Pajo"
    ],
    "name:fil_x_preferred":[
        "Pajo"
    ],
    "name:ido_x_preferred":[
        "Pajo"
    ],
    "name:swe_x_preferred":[
        "Pajo"
    ],
    "wof:name":"Pajo",
    "wof:placetype":"locality"
},
  "geometry": {"coordinates":[121.07040000000001,13.5443],"type":"Point"}
}