{
  "type": "Feature",
  "properties": {
    "gn:admin1_code":"03",
    "gn:admin2_code":"63",
    "gn:admin3_code":"36910000.0",
    "gn:asciiname":"Salumague",
    "gn:country_code":"PH",
    "gn:dem":22,
    "gn:feature_class":"P",
    "gn:feature_code":"PPL",
    "gn:name":"Salumague",
    "gn:population":0,
    "gn:timezone":"Asia/Manila",
    "iso:country":"PH",
    "name:fil_x_preferred":[
        "Salamaque"
    ],
    "name:fil_x_variant":[
        "Salomague"
    ],
    "name:und_x_variant":[
        "Salumaque"
    ],
    "wof:name":"Salumague",
    "wof:placetype":"locality"
},
  "geometry": {"coordinates":[120.56231,15.66813],"type":"Point"}
}