{
  "type": "Feature",
  "properties": {
    "gn:admin1_code":"15",
    "gn:admin2_code":"27",
    "gn:admin3_code":"142703000.0",
    "gn:asciiname":"Duit",
    "gn:cc2":"PH",
    "gn:country_code":"PH",
    "gn:dem":846,
    "gn:feature_class":"P",
    "gn:feature_code":"PPL",
    "gn:name":"Duit",
    "gn:population":0,
    "gn:timezone":"Asia/Manila",
    "iso:country":"PH",
    "name:deu_x_preferred":[
        "Deut"
    ],
    "name:ind_x_preferred":[
        "Duit"
    ],
    "name:nld_x_preferred":[
        "Duit"
    ],
    "name:nor_x_preferred":[
        "Deut"
    ],
    "name:rus_x_preferred":[
        "\u0414\u0443\u0438\u0442"
    ],
    "name:swe_x_preferred":[
        "Duit"
    ],
    "name:und_x_variant":[
        "Duwit"
    ],
    "wof:name":"Duit",
    "wof:placetype":"locality"
},
  "geometry": {"coordinates":[121.09278,16.75222],"type":"Point"}
}