{
  "type": "Feature",
  "properties": {
    "gn:admin1_code":"40",
    "gn:admin2_code":"20",
    "gn:admin3_code":"42102000.0",
    "gn:asciiname":"Pasong Kabayo",
    "gn:country_code":"PH",
    "gn:dem":333,
    "gn:feature_class":"P",
    "gn:feature_code":"PPL",
    "gn:name":"Pasong Kabayo",
    "gn:population":0,
    "gn:timezone":"Asia/Manila",
    "iso:country":"PH",
    "name:und_x_variant":[
        "Pasong",
        "Pasong Kabayo"
    ],
    "wof:name":"Pasong Kabayo",
    "wof:placetype":"locality"
},
  "geometry": {"coordinates":[120.92137,14.20308],"type":"Point"}
}