{
  "type": "Feature",
  "properties": {
    "gn:admin1_code":"03",
    "gn:admin2_code":"64",
    "gn:admin3_code":"37108000.0",
    "gn:asciiname":"Lagunao",
    "gn:country_code":"PH",
    "gn:dem":12,
    "gn:feature_class":"P",
    "gn:feature_code":"PPL",
    "gn:name":"Lagunao",
    "gn:population":0,
    "gn:timezone":"Asia/Manila",
    "iso:country":"PH",
    "name:fil_x_preferred":[
        "Lagunao"
    ],
    "wof:name":"Lagunao",
    "wof:placetype":"locality"
},
  "geometry": {"coordinates":[119.9192,15.4349],"type":"Point"}
}