{
  "type": "Feature",
  "properties": {
    "gn:admin1_code":"05",
    "gn:admin2_code":"16",
    "gn:admin3_code":"51712000.0",
    "gn:asciiname":"Malobo",
    "gn:country_code":"PH",
    "gn:dem":93,
    "gn:feature_class":"P",
    "gn:feature_code":"PPL",
    "gn:name":"Malobo",
    "gn:population":0,
    "gn:timezone":"Asia/Manila",
    "iso:country":"PH",
    "name:fil_x_preferred":[
        "Malobo"
    ],
    "wof:name":"Malobo",
    "wof:placetype":"locality"
},
  "geometry": {"coordinates":[122.6146,13.9426],"type":"Point"}
}