{
  "type": "Feature",
  "properties": {
    "gn:country":"PH",
    "gn:fcode":"PPL",
    "gn:population":4580,
    "iso:country":"PH",
    "name:fil_x_preferred":[
        "Masapang"
    ],
    "qs:name":"Masapang",
    "qs:photos_9r":0,
    "qs:photos_sr":0,
    "qs:pop_sr":"4",
    "wof:name":"Masapang",
    "wof:placetype":"locality",
    "wof:population":4580
},
  "geometry": {"coordinates":[121.34229999999999,14.1971],"type":"Point"}
}