{
  "type": "Feature",
  "properties": {
    "gn:admin1_code":"NCR",
    "gn:admin2_code":"137400000",
    "gn:admin3_code":"137404000.0",
    "gn:asciiname":"Cubao",
    "gn:country_code":"PH",
    "gn:dem":47,
    "gn:feature_class":"P",
    "gn:feature_code":"PPL",
    "gn:name":"Cubao",
    "gn:population":0,
    "gn:timezone":"Asia/Manila",
    "iso:country":"PH",
    "name:fil_x_preferred":[
        "Cubao"
    ],
    "wof:name":"Cubao",
    "wof:placetype":"locality"
},
  "geometry": {"coordinates":[121.05,14.61667],"type":"Point"}
}