{
  "type": "Feature",
  "properties": {
    "gn:admin1_code":"15",
    "gn:admin2_code":"27",
    "gn:admin3_code":"142704000.0",
    "gn:asciiname":"Aguaton",
    "gn:country_code":"PH",
    "gn:dem":581,
    "gn:feature_class":"P",
    "gn:feature_code":"PPL",
    "gn:name":"Aguaton",
    "gn:population":0,
    "gn:timezone":"Asia/Manila",
    "iso:country":"PH",
    "name:fil_x_preferred":[
        "Aguaton"
    ],
    "wof:name":"Aguaton",
    "wof:placetype":"locality"
},
  "geometry": {"coordinates":[121.23533999999999,16.78457],"type":"Point"}
}