{
  "type": "Feature",
  "properties": {
    "gn:admin1_code":"15",
    "gn:admin2_code":"32",
    "gn:admin3_code":"143215000.0",
    "gn:asciiname":"Tuigeo",
    "gn:country_code":"PH",
    "gn:dem":1116,
    "gn:feature_class":"P",
    "gn:feature_code":"PPL",
    "gn:name":"Tuigeo",
    "gn:population":0,
    "gn:timezone":"Asia/Manila",
    "iso:country":"PH",
    "name:fil_x_preferred":[
        "Tuigeo"
    ],
    "name:fil_x_variant":[
        "Tulgueo",
        "Tulgeo",
        "Tulgao"
    ],
    "wof:name":"Tuigeo",
    "wof:placetype":"locality"
},
  "geometry": {"coordinates":[121.0946,17.2645],"type":"Point"}
}