{
  "type": "Feature",
  "properties": {
    "gn:country":"PH",
    "gn:fcode":"PPLA3",
    "gn:pop":5010,
    "iso:country":"PH",
    "qs:name":"Bacon",
    "qs:photos_9r":0,
    "qs:photos_sr":0,
    "qs:pop_sr":"5",
    "wd:wordcount":5114,
    "wof:name":"Bacon",
    "wof:placetype":"locality",
    "wof:population":5010
},
  "geometry": {"coordinates":[124.04111,13.03778],"type":"Point"}
}