{
  "type": "Feature",
  "properties": {
    "gn:country":"PH",
    "gn:fcode":"PPL",
    "gn:pop":6042,
    "iso:country":"PH",
    "name:bcl_x_preferred":[
        "Macalelon"
    ],
    "name:cat_x_preferred":[
        "Macalelon"
    ],
    "name:dut_x_preferred":[
        "Macalelon"
    ],
    "name:eng_x_preferred":[
        "Macalelon"
    ],
    "name:fil_x_preferred":[
        "Macalelon"
    ],
    "name:fre_x_preferred":[
        "Macalelon"
    ],
    "name:ger_x_preferred":[
        "Macalelon"
    ],
    "name:ilo_x_preferred":[
        "Macalelon"
    ],
    "name:ind_x_preferred":[
        "Macalelon"
    ],
    "name:ita_x_preferred":[
        "Macalelon"
    ],
    "name:oci_x_preferred":[
        "Macalelon"
    ],
    "name:pag_x_preferred":[
        "Macalelon"
    ],
    "name:pam_x_preferred":[
        "Macalelon"
    ],
    "name:swe_x_preferred":[
        "Macalelon"
    ],
    "name:tgl_x_preferred":[
        "Macalelon"
    ],
    "name:vie_x_preferred":[
        "Macalelon"
    ],
    "name:war_x_preferred":[
        "Macalelon"
    ],
    "qs:name":"Macalelon",
    "qs:photos_9r":0,
    "qs:photos_sr":0,
    "qs:pop_sr":"5",
    "wd:wordcount":270,
    "wof:name":"Macalelon",
    "wof:placetype":"locality",
    "wof:population":6042
},
  "geometry": {"coordinates":[122.13861,13.74694],"type":"Point"}
}