{
  "type": "Feature",
  "properties": {
    "gn:admin1_code":"01",
    "gn:admin2_code":"51",
    "gn:admin3_code":"15524000.0",
    "gn:asciiname":"Cablong",
    "gn:country_code":"PH",
    "gn:dem":13,
    "gn:feature_class":"P",
    "gn:feature_code":"PPL",
    "gn:name":"Cablong",
    "gn:population":0,
    "gn:timezone":"Asia/Manila",
    "iso:country":"PH",
    "name:fil_x_preferred":[
        "Cablong"
    ],
    "wof:name":"Cablong",
    "wof:placetype":"locality"
},
  "geometry": {"coordinates":[120.44079000000001,15.96173],"type":"Point"}
}