{
  "type": "Feature",
  "properties": {
    "gn:admin1_code":"08",
    "gn:admin2_code":"55",
    "gn:admin3_code":"86004000.0",
    "gn:asciiname":"Nonoc",
    "gn:cc2":"PH",
    "gn:country_code":"PH",
    "gn:dem":66,
    "gn:feature_class":"P",
    "gn:feature_code":"PPL",
    "gn:name":"Nonoc",
    "gn:population":0,
    "gn:timezone":"Asia/Manila",
    "iso:country":"PH",
    "name:jpn_x_preferred":[
        "Nonoc"
    ],
    "name:und_x_variant":[
        "Nohoc",
        "Nonoc"
    ],
    "wof:name":"Nonoc",
    "wof:placetype":"locality"
},
  "geometry": {"coordinates":[125.06667,11.56667],"type":"Point"}
}