{
  "type": "Feature",
  "properties": {
    "gn:admin1_code":"12",
    "gn:admin2_code":"57",
    "gn:admin3_code":"124711000.0",
    "gn:asciiname":"Malilao",
    "gn:country_code":"PH",
    "gn:dem":17,
    "gn:feature_class":"P",
    "gn:feature_code":"PPL",
    "gn:name":"Malilao",
    "gn:population":0,
    "gn:timezone":"Asia/Manila",
    "iso:country":"PH",
    "name:fil_x_preferred":[
        "Malilao"
    ],
    "wof:name":"Malilao",
    "wof:placetype":"locality"
},
  "geometry": {"coordinates":[124.38500000000001,7.21167],"type":"Point"}
}