{
  "type": "Feature",
  "properties": {
    "gn:admin1_code":"01",
    "gn:admin2_code":"28",
    "gn:admin3_code":"12817000.0",
    "gn:asciiname":"Maumel",
    "gn:country_code":"PH",
    "gn:dem":31,
    "gn:feature_class":"P",
    "gn:feature_code":"PPL",
    "gn:name":"Maumel",
    "gn:population":0,
    "gn:timezone":"Asia/Manila",
    "iso:country":"PH",
    "name:fil_x_preferred":[
        "Maumel"
    ],
    "wof:name":"Maumel",
    "wof:placetype":"locality"
},
  "geometry": {"coordinates":[120.6272,18.3217],"type":"Point"}
}