{
  "type": "Feature",
  "properties": {
    "gn:admin1_code":"14",
    "gn:admin2_code":"60",
    "gn:admin3_code":"156615000.0",
    "gn:asciiname":"Dungun",
    "gn:country_code":"PH",
    "gn:dem":9,
    "gn:feature_class":"P",
    "gn:feature_code":"PPL",
    "gn:name":"Dungun",
    "gn:population":0,
    "gn:timezone":"Asia/Manila",
    "iso:country":"PH",
    "name:eng_x_preferred":[
        "Dungun"
    ],
    "wof:name":"Dungun",
    "wof:placetype":"locality"
},
  "geometry": {"coordinates":[121.82866,6.14856],"type":"Point"}
}