{
  "type": "Feature",
  "properties": {
    "gn:admin1_code":"03",
    "gn:admin2_code":"13",
    "gn:admin3_code":"31406000.0",
    "gn:asciiname":"Tulay",
    "gn:cc2":"PH",
    "gn:country_code":"PH",
    "gn:dem":18,
    "gn:feature_class":"P",
    "gn:feature_code":"PPL",
    "gn:name":"Tulay",
    "gn:population":0,
    "gn:timezone":"Asia/Manila",
    "iso:country":"PH",
    "name:und_x_variant":[
        "Tulay na Patpat",
        "Tulay"
    ],
    "wof:name":"Tulay",
    "wof:placetype":"locality"
},
  "geometry": {"coordinates":[120.91667,14.93333],"type":"Point"}
}