{
  "type": "Feature",
  "properties": {
    "gn:admin1_code":"15",
    "gn:admin2_code":"27",
    "gn:admin3_code":"142707000.0",
    "gn:asciiname":"Calupaan",
    "gn:country_code":"PH",
    "gn:dem":141,
    "gn:feature_class":"P",
    "gn:feature_code":"PPL",
    "gn:name":"Calupaan",
    "gn:population":0,
    "gn:timezone":"Asia/Manila",
    "iso:country":"PH",
    "wof:name":"Calupaan",
    "wof:placetype":"locality"
},
  "geometry": {"coordinates":[121.52104,16.87145],"type":"Point"}
}