{
  "type": "Feature",
  "properties": {
    "gn:admin1_code":"15",
    "gn:admin2_code":"32",
    "gn:admin3_code":"143208000.0",
    "gn:asciiname":"Lapoc",
    "gn:country_code":"PH",
    "gn:dem":897,
    "gn:feature_class":"P",
    "gn:feature_code":"PPL",
    "gn:name":"Lapoc",
    "gn:population":0,
    "gn:timezone":"Asia/Manila",
    "iso:country":"PH",
    "name:fil_x_preferred":[
        "Lapoc"
    ],
    "wof:name":"Lapoc",
    "wof:placetype":"locality"
},
  "geometry": {"coordinates":[121.1464,17.3939],"type":"Point"}
}