{
  "type": "Feature",
  "properties": {
    "gn:country":"PH",
    "gn:fcode":"PPLA3",
    "gn:pop":10299,
    "iso:country":"PH",
    "name:bcl_x_preferred":[
        "Tinambac"
    ],
    "name:dut_x_preferred":[
        "Tinambac"
    ],
    "name:eng_x_preferred":[
        "Tinambac"
    ],
    "name:fil_x_preferred":[
        "Tinambac"
    ],
    "name:fre_x_preferred":[
        "Tinambac"
    ],
    "name:ger_x_preferred":[
        "Tinambac"
    ],
    "name:ilo_x_preferred":[
        "Tinambac"
    ],
    "name:ind_x_preferred":[
        "Tinambac"
    ],
    "name:ita_x_preferred":[
        "Tinambac"
    ],
    "name:pag_x_preferred":[
        "Tinambac"
    ],
    "name:pam_x_preferred":[
        "Tinambac"
    ],
    "name:swe_x_preferred":[
        "Tinambac"
    ],
    "name:tgl_x_preferred":[
        "Tinambac"
    ],
    "name:vie_x_preferred":[
        "Tinambac"
    ],
    "name:war_x_preferred":[
        "Tinambac"
    ],
    "qs:name":"Tinambac",
    "qs:photos_9r":0,
    "qs:photos_sr":0,
    "qs:pop_sr":"6",
    "wof:name":"Tinambac",
    "wof:placetype":"locality",
    "wof:population":10299
},
  "geometry": {"coordinates":[123.3261,13.8164],"type":"Point"}
}