{
  "type": "Feature",
  "properties": {
    "gn:admin1_code":"40",
    "gn:admin2_code":"20",
    "gn:admin3_code":"42110000.0",
    "gn:asciiname":"Poblacion",
    "gn:country_code":"PH",
    "gn:dem":297,
    "gn:feature_class":"P",
    "gn:feature_code":"PPL",
    "gn:name":"Poblacion",
    "gn:population":0,
    "gn:timezone":"Asia/Manila",
    "iso:country":"PH",
    "name:deu_x_preferred":[
        "Poblaci\u00f3n"
    ],
    "name:spa_x_preferred":[
        "Poblaci\u00f3n"
    ],
    "wof:name":"Poblacion",
    "wof:placetype":"locality"
},
  "geometry": {"coordinates":[120.87673999999998,14.19558],"type":"Point"}
}