{
  "type": "Feature",
  "properties": {
    "gn:admin1_code":"14",
    "gn:admin2_code":"60",
    "gn:admin3_code":"156609000.0",
    "gn:asciiname":"Linuho",
    "gn:country_code":"PH",
    "gn:dem":234,
    "gn:feature_class":"P",
    "gn:feature_code":"PPL",
    "gn:name":"Linuho",
    "gn:population":0,
    "gn:timezone":"Asia/Manila",
    "iso:country":"PH",
    "name:fil_x_preferred":[
        "Linuho"
    ],
    "wof:name":"Linuho",
    "wof:placetype":"locality"
},
  "geometry": {"coordinates":[120.93667000000001,5.92639],"type":"Point"}
}