{
  "type": "Feature",
  "properties": {
    "gn:admin1_code":"13",
    "gn:admin2_code":"03",
    "gn:admin3_code":"160309000.0",
    "gn:asciiname":"Baylo",
    "gn:country_code":"PH",
    "gn:dem":34,
    "gn:feature_class":"P",
    "gn:feature_code":"PPL",
    "gn:name":"Baylo",
    "gn:population":0,
    "gn:timezone":"Asia/Manila",
    "iso:country":"PH",
    "name:fil_x_preferred":[
        "Baylo"
    ],
    "wof:name":"Baylo",
    "wof:placetype":"locality"
},
  "geometry": {"coordinates":[125.72917,8.41194],"type":"Point"}
}