{
  "type": "Feature",
  "properties": {
    "gn:admin1_code":"06",
    "gn:admin2_code":"30",
    "gn:admin3_code":"63006000.0",
    "gn:asciiname":"Balen",
    "gn:country_code":"PH",
    "gn:dem":9,
    "gn:feature_class":"P",
    "gn:feature_code":"PPL",
    "gn:name":"Balen",
    "gn:population":0,
    "gn:timezone":"Asia/Manila",
    "iso:country":"PH",
    "name:afr_x_preferred":[
        "Balen"
    ],
    "name:bre_x_preferred":[
        "Balen"
    ],
    "name:bul_x_preferred":[
        "\u0411\u0430\u043b\u0435\u043d"
    ],
    "name:cat_x_preferred":[
        "Balen"
    ],
    "name:ceb_x_preferred":[
        "Balen"
    ],
    "name:deu_x_preferred":[
        "Balen"
    ],
    "name:epo_x_preferred":[
        "Balen"
    ],
    "name:eus_x_preferred":[
        "Balen"
    ],
    "name:fas_x_preferred":[
        "\u0628\u0644\u0627\u0646"
    ],
    "name:fil_x_preferred":[
        "Balen"
    ],
    "name:fra_x_preferred":[
        "Balen"
    ],
    "name:ita_x_preferred":[
        "Balen"
    ],
    "name:nld_x_preferred":[
        "Balen"
    ],
    "name:nor_x_preferred":[
        "Balen"
    ],
    "name:oci_x_preferred":[
        "Balen"
    ],
    "name:pol_x_preferred":[
        "Balen"
    ],
    "name:por_x_preferred":[
        "Balen"
    ],
    "name:ron_x_preferred":[
        "Balen"
    ],
    "name:rus_x_preferred":[
        "\u0411\u0430\u043b\u0435\u043d"
    ],
    "name:slk_x_preferred":[
        "Balen"
    ],
    "name:spa_x_preferred":[
        "Balen"
    ],
    "name:swe_x_preferred":[
        "Balen"
    ],
    "name:vie_x_preferred":[
        "Balen"
    ],
    "name:vol_x_preferred":[
        "Balen"
    ],
    "name:war_x_preferred":[
        "Balen"
    ],
    "name:zho_x_preferred":[
        "\u5df4\u4f26"
    ],
    "wof:name":"Balen",
    "wof:placetype":"locality"
},
  "geometry": {"coordinates":[122.79389,10.99472],"type":"Point"}
}