{
  "type": "Feature",
  "properties": {
    "gn:admin1_code":"06",
    "gn:admin2_code":"30",
    "gn:admin3_code":"63006000.0",
    "gn:asciiname":"Balen",
    "gn:country_code":"PH",
    "gn:dem":9,
    "gn:feature_class":"P",
    "gn:feature_code":"PPL",
    "gn:name":"Balen",
    "gn:population":0,
    "gn:timezone":"Asia/Manila",
    "iso:country":"PH",
    "name:fil_x_preferred":[
        "Balen"
    ],
    "wof:name":"Balen",
    "wof:placetype":"locality"
},
  "geometry": {"coordinates":[122.79389,10.99472],"type":"Point"}
}