{
  "type": "Feature",
  "properties": {
    "gn:admin1_code":"07",
    "gn:admin2_code":"69",
    "gn:admin3_code":"76101000.0",
    "gn:asciiname":"Lumangcapan",
    "gn:country_code":"PH",
    "gn:dem":19,
    "gn:feature_class":"P",
    "gn:feature_code":"PPL",
    "gn:name":"Lumangcapan",
    "gn:population":0,
    "gn:timezone":"Asia/Manila",
    "iso:country":"PH",
    "name:fil_x_preferred":[
        "Lumangcapan"
    ],
    "wof:name":"Lumangcapan",
    "wof:placetype":"locality"
},
  "geometry": {"coordinates":[123.6327,9.2872],"type":"Point"}
}