{
  "type": "Feature",
  "properties": {
    "gn:admin1_code":"40",
    "gn:admin2_code":"33",
    "gn:admin3_code":"43411000.0",
    "gn:asciiname":"Kapatagan",
    "gn:country_code":"PH",
    "gn:dem":158,
    "gn:feature_class":"P",
    "gn:feature_code":"PPL",
    "gn:name":"Kapatagan",
    "gn:population":0,
    "gn:timezone":"Asia/Manila",
    "iso:country":"PH",
    "name:ceb_x_preferred":[
        "Kapatagan"
    ],
    "name:deu_x_preferred":[
        "Kapatagan"
    ],
    "name:fil_x_preferred":[
        "Kapatagan"
    ],
    "name:fra_x_preferred":[
        "Kapatagan"
    ],
    "name:ita_x_preferred":[
        "Kapatagan"
    ],
    "name:nld_x_preferred":[
        "Kapatagan"
    ],
    "name:war_x_preferred":[
        "Kapatagan"
    ],
    "wof:name":"Kapatagan",
    "wof:placetype":"locality"
},
  "geometry": {"coordinates":[121.23333,14.15],"type":"Point"}
}