{
  "type": "Feature",
  "properties": {
    "gn:country":"PH",
    "gn:fcode":"PPL",
    "gn:pop":14876,
    "iso:country":"PH",
    "name:fil_x_preferred":[
        "Guiljungan"
    ],
    "name:unk_x_variant":[
        "Guinjungan"
    ],
    "qs:name":"Guiljungan",
    "qs:photos_9r":0,
    "qs:photos_sr":0,
    "qs:pop_sr":"6",
    "wof:name":"Guiljungan",
    "wof:placetype":"locality",
    "wof:population":14876
},
  "geometry": {"coordinates":[122.6742,9.9805],"type":"Point"}
}