{
  "type": "Feature",
  "properties": {
    "gn:admin1_code":"07",
    "gn:admin2_code":"11",
    "gn:admin3_code":"71248000.0",
    "gn:asciiname":"Puerto San Pedro",
    "gn:country_code":"PH",
    "gn:dem":8,
    "gn:feature_class":"P",
    "gn:feature_code":"PPL",
    "gn:name":"Puerto San Pedro",
    "gn:population":0,
    "gn:timezone":"Asia/Manila",
    "iso:country":"PH",
    "name:fil_x_preferred":[
        "Puerto San Pedro"
    ],
    "wof:name":"Puerto San Pedro",
    "wof:placetype":"locality"
},
  "geometry": {"coordinates":[124.37388,10.1457],"type":"Point"}
}