{
  "type": "Feature",
  "properties": {
    "gn:admin1_code":"06",
    "gn:admin2_code":"30",
    "gn:admin3_code":"63023000.0",
    "gn:asciiname":"Kinambol",
    "gn:country_code":"PH",
    "gn:dem":79,
    "gn:feature_class":"P",
    "gn:feature_code":"PPL",
    "gn:name":"Kinambol",
    "gn:population":0,
    "gn:timezone":"Asia/Manila",
    "iso:country":"PH",
    "name:fil_x_preferred":[
        "Kinambol"
    ],
    "wof:name":"Kinambol",
    "wof:placetype":"locality"
},
  "geometry": {"coordinates":[122.4847,10.9748],"type":"Point"}
}