{
  "type": "Feature",
  "properties": {
    "gn:admin1_code":"15",
    "gn:admin2_code":"01",
    "gn:admin3_code":"140114000.0",
    "gn:asciiname":"Baliga",
    "gn:country_code":"PH",
    "gn:dem":187,
    "gn:feature_class":"P",
    "gn:feature_code":"PPL",
    "gn:name":"Baliga",
    "gn:population":0,
    "gn:timezone":"Asia/Manila",
    "iso:country":"PH",
    "name:ceb_x_preferred":[
        "Baliga"
    ],
    "name:fil_x_preferred":[
        "Baliga"
    ],
    "name:mar_x_preferred":[
        "\u092c\u093e\u0932\u0940\u0917\u093e"
    ],
    "name:swe_x_preferred":[
        "Baliga"
    ],
    "name:war_x_preferred":[
        "Baliga"
    ],
    "wof:name":"Baliga",
    "wof:placetype":"locality"
},
  "geometry": {"coordinates":[120.69589999999999,17.3032],"type":"Point"}
}