{
  "type": "Feature",
  "properties": {
    "gn:admin1_code":"07",
    "gn:admin2_code":"11",
    "gn:admin3_code":"71247000.0",
    "gn:asciiname":"Banderahan",
    "gn:country_code":"PH",
    "gn:dem":587,
    "gn:feature_class":"P",
    "gn:feature_code":"PPL",
    "gn:name":"Banderahan",
    "gn:population":0,
    "gn:timezone":"Asia/Manila",
    "iso:country":"PH",
    "name:fil_x_preferred":[
        "Banderahan"
    ],
    "wof:name":"Banderahan",
    "wof:placetype":"locality"
},
  "geometry": {"coordinates":[124.23271,9.71463],"type":"Point"}
}