{
  "type": "Feature",
  "properties": {
    "gn:admin1_code":"06",
    "gn:admin2_code":"18",
    "gn:admin3_code":"61901000.0",
    "gn:asciiname":"Angub",
    "gn:country_code":"PH",
    "gn:dem":20,
    "gn:feature_class":"P",
    "gn:feature_code":"PPL",
    "gn:name":"Angub",
    "gn:population":0,
    "gn:timezone":"Asia/Manila",
    "iso:country":"PH",
    "name:fil_x_preferred":[
        "Angub"
    ],
    "name:und_x_variant":[
        "Angur"
    ],
    "wof:name":"Angub",
    "wof:placetype":"locality"
},
  "geometry": {"coordinates":[122.6641,11.3494],"type":"Point"}
}