{
  "type": "Feature",
  "properties": {
    "gn:admin1_code":"14",
    "gn:admin2_code":"56",
    "gn:admin3_code":"153807000.0",
    "gn:asciiname":"Dubab",
    "gn:country_code":"PH",
    "gn:dem":11,
    "gn:feature_class":"P",
    "gn:feature_code":"PPL",
    "gn:name":"Dubab",
    "gn:population":0,
    "gn:timezone":"Asia/Manila",
    "iso:country":"PH",
    "name:fil_x_preferred":[
        "Dubab"
    ],
    "wof:name":"Dubab",
    "wof:placetype":"locality"
},
  "geometry": {"coordinates":[124.22417,7.17611],"type":"Point"}
}