{
  "type": "Feature",
  "properties": {
    "gn:admin1_code":"10",
    "gn:admin2_code":"42",
    "gn:admin3_code":"104210000.0",
    "gn:asciiname":"Capucao",
    "gn:country_code":"PH",
    "gn:dem":158,
    "gn:feature_class":"P",
    "gn:feature_code":"PPL",
    "gn:name":"Capucao",
    "gn:population":0,
    "gn:timezone":"Asia/Manila",
    "iso:country":"PH",
    "name:fil_x_preferred":[
        "Capucao"
    ],
    "wof:name":"Capucao",
    "wof:placetype":"locality"
},
  "geometry": {"coordinates":[123.78667,8.18861],"type":"Point"}
}