{
  "type": "Feature",
  "properties": {
    "gn:admin1_code":"08",
    "gn:admin2_code":"37",
    "gn:admin3_code":"83745000.0",
    "gn:asciiname":"Liogliog",
    "gn:country_code":"PH",
    "gn:dem":18,
    "gn:feature_class":"P",
    "gn:feature_code":"PPL",
    "gn:name":"Liogliog",
    "gn:population":0,
    "gn:timezone":"Asia/Manila",
    "iso:country":"PH",
    "name:eng_x_preferred":[
        "Liogliog"
    ],
    "name:und_x_variant":[
        "Lioliog"
    ],
    "wof:name":"Liogliog",
    "wof:placetype":"locality"
},
  "geometry": {"coordinates":[124.37139999999999,11.2917],"type":"Point"}
}