{
  "type": "Feature",
  "properties": {
    "gn:admin1_code":"08",
    "gn:admin2_code":"37",
    "gn:admin3_code":"83701000.0",
    "gn:asciiname":"Inalaran",
    "gn:country_code":"PH",
    "gn:dem":25,
    "gn:feature_class":"P",
    "gn:feature_code":"PPL",
    "gn:name":"Inalaran",
    "gn:population":0,
    "gn:timezone":"Asia/Manila",
    "iso:country":"PH",
    "name:fil_x_preferred":[
        "Inalaran"
    ],
    "wof:name":"Inalaran",
    "wof:placetype":"locality"
},
  "geometry": {"coordinates":[125.15260000000001,10.6193],"type":"Point"}
}