{
  "type": "Feature",
  "properties": {
    "gn:admin1_code":"40",
    "gn:admin2_code":"09",
    "gn:admin3_code":"41014000.0",
    "gn:asciiname":"Maagonlong",
    "gn:country_code":"PH",
    "gn:dem":284,
    "gn:feature_class":"P",
    "gn:feature_code":"PPL",
    "gn:name":"Maagonlong",
    "gn:population":0,
    "gn:timezone":"Asia/Manila",
    "iso:country":"PH",
    "name:fil_x_preferred":[
        "Malagonglong"
    ],
    "name:und_x_variant":[
        "Malagonlong"
    ],
    "wof:name":"Maagonlong",
    "wof:placetype":"locality"
},
  "geometry": {"coordinates":[121.1558,13.9116],"type":"Point"}
}