{
  "type": "Feature",
  "properties": {
    "gn:country":"PH",
    "gn:fcode":"PPL",
    "gn:pop":2810,
    "iso:country":"PH",
    "name:fil_x_preferred":[
        "San Antonio"
    ],
    "qs:name":"San Antonio",
    "qs:photos_9r":0,
    "qs:photos_sr":0,
    "qs:pop_sr":"4",
    "wof:name":"San Antonio",
    "wof:placetype":"locality",
    "wof:population":2810
},
  "geometry": {"coordinates":[121.79264000000001,17.27323],"type":"Point"}
}