{
  "type": "Feature",
  "properties": {
    "gn:admin1_code":"03",
    "gn:admin2_code":"13",
    "gn:admin3_code":"31420000.0",
    "gn:asciiname":"Cantulot",
    "gn:country_code":"PH",
    "gn:dem":130,
    "gn:feature_class":"P",
    "gn:feature_code":"PPL",
    "gn:name":"Cantulot",
    "gn:population":0,
    "gn:timezone":"Asia/Manila",
    "iso:country":"PH",
    "name:fil_x_preferred":[
        "Cantulot"
    ],
    "wof:name":"Cantulot",
    "wof:placetype":"locality"
},
  "geometry": {"coordinates":[121.10550000000001,14.8178],"type":"Point"}
}