{
  "type": "Feature",
  "properties": {
    "gn:admin1_code":"15",
    "gn:admin2_code":"27",
    "gn:admin3_code":"142709000.0",
    "gn:asciiname":"Piwong",
    "gn:country_code":"PH",
    "gn:dem":908,
    "gn:feature_class":"P",
    "gn:feature_code":"PPL",
    "gn:name":"Piwong",
    "gn:population":0,
    "gn:timezone":"Asia/Manila",
    "iso:country":"PH",
    "name:fil_x_preferred":[
        "Piwong"
    ],
    "wof:name":"Piwong",
    "wof:placetype":"locality"
},
  "geometry": {"coordinates":[121.08993999999998,16.84546],"type":"Point"}
}