{
  "type": "Feature",
  "properties": {
    "gn:admin1_code":"03",
    "gn:admin2_code":"47",
    "gn:admin3_code":"34902000.0",
    "gn:asciiname":"Larcon",
    "gn:country_code":"PH",
    "gn:dem":83,
    "gn:feature_class":"P",
    "gn:feature_code":"PPL",
    "gn:name":"Larcon",
    "gn:population":0,
    "gn:timezone":"Asia/Manila",
    "iso:country":"PH",
    "name:fil_x_preferred":[
        "Balacat Larcon"
    ],
    "wof:name":"Larcon",
    "wof:placetype":"locality"
},
  "geometry": {"coordinates":[121.1591,15.6423],"type":"Point"}
}