{
  "type": "Feature",
  "properties": {
    "gn:admin1_code":"01",
    "gn:admin2_code":"29",
    "gn:admin3_code":"12907000.0",
    "gn:asciiname":"Tamurong",
    "gn:country_code":"PH",
    "gn:dem":6,
    "gn:feature_class":"P",
    "gn:feature_code":"PPL",
    "gn:name":"Tamurong",
    "gn:population":0,
    "gn:timezone":"Asia/Manila",
    "iso:country":"PH",
    "name:und_x_variant":[
        "Pantay Tamorong",
        "Pantay-Tamurong",
        "Tamurong"
    ],
    "wof:name":"Tamurong",
    "wof:placetype":"locality"
},
  "geometry": {"coordinates":[120.40402,17.52589],"type":"Point"}
}