{
  "type": "Feature",
  "properties": {
    "gn:admin1_code":"40",
    "gn:admin2_code":"H2",
    "gn:admin3_code":"45619000.0",
    "gn:asciiname":"San Isidro Kanluran",
    "gn:country_code":"PH",
    "gn:dem":69,
    "gn:feature_class":"P",
    "gn:feature_code":"PPL",
    "gn:name":"San Isidro Kanluran",
    "gn:population":0,
    "gn:timezone":"Asia/Manila",
    "iso:country":"PH",
    "name:fil_x_preferred":[
        "San Isidro Kanluran"
    ],
    "name:fil_x_variant":[
        "San Isidro"
    ],
    "wof:name":"San Isidro Kanluran",
    "wof:placetype":"locality"
},
  "geometry": {"coordinates":[122.08750000000001,13.8671],"type":"Point"}
}