{
  "type": "Feature",
  "properties": {
    "iso:country":"PH",
    "name:bcl_x_preferred":[
        "Ganassi"
    ],
    "name:cbk_zam_x_preferred":[
        "Ganassi"
    ],
    "name:ceb_x_preferred":[
        "Ganassi"
    ],
    "name:deu_x_preferred":[
        "Ganassi"
    ],
    "name:eng_x_preferred":[
        "Ganassi"
    ],
    "name:fra_x_preferred":[
        "Ganassi"
    ],
    "name:ilo_x_preferred":[
        "Ganassi"
    ],
    "name:ind_x_preferred":[
        "Ganassi"
    ],
    "name:ita_x_preferred":[
        "Ganassi"
    ],
    "name:nld_x_preferred":[
        "Ganassi"
    ],
    "name:pag_x_preferred":[
        "Ganassi"
    ],
    "name:pam_x_preferred":[
        "Ganassi"
    ],
    "name:spa_x_preferred":[
        "Ganassi"
    ],
    "name:swe_x_preferred":[
        "Ganassi"
    ],
    "name:tgl_x_preferred":[
        "Ganassi"
    ],
    "name:und_x_variant":[
        "Ganasi"
    ],
    "name:urd_x_preferred":[
        "\u06af\u0627\u0646\u0627\u0633\u06cc\u060c \u0644\u0627\u0646\u0627\u0624 \u062c\u0646\u0648\u0628\u06cc"
    ],
    "name:urd_x_variant":[
        "\u06af\u0627\u0646\u0627\u0633\u06cc"
    ],
    "name:vie_x_preferred":[
        "Ganassi"
    ],
    "name:war_x_preferred":[
        "Ganassi"
    ],
    "qs:gn_country":"PH",
    "qs:gn_fcode":"PPLA3",
    "qs:gn_pop":2412,
    "qs:name":"Ganassi",
    "qs:name_adm0":"Philippines",
    "qs:name_adm1":"Autonomous Region in Muslim Mindanao",
    "qs:photos":0,
    "qs:photos_1k":0,
    "qs:photos_9k":0,
    "qs:photos_9r":0,
    "qs:photos_all":0,
    "qs:photos_sr":0,
    "qs:placetype":"Town",
    "qs:pop_sr":"4",
    "qs:woe_adm0":23424934,
    "wd:wordcount":151,
    "wof:name":"Ganassi",
    "wof:placetype":"locality",
    "wof:population":2412
},
  "geometry": {"coordinates":[124.10344000000001,7.82694],"type":"Point"}
}