{
  "type": "Feature",
  "properties": {
    "gn:admin1_code":"10",
    "gn:admin2_code":"43",
    "gn:admin3_code":"104324000.0",
    "gn:asciiname":"Sugbongcogon",
    "gn:country_code":"PH",
    "gn:dem":8,
    "gn:feature_class":"P",
    "gn:feature_code":"PPL",
    "gn:name":"Sugbongcogon",
    "gn:population":0,
    "gn:timezone":"Asia/Manila",
    "iso:country":"PH",
    "name:fil_x_preferred":[
        "Sugbongcogon"
    ],
    "wof:name":"Sugbongcogon",
    "wof:placetype":"locality"
},
  "geometry": {"coordinates":[124.74639000000001,8.52583],"type":"Point"}
}