{
  "type": "Feature",
  "properties": {
    "gn:admin1_code":"40",
    "gn:admin2_code":"20",
    "gn:admin3_code":"42110000.0",
    "gn:asciiname":"Mangpong",
    "gn:country_code":"PH",
    "gn:dem":292,
    "gn:feature_class":"P",
    "gn:feature_code":"PPL",
    "gn:name":"Mangpong",
    "gn:population":0,
    "gn:timezone":"Asia/Manila",
    "iso:country":"PH",
    "name:fil_x_preferred":[
        "Mangpong"
    ],
    "wof:name":"Mangpong",
    "wof:placetype":"locality"
},
  "geometry": {"coordinates":[120.84528,14.18306],"type":"Point"}
}