{
  "type": "Feature",
  "properties": {
    "gn:admin1_code":"14",
    "gn:admin2_code":"56",
    "gn:admin3_code":"153807000.0",
    "gn:asciiname":"Badibadi",
    "gn:country_code":"PH",
    "gn:dem":12,
    "gn:feature_class":"P",
    "gn:feature_code":"PPL",
    "gn:name":"Badibadi",
    "gn:population":0,
    "gn:timezone":"Asia/Manila",
    "iso:country":"PH",
    "name:fil_x_preferred":[
        "Badibadi"
    ],
    "wof:name":"Badibadi",
    "wof:placetype":"locality"
},
  "geometry": {"coordinates":[124.21666999999999,7.18333],"type":"Point"}
}