{
  "type": "Feature",
  "properties": {
    "gn:admin1_code":"14",
    "gn:admin2_code":"60",
    "gn:admin3_code":"156605000.0",
    "gn:asciiname":"Palan",
    "gn:country_code":"PH",
    "gn:dem":102,
    "gn:feature_class":"P",
    "gn:feature_code":"PPL",
    "gn:name":"Palan",
    "gn:population":0,
    "gn:timezone":"Asia/Manila",
    "iso:country":"PH",
    "name:ceb_x_preferred":[
        "Palan"
    ],
    "name:fil_x_preferred":[
        "Palan"
    ],
    "name:swe_x_preferred":[
        "Palan"
    ],
    "wof:name":"Palan",
    "wof:placetype":"locality"
},
  "geometry": {"coordinates":[121.02199,5.98515],"type":"Point"}
}