{
  "type": "Feature",
  "properties": {
    "gn:country":"PH",
    "gn:fcode":"ADM3",
    "gn:population":15620,
    "iso:country":"PH",
    "name:fil_x_preferred":[
        "Santa Magdalena"
    ],
    "name:und_x_variant":[
        "Busaingan"
    ],
    "qs:name":"Santa Magdalena",
    "qs:photos_9r":0,
    "qs:photos_sr":0,
    "qs:pop_sr":"6",
    "wof:name":"Santa Magdalena",
    "wof:placetype":"localadmin",
    "wof:population":15620
},
  "geometry": {"coordinates":[124.08333,12.65],"type":"Point"}
}