{
  "type": "Feature",
  "properties": {
    "gn:admin1_code":"03",
    "gn:admin2_code":"50",
    "gn:admin3_code":"35412000.0",
    "gn:asciiname":"Puti",
    "gn:country_code":"PH",
    "gn:dem":5,
    "gn:feature_class":"P",
    "gn:feature_code":"PPL",
    "gn:name":"Puti",
    "gn:population":0,
    "gn:timezone":"Asia/Manila",
    "iso:country":"PH",
    "name:ceb_x_preferred":[
        "Puti"
    ],
    "name:deu_x_preferred":[
        "Puti"
    ],
    "name:est_x_preferred":[
        "Puti"
    ],
    "name:swe_x_preferred":[
        "Puti"
    ],
    "wof:name":"Puti",
    "wof:placetype":"locality"
},
  "geometry": {"coordinates":[120.68931000000001,14.85033],"type":"Point"}
}