{
  "type": "Feature",
  "properties": {
    "gn:country":"PH",
    "gn:fcode":"ADM3",
    "gn:pop":23740,
    "iso:country":"PH",
    "name:fil_x_preferred":[
        "Panglao"
    ],
    "qs:name":"Panglao",
    "qs:photos_9r":0,
    "qs:photos_sr":0,
    "qs:pop_sr":"7",
    "wd:wordcount":17,
    "wof:name":"Panglao",
    "wof:placetype":"localadmin",
    "wof:population":23740
},
  "geometry": {"coordinates":[123.78333000000001,9.58333],"type":"Point"}
}