{
  "type": "Feature",
  "properties": {
    "gn:admin1_code":"07",
    "gn:admin2_code":"11",
    "gn:admin3_code":"71226000.0",
    "gn:asciiname":"Campao Occidental",
    "gn:country_code":"PH",
    "gn:dem":36,
    "gn:feature_class":"P",
    "gn:feature_code":"PPL",
    "gn:name":"Campao Occidental",
    "gn:population":0,
    "gn:timezone":"Asia/Manila",
    "iso:country":"PH",
    "name:fil_x_preferred":[
        "Campao"
    ],
    "name:fil_x_variant":[
        "Campao Occidental"
    ],
    "wof:name":"Campao Occidental",
    "wof:placetype":"locality"
},
  "geometry": {"coordinates":[124.14018,10.11195],"type":"Point"}
}