{
  "type": "Feature",
  "properties": {
    "gn:admin1_code":"13",
    "gn:admin2_code":"61",
    "gn:admin3_code":"166701000.0",
    "gn:asciiname":"Alipao",
    "gn:country_code":"PH",
    "gn:dem":50,
    "gn:feature_class":"P",
    "gn:feature_code":"PPL",
    "gn:name":"Alipao",
    "gn:population":0,
    "gn:timezone":"Asia/Manila",
    "iso:country":"PH",
    "name:fil_x_preferred":[
        "Alipao"
    ],
    "wof:name":"Alipao",
    "wof:placetype":"locality"
},
  "geometry": {"coordinates":[125.58159999999999,9.502],"type":"Point"}
}