{
  "type": "Feature",
  "properties": {
    "gn:admin1_code":"02",
    "gn:admin2_code":"14",
    "gn:admin3_code":"21516000.0",
    "gn:asciiname":"Catugan Norte",
    "gn:country_code":"PH",
    "gn:dem":5,
    "gn:feature_class":"P",
    "gn:feature_code":"PPL",
    "gn:name":"Catugan Norte",
    "gn:population":0,
    "gn:timezone":"Asia/Manila",
    "iso:country":"PH",
    "name:fil_x_preferred":[
        "Catugan Norte"
    ],
    "name:fil_x_variant":[
        "Catocan Norte"
    ],
    "wof:name":"Catugan Norte",
    "wof:placetype":"locality"
},
  "geometry": {"coordinates":[121.62045000000001,18.19178],"type":"Point"}
}