{
  "type": "Feature",
  "properties": {
    "gn:admin1_code":"07",
    "gn:admin2_code":"21",
    "gn:admin3_code":"72237000.0",
    "gn:asciiname":"Rizal",
    "gn:country_code":"PH",
    "gn:dem":13,
    "gn:feature_class":"P",
    "gn:feature_code":"PPL",
    "gn:name":"Rizal",
    "gn:population":0,
    "gn:timezone":"Asia/Manila",
    "iso:country":"PH",
    "name:ace_x_preferred":[
        "Propinsi Rizal"
    ],
    "name:ara_x_preferred":[
        "\u0631\u064a\u0632\u0627\u0644"
    ],
    "name:azb_x_preferred":[
        "\u0631\u06cc\u0632\u0627\u0644"
    ],
    "name:bcl_x_preferred":[
        "Rizal"
    ],
    "name:ceb_x_preferred":[
        "Rizal"
    ],
    "name:deu_x_preferred":[
        "Provinz Rizal"
    ],
    "name:fas_x_preferred":[
        "\u0631\u06cc\u0632\u0627\u0644"
    ],
    "name:fil_x_preferred":[
        "Rizal"
    ],
    "name:fin_x_preferred":[
        "Rizal"
    ],
    "name:fra_x_preferred":[
        "Rizal"
    ],
    "name:hin_x_preferred":[
        "\u0930\u093f\u091c\u093c\u093e\u0932 \u092a\u094d\u0930\u093e\u0928\u094d\u0924"
    ],
    "name:ilo_x_preferred":[
        "Rizal"
    ],
    "name:ind_x_preferred":[
        "Rizal"
    ],
    "name:jpn_x_preferred":[
        "\u30ea\u30b5\u30fc\u30eb\u5dde"
    ],
    "name:kor_x_preferred":[
        "\ub9ac\uc0b4\uc8fc"
    ],
    "name:mkd_x_preferred":[
        "\u0420\u0438\u0437\u0430\u043b"
    ],
    "name:msa_x_preferred":[
        "Rizal"
    ],
    "name:nld_x_preferred":[
        "Rizal"
    ],
    "name:nor_x_preferred":[
        "Rizal"
    ],
    "name:pag_x_preferred":[
        "Rizal"
    ],
    "name:pam_x_preferred":[
        "Rizal"
    ],
    "name:pol_x_preferred":[
        "Rizal"
    ],
    "name:rus_x_preferred":[
        "\u0420\u0438\u0441\u0430\u043b\u044c"
    ],
    "name:sco_x_preferred":[
        "Rizal"
    ],
    "name:swe_x_preferred":[
        "Rizal"
    ],
    "name:tam_x_preferred":[
        "\u0bb0\u0bbf\u0b9a\u0bbe\u0bb2\u0bcd"
    ],
    "name:tgl_x_preferred":[
        "Rizal"
    ],
    "name:tha_x_preferred":[
        "\u0e08\u0e31\u0e07\u0e2b\u0e27\u0e31\u0e14\u0e23\u0e35\u0e0b\u0e31\u0e25"
    ],
    "name:tur_x_preferred":[
        "Rizal"
    ],
    "name:ukr_x_preferred":[
        "\u0420\u0456\u0441\u0430\u043b\u044c"
    ],
    "name:urd_x_preferred":[
        "\u0631\u06cc\u0632\u0627\u0644"
    ],
    "name:vie_x_preferred":[
        "Rizal"
    ],
    "name:war_x_preferred":[
        "Rizal"
    ],
    "name:zho_x_preferred":[
        "\u9ece\u524e\u7701"
    ],
    "wof:name":"Rizal",
    "wof:placetype":"locality"
},
  "geometry": {"coordinates":[123.6084,10.3137],"type":"Point"}
}