{
  "type": "Feature",
  "properties": {
    "gn:admin1_code":"07",
    "gn:admin2_code":"21",
    "gn:admin3_code":"72237000.0",
    "gn:asciiname":"Rizal",
    "gn:country_code":"PH",
    "gn:dem":13,
    "gn:feature_class":"P",
    "gn:feature_code":"PPL",
    "gn:name":"Rizal",
    "gn:population":0,
    "gn:timezone":"Asia/Manila",
    "iso:country":"PH",
    "name:fil_x_preferred":[
        "Rizal"
    ],
    "wof:name":"Rizal",
    "wof:placetype":"locality"
},
  "geometry": {"coordinates":[123.6084,10.3137],"type":"Point"}
}