{
  "type": "Feature",
  "properties": {
    "gn:admin1_code":"07",
    "gn:admin2_code":"21",
    "gn:asciiname":"Sangi",
    "gn:country_code":"PH",
    "gn:dem":1,
    "gn:feature_class":"P",
    "gn:feature_code":"PPL",
    "gn:name":"Sangi",
    "gn:population":0,
    "gn:timezone":"Asia/Manila",
    "iso:country":"PH",
    "name:fil_x_preferred":[
        "Sangi"
    ],
    "wof:name":"Sangi",
    "wof:placetype":"locality"
},
  "geometry": {"coordinates":[123.71666999999999,10.16667],"type":"Point"}
}