{
  "type": "Feature",
  "properties": {
    "gn:admin1_code":"03",
    "gn:admin2_code":"G8",
    "gn:admin3_code":"37707000.0",
    "gn:asciiname":"Quirino",
    "gn:country_code":"PH",
    "gn:dem":36,
    "gn:feature_class":"P",
    "gn:feature_code":"PPL",
    "gn:name":"Quirino",
    "gn:population":0,
    "gn:timezone":"Asia/Manila",
    "iso:country":"PH",
    "name:fil_x_preferred":[
        "Quirino"
    ],
    "wof:name":"Quirino",
    "wof:placetype":"locality"
},
  "geometry": {"coordinates":[121.4803,15.7658],"type":"Point"}
}