{
  "type": "Feature",
  "properties": {
    "gn:country":"PH",
    "gn:fcode":"PPL",
    "gn:pop":3132,
    "iso:country":"PH",
    "name:fil_x_preferred":[
        "Libertad"
    ],
    "qs:name":"Libertad",
    "qs:photos_9r":0,
    "qs:photos_sr":0,
    "qs:pop_sr":"4",
    "wd:wordcount":414,
    "wof:name":"Libertad",
    "wof:placetype":"locality",
    "wof:population":3132
},
  "geometry": {"coordinates":[123.56667,10.83333],"type":"Point"}
}