{
  "type": "Feature",
  "properties": {
    "gn:admin1_code":"03",
    "gn:admin2_code":"47",
    "gn:admin3_code":"34929000.0",
    "gn:asciiname":"Buasao",
    "gn:country_code":"PH",
    "gn:dem":48,
    "gn:feature_class":"P",
    "gn:feature_code":"PPL",
    "gn:name":"Buasao",
    "gn:population":0,
    "gn:timezone":"Asia/Manila",
    "iso:country":"PH",
    "name:fil_x_preferred":[
        "Buasao"
    ],
    "wof:name":"Buasao",
    "wof:placetype":"locality"
},
  "geometry": {"coordinates":[120.89373000000001,15.6237],"type":"Point"}
}