{
  "type": "Feature",
  "properties": {
    "gn:admin1_code":"03",
    "gn:admin2_code":"50",
    "gn:admin3_code":"35422000.0",
    "gn:asciiname":"Batang First",
    "gn:country_code":"PH",
    "gn:dem":5,
    "gn:feature_class":"P",
    "gn:feature_code":"PPL",
    "gn:name":"Batang First",
    "gn:population":0,
    "gn:timezone":"Asia/Manila",
    "iso:country":"PH",
    "name:fil_x_preferred":[
        "Batang Primero"
    ],
    "name:fil_x_variant":[
        "Batong Macuyat",
        "Batang 1st",
        "Batang-macuyad",
        "Batang"
    ],
    "name:und_x_variant":[
        "Batang 1st",
        "Batang",
        "Batang-macuyad",
        "Batong Macuyat",
        "Batang First"
    ],
    "wof:name":"Batang First",
    "wof:placetype":"locality"
},
  "geometry": {"coordinates":[120.62092,14.83052],"type":"Point"}
}