{
  "type": "Feature",
  "properties": {
    "gn:admin1_code":"03",
    "gn:admin2_code":"47",
    "gn:admin3_code":"34906000.0",
    "gn:asciiname":"Santa Clara",
    "gn:country_code":"PH",
    "gn:dem":33,
    "gn:feature_class":"P",
    "gn:feature_code":"PPL",
    "gn:name":"Santa Clara",
    "gn:population":0,
    "gn:timezone":"Asia/Manila",
    "iso:country":"PH",
    "name:fil_x_preferred":[
        "Santa Clara"
    ],
    "name:fil_x_variant":[
        "Santa Clara Malki"
    ],
    "name:und_x_variant":[
        "Santa Clara Malki",
        "Santa Clara"
    ],
    "wof:name":"Santa Clara",
    "wof:placetype":"locality"
},
  "geometry": {"coordinates":[120.7158,15.7063],"type":"Point"}
}