{
  "type": "Feature",
  "properties": {
    "gn:country":"PH",
    "gn:fcode":"ADM3",
    "gn:pop":32288,
    "iso:country":"PH",
    "name:ceb_x_preferred":[
        "Madridejos"
    ],
    "name:deu_x_preferred":[
        "Madridejos"
    ],
    "name:fra_x_preferred":[
        "Madridejos"
    ],
    "name:ita_x_preferred":[
        "Madridejos"
    ],
    "name:nld_x_preferred":[
        "Madridejos"
    ],
    "name:war_x_preferred":[
        "Madridejos"
    ],
    "qs:name":"Madridejos",
    "qs:photos_9r":0,
    "qs:photos_sr":0,
    "qs:pop_sr":"7",
    "wd:wordcount":26,
    "wof:name":"Madridejos",
    "wof:placetype":"localadmin",
    "wof:population":32288
},
  "geometry": {"coordinates":[123.73333,11.26667],"type":"Point"}
}