{
  "type": "Feature",
  "properties": {
    "gn:country":"PH",
    "gn:fcode":"PPL",
    "gn:pop":2219,
    "iso:country":"PH",
    "name:fil_x_preferred":[
        "Bil-Loca"
    ],
    "qs:name":"Bil-Loca",
    "qs:photos_9r":0,
    "qs:photos_sr":0,
    "qs:pop_sr":"4",
    "wof:name":"Bil-Loca",
    "wof:placetype":"locality",
    "wof:population":2219
},
  "geometry": {"coordinates":[120.56870000000001,18.0875],"type":"Point"}
}