{
  "type": "Feature",
  "properties": {
    "gn:admin1_code":"01",
    "gn:admin2_code":"29",
    "gn:admin3_code":"12908000.0",
    "gn:asciiname":"Maspiil",
    "gn:country_code":"PH",
    "gn:dem":407,
    "gn:feature_class":"P",
    "gn:feature_code":"PPL",
    "gn:name":"Maspiil",
    "gn:population":0,
    "gn:timezone":"Asia/Manila",
    "iso:country":"PH",
    "name:fil_x_preferred":[
        "Maspiil"
    ],
    "wof:name":"Maspiil",
    "wof:placetype":"locality"
},
  "geometry": {"coordinates":[120.73333,17.01667],"type":"Point"}
}