{
  "type": "Feature",
  "properties": {
    "gn:admin1_code":"08",
    "gn:admin2_code":"55",
    "gn:admin3_code":"86003000.0",
    "gn:asciiname":"Obrevo",
    "gn:country_code":"PH",
    "gn:dem":4,
    "gn:feature_class":"P",
    "gn:feature_code":"PPL",
    "gn:name":"Obrevo",
    "gn:population":0,
    "gn:timezone":"Asia/Manila",
    "iso:country":"PH",
    "name:fil_x_preferred":[
        "Obrero"
    ],
    "wof:name":"Obrevo",
    "wof:placetype":"locality"
},
  "geometry": {"coordinates":[124.59139999999999,12.0687],"type":"Point"}
}