{
  "type": "Feature",
  "properties": {
    "gn:admin1_code":"02",
    "gn:admin2_code":"31",
    "gn:admin3_code":"23131000.0",
    "gn:asciiname":"Maldam East",
    "gn:country_code":"PH",
    "gn:dem":100,
    "gn:feature_class":"P",
    "gn:feature_code":"PPL",
    "gn:name":"Maldam East",
    "gn:population":0,
    "gn:timezone":"Asia/Manila",
    "iso:country":"PH",
    "name:eng_x_preferred":[
        "Maldam East"
    ],
    "wof:name":"Maldam East",
    "wof:placetype":"locality"
},
  "geometry": {"coordinates":[122.07374,16.93165],"type":"Point"}
}