{
  "type": "Feature",
  "properties": {
    "gn:admin1_code":"08",
    "gn:admin2_code":"37",
    "gn:admin3_code":"83705000.0",
    "gn:asciiname":"Nabungkagan",
    "gn:country_code":"PH",
    "gn:dem":3,
    "gn:feature_class":"P",
    "gn:feature_code":"PPL",
    "gn:name":"Nabungkagan",
    "gn:population":0,
    "gn:timezone":"Asia/Manila",
    "iso:country":"PH",
    "name:eng_x_preferred":[
        "Nabungkagan"
    ],
    "wof:name":"Nabungkagan",
    "wof:placetype":"locality"
},
  "geometry": {"coordinates":[124.8087,11.4036],"type":"Point"}
}