{
  "type": "Feature",
  "properties": {
    "gn:admin1_code":"07",
    "gn:admin2_code":"46",
    "gn:admin3_code":"74619000.0",
    "gn:asciiname":"Napacao",
    "gn:country_code":"PH",
    "gn:dem":377,
    "gn:feature_class":"P",
    "gn:feature_code":"PPL",
    "gn:name":"Napacao",
    "gn:population":0,
    "gn:timezone":"Asia/Manila",
    "iso:country":"PH",
    "name:fil_x_preferred":[
        "Napacao"
    ],
    "wof:name":"Napacao",
    "wof:placetype":"locality"
},
  "geometry": {"coordinates":[123.09999999999999,9.15],"type":"Point"}
}