{
  "type": "Feature",
  "properties": {
    "gn:country":"PH",
    "gn:fcode":"ADM3",
    "gn:pop":65931,
    "iso:country":"PH",
    "name:fil_x_preferred":[
        "Mangatarem"
    ],
    "qs:name":"Mangatarem",
    "qs:photos_9r":0,
    "qs:photos_sr":0,
    "qs:pop_sr":"8",
    "wof:name":"Mangatarem",
    "wof:placetype":"localadmin",
    "wof:population":65931
},
  "geometry": {"coordinates":[120.26667,15.73333],"type":"Point"}
}