{
  "type": "Feature",
  "properties": {
    "gn:country":"PH",
    "gn:fcode":"ADM3",
    "gn:population":65931,
    "iso:country":"PH",
    "name:bcl_x_preferred":[
        "Mangatarem"
    ],
    "name:ceb_x_preferred":[
        "Mangatarem"
    ],
    "name:deu_x_preferred":[
        "Mangatarem"
    ],
    "name:fil_x_preferred":[
        "Mangatarem"
    ],
    "name:fra_x_preferred":[
        "Mangatarem"
    ],
    "name:ilo_x_preferred":[
        "Mangatarem"
    ],
    "name:ind_x_preferred":[
        "Mangatarem"
    ],
    "name:ita_x_preferred":[
        "Mangatarem"
    ],
    "name:nld_x_preferred":[
        "Mangatarem"
    ],
    "name:pag_x_preferred":[
        "Mangatarem"
    ],
    "name:pam_x_preferred":[
        "Mangatarem"
    ],
    "name:spa_x_preferred":[
        "Mangatarem"
    ],
    "name:swe_x_preferred":[
        "Mangatarem"
    ],
    "name:tgl_x_preferred":[
        "Mangatarem"
    ],
    "name:vie_x_preferred":[
        "Mangatarem"
    ],
    "name:war_x_preferred":[
        "Mangatarem"
    ],
    "qs:name":"Mangatarem",
    "qs:photos_9r":0,
    "qs:photos_sr":0,
    "qs:pop_sr":"8",
    "wof:name":"Mangatarem",
    "wof:placetype":"localadmin",
    "wof:population":65931
},
  "geometry": {"coordinates":[120.26667,15.73333],"type":"Point"}
}