{
  "type": "Feature",
  "properties": {
    "gn:admin1_code":"14",
    "gn:admin2_code":"60",
    "gn:admin3_code":"156609000.0",
    "gn:asciiname":"Silangkan Market",
    "gn:country_code":"PH",
    "gn:dem":18,
    "gn:feature_class":"P",
    "gn:feature_code":"PPL",
    "gn:name":"Silangkan Market",
    "gn:population":0,
    "gn:timezone":"Asia/Manila",
    "iso:country":"PH",
    "name:eng_x_preferred":[
        "Silangkan Market"
    ],
    "name:und_x_variant":[
        "Cilancan",
        "Silangkan"
    ],
    "wof:name":"Silangkan Market",
    "wof:placetype":"locality"
},
  "geometry": {"coordinates":[120.89149999999999,5.9788],"type":"Point"}
}