{
  "type": "Feature",
  "properties": {
    "gn:admin1_code":"06",
    "gn:admin2_code":"30",
    "gn:admin3_code":"63025000.0",
    "gn:asciiname":"Binulusan",
    "gn:country_code":"PH",
    "gn:dem":346,
    "gn:feature_class":"P",
    "gn:feature_code":"PPL",
    "gn:name":"Binulusan",
    "gn:population":0,
    "gn:timezone":"Asia/Manila",
    "iso:country":"PH",
    "name:fil_x_preferred":[
        "Binulusan"
    ],
    "wof:name":"Binulusan",
    "wof:placetype":"locality"
},
  "geometry": {"coordinates":[122.38311000000002,11.14062],"type":"Point"}
}