{
  "type": "Feature",
  "properties": {
    "gn:admin1_code":"05",
    "gn:admin2_code":"16",
    "gn:admin3_code":"51730000.0",
    "gn:asciiname":"Agrupacion",
    "gn:country_code":"PH",
    "gn:dem":71,
    "gn:feature_class":"P",
    "gn:feature_code":"PPL",
    "gn:name":"Agrupacion",
    "gn:population":0,
    "gn:timezone":"Asia/Manila",
    "iso:country":"PH",
    "name:fil_x_preferred":[
        "Agrupacion"
    ],
    "wof:name":"Agrupacion",
    "wof:placetype":"locality"
},
  "geometry": {"coordinates":[122.81659999999999,13.7987],"type":"Point"}
}