{
  "type": "Feature",
  "properties": {
    "gn:country":"PH",
    "gn:fcode":"ADM3",
    "gn:population":16507,
    "iso:country":"PH",
    "name:fil_x_preferred":[
        "Lagawe"
    ],
    "qs:name":"Lagawe",
    "qs:photos_9r":0,
    "qs:photos_sr":0,
    "qs:pop_sr":"6",
    "wof:name":"Lagawe",
    "wof:placetype":"localadmin",
    "wof:population":16507
},
  "geometry": {"coordinates":[121.23333,16.78333],"type":"Point"}
}