{
  "type": "Feature",
  "properties": {
    "gn:country":"PH",
    "gn:fcode":"PPL",
    "gn:pop":14729,
    "iso:country":"PH",
    "name:fil_x_preferred":[
        "Lalig"
    ],
    "qs:name":"Lalig",
    "qs:photos_9r":0,
    "qs:photos_sr":0,
    "qs:pop_sr":"6",
    "wof:name":"Lalig",
    "wof:placetype":"locality",
    "wof:population":14729
},
  "geometry": {"coordinates":[121.32647,13.98255],"type":"Point"}
}