{
  "type": "Feature",
  "properties": {
    "gn:admin1_code":"09",
    "gn:admin2_code":"66",
    "gn:admin3_code":"97332000.0",
    "gn:asciiname":"Muroc",
    "gn:country_code":"PH",
    "gn:dem":428,
    "gn:feature_class":"P",
    "gn:feature_code":"PPL",
    "gn:name":"Muroc",
    "gn:population":0,
    "gn:timezone":"Asia/Manila",
    "iso:country":"PH",
    "wof:name":"Muroc",
    "wof:placetype":"locality"
},
  "geometry": {"coordinates":[122.095,7.01611],"type":"Point"}
}