{
  "type": "Feature",
  "properties": {
    "gn:admin1_code":"06",
    "gn:admin2_code":"H3",
    "gn:admin3_code":"64531000.0",
    "gn:asciiname":"Cancilayan",
    "gn:country_code":"PH",
    "gn:dem":131,
    "gn:feature_class":"P",
    "gn:feature_code":"PPL",
    "gn:name":"Cancilayan",
    "gn:population":0,
    "gn:timezone":"Asia/Manila",
    "iso:country":"PH",
    "name:fil_x_preferred":[
        "Cancilayan"
    ],
    "wof:name":"Cancilayan",
    "wof:placetype":"locality"
},
  "geometry": {"coordinates":[123.1498,10.8245],"type":"Point"}
}