{
  "type": "Feature",
  "properties": {
    "gn:country":"PH",
    "gn:fcode":"PPLA3",
    "gn:pop":8723,
    "iso:country":"PH",
    "name:bcl_x_preferred":[
        "Coron"
    ],
    "name:cat_x_preferred":[
        "Coron"
    ],
    "name:deu_x_preferred":[
        "Coron"
    ],
    "name:eng_x_preferred":[
        "Coron"
    ],
    "name:fas_x_preferred":[
        "\u06a9\u0648\u0631\u0648\u0646\u060c \u067e\u0627\u0644\u0627\u0648\u0627\u0646"
    ],
    "name:fil_x_preferred":[
        "Coron"
    ],
    "name:fra_x_preferred":[
        "Coron"
    ],
    "name:ilo_x_preferred":[
        "Coron"
    ],
    "name:ind_x_preferred":[
        "Coron"
    ],
    "name:ita_x_preferred":[
        "Coron"
    ],
    "name:jpn_x_preferred":[
        "\u30b3\u30ed\u30f3"
    ],
    "name:nld_x_preferred":[
        "Coron"
    ],
    "name:oci_x_preferred":[
        "Coron"
    ],
    "name:pag_x_preferred":[
        "Coron"
    ],
    "name:pam_x_preferred":[
        "Coron"
    ],
    "name:spa_x_preferred":[
        "Cor\u00f3n"
    ],
    "name:swe_x_preferred":[
        "Coron"
    ],
    "name:tgl_x_preferred":[
        "Coron"
    ],
    "name:vie_x_preferred":[
        "Coron"
    ],
    "name:war_x_preferred":[
        "Coron"
    ],
    "name:zho_x_preferred":[
        "\u79d1\u9686"
    ],
    "qs:name":"Coron",
    "qs:photos_9r":0,
    "qs:photos_sr":0,
    "qs:pop_sr":"5",
    "wd:wordcount":88,
    "wof:name":"Coron",
    "wof:placetype":"locality",
    "wof:population":8723
},
  "geometry": {"coordinates":[120.2043,11.9986],"type":"Point"}
}