{
  "type": "Feature",
  "properties": {
    "gn:admin1_code":"03",
    "gn:admin2_code":"50",
    "gn:admin3_code":"35408000.0",
    "gn:asciiname":"Dau",
    "gn:country_code":"PH",
    "gn:dem":11,
    "gn:feature_class":"P",
    "gn:feature_code":"PPL",
    "gn:name":"Dau",
    "gn:population":0,
    "gn:timezone":"Asia/Manila",
    "iso:country":"PH",
    "name:cat_x_preferred":[
        "Dau"
    ],
    "name:ceb_x_preferred":[
        "Dau"
    ],
    "name:fil_x_preferred":[
        "Dau"
    ],
    "name:swe_x_preferred":[
        "Dau"
    ],
    "wof:name":"Dau",
    "wof:placetype":"locality"
},
  "geometry": {"coordinates":[120.5468,14.9146],"type":"Point"}
}