{
  "type": "Feature",
  "properties": {
    "gn:admin1_code":"15",
    "gn:admin2_code":"10",
    "gn:admin3_code":"141105000.0",
    "gn:asciiname":"Amgaleyley",
    "gn:country_code":"PH",
    "gn:dem":1893,
    "gn:feature_class":"P",
    "gn:feature_code":"PPL",
    "gn:name":"Amgaleyley",
    "gn:population":0,
    "gn:timezone":"Asia/Manila",
    "iso:country":"PH",
    "name:fil_x_preferred":[
        "Amgaleyley"
    ],
    "name:fil_x_variant":[
        "Angaleyguey"
    ],
    "wof:name":"Amgaleyley",
    "wof:placetype":"locality"
},
  "geometry": {"coordinates":[120.81134,16.71647],"type":"Point"}
}