{
  "type": "Feature",
  "properties": {
    "gn:admin1_code":"02",
    "gn:admin2_code":"31",
    "gn:admin3_code":"23120000.0",
    "gn:asciiname":"Rangayan",
    "gn:country_code":"PH",
    "gn:dem":80,
    "gn:feature_class":"P",
    "gn:feature_code":"PPL",
    "gn:name":"Rangayan",
    "gn:population":0,
    "gn:timezone":"Asia/Manila",
    "iso:country":"PH",
    "name:fil_x_preferred":[
        "Rang-Ayan"
    ],
    "wof:name":"Rangayan",
    "wof:placetype":"locality"
},
  "geometry": {"coordinates":[121.898,16.94916],"type":"Point"}
}