{
  "type": "Feature",
  "properties": {
    "gn:admin1_code":"15",
    "gn:admin2_code":"10",
    "gn:admin3_code":"141107000.0",
    "gn:asciiname":"Padeyto",
    "gn:country_code":"PH",
    "gn:dem":1544,
    "gn:feature_class":"P",
    "gn:feature_code":"PPL",
    "gn:name":"Padeyto",
    "gn:population":0,
    "gn:timezone":"Asia/Manila",
    "iso:country":"PH",
    "name:fil_x_preferred":[
        "Padeyto"
    ],
    "wof:name":"Padeyto",
    "wof:placetype":"locality"
},
  "geometry": {"coordinates":[120.83614,16.63598],"type":"Point"}
}