{
  "type": "Feature",
  "properties": {
    "gn:admin1_code":"03",
    "gn:admin2_code":"47",
    "gn:admin3_code":"34930000.0",
    "gn:asciiname":"Bantug na Malaki",
    "gn:country_code":"PH",
    "gn:dem":46,
    "gn:feature_class":"P",
    "gn:feature_code":"PPL",
    "gn:name":"Bantug na Malaki",
    "gn:population":0,
    "gn:timezone":"Asia/Manila",
    "iso:country":"PH",
    "wof:name":"Bantug na Malaki",
    "wof:placetype":"locality"
},
  "geometry": {"coordinates":[120.93333,15.61667],"type":"Point"}
}