{
  "type": "Feature",
  "properties": {
    "iso:country":"PH",
    "name:bcl_x_preferred":[
        "Marantao"
    ],
    "name:cbk_zam_x_preferred":[
        "Marantao"
    ],
    "name:ceb_x_preferred":[
        "Marantao"
    ],
    "name:deu_x_preferred":[
        "Marantao"
    ],
    "name:eng_x_preferred":[
        "Marantao"
    ],
    "name:fra_x_preferred":[
        "Marantao"
    ],
    "name:ilo_x_preferred":[
        "Marantao"
    ],
    "name:ind_x_preferred":[
        "Marantao"
    ],
    "name:ita_x_preferred":[
        "Marantao"
    ],
    "name:nld_x_preferred":[
        "Marantao"
    ],
    "name:pag_x_preferred":[
        "Marantao"
    ],
    "name:pam_x_preferred":[
        "Marantao"
    ],
    "name:spa_x_preferred":[
        "Marantao"
    ],
    "name:swe_x_preferred":[
        "Marantao"
    ],
    "name:tgl_x_preferred":[
        "Marantao"
    ],
    "name:urd_x_preferred":[
        "\u0645\u0627\u0631\u0627\u0646\u062a\u0627\u0648\u060c \u0644\u0627\u0646\u0627\u0624 \u062c\u0646\u0648\u0628\u06cc"
    ],
    "name:urd_x_variant":[
        "\u0645\u0627\u0631\u0627\u0646\u062a\u0627\u0648"
    ],
    "name:vie_x_preferred":[
        "Marantao"
    ],
    "name:war_x_preferred":[
        "Marantao"
    ],
    "qs:gn_country":"PH",
    "qs:gn_fcode":"PPLA3",
    "qs:gn_pop":3572,
    "qs:name":"Marantao",
    "qs:name_adm0":"Philippines",
    "qs:name_adm1":"Autonomous Region in Muslim Mindanao",
    "qs:photos":0,
    "qs:photos_1k":0,
    "qs:photos_9k":0,
    "qs:photos_9r":0,
    "qs:photos_all":0,
    "qs:photos_sr":0,
    "qs:placetype":"Town",
    "qs:pop_sr":"4",
    "qs:woe_adm0":23424934,
    "wd:wordcount":148,
    "wof:name":"Marantao",
    "wof:placetype":"locality",
    "wof:population":3572
},
  "geometry": {"coordinates":[124.23333,7.95],"type":"Point"}
}