{
  "type": "Feature",
  "properties": {
    "iso:country":"PH",
    "name:ast_x_preferred":[
        "San Miguel"
    ],
    "name:bcl_x_preferred":[
        "San Miguel"
    ],
    "name:cat_x_preferred":[
        "San Miguel"
    ],
    "name:cbk_zam_x_preferred":[
        "San Miguel"
    ],
    "name:ceb_x_preferred":[
        "San Miguel"
    ],
    "name:deu_x_preferred":[
        "San Miguel"
    ],
    "name:eng_x_preferred":[
        "San Miguel"
    ],
    "name:fil_x_preferred":[
        "San Miguel"
    ],
    "name:fra_x_preferred":[
        "San Miguel"
    ],
    "name:ilo_x_preferred":[
        "San Miguel"
    ],
    "name:ind_x_preferred":[
        "San Miguel"
    ],
    "name:ita_x_preferred":[
        "San Miguel"
    ],
    "name:nld_x_preferred":[
        "San Miguel"
    ],
    "name:nob_x_preferred":[
        "San Miguel"
    ],
    "name:oci_x_preferred":[
        "San Miguel"
    ],
    "name:pag_x_preferred":[
        "San Muigel Mayumo"
    ],
    "name:pag_x_variant":[
        "San Miguel"
    ],
    "name:pam_x_preferred":[
        "San Miguel"
    ],
    "name:spa_x_preferred":[
        "San Miguel"
    ],
    "name:tgl_x_preferred":[
        "San Miguel"
    ],
    "name:urd_x_preferred":[
        "\u0633\u0627\u0646 \u0645\u06cc\u06af\u0648\u0626\u06cc\u0644"
    ],
    "name:vie_x_preferred":[
        "San Miguel"
    ],
    "name:war_x_preferred":[
        "San Miguel"
    ],
    "qs:gn_country":"PH",
    "qs:gn_fcode":"PPL",
    "qs:gn_pop":65661,
    "qs:name":"San Miguel",
    "qs:name_adm0":"Philippines",
    "qs:name_adm1":"Central Luzon",
    "qs:photos":69,
    "qs:photos_1k":14,
    "qs:photos_9k":1,
    "qs:photos_9r":2,
    "qs:photos_all":69,
    "qs:photos_sr":2,
    "qs:placetype":"Town",
    "qs:pop_sr":"8",
    "qs:woe_adm0":23424934,
    "wd:wordcount":1285,
    "wof:name":"San Miguel",
    "wof:placetype":"locality",
    "wof:population":65661
},
  "geometry": {"coordinates":[120.97568,15.1423],"type":"Point"}
}