{
  "type": "Feature",
  "properties": {
    "gn:admin1_code":"40",
    "gn:admin2_code":"20",
    "gn:admin3_code":"42106000.0",
    "gn:asciiname":"San Dionisio",
    "gn:country_code":"PH",
    "gn:dem":80,
    "gn:feature_class":"P",
    "gn:feature_code":"PPL",
    "gn:name":"San Dionisio",
    "gn:population":0,
    "gn:timezone":"Asia/Manila",
    "iso:country":"PH",
    "name:ceb_x_preferred":[
        "San Dionisio"
    ],
    "name:fra_x_preferred":[
        "San Dionisio"
    ],
    "name:nld_x_preferred":[
        "San Dionisio"
    ],
    "name:por_x_preferred":[
        "San Dionisio"
    ],
    "name:spa_x_preferred":[
        "San Dionisio"
    ],
    "name:srp_x_preferred":[
        "\u0421\u0430\u043d \u0414\u0438\u043e\u043d\u0438\u0441\u0438\u043e"
    ],
    "name:swe_x_preferred":[
        "San Dionisio"
    ],
    "name:und_x_variant":[
        "Barangay Uno"
    ],
    "wof:name":"San Dionisio",
    "wof:placetype":"locality"
},
  "geometry": {"coordinates":[120.95244,14.3414],"type":"Point"}
}