{
  "type": "Feature",
  "properties": {
    "gn:admin1_code":"03",
    "gn:admin2_code":"63",
    "gn:admin3_code":"36916000.0",
    "gn:asciiname":"San Jose de Urquico",
    "gn:country_code":"PH",
    "gn:dem":60,
    "gn:feature_class":"P",
    "gn:feature_code":"PPL",
    "gn:name":"San Jose de Urquico",
    "gn:population":0,
    "gn:timezone":"Asia/Manila",
    "iso:country":"PH",
    "name:fil_x_preferred":[
        "San Jose"
    ],
    "wof:name":"San Jose de Urquico",
    "wof:placetype":"locality"
},
  "geometry": {"coordinates":[120.56773,15.4554],"type":"Point"}
}