{
  "type": "Feature",
  "properties": {
    "gn:admin1_code":"03",
    "gn:admin2_code":"50",
    "gn:admin3_code":"35414000.0",
    "gn:asciiname":"Dawe",
    "gn:country_code":"PH",
    "gn:dem":6,
    "gn:feature_class":"P",
    "gn:feature_code":"PPL",
    "gn:name":"Dawe",
    "gn:population":0,
    "gn:timezone":"Asia/Manila",
    "iso:country":"PH",
    "wof:name":"Dawe",
    "wof:placetype":"locality"
},
  "geometry": {"coordinates":[120.67565999999999,14.95133],"type":"Point"}
}