{
  "type": "Feature",
  "properties": {
    "gn:admin1_code":"02",
    "gn:admin2_code":"31",
    "gn:admin3_code":"23114000.0",
    "gn:asciiname":"Arusip",
    "gn:country_code":"PH",
    "gn:dem":41,
    "gn:feature_class":"P",
    "gn:feature_code":"PPL",
    "gn:name":"Arusip",
    "gn:population":0,
    "gn:timezone":"Asia/Manila",
    "iso:country":"PH",
    "name:fil_x_preferred":[
        "Arusip"
    ],
    "wof:name":"Arusip",
    "wof:placetype":"locality"
},
  "geometry": {"coordinates":[121.84893,17.11697],"type":"Point"}
}