{
  "type": "Feature",
  "properties": {
    "gn:country":"PH",
    "gn:fcode":"PPL",
    "gn:pop":7587,
    "iso:country":"PH",
    "name:fil_x_preferred":[
        "Masaya"
    ],
    "qs:name":"Masaya",
    "qs:photos_9r":0,
    "qs:photos_sr":0,
    "qs:pop_sr":"5",
    "wd:wordcount":1539,
    "wof:name":"Masaya",
    "wof:placetype":"locality",
    "wof:population":7587
},
  "geometry": {"coordinates":[121.27330000000001,14.1434],"type":"Point"}
}