{
  "type": "Feature",
  "properties": {
    "gn:country":"PH",
    "gn:fcode":"PPL",
    "gn:pop":7587,
    "iso:country":"PH",
    "name:ara_x_preferred":[
        "\u0645\u0633\u0627\u064a\u0627"
    ],
    "name:bul_x_preferred":[
        "\u041c\u0430\u0441\u0430\u044f"
    ],
    "name:ces_x_preferred":[
        "Masaya"
    ],
    "name:deu_x_preferred":[
        "Masaya"
    ],
    "name:epo_x_preferred":[
        "Masaya"
    ],
    "name:eus_x_preferred":[
        "Masaya"
    ],
    "name:fil_x_preferred":[
        "Masaya"
    ],
    "name:fin_x_preferred":[
        "Masaya"
    ],
    "name:fra_x_preferred":[
        "Masaya"
    ],
    "name:hrv_x_preferred":[
        "Masaya"
    ],
    "name:hun_x_preferred":[
        "Masaya"
    ],
    "name:ido_x_preferred":[
        "Masaya"
    ],
    "name:jpn_x_preferred":[
        "\u30de\u30b5\u30e4"
    ],
    "name:kat_x_preferred":[
        "\u10db\u10d0\u10e1\u10d0\u10d8\u10d0"
    ],
    "name:kor_x_preferred":[
        "\ub9c8\uc0ac\uc57c"
    ],
    "name:lit_x_preferred":[
        "Masaja"
    ],
    "name:mon_x_preferred":[
        "\u041c\u0430\u0441\u0430\u044f"
    ],
    "name:nld_x_preferred":[
        "Masaya"
    ],
    "name:nor_x_preferred":[
        "Masaya"
    ],
    "name:pol_x_preferred":[
        "Masaya"
    ],
    "name:rus_x_preferred":[
        "\u041c\u0430\u0441\u0430\u044f"
    ],
    "name:sco_x_preferred":[
        "Masaya"
    ],
    "name:spa_x_preferred":[
        "Masaya"
    ],
    "name:swe_x_preferred":[
        "Masaya"
    ],
    "name:tha_x_preferred":[
        "\u0e21\u0e32\u0e0b\u0e32\u0e22\u0e32"
    ],
    "name:ukr_x_preferred":[
        "\u041c\u0430\u0441\u0430\u0439\u044f"
    ],
    "name:urd_x_preferred":[
        "\u0645\u0627\u0633\u0627\u06cc\u0627"
    ],
    "name:vie_x_preferred":[
        "Masaya"
    ],
    "name:war_x_preferred":[
        "Masaya"
    ],
    "name:zho_x_preferred":[
        "\u99ac\u85a9\u4e9e"
    ],
    "qs:name":"Masaya",
    "qs:photos_9r":0,
    "qs:photos_sr":0,
    "qs:pop_sr":"5",
    "wd:wordcount":1539,
    "wof:name":"Masaya",
    "wof:placetype":"locality",
    "wof:population":7587
},
  "geometry": {"coordinates":[121.27330000000001,14.1434],"type":"Point"}
}