{
  "type": "Feature",
  "properties": {
    "gn:admin1_code":"07",
    "gn:admin2_code":"21",
    "gn:admin3_code":"72229000.0",
    "gn:asciiname":"Lanaya",
    "gn:country_code":"PH",
    "gn:dem":542,
    "gn:feature_class":"P",
    "gn:feature_code":"PPL",
    "gn:name":"Lanaya",
    "gn:population":0,
    "gn:timezone":"Asia/Manila",
    "iso:country":"PH",
    "name:fil_x_preferred":[
        "Lanaya"
    ],
    "name:tam_x_preferred":[
        "\u0bb2\u0ba9\u0baf\u0bbe"
    ],
    "wof:name":"Lanaya",
    "wof:placetype":"locality"
},
  "geometry": {"coordinates":[123.36667,9.68333],"type":"Point"}
}