{
  "type": "Feature",
  "properties": {
    "gn:admin1_code":"05",
    "gn:admin2_code":"58",
    "gn:admin3_code":"56207000.0",
    "gn:asciiname":"Tinanogan",
    "gn:country_code":"PH",
    "gn:dem":10,
    "gn:feature_class":"P",
    "gn:feature_code":"PPL",
    "gn:name":"Tinanogan",
    "gn:population":0,
    "gn:timezone":"Asia/Manila",
    "iso:country":"PH",
    "name:fil_x_preferred":[
        "Tinanogan"
    ],
    "name:und_x_variant":[
        "Catundulan"
    ],
    "wof:name":"Tinanogan",
    "wof:placetype":"locality"
},
  "geometry": {"coordinates":[123.5343,12.9486],"type":"Point"}
}