{
  "type": "Feature",
  "properties": {
    "gn:admin1_code":"14",
    "gn:admin2_code":"56",
    "gn:admin3_code":"153811000.0",
    "gn:asciiname":"Talauban",
    "gn:country_code":"PH",
    "gn:dem":39,
    "gn:feature_class":"P",
    "gn:feature_code":"PPL",
    "gn:name":"Talauban",
    "gn:population":0,
    "gn:timezone":"Asia/Manila",
    "iso:country":"PH",
    "wof:name":"Talauban",
    "wof:placetype":"locality"
},
  "geometry": {"coordinates":[124.06028000000001,7.35028],"type":"Point"}
}