{
  "type": "Feature",
  "properties": {
    "gn:admin1_code":"07",
    "gn:admin2_code":"11",
    "gn:admin3_code":"71236000.0",
    "gn:asciiname":"Libertad Norte",
    "gn:country_code":"PH",
    "gn:dem":267,
    "gn:feature_class":"P",
    "gn:feature_code":"PPL",
    "gn:name":"Libertad Norte",
    "gn:population":0,
    "gn:timezone":"Asia/Manila",
    "iso:country":"PH",
    "name:fil_x_preferred":[
        "Libertad Norte"
    ],
    "wof:name":"Libertad Norte",
    "wof:placetype":"locality"
},
  "geometry": {"coordinates":[124.1191,9.8923],"type":"Point"}
}