{
  "type": "Feature",
  "properties": {
    "gn:admin1_code":"08",
    "gn:admin2_code":"37",
    "gn:admin3_code":"83729000.0",
    "gn:asciiname":"Kabayugan",
    "gn:country_code":"PH",
    "gn:dem":21,
    "gn:feature_class":"P",
    "gn:feature_code":"PPL",
    "gn:name":"Kabayugan",
    "gn:population":0,
    "gn:timezone":"Asia/Manila",
    "iso:country":"PH",
    "name:fil_x_preferred":[
        "Kabayugan"
    ],
    "wof:name":"Kabayugan",
    "wof:placetype":"locality"
},
  "geometry": {"coordinates":[124.4409,11.3837],"type":"Point"}
}