{
  "type": "Feature",
  "properties": {
    "gn:country":"PH",
    "gn:fcode":"ADM3",
    "gn:pop":17804,
    "iso:country":"PH",
    "name:fil_x_preferred":[
        "Dupax del Sur"
    ],
    "qs:name":"Dupax del Sur",
    "qs:photos_9r":0,
    "qs:photos_sr":0,
    "qs:pop_sr":"6",
    "wd:wordcount":451,
    "wof:name":"Dupax del Sur",
    "wof:placetype":"localadmin",
    "wof:population":17804
},
  "geometry": {"coordinates":[121.18333,16.13333],"type":"Point"}
}