{
  "type": "Feature",
  "properties": {
    "gn:country":"PH",
    "gn:fcode":"ADM3",
    "gn:pop":17804,
    "iso:country":"PH",
    "name:bcl_x_preferred":[
        "Dupax del Sur"
    ],
    "name:cat_x_preferred":[
        "Dupax del Sur"
    ],
    "name:ceb_x_preferred":[
        "Dupax del Sur"
    ],
    "name:deu_x_preferred":[
        "Dupax del Sur"
    ],
    "name:eng_x_preferred":[
        "Dupax del Sur"
    ],
    "name:fil_x_preferred":[
        "Dupax del Sur"
    ],
    "name:fra_x_preferred":[
        "Dupax del Sur"
    ],
    "name:ilo_x_preferred":[
        "Dupax del Sur"
    ],
    "name:ind_x_preferred":[
        "Dupax del Sur"
    ],
    "name:ita_x_preferred":[
        "Dupax del Sur"
    ],
    "name:jpn_x_preferred":[
        "\u30c7\u30e5\u30d1\u30b9\u30fb\u30c7\u30eb\u30fb\u30b9\u30fc\u30eb"
    ],
    "name:nld_x_preferred":[
        "Dupax del Sur"
    ],
    "name:oci_x_preferred":[
        "Dupax del Sur"
    ],
    "name:pag_x_preferred":[
        "Dupax del Sur"
    ],
    "name:pam_x_preferred":[
        "Dupax del Sur"
    ],
    "name:spa_x_preferred":[
        "Dupax del Sur"
    ],
    "name:swe_x_preferred":[
        "Dupax del Sur"
    ],
    "name:tgl_x_preferred":[
        "Dupax del Sur"
    ],
    "name:vie_x_preferred":[
        "Dupax del Sur"
    ],
    "name:war_x_preferred":[
        "Dupax del Sur"
    ],
    "qs:name":"Dupax del Sur",
    "qs:photos_9r":0,
    "qs:photos_sr":0,
    "qs:pop_sr":"6",
    "wd:wordcount":451,
    "wof:name":"Dupax del Sur",
    "wof:placetype":"localadmin",
    "wof:population":17804
},
  "geometry": {"coordinates":[121.18333,16.13333],"type":"Point"}
}