{
  "type": "Feature",
  "properties": {
    "iso:country":"PH",
    "name:fil_x_preferred":[
        "Caningay"
    ],
    "qs:gn_country":"PH",
    "qs:gn_fcode":"PPL",
    "qs:gn_pop":3296,
    "qs:name":"Caningay",
    "qs:name_adm0":"Philippines",
    "qs:name_adm1":"Western Visayas",
    "qs:photos":0,
    "qs:photos_1k":0,
    "qs:photos_9k":0,
    "qs:photos_9r":0,
    "qs:photos_all":0,
    "qs:photos_sr":0,
    "qs:placetype":"Town",
    "qs:pop_sr":"4",
    "qs:woe_adm0":23424934,
    "wd:wordcount":1520,
    "wof:name":"Caningay",
    "wof:placetype":"locality",
    "wof:population":3296
},
  "geometry": {"coordinates":[122.6442,9.8297],"type":"Point"}
}