{
  "type": "Feature",
  "properties": {
    "gn:country":"PH",
    "gn:fcode":"PPLA3",
    "gn:pop":0,
    "iso:country":"PH",
    "name:bcl_x_preferred":[
        "San Fabian"
    ],
    "name:cat_x_preferred":[
        "San Fabian"
    ],
    "name:dut_x_preferred":[
        "San Fabian"
    ],
    "name:eng_x_preferred":[
        "San Fabian"
    ],
    "name:fil_x_preferred":[
        "San Fabian"
    ],
    "name:fre_x_preferred":[
        "San Fabian"
    ],
    "name:ger_x_preferred":[
        "San Fabian"
    ],
    "name:ilo_x_preferred":[
        "San Fabian"
    ],
    "name:ind_x_preferred":[
        "San Fabian"
    ],
    "name:ita_x_preferred":[
        "San Fabian"
    ],
    "name:jpn_x_preferred":[
        "\u30b5\u30f3\u30d5\u30a1\u30d3\u30a2\u30f3"
    ],
    "name:may_x_preferred":[
        "San Fabian"
    ],
    "name:oci_x_preferred":[
        "San Fabian"
    ],
    "name:pag_x_preferred":[
        "San Fabian"
    ],
    "name:pam_x_preferred":[
        "San Fabian"
    ],
    "name:spa_x_preferred":[
        "San Fabi\u00e1n"
    ],
    "name:swe_x_preferred":[
        "San Fabian"
    ],
    "name:tgl_x_preferred":[
        "San Fabian"
    ],
    "name:unk_x_variant":[
        "Baley na San Fabian"
    ],
    "name:vie_x_preferred":[
        "San Fabian"
    ],
    "name:war_x_preferred":[
        "San Fabian"
    ],
    "qs:name":"San Fabian",
    "qs:photos_9r":0,
    "qs:photos_sr":0,
    "qs:pop_sr":"0",
    "wof:name":"San Fabian",
    "wof:placetype":"locality",
    "wof:population":0
},
  "geometry": {"coordinates":[120.40560000000001,16.1231],"type":"Point"}
}