{
  "type": "Feature",
  "properties": {
    "gn:admin1_code":"06",
    "gn:admin2_code":"06",
    "gn:admin3_code":"60615000.0",
    "gn:asciiname":"Aguila",
    "gn:country_code":"PH",
    "gn:dem":9,
    "gn:feature_class":"P",
    "gn:feature_code":"PPL",
    "gn:name":"Aguila",
    "gn:population":0,
    "gn:timezone":"Asia/Manila",
    "iso:country":"PH",
    "name:fil_x_preferred":[
        "Aguila"
    ],
    "wof:name":"Aguila",
    "wof:placetype":"locality"
},
  "geometry": {"coordinates":[122.0874,11.5105],"type":"Point"}
}