{
  "type": "Feature",
  "properties": {
    "gn:admin1_code":"03",
    "gn:admin2_code":"64",
    "gn:admin3_code":"37106000.0",
    "gn:asciiname":"Pinayonan",
    "gn:country_code":"PH",
    "gn:dem":34,
    "gn:feature_class":"P",
    "gn:feature_code":"PPL",
    "gn:name":"Pinayonan",
    "gn:population":0,
    "gn:timezone":"Asia/Manila",
    "iso:country":"PH",
    "name:fil_x_preferred":[
        "Pinayonan"
    ],
    "wof:name":"Pinayonan",
    "wof:placetype":"locality"
},
  "geometry": {"coordinates":[119.91500000000001,15.5178],"type":"Point"}
}