{
  "type": "Feature",
  "properties": {
    "gn:admin1_code":"02",
    "gn:admin2_code":"14",
    "gn:admin3_code":"21513000.0",
    "gn:asciiname":"Cunig",
    "gn:country_code":"PH",
    "gn:dem":16,
    "gn:feature_class":"P",
    "gn:feature_code":"PPL",
    "gn:name":"Cunig",
    "gn:population":0,
    "gn:timezone":"Asia/Manila",
    "iso:country":"PH",
    "wof:name":"Cunig",
    "wof:placetype":"locality"
},
  "geometry": {"coordinates":[121.6892,18.03188],"type":"Point"}
}