{
  "type": "Feature",
  "properties": {
    "gn:admin1_code":"02",
    "gn:admin2_code":"31",
    "gn:admin3_code":"23113000.0",
    "gn:asciiname":"Lenzon",
    "gn:country_code":"PH",
    "gn:dem":47,
    "gn:feature_class":"P",
    "gn:feature_code":"PPL",
    "gn:name":"Lenzon",
    "gn:population":0,
    "gn:timezone":"Asia/Manila",
    "iso:country":"PH",
    "name:fil_x_preferred":[
        "Lenon"
    ],
    "name:fil_x_variant":[
        "Lenzon"
    ],
    "wof:name":"Lenzon",
    "wof:placetype":"locality"
},
  "geometry": {"coordinates":[121.81088,17.03766],"type":"Point"}
}