{
  "type": "Feature",
  "properties": {
    "iso:country":"PH",
    "name:bcl_x_preferred":[
        "Balilihan"
    ],
    "name:deu_x_preferred":[
        "Balilihan"
    ],
    "name:eng_x_preferred":[
        "Balilihan"
    ],
    "name:fil_x_preferred":[
        "Ilihan"
    ],
    "name:fra_x_preferred":[
        "Balilihan"
    ],
    "name:ilo_x_preferred":[
        "Balilihan"
    ],
    "name:ind_x_preferred":[
        "Balilihan"
    ],
    "name:ita_x_preferred":[
        "Balilihan"
    ],
    "name:nld_x_preferred":[
        "Balilihan"
    ],
    "name:nob_x_preferred":[
        "Balilihan"
    ],
    "name:pag_x_preferred":[
        "Balilihan"
    ],
    "name:pam_x_preferred":[
        "Balilihan"
    ],
    "name:swe_x_preferred":[
        "Balilihan"
    ],
    "name:tgl_x_preferred":[
        "Balilihan"
    ],
    "name:war_x_preferred":[
        "Balilihan"
    ],
    "name:zho_x_preferred":[
        "\u5df4\u91cc\u91cc\u6f22"
    ],
    "qs:gn_country":"PH",
    "qs:gn_fcode":"PPL",
    "qs:gn_pop":0,
    "qs:name":"Balilihan",
    "qs:name_adm0":"Philippines",
    "qs:name_adm1":"Central Visayas",
    "qs:photos":303,
    "qs:photos_1k":61,
    "qs:photos_9k":1,
    "qs:photos_9r":5,
    "qs:photos_all":303,
    "qs:photos_sr":5,
    "qs:placetype":"Town",
    "qs:pop_sr":"0",
    "qs:woe_adm0":23424934,
    "wof:name":"Balilihan",
    "wof:placetype":"locality"
},
  "geometry": {"coordinates":[124.06667,10.03333],"type":"Point"}
}