{
  "type": "Feature",
  "properties": {
    "gn:country":"PH",
    "gn:fcode":"PPLA3",
    "gn:pop":10812,
    "iso:country":"PH",
    "name:bcl_x_preferred":[
        "Pambujan"
    ],
    "name:deu_x_preferred":[
        "Pambujan"
    ],
    "name:eng_x_preferred":[
        "Pambujan"
    ],
    "name:fil_x_preferred":[
        "Pambujan"
    ],
    "name:fra_x_preferred":[
        "Pambujan"
    ],
    "name:ilo_x_preferred":[
        "Pambujan"
    ],
    "name:ind_x_preferred":[
        "Pambujan"
    ],
    "name:ita_x_preferred":[
        "Pambujan"
    ],
    "name:nld_x_preferred":[
        "Pambujan"
    ],
    "name:pag_x_preferred":[
        "Pambujan"
    ],
    "name:pam_x_preferred":[
        "Pambujan"
    ],
    "name:swe_x_preferred":[
        "Pambujan"
    ],
    "name:tgl_x_preferred":[
        "Pambujan"
    ],
    "name:unk_x_variant":[
        "Pamuhan"
    ],
    "name:vie_x_preferred":[
        "Pambujan"
    ],
    "name:war_x_preferred":[
        "Pambujan"
    ],
    "qs:name":"Pambujan",
    "qs:photos_9r":0,
    "qs:photos_sr":0,
    "qs:pop_sr":"6",
    "wof:name":"Pambujan",
    "wof:placetype":"locality",
    "wof:population":10812
},
  "geometry": {"coordinates":[124.9276,12.5642],"type":"Point"}
}