{
  "type": "Feature",
  "properties": {
    "gn:admin1_code":"08",
    "gn:admin2_code":"67",
    "gn:admin3_code":"84814000.0",
    "gn:asciiname":"Lagadian",
    "gn:country_code":"PH",
    "gn:dem":85,
    "gn:feature_class":"P",
    "gn:feature_code":"PPL",
    "gn:name":"Lagadian",
    "gn:population":0,
    "gn:timezone":"Asia/Manila",
    "iso:country":"PH",
    "name:fil_x_preferred":[
        "Lagadian"
    ],
    "name:und_x_variant":[
        "Lagadean"
    ],
    "wof:name":"Lagadian",
    "wof:placetype":"locality"
},
  "geometry": {"coordinates":[125.13330000000001,12.5281],"type":"Point"}
}