{
  "type": "Feature",
  "properties": {
    "gn:admin1_code":"03",
    "gn:admin2_code":"G8",
    "gn:admin3_code":"37702000.0",
    "gn:asciiname":"Dumog",
    "gn:cc2":"PH",
    "gn:country_code":"PH",
    "gn:dem":17,
    "gn:feature_class":"P",
    "gn:feature_code":"PPL",
    "gn:name":"Dumog",
    "gn:population":0,
    "gn:timezone":"Asia/Manila",
    "iso:country":"PH",
    "name:dan_x_preferred":[
        "Dumog"
    ],
    "name:deu_x_preferred":[
        "Dumog"
    ],
    "name:spa_x_preferred":[
        "Dumog"
    ],
    "name:und_x_variant":[
        "Dumag"
    ],
    "wof:name":"Dumog",
    "wof:placetype":"locality"
},
  "geometry": {"coordinates":[122.03667,16.11028],"type":"Point"}
}