{
  "type": "Feature",
  "properties": {
    "gn:admin1_code":"03",
    "gn:admin2_code":"13",
    "gn:admin3_code":"31422000.0",
    "gn:asciiname":"Pasong Callos",
    "gn:country_code":"PH",
    "gn:dem":52,
    "gn:feature_class":"P",
    "gn:feature_code":"PPL",
    "gn:name":"Pasong Callos",
    "gn:population":0,
    "gn:timezone":"Asia/Manila",
    "iso:country":"PH",
    "name:fil_x_preferred":[
        "Pasong Callos"
    ],
    "name:fil_x_variant":[
        "Pasong Bangkal"
    ],
    "wof:name":"Pasong Callos",
    "wof:placetype":"locality"
},
  "geometry": {"coordinates":[121.0151,15.0082],"type":"Point"}
}