{
  "type": "Feature",
  "properties": {
    "gn:admin1_code":"40",
    "gn:admin2_code":"33",
    "gn:admin3_code":"43410000.0",
    "gn:asciiname":"Luquin",
    "gn:country_code":"PH",
    "gn:dem":245,
    "gn:feature_class":"P",
    "gn:feature_code":"PPL",
    "gn:name":"Luquin",
    "gn:population":0,
    "gn:timezone":"Asia/Manila",
    "iso:country":"PH",
    "name:arg_x_preferred":[
        "Luquin"
    ],
    "name:ast_x_preferred":[
        "Lukin"
    ],
    "name:bre_x_preferred":[
        "Lukin"
    ],
    "name:cat_x_preferred":[
        "Luquin"
    ],
    "name:ceb_x_preferred":[
        "Luqu\u00edn"
    ],
    "name:eus_x_preferred":[
        "Lukin"
    ],
    "name:fil_x_preferred":[
        "Luquin"
    ],
    "name:fra_x_preferred":[
        "Luquin"
    ],
    "name:hun_x_preferred":[
        "Luquin"
    ],
    "name:ita_x_preferred":[
        "Luquin"
    ],
    "name:msa_x_preferred":[
        "Luquin"
    ],
    "name:nld_x_preferred":[
        "Luquin"
    ],
    "name:oci_x_preferred":[
        "Lukin"
    ],
    "name:pol_x_preferred":[
        "Luquin"
    ],
    "name:por_x_preferred":[
        "Luquin"
    ],
    "name:rus_x_preferred":[
        "\u041b\u0443\u043a\u0438\u043d"
    ],
    "name:sco_x_preferred":[
        "Luquin"
    ],
    "name:spa_x_preferred":[
        "Luquin"
    ],
    "name:swe_x_preferred":[
        "Luqu\u00edn"
    ],
    "name:ukr_x_preferred":[
        "\u041b\u0443\u043a\u0456\u043d"
    ],
    "name:uzb_x_preferred":[
        "Luquin"
    ],
    "name:vie_x_preferred":[
        "Luquin"
    ],
    "name:war_x_preferred":[
        "Luquin"
    ],
    "wof:name":"Luquin",
    "wof:placetype":"locality"
},
  "geometry": {"coordinates":[121.43333,14.13333],"type":"Point"}
}