{
  "type": "Feature",
  "properties": {
    "gn:admin1_code":"40",
    "gn:admin2_code":"33",
    "gn:admin3_code":"43410000.0",
    "gn:asciiname":"Luquin",
    "gn:country_code":"PH",
    "gn:dem":245,
    "gn:feature_class":"P",
    "gn:feature_code":"PPL",
    "gn:name":"Luquin",
    "gn:population":0,
    "gn:timezone":"Asia/Manila",
    "iso:country":"PH",
    "name:fil_x_preferred":[
        "Luquin"
    ],
    "wof:name":"Luquin",
    "wof:placetype":"locality"
},
  "geometry": {"coordinates":[121.43333,14.13333],"type":"Point"}
}