{
  "type": "Feature",
  "properties": {
    "gn:admin1_code":"07",
    "gn:admin2_code":"21",
    "gn:admin3_code":"72253000.0",
    "gn:asciiname":"General",
    "gn:country_code":"PH",
    "gn:dem":185,
    "gn:feature_class":"P",
    "gn:feature_code":"PPL",
    "gn:name":"General",
    "gn:population":0,
    "gn:timezone":"Asia/Manila",
    "iso:country":"PH",
    "name:fil_x_preferred":[
        "General"
    ],
    "wof:name":"General",
    "wof:placetype":"locality"
},
  "geometry": {"coordinates":[124.45462999999999,10.64205],"type":"Point"}
}