{
  "type": "Feature",
  "properties": {
    "gn:admin1_code":"03",
    "gn:admin2_code":"50",
    "gn:admin3_code":"35412000.0",
    "gn:asciiname":"Sapang Kawayan",
    "gn:country_code":"PH",
    "gn:dem":7,
    "gn:feature_class":"P",
    "gn:feature_code":"PPL",
    "gn:name":"Sapang Kawayan",
    "gn:population":0,
    "gn:timezone":"Asia/Manila",
    "iso:country":"PH",
    "name:fil_x_preferred":[
        "Kawayan"
    ],
    "name:fil_x_variant":[
        "Sapang Kawayan",
        "Sapang Nouyayan",
        "Sapang Nauayan",
        "Sapang Cauayan",
        "Cauayan",
        "Sapang Cawayan"
    ],
    "name:und_x_variant":[
        "Cauayan",
        "Sapang Cawayan",
        "Sapang Cauayan",
        "Sapang Nouyayan",
        "Sapang Nauayan"
    ],
    "wof:name":"Sapang Kawayan",
    "wof:placetype":"locality"
},
  "geometry": {"coordinates":[120.68600000000001,14.80508],"type":"Point"}
}