{
  "type": "Feature",
  "properties": {
    "gn:admin1_code":"09",
    "gn:admin2_code":"ZSI",
    "gn:admin3_code":"98311000.0",
    "gn:asciiname":"Guintocan",
    "gn:country_code":"PH",
    "gn:dem":79,
    "gn:feature_class":"P",
    "gn:feature_code":"PPL",
    "gn:name":"Guintocan",
    "gn:population":0,
    "gn:timezone":"Asia/Manila",
    "iso:country":"PH",
    "name:fil_x_preferred":[
        "Guintocan"
    ],
    "wof:name":"Guintocan",
    "wof:placetype":"locality"
},
  "geometry": {"coordinates":[122.9225,7.61194],"type":"Point"}
}