{
  "type": "Feature",
  "properties": {
    "gn:admin1_code":"40",
    "gn:admin2_code":"33",
    "gn:admin3_code":"43424000.0",
    "gn:asciiname":"Santa Maria Magdalena",
    "gn:country_code":"PH",
    "gn:dem":101,
    "gn:feature_class":"P",
    "gn:feature_code":"PPL",
    "gn:name":"Santa Maria Magdalena",
    "gn:population":0,
    "gn:timezone":"Asia/Manila",
    "iso:country":"PH",
    "name:fil_x_preferred":[
        "Santa Maria Magdalena"
    ],
    "wof:name":"Santa Maria Magdalena",
    "wof:placetype":"locality"
},
  "geometry": {"coordinates":[121.3051,14.0926],"type":"Point"}
}