{
  "type": "Feature",
  "properties": {
    "gn:gn_country":"PH",
    "gn:gn_fcode":"PPL",
    "gn:gn_pop":3017,
    "gn:population":3017,
    "iso:country":"PH",
    "name:fil_x_preferred":[
        "Caraycayon"
    ],
    "qs_pg:aaroncc":"PH",
    "qs_pg:gn_country":"PH",
    "qs_pg:gn_fcode":"PPL",
    "qs_pg:gn_pop":3017,
    "qs_pg:name":"Caraycayon",
    "qs_pg:photos_9r":0,
    "qs_pg:photos_sr":0,
    "qs_pg:pop_sr":4,
    "qs_pg:qs_pg_placetype":"locality",
    "wof:name":"Caraycayon",
    "wof:placetype":"locality",
    "wof:population":3017
},
  "geometry": {"coordinates":[123.48333,13.61667],"type":"Point"}
}