{
  "type": "Feature",
  "properties": {
    "gn:admin1_code":"03",
    "gn:admin2_code":"50",
    "gn:admin3_code":"35401000.0",
    "gn:asciiname":"Santa Terista",
    "gn:country_code":"PH",
    "gn:dem":99,
    "gn:feature_class":"P",
    "gn:feature_code":"PPL",
    "gn:name":"Santa Terista",
    "gn:population":0,
    "gn:timezone":"Asia/Manila",
    "iso:country":"PH",
    "wof:name":"Santa Terista",
    "wof:placetype":"locality"
},
  "geometry": {"coordinates":[120.58472,15.15333],"type":"Point"}
}