{
  "type": "Feature",
  "properties": {
    "gn:admin1_code":"40",
    "gn:admin2_code":"09",
    "gn:admin3_code":"41024000.0",
    "gn:asciiname":"Abiacao",
    "gn:country_code":"PH",
    "gn:dem":98,
    "gn:feature_class":"P",
    "gn:feature_code":"PPL",
    "gn:name":"Abiacao",
    "gn:population":0,
    "gn:timezone":"Asia/Manila",
    "iso:country":"PH",
    "name:fil_x_preferred":[
        "Abiacao"
    ],
    "wof:name":"Abiacao",
    "wof:placetype":"locality"
},
  "geometry": {"coordinates":[120.94289000000001,13.84168],"type":"Point"}
}