{
  "type": "Feature",
  "properties": {
    "gn:admin1_code":"40",
    "gn:admin2_code":"H2",
    "gn:admin3_code":"45640000.0",
    "gn:asciiname":"Payao",
    "gn:country_code":"PH",
    "gn:dem":235,
    "gn:feature_class":"P",
    "gn:feature_code":"PPL",
    "gn:name":"Payao",
    "gn:population":0,
    "gn:timezone":"Asia/Manila",
    "iso:country":"PH",
    "name:ceb_x_preferred":[
        "Payao"
    ],
    "name:fil_x_preferred":[
        "Payao"
    ],
    "name:swe_x_preferred":[
        "Payao"
    ],
    "wof:name":"Payao",
    "wof:placetype":"locality"
},
  "geometry": {"coordinates":[122.59999999999999,13.35],"type":"Point"}
}