{
  "type": "Feature",
  "properties": {
    "gn:admin1_code":"06",
    "gn:admin2_code":"30",
    "gn:admin3_code":"63046000.0",
    "gn:asciiname":"Lanag Sur",
    "gn:country_code":"PH",
    "gn:dem":108,
    "gn:feature_class":"P",
    "gn:feature_code":"PPL",
    "gn:name":"Lanag Sur",
    "gn:population":0,
    "gn:timezone":"Asia/Manila",
    "iso:country":"PH",
    "name:fil_x_preferred":[
        "Lanag Sur"
    ],
    "name:und_x_variant":[
        "Lanag",
        "Lanang"
    ],
    "wof:name":"Lanag Sur",
    "wof:placetype":"locality"
},
  "geometry": {"coordinates":[122.3203,10.75925],"type":"Point"}
}