{
  "type": "Feature",
  "properties": {
    "gn:admin1_code":"40",
    "gn:admin2_code":"H2",
    "gn:admin3_code":"45603000.0",
    "gn:asciiname":"Carinay",
    "gn:country_code":"PH",
    "gn:dem":69,
    "gn:feature_class":"P",
    "gn:feature_code":"PPL",
    "gn:name":"Carinay",
    "gn:population":0,
    "gn:timezone":"Asia/Manila",
    "iso:country":"PH",
    "name:fil_x_preferred":[
        "Carinay"
    ],
    "wof:name":"Carinay",
    "wof:placetype":"locality"
},
  "geometry": {"coordinates":[121.87972000000001,14.03972],"type":"Point"}
}