{
  "type": "Feature",
  "properties": {
    "gn:admin1_code":"09",
    "gn:admin2_code":"ZSI",
    "gn:admin3_code":"98316000.0",
    "gn:asciiname":"Looc Labuan",
    "gn:country_code":"PH",
    "gn:dem":7,
    "gn:feature_class":"P",
    "gn:feature_code":"PPL",
    "gn:name":"Looc Labuan",
    "gn:population":0,
    "gn:timezone":"Asia/Manila",
    "iso:country":"PH",
    "name:und_x_variant":[
        "Looc",
        "Looc Labuan"
    ],
    "wof:name":"Looc Labuan",
    "wof:placetype":"locality"
},
  "geometry": {"coordinates":[122.47129,7.56058],"type":"Point"}
}