{
  "type": "Feature",
  "properties": {
    "gn:admin1_code":"10",
    "gn:admin2_code":"12",
    "gn:admin3_code":"101321000.0",
    "gn:asciiname":"Kulaman",
    "gn:country_code":"PH",
    "gn:dem":412,
    "gn:feature_class":"P",
    "gn:feature_code":"PPL",
    "gn:name":"Kulaman",
    "gn:population":0,
    "gn:timezone":"Asia/Manila",
    "iso:country":"PH",
    "name:fil_x_preferred":[
        "Kulaman"
    ],
    "wof:name":"Kulaman",
    "wof:placetype":"locality"
},
  "geometry": {"coordinates":[125.16916999999999,7.79972],"type":"Point"}
}