{
  "type": "Feature",
  "properties": {
    "gn:admin1_code":"02",
    "gn:admin2_code":"48",
    "gn:admin3_code":"25015000.0",
    "gn:asciiname":"Gadeng",
    "gn:country_code":"PH",
    "gn:dem":670,
    "gn:feature_class":"P",
    "gn:feature_code":"PPL",
    "gn:name":"Gadeng",
    "gn:population":0,
    "gn:timezone":"Asia/Manila",
    "iso:country":"PH",
    "name:fil_x_preferred":[
        "Gadeng"
    ],
    "wof:name":"Gadeng",
    "wof:placetype":"locality"
},
  "geometry": {"coordinates":[121.33333,16.01667],"type":"Point"}
}