{
  "type": "Feature",
  "properties": {
    "gn:admin1_code":"05",
    "gn:admin2_code":"15",
    "gn:admin3_code":"51607000.0",
    "gn:asciiname":"Tarong",
    "gn:country_code":"PH",
    "gn:dem":59,
    "gn:feature_class":"P",
    "gn:feature_code":"PPL",
    "gn:name":"Tarong",
    "gn:population":0,
    "gn:timezone":"Asia/Manila",
    "iso:country":"PH",
    "name:fil_x_preferred":[
        "Tarong"
    ],
    "wof:name":"Tarong",
    "wof:placetype":"locality"
},
  "geometry": {"coordinates":[123.07810000000001,13.9465],"type":"Point"}
}