{
  "type": "Feature",
  "properties": {
    "gn:admin1_code":"10",
    "gn:admin2_code":"34",
    "gn:admin3_code":"103515000.0",
    "gn:asciiname":"Pantao",
    "gn:country_code":"PH",
    "gn:dem":663,
    "gn:feature_class":"P",
    "gn:feature_code":"PPL",
    "gn:name":"Pantao",
    "gn:population":0,
    "gn:timezone":"Asia/Manila",
    "iso:country":"PH",
    "name:fil_x_preferred":[
        "Pantao"
    ],
    "wof:name":"Pantao",
    "wof:placetype":"locality"
},
  "geometry": {"coordinates":[123.95,7.85],"type":"Point"}
}