{
  "type": "Feature",
  "properties": {
    "gn:admin1_code":"15",
    "gn:admin2_code":"H6",
    "gn:admin3_code":"148104000.0",
    "gn:asciiname":"Gubus",
    "gn:country_code":"PH",
    "gn:dem":453,
    "gn:feature_class":"P",
    "gn:feature_code":"PPL",
    "gn:name":"Gubus",
    "gn:population":0,
    "gn:timezone":"Asia/Manila",
    "iso:country":"PH",
    "name:fil_x_preferred":[
        "Gubus"
    ],
    "name:und_x_variant":[
        "Bubuc",
        "Gubuc"
    ],
    "wof:name":"Gubus",
    "wof:placetype":"locality"
},
  "geometry": {"coordinates":[121.21865,18.07325],"type":"Point"}
}