{
  "type": "Feature",
  "properties": {
    "gn:admin1_code":"41",
    "gn:admin2_code":"49",
    "gn:admin3_code":"175319000.0",
    "gn:asciiname":"Itaytay",
    "gn:country_code":"PH",
    "gn:dem":4,
    "gn:feature_class":"P",
    "gn:feature_code":"PPL",
    "gn:name":"Itaytay",
    "gn:population":0,
    "gn:timezone":"Asia/Manila",
    "iso:country":"PH",
    "name:eng_x_preferred":[
        "Itaytay"
    ],
    "wof:name":"Itaytay",
    "wof:placetype":"locality"
},
  "geometry": {"coordinates":[119.17749999999999,10.41229],"type":"Point"}
}