{
  "type": "Feature",
  "properties": {
    "gn:country":"PH",
    "gn:fcode":"PPL",
    "gn:population":2232,
    "iso:country":"PH",
    "name:fil_x_preferred":[
        "Bukid"
    ],
    "name:und_x_variant":[
        "Buquid"
    ],
    "qs:name":"Bukid",
    "qs:photos_9r":0,
    "qs:photos_sr":0,
    "qs:pop_sr":"4",
    "wof:name":"Bukid",
    "wof:placetype":"locality",
    "wof:population":2232
},
  "geometry": {"coordinates":[125.40555999999999,5.57167],"type":"Point"}
}