{
  "type": "Feature",
  "properties": {
    "gn:admin1_code":"40",
    "gn:admin2_code":"H2",
    "gn:admin3_code":"45610000.0",
    "gn:asciiname":"Ajos",
    "gn:country_code":"PH",
    "gn:dem":11,
    "gn:feature_class":"P",
    "gn:feature_code":"PPL",
    "gn:name":"Ajos",
    "gn:population":0,
    "gn:timezone":"Asia/Manila",
    "iso:country":"PH",
    "name:fil_x_preferred":[
        "Ajos"
    ],
    "wof:name":"Ajos",
    "wof:placetype":"locality"
},
  "geometry": {"coordinates":[122.35599999999999,13.5491],"type":"Point"}
}