{
  "type": "Feature",
  "properties": {
    "gn:admin1_code":"15",
    "gn:admin2_code":"44",
    "gn:admin3_code":"144405000.0",
    "gn:asciiname":"Litiong",
    "gn:country_code":"PH",
    "gn:dem":822,
    "gn:feature_class":"P",
    "gn:feature_code":"PPL",
    "gn:name":"Litiong",
    "gn:population":0,
    "gn:timezone":"Asia/Manila",
    "iso:country":"PH",
    "name:fil_x_preferred":[
        "Litiong"
    ],
    "wof:name":"Litiong",
    "wof:placetype":"locality"
},
  "geometry": {"coordinates":[121.25463999999999,17.09795],"type":"Point"}
}