{
  "type": "Feature",
  "properties": {
    "gn:admin1_code":"01",
    "gn:admin2_code":"29",
    "gn:admin3_code":"12930000.0",
    "gn:asciiname":"Aguing",
    "gn:country_code":"PH",
    "gn:dem":29,
    "gn:feature_class":"P",
    "gn:feature_code":"PPL",
    "gn:name":"Aguing",
    "gn:population":0,
    "gn:timezone":"Asia/Manila",
    "iso:country":"PH",
    "name:fil_x_preferred":[
        "Aguing"
    ],
    "wof:name":"Aguing",
    "wof:placetype":"locality"
},
  "geometry": {"coordinates":[120.4859,17.8681],"type":"Point"}
}