{
  "type": "Feature",
  "properties": {
    "gn:admin1_code":"08",
    "gn:admin2_code":"37",
    "gn:admin3_code":"83735000.0",
    "gn:asciiname":"Gibuga",
    "gn:country_code":"PH",
    "gn:dem":9,
    "gn:feature_class":"P",
    "gn:feature_code":"PPL",
    "gn:name":"Gibuga",
    "gn:population":0,
    "gn:timezone":"Asia/Manila",
    "iso:country":"PH",
    "name:fil_x_preferred":[
        "Gibuga"
    ],
    "wof:name":"Gibuga",
    "wof:placetype":"locality"
},
  "geometry": {"coordinates":[124.98333,10.88333],"type":"Point"}
}