{
  "type": "Feature",
  "properties": {
    "gn:admin1_code":"41",
    "gn:admin2_code":"54",
    "gn:admin3_code":"175914000.0",
    "gn:asciiname":"Busay",
    "gn:country_code":"PH",
    "gn:dem":35,
    "gn:feature_class":"P",
    "gn:feature_code":"PPL",
    "gn:name":"Busay",
    "gn:population":0,
    "gn:timezone":"Asia/Manila",
    "iso:country":"PH",
    "name:fil_x_preferred":[
        "Busay"
    ],
    "wof:name":"Busay",
    "wof:placetype":"locality"
},
  "geometry": {"coordinates":[121.95061,12.07766],"type":"Point"}
}