{
  "type": "Feature",
  "properties": {
    "gn:admin1_code":"07",
    "gn:admin2_code":"46",
    "gn:admin3_code":"74603000.0",
    "gn:asciiname":"Calangag",
    "gn:country_code":"PH",
    "gn:dem":81,
    "gn:feature_class":"P",
    "gn:feature_code":"PPL",
    "gn:name":"Calangag",
    "gn:population":0,
    "gn:timezone":"Asia/Manila",
    "iso:country":"PH",
    "name:fil_x_preferred":[
        "Calangag"
    ],
    "wof:name":"Calangag",
    "wof:placetype":"locality"
},
  "geometry": {"coordinates":[123.2732,9.2402],"type":"Point"}
}