{
  "type": "Feature",
  "properties": {
    "gn:country":"PH",
    "gn:fcode":"PPL",
    "gn:population":7031,
    "iso:country":"PH",
    "name:und_x_variant":[
        "Pasong Kawayan"
    ],
    "qs:name":"Pasong Kawayan I",
    "qs:photos_9r":0,
    "qs:photos_sr":0,
    "qs:pop_sr":"5",
    "wof:name":"Pasong Kawayan I",
    "wof:placetype":"locality",
    "wof:population":7031
},
  "geometry": {"coordinates":[120.87051,14.34745],"type":"Point"}
}