{
  "type": "Feature",
  "properties": {
    "gn:admin1_code":"06",
    "gn:admin2_code":"30",
    "gn:admin3_code":"63016000.0",
    "gn:asciiname":"Navalas",
    "gn:country_code":"PH",
    "gn:dem":55,
    "gn:feature_class":"P",
    "gn:feature_code":"PPL",
    "gn:name":"Navalas",
    "gn:population":0,
    "gn:timezone":"Asia/Manila",
    "iso:country":"PH",
    "name:fil_x_preferred":[
        "Navalas"
    ],
    "wof:name":"Navalas",
    "wof:placetype":"locality"
},
  "geometry": {"coordinates":[122.6163,11.0087],"type":"Point"}
}