{
  "type": "Feature",
  "properties": {
    "gn:admin1_code":"08",
    "gn:admin2_code":"59",
    "gn:admin3_code":"86402000.0",
    "gn:asciiname":"Casaw",
    "gn:country_code":"PH",
    "gn:dem":8,
    "gn:feature_class":"P",
    "gn:feature_code":"PPL",
    "gn:name":"Casaw",
    "gn:population":0,
    "gn:timezone":"Asia/Manila",
    "iso:country":"PH",
    "name:fil_x_preferred":[
        "Casaw"
    ],
    "wof:name":"Casaw",
    "wof:placetype":"locality"
},
  "geometry": {"coordinates":[124.9695,10.3698],"type":"Point"}
}