{
  "type": "Feature",
  "properties": {
    "gn:admin1_code":"07",
    "gn:admin2_code":"11",
    "gn:admin3_code":"71230000.0",
    "gn:asciiname":"Cansuaguit",
    "gn:cc2":"PH",
    "gn:country_code":"PH",
    "gn:dem":205,
    "gn:feature_class":"P",
    "gn:feature_code":"PPL",
    "gn:name":"Cansuaguit",
    "gn:population":0,
    "gn:timezone":"Asia/Manila",
    "iso:country":"PH",
    "name:und_x_variant":[
        "Cansaguit",
        "Cansuagit",
        "Cansuaguit"
    ],
    "wof:name":"Cansuaguit",
    "wof:placetype":"locality"
},
  "geometry": {"coordinates":[123.84944,9.83944],"type":"Point"}
}