{
  "type": "Feature",
  "properties": {
    "gn:admin1_code":"08",
    "gn:admin2_code":"67",
    "gn:admin3_code":"84824000.0",
    "gn:asciiname":"Kapipian",
    "gn:cc2":"PH",
    "gn:country_code":"PH",
    "gn:dem":246,
    "gn:feature_class":"P",
    "gn:feature_code":"PPL",
    "gn:name":"Kapipian",
    "gn:population":0,
    "gn:timezone":"Asia/Manila",
    "iso:country":"PH",
    "name:und_x_variant":[
        "Gapipian",
        "Kapipian"
    ],
    "wof:name":"Kapipian",
    "wof:placetype":"locality"
},
  "geometry": {"coordinates":[124.65000000000001,12.26667],"type":"Point"}
}