{
  "type": "Feature",
  "properties": {
    "gn:country":"PH",
    "gn:fcode":"PPL",
    "gn:pop":2171,
    "iso:country":"PH",
    "name:ara_x_preferred":[
        "\u0628\u0627\u0643\u0648\u0644\u0648\u062f"
    ],
    "name:bcl_x_preferred":[
        "Bacolod"
    ],
    "name:bul_x_preferred":[
        "\u0411\u0430\u043a\u043e\u043b\u043e\u0434"
    ],
    "name:ceb_x_preferred":[
        "Bacolod"
    ],
    "name:deu_x_preferred":[
        "Bacolod City"
    ],
    "name:epo_x_preferred":[
        "Bacolod"
    ],
    "name:fas_x_preferred":[
        "\u0628\u0627\u06a9\u0644\u0648\u062f"
    ],
    "name:fra_x_preferred":[
        "Bacolod"
    ],
    "name:hrv_x_preferred":[
        "Bacolod"
    ],
    "name:ilo_x_preferred":[
        "Bacolod"
    ],
    "name:ind_x_preferred":[
        "Kota Bacolod"
    ],
    "name:ita_x_preferred":[
        "Bacolod"
    ],
    "name:jpn_x_preferred":[
        "\u30d0\u30b3\u30ed\u30c9"
    ],
    "name:kor_x_preferred":[
        "\ubc14\ucf5c\ub85c\ub4dc"
    ],
    "name:lat_x_preferred":[
        "Urbs Bacolodensis"
    ],
    "name:lit_x_preferred":[
        "Bakolodas"
    ],
    "name:nld_x_preferred":[
        "Bacolod"
    ],
    "name:nor_x_preferred":[
        "Bacolod"
    ],
    "name:pag_x_preferred":[
        "Bacolod"
    ],
    "name:pam_x_preferred":[
        "Bacolod"
    ],
    "name:pol_x_preferred":[
        "Bacolod"
    ],
    "name:por_x_preferred":[
        "Bac\u00f3lod"
    ],
    "name:rus_x_preferred":[
        "\u0411\u0430\u043a\u043e\u043b\u043e\u0434"
    ],
    "name:spa_x_preferred":[
        "Bac\u00f3lod"
    ],
    "name:swe_x_preferred":[
        "Bacolod City"
    ],
    "name:szl_x_preferred":[
        "Bacolod"
    ],
    "name:tgl_x_preferred":[
        "Bacolod"
    ],
    "name:tha_x_preferred":[
        "\u0e1a\u0e32\u0e42\u0e04\u0e42\u0e25\u0e14"
    ],
    "name:tur_x_preferred":[
        "Bacolod"
    ],
    "name:ukr_x_preferred":[
        "\u0411\u0430\u043a\u043e\u043b\u043e\u0434"
    ],
    "name:unk_x_variant":[
        "Baculod"
    ],
    "name:urd_x_preferred":[
        "\u0628\u0627\u06a9\u0648\u0644\u0648\u062f"
    ],
    "name:uzb_x_preferred":[
        "Bakolod"
    ],
    "name:vec_x_preferred":[
        "Bac\u00f3lod"
    ],
    "name:vie_x_preferred":[
        "Bacolod"
    ],
    "name:war_x_preferred":[
        "Bacolod"
    ],
    "name:zho_x_preferred":[
        "\u63cf\u6208\u5f8b"
    ],
    "qs:name":"Bacolod",
    "qs:photos_9r":0,
    "qs:photos_sr":0,
    "qs:pop_sr":"4",
    "wd:wordcount":5889,
    "wof:name":"Bacolod",
    "wof:placetype":"locality",
    "wof:population":2171
},
  "geometry": {"coordinates":[126.28944,8.93167],"type":"Point"}
}