{
  "type": "Feature",
  "properties": {
    "gn:country":"PH",
    "gn:fcode":"PPL",
    "gn:pop":2171,
    "iso:country":"PH",
    "name:unk_x_variant":[
        "Baculod"
    ],
    "qs:name":"Bacolod",
    "qs:photos_9r":0,
    "qs:photos_sr":0,
    "qs:pop_sr":"4",
    "wd:wordcount":5889,
    "wof:name":"Bacolod",
    "wof:placetype":"locality",
    "wof:population":2171
},
  "geometry": {"coordinates":[126.28944,8.93167],"type":"Point"}
}