{
  "type": "Feature",
  "properties": {
    "gn:admin1_code":"12",
    "gn:admin2_code":"57",
    "gn:admin3_code":"124704000.0",
    "gn:asciiname":"Hinatilan",
    "gn:country_code":"PH",
    "gn:dem":164,
    "gn:feature_class":"P",
    "gn:feature_code":"PPL",
    "gn:name":"Hinatilan",
    "gn:population":0,
    "gn:timezone":"Asia/Manila",
    "iso:country":"PH",
    "name:fil_x_preferred":[
        "Hinatilan"
    ],
    "wof:name":"Hinatilan",
    "wof:placetype":"locality"
},
  "geometry": {"coordinates":[125.05,7.03333],"type":"Point"}
}