{
  "type": "Feature",
  "properties": {
    "gn:admin1_code":"08",
    "gn:admin2_code":"H9",
    "gn:admin3_code":"87805000.0",
    "gn:asciiname":"Acaban",
    "gn:country_code":"PH",
    "gn:dem":16,
    "gn:feature_class":"P",
    "gn:feature_code":"PPL",
    "gn:name":"Acaban",
    "gn:population":0,
    "gn:timezone":"Asia/Manila",
    "iso:country":"PH",
    "name:fil_x_preferred":[
        "Acaban"
    ],
    "name:und_x_variant":[
        "Tacaban",
        "Acaban",
        "Acapan"
    ],
    "wof:name":"Acaban",
    "wof:placetype":"locality"
},
  "geometry": {"coordinates":[124.50060000000001,11.6881],"type":"Point"}
}