{
  "type": "Feature",
  "properties": {
    "gn:country":"PH",
    "gn:fcode":"PPL",
    "gn:population":2139,
    "iso:country":"PH",
    "name:fil_x_preferred":[
        "Nancalobasaan"
    ],
    "name:fil_x_variant":[
        "Nancalabasaan"
    ],
    "qs:name":"Nancalobasaan",
    "qs:photos_9r":0,
    "qs:photos_sr":0,
    "qs:pop_sr":"4",
    "wof:name":"Nancalobasaan",
    "wof:placetype":"locality",
    "wof:population":2139
},
  "geometry": {"coordinates":[120.8426,15.9342],"type":"Point"}
}