{
  "type": "Feature",
  "properties": {
    "gn:admin1_code":"05",
    "gn:admin2_code":"05",
    "gn:admin3_code":"50504000.0",
    "gn:asciiname":"Bololo",
    "gn:country_code":"PH",
    "gn:dem":205,
    "gn:feature_class":"P",
    "gn:feature_code":"PPL",
    "gn:name":"Bololo",
    "gn:population":0,
    "gn:timezone":"Asia/Manila",
    "iso:country":"PH",
    "name:fil_x_preferred":[
        "Bololo"
    ],
    "wof:name":"Bololo",
    "wof:placetype":"locality"
},
  "geometry": {"coordinates":[123.53333000000001,13.15],"type":"Point"}
}