{
  "type": "Feature",
  "properties": {
    "gn:admin1_code":"02",
    "gn:admin2_code":"14",
    "gn:admin3_code":"21517000.0",
    "gn:asciiname":"Calapangan Norte",
    "gn:country_code":"PH",
    "gn:dem":9,
    "gn:feature_class":"P",
    "gn:feature_code":"PPL",
    "gn:name":"Calapangan Norte",
    "gn:population":0,
    "gn:timezone":"Asia/Manila",
    "iso:country":"PH",
    "wof:name":"Calapangan Norte",
    "wof:placetype":"locality"
},
  "geometry": {"coordinates":[121.60952,18.02224],"type":"Point"}
}