{
  "type": "Feature",
  "properties": {
    "gn:country":"PH",
    "gn:fcode":"PPL",
    "gn:population":5130,
    "iso:country":"PH",
    "name:fil_x_preferred":[
        "Puloypuloy"
    ],
    "name:und_x_variant":[
        "Poloy-Poloy"
    ],
    "qs:name":"Puloypuloy",
    "qs:photos_9r":0,
    "qs:photos_sr":0,
    "qs:pop_sr":"5",
    "wof:name":"Puloypuloy",
    "wof:placetype":"locality",
    "wof:population":5130
},
  "geometry": {"coordinates":[124.096,6.63517],"type":"Point"}
}