{
  "type": "Feature",
  "properties": {
    "iso:country":"PH",
    "name:bcl_x_preferred":[
        "Cuartero"
    ],
    "name:cbk_zam_x_preferred":[
        "Cuartero"
    ],
    "name:ceb_x_preferred":[
        "Cuartero"
    ],
    "name:deu_x_preferred":[
        "Cuartero"
    ],
    "name:eng_x_preferred":[
        "Cuartero"
    ],
    "name:fil_x_preferred":[
        "Cuartero"
    ],
    "name:fra_x_preferred":[
        "Cuartero"
    ],
    "name:ilo_x_preferred":[
        "Cuartero"
    ],
    "name:ind_x_preferred":[
        "Cuartero"
    ],
    "name:ita_x_preferred":[
        "Cuartero"
    ],
    "name:nld_x_preferred":[
        "Cuartero"
    ],
    "name:pag_x_preferred":[
        "Cuartero"
    ],
    "name:pam_x_preferred":[
        "Cuartero"
    ],
    "name:swe_x_preferred":[
        "Cuartero"
    ],
    "name:tgl_x_preferred":[
        "Cuartero"
    ],
    "name:und_x_variant":[
        "Cuariero"
    ],
    "name:vie_x_preferred":[
        "Cuartero"
    ],
    "name:war_x_preferred":[
        "Cuartero"
    ],
    "qs:gn_country":"PH",
    "qs:gn_fcode":"PPL",
    "qs:gn_pop":3519,
    "qs:name":"Cuartero",
    "qs:name_adm0":"Philippines",
    "qs:name_adm1":"Western Visayas",
    "qs:photos":0,
    "qs:photos_1k":0,
    "qs:photos_9k":1,
    "qs:photos_9r":1,
    "qs:photos_all":1,
    "qs:photos_sr":0,
    "qs:placetype":"Town",
    "qs:pop_sr":"4",
    "qs:woe_adm0":23424934,
    "wd:wordcount":155,
    "wof:name":"Cuartero",
    "wof:placetype":"locality",
    "wof:population":3519
},
  "geometry": {"coordinates":[122.6694,11.3407],"type":"Point"}
}