{
  "type": "Feature",
  "properties": {
    "gn:admin1_code":"06",
    "gn:admin2_code":"30",
    "gn:admin3_code":"63035000.0",
    "gn:asciiname":"Malag-it",
    "gn:country_code":"PH",
    "gn:dem":54,
    "gn:feature_class":"P",
    "gn:feature_code":"PPL",
    "gn:name":"Malag-it",
    "gn:population":0,
    "gn:timezone":"Asia/Manila",
    "iso:country":"PH",
    "name:fil_x_preferred":[
        "Malag-it"
    ],
    "wof:name":"Malag-it",
    "wof:placetype":"locality"
},
  "geometry": {"coordinates":[122.59999999999999,11.16667],"type":"Point"}
}