{
  "type": "Feature",
  "properties": {
    "gn:admin1_code":"08",
    "gn:admin2_code":"23",
    "gn:admin3_code":"82619000.0",
    "gn:asciiname":"Pangdap",
    "gn:country_code":"PH",
    "gn:dem":5,
    "gn:feature_class":"P",
    "gn:feature_code":"PPL",
    "gn:name":"Pangdap",
    "gn:population":0,
    "gn:timezone":"Asia/Manila",
    "iso:country":"PH",
    "name:fil_x_preferred":[
        "Pangdap"
    ],
    "wof:name":"Pangdap",
    "wof:placetype":"locality"
},
  "geometry": {"coordinates":[125.66846,11.10776],"type":"Point"}
}