{
  "type": "Feature",
  "properties": {
    "gn:admin1_code":"14",
    "gn:admin2_code":"60",
    "gn:admin3_code":"156610000.0",
    "gn:asciiname":"Bunlan",
    "gn:country_code":"PH",
    "gn:dem":12,
    "gn:feature_class":"P",
    "gn:feature_code":"PPL",
    "gn:name":"Bunlan",
    "gn:population":0,
    "gn:timezone":"Asia/Manila",
    "iso:country":"PH",
    "name:und_x_variant":[
        "Bonin"
    ],
    "wof:name":"Bunlan",
    "wof:placetype":"locality"
},
  "geometry": {"coordinates":[121.19007999999999,5.79642],"type":"Point"}
}