{
  "type": "Feature",
  "properties": {
    "gn:admin1_code":"15",
    "gn:admin2_code":"10",
    "gn:admin3_code":"141104000.0",
    "gn:asciiname":"Pilpiok",
    "gn:country_code":"PH",
    "gn:dem":1360,
    "gn:feature_class":"P",
    "gn:feature_code":"PPL",
    "gn:name":"Pilpiok",
    "gn:population":0,
    "gn:timezone":"Asia/Manila",
    "iso:country":"PH",
    "name:eng_x_preferred":[
        "Pilpiok"
    ],
    "wof:name":"Pilpiok",
    "wof:placetype":"locality"
},
  "geometry": {"coordinates":[120.8563,16.3873],"type":"Point"}
}