{
  "type": "Feature",
  "properties": {
    "gn:admin1_code":"41",
    "gn:admin2_code":"41",
    "gn:admin3_code":"175204000.0",
    "gn:asciiname":"Calag",
    "gn:country_code":"PH",
    "gn:dem":10,
    "gn:feature_class":"P",
    "gn:feature_code":"PPL",
    "gn:name":"Calag",
    "gn:population":0,
    "gn:timezone":"Asia/Manila",
    "iso:country":"PH",
    "name:fil_x_preferred":[
        "Calag"
    ],
    "wof:name":"Calag",
    "wof:placetype":"locality"
},
  "geometry": {"coordinates":[121.3467,12.3536],"type":"Point"}
}