{
  "type": "Feature",
  "properties": {
    "gn:country":"PH",
    "gn:fcode":"ADM3",
    "gn:pop":29019,
    "iso:country":"PH",
    "name:fil_x_preferred":[
        "Abulug"
    ],
    "name:fil_x_variant":[
        "Bayan ng Abulug"
    ],
    "qs:name":"Abulug",
    "qs:photos_9r":0,
    "qs:photos_sr":0,
    "qs:pop_sr":"7",
    "wof:name":"Abulug",
    "wof:placetype":"localadmin",
    "wof:population":29019
},
  "geometry": {"coordinates":[121.43011,18.39549],"type":"Point"}
}