{
  "type": "Feature",
  "properties": {
    "iso:country":"PH",
    "name:fil_x_preferred":[
        "Ibung"
    ],
    "qs:gn_country":"PH",
    "qs:gn_fcode":"PPL",
    "qs:gn_pop":4462,
    "qs:name":"Ibung",
    "qs:name_adm0":"Philippines",
    "qs:name_adm1":"Cagayan Valley",
    "qs:photos":0,
    "qs:photos_1k":0,
    "qs:photos_9k":1,
    "qs:photos_9r":1,
    "qs:photos_all":1,
    "qs:photos_sr":0,
    "qs:placetype":"Town",
    "qs:pop_sr":"4",
    "qs:woe_adm0":23424934,
    "wof:name":"Ibung",
    "wof:placetype":"locality",
    "wof:population":4462
},
  "geometry": {"coordinates":[121.18613999999999,16.60938],"type":"Point"}
}