{
  "type": "Feature",
  "properties": {
    "gn:admin1_code":"40",
    "gn:admin2_code":"H2",
    "gn:admin3_code":"45628000.0",
    "gn:asciiname":"Campusa",
    "gn:country_code":"PH",
    "gn:dem":72,
    "gn:feature_class":"P",
    "gn:feature_code":"PPL",
    "gn:name":"Campusa",
    "gn:population":0,
    "gn:timezone":"Asia/Manila",
    "iso:country":"PH",
    "name:fil_x_preferred":[
        "Campusa"
    ],
    "wof:name":"Campusa",
    "wof:placetype":"locality"
},
  "geometry": {"coordinates":[122.45,13.55],"type":"Point"}
}