{
  "type": "Feature",
  "properties": {
    "gn:admin1_code":"41",
    "gn:admin2_code":"38",
    "gn:admin3_code":"174004000.0",
    "gn:asciiname":"Mendez",
    "gn:country_code":"PH",
    "gn:dem":237,
    "gn:feature_class":"P",
    "gn:feature_code":"PPL",
    "gn:name":"Mendez",
    "gn:population":0,
    "gn:timezone":"Asia/Manila",
    "iso:country":"PH",
    "name:fil_x_preferred":[
        "Mendez"
    ],
    "name:srp_x_preferred":[
        "\u041c\u0435\u043d\u0434\u0435\u0437"
    ],
    "wof:name":"Mendez",
    "wof:placetype":"locality"
},
  "geometry": {"coordinates":[121.9084,13.5068],"type":"Point"}
}