{
  "type": "Feature",
  "properties": {
    "gn:admin1_code":"06",
    "gn:admin2_code":"04",
    "gn:admin3_code":"60406000.0",
    "gn:asciiname":"Kolongkolong",
    "gn:country_code":"PH",
    "gn:dem":8,
    "gn:feature_class":"P",
    "gn:feature_code":"PPL",
    "gn:name":"Kolongkolong",
    "gn:population":0,
    "gn:timezone":"Asia/Manila",
    "iso:country":"PH",
    "name:fil_x_preferred":[
        "Kolongkolong"
    ],
    "name:und_x_variant":[
        "Colongcolong"
    ],
    "wof:name":"Kolongkolong",
    "wof:placetype":"locality"
},
  "geometry": {"coordinates":[122.1799,11.812],"type":"Point"}
}