{
  "type": "Feature",
  "properties": {
    "gn:admin1_code":"02",
    "gn:admin2_code":"31",
    "gn:admin3_code":"23131000.0",
    "gn:asciiname":"Baraggutan",
    "gn:country_code":"PH",
    "gn:dem":71,
    "gn:feature_class":"P",
    "gn:feature_code":"PPL",
    "gn:name":"Baraggutan",
    "gn:population":0,
    "gn:timezone":"Asia/Manila",
    "iso:country":"PH",
    "name:fil_x_preferred":[
        "Baraggutan"
    ],
    "wof:name":"Baraggutan",
    "wof:placetype":"locality"
},
  "geometry": {"coordinates":[122.02417,16.92167],"type":"Point"}
}