{
  "type": "Feature",
  "properties": {
    "gn:country":"PH",
    "gn:fcode":"ADM3",
    "gn:pop":15827,
    "iso:country":"PH",
    "name:fil_x_preferred":[
        "Tomas Oppus"
    ],
    "qs:name":"Tomas Oppus",
    "qs:photos_9r":0,
    "qs:photos_sr":0,
    "qs:pop_sr":"6",
    "wof:name":"Tomas Oppus",
    "wof:placetype":"localadmin",
    "wof:population":15827
},
  "geometry": {"coordinates":[124.95,10.28333],"type":"Point"}
}