{
  "type": "Feature",
  "properties": {
    "gn:admin1_code":"40",
    "gn:admin2_code":"H2",
    "gn:admin3_code":"45623000.0",
    "gn:asciiname":"Nalunao",
    "gn:country_code":"PH",
    "gn:dem":422,
    "gn:feature_class":"P",
    "gn:feature_code":"PPL",
    "gn:name":"Nalunao",
    "gn:population":0,
    "gn:timezone":"Asia/Manila",
    "iso:country":"PH",
    "name:fil_x_preferred":[
        "Nalunao"
    ],
    "wof:name":"Nalunao",
    "wof:placetype":"locality"
},
  "geometry": {"coordinates":[121.5365,14.1629],"type":"Point"}
}