{
  "type": "Feature",
  "properties": {
    "gn:country":"PH",
    "gn:fcode":"PPL",
    "gn:population":3969,
    "iso:country":"PH",
    "name:und_x_variant":[
        "Itig"
    ],
    "qs:name":"Idtig",
    "qs:photos_9r":0,
    "qs:photos_sr":0,
    "qs:pop_sr":"4",
    "wof:name":"Idtig",
    "wof:placetype":"locality",
    "wof:population":3969
},
  "geometry": {"coordinates":[124.77278,6.79889],"type":"Point"}
}