{
  "type": "Feature",
  "properties": {
    "gn:admin1_code":"06",
    "gn:admin2_code":"H3",
    "gn:admin3_code":"64524000.0",
    "gn:asciiname":"Hacienda Bascona",
    "gn:country_code":"PH",
    "gn:dem":14,
    "gn:feature_class":"P",
    "gn:feature_code":"PPL",
    "gn:name":"Hacienda Basco\u00f1a",
    "gn:population":0,
    "gn:timezone":"Asia/Manila",
    "iso:country":"PH",
    "name:fil_x_preferred":[
        "Hacienda Basco\u00f1a"
    ],
    "name:fil_x_variant":[
        "Basconia Hacienda"
    ],
    "wof:name":"Hacienda Bascona",
    "wof:placetype":"locality"
},
  "geometry": {"coordinates":[123.4195,10.50886],"type":"Point"}
}