{
  "type": "Feature",
  "properties": {
    "gn:admin1_code":"41",
    "gn:admin2_code":"41",
    "gn:admin3_code":"175208000.0",
    "gn:asciiname":"Matandang Naujan",
    "gn:country_code":"PH",
    "gn:dem":20,
    "gn:feature_class":"P",
    "gn:feature_code":"PPL",
    "gn:name":"Matandang Naujan",
    "gn:population":0,
    "gn:timezone":"Asia/Manila",
    "iso:country":"PH",
    "name:eng_x_preferred":[
        "Matandang Naujan"
    ],
    "wof:name":"Matandang Naujan",
    "wof:placetype":"locality"
},
  "geometry": {"coordinates":[121.26312,13.26789],"type":"Point"}
}