{
  "type": "Feature",
  "properties": {
    "gn:country":"PH",
    "gn:fcode":"PPL",
    "gn:pop":8607,
    "iso:country":"PH",
    "name:fil_x_preferred":[
        "Alicante"
    ],
    "qs:name":"Alicante",
    "qs:photos_9r":0,
    "qs:photos_sr":0,
    "qs:pop_sr":"5",
    "wof:name":"Alicante",
    "wof:placetype":"locality",
    "wof:population":8607
},
  "geometry": {"coordinates":[123.0185,10.89704],"type":"Point"}
}