{
  "type": "Feature",
  "properties": {
    "gn:admin1_code":"09",
    "gn:admin2_code":"66",
    "gn:admin3_code":"97306000.0",
    "gn:asciiname":"Lower Dimaya",
    "gn:country_code":"PH",
    "gn:dem":36,
    "gn:feature_class":"P",
    "gn:feature_code":"PPL",
    "gn:name":"Lower Dimaya",
    "gn:population":0,
    "gn:timezone":"Asia/Manila",
    "iso:country":"PH",
    "wof:name":"Lower Dimaya",
    "wof:placetype":"locality"
},
  "geometry": {"coordinates":[123.33,7.60472],"type":"Point"}
}