{
  "type": "Feature",
  "properties": {
    "iso:country":"PH",
    "name:bcl_x_preferred":[
        "Ma-ayon"
    ],
    "name:cbk_zam_x_preferred":[
        "Ma-ayon"
    ],
    "name:ceb_x_preferred":[
        "Ma-ayon"
    ],
    "name:deu_x_preferred":[
        "Ma-ayon"
    ],
    "name:eng_x_preferred":[
        "Ma-ayon"
    ],
    "name:fil_x_preferred":[
        "Ma-ayon"
    ],
    "name:fra_x_preferred":[
        "Ma-ayon"
    ],
    "name:ilo_x_preferred":[
        "Ma-ayon"
    ],
    "name:ind_x_preferred":[
        "Ma-ayon"
    ],
    "name:ita_x_preferred":[
        "Ma-ayon"
    ],
    "name:nld_x_preferred":[
        "Ma-ayon"
    ],
    "name:nob_x_preferred":[
        "Ma-ayon"
    ],
    "name:pag_x_preferred":[
        "Ma-ayon"
    ],
    "name:pam_x_preferred":[
        "Ma-ayon"
    ],
    "name:swe_x_preferred":[
        "Ma-ayon"
    ],
    "name:tgl_x_preferred":[
        "Ma-ayon"
    ],
    "name:urd_x_preferred":[
        "\u0645\u0627-\u0627\u06cc\u0648\u0646\u060c \u06a9\u0627\u067e\u06cc\u0632"
    ],
    "name:urd_x_variant":[
        "\u0645\u0627-\u0627\u06cc\u0648\u0646"
    ],
    "name:vie_x_preferred":[
        "Ma-ayon"
    ],
    "name:war_x_preferred":[
        "Maayon"
    ],
    "name:war_x_variant":[
        "Ma-ayon"
    ],
    "qs:gn_country":"PH",
    "qs:gn_fcode":"ADM3",
    "qs:gn_pop":34668,
    "qs:name":"Ma-ayon",
    "qs:name_adm0":"Philippines",
    "qs:name_adm1":"Western Visayas",
    "qs:photos":0,
    "qs:photos_1k":0,
    "qs:photos_9k":1,
    "qs:photos_9r":1,
    "qs:photos_all":3,
    "qs:photos_sr":0,
    "qs:placetype":"Town",
    "qs:pop_sr":"7",
    "qs:woe_adm0":23424934,
    "wd:wordcount":154,
    "wof:name":"Ma-ayon",
    "wof:placetype":"locality",
    "wof:population":34668
},
  "geometry": {"coordinates":[122.84999999999999,11.36667],"type":"Point"}
}