{
  "type": "Feature",
  "properties": {
    "gn:admin1_code":"02",
    "gn:admin2_code":"14",
    "gn:admin3_code":"21520000.0",
    "gn:asciiname":"Villa Rey",
    "gn:country_code":"PH",
    "gn:dem":64,
    "gn:feature_class":"P",
    "gn:feature_code":"PPL",
    "gn:name":"Villa Rey",
    "gn:population":0,
    "gn:timezone":"Asia/Manila",
    "iso:country":"PH",
    "name:fil_x_preferred":[
        "Villa Rey"
    ],
    "name:und_x_variant":[
        "San Gaspar"
    ],
    "wof:name":"Villa Rey",
    "wof:placetype":"locality"
},
  "geometry": {"coordinates":[121.54859999999999,17.7083],"type":"Point"}
}