{
  "type": "Feature",
  "properties": {
    "gn:admin1_code":"15",
    "gn:admin2_code":"01",
    "gn:admin3_code":"140118000.0",
    "gn:asciiname":"Suyo",
    "gn:country_code":"PH",
    "gn:dem":42,
    "gn:feature_class":"P",
    "gn:feature_code":"PPL",
    "gn:name":"Suyo",
    "gn:population":0,
    "gn:timezone":"Asia/Manila",
    "iso:country":"PH",
    "name:fil_x_preferred":[
        "Suyo"
    ],
    "wof:name":"Suyo",
    "wof:placetype":"locality"
},
  "geometry": {"coordinates":[120.5689,17.5527],"type":"Point"}
}