{
  "type": "Feature",
  "properties": {
    "gn:admin1_code":"06",
    "gn:admin2_code":"J3",
    "gn:admin3_code":"67904000.0",
    "gn:asciiname":"Gaban",
    "gn:country_code":"PH",
    "gn:dem":101,
    "gn:feature_class":"P",
    "gn:feature_code":"PPL",
    "gn:name":"Gaban",
    "gn:population":0,
    "gn:timezone":"Asia/Manila",
    "iso:country":"PH",
    "name:fil_x_preferred":[
        "Gaban"
    ],
    "name:und_x_variant":[
        "Goban"
    ],
    "wof:name":"Gaban",
    "wof:placetype":"locality"
},
  "geometry": {"coordinates":[122.6639,10.6218],"type":"Point"}
}