{
  "type": "Feature",
  "properties": {
    "gn:admin1_code":"05",
    "gn:admin2_code":"58",
    "gn:admin3_code":"56205000.0",
    "gn:asciiname":"Burgos",
    "gn:country_code":"PH",
    "gn:dem":88,
    "gn:feature_class":"P",
    "gn:feature_code":"PPL",
    "gn:name":"Burgos",
    "gn:population":0,
    "gn:timezone":"Asia/Manila",
    "iso:country":"PH",
    "name:fil_x_preferred":[
        "Burgos"
    ],
    "wof:name":"Burgos",
    "wof:placetype":"locality"
},
  "geometry": {"coordinates":[124.0693,12.8819],"type":"Point"}
}