{
  "type": "Feature",
  "properties": {
    "gn:admin1_code":"41",
    "gn:admin2_code":"49",
    "gn:admin3_code":"175323000.0",
    "gn:asciiname":"Punkal",
    "gn:country_code":"PH",
    "gn:dem":7,
    "gn:feature_class":"P",
    "gn:feature_code":"PPL",
    "gn:name":"Punkal",
    "gn:population":0,
    "gn:timezone":"Asia/Manila",
    "iso:country":"PH",
    "name:eng_x_preferred":[
        "Punkal"
    ],
    "wof:name":"Punkal",
    "wof:placetype":"locality"
},
  "geometry": {"coordinates":[117.54900000000001,8.94149],"type":"Point"}
}