{
  "type": "Feature",
  "properties": {
    "gn:country":"PH",
    "gn:fcode":"PPL",
    "gn:pop":3137,
    "iso:country":"PH",
    "name:eng_x_historical":[
        "Weyler"
    ],
    "name:eng_x_preferred":[
        "Weyler"
    ],
    "name:fil_x_preferred":[
        "PeNa"
    ],
    "name:fil_x_variant":[
        "Pi\u00f1a"
    ],
    "qs:name":"Pi\u00f1a",
    "qs:photos_9r":0,
    "qs:photos_sr":0,
    "qs:pop_sr":"4",
    "wd:wordcount":338,
    "wof:name":"Pi\u00f1a",
    "wof:placetype":"locality",
    "wof:population":3137
},
  "geometry": {"coordinates":[124.4015,12.19078],"type":"Point"}
}