{
  "type": "Feature",
  "properties": {
    "gn:country":"PH",
    "gn:fcode":"PPL",
    "gn:pop":3137,
    "iso:country":"PH",
    "name:ara_x_preferred":[
        "\u0628\u064a\u0646\u0627"
    ],
    "name:deu_x_preferred":[
        "Ananasfaser"
    ],
    "name:eng_x_historical":[
        "Weyler"
    ],
    "name:eng_x_preferred":[
        "Weyler"
    ],
    "name:eng_x_variant":[
        "pi\u00f1a"
    ],
    "name:epo_x_preferred":[
        "ananasfibro"
    ],
    "name:fil_x_preferred":[
        "PeNa"
    ],
    "name:fil_x_variant":[
        "Pi\u00f1a"
    ],
    "name:fra_x_preferred":[
        "pi\u00f1a"
    ],
    "name:jpn_x_preferred":[
        "\u30d4\u30cb\u30e3"
    ],
    "name:new_x_preferred":[
        "\u092a\u093f\u0928\u093e"
    ],
    "name:nld_x_preferred":[
        "pi\u00f1a"
    ],
    "name:swe_x_preferred":[
        "Ananasfibrer"
    ],
    "qs:name":"Pi\u00f1a",
    "qs:photos_9r":0,
    "qs:photos_sr":0,
    "qs:pop_sr":"4",
    "wd:wordcount":338,
    "wof:name":"Pi\u00f1a",
    "wof:placetype":"locality",
    "wof:population":3137
},
  "geometry": {"coordinates":[124.4015,12.19078],"type":"Point"}
}