{
  "type": "Feature",
  "properties": {
    "gn:admin1_code":"02",
    "gn:admin2_code":"14",
    "gn:admin3_code":"21513000.0",
    "gn:asciiname":"Lawog",
    "gn:country_code":"PH",
    "gn:dem":22,
    "gn:feature_class":"P",
    "gn:feature_code":"PPL",
    "gn:name":"Lawog",
    "gn:population":0,
    "gn:timezone":"Asia/Manila",
    "iso:country":"PH",
    "name:fil_x_preferred":[
        "Lawog"
    ],
    "wof:name":"Lawog",
    "wof:placetype":"locality"
},
  "geometry": {"coordinates":[121.74124999999999,18.03959],"type":"Point"}
}