{
  "type": "Feature",
  "properties": {
    "gn:admin1_code":"01",
    "gn:admin2_code":"29",
    "gn:admin3_code":"12909000.0",
    "gn:asciiname":"Kilang",
    "gn:country_code":"PH",
    "gn:dem":20,
    "gn:feature_class":"P",
    "gn:feature_code":"PPL",
    "gn:name":"Kilang",
    "gn:population":0,
    "gn:timezone":"Asia/Manila",
    "iso:country":"PH",
    "name:fil_x_preferred":[
        "Kilang"
    ],
    "wof:name":"Kilang",
    "wof:placetype":"locality"
},
  "geometry": {"coordinates":[120.46666999999999,17.18333],"type":"Point"}
}