{
  "type": "Feature",
  "properties": {
    "gn:country":"PH",
    "gn:fcode":"ADM3",
    "gn:pop":32248,
    "iso:country":"PH",
    "name:unk_x_variant":[
        "Laurel City"
    ],
    "qs:name":"Laurel",
    "qs:photos_9r":0,
    "qs:photos_sr":0,
    "qs:pop_sr":"7",
    "wd:wordcount":444,
    "wof:name":"Laurel",
    "wof:placetype":"localadmin",
    "wof:population":32248
},
  "geometry": {"coordinates":[120.90846000000001,14.05429],"type":"Point"}
}