{
  "type": "Feature",
  "properties": {
    "gn:country":"PH",
    "gn:fcode":"ADM3",
    "gn:population":32248,
    "iso:country":"PH",
    "name:bul_x_preferred":[
        "\u041b\u043e\u0440\u044a\u043b"
    ],
    "name:cat_x_preferred":[
        "Laurel"
    ],
    "name:ceb_x_preferred":[
        "Laurel"
    ],
    "name:ces_x_preferred":[
        "Laurel"
    ],
    "name:deu_x_preferred":[
        "Laurel"
    ],
    "name:fra_x_preferred":[
        "Laurel"
    ],
    "name:ita_x_preferred":[
        "Laurel"
    ],
    "name:jpn_x_preferred":[
        "\u30ed\u30fc\u30ec\u30eb"
    ],
    "name:nld_x_preferred":[
        "Laurel"
    ],
    "name:pol_x_preferred":[
        "Laurel"
    ],
    "name:por_x_preferred":[
        "Laurel"
    ],
    "name:rus_x_preferred":[
        "\u041b\u0430\u0432\u0440"
    ],
    "name:slk_x_preferred":[
        "Laurel"
    ],
    "name:spa_x_preferred":[
        "Laurel"
    ],
    "name:srp_x_preferred":[
        "\u041b\u043e\u0440\u0435\u043b"
    ],
    "name:swe_x_preferred":[
        "Laurel"
    ],
    "name:tgl_x_preferred":[
        "Laurel"
    ],
    "name:ukr_x_preferred":[
        "\u041b\u043e\u0440\u0435\u043b"
    ],
    "name:und_x_variant":[
        "Laurel City"
    ],
    "name:vol_x_preferred":[
        "Laurel"
    ],
    "qs:name":"Laurel",
    "qs:photos_9r":0,
    "qs:photos_sr":0,
    "qs:pop_sr":"7",
    "wd:wordcount":444,
    "wof:name":"Laurel",
    "wof:placetype":"localadmin",
    "wof:population":32248
},
  "geometry": {"coordinates":[120.90846000000001,14.05429],"type":"Point"}
}