{
  "type": "Feature",
  "properties": {
    "gn:admin1_code":"15",
    "gn:admin2_code":"01",
    "gn:admin3_code":"140123000.0",
    "gn:asciiname":"Tangadan",
    "gn:country_code":"PH",
    "gn:dem":53,
    "gn:feature_class":"P",
    "gn:feature_code":"PPL",
    "gn:name":"Tangadan",
    "gn:population":0,
    "gn:timezone":"Asia/Manila",
    "iso:country":"PH",
    "wof:name":"Tangadan",
    "wof:placetype":"locality"
},
  "geometry": {"coordinates":[120.51667,17.51667],"type":"Point"}
}