{
  "type": "Feature",
  "properties": {
    "gn:admin1_code":"03",
    "gn:admin2_code":"50",
    "gn:admin3_code":"35404000.0",
    "gn:asciiname":"Talba",
    "gn:country_code":"PH",
    "gn:dem":8,
    "gn:feature_class":"P",
    "gn:feature_code":"PPL",
    "gn:name":"Talba",
    "gn:population":0,
    "gn:timezone":"Asia/Manila",
    "iso:country":"PH",
    "name:fil_x_preferred":[
        "Talba"
    ],
    "wof:name":"Talba",
    "wof:placetype":"locality"
},
  "geometry": {"coordinates":[120.66706000000001,14.98543],"type":"Point"}
}