{
  "type": "Feature",
  "properties": {
    "gn:country":"PH",
    "gn:fcode":"PPL",
    "gn:population":189090,
    "iso:country":"PH",
    "ne:ADM0CAP":0.0,
    "ne:ADM0NAME":"Philippines",
    "ne:ADM0_A3":"PHL",
    "ne:ADM1NAME":"Leyte",
    "ne:ADMIN1_COD":0,
    "ne:CAPALT":0,
    "ne:CHANGED":4,
    "ne:CHECKME":0,
    "ne:COMPARE":0,
    "ne:DIFFASCII":0,
    "ne:DIFFNOTE":"Changed scale rank.",
    "ne:ELEVATION":0.0,
    "ne:FEATURECLA":"Populated place",
    "ne:FEATURE_CL":"P",
    "ne:FEATURE_CO":"PPL",
    "ne:GEONAMEID":1695743,
    "ne:GEONAMESNO":"GeoNames spatial join with similar names only.",
    "ne:GN_ASCII":"Panalanoy",
    "ne:GN_POP":189090,
    "ne:GTOPO30":1.0,
    "ne:ISO_A2":"PH",
    "ne:LABELRANK":5,
    "ne:LATITUDE":11.250436,
    "ne:LONGITUDE":125.000008,
    "ne:LS_MATCH":1,
    "ne:LS_NAME":"Tacloban",
    "ne:MAX_AREAKM":31.0,
    "ne:MAX_AREAMI":12.0,
    "ne:MAX_BBXMAX":125.033333,
    "ne:MAX_BBXMIN":124.975,
    "ne:MAX_BBYMAX":11.258333,
    "ne:MAX_BBYMIN":11.15,
    "ne:MAX_NATSCA":10.0,
    "ne:MAX_PERKM":46.0,
    "ne:MAX_PERMI":28.0,
    "ne:MAX_POP10":280006,
    "ne:MAX_POP20":0,
    "ne:MAX_POP300":0,
    "ne:MAX_POP310":0,
    "ne:MAX_POP50":0,
    "ne:MEAN_BBXC":125.000563,
    "ne:MEAN_BBYC":11.205293,
    "ne:MEGACITY":0,
    "ne:MIN_AREAKM":31.0,
    "ne:MIN_AREAMI":12.0,
    "ne:MIN_BBXMAX":125.033333,
    "ne:MIN_BBXMIN":124.975,
    "ne:MIN_BBYMAX":11.258333,
    "ne:MIN_BBYMIN":11.15,
    "ne:MIN_PERKM":46.0,
    "ne:MIN_PERMI":28.0,
    "ne:NAME":"Tacloban",
    "ne:NAMEASCII":"Tacloban",
    "ne:NAMEDIFF":0,
    "ne:NATSCALE":20,
    "ne:POP1950":0,
    "ne:POP1955":0,
    "ne:POP1960":0,
    "ne:POP1965":0,
    "ne:POP1970":0,
    "ne:POP1975":0,
    "ne:POP1980":0,
    "ne:POP1985":0,
    "ne:POP1990":0,
    "ne:POP1995":0,
    "ne:POP2000":0,
    "ne:POP2005":0,
    "ne:POP2010":0,
    "ne:POP2015":0,
    "ne:POP2020":0,
    "ne:POP2025":0,
    "ne:POP2050":0,
    "ne:POP_MAX":280006,
    "ne:POP_MIN":189090,
    "ne:POP_OTHER":0,
    "ne:RANK_MAX":10,
    "ne:RANK_MIN":9,
    "ne:SCALERANK":7,
    "ne:SOV0NAME":"Philippines",
    "ne:SOV_A3":"PHL",
    "ne:TIMEZONE":"Asia/Manila",
    "ne:UN_FID":0,
    "ne:UN_LAT":0.0,
    "ne:UN_LONG":0.0,
    "ne:WORLDCITY":0,
    "qs:name":"Panalanoy",
    "qs:photos_9r":0,
    "qs:photos_sr":0,
    "qs:pop_sr":"10",
    "wof:name":"Panalanoy",
    "wof:placetype":"locality",
    "wof:population":189090
},
  "geometry": {"coordinates":[125.00639,11.25111],"type":"Point"}
}