{
  "type": "Feature",
  "properties": {
    "gn:country":"PH",
    "gn:fcode":"PPL",
    "gn:pop":2361,
    "iso:country":"PH",
    "name:fil_x_preferred":[
        "Maguling"
    ],
    "qs:name":"Maguling",
    "qs:photos_9r":0,
    "qs:photos_sr":0,
    "qs:pop_sr":"4",
    "wof:name":"Maguling",
    "wof:placetype":"locality",
    "wof:population":2361
},
  "geometry": {"coordinates":[124.40333,6.095],"type":"Point"}
}