{
  "type": "Feature",
  "properties": {
    "gn:admin1_code":"07",
    "gn:admin2_code":"21",
    "gn:admin3_code":"72229000.0",
    "gn:asciiname":"Juguiawan",
    "gn:country_code":"PH",
    "gn:dem":632,
    "gn:feature_class":"P",
    "gn:feature_code":"PPL",
    "gn:name":"Juguiawan",
    "gn:population":0,
    "gn:timezone":"Asia/Manila",
    "iso:country":"PH",
    "name:fil_x_preferred":[
        "Juguiawan"
    ],
    "wof:name":"Juguiawan",
    "wof:placetype":"locality"
},
  "geometry": {"coordinates":[123.392,9.6883],"type":"Point"}
}