{
  "type": "Feature",
  "properties": {
    "gn:country":"PH",
    "gn:fcode":"PPL",
    "gn:population":2164,
    "iso:country":"PH",
    "name:fil_x_preferred":[
        "San Eduardo"
    ],
    "qs:name":"San Eduardo",
    "qs:photos_9r":0,
    "qs:photos_sr":0,
    "qs:pop_sr":"4",
    "wof:name":"San Eduardo",
    "wof:placetype":"locality",
    "wof:population":2164
},
  "geometry": {"coordinates":[125.4503,12.1679],"type":"Point"}
}