{
  "type": "Feature",
  "properties": {
    "gn:admin1_code":"06",
    "gn:admin2_code":"06",
    "gn:admin3_code":"60608000.0",
    "gn:asciiname":"Governor Evelio B. Javier",
    "gn:country_code":"PH",
    "gn:dem":15,
    "gn:feature_class":"P",
    "gn:feature_code":"PPL",
    "gn:name":"Governor Evelio B. Javier",
    "gn:population":0,
    "gn:timezone":"Asia/Manila",
    "iso:country":"PH",
    "name:fil_x_preferred":[
        "Governor Evelio B. Javier"
    ],
    "wof:name":"Governor Evelio B. Javier",
    "wof:placetype":"locality"
},
  "geometry": {"coordinates":[121.9907,10.6826],"type":"Point"}
}