{
  "type": "Feature",
  "properties": {
    "gn:admin1_code":"06",
    "gn:admin2_code":"18",
    "gn:admin3_code":"61906000.0",
    "gn:asciiname":"Masnang",
    "gn:country_code":"PH",
    "gn:dem":152,
    "gn:feature_class":"P",
    "gn:feature_code":"PPL",
    "gn:name":"Masnang",
    "gn:population":0,
    "gn:timezone":"Asia/Manila",
    "iso:country":"PH",
    "name:fil_x_preferred":[
        "Masnang"
    ],
    "wof:name":"Masnang",
    "wof:placetype":"locality"
},
  "geometry": {"coordinates":[122.49691,11.35141],"type":"Point"}
}