{
  "type": "Feature",
  "properties": {
    "gn:admin1_code":"03",
    "gn:admin2_code":"47",
    "gn:admin3_code":"34907000.0",
    "gn:asciiname":"Bantug",
    "gn:country_code":"PH",
    "gn:dem":137,
    "gn:feature_class":"P",
    "gn:feature_code":"PPL",
    "gn:name":"Bantug",
    "gn:population":0,
    "gn:timezone":"Asia/Manila",
    "iso:country":"PH",
    "name:fil_x_preferred":[
        "Bantug"
    ],
    "wof:name":"Bantug",
    "wof:placetype":"locality"
},
  "geometry": {"coordinates":[121.3279,15.4396],"type":"Point"}
}