{
  "type": "Feature",
  "properties": {
    "gn:admin1_code":"41",
    "gn:admin2_code":"38",
    "gn:admin3_code":"174001000.0",
    "gn:asciiname":"Bantad",
    "gn:country_code":"PH",
    "gn:dem":27,
    "gn:feature_class":"P",
    "gn:feature_code":"PPL",
    "gn:name":"Bantad",
    "gn:population":0,
    "gn:timezone":"Asia/Manila",
    "iso:country":"PH",
    "name:fil_x_preferred":[
        "Bantad"
    ],
    "wof:name":"Bantad",
    "wof:placetype":"locality"
},
  "geometry": {"coordinates":[121.84829999999999,13.4568],"type":"Point"}
}