{
  "type": "Feature",
  "properties": {
    "gn:admin1_code":"11",
    "gn:admin2_code":"I7",
    "gn:admin3_code":"112317000.0",
    "gn:asciiname":"Linosutan",
    "gn:country_code":"PH",
    "gn:dem":-29,
    "gn:feature_class":"P",
    "gn:feature_code":"PPL",
    "gn:name":"Linosutan",
    "gn:population":0,
    "gn:timezone":"Asia/Manila",
    "iso:country":"PH",
    "name:fil_x_preferred":[
        "Linosutan"
    ],
    "wof:name":"Linosutan",
    "wof:placetype":"locality"
},
  "geometry": {"coordinates":[125.69361000000001,6.92222],"type":"Point"}
}