{
  "type": "Feature",
  "properties": {
    "gn:admin1_code":"01",
    "gn:admin2_code":"29",
    "gn:admin3_code":"12906000.0",
    "gn:asciiname":"Tamurong Primero",
    "gn:country_code":"PH",
    "gn:dem":7,
    "gn:feature_class":"P",
    "gn:feature_code":"PPL",
    "gn:name":"Tamurong Primero",
    "gn:population":0,
    "gn:timezone":"Asia/Manila",
    "iso:country":"PH",
    "name:und_x_variant":[
        "Tamurong"
    ],
    "wof:name":"Tamurong Primero",
    "wof:placetype":"locality"
},
  "geometry": {"coordinates":[120.41039000000001,17.21481],"type":"Point"}
}