{
  "type": "Feature",
  "properties": {
    "gn:admin1_code":"12",
    "gn:admin2_code":"M9",
    "gn:admin3_code":"128006000.0",
    "gn:asciiname":"Lintak",
    "gn:country_code":"PH",
    "gn:dem":486,
    "gn:feature_class":"P",
    "gn:feature_code":"PPL",
    "gn:name":"Lintak",
    "gn:population":0,
    "gn:timezone":"Asia/Manila",
    "iso:country":"PH",
    "name:fil_x_preferred":[
        "Lintak"
    ],
    "wof:name":"Lintak",
    "wof:placetype":"locality"
},
  "geometry": {"coordinates":[125.34999999999999,5.88333],"type":"Point"}
}