{
  "type": "Feature",
  "properties": {
    "gn:country":"PH",
    "gn:fcode":"ADM3",
    "gn:population":20626,
    "iso:country":"PH",
    "name:fil_x_preferred":[
        "Bacolod Grande"
    ],
    "qs:name":"Bacolod Grande",
    "qs:photos_9r":0,
    "qs:photos_sr":0,
    "qs:pop_sr":"7",
    "wof:name":"Bacolod Grande",
    "wof:placetype":"localadmin",
    "wof:population":20626
},
  "geometry": {"coordinates":[124.11667,7.88333],"type":"Point"}
}