{
  "type": "Feature",
  "properties": {
    "gn:admin1_code":"06",
    "gn:admin2_code":"H3",
    "gn:admin3_code":"64517000.0",
    "gn:asciiname":"Zamora",
    "gn:country_code":"PH",
    "gn:dem":122,
    "gn:elevation":"0.0",
    "gn:feature_class":"P",
    "gn:feature_code":"PPL",
    "gn:name":"Zamora",
    "gn:population":0,
    "gn:timezone":"Asia/Manila",
    "iso:country":"PH",
    "name:fil_x_preferred":[
        "Zamora"
    ],
    "wof:name":"Zamora",
    "wof:placetype":"locality"
},
  "geometry": {"coordinates":[123.0176,10.3704],"type":"Point"}
}