{
  "type": "Feature",
  "properties": {
    "gn:admin1_code":"06",
    "gn:admin2_code":"H3",
    "gn:admin3_code":"64517000.0",
    "gn:asciiname":"Zamora",
    "gn:country_code":"PH",
    "gn:dem":122,
    "gn:elevation":"0.0",
    "gn:feature_class":"P",
    "gn:feature_code":"PPL",
    "gn:name":"Zamora",
    "gn:population":0,
    "gn:timezone":"Asia/Manila",
    "iso:country":"PH",
    "name:ara_x_preferred":[
        "\u0632\u0627\u0645\u0648\u0631\u0627"
    ],
    "name:bel_x_preferred":[
        "\u0421\u0430\u043c\u043e\u0440\u0430"
    ],
    "name:bre_x_preferred":[
        "Zamora"
    ],
    "name:cat_x_preferred":[
        "Zamora"
    ],
    "name:ceb_x_preferred":[
        "Zamora"
    ],
    "name:ces_x_preferred":[
        "Zamora"
    ],
    "name:dan_x_preferred":[
        "Zamora"
    ],
    "name:deu_x_preferred":[
        "Zamora"
    ],
    "name:epo_x_preferred":[
        "Zamoro"
    ],
    "name:eus_x_preferred":[
        "Zamora"
    ],
    "name:fas_x_preferred":[
        "\u0632\u0627\u0645\u0648\u0631\u0627"
    ],
    "name:fil_x_preferred":[
        "Zamora"
    ],
    "name:fin_x_preferred":[
        "Zamora"
    ],
    "name:fra_x_preferred":[
        "Zamora"
    ],
    "name:glg_x_preferred":[
        "Zamora"
    ],
    "name:hrv_x_preferred":[
        "Zamora"
    ],
    "name:ina_x_preferred":[
        "Zamora"
    ],
    "name:ita_x_preferred":[
        "Zamora"
    ],
    "name:jpn_x_preferred":[
        "\u30b5\u30e2\u30e9"
    ],
    "name:kor_x_preferred":[
        "\uc0ac\ubaa8\ub77c"
    ],
    "name:ltz_x_preferred":[
        "Zamora"
    ],
    "name:mlg_x_preferred":[
        "Zamora"
    ],
    "name:nld_x_preferred":[
        "Zamora"
    ],
    "name:nor_x_preferred":[
        "Zamora"
    ],
    "name:pol_x_preferred":[
        "Zamora"
    ],
    "name:por_x_preferred":[
        "Zamora"
    ],
    "name:ron_x_preferred":[
        "Zamora"
    ],
    "name:rus_x_preferred":[
        "\u0421\u0430\u043c\u043e\u0440\u0430"
    ],
    "name:sco_x_preferred":[
        "Zamora"
    ],
    "name:slk_x_preferred":[
        "Zamora"
    ],
    "name:spa_x_preferred":[
        "Zamora"
    ],
    "name:srp_x_preferred":[
        "\u0417\u0430\u043c\u043e\u0440\u0430"
    ],
    "name:swe_x_preferred":[
        "Zamora"
    ],
    "name:tur_x_preferred":[
        "Zamora"
    ],
    "name:ukr_x_preferred":[
        "\u0421\u0430\u043c\u043e\u0440\u0430"
    ],
    "name:vie_x_preferred":[
        "Zamora"
    ],
    "name:war_x_preferred":[
        "Zamora"
    ],
    "name:zho_x_preferred":[
        "\u8428\u83ab\u62c9"
    ],
    "wof:name":"Zamora",
    "wof:placetype":"locality"
},
  "geometry": {"coordinates":[123.0176,10.3704],"type":"Point"}
}