{
  "type": "Feature",
  "properties": {
    "gn:admin1_code":"08",
    "gn:admin2_code":"37",
    "gn:admin3_code":"83714000.0",
    "gn:asciiname":"Inambak",
    "gn:country_code":"PH",
    "gn:dem":61,
    "gn:feature_class":"P",
    "gn:feature_code":"PPL",
    "gn:name":"Inambak",
    "gn:population":0,
    "gn:timezone":"Asia/Manila",
    "iso:country":"PH",
    "name:eng_x_preferred":[
        "Inambak"
    ],
    "wof:name":"Inambak",
    "wof:placetype":"locality"
},
  "geometry": {"coordinates":[124.5646,11.2803],"type":"Point"}
}