{
  "type": "Feature",
  "properties": {
    "gn:country":"PH",
    "gn:fcode":"PPL",
    "gn:pop":2611,
    "iso:country":"PH",
    "name:fil_x_preferred":[
        "Caracal"
    ],
    "qs:name":"Caracal",
    "qs:photos_9r":0,
    "qs:photos_sr":0,
    "qs:pop_sr":"4",
    "wd:wordcount":3612,
    "wof:name":"Caracal",
    "wof:placetype":"locality",
    "wof:population":2611
},
  "geometry": {"coordinates":[122.845,8.12722],"type":"Point"}
}