{
  "type": "Feature",
  "properties": {
    "gn:admin1_code":"07",
    "gn:admin2_code":"46",
    "gn:admin3_code":"74604000.0",
    "gn:asciiname":"Maasiom",
    "gn:country_code":"PH",
    "gn:dem":111,
    "gn:feature_class":"P",
    "gn:feature_code":"PPL",
    "gn:name":"Maasiom",
    "gn:population":0,
    "gn:timezone":"Asia/Manila",
    "iso:country":"PH",
    "name:fil_x_preferred":[
        "Maasiom"
    ],
    "name:und_x_variant":[
        "Maaslom"
    ],
    "wof:name":"Maasiom",
    "wof:placetype":"locality"
},
  "geometry": {"coordinates":[123.0872,9.6434],"type":"Point"}
}