{
  "type": "Feature",
  "properties": {
    "gn:admin1_code":"08",
    "gn:admin2_code":"55",
    "gn:admin3_code":"86009000.0",
    "gn:asciiname":"Malino",
    "gn:country_code":"PH",
    "gn:dem":221,
    "gn:feature_class":"P",
    "gn:feature_code":"PPL",
    "gn:name":"Malino",
    "gn:population":0,
    "gn:timezone":"Asia/Manila",
    "iso:country":"PH",
    "name:fil_x_preferred":[
        "Malino"
    ],
    "wof:name":"Malino",
    "wof:placetype":"locality"
},
  "geometry": {"coordinates":[124.98333,11.83333],"type":"Point"}
}