{
  "type": "Feature",
  "properties": {
    "gn:admin1_code":"08",
    "gn:admin2_code":"23",
    "gn:admin3_code":"82606000.0",
    "gn:asciiname":"Maloboga",
    "gn:country_code":"PH",
    "gn:dem":23,
    "gn:feature_class":"P",
    "gn:feature_code":"PPL",
    "gn:name":"Maloboga",
    "gn:population":0,
    "gn:timezone":"Asia/Manila",
    "iso:country":"PH",
    "name:fil_x_preferred":[
        "Maloboga"
    ],
    "wof:name":"Maloboga",
    "wof:placetype":"locality"
},
  "geometry": {"coordinates":[125.47669999999999,12.0736],"type":"Point"}
}