{
  "type": "Feature",
  "properties": {
    "gn:admin1_code":"01",
    "gn:admin2_code":"28",
    "gn:admin3_code":"12815000.0",
    "gn:asciiname":"Tarrag",
    "gn:country_code":"PH",
    "gn:dem":17,
    "gn:feature_class":"P",
    "gn:feature_code":"PPL",
    "gn:name":"Tarrag",
    "gn:population":0,
    "gn:timezone":"Asia/Manila",
    "iso:country":"PH",
    "name:fil_x_preferred":[
        "Tarrag"
    ],
    "wof:name":"Tarrag",
    "wof:placetype":"locality"
},
  "geometry": {"coordinates":[120.7945,18.5368],"type":"Point"}
}