{
  "type": "Feature",
  "properties": {
    "gn:admin1_code":"12",
    "gn:admin2_code":"B8",
    "gn:asciiname":"Pidtimbasan",
    "gn:cc2":"PH",
    "gn:country_code":"PH",
    "gn:dem":7,
    "gn:feature_class":"P",
    "gn:feature_code":"PPL",
    "gn:name":"Pidtimbasan",
    "gn:population":0,
    "gn:timezone":"Asia/Manila",
    "iso:country":"PH",
    "name:und_x_variant":[
        "Pitimbason"
    ],
    "wof:name":"Pidtimbasan",
    "wof:placetype":"locality"
},
  "geometry": {"coordinates":[124.30694,7.19306],"type":"Point"}
}