{
  "type": "Feature",
  "properties": {
    "gn:admin1_code":"40",
    "gn:admin2_code":"33",
    "gn:admin3_code":"43410000.0",
    "gn:asciiname":"Maravilla",
    "gn:country_code":"PH",
    "gn:dem":47,
    "gn:feature_class":"P",
    "gn:feature_code":"PPL",
    "gn:name":"Maravilla",
    "gn:population":0,
    "gn:timezone":"Asia/Manila",
    "iso:country":"PH",
    "name:fil_x_preferred":[
        "Maravilla"
    ],
    "name:spa_x_preferred":[
        "Maravilla"
    ],
    "wof:name":"Maravilla",
    "wof:placetype":"locality"
},
  "geometry": {"coordinates":[121.40779999999999,14.207],"type":"Point"}
}