{
  "type": "Feature",
  "properties": {
    "gn:country":"PH",
    "gn:fcode":"PPL",
    "gn:population":2720,
    "iso:country":"PH",
    "name:ast_x_preferred":[
        "Tapia"
    ],
    "name:cat_x_preferred":[
        "Tapia"
    ],
    "name:ceb_x_preferred":[
        "Tapia"
    ],
    "name:ces_x_preferred":[
        "Tapia"
    ],
    "name:deu_x_preferred":[
        "Tapia"
    ],
    "name:eus_x_preferred":[
        "Tapia"
    ],
    "name:fil_x_preferred":[
        "Tapia"
    ],
    "name:fin_x_preferred":[
        "Tapia"
    ],
    "name:fra_x_preferred":[
        "Tapia"
    ],
    "name:hun_x_preferred":[
        "Tapia"
    ],
    "name:ita_x_preferred":[
        "Tapia"
    ],
    "name:rus_x_preferred":[
        "\u0422\u0430\u043f\u0438\u044f"
    ],
    "name:spa_x_preferred":[
        "Tapia"
    ],
    "name:swe_x_preferred":[
        "Tapia"
    ],
    "name:ukr_x_preferred":[
        "\u0422\u0430\u043f\u0456\u044f"
    ],
    "qs:name":"Tapia",
    "qs:photos_9r":0,
    "qs:photos_sr":0,
    "qs:pop_sr":"4",
    "wd:wordcount":122,
    "wof:name":"Tapia",
    "wof:placetype":"locality",
    "wof:population":2720
},
  "geometry": {"coordinates":[126.01194,7.75417],"type":"Point"}
}