{
  "type": "Feature",
  "properties": {
    "gn:admin1_code":"05",
    "gn:admin2_code":"05",
    "gn:admin3_code":"50503000.0",
    "gn:asciiname":"Banban",
    "gn:country_code":"PH",
    "gn:dem":52,
    "gn:feature_class":"P",
    "gn:feature_code":"PPL",
    "gn:name":"Banban",
    "gn:population":0,
    "gn:timezone":"Asia/Manila",
    "iso:country":"PH",
    "name:fil_x_preferred":[
        "Banban"
    ],
    "wof:name":"Banban",
    "wof:placetype":"locality"
},
  "geometry": {"coordinates":[123.71666999999999,13.08333],"type":"Point"}
}