{
  "type": "Feature",
  "properties": {
    "gn:admin1_code":"15",
    "gn:admin2_code":"01",
    "gn:admin3_code":"140120000.0",
    "gn:asciiname":"Maguyepyep",
    "gn:country_code":"PH",
    "gn:dem":215,
    "gn:feature_class":"P",
    "gn:feature_code":"PPL",
    "gn:name":"Maguyepyep",
    "gn:population":0,
    "gn:timezone":"Asia/Manila",
    "iso:country":"PH",
    "name:fil_x_preferred":[
        "Maguyepyep"
    ],
    "wof:name":"Maguyepyep",
    "wof:placetype":"locality"
},
  "geometry": {"coordinates":[120.76445,17.44083],"type":"Point"}
}