{
  "type": "Feature",
  "properties": {
    "gn:admin1_code":"08",
    "gn:admin2_code":"37",
    "gn:admin3_code":"83702000.0",
    "gn:asciiname":"Aslun",
    "gn:cc2":"PH",
    "gn:country_code":"PH",
    "gn:dem":34,
    "gn:feature_class":"P",
    "gn:feature_code":"PPL",
    "gn:name":"Aslun",
    "gn:population":0,
    "gn:timezone":"Asia/Manila",
    "iso:country":"PH",
    "name:und_x_variant":[
        "Aslom",
        "Aslun"
    ],
    "wof:name":"Aslun",
    "wof:placetype":"locality"
},
  "geometry": {"coordinates":[124.88472,11.16778],"type":"Point"}
}