{
  "type": "Feature",
  "properties": {
    "gn:admin1_code":"06",
    "gn:admin2_code":"30",
    "gn:admin3_code":"63028000.0",
    "gn:asciiname":"Ligtos",
    "gn:country_code":"PH",
    "gn:dem":122,
    "gn:feature_class":"P",
    "gn:feature_code":"PPL",
    "gn:name":"Ligtos",
    "gn:population":0,
    "gn:timezone":"Asia/Manila",
    "iso:country":"PH",
    "name:fil_x_preferred":[
        "Ligtos"
    ],
    "wof:name":"Ligtos",
    "wof:placetype":"locality"
},
  "geometry": {"coordinates":[122.366,10.82855],"type":"Point"}
}