{
  "type": "Feature",
  "properties": {
    "gn:admin1_code":"13",
    "gn:admin2_code":"61",
    "gn:admin3_code":"166717000.0",
    "gn:asciiname":"Mapaso",
    "gn:country_code":"PH",
    "gn:dem":12,
    "gn:feature_class":"P",
    "gn:feature_code":"PPL",
    "gn:name":"Mapaso",
    "gn:population":0,
    "gn:timezone":"Asia/Manila",
    "iso:country":"PH",
    "name:fil_x_preferred":[
        "Mapaso"
    ],
    "wof:name":"Mapaso",
    "wof:placetype":"locality"
},
  "geometry": {"coordinates":[125.5907,9.6506],"type":"Point"}
}