{
  "type": "Feature",
  "properties": {
    "gn:admin1_code":"11",
    "gn:admin2_code":"I7",
    "gn:admin3_code":"112301000.0",
    "gn:asciiname":"Sugayon",
    "gn:country_code":"PH",
    "gn:dem":31,
    "gn:feature_class":"P",
    "gn:feature_code":"PPL",
    "gn:name":"Sugayon",
    "gn:population":0,
    "gn:timezone":"Asia/Manila",
    "iso:country":"PH",
    "name:fil_x_preferred":[
        "Sugayon"
    ],
    "name:und_x_variant":[
        "Sagayon"
    ],
    "wof:name":"Sugayon",
    "wof:placetype":"locality"
},
  "geometry": {"coordinates":[125.7627,7.6474],"type":"Point"}
}