{
  "type": "Feature",
  "properties": {
    "gn:admin1_code":"14",
    "gn:admin2_code":"56",
    "gn:admin3_code":"153807000.0",
    "gn:asciiname":"Blit",
    "gn:country_code":"PH",
    "gn:dem":332,
    "gn:feature_class":"P",
    "gn:feature_code":"PPL",
    "gn:name":"Blit",
    "gn:population":0,
    "gn:timezone":"Asia/Manila",
    "iso:country":"PH",
    "name:fil_x_preferred":[
        "Blit"
    ],
    "wof:name":"Blit",
    "wof:placetype":"locality"
},
  "geometry": {"coordinates":[124.22444,7.00389],"type":"Point"}
}