{
  "type": "Feature",
  "properties": {
    "gn:admin1_code":"03",
    "gn:admin2_code":"50",
    "gn:admin3_code":"35410000.0",
    "gn:asciiname":"Telaxan",
    "gn:country_code":"PH",
    "gn:dem":3,
    "gn:feature_class":"P",
    "gn:feature_code":"PPL",
    "gn:name":"Telaxan",
    "gn:population":0,
    "gn:timezone":"Asia/Manila",
    "iso:country":"PH",
    "name:fil_x_preferred":[
        "Telaxan"
    ],
    "wof:name":"Telaxan",
    "wof:placetype":"locality"
},
  "geometry": {"coordinates":[120.657,14.8949],"type":"Point"}
}