{
  "type": "Feature",
  "properties": {
    "gn:admin1_code":"40",
    "gn:admin2_code":"09",
    "gn:admin3_code":"41003000.0",
    "gn:asciiname":"Gumamela",
    "gn:country_code":"PH",
    "gn:dem":26,
    "gn:feature_class":"P",
    "gn:feature_code":"PPL",
    "gn:name":"Gumamela",
    "gn:population":0,
    "gn:timezone":"Asia/Manila",
    "iso:country":"PH",
    "name:fil_x_preferred":[
        "Gumamela"
    ],
    "wof:name":"Gumamela",
    "wof:placetype":"locality"
},
  "geometry": {"coordinates":[120.74317000000001,13.94555],"type":"Point"}
}