{
  "type": "Feature",
  "properties": {
    "gn:admin1_code":"01",
    "gn:admin2_code":"29",
    "gn:admin3_code":"12905000.0",
    "gn:asciiname":"Lipit",
    "gn:country_code":"PH",
    "gn:dem":50,
    "gn:feature_class":"P",
    "gn:feature_code":"PPL",
    "gn:name":"Lipit",
    "gn:population":0,
    "gn:timezone":"Asia/Manila",
    "iso:country":"PH",
    "name:fil_x_preferred":[
        "Lipit"
    ],
    "name:fil_x_variant":[
        "Lipnit"
    ],
    "wof:name":"Lipit",
    "wof:placetype":"locality"
},
  "geometry": {"coordinates":[120.482,17.7712],"type":"Point"}
}