{
  "type": "Feature",
  "properties": {
    "gn:admin1_code":"10",
    "gn:admin2_code":"12",
    "gn:admin3_code":"101301000.0",
    "gn:asciiname":"San Vincente",
    "gn:country_code":"PH",
    "gn:dem":714,
    "gn:feature_class":"P",
    "gn:feature_code":"PPL",
    "gn:name":"San Vincente",
    "gn:population":0,
    "gn:timezone":"Asia/Manila",
    "iso:country":"PH",
    "name:fil_x_preferred":[
        "San Vincente"
    ],
    "wof:name":"San Vincente",
    "wof:placetype":"locality"
},
  "geometry": {"coordinates":[124.73528,8.23528],"type":"Point"}
}