{
  "type": "Feature",
  "properties": {
    "gn:admin1_code":"07",
    "gn:admin2_code":"11",
    "gn:asciiname":"Baliaut",
    "gn:country_code":"PH",
    "gn:dem":-9999,
    "gn:feature_class":"P",
    "gn:feature_code":"PPL",
    "gn:name":"Baliaut",
    "gn:population":0,
    "gn:timezone":"Asia/Manila",
    "iso:country":"PH",
    "name:fil_x_preferred":[
        "Baliaut"
    ],
    "wof:name":"Baliaut",
    "wof:placetype":"locality"
},
  "geometry": {"coordinates":[123.90000000000001,9.61667],"type":"Point"}
}