{
  "type": "Feature",
  "properties": {
    "gn:admin1_code":"03",
    "gn:admin2_code":"64",
    "gn:admin3_code":"37101000.0",
    "gn:asciiname":"Tauogtog",
    "gn:country_code":"PH",
    "gn:dem":17,
    "gn:feature_class":"P",
    "gn:feature_code":"PPL",
    "gn:name":"Tauogtog",
    "gn:population":0,
    "gn:timezone":"Asia/Manila",
    "iso:country":"PH",
    "name:fil_x_preferred":[
        "Tauogtog"
    ],
    "wof:name":"Tauogtog",
    "wof:placetype":"locality"
},
  "geometry": {"coordinates":[120.03333000000001,15.31667],"type":"Point"}
}