{
  "type": "Feature",
  "properties": {
    "gn:country":"PH",
    "gn:fcode":"PPL",
    "gn:pop":3612,
    "iso:country":"PH",
    "name:fil_x_preferred":[
        "Bulawin"
    ],
    "name:unk_x_variant":[
        "Bolawon"
    ],
    "qs:name":"Bulawin",
    "qs:photos_9r":0,
    "qs:photos_sr":0,
    "qs:pop_sr":"4",
    "wof:name":"Bulawin",
    "wof:placetype":"locality",
    "wof:population":3612
},
  "geometry": {"coordinates":[119.9564,15.4173],"type":"Point"}
}