{
  "type": "Feature",
  "properties": {
    "gn:admin1_code":"07",
    "gn:admin2_code":"21",
    "gn:admin3_code":"72224000.0",
    "gn:asciiname":"Doldol",
    "gn:country_code":"PH",
    "gn:dem":174,
    "gn:feature_class":"P",
    "gn:feature_code":"PPL",
    "gn:name":"Doldol",
    "gn:population":0,
    "gn:timezone":"Asia/Manila",
    "iso:country":"PH",
    "name:fil_x_preferred":[
        "Doldol"
    ],
    "wof:name":"Doldol",
    "wof:placetype":"locality"
},
  "geometry": {"coordinates":[123.4866,10.0668],"type":"Point"}
}