{
  "type": "Feature",
  "properties": {
    "gn:admin1_code":"14",
    "gn:admin2_code":"60",
    "gn:admin3_code":"156615000.0",
    "gn:asciiname":"Tapun Bubu",
    "gn:country_code":"PH",
    "gn:dem":7,
    "gn:feature_class":"P",
    "gn:feature_code":"PPL",
    "gn:name":"Tapun Bubu",
    "gn:population":0,
    "gn:timezone":"Asia/Manila",
    "iso:country":"PH",
    "name:eng_x_preferred":[
        "Tapun Bubu"
    ],
    "name:und_x_variant":[
        "Tambun Bubu"
    ],
    "wof:name":"Tapun Bubu",
    "wof:placetype":"locality"
},
  "geometry": {"coordinates":[121.85243,6.12465],"type":"Point"}
}