{
  "type": "Feature",
  "properties": {
    "gn:admin1_code":"06",
    "gn:admin2_code":"30",
    "gn:admin3_code":"63025000.0",
    "gn:asciiname":"Cabatangan",
    "gn:country_code":"PH",
    "gn:dem":337,
    "gn:feature_class":"P",
    "gn:feature_code":"PPL",
    "gn:name":"Cabatangan",
    "gn:population":0,
    "gn:timezone":"Asia/Manila",
    "iso:country":"PH",
    "name:fil_x_preferred":[
        "Cabatangan"
    ],
    "wof:name":"Cabatangan",
    "wof:placetype":"locality"
},
  "geometry": {"coordinates":[122.3646,11.07503],"type":"Point"}
}