{
  "type": "Feature",
  "properties": {
    "gn:country":"PH",
    "gn:fcode":"PPL",
    "gn:pop":2301,
    "iso:country":"PH",
    "name:unk_x_variant":[
        "Malidon"
    ],
    "qs:name":"Malidong",
    "qs:photos_9r":0,
    "qs:photos_sr":0,
    "qs:pop_sr":"4",
    "wof:name":"Malidong",
    "wof:placetype":"locality",
    "wof:population":2301
},
  "geometry": {"coordinates":[123.45962,13.01333],"type":"Point"}
}