{
  "type": "Feature",
  "properties": {
    "gn:admin1_code":"13",
    "gn:admin2_code":"61",
    "gn:admin3_code":"166727000.0",
    "gn:asciiname":"Timamana",
    "gn:country_code":"PH",
    "gn:dem":84,
    "gn:feature_class":"P",
    "gn:feature_code":"PPL",
    "gn:name":"Timamana",
    "gn:population":0,
    "gn:timezone":"Asia/Manila",
    "iso:country":"PH",
    "name:fil_x_preferred":[
        "Timamana"
    ],
    "wof:name":"Timamana",
    "wof:placetype":"locality"
},
  "geometry": {"coordinates":[125.5693,9.598],"type":"Point"}
}