{
  "type": "Feature",
  "properties": {
    "gn:admin1_code":"12",
    "gn:admin2_code":"71",
    "gn:admin3_code":"126506000.0",
    "gn:asciiname":"Kati",
    "gn:country_code":"PH",
    "gn:dem":30,
    "gn:feature_class":"P",
    "gn:feature_code":"PPL",
    "gn:name":"Kati",
    "gn:population":0,
    "gn:timezone":"Asia/Manila",
    "iso:country":"PH",
    "name:fil_x_preferred":[
        "Kati"
    ],
    "wof:name":"Kati",
    "wof:placetype":"locality"
},
  "geometry": {"coordinates":[124.111,6.62348],"type":"Point"}
}