{
  "type": "Feature",
  "properties": {
    "gn:admin1_code":"07",
    "gn:admin2_code":"46",
    "gn:admin3_code":"74620000.0",
    "gn:asciiname":"Tubtubon",
    "gn:country_code":"PH",
    "gn:dem":12,
    "gn:feature_class":"P",
    "gn:feature_code":"PPL",
    "gn:name":"Tubtubon",
    "gn:population":0,
    "gn:timezone":"Asia/Manila",
    "iso:country":"PH",
    "name:fil_x_preferred":[
        "Tubtubon"
    ],
    "name:und_x_variant":[
        "Tubtuban"
    ],
    "wof:name":"Tubtubon",
    "wof:placetype":"locality"
},
  "geometry": {"coordinates":[123.28489999999999,9.3523],"type":"Point"}
}