{
  "type": "Feature",
  "properties": {
    "gn:admin1_code":"02",
    "gn:admin2_code":"31",
    "gn:admin3_code":"23136000.0",
    "gn:asciiname":"Antagan",
    "gn:country_code":"PH",
    "gn:dem":32,
    "gn:feature_class":"P",
    "gn:feature_code":"PPL",
    "gn:name":"Antagan",
    "gn:population":0,
    "gn:timezone":"Asia/Manila",
    "iso:country":"PH",
    "name:fil_x_preferred":[
        "Antagan"
    ],
    "wof:name":"Antagan",
    "wof:placetype":"locality"
},
  "geometry": {"coordinates":[121.73999999999999,17.35448],"type":"Point"}
}