{
  "type": "Feature",
  "properties": {
    "gn:admin1_code":"08",
    "gn:admin2_code":"67",
    "gn:admin3_code":"84802000.0",
    "gn:asciiname":"Soleran",
    "gn:country_code":"PH",
    "gn:dem":-9999,
    "gn:feature_class":"P",
    "gn:feature_code":"PPL",
    "gn:name":"Soleran",
    "gn:population":0,
    "gn:timezone":"Asia/Manila",
    "iso:country":"PH",
    "name:fil_x_preferred":[
        "Soleran"
    ],
    "name:und_x_variant":[
        "Soleren"
    ],
    "wof:name":"Soleran",
    "wof:placetype":"locality"
},
  "geometry": {"coordinates":[124.36709999999999,12.6462],"type":"Point"}
}