{
  "type": "Feature",
  "properties": {
    "gn:admin1_code":"01",
    "gn:admin2_code":"51",
    "gn:admin3_code":"15533000.0",
    "gn:asciiname":"Cabaruan",
    "gn:country_code":"PH",
    "gn:dem":14,
    "gn:feature_class":"P",
    "gn:feature_code":"PPL",
    "gn:name":"Cabaruan",
    "gn:population":0,
    "gn:timezone":"Asia/Manila",
    "iso:country":"PH",
    "name:fil_x_preferred":[
        "Cabaroan"
    ],
    "name:fil_x_variant":[
        "Cabaruan"
    ],
    "wof:name":"Cabaruan",
    "wof:placetype":"locality"
},
  "geometry": {"coordinates":[120.42989,16.10533],"type":"Point"}
}