{
  "type": "Feature",
  "properties": {
    "gn:country":"PH",
    "gn:fcode":"PPL",
    "gn:pop":2168,
    "iso:country":"PH",
    "name:fil_x_preferred":[
        "Busdi"
    ],
    "name:unk_x_variant":[
        "Busde"
    ],
    "qs:name":"Busdi",
    "qs:photos_9r":0,
    "qs:photos_sr":0,
    "qs:pop_sr":"4",
    "wof:name":"Busdi",
    "wof:placetype":"locality",
    "wof:population":2168
},
  "geometry": {"coordinates":[125.25139,8.27611],"type":"Point"}
}