{
  "type": "Feature",
  "properties": {
    "iso:country":"PH",
    "name:fil_x_preferred":[
        "Apitong"
    ],
    "qs:gn_country":"PH",
    "qs:gn_fcode":"PPL",
    "qs:gn_pop":2402,
    "qs:name":"Apitong",
    "qs:name_adm0":"Philippines",
    "qs:name_adm1":"Mimaropa",
    "qs:photos":0,
    "qs:photos_1k":0,
    "qs:photos_9k":0,
    "qs:photos_9r":0,
    "qs:photos_all":0,
    "qs:photos_sr":0,
    "qs:placetype":"Town",
    "qs:pop_sr":"4",
    "qs:woe_adm0":23424934,
    "wd:wordcount":41,
    "wof:name":"Apitong",
    "wof:placetype":"locality",
    "wof:population":2402
},
  "geometry": {"coordinates":[121.2075,13.2391],"type":"Point"}
}