{
  "type": "Feature",
  "properties": {
    "gn:admin1_code":"06",
    "gn:admin2_code":"06",
    "gn:admin3_code":"60605000.0",
    "gn:asciiname":"Hiningaan",
    "gn:country_code":"PH",
    "gn:dem":20,
    "gn:feature_class":"P",
    "gn:feature_code":"PPL",
    "gn:name":"Hiningaan",
    "gn:population":0,
    "gn:timezone":"Asia/Manila",
    "iso:country":"PH",
    "name:fil_x_preferred":[
        "Hiningaan"
    ],
    "wof:name":"Hiningaan",
    "wof:placetype":"locality"
},
  "geometry": {"coordinates":[121.57810000000001,11.9161],"type":"Point"}
}