{
  "type": "Feature",
  "properties": {
    "gn:admin1_code":"15",
    "gn:admin2_code":"44",
    "gn:admin3_code":"144402000.0",
    "gn:asciiname":"Mount Data",
    "gn:country_code":"PH",
    "gn:dem":2139,
    "gn:feature_class":"P",
    "gn:feature_code":"PPL",
    "gn:name":"Mount Data",
    "gn:population":0,
    "gn:timezone":"Asia/Manila",
    "iso:country":"PH",
    "name:ceb_x_preferred":[
        "Mount Data"
    ],
    "name:deu_x_preferred":[
        "Data"
    ],
    "name:fil_x_preferred":[
        "Data"
    ],
    "name:ilo_x_preferred":[
        "Bantay Data"
    ],
    "name:nld_x_preferred":[
        "Mount Data"
    ],
    "name:nor_x_preferred":[
        "Mount Data"
    ],
    "name:spa_x_preferred":[
        "Monte Data"
    ],
    "wof:name":"Mount Data",
    "wof:placetype":"locality"
},
  "geometry": {"coordinates":[120.87388,16.86706],"type":"Point"}
}