{
  "type": "Feature",
  "properties": {
    "gn:admin1_code":"40",
    "gn:admin2_code":"09",
    "gn:admin3_code":"41018000.0",
    "gn:asciiname":"Lumang",
    "gn:country_code":"PH",
    "gn:dem":133,
    "gn:feature_class":"P",
    "gn:feature_code":"PPL",
    "gn:name":"Lumang",
    "gn:population":0,
    "gn:timezone":"Asia/Manila",
    "iso:country":"PH",
    "name:fil_x_preferred":[
        "Lumang"
    ],
    "name:und_x_variant":[
        "Lumang Lipa"
    ],
    "wof:name":"Lumang",
    "wof:placetype":"locality"
},
  "geometry": {"coordinates":[121.08629999999999,13.9748],"type":"Point"}
}