{
  "type": "Feature",
  "properties": {
    "gn:country":"PH",
    "gn:fcode":"PPL",
    "gn:population":2320,
    "iso:country":"PH",
    "name:fil_x_preferred":[
        "Pulangbato"
    ],
    "qs:name":"Pulangbato",
    "qs:photos_9r":0,
    "qs:photos_sr":0,
    "qs:pop_sr":"4",
    "wof:name":"Pulangbato",
    "wof:placetype":"locality",
    "wof:population":2320
},
  "geometry": {"coordinates":[121.39861000000001,13.7475],"type":"Point"}
}