{
  "type": "Feature",
  "properties": {
    "gn:admin1_code":"05",
    "gn:admin2_code":"58",
    "gn:admin3_code":"56207000.0",
    "gn:asciiname":"Banuangurang",
    "gn:country_code":"PH",
    "gn:dem":14,
    "gn:feature_class":"P",
    "gn:feature_code":"PPL",
    "gn:name":"Banuangurang",
    "gn:population":0,
    "gn:timezone":"Asia/Manila",
    "iso:country":"PH",
    "name:fil_x_preferred":[
        "Banuangurang"
    ],
    "name:und_x_variant":[
        "Bamaang Gurang"
    ],
    "wof:name":"Banuangurang",
    "wof:placetype":"locality"
},
  "geometry": {"coordinates":[123.6086,12.9575],"type":"Point"}
}