{
  "type": "Feature",
  "properties": {
    "gn:admin1_code":"40",
    "gn:admin2_code":"H2",
    "gn:admin3_code":"45607000.0",
    "gn:asciiname":"Agojo",
    "gn:country_code":"PH",
    "gn:dem":29,
    "gn:feature_class":"P",
    "gn:feature_code":"PPL",
    "gn:name":"Agojo",
    "gn:population":0,
    "gn:timezone":"Asia/Manila",
    "iso:country":"PH",
    "name:fil_x_preferred":[
        "Agojo"
    ],
    "name:und_x_variant":[
        "Agoho"
    ],
    "wof:name":"Agojo",
    "wof:placetype":"locality"
},
  "geometry": {"coordinates":[122.26452999999999,14.20475],"type":"Point"}
}