{
  "type": "Feature",
  "properties": {
    "gn:admin1_code":"40",
    "gn:admin2_code":"H2",
    "gn:admin3_code":"45607000.0",
    "gn:asciiname":"Esperanza Ilaya",
    "gn:country_code":"PH",
    "gn:dem":119,
    "gn:feature_class":"P",
    "gn:feature_code":"PPL",
    "gn:name":"Esperanza Ilaya",
    "gn:population":0,
    "gn:timezone":"Asia/Manila",
    "iso:country":"PH",
    "name:fil_x_preferred":[
        "Esperanza Ilaya"
    ],
    "name:und_x_variant":[
        "Esperanza Ibeya"
    ],
    "wof:name":"Esperanza Ilaya",
    "wof:placetype":"locality"
},
  "geometry": {"coordinates":[122.33333,13.91667],"type":"Point"}
}