{
  "type": "Feature",
  "properties": {
    "gn:admin1_code":"40",
    "gn:admin2_code":"H2",
    "gn:admin3_code":"45618000.0",
    "gn:asciiname":"Mulawin",
    "gn:country_code":"PH",
    "gn:dem":16,
    "gn:feature_class":"P",
    "gn:feature_code":"PPL",
    "gn:name":"Mulawin",
    "gn:population":0,
    "gn:timezone":"Asia/Manila",
    "iso:country":"PH",
    "name:ceb_x_preferred":[
        "Mulawin"
    ],
    "name:fil_x_preferred":[
        "Mulawin"
    ],
    "name:ind_x_preferred":[
        "Mulawin"
    ],
    "name:msa_x_preferred":[
        "Mulawin"
    ],
    "name:tgl_x_preferred":[
        "Mulawin"
    ],
    "wof:name":"Mulawin",
    "wof:placetype":"locality"
},
  "geometry": {"coordinates":[122.4207,13.9319],"type":"Point"}
}