{
  "type": "Feature",
  "properties": {
    "gn:admin1_code":"40",
    "gn:admin2_code":"53",
    "gn:admin3_code":"45807000.0",
    "gn:asciiname":"Looc",
    "gn:country_code":"PH",
    "gn:dem":4,
    "gn:feature_class":"P",
    "gn:feature_code":"PPL",
    "gn:name":"Looc",
    "gn:population":0,
    "gn:timezone":"Asia/Manila",
    "iso:country":"PH",
    "name:fil_x_preferred":[
        "Looc"
    ],
    "wof:name":"Looc",
    "wof:placetype":"locality"
},
  "geometry": {"coordinates":[121.32769999999999,14.373],"type":"Point"}
}