{
  "type": "Feature",
  "properties": {
    "gn:admin1_code":"40",
    "gn:admin2_code":"H2",
    "gn:admin3_code":"45624000.0",
    "gn:asciiname":"Colongcolong",
    "gn:country_code":"PH",
    "gn:dem":2,
    "gn:feature_class":"P",
    "gn:feature_code":"PPL",
    "gn:name":"Colongcolong",
    "gn:population":0,
    "gn:timezone":"Asia/Manila",
    "iso:country":"PH",
    "name:fil_x_preferred":[
        "Colongcolong"
    ],
    "wof:name":"Colongcolong",
    "wof:placetype":"locality"
},
  "geometry": {"coordinates":[121.63333,13.91667],"type":"Point"}
}