{
  "type": "Feature",
  "properties": {
    "gn:admin1_code":"03",
    "gn:admin2_code":"63",
    "gn:admin3_code":"36916000.0",
    "gn:asciiname":"Carangian",
    "gn:country_code":"PH",
    "gn:dem":55,
    "gn:feature_class":"P",
    "gn:feature_code":"PPL",
    "gn:name":"Carangian",
    "gn:population":0,
    "gn:timezone":"Asia/Manila",
    "iso:country":"PH",
    "name:fil_x_preferred":[
        "Carangian"
    ],
    "wof:name":"Carangian",
    "wof:placetype":"locality"
},
  "geometry": {"coordinates":[120.57473,15.48215],"type":"Point"}
}