{
  "type": "Feature",
  "properties": {
    "gn:admin1_code":"09",
    "gn:admin2_code":"ZSI",
    "gn:admin3_code":"98316000.0",
    "gn:asciiname":"Cayamcam",
    "gn:country_code":"PH",
    "gn:dem":16,
    "gn:feature_class":"P",
    "gn:feature_code":"PPL",
    "gn:name":"Cayamcam",
    "gn:population":0,
    "gn:timezone":"Asia/Manila",
    "iso:country":"PH",
    "name:fil_x_preferred":[
        "Gayamcam"
    ],
    "name:und_x_variant":[
        "Gayamcan"
    ],
    "wof:name":"Cayamcam",
    "wof:placetype":"locality"
},
  "geometry": {"coordinates":[122.37591999999999,7.52853],"type":"Point"}
}