{
  "type": "Feature",
  "properties": {
    "gn:admin1_code":"08",
    "gn:admin2_code":"37",
    "gn:admin3_code":"83746000.0",
    "gn:asciiname":"Kiloon",
    "gn:country_code":"PH",
    "gn:dem":14,
    "gn:feature_class":"P",
    "gn:feature_code":"PPL",
    "gn:name":"Kiloon",
    "gn:population":0,
    "gn:timezone":"Asia/Manila",
    "iso:country":"PH",
    "name:fil_x_preferred":[
        "Kiloon"
    ],
    "wof:name":"Kiloon",
    "wof:placetype":"locality"
},
  "geometry": {"coordinates":[124.98333,11.03333],"type":"Point"}
}