{
  "type": "Feature",
  "properties": {
    "gn:admin1_code":"41",
    "gn:admin2_code":"40",
    "gn:admin3_code":"175107000.0",
    "gn:asciiname":"Kalumpit",
    "gn:country_code":"PH",
    "gn:dem":403,
    "gn:feature_class":"P",
    "gn:feature_code":"PPL",
    "gn:name":"Kalumpit",
    "gn:population":0,
    "gn:timezone":"Asia/Manila",
    "iso:country":"PH",
    "name:eng_x_preferred":[
        "Kalumpit"
    ],
    "wof:name":"Kalumpit",
    "wof:placetype":"locality"
},
  "geometry": {"coordinates":[120.56619999999999,13.4911],"type":"Point"}
}