{
  "type": "Feature",
  "properties": {
    "gn:admin1_code":"02",
    "gn:admin2_code":"31",
    "gn:admin3_code":"23109000.0",
    "gn:asciiname":"Anonang",
    "gn:country_code":"PH",
    "gn:dem":217,
    "gn:feature_class":"P",
    "gn:feature_code":"PPL",
    "gn:name":"Anonang",
    "gn:population":0,
    "gn:timezone":"Asia/Manila",
    "iso:country":"PH",
    "name:fil_x_preferred":[
        "Anonang"
    ],
    "wof:name":"Anonang",
    "wof:placetype":"locality"
},
  "geometry": {"coordinates":[121.40860000000001,16.6768],"type":"Point"}
}