{
  "type": "Feature",
  "properties": {
    "gn:admin1_code":"40",
    "gn:admin2_code":"20",
    "gn:admin3_code":"42115000.0",
    "gn:asciiname":"Palangue II III",
    "gn:country_code":"PH",
    "gn:dem":88,
    "gn:feature_class":"P",
    "gn:feature_code":"PPL",
    "gn:name":"Palangue II III",
    "gn:population":0,
    "gn:timezone":"Asia/Manila",
    "iso:country":"PH",
    "name:fil_x_preferred":[
        "Palangue II III"
    ],
    "wof:name":"Palangue II III",
    "wof:placetype":"locality"
},
  "geometry": {"coordinates":[120.82021,14.27206],"type":"Point"}
}