{
  "type": "Feature",
  "properties": {
    "gn:admin1_code":"06",
    "gn:admin2_code":"30",
    "gn:admin3_code":"63038000.0",
    "gn:asciiname":"Siempreviva",
    "gn:country_code":"PH",
    "gn:dem":39,
    "gn:feature_class":"P",
    "gn:feature_code":"PPL",
    "gn:name":"Siempreviva",
    "gn:population":0,
    "gn:timezone":"Asia/Manila",
    "iso:country":"PH",
    "name:fil_x_preferred":[
        "Siempreviva"
    ],
    "name:und_x_variant":[
        "Simprevivo"
    ],
    "wof:name":"Siempreviva",
    "wof:placetype":"locality"
},
  "geometry": {"coordinates":[123.0926,11.2506],"type":"Point"}
}