{
  "type": "Feature",
  "properties": {
    "gn:admin1_code":"05",
    "gn:admin2_code":"58",
    "gn:admin3_code":"56212000.0",
    "gn:asciiname":"Manorabe",
    "gn:country_code":"PH",
    "gn:dem":14,
    "gn:feature_class":"P",
    "gn:feature_code":"PPL",
    "gn:name":"Manorabe",
    "gn:population":0,
    "gn:timezone":"Asia/Manila",
    "iso:country":"PH",
    "name:fil_x_preferred":[
        "Manorabe"
    ],
    "name:und_x_variant":[
        "Manurabe",
        "Manurabi"
    ],
    "wof:name":"Manorabe",
    "wof:placetype":"locality"
},
  "geometry": {"coordinates":[124.01309999999999,12.5422],"type":"Point"}
}