{
  "type": "Feature",
  "properties": {
    "gn:admin1_code":"03",
    "gn:admin2_code":"47",
    "gn:admin3_code":"34902000.0",
    "gn:asciiname":"Curva",
    "gn:country_code":"PH",
    "gn:dem":70,
    "gn:feature_class":"P",
    "gn:feature_code":"PPL",
    "gn:name":"Curva",
    "gn:population":0,
    "gn:timezone":"Asia/Manila",
    "iso:country":"PH",
    "name:fil_x_preferred":[
        "Curva"
    ],
    "name:und_x_variant":[
        "J. Tomacruz"
    ],
    "wof:name":"Curva",
    "wof:placetype":"locality"
},
  "geometry": {"coordinates":[121.1497,15.6225],"type":"Point"}
}