{
  "type": "Feature",
  "properties": {
    "gn:country":"PH",
    "gn:fcode":"PPL",
    "gn:population":3586,
    "iso:country":"PH",
    "name:und_x_variant":[
        "Caboluoy"
    ],
    "qs:name":"Cabaluay",
    "qs:photos_9r":0,
    "qs:photos_sr":0,
    "qs:pop_sr":"4",
    "wd:wordcount":297,
    "wof:name":"Cabaluay",
    "wof:placetype":"locality",
    "wof:population":3586
},
  "geometry": {"coordinates":[122.18028,7.00139],"type":"Point"}
}