{
  "type": "Feature",
  "properties": {
    "gn:admin1_code":"03",
    "gn:admin2_code":"63",
    "gn:admin3_code":"36913000.0",
    "gn:asciiname":"Pit-ao",
    "gn:country_code":"PH",
    "gn:dem":15,
    "gn:feature_class":"P",
    "gn:feature_code":"PPL",
    "gn:name":"Pit-ao",
    "gn:population":0,
    "gn:timezone":"Asia/Manila",
    "iso:country":"PH",
    "name:fil_x_preferred":[
        "Pitao"
    ],
    "wof:name":"Pit-ao",
    "wof:placetype":"locality"
},
  "geometry": {"coordinates":[120.37015,15.73245],"type":"Point"}
}