{
  "type": "Feature",
  "properties": {
    "gn:admin1_code":"15",
    "gn:admin2_code":"H6",
    "gn:admin3_code":"148101000.0",
    "gn:asciiname":"Naguilian",
    "gn:country_code":"PH",
    "gn:dem":281,
    "gn:feature_class":"P",
    "gn:feature_code":"PPL",
    "gn:name":"Naguilian",
    "gn:population":0,
    "gn:timezone":"Asia/Manila",
    "iso:country":"PH",
    "name:ceb_x_preferred":[
        "Naguilian"
    ],
    "name:deu_x_preferred":[
        "Naguilian"
    ],
    "name:fil_x_preferred":[
        "Naguilian"
    ],
    "name:fra_x_preferred":[
        "Naguilian"
    ],
    "name:ilo_x_preferred":[
        "Naguilian"
    ],
    "name:ita_x_preferred":[
        "Naguilian"
    ],
    "name:nld_x_preferred":[
        "Naguilian"
    ],
    "name:war_x_preferred":[
        "Naguilian"
    ],
    "wof:name":"Naguilian",
    "wof:placetype":"locality"
},
  "geometry": {"coordinates":[121.06667,18.11667000000001],"type":"Point"}
}