{
  "type": "Feature",
  "properties": {
    "gn:admin1_code":"15",
    "gn:admin2_code":"01",
    "gn:admin3_code":"140108000.0",
    "gn:asciiname":"Sumabsab",
    "gn:country_code":"PH",
    "gn:dem":103,
    "gn:feature_class":"P",
    "gn:feature_code":"PPL",
    "gn:name":"Sumabsab",
    "gn:population":0,
    "gn:timezone":"Asia/Manila",
    "iso:country":"PH",
    "name:fil_x_preferred":[
        "Sumabsab"
    ],
    "wof:name":"Sumabsab",
    "wof:placetype":"locality"
},
  "geometry": {"coordinates":[120.7028,17.7046],"type":"Point"}
}