{
  "type": "Feature",
  "properties": {
    "gn:admin1_code":"06",
    "gn:admin2_code":"18",
    "gn:admin3_code":"61902000.0",
    "gn:asciiname":"Centro",
    "gn:country_code":"PH",
    "gn:dem":21,
    "gn:feature_class":"P",
    "gn:feature_code":"PPL",
    "gn:name":"Centro",
    "gn:population":0,
    "gn:timezone":"Asia/Manila",
    "iso:country":"PH",
    "name:fil_x_preferred":[
        "Centro"
    ],
    "wof:name":"Centro",
    "wof:placetype":"locality"
},
  "geometry": {"coordinates":[122.7471,11.3485],"type":"Point"}
}