{
  "type": "Feature",
  "properties": {
    "gn:admin1_code":"01",
    "gn:admin2_code":"28",
    "gn:admin3_code":"12812000.0",
    "gn:asciiname":"Cavit",
    "gn:country_code":"PH",
    "gn:dem":5,
    "gn:feature_class":"P",
    "gn:feature_code":"PPL",
    "gn:name":"Cavit",
    "gn:population":0,
    "gn:timezone":"Asia/Manila",
    "iso:country":"PH",
    "name:deu_x_preferred":[
        "Cavit"
    ],
    "name:fil_x_preferred":[
        "Cavit"
    ],
    "wof:name":"Cavit",
    "wof:placetype":"locality"
},
  "geometry": {"coordinates":[120.53746,18.18687000000001],"type":"Point"}
}