{
  "type": "Feature",
  "properties": {
    "gn:country":"PH",
    "gn:fcode":"PPL",
    "gn:population":4005,
    "iso:country":"PH",
    "name:und_x_variant":[
        "Parian Dacula"
    ],
    "qs:name":"Parian Dakula",
    "qs:photos_9r":0,
    "qs:photos_sr":0,
    "qs:pop_sr":"4",
    "wof:name":"Parian Dakula",
    "wof:placetype":"locality",
    "wof:population":4005
},
  "geometry": {"coordinates":[120.77194,5.55667],"type":"Point"}
}