{
  "type": "Feature",
  "properties": {
    "gn:admin1_code":"02",
    "gn:admin2_code":"14",
    "gn:admin3_code":"21523000.0",
    "gn:asciiname":"Punti",
    "gn:country_code":"PH",
    "gn:dem":8,
    "gn:feature_class":"P",
    "gn:feature_code":"PPL",
    "gn:name":"Punti",
    "gn:population":0,
    "gn:timezone":"Asia/Manila",
    "iso:country":"PH",
    "name:fil_x_preferred":[
        "Punti"
    ],
    "name:nld_x_preferred":[
        "Wai t'auw"
    ],
    "name:zho_x_preferred":[
        "\u570d\u982d\u4eba"
    ],
    "wof:name":"Punti",
    "wof:placetype":"locality"
},
  "geometry": {"coordinates":[122.13105,18.39616],"type":"Point"}
}