{
  "type": "Feature",
  "properties": {
    "gn:admin1_code":"08",
    "gn:admin2_code":"67",
    "gn:admin3_code":"84811000.0",
    "gn:asciiname":"Calgomawas",
    "gn:country_code":"PH",
    "gn:dem":50,
    "gn:feature_class":"P",
    "gn:feature_code":"PPL",
    "gn:name":"Calgomawas",
    "gn:population":0,
    "gn:timezone":"Asia/Manila",
    "iso:country":"PH",
    "name:fil_x_preferred":[
        "Calgomawas"
    ],
    "wof:name":"Calgomawas",
    "wof:placetype":"locality"
},
  "geometry": {"coordinates":[124.30929999999999,12.5459],"type":"Point"}
}