{
  "type": "Feature",
  "properties": {
    "gn:admin1_code":"12",
    "gn:admin2_code":"M9",
    "gn:admin3_code":"128001000.0",
    "gn:asciiname":"Ladol",
    "gn:country_code":"PH",
    "gn:dem":8,
    "gn:feature_class":"P",
    "gn:feature_code":"PPL",
    "gn:name":"Ladol",
    "gn:population":0,
    "gn:timezone":"Asia/Manila",
    "iso:country":"PH",
    "name:fil_x_preferred":[
        "Ladol"
    ],
    "wof:name":"Ladol",
    "wof:placetype":"locality"
},
  "geometry": {"coordinates":[125.2825,6.07917],"type":"Point"}
}