{
  "type": "Feature",
  "properties": {
    "gn:admin1_code":"06",
    "gn:admin2_code":"30",
    "gn:admin3_code":"63018000.0",
    "gn:asciiname":"Patlad",
    "gn:country_code":"PH",
    "gn:dem":0,
    "gn:feature_class":"P",
    "gn:feature_code":"PPL",
    "gn:name":"Patlad",
    "gn:population":0,
    "gn:timezone":"Asia/Manila",
    "iso:country":"PH",
    "name:fil_x_preferred":[
        "Patlad"
    ],
    "wof:name":"Patlad",
    "wof:placetype":"locality"
},
  "geometry": {"coordinates":[122.666,10.812],"type":"Point"}
}