{
  "type": "Feature",
  "properties": {
    "gn:country":"PH",
    "gn:fcode":"ADM3",
    "gn:population":28415,
    "iso:country":"PH",
    "name:fil_x_preferred":[
        "Kitaotao"
    ],
    "qs:name":"Kitaotao",
    "qs:photos_9r":0,
    "qs:photos_sr":0,
    "qs:pop_sr":"7",
    "wof:name":"Kitaotao",
    "wof:placetype":"localadmin",
    "wof:population":28415
},
  "geometry": {"coordinates":[125.06667,7.61667],"type":"Point"}
}