{
  "type": "Feature",
  "properties": {
    "gn:admin1_code":"01",
    "gn:admin2_code":"51",
    "gn:admin3_code":"15527000.0",
    "gn:asciiname":"Malunec",
    "gn:country_code":"PH",
    "gn:dem":22,
    "gn:feature_class":"P",
    "gn:feature_code":"PPL",
    "gn:name":"Malunec",
    "gn:population":0,
    "gn:timezone":"Asia/Manila",
    "iso:country":"PH",
    "name:fil_x_preferred":[
        "Malunoc"
    ],
    "name:und_x_variant":[
        "Malunec"
    ],
    "wof:name":"Malunec",
    "wof:placetype":"locality"
},
  "geometry": {"coordinates":[120.26518,15.80961],"type":"Point"}
}