{
  "type": "Feature",
  "properties": {
    "gn:admin1_code":"05",
    "gn:admin2_code":"39",
    "gn:admin3_code":"54101000.0",
    "gn:asciiname":"Lanang",
    "gn:country_code":"PH",
    "gn:dem":7,
    "gn:elevation":"0.0",
    "gn:feature_class":"P",
    "gn:feature_code":"PPL",
    "gn:name":"Lanang",
    "gn:population":0,
    "gn:timezone":"Asia/Manila",
    "iso:country":"PH",
    "name:fil_x_preferred":[
        "Lanang"
    ],
    "wof:name":"Lanang",
    "wof:placetype":"locality"
},
  "geometry": {"coordinates":[123.3738,12.4321],"type":"Point"}
}