{
  "type": "Feature",
  "properties": {
    "gn:admin1_code":"03",
    "gn:admin2_code":"47",
    "gn:admin3_code":"34911000.0",
    "gn:asciiname":"Maybubon",
    "gn:country_code":"PH",
    "gn:dem":27,
    "gn:feature_class":"P",
    "gn:feature_code":"PPL",
    "gn:name":"Maybubon",
    "gn:population":0,
    "gn:timezone":"Asia/Manila",
    "iso:country":"PH",
    "name:fil_x_preferred":[
        "Maybobon"
    ],
    "wof:name":"Maybubon",
    "wof:placetype":"locality"
},
  "geometry": {"coordinates":[120.6651,15.6687],"type":"Point"}
}