{
  "type": "Feature",
  "properties": {
    "gn:admin1_code":"06",
    "gn:admin2_code":"H3",
    "gn:admin3_code":"64502000.0",
    "gn:asciiname":"Araal",
    "gn:country_code":"PH",
    "gn:dem":217,
    "gn:feature_class":"P",
    "gn:feature_code":"PPL",
    "gn:name":"Araal",
    "gn:population":0,
    "gn:timezone":"Asia/Manila",
    "iso:country":"PH",
    "name:fil_x_preferred":[
        "Araal"
    ],
    "name:fil_x_variant":[
        "Arraal"
    ],
    "wof:name":"Araal",
    "wof:placetype":"locality"
},
  "geometry": {"coordinates":[123.03440000000001,10.4411],"type":"Point"}
}