{
  "type": "Feature",
  "properties": {
    "gn:admin1_code":"15",
    "gn:admin2_code":"01",
    "gn:admin3_code":"140108000.0",
    "gn:asciiname":"Canan",
    "gn:country_code":"PH",
    "gn:dem":62,
    "gn:feature_class":"P",
    "gn:feature_code":"PPL",
    "gn:name":"Canan",
    "gn:population":0,
    "gn:timezone":"Asia/Manila",
    "iso:country":"PH",
    "name:deu_x_preferred":[
        "Canan"
    ],
    "name:fil_x_preferred":[
        "Canan"
    ],
    "name:fil_x_variant":[
        "Kanan"
    ],
    "name:fra_x_preferred":[
        "Canan"
    ],
    "wof:name":"Canan",
    "wof:placetype":"locality"
},
  "geometry": {"coordinates":[120.66889999999999,17.66099999999999],"type":"Point"}
}