{
  "type": "Feature",
  "properties": {
    "gn:admin1_code":"06",
    "gn:admin2_code":"30",
    "gn:admin3_code":"63023000.0",
    "gn:asciiname":"Ambulong",
    "gn:country_code":"PH",
    "gn:dem":85,
    "gn:feature_class":"P",
    "gn:feature_code":"PPL",
    "gn:name":"Ambulong",
    "gn:population":0,
    "gn:timezone":"Asia/Manila",
    "iso:country":"PH",
    "name:ceb_x_preferred":[
        "Ambulong Island"
    ],
    "name:fil_x_preferred":[
        "Ambulong"
    ],
    "wof:name":"Ambulong",
    "wof:placetype":"locality"
},
  "geometry": {"coordinates":[122.4937,10.9467],"type":"Point"}
}