{
  "type": "Feature",
  "properties": {
    "gn:admin1_code":"06",
    "gn:admin2_code":"06",
    "gn:admin3_code":"60608000.0",
    "gn:asciiname":"Paso",
    "gn:country_code":"PH",
    "gn:dem":134,
    "gn:feature_class":"P",
    "gn:feature_code":"PPL",
    "gn:name":"Paso",
    "gn:population":0,
    "gn:timezone":"Asia/Manila",
    "iso:country":"PH",
    "name:ceb_x_preferred":[
        "Paso"
    ],
    "name:deu_x_preferred":[
        "Paso"
    ],
    "name:fil_x_preferred":[
        "Paso"
    ],
    "name:fra_x_preferred":[
        "Paso"
    ],
    "name:glg_x_preferred":[
        "Paso"
    ],
    "name:rus_x_preferred":[
        "\u041f\u0430\u0441\u043e"
    ],
    "name:spa_x_preferred":[
        "Paso"
    ],
    "name:swe_x_preferred":[
        "Paso"
    ],
    "name:und_x_variant":[
        "Pasu"
    ],
    "wof:name":"Paso",
    "wof:placetype":"locality"
},
  "geometry": {"coordinates":[122.0472,10.6762],"type":"Point"}
}