{
  "type": "Feature",
  "properties": {
    "gn:admin1_code":"06",
    "gn:admin2_code":"30",
    "gn:admin3_code":"63022000.0",
    "gn:asciiname":"Tabuk-Suba",
    "gn:country_code":"PH",
    "gn:dem":7,
    "gn:feature_class":"P",
    "gn:feature_code":"PPL",
    "gn:name":"Tabuk-Suba",
    "gn:population":0,
    "gn:timezone":"Asia/Manila",
    "iso:country":"PH",
    "wof:name":"Tabuk-Suba",
    "wof:placetype":"locality"
},
  "geometry": {"coordinates":[122.56667,10.71667],"type":"Point"}
}