{
  "type": "Feature",
  "properties": {
    "gn:admin1_code":"06",
    "gn:admin2_code":"H3",
    "gn:admin3_code":"64521000.0",
    "gn:asciiname":"Sambag",
    "gn:country_code":"PH",
    "gn:dem":87,
    "gn:elevation":"0.0",
    "gn:feature_class":"P",
    "gn:feature_code":"PPL",
    "gn:name":"Sambag",
    "gn:population":0,
    "gn:timezone":"Asia/Manila",
    "iso:country":"PH",
    "name:fil_x_preferred":[
        "Sambag"
    ],
    "wof:name":"Sambag",
    "wof:placetype":"locality"
},
  "geometry": {"coordinates":[122.9696,10.3356],"type":"Point"}
}