{
  "type": "Feature",
  "properties": {
    "gn:admin1_code":"03",
    "gn:admin2_code":"G8",
    "gn:admin3_code":"37702000.0",
    "gn:asciiname":"Pasaroboy",
    "gn:country_code":"PH",
    "gn:dem":10,
    "gn:feature_class":"P",
    "gn:feature_code":"PPL",
    "gn:name":"Pasaroboy",
    "gn:population":0,
    "gn:timezone":"Asia/Manila",
    "iso:country":"PH",
    "name:fil_x_preferred":[
        "Pasaroboy"
    ],
    "name:und_x_variant":[
        "Pasaruboy"
    ],
    "wof:name":"Pasaroboy",
    "wof:placetype":"locality"
},
  "geometry": {"coordinates":[122.1288,16.2287],"type":"Point"}
}