{
  "type": "Feature",
  "properties": {
    "gn:country":"PH",
    "gn:fcode":"PPL",
    "gn:pop":2361,
    "iso:country":"PH",
    "name:fil_x_preferred":[
        "Bagroy"
    ],
    "qs:name":"Bagroy",
    "qs:photos_9r":0,
    "qs:photos_sr":0,
    "qs:pop_sr":"4",
    "wof:name":"Bagroy",
    "wof:placetype":"locality",
    "wof:population":2361
},
  "geometry": {"coordinates":[122.9362,10.2031],"type":"Point"}
}