{
  "type": "Feature",
  "properties": {
    "gn:admin1_code":"08",
    "gn:admin2_code":"23",
    "gn:admin3_code":"82609000.0",
    "gn:asciiname":"Suluan",
    "gn:country_code":"PH",
    "gn:dem":10,
    "gn:feature_class":"P",
    "gn:feature_code":"PPL",
    "gn:name":"Suluan",
    "gn:population":0,
    "gn:timezone":"Asia/Manila",
    "iso:country":"PH",
    "name:fil_x_preferred":[
        "Suluan"
    ],
    "name:por_x_preferred":[
        "Suluan"
    ],
    "name:war_x_preferred":[
        "Sul\u00fa-an"
    ],
    "wof:name":"Suluan",
    "wof:placetype":"locality"
},
  "geometry": {"coordinates":[125.831,10.9295],"type":"Point"}
}