{
  "type": "Feature",
  "properties": {
    "gn:admin1_code":"08",
    "gn:admin2_code":"67",
    "gn:admin3_code":"84803000.0",
    "gn:asciiname":"Bancalan",
    "gn:country_code":"PH",
    "gn:dem":6,
    "gn:feature_class":"P",
    "gn:feature_code":"PPL",
    "gn:name":"Bancalan",
    "gn:population":0,
    "gn:timezone":"Asia/Manila",
    "iso:country":"PH",
    "name:fil_x_preferred":[
        "Bancalan"
    ],
    "name:und_x_variant":[
        "Dancalan"
    ],
    "wof:name":"Bancalan",
    "wof:placetype":"locality"
},
  "geometry": {"coordinates":[124.5335,12.5187],"type":"Point"}
}