{
  "type": "Feature",
  "properties": {
    "gn:country":"PH",
    "gn:fcode":"PPL",
    "gn:pop":3936,
    "iso:country":"PH",
    "name:fil_x_preferred":[
        "Lamian"
    ],
    "qs:name":"Lamian",
    "qs:photos_9r":0,
    "qs:photos_sr":0,
    "qs:pop_sr":"4",
    "wd:wordcount":1428,
    "wof:name":"Lamian",
    "wof:placetype":"locality",
    "wof:population":3936
},
  "geometry": {"coordinates":[124.84639,6.30917],"type":"Point"}
}