{
  "type": "Feature",
  "properties": {
    "gn:country":"PH",
    "gn:fcode":"PPL",
    "gn:population":3936,
    "iso:country":"PH",
    "name:eng_x_preferred":[
        "pulled noodle"
    ],
    "name:fil_x_preferred":[
        "Lamian"
    ],
    "name:fra_x_preferred":[
        "La mian"
    ],
    "name:ind_x_preferred":[
        "Lamian"
    ],
    "name:ita_x_preferred":[
        "Lamian"
    ],
    "name:jpn_x_preferred":[
        "\u62c9\u9eba"
    ],
    "name:kor_x_preferred":[
        "\ub0a9\uba74"
    ],
    "name:nan_x_preferred":[
        "La-m\u012b"
    ],
    "name:nld_x_preferred":[
        "Lamian"
    ],
    "name:spa_x_preferred":[
        "Lamian"
    ],
    "name:vie_x_preferred":[
        "M\u00ec k\u00e9o"
    ],
    "name:yue_x_preferred":[
        "\u62c9\u9eb5"
    ],
    "name:zho_x_preferred":[
        "\u62c9\u9762"
    ],
    "qs:name":"Lamian",
    "qs:photos_9r":0,
    "qs:photos_sr":0,
    "qs:pop_sr":"4",
    "wd:wordcount":1428,
    "wof:name":"Lamian",
    "wof:placetype":"locality",
    "wof:population":3936
},
  "geometry": {"coordinates":[124.84639,6.30917],"type":"Point"}
}