{
  "type": "Feature",
  "properties": {
    "gn:admin1_code":"41",
    "gn:admin2_code":"54",
    "gn:admin3_code":"175912000.0",
    "gn:asciiname":"Camogtong",
    "gn:country_code":"PH",
    "gn:dem":17,
    "gn:feature_class":"P",
    "gn:feature_code":"PPL",
    "gn:name":"Camogtong",
    "gn:population":0,
    "gn:timezone":"Asia/Manila",
    "iso:country":"PH",
    "name:fil_x_preferred":[
        "Camogtong"
    ],
    "wof:name":"Camogtong",
    "wof:placetype":"locality"
},
  "geometry": {"coordinates":[122.0218,12.516],"type":"Point"}
}