{
  "type": "Feature",
  "properties": {
    "gn:admin1_code":"01",
    "gn:admin2_code":"51",
    "gn:admin3_code":"15521000.0",
    "gn:asciiname":"Magsaysay",
    "gn:country_code":"PH",
    "gn:dem":11,
    "gn:feature_class":"P",
    "gn:feature_code":"PPL",
    "gn:name":"Magsaysay",
    "gn:population":0,
    "gn:timezone":"Asia/Manila",
    "iso:country":"PH",
    "name:fil_x_preferred":[
        "Magsaysay"
    ],
    "wof:name":"Magsaysay",
    "wof:placetype":"locality"
},
  "geometry": {"coordinates":[120.15724,16.00652],"type":"Point"}
}