{
  "type": "Feature",
  "properties": {
    "gn:admin1_code":"05",
    "gn:admin2_code":"15",
    "gn:admin3_code":"51606000.0",
    "gn:asciiname":"Gahagahagan",
    "gn:country_code":"PH",
    "gn:dem":24,
    "gn:feature_class":"P",
    "gn:feature_code":"PPL",
    "gn:name":"Gahagahagan",
    "gn:population":0,
    "gn:timezone":"Asia/Manila",
    "iso:country":"PH",
    "name:fil_x_preferred":[
        "Gahagahagan"
    ],
    "wof:name":"Gahagahagan",
    "wof:placetype":"locality"
},
  "geometry": {"coordinates":[122.74160000000001,14.1825],"type":"Point"}
}