{
  "type": "Feature",
  "properties": {
    "gn:admin1_code":"02",
    "gn:admin2_code":"31",
    "gn:admin3_code":"23135000.0",
    "gn:asciiname":"Sinili",
    "gn:country_code":"PH",
    "gn:dem":106,
    "gn:feature_class":"P",
    "gn:feature_code":"PPL",
    "gn:name":"Sinili",
    "gn:population":0,
    "gn:timezone":"Asia/Manila",
    "iso:country":"PH",
    "wof:name":"Sinili",
    "wof:placetype":"locality"
},
  "geometry": {"coordinates":[121.56083,16.63332999999999],"type":"Point"}
}