{
  "type": "Feature",
  "properties": {
    "gn:admin1_code":"41",
    "gn:admin2_code":"41",
    "gn:admin3_code":"175208000.0",
    "gn:asciiname":"Bincong",
    "gn:country_code":"PH",
    "gn:dem":7,
    "gn:feature_class":"P",
    "gn:feature_code":"PPL",
    "gn:name":"Bincong",
    "gn:population":0,
    "gn:timezone":"Asia/Manila",
    "iso:country":"PH",
    "name:fil_x_preferred":[
        "Bincong"
    ],
    "wof:name":"Bincong",
    "wof:placetype":"locality"
},
  "geometry": {"coordinates":[121.36351999999999,13.27089],"type":"Point"}
}