{
  "type": "Feature",
  "properties": {
    "gn:admin1_code":"08",
    "gn:admin2_code":"55",
    "gn:admin3_code":"86002000.0",
    "gn:asciiname":"Cantaba",
    "gn:country_code":"PH",
    "gn:dem":8,
    "gn:feature_class":"P",
    "gn:feature_code":"PPL",
    "gn:name":"Cantaba",
    "gn:population":0,
    "gn:timezone":"Asia/Manila",
    "iso:country":"PH",
    "name:fil_x_preferred":[
        "Cantaba"
    ],
    "wof:name":"Cantaba",
    "wof:placetype":"locality"
},
  "geometry": {"coordinates":[125.06,11.31167],"type":"Point"}
}