{
  "type": "Feature",
  "properties": {
    "gn:admin1_code":"01",
    "gn:admin2_code":"51",
    "gn:admin3_code":"15545000.0",
    "gn:asciiname":"Baug",
    "gn:country_code":"PH",
    "gn:dem":13,
    "gn:feature_class":"P",
    "gn:feature_code":"PPL",
    "gn:name":"Baug",
    "gn:population":0,
    "gn:timezone":"Asia/Manila",
    "iso:country":"PH",
    "name:fil_x_preferred":[
        "Buag"
    ],
    "wof:name":"Baug",
    "wof:placetype":"locality"
},
  "geometry": {"coordinates":[120.36988999999998,15.81719],"type":"Point"}
}