{
  "type": "Feature",
  "properties": {
    "gn:admin1_code":"01",
    "gn:admin2_code":"51",
    "gn:admin3_code":"15542000.0",
    "gn:asciiname":"Cabitaoyan",
    "gn:country_code":"PH",
    "gn:dem":63,
    "gn:feature_class":"P",
    "gn:feature_code":"PPL",
    "gn:name":"Cabitaoyan",
    "gn:population":0,
    "gn:timezone":"Asia/Manila",
    "iso:country":"PH",
    "name:fil_x_preferred":[
        "Cabitaoyan"
    ],
    "wof:name":"Cabitaoyan",
    "wof:placetype":"locality"
},
  "geometry": {"coordinates":[120.05574,16.08172],"type":"Point"}
}