{
  "type": "Feature",
  "properties": {
    "gn:admin1_code":"40",
    "gn:admin2_code":"53",
    "gn:admin3_code":"45804000.0",
    "gn:asciiname":"Tabon",
    "gn:country_code":"PH",
    "gn:dem":99,
    "gn:feature_class":"P",
    "gn:feature_code":"PPL",
    "gn:name":"Tabon",
    "gn:population":0,
    "gn:timezone":"Asia/Manila",
    "iso:country":"PH",
    "name:fil_x_preferred":[
        "Tabon"
    ],
    "wof:name":"Tabon",
    "wof:placetype":"locality"
},
  "geometry": {"coordinates":[121.2342,14.3043],"type":"Point"}
}