{
  "type": "Feature",
  "properties": {
    "gn:admin1_code":"12",
    "gn:admin2_code":"57",
    "gn:admin3_code":"124703000.0",
    "gn:asciiname":"Abaga",
    "gn:country_code":"PH",
    "gn:dem":23,
    "gn:feature_class":"P",
    "gn:feature_code":"PPL",
    "gn:name":"Abaga",
    "gn:population":0,
    "gn:timezone":"Asia/Manila",
    "iso:country":"PH",
    "name:ceb_x_preferred":[
        "Abaga"
    ],
    "name:deu_x_preferred":[
        "Abaga"
    ],
    "name:fil_x_preferred":[
        "Abaga"
    ],
    "name:fra_x_preferred":[
        "Abaga"
    ],
    "name:swe_x_preferred":[
        "Abaga"
    ],
    "wof:name":"Abaga",
    "wof:placetype":"locality"
},
  "geometry": {"coordinates":[124.81667,7.16667],"type":"Point"}
}