{
  "type": "Feature",
  "properties": {
    "gn:admin1_code":"10",
    "gn:admin2_code":"17",
    "gn:admin3_code":"101801000.0",
    "gn:asciiname":"Kompol",
    "gn:country_code":"PH",
    "gn:dem":7,
    "gn:feature_class":"P",
    "gn:feature_code":"PPL",
    "gn:name":"Kompol",
    "gn:population":0,
    "gn:timezone":"Asia/Manila",
    "iso:country":"PH",
    "name:fil_x_preferred":[
        "Kompol"
    ],
    "wof:name":"Kompol",
    "wof:placetype":"locality"
},
  "geometry": {"coordinates":[124.66667,9.13333],"type":"Point"}
}