{
  "type": "Feature",
  "properties": {
    "gn:admin1_code":"07",
    "gn:admin2_code":"11",
    "gn:admin3_code":"71233000.0",
    "gn:asciiname":"Bolod",
    "gn:country_code":"PH",
    "gn:dem":19,
    "gn:feature_class":"P",
    "gn:feature_code":"PPL",
    "gn:name":"Bolod",
    "gn:population":0,
    "gn:timezone":"Asia/Manila",
    "iso:country":"PH",
    "name:fil_x_preferred":[
        "Bolod"
    ],
    "wof:name":"Bolod",
    "wof:placetype":"locality"
},
  "geometry": {"coordinates":[123.78436000000001,9.57556],"type":"Point"}
}