{
  "type": "Feature",
  "properties": {
    "gn:country":"PH",
    "gn:fcode":"PPL",
    "gn:pop":2236,
    "iso:country":"PH",
    "name:fil_x_preferred":[
        "Dapitan"
    ],
    "qs:name":"Dapitan",
    "qs:photos_9r":0,
    "qs:photos_sr":0,
    "qs:pop_sr":"4",
    "wd:wordcount":1409,
    "wof:name":"Dapitan",
    "wof:placetype":"locality",
    "wof:population":2236
},
  "geometry": {"coordinates":[123.94694,10.27056],"type":"Point"}
}