{
  "type": "Feature",
  "properties": {
    "gn:country":"PH",
    "gn:fcode":"PPL",
    "gn:pop":2236,
    "iso:country":"PH",
    "name:ara_x_preferred":[
        "\u062f\u0627\u0628\u064a\u062a\u0627\u0646"
    ],
    "name:bcl_x_preferred":[
        "Dapitan"
    ],
    "name:ben_x_preferred":[
        "\u09a1\u09be\u09aa\u09bf\u09a4\u09be\u09a8"
    ],
    "name:cat_x_preferred":[
        "Dapitan"
    ],
    "name:ceb_x_preferred":[
        "Dapitan"
    ],
    "name:dan_x_preferred":[
        "Dapitan"
    ],
    "name:deu_x_preferred":[
        "Dapitan"
    ],
    "name:diq_x_preferred":[
        "Dapitan"
    ],
    "name:ell_x_preferred":[
        "\u039d\u03c4\u03ac\u03c0\u03b9\u03c4\u03b1\u03bd"
    ],
    "name:eng_x_preferred":[
        "Dapitan"
    ],
    "name:fas_x_preferred":[
        "\u062f\u0627\u067e\u06cc\u062a\u0627\u0646"
    ],
    "name:fil_x_preferred":[
        "Dapitan"
    ],
    "name:fin_x_preferred":[
        "Dapitan"
    ],
    "name:fra_x_preferred":[
        "Dapitan"
    ],
    "name:guj_x_preferred":[
        "\u0aa6\u0ac7\u0aaa\u0abf\u0a9f\u0aa8"
    ],
    "name:hin_x_preferred":[
        "\u0926\u092a\u093f\u0924\u093e\u0928"
    ],
    "name:hun_x_preferred":[
        "Dapitan"
    ],
    "name:ilo_x_preferred":[
        "Dapitan"
    ],
    "name:ind_x_preferred":[
        "Dapitan"
    ],
    "name:ita_x_preferred":[
        "Dapitan"
    ],
    "name:jpn_x_preferred":[
        "\u30c0\u30d4\u30bf\u30f3"
    ],
    "name:kan_x_preferred":[
        "\u0ca1\u0caa\u0cbf\u0ca4\u0ca8\u0ccd"
    ],
    "name:kor_x_preferred":[
        "\ub2e4\ud53c\ud0c4"
    ],
    "name:lav_x_preferred":[
        "Dapitana"
    ],
    "name:lit_x_preferred":[
        "Dapitanas"
    ],
    "name:mar_x_preferred":[
        "\u0926\u0945\u092a\u093f\u091f\u0945\u0928"
    ],
    "name:msa_x_preferred":[
        "Dapitan"
    ],
    "name:nld_x_preferred":[
        "Dapitan"
    ],
    "name:nob_x_preferred":[
        "Dapitan"
    ],
    "name:pag_x_preferred":[
        "Dapitan"
    ],
    "name:pam_x_preferred":[
        "Dapitan"
    ],
    "name:pol_x_preferred":[
        "Dapitan"
    ],
    "name:por_x_preferred":[
        "Dapitan"
    ],
    "name:rus_x_preferred":[
        "\u0414\u0430\u043f\u0438\u0442\u0430\u043d"
    ],
    "name:sin_x_preferred":[
        "\u0da9\u0db4\u0dd2\u0da7\u0db1\u0dca"
    ],
    "name:spa_x_preferred":[
        "Dapitan"
    ],
    "name:swe_x_preferred":[
        "Dapitan"
    ],
    "name:tam_x_preferred":[
        "\u0b9f\u0baa\u0bcd\u0baa\u0bbf\u0b9f\u0ba9\u0bcd"
    ],
    "name:tel_x_preferred":[
        "\u0c21\u0c2a\u0c3f\u0c1f\u0c28\u0c4d"
    ],
    "name:tgl_x_preferred":[
        "Dapitan"
    ],
    "name:tha_x_preferred":[
        "\u0e14\u0e32\u0e1b\u0e34\u0e15\u0e31\u0e19"
    ],
    "name:tur_x_preferred":[
        "Dapitan"
    ],
    "name:ukr_x_preferred":[
        "\u0414\u0430\u043f\u0456\u0442\u0430\u043d"
    ],
    "name:urd_x_preferred":[
        "\u062f\u0627\u067e\u06cc\u062a\u0627\u0646"
    ],
    "name:vie_x_preferred":[
        "Dapitan"
    ],
    "name:war_x_preferred":[
        "Dapitan"
    ],
    "qs:name":"Dapitan",
    "qs:photos_9r":0,
    "qs:photos_sr":0,
    "qs:pop_sr":"4",
    "wd:wordcount":1409,
    "wof:name":"Dapitan",
    "wof:placetype":"locality",
    "wof:population":2236
},
  "geometry": {"coordinates":[123.94694,10.27056],"type":"Point"}
}