{
  "type": "Feature",
  "properties": {
    "gn:admin1_code":"07",
    "gn:admin2_code":"21",
    "gn:admin3_code":"72230000.0",
    "gn:asciiname":"Alang Alang",
    "gn:country_code":"PH",
    "gn:dem":8,
    "gn:feature_class":"P",
    "gn:feature_code":"PPL",
    "gn:name":"Alang Alang",
    "gn:population":0,
    "gn:timezone":"Asia/Manila",
    "iso:country":"PH",
    "name:fas_x_preferred":[
        "\u0627\u0644\u0627\u0646\u06af-\u0627\u0644\u0627\u0646\u06af"
    ],
    "name:fil_x_preferred":[
        "Alang Alang"
    ],
    "wof:name":"Alang Alang",
    "wof:placetype":"locality"
},
  "geometry": {"coordinates":[123.93333,10.33333],"type":"Point"}
}