{
  "type": "Feature",
  "properties": {
    "gn:admin1_code":"41",
    "gn:admin2_code":"54",
    "gn:admin3_code":"175902000.0",
    "gn:asciiname":"Tumalum",
    "gn:country_code":"PH",
    "gn:dem":30,
    "gn:feature_class":"P",
    "gn:feature_code":"PPL",
    "gn:name":"Tumalum",
    "gn:population":0,
    "gn:timezone":"Asia/Manila",
    "iso:country":"PH",
    "name:fil_x_preferred":[
        "Tumalum"
    ],
    "wof:name":"Tumalum",
    "wof:placetype":"locality"
},
  "geometry": {"coordinates":[122.08591,12.91571],"type":"Point"}
}