{
  "type": "Feature",
  "properties": {
    "gn:admin1_code":"03",
    "gn:admin2_code":"47",
    "gn:admin3_code":"34917000.0",
    "gn:asciiname":"Sawmill Student",
    "gn:country_code":"PH",
    "gn:dem":82,
    "gn:feature_class":"P",
    "gn:feature_code":"PPL",
    "gn:name":"Sawmill Student",
    "gn:population":0,
    "gn:timezone":"Asia/Manila",
    "iso:country":"PH",
    "name:fil_x_preferred":[
        "Sawmill Student"
    ],
    "wof:name":"Sawmill Student",
    "wof:placetype":"locality"
},
  "geometry": {"coordinates":[120.9421,15.729],"type":"Point"}
}