{
  "type": "Feature",
  "properties": {
    "gn:admin1_code":"13",
    "gn:admin2_code":"61",
    "gn:admin3_code":"166717000.0",
    "gn:asciiname":"Bugas-Bugas",
    "gn:country_code":"PH",
    "gn:dem":71,
    "gn:feature_class":"P",
    "gn:feature_code":"PPL",
    "gn:name":"Bugas-Bugas",
    "gn:population":0,
    "gn:timezone":"Asia/Manila",
    "iso:country":"PH",
    "name:fil_x_preferred":[
        "Bugas-Bugas"
    ],
    "wof:name":"Bugas-Bugas",
    "wof:placetype":"locality"
},
  "geometry": {"coordinates":[125.57470000000001,9.6531],"type":"Point"}
}