{
  "type": "Feature",
  "properties": {
    "gn:admin1_code":"01",
    "gn:admin2_code":"51",
    "gn:admin3_code":"15524000.0",
    "gn:asciiname":"Apaya",
    "gn:country_code":"PH",
    "gn:dem":16,
    "gn:feature_class":"P",
    "gn:feature_code":"PPL",
    "gn:name":"Apaya",
    "gn:population":0,
    "gn:timezone":"Asia/Manila",
    "iso:country":"PH",
    "name:azb_x_preferred":[
        "\u0622\u067e\u0627\u06cc\u0627"
    ],
    "name:fil_x_preferred":[
        "Apaya"
    ],
    "name:mya_x_preferred":[
        "\u1021\u1018\u101a\u1019\u101f\u102c\u101b\u102c\u1007\u102c"
    ],
    "wof:name":"Apaya",
    "wof:placetype":"locality"
},
  "geometry": {"coordinates":[120.41782000000001,15.88966],"type":"Point"}
}