{
  "type": "Feature",
  "properties": {
    "gn:admin1_code":"41",
    "gn:admin2_code":"49",
    "gn:admin3_code":"175310000.0",
    "gn:asciiname":"Baayad",
    "gn:country_code":"PH",
    "gn:dem":12,
    "gn:feature_class":"P",
    "gn:feature_code":"PPL",
    "gn:name":"Baayad",
    "gn:population":0,
    "gn:timezone":"Asia/Manila",
    "iso:country":"PH",
    "name:fil_x_preferred":[
        "Baayad"
    ],
    "wof:name":"Baayad",
    "wof:placetype":"locality"
},
  "geometry": {"coordinates":[121.03162,10.8026],"type":"Point"}
}