{
  "type": "Feature",
  "properties": {
    "gn:admin1_code":"10",
    "gn:admin2_code":"43",
    "gn:admin3_code":"104305000.0",
    "gn:asciiname":"Kabula",
    "gn:country_code":"PH",
    "gn:dem":50,
    "gn:feature_class":"P",
    "gn:feature_code":"PPL",
    "gn:name":"Kabula",
    "gn:population":0,
    "gn:timezone":"Asia/Manila",
    "iso:country":"PH",
    "name:fil_x_preferred":[
        "Kabula"
    ],
    "name:swa_x_preferred":[
        "Kabula"
    ],
    "name:und_x_variant":[
        "Sabula"
    ],
    "wof:name":"Kabula",
    "wof:placetype":"locality"
},
  "geometry": {"coordinates":[124.61278,8.39028],"type":"Point"}
}