{
  "type": "Feature",
  "properties": {
    "gn:admin1_code":"08",
    "gn:admin2_code":"37",
    "gn:admin3_code":"83743000.0",
    "gn:asciiname":"Tulaan",
    "gn:country_code":"PH",
    "gn:dem":5,
    "gn:feature_class":"P",
    "gn:feature_code":"PPL",
    "gn:name":"Tulaan",
    "gn:population":0,
    "gn:timezone":"Asia/Manila",
    "iso:country":"PH",
    "name:fil_x_preferred":[
        "Tulaan"
    ],
    "wof:name":"Tulaan",
    "wof:placetype":"locality"
},
  "geometry": {"coordinates":[124.8078,11.3855],"type":"Point"}
}