{
  "type": "Feature",
  "properties": {
    "gn:admin1_code":"06",
    "gn:admin2_code":"30",
    "gn:admin3_code":"63004000.0",
    "gn:asciiname":"Lonoc",
    "gn:country_code":"PH",
    "gn:dem":75,
    "gn:feature_class":"P",
    "gn:feature_code":"PPL",
    "gn:name":"Lonoc",
    "gn:population":0,
    "gn:timezone":"Asia/Manila",
    "iso:country":"PH",
    "name:fil_x_preferred":[
        "Lonoc"
    ],
    "wof:name":"Lonoc",
    "wof:placetype":"locality"
},
  "geometry": {"coordinates":[122.5264,10.9765],"type":"Point"}
}