{
  "type": "Feature",
  "properties": {
    "gn:admin1_code":"15",
    "gn:admin2_code":"H6",
    "gn:admin3_code":"148105000.0",
    "gn:asciiname":"San Gregorio",
    "gn:country_code":"PH",
    "gn:dem":22,
    "gn:feature_class":"P",
    "gn:feature_code":"PPL",
    "gn:name":"San Gregorio",
    "gn:population":0,
    "gn:timezone":"Asia/Manila",
    "iso:country":"PH",
    "name:ceb_x_preferred":[
        "San Gregorio"
    ],
    "name:ces_x_preferred":[
        "San Gregorio"
    ],
    "name:deu_x_preferred":[
        "San Gregorio"
    ],
    "name:fil_x_preferred":[
        "San Gregorio"
    ],
    "name:fra_x_preferred":[
        "San Gregorio"
    ],
    "name:glg_x_preferred":[
        "San Gregorio"
    ],
    "name:ita_x_preferred":[
        "San Gregorio"
    ],
    "name:nld_x_preferred":[
        "San Gregorio"
    ],
    "name:por_x_preferred":[
        "San Gregorio"
    ],
    "name:sco_x_preferred":[
        "San Gregorio"
    ],
    "name:spa_x_preferred":[
        "San Gregorio"
    ],
    "name:srp_x_preferred":[
        "San Gregorio"
    ],
    "name:swe_x_preferred":[
        "San Gregorio"
    ],
    "wof:name":"San Gregorio",
    "wof:placetype":"locality"
},
  "geometry": {"coordinates":[121.35498,18.29313],"type":"Point"}
}