{
  "type": "Feature",
  "properties": {
    "gn:admin1_code":"15",
    "gn:admin2_code":"01",
    "gn:admin3_code":"140103000.0",
    "gn:asciiname":"Nagtupacan",
    "gn:country_code":"PH",
    "gn:dem":80,
    "gn:feature_class":"P",
    "gn:feature_code":"PPL",
    "gn:name":"Nagtupacan",
    "gn:population":0,
    "gn:timezone":"Asia/Manila",
    "iso:country":"PH",
    "name:fil_x_preferred":[
        "Nagtupacan"
    ],
    "wof:name":"Nagtupacan",
    "wof:placetype":"locality"
},
  "geometry": {"coordinates":[120.7443,17.5742],"type":"Point"}
}