{
  "type": "Feature",
  "properties": {
    "gn:admin1_code":"02",
    "gn:admin2_code":"31",
    "gn:admin3_code":"23128000.0",
    "gn:asciiname":"San Francisco Norte",
    "gn:country_code":"PH",
    "gn:dem":123,
    "gn:feature_class":"P",
    "gn:feature_code":"PPL",
    "gn:name":"San Francisco Norte",
    "gn:population":0,
    "gn:timezone":"Asia/Manila",
    "iso:country":"PH",
    "name:fil_x_preferred":[
        "San Francisco Norte"
    ],
    "wof:name":"San Francisco Norte",
    "wof:placetype":"locality"
},
  "geometry": {"coordinates":[121.9042,16.736],"type":"Point"}
}