{
  "type": "Feature",
  "properties": {
    "gn:admin1_code":"13",
    "gn:admin2_code":"61",
    "gn:admin3_code":"166710000.0",
    "gn:asciiname":"Janaza",
    "gn:country_code":"PH",
    "gn:dem":13,
    "gn:feature_class":"P",
    "gn:feature_code":"PPL",
    "gn:name":"Janaza",
    "gn:population":0,
    "gn:timezone":"Asia/Manila",
    "iso:country":"PH",
    "name:fil_x_preferred":[
        "Janaza"
    ],
    "wof:name":"Janaza",
    "wof:placetype":"locality"
},
  "geometry": {"coordinates":[126.17749999999999,9.63417],"type":"Point"}
}