{
  "type": "Feature",
  "properties": {
    "gn:admin1_code":"05",
    "gn:admin2_code":"39",
    "gn:admin3_code":"54112000.0",
    "gn:asciiname":"Intukudan",
    "gn:country_code":"PH",
    "gn:dem":36,
    "gn:elevation":"0.0",
    "gn:feature_class":"P",
    "gn:feature_code":"PPL",
    "gn:name":"Intukudan",
    "gn:population":0,
    "gn:timezone":"Asia/Manila",
    "iso:country":"PH",
    "name:fil_x_preferred":[
        "Intukudan"
    ],
    "wof:name":"Intukudan",
    "wof:placetype":"locality"
},
  "geometry": {"coordinates":[123.50521000000001,12.25544],"type":"Point"}
}