{
  "type": "Feature",
  "properties": {
    "gn:admin1_code":"NCR",
    "gn:admin2_code":"137400000",
    "gn:admin3_code":"137405000.0",
    "gn:asciiname":"San Perfecto",
    "gn:country_code":"PH",
    "gn:dem":17,
    "gn:feature_class":"P",
    "gn:feature_code":"PPL",
    "gn:name":"San Perfecto",
    "gn:population":0,
    "gn:timezone":"Asia/Manila",
    "iso:country":"PH",
    "wof:name":"San Perfecto",
    "wof:placetype":"locality"
},
  "geometry": {"coordinates":[121.02549999999999,14.6053],"type":"Point"}
}