{
  "type": "Feature",
  "properties": {
    "gn:admin1_code":"40",
    "gn:admin2_code":"53",
    "gn:admin3_code":"45804000.0",
    "gn:asciiname":"Bombong",
    "gn:country_code":"PH",
    "gn:dem":40,
    "gn:feature_class":"P",
    "gn:feature_code":"PPL",
    "gn:name":"Bombong",
    "gn:population":0,
    "gn:timezone":"Asia/Manila",
    "iso:country":"PH",
    "name:fil_x_preferred":[
        "Bombong"
    ],
    "name:und_x_variant":[
        "Bongbong"
    ],
    "wof:name":"Bombong",
    "wof:placetype":"locality"
},
  "geometry": {"coordinates":[121.22329999999999,14.3904],"type":"Point"}
}