{
  "type": "Feature",
  "properties": {
    "gn:country":"PH",
    "gn:fcode":"PPL",
    "gn:population":2840,
    "iso:country":"PH",
    "name:fil_x_preferred":[
        "Sapol"
    ],
    "name:und_x_variant":[
        "Sapul"
    ],
    "qs:name":"Sapol",
    "qs:photos_9r":0,
    "qs:photos_sr":0,
    "qs:pop_sr":"4",
    "wof:name":"Sapol",
    "wof:placetype":"locality",
    "wof:population":2840
},
  "geometry": {"coordinates":[121.1893,13.365],"type":"Point"}
}