{
  "type": "Feature",
  "properties": {
    "gn:admin1_code":"02",
    "gn:admin2_code":"31",
    "gn:admin3_code":"23103000.0",
    "gn:asciiname":"Villa Fugu",
    "gn:country_code":"PH",
    "gn:dem":67,
    "gn:feature_class":"P",
    "gn:feature_code":"PPL",
    "gn:name":"Villa Fugu",
    "gn:population":0,
    "gn:timezone":"Asia/Manila",
    "iso:country":"PH",
    "name:fil_x_preferred":[
        "Villa Fugu"
    ],
    "wof:name":"Villa Fugu",
    "wof:placetype":"locality"
},
  "geometry": {"coordinates":[121.62764,16.95715],"type":"Point"}
}