{
  "type": "Feature",
  "properties": {
    "gn:admin1_code":"15",
    "gn:admin2_code":"44",
    "gn:admin3_code":"144403000.0",
    "gn:asciiname":"Laya",
    "gn:country_code":"PH",
    "gn:dem":972,
    "gn:feature_class":"P",
    "gn:feature_code":"PPL",
    "gn:name":"Laya",
    "gn:population":0,
    "gn:timezone":"Asia/Manila",
    "iso:country":"PH",
    "name:ceb_x_preferred":[
        "Laya"
    ],
    "name:deu_x_preferred":[
        "Laya"
    ],
    "name:fil_x_preferred":[
        "Laya"
    ],
    "name:pol_x_preferred":[
        "Laya"
    ],
    "name:que_x_preferred":[
        "Laya"
    ],
    "name:rus_x_preferred":[
        "\u041b\u0430\u0439\u044f"
    ],
    "name:swe_x_preferred":[
        "Laya"
    ],
    "wof:name":"Laya",
    "wof:placetype":"locality"
},
  "geometry": {"coordinates":[120.83320000000001,17.0856],"type":"Point"}
}