{
  "type": "Feature",
  "properties": {
    "gn:admin1_code":"03",
    "gn:admin2_code":"47",
    "gn:admin3_code":"34920000.0",
    "gn:asciiname":"Napon-Napon",
    "gn:cc2":"PH",
    "gn:country_code":"PH",
    "gn:dem":287,
    "gn:feature_class":"P",
    "gn:feature_code":"PPL",
    "gn:name":"Napon-Napon",
    "gn:population":0,
    "gn:timezone":"Asia/Manila",
    "iso:country":"PH",
    "name:fil_x_preferred":[
        "Napon-Napon"
    ],
    "name:und_x_variant":[
        "Naponapon"
    ],
    "wof:name":"Napon-Napon",
    "wof:placetype":"locality"
},
  "geometry": {"coordinates":[121.23583000000001,15.77583],"type":"Point"}
}