{
  "type": "Feature",
  "properties": {
    "gn:admin1_code":"09",
    "gn:admin2_code":"66",
    "gn:admin3_code":"97325000.0",
    "gn:asciiname":"Pantad",
    "gn:country_code":"PH",
    "gn:dem":175,
    "gn:feature_class":"P",
    "gn:feature_code":"PPL",
    "gn:name":"Pantad",
    "gn:population":0,
    "gn:timezone":"Asia/Manila",
    "iso:country":"PH",
    "wof:name":"Pantad",
    "wof:placetype":"locality"
},
  "geometry": {"coordinates":[123.44583,7.66389],"type":"Point"}
}