{
  "type": "Feature",
  "properties": {
    "gn:admin1_code":"40",
    "gn:admin2_code":"H2",
    "gn:admin3_code":"45610000.0",
    "gn:asciiname":"Ibabang Bacong",
    "gn:country_code":"PH",
    "gn:dem":36,
    "gn:feature_class":"P",
    "gn:feature_code":"PPL",
    "gn:name":"Ibabang Bacong",
    "gn:population":0,
    "gn:timezone":"Asia/Manila",
    "iso:country":"PH",
    "name:fil_x_preferred":[
        "Ibabang Bacong"
    ],
    "wof:name":"Ibabang Bacong",
    "wof:placetype":"locality"
},
  "geometry": {"coordinates":[122.2281,13.6236],"type":"Point"}
}