{
  "type": "Feature",
  "properties": {
    "gn:country":"PH",
    "gn:fcode":"PPL",
    "gn:pop":2292,
    "iso:country":"PH",
    "name:fil_x_preferred":[
        "Binulasan"
    ],
    "name:unk_x_variant":[
        "Binolasan"
    ],
    "qs:name":"Binulasan",
    "qs:photos_9r":0,
    "qs:photos_sr":0,
    "qs:pop_sr":"4",
    "wof:name":"Binulasan",
    "wof:placetype":"locality",
    "wof:population":2292
},
  "geometry": {"coordinates":[121.69781,14.73159],"type":"Point"}
}