{
  "type": "Feature",
  "properties": {
    "gn:admin1_code":"10",
    "gn:admin2_code":"12",
    "gn:admin3_code":"101318000.0",
    "gn:asciiname":"Locawon",
    "gn:country_code":"PH",
    "gn:dem":438,
    "gn:feature_class":"P",
    "gn:feature_code":"PPL",
    "gn:name":"Locawon",
    "gn:population":0,
    "gn:timezone":"Asia/Manila",
    "iso:country":"PH",
    "name:fil_x_preferred":[
        "Locawon"
    ],
    "wof:name":"Locawon",
    "wof:placetype":"locality"
},
  "geometry": {"coordinates":[125.37633,7.70968],"type":"Point"}
}