{
  "type": "Feature",
  "properties": {
    "gn:admin1_code":"06",
    "gn:admin2_code":"30",
    "gn:admin3_code":"63030000.0",
    "gn:asciiname":"Bugtong",
    "gn:country_code":"PH",
    "gn:dem":12,
    "gn:feature_class":"P",
    "gn:feature_code":"PPL",
    "gn:name":"Bugtong",
    "gn:population":0,
    "gn:timezone":"Asia/Manila",
    "iso:country":"PH",
    "name:fil_x_preferred":[
        "Bugtong"
    ],
    "name:und_x_variant":[
        "Bugtong Naulid"
    ],
    "wof:name":"Bugtong",
    "wof:placetype":"locality"
},
  "geometry": {"coordinates":[122.2611,10.6625],"type":"Point"}
}