{
  "type": "Feature",
  "properties": {
    "gn:admin1_code":"08",
    "gn:admin2_code":"67",
    "gn:admin3_code":"84808000.0",
    "gn:asciiname":"Caprasanon",
    "gn:country_code":"PH",
    "gn:dem":10,
    "gn:feature_class":"P",
    "gn:feature_code":"PPL",
    "gn:name":"Caprasanon",
    "gn:population":0,
    "gn:timezone":"Asia/Manila",
    "iso:country":"PH",
    "name:fil_x_preferred":[
        "Caprasanon"
    ],
    "wof:name":"Caprasanon",
    "wof:placetype":"locality"
},
  "geometry": {"coordinates":[125.04682,12.67986],"type":"Point"}
}