{
  "type": "Feature",
  "properties": {
    "gn:admin1_code":"10",
    "gn:admin2_code":"12",
    "gn:admin3_code":"101318000.0",
    "gn:asciiname":"Dao",
    "gn:country_code":"PH",
    "gn:dem":567,
    "gn:feature_class":"P",
    "gn:feature_code":"PPL",
    "gn:name":"Dao",
    "gn:population":0,
    "gn:timezone":"Asia/Manila",
    "iso:country":"PH",
    "name:fil_x_preferred":[
        "Dao"
    ],
    "wof:name":"Dao",
    "wof:placetype":"locality"
},
  "geometry": {"coordinates":[125.34425,7.77503],"type":"Point"}
}