{
  "type": "Feature",
  "properties": {
    "gn:country":"PH",
    "gn:fcode":"ADM3",
    "gn:population":45172,
    "iso:country":"PH",
    "name:bre_x_preferred":[
        "Gloria"
    ],
    "name:ceb_x_preferred":[
        "Gloria"
    ],
    "name:ces_x_preferred":[
        "Gloria"
    ],
    "name:dan_x_preferred":[
        "Gloria"
    ],
    "name:deu_x_preferred":[
        "Gloria"
    ],
    "name:est_x_preferred":[
        "Gloria"
    ],
    "name:fas_x_preferred":[
        "\u06af\u0644\u0648\u0631\u06cc\u0627"
    ],
    "name:fil_x_preferred":[
        "Gloria"
    ],
    "name:fin_x_preferred":[
        "Gloria"
    ],
    "name:fra_x_preferred":[
        "Gloria"
    ],
    "name:glg_x_preferred":[
        "Gloria"
    ],
    "name:heb_x_preferred":[
        "\u05d2\u05dc\u05d5\u05e8\u05d9\u05d4"
    ],
    "name:ita_x_preferred":[
        "Gloria"
    ],
    "name:jpn_x_preferred":[
        "\u30b0\u30ed\u30ea\u30a2"
    ],
    "name:kor_x_preferred":[
        "\uae00\ub85c\ub9ac\uc544"
    ],
    "name:lat_x_preferred":[
        "Gloria"
    ],
    "name:nld_x_preferred":[
        "Gloria"
    ],
    "name:pol_x_preferred":[
        "Gloria"
    ],
    "name:rus_x_preferred":[
        "\u0413\u043b\u043e\u0440\u0438\u044f"
    ],
    "name:spa_x_preferred":[
        "Gloria"
    ],
    "name:swe_x_preferred":[
        "Gloria"
    ],
    "name:tur_x_preferred":[
        "Gloria"
    ],
    "name:ukr_x_preferred":[
        "\u0413\u043b\u043e\u0440\u0456\u044f"
    ],
    "name:war_x_preferred":[
        "Gloria"
    ],
    "qs:name":"Gloria",
    "qs:photos_9r":0,
    "qs:photos_sr":0,
    "qs:pop_sr":"7",
    "wd:wordcount":704,
    "wof:name":"Gloria",
    "wof:placetype":"localadmin",
    "wof:population":45172
},
  "geometry": {"coordinates":[121.36667,12.91667],"type":"Point"}
}