{
  "type": "Feature",
  "properties": {
    "gn:country":"PH",
    "gn:fcode":"ADM3",
    "gn:pop":45172,
    "iso:country":"PH",
    "name:fil_x_preferred":[
        "Gloria"
    ],
    "qs:name":"Gloria",
    "qs:photos_9r":0,
    "qs:photos_sr":0,
    "qs:pop_sr":"7",
    "wd:wordcount":704,
    "wof:name":"Gloria",
    "wof:placetype":"localadmin",
    "wof:population":45172
},
  "geometry": {"coordinates":[121.36667,12.91667],"type":"Point"}
}