{
  "type": "Feature",
  "properties": {
    "gn:admin1_code":"15",
    "gn:admin2_code":"01",
    "gn:admin3_code":"140122000.0",
    "gn:asciiname":"Guimba",
    "gn:country_code":"PH",
    "gn:dem":73,
    "gn:feature_class":"P",
    "gn:feature_code":"PPL",
    "gn:name":"Guimba",
    "gn:population":0,
    "gn:timezone":"Asia/Manila",
    "iso:country":"PH",
    "name:fil_x_preferred":[
        "Guimba"
    ],
    "wof:name":"Guimba",
    "wof:placetype":"locality"
},
  "geometry": {"coordinates":[120.73220000000001,17.6796],"type":"Point"}
}