{
  "type": "Feature",
  "properties": {
    "gn:admin1_code":"15",
    "gn:admin2_code":"10",
    "gn:admin3_code":"141106000.0",
    "gn:asciiname":"Birac",
    "gn:country_code":"PH",
    "gn:dem":799,
    "gn:feature_class":"P",
    "gn:feature_code":"PPL",
    "gn:name":"Birac",
    "gn:population":0,
    "gn:timezone":"Asia/Manila",
    "iso:country":"PH",
    "name:ceb_x_preferred":[
        "Birac"
    ],
    "name:deu_x_preferred":[
        "Birac"
    ],
    "name:fra_x_preferred":[
        "Birac"
    ],
    "name:ita_x_preferred":[
        "Birac"
    ],
    "name:nds_x_preferred":[
        "Birac"
    ],
    "name:nld_x_preferred":[
        "Birac"
    ],
    "name:pol_x_preferred":[
        "Birac"
    ],
    "name:por_x_preferred":[
        "Birac"
    ],
    "name:rus_x_preferred":[
        "\u0411\u0438\u0440\u0430\u043a"
    ],
    "name:scn_x_preferred":[
        "Birac"
    ],
    "name:slk_x_preferred":[
        "Birac"
    ],
    "name:spa_x_preferred":[
        "Birac"
    ],
    "name:swe_x_preferred":[
        "Birac"
    ],
    "name:ukr_x_preferred":[
        "\u0411\u0456\u0440\u0430\u043a"
    ],
    "name:und_x_variant":[
        "Virac",
        "Vinac",
        "Birac"
    ],
    "wof:name":"Birac",
    "wof:placetype":"locality"
},
  "geometry": {"coordinates":[120.65906,16.35939],"type":"Point"}
}