{
  "type": "Feature",
  "properties": {
    "gn:admin1_code":"15",
    "gn:admin2_code":"10",
    "gn:admin3_code":"141106000.0",
    "gn:asciiname":"Birac",
    "gn:country_code":"PH",
    "gn:dem":799,
    "gn:feature_class":"P",
    "gn:feature_code":"PPL",
    "gn:name":"Birac",
    "gn:population":0,
    "gn:timezone":"Asia/Manila",
    "iso:country":"PH",
    "name:und_x_variant":[
        "Virac",
        "Vinac",
        "Birac"
    ],
    "wof:name":"Birac",
    "wof:placetype":"locality"
},
  "geometry": {"coordinates":[120.65906,16.35939],"type":"Point"}
}