{
  "type": "Feature",
  "properties": {
    "gn:admin1_code":"07",
    "gn:admin2_code":"11",
    "gn:admin3_code":"71226000.0",
    "gn:asciiname":"Mahanay",
    "gn:country_code":"PH",
    "gn:dem":9,
    "gn:feature_class":"P",
    "gn:feature_code":"PPL",
    "gn:name":"Mahanay",
    "gn:population":0,
    "gn:timezone":"Asia/Manila",
    "iso:country":"PH",
    "name:fil_x_preferred":[
        "Mahanay"
    ],
    "name:und_x_variant":[
        "Mahanay Island"
    ],
    "wof:name":"Mahanay",
    "wof:placetype":"locality"
},
  "geometry": {"coordinates":[124.23050000000001,10.1848],"type":"Point"}
}