{
  "type": "Feature",
  "properties": {
    "gn:admin1_code":"03",
    "gn:admin2_code":"G8",
    "gn:admin3_code":"37702000.0",
    "gn:asciiname":"Dibo Kong",
    "gn:country_code":"PH",
    "gn:dem":8,
    "gn:feature_class":"P",
    "gn:feature_code":"PPL",
    "gn:name":"Dibo Kong",
    "gn:population":0,
    "gn:timezone":"Asia/Manila",
    "iso:country":"PH",
    "name:fil_x_preferred":[
        "Dibo Kong"
    ],
    "wof:name":"Dibo Kong",
    "wof:placetype":"locality"
},
  "geometry": {"coordinates":[122.07389999999999,16.2424],"type":"Point"}
}