{
  "type": "Feature",
  "properties": {
    "gn:admin1_code":"01",
    "gn:admin2_code":"51",
    "gn:admin3_code":"15516000.0",
    "gn:asciiname":"Elevelen",
    "gn:country_code":"PH",
    "gn:dem":14,
    "gn:feature_class":"P",
    "gn:feature_code":"PPL",
    "gn:name":"Elevelen",
    "gn:population":0,
    "gn:timezone":"Asia/Manila",
    "iso:country":"PH",
    "name:fil_x_preferred":[
        "Elevelen"
    ],
    "wof:name":"Elevelen",
    "wof:placetype":"locality"
},
  "geometry": {"coordinates":[119.76361,15.98694],"type":"Point"}
}