{
  "type": "Feature",
  "properties": {
    "gn:admin1_code":"10",
    "gn:admin2_code":"12",
    "gn:admin3_code":"101311000.0",
    "gn:asciiname":"Tigbao",
    "gn:country_code":"PH",
    "gn:dem":703,
    "gn:feature_class":"P",
    "gn:feature_code":"PPL",
    "gn:name":"Tigbao",
    "gn:population":0,
    "gn:timezone":"Asia/Manila",
    "iso:country":"PH",
    "name:ceb_x_preferred":[
        "Tigbao"
    ],
    "name:fil_x_preferred":[
        "Tigbao"
    ],
    "wof:name":"Tigbao",
    "wof:placetype":"locality"
},
  "geometry": {"coordinates":[124.81305999999999,8.29222],"type":"Point"}
}