{
  "type": "Feature",
  "properties": {
    "gn:admin1_code":"03",
    "gn:admin2_code":"13",
    "gn:admin3_code":"31422000.0",
    "gn:asciiname":"Capihan",
    "gn:country_code":"PH",
    "gn:dem":22,
    "gn:feature_class":"P",
    "gn:feature_code":"PPL",
    "gn:name":"Capihan",
    "gn:population":0,
    "gn:timezone":"Asia/Manila",
    "iso:country":"PH",
    "name:fil_x_preferred":[
        "Capihan"
    ],
    "name:fil_x_variant":[
        "Cafihan"
    ],
    "wof:name":"Capihan",
    "wof:placetype":"locality"
},
  "geometry": {"coordinates":[120.935,15.00107],"type":"Point"}
}