{
  "type": "Feature",
  "properties": {
    "gn:admin1_code":"15",
    "gn:admin2_code":"44",
    "gn:admin3_code":"144404000.0",
    "gn:asciiname":"Ambayoan",
    "gn:country_code":"PH",
    "gn:dem":1335,
    "gn:feature_class":"P",
    "gn:feature_code":"PPL",
    "gn:name":"Ambayoan",
    "gn:population":0,
    "gn:timezone":"Asia/Manila",
    "iso:country":"PH",
    "name:fil_x_preferred":[
        "Ambayoan"
    ],
    "wof:name":"Ambayoan",
    "wof:placetype":"locality"
},
  "geometry": {"coordinates":[121.01803999999998,17.00245],"type":"Point"}
}