{
  "type": "Feature",
  "properties": {
    "gn:admin1_code":"08",
    "gn:admin2_code":"67",
    "gn:admin3_code":"84808000.0",
    "gn:asciiname":"Bongteo",
    "gn:country_code":"PH",
    "gn:dem":2,
    "gn:feature_class":"P",
    "gn:feature_code":"PPL",
    "gn:name":"Bongteo",
    "gn:population":0,
    "gn:timezone":"Asia/Manila",
    "iso:country":"PH",
    "name:fil_x_preferred":[
        "Bongteo"
    ],
    "name:und_x_variant":[
        "Bonglio",
        "Bonglieu",
        "Bongleu"
    ],
    "wof:name":"Bongteo",
    "wof:placetype":"locality"
},
  "geometry": {"coordinates":[125.024,12.5132],"type":"Point"}
}