{
  "type": "Feature",
  "properties": {
    "gn:admin1_code":"06",
    "gn:admin2_code":"04",
    "gn:admin3_code":"60409000.0",
    "gn:asciiname":"Casit-an",
    "gn:country_code":"PH",
    "gn:dem":140,
    "gn:feature_class":"P",
    "gn:feature_code":"PPL",
    "gn:name":"Casit-an",
    "gn:population":0,
    "gn:timezone":"Asia/Manila",
    "iso:country":"PH",
    "name:fil_x_preferred":[
        "Casit-an"
    ],
    "wof:name":"Casit-an",
    "wof:placetype":"locality"
},
  "geometry": {"coordinates":[122.31071,11.4557],"type":"Point"}
}