{
  "type": "Feature",
  "properties": {
    "gn:country":"PH",
    "gn:fcode":"PPL",
    "gn:population":2410,
    "iso:country":"PH",
    "name:fil_x_preferred":[
        "Batiano"
    ],
    "qs:name":"Batiano",
    "qs:photos_9r":0,
    "qs:photos_sr":0,
    "qs:pop_sr":"4",
    "wof:name":"Batiano",
    "wof:placetype":"locality",
    "wof:population":2410
},
  "geometry": {"coordinates":[126.4907,7.5534],"type":"Point"}
}