{
  "type": "Feature",
  "properties": {
    "gn:admin1_code":"08",
    "gn:admin2_code":"59",
    "gn:admin3_code":"86405000.0",
    "gn:asciiname":"Punta",
    "gn:country_code":"PH",
    "gn:dem":20,
    "gn:feature_class":"P",
    "gn:feature_code":"PPL",
    "gn:name":"Punta",
    "gn:population":0,
    "gn:timezone":"Asia/Manila",
    "iso:country":"PH",
    "name:deu_x_preferred":[
        "Punta"
    ],
    "name:fil_x_preferred":[
        "Punta"
    ],
    "name:fin_x_preferred":[
        "Punta"
    ],
    "name:jpn_x_preferred":[
        "\u30d7\u30f3\u30bf"
    ],
    "name:spa_x_preferred":[
        "Punta"
    ],
    "name:swe_x_preferred":[
        "Punta"
    ],
    "wof:name":"Punta",
    "wof:placetype":"locality"
},
  "geometry": {"coordinates":[125.06667,10.26667],"type":"Point"}
}