{
  "type": "Feature",
  "properties": {
    "gn:admin1_code":"06",
    "gn:admin2_code":"H3",
    "gn:admin3_code":"64513000.0",
    "gn:asciiname":"Galicia",
    "gn:country_code":"PH",
    "gn:dem":12,
    "gn:feature_class":"P",
    "gn:feature_code":"PPL",
    "gn:name":"Galicia",
    "gn:population":0,
    "gn:timezone":"Asia/Manila",
    "iso:country":"PH",
    "name:fil_x_preferred":[
        "Galicia"
    ],
    "wof:name":"Galicia",
    "wof:placetype":"locality"
},
  "geometry": {"coordinates":[122.7199,9.9827],"type":"Point"}
}