{
  "type": "Feature",
  "properties": {
    "gn:admin1_code":"10",
    "gn:admin2_code":"42",
    "gn:admin3_code":"104212000.0",
    "gn:asciiname":"Cartagena",
    "gn:country_code":"PH",
    "gn:dem":28,
    "gn:feature_class":"P",
    "gn:feature_code":"PPL",
    "gn:name":"Cartagena",
    "gn:population":0,
    "gn:timezone":"Asia/Manila",
    "iso:country":"PH",
    "name:eng_x_preferred":[
        "Cartagena"
    ],
    "wof:name":"Cartagena",
    "wof:placetype":"locality"
},
  "geometry": {"coordinates":[123.7319,8.5832],"type":"Point"}
}