{
  "type": "Feature",
  "properties": {
    "gn:admin1_code":"03",
    "gn:admin2_code":"47",
    "gn:admin3_code":"34926000.0",
    "gn:asciiname":"Asta",
    "gn:country_code":"PH",
    "gn:dem":85,
    "gn:feature_class":"P",
    "gn:feature_code":"PPL",
    "gn:name":"Asta",
    "gn:population":0,
    "gn:timezone":"Asia/Manila",
    "iso:country":"PH",
    "name:deu_x_preferred":[
        "Asta"
    ],
    "name:fil_x_preferred":[
        "Asta"
    ],
    "name:ita_x_preferred":[
        "Asta"
    ],
    "name:jpn_x_preferred":[
        "\u30a2\u30b9\u30bf"
    ],
    "name:lat_x_preferred":[
        "Asta"
    ],
    "name:nld_x_preferred":[
        "Asta"
    ],
    "name:pol_x_preferred":[
        "Asta"
    ],
    "name:por_x_preferred":[
        "Asta"
    ],
    "name:spa_x_preferred":[
        "Asta"
    ],
    "wof:name":"Asta",
    "wof:placetype":"locality"
},
  "geometry": {"coordinates":[120.95,15.75],"type":"Point"}
}