{
  "type": "Feature",
  "properties": {
    "gn:admin1_code":"03",
    "gn:admin2_code":"07",
    "gn:admin3_code":"30811000.0",
    "gn:asciiname":"Landing",
    "gn:country_code":"PH",
    "gn:dem":3,
    "gn:feature_class":"P",
    "gn:feature_code":"PPL",
    "gn:name":"Landing",
    "gn:population":0,
    "gn:timezone":"Asia/Manila",
    "iso:country":"PH",
    "name:ara_x_preferred":[
        "\u0647\u0628\u0648\u0637"
    ],
    "name:ast_x_preferred":[
        "Aterrizaxe"
    ],
    "name:bel_x_preferred":[
        "\u041f\u0430\u0441\u0430\u0434\u043a\u0430"
    ],
    "name:cat_x_preferred":[
        "Aterratge"
    ],
    "name:deu_x_preferred":[
        "Landung"
    ],
    "name:epo_x_preferred":[
        "Surteri\u011do"
    ],
    "name:fas_x_preferred":[
        "\u0641\u0631\u0648\u062f"
    ],
    "name:fil_x_preferred":[
        "Landing"
    ],
    "name:fra_x_preferred":[
        "Atterrissage"
    ],
    "name:glg_x_preferred":[
        "Aterraxe"
    ],
    "name:heb_x_preferred":[
        "\u05e0\u05d7\u05d9\u05ea\u05d4"
    ],
    "name:ind_x_preferred":[
        "Mendarat"
    ],
    "name:ita_x_preferred":[
        "Atterraggio"
    ],
    "name:kan_x_preferred":[
        "\u0cad\u0cc2\u0cb8\u0ccd\u0caa\u0cb0\u0ccd\u0cb6"
    ],
    "name:lav_x_preferred":[
        "Nos\u0113\u0161an\u0101s"
    ],
    "name:msa_x_preferred":[
        "Pendaratan"
    ],
    "name:nld_x_preferred":[
        "Landing"
    ],
    "name:pol_x_preferred":[
        "L\u0105dowanie"
    ],
    "name:por_x_preferred":[
        "Aterragem"
    ],
    "name:ron_x_preferred":[
        "Aterizare"
    ],
    "name:rus_x_preferred":[
        "\u041f\u043e\u0441\u0430\u0434\u043a\u0430"
    ],
    "name:spa_x_preferred":[
        "Aterrizaje"
    ],
    "name:swe_x_preferred":[
        "Landning"
    ],
    "name:tat_x_preferred":[
        "\u041e\u0447\u044b\u043f \u0442\u04e9\u0448\u04af"
    ],
    "name:tur_x_preferred":[
        "\u0130ni\u015f"
    ],
    "name:urd_x_preferred":[
        "\u0627\u062a\u0627\u0631"
    ],
    "name:vie_x_preferred":[
        "H\u1ea1 c\u00e1nh"
    ],
    "wof:name":"Landing",
    "wof:placetype":"locality"
},
  "geometry": {"coordinates":[120.56667,14.66667],"type":"Point"}
}