{
  "type": "Feature",
  "properties": {
    "gn:country":"PH",
    "gn:fcode":"PPL",
    "gn:pop":2406,
    "iso:country":"PH",
    "name:fil_x_preferred":[
        "Alayao"
    ],
    "qs:name":"Alayao",
    "qs:photos_9r":0,
    "qs:photos_sr":0,
    "qs:pop_sr":"4",
    "wof:name":"Alayao",
    "wof:placetype":"locality",
    "wof:population":2406
},
  "geometry": {"coordinates":[122.55240000000001,14.2818],"type":"Point"}
}