{
  "type": "Feature",
  "properties": {
    "gn:admin1_code":"07",
    "gn:admin2_code":"11",
    "gn:admin3_code":"71207000.0",
    "gn:asciiname":"Kabinday",
    "gn:country_code":"PH",
    "gn:dem":239,
    "gn:feature_class":"P",
    "gn:feature_code":"PPL",
    "gn:name":"Kabinday",
    "gn:population":0,
    "gn:timezone":"Asia/Manila",
    "iso:country":"PH",
    "name:fil_x_preferred":[
        "Kabinday"
    ],
    "wof:name":"Kabinday",
    "wof:placetype":"locality"
},
  "geometry": {"coordinates":[124.09999999999999,9.81667],"type":"Point"}
}