{
  "type": "Feature",
  "properties": {
    "gn:admin1_code":"10",
    "gn:admin2_code":"43",
    "gn:admin3_code":"104323000.0",
    "gn:asciiname":"Kiogak",
    "gn:cc2":"PH",
    "gn:country_code":"PH",
    "gn:dem":60,
    "gn:feature_class":"P",
    "gn:feature_code":"PPL",
    "gn:name":"Kiogak",
    "gn:population":0,
    "gn:timezone":"Asia/Manila",
    "iso:country":"PH",
    "name:und_x_variant":[
        "Kiugak",
        "Kiogak"
    ],
    "wof:name":"Kiogak",
    "wof:placetype":"locality"
},
  "geometry": {"coordinates":[124.7775,8.94611],"type":"Point"}
}