{
  "type": "Feature",
  "properties": {
    "gn:admin1_code":"05",
    "gn:admin2_code":"05",
    "gn:admin3_code":"50515000.0",
    "gn:asciiname":"Agojo",
    "gn:country_code":"PH",
    "gn:dem":17,
    "gn:feature_class":"P",
    "gn:feature_code":"PPL",
    "gn:name":"Agojo",
    "gn:population":0,
    "gn:timezone":"Asia/Manila",
    "iso:country":"PH",
    "name:fil_x_preferred":[
        "Agojo"
    ],
    "wof:name":"Agojo",
    "wof:placetype":"locality"
},
  "geometry": {"coordinates":[124.1712,13.2227],"type":"Point"}
}