{
  "type": "Feature",
  "properties": {
    "gn:admin1_code":"08",
    "gn:admin2_code":"37",
    "gn:admin3_code":"83723000.0",
    "gn:asciiname":"Gapas",
    "gn:country_code":"PH",
    "gn:dem":68,
    "gn:feature_class":"P",
    "gn:feature_code":"PPL",
    "gn:name":"Gapas",
    "gn:population":0,
    "gn:timezone":"Asia/Manila",
    "iso:country":"PH",
    "name:fil_x_preferred":[
        "Gapas"
    ],
    "wof:name":"Gapas",
    "wof:placetype":"locality"
},
  "geometry": {"coordinates":[124.83056000000001,11.17167],"type":"Point"}
}