{
  "type": "Feature",
  "properties": {
    "gn:admin1_code":"03",
    "gn:admin2_code":"50",
    "gn:admin3_code":"35414000.0",
    "gn:asciiname":"San Francisco Second",
    "gn:country_code":"PH",
    "gn:dem":6,
    "gn:feature_class":"P",
    "gn:feature_code":"PPL",
    "gn:name":"San Francisco Second",
    "gn:population":0,
    "gn:timezone":"Asia/Manila",
    "iso:country":"PH",
    "name:eng_x_preferred":[
        "San Francisco Second"
    ],
    "name:fil_x_preferred":[
        "San Francisco"
    ],
    "name:und_x_variant":[
        "San Francisco",
        "San Francisco Two"
    ],
    "wof:name":"San Francisco Second",
    "wof:placetype":"locality"
},
  "geometry": {"coordinates":[120.67572,14.96228],"type":"Point"}
}