{
  "type": "Feature",
  "properties": {
    "gn:admin1_code":"06",
    "gn:admin2_code":"30",
    "gn:admin3_code":"63044000.0",
    "gn:asciiname":"Samponongbolo",
    "gn:country_code":"PH",
    "gn:dem":73,
    "gn:feature_class":"P",
    "gn:feature_code":"PPL",
    "gn:name":"Samponongbolo",
    "gn:population":0,
    "gn:timezone":"Asia/Manila",
    "iso:country":"PH",
    "name:fil_x_preferred":[
        "Samponongbolo"
    ],
    "wof:name":"Samponongbolo",
    "wof:placetype":"locality"
},
  "geometry": {"coordinates":[123.0232,11.2861],"type":"Point"}
}