{
  "type": "Feature",
  "properties": {
    "gn:admin1_code":"08",
    "gn:admin2_code":"55",
    "gn:admin3_code":"86004000.0",
    "gn:asciiname":"Tinaga",
    "gn:country_code":"PH",
    "gn:dem":51,
    "gn:feature_class":"P",
    "gn:feature_code":"PPL",
    "gn:name":"Tinaga",
    "gn:population":0,
    "gn:timezone":"Asia/Manila",
    "iso:country":"PH",
    "name:ceb_x_preferred":[
        "Tinaga Island"
    ],
    "name:fil_x_preferred":[
        "Tinaga"
    ],
    "name:ilo_x_preferred":[
        "Tinaga"
    ],
    "name:und_x_variant":[
        "Tinago"
    ],
    "wof:name":"Tinaga",
    "wof:placetype":"locality"
},
  "geometry": {"coordinates":[125.0005,11.6216],"type":"Point"}
}