{
  "type": "Feature",
  "properties": {
    "gn:admin1_code":"03",
    "gn:admin2_code":"47",
    "gn:admin3_code":"34917000.0",
    "gn:asciiname":"Sapang Cawayan Segundo",
    "gn:country_code":"PH",
    "gn:dem":80,
    "gn:feature_class":"P",
    "gn:feature_code":"PPL",
    "gn:name":"Sapang Cawayan Segundo",
    "gn:population":0,
    "gn:timezone":"Asia/Manila",
    "iso:country":"PH",
    "name:fil_x_preferred":[
        "Sapang Cawayan Segundo"
    ],
    "name:fil_x_variant":[
        "Sapangkawayan Segundo"
    ],
    "name:und_x_variant":[
        "Sapangkawayan Segundo",
        "Sapang Cawayan Segundo"
    ],
    "wof:name":"Sapang Cawayan Segundo",
    "wof:placetype":"locality"
},
  "geometry": {"coordinates":[120.95,15.73333],"type":"Point"}
}