{
  "type": "Feature",
  "properties": {
    "gn:admin1_code":"13",
    "gn:admin2_code":"62",
    "gn:admin3_code":"166807000.0",
    "gn:asciiname":"Taganito",
    "gn:country_code":"PH",
    "gn:dem":184,
    "gn:feature_class":"P",
    "gn:feature_code":"PPL",
    "gn:name":"Taganito",
    "gn:population":0,
    "gn:timezone":"Asia/Manila",
    "iso:country":"PH",
    "name:fil_x_preferred":[
        "Taganito"
    ],
    "wof:name":"Taganito",
    "wof:placetype":"locality"
},
  "geometry": {"coordinates":[125.89082999999999,9.3275],"type":"Point"}
}