{
  "type": "Feature",
  "properties": {
    "gn:admin1_code":"10",
    "gn:admin2_code":"34",
    "gn:admin3_code":"103521000.0",
    "gn:asciiname":"Banasilon",
    "gn:country_code":"PH",
    "gn:dem":561,
    "gn:feature_class":"P",
    "gn:feature_code":"PPL",
    "gn:name":"Banasilon",
    "gn:population":0,
    "gn:timezone":"Asia/Manila",
    "iso:country":"PH",
    "name:und_x_variant":[
        "Banisilan",
        "Banasilon"
    ],
    "wof:name":"Banasilon",
    "wof:placetype":"locality"
},
  "geometry": {"coordinates":[123.96666999999999,8.05],"type":"Point"}
}