{
  "type": "Feature",
  "properties": {
    "gn:admin1_code":"14",
    "gn:admin2_code":"56",
    "gn:admin3_code":"153812000.0",
    "gn:asciiname":"Limbo",
    "gn:country_code":"PH",
    "gn:dem":15,
    "gn:feature_class":"P",
    "gn:feature_code":"PPL",
    "gn:name":"Limbo",
    "gn:population":0,
    "gn:timezone":"Asia/Manila",
    "iso:country":"PH",
    "name:afr_x_preferred":[
        "Limbo"
    ],
    "name:bul_x_preferred":[
        "\u041b\u0438\u043c\u0431\u043e"
    ],
    "name:cat_x_preferred":[
        "Llimbs"
    ],
    "name:ces_x_preferred":[
        "Limbus"
    ],
    "name:dan_x_preferred":[
        "Limbo"
    ],
    "name:deu_x_preferred":[
        "Limbus"
    ],
    "name:epo_x_preferred":[
        "Limbo"
    ],
    "name:eus_x_preferred":[
        "Linbo"
    ],
    "name:fas_x_preferred":[
        "\u0644\u06cc\u0645\u0628\u0648"
    ],
    "name:fil_x_preferred":[
        "Limbo"
    ],
    "name:fin_x_preferred":[
        "Limbus"
    ],
    "name:fra_x_preferred":[
        "Limbes"
    ],
    "name:heb_x_preferred":[
        "\u05dc\u05d9\u05de\u05d1\u05d5"
    ],
    "name:hun_x_preferred":[
        "Limbus"
    ],
    "name:hye_x_preferred":[
        "\u053c\u056b\u0574\u0562\u0578\u057d"
    ],
    "name:ina_x_preferred":[
        "Limbo"
    ],
    "name:ind_x_preferred":[
        "Limbo"
    ],
    "name:ita_x_preferred":[
        "Limbo"
    ],
    "name:kor_x_preferred":[
        "\uace0\uc131\uc18c"
    ],
    "name:lit_x_preferred":[
        "Pragarai"
    ],
    "name:nld_x_preferred":[
        "Voorgeborchte"
    ],
    "name:nno_x_preferred":[
        "Limbus"
    ],
    "name:nor_x_preferred":[
        "Limbo"
    ],
    "name:pol_x_preferred":[
        "Otch\u0142a\u0144"
    ],
    "name:por_x_preferred":[
        "Limbo"
    ],
    "name:rus_x_preferred":[
        "\u041b\u0438\u043c\u0431"
    ],
    "name:slk_x_preferred":[
        "Limbus"
    ],
    "name:slv_x_preferred":[
        "Predpekel"
    ],
    "name:spa_x_preferred":[
        "Limbo"
    ],
    "name:srp_x_preferred":[
        "\u041b\u0438\u043c\u0431\u043e"
    ],
    "name:swe_x_preferred":[
        "Limbo"
    ],
    "name:tgk_x_preferred":[
        "Limbo"
    ],
    "name:tha_x_preferred":[
        "\u0e25\u0e34\u0e21\u0e42\u0e1a"
    ],
    "name:tur_x_preferred":[
        "Limbo"
    ],
    "name:ukr_x_preferred":[
        "\u041b\u0456\u043c\u0431"
    ],
    "name:vie_x_preferred":[
        "L\u00e2m b\u00f4"
    ],
    "name:vls_x_preferred":[
        "V\u00f4orgeborchte"
    ],
    "name:zho_x_preferred":[
        "\u9748\u8584\u7344"
    ],
    "wof:name":"Limbo",
    "wof:placetype":"locality"
},
  "geometry": {"coordinates":[124.26582999999999,7.25083],"type":"Point"}
}