{
  "type": "Feature",
  "properties": {
    "gn:admin1_code":"14",
    "gn:admin2_code":"56",
    "gn:admin3_code":"153812000.0",
    "gn:asciiname":"Limbo",
    "gn:country_code":"PH",
    "gn:dem":15,
    "gn:feature_class":"P",
    "gn:feature_code":"PPL",
    "gn:name":"Limbo",
    "gn:population":0,
    "gn:timezone":"Asia/Manila",
    "iso:country":"PH",
    "name:fil_x_preferred":[
        "Limbo"
    ],
    "wof:name":"Limbo",
    "wof:placetype":"locality"
},
  "geometry": {"coordinates":[124.26582999999999,7.25083],"type":"Point"}
}