{
  "type": "Feature",
  "properties": {
    "gn:admin1_code":"40",
    "gn:admin2_code":"H2",
    "gn:admin3_code":"45618000.0",
    "gn:asciiname":"Aloneros",
    "gn:country_code":"PH",
    "gn:dem":11,
    "gn:feature_class":"P",
    "gn:feature_code":"PPL",
    "gn:name":"Aloneros",
    "gn:population":0,
    "gn:timezone":"Asia/Manila",
    "iso:country":"PH",
    "name:fil_x_preferred":[
        "Aloneros"
    ],
    "name:und_x_variant":[
        "Alunero"
    ],
    "wof:name":"Aloneros",
    "wof:placetype":"locality"
},
  "geometry": {"coordinates":[122.3698,13.9918],"type":"Point"}
}