{
  "type": "Feature",
  "properties": {
    "gn:admin1_code":"07",
    "gn:admin2_code":"11",
    "gn:admin3_code":"71211000.0",
    "gn:asciiname":"Tagapali",
    "gn:country_code":"PH",
    "gn:dem":169,
    "gn:feature_class":"P",
    "gn:feature_code":"PPL",
    "gn:name":"Tagapali",
    "gn:population":0,
    "gn:timezone":"Asia/Manila",
    "iso:country":"PH",
    "name:fil_x_preferred":[
        "Tagapali"
    ],
    "wof:name":"Tagapali",
    "wof:placetype":"locality"
},
  "geometry": {"coordinates":[124.4315,9.8547],"type":"Point"}
}