{
  "type": "Feature",
  "properties": {
    "gn:admin1_code":"06",
    "gn:admin2_code":"30",
    "gn:admin3_code":"63018000.0",
    "gn:asciiname":"Tubungan",
    "gn:country_code":"PH",
    "gn:dem":6,
    "gn:feature_class":"P",
    "gn:feature_code":"PPL",
    "gn:name":"Tubungan",
    "gn:population":0,
    "gn:timezone":"Asia/Manila",
    "iso:country":"PH",
    "name:bcl_x_preferred":[
        "Tubungan"
    ],
    "name:ceb_x_preferred":[
        "Tubungan"
    ],
    "name:deu_x_preferred":[
        "Tubungan"
    ],
    "name:fas_x_preferred":[
        "\u062a\u0648\u0628\u0648\u0646\u06af\u0646"
    ],
    "name:fil_x_preferred":[
        "Tubungan"
    ],
    "name:fra_x_preferred":[
        "Tubungan"
    ],
    "name:ilo_x_preferred":[
        "Tubungan"
    ],
    "name:ind_x_preferred":[
        "Tubungan"
    ],
    "name:ita_x_preferred":[
        "Tubungan"
    ],
    "name:nld_x_preferred":[
        "Tubungan"
    ],
    "name:nor_x_preferred":[
        "Tubungan"
    ],
    "name:pag_x_preferred":[
        "Tubungan"
    ],
    "name:pam_x_preferred":[
        "Tubungan"
    ],
    "name:spa_x_preferred":[
        "Tubung\u00e1n"
    ],
    "name:swe_x_preferred":[
        "Tubungan"
    ],
    "name:tgl_x_preferred":[
        "Tubungan"
    ],
    "name:urd_x_preferred":[
        "\u062a\u0648\u0628\u0646\u06af\u0646"
    ],
    "name:vie_x_preferred":[
        "Tubungan"
    ],
    "name:war_x_preferred":[
        "Tubungan"
    ],
    "wof:name":"Tubungan",
    "wof:placetype":"locality"
},
  "geometry": {"coordinates":[122.73972000000001,10.875],"type":"Point"}
}