{
  "type": "Feature",
  "properties": {
    "gn:admin1_code":"14",
    "gn:admin2_code":"35",
    "gn:admin3_code":"153634000.0",
    "gn:asciiname":"Maydaya",
    "gn:country_code":"PH",
    "gn:dem":709,
    "gn:feature_class":"P",
    "gn:feature_code":"PPL",
    "gn:name":"Maydaya",
    "gn:population":0,
    "gn:timezone":"Asia/Manila",
    "iso:country":"PH",
    "name:fil_x_preferred":[
        "Maydaya"
    ],
    "wof:name":"Maydaya",
    "wof:placetype":"locality"
},
  "geometry": {"coordinates":[124.36667,7.88333],"type":"Point"}
}