{
  "type": "Feature",
  "properties": {
    "gn:admin1_code":"08",
    "gn:admin2_code":"55",
    "gn:admin3_code":"86002000.0",
    "gn:asciiname":"Old San Agustin",
    "gn:country_code":"PH",
    "gn:dem":8,
    "gn:feature_class":"P",
    "gn:feature_code":"PPL",
    "gn:name":"Old San Agustin",
    "gn:population":0,
    "gn:timezone":"Asia/Manila",
    "iso:country":"PH",
    "name:fil_x_preferred":[
        "Old San Agustin"
    ],
    "wof:name":"Old San Agustin",
    "wof:placetype":"locality"
},
  "geometry": {"coordinates":[125.09721999999999,11.33361],"type":"Point"}
}