{
  "type": "Feature",
  "properties": {
    "gn:country":"PH",
    "gn:fcode":"PPL",
    "gn:pop":6835,
    "iso:country":"PH",
    "name:fil_x_preferred":[
        "San Vicente"
    ],
    "qs:name":"San Vicente",
    "qs:photos_9r":0,
    "qs:photos_sr":0,
    "qs:pop_sr":"5",
    "wd:wordcount":196,
    "wof:name":"San Vicente",
    "wof:placetype":"locality",
    "wof:population":6835
},
  "geometry": {"coordinates":[120.81901000000001,15.21324],"type":"Point"}
}