{
  "type": "Feature",
  "properties": {
    "gn:admin1_code":"08",
    "gn:admin2_code":"55",
    "gn:admin3_code":"86001000.0",
    "gn:asciiname":"Basiao",
    "gn:country_code":"PH",
    "gn:dem":20,
    "gn:feature_class":"P",
    "gn:feature_code":"PPL",
    "gn:name":"Basiao",
    "gn:population":0,
    "gn:timezone":"Asia/Manila",
    "iso:country":"PH",
    "name:eng_x_preferred":[
        "Basiao"
    ],
    "name:und_x_variant":[
        "Bakhaw",
        "Bacjao"
    ],
    "wof:name":"Basiao",
    "wof:placetype":"locality"
},
  "geometry": {"coordinates":[124.3177,11.9498],"type":"Point"}
}