{
  "type": "Feature",
  "properties": {
    "gn:admin1_code":"09",
    "gn:admin2_code":"66",
    "gn:asciiname":"Gelleman",
    "gn:country_code":"PH",
    "gn:dem":0,
    "gn:feature_class":"P",
    "gn:feature_code":"PPL",
    "gn:name":"Gelleman",
    "gn:population":0,
    "gn:timezone":"Asia/Manila",
    "iso:country":"PH",
    "wof:name":"Gelleman",
    "wof:placetype":"locality"
},
  "geometry": {"coordinates":[122.37444000000001,7.39222],"type":"Point"}
}