{
  "type": "Feature",
  "properties": {
    "iso:country":"PH",
    "name:bcl_x_preferred":[
        "Nasipit"
    ],
    "name:cbk_zam_x_preferred":[
        "Nasipit"
    ],
    "name:ceb_x_preferred":[
        "Nasipit"
    ],
    "name:deu_x_preferred":[
        "Nasipit"
    ],
    "name:eng_x_preferred":[
        "Nasipit"
    ],
    "name:fra_x_preferred":[
        "Nasipit"
    ],
    "name:ilo_x_preferred":[
        "Nasipit"
    ],
    "name:ind_x_preferred":[
        "Nasipit"
    ],
    "name:ita_x_preferred":[
        "Nasipit"
    ],
    "name:jpn_x_preferred":[
        "\u30ca\u30b7\u30d4\u30c3\u30c8"
    ],
    "name:msa_x_preferred":[
        "Nasipit"
    ],
    "name:nld_x_preferred":[
        "Nasipit"
    ],
    "name:pag_x_preferred":[
        "Nasipit"
    ],
    "name:pam_x_preferred":[
        "Nasipit"
    ],
    "name:spa_x_preferred":[
        "Nasipit"
    ],
    "name:swe_x_preferred":[
        "Nasipit"
    ],
    "name:tgl_x_preferred":[
        "Nasipit"
    ],
    "name:unk_x_variant":[
        "Nasapit"
    ],
    "name:vie_x_preferred":[
        "Nasipit"
    ],
    "name:war_x_preferred":[
        "Nasipit"
    ],
    "qs:gn_country":"PH",
    "qs:gn_fcode":"PPLA3",
    "qs:gn_pop":9407,
    "qs:name":"Nasipit",
    "qs:name_adm0":"Philippines",
    "qs:name_adm1":"Caraga",
    "qs:photos":58,
    "qs:photos_1k":12,
    "qs:photos_9k":1,
    "qs:photos_9r":2,
    "qs:photos_all":58,
    "qs:photos_sr":2,
    "qs:placetype":"Town",
    "qs:pop_sr":"5",
    "qs:woe_adm0":23424934,
    "wd:wordcount":1077,
    "wof:name":"Nasipit",
    "wof:placetype":"locality",
    "wof:population":9407
},
  "geometry": {"coordinates":[125.29472,8.96917],"type":"Point"}
}