{
  "type": "Feature",
  "properties": {
    "gn:admin1_code":"15",
    "gn:admin2_code":"01",
    "gn:admin3_code":"140127000.0",
    "gn:asciiname":"Bollilising",
    "gn:country_code":"PH",
    "gn:dem":213,
    "gn:feature_class":"P",
    "gn:feature_code":"PPL",
    "gn:name":"Bollilising",
    "gn:population":0,
    "gn:timezone":"Asia/Manila",
    "iso:country":"PH",
    "name:fil_x_preferred":[
        "Bollilising"
    ],
    "name:fil_x_variant":[
        "Bullilising"
    ],
    "name:und_x_variant":[
        "Bullilising"
    ],
    "wof:name":"Bollilising",
    "wof:placetype":"locality"
},
  "geometry": {"coordinates":[120.5989,17.3527],"type":"Point"}
}