{
  "type": "Feature",
  "properties": {
    "gn:admin1_code":"06",
    "gn:admin2_code":"30",
    "gn:admin3_code":"63002000.0",
    "gn:asciiname":"Ban-ag",
    "gn:country_code":"PH",
    "gn:dem":160,
    "gn:feature_class":"P",
    "gn:feature_code":"PPL",
    "gn:name":"Ban-ag",
    "gn:population":0,
    "gn:timezone":"Asia/Manila",
    "iso:country":"PH",
    "name:fil_x_preferred":[
        "Ban-ag"
    ],
    "wof:name":"Ban-ag",
    "wof:placetype":"locality"
},
  "geometry": {"coordinates":[122.41332,10.81522],"type":"Point"}
}