{
  "type": "Feature",
  "properties": {
    "gn:admin1_code":"41",
    "gn:admin2_code":"40",
    "gn:admin3_code":"175109000.0",
    "gn:asciiname":"Manamuc",
    "gn:country_code":"PH",
    "gn:dem":10,
    "gn:feature_class":"P",
    "gn:feature_code":"PPL",
    "gn:name":"Manamuc",
    "gn:population":0,
    "gn:timezone":"Asia/Manila",
    "iso:country":"PH",
    "name:fil_x_preferred":[
        "Manamuc"
    ],
    "name:und_x_variant":[
        "Manomoc",
        "Manamo",
        "Manamoc"
    ],
    "wof:name":"Manamuc",
    "wof:placetype":"locality"
},
  "geometry": {"coordinates":[120.81789999999999,12.9129],"type":"Point"}
}