{
  "type": "Feature",
  "properties": {
    "gn:admin1_code":"07",
    "gn:admin2_code":"21",
    "gn:admin3_code":"72203000.0",
    "gn:asciiname":"Locon",
    "gn:country_code":"PH",
    "gn:dem":35,
    "gn:feature_class":"P",
    "gn:feature_code":"PPL",
    "gn:name":"Locon",
    "gn:population":0,
    "gn:timezone":"Asia/Manila",
    "iso:country":"PH",
    "name:ara_x_preferred":[
        "\u0644\u0648\u0643\u0648\u0646"
    ],
    "name:bre_x_preferred":[
        "Locon"
    ],
    "name:cat_x_preferred":[
        "Locon"
    ],
    "name:ceb_x_preferred":[
        "Locon"
    ],
    "name:deu_x_preferred":[
        "Locon"
    ],
    "name:eus_x_preferred":[
        "Locon"
    ],
    "name:fil_x_preferred":[
        "Locon"
    ],
    "name:fra_x_preferred":[
        "Locon"
    ],
    "name:hun_x_preferred":[
        "Locon"
    ],
    "name:ind_x_preferred":[
        "Locon"
    ],
    "name:ita_x_preferred":[
        "Locon"
    ],
    "name:kaz_x_preferred":[
        "\u041b\u043e\u043a\u043e\u043d"
    ],
    "name:lat_x_preferred":[
        "Locon"
    ],
    "name:mlg_x_preferred":[
        "Locon"
    ],
    "name:msa_x_preferred":[
        "Locon"
    ],
    "name:nld_x_preferred":[
        "Locon"
    ],
    "name:oci_x_preferred":[
        "Locon"
    ],
    "name:pcd_x_preferred":[
        "Locon"
    ],
    "name:pms_x_preferred":[
        "Locon"
    ],
    "name:pol_x_preferred":[
        "Locon"
    ],
    "name:por_x_preferred":[
        "Locon"
    ],
    "name:ron_x_preferred":[
        "Locon"
    ],
    "name:slk_x_preferred":[
        "Locon"
    ],
    "name:spa_x_preferred":[
        "Locon"
    ],
    "name:swe_x_preferred":[
        "Locon"
    ],
    "name:ukr_x_preferred":[
        "\u041b\u043e\u043a\u043e\u043d"
    ],
    "name:vie_x_preferred":[
        "Locon"
    ],
    "name:vls_x_preferred":[
        "Lockon"
    ],
    "name:vol_x_preferred":[
        "Locon"
    ],
    "name:war_x_preferred":[
        "Locon"
    ],
    "wof:name":"Locon",
    "wof:placetype":"locality"
},
  "geometry": {"coordinates":[123.3407,9.7408],"type":"Point"}
}