{
  "type": "Feature",
  "properties": {
    "gn:admin1_code":"03",
    "gn:admin2_code":"64",
    "gn:admin3_code":"37112000.0",
    "gn:asciiname":"Mabangcal",
    "gn:country_code":"PH",
    "gn:dem":14,
    "gn:feature_class":"P",
    "gn:feature_code":"PPL",
    "gn:name":"Mabangcal",
    "gn:population":0,
    "gn:timezone":"Asia/Manila",
    "iso:country":"PH",
    "name:fil_x_preferred":[
        "Mabangcal"
    ],
    "name:und_x_variant":[
        "Mabancal",
        "Mabanocal"
    ],
    "wof:name":"Mabangcal",
    "wof:placetype":"locality"
},
  "geometry": {"coordinates":[120.07823,14.99448],"type":"Point"}
}