{
  "type": "Feature",
  "properties": {
    "gn:admin1_code":"40",
    "gn:admin2_code":"20",
    "gn:admin3_code":"42123000.0",
    "gn:asciiname":"I. Salud",
    "gn:country_code":"PH",
    "gn:dem":119,
    "gn:feature_class":"P",
    "gn:feature_code":"PPL",
    "gn:name":"I. Salud",
    "gn:population":0,
    "gn:timezone":"Asia/Manila",
    "iso:country":"PH",
    "name:fil_x_preferred":[
        "I. Salud"
    ],
    "wof:name":"I. Salud",
    "wof:placetype":"locality"
},
  "geometry": {"coordinates":[121.01445,14.30809],"type":"Point"}
}