{
  "type": "Feature",
  "properties": {
    "gn:admin1_code":"08",
    "gn:admin2_code":"67",
    "gn:admin3_code":"84814000.0",
    "gn:asciiname":"Cansapot",
    "gn:country_code":"PH",
    "gn:dem":12,
    "gn:feature_class":"P",
    "gn:feature_code":"PPL",
    "gn:name":"Cansapot",
    "gn:population":0,
    "gn:timezone":"Asia/Manila",
    "iso:country":"PH",
    "name:fil_x_preferred":[
        "Cansapot"
    ],
    "wof:name":"Cansapot",
    "wof:placetype":"locality"
},
  "geometry": {"coordinates":[125.10209999999999,12.5204],"type":"Point"}
}