{
  "type": "Feature",
  "properties": {
    "gn:admin1_code":"40",
    "gn:admin2_code":"33",
    "gn:admin3_code":"43417000.0",
    "gn:asciiname":"Bangkoro",
    "gn:country_code":"PH",
    "gn:dem":86,
    "gn:feature_class":"P",
    "gn:feature_code":"PPL",
    "gn:name":"Bangkoro",
    "gn:population":0,
    "gn:timezone":"Asia/Manila",
    "iso:country":"PH",
    "name:fil_x_preferred":[
        "Bangkoro"
    ],
    "wof:name":"Bangkoro",
    "wof:placetype":"locality"
},
  "geometry": {"coordinates":[121.4127,14.1738],"type":"Point"}
}