{
  "type": "Feature",
  "properties": {
    "gn:admin1_code":"12",
    "gn:admin2_code":"B8",
    "gn:asciiname":"Tadukun",
    "gn:country_code":"PH",
    "gn:dem":6,
    "gn:feature_class":"P",
    "gn:feature_code":"PPL",
    "gn:name":"Tadukun",
    "gn:population":0,
    "gn:timezone":"Asia/Manila",
    "iso:country":"PH",
    "wof:name":"Tadukun",
    "wof:placetype":"locality"
},
  "geometry": {"coordinates":[124.28610999999999,7.16389],"type":"Point"}
}