{
  "type": "Feature",
  "properties": {
    "gn:admin1_code":"41",
    "gn:admin2_code":"49",
    "gn:admin3_code":"175311000.0",
    "gn:asciiname":"Lingit",
    "gn:country_code":"PH",
    "gn:dem":13,
    "gn:feature_class":"P",
    "gn:feature_code":"PPL",
    "gn:name":"Lingit",
    "gn:population":0,
    "gn:timezone":"Asia/Manila",
    "iso:country":"PH",
    "name:eng_x_preferred":[
        "Lingit"
    ],
    "wof:name":"Lingit",
    "wof:placetype":"locality"
},
  "geometry": {"coordinates":[119.6764,10.49438],"type":"Point"}
}