{
  "type": "Feature",
  "properties": {
    "gn:admin1_code":"01",
    "gn:admin2_code":"28",
    "gn:admin3_code":"12811000.0",
    "gn:asciiname":"Papadog",
    "gn:country_code":"PH",
    "gn:dem":80,
    "gn:feature_class":"P",
    "gn:feature_code":"PPL",
    "gn:name":"Papadog",
    "gn:population":0,
    "gn:timezone":"Asia/Manila",
    "iso:country":"PH",
    "name:fil_x_preferred":[
        "Papadog"
    ],
    "wof:name":"Papadog",
    "wof:placetype":"locality"
},
  "geometry": {"coordinates":[120.63333,17.95],"type":"Point"}
}