{
  "type": "Feature",
  "properties": {
    "gn:country":"PH",
    "gn:fcode":"ADM3",
    "gn:pop":23450,
    "iso:country":"PH",
    "name:fil_x_preferred":[
        "Dauin"
    ],
    "qs:name":"Dauin",
    "qs:photos_9r":0,
    "qs:photos_sr":0,
    "qs:pop_sr":"7",
    "wd:wordcount":777,
    "wof:name":"Dauin",
    "wof:placetype":"localadmin",
    "wof:population":23450
},
  "geometry": {"coordinates":[123.21666999999999,9.21667],"type":"Point"}
}