{
  "type": "Feature",
  "properties": {
    "gn:country":"PH",
    "gn:fcode":"ADM3",
    "gn:pop":23450,
    "iso:country":"PH",
    "name:bcl_x_preferred":[
        "Dauin"
    ],
    "name:cat_x_preferred":[
        "Dauin"
    ],
    "name:ceb_x_preferred":[
        "Dauin"
    ],
    "name:deu_x_preferred":[
        "Dauin"
    ],
    "name:eng_x_preferred":[
        "Dauin"
    ],
    "name:fil_x_preferred":[
        "Dauin"
    ],
    "name:fra_x_preferred":[
        "Dauin"
    ],
    "name:ilo_x_preferred":[
        "Dauin"
    ],
    "name:ind_x_preferred":[
        "Dauin"
    ],
    "name:ita_x_preferred":[
        "Dauin"
    ],
    "name:jpn_x_preferred":[
        "\u30c0\u30a6\u30a4\u30f3"
    ],
    "name:nld_x_preferred":[
        "Dauin"
    ],
    "name:pag_x_preferred":[
        "Dauin"
    ],
    "name:pam_x_preferred":[
        "Dauin"
    ],
    "name:spa_x_preferred":[
        "Dauin"
    ],
    "name:swe_x_preferred":[
        "Dauin"
    ],
    "name:tgl_x_preferred":[
        "Dauin"
    ],
    "name:vie_x_preferred":[
        "Dauin"
    ],
    "name:war_x_preferred":[
        "Dauin"
    ],
    "qs:name":"Dauin",
    "qs:photos_9r":0,
    "qs:photos_sr":0,
    "qs:pop_sr":"7",
    "wd:wordcount":777,
    "wof:name":"Dauin",
    "wof:placetype":"localadmin",
    "wof:population":23450
},
  "geometry": {"coordinates":[123.21666999999999,9.21667],"type":"Point"}
}