{
  "type": "Feature",
  "properties": {
    "gn:admin1_code":"01",
    "gn:admin2_code":"51",
    "gn:admin3_code":"15532000.0",
    "gn:asciiname":"Anlabo",
    "gn:country_code":"PH",
    "gn:dem":14,
    "gn:feature_class":"P",
    "gn:feature_code":"PPL",
    "gn:name":"Anlabo",
    "gn:population":0,
    "gn:timezone":"Asia/Manila",
    "iso:country":"PH",
    "name:fil_x_preferred":[
        "Anlabo"
    ],
    "wof:name":"Anlabo",
    "wof:placetype":"locality"
},
  "geometry": {"coordinates":[120.37220000000001,15.9068],"type":"Point"}
}