{
  "type": "Feature",
  "properties": {
    "gn:admin1_code":"07",
    "gn:admin2_code":"11",
    "gn:admin3_code":"71242000.0",
    "gn:asciiname":"Taloto",
    "gn:country_code":"PH",
    "gn:dem":10,
    "gn:feature_class":"P",
    "gn:feature_code":"PPL",
    "gn:name":"Taloto",
    "gn:population":0,
    "gn:timezone":"Asia/Manila",
    "iso:country":"PH",
    "name:fil_x_preferred":[
        "Taloto"
    ],
    "name:und_x_variant":[
        "Taluto"
    ],
    "wof:name":"Taloto",
    "wof:placetype":"locality"
},
  "geometry": {"coordinates":[123.85212,9.67691],"type":"Point"}
}