{
  "type": "Feature",
  "properties": {
    "gn:admin1_code":"13",
    "gn:admin2_code":"02",
    "gn:admin3_code":"160211000.0",
    "gn:asciiname":"Cabayawa",
    "gn:country_code":"PH",
    "gn:dem":9,
    "gn:feature_class":"P",
    "gn:feature_code":"PPL",
    "gn:name":"Cabayawa",
    "gn:population":0,
    "gn:timezone":"Asia/Manila",
    "iso:country":"PH",
    "name:fil_x_preferred":[
        "Cabayawa"
    ],
    "wof:name":"Cabayawa",
    "wof:placetype":"locality"
},
  "geometry": {"coordinates":[125.52667,9.14917],"type":"Point"}
}