{
  "type": "Feature",
  "properties": {
    "gn:admin1_code":"10",
    "gn:admin2_code":"17",
    "gn:asciiname":"Libod",
    "gn:country_code":"PH",
    "gn:dem":58,
    "gn:feature_class":"P",
    "gn:feature_code":"PPL",
    "gn:name":"Libod",
    "gn:population":0,
    "gn:timezone":"Asia/Manila",
    "iso:country":"PH",
    "name:fil_x_preferred":[
        "Libod"
    ],
    "wof:name":"Libod",
    "wof:placetype":"locality"
},
  "geometry": {"coordinates":[125.7799,7.0649],"type":"Point"}
}