{
  "type": "Feature",
  "properties": {
    "gn:admin1_code":"06",
    "gn:admin2_code":"H3",
    "gn:admin3_code":"64510000.0",
    "gn:asciiname":"Carolan",
    "gn:country_code":"PH",
    "gn:dem":213,
    "gn:feature_class":"P",
    "gn:feature_code":"PPL",
    "gn:name":"Carolan",
    "gn:population":0,
    "gn:timezone":"Asia/Manila",
    "iso:country":"PH",
    "name:deu_x_preferred":[
        "Carolan"
    ],
    "name:fil_x_preferred":[
        "Carolan"
    ],
    "name:und_x_variant":[
        "Caralon"
    ],
    "wof:name":"Carolan",
    "wof:placetype":"locality"
},
  "geometry": {"coordinates":[122.9293,9.9653],"type":"Point"}
}