{
  "type": "Feature",
  "properties": {
    "gn:admin1_code":"07",
    "gn:admin2_code":"46",
    "gn:admin3_code":"74609000.0",
    "gn:asciiname":"Anjauan",
    "gn:country_code":"PH",
    "gn:dem":36,
    "gn:feature_class":"P",
    "gn:feature_code":"PPL",
    "gn:name":"Anjauan",
    "gn:population":0,
    "gn:timezone":"Asia/Manila",
    "iso:country":"PH",
    "name:und_x_variant":[
        "Anhauan",
        "Anjauan"
    ],
    "wof:name":"Anjauan",
    "wof:placetype":"locality"
},
  "geometry": {"coordinates":[123.25,9.18333],"type":"Point"}
}