{
  "type": "Feature",
  "properties": {
    "gn:admin1_code":"03",
    "gn:admin2_code":"47",
    "gn:admin3_code":"34922000.0",
    "gn:asciiname":"Labong",
    "gn:country_code":"PH",
    "gn:dem":39,
    "gn:feature_class":"P",
    "gn:feature_code":"PPL",
    "gn:name":"Labong",
    "gn:population":0,
    "gn:timezone":"Asia/Manila",
    "iso:country":"PH",
    "name:fil_x_preferred":[
        "Labong"
    ],
    "wof:name":"Labong",
    "wof:placetype":"locality"
},
  "geometry": {"coordinates":[120.8227,15.6159],"type":"Point"}
}