{
  "type": "Feature",
  "properties": {
    "gn:admin1_code":"40",
    "gn:admin2_code":"H2",
    "gn:admin3_code":"45631000.0",
    "gn:asciiname":"Bonbon",
    "gn:country_code":"PH",
    "gn:dem":7,
    "gn:feature_class":"P",
    "gn:feature_code":"PPL",
    "gn:name":"Bonbon",
    "gn:population":0,
    "gn:timezone":"Asia/Manila",
    "iso:country":"PH",
    "name:fil_x_preferred":[
        "Bonbon"
    ],
    "name:und_x_variant":[
        "Bonbom"
    ],
    "wof:name":"Bonbon",
    "wof:placetype":"locality"
},
  "geometry": {"coordinates":[121.91876000000001,15.04233],"type":"Point"}
}