{
  "type": "Feature",
  "properties": {
    "gn:admin1_code":"40",
    "gn:admin2_code":"H2",
    "gn:admin3_code":"45631000.0",
    "gn:asciiname":"Bonbon",
    "gn:country_code":"PH",
    "gn:dem":7,
    "gn:feature_class":"P",
    "gn:feature_code":"PPL",
    "gn:name":"Bonbon",
    "gn:population":0,
    "gn:timezone":"Asia/Manila",
    "iso:country":"PH",
    "name:ara_x_preferred":[
        "\u0628\u0648\u0646\u0628\u0648\u0646"
    ],
    "name:ast_x_preferred":[
        "Bomb\u00f3n"
    ],
    "name:cat_x_preferred":[
        "Bomb\u00f3"
    ],
    "name:ces_x_preferred":[
        "Bonbon"
    ],
    "name:eus_x_preferred":[
        "Bonboi"
    ],
    "name:fas_x_preferred":[
        "\u0628\u0646\u200c\u0628\u0646"
    ],
    "name:fil_x_preferred":[
        "Bonbon"
    ],
    "name:glg_x_preferred":[
        "Bomb\u00f3n"
    ],
    "name:hrv_x_preferred":[
        "Bombon"
    ],
    "name:ita_x_preferred":[
        "Cioccolatino"
    ],
    "name:jpn_x_preferred":[
        "\u30dc\u30f3\u30dc\u30f3\u83d3\u5b50"
    ],
    "name:por_x_preferred":[
        "Bombom"
    ],
    "name:spa_x_preferred":[
        "Bomb\u00f3n"
    ],
    "name:tur_x_preferred":[
        "Bonbon"
    ],
    "name:und_x_variant":[
        "Bonbom"
    ],
    "wof:name":"Bonbon",
    "wof:placetype":"locality"
},
  "geometry": {"coordinates":[121.91876000000001,15.04233],"type":"Point"}
}