{
  "type": "Feature",
  "properties": {
    "gn:admin1_code":"02",
    "gn:admin2_code":"48",
    "gn:asciiname":"Sabual",
    "gn:country_code":"PH",
    "gn:dem":751,
    "gn:feature_class":"P",
    "gn:feature_code":"PPL",
    "gn:name":"Sabual",
    "gn:population":0,
    "gn:timezone":"Asia/Manila",
    "iso:country":"PH",
    "name:fil_x_preferred":[
        "Sabual"
    ],
    "wof:name":"Sabual",
    "wof:placetype":"locality"
},
  "geometry": {"coordinates":[121.03333000000001,16.61667000000001],"type":"Point"}
}