{
  "type": "Feature",
  "properties": {
    "gn:admin1_code":"02",
    "gn:admin2_code":"68",
    "gn:admin3_code":"25705000.0",
    "gn:asciiname":"Bannuag",
    "gn:country_code":"PH",
    "gn:dem":100,
    "gn:feature_class":"P",
    "gn:feature_code":"PPL",
    "gn:name":"Bannuag",
    "gn:population":0,
    "gn:timezone":"Asia/Manila",
    "iso:country":"PH",
    "name:fil_x_preferred":[
        "Bannuag"
    ],
    "wof:name":"Bannuag",
    "wof:placetype":"locality"
},
  "geometry": {"coordinates":[121.59010000000001,16.5691],"type":"Point"}
}