{
  "type": "Feature",
  "properties": {
    "gn:admin1_code":"41",
    "gn:admin2_code":"41",
    "gn:admin3_code":"175203000.0",
    "gn:asciiname":"Panlanao",
    "gn:country_code":"PH",
    "gn:dem":57,
    "gn:feature_class":"P",
    "gn:feature_code":"PPL",
    "gn:name":"Panlanao",
    "gn:population":0,
    "gn:timezone":"Asia/Manila",
    "iso:country":"PH",
    "name:fil_x_preferred":[
        "Panlanao"
    ],
    "wof:name":"Panlanao",
    "wof:placetype":"locality"
},
  "geometry": {"coordinates":[121.45811999999999,12.71372],"type":"Point"}
}