{
  "type": "Feature",
  "properties": {
    "gn:admin1_code":"12",
    "gn:admin2_code":"57",
    "gn:admin3_code":"124711000.0",
    "gn:asciiname":"Kadinguilan",
    "gn:country_code":"PH",
    "gn:dem":20,
    "gn:feature_class":"P",
    "gn:feature_code":"PPL",
    "gn:name":"Kadinguilan",
    "gn:population":0,
    "gn:timezone":"Asia/Manila",
    "iso:country":"PH",
    "name:fil_x_preferred":[
        "Kadinguilan"
    ],
    "wof:name":"Kadinguilan",
    "wof:placetype":"locality"
},
  "geometry": {"coordinates":[124.38333,7.19056],"type":"Point"}
}