{
  "type": "Feature",
  "properties": {
    "gn:admin1_code":"09",
    "gn:admin2_code":"66",
    "gn:admin3_code":"97323000.0",
    "gn:asciiname":"Katipunan",
    "gn:country_code":"PH",
    "gn:dem":27,
    "gn:feature_class":"P",
    "gn:feature_code":"PPL",
    "gn:name":"Katipunan",
    "gn:population":0,
    "gn:timezone":"Asia/Manila",
    "iso:country":"PH",
    "name:afr_x_preferred":[
        "Katipunan"
    ],
    "name:ast_x_preferred":[
        "Katipunan"
    ],
    "name:bcl_x_preferred":[
        "Katipunan"
    ],
    "name:cat_x_preferred":[
        "Katipunan"
    ],
    "name:ceb_x_preferred":[
        "Katipunan"
    ],
    "name:deu_x_preferred":[
        "Katipunan"
    ],
    "name:eng_x_preferred":[
        "Katipunan"
    ],
    "name:fas_x_preferred":[
        "\u06a9\u0627\u062a\u06cc\u067e\u0648\u0646\u0627\u0646"
    ],
    "name:fin_x_preferred":[
        "Katipunan"
    ],
    "name:fra_x_preferred":[
        "Katipunan"
    ],
    "name:ilo_x_preferred":[
        "Katipunan"
    ],
    "name:ina_x_preferred":[
        "Katipunan"
    ],
    "name:ind_x_preferred":[
        "Katipunan"
    ],
    "name:ita_x_preferred":[
        "Katipunan"
    ],
    "name:jpn_x_preferred":[
        "\u30ab\u30c6\u30a3\u30d7\u30ca\u30f3"
    ],
    "name:kor_x_preferred":[
        "\uce74\ud2f0\ud478\ub09c"
    ],
    "name:lat_x_preferred":[
        "Katipunan"
    ],
    "name:msa_x_preferred":[
        "Katipunan"
    ],
    "name:nld_x_preferred":[
        "Katipunan"
    ],
    "name:nor_x_preferred":[
        "Katipunan"
    ],
    "name:pol_x_preferred":[
        "Katipunan"
    ],
    "name:rus_x_preferred":[
        "\u041a\u0430\u0442\u0438\u043f\u0443\u043d\u0430\u043d"
    ],
    "name:spa_x_preferred":[
        "Katipunan"
    ],
    "name:tgl_x_preferred":[
        "Katipunan"
    ],
    "name:vie_x_preferred":[
        "Katipunan"
    ],
    "name:zho_x_preferred":[
        "\u5361\u8482\u666e\u5357"
    ],
    "wof:name":"Katipunan",
    "wof:placetype":"locality"
},
  "geometry": {"coordinates":[123.4439,8.0518],"type":"Point"}
}