{
  "type": "Feature",
  "properties": {
    "gn:admin1_code":"01",
    "gn:admin2_code":"29",
    "gn:admin3_code":"12914000.0",
    "gn:asciiname":"Balasiw",
    "gn:country_code":"PH",
    "gn:dem":76,
    "gn:feature_class":"P",
    "gn:feature_code":"PPL",
    "gn:name":"Balasiw",
    "gn:population":0,
    "gn:timezone":"Asia/Manila",
    "iso:country":"PH",
    "name:fil_x_preferred":[
        "Balasiw"
    ],
    "name:fil_x_variant":[
        "Bal-lasiw",
        "Bal-lisiw",
        "Ballasio"
    ],
    "name:und_x_variant":[
        "Ballasio",
        "Bal-lisiw"
    ],
    "wof:name":"Balasiw",
    "wof:placetype":"locality"
},
  "geometry": {"coordinates":[120.51649999999999,17.4921],"type":"Point"}
}