{
  "type": "Feature",
  "properties": {
    "gn:country":"PH",
    "gn:fcode":"PPL",
    "gn:population":2216,
    "iso:country":"PH",
    "name:fil_x_preferred":[
        "Bacnor"
    ],
    "name:und_x_variant":[
        "Bacnor East"
    ],
    "qs_pg:aaroncc":"PH",
    "qs_pg:gn_country":"PH",
    "qs_pg:gn_fcode":"PPL",
    "qs_pg:gn_pop":2216,
    "qs_pg:name":"Bacnor",
    "qs_pg:photos_9r":0,
    "qs_pg:photos_sr":0,
    "qs_pg:pop_sr":4,
    "qs_pg:qs_pg_placetype":"locality",
    "wof:name":"Bacnor",
    "wof:placetype":"locality",
    "wof:population":2216
},
  "geometry": {"coordinates":[121.63333,16.98333],"type":"Point"}
}