{
  "type": "Feature",
  "properties": {
    "gn:admin1_code":"10",
    "gn:admin2_code":"12",
    "gn:admin3_code":"101316000.0",
    "gn:asciiname":"Kisawi",
    "gn:cc2":"PH",
    "gn:country_code":"PH",
    "gn:dem":326,
    "gn:feature_class":"P",
    "gn:feature_code":"PPL",
    "gn:name":"Kisawi",
    "gn:population":0,
    "gn:timezone":"Asia/Manila",
    "iso:country":"PH",
    "name:und_x_variant":[
        "Kisaw",
        "Kisawi"
    ],
    "wof:name":"Kisawi",
    "wof:placetype":"locality"
},
  "geometry": {"coordinates":[124.83028,7.57194],"type":"Point"}
}