{
  "type": "Feature",
  "properties": {
    "gn:admin1_code":"06",
    "gn:admin2_code":"30",
    "gn:admin3_code":"63017000.0",
    "gn:asciiname":"Batuan",
    "gn:country_code":"PH",
    "gn:dem":68,
    "gn:feature_class":"P",
    "gn:feature_code":"PPL",
    "gn:name":"Batuan",
    "gn:population":0,
    "gn:timezone":"Asia/Manila",
    "iso:country":"PH",
    "name:ceb_x_preferred":[
        "Batuan"
    ],
    "name:deu_x_preferred":[
        "Batuan"
    ],
    "name:fil_x_preferred":[
        "Batuan"
    ],
    "name:fra_x_preferred":[
        "Batuan"
    ],
    "name:ind_x_preferred":[
        "Batuan"
    ],
    "name:ita_x_preferred":[
        "Batuan"
    ],
    "name:nld_x_preferred":[
        "Batuan"
    ],
    "name:nor_x_preferred":[
        "Batuan"
    ],
    "name:swe_x_preferred":[
        "Batuan"
    ],
    "name:war_x_preferred":[
        "Batuan"
    ],
    "wof:name":"Batuan",
    "wof:placetype":"locality"
},
  "geometry": {"coordinates":[122.5968,11.0678],"type":"Point"}
}