{
  "type": "Feature",
  "properties": {
    "gn:admin1_code":"01",
    "gn:admin2_code":"28",
    "gn:admin3_code":"12816000.0",
    "gn:asciiname":"Bago",
    "gn:country_code":"PH",
    "gn:dem":15,
    "gn:feature_class":"P",
    "gn:feature_code":"PPL",
    "gn:name":"Bago",
    "gn:population":0,
    "gn:timezone":"Asia/Manila",
    "iso:country":"PH",
    "name:ceb_x_preferred":[
        "Bago"
    ],
    "name:ces_x_preferred":[
        "Bago"
    ],
    "name:fil_x_preferred":[
        "Bago"
    ],
    "name:fra_x_preferred":[
        "Bago"
    ],
    "name:ita_x_preferred":[
        "Bago"
    ],
    "name:nld_x_preferred":[
        "Bago"
    ],
    "name:rus_x_preferred":[
        "\u0411\u0430\u0433\u043e"
    ],
    "name:spa_x_preferred":[
        "Bago"
    ],
    "name:swe_x_preferred":[
        "Bago"
    ],
    "wof:name":"Bago",
    "wof:placetype":"locality"
},
  "geometry": {"coordinates":[120.5236,18.077],"type":"Point"}
}