{
  "type": "Feature",
  "properties": {
    "gn:admin1_code":"03",
    "gn:admin2_code":"47",
    "gn:admin3_code":"34919000.0",
    "gn:asciiname":"Pahingahan",
    "gn:country_code":"PH",
    "gn:dem":102,
    "gn:feature_class":"P",
    "gn:feature_code":"PPL",
    "gn:name":"Pahingahan",
    "gn:population":0,
    "gn:timezone":"Asia/Manila",
    "iso:country":"PH",
    "name:fil_x_preferred":[
        "Pahingahan"
    ],
    "wof:name":"Pahingahan",
    "wof:placetype":"locality"
},
  "geometry": {"coordinates":[121.11253000000001,15.40855],"type":"Point"}
}