{
  "type": "Feature",
  "properties": {
    "gn:admin1_code":"40",
    "gn:admin2_code":"H2",
    "gn:admin3_code":"45601000.0",
    "gn:asciiname":"Kinagunan Ibaba",
    "gn:country_code":"PH",
    "gn:dem":7,
    "gn:feature_class":"P",
    "gn:feature_code":"PPL",
    "gn:name":"Kinagunan Ibaba",
    "gn:population":0,
    "gn:timezone":"Asia/Manila",
    "iso:country":"PH",
    "name:fil_x_preferred":[
        "Kinaguan Ibaba"
    ],
    "name:und_x_variant":[
        "Quinagunan",
        "Ibabang Kinagunan",
        "Kinagunan",
        "Kinagunan Ibaba"
    ],
    "wof:name":"Kinagunan Ibaba",
    "wof:placetype":"locality"
},
  "geometry": {"coordinates":[121.90278000000001,13.87959],"type":"Point"}
}