{
  "type": "Feature",
  "properties": {
    "gn:admin1_code":"10",
    "gn:admin2_code":"42",
    "gn:admin3_code":"104215000.0",
    "gn:asciiname":"Macupa",
    "gn:country_code":"PH",
    "gn:dem":48,
    "gn:feature_class":"P",
    "gn:feature_code":"PPL",
    "gn:name":"Macupa",
    "gn:population":0,
    "gn:timezone":"Asia/Manila",
    "iso:country":"PH",
    "name:fil_x_preferred":[
        "Macupa"
    ],
    "wof:name":"Macupa",
    "wof:placetype":"locality"
},
  "geometry": {"coordinates":[123.7163,8.0752],"type":"Point"}
}