{
  "type": "Feature",
  "properties": {
    "gn:admin1_code":"11",
    "gn:admin2_code":"26",
    "gn:admin3_code":"112501000.0",
    "gn:asciiname":"Campawan",
    "gn:country_code":"PH",
    "gn:dem":45,
    "gn:feature_class":"P",
    "gn:feature_code":"PPL",
    "gn:name":"Campawan",
    "gn:population":0,
    "gn:timezone":"Asia/Manila",
    "iso:country":"PH",
    "name:fil_x_preferred":[
        "Campawan"
    ],
    "wof:name":"Campawan",
    "wof:placetype":"locality"
},
  "geometry": {"coordinates":[126.4845,7.6636],"type":"Point"}
}