{
  "type": "Feature",
  "properties": {
    "gn:admin1_code":"06",
    "gn:admin2_code":"04",
    "gn:admin3_code":"60402000.0",
    "gn:asciiname":"Panargo",
    "gn:country_code":"PH",
    "gn:dem":193,
    "gn:feature_class":"P",
    "gn:feature_code":"PPL",
    "gn:name":"Panargo",
    "gn:population":0,
    "gn:timezone":"Asia/Manila",
    "iso:country":"PH",
    "name:fil_x_preferred":[
        "Panargo"
    ],
    "wof:name":"Panargo",
    "wof:placetype":"locality"
},
  "geometry": {"coordinates":[122.36371,11.4878],"type":"Point"}
}