{
  "type": "Feature",
  "properties": {
    "iso:country":"PH",
    "name:bcl_x_preferred":[
        "Cervantes"
    ],
    "name:cat_x_preferred":[
        "Cervantes"
    ],
    "name:ceb_x_preferred":[
        "Cervantes"
    ],
    "name:deu_x_preferred":[
        "Cervantes"
    ],
    "name:eng_x_preferred":[
        "Cervantes"
    ],
    "name:fil_x_preferred":[
        "Cervantes"
    ],
    "name:fra_x_preferred":[
        "Cervantes"
    ],
    "name:ilo_x_preferred":[
        "Cervantes"
    ],
    "name:ind_x_preferred":[
        "Cervantes"
    ],
    "name:ita_x_preferred":[
        "Cervantes"
    ],
    "name:nld_x_preferred":[
        "Cervantes"
    ],
    "name:oci_x_preferred":[
        "Cervantes"
    ],
    "name:pag_x_preferred":[
        "Cervantes"
    ],
    "name:pam_x_preferred":[
        "Cervantes"
    ],
    "name:spa_x_preferred":[
        "Cervantes"
    ],
    "name:swe_x_preferred":[
        "Cervantes"
    ],
    "name:tgl_x_preferred":[
        "Cervantes"
    ],
    "name:vie_x_preferred":[
        "Cervantes"
    ],
    "name:war_x_preferred":[
        "Cervantes"
    ],
    "qs:gn_pop":0,
    "qs:name":"Cervantes",
    "qs:name_adm0":"Philippines",
    "qs:name_adm1":"Ilocos Region",
    "qs:photos":28,
    "qs:photos_1k":6,
    "qs:photos_9k":1,
    "qs:photos_9r":2,
    "qs:photos_all":28,
    "qs:photos_sr":2,
    "qs:placetype":"Town",
    "qs:pop_sr":"0",
    "qs:woe_adm0":23424934,
    "wof:name":"Cervantes",
    "wof:placetype":"locality"
},
  "geometry": {"coordinates":[120.727729,16.9863675],"type":"Point"}
}