{
  "type": "Feature",
  "properties": {
    "gn:country":"PH",
    "gn:fcode":"PPL",
    "gn:pop":3121,
    "iso:country":"PH",
    "name:fil_x_preferred":[
        "Balitoc"
    ],
    "qs:name":"Balitoc",
    "qs:photos_9r":0,
    "qs:photos_sr":0,
    "qs:pop_sr":"4",
    "wof:name":"Balitoc",
    "wof:placetype":"locality",
    "wof:population":3121
},
  "geometry": {"coordinates":[120.63554000000001,13.86269],"type":"Point"}
}