{
  "type": "Feature",
  "properties": {
    "gn:admin1_code":"02",
    "gn:admin2_code":"48",
    "gn:admin3_code":"25006000.0",
    "gn:asciiname":"Arwas",
    "gn:country_code":"PH",
    "gn:dem":409,
    "gn:feature_class":"P",
    "gn:feature_code":"PPL",
    "gn:name":"Arwas",
    "gn:population":0,
    "gn:timezone":"Asia/Manila",
    "iso:country":"PH",
    "name:fil_x_preferred":[
        "Arwas"
    ],
    "wof:name":"Arwas",
    "wof:placetype":"locality"
},
  "geometry": {"coordinates":[121.3274,16.6955],"type":"Point"}
}