{
  "type": "Feature",
  "properties": {
    "gn:admin1_code":"01",
    "gn:admin2_code":"51",
    "gn:admin3_code":"15524000.0",
    "gn:asciiname":"Amacalan",
    "gn:country_code":"PH",
    "gn:dem":18,
    "gn:feature_class":"P",
    "gn:feature_code":"PPL",
    "gn:name":"Amacalan",
    "gn:population":0,
    "gn:timezone":"Asia/Manila",
    "iso:country":"PH",
    "name:fil_x_preferred":[
        "Amacalam"
    ],
    "name:und_x_variant":[
        "Amcalan",
        "Amacalan"
    ],
    "wof:name":"Amacalan",
    "wof:placetype":"locality"
},
  "geometry": {"coordinates":[120.43789,15.88813],"type":"Point"}
}