{
  "type": "Feature",
  "properties": {
    "gn:country":"PH",
    "gn:fcode":"PPLA3",
    "gn:pop":2295,
    "iso:country":"PH",
    "name:bcl_x_preferred":[
        "Balud"
    ],
    "name:dut_x_preferred":[
        "Balud"
    ],
    "name:eng_x_preferred":[
        "Balud"
    ],
    "name:fil_x_preferred":[
        "Balud"
    ],
    "name:fre_x_preferred":[
        "Balud"
    ],
    "name:ger_x_preferred":[
        "Balud"
    ],
    "name:ilo_x_preferred":[
        "Balud"
    ],
    "name:ind_x_preferred":[
        "Balud"
    ],
    "name:ita_x_preferred":[
        "Balud"
    ],
    "name:pag_x_preferred":[
        "Balud"
    ],
    "name:pam_x_preferred":[
        "Balud"
    ],
    "name:swe_x_preferred":[
        "Balud"
    ],
    "name:tgl_x_preferred":[
        "Balud"
    ],
    "name:unk_x_variant":[
        "Balug"
    ],
    "name:vie_x_preferred":[
        "Balud"
    ],
    "name:war_x_preferred":[
        "Balud"
    ],
    "qs:name":"Balud",
    "qs:photos_9r":0,
    "qs:photos_sr":0,
    "qs:pop_sr":"4",
    "wof:name":"Balud",
    "wof:placetype":"locality",
    "wof:population":2295
},
  "geometry": {"coordinates":[123.19351,12.03686],"type":"Point"}
}