{
  "type": "Feature",
  "properties": {
    "gn:admin1_code":"08",
    "gn:admin2_code":"67",
    "gn:admin3_code":"84815000.0",
    "gn:asciiname":"Ginualgan",
    "gn:cc2":"PH",
    "gn:country_code":"PH",
    "gn:dem":9,
    "gn:feature_class":"P",
    "gn:feature_code":"PPL",
    "gn:name":"Ginualgan",
    "gn:population":0,
    "gn:timezone":"Asia/Manila",
    "iso:country":"PH",
    "name:und_x_variant":[
        "Ginulgan",
        "Genolgan",
        "Ginualgan"
    ],
    "wof:name":"Ginualgan",
    "wof:placetype":"locality"
},
  "geometry": {"coordinates":[124.91528,12.47056],"type":"Point"}
}