{
  "type": "Feature",
  "properties": {
    "gn:admin1_code":"03",
    "gn:admin2_code":"13",
    "gn:admin3_code":"31424000.0",
    "gn:asciiname":"Mambuyo",
    "gn:country_code":"PH",
    "gn:dem":243,
    "gn:feature_class":"P",
    "gn:feature_code":"PPL",
    "gn:name":"Mambuyo",
    "gn:population":0,
    "gn:timezone":"Asia/Manila",
    "iso:country":"PH",
    "name:fil_x_preferred":[
        "Mambuyo"
    ],
    "wof:name":"Mambuyo",
    "wof:placetype":"locality"
},
  "geometry": {"coordinates":[121.23180000000001,15.0147],"type":"Point"}
}