{
  "type": "Feature",
  "properties": {
    "gn:admin1_code":"05",
    "gn:admin2_code":"16",
    "gn:admin3_code":"51727000.0",
    "gn:asciiname":"Bactacang",
    "gn:country_code":"PH",
    "gn:dem":7,
    "gn:feature_class":"P",
    "gn:feature_code":"PPL",
    "gn:name":"Bactacang",
    "gn:population":0,
    "gn:timezone":"Asia/Manila",
    "iso:country":"PH",
    "name:fil_x_preferred":[
        "Bactacang"
    ],
    "name:und_x_variant":[
        "Bactacan"
    ],
    "wof:name":"Bactacang",
    "wof:placetype":"locality"
},
  "geometry": {"coordinates":[122.8927,13.6015],"type":"Point"}
}