{
  "type": "Feature",
  "properties": {
    "gn:admin1_code":"07",
    "gn:admin2_code":"46",
    "gn:admin3_code":"74625000.0",
    "gn:asciiname":"Bagaba",
    "gn:country_code":"PH",
    "gn:dem":354,
    "gn:feature_class":"P",
    "gn:feature_code":"PPL",
    "gn:name":"Bagaba",
    "gn:population":0,
    "gn:timezone":"Asia/Manila",
    "iso:country":"PH",
    "name:fil_x_preferred":[
        "Bagaba"
    ],
    "wof:name":"Bagaba",
    "wof:placetype":"locality"
},
  "geometry": {"coordinates":[123.18429999999999,9.1806],"type":"Point"}
}