{
  "type": "Feature",
  "properties": {
    "gn:admin1_code":"02",
    "gn:admin2_code":"14",
    "gn:admin3_code":"21504000.0",
    "gn:asciiname":"Barung",
    "gn:country_code":"PH",
    "gn:dem":20,
    "gn:feature_class":"P",
    "gn:feature_code":"PPL",
    "gn:name":"Barung",
    "gn:population":0,
    "gn:timezone":"Asia/Manila",
    "iso:country":"PH",
    "name:fil_x_preferred":[
        "Barung"
    ],
    "wof:name":"Barung",
    "wof:placetype":"locality"
},
  "geometry": {"coordinates":[121.65560000000001,17.7369],"type":"Point"}
}