{
  "type": "Feature",
  "properties": {
    "gn:admin1_code":"01",
    "gn:admin2_code":"51",
    "gn:admin3_code":"15527000.0",
    "gn:asciiname":"Bogtong Bunao",
    "gn:country_code":"PH",
    "gn:dem":13,
    "gn:feature_class":"P",
    "gn:feature_code":"PPL",
    "gn:name":"Bogtong Bunao",
    "gn:population":0,
    "gn:timezone":"Asia/Manila",
    "iso:country":"PH",
    "name:fil_x_preferred":[
        "Bunao"
    ],
    "wof:name":"Bogtong Bunao",
    "wof:placetype":"locality"
},
  "geometry": {"coordinates":[120.34341000000001,15.75609],"type":"Point"}
}