{
  "type": "Feature",
  "properties": {
    "gn:admin1_code":"08",
    "gn:admin2_code":"55",
    "gn:admin3_code":"86003000.0",
    "gn:asciiname":"Tabauan",
    "gn:country_code":"PH",
    "gn:dem":33,
    "gn:feature_class":"P",
    "gn:feature_code":"PPL",
    "gn:name":"Tabauan",
    "gn:population":0,
    "gn:timezone":"Asia/Manila",
    "iso:country":"PH",
    "name:fil_x_preferred":[
        "Tabauan"
    ],
    "wof:name":"Tabauan",
    "wof:placetype":"locality"
},
  "geometry": {"coordinates":[124.61190000000001,12.1113],"type":"Point"}
}