{
  "type": "Feature",
  "properties": {
    "gn:admin1_code":"41",
    "gn:admin2_code":"41",
    "gn:admin3_code":"175201000.0",
    "gn:asciiname":"Inabayan",
    "gn:country_code":"PH",
    "gn:dem":11,
    "gn:feature_class":"P",
    "gn:feature_code":"PPL",
    "gn:name":"Inabayan",
    "gn:population":0,
    "gn:timezone":"Asia/Manila",
    "iso:country":"PH",
    "name:fil_x_preferred":[
        "Inabayan"
    ],
    "wof:name":"Inabayan",
    "wof:placetype":"locality"
},
  "geometry": {"coordinates":[121.10290000000001,13.3695],"type":"Point"}
}