{
  "type": "Feature",
  "properties": {
    "gn:admin1_code":"01",
    "gn:admin2_code":"36",
    "gn:admin3_code":"13304000.0",
    "gn:asciiname":"Tagudtud",
    "gn:country_code":"PH",
    "gn:dem":336,
    "gn:feature_class":"P",
    "gn:feature_code":"PPL",
    "gn:name":"Tagudtud",
    "gn:population":0,
    "gn:timezone":"Asia/Manila",
    "iso:country":"PH",
    "name:fil_x_preferred":[
        "Tagudtud"
    ],
    "wof:name":"Tagudtud",
    "wof:placetype":"locality"
},
  "geometry": {"coordinates":[120.45361,16.59278],"type":"Point"}
}