{
  "type": "Feature",
  "properties": {
    "gn:admin1_code":"07",
    "gn:admin2_code":"21",
    "gn:admin3_code":"72251000.0",
    "gn:asciiname":"Matabang",
    "gn:country_code":"PH",
    "gn:dem":7,
    "gn:feature_class":"P",
    "gn:feature_code":"PPL",
    "gn:name":"Matabang",
    "gn:population":0,
    "gn:timezone":"Asia/Manila",
    "iso:country":"PH",
    "name:fil_x_preferred":[
        "Matabang"
    ],
    "name:und_x_variant":[
        "Concepcion"
    ],
    "wof:name":"Matabang",
    "wof:placetype":"locality"
},
  "geometry": {"coordinates":[123.6754,10.43677],"type":"Point"}
}