{
  "type": "Feature",
  "properties": {
    "gn:admin1_code":"06",
    "gn:admin2_code":"18",
    "gn:admin3_code":"61915000.0",
    "gn:asciiname":"Agsilab",
    "gn:country_code":"PH",
    "gn:dem":13,
    "gn:feature_class":"P",
    "gn:feature_code":"PPL",
    "gn:name":"Agsilab",
    "gn:population":0,
    "gn:timezone":"Asia/Manila",
    "iso:country":"PH",
    "name:fil_x_preferred":[
        "Agsilab"
    ],
    "wof:name":"Agsilab",
    "wof:placetype":"locality"
},
  "geometry": {"coordinates":[122.56694,11.51611],"type":"Point"}
}