{
  "type": "Feature",
  "properties": {
    "gn:admin1_code":"05",
    "gn:admin2_code":"15",
    "gn:admin3_code":"51607000.0",
    "gn:asciiname":"Gubat",
    "gn:country_code":"PH",
    "gn:dem":2,
    "gn:feature_class":"P",
    "gn:feature_code":"PPL",
    "gn:name":"Gubat",
    "gn:population":0,
    "gn:timezone":"Asia/Manila",
    "iso:country":"PH",
    "name:fil_x_preferred":[
        "Gubat"
    ],
    "wof:name":"Gubat",
    "wof:placetype":"locality"
},
  "geometry": {"coordinates":[122.9853,14.1138],"type":"Point"}
}