{
  "type": "Feature",
  "properties": {
    "gn:admin1_code":"41",
    "gn:admin2_code":"49",
    "gn:admin3_code":"175316000.0",
    "gn:asciiname":"Sugut",
    "gn:country_code":"PH",
    "gn:dem":21,
    "gn:feature_class":"P",
    "gn:feature_code":"PPL",
    "gn:name":"Sugut",
    "gn:population":0,
    "gn:timezone":"Asia/Manila",
    "iso:country":"PH",
    "name:fil_x_preferred":[
        "Sugut"
    ],
    "wof:name":"Sugut",
    "wof:placetype":"locality"
},
  "geometry": {"coordinates":[118.61667,9.55],"type":"Point"}
}