{
  "type": "Feature",
  "properties": {
    "gn:admin1_code":"10",
    "gn:admin2_code":"42",
    "gn:admin3_code":"104204000.0",
    "gn:asciiname":"Dapacan",
    "gn:country_code":"PH",
    "gn:dem":106,
    "gn:feature_class":"P",
    "gn:feature_code":"PPL",
    "gn:name":"Dapacan",
    "gn:population":0,
    "gn:timezone":"Asia/Manila",
    "iso:country":"PH",
    "name:fil_x_preferred":[
        "Dapacan"
    ],
    "wof:name":"Dapacan",
    "wof:placetype":"locality"
},
  "geometry": {"coordinates":[123.63472,8.54528],"type":"Point"}
}