{
  "type": "Feature",
  "properties": {
    "gn:country":"PH",
    "gn:fcode":"PPL",
    "gn:population":3902,
    "iso:country":"PH",
    "name:fil_x_preferred":[
        "Bangao"
    ],
    "qs:name":"Bangao",
    "qs:photos_9r":0,
    "qs:photos_sr":0,
    "qs:pop_sr":"4",
    "wof:name":"Bangao",
    "wof:placetype":"locality",
    "wof:population":3902
},
  "geometry": {"coordinates":[120.8404,16.8211],"type":"Point"}
}