{
  "type": "Feature",
  "properties": {
    "gn:admin1_code":"41",
    "gn:admin2_code":"54",
    "gn:admin3_code":"175912000.0",
    "gn:asciiname":"Mamayangcahoy",
    "gn:country_code":"PH",
    "gn:dem":101,
    "gn:feature_class":"P",
    "gn:feature_code":"PPL",
    "gn:name":"Mamayangcahoy",
    "gn:population":0,
    "gn:timezone":"Asia/Manila",
    "iso:country":"PH",
    "name:fil_x_preferred":[
        "Mamayangcahoy"
    ],
    "wof:name":"Mamayangcahoy",
    "wof:placetype":"locality"
},
  "geometry": {"coordinates":[122.0741,12.5662],"type":"Point"}
}