{
  "type": "Feature",
  "properties": {
    "gn:admin1_code":"03",
    "gn:admin2_code":"47",
    "gn:admin3_code":"34924000.0",
    "gn:asciiname":"Buliran",
    "gn:country_code":"PH",
    "gn:dem":22,
    "gn:feature_class":"P",
    "gn:feature_code":"PPL",
    "gn:name":"Buliran",
    "gn:population":0,
    "gn:timezone":"Asia/Manila",
    "iso:country":"PH",
    "name:fil_x_preferred":[
        "Buliran"
    ],
    "name:und_x_variant":[
        "Buliran One",
        "Buliran Primero",
        "Buliran First"
    ],
    "wof:name":"Buliran",
    "wof:placetype":"locality"
},
  "geometry": {"coordinates":[120.86445000000001,15.27214],"type":"Point"}
}