{
  "type": "Feature",
  "properties": {
    "iso:country":"PH",
    "name:bcl_x_preferred":[
        "Sapang Dalaga"
    ],
    "name:cbk_zam_x_preferred":[
        "Sapang Dalaga"
    ],
    "name:ceb_x_preferred":[
        "Sapang Dalaga"
    ],
    "name:deu_x_preferred":[
        "Sapang Dalaga"
    ],
    "name:eng_x_preferred":[
        "Sapang Dalaga"
    ],
    "name:fra_x_preferred":[
        "Sapang Dalaga"
    ],
    "name:ilo_x_preferred":[
        "Sapang Dalaga"
    ],
    "name:ind_x_preferred":[
        "Sapang Dalaga"
    ],
    "name:ita_x_preferred":[
        "Sapang Dalaga"
    ],
    "name:nld_x_preferred":[
        "Sapang Dalaga"
    ],
    "name:pag_x_preferred":[
        "Sapang Dalaga"
    ],
    "name:pam_x_preferred":[
        "Sapang Dalaga"
    ],
    "name:spa_x_preferred":[
        "Sapang Dalaga"
    ],
    "name:swe_x_preferred":[
        "Sapang Dalaga"
    ],
    "name:tgl_x_preferred":[
        "Sapang Dalaga"
    ],
    "name:vie_x_preferred":[
        "Sapang Dalaga"
    ],
    "name:war_x_preferred":[
        "Sapang Dalaga"
    ],
    "qs:gn_country":"PH",
    "qs:gn_fcode":"PPL",
    "qs:gn_pop":2742,
    "qs:name":"Sapang Dalaga",
    "qs:name_adm0":"Philippines",
    "qs:name_adm1":"Northern Mindanao",
    "qs:photos":0,
    "qs:photos_1k":0,
    "qs:photos_9k":0,
    "qs:photos_9r":0,
    "qs:photos_all":0,
    "qs:photos_sr":0,
    "qs:placetype":"Town",
    "qs:pop_sr":"4",
    "qs:woe_adm0":23424934,
    "wd:wordcount":383,
    "wof:name":"Sapang Dalaga",
    "wof:placetype":"locality",
    "wof:population":2742
},
  "geometry": {"coordinates":[123.5624,8.5399],"type":"Point"}
}