{
  "type": "Feature",
  "properties": {
    "gn:admin1_code":"08",
    "gn:admin2_code":"37",
    "gn:admin3_code":"83703000.0",
    "gn:asciiname":"Cantatoc",
    "gn:country_code":"PH",
    "gn:dem":216,
    "gn:feature_class":"P",
    "gn:feature_code":"PPL",
    "gn:name":"Cantatoc",
    "gn:population":0,
    "gn:timezone":"Asia/Manila",
    "iso:country":"PH",
    "wof:name":"Cantatoc",
    "wof:placetype":"locality"
},
  "geometry": {"coordinates":[124.68971999999999,10.99056],"type":"Point"}
}