{
  "type": "Feature",
  "properties": {
    "gn:admin1_code":"03",
    "gn:admin2_code":"13",
    "gn:admin3_code":"31421000.0",
    "gn:asciiname":"Mayantoc",
    "gn:country_code":"PH",
    "gn:dem":46,
    "gn:feature_class":"P",
    "gn:feature_code":"PPL",
    "gn:name":"Mayantoc",
    "gn:population":0,
    "gn:timezone":"Asia/Manila",
    "iso:country":"PH",
    "name:fil_x_preferred":[
        "Mayantoc"
    ],
    "wof:name":"Mayantoc",
    "wof:placetype":"locality"
},
  "geometry": {"coordinates":[121.02370000000001,15.2118],"type":"Point"}
}