{
  "type": "Feature",
  "properties": {
    "gn:admin1_code":"05",
    "gn:admin2_code":"05",
    "gn:admin3_code":"50507000.0",
    "gn:asciiname":"Mabayawas",
    "gn:country_code":"PH",
    "gn:dem":166,
    "gn:feature_class":"P",
    "gn:feature_code":"PPL",
    "gn:name":"Mabayawas",
    "gn:population":0,
    "gn:timezone":"Asia/Manila",
    "iso:country":"PH",
    "name:fil_x_preferred":[
        "Mabayawas"
    ],
    "wof:name":"Mabayawas",
    "wof:placetype":"locality"
},
  "geometry": {"coordinates":[123.42034,13.22752],"type":"Point"}
}