{
  "type": "Feature",
  "properties": {
    "gn:admin1_code":"06",
    "gn:admin2_code":"06",
    "gn:admin3_code":"60618000.0",
    "gn:asciiname":"Bongsod",
    "gn:country_code":"PH",
    "gn:dem":77,
    "gn:feature_class":"P",
    "gn:feature_code":"PPL",
    "gn:name":"Bongsod",
    "gn:population":0,
    "gn:timezone":"Asia/Manila",
    "iso:country":"PH",
    "name:fil_x_preferred":[
        "Bongsod"
    ],
    "name:und_x_variant":[
        "Bonsud",
        "Bongsud",
        "Bunsod"
    ],
    "wof:name":"Bongsod",
    "wof:placetype":"locality"
},
  "geometry": {"coordinates":[122.1403,11.026],"type":"Point"}
}