{
  "type": "Feature",
  "properties": {
    "gn:admin1_code":"09",
    "gn:admin2_code":"65",
    "gn:admin3_code":"97202000.0",
    "gn:asciiname":"Galas",
    "gn:country_code":"PH",
    "gn:dem":5,
    "gn:feature_class":"P",
    "gn:feature_code":"PPL",
    "gn:name":"Galas",
    "gn:population":0,
    "gn:timezone":"Asia/Manila",
    "iso:country":"PH",
    "name:fil_x_preferred":[
        "Galas"
    ],
    "name:rus_x_preferred":[
        "\u0413\u0430\u043b\u0430\u0442"
    ],
    "wof:name":"Galas",
    "wof:placetype":"locality"
},
  "geometry": {"coordinates":[123.3347,8.5598],"type":"Point"}
}