{
  "type": "Feature",
  "properties": {
    "gn:country":"PH",
    "gn:fcode":"PPL",
    "gn:population":2253,
    "iso:country":"PH",
    "name:eng_x_preferred":[
        "Cabalitian"
    ],
    "name:und_x_variant":[
        "Cabalician"
    ],
    "qs:name":"Cabalitian",
    "qs:photos_9r":0,
    "qs:photos_sr":0,
    "qs:pop_sr":"4",
    "wof:name":"Cabalitian",
    "wof:placetype":"locality",
    "wof:population":2253
},
  "geometry": {"coordinates":[120.79219999999999,16.0883],"type":"Point"}
}