{
  "type": "Feature",
  "properties": {
    "gn:admin1_code":"15",
    "gn:admin2_code":"44",
    "gn:admin3_code":"144408000.0",
    "gn:asciiname":"Daneo Saklit",
    "gn:country_code":"PH",
    "gn:dem":1067,
    "gn:feature_class":"P",
    "gn:feature_code":"PPL",
    "gn:name":"Daneo Saklit",
    "gn:population":0,
    "gn:timezone":"Asia/Manila",
    "iso:country":"PH",
    "name:fil_x_preferred":[
        "Daneo Saklit"
    ],
    "name:fil_x_variant":[
        "Saklit",
        "Saclit"
    ],
    "wof:name":"Daneo Saklit",
    "wof:placetype":"locality"
},
  "geometry": {"coordinates":[121.05683999999999,17.21124],"type":"Point"}
}