{
  "type": "Feature",
  "properties": {
    "gn:admin1_code":"14",
    "gn:admin2_code":"35",
    "gn:admin3_code":"153602000.0",
    "gn:asciiname":"Baguiangan",
    "gn:country_code":"PH",
    "gn:dem":103,
    "gn:feature_class":"P",
    "gn:feature_code":"PPL",
    "gn:name":"Baguiangan",
    "gn:population":0,
    "gn:timezone":"Asia/Manila",
    "iso:country":"PH",
    "name:fil_x_preferred":[
        "Baguiangan"
    ],
    "wof:name":"Baguiangan",
    "wof:placetype":"locality"
},
  "geometry": {"coordinates":[124.12888999999998,7.55694],"type":"Point"}
}