{
  "type": "Feature",
  "properties": {
    "gn:admin1_code":"15",
    "gn:admin2_code":"27",
    "gn:admin3_code":"142709000.0",
    "gn:asciiname":"Wagwaguen",
    "gn:country_code":"PH",
    "gn:dem":909,
    "gn:feature_class":"P",
    "gn:feature_code":"PPL",
    "gn:name":"Wagwaguen",
    "gn:population":0,
    "gn:timezone":"Asia/Manila",
    "iso:country":"PH",
    "name:fil_x_preferred":[
        "Wagwaguen"
    ],
    "wof:name":"Wagwaguen",
    "wof:placetype":"locality"
},
  "geometry": {"coordinates":[121.09999999999999,16.88332999999999],"type":"Point"}
}