{
  "type": "Feature",
  "properties": {
    "gn:admin1_code":"05",
    "gn:admin2_code":"16",
    "gn:admin3_code":"51708000.0",
    "gn:asciiname":"Quipayo",
    "gn:country_code":"PH",
    "gn:dem":4,
    "gn:feature_class":"P",
    "gn:feature_code":"PPL",
    "gn:name":"Quipayo",
    "gn:population":0,
    "gn:timezone":"Asia/Manila",
    "iso:country":"PH",
    "name:fil_x_preferred":[
        "Quipayo"
    ],
    "name:und_x_variant":[
        "Santa Cruz",
        "Quiniling Quipayo"
    ],
    "wof:name":"Quipayo",
    "wof:placetype":"locality"
},
  "geometry": {"coordinates":[123.20310000000001,13.699],"type":"Point"}
}