{
  "type": "Feature",
  "properties": {
    "gn:admin1_code":"03",
    "gn:admin2_code":"64",
    "gn:admin3_code":"37112000.0",
    "gn:asciiname":"Umaya",
    "gn:country_code":"PH",
    "gn:dem":35,
    "gn:feature_class":"P",
    "gn:feature_code":"PPL",
    "gn:name":"Umaya",
    "gn:population":0,
    "gn:timezone":"Asia/Manila",
    "iso:country":"PH",
    "name:eng_x_preferred":[
        "Umaya"
    ],
    "name:und_x_variant":[
        "Omaya",
        "Umaya"
    ],
    "wof:name":"Umaya",
    "wof:placetype":"locality"
},
  "geometry": {"coordinates":[120.1356,15.0061],"type":"Point"}
}