{
  "type": "Feature",
  "properties": {
    "gn:country":"PH",
    "gn:fcode":"PPLA3",
    "gn:population":33547,
    "iso:country":"PH",
    "name:bcl_x_preferred":[
        "Bay"
    ],
    "name:cat_x_preferred":[
        "Bay"
    ],
    "name:ceb_x_preferred":[
        "Bay"
    ],
    "name:deu_x_preferred":[
        "Bay"
    ],
    "name:eng_x_preferred":[
        "Bay"
    ],
    "name:fil_x_preferred":[
        "Bay"
    ],
    "name:fra_x_preferred":[
        "Bay"
    ],
    "name:ilo_x_preferred":[
        "Bay"
    ],
    "name:ind_x_preferred":[
        "Bay"
    ],
    "name:ita_x_preferred":[
        "Bay"
    ],
    "name:nld_x_preferred":[
        "Bay"
    ],
    "name:oci_x_preferred":[
        "Bay"
    ],
    "name:pag_x_preferred":[
        "Bay"
    ],
    "name:pam_x_preferred":[
        "Bay"
    ],
    "name:rus_x_preferred":[
        "\u0411\u0435\u0439"
    ],
    "name:spa_x_preferred":[
        "Bay"
    ],
    "name:swe_x_preferred":[
        "Bay"
    ],
    "name:tgl_x_preferred":[
        "Bay"
    ],
    "name:vie_x_preferred":[
        "Bay"
    ],
    "name:war_x_preferred":[
        "Bay"
    ],
    "qs_pg:aaroncc":"PH",
    "qs_pg:gn_country":"PH",
    "qs_pg:gn_fcode":"PPLA3",
    "qs_pg:gn_pop":33547,
    "qs_pg:name":"Bay",
    "qs_pg:photos_9r":0,
    "qs_pg:photos_sr":0,
    "qs_pg:pop_sr":7,
    "qs_pg:qs_pg_placetype":"locality",
    "wof:name":"Bay",
    "wof:placetype":"locality",
    "wof:population":33547
},
  "geometry": {"coordinates":[121.2848,14.1831],"type":"Point"}
}