{
  "type": "Feature",
  "properties": {
    "gn:admin1_code":"02",
    "gn:admin2_code":"31",
    "gn:admin3_code":"23113000.0",
    "gn:asciiname":"Upi",
    "gn:country_code":"PH",
    "gn:dem":48,
    "gn:feature_class":"P",
    "gn:feature_code":"PPL",
    "gn:name":"Upi",
    "gn:population":5647,
    "gn:timezone":"Asia/Manila",
    "iso:country":"PH",
    "name:fil_x_preferred":[
        "Upi"
    ],
    "name:fil_x_variant":[
        "Upi Norte",
        "Upie"
    ],
    "wof:name":"Upi",
    "wof:placetype":"locality",
    "wof:population":5647
},
  "geometry": {"coordinates":[121.83453,17.08262],"type":"Point"}
}