{
  "type": "Feature",
  "properties": {
    "gn:admin1_code":"12",
    "gn:admin2_code":"71",
    "gn:admin3_code":"126509000.0",
    "gn:asciiname":"Lupokon",
    "gn:country_code":"PH",
    "gn:dem":5,
    "gn:feature_class":"P",
    "gn:feature_code":"PPL",
    "gn:name":"Lupokon",
    "gn:population":0,
    "gn:timezone":"Asia/Manila",
    "iso:country":"PH",
    "name:fil_x_preferred":[
        "Lupokon"
    ],
    "wof:name":"Lupokon",
    "wof:placetype":"locality"
},
  "geometry": {"coordinates":[124.21417,6.19611],"type":"Point"}
}