{
  "type": "Feature",
  "properties": {
    "gn:gn_country":"PH",
    "gn:gn_fcode":"PPL",
    "gn:gn_pop":2581,
    "gn:population":2581,
    "iso:country":"PH",
    "name:fil_x_preferred":[
        "Mabilog"
    ],
    "qs_pg:aaroncc":"PH",
    "qs_pg:gn_country":"PH",
    "qs_pg:gn_fcode":"PPL",
    "qs_pg:gn_pop":2581,
    "qs_pg:name":"Mabilog",
    "qs_pg:photos_9r":0,
    "qs_pg:photos_sr":0,
    "qs_pg:pop_sr":4,
    "qs_pg:qs_pg_placetype":"locality",
    "wof:name":"Mabilog",
    "wof:placetype":"locality",
    "wof:population":2581
},
  "geometry": {"coordinates":[120.66573,15.39485],"type":"Point"}
}