{
  "type": "Feature",
  "properties": {
    "gn:admin1_code":"09",
    "gn:admin2_code":"ZSI",
    "gn:admin3_code":"98304000.0",
    "gn:asciiname":"Lamponac",
    "gn:country_code":"PH",
    "gn:dem":12,
    "gn:feature_class":"P",
    "gn:feature_code":"PPL",
    "gn:name":"Lamponac",
    "gn:population":0,
    "gn:timezone":"Asia/Manila",
    "iso:country":"PH",
    "name:fil_x_preferred":[
        "Lamponac"
    ],
    "wof:name":"Lamponac",
    "wof:placetype":"locality"
},
  "geometry": {"coordinates":[122.89639,7.65472],"type":"Point"}
}