{
  "type": "Feature",
  "properties": {
    "gn:admin1_code":"08",
    "gn:admin2_code":"67",
    "gn:admin3_code":"84809000.0",
    "gn:asciiname":"Lo-oc",
    "gn:country_code":"PH",
    "gn:dem":53,
    "gn:feature_class":"P",
    "gn:feature_code":"PPL",
    "gn:name":"Lo-oc",
    "gn:population":0,
    "gn:timezone":"Asia/Manila",
    "iso:country":"PH",
    "name:fil_x_preferred":[
        "Lo-oc"
    ],
    "wof:name":"Lo-oc",
    "wof:placetype":"locality"
},
  "geometry": {"coordinates":[125.25,12.33333],"type":"Point"}
}