{
  "type": "Feature",
  "properties": {
    "gn:admin1_code":"12",
    "gn:admin2_code":"57",
    "gn:admin3_code":"124713000.0",
    "gn:asciiname":"Cayacaca",
    "gn:country_code":"PH",
    "gn:dem":112,
    "gn:feature_class":"P",
    "gn:feature_code":"PPL",
    "gn:name":"Cayacaca",
    "gn:population":0,
    "gn:timezone":"Asia/Manila",
    "iso:country":"PH",
    "name:fil_x_preferred":[
        "Cayacaca"
    ],
    "wof:name":"Cayacaca",
    "wof:placetype":"locality"
},
  "geometry": {"coordinates":[124.94638999999999,7.36833],"type":"Point"}
}