{
  "type": "Feature",
  "properties": {
    "gn:admin1_code":"40",
    "gn:admin2_code":"F2",
    "gn:asciiname":"Bagumbuhay",
    "gn:country_code":"PH",
    "gn:dem":52,
    "gn:feature_class":"P",
    "gn:feature_code":"PPL",
    "gn:name":"Bagumbuhay",
    "gn:population":0,
    "gn:timezone":"Asia/Manila",
    "iso:country":"PH",
    "name:fil_x_preferred":[
        "Bagumbuhay"
    ],
    "wof:name":"Bagumbuhay",
    "wof:placetype":"locality"
},
  "geometry": {"coordinates":[121.06699999999999,14.6195],"type":"Point"}
}