{
  "type": "Feature",
  "properties": {
    "gn:admin1_code":"12",
    "gn:admin2_code":"71",
    "gn:admin3_code":"126505000.0",
    "gn:asciiname":"Cadiz",
    "gn:country_code":"PH",
    "gn:dem":5,
    "gn:feature_class":"P",
    "gn:feature_code":"PPL",
    "gn:name":"Cadiz",
    "gn:population":0,
    "gn:timezone":"Asia/Manila",
    "iso:country":"PH",
    "name:fil_x_preferred":[
        "Cadiz"
    ],
    "wof:name":"Cadiz",
    "wof:placetype":"locality"
},
  "geometry": {"coordinates":[124.05455000000001,6.58831],"type":"Point"}
}