{
  "type": "Feature",
  "properties": {
    "gn:admin1_code":"01",
    "gn:admin2_code":"29",
    "gn:admin3_code":"12925000.0",
    "gn:asciiname":"Bical",
    "gn:country_code":"PH",
    "gn:dem":7,
    "gn:feature_class":"P",
    "gn:feature_code":"PPL",
    "gn:name":"Bical",
    "gn:population":0,
    "gn:timezone":"Asia/Manila",
    "iso:country":"PH",
    "name:fil_x_preferred":[
        "Vical"
    ],
    "name:fil_x_variant":[
        "Bical"
    ],
    "wof:name":"Bical",
    "wof:placetype":"locality"
},
  "geometry": {"coordinates":[120.44056999999999,17.14225],"type":"Point"}
}