{
  "type": "Feature",
  "properties": {
    "gn:country":"PH",
    "gn:fcode":"PPL",
    "gn:population":2906,
    "iso:country":"PH",
    "name:fil_x_preferred":[
        "Balingueo"
    ],
    "qs:name":"Balingueo",
    "qs:photos_9r":0,
    "qs:photos_sr":0,
    "qs:pop_sr":"4",
    "wof:name":"Balingueo",
    "wof:placetype":"locality",
    "wof:population":2906
},
  "geometry": {"coordinates":[120.40973,15.9583],"type":"Point"}
}