{
  "type": "Feature",
  "properties": {
    "gn:admin1_code":"03",
    "gn:admin2_code":"13",
    "gn:admin3_code":"31421000.0",
    "gn:asciiname":"Madlum",
    "gn:country_code":"PH",
    "gn:dem":76,
    "gn:feature_class":"P",
    "gn:feature_code":"PPL",
    "gn:name":"Madlum",
    "gn:population":0,
    "gn:timezone":"Asia/Manila",
    "iso:country":"PH",
    "name:fil_x_preferred":[
        "Madlum"
    ],
    "wof:name":"Madlum",
    "wof:placetype":"locality"
},
  "geometry": {"coordinates":[121.07787,15.17367],"type":"Point"}
}