{
  "type": "Feature",
  "properties": {
    "gn:admin1_code":"02",
    "gn:admin2_code":"14",
    "gn:admin3_code":"21527000.0",
    "gn:asciiname":"Nabbotuan",
    "gn:country_code":"PH",
    "gn:dem":64,
    "gn:feature_class":"P",
    "gn:feature_code":"PPL",
    "gn:name":"Nabbotuan",
    "gn:population":0,
    "gn:timezone":"Asia/Manila",
    "iso:country":"PH",
    "name:fil_x_preferred":[
        "Nabbotoan"
    ],
    "name:fil_x_variant":[
        "Nabbotuan"
    ],
    "wof:name":"Nabbotuan",
    "wof:placetype":"locality"
},
  "geometry": {"coordinates":[121.57308999999999,17.5733],"type":"Point"}
}