{
  "type": "Feature",
  "properties": {
    "gn:admin1_code":"07",
    "gn:admin2_code":"21",
    "gn:admin3_code":"72219000.0",
    "gn:asciiname":"Panoypoy",
    "gn:country_code":"PH",
    "gn:dem":90,
    "gn:feature_class":"P",
    "gn:feature_code":"PPL",
    "gn:name":"Panoypoy",
    "gn:population":0,
    "gn:timezone":"Asia/Manila",
    "iso:country":"PH",
    "name:fil_x_preferred":[
        "Panoypoy"
    ],
    "wof:name":"Panoypoy",
    "wof:placetype":"locality"
},
  "geometry": {"coordinates":[123.92938999999998,10.41314],"type":"Point"}
}