{
  "type": "Feature",
  "properties": {
    "gn:admin1_code":"40",
    "gn:admin2_code":"09",
    "gn:admin3_code":"41003000.0",
    "gn:asciiname":"Lanatan",
    "gn:country_code":"PH",
    "gn:dem":33,
    "gn:feature_class":"P",
    "gn:feature_code":"PPL",
    "gn:name":"Lanatan",
    "gn:population":0,
    "gn:timezone":"Asia/Manila",
    "iso:country":"PH",
    "name:fil_x_preferred":[
        "Lanatan"
    ],
    "wof:name":"Lanatan",
    "wof:placetype":"locality"
},
  "geometry": {"coordinates":[120.72790999999999,13.96053],"type":"Point"}
}