{
  "type": "Feature",
  "properties": {
    "gn:admin1_code":"14",
    "gn:admin2_code":"72",
    "gn:admin3_code":"157005000.0",
    "gn:asciiname":"Tong Gusung",
    "gn:country_code":"PH",
    "gn:dem":9,
    "gn:feature_class":"P",
    "gn:feature_code":"PPL",
    "gn:name":"Tong Gusung",
    "gn:population":0,
    "gn:timezone":"Asia/Manila",
    "iso:country":"PH",
    "wof:name":"Tong Gusung",
    "wof:placetype":"locality"
},
  "geometry": {"coordinates":[119.40000000000001,4.75],"type":"Point"}
}