{
  "type": "Feature",
  "properties": {
    "gn:admin1_code":"40",
    "gn:admin2_code":"H2",
    "gn:admin3_code":"45627000.0",
    "gn:asciiname":"Saban",
    "gn:country_code":"PH",
    "gn:dem":9,
    "gn:feature_class":"P",
    "gn:feature_code":"PPL",
    "gn:name":"Saban",
    "gn:population":0,
    "gn:timezone":"Asia/Manila",
    "iso:country":"PH",
    "name:fil_x_preferred":[
        "Saban"
    ],
    "name:und_x_variant":[
        "Sabana"
    ],
    "wof:name":"Saban",
    "wof:placetype":"locality"
},
  "geometry": {"coordinates":[121.7195,14.17882],"type":"Point"}
}