{
  "type": "Feature",
  "properties": {
    "gn:admin1_code":"40",
    "gn:admin2_code":"33",
    "gn:admin3_code":"43428000.0",
    "gn:asciiname":"Pulong Cacawate",
    "gn:country_code":"PH",
    "gn:dem":100,
    "gn:feature_class":"P",
    "gn:feature_code":"PPL",
    "gn:name":"Pulong Cacawate",
    "gn:population":0,
    "gn:timezone":"Asia/Manila",
    "iso:country":"PH",
    "name:fil_x_preferred":[
        "Pulong Cacawate"
    ],
    "wof:name":"Pulong Cacawate",
    "wof:placetype":"locality"
},
  "geometry": {"coordinates":[121.0732,14.2262],"type":"Point"}
}