{
  "type": "Feature",
  "properties": {
    "gn:admin1_code":"01",
    "gn:admin2_code":"36",
    "gn:admin3_code":"13302000.0",
    "gn:asciiname":"San Antonia",
    "gn:country_code":"PH",
    "gn:dem":34,
    "gn:feature_class":"P",
    "gn:feature_code":"PPL",
    "gn:name":"San Antonia",
    "gn:population":0,
    "gn:timezone":"Asia/Manila",
    "iso:country":"PH",
    "name:fil_x_preferred":[
        "San Antonia"
    ],
    "name:fil_x_variant":[
        "San Antonio"
    ],
    "wof:name":"San Antonia",
    "wof:placetype":"locality"
},
  "geometry": {"coordinates":[120.40519999999999,16.404],"type":"Point"}
}