{
  "type": "Feature",
  "properties": {
    "iso:country":"PH",
    "name:fil_x_preferred":[
        "Tindog"
    ],
    "name:unk_x_variant":[
        "Tindug"
    ],
    "qs:gn_country":"PH",
    "qs:gn_fcode":"PPL",
    "qs:gn_pop":3306,
    "qs:name":"Tindog",
    "qs:name_adm0":"Philippines",
    "qs:name_adm1":"Central Visayas",
    "qs:photos":0,
    "qs:photos_1k":0,
    "qs:photos_9k":1,
    "qs:photos_9r":1,
    "qs:photos_all":1,
    "qs:photos_sr":0,
    "qs:placetype":"Town",
    "qs:pop_sr":"4",
    "qs:woe_adm0":23424934,
    "wof:name":"Tindog",
    "wof:placetype":"locality",
    "wof:population":3306
},
  "geometry": {"coordinates":[124.01179999999999,11.1247],"type":"Point"}
}