{
  "type": "Feature",
  "properties": {
    "gn:admin1_code":"13",
    "gn:admin2_code":"61",
    "gn:admin3_code":"166716000.0",
    "gn:asciiname":"Sogas",
    "gn:country_code":"PH",
    "gn:dem":7,
    "gn:feature_class":"P",
    "gn:feature_code":"PPL",
    "gn:name":"Sogas",
    "gn:population":0,
    "gn:timezone":"Asia/Manila",
    "iso:country":"PH",
    "name:fil_x_preferred":[
        "Sogas"
    ],
    "wof:name":"Sogas",
    "wof:placetype":"locality"
},
  "geometry": {"coordinates":[126.05389,9.82611],"type":"Point"}
}