{
  "type": "Feature",
  "properties": {
    "gn:admin1_code":"03",
    "gn:admin2_code":"64",
    "gn:admin3_code":"37110000.0",
    "gn:asciiname":"Yangil",
    "gn:country_code":"PH",
    "gn:dem":26,
    "gn:feature_class":"P",
    "gn:feature_code":"PPL",
    "gn:name":"Yangil",
    "gn:population":0,
    "gn:timezone":"Asia/Manila",
    "iso:country":"PH",
    "name:eng_x_preferred":[
        "Yangil"
    ],
    "wof:name":"Yangil",
    "wof:placetype":"locality"
},
  "geometry": {"coordinates":[120.1236,15.0997],"type":"Point"}
}