{
  "type": "Feature",
  "properties": {
    "gn:admin1_code":"06",
    "gn:admin2_code":"30",
    "gn:admin3_code":"63046000.0",
    "gn:asciiname":"Bagacay",
    "gn:country_code":"PH",
    "gn:dem":202,
    "gn:feature_class":"P",
    "gn:feature_code":"PPL",
    "gn:name":"Bagacay",
    "gn:population":0,
    "gn:timezone":"Asia/Manila",
    "iso:country":"PH",
    "name:fil_x_preferred":[
        "Bagacay"
    ],
    "wof:name":"Bagacay",
    "wof:placetype":"locality"
},
  "geometry": {"coordinates":[122.29089999999999,10.78905],"type":"Point"}
}