{
  "type": "Feature",
  "properties": {
    "gn:country":"PH",
    "gn:fcode":"PPL",
    "gn:pop":2828,
    "iso:country":"PH",
    "name:fil_x_preferred":[
        "Mapulo"
    ],
    "qs:name":"Mapulo",
    "qs:photos_9r":0,
    "qs:photos_sr":0,
    "qs:pop_sr":"4",
    "wof:name":"Mapulo",
    "wof:placetype":"locality",
    "wof:population":2828
},
  "geometry": {"coordinates":[121.1842,13.7317],"type":"Point"}
}