{
  "type": "Feature",
  "properties": {
    "gn:admin1_code":"02",
    "gn:admin2_code":"14",
    "gn:admin3_code":"21522000.0",
    "gn:asciiname":"Gammaro",
    "gn:country_code":"PH",
    "gn:dem":25,
    "gn:feature_class":"P",
    "gn:feature_code":"PPL",
    "gn:name":"Gammaro",
    "gn:population":0,
    "gn:timezone":"Asia/Manila",
    "iso:country":"PH",
    "name:und_x_variant":[
        "Gamaro"
    ],
    "wof:name":"Gammaro",
    "wof:placetype":"locality"
},
  "geometry": {"coordinates":[121.26129,18.51013],"type":"Point"}
}