{
  "type": "Feature",
  "properties": {
    "gn:admin1_code":"09",
    "gn:admin2_code":"65",
    "gn:asciiname":"Palid",
    "gn:country_code":"PH",
    "gn:dem":10,
    "gn:feature_class":"P",
    "gn:feature_code":"PPL",
    "gn:name":"Palid",
    "gn:population":0,
    "gn:timezone":"Asia/Manila",
    "iso:country":"PH",
    "name:eng_x_preferred":[
        "Palid"
    ],
    "wof:name":"Palid",
    "wof:placetype":"locality"
},
  "geometry": {"coordinates":[122.9576,8.314],"type":"Point"}
}