{
  "type": "Feature",
  "properties": {
    "gn:admin1_code":"08",
    "gn:admin2_code":"37",
    "gn:admin3_code":"83739000.0",
    "gn:asciiname":"Bugho",
    "gn:country_code":"PH",
    "gn:dem":15,
    "gn:feature_class":"P",
    "gn:feature_code":"PPL",
    "gn:name":"Bugho",
    "gn:population":0,
    "gn:timezone":"Asia/Manila",
    "iso:country":"PH",
    "name:fil_x_preferred":[
        "Bugho"
    ],
    "name:fil_x_variant":[
        "Bughu"
    ],
    "wof:name":"Bugho",
    "wof:placetype":"locality"
},
  "geometry": {"coordinates":[124.98026000000002,11.19794],"type":"Point"}
}