{
  "type": "Feature",
  "properties": {
    "gn:admin1_code":"06",
    "gn:admin2_code":"H3",
    "gn:admin3_code":"64504000.0",
    "gn:asciiname":"Amigos",
    "gn:country_code":"PH",
    "gn:dem":25,
    "gn:feature_class":"P",
    "gn:feature_code":"PPL",
    "gn:name":"Amigos",
    "gn:population":0,
    "gn:timezone":"Asia/Manila",
    "iso:country":"PH",
    "name:fil_x_preferred":[
        "Amigos"
    ],
    "wof:name":"Amigos",
    "wof:placetype":"locality"
},
  "geometry": {"coordinates":[123.3128,10.9323],"type":"Point"}
}