{
  "type": "Feature",
  "properties": {
    "gn:admin1_code":"03",
    "gn:admin2_code":"47",
    "gn:admin3_code":"34920000.0",
    "gn:asciiname":"East Poblacion",
    "gn:country_code":"PH",
    "gn:dem":337,
    "gn:feature_class":"P",
    "gn:feature_code":"PPL",
    "gn:name":"East Poblacion",
    "gn:population":0,
    "gn:timezone":"Asia/Manila",
    "iso:country":"PH",
    "name:fil_x_preferred":[
        "East Poblacion"
    ],
    "wof:name":"East Poblacion",
    "wof:placetype":"locality"
},
  "geometry": {"coordinates":[121.15389999999999,15.8017],"type":"Point"}
}