{
  "type": "Feature",
  "properties": {
    "gn:admin1_code":"07",
    "gn:admin2_code":"21",
    "gn:admin3_code":"72209000.0",
    "gn:asciiname":"Oboob",
    "gn:country_code":"PH",
    "gn:dem":13,
    "gn:feature_class":"P",
    "gn:feature_code":"PPL",
    "gn:name":"Oboob",
    "gn:population":0,
    "gn:timezone":"Asia/Manila",
    "iso:country":"PH",
    "name:fil_x_preferred":[
        "Oboob"
    ],
    "wof:name":"Oboob",
    "wof:placetype":"locality"
},
  "geometry": {"coordinates":[123.7488,11.1564],"type":"Point"}
}