{
  "type": "Feature",
  "properties": {
    "gn:admin1_code":"01",
    "gn:admin2_code":"29",
    "gn:admin3_code":"12913000.0",
    "gn:asciiname":"Cadoog East",
    "gn:country_code":"PH",
    "gn:dem":18,
    "gn:feature_class":"P",
    "gn:feature_code":"PPL",
    "gn:name":"Cadoog East",
    "gn:population":0,
    "gn:timezone":"Asia/Manila",
    "iso:country":"PH",
    "name:eng_x_preferred":[
        "Cadoog East"
    ],
    "name:fil_x_preferred":[
        "Bantugo"
    ],
    "wof:name":"Cadoog East",
    "wof:placetype":"locality"
},
  "geometry": {"coordinates":[120.5141,17.4341],"type":"Point"}
}