{
  "type": "Feature",
  "properties": {
    "gn:country":"PH",
    "gn:fcode":"ADM3",
    "gn:pop":22596,
    "iso:country":"PH",
    "name:fil_x_preferred":[
        "Gamay"
    ],
    "qs:name":"Gamay",
    "qs:photos_9r":0,
    "qs:photos_sr":0,
    "qs:pop_sr":"7",
    "wd:wordcount":924,
    "wof:name":"Gamay",
    "wof:placetype":"localadmin",
    "wof:population":22596
},
  "geometry": {"coordinates":[125.26667,12.38333],"type":"Point"}
}