{
  "type": "Feature",
  "properties": {
    "gn:country":"PH",
    "gn:fcode":"ADM3",
    "gn:pop":22596,
    "iso:country":"PH",
    "name:bul_x_preferred":[
        "\u0413\u0430\u043c\u0435 \u043d\u043e\u0430\u0440"
    ],
    "name:cat_x_preferred":[
        "gamay"
    ],
    "name:chv_x_preferred":[
        "\u0413\u0430\u043c\u044d"
    ],
    "name:deu_x_preferred":[
        "Gamay"
    ],
    "name:eng_x_preferred":[
        "Gamay"
    ],
    "name:fil_x_preferred":[
        "Gamay"
    ],
    "name:fin_x_preferred":[
        "Gamay"
    ],
    "name:fra_x_preferred":[
        "Gamay Noir"
    ],
    "name:heb_x_preferred":[
        "\u05d2\u05de\u05d0\u05d9"
    ],
    "name:hrv_x_preferred":[
        "Borgonja"
    ],
    "name:ita_x_preferred":[
        "Gamay"
    ],
    "name:jpn_x_preferred":[
        "\u30ac\u30e1"
    ],
    "name:ltz_x_preferred":[
        "Gamay"
    ],
    "name:nld_x_preferred":[
        "Gamay"
    ],
    "name:nob_x_preferred":[
        "Gamay"
    ],
    "name:oci_x_preferred":[
        "Gamay"
    ],
    "name:pcd_x_preferred":[
        "Gamay"
    ],
    "name:pol_x_preferred":[
        "Gamay"
    ],
    "name:por_x_preferred":[
        "Gamay"
    ],
    "name:ron_x_preferred":[
        "Gamay"
    ],
    "name:rus_x_preferred":[
        "\u0413\u0430\u043c\u0435"
    ],
    "name:scn_x_preferred":[
        "Gamay"
    ],
    "name:spa_x_preferred":[
        "Gamay"
    ],
    "name:swe_x_preferred":[
        "Gamay"
    ],
    "name:zho_x_preferred":[
        "\u4f73\u7f8e"
    ],
    "qs:name":"Gamay",
    "qs:photos_9r":0,
    "qs:photos_sr":0,
    "qs:pop_sr":"7",
    "wd:wordcount":924,
    "wof:name":"Gamay",
    "wof:placetype":"localadmin",
    "wof:population":22596
},
  "geometry": {"coordinates":[125.26667,12.38333],"type":"Point"}
}