{
  "type": "Feature",
  "properties": {
    "gn:admin1_code":"06",
    "gn:admin2_code":"30",
    "gn:admin3_code":"63035000.0",
    "gn:asciiname":"Nueva Union",
    "gn:country_code":"PH",
    "gn:dem":79,
    "gn:feature_class":"P",
    "gn:feature_code":"PPL",
    "gn:name":"Nueva Union",
    "gn:population":0,
    "gn:timezone":"Asia/Manila",
    "iso:country":"PH",
    "name:fil_x_preferred":[
        "Nueva Union"
    ],
    "wof:name":"Nueva Union",
    "wof:placetype":"locality"
},
  "geometry": {"coordinates":[122.6203,11.2174],"type":"Point"}
}