{
  "type": "Feature",
  "properties": {
    "gn:admin1_code":"06",
    "gn:admin2_code":"J3",
    "gn:admin3_code":"67901000.0",
    "gn:asciiname":"Calumingan",
    "gn:country_code":"PH",
    "gn:dem":5,
    "gn:feature_class":"P",
    "gn:feature_code":"PPL",
    "gn:name":"Calumingan",
    "gn:population":0,
    "gn:timezone":"Asia/Manila",
    "iso:country":"PH",
    "name:fil_x_preferred":[
        "Calumingan"
    ],
    "wof:name":"Calumingan",
    "wof:placetype":"locality"
},
  "geometry": {"coordinates":[122.693,10.726],"type":"Point"}
}