{
  "type": "Feature",
  "properties": {
    "gn:admin1_code":"07",
    "gn:admin2_code":"21",
    "gn:admin3_code":"72219000.0",
    "gn:asciiname":"Candoman",
    "gn:cc2":"PH",
    "gn:country_code":"PH",
    "gn:dem":50,
    "gn:feature_class":"P",
    "gn:feature_code":"PPL",
    "gn:name":"Candoman",
    "gn:population":0,
    "gn:timezone":"Asia/Manila",
    "iso:country":"PH",
    "name:und_x_variant":[
        "Canduman"
    ],
    "wof:name":"Candoman",
    "wof:placetype":"locality"
},
  "geometry": {"coordinates":[123.95,10.37528],"type":"Point"}
}