{
  "type": "Feature",
  "properties": {
    "gn:admin1_code":"08",
    "gn:admin2_code":"67",
    "gn:admin3_code":"84811000.0",
    "gn:asciiname":"Napanod",
    "gn:country_code":"PH",
    "gn:dem":23,
    "gn:feature_class":"P",
    "gn:feature_code":"PPL",
    "gn:name":"Napanod",
    "gn:population":0,
    "gn:timezone":"Asia/Manila",
    "iso:country":"PH",
    "name:fil_x_preferred":[
        "Napanod"
    ],
    "wof:name":"Napanod",
    "wof:placetype":"locality"
},
  "geometry": {"coordinates":[124.4016,12.5136],"type":"Point"}
}