{
  "type": "Feature",
  "properties": {
    "gn:admin1_code":"12",
    "gn:admin2_code":"71",
    "gn:admin3_code":"126507000.0",
    "gn:asciiname":"Dungoan",
    "gn:country_code":"PH",
    "gn:dem":18,
    "gn:feature_class":"P",
    "gn:feature_code":"PPL",
    "gn:name":"Dungoan",
    "gn:population":0,
    "gn:timezone":"Asia/Manila",
    "iso:country":"PH",
    "name:fil_x_preferred":[
        "Dungoan"
    ],
    "wof:name":"Dungoan",
    "wof:placetype":"locality"
},
  "geometry": {"coordinates":[124.79487,6.59684],"type":"Point"}
}