{
  "type": "Feature",
  "properties": {
    "gn:admin1_code":"02",
    "gn:admin2_code":"31",
    "gn:admin3_code":"23120000.0",
    "gn:asciiname":"Aguinaldo",
    "gn:country_code":"PH",
    "gn:dem":80,
    "gn:feature_class":"P",
    "gn:feature_code":"PPL",
    "gn:name":"Aguinaldo",
    "gn:population":0,
    "gn:timezone":"Asia/Manila",
    "iso:country":"PH",
    "name:fil_x_preferred":[
        "Aguinaldo"
    ],
    "name:fin_x_preferred":[
        "Aguinaldo"
    ],
    "name:nno_x_preferred":[
        "Aguinaldo"
    ],
    "name:nor_x_preferred":[
        "Aguinaldo"
    ],
    "name:spa_x_preferred":[
        "Aguinaldo"
    ],
    "wof:name":"Aguinaldo",
    "wof:placetype":"locality"
},
  "geometry": {"coordinates":[121.91454,16.93555],"type":"Point"}
}