{
  "type": "Feature",
  "properties": {
    "gn:admin1_code":"40",
    "gn:admin2_code":"H2",
    "gn:admin3_code":"45633000.0",
    "gn:asciiname":"Pambuhan",
    "gn:country_code":"PH",
    "gn:dem":23,
    "gn:feature_class":"P",
    "gn:feature_code":"PPL",
    "gn:name":"Pambuhan",
    "gn:population":0,
    "gn:timezone":"Asia/Manila",
    "iso:country":"PH",
    "name:fil_x_preferred":[
        "Pambuhan"
    ],
    "wof:name":"Pambuhan",
    "wof:placetype":"locality"
},
  "geometry": {"coordinates":[121.96776,14.19845],"type":"Point"}
}