{
  "type": "Feature",
  "properties": {
    "gn:admin1_code":"02",
    "gn:admin2_code":"48",
    "gn:admin3_code":"25010000.0",
    "gn:asciiname":"Cabalatan",
    "gn:country_code":"PH",
    "gn:dem":1484,
    "gn:feature_class":"P",
    "gn:feature_code":"PPL",
    "gn:name":"Cabalatan",
    "gn:population":0,
    "gn:timezone":"Asia/Manila",
    "iso:country":"PH",
    "name:eng_x_preferred":[
        "Cabalatan"
    ],
    "wof:name":"Cabalatan",
    "wof:placetype":"locality"
},
  "geometry": {"coordinates":[120.9057,16.2838],"type":"Point"}
}