{
  "type": "Feature",
  "properties": {
    "gn:country":"PH",
    "gn:fcode":"PPL",
    "gn:pop":2335,
    "iso:country":"PH",
    "name:fil_x_preferred":[
        "San Vicente"
    ],
    "qs:name":"San Vicente",
    "qs:photos_9r":0,
    "qs:photos_sr":0,
    "qs:pop_sr":"4",
    "wd:wordcount":196,
    "wof:name":"San Vicente",
    "wof:placetype":"locality",
    "wof:population":2335
},
  "geometry": {"coordinates":[125.03444,7.65111],"type":"Point"}
}