{
  "type": "Feature",
  "properties": {
    "gn:admin1_code":"06",
    "gn:admin2_code":"30",
    "gn:asciiname":"Toloato",
    "gn:country_code":"PH",
    "gn:dem":-9999,
    "gn:feature_class":"P",
    "gn:feature_code":"PPL",
    "gn:name":"Toloato",
    "gn:population":0,
    "gn:timezone":"Asia/Manila",
    "iso:country":"PH",
    "name:fil_x_preferred":[
        "Toloato"
    ],
    "wof:name":"Toloato",
    "wof:placetype":"locality"
},
  "geometry": {"coordinates":[123.09999999999999,11.28333],"type":"Point"}
}