{
  "type": "Feature",
  "properties": {
    "gn:admin1_code":"41",
    "gn:admin2_code":"40",
    "gn:admin3_code":"175110000.0",
    "gn:asciiname":"Mantor",
    "gn:country_code":"PH",
    "gn:dem":47,
    "gn:feature_class":"P",
    "gn:feature_code":"PPL",
    "gn:name":"Mantor",
    "gn:population":0,
    "gn:timezone":"Asia/Manila",
    "iso:country":"PH",
    "name:fil_x_preferred":[
        "Mantor"
    ],
    "wof:name":"Mantor",
    "wof:placetype":"locality"
},
  "geometry": {"coordinates":[121.09650999999999,12.21346],"type":"Point"}
}