{
  "type": "Feature",
  "properties": {
    "gn:admin1_code":"02",
    "gn:admin2_code":"14",
    "gn:admin3_code":"21529000.0",
    "gn:asciiname":"Larion Bajo",
    "gn:country_code":"PH",
    "gn:dem":21,
    "gn:feature_class":"P",
    "gn:feature_code":"PPL",
    "gn:name":"Larion Bajo",
    "gn:population":0,
    "gn:timezone":"Asia/Manila",
    "iso:country":"PH",
    "name:fil_x_preferred":[
        "Larion Bajo"
    ],
    "wof:name":"Larion Bajo",
    "wof:placetype":"locality"
},
  "geometry": {"coordinates":[121.75285,17.62607000000001],"type":"Point"}
}