{
  "type": "Feature",
  "properties": {
    "gn:admin1_code":"05",
    "gn:admin2_code":"15",
    "gn:admin3_code":"51602000.0",
    "gn:asciiname":"Negritos Camp",
    "gn:country_code":"PH",
    "gn:dem":45,
    "gn:feature_class":"P",
    "gn:feature_code":"PPL",
    "gn:name":"Negritos Camp",
    "gn:population":0,
    "gn:timezone":"Asia/Manila",
    "iso:country":"PH",
    "name:eng_x_preferred":[
        "Negritos Camp"
    ],
    "wof:name":"Negritos Camp",
    "wof:placetype":"locality"
},
  "geometry": {"coordinates":[122.551,14.2293],"type":"Point"}
}