{
  "type": "Feature",
  "properties": {
    "gn:admin1_code":"40",
    "gn:admin2_code":"09",
    "gn:admin3_code":"41015000.0",
    "gn:asciiname":"Masaguitsit",
    "gn:country_code":"PH",
    "gn:dem":28,
    "gn:feature_class":"P",
    "gn:feature_code":"PPL",
    "gn:name":"Masaguitsit",
    "gn:population":0,
    "gn:timezone":"Asia/Manila",
    "iso:country":"PH",
    "name:fil_x_preferred":[
        "Masaguitsit"
    ],
    "wof:name":"Masaguitsit",
    "wof:placetype":"locality"
},
  "geometry": {"coordinates":[121.1926,13.645],"type":"Point"}
}