{
  "type": "Feature",
  "properties": {
    "gn:admin1_code":"15",
    "gn:admin2_code":"10",
    "gn:admin3_code":"141104000.0",
    "gn:asciiname":"Pakak",
    "gn:country_code":"PH",
    "gn:dem":785,
    "gn:feature_class":"P",
    "gn:feature_code":"PPL",
    "gn:name":"Pakak",
    "gn:population":0,
    "gn:timezone":"Asia/Manila",
    "iso:country":"PH",
    "name:eng_x_preferred":[
        "Pakak"
    ],
    "wof:name":"Pakak",
    "wof:placetype":"locality"
},
  "geometry": {"coordinates":[120.7993,16.477],"type":"Point"}
}