{
  "type": "Feature",
  "properties": {
    "gn:admin1_code":"14",
    "gn:admin2_code":"56",
    "gn:admin3_code":"153819000.0",
    "gn:asciiname":"Iganatalik",
    "gn:country_code":"PH",
    "gn:dem":14,
    "gn:feature_class":"P",
    "gn:feature_code":"PPL",
    "gn:name":"Iganatalik",
    "gn:population":0,
    "gn:timezone":"Asia/Manila",
    "iso:country":"PH",
    "name:fil_x_preferred":[
        "Iganatalik"
    ],
    "wof:name":"Iganatalik",
    "wof:placetype":"locality"
},
  "geometry": {"coordinates":[124.76721999999999,6.81917],"type":"Point"}
}