{
  "type": "Feature",
  "properties": {
    "gn:admin1_code":"09",
    "gn:admin2_code":"66",
    "gn:admin3_code":"97332000.0",
    "gn:asciiname":"San Ramon Penal Colony",
    "gn:cc2":"PH",
    "gn:country_code":"PH",
    "gn:dem":11,
    "gn:feature_class":"P",
    "gn:feature_code":"PPL",
    "gn:name":"San Ramon Penal Colony",
    "gn:population":0,
    "gn:timezone":"Asia/Manila",
    "iso:country":"PH",
    "name:und_x_variant":[
        "Penal Colony",
        "San Ramon",
        "San Ramon Penal Farm",
        "San Ramon Penal Colony"
    ],
    "wof:name":"San Ramon Penal Colony",
    "wof:placetype":"locality"
},
  "geometry": {"coordinates":[121.92638999999998,7.00083],"type":"Point"}
}