{
  "type": "Feature",
  "properties": {
    "gn:admin1_code":"01",
    "gn:admin2_code":"29",
    "gn:admin3_code":"12903000.0",
    "gn:asciiname":"Nagguiddayan",
    "gn:country_code":"PH",
    "gn:dem":161,
    "gn:feature_class":"P",
    "gn:feature_code":"PPL",
    "gn:name":"Nagguiddayan",
    "gn:population":0,
    "gn:timezone":"Asia/Manila",
    "iso:country":"PH",
    "name:fil_x_preferred":[
        "Nagguiddayan"
    ],
    "wof:name":"Nagguiddayan",
    "wof:placetype":"locality"
},
  "geometry": {"coordinates":[120.46666999999999,17.58333],"type":"Point"}
}