{
  "type": "Feature",
  "properties": {
    "gn:country":"PH",
    "gn:fcode":"PPLA3",
    "gn:pop":2651,
    "iso:country":"PH",
    "name:bcl_x_preferred":[
        "Santa Lucia"
    ],
    "name:cat_x_preferred":[
        "Santa Lucia"
    ],
    "name:ceb_x_preferred":[
        "Santa Lucia"
    ],
    "name:deu_x_preferred":[
        "Santa Lucia"
    ],
    "name:eng_x_preferred":[
        "Santa Lucia"
    ],
    "name:fra_x_preferred":[
        "Santa Lucia"
    ],
    "name:ilo_x_preferred":[
        "Santa Lucia"
    ],
    "name:ind_x_preferred":[
        "Santa Lucia"
    ],
    "name:ita_x_preferred":[
        "Santa Lucia"
    ],
    "name:nld_x_preferred":[
        "Santa Lucia"
    ],
    "name:oci_x_preferred":[
        "Santa Lucia"
    ],
    "name:pag_x_preferred":[
        "Santa Lucia"
    ],
    "name:pam_x_preferred":[
        "Santa Lucia"
    ],
    "name:spa_x_preferred":[
        "Santa Luc\u00eda"
    ],
    "name:swe_x_preferred":[
        "Santa Lucia"
    ],
    "name:tgl_x_preferred":[
        "Santa Lucia"
    ],
    "name:vie_x_preferred":[
        "Santa Lucia"
    ],
    "name:war_x_preferred":[
        "Santa Lucia"
    ],
    "qs:name":"Santa Lucia",
    "qs:photos_9r":0,
    "qs:photos_sr":0,
    "qs:pop_sr":"4",
    "wd:wordcount":1106,
    "wof:name":"Santa Lucia",
    "wof:placetype":"locality",
    "wof:population":2651
},
  "geometry": {"coordinates":[120.45305999999999,17.1175],"type":"Point"}
}