{
  "type": "Feature",
  "properties": {
    "gn:admin1_code":"40",
    "gn:admin2_code":"H2",
    "gn:admin3_code":"45637000.0",
    "gn:asciiname":"Villagomez",
    "gn:country_code":"PH",
    "gn:dem":21,
    "gn:feature_class":"P",
    "gn:feature_code":"PPL",
    "gn:name":"Villagomez",
    "gn:population":0,
    "gn:timezone":"Asia/Manila",
    "iso:country":"PH",
    "name:fil_x_preferred":[
        "Villagomez"
    ],
    "wof:name":"Villagomez",
    "wof:placetype":"locality"
},
  "geometry": {"coordinates":[122.1242,14.0779],"type":"Point"}
}