{
  "type": "Feature",
  "properties": {
    "gn:admin1_code":"40",
    "gn:admin2_code":"09",
    "gn:admin3_code":"41006000.0",
    "gn:asciiname":"Locloc",
    "gn:country_code":"PH",
    "gn:dem":28,
    "gn:feature_class":"P",
    "gn:feature_code":"PPL",
    "gn:name":"Locloc",
    "gn:population":0,
    "gn:timezone":"Asia/Manila",
    "iso:country":"PH",
    "name:und_x_variant":[
        "Loctoc",
        "Locloc"
    ],
    "wof:name":"Locloc",
    "wof:placetype":"locality"
},
  "geometry": {"coordinates":[120.92124,13.79292],"type":"Point"}
}