{
  "type": "Feature",
  "properties": {
    "gn:admin1_code":"08",
    "gn:admin2_code":"37",
    "gn:admin3_code":"83702000.0",
    "gn:asciiname":"Maitum",
    "gn:country_code":"PH",
    "gn:dem":35,
    "gn:feature_class":"P",
    "gn:feature_code":"PPL",
    "gn:name":"Maitum",
    "gn:population":0,
    "gn:timezone":"Asia/Manila",
    "iso:country":"PH",
    "name:fil_x_preferred":[
        "Maitum"
    ],
    "wof:name":"Maitum",
    "wof:placetype":"locality"
},
  "geometry": {"coordinates":[124.81667,11.25],"type":"Point"}
}